Workbook
Name \T: #REF!
Name __dao1: #REF!
Name __dao2: #REF!
Name __dap2: #REF!
Name __day1: #REF!
Name __day2: #REF!
Name __dbu1: #REF!
Name __dbu2: #REF!
Name __doi3: #REF!
Name __E99999: #REF!
Name __Jan02: #REF!
Name __lap1: #REF!
Name __lap2: #REF!
Name __vc1: #REF!
Name __vc2: #REF!
Name __vc3: #REF!
Name _01_01_99: #REF!
Name _01_02_99: #REF!
Name _01_03_99: #REF!
Name _01_04_99: #REF!
Name _01_05_99: #REF!
Name _01_06_99: #REF!
Name _01_07_99: #REF!
Name _01_08_1999: #REF!
Name _1CAP002: #REF!
Name _2STREO7: #REF!
Name _4GOIC01: #REF!
Name _4OSLCTT: #REF!
Name _6BNTTTH: #REF!
Name _6DCTTBO: #REF!
Name _6DD24TT: #REF!
Name _6FCOTBU: #REF!
Name _6LATUBU: #REF!
Name _6SDTT24: #REF!
Name _6TBUDTT: #REF!
Name _6TDDDTT: #REF!
Name _6TLTTTH: #REF!
Name _6TUBUTT: #REF!
Name _6UCLVIS: #REF!
Name _7DNCABC: #REF!
Name _7HDCTBU: #REF!
Name _7PKTUBU: #REF!
Name _7TBHT20: #REF!
Name _7TBHT30: #REF!
Name _7TDCABC: #REF!
Name _dao1: #REF!
Name _dao2: #REF!
Name _dap2: #REF!
Name _day1: #REF!
Name _day2: #REF!
Name _dbu1: #REF!
Name _dbu2: #REF!
Name _doi3: #REF!
Name _E99999: #REF!
Name _Jan02: #REF!
Name _lap1: #REF!
Name _lap2: #REF!
Name _vc1: #REF!
Name _vc2: #REF!
Name _vc3: #REF!

Sheet TH
A1: CHÀO GIÁ SUNTORY PEPSI 2026
A3: Kinh doanh đề xuất xem xét giá sàn EXW 1250 USD/tấn
A5: STT | B5: Mã | C5: Tên | D5: Đơn giá vốn (Vnđ/Kg) | E5: Đơn giá vốn (USD/tấn) | F5: Giá bán EXW Kinh doanh đề nghị (USD/tấn) | G5: Lợi nhuận sau thuế | H5: % Lợi nhuận sau thuế | I5: Giá bán duyệt tháng 3
A6: 1 | B6: 110000332 | C6: Hạt nhựa rPET iSS01084G | D6: =+ISS01084G!J105 -> 31924.322 | E6: =+ISS01084G!K105 -> 1204.6914 | F6: 1250 | G6: =+F6-E6 -> 45.308615 | H6: =+G6/F6 -> 0.036246892 | I6: 1250
A7: 2 | B7: 110000483 | C7: Hạt Nhựa rPET iSS01G-S | D7: =+'ISS01G-S'!J105 -> 31916.263 | E7: =+'ISS01G-S'!K105 -> 1204.3873 | F7: 1230 | G7: =+F7-E7 -> 25.612732 | H7: =+G7/F7 -> 0.020823359 | I7: 1230
B10: Tính toán cho chào giá phần tăng thêm sản lượng 1.500-4500 mt
A11: STT | B11: Mã | C11: Tên | D11: Đơn giá vốn (Vnđ/Kg) | E11: Đơn giá vốn (USD/tấn) | F11: Giá bán EXW đề nghị (USD/tấn) | G11: Lợi nhuận sau thuế | H11: % Lợi nhuận sau thuế | I11: Giá bán duyệt tháng 4 | J11: Giá đầu vào tăng | K11: Chai | L11: Tằng giá khác
A12: 1 | B12: 110000332 | C12: Hạt nhựa rPET iSS01084G | D12: ='ISS01084G (2)'!J105 -> 28638.681 | E12: ='ISS01084G (2)'!K105 -> 1080.7049 | F12: =F6+J12 -> 1375.4717 | G12: =+F12-E12 -> 294.76675 | H12: =+G12/F12 -> 0.2143023 | I12: =1280+90 -> 1370 | J12: =K12+L12 -> 125.4717 | K12: =(2000*1000)/26500 -> 75.471698 | L12: 50
A13: 2 | B13: 110000483 | C13: Hạt Nhựa rPET iSS01G-S | D13: ='ISS01G-S (2)'!J105 -> 28630.622 | E13: ='ISS01G-S (2)'!K105 -> 1080.4008 | F13: =F7+J13 -> 1355.4717 | G13: =+F13-E13 -> 275.07087 | H13: =+G13/F13 -> 0.20293369 | I13: =1280+30 -> 1310 | J13: =K13+L13 -> 125.4717 | K13: =(2000*1000)/26500 -> 75.471698 | L13: 50
A15: STT | B15: Mã | C15: Tên | D15: Đơn giá vốn (Vnđ/Kg) | E15: Đơn giá vốn (USD/tấn) | F15: Giá bán EXW đề nghị (USD/tấn) | G15: Lợi nhuận sau thuế | H15: % Lợi nhuận sau thuế | I15: Giá bán duyệt tháng 4 | J15: Giá đầu vào tăng | K15: Chai | L15: Tằng giá khác
A16: 1 | B16: 110000332 | C16: Hạt nhựa rPET iSS01084G | D16: =D12+J12*26500/1000 -> 31963.681 | E16: =E12+J12 -> 1206.1766 | F16: =F12 -> 1375.4717 | G16: =+F16-E16 -> 169.29505 | H16: =+G16/F16 -> 0.12308145 | I16: =1280+90 -> 1370 | J16: =K16+L16 -> 125.4717 | K16: =(2000*1000)/26500 -> 75.471698 | L16: 50
A17: 2 | B17: 110000483 | C17: Hạt Nhựa rPET iSS01G-S | D17: =D13+J13*26500/1000 -> 31955.622 | E17: =E13+J13 -> 1205.8725 | F17: =F13 -> 1355.4717 | G17: =+F17-E17 -> 149.59917 | H17: =+G17/F17 -> 0.11036687 | I17: =1280+30 -> 1310 | J17: =K17+L17 -> 125.4717 | K17: =(2000*1000)/26500 -> 75.471698 | L17: 50
A19: => Tăng/giảm:
A20: 1 | B20: 110000332 | C20: Hạt nhựa rPET iSS01084G | D20: =D16-D6 -> 39.359411 | E20: =E16-E6 -> 1.4852608 | F20: =F16-F6 -> 125.4717 | G20: =G16-G6 -> 123.98644 | H20: =H16-H6 -> 0.086834559 | I20: =I16-I6 -> 120
A21: 2 | B21: 110000483 | C21: Hạt Nhựa rPET iSS01G-S | D21: =D17-D7 -> 39.359411 | E21: =E17-E7 -> 1.4852608 | F21: =F17-F7 -> 125.4717 | G21: =G17-G7 -> 123.98644 | H21: =H17-H7 -> 0.089543511 | I21: =I17-I7 -> 80

Sheet Chart
C1: CHÀO GIÁ SUNTORY PEPSI 2026
D4: Tỷ giá USD: | E4: =+ISS01084G!K5 -> 26500
E5: ISS01084G | I5: ISS01G-S
A6: No. | B6: SAP | C6: Chi phí Cost Items | D6: Chi phí VNĐ /Kg | E6: Đơn giá USD /Tấn | F6: Cơ cấu % chi phí /Giá | H6: Chi phí VNĐ /Kg | I6: Đơn giá USD /Tấn | J6: Cơ cấu % chi phí /Giá
A7: A | B7: 1521 | C7: Chi phí nguyên vật liệu | D7: =+SUM(D8:D8) -> 15000 | E7: =D7*1000/$E$4 -> 566.03774 | F7: =E7/$E$26 -> 0.45283019 | H7: =+SUM(H8:H8) -> 15000 | I7: =H7*1000/$E$4 -> 566.03774 | J7: =I7/$E$26 -> 0.45283019
A8: 1 | B8: 1521 | C8: Chi phí chai B1 | D8: =+SUMIFS(ISS01084G!J:J,ISS01084G!D:D,Chart!B8) -> 15000 | E8: =D8*1000/$E$4 -> 566.03774 | F8: =E8/$E$26 -> 0.45283019 | H8: =+SUMIFS('ISS01G-S'!J:J,'ISS01G-S'!D:D,Chart!B8) -> 15000 | I8: =H8*1000/$E$4 -> 566.03774 | J8: =I8/$E$26 -> 0.45283019
A9: B | B9: 1522 | C9: Hao hụt về tiền | D9: =+SUMIFS(ISS01084G!J:J,ISS01084G!D:D,Chart!B9) -> 2929.8891 | E9: =D9*1000/$E$4 -> 110.56185 | F9: =E9/$E$26 -> 0.088449481 | H9: =+SUMIFS('ISS01G-S'!J:J,'ISS01G-S'!D:D,Chart!B9) -> 2929.8891 | I9: =H9*1000/$E$4 -> 110.56185 | J9: =I9/$E$26 -> 0.088449481
A10: C | C10: Chi phí sản xuất | D10: =SUM(D11:D17) -> 8816.8201 | E10: =D10*1000/$E$4 -> 332.71019 | F10: =E10/$E$26 -> 0.26616815 | H10: =SUM(H11:H17) -> 8808.761 | I10: =H10*1000/$E$4 -> 332.40607 | J10: =I10/$E$26 -> 0.26592486
A11: 2 | B11: LAB | C11: Chi phí nhân công | D11: =+SUMIFS(ISS01084G!J:J,ISS01084G!D:D,Chart!B11) -> 2638.9452 | E11: =D11*1000/$E$4 -> 99.582838 | F11: =E11/$E$26 -> 0.079666271 | H11: =+SUMIFS('ISS01G-S'!J:J,'ISS01G-S'!D:D,Chart!B11) -> 2638.9452 | I11: =H11*1000/$E$4 -> 99.582838 | J11: =I11/$E$26 -> 0.079666271
A12: =+A11+1 -> 3 | B12: DEP | C12: Khấu hao | D12: =+SUMIFS(ISS01084G!J:J,ISS01084G!D:D,Chart!B12) -> 2122.7599 | E12: =D12*1000/$E$4 -> 80.104146 | F12: =E12/$E$26 -> 0.064083317 | H12: =+SUMIFS('ISS01G-S'!J:J,'ISS01G-S'!D:D,Chart!B12) -> 2122.7599 | I12: =H12*1000/$E$4 -> 80.104146 | J12: =I12/$E$26 -> 0.064083317
A13: =+A12+1 -> 4 | B13: ELEC | C13: Chi phí gián tiếp | D13: =+SUMIFS(ISS01084G!J:J,ISS01084G!D:D,Chart!B13) -> 1752.4949 | E13: =D13*1000/$E$4 -> 66.131883 | F13: =E13/$E$26 -> 0.052905506 | H13: =+SUMIFS('ISS01G-S'!J:J,'ISS01G-S'!D:D,Chart!B13) -> 1752.4949 | I13: =H13*1000/$E$4 -> 66.131883 | J13: =I13/$E$26 -> 0.052905506
A14: =+A13+1 -> 5 | B14: OTH | C14: Điện | D14: =+SUMIFS(ISS01084G!J:J,ISS01084G!D:D,Chart!B14) -> 1478.1805 | E14: =D14*1000/$E$4 -> 55.780394 | F14: =E14/$E$26 -> 0.044624316 | H14: =+SUMIFS('ISS01G-S'!J:J,'ISS01G-S'!D:D,Chart!B14) -> 1478.1805 | I14: =H14*1000/$E$4 -> 55.780394 | J14: =I14/$E$26 -> 0.044624316
A15: =+A14+1 -> 6 | B15: BAG | C15: Đóng gói | D15: =+SUMIFS(ISS01084G!J:J,ISS01084G!D:D,Chart!B15) -> 408.84273 | E15: =D15*1000/$E$4 -> 15.428027 | F15: =E15/$E$26 -> 0.012342422 | H15: =+SUMIFS('ISS01G-S'!J:J,'ISS01G-S'!D:D,Chart!B15) -> 408.84273 | I15: =H15*1000/$E$4 -> 15.428027 | J15: =I15/$E$26 -> 0.012342422
A16: =+A15+1 -> 7 | B16: CHE | C16: Hóa chất | D16: =+SUMIFS(ISS01084G!J:J,ISS01084G!D:D,Chart!B16) -> 393.50254 | E16: =D16*1000/$E$4 -> 14.849152 | F16: =E16/$E$26 -> 0.011879322 | H16: =+SUMIFS('ISS01G-S'!J:J,'ISS01G-S'!D:D,Chart!B16) -> 385.44345 | I16: =H16*1000/$E$4 -> 14.545036 | J16: =I16/$E$26 -> 0.011636029
A17: =+A16+1 -> 8 | B17: H2O | C17: Nước | D17: =+SUMIFS(ISS01084G!J:J,ISS01084G!D:D,Chart!B17) -> 22.094374 | E17: =D17*1000/$E$4 -> 0.83374995 | F17: =E17/$E$26 -> 0.00066699996 | H17: =+SUMIFS('ISS01G-S'!J:J,'ISS01G-S'!D:D,Chart!B17) -> 22.094374 | I17: =H17*1000/$E$4 -> 0.83374995 | J17: =I17/$E$26 -> 0.00066699996
A18: D | C18: Giá thành (A+B+C) | D18: =SUM(D8:D10) -> 26746.709 | E18: =D18*1000/$E$4 -> 1009.3098 | F18: =E18/$E$26 -> 0.80744782 | H18: =SUM(H8:H10) -> 26738.65 | I18: =H18*1000/$E$4 -> 1009.0057 | J18: =I18/$E$26 -> 0.80720453
A19: E | C19: CP quản lý, bán hàng, lãi vay | D19: =+SUM(D20:D22) -> 5177.6126 | E19: =D19*1000/$E$4 -> 195.38161 | F19: =E19/$E$26 -> 0.15630528 | H19: =+SUM(H20:H22) -> 5177.6126 | I19: =H19*1000/$E$4 -> 195.38161 | J19: =I19/$E$26 -> 0.15630528
A20: 9 | B20: 642 | C20: Chi phí bán hàng | D20: =+SUMIFS(ISS01084G!J:J,ISS01084G!D:D,Chart!B20) -> 3098.1952 | E20: =D20*1000/$E$4 -> 116.91303 | F20: =E20/$E$26 -> 0.093530422 | H20: =+SUMIFS('ISS01G-S'!J:J,'ISS01G-S'!D:D,Chart!B20) -> 3098.1952 | I20: =H20*1000/$E$4 -> 116.91303 | J20: =I20/$E$26 -> 0.093530422
A21: 10 | B21: 641 | C21: Chi phí quản lý | D21: =+SUMIFS(ISS01084G!J:J,ISS01084G!D:D,Chart!B21) -> 1525.3261 | E21: =D21*1000/$E$4 -> 57.559475 | F21: =E21/$E$26 -> 0.04604758 | H21: =+SUMIFS('ISS01G-S'!J:J,'ISS01G-S'!D:D,Chart!B21) -> 1525.3261 | I21: =H21*1000/$E$4 -> 57.559475 | J21: =I21/$E$26 -> 0.04604758
A22: 11 | B22: 635 | C22: Chi phí lãi vay | D22: =+SUMIFS(ISS01084G!J:J,ISS01084G!D:D,Chart!B22) -> 554.09125 | E22: =D22*1000/$E$4 -> 20.909104 | F22: =E22/$E$26 -> 0.016727283 | H22: =+SUMIFS('ISS01G-S'!J:J,'ISS01G-S'!D:D,Chart!B22) -> 554.09125 | I22: =H22*1000/$E$4 -> 20.909104 | J22: =I22/$E$26 -> 0.016727283
A23: F | C23: Điểm hòa vốn (D+E) | D23: =+D18+D19 -> 31924.322 | E23: =D23*1000/$E$4 -> 1204.6914 | F23: =E23/$E$26 -> 0.96375311 | H23: =+H18+H19 -> 31916.263 | I23: =H23*1000/$E$4 -> 1204.3873 | J23: =I23/$E$26 -> 0.96350981
A24: 12 | B24: TAX | C24: Thuế thu nhập | D24: =+SUMIFS(ISS01084G!J:J,ISS01084G!D:D,Chart!B24) -> 200.11305 | E24: =D24*1000/$E$4 -> 7.5514359 | F24: =E24/$E$26 -> 0.0060411487 | H24: =+SUMIFS('ISS01G-S'!J:J,'ISS01G-S'!D:D,Chart!B24) -> 113.1229 | I24: =H24*1000/$E$4 -> 4.2687886 | J24: =I24/$E$26 -> 0.0034150309
A25: G | B25: LN | C25: Lợi nhuận sau thuế | D25: =+SUMIFS(ISS01084G!J:J,ISS01084G!D:D,Chart!B25) -> 1000.5653 | E25: =D25*1000/$E$4 -> 37.757179 | F25: =E25/$E$26 -> 0.030205743 | H25: =+SUMIFS('ISS01G-S'!J:J,'ISS01G-S'!D:D,Chart!B25) -> 565.61449 | I25: =H25*1000/$E$4 -> 21.343943 | J25: =I25/$E$26 -> 0.017075154
A26: H | C26: Giá bán | D26: =+D23+D24+D25 -> 33125 | E26: =D26*1000/$E$4 -> 1250 | F26: =E26/$E$26 -> 1 | H26: =+H23+H24+H25 -> 32595 | I26: =H26*1000/$E$4 -> 1230 | J26: =I26/$E$26 -> 0.984
C27: % Lãi gộp nguyên liệu/Giá bán | F27: =F26-F7-F9 -> 0.45872033 | J27: =J26-J7-J9 -> 0.44272033
E28: ="ĐIỂM HÒA VỐN "&ROUND(E23,0)&"$" -> ĐIỂM HÒA VỐN 1205$ | I28: ="ĐIỂM HÒA VỐN "&ROUND(I23,0)&"$" -> ĐIỂM HÒA VỐN 1204$

Sheet ISS01084G
A1: Danh mục | C1: 1
C2: PHƯƠNG ÁN SẢN XUẤT TỪ 100% CHAI RA HẠT ISS01084G (NÂNG IV 10h)
C4: Nguyên liệu: | D4: 100% chai vảy mua ngoài
C5: Thành phẩm: | D5: HẠT rPET iSS01084G (IV > 0,8) | J5: Tỷ giá USD: | K5: 26500
C7: No. | D7: Nhóm | E7: Mã SAP | F7: Chi phí Cost Items | G7: Đơn vị tính Unit | H7: Định mức Standard | I7: Đơn giá (VNĐ) | J7: Chi phí đơn vị (VNĐ /Kg) | K7: Đơn giá (USD /Tấn) | L7: % giá bán | M7: Cơ sở tính
C8: A | D8: CÔNG ĐOẠN TẠO VẢY THÔ:
B9: Chai | C9: I | D9: 1521 | F9: B1 - Chai PET tuyển nước ngọt | G9: vnđ /Kg | H9: 1 | I9: 15000 | J9: =I9 -> 15000 | K9: =J9/$K$5*1000 -> 566.03774 | L9: =J9/$J$58 -> 0.71542389
B10: Hao hụt | C10: II | D10: 1522 | F10: Hao hụt do băm chai B1 (chai khác loại, bao lót, kẽm, nắp) | G10: % | H10: =SUM(H11:H20) -> 0.17890491 | J10: =SUM(J11:J20) -> 1249.9477 | K10: =J10/$K$5*1000 -> 47.167838 | L10: =J10/$J$58 -> 0.059616163
E11: 160012437 | F11: Chai PET Phi Thực Phẩm | G11: % | H11: 0 | I11: 6000 | J11: =+($J$9-I11)*H11 -> 0 | K11: =J11/$K$5*1000 -> 0 | L11: =J11/$J$58 -> 0 | M11: Thu hồi theo giá thị trường
A12: Chai khác2 | E12: 160012250 | F12: Chai PET B8 Sau Phân Loại | G12: % | H12: 0 | I12: 11000 | J12: =+($J$9-I12)*H12 -> 0 | K12: =J12/$K$5*1000 -> 0 | L12: =J12/$J$58 -> 0 | M12: Thu hồi theo giá thị trường
A13: B4 | E13: 160012398 | F13: Chai PET B4 Sau Phân Loại | G13: % | H13: 0.0013146811 | I13: 12500 | J13: =+($J$9-I13)*H13 -> 3.2867028 | K13: =J13/$K$5*1000 -> 0.12402652 | L13: =J13/$J$58 -> 0.00015675905 | M13: Thu hồi theo giá thị trường
A14: B5 | E14: 160012252 | F14: Chai PET B5 Sau Phân Loại | G14: % | H14: 0.0020155036 | I14: 12500 | J14: =+($J$9-I14)*H14 -> 5.038759 | K14: =J14/$K$5*1000 -> 0.19014185 | L14: =J14/$J$58 -> 0.00024032324 | M14: Thu hồi theo giá thị trường
A15: B6 | E15: 160012247 | F15: Chai PET B6 Sau Phân Loại | G15: % | H15: 0.00065144366 | I15: 12300 | J15: =+($J$9-I15)*H15 -> 1.7588979 | K15: =J15/$K$5*1000 -> 0.066373505 | L15: =J15/$J$58 -> 8.3890504e-05 | M15: Thu hồi theo giá thị trường
A16: Olefin | E16: 160012335 | F16: Phó Sản PET B1/B8 Vảy-Nắp | G16: % | H16: 0.094914291 | I16: 10500 | J16: =+($J$9-I16)*H16 -> 427.11431 | K16: =J16/$K$5*1000 -> 16.117521 | L16: =J16/$J$58 -> 0.020371185 | M16: Thu hồi theo giá thị trường
A17: Bụi | E17: 160012334 | F17: Phó Sản PET Bụi Sàn Rung | G17: % | H17: 0.032148664 | I17: 5000 | J17: =+($J$9-I17)*H17 -> 321.48664 | K17: =J17/$K$5*1000 -> 12.131571 | L17: =J17/$J$58 -> 0.015333282 | M17: Thu hồi theo giá thị trường
A18: Tomra | E18: 160012268 | F18: Phó Sản PET Tomra Cổng 2 | G18: % | H18: 0.015908152 | I18: 10500 | J18: =+($J$9-I18)*H18 -> 71.586682 | K18: =J18/$K$5*1000 -> 2.7013842 | L18: =J18/$J$58 -> 0.0034143215 | M18: Thu hồi theo giá thị trường
A19: Zigzag | E19: 160012311 | F19: Phó Sản PET Zigzag | G19: % | H19: 0.0054188111 | I19: 11000 | J19: =+($J$9-I19)*H19 -> 21.675244 | K19: =J19/$K$5*1000 -> 0.81793375 | L19: =J19/$J$58 -> 0.0010337992 | M19: Thu hồi theo giá thị trường
A20: Mất đi | F20: Hao hụt nhãn, PVC, đất, cát, nước mất đi | G20: % | H20: 0.026533364 | I20: 0 | J20: =+($J$9-I20)*H20 -> 398.00046 | K20: =J20/$K$5*1000 -> 15.018885 | L20: =J20/$J$58 -> 0.018982603 | M20: Hao hụt mất đi
C21: III | F21: Chi phí băm vảy (bale to flake) | J21: =SUM(J22:J33) -> 2321.031 | K21: =J21*1000/$K$5 -> 87.586075 | L21: =J21/$J$58 -> 0.1107014
A22: Băm | C22: 0 | D22: REL01 | F22: Công suất máy (capacity) | G22: Kg /h | H22: 4800 | M22: Công suất máy 4800 (CW1: 1200, CW2:1200, Boretech 2400)
A23: Băm | F23: Hiệu suất máy | G23: % | H23: 0.6 | M23: Bình quân 3 tháng liền kề theo BI
A24: Băm | B24: NCTT | C24: =+C22+1 -> 1 | D24: LAB | E24: 622 | F24: Chi phí nhân công trực tiếp | G24: tháng | H24: 1 | I24: 1811265742 | J24: =+I24/($H$22*$H$23*24*30) -> 873.48849 | K24: =J24/$K$5*1000 -> 32.96183 | L24: =J24/$J$58 -> 0.041660969 | M24: 11 người lựa chai trên chuyền, 1 người cắt kiện, phế, 1 người đóng gói, 0,5 xe nâng
A25: Băm | B25: NCGT | C25: =+C23+1 -> 1 | D25: LAB | E25: 6271 | F25: Chi phí nhân công gián tiếp | G25: tháng | H25: 1 | I25: 7.5152141e+08 | J25: =+I25/($H$22*$H$23*24*30) -> 362.42352 | K25: =J25/$K$5*1000 -> 13.676359 | L25: =J25/$J$58 -> 0.017285763 | M25: Lương trưởng ca, hành chính, tổ trưởng, quản lý sản xuất gián tiếp như QC, Kỹ thuật
A26: Băm | B26: VTPX | C26: =+C24+1 -> 2 | D26: OTH | E26: 6272 | F26: Chi phí vật tư phân xưởng | G26: tháng | H26: 1 | I26: 3.3060958e+08 | J26: =+I26/($H$22*$H$23*24*30) -> 159.43749 | K26: =J26/$K$5*1000 -> 6.0165091 | L26: =J26/$J$58 -> 0.0076043592 | M26: Chi phí thực tế bình quân 3 tháng liền kề
A27: Băm | B27: CCDC | C27: =+C25+1 -> 2 | D27: OTH | E27: 6273 | F27: Chi phí CCDC, bảo trì | G27: tháng | H27: 1 | I27: 1.9855935e+08 | J27: =+I27/($H$22*$H$23*24*30) -> 95.755858 | K27: =J27/$K$5*1000 -> 3.6134286 | L27: =J27/$J$58 -> 0.0045670685 | M27: Chi phí thực tế bình quân 3 tháng liền kề
A28: Băm | B28: KH | C28: =+C26+1 -> 3 | D28: DEP | E28: 6274.1 | F28: Chi phí khấu hao MMTB chính | G28: tháng | H28: 1 | I28: 3.6698932e+08 | J28: =+I28/($H$22*$H$23*24*30) -> 176.98173 | K28: =J28/$K$5*1000 -> 6.6785559 | L28: =J28/$J$58 -> 0.0084411305 | M28: Chi phí thực tế bình quân 3 tháng liền kề theo danh sách TSCĐ
A29: Băm | B29: KH | C29: =+C27+1 -> 3 | D29: DEP | E29: 6274.2 | F29: Chi phí khấu hao MMTB phụ | G29: tháng | H29: 1 | I29: 2.9525985e+08 | J29: =+I29/($H$22*$H$23*24*30) -> 142.38997 | K29: =J29/$K$5*1000 -> 5.3732065 | L29: =J29/$J$58 -> 0.0067912792 | M29: Chi phí thực tế bình quân 3 tháng liền kề theo danh sách TSCĐ
A30: Băm | B30: KH | C30: =+C28+1 -> 4 | D30: DEP | E30: 6274.3 | F30: Chi phí khấu hao MMTB dùng chung | G30: tháng | H30: 1 | I30: 1.4463942e+08 | J30: =+I30/($H$22*$H$23*24*30) -> 69.752806 | K30: =J30/$K$5*1000 -> 2.6321814 | L30: =J30/$J$58 -> 0.0033268549 | M30: Chi phí thực tế bình quân 3 tháng liền kề theo danh sách TSCĐ
A31: Băm | B31: KH | C31: =+C29+1 -> 4 | D31: DEP | E31: 6274.4 | F31: Chi phí khấu hao nhà xưởng | G31: tháng | H31: 1 | I31: 1.7358714e+08 | J31: =+I31/($H$22*$H$23*24*30) -> 83.712935 | K31: =J31/$K$5*1000 -> 3.1589787 | L31: =J31/$J$58 -> 0.0039926822 | M31: Chi phí thực tế bình quân 3 tháng liền kề theo danh sách TSCĐ
A32: Băm | B32: Điện | C32: =+C27+1 -> 3 | D32: ELEC | E32: 6275 | F32: Điện (electronic) kwh | G32: Kwh | H32: 1 | I32: 3.3791931e+08 | J32: =+I32/($H$22*$H$23*24*30) -> 162.96263 | K32: =J32/$K$5*1000 -> 6.1495332 | L32: =J32/$J$58 -> 0.0077724905 | M32: Chi phí thực tế bình quân 3 tháng liền kề. CW1: 178 Kwh, CW2: 185 Kwh, Boretech: 132 Kwh
A33: Băm | B33: Khác | C33: =+C28+1 -> 4 | D33: OTH | E33: 6277.6278 | F33: Chi phí bằng tiền khác | G33: tháng | H33: 1 | I33: 4.0253876e+08 | J33: =+I33/($H$22*$H$23*24*30) -> 194.12556 | K33: =J33/$K$5*1000 -> 7.3254929 | L33: =J33/$J$58 -> 0.0092588042 | M33: Chi phí thực tế bình quân 3 tháng liền kề
D34: Cộng giá thành A0 - Vảy thô (I+II+III) | J34: =J9+J10+J21 -> 18570.979 | K34: =J34*1000/$K$5 -> 700.79165 | L34: =J34/$J$58 -> 0.88574145
C35: B | D35: CÔNG ĐOẠN RỬA VẢY:
C36: IV | F36: Chi phí A0 - Vảy thô | G36: Kg | H36: 1 | I36: =+J34 -> 18570.979 | J36: =+H36*I36 -> 18570.979 | K36: =J36*1000/$K$5 -> 700.79165 | L36: =J36/$J$58 -> 0.88574145
C37: V | F37: Chi phí rửa vảy, tách kim loại (clean flake) | J37: =SUM(J40:J57) -> 2395.6123 | K37: =J37*1000/$K$5 -> 90.400465 | L37: =J37/$J$58 -> 0.11425855
A38: Rửa | C38: 0 | D38: VBAL1 | F38: Công suất máy (capacity) | G38: Kg /h | H38: 10760 | M38: Công suất máy 5860 (CW1: 1800, CW2:1660, Boretech 2400)
A39: Rửa | F39: Hiệu suất máy | G39: % | H39: 0.81 | M39: Bình quân 3 tháng liền kề theo BI
A40: Zigzag | B40: Hao hụt | C40: =+C38+1 -> 1 | D40: 1522 | E40: 160012311 | F40: Phó Sản PET Zigzag | G40: % | H40: 0.0016854746 | I40: 11000 | J40: =+($J$34-I40)*H40 -> 12.760692 | K40: =J40/$K$5*1000 -> 0.48153554 | L40: =J40/$J$58 -> 0.00060862025 | M40: Thu hồi theo giá thị trường
A41: Tomra | B41: Hao hụt | C41: =+C40+1 -> 2 | D41: 1522 | E41: 160012419 | F41: Phó Sản PET Tomra Cổng 3 | G41: % | H41: 0.033714201 | I41: 9500 | J41: =+($J$34-I41)*H41 -> 305.82079 | K41: =J41/$K$5*1000 -> 11.540407 | L41: =J41/$J$58 -> 0.0145861 | M41: Thu hồi theo giá thị trường
A42: Bụi | B42: Hao hụt | C42: =+C41+1 -> 3 | D42: 1522 | E42: 160012336 | F42: Phó Sản PET Bụi Cám | G42: % | H42: 0.021619268 | I42: 5000 | J42: =+($J$34-I42)*H42 -> 293.39462 | K42: =J42/$K$5*1000 -> 11.071495 | L42: =J42/$J$58 -> 0.013993435 | M42: Thu hồi theo giá thị trường
A43: Mất đi | B43: Hao hụt | D43: 1522 | F43: Hao hụt mất đi | G43: % | H43: 0.018663663 | I43: 0 | J43: =+($J$34-I43)*H43 -> 346.60248 | K43: =J43/$K$5*1000 -> 13.079339 | L43: =J43/$J$58 -> 0.01653118 | M43: Hao hụt mất đi
B44: Hóa chất | C44: =+C42+1 -> 4 | D44: CHE | E44: 700000180 | F44: Sodium Hydroxide (32%) NaOH | G44: Kg | H44: 0.03476 | I44: 5082 | J44: =+H44*I44 -> 176.65032 | K44: =J44/$K$5*1000 -> 6.6660498 | L44: =J44/$J$58 -> 0.0084253239 | M44: Hóa chất theo BOM
B45: Hóa chất | C45: =+C44+1 -> 5 | D45: CHE | E45: 120002594 | F45: Chất thủy tinh lỏng Na2-SiO3-9H2O | G45: Kg | H45: 0.00284 | I45: 11500 | J45: =+H45*I45 -> 32.66 | K45: =J45/$K$5*1000 -> 1.2324528 | L45: =J45/$J$58 -> 0.0015577163 | M45: Hóa chất theo BOM
B46: Hóa chất | C46: =+C45+1 -> 6 | D46: CHE | E46: 700000185 | F46: Chất phá bọt Antifoam CS04 | G46: Kg | H46: 0.00052 | I46: 52000 | J46: =+H46*I46 -> 27.04 | K46: =J46/$K$5*1000 -> 1.0203774 | L46: =J46/$J$58 -> 0.0012896708 | M46: Hóa chất theo BOM
A47: Rửa | B47: NCTT | C47: =+C46+1 -> 7 | D47: LAB | E47: 622 | F47: Chi phí nhân công trực tiếp | G47: tháng | H47: 1 | I47: 8.6107521e+08 | J47: =+I47/($H$38*$H$39*24*30) -> 137.21807 | K47: =J47/$K$5*1000 -> 5.1780403 | L47: =J47/$J$58 -> 0.0065446055 | M47: Nạp liệu 2 người + đóng gói, ra hàng: 2 người + xe nâng 2+ vệ sinh sàn, nước 1 người
A48: Rửa | B48: NCGT | C48: =+C47+1 -> 8 | D48: LAB | E48: 6271 | F48: Chi phí nhân công gián tiếp | G48: tháng | H48: 1 | I48: 1.6045471e+09 | J48: =+I48/($H$38*$H$39*24*30) -> 255.69526 | K48: =J48/$K$5*1000 -> 9.6488776 | L48: =J48/$J$58 -> 0.012195366 | M48: Lương trưởng ca, hành chính, tổ trưởng, quản lý sản xuất gián tiếp như QC, Kỹ thuật
A49: Rửa | B49: VTPX | C49: =+C48+1 -> 9 | D49: OTH | E49: 6272 | F49: Chi phí vật tư phân xưởng | G49: tháng | H49: 1 | I49: 329511625 | J49: =+I49/($H$38*$H$39*24*30) -> 52.509871 | K49: =J49/$K$5*1000 -> 1.9815046 | L49: =J49/$J$58 -> 0.0025044544 | M49: Chi phí thực tế bình quân 3 tháng liền kề
A50: Rửa | B50: CCDC | C50: =+C49+1 -> 10 | D50: OTH | E50: 6273 | F50: Chi phí CCDC, bảo trì | G50: tháng | H50: 1 | I50: 1.6951941e+08 | J50: =+I50/($H$38*$H$39*24*30) -> 27.014047 | K50: =J50/$K$5*1000 -> 1.019398 | L50: =J50/$J$58 -> 0.001288433 | M50: Chi phí thực tế bình quân 3 tháng liền kề
A51: Rửa | B51: KH | C51: =+C50+1 -> 11 | D51: DEP | E51: 6274.1 | F51: Chi phí khấu hao MMTB chính | G51: tháng | H51: 1 | I51: 1.0337983e+09 | J51: =+I51/($H$38*$H$39*24*30) -> 164.74264 | K51: =J51/$K$5*1000 -> 6.2167036 | L51: =J51/$J$58 -> 0.0078573882 | M51: Chi phí thực tế bình quân 3 tháng liền kề theo danh sách TSCĐ
A52: Rửa | B52: KH | C52: =+C51+1 -> 12 | D52: DEP | E52: 6274.2 | F52: Chi phí khấu hao MMTB phụ | G52: tháng | H52: 1 | I52: 4.0580144e+08 | J52: =+I52/($H$38*$H$39*24*30) -> 64.667161 | K52: =J52/$K$5*1000 -> 2.4402702 | L52: =J52/$J$58 -> 0.0030842954 | M52: Chi phí thực tế bình quân 3 tháng liền kề theo danh sách TSCĐ
A53: Rửa | B53: KH | C53: =+C52+1 -> 13 | D53: DEP | E53: 6274.3 | F53: Chi phí khấu hao MMTB dùng chung | G53: tháng | H53: 1 | I53: 3.9574764e+08 | J53: =+I53/($H$38*$H$39*24*30) -> 63.065022 | K53: =J53/$K$5*1000 -> 2.3798121 | L53: =J53/$J$58 -> 0.0030078815 | M53: Chi phí thực tế bình quân 3 tháng liền kề theo danh sách TSCĐ
A54: Rửa | B54: KH | C54: =+C53+1 -> 14 | D54: DEP | E54: 6274.4 | F54: Chi phí khấu hao nhà xưởng | G54: tháng | H54: 1 | I54: 4.7495145e+08 | J54: =+I54/($H$38*$H$39*24*30) -> 75.686676 | K54: =J54/$K$5*1000 -> 2.856101 | L54: =J54/$J$58 -> 0.0036098704 | M54: Chi phí thực tế bình quân 3 tháng liền kề theo danh sách TSCĐ
A55: Rửa | B55: Điện | C55: =+C51+1 -> 12 | D55: ELEC | E55: 6275 | F55: Điện (electronic) kwh | G55: tháng | H55: 1 | I55: 1.249738e+09 | J55: =+I55/($H$38*$H$39*24*30) -> 199.15407 | K55: =J55/$K$5*1000 -> 7.5152481 | L55: =J55/$J$58 -> 0.0094986387 | M55: Chi phí thực tế bình quân 3 tháng liền kề. CW1: 99,5 Kwh, CW2: 99,5 Kwh, Boretech: 316 Kwh
A56: Rửa | B56: Điện | C56: =+C55+1 -> 13 | D56: H2O | E56: 6275 | F56: Nước (water) m3/giờ | G56: tháng | H56: 1 | I56: 138647320 | J56: =+I56/($H$38*$H$39*24*30) -> 22.094374 | K56: =J56/$K$5*1000 -> 0.83374995 | L56: =J56/$J$58 -> 0.0010537895 | M56: Chi phí thực tế bình quân 3 tháng liền kề
A57: Rửa | B57: Khác | C57: =+C56+1 -> 14 | D57: OTH | E57: 6277.6278 | F57: Chi phí bằng tiền khác | G57: tháng | H57: 1 | I57: 8.7122939e+08 | J57: =+I57/($H$38*$H$39*24*30) -> 138.8362 | K57: =J57/$K$5*1000 -> 5.2391021 | L57: =J57/$J$58 -> 0.0066217825 | M57: Chi phí thực tế bình quân 3 tháng liền kề
D58: Giá thành - A1_Vảy sạch từ chai (IV+V): | J58: =J36+J37 -> 20966.591 | K58: =J58*1000/$K$5 -> 791.19211 | L58: =J58/$J$58 -> 1
C59: C | D59: CÔNG ĐOẠN TẠO HẠT QUA MÁY STARLINGER:
C60: I | F60: Vảy sạch từ chai | H60: 1 | J60: =+J58 -> 20966.591 | K60: =J60/$K$5*1000 -> 791.19211 | L60: =J60/$J$109 -> 0.63295369
C61: II | F61: Chi phí tạo hạt máy Starlinger | J61: =SUM(J62:J79) -> 3448.232 | K61: =J61*1000/$K$5 -> 130.12196 | L61: =J61/$J$109 -> 0.10409757
A62: Tạo hạt | C62: 0 | D62: REL01 | F62: Công suất máy (capacity) | G62: Kg /h | H62: 6000 | M62: Công suất máy 6000 (CW1: 1500, CW2:1500, Boretech 3000)
A63: Tạo hạt | F63: Hiệu suất máy | G63: % | H63: 0.75 | M63: Bình quân 3 tháng liền kề theo BI
A64: Đầu keo | B64: Hao hụt | C64: =+C63+1 -> 1 | D64: 1522 | E64: 160012357 | F64: Phó Sản PET Đầu Keo | G64: % | H64: 0.01613169 | I64: 8000 | J64: =+(J$60-I64)*H64 -> 209.17303 | K64: =J64/$K$5*1000 -> 7.8933219 | L64: =J64/$J$109 -> 0.0063146575 | M64: Thu hồi theo giá thị trường | N64: 4.0389911 | O64: =+K64-N64 -> 3.8543308
A65: HAD | B65: Hao hụt | C65: =+C64+1 -> 2 | D65: 1522 | E65: 160012417 | F65: Phó Sản PET HAD | G65: % | H65: 0.013616789 | I65: 9500 | J65: =+(J$60-I65)*H65 -> 156.13815 | K65: =J65/$K$5*1000 -> 5.8920056 | L65: =J65/$J$109 -> 0.0047136045 | M65: Thu hồi theo giá thị trường | N65: 3.6668698 | O65: =+K65-N65 -> 2.2251358
A66: Bụi | B66: Hao hụt | C66: =+C65+1 -> 3 | D66: 1522 | E66: 160012336 | F66: Phó Sản PET Bụi Cám | G66: % | H66: 0.00031953672 | I66: 5000 | J66: =+(J$60-I66)*H66 -> 5.1019121 | K66: =J66/$K$5*1000 -> 0.19252499 | L66: =J66/$J$109 -> 0.00015401999 | M66: Thu hồi theo giá thị trường | N66: 0 | O66: =+K66-N66 -> 0.19252499
A67: PP Hạt | B67: Hao hụt | C67: =+C66+1 -> 4 | D67: 1522 | E67: 160012418 | F67: Phó Sản PET Hạt Lẫn Kim Loại | G67: % | H67: 0.0085630943 | I67: 15000 | J67: =+(J$60-I67)*H67 -> 51.092481 | K67: =J67/$K$5*1000 -> 1.9280182 | L67: =J67/$J$109 -> 0.0015424145 | M67: Thu hồi theo giá thị trường | N67: 2.5970685 | O67: =+K67-N67 -> -0.66905037
A68: Mất đi | B68: Hao hụt | C68: =+C67+1 -> 5 | D68: 1522 | F68: Hao hụt mất đi do keo dính lưới | G68: % | H68: 0.014301667 | I68: 0 | J68: =+(J$60-I68)*H68 -> 299.8572 | K68: =J68/$K$5*1000 -> 11.315366 | L68: =J68/$J$109 -> 0.0090522928 | M68: Hao hụt mất đi | N68: 1.7145151 | O68: =+K68-N68 -> 9.600851
B69: Phụ gia | C69: =+C68+1 -> 6 | D69: CHE | E69: 120003033 | F69: Phụ gia Anti Yellow CC10379752Z8, Avient | G69: % | H69: =0.39/2500 -> 0.000156 | I69: 1007386 | J69: =+H69*I69 -> 157.15222 | K69: =J69/$K$5*1000 -> 5.9302723 | L69: =J69/$J$109 -> 0.0047442178 | M69: Hóa chất theo BOM | N69: 3.7365765 | O69: =+K69-N69 -> 2.1936958
A70: Tạo hạt | B70: NCTT | C70: =+C69+1 -> 7 | D70: LAB | E70: 622 | F70: Chi phí nhân công trực tiếp | G70: tháng | H70: 1 | I70: 4.8448571e+08 | J70: =H70*I70/($H$62*$H$63*24*30) -> 149.53263 | K70: =J70/$K$5*1000 -> 5.6427406 | L70: =J70/$J$109 -> 0.0045141925 | N70: 2.3146075 | O70: =+K70-N70 -> 3.3281331
A71: Tạo hạt | B71: NCGT | C71: =+C70+1 -> 8 | D71: LAB | E71: 6271 | F71: Chi phí nhân công gián tiếp | G71: tháng | H71: 1 | I71: 1.2206788e+09 | J71: =H71*I71/($H$62*$H$63*24*30) -> 376.75272 | K71: =J71/$K$5*1000 -> 14.217084 | L71: =J71/$J$109 -> 0.011373667 | M71: Lương trưởng ca, hành chính, tổ trưởng, quản lý sản xuất gián tiếp như QC, Kỹ thuật | N71: 10.418755 | O71: =+K71-N71 -> 3.7983291
A72: Tạo hạt | B72: VTPX | C72: =+C71+1 -> 9 | D72: OTH | E72: 6272 | F72: Chi phí vật tư phân xưởng | G72: tháng | H72: 1 | I72: 3.6280187e+08 | J72: =H72*I72/($H$62*$H$63*24*30) -> 111.97589 | K72: =J72/$K$5*1000 -> 4.2255051 | L72: =J72/$J$109 -> 0.0033804041 | M72: Chi phí thực tế bình quân 3 tháng liền kề | N72: 2.6427307 | O72: =+K72-N72 -> 1.5827744
A73: Tạo hạt | B73: CCDC | C73: =+C72+1 -> 10 | D73: OTH | E73: 6273 | F73: Chi phí CCDC, bảo trì | G73: tháng | H73: 1 | I73: 473941442 | J73: =H73*I73/($H$62*$H$63*24*30) -> 146.27822 | K73: =J73/$K$5*1000 -> 5.5199329 | L73: =J73/$J$109 -> 0.0044159463 | M73: Chi phí thực tế bình quân 3 tháng liền kề | N73: 6.0380666 | O73: =+K73-N73 -> -0.51813363
A74: Tạo hạt | B74: KH | C74: =+C73+1 -> 11 | D74: DEP | E74: 6274.1 | F74: Chi phí khấu hao MMTB chính | G74: tháng | H74: 1 | I74: 2.0103763e+09 | J74: =H74*I74/($H$62*$H$63*24*30) -> 620.48651 | K74: =J74/$K$5*1000 -> 23.414585 | L74: =J74/$J$109 -> 0.018731668 | M74: Chi phí thực tế bình quân 3 tháng liền kề theo danh sách TSCĐ | N74: 20.249816 | O74: =+K74-N74 -> 3.1647689
A75: Tạo hạt | B75: KH | C75: =+C74+1 -> 12 | D75: DEP | E75: 6274.2 | F75: Chi phí khấu hao MMTB phụ | G75: tháng | H75: 1 | I75: 4.1175931e+08 | J75: =H75*I75/($H$62*$H$63*24*30) -> 127.08621 | K75: =J75/$K$5*1000 -> 4.7957059 | L75: =J75/$J$109 -> 0.0038365647 | M75: Chi phí thực tế bình quân 3 tháng liền kề theo danh sách TSCĐ | N75: 1.8659215 | O75: =+K75-N75 -> 2.9297844
A76: Tạo hạt | B76: KH | C76: =+C75+1 -> 13 | D76: DEP | E76: 6274.3 | F76: Chi phí khấu hao MMTB dùng chung | G76: tháng | H76: 1 | I76: 2.3958891e+08 | J76: =H76*I76/($H$62*$H$63*24*30) -> 73.947194 | K76: =J76/$K$5*1000 -> 2.7904602 | L76: =J76/$J$109 -> 0.0022323681 | M76: Chi phí thực tế bình quân 3 tháng liền kề theo danh sách TSCĐ | N76: 2.1907838 | O76: =+K76-N76 -> 0.59967638
A77: Tạo hạt | B77: KH | C77: =+C76+1 -> 14 | D77: DEP | E77: 6274.4 | F77: Chi phí khấu hao nhà xưởng | G77: tháng | H77: 1 | I77: 2.8753955e+08 | J77: =H77*I77/($H$62*$H$63*24*30) -> 88.746776 | K77: =J77/$K$5*1000 -> 3.3489349 | L77: =J77/$J$109 -> 0.002679148 | M77: Chi phí thực tế bình quân 3 tháng liền kề theo danh sách TSCĐ | N77: 2.8399046 | O77: =+K77-N77 -> 0.50903034
A78: Tạo hạt | B78: Điện | C78: =+C74+1 -> 12 | D78: ELEC | E78: 6275 | F78: Điện (electronic) Starlinger | G78: Kwh | H78: 1 | I78: 2.1909214e+09 | J78: =H78*I78/($H$62*$H$63*24*30) -> 676.2103 | K78: =J78/$K$5*1000 -> 25.51737 | L78: =J78/$J$109 -> 0.020413896 | M78: Chi phí thực tế bình quân 3 tháng liền kề. CW1: 752 Kwh, CW2: 752 Kwh, Boretech: 1254 Kwh | N78: 15.547201 | O78: =+K78-N78 -> 9.9701688
A79: Tạo hạt | B79: Khác | C79: =+C78+1 -> 13 | D79: OTH | E79: 6277.6278 | F79: Chi phí bằng tiền khác | G79: tháng | H79: 1 | I79: 6.4378995e+08 | J79: =H79*I79/($H$62*$H$63*24*30) -> 198.7006 | K79: =J79/$K$5*1000 -> 7.4981359 | L79: =J79/$J$109 -> 0.0059985087 | M79: Chi phí thực tế bình quân 3 tháng liền kề | N79: 5.1172085 | O79: =+K79-N79 -> 2.3809274
D80: Giá thành tạo hạt máy Starlinger (III+IV) | J80: =J60+J61 -> 24414.823 | K80: =J80*1000/$K$5 -> 921.31408 | L80: =J80/$J$109 -> 0.73705126
C81: D | D81: CÔNG ĐOẠN NÂNG IV LÊN > 0,8 (LƯU MÁY SSP 10 TIẾNG):
C82: III | F82: Hạt rPET WSS01 | J82: =J80 -> 24414.823 | K82: =J82*1000/$K$5 -> 921.31408 | L82: =J82/$J$109 -> 0.73705126
C83: IV | F83: Chi phí nâng IV (10 tiếng) | J83: =SUM(J84:J98) -> 2331.8861 | K83: =J83*1000/$K$5 -> 87.995702 | L83: =J83/$J$109 -> 0.070396562
A84: Nâng IV 10H | C84: 0 | D84: REL01 | F84: Công suất máy (capacity) | G84: Kg /h | H84: 3492 | M84: Công suất máy 3492 (SSP-01: 1092, SSP-02: 2400)
A85: Nâng IV 10H | F85: Hiệu suất máy | G85: % | H85: 0.81 | M85: Bình quân 3 tháng liền kề theo BI
B86: Bao bì | C86: =+C85+1 -> 1 | D86: BAG | E86: 160012673 | F86: Pallet D4-1137R không nút-GC | G86: cái | H86: 1 | I86: 261000 | J86: =(I86*H86)/1100 -> 237.27273 | K86: =J86/$K$5*1000 -> 8.9536878 | L86: =J86/$J$109 -> 0.0071629503 | M86: Giao trong nước pallet đen, giao xuất khẩu pallet gỗ
B87: Bao bì | C87: =+C86+1 -> 2 | D87: BAG | E87: 140005072 | F87: Bao jumbo 105Lx105Wx150H (cm) đựng vảy | G87: cái | H87: 1 | I87: 165225 | J87: =(I87*H87)/1100 -> 150.20455 | K87: =J87/$K$5*1000 -> 5.6680961 | L87: =J87/$J$109 -> 0.0045344768 | M87: 1100 kg hạt/bao
B88: Bao bì | C88: =+C87+1 -> 3 | D88: BAG | E88: 140006090 | F88: Bao PE lót ngoài bao Jumbo | G88: cái | H88: 1 | I88: 23502 | J88: =(I88*H88)/1100 -> 21.365455 | K88: =J88/$K$5*1000 -> 0.80624357 | L88: =J88/$J$109 -> 0.00064499485 | M88: 1100 kg hạt/bao
A89: Nâng IV | B89: NCTT | C89: =+C88+1 -> 4 | D89: LAB | E89: 622 | F89: Chi phí nhân công trực tiếp | G89: tháng | H89: 1 | I89: 1.4639311e+08 | J89: =H89*I89/($H$84*$H$85*24*30) -> 71.883446 | K89: =J89/$K$5*1000 -> 2.7125829 | L89: =J89/$J$109 -> 0.0021700663 | M89: Nạp liệu 1, đóng gói 1, xe nâng 1
A90: Nâng IV | B90: NCGT | C90: =+C89+1 -> 5 | D90: LAB | E90: 6271 | F90: Chi phí nhân công gián tiếp | G90: tháng | H90: 1 | I90: 8.3895256e+08 | J90: =H90*I90/($H$84*$H$85*24*30) -> 411.95109 | K90: =J90/$K$5*1000 -> 15.545324 | L90: =J90/$J$109 -> 0.012436259 | M90: Lương trưởng ca, hành chính, tổ trưởng, quản lý sản xuất gián tiếp như QC, Kỹ thuật
A91: Nâng IV | B91: VTPX | C91: =+C90+1 -> 6 | D91: OTH | E91: 6272 | F91: Chi phí vật tư phân xưởng | G91: tháng | H91: 1 | I91: 1.3717563e+08 | J91: =H91*I91/($H$84*$H$85*24*30) -> 67.357383 | K91: =J91/$K$5*1000 -> 2.541788 | L91: =J91/$J$109 -> 0.0020334304 | M91: Chi phí thực tế bình quân 3 tháng liền kề
A92: Nâng IV | B92: CCDC | C92: =+C91+1 -> 7 | D92: OTH | E92: 6273 | F92: Chi phí CCDC, bảo trì | G92: tháng | H92: 1 | I92: 1.3671072e+08 | J92: =H92*I92/($H$84*$H$85*24*30) -> 67.129098 | K92: =J92/$K$5*1000 -> 2.5331735 | L92: =J92/$J$109 -> 0.0020265388 | M92: Chi phí thực tế bình quân 3 tháng liền kề
A93: Nâng IV | B93: KH | C93: =+C92+1 -> 8 | D93: DEP | E93: 6274.1 | F93: Chi phí khấu hao MMTB chính | G93: tháng | H93: 1 | I93: 3.643082e+08 | J93: =H93*I93/($H$84*$H$85*24*30) -> 178.88635 | K93: =J93/$K$5*1000 -> 6.7504282 | L93: =J93/$J$109 -> 0.0054003425 | M93: Chi phí thực tế bình quân 3 tháng liền kề theo danh sách TSCĐ
A94: Nâng IV | B94: KH | C94: =+C93+1 -> 9 | D94: DEP | E94: 6274.2 | F94: Chi phí khấu hao MMTB phụ | G94: tháng | H94: 1 | I94: 0 | J94: =H94*I94/($H$84*$H$85*24*30) -> 0 | K94: =J94/$K$5*1000 -> 0 | L94: =J94/$J$109 -> 0 | M94: Chi phí thực tế bình quân 3 tháng liền kề theo danh sách TSCĐ
A95: Nâng IV | B95: KH | C95: =+C94+1 -> 10 | D95: DEP | E95: 6274.3 | F95: Chi phí khấu hao MMTB dùng chung | G95: tháng | H95: 1 | I95: 1.7828552e+08 | J95: =H95*I95/($H$84*$H$85*24*30) -> 87.543582 | K95: =J95/$K$5*1000 -> 3.3035314 | L95: =J95/$J$109 -> 0.0026428251 | M95: Chi phí thực tế bình quân 3 tháng liền kề theo danh sách TSCĐ
A96: Nâng IV | B96: KH | C96: =+C95+1 -> 11 | D96: DEP | E96: 6274.4 | F96: Chi phí khấu hao nhà xưởng | G96: tháng | H96: 1 | I96: 2.1396707e+08 | J96: =H96*I96/($H$84*$H$85*24*30) -> 105.06431 | K96: =J96/$K$5*1000 -> 3.9646908 | L96: =J96/$J$109 -> 0.0031717526 | M96: Chi phí thực tế bình quân 3 tháng liền kề theo danh sách TSCĐ
A97: Nâng IV | B97: Điện | C97: =+C93+1 -> 9 | D97: ELEC | E97: 6275 | F97: Điện (electronic) SSP | G97: tháng | H97: 1 | I97: 1.4544275e+09 | J97: =H97*I97/($H$84*$H$85*24*30) -> 714.1679 | K97: =J97/$K$5*1000 -> 26.949732 | L97: =J97/$J$109 -> 0.021559786 | M97: Chi phí thực tế bình quân 3 tháng liền kề. CW1: 946 Kwh, Boretech: 487 Kwh
A98: Nâng IV | B98: Khác | C98: =+C97+1 -> 10 | D98: OTH | E98: 6277.6278 | F98: Chi phí bằng tiền khác | G98: tháng | H98: 1 | I98: 4.4612369e+08 | J98: =H98*I98/($H$84*$H$85*24*30) -> 219.06023 | K98: =J98/$K$5*1000 -> 8.2664238 | L98: =J98/$J$109 -> 0.006613139 | M98: Chi phí thực tế bình quân 3 tháng liền kề
C99: V | F99: Chi phí quản lý | J99: =SUM(J100:J104) -> 5177.6126 | K99: =J99*1000/$K$5 -> 195.38161 | L99: =J99/$J$109 -> 0.15630528
A100: LuongBH | B100: 641 | C100: 1 | D100: 641 | F100: Chi phí nhân sự bán hàng | G100: tháng | H100: 1 | I100: 4.7379281e+08 | J100: =+I100/($H$84*$H$85*24*30) -> 232.6466 | K100: =J100/$K$5*1000 -> 8.7791171 | L100: =J100/$J$109 -> 0.0070232937 | M100: Chi phí lương BGĐ, kế toán, HCNS, bán hàng…
A101: LuongQL | B101: 642 | C101: =+C100+1 -> 2 | D101: 642 | F101: Chi phí nhân sự quản lý | G101: tháng | H101: 1 | I101: 4.7196996e+09 | J101: =+I101/($H$84*$H$85*24*30) -> 2317.5153 | K101: =J101/$K$5*1000 -> 87.453407 | L101: =J101/$J$109 -> 0.069962725 | M101: Chi phí lương BGĐ, kế toán, HCNS, bán hàng…
A102: Banhang | B102: 641 | C102: =+C101+1 -> 3 | D102: 641 | F102: Chi phí bán hàng | G102: tháng | H102: 1 | I102: 2.6325862e+09 | J102: =+I102/($H$84*$H$85*24*30) -> 1292.6795 | K102: =J102/$K$5*1000 -> 48.780358 | L102: =J102/$J$109 -> 0.039024286 | M102: Chi phí lương BGĐ, kế toán, HCNS, bán hàng…
...

Sheet ISS01G-S
A1: Danh mục | C1: 1
C2: PHƯƠNG ÁN SẢN XUẤT TỪ 100% CHAI RA HẠT ISS01G-S (NÂNG IV 10h)
C4: Nguyên liệu: | D4: 100% chai vảy mua ngoài
C5: Thành phẩm: | D5: HẠT rPET ISS01G-S (IV > 0,8) | J5: Tỷ giá USD: | K5: 26500
C7: No. | D7: Nhóm | E7: Mã SAP | F7: Chi phí Cost Items | G7: Đơn vị tính Unit | H7: Định mức Standard | I7: Đơn giá (VNĐ) | J7: Chi phí đơn vị (VNĐ /Kg) | K7: Đơn giá (USD /Tấn) | L7: % giá bán | M7: Cơ sở tính
C8: A | D8: CÔNG ĐOẠN TẠO VẢY THÔ:
B9: Chai | C9: I | D9: 1521 | E9: 150000187 | F9: Chai PET B1.3 | G9: vnđ /Kg | H9: 1 | I9: 15000 | J9: =I9 -> 15000 | K9: =J9/$K$5*1000 -> 566.03774 | L9: =J9/$J$58 -> 0.71542389
B10: Hao hụt | C10: II | D10: 1522 | F10: Hao hụt do băm chai B1 (chai khác loại, bao lót, kẽm, nắp) | G10: % | H10: =SUM(H11:H20) -> 0.17890491 | J10: =SUM(J11:J20) -> 1249.9477 | K10: =J10/$K$5*1000 -> 47.167838 | L10: =J10/$J$58 -> 0.059616163
E11: 160012437 | F11: Chai PET Phi Thực Phẩm | G11: % | H11: 0 | I11: 6000 | J11: =+($J$9-I11)*H11 -> 0 | K11: =J11/$K$5*1000 -> 0 | L11: =J11/$J$58 -> 0 | M11: Thu hồi theo giá thị trường
A12: Chai khác2 | E12: 160012250 | F12: Chai PET B8 Sau Phân Loại | G12: % | H12: 0 | I12: 11000 | J12: =+($J$9-I12)*H12 -> 0 | K12: =J12/$K$5*1000 -> 0 | L12: =J12/$J$58 -> 0 | M12: Thu hồi theo giá thị trường
A13: B4 | E13: 160012398 | F13: Chai PET B4 Sau Phân Loại | G13: % | H13: 0.0013146811 | I13: 12500 | J13: =+($J$9-I13)*H13 -> 3.2867028 | K13: =J13/$K$5*1000 -> 0.12402652 | L13: =J13/$J$58 -> 0.00015675905 | M13: Thu hồi theo giá thị trường
A14: B5 | E14: 160012252 | F14: Chai PET B5 Sau Phân Loại | G14: % | H14: 0.0020155036 | I14: 12500 | J14: =+($J$9-I14)*H14 -> 5.038759 | K14: =J14/$K$5*1000 -> 0.19014185 | L14: =J14/$J$58 -> 0.00024032324 | M14: Thu hồi theo giá thị trường
A15: B6 | E15: 160012247 | F15: Chai PET B6 Sau Phân Loại | G15: % | H15: 0.00065144366 | I15: 12300 | J15: =+($J$9-I15)*H15 -> 1.7588979 | K15: =J15/$K$5*1000 -> 0.066373505 | L15: =J15/$J$58 -> 8.3890504e-05 | M15: Thu hồi theo giá thị trường
A16: Olefin | E16: 160012335 | F16: Phó Sản PET B1/B8 Vảy-Nắp | G16: % | H16: 0.094914291 | I16: 10500 | J16: =+($J$9-I16)*H16 -> 427.11431 | K16: =J16/$K$5*1000 -> 16.117521 | L16: =J16/$J$58 -> 0.020371185 | M16: Thu hồi theo giá thị trường
A17: Bụi | E17: 160012334 | F17: Phó Sản PET Bụi Sàn Rung | G17: % | H17: 0.032148664 | I17: 5000 | J17: =+($J$9-I17)*H17 -> 321.48664 | K17: =J17/$K$5*1000 -> 12.131571 | L17: =J17/$J$58 -> 0.015333282 | M17: Thu hồi theo giá thị trường
A18: Tomra | E18: 160012268 | F18: Phó Sản PET Tomra Cổng 2 | G18: % | H18: 0.015908152 | I18: 10500 | J18: =+($J$9-I18)*H18 -> 71.586682 | K18: =J18/$K$5*1000 -> 2.7013842 | L18: =J18/$J$58 -> 0.0034143215 | M18: Thu hồi theo giá thị trường
A19: Zigzag | E19: 160012311 | F19: Phó Sản PET Zigzag | G19: % | H19: 0.0054188111 | I19: 11000 | J19: =+($J$9-I19)*H19 -> 21.675244 | K19: =J19/$K$5*1000 -> 0.81793375 | L19: =J19/$J$58 -> 0.0010337992 | M19: Thu hồi theo giá thị trường
A20: Mất đi | F20: Hao hụt nhãn, PVC, đất, cát, nước mất đi | G20: % | H20: 0.026533364 | I20: 0 | J20: =+($J$9-I20)*H20 -> 398.00046 | K20: =J20/$K$5*1000 -> 15.018885 | L20: =J20/$J$58 -> 0.018982603 | M20: Hao hụt mất đi
C21: III | F21: Chi phí băm vảy (bale to flake) | J21: =SUM(J22:J33) -> 2321.031 | K21: =J21*1000/$K$5 -> 87.586075 | L21: =J21/$J$58 -> 0.1107014
A22: Băm | C22: 0 | D22: REL01 | F22: Công suất máy (capacity) | G22: Kg /h | H22: 4800 | M22: Công suất máy 4800 (CW1: 1200, CW2:1200, Boretech 2400)
A23: Băm | F23: Hiệu suất máy | G23: % | H23: 0.6 | M23: Bình quân 3 tháng liền kề theo BI
A24: Băm | B24: NCTT | C24: =+C22+1 -> 1 | D24: LAB | E24: 622 | F24: Chi phí nhân công trực tiếp | G24: tháng | H24: 1 | I24: 1811265742 | J24: =+I24/($H$22*$H$23*24*30) -> 873.48849 | K24: =J24/$K$5*1000 -> 32.96183 | L24: =J24/$J$58 -> 0.041660969 | M24: 11 người lựa chai trên chuyền, 1 người cắt kiện, phế, 1 người đóng gói, 0,5 xe nâng
A25: Băm | B25: NCGT | C25: =+C23+1 -> 1 | D25: LAB | E25: 6271 | F25: Chi phí nhân công gián tiếp | G25: tháng | H25: 1 | I25: 7.5152141e+08 | J25: =+I25/($H$22*$H$23*24*30) -> 362.42352 | K25: =J25/$K$5*1000 -> 13.676359 | L25: =J25/$J$58 -> 0.017285763 | M25: Lương trưởng ca, hành chính, tổ trưởng, quản lý sản xuất gián tiếp như QC, Kỹ thuật
A26: Băm | B26: VTPX | C26: =+C24+1 -> 2 | D26: OTH | E26: 6272 | F26: Chi phí vật tư phân xưởng | G26: tháng | H26: 1 | I26: 3.3060958e+08 | J26: =+I26/($H$22*$H$23*24*30) -> 159.43749 | K26: =J26/$K$5*1000 -> 6.0165091 | L26: =J26/$J$58 -> 0.0076043592 | M26: Chi phí thực tế bình quân 3 tháng liền kề
A27: Băm | B27: CCDC | C27: =+C25+1 -> 2 | D27: OTH | E27: 6273 | F27: Chi phí CCDC, bảo trì | G27: tháng | H27: 1 | I27: 1.9855935e+08 | J27: =+I27/($H$22*$H$23*24*30) -> 95.755858 | K27: =J27/$K$5*1000 -> 3.6134286 | L27: =J27/$J$58 -> 0.0045670685 | M27: Chi phí thực tế bình quân 3 tháng liền kề
A28: Băm | B28: KH | C28: =+C26+1 -> 3 | D28: DEP | E28: 6274.1 | F28: Chi phí khấu hao MMTB chính | G28: tháng | H28: 1 | I28: 3.6698932e+08 | J28: =+I28/($H$22*$H$23*24*30) -> 176.98173 | K28: =J28/$K$5*1000 -> 6.6785559 | L28: =J28/$J$58 -> 0.0084411305 | M28: Chi phí thực tế bình quân 3 tháng liền kề theo danh sách TSCĐ
A29: Băm | B29: KH | C29: =+C27+1 -> 3 | D29: DEP | E29: 6274.2 | F29: Chi phí khấu hao MMTB phụ | G29: tháng | H29: 1 | I29: 2.9525985e+08 | J29: =+I29/($H$22*$H$23*24*30) -> 142.38997 | K29: =J29/$K$5*1000 -> 5.3732065 | L29: =J29/$J$58 -> 0.0067912792 | M29: Chi phí thực tế bình quân 3 tháng liền kề theo danh sách TSCĐ
A30: Băm | B30: KH | C30: =+C28+1 -> 4 | D30: DEP | E30: 6274.3 | F30: Chi phí khấu hao MMTB dùng chung | G30: tháng | H30: 1 | I30: 1.4463942e+08 | J30: =+I30/($H$22*$H$23*24*30) -> 69.752806 | K30: =J30/$K$5*1000 -> 2.6321814 | L30: =J30/$J$58 -> 0.0033268549 | M30: Chi phí thực tế bình quân 3 tháng liền kề theo danh sách TSCĐ
A31: Băm | B31: KH | C31: =+C29+1 -> 4 | D31: DEP | E31: 6274.4 | F31: Chi phí khấu hao nhà xưởng | G31: tháng | H31: 1 | I31: 1.7358714e+08 | J31: =+I31/($H$22*$H$23*24*30) -> 83.712935 | K31: =J31/$K$5*1000 -> 3.1589787 | L31: =J31/$J$58 -> 0.0039926822 | M31: Chi phí thực tế bình quân 3 tháng liền kề theo danh sách TSCĐ
A32: Băm | B32: Điện | C32: =+C27+1 -> 3 | D32: ELEC | E32: 6275 | F32: Điện (electronic) kwh | G32: Kwh | H32: 1 | I32: 3.3791931e+08 | J32: =+I32/($H$22*$H$23*24*30) -> 162.96263 | K32: =J32/$K$5*1000 -> 6.1495332 | L32: =J32/$J$58 -> 0.0077724905 | M32: Chi phí thực tế bình quân 3 tháng liền kề. CW1: 178 Kwh, CW2: 185 Kwh, Boretech: 132 Kwh
A33: Băm | B33: Khác | C33: =+C28+1 -> 4 | D33: OTH | E33: 6277.6278 | F33: Chi phí bằng tiền khác | G33: tháng | H33: 1 | I33: 4.0253876e+08 | J33: =+I33/($H$22*$H$23*24*30) -> 194.12556 | K33: =J33/$K$5*1000 -> 7.3254929 | L33: =J33/$J$58 -> 0.0092588042 | M33: Chi phí thực tế bình quân 3 tháng liền kề
D34: Cộng giá thành A0 - Vảy thô (I+II+III) | J34: =J9+J10+J21 -> 18570.979 | K34: =J34*1000/$K$5 -> 700.79165 | L34: =J34/$J$58 -> 0.88574145
C35: B | D35: CÔNG ĐOẠN RỬA VẢY:
C36: IV | F36: Chi phí A0 - Vảy thô | G36: Kg | H36: 1 | I36: =+J34 -> 18570.979 | J36: =+H36*I36 -> 18570.979 | K36: =J36*1000/$K$5 -> 700.79165 | L36: =J36/$J$58 -> 0.88574145
C37: V | F37: Chi phí rửa vảy, tách kim loại (clean flake) | J37: =SUM(J40:J57) -> 2395.6123 | K37: =J37*1000/$K$5 -> 90.400465 | L37: =J37/$J$58 -> 0.11425855
A38: Rửa | C38: 0 | D38: VBAL1 | F38: Công suất máy (capacity) | G38: Kg /h | H38: 10760 | M38: Công suất máy 5860 (CW1: 1800, CW2:1660, Boretech 2400)
A39: Rửa | F39: Hiệu suất máy | G39: % | H39: 0.81 | M39: Bình quân 3 tháng liền kề theo BI
A40: Zigzag | B40: Hao hụt | C40: =+C38+1 -> 1 | D40: 1522 | E40: 160012311 | F40: Phó Sản PET Zigzag | G40: % | H40: 0.0016854746 | I40: 11000 | J40: =+($J$34-I40)*H40 -> 12.760692 | K40: =J40/$K$5*1000 -> 0.48153554 | L40: =J40/$J$58 -> 0.00060862025 | M40: Thu hồi theo giá thị trường
A41: Tomra | B41: Hao hụt | C41: =+C40+1 -> 2 | D41: 1522 | E41: 160012419 | F41: Phó Sản PET Tomra Cổng 3 | G41: % | H41: 0.033714201 | I41: 9500 | J41: =+($J$34-I41)*H41 -> 305.82079 | K41: =J41/$K$5*1000 -> 11.540407 | L41: =J41/$J$58 -> 0.0145861 | M41: Thu hồi theo giá thị trường
A42: Bụi | B42: Hao hụt | C42: =+C41+1 -> 3 | D42: 1522 | E42: 160012336 | F42: Phó Sản PET Bụi Cám | G42: % | H42: 0.021619268 | I42: 5000 | J42: =+($J$34-I42)*H42 -> 293.39462 | K42: =J42/$K$5*1000 -> 11.071495 | L42: =J42/$J$58 -> 0.013993435 | M42: Thu hồi theo giá thị trường
A43: Mất đi | B43: Hao hụt | D43: 1522 | F43: Hao hụt mất đi | G43: % | H43: 0.018663663 | I43: 0 | J43: =+($J$34-I43)*H43 -> 346.60248 | K43: =J43/$K$5*1000 -> 13.079339 | L43: =J43/$J$58 -> 0.01653118 | M43: Hao hụt mất đi
B44: Hóa chất | C44: =+C42+1 -> 4 | D44: CHE | E44: 700000180 | F44: Sodium Hydroxide (32%) NaOH | G44: Kg | H44: 0.03476 | I44: 5082 | J44: =+H44*I44 -> 176.65032 | K44: =J44/$K$5*1000 -> 6.6660498 | L44: =J44/$J$58 -> 0.0084253239 | M44: Hóa chất theo BOM
B45: Hóa chất | C45: =+C44+1 -> 5 | D45: CHE | E45: 120002594 | F45: Chất thủy tinh lỏng Na2-SiO3-9H2O | G45: Kg | H45: 0.00284 | I45: 11500 | J45: =+H45*I45 -> 32.66 | K45: =J45/$K$5*1000 -> 1.2324528 | L45: =J45/$J$58 -> 0.0015577163 | M45: Hóa chất theo BOM
B46: Hóa chất | C46: =+C45+1 -> 6 | D46: CHE | E46: 700000185 | F46: Chất phá bọt Antifoam CS04 | G46: Kg | H46: 0.00052 | I46: 52000 | J46: =+H46*I46 -> 27.04 | K46: =J46/$K$5*1000 -> 1.0203774 | L46: =J46/$J$58 -> 0.0012896708 | M46: Hóa chất theo BOM
A47: Rửa | B47: NCTT | C47: =+C46+1 -> 7 | D47: LAB | E47: 622 | F47: Chi phí nhân công trực tiếp | G47: tháng | H47: 1 | I47: 8.6107521e+08 | J47: =+I47/($H$38*$H$39*24*30) -> 137.21807 | K47: =J47/$K$5*1000 -> 5.1780403 | L47: =J47/$J$58 -> 0.0065446055 | M47: Nạp liệu 2 người + đóng gói, ra hàng: 2 người + xe nâng 2+ vệ sinh sàn, nước 1 người
A48: Rửa | B48: NCGT | C48: =+C47+1 -> 8 | D48: LAB | E48: 6271 | F48: Chi phí nhân công gián tiếp | G48: tháng | H48: 1 | I48: 1.6045471e+09 | J48: =+I48/($H$38*$H$39*24*30) -> 255.69526 | K48: =J48/$K$5*1000 -> 9.6488776 | L48: =J48/$J$58 -> 0.012195366 | M48: Lương trưởng ca, hành chính, tổ trưởng, quản lý sản xuất gián tiếp như QC, Kỹ thuật
A49: Rửa | B49: VTPX | C49: =+C48+1 -> 9 | D49: OTH | E49: 6272 | F49: Chi phí vật tư phân xưởng | G49: tháng | H49: 1 | I49: 329511625 | J49: =+I49/($H$38*$H$39*24*30) -> 52.509871 | K49: =J49/$K$5*1000 -> 1.9815046 | L49: =J49/$J$58 -> 0.0025044544 | M49: Chi phí thực tế bình quân 3 tháng liền kề
A50: Rửa | B50: CCDC | C50: =+C49+1 -> 10 | D50: OTH | E50: 6273 | F50: Chi phí CCDC, bảo trì | G50: tháng | H50: 1 | I50: 1.6951941e+08 | J50: =+I50/($H$38*$H$39*24*30) -> 27.014047 | K50: =J50/$K$5*1000 -> 1.019398 | L50: =J50/$J$58 -> 0.001288433 | M50: Chi phí thực tế bình quân 3 tháng liền kề
A51: Rửa | B51: KH | C51: =+C50+1 -> 11 | D51: DEP | E51: 6274.1 | F51: Chi phí khấu hao MMTB chính | G51: tháng | H51: 1 | I51: 1.0337983e+09 | J51: =+I51/($H$38*$H$39*24*30) -> 164.74264 | K51: =J51/$K$5*1000 -> 6.2167036 | L51: =J51/$J$58 -> 0.0078573882 | M51: Chi phí thực tế bình quân 3 tháng liền kề theo danh sách TSCĐ
A52: Rửa | B52: KH | C52: =+C51+1 -> 12 | D52: DEP | E52: 6274.2 | F52: Chi phí khấu hao MMTB phụ | G52: tháng | H52: 1 | I52: 4.0580144e+08 | J52: =+I52/($H$38*$H$39*24*30) -> 64.667161 | K52: =J52/$K$5*1000 -> 2.4402702 | L52: =J52/$J$58 -> 0.0030842954 | M52: Chi phí thực tế bình quân 3 tháng liền kề theo danh sách TSCĐ
A53: Rửa | B53: KH | C53: =+C52+1 -> 13 | D53: DEP | E53: 6274.3 | F53: Chi phí khấu hao MMTB dùng chung | G53: tháng | H53: 1 | I53: 3.9574764e+08 | J53: =+I53/($H$38*$H$39*24*30) -> 63.065022 | K53: =J53/$K$5*1000 -> 2.3798121 | L53: =J53/$J$58 -> 0.0030078815 | M53: Chi phí thực tế bình quân 3 tháng liền kề theo danh sách TSCĐ
A54: Rửa | B54: KH | C54: =+C53+1 -> 14 | D54: DEP | E54: 6274.4 | F54: Chi phí khấu hao nhà xưởng | G54: tháng | H54: 1 | I54: 4.7495145e+08 | J54: =+I54/($H$38*$H$39*24*30) -> 75.686676 | K54: =J54/$K$5*1000 -> 2.856101 | L54: =J54/$J$58 -> 0.0036098704 | M54: Chi phí thực tế bình quân 3 tháng liền kề theo danh sách TSCĐ
A55: Rửa | B55: Điện | C55: =+C51+1 -> 12 | D55: ELEC | E55: 6275 | F55: Điện (electronic) kwh | G55: tháng | H55: 1 | I55: 1.249738e+09 | J55: =+I55/($H$38*$H$39*24*30) -> 199.15407 | K55: =J55/$K$5*1000 -> 7.5152481 | L55: =J55/$J$58 -> 0.0094986387 | M55: Chi phí thực tế bình quân 3 tháng liền kề. CW1: 99,5 Kwh, CW2: 99,5 Kwh, Boretech: 316 Kwh
A56: Rửa | B56: Điện | C56: =+C55+1 -> 13 | D56: H2O | E56: 6275 | F56: Nước (water) m3/giờ | G56: tháng | H56: 1 | I56: 138647320 | J56: =+I56/($H$38*$H$39*24*30) -> 22.094374 | K56: =J56/$K$5*1000 -> 0.83374995 | L56: =J56/$J$58 -> 0.0010537895 | M56: Chi phí thực tế bình quân 3 tháng liền kề
A57: Rửa | B57: Khác | C57: =+C56+1 -> 14 | D57: OTH | E57: 6277.6278 | F57: Chi phí bằng tiền khác | G57: tháng | H57: 1 | I57: 8.7122939e+08 | J57: =+I57/($H$38*$H$39*24*30) -> 138.8362 | K57: =J57/$K$5*1000 -> 5.2391021 | L57: =J57/$J$58 -> 0.0066217825 | M57: Chi phí thực tế bình quân 3 tháng liền kề
D58: Giá thành - A1_Vảy sạch từ chai (IV+V): | J58: =J36+J37 -> 20966.591 | K58: =J58*1000/$K$5 -> 791.19211 | L58: =J58/$J$58 -> 1
C59: C | D59: CÔNG ĐOẠN TẠO HẠT
C60: I | F60: Vảy sạch từ chai | H60: 1 | J60: =+J58 -> 20966.591 | K60: =J60/$K$5*1000 -> 791.19211 | L60: =J60/$J$109 -> 0.64324562
C61: II | F61: Chi phí tạo hạt máy Starlinger | J61: =SUM(J62:J79) -> 3440.1729 | K61: =J61*1000/$K$5 -> 129.81785 | L61: =J61/$J$109 -> 0.10554296
A62: Tạo hạt | C62: 0 | D62: REL01 | F62: Công suất máy (capacity) | G62: Kg /h | H62: 6000 | M62: Công suất máy 6000 (CW1: 1500, CW2:1500, Boretech 3000)
A63: Tạo hạt | F63: Hiệu suất máy | G63: % | H63: 0.75 | M63: Bình quân 3 tháng liền kề theo BI
A64: Đầu keo | B64: Hao hụt | C64: =+C63+1 -> 1 | D64: 1522 | E64: 160012357 | F64: Phó Sản PET Đầu Keo | G64: % | H64: 0.01613169 | I64: 8000 | J64: =+(J$60-I64)*H64 -> 209.17303 | K64: =J64/$K$5*1000 -> 7.8933219 | L64: =J64/$J$109 -> 0.0064173349 | M64: Thu hồi theo giá thị trường
A65: HAD | B65: Hao hụt | C65: =+C64+1 -> 2 | D65: 1522 | E65: 160012417 | F65: Phó Sản PET HAD | G65: % | H65: 0.013616789 | I65: 9500 | J65: =+(J$60-I65)*H65 -> 156.13815 | K65: =J65/$K$5*1000 -> 5.8920056 | L65: =J65/$J$109 -> 0.0047902485 | M65: Thu hồi theo giá thị trường
A66: Bụi | B66: Hao hụt | C66: =+C65+1 -> 3 | D66: 1522 | E66: 160012336 | F66: Phó Sản PET Bụi Cám | G66: % | H66: 0.00031953672 | I66: 5000 | J66: =+(J$60-I66)*H66 -> 5.1019121 | K66: =J66/$K$5*1000 -> 0.19252499 | L66: =J66/$J$109 -> 0.00015652438 | M66: Thu hồi theo giá thị trường
A67: PP Hạt | B67: Hao hụt | D67: 1522 | E67: 160012418 | F67: Phó Sản PET Hạt Lẫn Kim Loại | G67: % | H67: 0.0085630943 | I67: 15000 | J67: =+(J$60-I67)*H67 -> 51.092481 | K67: =J67/$K$5*1000 -> 1.9280182 | L67: =J67/$J$109 -> 0.0015674944 | M67: Thu hồi theo giá thị trường
A68: Mất đi | B68: Hao hụt | C68: =+C66+1 -> 4 | D68: 1522 | F68: Hao hụt mất đi do keo dính lưới | G68: % | H68: 0.014301667 | I68: 0 | J68: =+(J$60-I68)*H68 -> 299.8572 | K68: =J68/$K$5*1000 -> 11.315366 | L68: =J68/$J$109 -> 0.0091994846 | M68: Hao hụt mất đi
B69: Phụ gia | C69: =+C68+1 -> 5 | D69: CHE | E69: 120003033 | F69: Phụ gia Anti Yellow CC10379752Z8, Avient | G69: % | H69: 0.000148 | I69: 1007386 | J69: =+H69*I69 -> 149.09313 | K69: =J69/$K$5*1000 -> 5.6261558 | L69: =J69/$J$109 -> 0.0045741104 | M69: Hóa chất theo BOM
A70: Tạo hạt | B70: NCTT | C70: =+C69+1 -> 6 | D70: LAB | E70: 622 | F70: Chi phí nhân công trực tiếp | G70: tháng | H70: 1 | I70: 4.8448571e+08 | J70: =H70*I70/($H$62*$H$63*24*30) -> 149.53263 | K70: =J70/$K$5*1000 -> 5.6427406 | L70: =J70/$J$109 -> 0.004587594
A71: Tạo hạt | B71: NCGT | C71: =+C70+1 -> 7 | D71: LAB | E71: 6271 | F71: Chi phí nhân công gián tiếp | G71: tháng | H71: 1 | I71: 1.2206788e+09 | J71: =H71*I71/($H$62*$H$63*24*30) -> 376.75272 | K71: =J71/$K$5*1000 -> 14.217084 | L71: =J71/$J$109 -> 0.011558605 | M71: Lương trưởng ca, hành chính, tổ trưởng, quản lý sản xuất gián tiếp như QC, Kỹ thuật
A72: Tạo hạt | B72: VTPX | C72: =+C71+1 -> 8 | D72: OTH | E72: 6272 | F72: Chi phí vật tư phân xưởng | G72: tháng | H72: 1 | I72: 3.6280187e+08 | J72: =H72*I72/($H$62*$H$63*24*30) -> 111.97589 | K72: =J72/$K$5*1000 -> 4.2255051 | L72: =J72/$J$109 -> 0.00343537 | M72: Chi phí thực tế bình quân 3 tháng liền kề
A73: Tạo hạt | B73: CCDC | C73: =+C72+1 -> 9 | D73: OTH | E73: 6273 | F73: Chi phí CCDC, bảo trì | G73: tháng | H73: 1 | I73: 473941442 | J73: =H73*I73/($H$62*$H$63*24*30) -> 146.27822 | K73: =J73/$K$5*1000 -> 5.5199329 | L73: =J73/$J$109 -> 0.0044877504 | M73: Chi phí thực tế bình quân 3 tháng liền kề
A74: Tạo hạt | B74: KH | C74: =+C73+1 -> 10 | D74: DEP | E74: 6274.1 | F74: Chi phí khấu hao MMTB chính | G74: tháng | H74: 1 | I74: 2.0103763e+09 | J74: =H74*I74/($H$62*$H$63*24*30) -> 620.48651 | K74: =J74/$K$5*1000 -> 23.414585 | L74: =J74/$J$109 -> 0.019036248 | M74: Chi phí thực tế bình quân 3 tháng liền kề theo danh sách TSCĐ
A75: Tạo hạt | B75: KH | C75: =+C74+1 -> 11 | D75: DEP | E75: 6274.2 | F75: Chi phí khấu hao MMTB phụ | G75: tháng | H75: 1 | I75: 4.1175931e+08 | J75: =H75*I75/($H$62*$H$63*24*30) -> 127.08621 | K75: =J75/$K$5*1000 -> 4.7957059 | L75: =J75/$J$109 -> 0.0038989479 | M75: Chi phí thực tế bình quân 3 tháng liền kề theo danh sách TSCĐ
A76: Tạo hạt | B76: KH | C76: =+C75+1 -> 12 | D76: DEP | E76: 6274.3 | F76: Chi phí khấu hao MMTB dùng chung | G76: tháng | H76: 1 | I76: 2.3958891e+08 | J76: =H76*I76/($H$62*$H$63*24*30) -> 73.947194 | K76: =J76/$K$5*1000 -> 2.7904602 | L76: =J76/$J$109 -> 0.0022686668 | M76: Chi phí thực tế bình quân 3 tháng liền kề theo danh sách TSCĐ
A77: Tạo hạt | B77: KH | C77: =+C76+1 -> 13 | D77: DEP | E77: 6274.4 | F77: Chi phí khấu hao nhà xưởng | G77: tháng | H77: 1 | I77: 2.8753955e+08 | J77: =H77*I77/($H$62*$H$63*24*30) -> 88.746776 | K77: =J77/$K$5*1000 -> 3.3489349 | L77: =J77/$J$109 -> 0.0027227113 | M77: Chi phí thực tế bình quân 3 tháng liền kề theo danh sách TSCĐ
A78: Tạo hạt | B78: Điện | C78: =+C74+1 -> 11 | D78: ELEC | E78: 6275 | F78: Điện (electronic) Starlinger | G78: Kwh | H78: 1 | I78: 2.1909214e+09 | J78: =H78*I78/($H$62*$H$63*24*30) -> 676.2103 | K78: =J78/$K$5*1000 -> 25.51737 | L78: =J78/$J$109 -> 0.020745829 | M78: Chi phí thực tế bình quân 3 tháng liền kề. CW1: 752 Kwh, CW2: 752 Kwh, Boretech: 1254 Kwh
A79: Tạo hạt | B79: Khác | C79: =+C78+1 -> 12 | D79: OTH | E79: 6277.6278 | F79: Chi phí bằng tiền khác | G79: tháng | H79: 1 | I79: 6.4378995e+08 | J79: =H79*I79/($H$62*$H$63*24*30) -> 198.7006 | K79: =J79/$K$5*1000 -> 7.4981359 | L79: =J79/$J$109 -> 0.0060960454 | M79: Chi phí thực tế bình quân 3 tháng liền kề
D80: Giá thành tạo hạt máy Starlinger (III+IV) | J80: =J60+J61 -> 24406.764 | K80: =J80*1000/$K$5 -> 921.00996 | L80: =J80/$J$109 -> 0.74878859
C81: D | D81: CÔNG ĐOẠN NÂNG IV LÊN > 0,8 (LƯU MÁY SSP 10 TIẾNG):
C82: III | F82: Hạt rPET WSS01 | J82: =J80 -> 24406.764 | K82: =J82*1000/$K$5 -> 921.00996 | L82: =J82/$J$109 -> 0.74878859
C83: IV | F83: Chi phí nâng IV (10 tiếng) | J83: =SUM(J84:J98) -> 2331.8861 | K83: =J83*1000/$K$5 -> 87.995702 | L83: =J83/$J$109 -> 0.071541221
A84: Nâng IV 10H | C84: 0 | D84: REL01 | F84: Công suất máy (capacity) | G84: Kg /h | H84: 3492 | M84: Công suất máy 3492 (SSP-01: 1092, SSP-02: 2400)
A85: Nâng IV 10H | F85: Hiệu suất máy | G85: % | H85: 0.81 | M85: Bình quân 3 tháng liền kề theo BI
B86: Bao bì | C86: =+C85+1 -> 1 | D86: BAG | E86: 160012673 | F86: Pallet D4-1137R không nút-GC | G86: cái | H86: 1 | I86: 261000 | J86: =(I86*H86)/1100 -> 237.27273 | K86: =J86/$K$5*1000 -> 8.9536878 | L86: =J86/$J$109 -> 0.007279421 | M86: Giao trong nước pallet đen, giao xuất khẩu pallet gỗ
B87: Bao bì | C87: =+C86+1 -> 2 | D87: BAG | E87: 140005072 | F87: Bao jumbo 105Lx105Wx150H (cm) đựng vảy | G87: cái | H87: 1 | I87: 165225 | J87: =(I87*H87)/1100 -> 150.20455 | K87: =J87/$K$5*1000 -> 5.6680961 | L87: =J87/$J$109 -> 0.0046082082 | M87: 1100 kg hạt/bao
B88: Bao bì | C88: =+C87+1 -> 3 | D88: BAG | E88: 140006090 | F88: Bao PE lót ngoài bao Jumbo | G88: cái | H88: 1 | I88: 23502 | J88: =(I88*H88)/1100 -> 21.365455 | K88: =J88/$K$5*1000 -> 0.80624357 | L88: =J88/$J$109 -> 0.00065548258 | M88: 1100 kg hạt/bao
A89: Nâng IV | B89: NCTT | C89: =+C88+1 -> 4 | D89: LAB | E89: 622 | F89: Chi phí nhân công trực tiếp | G89: tháng | H89: 1 | I89: 1.4639311e+08 | J89: =H89*I89/($H$84*$H$85*24*30) -> 71.883446 | K89: =J89/$K$5*1000 -> 2.7125829 | L89: =J89/$J$109 -> 0.0022053519 | M89: Nạp liệu 1, đóng gói 1, xe nâng 1
A90: Nâng IV | B90: NCGT | C90: =+C89+1 -> 5 | D90: LAB | E90: 6271 | F90: Chi phí nhân công gián tiếp | G90: tháng | H90: 1 | I90: 8.3895256e+08 | J90: =H90*I90/($H$84*$H$85*24*30) -> 411.95109 | K90: =J90/$K$5*1000 -> 15.545324 | L90: =J90/$J$109 -> 0.012638475 | M90: Lương trưởng ca, hành chính, tổ trưởng, quản lý sản xuất gián tiếp như QC, Kỹ thuật
A91: Nâng IV | B91: VTPX | C91: =+C90+1 -> 6 | D91: OTH | E91: 6272 | F91: Chi phí vật tư phân xưởng | G91: tháng | H91: 1 | I91: 1.3717563e+08 | J91: =H91*I91/($H$84*$H$85*24*30) -> 67.357383 | K91: =J91/$K$5*1000 -> 2.541788 | L91: =J91/$J$109 -> 0.0020664943 | M91: Chi phí thực tế bình quân 3 tháng liền kề
A92: Nâng IV | B92: CCDC | C92: =+C91+1 -> 7 | D92: OTH | E92: 6273 | F92: Chi phí CCDC, bảo trì | G92: tháng | H92: 1 | I92: 1.3671072e+08 | J92: =H92*I92/($H$84*$H$85*24*30) -> 67.129098 | K92: =J92/$K$5*1000 -> 2.5331735 | L92: =J92/$J$109 -> 0.0020594906 | M92: Chi phí thực tế bình quân 3 tháng liền kề
A93: Nâng IV | B93: KH | C93: =+C92+1 -> 8 | D93: DEP | E93: 6274.1 | F93: Chi phí khấu hao MMTB chính | G93: tháng | H93: 1 | I93: 3.643082e+08 | J93: =H93*I93/($H$84*$H$85*24*30) -> 178.88635 | K93: =J93/$K$5*1000 -> 6.7504282 | L93: =J93/$J$109 -> 0.005488153 | M93: Chi phí thực tế bình quân 3 tháng liền kề theo danh sách TSCĐ
A94: Nâng IV | B94: KH | C94: =+C93+1 -> 9 | D94: DEP | E94: 6274.2 | F94: Chi phí khấu hao MMTB phụ | G94: tháng | H94: 1 | I94: 0 | J94: =H94*I94/($H$84*$H$85*24*30) -> 0 | K94: =J94/$K$5*1000 -> 0 | L94: =J94/$J$109 -> 0 | M94: Chi phí thực tế bình quân 3 tháng liền kề theo danh sách TSCĐ
A95: Nâng IV | B95: KH | C95: =+C94+1 -> 10 | D95: DEP | E95: 6274.3 | F95: Chi phí khấu hao MMTB dùng chung | G95: tháng | H95: 1 | I95: 1.7828552e+08 | J95: =H95*I95/($H$84*$H$85*24*30) -> 87.543582 | K95: =J95/$K$5*1000 -> 3.3035314 | L95: =J95/$J$109 -> 0.0026857979 | M95: Chi phí thực tế bình quân 3 tháng liền kề theo danh sách TSCĐ
A96: Nâng IV | B96: KH | C96: =+C95+1 -> 11 | D96: DEP | E96: 6274.4 | F96: Chi phí khấu hao nhà xưởng | G96: tháng | H96: 1 | I96: 2.1396707e+08 | J96: =H96*I96/($H$84*$H$85*24*30) -> 105.06431 | K96: =J96/$K$5*1000 -> 3.9646908 | L96: =J96/$J$109 -> 0.0032233258 | M96: Chi phí thực tế bình quân 3 tháng liền kề theo danh sách TSCĐ
A97: Nâng IV | B97: Điện | C97: =+C93+1 -> 9 | D97: ELEC | E97: 6275 | F97: Điện (electronic) SSP | G97: tháng | H97: 1 | I97: 1.4544275e+09 | J97: =H97*I97/($H$84*$H$85*24*30) -> 714.1679 | K97: =J97/$K$5*1000 -> 26.949732 | L97: =J97/$J$109 -> 0.021910351 | M97: Chi phí thực tế bình quân 3 tháng liền kề. CW1: 946 Kwh, Boretech: 487 Kwh
A98: Nâng IV | B98: Khác | C98: =+C97+1 -> 10 | D98: OTH | E98: 6277.6278 | F98: Chi phí bằng tiền khác | G98: tháng | H98: 1 | I98: 4.4612369e+08 | J98: =H98*I98/($H$84*$H$85*24*30) -> 219.06023 | K98: =J98/$K$5*1000 -> 8.2664238 | L98: =J98/$J$109 -> 0.0067206697 | M98: Chi phí thực tế bình quân 3 tháng liền kề
C99: V | F99: Chi phí quản lý | J99: =SUM(J100:J104) -> 5177.6126 | K99: =J99*1000/$K$5 -> 195.38161 | L99: =J99/$J$109 -> 0.15884683
A100: LuongBH | B100: 641 | C100: 1 | D100: 641 | F100: Chi phí nhân sự bán hàng | G100: tháng | H100: 1 | I100: 4.7379281e+08 | J100: =+I100/($H$84*$H$85*24*30) -> 232.6466 | K100: =J100/$K$5*1000 -> 8.7791171 | L100: =J100/$J$109 -> 0.0071374936 | M100: Chi phí lương BGĐ, kế toán, HCNS, bán hàng…
A101: LuongQL | B101: 642 | C101: =+C100+1 -> 2 | D101: 642 | F101: Chi phí nhân sự quản lý | G101: tháng | H101: 1 | I101: 4.7196996e+09 | J101: =+I101/($H$84*$H$85*24*30) -> 2317.5153 | K101: =J101/$K$5*1000 -> 87.453407 | L101: =J101/$J$109 -> 0.071100331 | M101: Chi phí lương BGĐ, kế toán, HCNS, bán hàng…
A102: Banhang | B102: 641 | C102: =+C101+1 -> 3 | D102: 641 | F102: Chi phí bán hàng | G102: tháng | H102: 1 | I102: 2.6325862e+09 | J102: =+I102/($H$84*$H$85*24*30) -> 1292.6795 | K102: =J102/$K$5*1000 -> 48.780358 | L102: =J102/$J$109 -> 0.039658827 | M102: Chi phí lương BGĐ, kế toán, HCNS, bán hàng…
...

Sheet ISS01084G (2)
A1: Danh mục | C1: 1
C2: PHƯƠNG ÁN SẢN XUẤT TỪ 100% CHAI RA HẠT ISS01084G (NÂNG IV 10h)
C4: Nguyên liệu: | D4: 100% chai vảy mua ngoài
C5: Thành phẩm: | D5: HẠT rPET iSS01084G (IV > 0,8) | J5: Tỷ giá USD: | K5: 26500
C7: No. | D7: Nhóm | E7: Mã SAP | F7: Chi phí Cost Items | G7: Đơn vị tính Unit | H7: Định mức Standard | I7: Đơn giá (VNĐ) | J7: Chi phí đơn vị (VNĐ /Kg) | K7: Đơn giá (USD /Tấn) | L7: % giá bán | M7: Cơ sở tính
C8: A | D8: CÔNG ĐOẠN TẠO VẢY THÔ:
B9: Chai | C9: I | D9: 1521 | F9: B1 - Chai PET tuyển nước ngọt | G9: vnđ /Kg | H9: 1 | I9: 15000 | J9: =I9 -> 15000 | K9: =J9/$K$5*1000 -> 566.03774 | L9: =J9/$J$58 -> 0.72795007
B10: Hao hụt | C10: II | D10: 1522 | F10: Hao hụt do băm chai B1 (chai khác loại, bao lót, kẽm, nắp) | G10: % | H10: =SUM(H11:H20) -> 0.17890491 | J10: =SUM(J11:J20) -> 1249.9477 | K10: =J10/$K$5*1000 -> 47.167838 | L10: =J10/$J$58 -> 0.060659968
E11: 160012437 | F11: Chai PET Phi Thực Phẩm | G11: % | H11: 0 | I11: 6000 | J11: =+($J$9-I11)*H11 -> 0 | K11: =J11/$K$5*1000 -> 0 | L11: =J11/$J$58 -> 0 | M11: Thu hồi theo giá thị trường
A12: Chai khác2 | E12: 160012250 | F12: Chai PET B8 Sau Phân Loại | G12: % | H12: 0 | I12: 11000 | J12: =+($J$9-I12)*H12 -> 0 | K12: =J12/$K$5*1000 -> 0 | L12: =J12/$J$58 -> 0 | M12: Thu hồi theo giá thị trường
A13: B4 | E13: 160012398 | F13: Chai PET B4 Sau Phân Loại | G13: % | H13: 0.0013146811 | I13: 12500 | J13: =+($J$9-I13)*H13 -> 3.2867028 | K13: =J13/$K$5*1000 -> 0.12402652 | L13: =J13/$J$58 -> 0.0001595037 | M13: Thu hồi theo giá thị trường
A14: B5 | E14: 160012252 | F14: Chai PET B5 Sau Phân Loại | G14: % | H14: 0.0020155036 | I14: 12500 | J14: =+($J$9-I14)*H14 -> 5.038759 | K14: =J14/$K$5*1000 -> 0.19014185 | L14: =J14/$J$58 -> 0.000244531 | M14: Thu hồi theo giá thị trường
A15: B6 | E15: 160012247 | F15: Chai PET B6 Sau Phân Loại | G15: % | H15: 0.00065144366 | I15: 12300 | J15: =+($J$9-I15)*H15 -> 1.7588979 | K15: =J15/$K$5*1000 -> 0.066373505 | L15: =J15/$J$58 -> 8.5359323e-05 | M15: Thu hồi theo giá thị trường
A16: Olefin | E16: 160012335 | F16: Phó Sản PET B1/B8 Vảy-Nắp | G16: % | H16: 0.094914291 | I16: 10500 | J16: =+($J$9-I16)*H16 -> 427.11431 | K16: =J16/$K$5*1000 -> 16.117521 | L16: =J16/$J$58 -> 0.02072786 | M16: Thu hồi theo giá thị trường
A17: Bụi | E17: 160012334 | F17: Phó Sản PET Bụi Sàn Rung | G17: % | H17: 0.032148664 | I17: 5000 | J17: =+($J$9-I17)*H17 -> 321.48664 | K17: =J17/$K$5*1000 -> 12.131571 | L17: =J17/$J$58 -> 0.015601748 | M17: Thu hồi theo giá thị trường
A18: Tomra | E18: 160012268 | F18: Phó Sản PET Tomra Cổng 2 | G18: % | H18: 0.015908152 | I18: 10500 | J18: =+($J$9-I18)*H18 -> 71.586682 | K18: =J18/$K$5*1000 -> 2.7013842 | L18: =J18/$J$58 -> 0.003474102 | M18: Thu hồi theo giá thị trường
A19: Zigzag | E19: 160012311 | F19: Phó Sản PET Zigzag | G19: % | H19: 0.0054188111 | I19: 11000 | J19: =+($J$9-I19)*H19 -> 21.675244 | K19: =J19/$K$5*1000 -> 0.81793375 | L19: =J19/$J$58 -> 0.0010518997 | M19: Thu hồi theo giá thị trường
A20: Mất đi | F20: Hao hụt nhãn, PVC, đất, cát, nước mất đi | G20: % | H20: 0.026533364 | I20: 0 | J20: =+($J$9-I20)*H20 -> 398.00046 | K20: =J20/$K$5*1000 -> 15.018885 | L20: =J20/$J$58 -> 0.019314965 | M20: Hao hụt mất đi
C21: III | F21: Chi phí băm vảy (bale to flake) | J21: =SUM(J22:J33) -> 2321.031 | K21: =J21*1000/$K$5 -> 87.586075 | L21: =J21/$J$58 -> 0.11263965
A22: Băm | C22: 0 | D22: REL01 | F22: Công suất máy (capacity) | G22: Kg /h | H22: 4800 | M22: Công suất máy 4800 (CW1: 1200, CW2:1200, Boretech 2400)
A23: Băm | F23: Hiệu suất máy | G23: % | H23: 0.6 | M23: Bình quân 3 tháng liền kề theo BI
A24: Băm | B24: NCTT | C24: =+C22+1 -> 1 | D24: LAB | E24: 622 | F24: Chi phí nhân công trực tiếp | G24: tháng | H24: 1 | I24: 1811265742 | J24: =+I24/($H$22*$H$23*24*30) -> 873.48849 | K24: =J24/$K$5*1000 -> 32.96183 | L24: =J24/$J$58 -> 0.042390401 | M24: 11 người lựa chai trên chuyền, 1 người cắt kiện, phế, 1 người đóng gói, 0,5 xe nâng
A25: Băm | B25: NCGT | C25: =+C23+1 -> 1 | D25: LAB | E25: 6271 | F25: Chi phí nhân công gián tiếp | G25: tháng | H25: 1 | I25: 7.5152141e+08 | J25: =+I25/($H$22*$H$23*24*30) -> 362.42352 | K25: =J25/$K$5*1000 -> 13.676359 | L25: =J25/$J$58 -> 0.017588415 | M25: Lương trưởng ca, hành chính, tổ trưởng, quản lý sản xuất gián tiếp như QC, Kỹ thuật
A26: Băm | B26: VTPX | C26: =+C24+1 -> 2 | D26: OTH | E26: 6272 | F26: Chi phí vật tư phân xưởng | G26: tháng | H26: 1 | I26: 3.3060958e+08 | J26: =+I26/($H$22*$H$23*24*30) -> 159.43749 | K26: =J26/$K$5*1000 -> 6.0165091 | L26: =J26/$J$58 -> 0.0077375022 | M26: Chi phí thực tế bình quân 3 tháng liền kề
A27: Băm | B27: CCDC | C27: =+C25+1 -> 2 | D27: OTH | E27: 6273 | F27: Chi phí CCDC, bảo trì | G27: tháng | H27: 1 | I27: 1.9855935e+08 | J27: =+I27/($H$22*$H$23*24*30) -> 95.755858 | K27: =J27/$K$5*1000 -> 3.6134286 | L27: =J27/$J$58 -> 0.0046470323 | M27: Chi phí thực tế bình quân 3 tháng liền kề
A28: Băm | B28: KH | C28: =+C26+1 -> 3 | D28: DEP | E28: 6274.1 | F28: Chi phí khấu hao MMTB chính | G28: tháng | H28: 1 | I28: 3.6698932e+08 | J28: =+I28/($H$22*$H$23*24*30) -> 176.98173 | K28: =J28/$K$5*1000 -> 6.6785559 | L28: =J28/$J$58 -> 0.0085889242 | M28: Chi phí thực tế bình quân 3 tháng liền kề theo danh sách TSCĐ
A29: Băm | B29: KH | C29: =+C27+1 -> 3 | D29: DEP | E29: 6274.2 | F29: Chi phí khấu hao MMTB phụ | G29: tháng | H29: 1 | I29: 2.9525985e+08 | J29: =+I29/($H$22*$H$23*24*30) -> 142.38997 | K29: =J29/$K$5*1000 -> 5.3732065 | L29: =J29/$J$58 -> 0.0069101861 | M29: Chi phí thực tế bình quân 3 tháng liền kề theo danh sách TSCĐ
A30: Băm | B30: KH | C30: =+C28+1 -> 4 | D30: DEP | E30: 6274.3 | F30: Chi phí khấu hao MMTB dùng chung | G30: tháng | H30: 1 | I30: 1.4463942e+08 | J30: =+I30/($H$22*$H$23*24*30) -> 69.752806 | K30: =J30/$K$5*1000 -> 2.6321814 | L30: =J30/$J$58 -> 0.003385104 | M30: Chi phí thực tế bình quân 3 tháng liền kề theo danh sách TSCĐ
A31: Băm | B31: KH | C31: =+C29+1 -> 4 | D31: DEP | E31: 6274.4 | F31: Chi phí khấu hao nhà xưởng | G31: tháng | H31: 1 | I31: 1.7358714e+08 | J31: =+I31/($H$22*$H$23*24*30) -> 83.712935 | K31: =J31/$K$5*1000 -> 3.1589787 | L31: =J31/$J$58 -> 0.0040625891 | M31: Chi phí thực tế bình quân 3 tháng liền kề theo danh sách TSCĐ
A32: Băm | B32: Điện | C32: =+C27+1 -> 3 | D32: ELEC | E32: 6275 | F32: Điện (electronic) kwh | G32: Kwh | H32: 1 | I32: 3.3791931e+08 | J32: =+I32/($H$22*$H$23*24*30) -> 162.96263 | K32: =J32/$K$5*1000 -> 6.1495332 | L32: =J32/$J$58 -> 0.0079085772 | M32: Chi phí thực tế bình quân 3 tháng liền kề. CW1: 178 Kwh, CW2: 185 Kwh, Boretech: 132 Kwh
A33: Băm | B33: Khác | C33: =+C28+1 -> 4 | D33: OTH | E33: 6277.6278 | F33: Chi phí bằng tiền khác | G33: tháng | H33: 1 | I33: 4.0253876e+08 | J33: =+I33/($H$22*$H$23*24*30) -> 194.12556 | K33: =J33/$K$5*1000 -> 7.3254929 | L33: =J33/$J$58 -> 0.0094209145 | M33: Chi phí thực tế bình quân 3 tháng liền kề
D34: Cộng giá thành A0 - Vảy thô (I+II+III) | J34: =J9+J10+J21 -> 18570.979 | K34: =J34*1000/$K$5 -> 700.79165 | L34: =J34/$J$58 -> 0.90124969
C35: B | D35: CÔNG ĐOẠN RỬA VẢY:
C36: IV | F36: Chi phí A0 - Vảy thô | G36: Kg | H36: 1 | I36: =+J34 -> 18570.979 | J36: =+H36*I36 -> 18570.979 | K36: =J36*1000/$K$5 -> 700.79165 | L36: =J36/$J$58 -> 0.90124969
C37: V | F37: Chi phí rửa vảy, tách kim loại (clean flake) | J37: =SUM(J40:J57) -> 2034.83 | K37: =J37*1000/$K$5 -> 76.786039 | L37: =J37/$J$58 -> 0.098750312
A38: Rửa | C38: 0 | D38: VBAL1 | F38: Công suất máy (capacity) | G38: Kg /h | H38: 15381.993 | I38: 1.7933333 | M38: Công suất máy 5860 (CW1: 1800, CW2:1660, Boretech 2400)
A39: Rửa | F39: Hiệu suất máy | G39: % | H39: 0.81 | I39: 15381.993 | M39: Bình quân 3 tháng liền kề theo BI
A40: Zigzag | B40: Hao hụt | C40: =+C38+1 -> 1 | D40: 1522 | E40: 160012311 | F40: Phó Sản PET Zigzag | G40: % | H40: 0.0016854746 | I40: 11000 | J40: =+($J$34-I40)*H40 -> 12.760692 | K40: =J40/$K$5*1000 -> 0.48153554 | L40: =J40/$J$58 -> 0.00061927644 | M40: Thu hồi theo giá thị trường
A41: Tomra | B41: Hao hụt | C41: =+C40+1 -> 2 | D41: 1522 | E41: 160012419 | F41: Phó Sản PET Tomra Cổng 3 | G41: % | H41: 0.033714201 | I41: 9500 | J41: =+($J$34-I41)*H41 -> 305.82079 | K41: =J41/$K$5*1000 -> 11.540407 | L41: =J41/$J$58 -> 0.014841485 | M41: Thu hồi theo giá thị trường
A42: Bụi | B42: Hao hụt | C42: =+C41+1 -> 3 | D42: 1522 | E42: 160012336 | F42: Phó Sản PET Bụi Cám | G42: % | H42: 0.021619268 | I42: 5000 | J42: =+($J$34-I42)*H42 -> 293.39462 | K42: =J42/$K$5*1000 -> 11.071495 | L42: =J42/$J$58 -> 0.014238442 | M42: Thu hồi theo giá thị trường
A43: Mất đi | B43: Hao hụt | D43: 1522 | F43: Hao hụt mất đi | G43: % | H43: 0.018663663 | I43: 0 | J43: =+($J$34-I43)*H43 -> 346.60248 | K43: =J43/$K$5*1000 -> 13.079339 | L43: =J43/$J$58 -> 0.01682062 | M43: Hao hụt mất đi
B44: Hóa chất | C44: =+C42+1 -> 4 | D44: CHE | E44: 700000180 | F44: Sodium Hydroxide (32%) NaOH | G44: Kg | H44: 0.03476 | I44: 5082 | J44: =+H44*I44 -> 176.65032 | K44: =J44/$K$5*1000 -> 6.6660498 | L44: =J44/$J$58 -> 0.0085728409 | M44: Hóa chất theo BOM
B45: Hóa chất | C45: =+C44+1 -> 5 | D45: CHE | E45: 120002594 | F45: Chất thủy tinh lỏng Na2-SiO3-9H2O | G45: Kg | H45: 0.00284 | I45: 11500 | J45: =+H45*I45 -> 32.66 | K45: =J45/$K$5*1000 -> 1.2324528 | L45: =J45/$J$58 -> 0.00158499 | M45: Hóa chất theo BOM
B46: Hóa chất | C46: =+C45+1 -> 6 | D46: CHE | E46: 700000185 | F46: Chất phá bọt Antifoam CS04 | G46: Kg | H46: 0.00052 | I46: 52000 | J46: =+H46*I46 -> 27.04 | K46: =J46/$K$5*1000 -> 1.0203774 | L46: =J46/$J$58 -> 0.0013122513 | M46: Hóa chất theo BOM
A47: Rửa | B47: NCTT | C47: =+C46+1 -> 7 | D47: LAB | E47: 622 | F47: Chi phí nhân công trực tiếp | G47: tháng | H47: 1 | I47: 8.6107521e+08 | J47: =+I47/($H$38*$H$39*24*30) -> 95.986677 | K47: =J47/$K$5*1000 -> 3.6221388 | L47: =J47/$J$58 -> 0.0046582339 | M47: Nạp liệu 2 người + đóng gói, ra hàng: 2 người + xe nâng 2+ vệ sinh sàn, nước 1 người
A48: Rửa | B48: NCGT | C48: =+C47+1 -> 8 | D48: LAB | E48: 6271 | F48: Chi phí nhân công gián tiếp | G48: tháng | H48: 1 | I48: 1.6045471e+09 | J48: =+I48/($H$38*$H$39*24*30) -> 178.86375 | K48: =J48/$K$5*1000 -> 6.7495755 | L48: =J48/$J$58 -> 0.0086802587 | M48: Lương trưởng ca, hành chính, tổ trưởng, quản lý sản xuất gián tiếp như QC, Kỹ thuật
A49: Rửa | B49: VTPX | C49: =+C48+1 -> 9 | D49: OTH | E49: 6272 | F49: Chi phí vật tư phân xưởng | G49: tháng | H49: 1 | I49: 329511625 | J49: =+I49/($H$38*$H$39*24*30) -> 36.731665 | K49: =J49/$K$5*1000 -> 1.3861006 | L49: =J49/$J$58 -> 0.0017825879 | M49: Chi phí thực tế bình quân 3 tháng liền kề
A50: Rửa | B50: CCDC | C50: =+C49+1 -> 10 | D50: OTH | E50: 6273 | F50: Chi phí CCDC, bảo trì | G50: tháng | H50: 1 | I50: 1.6951941e+08 | J50: =+I50/($H$38*$H$39*24*30) -> 18.896846 | K50: =J50/$K$5*1000 -> 0.71308851 | L50: =J50/$J$58 -> 0.00091706401 | M50: Chi phí thực tế bình quân 3 tháng liền kề
A51: Rửa | B51: KH | C51: =+C50+1 -> 11 | D51: DEP | E51: 6274.1 | F51: Chi phí khấu hao MMTB chính | G51: tháng | H51: 1 | I51: 1.0337983e+09 | J51: =+I51/($H$38*$H$39*24*30) -> 115.24065 | K51: =J51/$K$5*1000 -> 4.3487037 | L51: =J51/$J$58 -> 0.0055926292 | M51: Chi phí thực tế bình quân 3 tháng liền kề theo danh sách TSCĐ
A52: Rửa | B52: KH | C52: =+C51+1 -> 12 | D52: DEP | E52: 6274.2 | F52: Chi phí khấu hao MMTB phụ | G52: tháng | H52: 1 | I52: 4.0580144e+08 | J52: =+I52/($H$38*$H$39*24*30) -> 45.235923 | K52: =J52/$K$5*1000 -> 1.707016 | L52: =J52/$J$58 -> 0.0021952996 | M52: Chi phí thực tế bình quân 3 tháng liền kề theo danh sách TSCĐ
A53: Rửa | B53: KH | C53: =+C52+1 -> 13 | D53: DEP | E53: 6274.3 | F53: Chi phí khấu hao MMTB dùng chung | G53: tháng | H53: 1 | I53: 3.9574764e+08 | J53: =+I53/($H$38*$H$39*24*30) -> 44.115195 | K53: =J53/$K$5*1000 -> 1.6647244 | L53: =J53/$J$58 -> 0.0021409107 | M53: Chi phí thực tế bình quân 3 tháng liền kề theo danh sách TSCĐ
A54: Rửa | B54: KH | C54: =+C53+1 -> 14 | D54: DEP | E54: 6274.4 | F54: Chi phí khấu hao nhà xưởng | G54: tháng | H54: 1 | I54: 4.7495145e+08 | J54: =+I54/($H$38*$H$39*24*30) -> 52.944285 | K54: =J54/$K$5*1000 -> 1.9978976 | L54: =J54/$J$58 -> 0.0025693864 | M54: Chi phí thực tế bình quân 3 tháng liền kề theo danh sách TSCĐ
A55: Rửa | B55: Điện | C55: =+C51+1 -> 12 | D55: ELEC | E55: 6275 | F55: Điện (electronic) kwh | G55: tháng | H55: 1 | I55: 1.249738e+09 | J55: =+I55/($H$38*$H$39*24*30) -> 139.3121 | K55: =J55/$K$5*1000 -> 5.2570605 | L55: =J55/$J$58 -> 0.0067608171 | M55: Chi phí thực tế bình quân 3 tháng liền kề. CW1: 99,5 Kwh, CW2: 99,5 Kwh, Boretech: 316 Kwh
A56: Rửa | B56: Điện | C56: =+C55+1 -> 13 | D56: H2O | E56: 6275 | F56: Nước (water) m3/giờ | G56: tháng | H56: 1 | I56: 138647320 | J56: =+I56/($H$38*$H$39*24*30) -> 15.455439 | K56: =J56/$K$5*1000 -> 0.58322412 | L56: =J56/$J$58 -> 0.00075005254 | M56: Chi phí thực tế bình quân 3 tháng liền kề
A57: Rửa | B57: Khác | C57: =+C56+1 -> 14 | D57: OTH | E57: 6277.6278 | F57: Chi phí bằng tiền khác | G57: tháng | H57: 1 | I57: 8.7122939e+08 | J57: =+I57/($H$38*$H$39*24*30) -> 97.118595 | K57: =J57/$K$5*1000 -> 3.6648526 | L57: =J57/$J$58 -> 0.0047131659 | M57: Chi phí thực tế bình quân 3 tháng liền kề
D58: Giá thành - A1_Vảy sạch từ chai (IV+V): | J58: =J36+J37 -> 20605.809 | K58: =J58*1000/$K$5 -> 777.57769 | L58: =J58/$J$58 -> 1
C59: C | D59: CÔNG ĐOẠN TẠO HẠT QUA MÁY STARLINGER:
C60: I | F60: Vảy sạch từ chai | H60: 1 | J60: =+J58 -> 20605.809 | K60: =J60/$K$5*1000 -> 777.57769 | L60: =J60/$J$109 -> 0.62206215
C61: II | F61: Chi phí tạo hạt máy Starlinger | J61: =SUM(J62:J79) -> 2656.9843 | K61: =J61*1000/$K$5 -> 100.26356 | L61: =J61/$J$109 -> 0.080210846
A62: Tạo hạt | C62: 0 | D62: REL01 | F62: Công suất máy (capacity) | G62: Kg /h | H62: 8577.3196 | I62: 1.7182131 | M62: Công suất máy 6000 (CW1: 1500, CW2:1500, Boretech 3000)
A63: Tạo hạt | F63: Hiệu suất máy | G63: % | H63: 0.75 | I63: =+I62*I85 -> 8577.3196 | M63: Bình quân 3 tháng liền kề theo BI
A64: Đầu keo | B64: Hao hụt | C64: =+C63+1 -> 1 | D64: 1522 | E64: 160012357 | F64: Phó Sản PET Đầu Keo | G64: % | H64: 0.01613169 | I64: 8000 | J64: =+(J$60-I64)*H64 -> 203.353 | K64: =J64/$K$5*1000 -> 7.6736982 | L64: =J64/$J$109 -> 0.0061389585 | M64: Thu hồi theo giá thị trường | N64: 4.0389911 | O64: =+K64-N64 -> 3.6347071
A65: HAD | B65: Hao hụt | C65: =+C64+1 -> 2 | D65: 1522 | E65: 160012417 | F65: Phó Sản PET HAD | G65: % | H65: 0.013616789 | I65: 9500 | J65: =+(J$60-I65)*H65 -> 151.22545 | K65: =J65/$K$5*1000 -> 5.7066209 | L65: =J65/$J$109 -> 0.0045652967 | M65: Thu hồi theo giá thị trường | N65: 3.6668698 | O65: =+K65-N65 -> 2.0397511
A66: Bụi | B66: Hao hụt | C66: =+C65+1 -> 3 | D66: 1522 | E66: 160012336 | F66: Phó Sản PET Bụi Cám | G66: % | H66: 0.00031953672 | I66: 5000 | J66: =+(J$60-I66)*H66 -> 4.986629 | K66: =J66/$K$5*1000 -> 0.18817468 | L66: =J66/$J$109 -> 0.00015053974 | M66: Thu hồi theo giá thị trường | N66: 0 | O66: =+K66-N66 -> 0.18817468
A67: PP Hạt | B67: Hao hụt | C67: =+C66+1 -> 4 | D67: 1522 | E67: 160012418 | F67: Phó Sản PET Hạt Lẫn Kim Loại | G67: % | H67: 0.0085630943 | I67: 15000 | J67: =+(J$60-I67)*H67 -> 48.003069 | K67: =J67/$K$5*1000 -> 1.8114366 | L67: =J67/$J$109 -> 0.0014491492 | M67: Thu hồi theo giá thị trường | N67: 2.5970685 | O67: =+K67-N67 -> -0.78563198
A68: Mất đi | B68: Hao hụt | C68: =+C67+1 -> 5 | D68: 1522 | F68: Hao hụt mất đi do keo dính lưới | G68: % | H68: 0.014301667 | I68: 0 | J68: =+(J$60-I68)*H68 -> 294.69741 | K68: =J68/$K$5*1000 -> 11.120657 | L68: =J68/$J$109 -> 0.0088965257 | M68: Hao hụt mất đi | N68: 1.7145151 | O68: =+K68-N68 -> 9.406142
B69: Phụ gia | C69: =+C68+1 -> 6 | D69: CHE | E69: 120003033 | F69: Phụ gia Anti Yellow CC10379752Z8, Avient | G69: % | H69: =0.39/2500 -> 0.000156 | I69: 1007386 | J69: =+H69*I69 -> 157.15222 | K69: =J69/$K$5*1000 -> 5.9302723 | L69: =J69/$J$109 -> 0.0047442178 | M69: Hóa chất theo BOM | N69: 3.7365765 | O69: =+K69-N69 -> 2.1936958
A70: Tạo hạt | B70: NCTT | C70: =+C69+1 -> 7 | D70: LAB | E70: 622 | F70: Chi phí nhân công trực tiếp | G70: tháng | H70: 1 | I70: 4.8448571e+08 | J70: =H70*I70/($H$62*$H$63*24*30) -> 104.60095 | K70: =J70/$K$5*1000 -> 3.9472056 | L70: =J70/$J$109 -> 0.0031577645 | N70: 2.3146075 | O70: =+K70-N70 -> 1.6325981
A71: Tạo hạt | B71: NCGT | C71: =+C70+1 -> 8 | D71: LAB | E71: 6271 | F71: Chi phí nhân công gián tiếp | G71: tháng | H71: 1 | I71: 1.2206788e+09 | J71: =H71*I71/($H$62*$H$63*24*30) -> 263.54577 | K71: =J71/$K$5*1000 -> 9.9451235 | L71: =J71/$J$109 -> 0.0079560988 | M71: Lương trưởng ca, hành chính, tổ trưởng, quản lý sản xuất gián tiếp như QC, Kỹ thuật | N71: 10.418755 | O71: =+K71-N71 -> -0.47363123
A72: Tạo hạt | B72: VTPX | C72: =+C71+1 -> 9 | D72: OTH | E72: 6272 | F72: Chi phí vật tư phân xưởng | G72: tháng | H72: 1 | I72: 3.6280187e+08 | J72: =H72*I72/($H$62*$H$63*24*30) -> 78.329286 | K72: =J72/$K$5*1000 -> 2.9558221 | L72: =J72/$J$109 -> 0.0023646577 | M72: Chi phí thực tế bình quân 3 tháng liền kề | N72: 2.6427307 | O72: =+K72-N72 -> 0.31309138
A73: Tạo hạt | B73: CCDC | C73: =+C72+1 -> 10 | D73: OTH | E73: 6273 | F73: Chi phí CCDC, bảo trì | G73: tháng | H73: 1 | I73: 473941442 | J73: =H73*I73/($H$62*$H$63*24*30) -> 102.32443 | K73: =J73/$K$5*1000 -> 3.8612992 | L73: =J73/$J$109 -> 0.0030890394 | M73: Chi phí thực tế bình quân 3 tháng liền kề | N73: 6.0380666 | O73: =+K73-N73 -> -2.1767673
A74: Tạo hạt | B74: KH | C74: =+C73+1 -> 11 | D74: DEP | E74: 6274.1 | F74: Chi phí khấu hao MMTB chính | G74: tháng | H74: 1 | I74: 2.0103763e+09 | J74: =H74*I74/($H$62*$H$63*24*30) -> 434.04225 | K74: =J74/$K$5*1000 -> 16.378953 | L74: =J74/$J$109 -> 0.013103162 | M74: Chi phí thực tế bình quân 3 tháng liền kề theo danh sách TSCĐ | N74: 20.249816 | O74: =+K74-N74 -> -3.8708637
A75: Tạo hạt | B75: KH | C75: =+C74+1 -> 12 | D75: DEP | E75: 6274.2 | F75: Chi phí khấu hao MMTB phụ | G75: tháng | H75: 1 | I75: 4.1175931e+08 | J75: =H75*I75/($H$62*$H$63*24*30) -> 88.899246 | K75: =J75/$K$5*1000 -> 3.3546885 | L75: =J75/$J$109 -> 0.0026837508 | M75: Chi phí thực tế bình quân 3 tháng liền kề theo danh sách TSCĐ | N75: 1.8659215 | O75: =+K75-N75 -> 1.488767
A76: Tạo hạt | B76: KH | C76: =+C75+1 -> 13 | D76: DEP | E76: 6274.3 | F76: Chi phí khấu hao MMTB dùng chung | G76: tháng | H76: 1 | I76: 2.3958891e+08 | J76: =H76*I76/($H$62*$H$63*24*30) -> 51.727484 | K76: =J76/$K$5*1000 -> 1.9519805 | L76: =J76/$J$109 -> 0.0015615844 | M76: Chi phí thực tế bình quân 3 tháng liền kề theo danh sách TSCĐ | N76: 2.1907838 | O76: =+K76-N76 -> -0.23880324
A77: Tạo hạt | B77: KH | C77: =+C76+1 -> 14 | D77: DEP | E77: 6274.4 | F77: Chi phí khấu hao nhà xưởng | G77: tháng | H77: 1 | I77: 2.8753955e+08 | J77: =H77*I77/($H$62*$H$63*24*30) -> 62.080076 | K77: =J77/$K$5*1000 -> 2.3426444 | L77: =J77/$J$109 -> 0.0018741155 | M77: Chi phí thực tế bình quân 3 tháng liền kề theo danh sách TSCĐ | N77: 2.8399046 | O77: =+K77-N77 -> -0.49726021
A78: Tạo hạt | B78: Điện | C78: =+C74+1 -> 12 | D78: ELEC | E78: 6275 | F78: Điện (electronic) Starlinger | G78: Kwh | H78: 1 | I78: 2.1909214e+09 | J78: =H78*I78/($H$62*$H$63*24*30) -> 473.02211 | K78: =J78/$K$5*1000 -> 17.849891 | L78: =J78/$J$109 -> 0.014279913 | M78: Chi phí thực tế bình quân 3 tháng liền kề. CW1: 752 Kwh, CW2: 752 Kwh, Boretech: 1254 Kwh | N78: 15.547201 | O78: =+K78-N78 -> 2.3026899
A79: Tạo hạt | B79: Khác | C79: =+C78+1 -> 13 | D79: OTH | E79: 6277.6278 | F79: Chi phí bằng tiền khác | G79: tháng | H79: 1 | I79: 6.4378995e+08 | J79: =H79*I79/($H$62*$H$63*24*30) -> 138.99489 | K79: =J79/$K$5*1000 -> 5.2450902 | L79: =J79/$J$109 -> 0.0041960722 | M79: Chi phí thực tế bình quân 3 tháng liền kề | N79: 5.1172085 | O79: =+K79-N79 -> 0.12788177
D80: Giá thành tạo hạt máy Starlinger (III+IV) | J80: =J60+J61 -> 23262.793 | K80: =J80*1000/$K$5 -> 877.84125 | L80: =J80/$J$109 -> 0.702273
C81: D | D81: CÔNG ĐOẠN NÂNG IV LÊN > 0,8 (LƯU MÁY SSP 10 TIẾNG):
C82: III | F82: Hạt rPET WSS01 | J82: =J80 -> 23262.793 | K82: =J82*1000/$K$5 -> 877.84125 | L82: =J82/$J$109 -> 0.702273
C83: IV | F83: Chi phí nâng IV (10 tiếng) | J83: =SUM(J84:J98) -> 1754.0485 | K83: =J83*1000/$K$5 -> 66.190511 | L83: =J83/$J$109 -> 0.052952409
A84: Nâng IV 10H | C84: 0 | D84: REL01 | F84: Công suất máy (capacity) | G84: Kg /h | H84: 4992 | I84: =H84+1500 -> 6492 | M84: Công suất máy 3492 (SSP-01: 1092, SSP-02: 2400)
A85: Nâng IV 10H | F85: Hiệu suất máy | G85: % | H85: 0.81 | I85: =3492+1500 -> 4992 | M85: Bình quân 3 tháng liền kề theo BI
B86: Bao bì | C86: =+C85+1 -> 1 | D86: BAG | E86: 160012673 | F86: Pallet D4-1137R không nút-GC | G86: cái | H86: 1 | I86: 261000 | J86: =(I86*H86)/1100 -> 237.27273 | K86: =J86/$K$5*1000 -> 8.9536878 | L86: =J86/$J$109 -> 0.0071629503 | M86: Giao trong nước pallet đen, giao xuất khẩu pallet gỗ
B87: Bao bì | C87: =+C86+1 -> 2 | D87: BAG | E87: 140005072 | F87: Bao jumbo 105Lx105Wx150H (cm) đựng vảy | G87: cái | H87: 1 | I87: 165225 | J87: =(I87*H87)/1100 -> 150.20455 | K87: =J87/$K$5*1000 -> 5.6680961 | L87: =J87/$J$109 -> 0.0045344768 | M87: 1100 kg hạt/bao
B88: Bao bì | C88: =+C87+1 -> 3 | D88: BAG | E88: 140006090 | F88: Bao PE lót ngoài bao Jumbo | G88: cái | H88: 1 | I88: 23502 | J88: =(I88*H88)/1100 -> 21.365455 | K88: =J88/$K$5*1000 -> 0.80624357 | L88: =J88/$J$109 -> 0.00064499485 | M88: 1100 kg hạt/bao
A89: Nâng IV | B89: NCTT | C89: =+C88+1 -> 4 | D89: LAB | E89: 622 | F89: Chi phí nhân công trực tiếp | G89: tháng | H89: 1 | I89: 1.4639311e+08 | J89: =H89*I89/($H$84*$H$85*24*30) -> 50.283853 | K89: =J89/$K$5*1000 -> 1.8975039 | L89: =J89/$J$109 -> 0.0015180031 | M89: Nạp liệu 1, đóng gói 1, xe nâng 1
A90: Nâng IV | B90: NCGT | C90: =+C89+1 -> 5 | D90: LAB | E90: 6271 | F90: Chi phí nhân công gián tiếp | G90: tháng | H90: 1 | I90: 8.3895256e+08 | J90: =H90*I90/($H$84*$H$85*24*30) -> 288.16771 | K90: =J90/$K$5*1000 -> 10.874253 | L90: =J90/$J$109 -> 0.0086994025 | M90: Lương trưởng ca, hành chính, tổ trưởng, quản lý sản xuất gián tiếp như QC, Kỹ thuật
A91: Nâng IV | B91: VTPX | C91: =+C90+1 -> 6 | D91: OTH | E91: 6272 | F91: Chi phí vật tư phân xưởng | G91: tháng | H91: 1 | I91: 1.3717563e+08 | J91: =H91*I91/($H$84*$H$85*24*30) -> 47.117785 | K91: =J91/$K$5*1000 -> 1.7780296 | L91: =J91/$J$109 -> 0.0014224237 | M91: Chi phí thực tế bình quân 3 tháng liền kề
A92: Nâng IV | B92: CCDC | C92: =+C91+1 -> 7 | D92: OTH | E92: 6273 | F92: Chi phí CCDC, bảo trì | G92: tháng | H92: 1 | I92: 1.3671072e+08 | J92: =H92*I92/($H$84*$H$85*24*30) -> 46.958095 | K92: =J92/$K$5*1000 -> 1.7720036 | L92: =J92/$J$109 -> 0.0014176029 | M92: Chi phí thực tế bình quân 3 tháng liền kề
A93: Nâng IV | B93: KH | C93: =+C92+1 -> 8 | D93: DEP | E93: 6274.1 | F93: Chi phí khấu hao MMTB chính | G93: tháng | H93: 1 | I93: 3.643082e+08 | J93: =H93*I93/($H$84*$H$85*24*30) -> 125.13444 | K93: =J93/$K$5*1000 -> 4.7220543 | L93: =J93/$J$109 -> 0.0037776434 | M93: Chi phí thực tế bình quân 3 tháng liền kề theo danh sách TSCĐ
A94: Nâng IV | B94: KH | C94: =+C93+1 -> 9 | D94: DEP | E94: 6274.2 | F94: Chi phí khấu hao MMTB phụ | G94: tháng | H94: 1 | I94: 0 | J94: =H94*I94/($H$84*$H$85*24*30) -> 0 | K94: =J94/$K$5*1000 -> 0 | L94: =J94/$J$109 -> 0 | M94: Chi phí thực tế bình quân 3 tháng liền kề theo danh sách TSCĐ
A95: Nâng IV | B95: KH | C95: =+C94+1 -> 10 | D95: DEP | E95: 6274.3 | F95: Chi phí khấu hao MMTB dùng chung | G95: tháng | H95: 1 | I95: 1.7828552e+08 | J95: =H95*I95/($H$84*$H$85*24*30) -> 61.238419 | K95: =J95/$K$5*1000 -> 2.3108837 | L95: =J95/$J$109 -> 0.001848707 | M95: Chi phí thực tế bình quân 3 tháng liền kề theo danh sách TSCĐ
A96: Nâng IV | B96: KH | C96: =+C95+1 -> 11 | D96: DEP | E96: 6274.4 | F96: Chi phí khấu hao nhà xưởng | G96: tháng | H96: 1 | I96: 2.1396707e+08 | J96: =H96*I96/($H$84*$H$85*24*30) -> 73.494502 | K96: =J96/$K$5*1000 -> 2.7733774 | L96: =J96/$J$109 -> 0.002218702 | M96: Chi phí thực tế bình quân 3 tháng liền kề theo danh sách TSCĐ
A97: Nâng IV | B97: Điện | C97: =+C93+1 -> 9 | D97: ELEC | E97: 6275 | F97: Điện (electronic) SSP | G97: tháng | H97: 1 | I97: 1.4544275e+09 | J97: =H97*I97/($H$84*$H$85*24*30) -> 499.57418 | K97: =J97/$K$5*1000 -> 18.851856 | L97: =J97/$J$109 -> 0.015081485 | M97: Chi phí thực tế bình quân 3 tháng liền kề. CW1: 946 Kwh, Boretech: 487 Kwh
A98: Nâng IV | B98: Khác | C98: =+C97+1 -> 10 | D98: OTH | E98: 6277.6278 | F98: Chi phí bằng tiền khác | G98: tháng | H98: 1 | I98: 4.4612369e+08 | J98: =H98*I98/($H$84*$H$85*24*30) -> 153.23684 | K98: =J98/$K$5*1000 -> 5.7825224 | L98: =J98/$J$109 -> 0.0046260179 | M98: Chi phí thực tế bình quân 3 tháng liền kề
C99: V | F99: Chi phí quản lý | J99: =SUM(J100:J104) -> 3621.8396 | K99: =J99*1000/$K$5 -> 136.67319 | L99: =J99/$J$109 -> 0.10933855
A100: LuongBH | B100: 641 | C100: 1 | D100: 641 | F100: Chi phí nhân sự bán hàng | G100: tháng | H100: 1 | I100: 4.7379281e+08 | J100: =+I100/($H$84*$H$85*24*30) -> 162.74077 | K100: =J100/$K$5*1000 -> 6.1411612 | L100: =J100/$J$109 -> 0.004912929 | M100: Chi phí lương BGĐ, kế toán, HCNS, bán hàng…
A101: LuongQL | B101: 642 | C101: =+C100+1 -> 2 | D101: 642 | F101: Chi phí nhân sự quản lý | G101: tháng | H101: 1 | I101: 4.7196996e+09 | J101: =+I101/($H$84*$H$85*24*30) -> 1621.1465 | K101: =J101/$K$5*1000 -> 61.17534 | L101: =J101/$J$109 -> 0.048940272 | M101: Chi phí lương BGĐ, kế toán, HCNS, bán hàng…
A102: Banhang | B102: 641 | C102: =+C101+1 -> 3 | D102: 641 | F102: Chi phí bán hàng | G102: tháng | H102: 1 | I102: 2.6325862e+09 | J102: =+I102/($H$84*$H$85*24*30) -> 904.25415 | K102: =J102/$K$5*1000 -> 34.122798 | L102: =J102/$J$109 -> 0.027298239 | M102: Chi phí lương BGĐ, kế toán, HCNS, bán hàng…
...

Sheet ISS01G-S (2)
A1: Danh mục | C1: 1
C2: PHƯƠNG ÁN SẢN XUẤT TỪ 100% CHAI RA HẠT ISS01G-S (NÂNG IV 10h)
C4: Nguyên liệu: | D4: 100% chai vảy mua ngoài
C5: Thành phẩm: | D5: HẠT rPET ISS01G-S (IV > 0,8) | J5: Tỷ giá USD: | K5: 26500
C7: No. | D7: Nhóm | E7: Mã SAP | F7: Chi phí Cost Items | G7: Đơn vị tính Unit | H7: Định mức Standard | I7: Đơn giá (VNĐ) | J7: Chi phí đơn vị (VNĐ /Kg) | K7: Đơn giá (USD /Tấn) | L7: % giá bán | M7: Cơ sở tính
C8: A | D8: CÔNG ĐOẠN TẠO VẢY THÔ:
B9: Chai | C9: I | D9: 1521 | E9: 150000187 | F9: Chai PET B1.3 | G9: vnđ /Kg | H9: 1 | I9: 15000 | J9: =I9 -> 15000 | K9: =J9/$K$5*1000 -> 566.03774 | L9: =J9/$J$58 -> 0.72795007
B10: Hao hụt | C10: II | D10: 1522 | F10: Hao hụt do băm chai B1 (chai khác loại, bao lót, kẽm, nắp) | G10: % | H10: =SUM(H11:H20) -> 0.17890491 | J10: =SUM(J11:J20) -> 1249.9477 | K10: =J10/$K$5*1000 -> 47.167838 | L10: =J10/$J$58 -> 0.060659968
E11: 160012437 | F11: Chai PET Phi Thực Phẩm | G11: % | H11: 0 | I11: 6000 | J11: =+($J$9-I11)*H11 -> 0 | K11: =J11/$K$5*1000 -> 0 | L11: =J11/$J$58 -> 0 | M11: Thu hồi theo giá thị trường
A12: Chai khác2 | E12: 160012250 | F12: Chai PET B8 Sau Phân Loại | G12: % | H12: 0 | I12: 11000 | J12: =+($J$9-I12)*H12 -> 0 | K12: =J12/$K$5*1000 -> 0 | L12: =J12/$J$58 -> 0 | M12: Thu hồi theo giá thị trường
A13: B4 | E13: 160012398 | F13: Chai PET B4 Sau Phân Loại | G13: % | H13: 0.0013146811 | I13: 12500 | J13: =+($J$9-I13)*H13 -> 3.2867028 | K13: =J13/$K$5*1000 -> 0.12402652 | L13: =J13/$J$58 -> 0.0001595037 | M13: Thu hồi theo giá thị trường
A14: B5 | E14: 160012252 | F14: Chai PET B5 Sau Phân Loại | G14: % | H14: 0.0020155036 | I14: 12500 | J14: =+($J$9-I14)*H14 -> 5.038759 | K14: =J14/$K$5*1000 -> 0.19014185 | L14: =J14/$J$58 -> 0.000244531 | M14: Thu hồi theo giá thị trường
A15: B6 | E15: 160012247 | F15: Chai PET B6 Sau Phân Loại | G15: % | H15: 0.00065144366 | I15: 12300 | J15: =+($J$9-I15)*H15 -> 1.7588979 | K15: =J15/$K$5*1000 -> 0.066373505 | L15: =J15/$J$58 -> 8.5359323e-05 | M15: Thu hồi theo giá thị trường
A16: Olefin | E16: 160012335 | F16: Phó Sản PET B1/B8 Vảy-Nắp | G16: % | H16: 0.094914291 | I16: 10500 | J16: =+($J$9-I16)*H16 -> 427.11431 | K16: =J16/$K$5*1000 -> 16.117521 | L16: =J16/$J$58 -> 0.02072786 | M16: Thu hồi theo giá thị trường
A17: Bụi | E17: 160012334 | F17: Phó Sản PET Bụi Sàn Rung | G17: % | H17: 0.032148664 | I17: 5000 | J17: =+($J$9-I17)*H17 -> 321.48664 | K17: =J17/$K$5*1000 -> 12.131571 | L17: =J17/$J$58 -> 0.015601748 | M17: Thu hồi theo giá thị trường
A18: Tomra | E18: 160012268 | F18: Phó Sản PET Tomra Cổng 2 | G18: % | H18: 0.015908152 | I18: 10500 | J18: =+($J$9-I18)*H18 -> 71.586682 | K18: =J18/$K$5*1000 -> 2.7013842 | L18: =J18/$J$58 -> 0.003474102 | M18: Thu hồi theo giá thị trường
A19: Zigzag | E19: 160012311 | F19: Phó Sản PET Zigzag | G19: % | H19: 0.0054188111 | I19: 11000 | J19: =+($J$9-I19)*H19 -> 21.675244 | K19: =J19/$K$5*1000 -> 0.81793375 | L19: =J19/$J$58 -> 0.0010518997 | M19: Thu hồi theo giá thị trường
A20: Mất đi | F20: Hao hụt nhãn, PVC, đất, cát, nước mất đi | G20: % | H20: 0.026533364 | I20: 0 | J20: =+($J$9-I20)*H20 -> 398.00046 | K20: =J20/$K$5*1000 -> 15.018885 | L20: =J20/$J$58 -> 0.019314965 | M20: Hao hụt mất đi
C21: III | F21: Chi phí băm vảy (bale to flake) | J21: =SUM(J22:J33) -> 2321.031 | K21: =J21*1000/$K$5 -> 87.586075 | L21: =J21/$J$58 -> 0.11263965
A22: Băm | C22: 0 | D22: REL01 | F22: Công suất máy (capacity) | G22: Kg /h | H22: 4800 | M22: Công suất máy 4800 (CW1: 1200, CW2:1200, Boretech 2400)
A23: Băm | F23: Hiệu suất máy | G23: % | H23: 0.6 | M23: Bình quân 3 tháng liền kề theo BI
A24: Băm | B24: NCTT | C24: =+C22+1 -> 1 | D24: LAB | E24: 622 | F24: Chi phí nhân công trực tiếp | G24: tháng | H24: 1 | I24: 1811265742 | J24: =+I24/($H$22*$H$23*24*30) -> 873.48849 | K24: =J24/$K$5*1000 -> 32.96183 | L24: =J24/$J$58 -> 0.042390401 | M24: 11 người lựa chai trên chuyền, 1 người cắt kiện, phế, 1 người đóng gói, 0,5 xe nâng
A25: Băm | B25: NCGT | C25: =+C23+1 -> 1 | D25: LAB | E25: 6271 | F25: Chi phí nhân công gián tiếp | G25: tháng | H25: 1 | I25: 7.5152141e+08 | J25: =+I25/($H$22*$H$23*24*30) -> 362.42352 | K25: =J25/$K$5*1000 -> 13.676359 | L25: =J25/$J$58 -> 0.017588415 | M25: Lương trưởng ca, hành chính, tổ trưởng, quản lý sản xuất gián tiếp như QC, Kỹ thuật
A26: Băm | B26: VTPX | C26: =+C24+1 -> 2 | D26: OTH | E26: 6272 | F26: Chi phí vật tư phân xưởng | G26: tháng | H26: 1 | I26: 3.3060958e+08 | J26: =+I26/($H$22*$H$23*24*30) -> 159.43749 | K26: =J26/$K$5*1000 -> 6.0165091 | L26: =J26/$J$58 -> 0.0077375022 | M26: Chi phí thực tế bình quân 3 tháng liền kề
A27: Băm | B27: CCDC | C27: =+C25+1 -> 2 | D27: OTH | E27: 6273 | F27: Chi phí CCDC, bảo trì | G27: tháng | H27: 1 | I27: 1.9855935e+08 | J27: =+I27/($H$22*$H$23*24*30) -> 95.755858 | K27: =J27/$K$5*1000 -> 3.6134286 | L27: =J27/$J$58 -> 0.0046470323 | M27: Chi phí thực tế bình quân 3 tháng liền kề
A28: Băm | B28: KH | C28: =+C26+1 -> 3 | D28: DEP | E28: 6274.1 | F28: Chi phí khấu hao MMTB chính | G28: tháng | H28: 1 | I28: 3.6698932e+08 | J28: =+I28/($H$22*$H$23*24*30) -> 176.98173 | K28: =J28/$K$5*1000 -> 6.6785559 | L28: =J28/$J$58 -> 0.0085889242 | M28: Chi phí thực tế bình quân 3 tháng liền kề theo danh sách TSCĐ
A29: Băm | B29: KH | C29: =+C27+1 -> 3 | D29: DEP | E29: 6274.2 | F29: Chi phí khấu hao MMTB phụ | G29: tháng | H29: 1 | I29: 2.9525985e+08 | J29: =+I29/($H$22*$H$23*24*30) -> 142.38997 | K29: =J29/$K$5*1000 -> 5.3732065 | L29: =J29/$J$58 -> 0.0069101861 | M29: Chi phí thực tế bình quân 3 tháng liền kề theo danh sách TSCĐ
A30: Băm | B30: KH | C30: =+C28+1 -> 4 | D30: DEP | E30: 6274.3 | F30: Chi phí khấu hao MMTB dùng chung | G30: tháng | H30: 1 | I30: 1.4463942e+08 | J30: =+I30/($H$22*$H$23*24*30) -> 69.752806 | K30: =J30/$K$5*1000 -> 2.6321814 | L30: =J30/$J$58 -> 0.003385104 | M30: Chi phí thực tế bình quân 3 tháng liền kề theo danh sách TSCĐ
A31: Băm | B31: KH | C31: =+C29+1 -> 4 | D31: DEP | E31: 6274.4 | F31: Chi phí khấu hao nhà xưởng | G31: tháng | H31: 1 | I31: 1.7358714e+08 | J31: =+I31/($H$22*$H$23*24*30) -> 83.712935 | K31: =J31/$K$5*1000 -> 3.1589787 | L31: =J31/$J$58 -> 0.0040625891 | M31: Chi phí thực tế bình quân 3 tháng liền kề theo danh sách TSCĐ
A32: Băm | B32: Điện | C32: =+C27+1 -> 3 | D32: ELEC | E32: 6275 | F32: Điện (electronic) kwh | G32: Kwh | H32: 1 | I32: 3.3791931e+08 | J32: =+I32/($H$22*$H$23*24*30) -> 162.96263 | K32: =J32/$K$5*1000 -> 6.1495332 | L32: =J32/$J$58 -> 0.0079085772 | M32: Chi phí thực tế bình quân 3 tháng liền kề. CW1: 178 Kwh, CW2: 185 Kwh, Boretech: 132 Kwh
A33: Băm | B33: Khác | C33: =+C28+1 -> 4 | D33: OTH | E33: 6277.6278 | F33: Chi phí bằng tiền khác | G33: tháng | H33: 1 | I33: 4.0253876e+08 | J33: =+I33/($H$22*$H$23*24*30) -> 194.12556 | K33: =J33/$K$5*1000 -> 7.3254929 | L33: =J33/$J$58 -> 0.0094209145 | M33: Chi phí thực tế bình quân 3 tháng liền kề
D34: Cộng giá thành A0 - Vảy thô (I+II+III) | J34: =J9+J10+J21 -> 18570.979 | K34: =J34*1000/$K$5 -> 700.79165 | L34: =J34/$J$58 -> 0.90124969
C35: B | D35: CÔNG ĐOẠN RỬA VẢY:
C36: IV | F36: Chi phí A0 - Vảy thô | G36: Kg | H36: 1 | I36: =+J34 -> 18570.979 | J36: =+H36*I36 -> 18570.979 | K36: =J36*1000/$K$5 -> 700.79165 | L36: =J36/$J$58 -> 0.90124969
C37: V | F37: Chi phí rửa vảy, tách kim loại (clean flake) | J37: =SUM(J40:J57) -> 2034.83 | K37: =J37*1000/$K$5 -> 76.786039 | L37: =J37/$J$58 -> 0.098750312
A38: Rửa | C38: 0 | D38: VBAL1 | F38: Công suất máy (capacity) | G38: Kg /h | H38: 15381.993 | M38: Công suất máy 5860 (CW1: 1800, CW2:1660, Boretech 2400)
A39: Rửa | F39: Hiệu suất máy | G39: % | H39: 0.81 | M39: Bình quân 3 tháng liền kề theo BI
A40: Zigzag | B40: Hao hụt | C40: =+C38+1 -> 1 | D40: 1522 | E40: 160012311 | F40: Phó Sản PET Zigzag | G40: % | H40: 0.0016854746 | I40: 11000 | J40: =+($J$34-I40)*H40 -> 12.760692 | K40: =J40/$K$5*1000 -> 0.48153554 | L40: =J40/$J$58 -> 0.00061927644 | M40: Thu hồi theo giá thị trường
A41: Tomra | B41: Hao hụt | C41: =+C40+1 -> 2 | D41: 1522 | E41: 160012419 | F41: Phó Sản PET Tomra Cổng 3 | G41: % | H41: 0.033714201 | I41: 9500 | J41: =+($J$34-I41)*H41 -> 305.82079 | K41: =J41/$K$5*1000 -> 11.540407 | L41: =J41/$J$58 -> 0.014841485 | M41: Thu hồi theo giá thị trường
A42: Bụi | B42: Hao hụt | C42: =+C41+1 -> 3 | D42: 1522 | E42: 160012336 | F42: Phó Sản PET Bụi Cám | G42: % | H42: 0.021619268 | I42: 5000 | J42: =+($J$34-I42)*H42 -> 293.39462 | K42: =J42/$K$5*1000 -> 11.071495 | L42: =J42/$J$58 -> 0.014238442 | M42: Thu hồi theo giá thị trường
A43: Mất đi | B43: Hao hụt | D43: 1522 | F43: Hao hụt mất đi | G43: % | H43: 0.018663663 | I43: 0 | J43: =+($J$34-I43)*H43 -> 346.60248 | K43: =J43/$K$5*1000 -> 13.079339 | L43: =J43/$J$58 -> 0.01682062 | M43: Hao hụt mất đi
B44: Hóa chất | C44: =+C42+1 -> 4 | D44: CHE | E44: 700000180 | F44: Sodium Hydroxide (32%) NaOH | G44: Kg | H44: 0.03476 | I44: 5082 | J44: =+H44*I44 -> 176.65032 | K44: =J44/$K$5*1000 -> 6.6660498 | L44: =J44/$J$58 -> 0.0085728409 | M44: Hóa chất theo BOM
B45: Hóa chất | C45: =+C44+1 -> 5 | D45: CHE | E45: 120002594 | F45: Chất thủy tinh lỏng Na2-SiO3-9H2O | G45: Kg | H45: 0.00284 | I45: 11500 | J45: =+H45*I45 -> 32.66 | K45: =J45/$K$5*1000 -> 1.2324528 | L45: =J45/$J$58 -> 0.00158499 | M45: Hóa chất theo BOM
B46: Hóa chất | C46: =+C45+1 -> 6 | D46: CHE | E46: 700000185 | F46: Chất phá bọt Antifoam CS04 | G46: Kg | H46: 0.00052 | I46: 52000 | J46: =+H46*I46 -> 27.04 | K46: =J46/$K$5*1000 -> 1.0203774 | L46: =J46/$J$58 -> 0.0013122513 | M46: Hóa chất theo BOM
A47: Rửa | B47: NCTT | C47: =+C46+1 -> 7 | D47: LAB | E47: 622 | F47: Chi phí nhân công trực tiếp | G47: tháng | H47: 1 | I47: 8.6107521e+08 | J47: =+I47/($H$38*$H$39*24*30) -> 95.986677 | K47: =J47/$K$5*1000 -> 3.6221388 | L47: =J47/$J$58 -> 0.0046582339 | M47: Nạp liệu 2 người + đóng gói, ra hàng: 2 người + xe nâng 2+ vệ sinh sàn, nước 1 người
A48: Rửa | B48: NCGT | C48: =+C47+1 -> 8 | D48: LAB | E48: 6271 | F48: Chi phí nhân công gián tiếp | G48: tháng | H48: 1 | I48: 1.6045471e+09 | J48: =+I48/($H$38*$H$39*24*30) -> 178.86375 | K48: =J48/$K$5*1000 -> 6.7495755 | L48: =J48/$J$58 -> 0.0086802587 | M48: Lương trưởng ca, hành chính, tổ trưởng, quản lý sản xuất gián tiếp như QC, Kỹ thuật
A49: Rửa | B49: VTPX | C49: =+C48+1 -> 9 | D49: OTH | E49: 6272 | F49: Chi phí vật tư phân xưởng | G49: tháng | H49: 1 | I49: 329511625 | J49: =+I49/($H$38*$H$39*24*30) -> 36.731665 | K49: =J49/$K$5*1000 -> 1.3861006 | L49: =J49/$J$58 -> 0.0017825879 | M49: Chi phí thực tế bình quân 3 tháng liền kề
A50: Rửa | B50: CCDC | C50: =+C49+1 -> 10 | D50: OTH | E50: 6273 | F50: Chi phí CCDC, bảo trì | G50: tháng | H50: 1 | I50: 1.6951941e+08 | J50: =+I50/($H$38*$H$39*24*30) -> 18.896846 | K50: =J50/$K$5*1000 -> 0.71308851 | L50: =J50/$J$58 -> 0.00091706401 | M50: Chi phí thực tế bình quân 3 tháng liền kề
A51: Rửa | B51: KH | C51: =+C50+1 -> 11 | D51: DEP | E51: 6274.1 | F51: Chi phí khấu hao MMTB chính | G51: tháng | H51: 1 | I51: 1.0337983e+09 | J51: =+I51/($H$38*$H$39*24*30) -> 115.24065 | K51: =J51/$K$5*1000 -> 4.3487037 | L51: =J51/$J$58 -> 0.0055926292 | M51: Chi phí thực tế bình quân 3 tháng liền kề theo danh sách TSCĐ
A52: Rửa | B52: KH | C52: =+C51+1 -> 12 | D52: DEP | E52: 6274.2 | F52: Chi phí khấu hao MMTB phụ | G52: tháng | H52: 1 | I52: 4.0580144e+08 | J52: =+I52/($H$38*$H$39*24*30) -> 45.235923 | K52: =J52/$K$5*1000 -> 1.707016 | L52: =J52/$J$58 -> 0.0021952996 | M52: Chi phí thực tế bình quân 3 tháng liền kề theo danh sách TSCĐ
A53: Rửa | B53: KH | C53: =+C52+1 -> 13 | D53: DEP | E53: 6274.3 | F53: Chi phí khấu hao MMTB dùng chung | G53: tháng | H53: 1 | I53: 3.9574764e+08 | J53: =+I53/($H$38*$H$39*24*30) -> 44.115195 | K53: =J53/$K$5*1000 -> 1.6647244 | L53: =J53/$J$58 -> 0.0021409107 | M53: Chi phí thực tế bình quân 3 tháng liền kề theo danh sách TSCĐ
A54: Rửa | B54: KH | C54: =+C53+1 -> 14 | D54: DEP | E54: 6274.4 | F54: Chi phí khấu hao nhà xưởng | G54: tháng | H54: 1 | I54: 4.7495145e+08 | J54: =+I54/($H$38*$H$39*24*30) -> 52.944285 | K54: =J54/$K$5*1000 -> 1.9978976 | L54: =J54/$J$58 -> 0.0025693864 | M54: Chi phí thực tế bình quân 3 tháng liền kề theo danh sách TSCĐ
A55: Rửa | B55: Điện | C55: =+C51+1 -> 12 | D55: ELEC | E55: 6275 | F55: Điện (electronic) kwh | G55: tháng | H55: 1 | I55: 1.249738e+09 | J55: =+I55/($H$38*$H$39*24*30) -> 139.3121 | K55: =J55/$K$5*1000 -> 5.2570605 | L55: =J55/$J$58 -> 0.0067608171 | M55: Chi phí thực tế bình quân 3 tháng liền kề. CW1: 99,5 Kwh, CW2: 99,5 Kwh, Boretech: 316 Kwh
A56: Rửa | B56: Điện | C56: =+C55+1 -> 13 | D56: H2O | E56: 6275 | F56: Nước (water) m3/giờ | G56: tháng | H56: 1 | I56: 138647320 | J56: =+I56/($H$38*$H$39*24*30) -> 15.455439 | K56: =J56/$K$5*1000 -> 0.58322412 | L56: =J56/$J$58 -> 0.00075005254 | M56: Chi phí thực tế bình quân 3 tháng liền kề
A57: Rửa | B57: Khác | C57: =+C56+1 -> 14 | D57: OTH | E57: 6277.6278 | F57: Chi phí bằng tiền khác | G57: tháng | H57: 1 | I57: 8.7122939e+08 | J57: =+I57/($H$38*$H$39*24*30) -> 97.118595 | K57: =J57/$K$5*1000 -> 3.6648526 | L57: =J57/$J$58 -> 0.0047131659 | M57: Chi phí thực tế bình quân 3 tháng liền kề
D58: Giá thành - A1_Vảy sạch từ chai (IV+V): | J58: =J36+J37 -> 20605.809 | K58: =J58*1000/$K$5 -> 777.57769 | L58: =J58/$J$58 -> 1
C59: C | D59: CÔNG ĐOẠN TẠO HẠT
C60: I | F60: Vảy sạch từ chai | H60: 1 | J60: =+J58 -> 20605.809 | K60: =J60/$K$5*1000 -> 777.57769 | L60: =J60/$J$109 -> 0.63217698
C61: II | F61: Chi phí tạo hạt máy Starlinger | J61: =SUM(J62:J79) -> 2648.9252 | K61: =J61*1000/$K$5 -> 99.959441 | L61: =J61/$J$109 -> 0.081267838
A62: Tạo hạt | C62: 0 | D62: REL01 | F62: Công suất máy (capacity) | G62: Kg /h | H62: 8577.3196 | M62: Công suất máy 6000 (CW1: 1500, CW2:1500, Boretech 3000)
A63: Tạo hạt | F63: Hiệu suất máy | G63: % | H63: 0.75 | M63: Bình quân 3 tháng liền kề theo BI
A64: Đầu keo | B64: Hao hụt | C64: =+C63+1 -> 1 | D64: 1522 | E64: 160012357 | F64: Phó Sản PET Đầu Keo | G64: % | H64: 0.01613169 | I64: 8000 | J64: =+(J$60-I64)*H64 -> 203.353 | K64: =J64/$K$5*1000 -> 7.6736982 | L64: =J64/$J$109 -> 0.006238779 | M64: Thu hồi theo giá thị trường
A65: HAD | B65: Hao hụt | C65: =+C64+1 -> 2 | D65: 1522 | E65: 160012417 | F65: Phó Sản PET HAD | G65: % | H65: 0.013616789 | I65: 9500 | J65: =+(J$60-I65)*H65 -> 151.22545 | K65: =J65/$K$5*1000 -> 5.7066209 | L65: =J65/$J$109 -> 0.0046395291 | M65: Thu hồi theo giá thị trường
A66: Bụi | B66: Hao hụt | C66: =+C65+1 -> 3 | D66: 1522 | E66: 160012336 | F66: Phó Sản PET Bụi Cám | G66: % | H66: 0.00031953672 | I66: 5000 | J66: =+(J$60-I66)*H66 -> 4.986629 | K66: =J66/$K$5*1000 -> 0.18817468 | L66: =J66/$J$109 -> 0.00015298754 | M66: Thu hồi theo giá thị trường
A67: PP Hạt | B67: Hao hụt | D67: 1522 | E67: 160012418 | F67: Phó Sản PET Hạt Lẫn Kim Loại | G67: % | H67: 0.0085630943 | I67: 15000 | J67: =+(J$60-I67)*H67 -> 48.003069 | K67: =J67/$K$5*1000 -> 1.8114366 | L67: =J67/$J$109 -> 0.0014727126 | M67: Thu hồi theo giá thị trường
A68: Mất đi | B68: Hao hụt | C68: =+C66+1 -> 4 | D68: 1522 | F68: Hao hụt mất đi do keo dính lưới | G68: % | H68: 0.014301667 | I68: 0 | J68: =+(J$60-I68)*H68 -> 294.69741 | K68: =J68/$K$5*1000 -> 11.120657 | L68: =J68/$J$109 -> 0.0090411846 | M68: Hao hụt mất đi
B69: Phụ gia | C69: =+C68+1 -> 5 | D69: CHE | E69: 120003033 | F69: Phụ gia Anti Yellow CC10379752Z8, Avient | G69: % | H69: 0.000148 | I69: 1007386 | J69: =+H69*I69 -> 149.09313 | K69: =J69/$K$5*1000 -> 5.6261558 | L69: =J69/$J$109 -> 0.0045741104 | M69: Hóa chất theo BOM
A70: Tạo hạt | B70: NCTT | C70: =+C69+1 -> 6 | D70: LAB | E70: 622 | F70: Chi phí nhân công trực tiếp | G70: tháng | H70: 1 | I70: 4.8448571e+08 | J70: =H70*I70/($H$62*$H$63*24*30) -> 104.60095 | K70: =J70/$K$5*1000 -> 3.9472056 | L70: =J70/$J$109 -> 0.0032091102
A71: Tạo hạt | B71: NCGT | C71: =+C70+1 -> 7 | D71: LAB | E71: 6271 | F71: Chi phí nhân công gián tiếp | G71: tháng | H71: 1 | I71: 1.2206788e+09 | J71: =H71*I71/($H$62*$H$63*24*30) -> 263.54577 | K71: =J71/$K$5*1000 -> 9.9451235 | L71: =J71/$J$109 -> 0.0080854663 | M71: Lương trưởng ca, hành chính, tổ trưởng, quản lý sản xuất gián tiếp như QC, Kỹ thuật
A72: Tạo hạt | B72: VTPX | C72: =+C71+1 -> 8 | D72: OTH | E72: 6272 | F72: Chi phí vật tư phân xưởng | G72: tháng | H72: 1 | I72: 3.6280187e+08 | J72: =H72*I72/($H$62*$H$63*24*30) -> 78.329286 | K72: =J72/$K$5*1000 -> 2.9558221 | L72: =J72/$J$109 -> 0.0024031074 | M72: Chi phí thực tế bình quân 3 tháng liền kề
A73: Tạo hạt | B73: CCDC | C73: =+C72+1 -> 9 | D73: OTH | E73: 6273 | F73: Chi phí CCDC, bảo trì | G73: tháng | H73: 1 | I73: 473941442 | J73: =H73*I73/($H$62*$H$63*24*30) -> 102.32443 | K73: =J73/$K$5*1000 -> 3.8612992 | L73: =J73/$J$109 -> 0.0031392677 | M73: Chi phí thực tế bình quân 3 tháng liền kề
A74: Tạo hạt | B74: KH | C74: =+C73+1 -> 10 | D74: DEP | E74: 6274.1 | F74: Chi phí khấu hao MMTB chính | G74: tháng | H74: 1 | I74: 2.0103763e+09 | J74: =H74*I74/($H$62*$H$63*24*30) -> 434.04225 | K74: =J74/$K$5*1000 -> 16.378953 | L74: =J74/$J$109 -> 0.013316222 | M74: Chi phí thực tế bình quân 3 tháng liền kề theo danh sách TSCĐ
A75: Tạo hạt | B75: KH | C75: =+C74+1 -> 11 | D75: DEP | E75: 6274.2 | F75: Chi phí khấu hao MMTB phụ | G75: tháng | H75: 1 | I75: 4.1175931e+08 | J75: =H75*I75/($H$62*$H$63*24*30) -> 88.899246 | K75: =J75/$K$5*1000 -> 3.3546885 | L75: =J75/$J$109 -> 0.002727389 | M75: Chi phí thực tế bình quân 3 tháng liền kề theo danh sách TSCĐ
A76: Tạo hạt | B76: KH | C76: =+C75+1 -> 12 | D76: DEP | E76: 6274.3 | F76: Chi phí khấu hao MMTB dùng chung | G76: tháng | H76: 1 | I76: 2.3958891e+08 | J76: =H76*I76/($H$62*$H$63*24*30) -> 51.727484 | K76: =J76/$K$5*1000 -> 1.9519805 | L76: =J76/$J$109 -> 0.0015869761 | M76: Chi phí thực tế bình quân 3 tháng liền kề theo danh sách TSCĐ
A77: Tạo hạt | B77: KH | C77: =+C76+1 -> 13 | D77: DEP | E77: 6274.4 | F77: Chi phí khấu hao nhà xưởng | G77: tháng | H77: 1 | I77: 2.8753955e+08 | J77: =H77*I77/($H$62*$H$63*24*30) -> 62.080076 | K77: =J77/$K$5*1000 -> 2.3426444 | L77: =J77/$J$109 -> 0.0019045889 | M77: Chi phí thực tế bình quân 3 tháng liền kề theo danh sách TSCĐ
A78: Tạo hạt | B78: Điện | C78: =+C74+1 -> 11 | D78: ELEC | E78: 6275 | F78: Điện (electronic) Starlinger | G78: Kwh | H78: 1 | I78: 2.1909214e+09 | J78: =H78*I78/($H$62*$H$63*24*30) -> 473.02211 | K78: =J78/$K$5*1000 -> 17.849891 | L78: =J78/$J$109 -> 0.014512106 | M78: Chi phí thực tế bình quân 3 tháng liền kề. CW1: 752 Kwh, CW2: 752 Kwh, Boretech: 1254 Kwh
A79: Tạo hạt | B79: Khác | C79: =+C78+1 -> 12 | D79: OTH | E79: 6277.6278 | F79: Chi phí bằng tiền khác | G79: tháng | H79: 1 | I79: 6.4378995e+08 | J79: =H79*I79/($H$62*$H$63*24*30) -> 138.99489 | K79: =J79/$K$5*1000 -> 5.2450902 | L79: =J79/$J$109 -> 0.004264301 | M79: Chi phí thực tế bình quân 3 tháng liền kề
D80: Giá thành tạo hạt máy Starlinger (III+IV) | J80: =J60+J61 -> 23254.734 | K80: =J80*1000/$K$5 -> 877.53713 | L80: =J80/$J$109 -> 0.71344482
C81: D | D81: CÔNG ĐOẠN NÂNG IV LÊN > 0,8 (LƯU MÁY SSP 10 TIẾNG):
C82: III | F82: Hạt rPET WSS01 | J82: =J80 -> 23254.734 | K82: =J82*1000/$K$5 -> 877.53713 | L82: =J82/$J$109 -> 0.71344482
C83: IV | F83: Chi phí nâng IV (10 tiếng) | J83: =SUM(J84:J98) -> 1754.0485 | K83: =J83*1000/$K$5 -> 66.190511 | L83: =J83/$J$109 -> 0.053813424
A84: Nâng IV 10H | C84: 0 | D84: REL01 | F84: Công suất máy (capacity) | G84: Kg /h | H84: 4992 | M84: Công suất máy 3492 (SSP-01: 1092, SSP-02: 2400)
A85: Nâng IV 10H | F85: Hiệu suất máy | G85: % | H85: 0.81 | M85: Bình quân 3 tháng liền kề theo BI
B86: Bao bì | C86: =+C85+1 -> 1 | D86: BAG | E86: 160012673 | F86: Pallet D4-1137R không nút-GC | G86: cái | H86: 1 | I86: 261000 | J86: =(I86*H86)/1100 -> 237.27273 | K86: =J86/$K$5*1000 -> 8.9536878 | L86: =J86/$J$109 -> 0.007279421 | M86: Giao trong nước pallet đen, giao xuất khẩu pallet gỗ
B87: Bao bì | C87: =+C86+1 -> 2 | D87: BAG | E87: 140005072 | F87: Bao jumbo 105Lx105Wx150H (cm) đựng vảy | G87: cái | H87: 1 | I87: 165225 | J87: =(I87*H87)/1100 -> 150.20455 | K87: =J87/$K$5*1000 -> 5.6680961 | L87: =J87/$J$109 -> 0.0046082082 | M87: 1100 kg hạt/bao
B88: Bao bì | C88: =+C87+1 -> 3 | D88: BAG | E88: 140006090 | F88: Bao PE lót ngoài bao Jumbo | G88: cái | H88: 1 | I88: 23502 | J88: =(I88*H88)/1100 -> 21.365455 | K88: =J88/$K$5*1000 -> 0.80624357 | L88: =J88/$J$109 -> 0.00065548258 | M88: 1100 kg hạt/bao
A89: Nâng IV | B89: NCTT | C89: =+C88+1 -> 4 | D89: LAB | E89: 622 | F89: Chi phí nhân công trực tiếp | G89: tháng | H89: 1 | I89: 1.4639311e+08 | J89: =H89*I89/($H$84*$H$85*24*30) -> 50.283853 | K89: =J89/$K$5*1000 -> 1.8975039 | L89: =J89/$J$109 -> 0.0015426861 | M89: Nạp liệu 1, đóng gói 1, xe nâng 1
A90: Nâng IV | B90: NCGT | C90: =+C89+1 -> 5 | D90: LAB | E90: 6271 | F90: Chi phí nhân công gián tiếp | G90: tháng | H90: 1 | I90: 8.3895256e+08 | J90: =H90*I90/($H$84*$H$85*24*30) -> 288.16771 | K90: =J90/$K$5*1000 -> 10.874253 | L90: =J90/$J$109 -> 0.0088408562 | M90: Lương trưởng ca, hành chính, tổ trưởng, quản lý sản xuất gián tiếp như QC, Kỹ thuật
A91: Nâng IV | B91: VTPX | C91: =+C90+1 -> 6 | D91: OTH | E91: 6272 | F91: Chi phí vật tư phân xưởng | G91: tháng | H91: 1 | I91: 1.3717563e+08 | J91: =H91*I91/($H$84*$H$85*24*30) -> 47.117785 | K91: =J91/$K$5*1000 -> 1.7780296 | L91: =J91/$J$109 -> 0.0014455525 | M91: Chi phí thực tế bình quân 3 tháng liền kề
A92: Nâng IV | B92: CCDC | C92: =+C91+1 -> 7 | D92: OTH | E92: 6273 | F92: Chi phí CCDC, bảo trì | G92: tháng | H92: 1 | I92: 1.3671072e+08 | J92: =H92*I92/($H$84*$H$85*24*30) -> 46.958095 | K92: =J92/$K$5*1000 -> 1.7720036 | L92: =J92/$J$109 -> 0.0014406533 | M92: Chi phí thực tế bình quân 3 tháng liền kề
A93: Nâng IV | B93: KH | C93: =+C92+1 -> 8 | D93: DEP | E93: 6274.1 | F93: Chi phí khấu hao MMTB chính | G93: tháng | H93: 1 | I93: 3.643082e+08 | J93: =H93*I93/($H$84*$H$85*24*30) -> 125.13444 | K93: =J93/$K$5*1000 -> 4.7220543 | L93: =J93/$J$109 -> 0.0038390685 | M93: Chi phí thực tế bình quân 3 tháng liền kề theo danh sách TSCĐ
A94: Nâng IV | B94: KH | C94: =+C93+1 -> 9 | D94: DEP | E94: 6274.2 | F94: Chi phí khấu hao MMTB phụ | G94: tháng | H94: 1 | I94: 0 | J94: =H94*I94/($H$84*$H$85*24*30) -> 0 | K94: =J94/$K$5*1000 -> 0 | L94: =J94/$J$109 -> 0 | M94: Chi phí thực tế bình quân 3 tháng liền kề theo danh sách TSCĐ
A95: Nâng IV | B95: KH | C95: =+C94+1 -> 10 | D95: DEP | E95: 6274.3 | F95: Chi phí khấu hao MMTB dùng chung | G95: tháng | H95: 1 | I95: 1.7828552e+08 | J95: =H95*I95/($H$84*$H$85*24*30) -> 61.238419 | K95: =J95/$K$5*1000 -> 2.3108837 | L95: =J95/$J$109 -> 0.0018787673 | M95: Chi phí thực tế bình quân 3 tháng liền kề theo danh sách TSCĐ
A96: Nâng IV | B96: KH | C96: =+C95+1 -> 11 | D96: DEP | E96: 6274.4 | F96: Chi phí khấu hao nhà xưởng | G96: tháng | H96: 1 | I96: 2.1396707e+08 | J96: =H96*I96/($H$84*$H$85*24*30) -> 73.494502 | K96: =J96/$K$5*1000 -> 2.7733774 | L96: =J96/$J$109 -> 0.0022547784 | M96: Chi phí thực tế bình quân 3 tháng liền kề theo danh sách TSCĐ
A97: Nâng IV | B97: Điện | C97: =+C93+1 -> 9 | D97: ELEC | E97: 6275 | F97: Điện (electronic) SSP | G97: tháng | H97: 1 | I97: 1.4544275e+09 | J97: =H97*I97/($H$84*$H$85*24*30) -> 499.57418 | K97: =J97/$K$5*1000 -> 18.851856 | L97: =J97/$J$109 -> 0.015326712 | M97: Chi phí thực tế bình quân 3 tháng liền kề. CW1: 946 Kwh, Boretech: 487 Kwh
A98: Nâng IV | B98: Khác | C98: =+C97+1 -> 10 | D98: OTH | E98: 6277.6278 | F98: Chi phí bằng tiền khác | G98: tháng | H98: 1 | I98: 4.4612369e+08 | J98: =H98*I98/($H$84*$H$85*24*30) -> 153.23684 | K98: =J98/$K$5*1000 -> 5.7825224 | L98: =J98/$J$109 -> 0.0047012377 | M98: Chi phí thực tế bình quân 3 tháng liền kề
C99: V | F99: Chi phí quản lý | J99: =SUM(J100:J104) -> 3621.8396 | K99: =J99*1000/$K$5 -> 136.67319 | L99: =J99/$J$109 -> 0.11111642
A100: LuongBH | B100: 641 | C100: 1 | D100: 641 | F100: Chi phí nhân sự bán hàng | G100: tháng | H100: 1 | I100: 4.7379281e+08 | J100: =+I100/($H$84*$H$85*24*30) -> 162.74077 | K100: =J100/$K$5*1000 -> 6.1411612 | L100: =J100/$J$109 -> 0.004992814 | M100: Chi phí lương BGĐ, kế toán, HCNS, bán hàng…
A101: LuongQL | B101: 642 | C101: =+C100+1 -> 2 | D101: 642 | F101: Chi phí nhân sự quản lý | G101: tháng | H101: 1 | I101: 4.7196996e+09 | J101: =+I101/($H$84*$H$85*24*30) -> 1621.1465 | K101: =J101/$K$5*1000 -> 61.17534 | L101: =J101/$J$109 -> 0.049736049 | M101: Chi phí lương BGĐ, kế toán, HCNS, bán hàng…
A102: Banhang | B102: 641 | C102: =+C101+1 -> 3 | D102: 641 | F102: Chi phí bán hàng | G102: tháng | H102: 1 | I102: 2.6325862e+09 | J102: =+I102/($H$84*$H$85*24*30) -> 904.25415 | K102: =J102/$K$5*1000 -> 34.122798 | L102: =J102/$J$109 -> 0.027742112 | M102: Chi phí lương BGĐ, kế toán, HCNS, bán hàng…
...
