Workbook
Name EXR: EXR!$D$3
Name EXR_FC01: EXR!$B$7
Name EXR_FC02: EXR!$C$7
Name EXR_FC03: EXR!$D$7
Name EXR_FC04: EXR!$E$7
Name EXR_FC05: EXR!$F$7
Name EXR_FC06: EXR!$G$7
Name EXR_FC07: EXR!$H$7
Name EXR_FC08: EXR!$I$8
Name EXR_FC09: EXR!$J$8
Name EXR_FC10: EXR!$K$8
Name EXR_FC11: EXR!$L$8
Name EXR_FC12: EXR!$M$8

Sheet Working-T05-B2
P1: cthuc | Q1: cthuc | AJ1: cthuc | AM1: =AM2/26.2 -> 1165.5195 | AZ1: SUNTORY/NIAGARA
L2: =L3-SUM(Sales!G3:H100) -> 0 | N2: =N3-SUM(Sales!$I$3:$I$100) -> 0 | AM2: =AM3/S3 -> 30536.611 | BK2: =BK3/AM3 -> 0.14811753
K3: =SUBTOTAL(9,K8:K150) -> 2477774 | L3: =SUBTOTAL(9,L8:L150) -> 30800 | N3: =SUBTOTAL(9,N8:N150) -> 5449793.7 | P3: =SUBTOTAL(9,P8:P150) -> 0 | Q3: =SUBTOTAL(9,Q8:Q150) -> 1461441.8 | R3: =SUBTOTAL(9,R8:R150) -> 4019151.9 | S3: =SUBTOTAL(9,S8:S150) -> 5480593.7 | U3: 1.10125 | AJ3: =SUBTOTAL(9,AJ8:AJ150) -> 0 | AK3: =SUBTOTAL(9,AK8:AK150) -> 3.6353097e+10 | AL3: =SUBTOTAL(9,AL8:AL150) -> 1.3100566e+11 | AM3: =SUBTOTAL(9,AM8:AM150) -> 1.6735876e+11 | AQ3: =SUBTOTAL(9,AQ8:AQ150) -> 0 | AR3: =SUBTOTAL(9,AR8:AR150) -> 5.0898471e+08 | AS3: =SUBTOTAL(9,AS8:AS150) -> 1.6552662e+09 | AT3: =SUBTOTAL(9,AT8:AT150) -> 2.1642509e+09 | AX3: =SUBTOTAL(9,AX8:AX150) -> 0 | AY3: =SUBTOTAL(9,AY8:AY150) -> 212136320 | AZ3: =SUBTOTAL(9,AZ8:AZ150) -> 2.2469285e+09 | BA3: =SUBTOTAL(9,BA8:BA150) -> 2.4590648e+09 | BC3: =SUBTOTAL(9,BC8:BC150) -> 0 | BD3: =SUBTOTAL(9,BD8:BD150) -> 3.7989844e+10 | BE3: =SUBTOTAL(9,BE8:BE150) -> 1.0458015e+11 | BF3: =SUBTOTAL(9,BF8:BF150) -> 1.4256999e+11 | BH3: =SUBTOTAL(9,BH8:BH150) -> 0 | BI3: =SUBTOTAL(9,BI8:BI150) -> -1.6367468e+09 | BJ3: =SUBTOTAL(9,BJ8:BJ150) -> 2.6425513e+10 | BK3: =SUBTOTAL(9,BK8:BK150) -> 2.4788767e+10 | BM3: =SUBTOTAL(9,BM8:BM150) -> 1.4091985e+11 | BN3: =SUBTOTAL(9,BN8:BN150) -> 1.0085096e+11 | BO3: =SUBTOTAL(9,BO8:BO150) -> 1.3550527e+09 | BP3: =SUBTOTAL(9,BP8:BP150) -> 3.1187799e+08 | BQ3: =SUBTOTAL(9,BQ8:BQ150) -> 6.2427281e+09 | BR3: =SUBTOTAL(9,BR8:BR150) -> 8.9941607e+08 | BS3: =SUBTOTAL(9,BS8:BS150) -> 4.9100642e+09 | BT3: =SUBTOTAL(9,BT8:BT150) -> 7.3587196e+09 | ... BV3: =SUBTOTAL(9,BV8:BV150) -> 1.7193314e+10
A4: LINK | B4: SOURCE | C4: Kênh | D4: Mã khách | Mã SKU | E4: Mã khách | F4: Tên khách | G4: Mã SKU | H4: Tên SKU | K4: SỐ LƯỢNG SO CÒN GIAO ĐẦU T05 | L4: SALES | M4: CÒN LẠI | N4: SALES | P4: THÁNG 05
L5: Đã có PO | N5: Chưa có PO | P5: SẢN LƯỢNG | U5: GIÁ BÁN THEO HĐ | Z5: TỶ GIÁ | AE5: GIÁ BÁN (VND/kg) | AJ5: DOANH THU (VND) | AO5: CP VC (VND) | AV5: CP Hoa hồng (VND) | BC5: GIÁ VỐN (VND) | BH5: LÃI GỘP KẾ TOÁN (VND) | BM5: GIÁ VỐN-BREAKDOWN | BW5: Check
P6: SO+Hóa đơn | Q6: SO+Chưa hóa đơn | R6: Dự báo | S6: Tổng | T6: Check | U6: SO+Hóa đơn | V6: SO+Chưa hóa đơn | W6: Dự báo | X6: TB | Z6: SO+Hóa đơn | AA6: SO+Chưa hóa đơn | AB6: Dự báo | AC6: TB | AE6: SO+Hóa đơn | AF6: SO+Chưa hóa đơn | AG6: Dự báo | AH6: TB | AJ6: SO+Hóa đơn | AK6: SO+Chưa hóa đơn | AL6: Dự báo | AM6: TỔNG | AO6: ĐG | AQ6: SO+Hóa đơn | AR6: SO+Chưa hóa đơn | AS6: Dự báo | AT6: Tổng | AV6: ĐG | AX6: SO+Hóa đơn | AY6: SO+Chưa hóa đơn | AZ6: Dự báo | BA6: Tổng | BC6: SO+Hóa đơn | BD6: SO+Chưa hóa đơn | BE6: Dự báo | BF6: Tổng | BH6: SO+Hóa đơn | BI6: SO+Chưa hóa đơn | BJ6: Dự báo | BK6: Tổng | BM6: Tổng | BN6: Nhựa | BO6: Màu/hóa chất/phụ gia | BP6: Bao bì | BQ6: Điện | BR6: Gia công | BS6: NCTT | BT6: NCGT | BU6: Khấu hao máy | BV6: CP sx chung
A8: =_xlfn.XLOOKUP($G8,MD_SKU[Mã SKU],MD_SKU[Link vào file BCQT]) -> Phó sản | B8: TC-026 | C8: NĐ | D8: 105382 | 160012611 | E8: 105382 | F8: Văn Minh | G8: 160012611 | H8: Vảy HD Ép Hỗn Hợp ST | K8: =SUMIFS('Working-T05-B1'!L$8:L$150,'Working-T05-B1'!$C$8:$C$150,$D8) -> 60756 | L8: {=SUMPRODUCT(Sales!$G$3:$H$100*(Sales!$B$3:$B$100=$D8))} -> 0 | M8: =K8-L8 -> 60756 | N8: =SUMIFS(Sales!$I$3:$I$100,Sales!$B$3:$B$100,$D8) -> 0 | P8: =SUMIFS('Working-T05-B1'!O$8:O$150,'Working-T05-B1'!$C$8:$C$150,$D8) -> 0 | Q8: =MAX(0,MIN(K8,L8+N8)-P8) -> 0 | R8: =MAX(0,L8+N8-SUM(P8:Q8)) -> 0 | S8: =SUM(P8:R8) -> 0 | T8: =S8-(L8+N8) -> 0 | U8: =IFERROR(AE8/Z8,0) -> 0 | V8: =IFERROR(AF8/AA8,0) -> 0 | W8: =IF(AND(R8>0,V8>0),V8,0) -> 0 | X8: =IFERROR(IF($C8="XK",$AM8/$S8/$AC8,$AM8/$S8),0) -> 0 | AA8: =IF($C8="NĐ",1,EXR_FC05) -> 1 | AB8: =IF($C8="NĐ",1,EXR_FC05) -> 1 | AC8: =IFERROR(SUMPRODUCT(AJ8:AL8,Z8:AB8)/AM8,0) -> 0 | AE8: =IFERROR(AJ8/P8,0) -> 0 | AF8: =IFERROR(AK8/Q8,0) -> 0 | AG8: =W8*AB8 -> 0 | AJ8: =SUMIFS('Working-T05-B1'!AI$8:AI$150,'Working-T05-B1'!$C$8:$C$150,$D8) -> 0 | AK8: =SUMIFS('Working-T05-B1'!AJ$8:AJ$150,'Working-T05-B1'!$C$8:$C$150,$D8) -> 0 | AL8: =R8*AG8 -> 0 | AM8: =SUM(AJ8:AL8) -> 0 | AO8: =IFERROR(SUM(AQ8:AR8)/SUM(P8:Q8),0) -> 0 | AQ8: =SUMIFS('Working-T05-B1'!AP$8:AP$150,'Working-T05-B1'!$C$8:$C$150,$D8) -> 0 | AR8: =SUMIFS('Working-T05-B1'!AQ$8:AQ$150,'Working-T05-B1'!$C$8:$C$150,$D8) -> 0 | AS8: =AO8*R8 -> 0 | AT8: =SUM(AQ8:AS8) -> 0 | AV8: =IFERROR(BA8/S8,0) -> 0 | AX8: =SUMIFS('Working-T05-B1'!AW$8:AW$150,'Working-T05-B1'!$C$8:$C$150,$D8) -> 0 | AY8: =SUMIFS('Working-T05-B1'!AX$8:AX$150,'Working-T05-B1'!$C$8:$C$150,$D8) -> 0 | BA8: =SUM(AX8:AZ8) -> 0 | BC8: =_xlfn.XLOOKUP($G8,'GIÁ XUẤT KHO'!$A$4:$A$97,'GIÁ XUẤT KHO'!$AW$4:$AW$97)*P8 -> 0 | BD8: =_xlfn.XLOOKUP($G8,'GIÁ XUẤT KHO'!$A$4:$A$97,'GIÁ XUẤT KHO'!$AW$4:$AW$97)*Q8 -> 0 | BE8: =_xlfn.XLOOKUP($G8,'GIÁ XUẤT KHO'!$A$4:$A$97,'GIÁ XUẤT KHO'!$AW$4:$AW$97)*R8 -> 0 | BF8: =SUM(BC8:BE8) -> 0 | BH8: =AJ8-BC8 -> 0 | BI8: =AK8-BD8 -> 0 | BJ8: =AL8-BE8 -> 0 | BK8: =SUM(BH8:BJ8) -> 0 | BM8: =SUM(BN8:BV8) -> 0 | BN8: =SUMIFS('GIÁ XUẤT KHO'!AX$4:AX$97,'GIÁ XUẤT KHO'!$A$4:$A$97,$G8)*$S8 -> 0 | BO8: =SUMIFS('GIÁ XUẤT KHO'!AY$4:AY$97,'GIÁ XUẤT KHO'!$A$4:$A$97,$G8)*$S8 -> 0 | BP8: =SUMIFS('GIÁ XUẤT KHO'!AZ$4:AZ$97,'GIÁ XUẤT KHO'!$A$4:$A$97,$G8)*$S8 -> 0 | BQ8: =SUMIFS('GIÁ XUẤT KHO'!BA$4:BA$97,'GIÁ XUẤT KHO'!$A$4:$A$97,$G8)*$S8 -> 0 | BR8: =SUMIFS('GIÁ XUẤT KHO'!BB$4:BB$97,'GIÁ XUẤT KHO'!$A$4:$A$97,$G8)*$S8 -> 0 | BS8: =SUMIFS('GIÁ XUẤT KHO'!BC$4:BC$97,'GIÁ XUẤT KHO'!$A$4:$A$97,$G8)*$S8 -> 0 | BT8: =SUMIFS('GIÁ XUẤT KHO'!BD$4:BD$97,'GIÁ XUẤT KHO'!$A$4:$A$97,$G8)*$S8 -> 0 | BU8: =SUMIFS('GIÁ XUẤT KHO'!BE$4:BE$97,'GIÁ XUẤT KHO'!$A$4:$A$97,$G8)*$S8 -> 0 | BV8: =SUMIFS('GIÁ XUẤT KHO'!BF$4:BF$97,'GIÁ XUẤT KHO'!$A$4:$A$97,$G8)*$S8 -> 0 | BW8: =BM8-BF8 -> 0
A9: =_xlfn.XLOOKUP($G9,MD_SKU[Mã SKU],MD_SKU[Link vào file BCQT]) -> Vảy rHDPE ép | B9: TC-026 | C9: NĐ | D9: 105382 | 110000408 | E9: 105382 | F9: Văn Minh | G9: 110000408 | H9: Vảy HD Ép Trắng | K9: =SUMIFS('Working-T05-B1'!L$8:L$150,'Working-T05-B1'!$C$8:$C$150,$D9) -> 96000 | L9: {=SUMPRODUCT(Sales!$G$3:$H$100*(Sales!$B$3:$B$100=$D9))} -> 0 | M9: =K9-L9 -> 96000 | N9: =SUMIFS(Sales!$I$3:$I$100,Sales!$B$3:$B$100,$D9) -> 0 | P9: =SUMIFS('Working-T05-B1'!O$8:O$150,'Working-T05-B1'!$C$8:$C$150,$D9) -> 0 | Q9: =MAX(0,MIN(K9,L9+N9)-P9) -> 0 | R9: =MAX(0,L9+N9-SUM(P9:Q9)) -> 0 | S9: =SUM(P9:R9) -> 0 | T9: =S9-(L9+N9) -> 0 | U9: =IFERROR(AE9/Z9,0) -> 0 | V9: =IFERROR(AF9/AA9,0) -> 0 | W9: =IF(AND(R9>0,V9>0),V9,0) -> 0 | X9: =IFERROR(IF($C9="XK",$AM9/$S9/$AC9,$AM9/$S9),0) -> 0 | AA9: =IF($C9="NĐ",1,EXR_FC05) -> 1 | AB9: =IF($C9="NĐ",1,EXR_FC05) -> 1 | AC9: =IFERROR(SUMPRODUCT(AJ9:AL9,Z9:AB9)/AM9,0) -> 0 | AE9: =IFERROR(AJ9/P9,0) -> 0 | AF9: =IFERROR(AK9/Q9,0) -> 0 | AG9: =W9*AB9 -> 0 | AJ9: =SUMIFS('Working-T05-B1'!AI$8:AI$150,'Working-T05-B1'!$C$8:$C$150,$D9) -> 0 | AK9: =SUMIFS('Working-T05-B1'!AJ$8:AJ$150,'Working-T05-B1'!$C$8:$C$150,$D9) -> 0 | AL9: =R9*AG9 -> 0 | AM9: =SUM(AJ9:AL9) -> 0 | AO9: =IFERROR(SUM(AQ9:AR9)/SUM(P9:Q9),0) -> 0 | AQ9: =SUMIFS('Working-T05-B1'!AP$8:AP$150,'Working-T05-B1'!$C$8:$C$150,$D9) -> 0 | AR9: =SUMIFS('Working-T05-B1'!AQ$8:AQ$150,'Working-T05-B1'!$C$8:$C$150,$D9) -> 0 | AS9: =AO9*R9 -> 0 | AT9: =SUM(AQ9:AS9) -> 0 | AV9: =IFERROR(BA9/S9,0) -> 0 | AX9: =SUMIFS('Working-T05-B1'!AW$8:AW$150,'Working-T05-B1'!$C$8:$C$150,$D9) -> 0 | AY9: =SUMIFS('Working-T05-B1'!AX$8:AX$150,'Working-T05-B1'!$C$8:$C$150,$D9) -> 0 | BA9: =SUM(AX9:AZ9) -> 0 | BC9: =_xlfn.XLOOKUP($G9,'GIÁ XUẤT KHO'!$A$4:$A$97,'GIÁ XUẤT KHO'!$AW$4:$AW$97)*P9 -> 0 | BD9: =_xlfn.XLOOKUP($G9,'GIÁ XUẤT KHO'!$A$4:$A$97,'GIÁ XUẤT KHO'!$AW$4:$AW$97)*Q9 -> 0 | BE9: =_xlfn.XLOOKUP($G9,'GIÁ XUẤT KHO'!$A$4:$A$97,'GIÁ XUẤT KHO'!$AW$4:$AW$97)*R9 -> 0 | BF9: =SUM(BC9:BE9) -> 0 | BH9: =AJ9-BC9 -> 0 | BI9: =AK9-BD9 -> 0 | BJ9: =AL9-BE9 -> 0 | BK9: =SUM(BH9:BJ9) -> 0 | BM9: =SUM(BN9:BV9) -> 0 | BN9: =SUMIFS('GIÁ XUẤT KHO'!AX$4:AX$97,'GIÁ XUẤT KHO'!$A$4:$A$97,$G9)*$S9 -> 0 | BO9: =SUMIFS('GIÁ XUẤT KHO'!AY$4:AY$97,'GIÁ XUẤT KHO'!$A$4:$A$97,$G9)*$S9 -> 0 | BP9: =SUMIFS('GIÁ XUẤT KHO'!AZ$4:AZ$97,'GIÁ XUẤT KHO'!$A$4:$A$97,$G9)*$S9 -> 0 | BQ9: =SUMIFS('GIÁ XUẤT KHO'!BA$4:BA$97,'GIÁ XUẤT KHO'!$A$4:$A$97,$G9)*$S9 -> 0 | BR9: =SUMIFS('GIÁ XUẤT KHO'!BB$4:BB$97,'GIÁ XUẤT KHO'!$A$4:$A$97,$G9)*$S9 -> 0 | BS9: =SUMIFS('GIÁ XUẤT KHO'!BC$4:BC$97,'GIÁ XUẤT KHO'!$A$4:$A$97,$G9)*$S9 -> 0 | BT9: =SUMIFS('GIÁ XUẤT KHO'!BD$4:BD$97,'GIÁ XUẤT KHO'!$A$4:$A$97,$G9)*$S9 -> 0 | BU9: =SUMIFS('GIÁ XUẤT KHO'!BE$4:BE$97,'GIÁ XUẤT KHO'!$A$4:$A$97,$G9)*$S9 -> 0 | BV9: =SUMIFS('GIÁ XUẤT KHO'!BF$4:BF$97,'GIÁ XUẤT KHO'!$A$4:$A$97,$G9)*$S9 -> 0 | BW9: =BM9-BF9 -> 0
A10: =_xlfn.XLOOKUP($G10,MD_SKU[Mã SKU],MD_SKU[Link vào file BCQT]) -> Phó sản | B10: TC-026 | C10: NĐ | D10: 105405 | 160012801 | E10: 105405 | F10: Cường Gia Phát | G10: 160012801 | H10: Vảy PET GC Dây Đai | K10: =SUMIFS('Working-T05-B1'!L$8:L$150,'Working-T05-B1'!$C$8:$C$150,$D10) -> 80930 | L10: {=SUMPRODUCT(Sales!$G$3:$H$100*(Sales!$B$3:$B$100=$D10))} -> 0 | M10: =K10-L10 -> 80930 | N10: =SUMIFS(Sales!$I$3:$I$100,Sales!$B$3:$B$100,$D10) -> 100000 | P10: =SUMIFS('Working-T05-B1'!O$8:O$150,'Working-T05-B1'!$C$8:$C$150,$D10) -> 0 | Q10: =MAX(0,MIN(K10,L10+N10)-P10) -> 80930 | R10: =MAX(0,L10+N10-SUM(P10:Q10)) -> 19070 | S10: =SUM(P10:R10) -> 100000 | T10: =S10-(L10+N10) -> 0 | U10: =IFERROR(AE10/Z10,0) -> 0 | V10: =IFERROR(AF10/AA10,0) -> 12000 | W10: =IF(AND(R10>0,V10>0),V10,0) -> 12000 | X10: =IFERROR(IF($C10="XK",$AM10/$S10/$AC10,$AM10/$S10),0) -> 12000 | AA10: =IF($C10="NĐ",1,EXR_FC05) -> 1 | AB10: =IF($C10="NĐ",1,EXR_FC05) -> 1 | AC10: =IFERROR(SUMPRODUCT(AJ10:AL10,Z10:AB10)/AM10,0) -> 1 | AE10: =IFERROR(AJ10/P10,0) -> 0 | AF10: =IFERROR(AK10/Q10,0) -> 12000 | AG10: =W10*AB10 -> 12000 | AJ10: =SUMIFS('Working-T05-B1'!AI$8:AI$150,'Working-T05-B1'!$C$8:$C$150,$D10) -> 0 | AK10: =SUMIFS('Working-T05-B1'!AJ$8:AJ$150,'Working-T05-B1'!$C$8:$C$150,$D10) -> 971160000 | AL10: =R10*AG10 -> 228840000 | AM10: =SUM(AJ10:AL10) -> 1200000000 | AO10: =IFERROR(SUM(AQ10:AR10)/SUM(P10:Q10),0) -> 0 | AQ10: =SUMIFS('Working-T05-B1'!AP$8:AP$150,'Working-T05-B1'!$C$8:$C$150,$D10) -> 0 | AR10: =SUMIFS('Working-T05-B1'!AQ$8:AQ$150,'Working-T05-B1'!$C$8:$C$150,$D10) -> 0 | AS10: =AO10*R10 -> 0 | AT10: =SUM(AQ10:AS10) -> 0 | AV10: =IFERROR(BA10/S10,0) -> 0 | AX10: =SUMIFS('Working-T05-B1'!AW$8:AW$150,'Working-T05-B1'!$C$8:$C$150,$D10) -> 0 | AY10: =SUMIFS('Working-T05-B1'!AX$8:AX$150,'Working-T05-B1'!$C$8:$C$150,$D10) -> 0 | BA10: =SUM(AX10:AZ10) -> 0 | BC10: =_xlfn.XLOOKUP($G10,'GIÁ XUẤT KHO'!$A$4:$A$97,'GIÁ XUẤT KHO'!$AW$4:$AW$97)*P10 -> 0 | BD10: =_xlfn.XLOOKUP($G10,'GIÁ XUẤT KHO'!$A$4:$A$97,'GIÁ XUẤT KHO'!$AW$4:$AW$97)*Q10 -> 1.5574951e+09 | BE10: =_xlfn.XLOOKUP($G10,'GIÁ XUẤT KHO'!$A$4:$A$97,'GIÁ XUẤT KHO'!$AW$4:$AW$97)*R10 -> 3.6700149e+08 | BF10: =SUM(BC10:BE10) -> 1.9244965e+09 | BH10: =AJ10-BC10 -> 0 | BI10: =AK10-BD10 -> -5.8633506e+08 | BJ10: =AL10-BE10 -> -1.3816149e+08 | BK10: =SUM(BH10:BJ10) -> -7.2449655e+08 | BM10: =SUM(BN10:BV10) -> 1.9244965e+09 | BN10: =SUMIFS('GIÁ XUẤT KHO'!AX$4:AX$97,'GIÁ XUẤT KHO'!$A$4:$A$97,$G10)*$S10 -> 1.217176e+09 | BO10: =SUMIFS('GIÁ XUẤT KHO'!AY$4:AY$97,'GIÁ XUẤT KHO'!$A$4:$A$97,$G10)*$S10 -> 0.58393629 | BP10: =SUMIFS('GIÁ XUẤT KHO'!AZ$4:AZ$97,'GIÁ XUẤT KHO'!$A$4:$A$97,$G10)*$S10 -> 9.3429806 | BQ10: =SUMIFS('GIÁ XUẤT KHO'!BA$4:BA$97,'GIÁ XUẤT KHO'!$A$4:$A$97,$G10)*$S10 -> 72585904 | BR10: =SUMIFS('GIÁ XUẤT KHO'!BB$4:BB$97,'GIÁ XUẤT KHO'!$A$4:$A$97,$G10)*$S10 -> 0 | BS10: =SUMIFS('GIÁ XUẤT KHO'!BC$4:BC$97,'GIÁ XUẤT KHO'!$A$4:$A$97,$G10)*$S10 -> 1.4978174e+08 | BT10: =SUMIFS('GIÁ XUẤT KHO'!BD$4:BD$97,'GIÁ XUẤT KHO'!$A$4:$A$97,$G10)*$S10 -> 1.6243981e+08 | BU10: =SUMIFS('GIÁ XUẤT KHO'!BE$4:BE$97,'GIÁ XUẤT KHO'!$A$4:$A$97,$G10)*$S10 -> 15714904 | BV10: =SUMIFS('GIÁ XUẤT KHO'!BF$4:BF$97,'GIÁ XUẤT KHO'!$A$4:$A$97,$G10)*$S10 -> 3.0679813e+08 | BW10: =BM10-BF10 -> 0
A11: =_xlfn.XLOOKUP($G11,MD_SKU[Mã SKU],MD_SKU[Link vào file BCQT]) -> Hạt rPET | B11: TC-026 | C11: NĐ | D11: 104909 | 110000329 | E11: 104909 | F11: Công ty TNHH La Vie | G11: 110000329 | H11: Hạt nhựa rPET WSS01 | K11: =SUMIFS('Working-T05-B1'!L$8:L$150,'Working-T05-B1'!$C$8:$C$150,$D11) -> 230400 | L11: {=SUMPRODUCT(Sales!$G$3:$H$100*(Sales!$B$3:$B$100=$D11))} -> 30800 | M11: =K11-L11 -> 199600 | N11: =SUMIFS(Sales!$I$3:$I$100,Sales!$B$3:$B$100,$D11) -> 0 | P11: =SUMIFS('Working-T05-B1'!O$8:O$150,'Working-T05-B1'!$C$8:$C$150,$D11) -> 0 | Q11: =MAX(0,MIN(K11,L11+N11)-P11) -> 30800 | R11: =MAX(0,L11+N11-SUM(P11:Q11)) -> 0 | S11: =SUM(P11:R11) -> 30800 | T11: =S11-(L11+N11) -> 0 | U11: =IFERROR(AE11/Z11,0) -> 0 | V11: =IFERROR(AF11/AA11,0) -> 33832.83 | W11: =IF(AND(R11>0,V11>0),V11,0) -> 0 | X11: =IFERROR(IF($C11="XK",$AM11/$S11/$AC11,$AM11/$S11),0) -> 33832.83 | AA11: =IF($C11="NĐ",1,EXR_FC05) -> 1 | AB11: =IF($C11="NĐ",1,EXR_FC05) -> 1 | AC11: =IFERROR(SUMPRODUCT(AJ11:AL11,Z11:AB11)/AM11,0) -> 1 | AE11: =IFERROR(AJ11/P11,0) -> 0 | AF11: =IFERROR(AK11/Q11,0) -> 33832.83 | AG11: =W11*AB11 -> 0 | AJ11: =SUMIFS('Working-T05-B1'!AI$8:AI$150,'Working-T05-B1'!$C$8:$C$150,$D11) -> 0 | AK11: =SUMIFS('Working-T05-B1'!AJ$8:AJ$150,'Working-T05-B1'!$C$8:$C$150,$D11) -> 1042051164 | AL11: =R11*AG11 -> 0 | AM11: =SUM(AJ11:AL11) -> 1042051164 | AO11: =IFERROR(SUM(AQ11:AR11)/SUM(P11:Q11),0) -> 0 | AQ11: =SUMIFS('Working-T05-B1'!AP$8:AP$150,'Working-T05-B1'!$C$8:$C$150,$D11) -> 0 | AR11: =SUMIFS('Working-T05-B1'!AQ$8:AQ$150,'Working-T05-B1'!$C$8:$C$150,$D11) -> 0 | AS11: =AO11*R11 -> 0 | AT11: =SUM(AQ11:AS11) -> 0 | AV11: =IFERROR(BA11/S11,0) -> 0 | AX11: =SUMIFS('Working-T05-B1'!AW$8:AW$150,'Working-T05-B1'!$C$8:$C$150,$D11) -> 0 | AY11: =SUMIFS('Working-T05-B1'!AX$8:AX$150,'Working-T05-B1'!$C$8:$C$150,$D11) -> 0 | BA11: =SUM(AX11:AZ11) -> 0 | BC11: =_xlfn.XLOOKUP($G11,'GIÁ XUẤT KHO'!$A$4:$A$97,'GIÁ XUẤT KHO'!$AW$4:$AW$97)*P11 -> 0 | BD11: =_xlfn.XLOOKUP($G11,'GIÁ XUẤT KHO'!$A$4:$A$97,'GIÁ XUẤT KHO'!$AW$4:$AW$97)*Q11 -> 1.0002541e+09 | BE11: =_xlfn.XLOOKUP($G11,'GIÁ XUẤT KHO'!$A$4:$A$97,'GIÁ XUẤT KHO'!$AW$4:$AW$97)*R11 -> 0 | BF11: =SUM(BC11:BE11) -> 1.0002541e+09 | BH11: =AJ11-BC11 -> 0 | BI11: =AK11-BD11 -> 41797097 | BJ11: =AL11-BE11 -> 0 | BK11: =SUM(BH11:BJ11) -> 41797097 | BM11: =SUM(BN11:BV11) -> 1.0002541e+09 | BN11: =SUMIFS('GIÁ XUẤT KHO'!AX$4:AX$97,'GIÁ XUẤT KHO'!$A$4:$A$97,$G11)*$S11 -> 6.0211978e+08 | BO11: =SUMIFS('GIÁ XUẤT KHO'!AY$4:AY$97,'GIÁ XUẤT KHO'!$A$4:$A$97,$G11)*$S11 -> 2702006.6 | BP11: =SUMIFS('GIÁ XUẤT KHO'!AZ$4:AZ$97,'GIÁ XUẤT KHO'!$A$4:$A$97,$G11)*$S11 -> 8.6119702 | BQ11: =SUMIFS('GIÁ XUẤT KHO'!BA$4:BA$97,'GIÁ XUẤT KHO'!$A$4:$A$97,$G11)*$S11 -> 64998199 | BR11: =SUMIFS('GIÁ XUẤT KHO'!BB$4:BB$97,'GIÁ XUẤT KHO'!$A$4:$A$97,$G11)*$S11 -> 6081552.9 | BS11: =SUMIFS('GIÁ XUẤT KHO'!BC$4:BC$97,'GIÁ XUẤT KHO'!$A$4:$A$97,$G11)*$S11 -> 48034157 | BT11: =SUMIFS('GIÁ XUẤT KHO'!BD$4:BD$97,'GIÁ XUẤT KHO'!$A$4:$A$97,$G11)*$S11 -> 77478929 | BU11: =SUMIFS('GIÁ XUẤT KHO'!BE$4:BE$97,'GIÁ XUẤT KHO'!$A$4:$A$97,$G11)*$S11 -> 36355980 | BV11: =SUMIFS('GIÁ XUẤT KHO'!BF$4:BF$97,'GIÁ XUẤT KHO'!$A$4:$A$97,$G11)*$S11 -> 1.6248345e+08 | BW11: =BM11-BF11 -> 0
A12: =_xlfn.XLOOKUP($G12,MD_SKU[Mã SKU],MD_SKU[Link vào file BCQT]) -> Vảy rHDPE ép | B12: TC-026 | C12: NĐ | D12: 105324 | 110000409 | E12: 105324 | F12: NHỰA TRƯỜNG AN | G12: 110000409 | H12: Vảy HD Ép Vàng | K12: =SUMIFS('Working-T05-B1'!L$8:L$150,'Working-T05-B1'!$C$8:$C$150,$D12) -> 3000 | L12: {=SUMPRODUCT(Sales!$G$3:$H$100*(Sales!$B$3:$B$100=$D12))} -> 0 | M12: =K12-L12 -> 3000 | N12: =SUMIFS(Sales!$I$3:$I$100,Sales!$B$3:$B$100,$D12) -> 6000 | P12: =SUMIFS('Working-T05-B1'!O$8:O$150,'Working-T05-B1'!$C$8:$C$150,$D12) -> 0 | Q12: =MAX(0,MIN(K12,L12+N12)-P12) -> 3000 | R12: =MAX(0,L12+N12-SUM(P12:Q12)) -> 3000 | S12: =SUM(P12:R12) -> 6000 | T12: =S12-(L12+N12) -> 0 | U12: =IFERROR(AE12/Z12,0) -> 0 | V12: =IFERROR(AF12/AA12,0) -> 15740.741 | W12: =IF(AND(R12>0,V12>0),V12,0) -> 15740.741 | X12: =IFERROR(IF($C12="XK",$AM12/$S12/$AC12,$AM12/$S12),0) -> 15740.741 | AA12: =IF($C12="NĐ",1,EXR_FC05) -> 1 | AB12: =IF($C12="NĐ",1,EXR_FC05) -> 1 | AC12: =IFERROR(SUMPRODUCT(AJ12:AL12,Z12:AB12)/AM12,0) -> 1 | AE12: =IFERROR(AJ12/P12,0) -> 0 | AF12: =IFERROR(AK12/Q12,0) -> 15740.741 | AG12: =W12*AB12 -> 15740.741 | AJ12: =SUMIFS('Working-T05-B1'!AI$8:AI$150,'Working-T05-B1'!$C$8:$C$150,$D12) -> 0 | AK12: =SUMIFS('Working-T05-B1'!AJ$8:AJ$150,'Working-T05-B1'!$C$8:$C$150,$D12) -> 47222222 | AL12: =R12*AG12 -> 47222222 | AM12: =SUM(AJ12:AL12) -> 94444444 | AO12: =IFERROR(SUM(AQ12:AR12)/SUM(P12:Q12),0) -> 0 | AQ12: =SUMIFS('Working-T05-B1'!AP$8:AP$150,'Working-T05-B1'!$C$8:$C$150,$D12) -> 0 | AR12: =SUMIFS('Working-T05-B1'!AQ$8:AQ$150,'Working-T05-B1'!$C$8:$C$150,$D12) -> 0 | AS12: =AO12*R12 -> 0 | AT12: =SUM(AQ12:AS12) -> 0 | AV12: =IFERROR(BA12/S12,0) -> 0 | AX12: =SUMIFS('Working-T05-B1'!AW$8:AW$150,'Working-T05-B1'!$C$8:$C$150,$D12) -> 0 | AY12: =SUMIFS('Working-T05-B1'!AX$8:AX$150,'Working-T05-B1'!$C$8:$C$150,$D12) -> 0 | BA12: =SUM(AX12:AZ12) -> 0 | BC12: =_xlfn.XLOOKUP($G12,'GIÁ XUẤT KHO'!$A$4:$A$97,'GIÁ XUẤT KHO'!$AW$4:$AW$97)*P12 -> 0 | BD12: =_xlfn.XLOOKUP($G12,'GIÁ XUẤT KHO'!$A$4:$A$97,'GIÁ XUẤT KHO'!$AW$4:$AW$97)*Q12 -> 46759664 | BE12: =_xlfn.XLOOKUP($G12,'GIÁ XUẤT KHO'!$A$4:$A$97,'GIÁ XUẤT KHO'!$AW$4:$AW$97)*R12 -> 46759664 | BF12: =SUM(BC12:BE12) -> 93519328 | BH12: =AJ12-BC12 -> 0 | BI12: =AK12-BD12 -> 462558.33 | BJ12: =AL12-BE12 -> 462558.33 | BK12: =SUM(BH12:BJ12) -> 925116.66 | BM12: =SUM(BN12:BV12) -> 93519328 | BN12: =SUMIFS('GIÁ XUẤT KHO'!AX$4:AX$97,'GIÁ XUẤT KHO'!$A$4:$A$97,$G12)*$S12 -> 88163097 | BO12: =SUMIFS('GIÁ XUẤT KHO'!AY$4:AY$97,'GIÁ XUẤT KHO'!$A$4:$A$97,$G12)*$S12 -> 0.2640264 | BP12: =SUMIFS('GIÁ XUẤT KHO'!AZ$4:AZ$97,'GIÁ XUẤT KHO'!$A$4:$A$97,$G12)*$S12 -> 0 | BQ12: =SUMIFS('GIÁ XUẤT KHO'!BA$4:BA$97,'GIÁ XUẤT KHO'!$A$4:$A$97,$G12)*$S12 -> 748615.45 | BR12: =SUMIFS('GIÁ XUẤT KHO'!BB$4:BB$97,'GIÁ XUẤT KHO'!$A$4:$A$97,$G12)*$S12 -> 36585.347 | BS12: =SUMIFS('GIÁ XUẤT KHO'!BC$4:BC$97,'GIÁ XUẤT KHO'!$A$4:$A$97,$G12)*$S12 -> 1427976 | BT12: =SUMIFS('GIÁ XUẤT KHO'!BD$4:BD$97,'GIÁ XUẤT KHO'!$A$4:$A$97,$G12)*$S12 -> 1081458.5 | BU12: =SUMIFS('GIÁ XUẤT KHO'!BE$4:BE$97,'GIÁ XUẤT KHO'!$A$4:$A$97,$G12)*$S12 -> 666959.47 | BV12: =SUMIFS('GIÁ XUẤT KHO'!BF$4:BF$97,'GIÁ XUẤT KHO'!$A$4:$A$97,$G12)*$S12 -> 1394635.5 | BW12: =BM12-BF12 -> 0
A13: =_xlfn.XLOOKUP($G13,MD_SKU[Mã SKU],MD_SKU[Link vào file BCQT]) -> Vảy rHDPE ép | B13: TC-026 | C13: NĐ | D13: 105324 | 110000410 | E13: 105324 | F13: NHỰA TRƯỜNG AN | G13: 110000410 | H13: Vảy HD Ép Lá | K13: =SUMIFS('Working-T05-B1'!L$8:L$150,'Working-T05-B1'!$C$8:$C$150,$D13) -> 10500 | L13: {=SUMPRODUCT(Sales!$G$3:$H$100*(Sales!$B$3:$B$100=$D13))} -> 0 | M13: =K13-L13 -> 10500 | N13: =SUMIFS(Sales!$I$3:$I$100,Sales!$B$3:$B$100,$D13) -> 0 | P13: =SUMIFS('Working-T05-B1'!O$8:O$150,'Working-T05-B1'!$C$8:$C$150,$D13) -> 0 | Q13: =MAX(0,MIN(K13,L13+N13)-P13) -> 0 | R13: =MAX(0,L13+N13-SUM(P13:Q13)) -> 0 | S13: =SUM(P13:R13) -> 0 | T13: =S13-(L13+N13) -> 0 | U13: =IFERROR(AE13/Z13,0) -> 0 | V13: =IFERROR(AF13/AA13,0) -> 0 | W13: =IF(AND(R13>0,V13>0),V13,0) -> 0 | X13: =IFERROR(IF($C13="XK",$AM13/$S13/$AC13,$AM13/$S13),0) -> 0 | AA13: =IF($C13="NĐ",1,EXR_FC05) -> 1 | AB13: =IF($C13="NĐ",1,EXR_FC05) -> 1 | AC13: =IFERROR(SUMPRODUCT(AJ13:AL13,Z13:AB13)/AM13,0) -> 0 | AE13: =IFERROR(AJ13/P13,0) -> 0 | AF13: =IFERROR(AK13/Q13,0) -> 0 | AG13: =W13*AB13 -> 0 | AJ13: =SUMIFS('Working-T05-B1'!AI$8:AI$150,'Working-T05-B1'!$C$8:$C$150,$D13) -> 0 | AK13: =SUMIFS('Working-T05-B1'!AJ$8:AJ$150,'Working-T05-B1'!$C$8:$C$150,$D13) -> 0 | AL13: =R13*AG13 -> 0 | AM13: =SUM(AJ13:AL13) -> 0 | AO13: =IFERROR(SUM(AQ13:AR13)/SUM(P13:Q13),0) -> 0 | AQ13: =SUMIFS('Working-T05-B1'!AP$8:AP$150,'Working-T05-B1'!$C$8:$C$150,$D13) -> 0 | AR13: =SUMIFS('Working-T05-B1'!AQ$8:AQ$150,'Working-T05-B1'!$C$8:$C$150,$D13) -> 0 | AS13: =AO13*R13 -> 0 | AT13: =SUM(AQ13:AS13) -> 0 | AV13: =IFERROR(BA13/S13,0) -> 0 | AX13: =SUMIFS('Working-T05-B1'!AW$8:AW$150,'Working-T05-B1'!$C$8:$C$150,$D13) -> 0 | AY13: =SUMIFS('Working-T05-B1'!AX$8:AX$150,'Working-T05-B1'!$C$8:$C$150,$D13) -> 0 | BA13: =SUM(AX13:AZ13) -> 0 | BC13: =_xlfn.XLOOKUP($G13,'GIÁ XUẤT KHO'!$A$4:$A$97,'GIÁ XUẤT KHO'!$AW$4:$AW$97)*P13 -> 0 | BD13: =_xlfn.XLOOKUP($G13,'GIÁ XUẤT KHO'!$A$4:$A$97,'GIÁ XUẤT KHO'!$AW$4:$AW$97)*Q13 -> 0 | BE13: =_xlfn.XLOOKUP($G13,'GIÁ XUẤT KHO'!$A$4:$A$97,'GIÁ XUẤT KHO'!$AW$4:$AW$97)*R13 -> 0 | BF13: =SUM(BC13:BE13) -> 0 | BH13: =AJ13-BC13 -> 0 | BI13: =AK13-BD13 -> 0 | BJ13: =AL13-BE13 -> 0 | BK13: =SUM(BH13:BJ13) -> 0 | BM13: =SUM(BN13:BV13) -> 0 | BN13: =SUMIFS('GIÁ XUẤT KHO'!AX$4:AX$97,'GIÁ XUẤT KHO'!$A$4:$A$97,$G13)*$S13 -> 0 | BO13: =SUMIFS('GIÁ XUẤT KHO'!AY$4:AY$97,'GIÁ XUẤT KHO'!$A$4:$A$97,$G13)*$S13 -> 0 | BP13: =SUMIFS('GIÁ XUẤT KHO'!AZ$4:AZ$97,'GIÁ XUẤT KHO'!$A$4:$A$97,$G13)*$S13 -> 0 | BQ13: =SUMIFS('GIÁ XUẤT KHO'!BA$4:BA$97,'GIÁ XUẤT KHO'!$A$4:$A$97,$G13)*$S13 -> 0 | BR13: =SUMIFS('GIÁ XUẤT KHO'!BB$4:BB$97,'GIÁ XUẤT KHO'!$A$4:$A$97,$G13)*$S13 -> 0 | BS13: =SUMIFS('GIÁ XUẤT KHO'!BC$4:BC$97,'GIÁ XUẤT KHO'!$A$4:$A$97,$G13)*$S13 -> 0 | BT13: =SUMIFS('GIÁ XUẤT KHO'!BD$4:BD$97,'GIÁ XUẤT KHO'!$A$4:$A$97,$G13)*$S13 -> 0 | BU13: =SUMIFS('GIÁ XUẤT KHO'!BE$4:BE$97,'GIÁ XUẤT KHO'!$A$4:$A$97,$G13)*$S13 -> 0 | BV13: =SUMIFS('GIÁ XUẤT KHO'!BF$4:BF$97,'GIÁ XUẤT KHO'!$A$4:$A$97,$G13)*$S13 -> 0 | BW13: =BM13-BF13 -> 0
A14: =_xlfn.XLOOKUP($G14,MD_SKU[Mã SKU],MD_SKU[Link vào file BCQT]) -> Vảy rHDPE ép | B14: TC-026 | C14: NĐ | D14: 105324 | 110000407 | E14: 105324 | F14: NHỰA TRƯỜNG AN | G14: 110000407 | H14: Vảy HD Ép Đỏ | K14: =SUMIFS('Working-T05-B1'!L$8:L$150,'Working-T05-B1'!$C$8:$C$150,$D14) -> 24000 | L14: {=SUMPRODUCT(Sales!$G$3:$H$100*(Sales!$B$3:$B$100=$D14))} -> 0 | M14: =K14-L14 -> 24000 | N14: =SUMIFS(Sales!$I$3:$I$100,Sales!$B$3:$B$100,$D14) -> 12000 | P14: =SUMIFS('Working-T05-B1'!O$8:O$150,'Working-T05-B1'!$C$8:$C$150,$D14) -> 0 | Q14: =MAX(0,MIN(K14,L14+N14)-P14) -> 12000 | R14: =MAX(0,L14+N14-SUM(P14:Q14)) -> 0 | S14: =SUM(P14:R14) -> 12000 | T14: =S14-(L14+N14) -> 0 | U14: =IFERROR(AE14/Z14,0) -> 0 | V14: =IFERROR(AF14/AA14,0) -> 15740.741 | W14: =IF(AND(R14>0,V14>0),V14,0) -> 0 | X14: =IFERROR(IF($C14="XK",$AM14/$S14/$AC14,$AM14/$S14),0) -> 15740.741 | AA14: =IF($C14="NĐ",1,EXR_FC05) -> 1 | AB14: =IF($C14="NĐ",1,EXR_FC05) -> 1 | AC14: =IFERROR(SUMPRODUCT(AJ14:AL14,Z14:AB14)/AM14,0) -> 1 | AE14: =IFERROR(AJ14/P14,0) -> 0 | AF14: =IFERROR(AK14/Q14,0) -> 15740.741 | AG14: =W14*AB14 -> 0 | AJ14: =SUMIFS('Working-T05-B1'!AI$8:AI$150,'Working-T05-B1'!$C$8:$C$150,$D14) -> 0 | AK14: =SUMIFS('Working-T05-B1'!AJ$8:AJ$150,'Working-T05-B1'!$C$8:$C$150,$D14) -> 1.8888889e+08 | AL14: =R14*AG14 -> 0 | AM14: =SUM(AJ14:AL14) -> 1.8888889e+08 | AO14: =IFERROR(SUM(AQ14:AR14)/SUM(P14:Q14),0) -> 0 | AQ14: =SUMIFS('Working-T05-B1'!AP$8:AP$150,'Working-T05-B1'!$C$8:$C$150,$D14) -> 0 | AR14: =SUMIFS('Working-T05-B1'!AQ$8:AQ$150,'Working-T05-B1'!$C$8:$C$150,$D14) -> 0 | AS14: =AO14*R14 -> 0 | AT14: =SUM(AQ14:AS14) -> 0 | AV14: =IFERROR(BA14/S14,0) -> 0 | AX14: =SUMIFS('Working-T05-B1'!AW$8:AW$150,'Working-T05-B1'!$C$8:$C$150,$D14) -> 0 | AY14: =SUMIFS('Working-T05-B1'!AX$8:AX$150,'Working-T05-B1'!$C$8:$C$150,$D14) -> 0 | BA14: =SUM(AX14:AZ14) -> 0 | BC14: =_xlfn.XLOOKUP($G14,'GIÁ XUẤT KHO'!$A$4:$A$97,'GIÁ XUẤT KHO'!$AW$4:$AW$97)*P14 -> 0 | BD14: =_xlfn.XLOOKUP($G14,'GIÁ XUẤT KHO'!$A$4:$A$97,'GIÁ XUẤT KHO'!$AW$4:$AW$97)*Q14 -> 6.3425562e+08 | BE14: =_xlfn.XLOOKUP($G14,'GIÁ XUẤT KHO'!$A$4:$A$97,'GIÁ XUẤT KHO'!$AW$4:$AW$97)*R14 -> 0 | BF14: =SUM(BC14:BE14) -> 6.3425562e+08 | BH14: =AJ14-BC14 -> 0 | BI14: =AK14-BD14 -> -4.4536673e+08 | BJ14: =AL14-BE14 -> 0 | BK14: =SUM(BH14:BJ14) -> -4.4536673e+08 | BM14: =SUM(BN14:BV14) -> 6.3425562e+08 | BN14: =SUMIFS('GIÁ XUẤT KHO'!AX$4:AX$97,'GIÁ XUẤT KHO'!$A$4:$A$97,$G14)*$S14 -> 2.299744e+08 | BO14: =SUMIFS('GIÁ XUẤT KHO'!AY$4:AY$97,'GIÁ XUẤT KHO'!$A$4:$A$97,$G14)*$S14 -> 116210.35 | BP14: =SUMIFS('GIÁ XUẤT KHO'!AZ$4:AZ$97,'GIÁ XUẤT KHO'!$A$4:$A$97,$G14)*$S14 -> 1991055.3 | BQ14: =SUMIFS('GIÁ XUẤT KHO'!BA$4:BA$97,'GIÁ XUẤT KHO'!$A$4:$A$97,$G14)*$S14 -> 48462854 | BR14: =SUMIFS('GIÁ XUẤT KHO'!BB$4:BB$97,'GIÁ XUẤT KHO'!$A$4:$A$97,$G14)*$S14 -> 5209662.7 | BS14: =SUMIFS('GIÁ XUẤT KHO'!BC$4:BC$97,'GIÁ XUẤT KHO'!$A$4:$A$97,$G14)*$S14 -> 97711593 | BT14: =SUMIFS('GIÁ XUẤT KHO'!BD$4:BD$97,'GIÁ XUẤT KHO'!$A$4:$A$97,$G14)*$S14 -> 89153977 | BU14: =SUMIFS('GIÁ XUẤT KHO'!BE$4:BE$97,'GIÁ XUẤT KHO'!$A$4:$A$97,$G14)*$S14 -> 46994558 | BV14: =SUMIFS('GIÁ XUẤT KHO'!BF$4:BF$97,'GIÁ XUẤT KHO'!$A$4:$A$97,$G14)*$S14 -> 1.1464131e+08 | BW14: =BM14-BF14 -> 0
A15: =_xlfn.XLOOKUP($G15,MD_SKU[Mã SKU],MD_SKU[Link vào file BCQT]) -> Hạt rHDPE thổi | B15: TC-026 | C15: NĐ | D15: 105349 | 110000341 | E15: 105349 | F15: MTVN Plastic | G15: 110000341 | H15: Hạt nhựa rHDB04B01 | K15: =SUMIFS('Working-T05-B1'!L$8:L$150,'Working-T05-B1'!$C$8:$C$150,$D15) -> 30500 | L15: {=SUMPRODUCT(Sales!$G$3:$H$100*(Sales!$B$3:$B$100=$D15))} -> 0 | M15: =K15-L15 -> 30500 | N15: =SUMIFS(Sales!$I$3:$I$100,Sales!$B$3:$B$100,$D15) -> 30000 | P15: =SUMIFS('Working-T05-B1'!O$8:O$150,'Working-T05-B1'!$C$8:$C$150,$D15) -> 0 | Q15: =MAX(0,MIN(K15,L15+N15)-P15) -> 30000 | R15: =MAX(0,L15+N15-SUM(P15:Q15)) -> 0 | S15: =SUM(P15:R15) -> 30000 | T15: =S15-(L15+N15) -> 0 | U15: =IFERROR(AE15/Z15,0) -> 0 | V15: =IFERROR(AF15/AA15,0) -> 16203.704 | W15: =IF(AND(R15>0,V15>0),V15,0) -> 0 | X15: =IFERROR(IF($C15="XK",$AM15/$S15/$AC15,$AM15/$S15),0) -> 16203.704 | AA15: =IF($C15="NĐ",1,EXR_FC05) -> 1 | AB15: =IF($C15="NĐ",1,EXR_FC05) -> 1 | AC15: =IFERROR(SUMPRODUCT(AJ15:AL15,Z15:AB15)/AM15,0) -> 1 | AE15: =IFERROR(AJ15/P15,0) -> 0 | AF15: =IFERROR(AK15/Q15,0) -> 16203.704 | AG15: =W15*AB15 -> 0 | AJ15: =SUMIFS('Working-T05-B1'!AI$8:AI$150,'Working-T05-B1'!$C$8:$C$150,$D15) -> 0 | AK15: =SUMIFS('Working-T05-B1'!AJ$8:AJ$150,'Working-T05-B1'!$C$8:$C$150,$D15) -> 4.8611111e+08 | AL15: =R15*AG15 -> 0 | AM15: =SUM(AJ15:AL15) -> 4.8611111e+08 | AO15: =IFERROR(SUM(AQ15:AR15)/SUM(P15:Q15),0) -> 0 | AQ15: =SUMIFS('Working-T05-B1'!AP$8:AP$150,'Working-T05-B1'!$C$8:$C$150,$D15) -> 0 | AR15: =SUMIFS('Working-T05-B1'!AQ$8:AQ$150,'Working-T05-B1'!$C$8:$C$150,$D15) -> 0 | AS15: =AO15*R15 -> 0 | AT15: =SUM(AQ15:AS15) -> 0 | AV15: =IFERROR(BA15/S15,0) -> 0 | AX15: =SUMIFS('Working-T05-B1'!AW$8:AW$150,'Working-T05-B1'!$C$8:$C$150,$D15) -> 0 | AY15: =SUMIFS('Working-T05-B1'!AX$8:AX$150,'Working-T05-B1'!$C$8:$C$150,$D15) -> 0 | BA15: =SUM(AX15:AZ15) -> 0 | BC15: =_xlfn.XLOOKUP($G15,'GIÁ XUẤT KHO'!$A$4:$A$97,'GIÁ XUẤT KHO'!$AW$4:$AW$97)*P15 -> 0 | BD15: =_xlfn.XLOOKUP($G15,'GIÁ XUẤT KHO'!$A$4:$A$97,'GIÁ XUẤT KHO'!$AW$4:$AW$97)*Q15 -> 6.1048755e+08 | BE15: =_xlfn.XLOOKUP($G15,'GIÁ XUẤT KHO'!$A$4:$A$97,'GIÁ XUẤT KHO'!$AW$4:$AW$97)*R15 -> 0 | BF15: =SUM(BC15:BE15) -> 6.1048755e+08 | BH15: =AJ15-BC15 -> 0 | BI15: =AK15-BD15 -> -1.2437644e+08 | BJ15: =AL15-BE15 -> 0 | BK15: =SUM(BH15:BJ15) -> -1.2437644e+08 | BM15: =SUM(BN15:BV15) -> 6.1048755e+08 | BN15: =SUMIFS('GIÁ XUẤT KHO'!AX$4:AX$97,'GIÁ XUẤT KHO'!$A$4:$A$97,$G15)*$S15 -> 3.9517871e+08 | BO15: =SUMIFS('GIÁ XUẤT KHO'!AY$4:AY$97,'GIÁ XUẤT KHO'!$A$4:$A$97,$G15)*$S15 -> 10029045 | BP15: =SUMIFS('GIÁ XUẤT KHO'!AZ$4:AZ$97,'GIÁ XUẤT KHO'!$A$4:$A$97,$G15)*$S15 -> 4911419 | BQ15: =SUMIFS('GIÁ XUẤT KHO'!BA$4:BA$97,'GIÁ XUẤT KHO'!$A$4:$A$97,$G15)*$S15 -> 33250668 | BR15: =SUMIFS('GIÁ XUẤT KHO'!BB$4:BB$97,'GIÁ XUẤT KHO'!$A$4:$A$97,$G15)*$S15 -> 7139174.3 | BS15: =SUMIFS('GIÁ XUẤT KHO'!BC$4:BC$97,'GIÁ XUẤT KHO'!$A$4:$A$97,$G15)*$S15 -> 42618160 | BT15: =SUMIFS('GIÁ XUẤT KHO'!BD$4:BD$97,'GIÁ XUẤT KHO'!$A$4:$A$97,$G15)*$S15 -> 40571790 | BU15: =SUMIFS('GIÁ XUẤT KHO'!BE$4:BE$97,'GIÁ XUẤT KHO'!$A$4:$A$97,$G15)*$S15 -> 8246135.1 | BV15: =SUMIFS('GIÁ XUẤT KHO'!BF$4:BF$97,'GIÁ XUẤT KHO'!$A$4:$A$97,$G15)*$S15 -> 68542448 | BW15: =BM15-BF15 -> 0
A16: =_xlfn.XLOOKUP($G16,MD_SKU[Mã SKU],MD_SKU[Link vào file BCQT]) -> Hạt rHDPE ép | B16: TC-026 | C16: NĐ | D16: 1000 | 110000360 | E16: 1000 | F16: Duy Tân | G16: 110000360 | H16: Hạt nhựa rHDI4L01 | K16: =SUMIFS('Working-T05-B1'!L$8:L$150,'Working-T05-B1'!$C$8:$C$150,$D16) -> 11000 | L16: {=SUMPRODUCT(Sales!$G$3:$H$100*(Sales!$B$3:$B$100=$D16))} -> 0 | M16: =K16-L16 -> 11000 | N16: =SUMIFS(Sales!$I$3:$I$100,Sales!$B$3:$B$100,$D16) -> 0 | P16: =SUMIFS('Working-T05-B1'!O$8:O$150,'Working-T05-B1'!$C$8:$C$150,$D16) -> 0 | Q16: =MAX(0,MIN(K16,L16+N16)-P16) -> 0 | R16: =MAX(0,L16+N16-SUM(P16:Q16)) -> 0 | S16: =SUM(P16:R16) -> 0 | T16: =S16-(L16+N16) -> 0 | U16: =IFERROR(AE16/Z16,0) -> 0 | V16: =IFERROR(AF16/AA16,0) -> 0 | W16: =IF(AND(R16>0,V16>0),V16,0) -> 0 | X16: =IFERROR(IF($C16="XK",$AM16/$S16/$AC16,$AM16/$S16),0) -> 0 | AA16: =IF($C16="NĐ",1,EXR_FC05) -> 1 | AB16: =IF($C16="NĐ",1,EXR_FC05) -> 1 | AC16: =IFERROR(SUMPRODUCT(AJ16:AL16,Z16:AB16)/AM16,0) -> 0 | AE16: =IFERROR(AJ16/P16,0) -> 0 | AF16: =IFERROR(AK16/Q16,0) -> 0 | AG16: =W16*AB16 -> 0 | AJ16: =SUMIFS('Working-T05-B1'!AI$8:AI$150,'Working-T05-B1'!$C$8:$C$150,$D16) -> 0 | AK16: =SUMIFS('Working-T05-B1'!AJ$8:AJ$150,'Working-T05-B1'!$C$8:$C$150,$D16) -> 0 | AL16: =R16*AG16 -> 0 | AM16: =SUM(AJ16:AL16) -> 0 | AO16: =IFERROR(SUM(AQ16:AR16)/SUM(P16:Q16),0) -> 0 | AQ16: =SUMIFS('Working-T05-B1'!AP$8:AP$150,'Working-T05-B1'!$C$8:$C$150,$D16) -> 0 | AR16: =SUMIFS('Working-T05-B1'!AQ$8:AQ$150,'Working-T05-B1'!$C$8:$C$150,$D16) -> 0 | AS16: =AO16*R16 -> 0 | AT16: =SUM(AQ16:AS16) -> 0 | AV16: =IFERROR(BA16/S16,0) -> 0 | AX16: =SUMIFS('Working-T05-B1'!AW$8:AW$150,'Working-T05-B1'!$C$8:$C$150,$D16) -> 0 | AY16: =SUMIFS('Working-T05-B1'!AX$8:AX$150,'Working-T05-B1'!$C$8:$C$150,$D16) -> 0 | BA16: =SUM(AX16:AZ16) -> 0 | BC16: =_xlfn.XLOOKUP($G16,'GIÁ XUẤT KHO'!$A$4:$A$97,'GIÁ XUẤT KHO'!$AW$4:$AW$97)*P16 -> 0 | BD16: =_xlfn.XLOOKUP($G16,'GIÁ XUẤT KHO'!$A$4:$A$97,'GIÁ XUẤT KHO'!$AW$4:$AW$97)*Q16 -> 0 | BE16: =_xlfn.XLOOKUP($G16,'GIÁ XUẤT KHO'!$A$4:$A$97,'GIÁ XUẤT KHO'!$AW$4:$AW$97)*R16 -> 0 | BF16: =SUM(BC16:BE16) -> 0 | BH16: =AJ16-BC16 -> 0 | BI16: =AK16-BD16 -> 0 | BJ16: =AL16-BE16 -> 0 | BK16: =SUM(BH16:BJ16) -> 0 | BM16: =SUM(BN16:BV16) -> 0 | BN16: =SUMIFS('GIÁ XUẤT KHO'!AX$4:AX$97,'GIÁ XUẤT KHO'!$A$4:$A$97,$G16)*$S16 -> 0 | BO16: =SUMIFS('GIÁ XUẤT KHO'!AY$4:AY$97,'GIÁ XUẤT KHO'!$A$4:$A$97,$G16)*$S16 -> 0 | BP16: =SUMIFS('GIÁ XUẤT KHO'!AZ$4:AZ$97,'GIÁ XUẤT KHO'!$A$4:$A$97,$G16)*$S16 -> 0 | BQ16: =SUMIFS('GIÁ XUẤT KHO'!BA$4:BA$97,'GIÁ XUẤT KHO'!$A$4:$A$97,$G16)*$S16 -> 0 | BR16: =SUMIFS('GIÁ XUẤT KHO'!BB$4:BB$97,'GIÁ XUẤT KHO'!$A$4:$A$97,$G16)*$S16 -> 0 | BS16: =SUMIFS('GIÁ XUẤT KHO'!BC$4:BC$97,'GIÁ XUẤT KHO'!$A$4:$A$97,$G16)*$S16 -> 0 | BT16: =SUMIFS('GIÁ XUẤT KHO'!BD$4:BD$97,'GIÁ XUẤT KHO'!$A$4:$A$97,$G16)*$S16 -> 0 | BU16: =SUMIFS('GIÁ XUẤT KHO'!BE$4:BE$97,'GIÁ XUẤT KHO'!$A$4:$A$97,$G16)*$S16 -> 0 | BV16: =SUMIFS('GIÁ XUẤT KHO'!BF$4:BF$97,'GIÁ XUẤT KHO'!$A$4:$A$97,$G16)*$S16 -> 0 | BW16: =BM16-BF16 -> 0
A17: =_xlfn.XLOOKUP($G17,MD_SKU[Mã SKU],MD_SKU[Link vào file BCQT]) -> Phó sản | B17: TC-026 | C17: NĐ | D17: 105229 | 160012801 | E17: 105229 | F17: GIA TƯỜNG | G17: 160012801 | H17: Vảy PET GC Dây Đai | K17: =SUMIFS('Working-T05-B1'!L$8:L$150,'Working-T05-B1'!$C$8:$C$150,$D17) -> 5000 | L17: {=SUMPRODUCT(Sales!$G$3:$H$100*(Sales!$B$3:$B$100=$D17))} -> 0 | M17: =K17-L17 -> 5000 | N17: =SUMIFS(Sales!$I$3:$I$100,Sales!$B$3:$B$100,$D17) -> 0 | P17: =SUMIFS('Working-T05-B1'!O$8:O$150,'Working-T05-B1'!$C$8:$C$150,$D17) -> 0 | Q17: =MAX(0,MIN(K17,L17+N17)-P17) -> 0 | R17: =MAX(0,L17+N17-SUM(P17:Q17)) -> 0 | S17: =SUM(P17:R17) -> 0 | T17: =S17-(L17+N17) -> 0 | U17: =IFERROR(AE17/Z17,0) -> 0 | V17: =IFERROR(AF17/AA17,0) -> 0 | W17: =IF(AND(R17>0,V17>0),V17,0) -> 0 | X17: =IFERROR(IF($C17="XK",$AM17/$S17/$AC17,$AM17/$S17),0) -> 0 | AA17: =IF($C17="NĐ",1,EXR_FC05) -> 1 | AB17: =IF($C17="NĐ",1,EXR_FC05) -> 1 | AC17: =IFERROR(SUMPRODUCT(AJ17:AL17,Z17:AB17)/AM17,0) -> 0 | AE17: =IFERROR(AJ17/P17,0) -> 0 | AF17: =IFERROR(AK17/Q17,0) -> 0 | AG17: =W17*AB17 -> 0 | AJ17: =SUMIFS('Working-T05-B1'!AI$8:AI$150,'Working-T05-B1'!$C$8:$C$150,$D17) -> 0 | AK17: =SUMIFS('Working-T05-B1'!AJ$8:AJ$150,'Working-T05-B1'!$C$8:$C$150,$D17) -> 0 | AL17: =R17*AG17 -> 0 | AM17: =SUM(AJ17:AL17) -> 0 | AO17: =IFERROR(SUM(AQ17:AR17)/SUM(P17:Q17),0) -> 0 | AQ17: =SUMIFS('Working-T05-B1'!AP$8:AP$150,'Working-T05-B1'!$C$8:$C$150,$D17) -> 0 | AR17: =SUMIFS('Working-T05-B1'!AQ$8:AQ$150,'Working-T05-B1'!$C$8:$C$150,$D17) -> 0 | AS17: =AO17*R17 -> 0 | AT17: =SUM(AQ17:AS17) -> 0 | AV17: =IFERROR(BA17/S17,0) -> 0 | AX17: =SUMIFS('Working-T05-B1'!AW$8:AW$150,'Working-T05-B1'!$C$8:$C$150,$D17) -> 0 | AY17: =SUMIFS('Working-T05-B1'!AX$8:AX$150,'Working-T05-B1'!$C$8:$C$150,$D17) -> 0 | BA17: =SUM(AX17:AZ17) -> 0 | BC17: =_xlfn.XLOOKUP($G17,'GIÁ XUẤT KHO'!$A$4:$A$97,'GIÁ XUẤT KHO'!$AW$4:$AW$97)*P17 -> 0 | BD17: =_xlfn.XLOOKUP($G17,'GIÁ XUẤT KHO'!$A$4:$A$97,'GIÁ XUẤT KHO'!$AW$4:$AW$97)*Q17 -> 0 | BE17: =_xlfn.XLOOKUP($G17,'GIÁ XUẤT KHO'!$A$4:$A$97,'GIÁ XUẤT KHO'!$AW$4:$AW$97)*R17 -> 0 | BF17: =SUM(BC17:BE17) -> 0 | BH17: =AJ17-BC17 -> 0 | BI17: =AK17-BD17 -> 0 | BJ17: =AL17-BE17 -> 0 | BK17: =SUM(BH17:BJ17) -> 0 | BM17: =SUM(BN17:BV17) -> 0 | BN17: =SUMIFS('GIÁ XUẤT KHO'!AX$4:AX$97,'GIÁ XUẤT KHO'!$A$4:$A$97,$G17)*$S17 -> 0 | BO17: =SUMIFS('GIÁ XUẤT KHO'!AY$4:AY$97,'GIÁ XUẤT KHO'!$A$4:$A$97,$G17)*$S17 -> 0 | BP17: =SUMIFS('GIÁ XUẤT KHO'!AZ$4:AZ$97,'GIÁ XUẤT KHO'!$A$4:$A$97,$G17)*$S17 -> 0 | BQ17: =SUMIFS('GIÁ XUẤT KHO'!BA$4:BA$97,'GIÁ XUẤT KHO'!$A$4:$A$97,$G17)*$S17 -> 0 | BR17: =SUMIFS('GIÁ XUẤT KHO'!BB$4:BB$97,'GIÁ XUẤT KHO'!$A$4:$A$97,$G17)*$S17 -> 0 | BS17: =SUMIFS('GIÁ XUẤT KHO'!BC$4:BC$97,'GIÁ XUẤT KHO'!$A$4:$A$97,$G17)*$S17 -> 0 | BT17: =SUMIFS('GIÁ XUẤT KHO'!BD$4:BD$97,'GIÁ XUẤT KHO'!$A$4:$A$97,$G17)*$S17 -> 0 | BU17: =SUMIFS('GIÁ XUẤT KHO'!BE$4:BE$97,'GIÁ XUẤT KHO'!$A$4:$A$97,$G17)*$S17 -> 0 | BV17: =SUMIFS('GIÁ XUẤT KHO'!BF$4:BF$97,'GIÁ XUẤT KHO'!$A$4:$A$97,$G17)*$S17 -> 0 | BW17: =BM17-BF17 -> 0
A18: =_xlfn.XLOOKUP($G18,MD_SKU[Mã SKU],MD_SKU[Link vào file BCQT]) -> Hạt rHDPE ép | B18: TC-026 | C18: NĐ | D18: 105339 | 110000364 | E18: 105339 | F18: HUY THÀNH | G18: 110000364 | H18: Hạt nhựa rHDI3Y01 | K18: =SUMIFS('Working-T05-B1'!L$8:L$150,'Working-T05-B1'!$C$8:$C$150,$D18) -> 33000 | L18: {=SUMPRODUCT(Sales!$G$3:$H$100*(Sales!$B$3:$B$100=$D18))} -> 0 | M18: =K18-L18 -> 33000 | N18: =SUMIFS(Sales!$I$3:$I$100,Sales!$B$3:$B$100,$D18) -> 0 | P18: =SUMIFS('Working-T05-B1'!O$8:O$150,'Working-T05-B1'!$C$8:$C$150,$D18) -> 0 | Q18: =MAX(0,MIN(K18,L18+N18)-P18) -> 0 | R18: =MAX(0,L18+N18-SUM(P18:Q18)) -> 0 | S18: =SUM(P18:R18) -> 0 | T18: =S18-(L18+N18) -> 0 | U18: =IFERROR(AE18/Z18,0) -> 0 | V18: =IFERROR(AF18/AA18,0) -> 0 | W18: =IF(AND(R18>0,V18>0),V18,0) -> 0 | X18: =IFERROR(IF($C18="XK",$AM18/$S18/$AC18,$AM18/$S18),0) -> 0 | AA18: =IF($C18="NĐ",1,EXR_FC05) -> 1 | AB18: =IF($C18="NĐ",1,EXR_FC05) -> 1 | AC18: =IFERROR(SUMPRODUCT(AJ18:AL18,Z18:AB18)/AM18,0) -> 0 | AE18: =IFERROR(AJ18/P18,0) -> 0 | AF18: =IFERROR(AK18/Q18,0) -> 0 | AG18: =W18*AB18 -> 0 | AJ18: =SUMIFS('Working-T05-B1'!AI$8:AI$150,'Working-T05-B1'!$C$8:$C$150,$D18) -> 0 | AK18: =SUMIFS('Working-T05-B1'!AJ$8:AJ$150,'Working-T05-B1'!$C$8:$C$150,$D18) -> 0 | AL18: =R18*AG18 -> 0 | AM18: =SUM(AJ18:AL18) -> 0 | AO18: =IFERROR(SUM(AQ18:AR18)/SUM(P18:Q18),0) -> 0 | AQ18: =SUMIFS('Working-T05-B1'!AP$8:AP$150,'Working-T05-B1'!$C$8:$C$150,$D18) -> 0 | AR18: =SUMIFS('Working-T05-B1'!AQ$8:AQ$150,'Working-T05-B1'!$C$8:$C$150,$D18) -> 0 | AS18: =AO18*R18 -> 0 | AT18: =SUM(AQ18:AS18) -> 0 | AV18: =IFERROR(BA18/S18,0) -> 0 | AX18: =SUMIFS('Working-T05-B1'!AW$8:AW$150,'Working-T05-B1'!$C$8:$C$150,$D18) -> 0 | AY18: =SUMIFS('Working-T05-B1'!AX$8:AX$150,'Working-T05-B1'!$C$8:$C$150,$D18) -> 0 | BA18: =SUM(AX18:AZ18) -> 0 | BC18: =_xlfn.XLOOKUP($G18,'GIÁ XUẤT KHO'!$A$4:$A$97,'GIÁ XUẤT KHO'!$AW$4:$AW$97)*P18 -> 0 | BD18: =_xlfn.XLOOKUP($G18,'GIÁ XUẤT KHO'!$A$4:$A$97,'GIÁ XUẤT KHO'!$AW$4:$AW$97)*Q18 -> 0 | BE18: =_xlfn.XLOOKUP($G18,'GIÁ XUẤT KHO'!$A$4:$A$97,'GIÁ XUẤT KHO'!$AW$4:$AW$97)*R18 -> 0 | BF18: =SUM(BC18:BE18) -> 0 | BH18: =AJ18-BC18 -> 0 | BI18: =AK18-BD18 -> 0 | BJ18: =AL18-BE18 -> 0 | BK18: =SUM(BH18:BJ18) -> 0 | BM18: =SUM(BN18:BV18) -> 0 | BN18: =SUMIFS('GIÁ XUẤT KHO'!AX$4:AX$97,'GIÁ XUẤT KHO'!$A$4:$A$97,$G18)*$S18 -> 0 | BO18: =SUMIFS('GIÁ XUẤT KHO'!AY$4:AY$97,'GIÁ XUẤT KHO'!$A$4:$A$97,$G18)*$S18 -> 0 | BP18: =SUMIFS('GIÁ XUẤT KHO'!AZ$4:AZ$97,'GIÁ XUẤT KHO'!$A$4:$A$97,$G18)*$S18 -> 0 | BQ18: =SUMIFS('GIÁ XUẤT KHO'!BA$4:BA$97,'GIÁ XUẤT KHO'!$A$4:$A$97,$G18)*$S18 -> 0 | BR18: =SUMIFS('GIÁ XUẤT KHO'!BB$4:BB$97,'GIÁ XUẤT KHO'!$A$4:$A$97,$G18)*$S18 -> 0 | BS18: =SUMIFS('GIÁ XUẤT KHO'!BC$4:BC$97,'GIÁ XUẤT KHO'!$A$4:$A$97,$G18)*$S18 -> 0 | BT18: =SUMIFS('GIÁ XUẤT KHO'!BD$4:BD$97,'GIÁ XUẤT KHO'!$A$4:$A$97,$G18)*$S18 -> 0 | BU18: =SUMIFS('GIÁ XUẤT KHO'!BE$4:BE$97,'GIÁ XUẤT KHO'!$A$4:$A$97,$G18)*$S18 -> 0 | BV18: =SUMIFS('GIÁ XUẤT KHO'!BF$4:BF$97,'GIÁ XUẤT KHO'!$A$4:$A$97,$G18)*$S18 -> 0 | BW18: =BM18-BF18 -> 0
A19: =_xlfn.XLOOKUP($G19,MD_SKU[Mã SKU],MD_SKU[Link vào file BCQT]) -> Phó sản | B19: TC-026 | C19: NĐ | D19: 105371 | 160012334 | E19: 105371 | F19: VINAFIBER | G19: 160012334 | H19: Phó Sản PET Bụi Cám Sau Sàn Rung | K19: =SUMIFS('Working-T05-B1'!L$8:L$150,'Working-T05-B1'!$C$8:$C$150,$D19) -> 25876 | L19: {=SUMPRODUCT(Sales!$G$3:$H$100*(Sales!$B$3:$B$100=$D19))} -> 0 | M19: =K19-L19 -> 25876 | N19: =SUMIFS(Sales!$I$3:$I$100,Sales!$B$3:$B$100,$D19) -> 0 | P19: =SUMIFS('Working-T05-B1'!O$8:O$150,'Working-T05-B1'!$C$8:$C$150,$D19) -> 0 | Q19: =MAX(0,MIN(K19,L19+N19)-P19) -> 0 | R19: =MAX(0,L19+N19-SUM(P19:Q19)) -> 0 | S19: =SUM(P19:R19) -> 0 | T19: =S19-(L19+N19) -> 0 | U19: =IFERROR(AE19/Z19,0) -> 0 | V19: =IFERROR(AF19/AA19,0) -> 0 | W19: =IF(AND(R19>0,V19>0),V19,0) -> 0 | X19: =IFERROR(IF($C19="XK",$AM19/$S19/$AC19,$AM19/$S19),0) -> 0 | AA19: =IF($C19="NĐ",1,EXR_FC05) -> 1 | AB19: =IF($C19="NĐ",1,EXR_FC05) -> 1 | AC19: =IFERROR(SUMPRODUCT(AJ19:AL19,Z19:AB19)/AM19,0) -> 0 | AE19: =IFERROR(AJ19/P19,0) -> 0 | AF19: =IFERROR(AK19/Q19,0) -> 0 | AG19: =W19*AB19 -> 0 | AJ19: =SUMIFS('Working-T05-B1'!AI$8:AI$150,'Working-T05-B1'!$C$8:$C$150,$D19) -> 0 | AK19: =SUMIFS('Working-T05-B1'!AJ$8:AJ$150,'Working-T05-B1'!$C$8:$C$150,$D19) -> 0 | AL19: =R19*AG19 -> 0 | AM19: =SUM(AJ19:AL19) -> 0 | AO19: =IFERROR(SUM(AQ19:AR19)/SUM(P19:Q19),0) -> 0 | AQ19: =SUMIFS('Working-T05-B1'!AP$8:AP$150,'Working-T05-B1'!$C$8:$C$150,$D19) -> 0 | AR19: =SUMIFS('Working-T05-B1'!AQ$8:AQ$150,'Working-T05-B1'!$C$8:$C$150,$D19) -> 0 | AS19: =AO19*R19 -> 0 | AT19: =SUM(AQ19:AS19) -> 0 | AV19: =IFERROR(BA19/S19,0) -> 0 | AX19: =SUMIFS('Working-T05-B1'!AW$8:AW$150,'Working-T05-B1'!$C$8:$C$150,$D19) -> 0 | AY19: =SUMIFS('Working-T05-B1'!AX$8:AX$150,'Working-T05-B1'!$C$8:$C$150,$D19) -> 0 | BA19: =SUM(AX19:AZ19) -> 0 | BC19: =_xlfn.XLOOKUP($G19,'GIÁ XUẤT KHO'!$A$4:$A$97,'GIÁ XUẤT KHO'!$AW$4:$AW$97)*P19 -> 0 | BD19: =_xlfn.XLOOKUP($G19,'GIÁ XUẤT KHO'!$A$4:$A$97,'GIÁ XUẤT KHO'!$AW$4:$AW$97)*Q19 -> 0 | BE19: =_xlfn.XLOOKUP($G19,'GIÁ XUẤT KHO'!$A$4:$A$97,'GIÁ XUẤT KHO'!$AW$4:$AW$97)*R19 -> 0 | BF19: =SUM(BC19:BE19) -> 0 | BH19: =AJ19-BC19 -> 0 | BI19: =AK19-BD19 -> 0 | BJ19: =AL19-BE19 -> 0 | BK19: =SUM(BH19:BJ19) -> 0 | BM19: =SUM(BN19:BV19) -> 0 | BN19: =SUMIFS('GIÁ XUẤT KHO'!AX$4:AX$97,'GIÁ XUẤT KHO'!$A$4:$A$97,$G19)*$S19 -> 0 | BO19: =SUMIFS('GIÁ XUẤT KHO'!AY$4:AY$97,'GIÁ XUẤT KHO'!$A$4:$A$97,$G19)*$S19 -> 0 | BP19: =SUMIFS('GIÁ XUẤT KHO'!AZ$4:AZ$97,'GIÁ XUẤT KHO'!$A$4:$A$97,$G19)*$S19 -> 0 | BQ19: =SUMIFS('GIÁ XUẤT KHO'!BA$4:BA$97,'GIÁ XUẤT KHO'!$A$4:$A$97,$G19)*$S19 -> 0 | BR19: =SUMIFS('GIÁ XUẤT KHO'!BB$4:BB$97,'GIÁ XUẤT KHO'!$A$4:$A$97,$G19)*$S19 -> 0 | BS19: =SUMIFS('GIÁ XUẤT KHO'!BC$4:BC$97,'GIÁ XUẤT KHO'!$A$4:$A$97,$G19)*$S19 -> 0 | BT19: =SUMIFS('GIÁ XUẤT KHO'!BD$4:BD$97,'GIÁ XUẤT KHO'!$A$4:$A$97,$G19)*$S19 -> 0 | BU19: =SUMIFS('GIÁ XUẤT KHO'!BE$4:BE$97,'GIÁ XUẤT KHO'!$A$4:$A$97,$G19)*$S19 -> 0 | BV19: =SUMIFS('GIÁ XUẤT KHO'!BF$4:BF$97,'GIÁ XUẤT KHO'!$A$4:$A$97,$G19)*$S19 -> 0 | BW19: =BM19-BF19 -> 0
... A23: =_xlfn.XLOOKUP($G23,MD_SKU[Mã SKU],MD_SKU[Link vào file BCQT]) -> Hạt rHDPE thổi | B23: TC-026 | C23: XK | D23: 200393 | 110000341 | E23: 200393 | F23: Orient Plastic | G23: 110000341 | H23: Hạt nhựa rHDB04B01 | K23: =SUMIFS('Working-T05-B1'!L$8:L$150,'Working-T05-B1'!$C$8:$C$150,$D23) -> 81000 | L23: {=SUMPRODUCT(Sales!$G$3:$H$100*(Sales!$B$3:$B$100=$D23))} -> 0 | M23: =K23-L23 -> 81000 | N23: =SUMIFS(Sales!$I$3:$I$100,Sales!$B$3:$B$100,$D23) -> 0 | P23: =SUMIFS('Working-T05-B1'!O$8:O$150,'Working-T05-B1'!$C$8:$C$150,$D23) -> 0 | Q23: =MAX(0,MIN(K23,L23+N23)-P23) -> 0 | R23: =MAX(0,L23+N23-SUM(P23:Q23)) -> 0 | S23: =SUM(P23:R23) -> 0 | T23: =S23-(L23+N23) -> 0 | U23: =IFERROR(AE23/Z23,0) -> 0 | V23: =IFERROR(AF23/AA23,0) -> 0 | W23: =IF(AND(R23>0,V23>0),V23,0) -> 0 | X23: =IFERROR(IF($C23="XK",$AM23/$S23/$AC23,$AM23/$S23),0) -> 0 | AA23: =IF($C23="NĐ",1,EXR_FC05) -> 26300 | AB23: =IF($C23="NĐ",1,EXR_FC05) -> 26300 | AC23: =IFERROR(SUMPRODUCT(AJ23:AL23,Z23:AB23)/AM23,0) -> 0 | AE23: =IFERROR(AJ23/P23,0) -> 0 | AF23: =IFERROR(AK23/Q23,0) -> 0 | AG23: =W23*AB23 -> 0 | AJ23: =SUMIFS('Working-T05-B1'!AI$8:AI$150,'Working-T05-B1'!$C$8:$C$150,$D23) -> 0 | AK23: =SUMIFS('Working-T05-B1'!AJ$8:AJ$150,'Working-T05-B1'!$C$8:$C$150,$D23) -> 0 | AL23: =R23*AG23 -> 0 | AM23: =SUM(AJ23:AL23) -> 0 | AO23: =IFERROR(SUM(AQ23:AR23)/SUM(P23:Q23),0) -> 0 | AQ23: =SUMIFS('Working-T05-B1'!AP$8:AP$150,'Working-T05-B1'!$C$8:$C$150,$D23) -> 0 | AR23: =SUMIFS('Working-T05-B1'!AQ$8:AQ$150,'Working-T05-B1'!$C$8:$C$150,$D23) -> 0 | AS23: =AO23*R23 -> 0 | AT23: =SUM(AQ23:AS23) -> 0 | AV23: =IFERROR(BA23/S23,0) -> 0 | AX23: =SUMIFS('Working-T05-B1'!AW$8:AW$150,'Working-T05-B1'!$C$8:$C$150,$D23) -> 0 | AY23: =SUMIFS('Working-T05-B1'!AX$8:AX$150,'Working-T05-B1'!$C$8:$C$150,$D23) -> 0 | BA23: =SUM(AX23:AZ23) -> 0 | BC23: =_xlfn.XLOOKUP($G23,'GIÁ XUẤT KHO'!$A$4:$A$97,'GIÁ XUẤT KHO'!$AW$4:$AW$97)*P23 -> 0 | BD23: =_xlfn.XLOOKUP($G23,'GIÁ XUẤT KHO'!$A$4:$A$97,'GIÁ XUẤT KHO'!$AW$4:$AW$97)*Q23 -> 0 | BE23: =_xlfn.XLOOKUP($G23,'GIÁ XUẤT KHO'!$A$4:$A$97,'GIÁ XUẤT KHO'!$AW$4:$AW$97)*R23 -> 0 | BF23: =SUM(BC23:BE23) -> 0 | BH23: =AJ23-BC23 -> 0 | BI23: =AK23-BD23 -> 0 | BJ23: =AL23-BE23 -> 0 | BK23: =SUM(BH23:BJ23) -> 0 | BM23: =SUM(BN23:BV23) -> 0 | BN23: =SUMIFS('GIÁ XUẤT KHO'!AX$4:AX$97,'GIÁ XUẤT KHO'!$A$4:$A$97,$G23)*$S23 -> 0 | BO23: =SUMIFS('GIÁ XUẤT KHO'!AY$4:AY$97,'GIÁ XUẤT KHO'!$A$4:$A$97,$G23)*$S23 -> 0 | BP23: =SUMIFS('GIÁ XUẤT KHO'!AZ$4:AZ$97,'GIÁ XUẤT KHO'!$A$4:$A$97,$G23)*$S23 -> 0 | BQ23: =SUMIFS('GIÁ XUẤT KHO'!BA$4:BA$97,'GIÁ XUẤT KHO'!$A$4:$A$97,$G23)*$S23 -> 0 | BR23: =SUMIFS('GIÁ XUẤT KHO'!BB$4:BB$97,'GIÁ XUẤT KHO'!$A$4:$A$97,$G23)*$S23 -> 0 | BS23: =SUMIFS('GIÁ XUẤT KHO'!BC$4:BC$97,'GIÁ XUẤT KHO'!$A$4:$A$97,$G23)*$S23 -> 0 | BT23: =SUMIFS('GIÁ XUẤT KHO'!BD$4:BD$97,'GIÁ XUẤT KHO'!$A$4:$A$97,$G23)*$S23 -> 0 | BU23: =SUMIFS('GIÁ XUẤT KHO'!BE$4:BE$97,'GIÁ XUẤT KHO'!$A$4:$A$97,$G23)*$S23 -> 0 | BV23: =SUMIFS('GIÁ XUẤT KHO'!BF$4:BF$97,'GIÁ XUẤT KHO'!$A$4:$A$97,$G23)*$S23 -> 0 | BW23: =BM23-BF23 -> 0
A24: =_xlfn.XLOOKUP($G24,MD_SKU[Mã SKU],MD_SKU[Link vào file BCQT]) -> Hạt rPET | B24: TC-026 | C24: NĐ | D24: 105271 | 110000332 | E24: 105271 | F24: Suntory- Ngọc Nghĩa Tây Ninh | G24: 110000332 | H24: Hạt nhựa rPET iSS01084G | K24: =SUMIFS('Working-T05-B1'!L$8:L$150,'Working-T05-B1'!$C$8:$C$150,$D24) -> 88000 | L24: {=SUMPRODUCT(Sales!$G$3:$H$100*(Sales!$B$3:$B$100=$D24))} -> 0 | M24: =K24-L24 -> 88000 | N24: =SUMIFS(Sales!$I$3:$I$100,Sales!$B$3:$B$100,$D24) -> 88000 | P24: =SUMIFS('Working-T05-B1'!O$8:O$150,'Working-T05-B1'!$C$8:$C$150,$D24) -> 0 | Q24: =MAX(0,MIN(K24,L24+N24)-P24) -> 88000 | R24: =MAX(0,L24+N24-SUM(P24:Q24)) -> 0 | S24: =SUM(P24:R24) -> 88000 | T24: =S24-(L24+N24) -> 0 | U24: =IFERROR(AE24/Z24,0) -> 0 | V24: =IFERROR(AF24/AA24,0) -> 31844 | W24: =IF(AND(R24>0,V24>0),V24,0) -> 0 | X24: =IFERROR(IF($C24="XK",$AM24/$S24/$AC24,$AM24/$S24),0) -> 31844 | AA24: =IF($C24="NĐ",1,EXR_FC05) -> 1 | AB24: =IF($C24="NĐ",1,EXR_FC05) -> 1 | AC24: =IFERROR(SUMPRODUCT(AJ24:AL24,Z24:AB24)/AM24,0) -> 1 | AE24: =IFERROR(AJ24/P24,0) -> 0 | AF24: =IFERROR(AK24/Q24,0) -> 31844 | AG24: =W24*AB24 -> 0 | AJ24: =SUMIFS('Working-T05-B1'!AI$8:AI$150,'Working-T05-B1'!$C$8:$C$150,$D24) -> 0 | AK24: =SUMIFS('Working-T05-B1'!AJ$8:AJ$150,'Working-T05-B1'!$C$8:$C$150,$D24) -> 2802272000 | AL24: =R24*AG24 -> 0 | AM24: =SUM(AJ24:AL24) -> 2802272000 | AO24: =IFERROR(SUM(AQ24:AR24)/SUM(P24:Q24),0) -> 263 | AQ24: =SUMIFS('Working-T05-B1'!AP$8:AP$150,'Working-T05-B1'!$C$8:$C$150,$D24) -> 0 | AR24: =SUMIFS('Working-T05-B1'!AQ$8:AQ$150,'Working-T05-B1'!$C$8:$C$150,$D24) -> 23144000 | AS24: =AO24*R24 -> 0 | AT24: =SUM(AQ24:AS24) -> 23144000 | AV24: =IFERROR(BA24/S24,0) -> 1910.64 | AX24: =SUMIFS('Working-T05-B1'!AW$8:AW$150,'Working-T05-B1'!$C$8:$C$150,$D24) -> 0 | AY24: =SUMIFS('Working-T05-B1'!AX$8:AX$150,'Working-T05-B1'!$C$8:$C$150,$D24) -> 168136320 | BA24: =SUM(AX24:AZ24) -> 168136320 | BB24: x | BC24: =_xlfn.XLOOKUP($G24,'GIÁ XUẤT KHO'!$A$4:$A$97,'GIÁ XUẤT KHO'!$AW$4:$AW$97)*P24 -> 0 | BD24: =_xlfn.XLOOKUP($G24,'GIÁ XUẤT KHO'!$A$4:$A$97,'GIÁ XUẤT KHO'!$AW$4:$AW$97)*Q24 -> 2.4655598e+09 | BE24: =_xlfn.XLOOKUP($G24,'GIÁ XUẤT KHO'!$A$4:$A$97,'GIÁ XUẤT KHO'!$AW$4:$AW$97)*R24 -> 0 | BF24: =SUM(BC24:BE24) -> 2.4655598e+09 | BH24: =AJ24-BC24 -> 0 | BI24: =AK24-BD24 -> 3.3671221e+08 | BJ24: =AL24-BE24 -> 0 | BK24: =SUM(BH24:BJ24) -> 3.3671221e+08 | BM24: =SUM(BN24:BV24) -> 2.4655598e+09 | BN24: =SUMIFS('GIÁ XUẤT KHO'!AX$4:AX$97,'GIÁ XUẤT KHO'!$A$4:$A$97,$G24)*$S24 -> 1.4575333e+09 | BO24: =SUMIFS('GIÁ XUẤT KHO'!AY$4:AY$97,'GIÁ XUẤT KHO'!$A$4:$A$97,$G24)*$S24 -> 24217604 | BP24: =SUMIFS('GIÁ XUẤT KHO'!AZ$4:AZ$97,'GIÁ XUẤT KHO'!$A$4:$A$97,$G24)*$S24 -> 9866.9956 | BQ24: =SUMIFS('GIÁ XUẤT KHO'!BA$4:BA$97,'GIÁ XUẤT KHO'!$A$4:$A$97,$G24)*$S24 -> 1.6083751e+08 | BR24: =SUMIFS('GIÁ XUẤT KHO'!BB$4:BB$97,'GIÁ XUẤT KHO'!$A$4:$A$97,$G24)*$S24 -> 19037093 | BS24: =SUMIFS('GIÁ XUẤT KHO'!BC$4:BC$97,'GIÁ XUẤT KHO'!$A$4:$A$97,$G24)*$S24 -> 1.1509655e+08 | BT24: =SUMIFS('GIÁ XUẤT KHO'!BD$4:BD$97,'GIÁ XUẤT KHO'!$A$4:$A$97,$G24)*$S24 -> 1.8546927e+08 | BU24: =SUMIFS('GIÁ XUẤT KHO'!BE$4:BE$97,'GIÁ XUẤT KHO'!$A$4:$A$97,$G24)*$S24 -> 44526341 | BV24: =SUMIFS('GIÁ XUẤT KHO'!BF$4:BF$97,'GIÁ XUẤT KHO'!$A$4:$A$97,$G24)*$S24 -> 4.5883224e+08 | BW24: =BM24-BF24 -> 0
A25: =_xlfn.XLOOKUP($G25,MD_SKU[Mã SKU],MD_SKU[Link vào file BCQT]) -> Vảy rPET | B25: TC-026 | C25: XK | D25: 200332 | 110000507 | E25: 200332 | F25: OUTEIRINHO | G25: 110000507 | H25: Vảy FPET201 | K25: =SUMIFS('Working-T05-B1'!L$8:L$150,'Working-T05-B1'!$C$8:$C$150,$D25) -> 770000 | L25: {=SUMPRODUCT(Sales!$G$3:$H$100*(Sales!$B$3:$B$100=$D25))} -> 0 | M25: =K25-L25 -> 770000 | N25: =SUMIFS(Sales!$I$3:$I$100,Sales!$B$3:$B$100,$D25) -> 770000 | P25: =SUMIFS('Working-T05-B1'!O$8:O$150,'Working-T05-B1'!$C$8:$C$150,$D25) -> 0 | Q25: =MAX(0,MIN(K25,L25+N25)-P25) -> 770000 | R25: =MAX(0,L25+N25-SUM(P25:Q25)) -> 0 | S25: =SUM(P25:R25) -> 770000 | T25: =S25-(L25+N25) -> 0 | U25: =IFERROR(AE25/Z25,0) -> 0 | V25: =IFERROR(AF25/AA25,0) -> 0.84 | W25: =IF(AND(R25>0,V25>0),V25,0) -> 0 | X25: =IFERROR(IF($C25="XK",$AM25/$S25/$AC25,$AM25/$S25),0) -> 0.84 | AA25: =IF($C25="NĐ",1,EXR_FC05) -> 26300 | AB25: =IF($C25="NĐ",1,EXR_FC05) -> 26300 | AC25: =IFERROR(SUMPRODUCT(AJ25:AL25,Z25:AB25)/AM25,0) -> 26300 | AE25: =IFERROR(AJ25/P25,0) -> 0 | AF25: =IFERROR(AK25/Q25,0) -> 22092 | AG25: =W25*AB25 -> 0 | AJ25: =SUMIFS('Working-T05-B1'!AI$8:AI$150,'Working-T05-B1'!$C$8:$C$150,$D25) -> 0 | AK25: =SUMIFS('Working-T05-B1'!AJ$8:AJ$150,'Working-T05-B1'!$C$8:$C$150,$D25) -> 17010840000 | AL25: =R25*AG25 -> 0 | AM25: =SUM(AJ25:AL25) -> 17010840000 | AO25: =IFERROR(SUM(AQ25:AR25)/SUM(P25:Q25),0) -> 526 | AQ25: =SUMIFS('Working-T05-B1'!AP$8:AP$150,'Working-T05-B1'!$C$8:$C$150,$D25) -> 0 | AR25: =SUMIFS('Working-T05-B1'!AQ$8:AQ$150,'Working-T05-B1'!$C$8:$C$150,$D25) -> 405020000 | AS25: =AO25*R25 -> 0 | AT25: =SUM(AQ25:AS25) -> 405020000 | AV25: =IFERROR(BA25/S25,0) -> 0 | AX25: =SUMIFS('Working-T05-B1'!AW$8:AW$150,'Working-T05-B1'!$C$8:$C$150,$D25) -> 0 | AY25: =SUMIFS('Working-T05-B1'!AX$8:AX$150,'Working-T05-B1'!$C$8:$C$150,$D25) -> 0 | BA25: =SUM(AX25:AZ25) -> 0 | BC25: =_xlfn.XLOOKUP($G25,'GIÁ XUẤT KHO'!$A$4:$A$97,'GIÁ XUẤT KHO'!$AW$4:$AW$97)*P25 -> 0 | BD25: =_xlfn.XLOOKUP($G25,'GIÁ XUẤT KHO'!$A$4:$A$97,'GIÁ XUẤT KHO'!$AW$4:$AW$97)*Q25 -> 1.9788494e+10 | BE25: =_xlfn.XLOOKUP($G25,'GIÁ XUẤT KHO'!$A$4:$A$97,'GIÁ XUẤT KHO'!$AW$4:$AW$97)*R25 -> 0 | BF25: =SUM(BC25:BE25) -> 1.9788494e+10 | BH25: =AJ25-BC25 -> 0 | BI25: =AK25-BD25 -> -2.777654e+09 | BJ25: =AL25-BE25 -> 0 | BK25: =SUM(BH25:BJ25) -> -2.777654e+09 | BM25: =SUM(BN25:BV25) -> 1.9788494e+10 | BN25: =SUMIFS('GIÁ XUẤT KHO'!AX$4:AX$97,'GIÁ XUẤT KHO'!$A$4:$A$97,$G25)*$S25 -> 1.7202388e+10 | BO25: =SUMIFS('GIÁ XUẤT KHO'!AY$4:AY$97,'GIÁ XUẤT KHO'!$A$4:$A$97,$G25)*$S25 -> 27108757 | BP25: =SUMIFS('GIÁ XUẤT KHO'!AZ$4:AZ$97,'GIÁ XUẤT KHO'!$A$4:$A$97,$G25)*$S25 -> 0 | BQ25: =SUMIFS('GIÁ XUẤT KHO'!BA$4:BA$97,'GIÁ XUẤT KHO'!$A$4:$A$97,$G25)*$S25 -> 1.2277351e+08 | BR25: =SUMIFS('GIÁ XUẤT KHO'!BB$4:BB$97,'GIÁ XUẤT KHO'!$A$4:$A$97,$G25)*$S25 -> 0 | BS25: =SUMIFS('GIÁ XUẤT KHO'!BC$4:BC$97,'GIÁ XUẤT KHO'!$A$4:$A$97,$G25)*$S25 -> 4.694981e+08 | BT25: =SUMIFS('GIÁ XUẤT KHO'!BD$4:BD$97,'GIÁ XUẤT KHO'!$A$4:$A$97,$G25)*$S25 -> 670236875 | BU25: =SUMIFS('GIÁ XUẤT KHO'!BE$4:BE$97,'GIÁ XUẤT KHO'!$A$4:$A$97,$G25)*$S25 -> 73897320 | BV25: =SUMIFS('GIÁ XUẤT KHO'!BF$4:BF$97,'GIÁ XUẤT KHO'!$A$4:$A$97,$G25)*$S25 -> 1.2225918e+09 | BW25: =BM25-BF25 -> 0
A26: =_xlfn.XLOOKUP($G26,MD_SKU[Mã SKU],MD_SKU[Link vào file BCQT]) -> Hạt rPET | B26: TC-026 | C26: XK | D26: 200330 | 110000355 | E26: 200330 | F26: Fega Polymers Member | G26: 110000355 | H26: Hạt nhựa rPET iSS01G 1 | K26: =SUMIFS('Working-T05-B1'!L$8:L$150,'Working-T05-B1'!$C$8:$C$150,$D26) -> 0 | L26: {=SUMPRODUCT(Sales!$G$3:$H$100*(Sales!$B$3:$B$100=$D26))} -> 0 | M26: =K26-L26 -> 0 | N26: =SUMIFS(Sales!$I$3:$I$100,Sales!$B$3:$B$100,$D26) -> 0 | P26: =SUMIFS('Working-T05-B1'!O$8:O$150,'Working-T05-B1'!$C$8:$C$150,$D26) -> 0 | Q26: =MAX(0,MIN(K26,L26+N26)-P26) -> 0 | R26: =MAX(0,L26+N26-SUM(P26:Q26)) -> 0 | S26: =SUM(P26:R26) -> 0 | T26: =S26-(L26+N26) -> 0 | U26: =IFERROR(AE26/Z26,0) -> 0 | V26: =IFERROR(AF26/AA26,0) -> 0 | W26: =IF(AND(R26>0,V26>0),V26,0) -> 0 | X26: =IFERROR(IF($C26="XK",$AM26/$S26/$AC26,$AM26/$S26),0) -> 0 | AA26: =IF($C26="NĐ",1,EXR_FC05) -> 26300 | AB26: =IF($C26="NĐ",1,EXR_FC05) -> 26300 | AC26: =IFERROR(SUMPRODUCT(AJ26:AL26,Z26:AB26)/AM26,0) -> 0 | AE26: =IFERROR(AJ26/P26,0) -> 0 | AF26: =IFERROR(AK26/Q26,0) -> 0 | AG26: =W26*AB26 -> 0 | AJ26: =SUMIFS('Working-T05-B1'!AI$8:AI$150,'Working-T05-B1'!$C$8:$C$150,$D26) -> 0 | AK26: =SUMIFS('Working-T05-B1'!AJ$8:AJ$150,'Working-T05-B1'!$C$8:$C$150,$D26) -> 0 | AL26: =R26*AG26 -> 0 | AM26: =SUM(AJ26:AL26) -> 0 | AO26: =IFERROR(SUM(AQ26:AR26)/SUM(P26:Q26),0) -> 0 | AQ26: =SUMIFS('Working-T05-B1'!AP$8:AP$150,'Working-T05-B1'!$C$8:$C$150,$D26) -> 0 | AR26: =SUMIFS('Working-T05-B1'!AQ$8:AQ$150,'Working-T05-B1'!$C$8:$C$150,$D26) -> 0 | AS26: =AO26*R26 -> 0 | AT26: =SUM(AQ26:AS26) -> 0 | AV26: =IFERROR(BA26/S26,0) -> 0 | AX26: =SUMIFS('Working-T05-B1'!AW$8:AW$150,'Working-T05-B1'!$C$8:$C$150,$D26) -> 0 | AY26: =SUMIFS('Working-T05-B1'!AX$8:AX$150,'Working-T05-B1'!$C$8:$C$150,$D26) -> 0 | BA26: =SUM(AX26:AZ26) -> 0 | BC26: =_xlfn.XLOOKUP($G26,'GIÁ XUẤT KHO'!$A$4:$A$97,'GIÁ XUẤT KHO'!$AW$4:$AW$97)*P26 -> 0 | BD26: =_xlfn.XLOOKUP($G26,'GIÁ XUẤT KHO'!$A$4:$A$97,'GIÁ XUẤT KHO'!$AW$4:$AW$97)*Q26 -> 0 | BE26: =_xlfn.XLOOKUP($G26,'GIÁ XUẤT KHO'!$A$4:$A$97,'GIÁ XUẤT KHO'!$AW$4:$AW$97)*R26 -> 0 | BF26: =SUM(BC26:BE26) -> 0 | BH26: =AJ26-BC26 -> 0 | BI26: =AK26-BD26 -> 0 | BJ26: =AL26-BE26 -> 0 | BK26: =SUM(BH26:BJ26) -> 0 | BM26: =SUM(BN26:BV26) -> 0 | BN26: =SUMIFS('GIÁ XUẤT KHO'!AX$4:AX$97,'GIÁ XUẤT KHO'!$A$4:$A$97,$G26)*$S26 -> 0 | BO26: =SUMIFS('GIÁ XUẤT KHO'!AY$4:AY$97,'GIÁ XUẤT KHO'!$A$4:$A$97,$G26)*$S26 -> 0 | BP26: =SUMIFS('GIÁ XUẤT KHO'!AZ$4:AZ$97,'GIÁ XUẤT KHO'!$A$4:$A$97,$G26)*$S26 -> 0 | BQ26: =SUMIFS('GIÁ XUẤT KHO'!BA$4:BA$97,'GIÁ XUẤT KHO'!$A$4:$A$97,$G26)*$S26 -> 0 | BR26: =SUMIFS('GIÁ XUẤT KHO'!BB$4:BB$97,'GIÁ XUẤT KHO'!$A$4:$A$97,$G26)*$S26 -> 0 | BS26: =SUMIFS('GIÁ XUẤT KHO'!BC$4:BC$97,'GIÁ XUẤT KHO'!$A$4:$A$97,$G26)*$S26 -> 0 | BT26: =SUMIFS('GIÁ XUẤT KHO'!BD$4:BD$97,'GIÁ XUẤT KHO'!$A$4:$A$97,$G26)*$S26 -> 0 | BU26: =SUMIFS('GIÁ XUẤT KHO'!BE$4:BE$97,'GIÁ XUẤT KHO'!$A$4:$A$97,$G26)*$S26 -> 0 | BV26: =SUMIFS('GIÁ XUẤT KHO'!BF$4:BF$97,'GIÁ XUẤT KHO'!$A$4:$A$97,$G26)*$S26 -> 0 | BW26: =BM26-BF26 -> 0
A27: =_xlfn.XLOOKUP($G27,MD_SKU[Mã SKU],MD_SKU[Link vào file BCQT]) -> Phó sản | B27: TC-026 | C27: NĐ | D27: 105324 | 160012951 | E27: 105324 | F27: NHỰA TRƯỜNG AN | G27: 160012951 | H27: Vảy HD Ép Hỗn Hợp SSR | K27: =SUMIFS('Working-T05-B1'!L$8:L$150,'Working-T05-B1'!$C$8:$C$150,$D27) -> 11266 | L27: {=SUMPRODUCT(Sales!$G$3:$H$100*(Sales!$B$3:$B$100=$D27))} -> 0 | M27: =K27-L27 -> 11266 | N27: =SUMIFS(Sales!$I$3:$I$100,Sales!$B$3:$B$100,$D27) -> 0 | P27: =SUMIFS('Working-T05-B1'!O$8:O$150,'Working-T05-B1'!$C$8:$C$150,$D27) -> 0 | Q27: =MAX(0,MIN(K27,L27+N27)-P27) -> 0 | R27: =MAX(0,L27+N27-SUM(P27:Q27)) -> 0 | S27: =SUM(P27:R27) -> 0 | T27: =S27-(L27+N27) -> 0 | U27: =IFERROR(AE27/Z27,0) -> 0 | V27: =IFERROR(AF27/AA27,0) -> 0 | W27: =IF(AND(R27>0,V27>0),V27,0) -> 0 | X27: =IFERROR(IF($C27="XK",$AM27/$S27/$AC27,$AM27/$S27),0) -> 0 | AA27: =IF($C27="NĐ",1,EXR_FC05) -> 1 | AB27: =IF($C27="NĐ",1,EXR_FC05) -> 1 | AC27: =IFERROR(SUMPRODUCT(AJ27:AL27,Z27:AB27)/AM27,0) -> 0 | AE27: =IFERROR(AJ27/P27,0) -> 0 | AF27: =IFERROR(AK27/Q27,0) -> 0 | AG27: =W27*AB27 -> 0 | AJ27: =SUMIFS('Working-T05-B1'!AI$8:AI$150,'Working-T05-B1'!$C$8:$C$150,$D27) -> 0 | AK27: =SUMIFS('Working-T05-B1'!AJ$8:AJ$150,'Working-T05-B1'!$C$8:$C$150,$D27) -> 0 | AL27: =R27*AG27 -> 0 | AM27: =SUM(AJ27:AL27) -> 0 | AO27: =IFERROR(SUM(AQ27:AR27)/SUM(P27:Q27),0) -> 0 | AQ27: =SUMIFS('Working-T05-B1'!AP$8:AP$150,'Working-T05-B1'!$C$8:$C$150,$D27) -> 0 | AR27: =SUMIFS('Working-T05-B1'!AQ$8:AQ$150,'Working-T05-B1'!$C$8:$C$150,$D27) -> 0 | AS27: =AO27*R27 -> 0 | AT27: =SUM(AQ27:AS27) -> 0 | AV27: =IFERROR(BA27/S27,0) -> 0 | AX27: =SUMIFS('Working-T05-B1'!AW$8:AW$150,'Working-T05-B1'!$C$8:$C$150,$D27) -> 0 | AY27: =SUMIFS('Working-T05-B1'!AX$8:AX$150,'Working-T05-B1'!$C$8:$C$150,$D27) -> 0 | BA27: =SUM(AX27:AZ27) -> 0 | BC27: =_xlfn.XLOOKUP($G27,'GIÁ XUẤT KHO'!$A$4:$A$97,'GIÁ XUẤT KHO'!$AW$4:$AW$97)*P27 -> 0 | BD27: =_xlfn.XLOOKUP($G27,'GIÁ XUẤT KHO'!$A$4:$A$97,'GIÁ XUẤT KHO'!$AW$4:$AW$97)*Q27 -> 0 | BE27: =_xlfn.XLOOKUP($G27,'GIÁ XUẤT KHO'!$A$4:$A$97,'GIÁ XUẤT KHO'!$AW$4:$AW$97)*R27 -> 0 | BF27: =SUM(BC27:BE27) -> 0 | BH27: =AJ27-BC27 -> 0 | BI27: =AK27-BD27 -> 0 | BJ27: =AL27-BE27 -> 0 | BK27: =SUM(BH27:BJ27) -> 0 | BM27: =SUM(BN27:BV27) -> 0 | BN27: =SUMIFS('GIÁ XUẤT KHO'!AX$4:AX$97,'GIÁ XUẤT KHO'!$A$4:$A$97,$G27)*$S27 -> 0 | BO27: =SUMIFS('GIÁ XUẤT KHO'!AY$4:AY$97,'GIÁ XUẤT KHO'!$A$4:$A$97,$G27)*$S27 -> 0 | BP27: =SUMIFS('GIÁ XUẤT KHO'!AZ$4:AZ$97,'GIÁ XUẤT KHO'!$A$4:$A$97,$G27)*$S27 -> 0 | BQ27: =SUMIFS('GIÁ XUẤT KHO'!BA$4:BA$97,'GIÁ XUẤT KHO'!$A$4:$A$97,$G27)*$S27 -> 0 | BR27: =SUMIFS('GIÁ XUẤT KHO'!BB$4:BB$97,'GIÁ XUẤT KHO'!$A$4:$A$97,$G27)*$S27 -> 0 | BS27: =SUMIFS('GIÁ XUẤT KHO'!BC$4:BC$97,'GIÁ XUẤT KHO'!$A$4:$A$97,$G27)*$S27 -> 0 | BT27: =SUMIFS('GIÁ XUẤT KHO'!BD$4:BD$97,'GIÁ XUẤT KHO'!$A$4:$A$97,$G27)*$S27 -> 0 | BU27: =SUMIFS('GIÁ XUẤT KHO'!BE$4:BE$97,'GIÁ XUẤT KHO'!$A$4:$A$97,$G27)*$S27 -> 0 | BV27: =SUMIFS('GIÁ XUẤT KHO'!BF$4:BF$97,'GIÁ XUẤT KHO'!$A$4:$A$97,$G27)*$S27 -> 0 | BW27: =BM27-BF27 -> 0
A28: =_xlfn.XLOOKUP($G28,MD_SKU[Mã SKU],MD_SKU[Link vào file BCQT]) -> Phó sản | B28: TC-026 | C28: NĐ | D28: 105324 | 160012611 | E28: 105324 | F28: NHỰA TRƯỜNG AN | G28: 160012611 | H28: Vảy HD Ép Hỗn Hợp ST | K28: =SUMIFS('Working-T05-B1'!L$8:L$150,'Working-T05-B1'!$C$8:$C$150,$D28) -> 25000 | L28: {=SUMPRODUCT(Sales!$G$3:$H$100*(Sales!$B$3:$B$100=$D28))} -> 0 | M28: =K28-L28 -> 25000 | N28: =SUMIFS(Sales!$I$3:$I$100,Sales!$B$3:$B$100,$D28) -> 0 | P28: =SUMIFS('Working-T05-B1'!O$8:O$150,'Working-T05-B1'!$C$8:$C$150,$D28) -> 0 | Q28: =MAX(0,MIN(K28,L28+N28)-P28) -> 0 | R28: =MAX(0,L28+N28-SUM(P28:Q28)) -> 0 | S28: =SUM(P28:R28) -> 0 | T28: =S28-(L28+N28) -> 0 | U28: =IFERROR(AE28/Z28,0) -> 0 | V28: =IFERROR(AF28/AA28,0) -> 0 | W28: =IF(AND(R28>0,V28>0),V28,0) -> 0 | X28: =IFERROR(IF($C28="XK",$AM28/$S28/$AC28,$AM28/$S28),0) -> 0 | AA28: =IF($C28="NĐ",1,EXR_FC05) -> 1 | AB28: =IF($C28="NĐ",1,EXR_FC05) -> 1 | AC28: =IFERROR(SUMPRODUCT(AJ28:AL28,Z28:AB28)/AM28,0) -> 0 | AE28: =IFERROR(AJ28/P28,0) -> 0 | AF28: =IFERROR(AK28/Q28,0) -> 0 | AG28: =W28*AB28 -> 0 | AJ28: =SUMIFS('Working-T05-B1'!AI$8:AI$150,'Working-T05-B1'!$C$8:$C$150,$D28) -> 0 | AK28: =SUMIFS('Working-T05-B1'!AJ$8:AJ$150,'Working-T05-B1'!$C$8:$C$150,$D28) -> 0 | AL28: =R28*AG28 -> 0 | AM28: =SUM(AJ28:AL28) -> 0 | AO28: =IFERROR(SUM(AQ28:AR28)/SUM(P28:Q28),0) -> 0 | AQ28: =SUMIFS('Working-T05-B1'!AP$8:AP$150,'Working-T05-B1'!$C$8:$C$150,$D28) -> 0 | AR28: =SUMIFS('Working-T05-B1'!AQ$8:AQ$150,'Working-T05-B1'!$C$8:$C$150,$D28) -> 0 | AS28: =AO28*R28 -> 0 | AT28: =SUM(AQ28:AS28) -> 0 | AV28: =IFERROR(BA28/S28,0) -> 0 | AX28: =SUMIFS('Working-T05-B1'!AW$8:AW$150,'Working-T05-B1'!$C$8:$C$150,$D28) -> 0 | AY28: =SUMIFS('Working-T05-B1'!AX$8:AX$150,'Working-T05-B1'!$C$8:$C$150,$D28) -> 0 | BA28: =SUM(AX28:AZ28) -> 0 | BC28: =_xlfn.XLOOKUP($G28,'GIÁ XUẤT KHO'!$A$4:$A$97,'GIÁ XUẤT KHO'!$AW$4:$AW$97)*P28 -> 0 | BD28: =_xlfn.XLOOKUP($G28,'GIÁ XUẤT KHO'!$A$4:$A$97,'GIÁ XUẤT KHO'!$AW$4:$AW$97)*Q28 -> 0 | BE28: =_xlfn.XLOOKUP($G28,'GIÁ XUẤT KHO'!$A$4:$A$97,'GIÁ XUẤT KHO'!$AW$4:$AW$97)*R28 -> 0 | BF28: =SUM(BC28:BE28) -> 0 | BH28: =AJ28-BC28 -> 0 | BI28: =AK28-BD28 -> 0 | BJ28: =AL28-BE28 -> 0 | BK28: =SUM(BH28:BJ28) -> 0 | BM28: =SUM(BN28:BV28) -> 0 | BN28: =SUMIFS('GIÁ XUẤT KHO'!AX$4:AX$97,'GIÁ XUẤT KHO'!$A$4:$A$97,$G28)*$S28 -> 0 | BO28: =SUMIFS('GIÁ XUẤT KHO'!AY$4:AY$97,'GIÁ XUẤT KHO'!$A$4:$A$97,$G28)*$S28 -> 0 | BP28: =SUMIFS('GIÁ XUẤT KHO'!AZ$4:AZ$97,'GIÁ XUẤT KHO'!$A$4:$A$97,$G28)*$S28 -> 0 | BQ28: =SUMIFS('GIÁ XUẤT KHO'!BA$4:BA$97,'GIÁ XUẤT KHO'!$A$4:$A$97,$G28)*$S28 -> 0 | BR28: =SUMIFS('GIÁ XUẤT KHO'!BB$4:BB$97,'GIÁ XUẤT KHO'!$A$4:$A$97,$G28)*$S28 -> 0 | BS28: =SUMIFS('GIÁ XUẤT KHO'!BC$4:BC$97,'GIÁ XUẤT KHO'!$A$4:$A$97,$G28)*$S28 -> 0 | BT28: =SUMIFS('GIÁ XUẤT KHO'!BD$4:BD$97,'GIÁ XUẤT KHO'!$A$4:$A$97,$G28)*$S28 -> 0 | BU28: =SUMIFS('GIÁ XUẤT KHO'!BE$4:BE$97,'GIÁ XUẤT KHO'!$A$4:$A$97,$G28)*$S28 -> 0 | BV28: =SUMIFS('GIÁ XUẤT KHO'!BF$4:BF$97,'GIÁ XUẤT KHO'!$A$4:$A$97,$G28)*$S28 -> 0 | BW28: =BM28-BF28 -> 0
A29: =_xlfn.XLOOKUP($G29,MD_SKU[Mã SKU],MD_SKU[Link vào file BCQT]) -> Hạt rHDPE thổi | B29: TC-026 | C29: NĐ | D29: 1005 | 110000425 | E29: 1005 | F29: Duy Tân Long An | G29: 110000425 | H29: Hạt Nhựa HCBF-Whi-U | K29: =SUMIFS('Working-T05-B1'!L$8:L$150,'Working-T05-B1'!$C$8:$C$150,$D29) -> 17875 | L29: {=SUMPRODUCT(Sales!$G$3:$H$100*(Sales!$B$3:$B$100=$D29))} -> 0 | M29: =K29-L29 -> 17875 | N29: =SUMIFS(Sales!$I$3:$I$100,Sales!$B$3:$B$100,$D29) -> 0 | P29: =SUMIFS('Working-T05-B1'!O$8:O$150,'Working-T05-B1'!$C$8:$C$150,$D29) -> 0 | Q29: =MAX(0,MIN(K29,L29+N29)-P29) -> 0 | R29: =MAX(0,L29+N29-SUM(P29:Q29)) -> 0 | S29: =SUM(P29:R29) -> 0 | T29: =S29-(L29+N29) -> 0 | U29: =IFERROR(AE29/Z29,0) -> 0 | V29: =IFERROR(AF29/AA29,0) -> 0 | W29: =IF(AND(R29>0,V29>0),V29,0) -> 0 | X29: =IFERROR(IF($C29="XK",$AM29/$S29/$AC29,$AM29/$S29),0) -> 0 | AA29: =IF($C29="NĐ",1,EXR_FC05) -> 1 | AB29: =IF($C29="NĐ",1,EXR_FC05) -> 1 | AC29: =IFERROR(SUMPRODUCT(AJ29:AL29,Z29:AB29)/AM29,0) -> 0 | AE29: =IFERROR(AJ29/P29,0) -> 0 | AF29: =IFERROR(AK29/Q29,0) -> 0 | AG29: =W29*AB29 -> 0 | AJ29: =SUMIFS('Working-T05-B1'!AI$8:AI$150,'Working-T05-B1'!$C$8:$C$150,$D29) -> 0 | AK29: =SUMIFS('Working-T05-B1'!AJ$8:AJ$150,'Working-T05-B1'!$C$8:$C$150,$D29) -> 0 | AL29: =R29*AG29 -> 0 | AM29: =SUM(AJ29:AL29) -> 0 | AO29: =IFERROR(SUM(AQ29:AR29)/SUM(P29:Q29),0) -> 0 | AQ29: =SUMIFS('Working-T05-B1'!AP$8:AP$150,'Working-T05-B1'!$C$8:$C$150,$D29) -> 0 | AR29: =SUMIFS('Working-T05-B1'!AQ$8:AQ$150,'Working-T05-B1'!$C$8:$C$150,$D29) -> 0 | AS29: =AO29*R29 -> 0 | AT29: =SUM(AQ29:AS29) -> 0 | AV29: =IFERROR(BA29/S29,0) -> 0 | AX29: =SUMIFS('Working-T05-B1'!AW$8:AW$150,'Working-T05-B1'!$C$8:$C$150,$D29) -> 0 | AY29: =SUMIFS('Working-T05-B1'!AX$8:AX$150,'Working-T05-B1'!$C$8:$C$150,$D29) -> 0 | BA29: =SUM(AX29:AZ29) -> 0 | BC29: =_xlfn.XLOOKUP($G29,'GIÁ XUẤT KHO'!$A$4:$A$97,'GIÁ XUẤT KHO'!$AW$4:$AW$97)*P29 -> 0 | BD29: =_xlfn.XLOOKUP($G29,'GIÁ XUẤT KHO'!$A$4:$A$97,'GIÁ XUẤT KHO'!$AW$4:$AW$97)*Q29 -> 0 | BE29: =_xlfn.XLOOKUP($G29,'GIÁ XUẤT KHO'!$A$4:$A$97,'GIÁ XUẤT KHO'!$AW$4:$AW$97)*R29 -> 0 | BF29: =SUM(BC29:BE29) -> 0 | BH29: =AJ29-BC29 -> 0 | BI29: =AK29-BD29 -> 0 | BJ29: =AL29-BE29 -> 0 | BK29: =SUM(BH29:BJ29) -> 0 | BM29: =SUM(BN29:BV29) -> 0 | BN29: =SUMIFS('GIÁ XUẤT KHO'!AX$4:AX$97,'GIÁ XUẤT KHO'!$A$4:$A$97,$G29)*$S29 -> 0 | BO29: =SUMIFS('GIÁ XUẤT KHO'!AY$4:AY$97,'GIÁ XUẤT KHO'!$A$4:$A$97,$G29)*$S29 -> 0 | BP29: =SUMIFS('GIÁ XUẤT KHO'!AZ$4:AZ$97,'GIÁ XUẤT KHO'!$A$4:$A$97,$G29)*$S29 -> 0 | BQ29: =SUMIFS('GIÁ XUẤT KHO'!BA$4:BA$97,'GIÁ XUẤT KHO'!$A$4:$A$97,$G29)*$S29 -> 0 | BR29: =SUMIFS('GIÁ XUẤT KHO'!BB$4:BB$97,'GIÁ XUẤT KHO'!$A$4:$A$97,$G29)*$S29 -> 0 | BS29: =SUMIFS('GIÁ XUẤT KHO'!BC$4:BC$97,'GIÁ XUẤT KHO'!$A$4:$A$97,$G29)*$S29 -> 0 | BT29: =SUMIFS('GIÁ XUẤT KHO'!BD$4:BD$97,'GIÁ XUẤT KHO'!$A$4:$A$97,$G29)*$S29 -> 0 | BU29: =SUMIFS('GIÁ XUẤT KHO'!BE$4:BE$97,'GIÁ XUẤT KHO'!$A$4:$A$97,$G29)*$S29 -> 0 | BV29: =SUMIFS('GIÁ XUẤT KHO'!BF$4:BF$97,'GIÁ XUẤT KHO'!$A$4:$A$97,$G29)*$S29 -> 0 | BW29: =BM29-BF29 -> 0
A30: =_xlfn.XLOOKUP($G30,MD_SKU[Mã SKU],MD_SKU[Link vào file BCQT]) -> Hạt rHDPE ép | B30: TC-026 | C30: NĐ | D30: 105263 | 110000361 | E30: 105263 | F30: Unilever Duy Tân | G30: 110000361 | H30: Hạt nhựa rHDI3R01 | K30: =SUMIFS('Working-T05-B1'!L$8:L$150,'Working-T05-B1'!$C$8:$C$150,$D30) -> 22000 | L30: {=SUMPRODUCT(Sales!$G$3:$H$100*(Sales!$B$3:$B$100=$D30))} -> 0 | M30: =K30-L30 -> 22000 | N30: =SUMIFS(Sales!$I$3:$I$100,Sales!$B$3:$B$100,$D30) -> 0 | P30: =SUMIFS('Working-T05-B1'!O$8:O$150,'Working-T05-B1'!$C$8:$C$150,$D30) -> 0 | Q30: =MAX(0,MIN(K30,L30+N30)-P30) -> 0 | R30: =MAX(0,L30+N30-SUM(P30:Q30)) -> 0 | S30: =SUM(P30:R30) -> 0 | T30: =S30-(L30+N30) -> 0 | U30: =IFERROR(AE30/Z30,0) -> 0 | V30: =IFERROR(AF30/AA30,0) -> 0 | W30: =IF(AND(R30>0,V30>0),V30,0) -> 0 | X30: =IFERROR(IF($C30="XK",$AM30/$S30/$AC30,$AM30/$S30),0) -> 0 | AA30: =IF($C30="NĐ",1,EXR_FC05) -> 1 | AB30: =IF($C30="NĐ",1,EXR_FC05) -> 1 | AC30: =IFERROR(SUMPRODUCT(AJ30:AL30,Z30:AB30)/AM30,0) -> 0 | AE30: =IFERROR(AJ30/P30,0) -> 0 | AF30: =IFERROR(AK30/Q30,0) -> 0 | AG30: =W30*AB30 -> 0 | AJ30: =SUMIFS('Working-T05-B1'!AI$8:AI$150,'Working-T05-B1'!$C$8:$C$150,$D30) -> 0 | AK30: =SUMIFS('Working-T05-B1'!AJ$8:AJ$150,'Working-T05-B1'!$C$8:$C$150,$D30) -> 0 | AL30: =R30*AG30 -> 0 | AM30: =SUM(AJ30:AL30) -> 0 | AO30: =IFERROR(SUM(AQ30:AR30)/SUM(P30:Q30),0) -> 0 | AQ30: =SUMIFS('Working-T05-B1'!AP$8:AP$150,'Working-T05-B1'!$C$8:$C$150,$D30) -> 0 | AR30: =SUMIFS('Working-T05-B1'!AQ$8:AQ$150,'Working-T05-B1'!$C$8:$C$150,$D30) -> 0 | AS30: =AO30*R30 -> 0 | AT30: =SUM(AQ30:AS30) -> 0 | AV30: =IFERROR(BA30/S30,0) -> 0 | AX30: =SUMIFS('Working-T05-B1'!AW$8:AW$150,'Working-T05-B1'!$C$8:$C$150,$D30) -> 0 | AY30: =SUMIFS('Working-T05-B1'!AX$8:AX$150,'Working-T05-B1'!$C$8:$C$150,$D30) -> 0 | BA30: =SUM(AX30:AZ30) -> 0 | BC30: =_xlfn.XLOOKUP($G30,'GIÁ XUẤT KHO'!$A$4:$A$97,'GIÁ XUẤT KHO'!$AW$4:$AW$97)*P30 -> 0 | BD30: =_xlfn.XLOOKUP($G30,'GIÁ XUẤT KHO'!$A$4:$A$97,'GIÁ XUẤT KHO'!$AW$4:$AW$97)*Q30 -> 0 | BE30: =_xlfn.XLOOKUP($G30,'GIÁ XUẤT KHO'!$A$4:$A$97,'GIÁ XUẤT KHO'!$AW$4:$AW$97)*R30 -> 0 | BF30: =SUM(BC30:BE30) -> 0 | BH30: =AJ30-BC30 -> 0 | BI30: =AK30-BD30 -> 0 | BJ30: =AL30-BE30 -> 0 | BK30: =SUM(BH30:BJ30) -> 0 | BM30: =SUM(BN30:BV30) -> 0 | BN30: =SUMIFS('GIÁ XUẤT KHO'!AX$4:AX$97,'GIÁ XUẤT KHO'!$A$4:$A$97,$G30)*$S30 -> 0 | BO30: =SUMIFS('GIÁ XUẤT KHO'!AY$4:AY$97,'GIÁ XUẤT KHO'!$A$4:$A$97,$G30)*$S30 -> 0 | BP30: =SUMIFS('GIÁ XUẤT KHO'!AZ$4:AZ$97,'GIÁ XUẤT KHO'!$A$4:$A$97,$G30)*$S30 -> 0 | BQ30: =SUMIFS('GIÁ XUẤT KHO'!BA$4:BA$97,'GIÁ XUẤT KHO'!$A$4:$A$97,$G30)*$S30 -> 0 | BR30: =SUMIFS('GIÁ XUẤT KHO'!BB$4:BB$97,'GIÁ XUẤT KHO'!$A$4:$A$97,$G30)*$S30 -> 0 | BS30: =SUMIFS('GIÁ XUẤT KHO'!BC$4:BC$97,'GIÁ XUẤT KHO'!$A$4:$A$97,$G30)*$S30 -> 0 | BT30: =SUMIFS('GIÁ XUẤT KHO'!BD$4:BD$97,'GIÁ XUẤT KHO'!$A$4:$A$97,$G30)*$S30 -> 0 | BU30: =SUMIFS('GIÁ XUẤT KHO'!BE$4:BE$97,'GIÁ XUẤT KHO'!$A$4:$A$97,$G30)*$S30 -> 0 | BV30: =SUMIFS('GIÁ XUẤT KHO'!BF$4:BF$97,'GIÁ XUẤT KHO'!$A$4:$A$97,$G30)*$S30 -> 0 | BW30: =BM30-BF30 -> 0
A31: =_xlfn.XLOOKUP($G31,MD_SKU[Mã SKU],MD_SKU[Link vào file BCQT]) -> Hạt rPET | B31: TC-026 | C31: NĐ | D31: 105354 | 110000354 | E31: 105354 | F31: UNILEVER - NNG-TN | G31: 110000354 | H31: Hạt nhựa rPET WSS01G 1 | K31: =SUMIFS('Working-T05-B1'!L$8:L$150,'Working-T05-B1'!$C$8:$C$150,$D31) -> 44000 | L31: {=SUMPRODUCT(Sales!$G$3:$H$100*(Sales!$B$3:$B$100=$D31))} -> 0 | M31: =K31-L31 -> 44000 | N31: =SUMIFS(Sales!$I$3:$I$100,Sales!$B$3:$B$100,$D31) -> 88000 | P31: =SUMIFS('Working-T05-B1'!O$8:O$150,'Working-T05-B1'!$C$8:$C$150,$D31) -> 0 | Q31: =MAX(0,MIN(K31,L31+N31)-P31) -> 44000 | R31: =MAX(0,L31+N31-SUM(P31:Q31)) -> 44000 | S31: =SUM(P31:R31) -> 88000 | T31: =S31-(L31+N31) -> 0 | U31: =IFERROR(AE31/Z31,0) -> 0 | V31: =IFERROR(AF31/AA31,0) -> 31679 | W31: =IF(AND(R31>0,V31>0),V31,0) -> 31679 | X31: =IFERROR(IF($C31="XK",$AM31/$S31/$AC31,$AM31/$S31),0) -> 31679 | AA31: =IF($C31="NĐ",1,EXR_FC05) -> 1 | AB31: =IF($C31="NĐ",1,EXR_FC05) -> 1 | AC31: =IFERROR(SUMPRODUCT(AJ31:AL31,Z31:AB31)/AM31,0) -> 1 | AE31: =IFERROR(AJ31/P31,0) -> 0 | AF31: =IFERROR(AK31/Q31,0) -> 31679 | AG31: =W31*AB31 -> 31679 | AJ31: =SUMIFS('Working-T05-B1'!AI$8:AI$150,'Working-T05-B1'!$C$8:$C$150,$D31) -> 0 | AK31: =SUMIFS('Working-T05-B1'!AJ$8:AJ$150,'Working-T05-B1'!$C$8:$C$150,$D31) -> 1393876000 | AL31: =R31*AG31 -> 1393876000 | AM31: =SUM(AJ31:AL31) -> 2787752000 | AO31: =IFERROR(SUM(AQ31:AR31)/SUM(P31:Q31),0) -> 165.16 | AQ31: =SUMIFS('Working-T05-B1'!AP$8:AP$150,'Working-T05-B1'!$C$8:$C$150,$D31) -> 0 | AR31: =SUMIFS('Working-T05-B1'!AQ$8:AQ$150,'Working-T05-B1'!$C$8:$C$150,$D31) -> 7267040.2 | AS31: =AO31*R31 -> 7267040.2 | AT31: =SUM(AQ31:AS31) -> 14534080 | AV31: =IFERROR(BA31/S31,0) -> 0 | AX31: =SUMIFS('Working-T05-B1'!AW$8:AW$150,'Working-T05-B1'!$C$8:$C$150,$D31) -> 0 | AY31: =SUMIFS('Working-T05-B1'!AX$8:AX$150,'Working-T05-B1'!$C$8:$C$150,$D31) -> 0 | BA31: =SUM(AX31:AZ31) -> 0 | BC31: =_xlfn.XLOOKUP($G31,'GIÁ XUẤT KHO'!$A$4:$A$97,'GIÁ XUẤT KHO'!$AW$4:$AW$97)*P31 -> 0 | BD31: =_xlfn.XLOOKUP($G31,'GIÁ XUẤT KHO'!$A$4:$A$97,'GIÁ XUẤT KHO'!$AW$4:$AW$97)*Q31 -> 1.097265e+09 | BE31: =_xlfn.XLOOKUP($G31,'GIÁ XUẤT KHO'!$A$4:$A$97,'GIÁ XUẤT KHO'!$AW$4:$AW$97)*R31 -> 1.097265e+09 | BF31: =SUM(BC31:BE31) -> 2.19453e+09 | BH31: =AJ31-BC31 -> 0 | BI31: =AK31-BD31 -> 2.9661099e+08 | BJ31: =AL31-BE31 -> 2.9661099e+08 | BK31: =SUM(BH31:BJ31) -> 5.9322198e+08 | BM31: =SUM(BN31:BV31) -> 2.19453e+09 | BN31: =SUMIFS('GIÁ XUẤT KHO'!AX$4:AX$97,'GIÁ XUẤT KHO'!$A$4:$A$97,$G31)*$S31 -> 1.5847209e+09 | BO31: =SUMIFS('GIÁ XUẤT KHO'!AY$4:AY$97,'GIÁ XUẤT KHO'!$A$4:$A$97,$G31)*$S31 -> 16096370 | BP31: =SUMIFS('GIÁ XUẤT KHO'!AZ$4:AZ$97,'GIÁ XUẤT KHO'!$A$4:$A$97,$G31)*$S31 -> 8468.5139 | BQ31: =SUMIFS('GIÁ XUẤT KHO'!BA$4:BA$97,'GIÁ XUẤT KHO'!$A$4:$A$97,$G31)*$S31 -> 1.1251246e+08 | BR31: =SUMIFS('GIÁ XUẤT KHO'!BB$4:BB$97,'GIÁ XUẤT KHO'!$A$4:$A$97,$G31)*$S31 -> 15451604 | BS31: =SUMIFS('GIÁ XUẤT KHO'!BC$4:BC$97,'GIÁ XUẤT KHO'!$A$4:$A$97,$G31)*$S31 -> 63477196 | BT31: =SUMIFS('GIÁ XUẤT KHO'!BD$4:BD$97,'GIÁ XUẤT KHO'!$A$4:$A$97,$G31)*$S31 -> 1.0210446e+08 | BU31: =SUMIFS('GIÁ XUẤT KHO'!BE$4:BE$97,'GIÁ XUẤT KHO'!$A$4:$A$97,$G31)*$S31 -> 27765119 | BV31: =SUMIFS('GIÁ XUẤT KHO'!BF$4:BF$97,'GIÁ XUẤT KHO'!$A$4:$A$97,$G31)*$S31 -> 2.7239348e+08 | BW31: =BM31-BF31 -> 0
A32: =_xlfn.XLOOKUP($G32,MD_SKU[Mã SKU],MD_SKU[Link vào file BCQT]) -> Phó sản | B32: TC-026 | C32: NĐ | D32: 105382 | 160012974 | E32: 105382 | F32: Văn Minh | G32: 160012974 | H32: Vảy HD Ép Hỗn Hợp Cuối Sau Sấy | K32: =SUMIFS('Working-T05-B1'!L$8:L$150,'Working-T05-B1'!$C$8:$C$150,$D32) -> 46997 | L32: {=SUMPRODUCT(Sales!$G$3:$H$100*(Sales!$B$3:$B$100=$D32))} -> 0 | M32: =K32-L32 -> 46997 | N32: =SUMIFS(Sales!$I$3:$I$100,Sales!$B$3:$B$100,$D32) -> 0 | P32: =SUMIFS('Working-T05-B1'!O$8:O$150,'Working-T05-B1'!$C$8:$C$150,$D32) -> 0 | Q32: =MAX(0,MIN(K32,L32+N32)-P32) -> 0 | R32: =MAX(0,L32+N32-SUM(P32:Q32)) -> 0 | S32: =SUM(P32:R32) -> 0 | T32: =S32-(L32+N32) -> 0 | U32: =IFERROR(AE32/Z32,0) -> 0 | V32: =IFERROR(AF32/AA32,0) -> 0 | W32: =IF(AND(R32>0,V32>0),V32,0) -> 0 | X32: =IFERROR(IF($C32="XK",$AM32/$S32/$AC32,$AM32/$S32),0) -> 0 | AA32: =IF($C32="NĐ",1,EXR_FC05) -> 1 | AB32: =IF($C32="NĐ",1,EXR_FC05) -> 1 | AC32: =IFERROR(SUMPRODUCT(AJ32:AL32,Z32:AB32)/AM32,0) -> 0 | AE32: =IFERROR(AJ32/P32,0) -> 0 | AF32: =IFERROR(AK32/Q32,0) -> 0 | AG32: =W32*AB32 -> 0 | AJ32: =SUMIFS('Working-T05-B1'!AI$8:AI$150,'Working-T05-B1'!$C$8:$C$150,$D32) -> 0 | AK32: =SUMIFS('Working-T05-B1'!AJ$8:AJ$150,'Working-T05-B1'!$C$8:$C$150,$D32) -> 0 | AL32: =R32*AG32 -> 0 | AM32: =SUM(AJ32:AL32) -> 0 | AO32: =IFERROR(SUM(AQ32:AR32)/SUM(P32:Q32),0) -> 0 | AQ32: =SUMIFS('Working-T05-B1'!AP$8:AP$150,'Working-T05-B1'!$C$8:$C$150,$D32) -> 0 | AR32: =SUMIFS('Working-T05-B1'!AQ$8:AQ$150,'Working-T05-B1'!$C$8:$C$150,$D32) -> 0 | AS32: =AO32*R32 -> 0 | AT32: =SUM(AQ32:AS32) -> 0 | AV32: =IFERROR(BA32/S32,0) -> 0 | AX32: =SUMIFS('Working-T05-B1'!AW$8:AW$150,'Working-T05-B1'!$C$8:$C$150,$D32) -> 0 | AY32: =SUMIFS('Working-T05-B1'!AX$8:AX$150,'Working-T05-B1'!$C$8:$C$150,$D32) -> 0 | BA32: =SUM(AX32:AZ32) -> 0 | BC32: =_xlfn.XLOOKUP($G32,'GIÁ XUẤT KHO'!$A$4:$A$97,'GIÁ XUẤT KHO'!$AW$4:$AW$97)*P32 -> 0 | BD32: =_xlfn.XLOOKUP($G32,'GIÁ XUẤT KHO'!$A$4:$A$97,'GIÁ XUẤT KHO'!$AW$4:$AW$97)*Q32 -> 0 | BE32: =_xlfn.XLOOKUP($G32,'GIÁ XUẤT KHO'!$A$4:$A$97,'GIÁ XUẤT KHO'!$AW$4:$AW$97)*R32 -> 0 | BF32: =SUM(BC32:BE32) -> 0 | BH32: =AJ32-BC32 -> 0 | BI32: =AK32-BD32 -> 0 | BJ32: =AL32-BE32 -> 0 | BK32: =SUM(BH32:BJ32) -> 0 | BM32: =SUM(BN32:BV32) -> 0 | BN32: =SUMIFS('GIÁ XUẤT KHO'!AX$4:AX$97,'GIÁ XUẤT KHO'!$A$4:$A$97,$G32)*$S32 -> 0 | BO32: =SUMIFS('GIÁ XUẤT KHO'!AY$4:AY$97,'GIÁ XUẤT KHO'!$A$4:$A$97,$G32)*$S32 -> 0 | BP32: =SUMIFS('GIÁ XUẤT KHO'!AZ$4:AZ$97,'GIÁ XUẤT KHO'!$A$4:$A$97,$G32)*$S32 -> 0 | BQ32: =SUMIFS('GIÁ XUẤT KHO'!BA$4:BA$97,'GIÁ XUẤT KHO'!$A$4:$A$97,$G32)*$S32 -> 0 | BR32: =SUMIFS('GIÁ XUẤT KHO'!BB$4:BB$97,'GIÁ XUẤT KHO'!$A$4:$A$97,$G32)*$S32 -> 0 | BS32: =SUMIFS('GIÁ XUẤT KHO'!BC$4:BC$97,'GIÁ XUẤT KHO'!$A$4:$A$97,$G32)*$S32 -> 0 | BT32: =SUMIFS('GIÁ XUẤT KHO'!BD$4:BD$97,'GIÁ XUẤT KHO'!$A$4:$A$97,$G32)*$S32 -> 0 | BU32: =SUMIFS('GIÁ XUẤT KHO'!BE$4:BE$97,'GIÁ XUẤT KHO'!$A$4:$A$97,$G32)*$S32 -> 0 | BV32: =SUMIFS('GIÁ XUẤT KHO'!BF$4:BF$97,'GIÁ XUẤT KHO'!$A$4:$A$97,$G32)*$S32 -> 0 | BW32: =BM32-BF32 -> 0
A33: =_xlfn.XLOOKUP($G33,MD_SKU[Mã SKU],MD_SKU[Link vào file BCQT]) -> Phó sản | B33: TC-026 | C33: NĐ | D33: 105382 | 160012951 | E33: 105382 | F33: Văn Minh | G33: 160012951 | H33: Vảy HD Ép Hỗn Hợp SSR | K33: =SUMIFS('Working-T05-B1'!L$8:L$150,'Working-T05-B1'!$C$8:$C$150,$D33) -> 6995 | L33: {=SUMPRODUCT(Sales!$G$3:$H$100*(Sales!$B$3:$B$100=$D33))} -> 0 | M33: =K33-L33 -> 6995 | N33: =SUMIFS(Sales!$I$3:$I$100,Sales!$B$3:$B$100,$D33) -> 0 | P33: =SUMIFS('Working-T05-B1'!O$8:O$150,'Working-T05-B1'!$C$8:$C$150,$D33) -> 0 | Q33: =MAX(0,MIN(K33,L33+N33)-P33) -> 0 | R33: =MAX(0,L33+N33-SUM(P33:Q33)) -> 0 | S33: =SUM(P33:R33) -> 0 | T33: =S33-(L33+N33) -> 0 | U33: =IFERROR(AE33/Z33,0) -> 0 | V33: =IFERROR(AF33/AA33,0) -> 0 | W33: =IF(AND(R33>0,V33>0),V33,0) -> 0 | X33: =IFERROR(IF($C33="XK",$AM33/$S33/$AC33,$AM33/$S33),0) -> 0 | AA33: =IF($C33="NĐ",1,EXR_FC05) -> 1 | AB33: =IF($C33="NĐ",1,EXR_FC05) -> 1 | AC33: =IFERROR(SUMPRODUCT(AJ33:AL33,Z33:AB33)/AM33,0) -> 0 | AE33: =IFERROR(AJ33/P33,0) -> 0 | AF33: =IFERROR(AK33/Q33,0) -> 0 | AG33: =W33*AB33 -> 0 | AJ33: =SUMIFS('Working-T05-B1'!AI$8:AI$150,'Working-T05-B1'!$C$8:$C$150,$D33) -> 0 | AK33: =SUMIFS('Working-T05-B1'!AJ$8:AJ$150,'Working-T05-B1'!$C$8:$C$150,$D33) -> 0 | AL33: =R33*AG33 -> 0 | AM33: =SUM(AJ33:AL33) -> 0 | AO33: =IFERROR(SUM(AQ33:AR33)/SUM(P33:Q33),0) -> 0 | AQ33: =SUMIFS('Working-T05-B1'!AP$8:AP$150,'Working-T05-B1'!$C$8:$C$150,$D33) -> 0 | AR33: =SUMIFS('Working-T05-B1'!AQ$8:AQ$150,'Working-T05-B1'!$C$8:$C$150,$D33) -> 0 | AS33: =AO33*R33 -> 0 | AT33: =SUM(AQ33:AS33) -> 0 | AV33: =IFERROR(BA33/S33,0) -> 0 | AX33: =SUMIFS('Working-T05-B1'!AW$8:AW$150,'Working-T05-B1'!$C$8:$C$150,$D33) -> 0 | AY33: =SUMIFS('Working-T05-B1'!AX$8:AX$150,'Working-T05-B1'!$C$8:$C$150,$D33) -> 0 | BA33: =SUM(AX33:AZ33) -> 0 | BC33: =_xlfn.XLOOKUP($G33,'GIÁ XUẤT KHO'!$A$4:$A$97,'GIÁ XUẤT KHO'!$AW$4:$AW$97)*P33 -> 0 | BD33: =_xlfn.XLOOKUP($G33,'GIÁ XUẤT KHO'!$A$4:$A$97,'GIÁ XUẤT KHO'!$AW$4:$AW$97)*Q33 -> 0 | BE33: =_xlfn.XLOOKUP($G33,'GIÁ XUẤT KHO'!$A$4:$A$97,'GIÁ XUẤT KHO'!$AW$4:$AW$97)*R33 -> 0 | BF33: =SUM(BC33:BE33) -> 0 | BH33: =AJ33-BC33 -> 0 | BI33: =AK33-BD33 -> 0 | BJ33: =AL33-BE33 -> 0 | BK33: =SUM(BH33:BJ33) -> 0 | BM33: =SUM(BN33:BV33) -> 0 | BN33: =SUMIFS('GIÁ XUẤT KHO'!AX$4:AX$97,'GIÁ XUẤT KHO'!$A$4:$A$97,$G33)*$S33 -> 0 | BO33: =SUMIFS('GIÁ XUẤT KHO'!AY$4:AY$97,'GIÁ XUẤT KHO'!$A$4:$A$97,$G33)*$S33 -> 0 | BP33: =SUMIFS('GIÁ XUẤT KHO'!AZ$4:AZ$97,'GIÁ XUẤT KHO'!$A$4:$A$97,$G33)*$S33 -> 0 | BQ33: =SUMIFS('GIÁ XUẤT KHO'!BA$4:BA$97,'GIÁ XUẤT KHO'!$A$4:$A$97,$G33)*$S33 -> 0 | BR33: =SUMIFS('GIÁ XUẤT KHO'!BB$4:BB$97,'GIÁ XUẤT KHO'!$A$4:$A$97,$G33)*$S33 -> 0 | BS33: =SUMIFS('GIÁ XUẤT KHO'!BC$4:BC$97,'GIÁ XUẤT KHO'!$A$4:$A$97,$G33)*$S33 -> 0 | BT33: =SUMIFS('GIÁ XUẤT KHO'!BD$4:BD$97,'GIÁ XUẤT KHO'!$A$4:$A$97,$G33)*$S33 -> 0 | BU33: =SUMIFS('GIÁ XUẤT KHO'!BE$4:BE$97,'GIÁ XUẤT KHO'!$A$4:$A$97,$G33)*$S33 -> 0 | BV33: =SUMIFS('GIÁ XUẤT KHO'!BF$4:BF$97,'GIÁ XUẤT KHO'!$A$4:$A$97,$G33)*$S33 -> 0 | BW33: =BM33-BF33 -> 0
A34: =_xlfn.XLOOKUP($G34,MD_SKU[Mã SKU],MD_SKU[Link vào file BCQT]) -> Hạt rHDPE thổi | B34: TC-026 | C34: NĐ | D34: 105424 | 110000374 | E34: 105424 | F34: HIỆP PHƯỚC THÀNH | G34: 110000374 | H34: Hạt Nhựa rHDB03N02 | K34: =SUMIFS('Working-T05-B1'!L$8:L$150,'Working-T05-B1'!$C$8:$C$150,$D34) -> 50 | L34: {=SUMPRODUCT(Sales!$G$3:$H$100*(Sales!$B$3:$B$100=$D34))} -> 0 | M34: =K34-L34 -> 50 | N34: =SUMIFS(Sales!$I$3:$I$100,Sales!$B$3:$B$100,$D34) -> 0 | P34: =SUMIFS('Working-T05-B1'!O$8:O$150,'Working-T05-B1'!$C$8:$C$150,$D34) -> 0 | Q34: =MAX(0,MIN(K34,L34+N34)-P34) -> 0 | R34: =MAX(0,L34+N34-SUM(P34:Q34)) -> 0 | S34: =SUM(P34:R34) -> 0 | T34: =S34-(L34+N34) -> 0 | U34: =IFERROR(AE34/Z34,0) -> 0 | V34: =IFERROR(AF34/AA34,0) -> 0 | W34: =IF(AND(R34>0,V34>0),V34,0) -> 0 | X34: =IFERROR(IF($C34="XK",$AM34/$S34/$AC34,$AM34/$S34),0) -> 0 | AA34: =IF($C34="NĐ",1,EXR_FC05) -> 1 | AB34: =IF($C34="NĐ",1,EXR_FC05) -> 1 | AC34: =IFERROR(SUMPRODUCT(AJ34:AL34,Z34:AB34)/AM34,0) -> 0 | AE34: =IFERROR(AJ34/P34,0) -> 0 | AF34: =IFERROR(AK34/Q34,0) -> 0 | AG34: =W34*AB34 -> 0 | AJ34: =SUMIFS('Working-T05-B1'!AI$8:AI$150,'Working-T05-B1'!$C$8:$C$150,$D34) -> 0 | AK34: =SUMIFS('Working-T05-B1'!AJ$8:AJ$150,'Working-T05-B1'!$C$8:$C$150,$D34) -> 0 | AL34: =R34*AG34 -> 0 | AM34: =SUM(AJ34:AL34) -> 0 | AO34: =IFERROR(SUM(AQ34:AR34)/SUM(P34:Q34),0) -> 0 | AQ34: =SUMIFS('Working-T05-B1'!AP$8:AP$150,'Working-T05-B1'!$C$8:$C$150,$D34) -> 0 | AR34: =SUMIFS('Working-T05-B1'!AQ$8:AQ$150,'Working-T05-B1'!$C$8:$C$150,$D34) -> 0 | AS34: =AO34*R34 -> 0 | AT34: =SUM(AQ34:AS34) -> 0 | AV34: =IFERROR(BA34/S34,0) -> 0 | AX34: =SUMIFS('Working-T05-B1'!AW$8:AW$150,'Working-T05-B1'!$C$8:$C$150,$D34) -> 0 | AY34: =SUMIFS('Working-T05-B1'!AX$8:AX$150,'Working-T05-B1'!$C$8:$C$150,$D34) -> 0 | BA34: =SUM(AX34:AZ34) -> 0 | BC34: =_xlfn.XLOOKUP($G34,'GIÁ XUẤT KHO'!$A$4:$A$97,'GIÁ XUẤT KHO'!$AW$4:$AW$97)*P34 -> 0 | BD34: =_xlfn.XLOOKUP($G34,'GIÁ XUẤT KHO'!$A$4:$A$97,'GIÁ XUẤT KHO'!$AW$4:$AW$97)*Q34 -> 0 | BE34: =_xlfn.XLOOKUP($G34,'GIÁ XUẤT KHO'!$A$4:$A$97,'GIÁ XUẤT KHO'!$AW$4:$AW$97)*R34 -> 0 | BF34: =SUM(BC34:BE34) -> 0 | BH34: =AJ34-BC34 -> 0 | BI34: =AK34-BD34 -> 0 | BJ34: =AL34-BE34 -> 0 | BK34: =SUM(BH34:BJ34) -> 0 | BM34: =SUM(BN34:BV34) -> 0 | BN34: =SUMIFS('GIÁ XUẤT KHO'!AX$4:AX$97,'GIÁ XUẤT KHO'!$A$4:$A$97,$G34)*$S34 -> 0 | BO34: =SUMIFS('GIÁ XUẤT KHO'!AY$4:AY$97,'GIÁ XUẤT KHO'!$A$4:$A$97,$G34)*$S34 -> 0 | BP34: =SUMIFS('GIÁ XUẤT KHO'!AZ$4:AZ$97,'GIÁ XUẤT KHO'!$A$4:$A$97,$G34)*$S34 -> 0 | BQ34: =SUMIFS('GIÁ XUẤT KHO'!BA$4:BA$97,'GIÁ XUẤT KHO'!$A$4:$A$97,$G34)*$S34 -> 0 | BR34: =SUMIFS('GIÁ XUẤT KHO'!BB$4:BB$97,'GIÁ XUẤT KHO'!$A$4:$A$97,$G34)*$S34 -> 0 | BS34: =SUMIFS('GIÁ XUẤT KHO'!BC$4:BC$97,'GIÁ XUẤT KHO'!$A$4:$A$97,$G34)*$S34 -> 0 | BT34: =SUMIFS('GIÁ XUẤT KHO'!BD$4:BD$97,'GIÁ XUẤT KHO'!$A$4:$A$97,$G34)*$S34 -> 0 | BU34: =SUMIFS('GIÁ XUẤT KHO'!BE$4:BE$97,'GIÁ XUẤT KHO'!$A$4:$A$97,$G34)*$S34 -> 0 | BV34: =SUMIFS('GIÁ XUẤT KHO'!BF$4:BF$97,'GIÁ XUẤT KHO'!$A$4:$A$97,$G34)*$S34 -> 0 | BW34: =BM34-BF34 -> 0
A35: =_xlfn.XLOOKUP($G35,MD_SKU[Mã SKU],MD_SKU[Link vào file BCQT]) -> Hạt rPET | B35: TC-026 | C35: NĐ | D35: 105281 | 110000354 | E35: 105281 | F35: Plascene- DTP | G35: 110000354 | H35: Hạt nhựa rPET WSS01G 1 | K35: =SUMIFS('Working-T05-B1'!L$8:L$150,'Working-T05-B1'!$C$8:$C$150,$D35) -> 19100 | L35: {=SUMPRODUCT(Sales!$G$3:$H$100*(Sales!$B$3:$B$100=$D35))} -> 0 | M35: =K35-L35 -> 19100 | N35: =SUMIFS(Sales!$I$3:$I$100,Sales!$B$3:$B$100,$D35) -> 122000 | P35: =SUMIFS('Working-T05-B1'!O$8:O$150,'Working-T05-B1'!$C$8:$C$150,$D35) -> 0 | Q35: =MAX(0,MIN(K35,L35+N35)-P35) -> 19100 | R35: =MAX(0,L35+N35-SUM(P35:Q35)) -> 102900 | S35: =SUM(P35:R35) -> 122000 | T35: =S35-(L35+N35) -> 0 | U35: =IFERROR(AE35/Z35,0) -> 0 | V35: =IFERROR(AF35/AA35,0) -> 31897 | W35: =IF(AND(R35>0,V35>0),V35,0) -> 31897 | X35: =IFERROR(IF($C35="XK",$AM35/$S35/$AC35,$AM35/$S35),0) -> 31897 | AA35: =IF($C35="NĐ",1,EXR_FC05) -> 1 | AB35: =IF($C35="NĐ",1,EXR_FC05) -> 1 | AC35: =IFERROR(SUMPRODUCT(AJ35:AL35,Z35:AB35)/AM35,0) -> 1 | AE35: =IFERROR(AJ35/P35,0) -> 0 | AF35: =IFERROR(AK35/Q35,0) -> 31897 | AG35: =W35*AB35 -> 31897 | AJ35: =SUMIFS('Working-T05-B1'!AI$8:AI$150,'Working-T05-B1'!$C$8:$C$150,$D35) -> 0 | AK35: =SUMIFS('Working-T05-B1'!AJ$8:AJ$150,'Working-T05-B1'!$C$8:$C$150,$D35) -> 609232700 | AL35: =R35*AG35 -> 3282201300 | AM35: =SUM(AJ35:AL35) -> 3891434000 | AO35: =IFERROR(SUM(AQ35:AR35)/SUM(P35:Q35),0) -> 0 | AQ35: =SUMIFS('Working-T05-B1'!AP$8:AP$150,'Working-T05-B1'!$C$8:$C$150,$D35) -> 0 | AR35: =SUMIFS('Working-T05-B1'!AQ$8:AQ$150,'Working-T05-B1'!$C$8:$C$150,$D35) -> 0 | AS35: =AO35*R35 -> 0 | AT35: =SUM(AQ35:AS35) -> 0 | AV35: =IFERROR(BA35/S35,0) -> 0 | AX35: =SUMIFS('Working-T05-B1'!AW$8:AW$150,'Working-T05-B1'!$C$8:$C$150,$D35) -> 0 | AY35: =SUMIFS('Working-T05-B1'!AX$8:AX$150,'Working-T05-B1'!$C$8:$C$150,$D35) -> 0 | BA35: =SUM(AX35:AZ35) -> 0 | BC35: =_xlfn.XLOOKUP($G35,'GIÁ XUẤT KHO'!$A$4:$A$97,'GIÁ XUẤT KHO'!$AW$4:$AW$97)*P35 -> 0 | BD35: =_xlfn.XLOOKUP($G35,'GIÁ XUẤT KHO'!$A$4:$A$97,'GIÁ XUẤT KHO'!$AW$4:$AW$97)*Q35 -> 4.7631277e+08 | BE35: =_xlfn.XLOOKUP($G35,'GIÁ XUẤT KHO'!$A$4:$A$97,'GIÁ XUẤT KHO'!$AW$4:$AW$97)*R35 -> 2.5661039e+09 | BF35: =SUM(BC35:BE35) -> 3.0424166e+09 | BH35: =AJ35-BC35 -> 0 | BI35: =AK35-BD35 -> 1.3291993e+08 | BJ35: =AL35-BE35 -> 7.1609744e+08 | BK35: =SUM(BH35:BJ35) -> 8.4901738e+08 | BM35: =SUM(BN35:BV35) -> 3.0424166e+09 | BN35: =SUMIFS('GIÁ XUẤT KHO'!AX$4:AX$97,'GIÁ XUẤT KHO'!$A$4:$A$97,$G35)*$S35 -> 2.1969994e+09 | BO35: =SUMIFS('GIÁ XUẤT KHO'!AY$4:AY$97,'GIÁ XUẤT KHO'!$A$4:$A$97,$G35)*$S35 -> 22315422 | BP35: =SUMIFS('GIÁ XUẤT KHO'!AZ$4:AZ$97,'GIÁ XUẤT KHO'!$A$4:$A$97,$G35)*$S35 -> 11740.44 | BQ35: =SUMIFS('GIÁ XUẤT KHO'!BA$4:BA$97,'GIÁ XUẤT KHO'!$A$4:$A$97,$G35)*$S35 -> 1.5598319e+08 | BR35: =SUMIFS('GIÁ XUẤT KHO'!BB$4:BB$97,'GIÁ XUẤT KHO'!$A$4:$A$97,$G35)*$S35 -> 21421542 | BS35: =SUMIFS('GIÁ XUẤT KHO'!BC$4:BC$97,'GIÁ XUẤT KHO'!$A$4:$A$97,$G35)*$S35 -> 88002477 | BT35: =SUMIFS('GIÁ XUẤT KHO'!BD$4:BD$97,'GIÁ XUẤT KHO'!$A$4:$A$97,$G35)*$S35 -> 1.4155391e+08 | BU35: =SUMIFS('GIÁ XUẤT KHO'!BE$4:BE$97,'GIÁ XUẤT KHO'!$A$4:$A$97,$G35)*$S35 -> 38492551 | BV35: =SUMIFS('GIÁ XUẤT KHO'!BF$4:BF$97,'GIÁ XUẤT KHO'!$A$4:$A$97,$G35)*$S35 -> 3.7763642e+08 | BW35: =BM35-BF35 -> 0
A36: =_xlfn.XLOOKUP($G36,MD_SKU[Mã SKU],MD_SKU[Link vào file BCQT]) -> Hạt rPET | B36: TC-026 | C36: NĐ | D36: 105263 | 110000354 | E36: 105263 | F36: Unilever Duy Tân | G36: 110000354 | H36: Hạt nhựa rPET WSS01G 1 | K36: =SUMIFS('Working-T05-B1'!L$8:L$150,'Working-T05-B1'!$C$8:$C$150,$D36) -> 44000 | L36: {=SUMPRODUCT(Sales!$G$3:$H$100*(Sales!$B$3:$B$100=$D36))} -> 0 | M36: =K36-L36 -> 44000 | N36: =SUMIFS(Sales!$I$3:$I$100,Sales!$B$3:$B$100,$D36) -> 6311.7965 | P36: =SUMIFS('Working-T05-B1'!O$8:O$150,'Working-T05-B1'!$C$8:$C$150,$D36) -> 0 | Q36: =MAX(0,MIN(K36,L36+N36)-P36) -> 6311.7965 | R36: =MAX(0,L36+N36-SUM(P36:Q36)) -> 0 | S36: =SUM(P36:R36) -> 6311.7965 | T36: =S36-(L36+N36) -> 0 | U36: =IFERROR(AE36/Z36,0) -> 0 | V36: =IFERROR(AF36/AA36,0) -> 31513 | W36: =IF(AND(R36>0,V36>0),V36,0) -> 0 | X36: =IFERROR(IF($C36="XK",$AM36/$S36/$AC36,$AM36/$S36),0) -> 31513 | AA36: =IF($C36="NĐ",1,EXR_FC05) -> 1 | AB36: =IF($C36="NĐ",1,EXR_FC05) -> 1 | AC36: =IFERROR(SUMPRODUCT(AJ36:AL36,Z36:AB36)/AM36,0) -> 1 | AE36: =IFERROR(AJ36/P36,0) -> 0 | AF36: =IFERROR(AK36/Q36,0) -> 31513 | AG36: =W36*AB36 -> 0 | AJ36: =SUMIFS('Working-T05-B1'!AI$8:AI$150,'Working-T05-B1'!$C$8:$C$150,$D36) -> 0 | AK36: =SUMIFS('Working-T05-B1'!AJ$8:AJ$150,'Working-T05-B1'!$C$8:$C$150,$D36) -> 1.9890364e+08 | AL36: =R36*AG36 -> 0 | AM36: =SUM(AJ36:AL36) -> 1.9890364e+08 | AO36: =IFERROR(SUM(AQ36:AR36)/SUM(P36:Q36),0) -> 0 | AQ36: =SUMIFS('Working-T05-B1'!AP$8:AP$150,'Working-T05-B1'!$C$8:$C$150,$D36) -> 0 | AR36: =SUMIFS('Working-T05-B1'!AQ$8:AQ$150,'Working-T05-B1'!$C$8:$C$150,$D36) -> 0 | AS36: =AO36*R36 -> 0 | AT36: =SUM(AQ36:AS36) -> 0 | AV36: =IFERROR(BA36/S36,0) -> 0 | AX36: =SUMIFS('Working-T05-B1'!AW$8:AW$150,'Working-T05-B1'!$C$8:$C$150,$D36) -> 0 | AY36: =SUMIFS('Working-T05-B1'!AX$8:AX$150,'Working-T05-B1'!$C$8:$C$150,$D36) -> 0 | BA36: =SUM(AX36:AZ36) -> 0 | BC36: =_xlfn.XLOOKUP($G36,'GIÁ XUẤT KHO'!$A$4:$A$97,'GIÁ XUẤT KHO'!$AW$4:$AW$97)*P36 -> 0 | BD36: =_xlfn.XLOOKUP($G36,'GIÁ XUẤT KHO'!$A$4:$A$97,'GIÁ XUẤT KHO'!$AW$4:$AW$97)*Q36 -> 1.5740258e+08 | BE36: =_xlfn.XLOOKUP($G36,'GIÁ XUẤT KHO'!$A$4:$A$97,'GIÁ XUẤT KHO'!$AW$4:$AW$97)*R36 -> 0 | BF36: =SUM(BC36:BE36) -> 1.5740258e+08 | BH36: =AJ36-BC36 -> 0 | BI36: =AK36-BD36 -> 41501065 | BJ36: =AL36-BE36 -> 0 | BK36: =SUM(BH36:BJ36) -> 41501065 | BM36: =SUM(BN36:BV36) -> 1.5740258e+08 | BN36: =SUMIFS('GIÁ XUẤT KHO'!AX$4:AX$97,'GIÁ XUẤT KHO'!$A$4:$A$97,$G36)*$S36 -> 1.1366404e+08 | BO36: =SUMIFS('GIÁ XUẤT KHO'!AY$4:AY$97,'GIÁ XUẤT KHO'!$A$4:$A$97,$G36)*$S36 -> 1154511.5 | BP36: =SUMIFS('GIÁ XUẤT KHO'!AZ$4:AZ$97,'GIÁ XUẤT KHO'!$A$4:$A$97,$G36)*$S36 -> 607.40383 | BQ36: =SUMIFS('GIÁ XUẤT KHO'!BA$4:BA$97,'GIÁ XUẤT KHO'!$A$4:$A$97,$G36)*$S36 -> 8069952 | BR36: =SUMIFS('GIÁ XUẤT KHO'!BB$4:BB$97,'GIÁ XUẤT KHO'!$A$4:$A$97,$G36)*$S36 -> 1108265.7 | BS36: =SUMIFS('GIÁ XUẤT KHO'!BC$4:BC$97,'GIÁ XUẤT KHO'!$A$4:$A$97,$G36)*$S36 -> 4552899.4 | BT36: =SUMIFS('GIÁ XUẤT KHO'!BD$4:BD$97,'GIÁ XUẤT KHO'!$A$4:$A$97,$G36)*$S36 -> 7323438.2 | BU36: =SUMIFS('GIÁ XUẤT KHO'!BE$4:BE$97,'GIÁ XUẤT KHO'!$A$4:$A$97,$G36)*$S36 -> 1991452.1 | BV36: =SUMIFS('GIÁ XUẤT KHO'!BF$4:BF$97,'GIÁ XUẤT KHO'!$A$4:$A$97,$G36)*$S36 -> 19537412 | BW36: =BM36-BF36 -> 0
... A38: =_xlfn.XLOOKUP($G38,MD_SKU[Mã SKU],MD_SKU[Link vào file BCQT]) -> Hạt rPP | B38: TC-026 | C38: NĐ | D38: 105383 | 110000472 | E38: 105383 | F38: Aeonmall - DTP | G38: 110000472 | H38: Hạt Nhựa rPP20Gy01 | K38: =SUMIFS('Working-T05-B1'!L$8:L$150,'Working-T05-B1'!$C$8:$C$150,$D38) -> 500 | L38: {=SUMPRODUCT(Sales!$G$3:$H$100*(Sales!$B$3:$B$100=$D38))} -> 0 | M38: =K38-L38 -> 500 | N38: =SUMIFS(Sales!$I$3:$I$100,Sales!$B$3:$B$100,$D38) -> 0 | P38: =SUMIFS('Working-T05-B1'!O$8:O$150,'Working-T05-B1'!$C$8:$C$150,$D38) -> 0 | Q38: =MAX(0,MIN(K38,L38+N38)-P38) -> 0 | R38: =MAX(0,L38+N38-SUM(P38:Q38)) -> 0 | S38: =SUM(P38:R38) -> 0 | T38: =S38-(L38+N38) -> 0 | U38: =IFERROR(AE38/Z38,0) -> 0 | V38: =IFERROR(AF38/AA38,0) -> 0 | W38: =IF(AND(R38>0,V38>0),V38,0) -> 0 | X38: =IFERROR(IF($C38="XK",$AM38/$S38/$AC38,$AM38/$S38),0) -> 0 | AA38: =IF($C38="NĐ",1,EXR_FC05) -> 1 | AB38: =IF($C38="NĐ",1,EXR_FC05) -> 1 | AC38: =IFERROR(SUMPRODUCT(AJ38:AL38,Z38:AB38)/AM38,0) -> 0 | AE38: =IFERROR(AJ38/P38,0) -> 0 | AF38: =IFERROR(AK38/Q38,0) -> 0 | AG38: =W38*AB38 -> 0 | AJ38: =SUMIFS('Working-T05-B1'!AI$8:AI$150,'Working-T05-B1'!$C$8:$C$150,$D38) -> 0 | AK38: =SUMIFS('Working-T05-B1'!AJ$8:AJ$150,'Working-T05-B1'!$C$8:$C$150,$D38) -> 0 | AL38: =R38*AG38 -> 0 | AM38: =SUM(AJ38:AL38) -> 0 | AO38: =IFERROR(SUM(AQ38:AR38)/SUM(P38:Q38),0) -> 0 | AQ38: =SUMIFS('Working-T05-B1'!AP$8:AP$150,'Working-T05-B1'!$C$8:$C$150,$D38) -> 0 | AR38: =SUMIFS('Working-T05-B1'!AQ$8:AQ$150,'Working-T05-B1'!$C$8:$C$150,$D38) -> 0 | AS38: =AO38*R38 -> 0 | AT38: =SUM(AQ38:AS38) -> 0 | AV38: =IFERROR(BA38/S38,0) -> 0 | AX38: =SUMIFS('Working-T05-B1'!AW$8:AW$150,'Working-T05-B1'!$C$8:$C$150,$D38) -> 0 | AY38: =SUMIFS('Working-T05-B1'!AX$8:AX$150,'Working-T05-B1'!$C$8:$C$150,$D38) -> 0 | BA38: =SUM(AX38:AZ38) -> 0 | BC38: =_xlfn.XLOOKUP($G38,'GIÁ XUẤT KHO'!$A$4:$A$97,'GIÁ XUẤT KHO'!$AW$4:$AW$97)*P38 -> 0 | BD38: =_xlfn.XLOOKUP($G38,'GIÁ XUẤT KHO'!$A$4:$A$97,'GIÁ XUẤT KHO'!$AW$4:$AW$97)*Q38 -> 0 | BE38: =_xlfn.XLOOKUP($G38,'GIÁ XUẤT KHO'!$A$4:$A$97,'GIÁ XUẤT KHO'!$AW$4:$AW$97)*R38 -> 0 | BF38: =SUM(BC38:BE38) -> 0 | BH38: =AJ38-BC38 -> 0 | BI38: =AK38-BD38 -> 0 | BJ38: =AL38-BE38 -> 0 | BK38: =SUM(BH38:BJ38) -> 0 | BM38: =SUM(BN38:BV38) -> 0 | BN38: =SUMIFS('GIÁ XUẤT KHO'!AX$4:AX$97,'GIÁ XUẤT KHO'!$A$4:$A$97,$G38)*$S38 -> 0 | BO38: =SUMIFS('GIÁ XUẤT KHO'!AY$4:AY$97,'GIÁ XUẤT KHO'!$A$4:$A$97,$G38)*$S38 -> 0 | BP38: =SUMIFS('GIÁ XUẤT KHO'!AZ$4:AZ$97,'GIÁ XUẤT KHO'!$A$4:$A$97,$G38)*$S38 -> 0 | BQ38: =SUMIFS('GIÁ XUẤT KHO'!BA$4:BA$97,'GIÁ XUẤT KHO'!$A$4:$A$97,$G38)*$S38 -> 0 | BR38: =SUMIFS('GIÁ XUẤT KHO'!BB$4:BB$97,'GIÁ XUẤT KHO'!$A$4:$A$97,$G38)*$S38 -> 0 | BS38: =SUMIFS('GIÁ XUẤT KHO'!BC$4:BC$97,'GIÁ XUẤT KHO'!$A$4:$A$97,$G38)*$S38 -> 0 | BT38: =SUMIFS('GIÁ XUẤT KHO'!BD$4:BD$97,'GIÁ XUẤT KHO'!$A$4:$A$97,$G38)*$S38 -> 0 | BU38: =SUMIFS('GIÁ XUẤT KHO'!BE$4:BE$97,'GIÁ XUẤT KHO'!$A$4:$A$97,$G38)*$S38 -> 0 | BV38: =SUMIFS('GIÁ XUẤT KHO'!BF$4:BF$97,'GIÁ XUẤT KHO'!$A$4:$A$97,$G38)*$S38 -> 0 | BW38: =BM38-BF38 -> 0
A39: =_xlfn.XLOOKUP($G39,MD_SKU[Mã SKU],MD_SKU[Link vào file BCQT]) -> Hạt rPET | B39: Sales | C39: =IF(LEFT($E39,1)="2","XK","NĐ") -> NĐ | D39: 1000 | 110000354 | E39: 1000 | F39: CPSX Nhựa Duy Tân | G39: 110000354 | H39: Hạt nhựa rPET WSS01G | J39: DDP | N39: =SUMIFS(Sales!$I$3:$I$100,Sales!$B$3:$B$100,$D39) -> 6311.7965 | R39: =MAX(0,L39+N39-SUM(P39:Q39)) -> 6311.7965 | S39: =SUM(P39:R39) -> 6311.7965 | W39: =1.28*EXR_FC05 -> 33664 | X39: =IFERROR(IF($C39="XK",$AM39/$S39/$AC39,$AM39/$S39),0) -> 33664 | AA39: =IF($C39="NĐ",1,EXR_FC05) -> 1 | AB39: =IF($C39="NĐ",1,EXR_FC05) -> 1 | AC39: =IFERROR(SUMPRODUCT(AJ39:AL39,Z39:AB39)/AM39,0) -> 1 | AG39: =W39*AB39 -> 33664 | AL39: =R39*AG39 -> 2.1248032e+08 | AM39: =SUM(AJ39:AL39) -> 2.1248032e+08 | AS39: =AO39*R39 -> 0 | AT39: =SUM(AQ39:AS39) -> 0 | BA39: =SUM(AX39:AZ39) -> 0 | BE39: =_xlfn.XLOOKUP($G39,'GIÁ XUẤT KHO'!$A$4:$A$97,'GIÁ XUẤT KHO'!$AW$4:$AW$97)*R39 -> 1.5740258e+08 | BF39: =SUM(BC39:BE39) -> 1.5740258e+08 | BI39: =AK39-BD39 -> 0 | BJ39: =AL39-BE39 -> 55077739 | BK39: =SUM(BH39:BJ39) -> 55077739 | BM39: =SUM(BN39:BV39) -> 1.5740258e+08 | BN39: =SUMIFS('GIÁ XUẤT KHO'!AX$4:AX$97,'GIÁ XUẤT KHO'!$A$4:$A$97,$G39)*$S39 -> 1.1366404e+08 | BO39: =SUMIFS('GIÁ XUẤT KHO'!AY$4:AY$97,'GIÁ XUẤT KHO'!$A$4:$A$97,$G39)*$S39 -> 1154511.5 | BP39: =SUMIFS('GIÁ XUẤT KHO'!AZ$4:AZ$97,'GIÁ XUẤT KHO'!$A$4:$A$97,$G39)*$S39 -> 607.40383 | BQ39: =SUMIFS('GIÁ XUẤT KHO'!BA$4:BA$97,'GIÁ XUẤT KHO'!$A$4:$A$97,$G39)*$S39 -> 8069952 | BR39: =SUMIFS('GIÁ XUẤT KHO'!BB$4:BB$97,'GIÁ XUẤT KHO'!$A$4:$A$97,$G39)*$S39 -> 1108265.7 | BS39: =SUMIFS('GIÁ XUẤT KHO'!BC$4:BC$97,'GIÁ XUẤT KHO'!$A$4:$A$97,$G39)*$S39 -> 4552899.4 | BT39: =SUMIFS('GIÁ XUẤT KHO'!BD$4:BD$97,'GIÁ XUẤT KHO'!$A$4:$A$97,$G39)*$S39 -> 7323438.2 | BU39: =SUMIFS('GIÁ XUẤT KHO'!BE$4:BE$97,'GIÁ XUẤT KHO'!$A$4:$A$97,$G39)*$S39 -> 1991452.1 | BV39: =SUMIFS('GIÁ XUẤT KHO'!BF$4:BF$97,'GIÁ XUẤT KHO'!$A$4:$A$97,$G39)*$S39 -> 19537412 | BW39: =BM39-BF39 -> 0
A40: =_xlfn.XLOOKUP($G40,MD_SKU[Mã SKU],MD_SKU[Link vào file BCQT]) -> Hạt rHDPE ép | B40: Sales | C40: =IF(LEFT($E40,1)="2","XK","NĐ") -> NĐ | D40: 1000 | 110000361 | E40: 1000 | F40: CPSX Nhựa Duy Tân | G40: 110000361 | H40: Hạt nhựa rHDI3R01 | J40: DDP | N40: =SUMIFS(Sales!$I$3:$I$100,Sales!$B$3:$B$100,$D40) -> 6920.9129 | R40: =MAX(0,L40+N40-SUM(P40:Q40)) -> 6920.9129 | S40: =SUM(P40:R40) -> 6920.9129 | W40: =1.23*EXR_FC05 -> 32349 | X40: =IFERROR(IF($C40="XK",$AM40/$S40/$AC40,$AM40/$S40),0) -> 32349 | AA40: =IF($C40="NĐ",1,EXR_FC05) -> 1 | AB40: =IF($C40="NĐ",1,EXR_FC05) -> 1 | AC40: =IFERROR(SUMPRODUCT(AJ40:AL40,Z40:AB40)/AM40,0) -> 1 | AG40: =W40*AB40 -> 32349 | AL40: =R40*AG40 -> 2.2388461e+08 | AM40: =SUM(AJ40:AL40) -> 2.2388461e+08 | AS40: =AO40*R40 -> 0 | AT40: =SUM(AQ40:AS40) -> 0 | BA40: =SUM(AX40:AZ40) -> 0 | BE40: =_xlfn.XLOOKUP($G40,'GIÁ XUẤT KHO'!$A$4:$A$97,'GIÁ XUẤT KHO'!$AW$4:$AW$97)*R40 -> 3.3072748e+08 | BF40: =SUM(BC40:BE40) -> 3.3072748e+08 | BI40: =AK40-BD40 -> 0 | BJ40: =AL40-BE40 -> -1.0684287e+08 | BK40: =SUM(BH40:BJ40) -> -1.0684287e+08 | BM40: =SUM(BN40:BV40) -> 3.3072748e+08 | BN40: =SUMIFS('GIÁ XUẤT KHO'!AX$4:AX$97,'GIÁ XUẤT KHO'!$A$4:$A$97,$G40)*$S40 -> 87223585 | BO40: =SUMIFS('GIÁ XUẤT KHO'!AY$4:AY$97,'GIÁ XUẤT KHO'!$A$4:$A$97,$G40)*$S40 -> 1645637.9 | BP40: =SUMIFS('GIÁ XUẤT KHO'!AZ$4:AZ$97,'GIÁ XUẤT KHO'!$A$4:$A$97,$G40)*$S40 -> 1821404.4 | BQ40: =SUMIFS('GIÁ XUẤT KHO'!BA$4:BA$97,'GIÁ XUẤT KHO'!$A$4:$A$97,$G40)*$S40 -> 33451565 | BR40: =SUMIFS('GIÁ XUẤT KHO'!BB$4:BB$97,'GIÁ XUẤT KHO'!$A$4:$A$97,$G40)*$S40 -> 5336569.3 | BS40: =SUMIFS('GIÁ XUẤT KHO'!BC$4:BC$97,'GIÁ XUẤT KHO'!$A$4:$A$97,$G40)*$S40 -> 58295121 | BT40: =SUMIFS('GIÁ XUẤT KHO'!BD$4:BD$97,'GIÁ XUẤT KHO'!$A$4:$A$97,$G40)*$S40 -> 51955187 | BU40: =SUMIFS('GIÁ XUẤT KHO'!BE$4:BE$97,'GIÁ XUẤT KHO'!$A$4:$A$97,$G40)*$S40 -> 31741527 | BV40: =SUMIFS('GIÁ XUẤT KHO'!BF$4:BF$97,'GIÁ XUẤT KHO'!$A$4:$A$97,$G40)*$S40 -> 59256885 | BW40: =BM40-BF40 -> 0
A41: =_xlfn.XLOOKUP($G41,MD_SKU[Mã SKU],MD_SKU[Link vào file BCQT]) -> Hạt rHDPE ép | B41: Sales | C41: =IF(LEFT($E41,1)="2","XK","NĐ") -> NĐ | D41: 1000 | 110000363 | E41: 1000 | F41: CPSX Nhựa Duy Tân | G41: 110000363 | H41: Hạt nhựa rHDPE rHDI3Gy01 | J41: DDP | N41: =SUMIFS(Sales!$I$3:$I$100,Sales!$B$3:$B$100,$D41) -> 1375 | R41: =MAX(0,L41+N41-SUM(P41:Q41)) -> 1375 | S41: =SUM(P41:R41) -> 1375 | W41: =1.23*EXR_FC05 -> 32349 | X41: =IFERROR(IF($C41="XK",$AM41/$S41/$AC41,$AM41/$S41),0) -> 32349 | AA41: =IF($C41="NĐ",1,EXR_FC05) -> 1 | AB41: =IF($C41="NĐ",1,EXR_FC05) -> 1 | AC41: =IFERROR(SUMPRODUCT(AJ41:AL41,Z41:AB41)/AM41,0) -> 1 | AG41: =W41*AB41 -> 32349 | AL41: =R41*AG41 -> 44479875 | AM41: =SUM(AJ41:AL41) -> 44479875 | AS41: =AO41*R41 -> 0 | AT41: =SUM(AQ41:AS41) -> 0 | BA41: =SUM(AX41:AZ41) -> 0 | BE41: =_xlfn.XLOOKUP($G41,'GIÁ XUẤT KHO'!$A$4:$A$97,'GIÁ XUẤT KHO'!$AW$4:$AW$97)*R41 -> 25648905 | BF41: =SUM(BC41:BE41) -> 25648905 | BI41: =AK41-BD41 -> 0 | BJ41: =AL41-BE41 -> 18830970 | BK41: =SUM(BH41:BJ41) -> 18830970 | BM41: =SUM(BN41:BV41) -> 25648905 | BN41: =SUMIFS('GIÁ XUẤT KHO'!AX$4:AX$97,'GIÁ XUẤT KHO'!$A$4:$A$97,$G41)*$S41 -> 19968512 | BO41: =SUMIFS('GIÁ XUẤT KHO'!AY$4:AY$97,'GIÁ XUẤT KHO'!$A$4:$A$97,$G41)*$S41 -> 49017.54 | BP41: =SUMIFS('GIÁ XUẤT KHO'!AZ$4:AZ$97,'GIÁ XUẤT KHO'!$A$4:$A$97,$G41)*$S41 -> 1454.1086 | BQ41: =SUMIFS('GIÁ XUẤT KHO'!BA$4:BA$97,'GIÁ XUẤT KHO'!$A$4:$A$97,$G41)*$S41 -> 1290066.8 | BR41: =SUMIFS('GIÁ XUẤT KHO'!BB$4:BB$97,'GIÁ XUẤT KHO'!$A$4:$A$97,$G41)*$S41 -> 351053.99 | BS41: =SUMIFS('GIÁ XUẤT KHO'!BC$4:BC$97,'GIÁ XUẤT KHO'!$A$4:$A$97,$G41)*$S41 -> 744871.91 | BT41: =SUMIFS('GIÁ XUẤT KHO'!BD$4:BD$97,'GIÁ XUẤT KHO'!$A$4:$A$97,$G41)*$S41 -> 775637.32 | BU41: =SUMIFS('GIÁ XUẤT KHO'!BE$4:BE$97,'GIÁ XUẤT KHO'!$A$4:$A$97,$G41)*$S41 -> 891092.11 | BV41: =SUMIFS('GIÁ XUẤT KHO'!BF$4:BF$97,'GIÁ XUẤT KHO'!$A$4:$A$97,$G41)*$S41 -> 1577198.9 | BW41: =BM41-BF41 -> 0
A42: =_xlfn.XLOOKUP($G42,MD_SKU[Mã SKU],MD_SKU[Link vào file BCQT]) -> Hạt rHDPE ép | B42: Sales | C42: =IF(LEFT($E42,1)="2","XK","NĐ") -> NĐ | D42: 1000 | 110000364 | E42: 1000 | F42: CPSX Nhựa Duy Tân | G42: 110000364 | H42: Hạt nhựa rHDPE rHDI3Y01 | J42: DDP | N42: =SUMIFS(Sales!$I$3:$I$100,Sales!$B$3:$B$100,$D42) -> 6349.2402 | R42: =MAX(0,L42+N42-SUM(P42:Q42)) -> 6349.2402 | S42: =SUM(P42:R42) -> 6349.2402 | W42: =1.23*EXR_FC05 -> 32349 | X42: =IFERROR(IF($C42="XK",$AM42/$S42/$AC42,$AM42/$S42),0) -> 32349 | AA42: =IF($C42="NĐ",1,EXR_FC05) -> 1 | AB42: =IF($C42="NĐ",1,EXR_FC05) -> 1 | AC42: =IFERROR(SUMPRODUCT(AJ42:AL42,Z42:AB42)/AM42,0) -> 1 | AG42: =W42*AB42 -> 32349 | AL42: =R42*AG42 -> 2.0539157e+08 | AM42: =SUM(AJ42:AL42) -> 2.0539157e+08 | AS42: =AO42*R42 -> 0 | AT42: =SUM(AQ42:AS42) -> 0 | BA42: =SUM(AX42:AZ42) -> 0 | BE42: =_xlfn.XLOOKUP($G42,'GIÁ XUẤT KHO'!$A$4:$A$97,'GIÁ XUẤT KHO'!$AW$4:$AW$97)*R42 -> 1.3932288e+08 | BF42: =SUM(BC42:BE42) -> 1.3932288e+08 | BI42: =AK42-BD42 -> 0 | BJ42: =AL42-BE42 -> 66068687 | BK42: =SUM(BH42:BJ42) -> 66068687 | BM42: =SUM(BN42:BV42) -> 1.3932288e+08 | BN42: =SUMIFS('GIÁ XUẤT KHO'!AX$4:AX$97,'GIÁ XUẤT KHO'!$A$4:$A$97,$G42)*$S42 -> 1.1359893e+08 | BO42: =SUMIFS('GIÁ XUẤT KHO'!AY$4:AY$97,'GIÁ XUẤT KHO'!$A$4:$A$97,$G42)*$S42 -> 285542.81 | BP42: =SUMIFS('GIÁ XUẤT KHO'!AZ$4:AZ$97,'GIÁ XUẤT KHO'!$A$4:$A$97,$G42)*$S42 -> 101.97341 | BQ42: =SUMIFS('GIÁ XUẤT KHO'!BA$4:BA$97,'GIÁ XUẤT KHO'!$A$4:$A$97,$G42)*$S42 -> 3608857.9 | BR42: =SUMIFS('GIÁ XUẤT KHO'!BB$4:BB$97,'GIÁ XUẤT KHO'!$A$4:$A$97,$G42)*$S42 -> 1174562.8 | BS42: =SUMIFS('GIÁ XUẤT KHO'!BC$4:BC$97,'GIÁ XUẤT KHO'!$A$4:$A$97,$G42)*$S42 -> 4300368 | BT42: =SUMIFS('GIÁ XUẤT KHO'!BD$4:BD$97,'GIÁ XUẤT KHO'!$A$4:$A$97,$G42)*$S42 -> 4797553.9 | BU42: =SUMIFS('GIÁ XUẤT KHO'!BE$4:BE$97,'GIÁ XUẤT KHO'!$A$4:$A$97,$G42)*$S42 -> 4610555.9 | BV42: =SUMIFS('GIÁ XUẤT KHO'!BF$4:BF$97,'GIÁ XUẤT KHO'!$A$4:$A$97,$G42)*$S42 -> 6946410.7 | BW42: =BM42-BF42 -> 0
A43: =_xlfn.XLOOKUP($G43,MD_SKU[Mã SKU],MD_SKU[Link vào file BCQT]) -> Hạt rHDPE ép | B43: Sales | C43: =IF(LEFT($E43,1)="2","XK","NĐ") -> NĐ | D43: 1000 | 110000366 | E43: 1000 | F43: CPSX Nhựa Duy Tân | G43: 110000366 | H43: Hạt nhựa rHDI3G01 | J43: DDP | N43: =SUMIFS(Sales!$I$3:$I$100,Sales!$B$3:$B$100,$D43) -> 1375 | R43: =MAX(0,L43+N43-SUM(P43:Q43)) -> 1375 | S43: =SUM(P43:R43) -> 1375 | W43: =1.23*EXR_FC05 -> 32349 | X43: =IFERROR(IF($C43="XK",$AM43/$S43/$AC43,$AM43/$S43),0) -> 32349 | AA43: =IF($C43="NĐ",1,EXR_FC05) -> 1 | AB43: =IF($C43="NĐ",1,EXR_FC05) -> 1 | AC43: =IFERROR(SUMPRODUCT(AJ43:AL43,Z43:AB43)/AM43,0) -> 1 | AG43: =W43*AB43 -> 32349 | AL43: =R43*AG43 -> 44479875 | AM43: =SUM(AJ43:AL43) -> 44479875 | AS43: =AO43*R43 -> 0 | AT43: =SUM(AQ43:AS43) -> 0 | BA43: =SUM(AX43:AZ43) -> 0 | BE43: =_xlfn.XLOOKUP($G43,'GIÁ XUẤT KHO'!$A$4:$A$97,'GIÁ XUẤT KHO'!$AW$4:$AW$97)*R43 -> 34344520 | BF43: =SUM(BC43:BE43) -> 34344520 | BI43: =AK43-BD43 -> 0 | BJ43: =AL43-BE43 -> 10135355 | BK43: =SUM(BH43:BJ43) -> 10135355 | BM43: =SUM(BN43:BV43) -> 34344520 | BN43: =SUMIFS('GIÁ XUẤT KHO'!AX$4:AX$97,'GIÁ XUẤT KHO'!$A$4:$A$97,$G43)*$S43 -> 22724303 | BO43: =SUMIFS('GIÁ XUẤT KHO'!AY$4:AY$97,'GIÁ XUẤT KHO'!$A$4:$A$97,$G43)*$S43 -> 2566892.5 | BP43: =SUMIFS('GIÁ XUẤT KHO'!AZ$4:AZ$97,'GIÁ XUẤT KHO'!$A$4:$A$97,$G43)*$S43 -> 3662.5048 | BQ43: =SUMIFS('GIÁ XUẤT KHO'!BA$4:BA$97,'GIÁ XUẤT KHO'!$A$4:$A$97,$G43)*$S43 -> 1490356.9 | BR43: =SUMIFS('GIÁ XUẤT KHO'!BB$4:BB$97,'GIÁ XUẤT KHO'!$A$4:$A$97,$G43)*$S43 -> 377929.44 | BS43: =SUMIFS('GIÁ XUẤT KHO'!BC$4:BC$97,'GIÁ XUẤT KHO'!$A$4:$A$97,$G43)*$S43 -> 1868115.6 | BT43: =SUMIFS('GIÁ XUẤT KHO'!BD$4:BD$97,'GIÁ XUẤT KHO'!$A$4:$A$97,$G43)*$S43 -> 2117220.6 | BU43: =SUMIFS('GIÁ XUẤT KHO'!BE$4:BE$97,'GIÁ XUẤT KHO'!$A$4:$A$97,$G43)*$S43 -> 932015.54 | BV43: =SUMIFS('GIÁ XUẤT KHO'!BF$4:BF$97,'GIÁ XUẤT KHO'!$A$4:$A$97,$G43)*$S43 -> 2264024.7 | BW43: =BM43-BF43 -> 0
A44: =_xlfn.XLOOKUP($G44,MD_SKU[Mã SKU],MD_SKU[Link vào file BCQT]) -> Hạt rHDPE ép | B44: Sales | C44: =IF(LEFT($E44,1)="2","XK","NĐ") -> NĐ | D44: 1000 | 110000373 | E44: 1000 | F44: CPSX Nhựa Duy Tân | G44: 110000373 | H44: Hạt nhựa rHDPE rHDI4DL01 | J44: DDP | N44: =SUMIFS(Sales!$I$3:$I$100,Sales!$B$3:$B$100,$D44) -> 23375 | R44: =MAX(0,L44+N44-SUM(P44:Q44)) -> 23375 | S44: =SUM(P44:R44) -> 23375 | W44: =1.23*EXR_FC05 -> 32349 | X44: =IFERROR(IF($C44="XK",$AM44/$S44/$AC44,$AM44/$S44),0) -> 32349 | AA44: =IF($C44="NĐ",1,EXR_FC05) -> 1 | AB44: =IF($C44="NĐ",1,EXR_FC05) -> 1 | AC44: =IFERROR(SUMPRODUCT(AJ44:AL44,Z44:AB44)/AM44,0) -> 1 | AG44: =W44*AB44 -> 32349 | AL44: =R44*AG44 -> 756157875 | AM44: =SUM(AJ44:AL44) -> 756157875 | AS44: =AO44*R44 -> 0 | AT44: =SUM(AQ44:AS44) -> 0 | BA44: =SUM(AX44:AZ44) -> 0 | BE44: =_xlfn.XLOOKUP($G44,'GIÁ XUẤT KHO'!$A$4:$A$97,'GIÁ XUẤT KHO'!$AW$4:$AW$97)*R44 -> 5.5100819e+08 | BF44: =SUM(BC44:BE44) -> 5.5100819e+08 | BI44: =AK44-BD44 -> 0 | BJ44: =AL44-BE44 -> 2.0514968e+08 | BK44: =SUM(BH44:BJ44) -> 2.0514968e+08 | BM44: =SUM(BN44:BV44) -> 5.5100819e+08 | BN44: =SUMIFS('GIÁ XUẤT KHO'!AX$4:AX$97,'GIÁ XUẤT KHO'!$A$4:$A$97,$G44)*$S44 -> 3.9341709e+08 | BO44: =SUMIFS('GIÁ XUẤT KHO'!AY$4:AY$97,'GIÁ XUẤT KHO'!$A$4:$A$97,$G44)*$S44 -> 31045388 | BP44: =SUMIFS('GIÁ XUẤT KHO'!AZ$4:AZ$97,'GIÁ XUẤT KHO'!$A$4:$A$97,$G44)*$S44 -> 2427061.6 | BQ44: =SUMIFS('GIÁ XUẤT KHO'!BA$4:BA$97,'GIÁ XUẤT KHO'!$A$4:$A$97,$G44)*$S44 -> 25035838 | BR44: =SUMIFS('GIÁ XUẤT KHO'!BB$4:BB$97,'GIÁ XUẤT KHO'!$A$4:$A$97,$G44)*$S44 -> 4574750.7 | BS44: =SUMIFS('GIÁ XUẤT KHO'!BC$4:BC$97,'GIÁ XUẤT KHO'!$A$4:$A$97,$G44)*$S44 -> 20887677 | BT44: =SUMIFS('GIÁ XUẤT KHO'!BD$4:BD$97,'GIÁ XUẤT KHO'!$A$4:$A$97,$G44)*$S44 -> 23532347 | BU44: =SUMIFS('GIÁ XUẤT KHO'!BE$4:BE$97,'GIÁ XUẤT KHO'!$A$4:$A$97,$G44)*$S44 -> 23172012 | BV44: =SUMIFS('GIÁ XUẤT KHO'!BF$4:BF$97,'GIÁ XUẤT KHO'!$A$4:$A$97,$G44)*$S44 -> 26916031 | BW44: =BM44-BF44 -> 0
A45: =_xlfn.XLOOKUP($G45,MD_SKU[Mã SKU],MD_SKU[Link vào file BCQT]) -> Hạt rPET | B45: Sales | C45: =IF(LEFT($E45,1)="2","XK","NĐ") -> NĐ | D45: 104894 | 110000354 | E45: 104894 | F45: UNILEVER-NGỌC NGHĨA | G45: 110000354 | H45: Hạt nhựa rPET WSS01G | J45: DDP | N45: =SUMIFS(Sales!$I$3:$I$100,Sales!$B$3:$B$100,$D45) -> 220000 | R45: =MAX(0,L45+N45-SUM(P45:Q45)) -> 220000 | S45: =SUM(P45:R45) -> 220000 | W45: =W31 -> 31679 | X45: =IFERROR(IF($C45="XK",$AM45/$S45/$AC45,$AM45/$S45),0) -> 31679 | AA45: =IF($C45="NĐ",1,EXR_FC05) -> 1 | AB45: =IF($C45="NĐ",1,EXR_FC05) -> 1 | AC45: =IFERROR(SUMPRODUCT(AJ45:AL45,Z45:AB45)/AM45,0) -> 1 | AG45: =W45*AB45 -> 31679 | AL45: =R45*AG45 -> 6969380000 | AM45: =SUM(AJ45:AL45) -> 6969380000 | AO45: =AO31 -> 165.16 | AS45: =AO45*R45 -> 36335201 | AT45: =SUM(AQ45:AS45) -> 36335201 | BA45: =SUM(AX45:AZ45) -> 0 | BE45: =_xlfn.XLOOKUP($G45,'GIÁ XUẤT KHO'!$A$4:$A$97,'GIÁ XUẤT KHO'!$AW$4:$AW$97)*R45 -> 5.4863251e+09 | BF45: =SUM(BC45:BE45) -> 5.4863251e+09 | BI45: =AK45-BD45 -> 0 | BJ45: =AL45-BE45 -> 1.4830549e+09 | BK45: =SUM(BH45:BJ45) -> 1.4830549e+09 | BM45: =SUM(BN45:BV45) -> 5.4863251e+09 | BN45: =SUMIFS('GIÁ XUẤT KHO'!AX$4:AX$97,'GIÁ XUẤT KHO'!$A$4:$A$97,$G45)*$S45 -> 3.9618022e+09 | BO45: =SUMIFS('GIÁ XUẤT KHO'!AY$4:AY$97,'GIÁ XUẤT KHO'!$A$4:$A$97,$G45)*$S45 -> 40240925 | BP45: =SUMIFS('GIÁ XUẤT KHO'!AZ$4:AZ$97,'GIÁ XUẤT KHO'!$A$4:$A$97,$G45)*$S45 -> 21171.285 | BQ45: =SUMIFS('GIÁ XUẤT KHO'!BA$4:BA$97,'GIÁ XUẤT KHO'!$A$4:$A$97,$G45)*$S45 -> 2.8128116e+08 | BR45: =SUMIFS('GIÁ XUẤT KHO'!BB$4:BB$97,'GIÁ XUẤT KHO'!$A$4:$A$97,$G45)*$S45 -> 38629010 | BS45: =SUMIFS('GIÁ XUẤT KHO'!BC$4:BC$97,'GIÁ XUẤT KHO'!$A$4:$A$97,$G45)*$S45 -> 1.5869299e+08 | BT45: =SUMIFS('GIÁ XUẤT KHO'!BD$4:BD$97,'GIÁ XUẤT KHO'!$A$4:$A$97,$G45)*$S45 -> 2.5526114e+08 | BU45: =SUMIFS('GIÁ XUẤT KHO'!BE$4:BE$97,'GIÁ XUẤT KHO'!$A$4:$A$97,$G45)*$S45 -> 69412797 | BV45: =SUMIFS('GIÁ XUẤT KHO'!BF$4:BF$97,'GIÁ XUẤT KHO'!$A$4:$A$97,$G45)*$S45 -> 6.8098371e+08 | BW45: =BM45-BF45 -> 0
A46: =_xlfn.XLOOKUP($G46,MD_SKU[Mã SKU],MD_SKU[Link vào file BCQT]) -> Hạt rPET | B46: Sales | C46: =IF(LEFT($E46,1)="2","XK","NĐ") -> NĐ | D46: 105194 | 110000332 | E46: 105194 | F46: Suntory Việt Nam | G46: 110000332 | H46: Hạt nhựa rPET iSS01084G | J46: DDP | N46: =SUMIFS(Sales!$I$3:$I$100,Sales!$B$3:$B$100,$D46) -> 572000 | R46: =MAX(0,L46+N46-SUM(P46:Q46)) -> 572000 | S46: =SUM(P46:R46) -> 572000 | W46: 32240 | X46: =IFERROR(IF($C46="XK",$AM46/$S46/$AC46,$AM46/$S46),0) -> 32240 | AA46: =IF($C46="NĐ",1,EXR_FC05) -> 1 | AB46: =IF($C46="NĐ",1,EXR_FC05) -> 1 | AC46: =IFERROR(SUMPRODUCT(AJ46:AL46,Z46:AB46)/AM46,0) -> 1 | AG46: =W46*AB46 -> 32240 | AL46: =R46*AG46 -> 18441280000 | AM46: =SUM(AJ46:AL46) -> 18441280000 | AO46: =25*EXR_FC05/1000 -> 657.5 | AS46: =AO46*R46 -> 376090000 | AT46: =SUM(AQ46:AS46) -> 376090000 | AZ46: =6%*AL46 -> 1106476800 | BA46: =SUM(AX46:AZ46) -> 1106476800 | BB46: x | BE46: =_xlfn.XLOOKUP($G46,'GIÁ XUẤT KHO'!$A$4:$A$97,'GIÁ XUẤT KHO'!$AW$4:$AW$97)*R46 -> 1.6026139e+10 | BF46: =SUM(BC46:BE46) -> 1.6026139e+10 | BI46: =AK46-BD46 -> 0 | BJ46: =AL46-BE46 -> 2.4151413e+09 | BK46: =SUM(BH46:BJ46) -> 2.4151413e+09 | BM46: =SUM(BN46:BV46) -> 1.6026139e+10 | BN46: =SUMIFS('GIÁ XUẤT KHO'!AX$4:AX$97,'GIÁ XUẤT KHO'!$A$4:$A$97,$G46)*$S46 -> 9.4739666e+09 | BO46: =SUMIFS('GIÁ XUẤT KHO'!AY$4:AY$97,'GIÁ XUẤT KHO'!$A$4:$A$97,$G46)*$S46 -> 1.5741443e+08 | BP46: =SUMIFS('GIÁ XUẤT KHO'!AZ$4:AZ$97,'GIÁ XUẤT KHO'!$A$4:$A$97,$G46)*$S46 -> 64135.471 | BQ46: =SUMIFS('GIÁ XUẤT KHO'!BA$4:BA$97,'GIÁ XUẤT KHO'!$A$4:$A$97,$G46)*$S46 -> 1.0454438e+09 | BR46: =SUMIFS('GIÁ XUẤT KHO'!BB$4:BB$97,'GIÁ XUẤT KHO'!$A$4:$A$97,$G46)*$S46 -> 1.237411e+08 | BS46: =SUMIFS('GIÁ XUẤT KHO'!BC$4:BC$97,'GIÁ XUẤT KHO'!$A$4:$A$97,$G46)*$S46 -> 7.4812758e+08 | BT46: =SUMIFS('GIÁ XUẤT KHO'!BD$4:BD$97,'GIÁ XUẤT KHO'!$A$4:$A$97,$G46)*$S46 -> 1.2055502e+09 | BU46: =SUMIFS('GIÁ XUẤT KHO'!BE$4:BE$97,'GIÁ XUẤT KHO'!$A$4:$A$97,$G46)*$S46 -> 2.8942122e+08 | BV46: =SUMIFS('GIÁ XUẤT KHO'!BF$4:BF$97,'GIÁ XUẤT KHO'!$A$4:$A$97,$G46)*$S46 -> 2.9824096e+09 | BW46: =BM46-BF46 -> 0
A47: =_xlfn.XLOOKUP($G47,MD_SKU[Mã SKU],MD_SKU[Link vào file BCQT]) -> Hạt rPET | B47: Sales | C47: =IF(LEFT($E47,1)="2","XK","NĐ") -> NĐ | D47: 105207 | 110000332 | E47: 105207 | F47: Suntory Sri Thái Bình Dương | G47: 110000332 | H47: Hạt nhựa rPET iSS01084G | J47: DDP | N47: =SUMIFS(Sales!$I$3:$I$100,Sales!$B$3:$B$100,$D47) -> 242000 | R47: =MAX(0,L47+N47-SUM(P47:Q47)) -> 242000 | S47: =SUM(P47:R47) -> 242000 | W47: 31844 | X47: =IFERROR(IF($C47="XK",$AM47/$S47/$AC47,$AM47/$S47),0) -> 31844 | AA47: =IF($C47="NĐ",1,EXR_FC05) -> 1 | AB47: =IF($C47="NĐ",1,EXR_FC05) -> 1 | AC47: =IFERROR(SUMPRODUCT(AJ47:AL47,Z47:AB47)/AM47,0) -> 1 | AG47: =W47*AB47 -> 31844 | AL47: =R47*AG47 -> 7706248000 | AM47: =SUM(AJ47:AL47) -> 7706248000 | AO47: =20*EXR_FC05/1000 -> 526 | AS47: =AO47*R47 -> 127292000 | AT47: =SUM(AQ47:AS47) -> 127292000 | AZ47: =6%*AL47 -> 462374880 | BA47: =SUM(AX47:AZ47) -> 462374880 | BB47: x | BE47: =_xlfn.XLOOKUP($G47,'GIÁ XUẤT KHO'!$A$4:$A$97,'GIÁ XUẤT KHO'!$AW$4:$AW$97)*R47 -> 6.7802894e+09 | BF47: =SUM(BC47:BE47) -> 6.7802894e+09 | BI47: =AK47-BD47 -> 0 | BJ47: =AL47-BE47 -> 9.2595857e+08 | BK47: =SUM(BH47:BJ47) -> 9.2595857e+08 | BM47: =SUM(BN47:BV47) -> 6.7802894e+09 | BN47: =SUMIFS('GIÁ XUẤT KHO'!AX$4:AX$97,'GIÁ XUẤT KHO'!$A$4:$A$97,$G47)*$S47 -> 4.0082166e+09 | BO47: =SUMIFS('GIÁ XUẤT KHO'!AY$4:AY$97,'GIÁ XUẤT KHO'!$A$4:$A$97,$G47)*$S47 -> 66598411 | BP47: =SUMIFS('GIÁ XUẤT KHO'!AZ$4:AZ$97,'GIÁ XUẤT KHO'!$A$4:$A$97,$G47)*$S47 -> 27134.238 | BQ47: =SUMIFS('GIÁ XUẤT KHO'!BA$4:BA$97,'GIÁ XUẤT KHO'!$A$4:$A$97,$G47)*$S47 -> 4.4230315e+08 | BR47: =SUMIFS('GIÁ XUẤT KHO'!BB$4:BB$97,'GIÁ XUẤT KHO'!$A$4:$A$97,$G47)*$S47 -> 52352005 | BS47: =SUMIFS('GIÁ XUẤT KHO'!BC$4:BC$97,'GIÁ XUẤT KHO'!$A$4:$A$97,$G47)*$S47 -> 3.1651551e+08 | BT47: =SUMIFS('GIÁ XUẤT KHO'!BD$4:BD$97,'GIÁ XUẤT KHO'!$A$4:$A$97,$G47)*$S47 -> 5.1004048e+08 | BU47: =SUMIFS('GIÁ XUẤT KHO'!BE$4:BE$97,'GIÁ XUẤT KHO'!$A$4:$A$97,$G47)*$S47 -> 1.2244744e+08 | BV47: =SUMIFS('GIÁ XUẤT KHO'!BF$4:BF$97,'GIÁ XUẤT KHO'!$A$4:$A$97,$G47)*$S47 -> 1.2617887e+09 | BW47: =BM47-BF47 -> 0
A48: =_xlfn.XLOOKUP($G48,MD_SKU[Mã SKU],MD_SKU[Link vào file BCQT]) -> Hạt rHDPE thổi | B48: Sales | C48: =IF(LEFT($E48,1)="2","XK","NĐ") -> NĐ | D48: 105223 | 110000339 | E48: 105223 | F48: Dynaplast Bắc Ninh | G48: 110000339 | H48: Hạt nhựa rHDPE MBF01 | J48: DDP | N48: =SUMIFS(Sales!$I$3:$I$100,Sales!$B$3:$B$100,$D48) -> 70000 | R48: =MAX(0,L48+N48-SUM(P48:Q48)) -> 70000 | S48: =SUM(P48:R48) -> 70000 | W48: =1.36*EXR_FC05 -> 35768 | X48: =IFERROR(IF($C48="XK",$AM48/$S48/$AC48,$AM48/$S48),0) -> 35768 | AA48: =IF($C48="NĐ",1,EXR_FC05) -> 1 | AB48: =IF($C48="NĐ",1,EXR_FC05) -> 1 | AC48: =IFERROR(SUMPRODUCT(AJ48:AL48,Z48:AB48)/AM48,0) -> 1 | AG48: =W48*AB48 -> 35768 | AL48: =R48*AG48 -> 2503760000 | AM48: =SUM(AJ48:AL48) -> 2503760000 | AO48: =30*EXR_FC05/1000 -> 789 | AS48: =AO48*R48 -> 55230000 | AT48: =SUM(AQ48:AS48) -> 55230000 | BA48: =SUM(AX48:AZ48) -> 0 | BE48: =_xlfn.XLOOKUP($G48,'GIÁ XUẤT KHO'!$A$4:$A$97,'GIÁ XUẤT KHO'!$AW$4:$AW$97)*R48 -> 2.0991777e+09 | BF48: =SUM(BC48:BE48) -> 2.0991777e+09 | BI48: =AK48-BD48 -> 0 | BJ48: =AL48-BE48 -> 4.0458225e+08 | BK48: =SUM(BH48:BJ48) -> 4.0458225e+08 | BM48: =SUM(BN48:BV48) -> 2.0991777e+09 | BN48: =SUMIFS('GIÁ XUẤT KHO'!AX$4:AX$97,'GIÁ XUẤT KHO'!$A$4:$A$97,$G48)*$S48 -> 1.5221429e+09 | BO48: =SUMIFS('GIÁ XUẤT KHO'!AY$4:AY$97,'GIÁ XUẤT KHO'!$A$4:$A$97,$G48)*$S48 -> 32737239 | BP48: =SUMIFS('GIÁ XUẤT KHO'!AZ$4:AZ$97,'GIÁ XUẤT KHO'!$A$4:$A$97,$G48)*$S48 -> 55332772 | BQ48: =SUMIFS('GIÁ XUẤT KHO'!BA$4:BA$97,'GIÁ XUẤT KHO'!$A$4:$A$97,$G48)*$S48 -> 93971028 | BR48: =SUMIFS('GIÁ XUẤT KHO'!BB$4:BB$97,'GIÁ XUẤT KHO'!$A$4:$A$97,$G48)*$S48 -> 16760157 | BS48: =SUMIFS('GIÁ XUẤT KHO'!BC$4:BC$97,'GIÁ XUẤT KHO'!$A$4:$A$97,$G48)*$S48 -> 1.092989e+08 | BT48: =SUMIFS('GIÁ XUẤT KHO'!BD$4:BD$97,'GIÁ XUẤT KHO'!$A$4:$A$97,$G48)*$S48 -> 98956371 | BU48: =SUMIFS('GIÁ XUẤT KHO'!BE$4:BE$97,'GIÁ XUẤT KHO'!$A$4:$A$97,$G48)*$S48 -> 30865470 | BV48: =SUMIFS('GIÁ XUẤT KHO'!BF$4:BF$97,'GIÁ XUẤT KHO'!$A$4:$A$97,$G48)*$S48 -> 1.3911289e+08 | BW48: =BM48-BF48 -> 0
A49: =_xlfn.XLOOKUP($G49,MD_SKU[Mã SKU],MD_SKU[Link vào file BCQT]) -> Vảy rHDPE ép | B49: Sales | C49: =IF(LEFT($E49,1)="2","XK","NĐ") -> NĐ | D49: 105248 | 110000407 | E49: 105248 | F49: ĐẠI NHẤT LONG | G49: 110000407 | H49: Vảy HD Ép Đỏ | J49: EXW | N49: =SUMIFS(Sales!$I$3:$I$100,Sales!$B$3:$B$100,$D49) -> 6000 | R49: =MAX(0,L49+N49-SUM(P49:Q49)) -> 6000 | S49: =SUM(P49:R49) -> 6000 | W49: =1.16*EXR_FC05 -> 30508 | X49: =IFERROR(IF($C49="XK",$AM49/$S49/$AC49,$AM49/$S49),0) -> 30508 | AA49: =IF($C49="NĐ",1,EXR_FC05) -> 1 | AB49: =IF($C49="NĐ",1,EXR_FC05) -> 1 | AC49: =IFERROR(SUMPRODUCT(AJ49:AL49,Z49:AB49)/AM49,0) -> 1 | AG49: =W49*AB49 -> 30508 | AL49: =R49*AG49 -> 1.83048e+08 | AM49: =SUM(AJ49:AL49) -> 1.83048e+08 | AS49: =AO49*R49 -> 0 | AT49: =SUM(AQ49:AS49) -> 0 | BA49: =SUM(AX49:AZ49) -> 0 | BE49: =_xlfn.XLOOKUP($G49,'GIÁ XUẤT KHO'!$A$4:$A$97,'GIÁ XUẤT KHO'!$AW$4:$AW$97)*R49 -> 3.1712781e+08 | BF49: =SUM(BC49:BE49) -> 3.1712781e+08 | BI49: =AK49-BD49 -> 0 | BJ49: =AL49-BE49 -> -1.3407981e+08 | BK49: =SUM(BH49:BJ49) -> -1.3407981e+08 | BM49: =SUM(BN49:BV49) -> 3.1712781e+08 | BN49: =SUMIFS('GIÁ XUẤT KHO'!AX$4:AX$97,'GIÁ XUẤT KHO'!$A$4:$A$97,$G49)*$S49 -> 1.149872e+08 | BO49: =SUMIFS('GIÁ XUẤT KHO'!AY$4:AY$97,'GIÁ XUẤT KHO'!$A$4:$A$97,$G49)*$S49 -> 58105.174 | BP49: =SUMIFS('GIÁ XUẤT KHO'!AZ$4:AZ$97,'GIÁ XUẤT KHO'!$A$4:$A$97,$G49)*$S49 -> 995527.63 | BQ49: =SUMIFS('GIÁ XUẤT KHO'!BA$4:BA$97,'GIÁ XUẤT KHO'!$A$4:$A$97,$G49)*$S49 -> 24231427 | BR49: =SUMIFS('GIÁ XUẤT KHO'!BB$4:BB$97,'GIÁ XUẤT KHO'!$A$4:$A$97,$G49)*$S49 -> 2604831.4 | BS49: =SUMIFS('GIÁ XUẤT KHO'!BC$4:BC$97,'GIÁ XUẤT KHO'!$A$4:$A$97,$G49)*$S49 -> 48855797 | BT49: =SUMIFS('GIÁ XUẤT KHO'!BD$4:BD$97,'GIÁ XUẤT KHO'!$A$4:$A$97,$G49)*$S49 -> 44576989 | BU49: =SUMIFS('GIÁ XUẤT KHO'!BE$4:BE$97,'GIÁ XUẤT KHO'!$A$4:$A$97,$G49)*$S49 -> 23497279 | BV49: =SUMIFS('GIÁ XUẤT KHO'!BF$4:BF$97,'GIÁ XUẤT KHO'!$A$4:$A$97,$G49)*$S49 -> 57320654 | BW49: =BM49-BF49 -> 0
A50: =_xlfn.XLOOKUP($G50,MD_SKU[Mã SKU],MD_SKU[Link vào file BCQT]) -> Vảy rPP | B50: Sales | C50: =IF(LEFT($E50,1)="2","XK","NĐ") -> NĐ | D50: 105248 | 110000421 | E50: 105248 | F50: ĐẠI NHẤT LONG | G50: 110000421 | H50: Vảy PP Đỏ Nhạt | J50: EXW | N50: =SUMIFS(Sales!$I$3:$I$100,Sales!$B$3:$B$100,$D50) -> 11000 | R50: =MAX(0,L50+N50-SUM(P50:Q50)) -> 11000 | S50: =SUM(P50:R50) -> 11000 | W50: =1.12*EXR_FC05 -> 29456 | X50: =IFERROR(IF($C50="XK",$AM50/$S50/$AC50,$AM50/$S50),0) -> 29456 | AA50: =IF($C50="NĐ",1,EXR_FC05) -> 1 | AB50: =IF($C50="NĐ",1,EXR_FC05) -> 1 | AC50: =IFERROR(SUMPRODUCT(AJ50:AL50,Z50:AB50)/AM50,0) -> 1 | AG50: =W50*AB50 -> 29456 | AL50: =R50*AG50 -> 3.24016e+08 | AM50: =SUM(AJ50:AL50) -> 3.24016e+08 | AS50: =AO50*R50 -> 0 | AT50: =SUM(AQ50:AS50) -> 0 | BA50: =SUM(AX50:AZ50) -> 0 | BE50: =_xlfn.XLOOKUP($G50,'GIÁ XUẤT KHO'!$A$4:$A$97,'GIÁ XUẤT KHO'!$AW$4:$AW$97)*R50 -> 2.2421588e+08 | BF50: =SUM(BC50:BE50) -> 2.2421588e+08 | BI50: =AK50-BD50 -> 0 | BJ50: =AL50-BE50 -> 99800117 | BK50: =SUM(BH50:BJ50) -> 99800117 | BM50: =SUM(BN50:BV50) -> 2.2421588e+08 | BN50: =SUMIFS('GIÁ XUẤT KHO'!AX$4:AX$97,'GIÁ XUẤT KHO'!$A$4:$A$97,$G50)*$S50 -> 2.0203703e+08 | BO50: =SUMIFS('GIÁ XUẤT KHO'!AY$4:AY$97,'GIÁ XUẤT KHO'!$A$4:$A$97,$G50)*$S50 -> 1411297.6 | BP50: =SUMIFS('GIÁ XUẤT KHO'!AZ$4:AZ$97,'GIÁ XUẤT KHO'!$A$4:$A$97,$G50)*$S50 -> 2736.2665 | BQ50: =SUMIFS('GIÁ XUẤT KHO'!BA$4:BA$97,'GIÁ XUẤT KHO'!$A$4:$A$97,$G50)*$S50 -> 1867707.4 | BR50: =SUMIFS('GIÁ XUẤT KHO'!BB$4:BB$97,'GIÁ XUẤT KHO'!$A$4:$A$97,$G50)*$S50 -> 7707.7377 | BS50: =SUMIFS('GIÁ XUẤT KHO'!BC$4:BC$97,'GIÁ XUẤT KHO'!$A$4:$A$97,$G50)*$S50 -> 3679526.8 | BT50: =SUMIFS('GIÁ XUẤT KHO'!BD$4:BD$97,'GIÁ XUẤT KHO'!$A$4:$A$97,$G50)*$S50 -> 5270482.4 | BU50: =SUMIFS('GIÁ XUẤT KHO'!BE$4:BE$97,'GIÁ XUẤT KHO'!$A$4:$A$97,$G50)*$S50 -> 3496328.8 | BV50: =SUMIFS('GIÁ XUẤT KHO'!BF$4:BF$97,'GIÁ XUẤT KHO'!$A$4:$A$97,$G50)*$S50 -> 6443063.3 | BW50: =BM50-BF50 -> 0
A51: =_xlfn.XLOOKUP($G51,MD_SKU[Mã SKU],MD_SKU[Link vào file BCQT]) -> Hạt rHDPE thổi | B51: Sales | C51: =IF(LEFT($E51,1)="2","XK","NĐ") -> NĐ | D51: 105263 | 110000339 | E51: 105263 | F51: Unilever Duy Tân | G51: 110000339 | H51: Hạt nhựa rHDPE MBF01 | J51: EXW | N51: =SUMIFS(Sales!$I$3:$I$100,Sales!$B$3:$B$100,$D51) -> 215000 | R51: =MAX(0,L51+N51-SUM(P51:Q51)) -> 215000 | S51: =SUM(P51:R51) -> 215000 | W51: =V36 -> 31513 | X51: =IFERROR(IF($C51="XK",$AM51/$S51/$AC51,$AM51/$S51),0) -> 31513 | AA51: =IF($C51="NĐ",1,EXR_FC05) -> 1 | AB51: =IF($C51="NĐ",1,EXR_FC05) -> 1 | AC51: =IFERROR(SUMPRODUCT(AJ51:AL51,Z51:AB51)/AM51,0) -> 1 | AG51: =W51*AB51 -> 31513 | AL51: =R51*AG51 -> 6775295000 | AM51: =SUM(AJ51:AL51) -> 6775295000 | AS51: =AO51*R51 -> 0 | AT51: =SUM(AQ51:AS51) -> 0 | BA51: =SUM(AX51:AZ51) -> 0 | BE51: =_xlfn.XLOOKUP($G51,'GIÁ XUẤT KHO'!$A$4:$A$97,'GIÁ XUẤT KHO'!$AW$4:$AW$97)*R51 -> 6.4474745e+09 | BF51: =SUM(BC51:BE51) -> 6.4474745e+09 | BI51: =AK51-BD51 -> 0 | BJ51: =AL51-BE51 -> 3.2782049e+08 | BK51: =SUM(BH51:BJ51) -> 3.2782049e+08 | BM51: =SUM(BN51:BV51) -> 6.4474745e+09 | BN51: =SUMIFS('GIÁ XUẤT KHO'!AX$4:AX$97,'GIÁ XUẤT KHO'!$A$4:$A$97,$G51)*$S51 -> 4.6751533e+09 | BO51: =SUMIFS('GIÁ XUẤT KHO'!AY$4:AY$97,'GIÁ XUẤT KHO'!$A$4:$A$97,$G51)*$S51 -> 1.0055009e+08 | BP51: =SUMIFS('GIÁ XUẤT KHO'!AZ$4:AZ$97,'GIÁ XUẤT KHO'!$A$4:$A$97,$G51)*$S51 -> 1.6995066e+08 | BQ51: =SUMIFS('GIÁ XUẤT KHO'!BA$4:BA$97,'GIÁ XUẤT KHO'!$A$4:$A$97,$G51)*$S51 -> 2.886253e+08 | BR51: =SUMIFS('GIÁ XUẤT KHO'!BB$4:BB$97,'GIÁ XUẤT KHO'!$A$4:$A$97,$G51)*$S51 -> 51477624 | BS51: =SUMIFS('GIÁ XUẤT KHO'!BC$4:BC$97,'GIÁ XUẤT KHO'!$A$4:$A$97,$G51)*$S51 -> 3.3570376e+08 | BT51: =SUMIFS('GIÁ XUẤT KHO'!BD$4:BD$97,'GIÁ XUẤT KHO'!$A$4:$A$97,$G51)*$S51 -> 3.0393743e+08 | BU51: =SUMIFS('GIÁ XUẤT KHO'!BE$4:BE$97,'GIÁ XUẤT KHO'!$A$4:$A$97,$G51)*$S51 -> 94801087 | BV51: =SUMIFS('GIÁ XUẤT KHO'!BF$4:BF$97,'GIÁ XUẤT KHO'!$A$4:$A$97,$G51)*$S51 -> 4.2727529e+08 | BW51: =BM51-BF51 -> 0
A52: =_xlfn.XLOOKUP($G52,MD_SKU[Mã SKU],MD_SKU[Link vào file BCQT]) -> Hạt rHDPE thổi | B52: Sales | C52: =IF(LEFT($E52,1)="2","XK","NĐ") -> NĐ | D52: 105263 | 110000481 | E52: 105263 | F52: Unilever Duy Tân | G52: 110000481 | H52: Hạt nhựa rHDPE PCF01 | J52: EXW | N52: =SUMIFS(Sales!$I$3:$I$100,Sales!$B$3:$B$100,$D52) -> 50000 | R52: =MAX(0,L52+N52-SUM(P52:Q52)) -> 50000 | S52: =SUM(P52:R52) -> 50000 | W52: =W51 -> 31513 | X52: =IFERROR(IF($C52="XK",$AM52/$S52/$AC52,$AM52/$S52),0) -> 31513 | AA52: =IF($C52="NĐ",1,EXR_FC05) -> 1 | AB52: =IF($C52="NĐ",1,EXR_FC05) -> 1 | AC52: =IFERROR(SUMPRODUCT(AJ52:AL52,Z52:AB52)/AM52,0) -> 1 | AG52: =W52*AB52 -> 31513 | AL52: =R52*AG52 -> 1575650000 | AM52: =SUM(AJ52:AL52) -> 1575650000 | AS52: =AO52*R52 -> 0 | AT52: =SUM(AQ52:AS52) -> 0 | BA52: =SUM(AX52:AZ52) -> 0 | BE52: =_xlfn.XLOOKUP($G52,'GIÁ XUẤT KHO'!$A$4:$A$97,'GIÁ XUẤT KHO'!$AW$4:$AW$97)*R52 -> 1.4010647e+09 | BF52: =SUM(BC52:BE52) -> 1.4010647e+09 | BI52: =AK52-BD52 -> 0 | BJ52: =AL52-BE52 -> 1.7458528e+08 | BK52: =SUM(BH52:BJ52) -> 1.7458528e+08 | BM52: =SUM(BN52:BV52) -> 1.4010647e+09 | BN52: =SUMIFS('GIÁ XUẤT KHO'!AX$4:AX$97,'GIÁ XUẤT KHO'!$A$4:$A$97,$G52)*$S52 -> 1.0270757e+09 | BO52: =SUMIFS('GIÁ XUẤT KHO'!AY$4:AY$97,'GIÁ XUẤT KHO'!$A$4:$A$97,$G52)*$S52 -> 10687636 | BP52: =SUMIFS('GIÁ XUẤT KHO'!AZ$4:AZ$97,'GIÁ XUẤT KHO'!$A$4:$A$97,$G52)*$S52 -> 59637559 | BQ52: =SUMIFS('GIÁ XUẤT KHO'!BA$4:BA$97,'GIÁ XUẤT KHO'!$A$4:$A$97,$G52)*$S52 -> 58363455 | BR52: =SUMIFS('GIÁ XUẤT KHO'!BB$4:BB$97,'GIÁ XUẤT KHO'!$A$4:$A$97,$G52)*$S52 -> 10059180 | BS52: =SUMIFS('GIÁ XUẤT KHO'!BC$4:BC$97,'GIÁ XUẤT KHO'!$A$4:$A$97,$G52)*$S52 -> 68924277 | BT52: =SUMIFS('GIÁ XUẤT KHO'!BD$4:BD$97,'GIÁ XUẤT KHO'!$A$4:$A$97,$G52)*$S52 -> 60648133 | BU52: =SUMIFS('GIÁ XUẤT KHO'!BE$4:BE$97,'GIÁ XUẤT KHO'!$A$4:$A$97,$G52)*$S52 -> 7519548.2 | BV52: =SUMIFS('GIÁ XUẤT KHO'!BF$4:BF$97,'GIÁ XUẤT KHO'!$A$4:$A$97,$G52)*$S52 -> 98149231 | BW52: =BM52-BF52 -> 0
A53: =_xlfn.XLOOKUP($G53,MD_SKU[Mã SKU],MD_SKU[Link vào file BCQT]) -> Hạt rPET | B53: Sales | C53: =IF(LEFT($E53,1)="2","XK","NĐ") -> NĐ | D53: 105266 | 110000354 | E53: 105266 | F53: MIDA | G53: 110000354 | H53: Hạt nhựa rPET WSS01G | J53: EXW | N53: =SUMIFS(Sales!$I$3:$I$100,Sales!$B$3:$B$100,$D53) -> 18150 | R53: =MAX(0,L53+N53-SUM(P53:Q53)) -> 18150 | S53: =SUM(P53:R53) -> 18150 | W53: =1.28*EXR_FC05 -> 33664 | X53: =IFERROR(IF($C53="XK",$AM53/$S53/$AC53,$AM53/$S53),0) -> 33664 | AA53: =IF($C53="NĐ",1,EXR_FC05) -> 1 | AB53: =IF($C53="NĐ",1,EXR_FC05) -> 1 | AC53: =IFERROR(SUMPRODUCT(AJ53:AL53,Z53:AB53)/AM53,0) -> 1 | AG53: =W53*AB53 -> 33664 | AL53: =R53*AG53 -> 611001600 | AM53: =SUM(AJ53:AL53) -> 611001600 | AS53: =AO53*R53 -> 0 | AT53: =SUM(AQ53:AS53) -> 0 | BA53: =SUM(AX53:AZ53) -> 0 | BE53: =_xlfn.XLOOKUP($G53,'GIÁ XUẤT KHO'!$A$4:$A$97,'GIÁ XUẤT KHO'!$AW$4:$AW$97)*R53 -> 4.5262182e+08 | BF53: =SUM(BC53:BE53) -> 4.5262182e+08 | BI53: =AK53-BD53 -> 0 | BJ53: =AL53-BE53 -> 1.5837978e+08 | BK53: =SUM(BH53:BJ53) -> 1.5837978e+08 | BM53: =SUM(BN53:BV53) -> 4.5262182e+08 | BN53: =SUMIFS('GIÁ XUẤT KHO'!AX$4:AX$97,'GIÁ XUẤT KHO'!$A$4:$A$97,$G53)*$S53 -> 3.2684868e+08 | BO53: =SUMIFS('GIÁ XUẤT KHO'!AY$4:AY$97,'GIÁ XUẤT KHO'!$A$4:$A$97,$G53)*$S53 -> 3319876.3 | BP53: =SUMIFS('GIÁ XUẤT KHO'!AZ$4:AZ$97,'GIÁ XUẤT KHO'!$A$4:$A$97,$G53)*$S53 -> 1746.631 | BQ53: =SUMIFS('GIÁ XUẤT KHO'!BA$4:BA$97,'GIÁ XUẤT KHO'!$A$4:$A$97,$G53)*$S53 -> 23205695 | BR53: =SUMIFS('GIÁ XUẤT KHO'!BB$4:BB$97,'GIÁ XUẤT KHO'!$A$4:$A$97,$G53)*$S53 -> 3186893.3 | BS53: =SUMIFS('GIÁ XUẤT KHO'!BC$4:BC$97,'GIÁ XUẤT KHO'!$A$4:$A$97,$G53)*$S53 -> 13092172 | BT53: =SUMIFS('GIÁ XUẤT KHO'!BD$4:BD$97,'GIÁ XUẤT KHO'!$A$4:$A$97,$G53)*$S53 -> 21059044 | BU53: =SUMIFS('GIÁ XUẤT KHO'!BE$4:BE$97,'GIÁ XUẤT KHO'!$A$4:$A$97,$G53)*$S53 -> 5726555.8 | BV53: =SUMIFS('GIÁ XUẤT KHO'!BF$4:BF$97,'GIÁ XUẤT KHO'!$A$4:$A$97,$G53)*$S53 -> 56181156 | BW53: =BM53-BF53 -> 0
A54: =_xlfn.XLOOKUP($G54,MD_SKU[Mã SKU],MD_SKU[Link vào file BCQT]) -> Hạt rPET | B54: Sales | C54: =IF(LEFT($E54,1)="2","XK","NĐ") -> NĐ | D54: 105286 | 110000355 | E54: 105286 | F54: Mondelez - Việt Thành | G54: 110000355 | H54: Hạt nhựa rPET iSS01G | J54: EXW | N54: =SUMIFS(Sales!$I$3:$I$100,Sales!$B$3:$B$100,$D54) -> 44000 | R54: =MAX(0,L54+N54-SUM(P54:Q54)) -> 44000 | S54: =SUM(P54:R54) -> 44000 | W54: =1.31*EXR_FC05 -> 34453 | X54: =IFERROR(IF($C54="XK",$AM54/$S54/$AC54,$AM54/$S54),0) -> 34453 | AA54: =IF($C54="NĐ",1,EXR_FC05) -> 1 | AB54: =IF($C54="NĐ",1,EXR_FC05) -> 1 | AC54: =IFERROR(SUMPRODUCT(AJ54:AL54,Z54:AB54)/AM54,0) -> 1 | AG54: =W54*AB54 -> 34453 | AL54: =R54*AG54 -> 1515932000 | AM54: =SUM(AJ54:AL54) -> 1515932000 | AS54: =AO54*R54 -> 0 | AT54: =SUM(AQ54:AS54) -> 0 | BA54: =SUM(AX54:AZ54) -> 0 | BE54: =_xlfn.XLOOKUP($G54,'GIÁ XUẤT KHO'!$A$4:$A$97,'GIÁ XUẤT KHO'!$AW$4:$AW$97)*R54 -> 1.1512199e+09 | BF54: =SUM(BC54:BE54) -> 1.1512199e+09 | BI54: =AK54-BD54 -> 0 | BJ54: =AL54-BE54 -> 3.6471215e+08 | BK54: =SUM(BH54:BJ54) -> 3.6471215e+08 | BM54: =SUM(BN54:BV54) -> 1.1512199e+09 | BN54: =SUMIFS('GIÁ XUẤT KHO'!AX$4:AX$97,'GIÁ XUẤT KHO'!$A$4:$A$97,$G54)*$S54 -> 8.5616315e+08 | BO54: =SUMIFS('GIÁ XUẤT KHO'!AY$4:AY$97,'GIÁ XUẤT KHO'!$A$4:$A$97,$G54)*$S54 -> 7440302.7 | BP54: =SUMIFS('GIÁ XUẤT KHO'!AZ$4:AZ$97,'GIÁ XUẤT KHO'!$A$4:$A$97,$G54)*$S54 -> 1481.9451 | BQ54: =SUMIFS('GIÁ XUẤT KHO'!BA$4:BA$97,'GIÁ XUẤT KHO'!$A$4:$A$97,$G54)*$S54 -> 35130746 | BR54: =SUMIFS('GIÁ XUẤT KHO'!BB$4:BB$97,'GIÁ XUẤT KHO'!$A$4:$A$97,$G54)*$S54 -> 10207463 | BS54: =SUMIFS('GIÁ XUẤT KHO'!BC$4:BC$97,'GIÁ XUẤT KHO'!$A$4:$A$97,$G54)*$S54 -> 19052298 | BT54: =SUMIFS('GIÁ XUẤT KHO'!BD$4:BD$97,'GIÁ XUẤT KHO'!$A$4:$A$97,$G54)*$S54 -> 64856869 | BU54: =SUMIFS('GIÁ XUẤT KHO'!BE$4:BE$97,'GIÁ XUẤT KHO'!$A$4:$A$97,$G54)*$S54 -> 3361358.4 | BV54: =SUMIFS('GIÁ XUẤT KHO'!BF$4:BF$97,'GIÁ XUẤT KHO'!$A$4:$A$97,$G54)*$S54 -> 1.5500619e+08 | BW54: =BM54-BF54 -> 0
A55: =_xlfn.XLOOKUP($G55,MD_SKU[Mã SKU],MD_SKU[Link vào file BCQT]) -> Hạt rPET | B55: Sales | C55: =IF(LEFT($E55,1)="2","XK","NĐ") -> NĐ | D55: 105291 | 110000354 | E55: 105291 | F55: AN NHẬT | G55: 110000354 | H55: Hạt nhựa rPET WSS01G | J55: EXW | N55: =SUMIFS(Sales!$I$3:$I$100,Sales!$B$3:$B$100,$D55) -> 4400 | R55: =MAX(0,L55+N55-SUM(P55:Q55)) -> 4400 | S55: =SUM(P55:R55) -> 4400 | W55: =1.28*EXR_FC05 -> 33664 | X55: =IFERROR(IF($C55="XK",$AM55/$S55/$AC55,$AM55/$S55),0) -> 33664 | AA55: =IF($C55="NĐ",1,EXR_FC05) -> 1 | AB55: =IF($C55="NĐ",1,EXR_FC05) -> 1 | AC55: =IFERROR(SUMPRODUCT(AJ55:AL55,Z55:AB55)/AM55,0) -> 1 | AG55: =W55*AB55 -> 33664 | AL55: =R55*AG55 -> 148121600 | AM55: =SUM(AJ55:AL55) -> 148121600 | AS55: =AO55*R55 -> 0 | AT55: =SUM(AQ55:AS55) -> 0 | BA55: =SUM(AX55:AZ55) -> 0 | BE55: =_xlfn.XLOOKUP($G55,'GIÁ XUẤT KHO'!$A$4:$A$97,'GIÁ XUẤT KHO'!$AW$4:$AW$97)*R55 -> 1.097265e+08 | BF55: =SUM(BC55:BE55) -> 1.097265e+08 | BI55: =AK55-BD55 -> 0 | BJ55: =AL55-BE55 -> 38395099 | BK55: =SUM(BH55:BJ55) -> 38395099 | BM55: =SUM(BN55:BV55) -> 1.097265e+08 | BN55: =SUMIFS('GIÁ XUẤT KHO'!AX$4:AX$97,'GIÁ XUẤT KHO'!$A$4:$A$97,$G55)*$S55 -> 79236043 | BO55: =SUMIFS('GIÁ XUẤT KHO'!AY$4:AY$97,'GIÁ XUẤT KHO'!$A$4:$A$97,$G55)*$S55 -> 804818.5 | BP55: =SUMIFS('GIÁ XUẤT KHO'!AZ$4:AZ$97,'GIÁ XUẤT KHO'!$A$4:$A$97,$G55)*$S55 -> 423.42569 | BQ55: =SUMIFS('GIÁ XUẤT KHO'!BA$4:BA$97,'GIÁ XUẤT KHO'!$A$4:$A$97,$G55)*$S55 -> 5625623.2 | BR55: =SUMIFS('GIÁ XUẤT KHO'!BB$4:BB$97,'GIÁ XUẤT KHO'!$A$4:$A$97,$G55)*$S55 -> 772580.2 | BS55: =SUMIFS('GIÁ XUẤT KHO'!BC$4:BC$97,'GIÁ XUẤT KHO'!$A$4:$A$97,$G55)*$S55 -> 3173859.8 | BT55: =SUMIFS('GIÁ XUẤT KHO'!BD$4:BD$97,'GIÁ XUẤT KHO'!$A$4:$A$97,$G55)*$S55 -> 5105222.9 | BU55: =SUMIFS('GIÁ XUẤT KHO'!BE$4:BE$97,'GIÁ XUẤT KHO'!$A$4:$A$97,$G55)*$S55 -> 1388255.9 | BV55: =SUMIFS('GIÁ XUẤT KHO'!BF$4:BF$97,'GIÁ XUẤT KHO'!$A$4:$A$97,$G55)*$S55 -> 13619674 | BW55: =BM55-BF55 -> 0
A56: =_xlfn.XLOOKUP($G56,MD_SKU[Mã SKU],MD_SKU[Link vào file BCQT]) -> Hạt rHDPE thổi | B56: Sales | C56: =IF(LEFT($E56,1)="2","XK","NĐ") -> NĐ | D56: 105314 | 110000374 | E56: 105314 | F56: VILUBE - DTP | G56: 110000374 | H56: Hạt nhựa rHDPE rHDB03N02 | J56: EXW | N56: =SUMIFS(Sales!$I$3:$I$100,Sales!$B$3:$B$100,$D56) -> 68750 | R56: =MAX(0,L56+N56-SUM(P56:Q56)) -> 68750 | S56: =SUM(P56:R56) -> 68750 | W56: =1.3*EXR_FC05 -> 34190 | X56: =IFERROR(IF($C56="XK",$AM56/$S56/$AC56,$AM56/$S56),0) -> 34190 | AA56: =IF($C56="NĐ",1,EXR_FC05) -> 1 | AB56: =IF($C56="NĐ",1,EXR_FC05) -> 1 | AC56: =IFERROR(SUMPRODUCT(AJ56:AL56,Z56:AB56)/AM56,0) -> 1 | AG56: =W56*AB56 -> 34190 | AL56: =R56*AG56 -> 2350562500 | AM56: =SUM(AJ56:AL56) -> 2350562500 | AS56: =AO56*R56 -> 0 | AT56: =SUM(AQ56:AS56) -> 0 | BA56: =SUM(AX56:AZ56) -> 0 | BE56: =_xlfn.XLOOKUP($G56,'GIÁ XUẤT KHO'!$A$4:$A$97,'GIÁ XUẤT KHO'!$AW$4:$AW$97)*R56 -> 1.9180129e+09 | BF56: =SUM(BC56:BE56) -> 1.9180129e+09 | BI56: =AK56-BD56 -> 0 | BJ56: =AL56-BE56 -> 4.3254958e+08 | BK56: =SUM(BH56:BJ56) -> 4.3254958e+08 | BM56: =SUM(BN56:BV56) -> 1.9180129e+09 | BN56: =SUMIFS('GIÁ XUẤT KHO'!AX$4:AX$97,'GIÁ XUẤT KHO'!$A$4:$A$97,$G56)*$S56 -> 1.3958275e+09 | BO56: =SUMIFS('GIÁ XUẤT KHO'!AY$4:AY$97,'GIÁ XUẤT KHO'!$A$4:$A$97,$G56)*$S56 -> 12162218 | BP56: =SUMIFS('GIÁ XUẤT KHO'!AZ$4:AZ$97,'GIÁ XUẤT KHO'!$A$4:$A$97,$G56)*$S56 -> 9019078.8 | BQ56: =SUMIFS('GIÁ XUẤT KHO'!BA$4:BA$97,'GIÁ XUẤT KHO'!$A$4:$A$97,$G56)*$S56 -> 1.6823721e+08 | BR56: =SUMIFS('GIÁ XUẤT KHO'!BB$4:BB$97,'GIÁ XUẤT KHO'!$A$4:$A$97,$G56)*$S56 -> 12512247 | BS56: =SUMIFS('GIÁ XUẤT KHO'!BC$4:BC$97,'GIÁ XUẤT KHO'!$A$4:$A$97,$G56)*$S56 -> 59506532 | BT56: =SUMIFS('GIÁ XUẤT KHO'!BD$4:BD$97,'GIÁ XUẤT KHO'!$A$4:$A$97,$G56)*$S56 -> 75427184 | BU56: =SUMIFS('GIÁ XUẤT KHO'!BE$4:BE$97,'GIÁ XUẤT KHO'!$A$4:$A$97,$G56)*$S56 -> 53730222 | BV56: =SUMIFS('GIÁ XUẤT KHO'!BF$4:BF$97,'GIÁ XUẤT KHO'!$A$4:$A$97,$G56)*$S56 -> 1.3159074e+08 | BW56: =BM56-BF56 -> 0
A57: =_xlfn.XLOOKUP($G57,MD_SKU[Mã SKU],MD_SKU[Link vào file BCQT]) -> Hạt rPET | B57: Sales | C57: =IF(LEFT($E57,1)="2","XK","NĐ") -> NĐ | D57: 105315 | 110000355 | E57: 105315 | F57: Kao Viet Nam | G57: 110000355 | H57: Hạt nhựa rPET iSS01G | J57: EXW | N57: =SUMIFS(Sales!$I$3:$I$100,Sales!$B$3:$B$100,$D57) -> 3000 | R57: =MAX(0,L57+N57-SUM(P57:Q57)) -> 3000 | S57: =SUM(P57:R57) -> 3000 | W57: =1.31*EXR_FC05 -> 34453 | X57: =IFERROR(IF($C57="XK",$AM57/$S57/$AC57,$AM57/$S57),0) -> 34453 | AA57: =IF($C57="NĐ",1,EXR_FC05) -> 1 | AB57: =IF($C57="NĐ",1,EXR_FC05) -> 1 | AC57: =IFERROR(SUMPRODUCT(AJ57:AL57,Z57:AB57)/AM57,0) -> 1 | AG57: =W57*AB57 -> 34453 | AL57: =R57*AG57 -> 103359000 | AM57: =SUM(AJ57:AL57) -> 103359000 | AS57: =AO57*R57 -> 0 | AT57: =SUM(AQ57:AS57) -> 0 | BA57: =SUM(AX57:AZ57) -> 0 | BE57: =_xlfn.XLOOKUP($G57,'GIÁ XUẤT KHO'!$A$4:$A$97,'GIÁ XUẤT KHO'!$AW$4:$AW$97)*R57 -> 78492263 | BF57: =SUM(BC57:BE57) -> 78492263 | BI57: =AK57-BD57 -> 0 | BJ57: =AL57-BE57 -> 24866737 | BK57: =SUM(BH57:BJ57) -> 24866737 | BM57: =SUM(BN57:BV57) -> 78492263 | BN57: =SUMIFS('GIÁ XUẤT KHO'!AX$4:AX$97,'GIÁ XUẤT KHO'!$A$4:$A$97,$G57)*$S57 -> 58374760 | BO57: =SUMIFS('GIÁ XUẤT KHO'!AY$4:AY$97,'GIÁ XUẤT KHO'!$A$4:$A$97,$G57)*$S57 -> 507293.36 | BP57: =SUMIFS('GIÁ XUẤT KHO'!AZ$4:AZ$97,'GIÁ XUẤT KHO'!$A$4:$A$97,$G57)*$S57 -> 101.04171 | BQ57: =SUMIFS('GIÁ XUẤT KHO'!BA$4:BA$97,'GIÁ XUẤT KHO'!$A$4:$A$97,$G57)*$S57 -> 2395278.1 | BR57: =SUMIFS('GIÁ XUẤT KHO'!BB$4:BB$97,'GIÁ XUẤT KHO'!$A$4:$A$97,$G57)*$S57 -> 695963.4 | BS57: =SUMIFS('GIÁ XUẤT KHO'!BC$4:BC$97,'GIÁ XUẤT KHO'!$A$4:$A$97,$G57)*$S57 -> 1299020.3 | BT57: =SUMIFS('GIÁ XUẤT KHO'!BD$4:BD$97,'GIÁ XUẤT KHO'!$A$4:$A$97,$G57)*$S57 -> 4422059.3 | BU57: =SUMIFS('GIÁ XUẤT KHO'!BE$4:BE$97,'GIÁ XUẤT KHO'!$A$4:$A$97,$G57)*$S57 -> 229183.53 | BV57: =SUMIFS('GIÁ XUẤT KHO'!BF$4:BF$97,'GIÁ XUẤT KHO'!$A$4:$A$97,$G57)*$S57 -> 10568604 | BW57: =BM57-BF57 -> 0
A58: =_xlfn.XLOOKUP($G58,MD_SKU[Mã SKU],MD_SKU[Link vào file BCQT]) -> Hạt rPET | B58: Sales | C58: =IF(LEFT($E58,1)="2","XK","NĐ") -> NĐ | D58: 105328 | 110000332 | E58: 105328 | F58: CN COCA-COLA VN - LONG AN | G58: 110000332 | H58: Hạt nhựa rPET iSS01084G | J58: DDP | N58: =SUMIFS(Sales!$I$3:$I$100,Sales!$B$3:$B$100,$D58) -> 88000 | R58: =MAX(0,L58+N58-SUM(P58:Q58)) -> 88000 | S58: =SUM(P58:R58) -> 88000 | W58: =1.284*EXR_FC05 -> 33769.2 | X58: =IFERROR(IF($C58="XK",$AM58/$S58/$AC58,$AM58/$S58),0) -> 33769.2 | AA58: =IF($C58="NĐ",1,EXR_FC05) -> 1 | AB58: =IF($C58="NĐ",1,EXR_FC05) -> 1 | AC58: =IFERROR(SUMPRODUCT(AJ58:AL58,Z58:AB58)/AM58,0) -> 1 | AG58: =W58*AB58 -> 33769.2 | AL58: =R58*AG58 -> 2.9716896e+09 | AM58: =SUM(AJ58:AL58) -> 2.9716896e+09 | AO58: =10*EXR_FC05/1000 -> 263 | AS58: =AO58*R58 -> 23144000 | AT58: =SUM(AQ58:AS58) -> 23144000 | BA58: =SUM(AX58:AZ58) -> 0 | BE58: =_xlfn.XLOOKUP($G58,'GIÁ XUẤT KHO'!$A$4:$A$97,'GIÁ XUẤT KHO'!$AW$4:$AW$97)*R58 -> 2.4655598e+09 | BF58: =SUM(BC58:BE58) -> 2.4655598e+09 | BI58: =AK58-BD58 -> 0 | BJ58: =AL58-BE58 -> 5.0612981e+08 | BK58: =SUM(BH58:BJ58) -> 5.0612981e+08 | BM58: =SUM(BN58:BV58) -> 2.4655598e+09 | BN58: =SUMIFS('GIÁ XUẤT KHO'!AX$4:AX$97,'GIÁ XUẤT KHO'!$A$4:$A$97,$G58)*$S58 -> 1.4575333e+09 | BO58: =SUMIFS('GIÁ XUẤT KHO'!AY$4:AY$97,'GIÁ XUẤT KHO'!$A$4:$A$97,$G58)*$S58 -> 24217604 | BP58: =SUMIFS('GIÁ XUẤT KHO'!AZ$4:AZ$97,'GIÁ XUẤT KHO'!$A$4:$A$97,$G58)*$S58 -> 9866.9956 | BQ58: =SUMIFS('GIÁ XUẤT KHO'!BA$4:BA$97,'GIÁ XUẤT KHO'!$A$4:$A$97,$G58)*$S58 -> 1.6083751e+08 | BR58: =SUMIFS('GIÁ XUẤT KHO'!BB$4:BB$97,'GIÁ XUẤT KHO'!$A$4:$A$97,$G58)*$S58 -> 19037093 | BS58: =SUMIFS('GIÁ XUẤT KHO'!BC$4:BC$97,'GIÁ XUẤT KHO'!$A$4:$A$97,$G58)*$S58 -> 1.1509655e+08 | BT58: =SUMIFS('GIÁ XUẤT KHO'!BD$4:BD$97,'GIÁ XUẤT KHO'!$A$4:$A$97,$G58)*$S58 -> 1.8546927e+08 | BU58: =SUMIFS('GIÁ XUẤT KHO'!BE$4:BE$97,'GIÁ XUẤT KHO'!$A$4:$A$97,$G58)*$S58 -> 44526341 | BV58: =SUMIFS('GIÁ XUẤT KHO'!BF$4:BF$97,'GIÁ XUẤT KHO'!$A$4:$A$97,$G58)*$S58 -> 4.5883224e+08 | BW58: =BM58-BF58 -> 0
A59: =_xlfn.XLOOKUP($G59,MD_SKU[Mã SKU],MD_SKU[Link vào file BCQT]) -> Vảy rHDPE ép | B59: Sales | C59: =IF(LEFT($E59,1)="2","XK","NĐ") -> NĐ | D59: 105339 | 110000409 | E59: 105339 | F59: HUY THÀNH | G59: 110000409 | H59: Vảy HD Ép Vàng | J59: EXW | N59: =SUMIFS(Sales!$I$3:$I$100,Sales!$B$3:$B$100,$D59) -> 11000 | R59: =MAX(0,L59+N59-SUM(P59:Q59)) -> 11000 | S59: =SUM(P59:R59) -> 11000 | W59: =1.12*EXR_FC05 -> 29456 | X59: =IFERROR(IF($C59="XK",$AM59/$S59/$AC59,$AM59/$S59),0) -> 29456 | AA59: =IF($C59="NĐ",1,EXR_FC05) -> 1 | AB59: =IF($C59="NĐ",1,EXR_FC05) -> 1 | AC59: =IFERROR(SUMPRODUCT(AJ59:AL59,Z59:AB59)/AM59,0) -> 1 | AG59: =W59*AB59 -> 29456 | AL59: =R59*AG59 -> 3.24016e+08 | AM59: =SUM(AJ59:AL59) -> 3.24016e+08 | AS59: =AO59*R59 -> 0 | AT59: =SUM(AQ59:AS59) -> 0 | AZ59: =700*R59 -> 7700000 | BA59: =SUM(AX59:AZ59) -> 7700000 | BE59: =_xlfn.XLOOKUP($G59,'GIÁ XUẤT KHO'!$A$4:$A$97,'GIÁ XUẤT KHO'!$AW$4:$AW$97)*R59 -> 1.714521e+08 | BF59: =SUM(BC59:BE59) -> 1.714521e+08 | BI59: =AK59-BD59 -> 0 | BJ59: =AL59-BE59 -> 1.525639e+08 | BK59: =SUM(BH59:BJ59) -> 1.525639e+08 | BM59: =SUM(BN59:BV59) -> 1.714521e+08 | BN59: =SUMIFS('GIÁ XUẤT KHO'!AX$4:AX$97,'GIÁ XUẤT KHO'!$A$4:$A$97,$G59)*$S59 -> 1.6163235e+08 | BO59: =SUMIFS('GIÁ XUẤT KHO'!AY$4:AY$97,'GIÁ XUẤT KHO'!$A$4:$A$97,$G59)*$S59 -> 0.4840484 | BP59: =SUMIFS('GIÁ XUẤT KHO'!AZ$4:AZ$97,'GIÁ XUẤT KHO'!$A$4:$A$97,$G59)*$S59 -> 0 | BQ59: =SUMIFS('GIÁ XUẤT KHO'!BA$4:BA$97,'GIÁ XUẤT KHO'!$A$4:$A$97,$G59)*$S59 -> 1372461.7 | BR59: =SUMIFS('GIÁ XUẤT KHO'!BB$4:BB$97,'GIÁ XUẤT KHO'!$A$4:$A$97,$G59)*$S59 -> 67073.135 | BS59: =SUMIFS('GIÁ XUẤT KHO'!BC$4:BC$97,'GIÁ XUẤT KHO'!$A$4:$A$97,$G59)*$S59 -> 2617956 | BT59: =SUMIFS('GIÁ XUẤT KHO'!BD$4:BD$97,'GIÁ XUẤT KHO'!$A$4:$A$97,$G59)*$S59 -> 1982673.9 | BU59: =SUMIFS('GIÁ XUẤT KHO'!BE$4:BE$97,'GIÁ XUẤT KHO'!$A$4:$A$97,$G59)*$S59 -> 1222759 | BV59: =SUMIFS('GIÁ XUẤT KHO'!BF$4:BF$97,'GIÁ XUẤT KHO'!$A$4:$A$97,$G59)*$S59 -> 2556831.8 | BW59: =BM59-BF59 -> 0
A60: =_xlfn.XLOOKUP($G60,MD_SKU[Mã SKU],MD_SKU[Link vào file BCQT]) -> Hạt rPP | B60: Sales | C60: =IF(LEFT($E60,1)="2","XK","NĐ") -> NĐ | D60: 105362 | 110000393 | E60: 105362 | F60: Hiệp Thành - IKEA | G60: 110000393 | H60: Hạt nhựa rPP20Be01 | J60: EXW | N60: =SUMIFS(Sales!$I$3:$I$100,Sales!$B$3:$B$100,$D60) -> 15000 | R60: =MAX(0,L60+N60-SUM(P60:Q60)) -> 15000 | S60: =SUM(P60:R60) -> 15000 | W60: =1.19*EXR_FC05 -> 31297 | X60: =IFERROR(IF($C60="XK",$AM60/$S60/$AC60,$AM60/$S60),0) -> 31297 | AA60: =IF($C60="NĐ",1,EXR_FC05) -> 1 | AB60: =IF($C60="NĐ",1,EXR_FC05) -> 1 | AC60: =IFERROR(SUMPRODUCT(AJ60:AL60,Z60:AB60)/AM60,0) -> 1 | AG60: =W60*AB60 -> 31297 | AL60: =R60*AG60 -> 469455000 | AM60: =SUM(AJ60:AL60) -> 469455000 | AS60: =AO60*R60 -> 0 | AT60: =SUM(AQ60:AS60) -> 0 | BA60: =SUM(AX60:AZ60) -> 0 | BE60: =_xlfn.XLOOKUP($G60,'GIÁ XUẤT KHO'!$A$4:$A$97,'GIÁ XUẤT KHO'!$AW$4:$AW$97)*R60 -> 3.3043743e+08 | BF60: =SUM(BC60:BE60) -> 3.3043743e+08 | BI60: =AK60-BD60 -> 0 | BJ60: =AL60-BE60 -> 1.3901757e+08 | BK60: =SUM(BH60:BJ60) -> 1.3901757e+08 | BM60: =SUM(BN60:BV60) -> 3.3043743e+08 | BN60: =SUMIFS('GIÁ XUẤT KHO'!AX$4:AX$97,'GIÁ XUẤT KHO'!$A$4:$A$97,$G60)*$S60 -> 2.140807e+08 | BO60: =SUMIFS('GIÁ XUẤT KHO'!AY$4:AY$97,'GIÁ XUẤT KHO'!$A$4:$A$97,$G60)*$S60 -> 20291236 | BP60: =SUMIFS('GIÁ XUẤT KHO'!AZ$4:AZ$97,'GIÁ XUẤT KHO'!$A$4:$A$97,$G60)*$S60 -> 126.84481 | BQ60: =SUMIFS('GIÁ XUẤT KHO'!BA$4:BA$97,'GIÁ XUẤT KHO'!$A$4:$A$97,$G60)*$S60 -> 13514961 | BR60: =SUMIFS('GIÁ XUẤT KHO'!BB$4:BB$97,'GIÁ XUẤT KHO'!$A$4:$A$97,$G60)*$S60 -> 2961908.1 | BS60: =SUMIFS('GIÁ XUẤT KHO'!BC$4:BC$97,'GIÁ XUẤT KHO'!$A$4:$A$97,$G60)*$S60 -> 15624226 | BT60: =SUMIFS('GIÁ XUẤT KHO'!BD$4:BD$97,'GIÁ XUẤT KHO'!$A$4:$A$97,$G60)*$S60 -> 13552658 | BU60: =SUMIFS('GIÁ XUẤT KHO'!BE$4:BE$97,'GIÁ XUẤT KHO'!$A$4:$A$97,$G60)*$S60 -> 12507484 | BV60: =SUMIFS('GIÁ XUẤT KHO'!BF$4:BF$97,'GIÁ XUẤT KHO'!$A$4:$A$97,$G60)*$S60 -> 37904136 | BW60: =BM60-BF60 -> 0
A61: =_xlfn.XLOOKUP($G61,MD_SKU[Mã SKU],MD_SKU[Link vào file BCQT]) -> Phó sản | B61: Sales | C61: =IF(LEFT($E61,1)="2","XK","NĐ") -> NĐ | D61: 105371 | 160012956 | E61: 105371 | F61: VINAFIBER | G61: 160012956 | H61: Vảy PET Tomra SLR | J61: EXW | N61: =SUMIFS(Sales!$I$3:$I$100,Sales!$B$3:$B$100,$D61) -> 150000 | R61: =MAX(0,L61+N61-SUM(P61:Q61)) -> 150000 | S61: =SUM(P61:R61) -> 150000 | W61: 11111.111 | X61: =IFERROR(IF($C61="XK",$AM61/$S61/$AC61,$AM61/$S61),0) -> 11111.111 | AA61: =IF($C61="NĐ",1,EXR_FC05) -> 1 | AB61: =IF($C61="NĐ",1,EXR_FC05) -> 1 | AC61: =IFERROR(SUMPRODUCT(AJ61:AL61,Z61:AB61)/AM61,0) -> 1 | AG61: =W61*AB61 -> 11111.111 | AL61: =R61*AG61 -> 1.6666667e+09 | AM61: =SUM(AJ61:AL61) -> 1.6666667e+09 | AS61: =AO61*R61 -> 0 | AT61: =SUM(AQ61:AS61) -> 0 | BA61: =SUM(AX61:AZ61) -> 0 | BE61: =_xlfn.XLOOKUP($G61,'GIÁ XUẤT KHO'!$A$4:$A$97,'GIÁ XUẤT KHO'!$AW$4:$AW$97)*R61 -> 1.1443038e+09 | BF61: =SUM(BC61:BE61) -> 1.1443038e+09 | BI61: =AK61-BD61 -> 0 | BJ61: =AL61-BE61 -> 5.2236282e+08 | BK61: =SUM(BH61:BJ61) -> 5.2236282e+08 | BM61: =SUM(BN61:BV61) -> 1.1443038e+09 | BN61: =SUMIFS('GIÁ XUẤT KHO'!AX$4:AX$97,'GIÁ XUẤT KHO'!$A$4:$A$97,$G61)*$S61 -> 1.1443038e+09 | BO61: =SUMIFS('GIÁ XUẤT KHO'!AY$4:AY$97,'GIÁ XUẤT KHO'!$A$4:$A$97,$G61)*$S61 -> 0 | BP61: =SUMIFS('GIÁ XUẤT KHO'!AZ$4:AZ$97,'GIÁ XUẤT KHO'!$A$4:$A$97,$G61)*$S61 -> 0 | BQ61: =SUMIFS('GIÁ XUẤT KHO'!BA$4:BA$97,'GIÁ XUẤT KHO'!$A$4:$A$97,$G61)*$S61 -> 0 | BR61: =SUMIFS('GIÁ XUẤT KHO'!BB$4:BB$97,'GIÁ XUẤT KHO'!$A$4:$A$97,$G61)*$S61 -> 0 | BS61: =SUMIFS('GIÁ XUẤT KHO'!BC$4:BC$97,'GIÁ XUẤT KHO'!$A$4:$A$97,$G61)*$S61 -> 0 | BT61: =SUMIFS('GIÁ XUẤT KHO'!BD$4:BD$97,'GIÁ XUẤT KHO'!$A$4:$A$97,$G61)*$S61 -> 0 | BU61: =SUMIFS('GIÁ XUẤT KHO'!BE$4:BE$97,'GIÁ XUẤT KHO'!$A$4:$A$97,$G61)*$S61 -> 0 | BV61: =SUMIFS('GIÁ XUẤT KHO'!BF$4:BF$97,'GIÁ XUẤT KHO'!$A$4:$A$97,$G61)*$S61 -> 0 | BW61: =BM61-BF61 -> 0
A62: =_xlfn.XLOOKUP($G62,MD_SKU[Mã SKU],MD_SKU[Link vào file BCQT]) -> Hạt rHDPE thổi | B62: Sales | C62: =IF(LEFT($E62,1)="2","XK","NĐ") -> NĐ | D62: 105372 | 110000495 | E62: 105372 | F62: SANOFI - DTP | G62: 110000495 | H62: Hạt Nhựa rHDA03W01 | J62: EXW | N62: =SUMIFS(Sales!$I$3:$I$100,Sales!$B$3:$B$100,$D62) -> 8000 | R62: =MAX(0,L62+N62-SUM(P62:Q62)) -> 8000 | S62: =SUM(P62:R62) -> 8000 | W62: =1.35*EXR_FC05 -> 35505 | X62: =IFERROR(IF($C62="XK",$AM62/$S62/$AC62,$AM62/$S62),0) -> 35505 | AA62: =IF($C62="NĐ",1,EXR_FC05) -> 1 | AB62: =IF($C62="NĐ",1,EXR_FC05) -> 1 | AC62: =IFERROR(SUMPRODUCT(AJ62:AL62,Z62:AB62)/AM62,0) -> 1 | AG62: =W62*AB62 -> 35505 | AL62: =R62*AG62 -> 284040000 | AM62: =SUM(AJ62:AL62) -> 284040000 | AS62: =AO62*R62 -> 0 | AT62: =SUM(AQ62:AS62) -> 0 | BA62: =SUM(AX62:AZ62) -> 0 | BE62: =_xlfn.XLOOKUP($G62,'GIÁ XUẤT KHO'!$A$4:$A$97,'GIÁ XUẤT KHO'!$AW$4:$AW$97)*R62 -> 2.3658866e+08 | BF62: =SUM(BC62:BE62) -> 2.3658866e+08 | BI62: =AK62-BD62 -> 0 | BJ62: =AL62-BE62 -> 47451339 | BK62: =SUM(BH62:BJ62) -> 47451339 | BM62: =SUM(BN62:BV62) -> 2.3658866e+08 | BN62: =SUMIFS('GIÁ XUẤT KHO'!AX$4:AX$97,'GIÁ XUẤT KHO'!$A$4:$A$97,$G62)*$S62 -> 1.4364014e+08 | BO62: =SUMIFS('GIÁ XUẤT KHO'!AY$4:AY$97,'GIÁ XUẤT KHO'!$A$4:$A$97,$G62)*$S62 -> 16652967 | BP62: =SUMIFS('GIÁ XUẤT KHO'!AZ$4:AZ$97,'GIÁ XUẤT KHO'!$A$4:$A$97,$G62)*$S62 -> 4012852.3 | BQ62: =SUMIFS('GIÁ XUẤT KHO'!BA$4:BA$97,'GIÁ XUẤT KHO'!$A$4:$A$97,$G62)*$S62 -> 17579185 | BR62: =SUMIFS('GIÁ XUẤT KHO'!BB$4:BB$97,'GIÁ XUẤT KHO'!$A$4:$A$97,$G62)*$S62 -> 3368284.1 | BS62: =SUMIFS('GIÁ XUẤT KHO'!BC$4:BC$97,'GIÁ XUẤT KHO'!$A$4:$A$97,$G62)*$S62 -> 15939608 | BT62: =SUMIFS('GIÁ XUẤT KHO'!BD$4:BD$97,'GIÁ XUẤT KHO'!$A$4:$A$97,$G62)*$S62 -> 11848573 | BU62: =SUMIFS('GIÁ XUẤT KHO'!BE$4:BE$97,'GIÁ XUẤT KHO'!$A$4:$A$97,$G62)*$S62 -> 9778270.7 | BV62: =SUMIFS('GIÁ XUẤT KHO'!BF$4:BF$97,'GIÁ XUẤT KHO'!$A$4:$A$97,$G62)*$S62 -> 13768778 | BW62: =BM62-BF62 -> 0
A63: =_xlfn.XLOOKUP($G63,MD_SKU[Mã SKU],MD_SKU[Link vào file BCQT]) -> Hạt rPET | B63: Sales | C63: =IF(LEFT($E63,1)="2","XK","NĐ") -> NĐ | D63: 105397 | 110000354 | E63: 105397 | F63: Olam Duy Tân | G63: 110000354 | H63: Hạt nhựa rPET WSS01G | J63: EXW | N63: =SUMIFS(Sales!$I$3:$I$100,Sales!$B$3:$B$100,$D63) -> 48800 | R63: =MAX(0,L63+N63-SUM(P63:Q63)) -> 48800 | S63: =SUM(P63:R63) -> 48800 | W63: =1.28*EXR_FC05 -> 33664 | X63: =IFERROR(IF($C63="XK",$AM63/$S63/$AC63,$AM63/$S63),0) -> 33664 | AA63: =IF($C63="NĐ",1,EXR_FC05) -> 1 | AB63: =IF($C63="NĐ",1,EXR_FC05) -> 1 | AC63: =IFERROR(SUMPRODUCT(AJ63:AL63,Z63:AB63)/AM63,0) -> 1 | AG63: =W63*AB63 -> 33664 | AL63: =R63*AG63 -> 1642803200 | AM63: =SUM(AJ63:AL63) -> 1642803200 | AS63: =AO63*R63 -> 0 | AT63: =SUM(AQ63:AS63) -> 0 | BA63: =SUM(AX63:AZ63) -> 0 | BE63: =_xlfn.XLOOKUP($G63,'GIÁ XUẤT KHO'!$A$4:$A$97,'GIÁ XUẤT KHO'!$AW$4:$AW$97)*R63 -> 1.2169666e+09 | BF63: =SUM(BC63:BE63) -> 1.2169666e+09 | BI63: =AK63-BD63 -> 0 | BJ63: =AL63-BE63 -> 4.2583655e+08 | BK63: =SUM(BH63:BJ63) -> 4.2583655e+08 | BM63: =SUM(BN63:BV63) -> 1.2169666e+09 | BN63: =SUMIFS('GIÁ XUẤT KHO'!AX$4:AX$97,'GIÁ XUẤT KHO'!$A$4:$A$97,$G63)*$S63 -> 8.7879975e+08 | BO63: =SUMIFS('GIÁ XUẤT KHO'!AY$4:AY$97,'GIÁ XUẤT KHO'!$A$4:$A$97,$G63)*$S63 -> 8926168.9 | BP63: =SUMIFS('GIÁ XUẤT KHO'!AZ$4:AZ$97,'GIÁ XUẤT KHO'!$A$4:$A$97,$G63)*$S63 -> 4696.1759 | BQ63: =SUMIFS('GIÁ XUẤT KHO'!BA$4:BA$97,'GIÁ XUẤT KHO'!$A$4:$A$97,$G63)*$S63 -> 62393275 | BR63: =SUMIFS('GIÁ XUẤT KHO'!BB$4:BB$97,'GIÁ XUẤT KHO'!$A$4:$A$97,$G63)*$S63 -> 8568616.7 | BS63: =SUMIFS('GIÁ XUẤT KHO'!BC$4:BC$97,'GIÁ XUẤT KHO'!$A$4:$A$97,$G63)*$S63 -> 35200991 | BT63: =SUMIFS('GIÁ XUẤT KHO'!BD$4:BD$97,'GIÁ XUẤT KHO'!$A$4:$A$97,$G63)*$S63 -> 56621563 | BU63: =SUMIFS('GIÁ XUẤT KHO'!BE$4:BE$97,'GIÁ XUẤT KHO'!$A$4:$A$97,$G63)*$S63 -> 15397020 | BV63: =SUMIFS('GIÁ XUẤT KHO'!BF$4:BF$97,'GIÁ XUẤT KHO'!$A$4:$A$97,$G63)*$S63 -> 1.5105457e+08 | BW63: =BM63-BF63 -> 0
A64: =_xlfn.XLOOKUP($G64,MD_SKU[Mã SKU],MD_SKU[Link vào file BCQT]) -> Hạt rPET | B64: Sales | C64: =IF(LEFT($E64,1)="2","XK","NĐ") -> XK | D64: 200311 | 110000354 | E64: 200311 | F64: Plascene, Inc. | G64: 110000354 | H64: Hạt nhựa rPET WSS01G | J64: FOB | N64: =SUMIFS(Sales!$I$3:$I$100,Sales!$B$3:$B$100,$D64) -> 154000 | R64: =MAX(0,L64+N64-SUM(P64:Q64)) -> 154000 | S64: =SUM(P64:R64) -> 154000 | W64: 1.1 | X64: =IFERROR(IF($C64="XK",$AM64/$S64/$AC64,$AM64/$S64),0) -> 1.1 | AA64: =IF($C64="NĐ",1,EXR_FC05) -> 26300 | AB64: =IF($C64="NĐ",1,EXR_FC05) -> 26300 | AC64: =IFERROR(SUMPRODUCT(AJ64:AL64,Z64:AB64)/AM64,0) -> 26300 | AG64: =W64*AB64 -> 28930 | AL64: =R64*AG64 -> 4.45522e+09 | AM64: =SUM(AJ64:AL64) -> 4.45522e+09 | AO64: =20*EXR_FC05/1000 -> 526 | AS64: =AO64*R64 -> 81004000 | AT64: =SUM(AQ64:AS64) -> 81004000 | BA64: =SUM(AX64:AZ64) -> 0 | BE64: =_xlfn.XLOOKUP($G64,'GIÁ XUẤT KHO'!$A$4:$A$97,'GIÁ XUẤT KHO'!$AW$4:$AW$97)*R64 -> 3.8404275e+09 | BF64: =SUM(BC64:BE64) -> 3.8404275e+09 | BI64: =AK64-BD64 -> 0 | BJ64: =AL64-BE64 -> 6.1479246e+08 | BK64: =SUM(BH64:BJ64) -> 6.1479246e+08 | BM64: =SUM(BN64:BV64) -> 3.8404275e+09 | BN64: =SUMIFS('GIÁ XUẤT KHO'!AX$4:AX$97,'GIÁ XUẤT KHO'!$A$4:$A$97,$G64)*$S64 -> 2.7732615e+09 | BO64: =SUMIFS('GIÁ XUẤT KHO'!AY$4:AY$97,'GIÁ XUẤT KHO'!$A$4:$A$97,$G64)*$S64 -> 28168648 | BP64: =SUMIFS('GIÁ XUẤT KHO'!AZ$4:AZ$97,'GIÁ XUẤT KHO'!$A$4:$A$97,$G64)*$S64 -> 14819.899 | BQ64: =SUMIFS('GIÁ XUẤT KHO'!BA$4:BA$97,'GIÁ XUẤT KHO'!$A$4:$A$97,$G64)*$S64 -> 1.9689681e+08 | BR64: =SUMIFS('GIÁ XUẤT KHO'!BB$4:BB$97,'GIÁ XUẤT KHO'!$A$4:$A$97,$G64)*$S64 -> 27040307 | BS64: =SUMIFS('GIÁ XUẤT KHO'!BC$4:BC$97,'GIÁ XUẤT KHO'!$A$4:$A$97,$G64)*$S64 -> 1.1108509e+08 | BT64: =SUMIFS('GIÁ XUẤT KHO'!BD$4:BD$97,'GIÁ XUẤT KHO'!$A$4:$A$97,$G64)*$S64 -> 1.786828e+08 | BU64: =SUMIFS('GIÁ XUẤT KHO'!BE$4:BE$97,'GIÁ XUẤT KHO'!$A$4:$A$97,$G64)*$S64 -> 48588958 | BV64: =SUMIFS('GIÁ XUẤT KHO'!BF$4:BF$97,'GIÁ XUẤT KHO'!$A$4:$A$97,$G64)*$S64 -> 4.766886e+08 | BW64: =BM64-BF64 -> 0
A65: =_xlfn.XLOOKUP($G65,MD_SKU[Mã SKU],MD_SKU[Link vào file BCQT]) -> Hạt rPET | B65: Sales | C65: =IF(LEFT($E65,1)="2","XK","NĐ") -> XK | D65: 200319 | 110000354 | E65: 200319 | F65: Niagara Bottling, LLC | G65: 110000354 | H65: Hạt nhựa rPET WSS01G | J65: FOB | N65: =SUMIFS(Sales!$I$3:$I$100,Sales!$B$3:$B$100,$D65) -> 1012000 | R65: =MAX(0,L65+N65-SUM(P65:Q65)) -> 1012000 | S65: =SUM(P65:R65) -> 1012000 | W65: 1.221 | X65: =IFERROR(IF($C65="XK",$AM65/$S65/$AC65,$AM65/$S65),0) -> 1.221 | AA65: =IF($C65="NĐ",1,EXR_FC05) -> 26300 | AB65: =IF($C65="NĐ",1,EXR_FC05) -> 26300 | AC65: =IFERROR(SUMPRODUCT(AJ65:AL65,Z65:AB65)/AM65,0) -> 26300 | AG65: =W65*AB65 -> 32112.3 | AL65: =R65*AG65 -> 3.2497648e+10 | AM65: =SUM(AJ65:AL65) -> 3.2497648e+10 | AO65: =20*EXR_FC05/1000 -> 526 | AS65: =AO65*R65 -> 532312000 | AT65: =SUM(AQ65:AS65) -> 532312000 | AZ65: =1.5%*AL65 -> 4.8746471e+08 | BA65: =SUM(AX65:AZ65) -> 4.8746471e+08 | BE65: =_xlfn.XLOOKUP($G65,'GIÁ XUẤT KHO'!$A$4:$A$97,'GIÁ XUẤT KHO'!$AW$4:$AW$97)*R65 -> 2.5237095e+10 | BF65: =SUM(BC65:BE65) -> 2.5237095e+10 | BI65: =AK65-BD65 -> 0 | BJ65: =AL65-BE65 -> 7.2605523e+09 | BK65: =SUM(BH65:BJ65) -> 7.2605523e+09 | BM65: =SUM(BN65:BV65) -> 2.5237095e+10 | BN65: =SUMIFS('GIÁ XUẤT KHO'!AX$4:AX$97,'GIÁ XUẤT KHO'!$A$4:$A$97,$G65)*$S65 -> 1.822429e+10 | BO65: =SUMIFS('GIÁ XUẤT KHO'!AY$4:AY$97,'GIÁ XUẤT KHO'!$A$4:$A$97,$G65)*$S65 -> 1.8510826e+08 | BP65: =SUMIFS('GIÁ XUẤT KHO'!AZ$4:AZ$97,'GIÁ XUẤT KHO'!$A$4:$A$97,$G65)*$S65 -> 97387.91 | BQ65: =SUMIFS('GIÁ XUẤT KHO'!BA$4:BA$97,'GIÁ XUẤT KHO'!$A$4:$A$97,$G65)*$S65 -> 1.2938933e+09 | BR65: =SUMIFS('GIÁ XUẤT KHO'!BB$4:BB$97,'GIÁ XUẤT KHO'!$A$4:$A$97,$G65)*$S65 -> 1.7769345e+08 | BS65: =SUMIFS('GIÁ XUẤT KHO'!BC$4:BC$97,'GIÁ XUẤT KHO'!$A$4:$A$97,$G65)*$S65 -> 7.2998776e+08 | BT65: =SUMIFS('GIÁ XUẤT KHO'!BD$4:BD$97,'GIÁ XUẤT KHO'!$A$4:$A$97,$G65)*$S65 -> 1.1742013e+09 | BU65: =SUMIFS('GIÁ XUẤT KHO'!BE$4:BE$97,'GIÁ XUẤT KHO'!$A$4:$A$97,$G65)*$S65 -> 3.1929887e+08 | BV65: =SUMIFS('GIÁ XUẤT KHO'!BF$4:BF$97,'GIÁ XUẤT KHO'!$A$4:$A$97,$G65)*$S65 -> 3.1325251e+09 | BW65: =BM65-BF65 -> 0
A66: =_xlfn.XLOOKUP($G66,MD_SKU[Mã SKU],MD_SKU[Link vào file BCQT]) -> Hạt rPET | B66: Sales | C66: =IF(LEFT($E66,1)="2","XK","NĐ") -> XK | D66: 200359 | 110000359 | E66: 200359 | F66: PREMIUM WATER | G66: 110000359 | H66: Hạt nhựa rPET WSS03G | N66: =SUMIFS(Sales!$I$3:$I$100,Sales!$B$3:$B$100,$D66) -> 0 | R66: =MAX(0,L66+N66-SUM(P66:Q66)) -> 0 | S66: =SUM(P66:R66) -> 0 | X66: =IFERROR(IF($C66="XK",$AM66/$S66/$AC66,$AM66/$S66),0) -> 0 | AA66: =IF($C66="NĐ",1,EXR_FC05) -> 26300 | AB66: =IF($C66="NĐ",1,EXR_FC05) -> 26300 | AC66: =IFERROR(SUMPRODUCT(AJ66:AL66,Z66:AB66)/AM66,0) -> 0 | AG66: =W66*AB66 -> 0 | AL66: =R66*AG66 -> 0 | AM66: =SUM(AJ66:AL66) -> 0 | AS66: =AO66*R66 -> 0 | AT66: =SUM(AQ66:AS66) -> 0 | BA66: =SUM(AX66:AZ66) -> 0 | BE66: =_xlfn.XLOOKUP($G66,'GIÁ XUẤT KHO'!$A$4:$A$97,'GIÁ XUẤT KHO'!$AW$4:$AW$97)*R66 -> 0 | BF66: =SUM(BC66:BE66) -> 0 | BI66: =AK66-BD66 -> 0 | BJ66: =AL66-BE66 -> 0 | BK66: =SUM(BH66:BJ66) -> 0 | BM66: =SUM(BN66:BV66) -> 0 | BN66: =SUMIFS('GIÁ XUẤT KHO'!AX$4:AX$97,'GIÁ XUẤT KHO'!$A$4:$A$97,$G66)*$S66 -> 0 | BO66: =SUMIFS('GIÁ XUẤT KHO'!AY$4:AY$97,'GIÁ XUẤT KHO'!$A$4:$A$97,$G66)*$S66 -> 0 | BP66: =SUMIFS('GIÁ XUẤT KHO'!AZ$4:AZ$97,'GIÁ XUẤT KHO'!$A$4:$A$97,$G66)*$S66 -> 0 | BQ66: =SUMIFS('GIÁ XUẤT KHO'!BA$4:BA$97,'GIÁ XUẤT KHO'!$A$4:$A$97,$G66)*$S66 -> 0 | BR66: =SUMIFS('GIÁ XUẤT KHO'!BB$4:BB$97,'GIÁ XUẤT KHO'!$A$4:$A$97,$G66)*$S66 -> 0 | BS66: =SUMIFS('GIÁ XUẤT KHO'!BC$4:BC$97,'GIÁ XUẤT KHO'!$A$4:$A$97,$G66)*$S66 -> 0 | BT66: =SUMIFS('GIÁ XUẤT KHO'!BD$4:BD$97,'GIÁ XUẤT KHO'!$A$4:$A$97,$G66)*$S66 -> 0 | BU66: =SUMIFS('GIÁ XUẤT KHO'!BE$4:BE$97,'GIÁ XUẤT KHO'!$A$4:$A$97,$G66)*$S66 -> 0 | BV66: =SUMIFS('GIÁ XUẤT KHO'!BF$4:BF$97,'GIÁ XUẤT KHO'!$A$4:$A$97,$G66)*$S66 -> 0 | BW66: =BM66-BF66 -> 0
A67: =_xlfn.XLOOKUP($G67,MD_SKU[Mã SKU],MD_SKU[Link vào file BCQT]) -> Hạt rPET | B67: Sales | C67: =IF(LEFT($E67,1)="2","XK","NĐ") -> XK | D67: 200361 | 110000332 | E67: 200361 | F67: MCP-Resinex | G67: 110000332 | H67: Hạt nhựa rPET iSS01084G | J67: FOB | N67: =SUMIFS(Sales!$I$3:$I$100,Sales!$B$3:$B$100,$D67) -> 22000 | R67: =MAX(0,L67+N67-SUM(P67:Q67)) -> 22000 | S67: =SUM(P67:R67) -> 22000 | W67: 1.39 | X67: =IFERROR(IF($C67="XK",$AM67/$S67/$AC67,$AM67/$S67),0) -> 1.39 | AA67: =IF($C67="NĐ",1,EXR_FC05) -> 26300 | AB67: =IF($C67="NĐ",1,EXR_FC05) -> 26300 | AC67: =IFERROR(SUMPRODUCT(AJ67:AL67,Z67:AB67)/AM67,0) -> 26300 | AG67: =W67*AB67 -> 36557 | AL67: =R67*AG67 -> 804254000 | AM67: =SUM(AJ67:AL67) -> 804254000 | AO67: =20*EXR_FC05/1000 -> 526 | AS67: =AO67*R67 -> 11572000 | AT67: =SUM(AQ67:AS67) -> 11572000 | BA67: =SUM(AX67:AZ67) -> 0 | BE67: =_xlfn.XLOOKUP($G67,'GIÁ XUẤT KHO'!$A$4:$A$97,'GIÁ XUẤT KHO'!$AW$4:$AW$97)*R67 -> 6.1638995e+08 | BF67: =SUM(BC67:BE67) -> 6.1638995e+08 | BI67: =AK67-BD67 -> 0 | BJ67: =AL67-BE67 -> 1.8786405e+08 | BK67: =SUM(BH67:BJ67) -> 1.8786405e+08 | BM67: =SUM(BN67:BV67) -> 6.1638995e+08 | BN67: =SUMIFS('GIÁ XUẤT KHO'!AX$4:AX$97,'GIÁ XUẤT KHO'!$A$4:$A$97,$G67)*$S67 -> 3.6438333e+08 | BO67: =SUMIFS('GIÁ XUẤT KHO'!AY$4:AY$97,'GIÁ XUẤT KHO'!$A$4:$A$97,$G67)*$S67 -> 6054401 | BP67: =SUMIFS('GIÁ XUẤT KHO'!AZ$4:AZ$97,'GIÁ XUẤT KHO'!$A$4:$A$97,$G67)*$S67 -> 2466.7489 | BQ67: =SUMIFS('GIÁ XUẤT KHO'!BA$4:BA$97,'GIÁ XUẤT KHO'!$A$4:$A$97,$G67)*$S67 -> 40209377 | BR67: =SUMIFS('GIÁ XUẤT KHO'!BB$4:BB$97,'GIÁ XUẤT KHO'!$A$4:$A$97,$G67)*$S67 -> 4759273.2 | BS67: =SUMIFS('GIÁ XUẤT KHO'!BC$4:BC$97,'GIÁ XUẤT KHO'!$A$4:$A$97,$G67)*$S67 -> 28774138 | BT67: =SUMIFS('GIÁ XUẤT KHO'!BD$4:BD$97,'GIÁ XUẤT KHO'!$A$4:$A$97,$G67)*$S67 -> 46367316 | BU67: =SUMIFS('GIÁ XUẤT KHO'!BE$4:BE$97,'GIÁ XUẤT KHO'!$A$4:$A$97,$G67)*$S67 -> 11131585 | BV67: =SUMIFS('GIÁ XUẤT KHO'!BF$4:BF$97,'GIÁ XUẤT KHO'!$A$4:$A$97,$G67)*$S67 -> 1.1470806e+08 | BW67: =BM67-BF67 -> 0
A68: =_xlfn.XLOOKUP($G68,MD_SKU[Mã SKU],MD_SKU[Link vào file BCQT]) -> Hạt rPET | B68: Sales | C68: =IF(LEFT($E68,1)="2","XK","NĐ") -> XK | D68: 200365 | 110000355 | E68: 200365 | F68: Vinmar International | G68: 110000355 | H68: Hạt nhựa rPET iSS01G | J68: FOB | N68: =SUMIFS(Sales!$I$3:$I$100,Sales!$B$3:$B$100,$D68) -> 506000 | R68: =MAX(0,L68+N68-SUM(P68:Q68)) -> 506000 | S68: =SUM(P68:R68) -> 506000 | W68: =1.31-0.07+N("giảm gia") -> 1.24 | X68: =IFERROR(IF($C68="XK",$AM68/$S68/$AC68,$AM68/$S68),0) -> 1.24 | AA68: =IF($C68="NĐ",1,EXR_FC05) -> 26300 | AB68: =IF($C68="NĐ",1,EXR_FC05) -> 26300 | AC68: =IFERROR(SUMPRODUCT(AJ68:AL68,Z68:AB68)/AM68,0) -> 26300 | AG68: =W68*AB68 -> 32612 | AL68: =R68*AG68 -> 16501672000 | AM68: =SUM(AJ68:AL68) -> 16501672000 | AO68: =20*EXR_FC05/1000 -> 526 | AS68: =AO68*R68 -> 266156000 | AT68: =SUM(AQ68:AS68) -> 266156000 | BA68: =SUM(AX68:AZ68) -> 0 | BE68: =_xlfn.XLOOKUP($G68,'GIÁ XUẤT KHO'!$A$4:$A$97,'GIÁ XUẤT KHO'!$AW$4:$AW$97)*R68 -> 1.3239028e+10 | BF68: =SUM(BC68:BE68) -> 1.3239028e+10 | BI68: =AK68-BD68 -> 0 | BJ68: =AL68-BE68 -> 3.2626437e+09 | BK68: =SUM(BH68:BJ68) -> 3.2626437e+09 | BM68: =SUM(BN68:BV68) -> 1.3239028e+10 | BN68: =SUMIFS('GIÁ XUẤT KHO'!AX$4:AX$97,'GIÁ XUẤT KHO'!$A$4:$A$97,$G68)*$S68 -> 9.8458762e+09 | BO68: =SUMIFS('GIÁ XUẤT KHO'!AY$4:AY$97,'GIÁ XUẤT KHO'!$A$4:$A$97,$G68)*$S68 -> 85563481 | BP68: =SUMIFS('GIÁ XUẤT KHO'!AZ$4:AZ$97,'GIÁ XUẤT KHO'!$A$4:$A$97,$G68)*$S68 -> 17042.369 | BQ68: =SUMIFS('GIÁ XUẤT KHO'!BA$4:BA$97,'GIÁ XUẤT KHO'!$A$4:$A$97,$G68)*$S68 -> 4.0400357e+08 | BR68: =SUMIFS('GIÁ XUẤT KHO'!BB$4:BB$97,'GIÁ XUẤT KHO'!$A$4:$A$97,$G68)*$S68 -> 1.1738583e+08 | BS68: =SUMIFS('GIÁ XUẤT KHO'!BC$4:BC$97,'GIÁ XUẤT KHO'!$A$4:$A$97,$G68)*$S68 -> 2.1910143e+08 | BT68: =SUMIFS('GIÁ XUẤT KHO'!BD$4:BD$97,'GIÁ XUẤT KHO'!$A$4:$A$97,$G68)*$S68 -> 7.45854e+08 | BU68: =SUMIFS('GIÁ XUẤT KHO'!BE$4:BE$97,'GIÁ XUẤT KHO'!$A$4:$A$97,$G68)*$S68 -> 38655622 | BV68: =SUMIFS('GIÁ XUẤT KHO'!BF$4:BF$97,'GIÁ XUẤT KHO'!$A$4:$A$97,$G68)*$S68 -> 1.7825712e+09 | BW68: =BM68-BF68 -> 0
A69: =_xlfn.XLOOKUP($G69,MD_SKU[Mã SKU],MD_SKU[Link vào file BCQT]) -> Hạt rPET | B69: Sales | C69: =IF(LEFT($E69,1)="2","XK","NĐ") -> XK | D69: 200383 | 110000354 | E69: 200383 | F69: Natures Organics - PIA | G69: 110000354 | H69: Hạt nhựa rPET WSS01G | J69: FOB | N69: =SUMIFS(Sales!$I$3:$I$100,Sales!$B$3:$B$100,$D69) -> 44000 | R69: =MAX(0,L69+N69-SUM(P69:Q69)) -> 44000 | S69: =SUM(P69:R69) -> 44000 | W69: 1.3 | X69: =IFERROR(IF($C69="XK",$AM69/$S69/$AC69,$AM69/$S69),0) -> 1.3 | AA69: =IF($C69="NĐ",1,EXR_FC05) -> 26300 | AB69: =IF($C69="NĐ",1,EXR_FC05) -> 26300 | AC69: =IFERROR(SUMPRODUCT(AJ69:AL69,Z69:AB69)/AM69,0) -> 26300 | AG69: =W69*AB69 -> 34190 | AL69: =R69*AG69 -> 1504360000 | AM69: =SUM(AJ69:AL69) -> 1504360000 | AO69: =20*EXR_FC05/1000 -> 526 | AS69: =AO69*R69 -> 23144000 | AT69: =SUM(AQ69:AS69) -> 23144000 | BA69: =SUM(AX69:AZ69) -> 0 | BE69: =_xlfn.XLOOKUP($G69,'GIÁ XUẤT KHO'!$A$4:$A$97,'GIÁ XUẤT KHO'!$AW$4:$AW$97)*R69 -> 1.097265e+09 | BF69: =SUM(BC69:BE69) -> 1.097265e+09 | BI69: =AK69-BD69 -> 0 | BJ69: =AL69-BE69 -> 4.0709499e+08 | BK69: =SUM(BH69:BJ69) -> 4.0709499e+08 | BM69: =SUM(BN69:BV69) -> 1.097265e+09 | BN69: =SUMIFS('GIÁ XUẤT KHO'!AX$4:AX$97,'GIÁ XUẤT KHO'!$A$4:$A$97,$G69)*$S69 -> 7.9236043e+08 | BO69: =SUMIFS('GIÁ XUẤT KHO'!AY$4:AY$97,'GIÁ XUẤT KHO'!$A$4:$A$97,$G69)*$S69 -> 8048185 | BP69: =SUMIFS('GIÁ XUẤT KHO'!AZ$4:AZ$97,'GIÁ XUẤT KHO'!$A$4:$A$97,$G69)*$S69 -> 4234.2569 | BQ69: =SUMIFS('GIÁ XUẤT KHO'!BA$4:BA$97,'GIÁ XUẤT KHO'!$A$4:$A$97,$G69)*$S69 -> 56256232 | BR69: =SUMIFS('GIÁ XUẤT KHO'!BB$4:BB$97,'GIÁ XUẤT KHO'!$A$4:$A$97,$G69)*$S69 -> 7725802 | BS69: =SUMIFS('GIÁ XUẤT KHO'!BC$4:BC$97,'GIÁ XUẤT KHO'!$A$4:$A$97,$G69)*$S69 -> 31738598 | BT69: =SUMIFS('GIÁ XUẤT KHO'!BD$4:BD$97,'GIÁ XUẤT KHO'!$A$4:$A$97,$G69)*$S69 -> 51052229 | BU69: =SUMIFS('GIÁ XUẤT KHO'!BE$4:BE$97,'GIÁ XUẤT KHO'!$A$4:$A$97,$G69)*$S69 -> 13882559 | BV69: =SUMIFS('GIÁ XUẤT KHO'!BF$4:BF$97,'GIÁ XUẤT KHO'!$A$4:$A$97,$G69)*$S69 -> 1.3619674e+08 | BW69: =BM69-BF69 -> 0
A70: =_xlfn.XLOOKUP($G70,MD_SKU[Mã SKU],MD_SKU[Link vào file BCQT]) -> Hạt rPET | B70: Sales | C70: =IF(LEFT($E70,1)="2","XK","NĐ") -> XK | D70: 200400 | 110000354 | E70: 200400 | F70: SHEPLEY SPRING | G70: 110000354 | H70: Hạt nhựa rPET WSS01G | J70: FOB | N70: =SUMIFS(Sales!$I$3:$I$100,Sales!$B$3:$B$100,$D70) -> 220000 | R70: =MAX(0,L70+N70-SUM(P70:Q70)) -> 220000 | S70: =SUM(P70:R70) -> 220000 | W70: 1.15 | X70: =IFERROR(IF($C70="XK",$AM70/$S70/$AC70,$AM70/$S70),0) -> 1.15 | AA70: =IF($C70="NĐ",1,EXR_FC05) -> 26300 | AB70: =IF($C70="NĐ",1,EXR_FC05) -> 26300 | AC70: =IFERROR(SUMPRODUCT(AJ70:AL70,Z70:AB70)/AM70,0) -> 26300 | AG70: =W70*AB70 -> 30245 | AL70: =R70*AG70 -> 6.6539e+09 | AM70: =SUM(AJ70:AL70) -> 6.6539e+09 | AO70: =20*EXR_FC05/1000 -> 526 | AS70: =AO70*R70 -> 115720000 | AT70: =SUM(AQ70:AS70) -> 115720000 | AZ70: =1.5%*AL70 -> 99808500 | BA70: =SUM(AX70:AZ70) -> 99808500 | BE70: =_xlfn.XLOOKUP($G70,'GIÁ XUẤT KHO'!$A$4:$A$97,'GIÁ XUẤT KHO'!$AW$4:$AW$97)*R70 -> 5.4863251e+09 | BF70: =SUM(BC70:BE70) -> 5.4863251e+09 | BI70: =AK70-BD70 -> 0 | BJ70: =AL70-BE70 -> 1.1675749e+09 | BK70: =SUM(BH70:BJ70) -> 1.1675749e+09 | BM70: =SUM(BN70:BV70) -> 5.4863251e+09 | BN70: =SUMIFS('GIÁ XUẤT KHO'!AX$4:AX$97,'GIÁ XUẤT KHO'!$A$4:$A$97,$G70)*$S70 -> 3.9618022e+09 | BO70: =SUMIFS('GIÁ XUẤT KHO'!AY$4:AY$97,'GIÁ XUẤT KHO'!$A$4:$A$97,$G70)*$S70 -> 40240925 | BP70: =SUMIFS('GIÁ XUẤT KHO'!AZ$4:AZ$97,'GIÁ XUẤT KHO'!$A$4:$A$97,$G70)*$S70 -> 21171.285 | BQ70: =SUMIFS('GIÁ XUẤT KHO'!BA$4:BA$97,'GIÁ XUẤT KHO'!$A$4:$A$97,$G70)*$S70 -> 2.8128116e+08 | BR70: =SUMIFS('GIÁ XUẤT KHO'!BB$4:BB$97,'GIÁ XUẤT KHO'!$A$4:$A$97,$G70)*$S70 -> 38629010 | BS70: =SUMIFS('GIÁ XUẤT KHO'!BC$4:BC$97,'GIÁ XUẤT KHO'!$A$4:$A$97,$G70)*$S70 -> 1.5869299e+08 | BT70: =SUMIFS('GIÁ XUẤT KHO'!BD$4:BD$97,'GIÁ XUẤT KHO'!$A$4:$A$97,$G70)*$S70 -> 2.5526114e+08 | BU70: =SUMIFS('GIÁ XUẤT KHO'!BE$4:BE$97,'GIÁ XUẤT KHO'!$A$4:$A$97,$G70)*$S70 -> 69412797 | BV70: =SUMIFS('GIÁ XUẤT KHO'!BF$4:BF$97,'GIÁ XUẤT KHO'!$A$4:$A$97,$G70)*$S70 -> 6.8098371e+08 | BW70: =BM70-BF70 -> 0
A71: =_xlfn.XLOOKUP($G71,MD_SKU[Mã SKU],MD_SKU[Link vào file BCQT]) -> Hạt rPP | B71: Sales | C71: =IF(LEFT($E71,1)="2","XK","NĐ") -> NĐ | D71: Aeonmall/ (Home Coordy) | 110000394 | E71: Aeonmall/ (Home Coordy) | F71: Aeonmall/ (Home Coordy) | G71: 110000394 | H71: Hạt nhựa rPP15Gy02 | J71: EXW | N71: =SUMIFS(Sales!$I$3:$I$100,Sales!$B$3:$B$100,$D71) -> 1375 | R71: =MAX(0,L71+N71-SUM(P71:Q71)) -> 1375 | S71: =SUM(P71:R71) -> 1375 | W71: =1.19*EXR_FC05 -> 31297 | X71: =IFERROR(IF($C71="XK",$AM71/$S71/$AC71,$AM71/$S71),0) -> 31297 | AA71: =IF($C71="NĐ",1,EXR_FC05) -> 1 | AB71: =IF($C71="NĐ",1,EXR_FC05) -> 1 | AC71: =IFERROR(SUMPRODUCT(AJ71:AL71,Z71:AB71)/AM71,0) -> 1 | AG71: =W71*AB71 -> 31297 | AL71: =R71*AG71 -> 43033375 | AM71: =SUM(AJ71:AL71) -> 43033375 | AS71: =AO71*R71 -> 0 | AT71: =SUM(AQ71:AS71) -> 0 | BA71: =SUM(AX71:AZ71) -> 0 | BE71: =_xlfn.XLOOKUP($G71,'GIÁ XUẤT KHO'!$A$4:$A$97,'GIÁ XUẤT KHO'!$AW$4:$AW$97)*R71 -> 40691848 | BF71: =SUM(BC71:BE71) -> 40691848 | BI71: =AK71-BD71 -> 0 | BJ71: =AL71-BE71 -> 2341526.6 | BK71: =SUM(BH71:BJ71) -> 2341526.6 | BM71: =SUM(BN71:BV71) -> 40691848 | BN71: =SUMIFS('GIÁ XUẤT KHO'!AX$4:AX$97,'GIÁ XUẤT KHO'!$A$4:$A$97,$G71)*$S71 -> 25355822 | BO71: =SUMIFS('GIÁ XUẤT KHO'!AY$4:AY$97,'GIÁ XUẤT KHO'!$A$4:$A$97,$G71)*$S71 -> 142105.75 | BP71: =SUMIFS('GIÁ XUẤT KHO'!AZ$4:AZ$97,'GIÁ XUẤT KHO'!$A$4:$A$97,$G71)*$S71 -> 5.0182482 | BQ71: =SUMIFS('GIÁ XUẤT KHO'!BA$4:BA$97,'GIÁ XUẤT KHO'!$A$4:$A$97,$G71)*$S71 -> 2206408.3 | BR71: =SUMIFS('GIÁ XUẤT KHO'!BB$4:BB$97,'GIÁ XUẤT KHO'!$A$4:$A$97,$G71)*$S71 -> 448217.88 | BS71: =SUMIFS('GIÁ XUẤT KHO'!BC$4:BC$97,'GIÁ XUẤT KHO'!$A$4:$A$97,$G71)*$S71 -> 4503945 | BT71: =SUMIFS('GIÁ XUẤT KHO'!BD$4:BD$97,'GIÁ XUẤT KHO'!$A$4:$A$97,$G71)*$S71 -> 2080207.4 | BU71: =SUMIFS('GIÁ XUẤT KHO'!BE$4:BE$97,'GIÁ XUẤT KHO'!$A$4:$A$97,$G71)*$S71 -> 1275618.6 | BV71: =SUMIFS('GIÁ XUẤT KHO'!BF$4:BF$97,'GIÁ XUẤT KHO'!$A$4:$A$97,$G71)*$S71 -> 4679518.4 | BW71: =BM71-BF71 -> 0
AM72: =SUM(AJ72:AL72) -> 0 | BA72: =SUM(AX72:AZ72) -> 0 | BF72: =SUM(BC72:BE72) -> 0 | BK72: =SUM(BH72:BJ72) -> 0
AM73: =SUM(AJ73:AL73) -> 0 | BA73: =SUM(AX73:AZ73) -> 0 | BF73: =SUM(BC73:BE73) -> 0 | BK73: =SUM(BH73:BJ73) -> 0
AM74: =SUM(AJ74:AL74) -> 0 | BA74: =SUM(AX74:AZ74) -> 0 | BF74: =SUM(BC74:BE74) -> 0 | BK74: =SUM(BH74:BJ74) -> 0
AM75: =SUM(AJ75:AL75) -> 0 | BA75: =SUM(AX75:AZ75) -> 0 | BF75: =SUM(BC75:BE75) -> 0 | BK75: =SUM(BH75:BJ75) -> 0
AM76: =SUM(AJ76:AL76) -> 0 | BA76: =SUM(AX76:AZ76) -> 0 | BF76: =SUM(BC76:BE76) -> 0 | BK76: =SUM(BH76:BJ76) -> 0
AM77: =SUM(AJ77:AL77) -> 0 | BA77: =SUM(AX77:AZ77) -> 0 | BF77: =SUM(BC77:BE77) -> 0 | BK77: =SUM(BH77:BJ77) -> 0
AM78: =SUM(AJ78:AL78) -> 0 | BA78: =SUM(AX78:AZ78) -> 0 | BF78: =SUM(BC78:BE78) -> 0 | BK78: =SUM(BH78:BJ78) -> 0
AM79: =SUM(AJ79:AL79) -> 0 | BA79: =SUM(AX79:AZ79) -> 0 | BF79: =SUM(BC79:BE79) -> 0 | BK79: =SUM(BH79:BJ79) -> 0
AM80: =SUM(AJ80:AL80) -> 0 | BA80: =SUM(AX80:AZ80) -> 0 | BF80: =SUM(BC80:BE80) -> 0 | BK80: =SUM(BH80:BJ80) -> 0
AM81: =SUM(AJ81:AL81) -> 0 | BA81: =SUM(AX81:AZ81) -> 0 | BF81: =SUM(BC81:BE81) -> 0 | BK81: =SUM(BH81:BJ81) -> 0
AM82: =SUM(AJ82:AL82) -> 0 | BA82: =SUM(AX82:AZ82) -> 0 | BF82: =SUM(BC82:BE82) -> 0 | BK82: =SUM(BH82:BJ82) -> 0
AM83: =SUM(AJ83:AL83) -> 0 | BA83: =SUM(AX83:AZ83) -> 0 | BF83: =SUM(BC83:BE83) -> 0 | BK83: =SUM(BH83:BJ83) -> 0
... AM97: =SUM(AJ97:AL97) -> 0 | BA97: =SUM(AX97:AZ97) -> 0 | BF97: =SUM(BC97:BE97) -> 0 | BK97: =SUM(BH97:BJ97) -> 0
A98: Doanh thu khác | H98: Điều chỉnh doanh thu Niagara-Q1 | AL98: =210655.5*EXR_FC05 -> 5540239650 | AM98: =SUM(AJ98:AL98) -> 5540239650 | AZ98: =3159.8325*EXR_FC05 -> 83103595 | BA98: =SUM(AX98:AZ98) -> 83103595 | BF98: =SUM(BC98:BE98) -> 0 | BH98: =AJ98-BC98 -> 0 | BI98: =AK98-BD98 -> 0 | BJ98: =AL98-BE98 -> 5540239650 | BK98: =SUM(BH98:BJ98) -> 5540239650
A99: Thuê xưởng, thuê máy | H99: Điều chỉnh thuê xưởng thuê máy 2025 | K99: =SUMIFS('Working-T05-B1'!L$8:L$150,'Working-T05-B1'!$C$8:$C$150,$D99) -> 0 | L99: {=SUMPRODUCT(Sales!$G$3:$H$100*(Sales!$B$3:$B$100=$D99))} -> 0 | P99: =SUMIFS('Working-T05-B1'!O$8:O$150,'Working-T05-B1'!$C$8:$C$150,$D99) -> 0 | S99: =SUM(P99:R99) -> 0 | X99: =IFERROR(IF($C99="XK",$AM99/$S99/$AC99,$AM99/$S99),0) -> 0 | Z99: =IF($C99="NĐ",1,IFERROR(SUMIFS(Data_FAGLL03[Amount in local currency],Data_FAGLL03[Offsetting acct no.],$E99,Data_FAGLL03[Material],$G99)/SUMIFS(Data_FAGLL03[Dthu (USD)],Data_FAGLL03[Offsetting acct no.],$E99,Data_FAGLL03[Material],$G99),0)) -> 0 | AA99: =IF($C99="NĐ",1,EXR_FC05) -> 26300 | AB99: =IF($C99="NĐ",1,EXR_FC05) -> 26300 | AC99: =IFERROR(SUMPRODUCT(AJ99:AL99,Z99:AB99)/AM99,0) -> 0 | AE99: =IFERROR(AJ99/P99,0) -> 0 | AF99: =IFERROR(AK99/Q99,0) -> 0 | AG99: =W99*AB99 -> 0 | AL99: =R99*AG99 -> 0 | AM99: =SUM(AJ99:AL99) -> 0 | AV99: =IFERROR(BA99/S99,0) -> 0 | BA99: =SUM(AX99:AZ99) -> 0 | BE99: 1113447612 | BF99: =SUM(BC99:BE99) -> 1113447612 | BH99: =AJ99-BC99 -> 0 | BI99: =AK99-BD99 -> 0 | BJ99: =AL99-BE99 -> -1113447612 | BK99: =SUM(BH99:BJ99) -> -1113447612
A100: Pallet/Bao bì xuất hàng | H100: Pallet xuất hàng | K100: =SUMIFS('Working-T05-B1'!L$8:L$150,'Working-T05-B1'!$C$8:$C$150,$D100) -> 0 | L100: {=SUMPRODUCT(Sales!$G$3:$H$100*(Sales!$B$3:$B$100=$D100))} -> 0 | P100: =SUMIFS('Working-T05-B1'!O$8:O$150,'Working-T05-B1'!$C$8:$C$150,$D100) -> 0 | S100: =SUM(P100:R100) -> 0 | X100: =IFERROR(IF($C100="XK",$AM100/$S100/$AC100,$AM100/$S100),0) -> 0 | Z100: =IF($C100="NĐ",1,IFERROR(SUMIFS(Data_FAGLL03[Amount in local currency],Data_FAGLL03[Offsetting acct no.],$E100,Data_FAGLL03[Material],$G100)/SUMIFS(Data_FAGLL03[Dthu (USD)],Data_FAGLL03[Offsetting acct no.],$E100,Data_FAGLL03[Material],$G100),0)) -> 0 | AA100: =IF($C100="NĐ",1,EXR_FC05) -> 26300 | AB100: =IF($C100="NĐ",1,EXR_FC05) -> 26300 | AC100: =IFERROR(SUMPRODUCT(AJ100:AL100,Z100:AB100)/AM100,0) -> 0 | AE100: =IFERROR(AJ100/P100,0) -> 0 | AF100: =IFERROR(AK100/Q100,0) -> 0 | AG100: =W100*AB100 -> 0 | AL100: =R100*AG100 -> 0 | AM100: =SUM(AJ100:AL100) -> 0 | AV100: =IFERROR(BA100/S100,0) -> 0 | BA100: =SUM(AX100:AZ100) -> 0 | BE100: 500000000 | BF100: =SUM(BC100:BE100) -> 500000000 | BH100: =AJ100-BC100 -> 0 | BI100: =AK100-BD100 -> 0 | BJ100: =AL100-BE100 -> -500000000 | BK100: =SUM(BH100:BJ100) -> -500000000
A101: GVHB khác | H101: VAT không được khấu trừ | K101: =SUMIFS('Working-T05-B1'!L$8:L$150,'Working-T05-B1'!$C$8:$C$150,$D101) -> 0 | L101: {=SUMPRODUCT(Sales!$G$3:$H$100*(Sales!$B$3:$B$100=$D101))} -> 0 | P101: =SUMIFS('Working-T05-B1'!O$8:O$150,'Working-T05-B1'!$C$8:$C$150,$D101) -> 0 | S101: =SUM(P101:R101) -> 0 | X101: =IFERROR(IF($C101="XK",$AM101/$S101/$AC101,$AM101/$S101),0) -> 0 | Z101: =IF($C101="NĐ",1,IFERROR(SUMIFS(Data_FAGLL03[Amount in local currency],Data_FAGLL03[Offsetting acct no.],$E101,Data_FAGLL03[Material],$G101)/SUMIFS(Data_FAGLL03[Dthu (USD)],Data_FAGLL03[Offsetting acct no.],$E101,Data_FAGLL03[Material],$G101),0)) -> 0 | AA101: =IF($C101="NĐ",1,EXR_FC05) -> 26300 | AB101: =IF($C101="NĐ",1,EXR_FC05) -> 26300 | AC101: =IFERROR(SUMPRODUCT(AJ101:AL101,Z101:AB101)/AM101,0) -> 0 | AE101: =IFERROR(AJ101/P101,0) -> 0 | AF101: =IFERROR(AK101/Q101,0) -> 0 | AG101: =W101*AB101 -> 0 | AL101: =R101*AG101 -> 0 | AM101: =SUM(AJ101:AL101) -> 0 | AV101: =IFERROR(BA101/S101,0) -> 0 | BA101: =SUM(AX101:AZ101) -> 0 | BE101: 36700352 | BF101: =SUM(BC101:BE101) -> 36700352 | BH101: =AJ101-BC101 -> 0 | BI101: =AK101-BD101 -> 0 | BJ101: =AL101-BE101 -> -36700352 | BK101: =SUM(BH101:BJ101) -> -36700352
K102: =SUMIFS('Working-T05-B1'!L$8:L$150,'Working-T05-B1'!$C$8:$C$150,$D102) -> 0 | L102: {=SUMPRODUCT(Sales!$G$3:$H$100*(Sales!$B$3:$B$100=$D102))} -> 0 | P102: =SUMIFS('Working-T05-B1'!O$8:O$150,'Working-T05-B1'!$C$8:$C$150,$D102) -> 0 | S102: =SUM(P102:R102) -> 0 | X102: =IFERROR(IF($C102="XK",$AM102/$S102/$AC102,$AM102/$S102),0) -> 0 | Z102: =IF($C102="NĐ",1,IFERROR(SUMIFS(Data_FAGLL03[Amount in local currency],Data_FAGLL03[Offsetting acct no.],$E102,Data_FAGLL03[Material],$G102)/SUMIFS(Data_FAGLL03[Dthu (USD)],Data_FAGLL03[Offsetting acct no.],$E102,Data_FAGLL03[Material],$G102),0)) -> 0 | AA102: =IF($C102="NĐ",1,EXR_FC05) -> 26300 | AB102: =IF($C102="NĐ",1,EXR_FC05) -> 26300 | AC102: =IFERROR(SUMPRODUCT(AJ102:AL102,Z102:AB102)/AM102,0) -> 0 | AE102: =IFERROR(AJ102/P102,0) -> 0 | AF102: =IFERROR(AK102/Q102,0) -> 0 | AG102: =W102*AB102 -> 0 | AL102: =R102*AG102 -> 0 | AM102: =SUM(AJ102:AL102) -> 0 | AV102: =IFERROR(BA102/S102,0) -> 0 | BA102: =SUM(AX102:AZ102) -> 0 | BF102: =SUM(BC102:BE102) -> 0 | BH102: =AJ102-BC102 -> 0 | BI102: =AK102-BD102 -> 0 | BJ102: =AL102-BE102 -> 0 | BK102: =SUM(BH102:BJ102) -> 0
K103: =SUMIFS('Working-T05-B1'!L$8:L$150,'Working-T05-B1'!$C$8:$C$150,$D103) -> 0 | L103: {=SUMPRODUCT(Sales!$G$3:$H$100*(Sales!$B$3:$B$100=$D103))} -> 0 | P103: =SUMIFS('Working-T05-B1'!O$8:O$150,'Working-T05-B1'!$C$8:$C$150,$D103) -> 0 | S103: =SUM(P103:R103) -> 0 | X103: =IFERROR(IF($C103="XK",$AM103/$S103/$AC103,$AM103/$S103),0) -> 0 | Z103: =IF($C103="NĐ",1,IFERROR(SUMIFS(Data_FAGLL03[Amount in local currency],Data_FAGLL03[Offsetting acct no.],$E103,Data_FAGLL03[Material],$G103)/SUMIFS(Data_FAGLL03[Dthu (USD)],Data_FAGLL03[Offsetting acct no.],$E103,Data_FAGLL03[Material],$G103),0)) -> 0 | AA103: =IF($C103="NĐ",1,EXR_FC05) -> 26300 | AB103: =IF($C103="NĐ",1,EXR_FC05) -> 26300 | AC103: =IFERROR(SUMPRODUCT(AJ103:AL103,Z103:AB103)/AM103,0) -> 0 | AE103: =IFERROR(AJ103/P103,0) -> 0 | AF103: =IFERROR(AK103/Q103,0) -> 0 | AG103: =W103*AB103 -> 0 | AL103: =R103*AG103 -> 0 | AM103: =SUM(AJ103:AL103) -> 0 | AV103: =IFERROR(BA103/S103,0) -> 0 | BA103: =SUM(AX103:AZ103) -> 0 | BF103: =SUM(BC103:BE103) -> 0 | BH103: =AJ103-BC103 -> 0 | BI103: =AK103-BD103 -> 0 | BJ103: =AL103-BE103 -> 0 | BK103: =SUM(BH103:BJ103) -> 0
K104: =SUMIFS('Working-T05-B1'!L$8:L$150,'Working-T05-B1'!$C$8:$C$150,$D104) -> 0 | L104: {=SUMPRODUCT(Sales!$G$3:$H$100*(Sales!$B$3:$B$100=$D104))} -> 0 | P104: =SUMIFS('Working-T05-B1'!O$8:O$150,'Working-T05-B1'!$C$8:$C$150,$D104) -> 0 | S104: =SUM(P104:R104) -> 0 | X104: =IFERROR(IF($C104="XK",$AM104/$S104/$AC104,$AM104/$S104),0) -> 0 | Z104: =IF($C104="NĐ",1,IFERROR(SUMIFS(Data_FAGLL03[Amount in local currency],Data_FAGLL03[Offsetting acct no.],$E104,Data_FAGLL03[Material],$G104)/SUMIFS(Data_FAGLL03[Dthu (USD)],Data_FAGLL03[Offsetting acct no.],$E104,Data_FAGLL03[Material],$G104),0)) -> 0 | AA104: =IF($C104="NĐ",1,EXR_FC05) -> 26300 | AB104: =IF($C104="NĐ",1,EXR_FC05) -> 26300 | AC104: =IFERROR(SUMPRODUCT(AJ104:AL104,Z104:AB104)/AM104,0) -> 0 | AE104: =IFERROR(AJ104/P104,0) -> 0 | AF104: =IFERROR(AK104/Q104,0) -> 0 | AG104: =W104*AB104 -> 0 | AL104: =R104*AG104 -> 0 | AM104: =SUM(AJ104:AL104) -> 0 | AV104: =IFERROR(BA104/S104,0) -> 0 | BA104: =SUM(AX104:AZ104) -> 0 | BF104: =SUM(BC104:BE104) -> 0 | BH104: =AJ104-BC104 -> 0 | BI104: =AK104-BD104 -> 0 | BJ104: =AL104-BE104 -> 0 | BK104: =SUM(BH104:BJ104) -> 0
K105: =SUMIFS('Working-T05-B1'!L$8:L$150,'Working-T05-B1'!$C$8:$C$150,$D105) -> 0 | L105: {=SUMPRODUCT(Sales!$G$3:$H$100*(Sales!$B$3:$B$100=$D105))} -> 0 | P105: =SUMIFS('Working-T05-B1'!O$8:O$150,'Working-T05-B1'!$C$8:$C$150,$D105) -> 0 | S105: =SUM(P105:R105) -> 0 | X105: =IFERROR(IF($C105="XK",$AM105/$S105/$AC105,$AM105/$S105),0) -> 0 | Z105: =IF($C105="NĐ",1,IFERROR(SUMIFS(Data_FAGLL03[Amount in local currency],Data_FAGLL03[Offsetting acct no.],$E105,Data_FAGLL03[Material],$G105)/SUMIFS(Data_FAGLL03[Dthu (USD)],Data_FAGLL03[Offsetting acct no.],$E105,Data_FAGLL03[Material],$G105),0)) -> 0 | AA105: =IF($C105="NĐ",1,EXR_FC05) -> 26300 | AB105: =IF($C105="NĐ",1,EXR_FC05) -> 26300 | AC105: =IFERROR(SUMPRODUCT(AJ105:AL105,Z105:AB105)/AM105,0) -> 0 | AE105: =IFERROR(AJ105/P105,0) -> 0 | AF105: =IFERROR(AK105/Q105,0) -> 0 | AG105: =W105*AB105 -> 0 | AL105: =R105*AG105 -> 0 | AM105: =SUM(AJ105:AL105) -> 0 | AV105: =IFERROR(BA105/S105,0) -> 0 | BA105: =SUM(AX105:AZ105) -> 0 | BF105: =SUM(BC105:BE105) -> 0 | BH105: =AJ105-BC105 -> 0 | BI105: =AK105-BD105 -> 0 | BJ105: =AL105-BE105 -> 0 | BK105: =SUM(BH105:BJ105) -> 0
K106: =SUMIFS('Working-T05-B1'!L$8:L$150,'Working-T05-B1'!$C$8:$C$150,$D106) -> 0 | L106: {=SUMPRODUCT(Sales!$G$3:$H$100*(Sales!$B$3:$B$100=$D106))} -> 0 | P106: =SUMIFS('Working-T05-B1'!O$8:O$150,'Working-T05-B1'!$C$8:$C$150,$D106) -> 0 | S106: =SUM(P106:R106) -> 0 | X106: =IFERROR(IF($C106="XK",$AM106/$S106/$AC106,$AM106/$S106),0) -> 0 | Z106: =IF($C106="NĐ",1,IFERROR(SUMIFS(Data_FAGLL03[Amount in local currency],Data_FAGLL03[Offsetting acct no.],$E106,Data_FAGLL03[Material],$G106)/SUMIFS(Data_FAGLL03[Dthu (USD)],Data_FAGLL03[Offsetting acct no.],$E106,Data_FAGLL03[Material],$G106),0)) -> 0 | AA106: =IF($C106="NĐ",1,EXR_FC05) -> 26300 | AB106: =IF($C106="NĐ",1,EXR_FC05) -> 26300 | AC106: =IFERROR(SUMPRODUCT(AJ106:AL106,Z106:AB106)/AM106,0) -> 0 | AE106: =IFERROR(AJ106/P106,0) -> 0 | AF106: =IFERROR(AK106/Q106,0) -> 0 | AG106: =W106*AB106 -> 0 | AL106: =R106*AG106 -> 0 | AM106: =SUM(AJ106:AL106) -> 0 | AV106: =IFERROR(BA106/S106,0) -> 0 | BA106: =SUM(AX106:AZ106) -> 0 | BF106: =SUM(BC106:BE106) -> 0 | BH106: =AJ106-BC106 -> 0 | BI106: =AK106-BD106 -> 0 | BJ106: =AL106-BE106 -> 0 | BK106: =SUM(BH106:BJ106) -> 0
K107: =SUMIFS('Working-T05-B1'!L$8:L$150,'Working-T05-B1'!$C$8:$C$150,$D107) -> 0 | L107: {=SUMPRODUCT(Sales!$G$3:$H$100*(Sales!$B$3:$B$100=$D107))} -> 0 | P107: =SUMIFS('Working-T05-B1'!O$8:O$150,'Working-T05-B1'!$C$8:$C$150,$D107) -> 0 | S107: =SUM(P107:R107) -> 0 | X107: =IFERROR(IF($C107="XK",$AM107/$S107/$AC107,$AM107/$S107),0) -> 0 | Z107: =IF($C107="NĐ",1,IFERROR(SUMIFS(Data_FAGLL03[Amount in local currency],Data_FAGLL03[Offsetting acct no.],$E107,Data_FAGLL03[Material],$G107)/SUMIFS(Data_FAGLL03[Dthu (USD)],Data_FAGLL03[Offsetting acct no.],$E107,Data_FAGLL03[Material],$G107),0)) -> 0 | AA107: =IF($C107="NĐ",1,EXR_FC05) -> 26300 | AB107: =IF($C107="NĐ",1,EXR_FC05) -> 26300 | AC107: =IFERROR(SUMPRODUCT(AJ107:AL107,Z107:AB107)/AM107,0) -> 0 | AE107: =IFERROR(AJ107/P107,0) -> 0 | AF107: =IFERROR(AK107/Q107,0) -> 0 | AG107: =W107*AB107 -> 0 | AL107: =R107*AG107 -> 0 | AM107: =SUM(AJ107:AL107) -> 0 | AV107: =IFERROR(BA107/S107,0) -> 0 | BA107: =SUM(AX107:AZ107) -> 0 | BF107: =SUM(BC107:BE107) -> 0 | BH107: =AJ107-BC107 -> 0 | BI107: =AK107-BD107 -> 0 | BJ107: =AL107-BE107 -> 0 | BK107: =SUM(BH107:BJ107) -> 0
K108: =SUMIFS('Working-T05-B1'!L$8:L$150,'Working-T05-B1'!$C$8:$C$150,$D108) -> 0 | L108: {=SUMPRODUCT(Sales!$G$3:$H$100*(Sales!$B$3:$B$100=$D108))} -> 0 | P108: =SUMIFS('Working-T05-B1'!O$8:O$150,'Working-T05-B1'!$C$8:$C$150,$D108) -> 0 | S108: =SUM(P108:R108) -> 0 | X108: =IFERROR(IF($C108="XK",$AM108/$S108/$AC108,$AM108/$S108),0) -> 0 | Z108: =IF($C108="NĐ",1,IFERROR(SUMIFS(Data_FAGLL03[Amount in local currency],Data_FAGLL03[Offsetting acct no.],$E108,Data_FAGLL03[Material],$G108)/SUMIFS(Data_FAGLL03[Dthu (USD)],Data_FAGLL03[Offsetting acct no.],$E108,Data_FAGLL03[Material],$G108),0)) -> 0 | AA108: =IF($C108="NĐ",1,EXR_FC05) -> 26300 | AB108: =IF($C108="NĐ",1,EXR_FC05) -> 26300 | AC108: =IFERROR(SUMPRODUCT(AJ108:AL108,Z108:AB108)/AM108,0) -> 0 | AE108: =IFERROR(AJ108/P108,0) -> 0 | AF108: =IFERROR(AK108/Q108,0) -> 0 | AG108: =W108*AB108 -> 0 | AL108: =R108*AG108 -> 0 | AM108: =SUM(AJ108:AL108) -> 0 | AV108: =IFERROR(BA108/S108,0) -> 0 | BA108: =SUM(AX108:AZ108) -> 0 | BF108: =SUM(BC108:BE108) -> 0 | BH108: =AJ108-BC108 -> 0 | BI108: =AK108-BD108 -> 0 | BJ108: =AL108-BE108 -> 0 | BK108: =SUM(BH108:BJ108) -> 0
K109: =SUMIFS('Working-T05-B1'!L$8:L$150,'Working-T05-B1'!$C$8:$C$150,$D109) -> 0 | L109: {=SUMPRODUCT(Sales!$G$3:$H$100*(Sales!$B$3:$B$100=$D109))} -> 0 | P109: =SUMIFS('Working-T05-B1'!O$8:O$150,'Working-T05-B1'!$C$8:$C$150,$D109) -> 0 | S109: =SUM(P109:R109) -> 0 | X109: =IFERROR(IF($C109="XK",$AM109/$S109/$AC109,$AM109/$S109),0) -> 0 | Z109: =IF($C109="NĐ",1,IFERROR(SUMIFS(Data_FAGLL03[Amount in local currency],Data_FAGLL03[Offsetting acct no.],$E109,Data_FAGLL03[Material],$G109)/SUMIFS(Data_FAGLL03[Dthu (USD)],Data_FAGLL03[Offsetting acct no.],$E109,Data_FAGLL03[Material],$G109),0)) -> 0 | AA109: =IF($C109="NĐ",1,EXR_FC05) -> 26300 | AB109: =IF($C109="NĐ",1,EXR_FC05) -> 26300 | AC109: =IFERROR(SUMPRODUCT(AJ109:AL109,Z109:AB109)/AM109,0) -> 0 | AE109: =IFERROR(AJ109/P109,0) -> 0 | AF109: =IFERROR(AK109/Q109,0) -> 0 | AG109: =W109*AB109 -> 0 | AL109: =R109*AG109 -> 0 | AM109: =SUM(AJ109:AL109) -> 0 | AV109: =IFERROR(BA109/S109,0) -> 0 | BA109: =SUM(AX109:AZ109) -> 0 | BF109: =SUM(BC109:BE109) -> 0 | BH109: =AJ109-BC109 -> 0 | BI109: =AK109-BD109 -> 0 | BJ109: =AL109-BE109 -> 0 | BK109: =SUM(BH109:BJ109) -> 0
K110: =SUMIFS('Working-T05-B1'!L$8:L$150,'Working-T05-B1'!$C$8:$C$150,$D110) -> 0 | L110: {=SUMPRODUCT(Sales!$G$3:$H$100*(Sales!$B$3:$B$100=$D110))} -> 0 | P110: =SUMIFS('Working-T05-B1'!O$8:O$150,'Working-T05-B1'!$C$8:$C$150,$D110) -> 0 | S110: =SUM(P110:R110) -> 0 | X110: =IFERROR(IF($C110="XK",$AM110/$S110/$AC110,$AM110/$S110),0) -> 0 | Z110: =IF($C110="NĐ",1,IFERROR(SUMIFS(Data_FAGLL03[Amount in local currency],Data_FAGLL03[Offsetting acct no.],$E110,Data_FAGLL03[Material],$G110)/SUMIFS(Data_FAGLL03[Dthu (USD)],Data_FAGLL03[Offsetting acct no.],$E110,Data_FAGLL03[Material],$G110),0)) -> 0 | AA110: =IF($C110="NĐ",1,EXR_FC05) -> 26300 | AB110: =IF($C110="NĐ",1,EXR_FC05) -> 26300 | AC110: =IFERROR(SUMPRODUCT(AJ110:AL110,Z110:AB110)/AM110,0) -> 0 | AE110: =IFERROR(AJ110/P110,0) -> 0 | AF110: =IFERROR(AK110/Q110,0) -> 0 | AG110: =W110*AB110 -> 0 | AL110: =R110*AG110 -> 0 | AM110: =SUM(AJ110:AL110) -> 0 | AV110: =IFERROR(BA110/S110,0) -> 0 | BA110: =SUM(AX110:AZ110) -> 0 | BF110: =SUM(BC110:BE110) -> 0 | BH110: =AJ110-BC110 -> 0 | BI110: =AK110-BD110 -> 0 | BJ110: =AL110-BE110 -> 0 | BK110: =SUM(BH110:BJ110) -> 0
K111: =SUMIFS('Working-T05-B1'!L$8:L$150,'Working-T05-B1'!$C$8:$C$150,$D111) -> 0 | L111: {=SUMPRODUCT(Sales!$G$3:$H$100*(Sales!$B$3:$B$100=$D111))} -> 0 | P111: =SUMIFS('Working-T05-B1'!O$8:O$150,'Working-T05-B1'!$C$8:$C$150,$D111) -> 0 | S111: =SUM(P111:R111) -> 0 | X111: =IFERROR(IF($C111="XK",$AM111/$S111/$AC111,$AM111/$S111),0) -> 0 | Z111: =IF($C111="NĐ",1,IFERROR(SUMIFS(Data_FAGLL03[Amount in local currency],Data_FAGLL03[Offsetting acct no.],$E111,Data_FAGLL03[Material],$G111)/SUMIFS(Data_FAGLL03[Dthu (USD)],Data_FAGLL03[Offsetting acct no.],$E111,Data_FAGLL03[Material],$G111),0)) -> 0 | AA111: =IF($C111="NĐ",1,EXR_FC05) -> 26300 | AB111: =IF($C111="NĐ",1,EXR_FC05) -> 26300 | AC111: =IFERROR(SUMPRODUCT(AJ111:AL111,Z111:AB111)/AM111,0) -> 0 | AE111: =IFERROR(AJ111/P111,0) -> 0 | AF111: =IFERROR(AK111/Q111,0) -> 0 | AG111: =W111*AB111 -> 0 | AL111: =R111*AG111 -> 0 | AM111: =SUM(AJ111:AL111) -> 0 | AV111: =IFERROR(BA111/S111,0) -> 0 | BA111: =SUM(AX111:AZ111) -> 0 | BF111: =SUM(BC111:BE111) -> 0 | BH111: =AJ111-BC111 -> 0 | BI111: =AK111-BD111 -> 0 | BJ111: =AL111-BE111 -> 0 | BK111: =SUM(BH111:BJ111) -> 0
K112: =SUMIFS('Working-T05-B1'!L$8:L$150,'Working-T05-B1'!$C$8:$C$150,$D112) -> 0 | L112: {=SUMPRODUCT(Sales!$G$3:$H$100*(Sales!$B$3:$B$100=$D112))} -> 0 | P112: =SUMIFS('Working-T05-B1'!O$8:O$150,'Working-T05-B1'!$C$8:$C$150,$D112) -> 0 | S112: =SUM(P112:R112) -> 0 | X112: =IFERROR(IF($C112="XK",$AM112/$S112/$AC112,$AM112/$S112),0) -> 0 | Z112: =IF($C112="NĐ",1,IFERROR(SUMIFS(Data_FAGLL03[Amount in local currency],Data_FAGLL03[Offsetting acct no.],$E112,Data_FAGLL03[Material],$G112)/SUMIFS(Data_FAGLL03[Dthu (USD)],Data_FAGLL03[Offsetting acct no.],$E112,Data_FAGLL03[Material],$G112),0)) -> 0 | AA112: =IF($C112="NĐ",1,EXR_FC05) -> 26300 | AB112: =IF($C112="NĐ",1,EXR_FC05) -> 26300 | AC112: =IFERROR(SUMPRODUCT(AJ112:AL112,Z112:AB112)/AM112,0) -> 0 | AE112: =IFERROR(AJ112/P112,0) -> 0 | AF112: =IFERROR(AK112/Q112,0) -> 0 | AG112: =W112*AB112 -> 0 | AL112: =R112*AG112 -> 0 | AM112: =SUM(AJ112:AL112) -> 0 | AV112: =IFERROR(BA112/S112,0) -> 0 | BA112: =SUM(AX112:AZ112) -> 0 | BF112: =SUM(BC112:BE112) -> 0 | BH112: =AJ112-BC112 -> 0 | BI112: =AK112-BD112 -> 0 | BJ112: =AL112-BE112 -> 0 | BK112: =SUM(BH112:BJ112) -> 0
K113: =SUMIFS('Working-T05-B1'!L$8:L$150,'Working-T05-B1'!$C$8:$C$150,$D113) -> 0 | L113: {=SUMPRODUCT(Sales!$G$3:$H$100*(Sales!$B$3:$B$100=$D113))} -> 0 | P113: =SUMIFS('Working-T05-B1'!O$8:O$150,'Working-T05-B1'!$C$8:$C$150,$D113) -> 0 | S113: =SUM(P113:R113) -> 0 | X113: =IFERROR(IF($C113="XK",$AM113/$S113/$AC113,$AM113/$S113),0) -> 0 | Z113: =IF($C113="NĐ",1,IFERROR(SUMIFS(Data_FAGLL03[Amount in local currency],Data_FAGLL03[Offsetting acct no.],$E113,Data_FAGLL03[Material],$G113)/SUMIFS(Data_FAGLL03[Dthu (USD)],Data_FAGLL03[Offsetting acct no.],$E113,Data_FAGLL03[Material],$G113),0)) -> 0 | AA113: =IF($C113="NĐ",1,EXR_FC05) -> 26300 | AB113: =IF($C113="NĐ",1,EXR_FC05) -> 26300 | AC113: =IFERROR(SUMPRODUCT(AJ113:AL113,Z113:AB113)/AM113,0) -> 0 | AE113: =IFERROR(AJ113/P113,0) -> 0 | AF113: =IFERROR(AK113/Q113,0) -> 0 | AG113: =W113*AB113 -> 0 | AL113: =R113*AG113 -> 0 | AM113: =SUM(AJ113:AL113) -> 0 | AV113: =IFERROR(BA113/S113,0) -> 0 | BA113: =SUM(AX113:AZ113) -> 0 | BF113: =SUM(BC113:BE113) -> 0 | BH113: =AJ113-BC113 -> 0 | BI113: =AK113-BD113 -> 0 | BJ113: =AL113-BE113 -> 0 | BK113: =SUM(BH113:BJ113) -> 0
... K127: =SUMIFS('Working-T05-B1'!L$8:L$150,'Working-T05-B1'!$C$8:$C$150,$D127) -> 0 | L127: {=SUMPRODUCT(Sales!$G$3:$H$100*(Sales!$B$3:$B$100=$D127))} -> 0 | P127: =SUMIFS('Working-T05-B1'!O$8:O$150,'Working-T05-B1'!$C$8:$C$150,$D127) -> 0 | S127: =SUM(P127:R127) -> 0 | X127: =IFERROR(IF($C127="XK",$AM127/$S127/$AC127,$AM127/$S127),0) -> 0 | Z127: =IF($C127="NĐ",1,IFERROR(SUMIFS(Data_FAGLL03[Amount in local currency],Data_FAGLL03[Offsetting acct no.],$E127,Data_FAGLL03[Material],$G127)/SUMIFS(Data_FAGLL03[Dthu (USD)],Data_FAGLL03[Offsetting acct no.],$E127,Data_FAGLL03[Material],$G127),0)) -> 0 | AA127: =IF($C127="NĐ",1,EXR_FC05) -> 26300 | AB127: =IF($C127="NĐ",1,EXR_FC05) -> 26300 | AC127: =IFERROR(SUMPRODUCT(AJ127:AL127,Z127:AB127)/AM127,0) -> 0 | AE127: =IFERROR(AJ127/P127,0) -> 0 | AF127: =IFERROR(AK127/Q127,0) -> 0 | AG127: =W127*AB127 -> 0 | AL127: =R127*AG127 -> 0 | AM127: =SUM(AJ127:AL127) -> 0 | AV127: =IFERROR(BA127/S127,0) -> 0 | BA127: =SUM(AX127:AZ127) -> 0 | BF127: =SUM(BC127:BE127) -> 0 | BH127: =AJ127-BC127 -> 0 | BI127: =AK127-BD127 -> 0 | BJ127: =AL127-BE127 -> 0 | BK127: =SUM(BH127:BJ127) -> 0
K128: =SUMIFS('Working-T05-B1'!L$8:L$150,'Working-T05-B1'!$C$8:$C$150,$D128) -> 0 | L128: {=SUMPRODUCT(Sales!$G$3:$H$100*(Sales!$B$3:$B$100=$D128))} -> 0 | P128: =SUMIFS('Working-T05-B1'!O$8:O$150,'Working-T05-B1'!$C$8:$C$150,$D128) -> 0 | S128: =SUM(P128:R128) -> 0 | X128: =IFERROR(IF($C128="XK",$AM128/$S128/$AC128,$AM128/$S128),0) -> 0 | Z128: =IF($C128="NĐ",1,IFERROR(SUMIFS(Data_FAGLL03[Amount in local currency],Data_FAGLL03[Offsetting acct no.],$E128,Data_FAGLL03[Material],$G128)/SUMIFS(Data_FAGLL03[Dthu (USD)],Data_FAGLL03[Offsetting acct no.],$E128,Data_FAGLL03[Material],$G128),0)) -> 0 | AA128: =IF($C128="NĐ",1,EXR_FC05) -> 26300 | AB128: =IF($C128="NĐ",1,EXR_FC05) -> 26300 | AC128: =IFERROR(SUMPRODUCT(AJ128:AL128,Z128:AB128)/AM128,0) -> 0 | AL128: =R128*AG128 -> 0 | AM128: =SUM(AJ128:AL128) -> 0 | AV128: =IFERROR(BA128/S128,0) -> 0 | BA128: =SUM(AX128:AZ128) -> 0 | BF128: =SUM(BC128:BE128) -> 0 | BH128: =AJ128-BC128 -> 0 | BI128: =AK128-BD128 -> 0 | BJ128: =AL128-BE128 -> 0 | BK128: =SUM(BH128:BJ128) -> 0
K129: =SUMIFS('Working-T05-B1'!L$8:L$150,'Working-T05-B1'!$C$8:$C$150,$D129) -> 0 | L129: {=SUMPRODUCT(Sales!$G$3:$H$100*(Sales!$B$3:$B$100=$D129))} -> 0 | P129: =SUMIFS('Working-T05-B1'!O$8:O$150,'Working-T05-B1'!$C$8:$C$150,$D129) -> 0 | S129: =SUM(P129:R129) -> 0 | X129: =IFERROR($AM129/$S129,0) -> 0 | Z129: =IF($C129="NĐ",1,IFERROR(SUMIFS(Data_FAGLL03[Amount in local currency],Data_FAGLL03[Offsetting acct no.],$E129,Data_FAGLL03[Material],$G129)/SUMIFS(Data_FAGLL03[Dthu (USD)],Data_FAGLL03[Offsetting acct no.],$E129,Data_FAGLL03[Material],$G129),0)) -> 0 | AA129: =IF($C129="NĐ",1,EXR_FC05) -> 26300 | AB129: =IF($C129="NĐ",1,EXR_FC05) -> 26300 | AC129: =IFERROR(SUMPRODUCT(AJ129:AL129,Z129:AB129)/AM129,0) -> 0 | AE129: =U129*Z129 -> 0 | AF129: =V129*AA129 -> 0 | AG129: =W129*AB129 -> 0 | AL129: =R129*AG129 -> 0 | AM129: =SUM(AJ129:AL129) -> 0 | AV129: =IFERROR(BA129/S129,0) -> 0 | BA129: =SUM(AX129:AZ129) -> 0 | BF129: =SUM(BC129:BE129) -> 0 | BH129: =AJ129-BC129 -> 0 | BI129: =AK129-BD129 -> 0 | BJ129: =AL129-BE129 -> 0 | BK129: =SUM(BH129:BJ129) -> 0
K130: =SUMIFS('Working-T05-B1'!L$8:L$150,'Working-T05-B1'!$C$8:$C$150,$D130) -> 0 | L130: {=SUMPRODUCT(Sales!$G$3:$H$100*(Sales!$B$3:$B$100=$D130))} -> 0 | P130: =SUMIFS('Working-T05-B1'!O$8:O$150,'Working-T05-B1'!$C$8:$C$150,$D130) -> 0 | S130: =SUM(P130:R130) -> 0 | X130: =IFERROR($AM130/$S130,0) -> 0 | Z130: =IF($C130="NĐ",1,IFERROR(SUMIFS(Data_FAGLL03[Amount in local currency],Data_FAGLL03[Offsetting acct no.],$E130,Data_FAGLL03[Material],$G130)/SUMIFS(Data_FAGLL03[Dthu (USD)],Data_FAGLL03[Offsetting acct no.],$E130,Data_FAGLL03[Material],$G130),0)) -> 0 | AA130: =IF($C130="NĐ",1,EXR_FC05) -> 26300 | AB130: =IF($C130="NĐ",1,EXR_FC05) -> 26300 | AC130: =IFERROR(SUMPRODUCT(AJ130:AL130,Z130:AB130)/AM130,0) -> 0 | AE130: =U130*Z130 -> 0 | AF130: =V130*AA130 -> 0 | AG130: =W130*AB130 -> 0 | AL130: =R130*AG130 -> 0 | AM130: =SUM(AJ130:AL130) -> 0 | AV130: =IFERROR(BA130/S130,0) -> 0 | BA130: =SUM(AX130:AZ130) -> 0 | BF130: =SUM(BC130:BE130) -> 0 | BH130: =AJ130-BC130 -> 0 | BI130: =AK130-BD130 -> 0 | BJ130: =AL130-BE130 -> 0 | BK130: =SUM(BH130:BJ130) -> 0
K131: =SUMIFS('Working-T05-B1'!L$8:L$150,'Working-T05-B1'!$C$8:$C$150,$D131) -> 0 | L131: {=SUMPRODUCT(Sales!$G$3:$H$100*(Sales!$B$3:$B$100=$D131))} -> 0 | P131: =SUMIFS('Working-T05-B1'!O$8:O$150,'Working-T05-B1'!$C$8:$C$150,$D131) -> 0 | S131: =SUM(P131:R131) -> 0 | X131: =IFERROR($AM131/$S131,0) -> 0 | Z131: =IF($C131="NĐ",1,IFERROR(SUMIFS(Data_FAGLL03[Amount in local currency],Data_FAGLL03[Offsetting acct no.],$E131,Data_FAGLL03[Material],$G131)/SUMIFS(Data_FAGLL03[Dthu (USD)],Data_FAGLL03[Offsetting acct no.],$E131,Data_FAGLL03[Material],$G131),0)) -> 0 | AA131: =IF($C131="NĐ",1,EXR_FC05) -> 26300 | AB131: =IF($C131="NĐ",1,EXR_FC05) -> 26300 | AC131: =IFERROR(SUMPRODUCT(AJ131:AL131,Z131:AB131)/AM131,0) -> 0 | AE131: =U131*Z131 -> 0 | AF131: =V131*AA131 -> 0 | AG131: =W131*AB131 -> 0 | AL131: =R131*AG131 -> 0 | AM131: =SUM(AJ131:AL131) -> 0 | AV131: =IFERROR(BA131/S131,0) -> 0 | BA131: =SUM(AX131:AZ131) -> 0 | BF131: =SUM(BC131:BE131) -> 0 | BH131: =AJ131-BC131 -> 0 | BI131: =AK131-BD131 -> 0 | BJ131: =AL131-BE131 -> 0 | BK131: =SUM(BH131:BJ131) -> 0
...

Sheet GIÁ XUẤT KHO
D1: Nhựa | E1: Nhựa | F1: Nhựa | G1: Nhựa | H1: Màu/hóa chất/phụ gia | I1: Màu/hóa chất/phụ gia | J1: Màu/hóa chất/phụ gia | K1: Gia công | L1: Điện | M1: Bao bì | N1: Bao bì | O1: Bao bì | P1: Bao bì | Q1: Bao bì | R1: NCTT | S1: NCTT | T1: NCGT | U1: Khấu hao máy | V1: X | W1: CP sx chung | AJ1: =AJ2-SUM('Working-T05-B2'!S8:S150) -> 0 | BH1: Bán | BK1: ='[1]GIÁ XUẤT KHO'!$BK$1 -> 5783401.8 | BL1: =SUMIFS($AJ$4:$AJ$97,$A$4:$A$97,"11*") -> 5230593.7
AJ2: =SUM(AJ4:AJ97) -> 5480593.7
A3: Mã SKU | B3: Tên SKU | C3: Qty | D3: Value_Hạt nhựa | E3: Value_Nhựa phế | F3: Value_Vảy mua ngoài | G3: Value_Bán TP | H3: Value_Màu | I3: Value_Keo xay | J3: Value_NVL phụ | K3: Value_Gia công | L3: Value_Cp điện sx | M3: Value_Bao bì đóng gói | N3: Value_Nylon màng co | O3: Value_Thùng giấy | P3: Value_Tem mã vạch | Q3: Value_Nhãn | R3: Value_Nhân công đứng máy | S3: Value_Nhân công đóng gói | T3: Value_Nhân công gián tiếp | U3: Value_Khấu hao máy | V3: Value_Khấu hao khuôn | W3: Value_Cp sx chung | Y3: ĐG | Z3: Nhựa | AA3: Màu/hóa chất/phụ gia | AB3: Gia công | AC3: Điện | AD3: Bao bì | AE3: NCTT | AF3: NCGT | AG3: Khấu hao máy | AH3: CP sx chung | AJ3: SL-03 | AM3: Nhựa | AN3: Màu/hóa chất/phụ gia | AO3: Bao bì | AP3: Điện | AQ3: Gia công | AR3: NCTT | AS3: NCGT | AT3: Khấu hao máy | AU3: CP sx chung | AW3: Tổng_ĐG_BC | AX3: Nhựa | AY3: Màu/hóa chất/phụ gia | AZ3: Bao bì | BA3: Điện | BB3: Gia công | BC3: NCTT | BD3: NCGT | BE3: Khấu hao máy | BF3: CP sx chung | BI3: 2 | BJ3: 3 | BK3: 4 | BL3: 5 | BM3: 6
A4: 110000329 | B4: Hạt nhựa rPET WSS01 | C4: 411288 | D4: 0 | E4: 7993588340 | F4: 74955 | G4: 127963366 | H4: 3755225 | I4: 0 | J4: 32326038 | K4: 115 | L4: 867953867 | M4: 81209917 | N4: 139 | O4: 0 | P4: 0 | Q4: 0 | R4: 641424427 | S4: 1 | T4: 1034615386 | U4: 485479813 | V4: 0 | W4: 2410804292 | Y4: =SUM(Z4:AH4) -> 33259.409 | Z4: =IFERROR(SUMIFS($D4:$W4,$D$1:$W$1,Z$3)/$C4,0) -> 19746.812 | AA4: =IFERROR(SUMIFS($D4:$W4,$D$1:$W$1,AA$3)/$C4,0) -> 87.727488 | AB4: =IFERROR(SUMIFS($D4:$W4,$D$1:$W$1,AB$3)/$C4,0) -> 0.00027960942 | AC4: =IFERROR(SUMIFS($D4:$W4,$D$1:$W$1,AC$3)/$C4,0) -> 2110.3311 | AD4: =IFERROR(SUMIFS($D4:$W4,$D$1:$W$1,AD$3)/$C4,0) -> 197.45302 | AE4: =IFERROR(SUMIFS($D4:$W4,$D$1:$W$1,AE$3)/$C4,0) -> 1559.5506 | AF4: =IFERROR(SUMIFS($D4:$W4,$D$1:$W$1,AF$3)/$C4,0) -> 2515.5497 | AG4: =IFERROR(SUMIFS($D4:$W4,$D$1:$W$1,AG$3)/$C4,0) -> 1180.389 | AH4: =IFERROR(SUMIFS($D4:$W4,$D$1:$W$1,AH$3)/$C4,0) -> 5861.5965 | AJ4: =SUMIFS('Working-T05-B2'!$S$8:$S$150,'Working-T05-B2'!$G$8:$G$150,$A4) -> 30800 | AK4: =C4-AJ4 -> 380488 | AM4: 0.01 | AU4: 0.1 | AW4: =SUM(AX4:BF4) -> 32475.781 | AX4: =Z4*(1-AM4) -> 19549.344 | AY4: =AA4*(1-AN4) -> 87.727488 | AZ4: =AB4*(1-AO4) -> 0.00027960942 | BA4: =AC4*(1-AP4) -> 2110.3311 | BB4: =AD4*(1-AQ4) -> 197.45302 | BC4: =AE4*(1-AR4) -> 1559.5506 | BD4: =AF4*(1-AS4) -> 2515.5497 | BE4: =AG4*(1-AT4) -> 1180.389 | BF4: =AH4*(1-AU4) -> 5275.4368 | BH4: Tổng | BI4: 1811100 | BJ4: 4279489 | BK4: =SUM(BK5:BK7) -> 4050000 | BL4: =SUM(BL5:BL7) -> 4260000 | BM4: =SUM(BM5:BM7) -> 4315000
A5: 110000332 | B5: Hạt nhựa rPET iSS01084G | C5: 441079.35 | D5: 16 | E5: 17518447662 | F5: 3631357 | G5: -10142741923 | H5: 73850651 | I5: 0 | J5: 47534407 | K5: 49456 | L5: 806160270 | M5: 95420869 | N5: -1909 | O5: 0 | P5: 0 | Q5: 0 | R5: 576893198 | S5: 1251 | T5: 929621172 | U5: 223177837 | V5: 0 | W5: 2555321058 | Y5: =SUM(Z5:AH5) -> 28764.36 | Z5: =IFERROR(SUMIFS($D5:$W5,$D$1:$W$1,Z$3)/$C5,0) -> 16730.18 | AA5: =IFERROR(SUMIFS($D5:$W5,$D$1:$W$1,AA$3)/$C5,0) -> 275.20005 | AB5: =IFERROR(SUMIFS($D5:$W5,$D$1:$W$1,AB$3)/$C5,0) -> 0.11212495 | AC5: =IFERROR(SUMIFS($D5:$W5,$D$1:$W$1,AC$3)/$C5,0) -> 1827.699 | AD5: =IFERROR(SUMIFS($D5:$W5,$D$1:$W$1,AD$3)/$C5,0) -> 216.3306 | AE5: =IFERROR(SUMIFS($D5:$W5,$D$1:$W$1,AE$3)/$C5,0) -> 1307.9153 | AF5: =IFERROR(SUMIFS($D5:$W5,$D$1:$W$1,AF$3)/$C5,0) -> 2107.6053 | AG5: =IFERROR(SUMIFS($D5:$W5,$D$1:$W$1,AG$3)/$C5,0) -> 505.98115 | AH5: =IFERROR(SUMIFS($D5:$W5,$D$1:$W$1,AH$3)/$C5,0) -> 5793.3364 | AJ5: =SUMIFS('Working-T05-B2'!$S$8:$S$150,'Working-T05-B2'!$G$8:$G$150,$A5) -> 1012000 | AK5: =C5-AJ5 -> -570920.65 | AM5: 0.01 | AU5: 0.1 | AW5: =SUM(AX5:BF5) -> 28017.725 | AX5: =Z5*(1-AM5) -> 16562.879 | AY5: =AA5*(1-AN5) -> 275.20005 | AZ5: =AB5*(1-AO5) -> 0.11212495 | BA5: =AC5*(1-AP5) -> 1827.699 | BB5: =AD5*(1-AQ5) -> 216.3306 | BC5: =AE5*(1-AR5) -> 1307.9153 | BD5: =AF5*(1-AS5) -> 2107.6053 | BE5: =AG5*(1-AT5) -> 505.98115 | BF5: =AH5*(1-AU5) -> 5214.0028 | BH5: Hạt PET | BK5: 3600000 | BL5: 3800000 | BM5: 3800000
A6: 110000339 | B6: Hạt Nhựa rHDPE MBF01 | C6: 199837.5 | D6: 35636309 | E6: 5909746730 | F6: 0 | G6: -1599936804 | H6: 82311513 | I6: 0 | J6: 11147457 | K6: 157965184 | L6: 268270505 | M6: 47847254 | N6: 0 | O6: 0 | P6: 0 | Q6: 0 | R6: 311854327 | S6: 174513 | T6: 282502769 | U6: 88115406 | V6: 0 | W6: 441269388 | Y6: =SUM(Z6:AH6) -> 30209.068 | Z6: =IFERROR(SUMIFS($D6:$W6,$D$1:$W$1,Z$3)/$C6,0) -> 21744.899 | AA6: =IFERROR(SUMIFS($D6:$W6,$D$1:$W$1,AA$3)/$C6,0) -> 467.67484 | AB6: =IFERROR(SUMIFS($D6:$W6,$D$1:$W$1,AB$3)/$C6,0) -> 790.46818 | AC6: =IFERROR(SUMIFS($D6:$W6,$D$1:$W$1,AC$3)/$C6,0) -> 1342.4433 | AD6: =IFERROR(SUMIFS($D6:$W6,$D$1:$W$1,AD$3)/$C6,0) -> 239.43081 | AE6: =IFERROR(SUMIFS($D6:$W6,$D$1:$W$1,AE$3)/$C6,0) -> 1561.4128 | AF6: =IFERROR(SUMIFS($D6:$W6,$D$1:$W$1,AF$3)/$C6,0) -> 1413.6624 | AG6: =IFERROR(SUMIFS($D6:$W6,$D$1:$W$1,AG$3)/$C6,0) -> 440.93529 | AH6: =IFERROR(SUMIFS($D6:$W6,$D$1:$W$1,AH$3)/$C6,0) -> 2208.1411 | AJ6: =SUMIFS('Working-T05-B2'!$S$8:$S$150,'Working-T05-B2'!$G$8:$G$150,$A6) -> 285000 | AK6: =C6-AJ6 -> -85162.5 | AU6: 0.1 | AW6: =SUM(AX6:BF6) -> 29988.254 | AX6: =Z6*(1-AM6) -> 21744.899 | AY6: =AA6*(1-AN6) -> 467.67484 | AZ6: =AB6*(1-AO6) -> 790.46818 | BA6: =AC6*(1-AP6) -> 1342.4433 | BB6: =AD6*(1-AQ6) -> 239.43081 | BC6: =AE6*(1-AR6) -> 1561.4128 | BD6: =AF6*(1-AS6) -> 1413.6624 | BE6: =AG6*(1-AT6) -> 440.93529 | BF6: =AH6*(1-AU6) -> 1987.3269 | BH6: Hạt Xơ sợi | BK6: 50000 | BL6: 60000 | BM6: 65000
A7: 110000341 | B7: Hạt nhựa rHDPE rHDB04B01 | C7: 101075.5 | D7: 362337 | E7: 274182945 | F7: 0 | G7: 1056884239 | H7: 30476414 | I7: 0 | J7: 3313276 | K7: 16547471 | L7: 112027598 | M7: 24052932 | N7: 255 | O7: 0 | P7: 0 | Q7: 0 | R7: 143583199 | S7: 5194 | T7: 136693798 | U7: 27782741 | V7: 0 | W7: 230932073 | Y7: =SUM(Z7:AH7) -> 20349.585 | Z7: =IFERROR(SUMIFS($D7:$W7,$D$1:$W$1,Z$3)/$C7,0) -> 13172.624 | AA7: =IFERROR(SUMIFS($D7:$W7,$D$1:$W$1,AA$3)/$C7,0) -> 334.30149 | AB7: =IFERROR(SUMIFS($D7:$W7,$D$1:$W$1,AB$3)/$C7,0) -> 163.71397 | AC7: =IFERROR(SUMIFS($D7:$W7,$D$1:$W$1,AC$3)/$C7,0) -> 1108.3556 | AD7: =IFERROR(SUMIFS($D7:$W7,$D$1:$W$1,AD$3)/$C7,0) -> 237.97248 | AE7: =IFERROR(SUMIFS($D7:$W7,$D$1:$W$1,AE$3)/$C7,0) -> 1420.6053 | AF7: =IFERROR(SUMIFS($D7:$W7,$D$1:$W$1,AF$3)/$C7,0) -> 1352.393 | AG7: =IFERROR(SUMIFS($D7:$W7,$D$1:$W$1,AG$3)/$C7,0) -> 274.87117 | AH7: =IFERROR(SUMIFS($D7:$W7,$D$1:$W$1,AH$3)/$C7,0) -> 2284.7483 | AJ7: =SUMIFS('Working-T05-B2'!$S$8:$S$150,'Working-T05-B2'!$G$8:$G$150,$A7) -> 30000 | AK7: =C7-AJ7 -> 71075.5 | AW7: =SUM(AX7:BF7) -> 20349.585 | AX7: =Z7*(1-AM7) -> 13172.624 | AY7: =AA7*(1-AN7) -> 334.30149 | AZ7: =AB7*(1-AO7) -> 163.71397 | BA7: =AC7*(1-AP7) -> 1108.3556 | BB7: =AD7*(1-AQ7) -> 237.97248 | BC7: =AE7*(1-AR7) -> 1420.6053 | BD7: =AF7*(1-AS7) -> 1352.393 | BE7: =AG7*(1-AT7) -> 274.87117 | BF7: =AH7*(1-AU7) -> 2284.7483 | BH7: Hạt HD thổi/PP | BK7: 400000 | BL7: 400000 | BM7: 450000
A8: 110000354 | B8: Hạt nhựa rPET WSS01G 1 | C8: 400184.5 | D8: 13 | E8: 5089089350 | F8: 41587 | G8: 2190262131 | H8: 5863039 | I8: 0 | J8: 67336027 | K8: 38511 | L8: 511656179 | M8: 70238014 | N8: 28945 | O8: 0 | P8: 0 | Q8: 0 | R8: 288665212 | S8: 584 | T8: 464325242 | U8: 126263298 | V8: 0 | W8: 1376359217 | Y8: =SUM(Z8:AH8) -> 25463.673 | Z8: =IFERROR(SUMIFS($D8:$W8,$D$1:$W$1,Z$3)/$C8,0) -> 18190.093 | AA8: =IFERROR(SUMIFS($D8:$W8,$D$1:$W$1,AA$3)/$C8,0) -> 182.9133 | AB8: =IFERROR(SUMIFS($D8:$W8,$D$1:$W$1,AB$3)/$C8,0) -> 0.096233112 | AC8: =IFERROR(SUMIFS($D8:$W8,$D$1:$W$1,AC$3)/$C8,0) -> 1278.5507 | AD8: =IFERROR(SUMIFS($D8:$W8,$D$1:$W$1,AD$3)/$C8,0) -> 175.58641 | AE8: =IFERROR(SUMIFS($D8:$W8,$D$1:$W$1,AE$3)/$C8,0) -> 721.33178 | AF8: =IFERROR(SUMIFS($D8:$W8,$D$1:$W$1,AF$3)/$C8,0) -> 1160.2779 | AG8: =IFERROR(SUMIFS($D8:$W8,$D$1:$W$1,AG$3)/$C8,0) -> 315.51271 | AH8: =IFERROR(SUMIFS($D8:$W8,$D$1:$W$1,AH$3)/$C8,0) -> 3439.3117 | AJ8: =SUMIFS('Working-T05-B2'!$S$8:$S$150,'Working-T05-B2'!$G$8:$G$150,$A8) -> 1943973.6 | AK8: =C8-AJ8 -> -1543789.1 | AM8: 0.01 | AU8: 0.1 | AW8: =SUM(AX8:BF8) -> 24937.841 | AX8: =Z8*(1-AM8) -> 18008.192 | AY8: =AA8*(1-AN8) -> 182.9133 | AZ8: =AB8*(1-AO8) -> 0.096233112 | BA8: =AC8*(1-AP8) -> 1278.5507 | BB8: =AD8*(1-AQ8) -> 175.58641 | BC8: =AE8*(1-AR8) -> 721.33178 | BD8: =AF8*(1-AS8) -> 1160.2779 | BE8: =AG8*(1-AT8) -> 315.51271 | BF8: =AH8*(1-AU8) -> 3095.3805
A9: 110000355 | B9: Hạt nhựa rPET iSS01G 1 | C9: 50325.75 | D9: 0 | E9: 126637587 | F9: 46288 | G9: 862458744 | H9: 147914 | I9: 0 | J9: 8362059 | K9: 1695 | L9: 40181389 | M9: 11659232 | N9: 15728 | O9: 0 | P9: 0 | Q9: 0 | R9: 21791351 | S9: 40 | T9: 74181150 | U9: 3844611 | V9: 0 | W9: 196989967 | Y9: =SUM(Z9:AH9) -> 26752.065 | Z9: =IFERROR(SUMIFS($D9:$W9,$D$1:$W$1,Z$3)/$C9,0) -> 19654.801 | AA9: =IFERROR(SUMIFS($D9:$W9,$D$1:$W$1,AA$3)/$C9,0) -> 169.09779 | AB9: =IFERROR(SUMIFS($D9:$W9,$D$1:$W$1,AB$3)/$C9,0) -> 0.033680571 | AC9: =IFERROR(SUMIFS($D9:$W9,$D$1:$W$1,AC$3)/$C9,0) -> 798.42603 | AD9: =IFERROR(SUMIFS($D9:$W9,$D$1:$W$1,AD$3)/$C9,0) -> 231.9878 | AE9: =IFERROR(SUMIFS($D9:$W9,$D$1:$W$1,AE$3)/$C9,0) -> 433.00678 | AF9: =IFERROR(SUMIFS($D9:$W9,$D$1:$W$1,AF$3)/$C9,0) -> 1474.0198 | AG9: =IFERROR(SUMIFS($D9:$W9,$D$1:$W$1,AG$3)/$C9,0) -> 76.39451 | AH9: =IFERROR(SUMIFS($D9:$W9,$D$1:$W$1,AH$3)/$C9,0) -> 3914.2977 | AJ9: =SUMIFS('Working-T05-B2'!$S$8:$S$150,'Working-T05-B2'!$G$8:$G$150,$A9) -> 597000 | AK9: =C9-AJ9 -> -546674.25 | AM9: 0.01 | AU9: 0.1 | AW9: =SUM(AX9:BF9) -> 26164.088 | AX9: =Z9*(1-AM9) -> 19458.253 | AY9: =AA9*(1-AN9) -> 169.09779 | AZ9: =AB9*(1-AO9) -> 0.033680571 | BA9: =AC9*(1-AP9) -> 798.42603 | BB9: =AD9*(1-AQ9) -> 231.9878 | BC9: =AE9*(1-AR9) -> 433.00678 | BD9: =AF9*(1-AS9) -> 1474.0198 | BE9: =AG9*(1-AT9) -> 76.39451 | BF9: =AH9*(1-AU9) -> 3522.8679
A10: 110000359 | B10: Hạt nhựa rPET WSS03G | C10: 1696930.8 | D10: 1696 | E10: 21242639924 | F10: 72728640 | G10: 11943321290 | H10: 37510470 | I10: 0 | J10: 1743319174 | K10: 7381606 | L10: 1798767019 | M10: 356806093 | N10: 136804 | O10: 0 | P10: 0 | Q10: 0 | R10: 1862688398 | S10: 98901 | T10: 1771070730 | U10: 737176894 | V10: 0 | W10: 4602738046 | Y10: =SUM(Z10:AH10) -> 27211.708 | Z10: =IFERROR(SUMIFS($D10:$W10,$D$1:$W$1,Z$3)/$C10,0) -> 19599.321 | AA10: =IFERROR(SUMIFS($D10:$W10,$D$1:$W$1,AA$3)/$C10,0) -> 1049.4415 | AB10: =IFERROR(SUMIFS($D10:$W10,$D$1:$W$1,AB$3)/$C10,0) -> 4.3499747 | AC10: =IFERROR(SUMIFS($D10:$W10,$D$1:$W$1,AC$3)/$C10,0) -> 1060.012 | AD10: =IFERROR(SUMIFS($D10:$W10,$D$1:$W$1,AD$3)/$C10,0) -> 210.34617 | AE10: =IFERROR(SUMIFS($D10:$W10,$D$1:$W$1,AE$3)/$C10,0) -> 1097.7391 | AF10: =IFERROR(SUMIFS($D10:$W10,$D$1:$W$1,AF$3)/$C10,0) -> 1043.6906 | AG10: =IFERROR(SUMIFS($D10:$W10,$D$1:$W$1,AG$3)/$C10,0) -> 434.41777 | AH10: =IFERROR(SUMIFS($D10:$W10,$D$1:$W$1,AH$3)/$C10,0) -> 2712.3899 | AJ10: =SUMIFS('Working-T05-B2'!$S$8:$S$150,'Working-T05-B2'!$G$8:$G$150,$A10) -> 333300 | AK10: =C10-AJ10 -> 1363630.8 | AM10: 0.01 | AW10: =SUM(AX10:BF10) -> 27015.715 | AX10: =Z10*(1-AM10) -> 19403.328 | AY10: =AA10*(1-AN10) -> 1049.4415 | AZ10: =AB10*(1-AO10) -> 4.3499747 | BA10: =AC10*(1-AP10) -> 1060.012 | BB10: =AD10*(1-AQ10) -> 210.34617 | BC10: =AE10*(1-AR10) -> 1097.7391 | BD10: =AF10*(1-AS10) -> 1043.6906 | BE10: =AG10*(1-AT10) -> 434.41777 | BF10: =AH10*(1-AU10) -> 2712.3899 | BH10: 2T GẦN NHẤT | BK10: =AVERAGE(BI4:BJ4) -> 3045294.5 | BL10: =AVERAGE(BJ4:BK4) -> 4164744.5 | BM10: =AVERAGE(BK4:BL4) -> 4155000
A11: 110000360 | B11: Hạt nhựa rHDI4L01 | C11: 40070 | D11: 182 | E11: 17695032 | F11: 0 | G11: 674049339 | H11: 66369852 | I11: 0 | J11: 1921984 | K11: 142508 | L11: 31294980 | M11: 7775543 | N11: 0 | O11: 0 | P11: 0 | Q11: 0 | R11: 36397291 | S11: 115 | T11: 34947317 | U11: 21985299 | V11: 0 | W11: 39647004 | Y11: =SUM(Z11:AH11) -> 23264.947 | Z11: =IFERROR(SUMIFS($D11:$W11,$D$1:$W$1,Z$3)/$C11,0) -> 17263.403 | AA11: =IFERROR(SUMIFS($D11:$W11,$D$1:$W$1,AA$3)/$C11,0) -> 1704.3134 | AB11: =IFERROR(SUMIFS($D11:$W11,$D$1:$W$1,AB$3)/$C11,0) -> 3.5564762 | AC11: =IFERROR(SUMIFS($D11:$W11,$D$1:$W$1,AC$3)/$C11,0) -> 781.00774 | AD11: =IFERROR(SUMIFS($D11:$W11,$D$1:$W$1,AD$3)/$C11,0) -> 194.04899 | AE11: =IFERROR(SUMIFS($D11:$W11,$D$1:$W$1,AE$3)/$C11,0) -> 908.34555 | AF11: =IFERROR(SUMIFS($D11:$W11,$D$1:$W$1,AF$3)/$C11,0) -> 872.15665 | AG11: =IFERROR(SUMIFS($D11:$W11,$D$1:$W$1,AG$3)/$C11,0) -> 548.6723 | AH11: =IFERROR(SUMIFS($D11:$W11,$D$1:$W$1,AH$3)/$C11,0) -> 989.44357 | AJ11: =SUMIFS('Working-T05-B2'!$S$8:$S$150,'Working-T05-B2'!$G$8:$G$150,$A11) -> 0 | AK11: =C11-AJ11 -> 40070 | AW11: =SUM(AX11:BF11) -> 23264.947 | AX11: =Z11*(1-AM11) -> 17263.403 | AY11: =AA11*(1-AN11) -> 1704.3134 | AZ11: =AB11*(1-AO11) -> 3.5564762 | BA11: =AC11*(1-AP11) -> 781.00774 | BB11: =AD11*(1-AQ11) -> 194.04899 | BC11: =AE11*(1-AR11) -> 908.34555 | BD11: =AF11*(1-AS11) -> 872.15665 | BE11: =AG11*(1-AT11) -> 548.6723 | BF11: =AH11*(1-AU11) -> 989.44357 | BH11: Tỷ lệ giảm | BK11: =BK10/BK4 -> 0.75192457 | BL11: =BL10/BL4 -> 0.97763955 | BM11: =BM10/BM4 -> 0.96292005
A12: 110000361 | B12: Hạt nhựa rHDI3R01 | C12: 21050 | D12: -11 | E12: 1760682659 | F12: 0 | G12: -1495391568 | H12: 3434869 | I12: 0 | J12: 1570349 | K12: 5539813 | L12: 101743143 | M12: 16231209 | N12: 0 | O12: 0 | P12: 0 | Q12: 0 | R12: 177051553 | S12: 253423 | T12: 158022026 | U12: 96542054 | V12: 0 | W12: 180230188 | Y12: =SUM(Z12:AH12) -> 47786.684 | Z12: =IFERROR(SUMIFS($D12:$W12,$D$1:$W$1,Z$3)/$C12,0) -> 12602.902 | AA12: =IFERROR(SUMIFS($D12:$W12,$D$1:$W$1,AA$3)/$C12,0) -> 237.77758 | AB12: =IFERROR(SUMIFS($D12:$W12,$D$1:$W$1,AB$3)/$C12,0) -> 263.17401 | AC12: =IFERROR(SUMIFS($D12:$W12,$D$1:$W$1,AC$3)/$C12,0) -> 4833.4035 | AD12: =IFERROR(SUMIFS($D12:$W12,$D$1:$W$1,AD$3)/$C12,0) -> 771.07881 | AE12: =IFERROR(SUMIFS($D12:$W12,$D$1:$W$1,AE$3)/$C12,0) -> 8423.0392 | AF12: =IFERROR(SUMIFS($D12:$W12,$D$1:$W$1,AF$3)/$C12,0) -> 7506.9846 | AG12: =IFERROR(SUMIFS($D12:$W12,$D$1:$W$1,AG$3)/$C12,0) -> 4586.3209 | AH12: =IFERROR(SUMIFS($D12:$W12,$D$1:$W$1,AH$3)/$C12,0) -> 8562.0042 | AJ12: =SUMIFS('Working-T05-B2'!$S$8:$S$150,'Working-T05-B2'!$G$8:$G$150,$A12) -> 6920.9129 | AK12: =C12-AJ12 -> 14129.087 | AW12: =SUM(AX12:BF12) -> 47786.684 | AX12: =Z12*(1-AM12) -> 12602.902 | AY12: =AA12*(1-AN12) -> 237.77758 | AZ12: =AB12*(1-AO12) -> 263.17401 | BA12: =AC12*(1-AP12) -> 4833.4035 | BB12: =AD12*(1-AQ12) -> 771.07881 | BC12: =AE12*(1-AR12) -> 8423.0392 | BD12: =AF12*(1-AS12) -> 7506.9846 | BE12: =AG12*(1-AT12) -> 4586.3209 | BF12: =AH12*(1-AU12) -> 8562.0042 | BH12: TP đầu 11* đầu kỳ | BJ12: 8086827.5 | BK12: =BJ12+BK4-BK1 -> 6353425.7 | BL12: =BK12+BL4-BL1 -> 5382832
A13: 110000363 | B13: Hạt nhựa rHDPE rHDI3Gy01 | C13: 243146.9 | D13: 42836 | E13: 150717075 | F13: 0 | G13: 3380354118 | H13: 882945 | I13: 0 | J13: 7785028 | K13: 257136 | L13: 228127805 | M13: 62078320 | N13: 0 | O13: 0 | P13: 0 | Q13: 0 | R13: 131698430 | S13: 20331 | T13: 137159135 | U13: 157575479 | V13: 0 | W13: 278902554 | Y13: =SUM(Z13:AH13) -> 18653.749 | Z13: =IFERROR(SUMIFS($D13:$W13,$D$1:$W$1,Z$3)/$C13,0) -> 14522.554 | AA13: =IFERROR(SUMIFS($D13:$W13,$D$1:$W$1,AA$3)/$C13,0) -> 35.64912 | AB13: =IFERROR(SUMIFS($D13:$W13,$D$1:$W$1,AB$3)/$C13,0) -> 1.0575335 | AC13: =IFERROR(SUMIFS($D13:$W13,$D$1:$W$1,AC$3)/$C13,0) -> 938.23037 | AD13: =IFERROR(SUMIFS($D13:$W13,$D$1:$W$1,AD$3)/$C13,0) -> 255.31199 | AE13: =IFERROR(SUMIFS($D13:$W13,$D$1:$W$1,AE$3)/$C13,0) -> 541.72503 | AF13: =IFERROR(SUMIFS($D13:$W13,$D$1:$W$1,AF$3)/$C13,0) -> 564.09987 | AG13: =IFERROR(SUMIFS($D13:$W13,$D$1:$W$1,AG$3)/$C13,0) -> 648.06699 | AH13: =IFERROR(SUMIFS($D13:$W13,$D$1:$W$1,AH$3)/$C13,0) -> 1147.0537 | AJ13: =SUMIFS('Working-T05-B2'!$S$8:$S$150,'Working-T05-B2'!$G$8:$G$150,$A13) -> 1375 | AK13: =C13-AJ13 -> 241771.9 | AW13: =SUM(AX13:BF13) -> 18653.749 | AX13: =Z13*(1-AM13) -> 14522.554 | AY13: =AA13*(1-AN13) -> 35.64912 | AZ13: =AB13*(1-AO13) -> 1.0575335 | BA13: =AC13*(1-AP13) -> 938.23037 | BB13: =AD13*(1-AQ13) -> 255.31199 | BC13: =AE13*(1-AR13) -> 541.72503 | BD13: =AF13*(1-AS13) -> 564.09987 | BE13: =AG13*(1-AT13) -> 648.06699 | BF13: =AH13*(1-AU13) -> 1147.0537
A14: 110000364 | B14: Hạt nhựa rHDI3Y01 | C14: 12515 | D14: 0 | E14: -144215268 | F14: 0 | G14: 368130345 | H14: 18 | I14: 0 | J14: 562816 | K14: 201 | L14: 7113427 | M14: 2315183 | N14: 0 | O14: 0 | P14: 0 | Q14: 0 | R14: 8476336 | S14: 128 | T14: 9456468 | U14: 9087876 | V14: 0 | W14: 13692084 | Y14: =SUM(Z14:AH14) -> 21943.237 | Z14: =IFERROR(SUMIFS($D14:$W14,$D$1:$W$1,Z$3)/$C14,0) -> 17891.736 | AA14: =IFERROR(SUMIFS($D14:$W14,$D$1:$W$1,AA$3)/$C14,0) -> 44.972753 | AB14: =IFERROR(SUMIFS($D14:$W14,$D$1:$W$1,AB$3)/$C14,0) -> 0.016060727 | AC14: =IFERROR(SUMIFS($D14:$W14,$D$1:$W$1,AC$3)/$C14,0) -> 568.39209 | AD14: =IFERROR(SUMIFS($D14:$W14,$D$1:$W$1,AD$3)/$C14,0) -> 184.99265 | AE14: =IFERROR(SUMIFS($D14:$W14,$D$1:$W$1,AE$3)/$C14,0) -> 677.30435 | AF14: =IFERROR(SUMIFS($D14:$W14,$D$1:$W$1,AF$3)/$C14,0) -> 755.61071 | AG14: =IFERROR(SUMIFS($D14:$W14,$D$1:$W$1,AG$3)/$C14,0) -> 726.15869 | AH14: =IFERROR(SUMIFS($D14:$W14,$D$1:$W$1,AH$3)/$C14,0) -> 1094.0539 | AJ14: =SUMIFS('Working-T05-B2'!$S$8:$S$150,'Working-T05-B2'!$G$8:$G$150,$A14) -> 6349.2402 | AK14: =C14-AJ14 -> 6165.7598 | AW14: =SUM(AX14:BF14) -> 21943.237 | AX14: =Z14*(1-AM14) -> 17891.736 | AY14: =AA14*(1-AN14) -> 44.972753 | AZ14: =AB14*(1-AO14) -> 0.016060727 | BA14: =AC14*(1-AP14) -> 568.39209 | BB14: =AD14*(1-AQ14) -> 184.99265 | BC14: =AE14*(1-AR14) -> 677.30435 | BD14: =AF14*(1-AS14) -> 755.61071 | BE14: =AG14*(1-AT14) -> 726.15869 | BF14: =AH14*(1-AU14) -> 1094.0539 | BH14: CPSX tăng/giảm | BK14: =(BK4*ROUND(BK11,2)+BK12)/(BK12+BK4) -> 0.90267629 | BL14: =(BL4*ROUND(BL11,2)+BL12)/(BL12+BL4) -> 0.99116442
A15: 110000366 | B15: Hạt nhựa rHDI3G01 | C15: 52200 | D15: 859 | E15: 8313128 | F15: 0 | G15: 854383173 | H15: 95571754 | I15: 0 | J15: 1876821 | K15: 139042 | L15: 56579366 | M15: 14347576 | N15: 0 | O15: 0 | P15: 0 | Q15: 0 | R15: 70916791 | S15: 3671 | T15: 80377392 | U15: 35382699 | V15: 0 | W15: 85950610 | Y15: =SUM(Z15:AH15) -> 24977.833 | Z15: =IFERROR(SUMIFS($D15:$W15,$D$1:$W$1,Z$3)/$C15,0) -> 16526.766 | AA15: =IFERROR(SUMIFS($D15:$W15,$D$1:$W$1,AA$3)/$C15,0) -> 1866.8309 | AB15: =IFERROR(SUMIFS($D15:$W15,$D$1:$W$1,AB$3)/$C15,0) -> 2.6636398 | AC15: =IFERROR(SUMIFS($D15:$W15,$D$1:$W$1,AC$3)/$C15,0) -> 1083.8959 | AD15: =IFERROR(SUMIFS($D15:$W15,$D$1:$W$1,AD$3)/$C15,0) -> 274.85778 | AE15: =IFERROR(SUMIFS($D15:$W15,$D$1:$W$1,AE$3)/$C15,0) -> 1358.6295 | AF15: =IFERROR(SUMIFS($D15:$W15,$D$1:$W$1,AF$3)/$C15,0) -> 1539.7968 | AG15: =IFERROR(SUMIFS($D15:$W15,$D$1:$W$1,AG$3)/$C15,0) -> 677.82948 | AH15: =IFERROR(SUMIFS($D15:$W15,$D$1:$W$1,AH$3)/$C15,0) -> 1646.5634 | AJ15: =SUMIFS('Working-T05-B2'!$S$8:$S$150,'Working-T05-B2'!$G$8:$G$150,$A15) -> 1375 | AK15: =C15-AJ15 -> 50825 | AW15: =SUM(AX15:BF15) -> 24977.833 | AX15: =Z15*(1-AM15) -> 16526.766 | AY15: =AA15*(1-AN15) -> 1866.8309 | AZ15: =AB15*(1-AO15) -> 2.6636398 | BA15: =AC15*(1-AP15) -> 1083.8959 | BB15: =AD15*(1-AQ15) -> 274.85778 | BC15: =AE15*(1-AR15) -> 1358.6295 | BD15: =AF15*(1-AS15) -> 1539.7968 | BE15: =AG15*(1-AT15) -> 677.82948 | BF15: =AH15*(1-AU15) -> 1646.5634
A16: 110000373 | B16: Hạt nhựa rHDPE rHDI4DL01 | C16: 6235.4 | D16: 57804 | E16: 50975816 | F16: 0 | G16: 53912387 | H16: 7876378 | I16: 0 | J16: 405137 | K16: 647431 | L16: 6678437 | M16: 1220338 | N16: 0 | O16: 0 | P16: 0 | Q16: 0 | R16: 5570847 | S16: 1047 | T16: 6277373 | U16: 6181252 | V16: 0 | W16: 7179988 | Y16: =SUM(Z16:AH16) -> 23572.543 | Z16: =IFERROR(SUMIFS($D16:$W16,$D$1:$W$1,Z$3)/$C16,0) -> 16830.678 | AA16: =IFERROR(SUMIFS($D16:$W16,$D$1:$W$1,AA$3)/$C16,0) -> 1328.1449 | AB16: =IFERROR(SUMIFS($D16:$W16,$D$1:$W$1,AB$3)/$C16,0) -> 103.83151 | AC16: =IFERROR(SUMIFS($D16:$W16,$D$1:$W$1,AC$3)/$C16,0) -> 1071.0519 | AD16: =IFERROR(SUMIFS($D16:$W16,$D$1:$W$1,AD$3)/$C16,0) -> 195.71126 | AE16: =IFERROR(SUMIFS($D16:$W16,$D$1:$W$1,AE$3)/$C16,0) -> 893.59047 | AF16: =IFERROR(SUMIFS($D16:$W16,$D$1:$W$1,AF$3)/$C16,0) -> 1006.7314 | AG16: =IFERROR(SUMIFS($D16:$W16,$D$1:$W$1,AG$3)/$C16,0) -> 991.31603 | AH16: =IFERROR(SUMIFS($D16:$W16,$D$1:$W$1,AH$3)/$C16,0) -> 1151.488 | AJ16: =SUMIFS('Working-T05-B2'!$S$8:$S$150,'Working-T05-B2'!$G$8:$G$150,$A16) -> 23375 | AK16: =C16-AJ16 -> -17139.6 | AW16: =SUM(AX16:BF16) -> 23572.543 | AX16: =Z16*(1-AM16) -> 16830.678 | AY16: =AA16*(1-AN16) -> 1328.1449 | AZ16: =AB16*(1-AO16) -> 103.83151 | BA16: =AC16*(1-AP16) -> 1071.0519 | BB16: =AD16*(1-AQ16) -> 195.71126 | BC16: =AE16*(1-AR16) -> 893.59047 | BD16: =AF16*(1-AS16) -> 1006.7314 | BE16: =AG16*(1-AT16) -> 991.31603 | BF16: =AH16*(1-AU16) -> 1151.488
A17: 110000374 | B17: Hạt Nhựa rHDB03N02 | C17: 297112.4 | D17: 20886564 | E17: 901107113 | F17: 0 | G17: 5110263112 | H17: 31880264 | I17: 0 | J17: 20680404 | K17: 38977166 | L17: 727059815 | M17: 54073364 | N17: 0 | O17: 0 | P17: 0 | Q17: 0 | R17: 257129259 | S17: 36245 | T17: 325968751 | U17: 232202405 | V17: 0 | W17: 568687115 | Y17: =SUM(Z17:AH17) -> 27898.37 | Z17: =IFERROR(SUMIFS($D17:$W17,$D$1:$W$1,Z$3)/$C17,0) -> 20302.945 | AA17: =IFERROR(SUMIFS($D17:$W17,$D$1:$W$1,AA$3)/$C17,0) -> 176.905 | AB17: =IFERROR(SUMIFS($D17:$W17,$D$1:$W$1,AB$3)/$C17,0) -> 131.1866 | AC17: =IFERROR(SUMIFS($D17:$W17,$D$1:$W$1,AC$3)/$C17,0) -> 2447.0867 | AD17: =IFERROR(SUMIFS($D17:$W17,$D$1:$W$1,AD$3)/$C17,0) -> 181.99632 | AE17: =IFERROR(SUMIFS($D17:$W17,$D$1:$W$1,AE$3)/$C17,0) -> 865.54955 | AF17: =IFERROR(SUMIFS($D17:$W17,$D$1:$W$1,AF$3)/$C17,0) -> 1097.1227 | AG17: =IFERROR(SUMIFS($D17:$W17,$D$1:$W$1,AG$3)/$C17,0) -> 781.53051 | AH17: =IFERROR(SUMIFS($D17:$W17,$D$1:$W$1,AH$3)/$C17,0) -> 1914.0471 | AJ17: =SUMIFS('Working-T05-B2'!$S$8:$S$150,'Working-T05-B2'!$G$8:$G$150,$A17) -> 68750 | AK17: =C17-AJ17 -> 228362.4 | AW17: =SUM(AX17:BF17) -> 27898.37 | AX17: =Z17*(1-AM17) -> 20302.945 | AY17: =AA17*(1-AN17) -> 176.905 | AZ17: =AB17*(1-AO17) -> 131.1866 | BA17: =AC17*(1-AP17) -> 2447.0867 | BB17: =AD17*(1-AQ17) -> 181.99632 | BC17: =AE17*(1-AR17) -> 865.54955 | BD17: =AF17*(1-AS17) -> 1097.1227 | BE17: =AG17*(1-AT17) -> 781.53051 | BF17: =AH17*(1-AU17) -> 1914.0471
