Workbook
Name \A: #REF!
Name \M: #REF!
Name _: #N/A
Name _____CON1: #REF!
Name _____CON2: #REF!
Name _____lai04: #REF!
Name _____NET2: #REF!
Name ____CON1: #REF!
Name ____CON2: #REF!
Name ____lai04: #REF!
Name ____NET2: #REF!
Name ____TAX3: #REF!
Name ____TAX5: #REF!
Name ____TAX8: #REF!
Name ___ATS98: #REF!
Name ___BGT02: [1]Budget!$A$1:$IV$65536
Name ___CON1: #REF!
Name ___CON2: #REF!
Name ___CHF98: #REF!
Name ___CHX2002: [2]Zellennamen!#REF!
Name ___CHX2003: [2]Zellennamen!#REF!
Name ___CHX2004: [2]Zellennamen!#REF!
Name ___CHX2005: [2]Zellennamen!#REF!
Name ___DTB2003: #REF!
Name ___DTB2004: #REF!
Name ___lai04: #REF!
Name ___LY01: '[3]Last Year'!$A$1:$IV$65536
Name ___Mkt1: '[4]Rolling F''Cast P&L'!$GQ$26:$GQ$42
Name ___NET2: #REF!
Name ___TAX3: #REF!
Name ___TAX5: #REF!
Name ___TAX8: #REF!
Name ___VAR1: #REF!
Name ___VAR2: #REF!
Name ___var22: '[5](Setup)'!$C$17
Name ___VAR3: #REF!
Name ___VAR4: #REF!
Name ___VAR5: #REF!
Name ___VAR6: #REF!
Name ___VAR7: #REF!
Name __ATS98: #REF!
Name __BGT02: [1]Budget!$A$1:$IV$65536
Name __CON1: #REF!
Name __CON2: #REF!
Name __CHF98: #REF!
Name __CHX2002: [2]Zellennamen!#REF!
Name __CHX2003: [2]Zellennamen!#REF!
Name __CHX2004: [2]Zellennamen!#REF!
Name __CHX2005: [2]Zellennamen!#REF!
Name __DAT1: #REF!
Name __DAT10: #REF!
Name __DAT11: #REF!
Name __DAT12: #REF!
Name __DAT13: #REF!
Name __DAT14: #REF!
Name __DAT15: #REF!
Name __DAT16: #REF!
Name __DAT17: #REF!
Name __DAT18: #REF!
Name __DAT19: #REF!

Sheet Chart mục tiêu
Q126: : Ước thực hiện cả năm
Q127: : Mục tiêu | S127: : thực hiện | U127: : Ước thực hiện cả năm

Sheet Data Chart
B3: 2 | T3: Không tính Lãi cho vay & Khấu hao, thuế TNDN
B4: Tháng | C4: Doanh thu | D4: Doanh thu bù các tháng trước | E4: Tổng Doanh thu + bù | F4: Sản lượng bán | G4: Sản lượng dự báo FC | H4: Sản lượng bù thêm các tháng trước thiếu | I4: Tổng sản lượng bán + bù | J4: Doanh thu | K4: Doanh thu | L4: Sản lượng bán | M4: Ước sản lượng bán thực hiện | N4: Lợi Nhuận Ròng (tỷ đồng) | P4: Lợi nhuận ròng (tỷ đồng) | R4: % Lợi nhuận/Doanh thu | T4: Ước tính lợi Nhuận ròng thực hiện (tỷ đồng) | V4: Ước % Lợi nhuận /Doanh thu | X4: EBITDA mục tiêu 2026 (tỷ đồng) | Z4: EBITDA thực hiện (tỷ) | AB4: % EBITDA thực hiện | AE4: Lũy kế EBITDA (tỷ đ) | AG4: Lũy kế EBITDA (tỷ) | AI4: LK Lợi nhuận ròng (tỷ) | AK4: LK Lợi nhuận ròng (tỷ)
C5: Mục tiêu | F5: kế hoạch | J5: Thực Hiện | K5: dự báo FC | L5: thực hiện | N5: Mục tiêu | P5: Thực hiện | R5: Thực hiện | AE5: Mục tiêu | AG5: Thực hiện | AI5: Mục tiêu | AK5: Thực hiện
C6: (Triệu đồng) | F6: Tấn | G6: Tấn | J6: (Tỷ đồng) | K6: (Tỷ đồng) | L6: (Tấn) | M6: (Tấn) | N6: Mục tiêu | O6: Mục tiêu sau loại trừ | P6: Thực hiện | Q6: Thực hiện sau loại trừ | R6: Thực hiện | S6: Sau loại trừ | T6: Thực hiện | U6: Sau loại trừ | V6: Thực hiện | W6: Sau loại trừ | X6: Mục tiêu | Y6: Sau loại trừ | Z6: Thực hiện | AA6: Sau loại trừ | AB6: Thực hiện | AC6: Sau loại trừ | AE6: Mục tiêu | AF6: Sau loại trừ | AG6: Thực hiện | AH6: Sau loại trừ | AI6: Mục tiêu | AJ6: Sau loại trừ | AK6: Thực hiện | AL6: Sau loại trừ
B7: T1.21 | J7: 2192.9406 | L7: 76.025 | P7: -145.31993 | R7: =P7/$J7 -> -0.066267152 | T7: -145.31993 | V7: =T7/$J7 -> -0.066267152 | Z7: 135.20192 | AC7: =Z7/$J7 -> 0.061653254 | AG7: =Z7 -> 135.20192
B8: T2.21 | J8: 1791.822 | L8: 61 | P8: -261.86612 | R8: =P8/$J8 -> -0.14614516 | T8: -261.86612 | V8: =T8/$J8 -> -0.14614516 | Z8: -214.83113 | AC8: =Z8/$J8 -> -0.11989535 | AG8: =AG7+Z8 -> -79.629209
B9: T3.21 | J9: 8682.0846 | L9: 303.8 | P9: 1493.5068 | R9: =P9/$J9 -> 0.17202169 | T9: 1493.5068 | V9: =T9/$J9 -> 0.17202169 | Z9: 1434.3937 | AC9: =Z9/$J9 -> 0.16521306 | AG9: =AG8+Z9 -> 1354.7645
B10: T4.21 | J10: 6264.3327 | L10: 215.35 | P10: 1012.555 | R10: =P10/$J10 -> 0.16163812 | T10: 1012.555 | V10: =T10/$J10 -> 0.16163812 | Z10: 912.27287 | AC10: =Z10/$J10 -> 0.1456297 | AG10: =AG9+Z10 -> 2267.0374
B11: T5.21 | J11: 1376.9734 | L11: 35.93 | P11: -227.06432 | R11: =P11/$J11 -> -0.16490102 | T11: -227.06432 | V11: =T11/$J11 -> -0.16490102 | Z11: -276.60379 | AC11: =Z11/$J11 -> -0.20087809 | AG11: =AG10+Z11 -> 1990.4336
B12: T6.21 | J12: 904.63137 | L12: 30.437 | P12: 283.60144 | R12: =P12/$J12 -> 0.31349945 | T12: 283.60144 | V12: =T12/$J12 -> 0.31349945 | Z12: -301.79639 | AC12: =Z12/$J12 -> -0.33361256 | AG12: =AG11+Z12 -> 1688.6372
B13: T7.21 | J13: 3085.5828 | L13: 87.5 | P13: 9709.9566 | R13: =P13/$J13 -> 3.1468793 | T13: 9709.9566 | V13: =T13/$J13 -> 3.1468793 | Z13: 175.36958 | AC13: =Z13/$J13 -> 0.056835157 | AG13: =AG12+Z13 -> 1864.0068
B14: T8.21 | J14: 2036.7564 | L14: 69.2 | P14: 853.9722 | R14: =P14/$J14 -> 0.41928048 | T14: 853.9722 | V14: =T14/$J14 -> 0.41928048 | Z14: -971.96542 | AC14: =Z14/$J14 -> -0.4772124 | AG14: =AG13+Z14 -> 892.04139
B15: T9.21 | J15: 4007.8346 | L15: 115.5 | P15: 1703.2444 | R15: =P15/$J15 -> 0.42497872 | T15: 1703.2444 | V15: =T15/$J15 -> 0.42497872 | Z15: 674.41148 | AC15: =Z15/$J15 -> 0.16827328 | AG15: =AG14+Z15 -> 1566.4529
B16: T10.21 | J16: 8372.3086 | L16: 262.5 | P16: 695.11938 | R16: =P16/$J16 -> 0.08302601 | T16: 695.11938 | V16: =T16/$J16 -> 0.08302601 | Z16: 1608.2381 | AC16: =Z16/$J16 -> 0.19209016 | AG16: =AG15+Z16 -> 3174.691
B17: T11.21 | J17: 8615.0336 | L17: 284.8 | P17: -10.75835 | R17: =P17/$J17 -> -0.0012487879 | T17: -10.75835 | V17: =T17/$J17 -> -0.0012487879 | Z17: 1137.527 | AC17: =Z17/$J17 -> 0.13203977 | AG17: =AG16+Z17 -> 4312.218
B18: T12.21 | J18: 13231.975 | L18: 589.92 | P18: 2797.121 | R18: =P18/$J18 -> 0.21139104 | T18: 2797.121 | V18: =T18/$J18 -> 0.21139104 | Z18: 1516.1379 | AC18: =Z18/$J18 -> 0.11458137 | AG18: =AG17+Z18 -> 5828.3559
B19: Tổng 2021 | C19: =SUM(C7:C18) -> 0 | J19: =SUM(J7:J18) -> 60562.276 | L19: =SUM(L7:L18) -> 2131.962 | P19: =SUM(P7:P18) -> 17904.068 | R19: =P19/$J19 -> 0.2956307 | T19: =SUM(T7:T18) -> 17904.068 | V19: =T19/$J19 -> 0.2956307 | X19: =SUM(X7:X18) -> 0 | Z19: =SUM(Z7:Z18) -> 5828.3559 | AC19: =Z19/$J19 -> 0.096237398 | AE19: =SUM(AE7:AE18) -> 0 | AG19: =AG18 -> 5828.3559 | AI19: =SUM(AI7:AI18) -> 0 | AK19: =AK18 -> 0
B20: Năm 2025
B21: 1 | C21: 127.18788 | F21: 4318.2229 | G21: 4318.2229 | J21: =IF($C56=0,#N/A,$C56) -> 126.09904 | L21: =IF($D56=0,#N/A,$D56) -> 4241.842 | N21: -1.6227981 | O21: -1.6227981 | P21: =IF($E56=0,#N/A,$E56) -> -1.6934607 | Q21: =IF($F56=0,#N/A,$F56) -> -1.6934607 | R21: =IFERROR(P21/($J21),#N/A) -> -0.013429609 | S21: =IFERROR(Q21/($J21),#N/A) -> -0.013429609 | T21: =P21 -> -1.6934607 | U21: =Q21 -> -1.6934607 | V21: =T21/$J21 -> -0.013429609 | W21: =U21/$J21 -> -0.013429609 | X21: 5.5859163 | Y21: 5.5859163 | Z21: =IF($G56=0,#N/A,$G56) -> 1.574238 | AA21: =IF($H56=0,#N/A,$H56) -> 1.574238 | AB21: =Z21/J21 -> 0.01248414 | AC21: =AA21/J21 -> 0.01248414 | AE21: =X21 -> 5.5859163 | AF21: =Y21 -> 5.5859163 | AG21: =Z21 -> 1.574238 | AH21: =AA21 -> 1.574238 | AI21: =N21 -> -1.6227981 | AJ21: =O21 -> -1.6227981 | AK21: =P21 -> -1.6934607 | AL21: =Q21 -> -1.6934607
B22: 2 | C22: 125.41159 | F22: 4253.3146 | G22: 4253.3146 | J22: =IF($C57=0,#N/A,$C57) -> 96.566805 | L22: =IF($D57=0,#N/A,$D57) -> 3245.53 | N22: 0.58682152 | O22: 0.58682152 | P22: =IF($E57=0,#N/A,$E57) -> -6.4192137 | Q22: =IF($F57=0,#N/A,$F57) -> -6.4192137 | R22: =IFERROR(P22/($J22),#N/A) -> -0.066474331 | S22: =IFERROR(Q22/($J22),#N/A) -> -0.066474331 | T22: =P22 -> -6.4192137 | U22: =Q22 -> -6.4192137 | V22: =T22/$J22 -> -0.066474331 | W22: =U22/$J22 -> -0.066474331 | X22: 8.9848388 | Y22: 8.9848388 | Z22: =IF($G57=0,#N/A,$G57) -> -3.2434715 | AA22: =IF($H57=0,#N/A,$H57) -> -3.2434715 | AB22: =Z22/J22 -> -0.033587851 | AC22: =AA22/J22 -> -0.033587851 | AE22: =AE21+X22 -> 14.570755 | AF22: =AF21+Y22 -> 14.570755 | AG22: =AG21+Z22 -> -1.6692335 | AH22: =AH21+AA22 -> -1.6692335 | AI22: =AI21+N22 -> -1.0359766 | AJ22: =AJ21+O22 -> -1.0359766 | AK22: =AK21+P22 -> -8.1126745 | AL22: =AL21+Q22 -> -8.1126745
B23: 3 | C23: 138.51989 | F23: 4678.5574 | G23: 4678.5574 | J23: =IF($C58=0,#N/A,$C58) -> 173.30582 | L23: =IF($D58=0,#N/A,$D58) -> 6165.199 | N23: 2.7456563 | O23: 2.7456563 | P23: =IF($E58=0,#N/A,$E58) -> -6.6654066 | Q23: =IF($F58=0,#N/A,$F58) -> -6.6654066 | R23: =IFERROR(P23/($J23),#N/A) -> -0.038460373 | S23: =IFERROR(Q23/($J23),#N/A) -> -0.038460373 | T23: =P23 -> -6.6654066 | U23: =Q23 -> -6.6654066 | V23: =T23/$J23 -> -0.038460373 | W23: =U23/$J23 -> -0.038460373 | X23: 11.407938 | Y23: 11.407938 | Z23: =IF($G58=0,#N/A,$G58) -> -4.054122 | AA23: =IF($H58=0,#N/A,$H58) -> -4.054122 | AB23: =Z23/J23 -> -0.023392878 | AC23: =AA23/J23 -> -0.023392878 | AE23: =AE22+X23 -> 25.978693 | AF23: =AF22+Y23 -> 25.978693 | AG23: =AG22+Z23 -> -5.7233555 | AH23: =AH22+AA23 -> -5.7233555 | AI23: =AI22+N23 -> 1.7096797 | AJ23: =AJ22+O23 -> 1.7096797 | AK23: =AK22+P23 -> -14.778081 | AL23: =AL22+Q23 -> -14.778081
B24: 4 | C24: 129.53382 | F24: 4394.2315 | G24: 4394.2315 | J24: =IF($C59=0,#N/A,$C59) -> 159.05685 | L24: =IF($D59=0,#N/A,$D59) -> 5559.431 | N24: -0.93658019 | O24: -0.93658019 | P24: =IF($E59=0,#N/A,$E59) -> 3.7037542 | Q24: =IF($F59=0,#N/A,$F59) -> 3.7037542 | R24: =IFERROR(P24/($J24),#N/A) -> 0.023285725 | S24: =IFERROR(Q24/($J24),#N/A) -> 0.023285725 | T24: =P24 -> 3.7037542 | U24: =Q24 -> 3.7037542 | V24: =T24/$J24 -> 0.023285725 | W24: =U24/$J24 -> 0.023285725 | X24: 7.4521583 | Y24: 7.4521583 | Z24: =IF($G59=0,#N/A,$G59) -> 6.7707201 | AA24: =IF($H59=0,#N/A,$H59) -> 6.7707201 | AB24: =Z24/J24 -> 0.042567924 | AC24: =AA24/J24 -> 0.042567924 | AE24: =AE23+X24 -> 33.430851 | AF24: =AF23+Y24 -> 33.430851 | AG24: =AG23+Z24 -> 1.0473646 | AH24: =AH23+AA24 -> 1.0473646 | AI24: =AI23+N24 -> 0.77309953 | AJ24: =AJ23+O24 -> 0.77309953 | AK24: =AK23+P24 -> -11.074327 | AL24: =AL23+Q24 -> -11.074327
B25: 5 | C25: 137.58723 | F25: 4663.4364 | G25: 4663.4364 | J25: =IF($C60=0,#N/A,$C60) -> 159.76531 | L25: =IF($D60=0,#N/A,$D60) -> 5019.773 | N25: 1.1280967 | O25: 1.1280967 | P25: =IF($E60=0,#N/A,$E60) -> 8.2274254 | Q25: =IF($F60=0,#N/A,$F60) -> 8.2274254 | R25: =IFERROR(P25/($J25),#N/A) -> 0.051496946 | S25: =IFERROR(Q25/($J25),#N/A) -> 0.051496946 | T25: =P25 -> 8.2274254 | U25: =Q25 -> 8.2274254 | V25: =T25/$J25 -> 0.051496946 | W25: =U25/$J25 -> 0.051496946 | X25: 9.769049 | Y25: 9.769049 | Z25: =IF($G60=0,#N/A,$G60) -> 11.229251 | AA25: =IF($H60=0,#N/A,$H60) -> 11.229251 | AB25: =Z25/J25 -> 0.070285914 | AC25: =AA25/J25 -> 0.070285914 | AE25: =AE24+X25 -> 43.1999 | AF25: =AF24+Y25 -> 43.1999 | AG25: =AG24+Z25 -> 12.276615 | AH25: =AH24+AA25 -> 12.276615 | AI25: =AI24+N25 -> 1.9011963 | AJ25: =AJ24+O25 -> 1.9011963 | AK25: =AK24+P25 -> -2.8469015 | AL25: =AL24+Q25 -> -2.8469015
B26: 6 | C26: 138.25385 | F26: 4691.9522 | G26: 4691.9522 | J26: =IF($C61=0,#N/A,$C61) -> #N/A | L26: =IF($D61=0,#N/A,$D61) -> #N/A | N26: 0.35162666 | O26: 0.35162666 | P26: =IF($E61=0,#N/A,$E61) -> #N/A | Q26: =IF($F61=0,#N/A,$F61) -> #N/A | R26: =IFERROR(P26/($J26),#N/A) -> #N/A | S26: =IFERROR(Q26/($J26),#N/A) -> #N/A | T26: =P26 -> #N/A | U26: =Q26 -> #N/A | V26: =T26/$J26 -> #N/A | W26: =U26/$J26 -> #N/A | X26: 9.1798751 | Y26: 9.1798751 | Z26: =IF($G61=0,#N/A,$G61) -> #N/A | AA26: =IF($H61=0,#N/A,$H61) -> #N/A | AB26: =Z26/J26 -> #N/A | AC26: =AA26/J26 -> #N/A | AE26: =AE25+X26 -> 52.379775 | AF26: =AF25+Y26 -> 52.379775 | AG26: =AG25+Z26 -> #N/A | AH26: =AH25+AA26 -> #N/A | AI26: =AI25+N26 -> 2.2528229 | AJ26: =AJ25+O26 -> 2.2528229 | AK26: =AK25+P26 -> #N/A | AL26: =AL25+Q26 -> #N/A
B27: 7 | C27: 137.70857 | F27: 4689.4225 | G27: 4689.4225 | J27: =IF($C62=0,#N/A,$C62) -> #N/A | L27: =IF($D62=0,#N/A,$D62) -> #N/A | N27: 5.6882325 | O27: 5.6882325 | P27: =IF($E62=0,#N/A,$E62) -> #N/A | Q27: =IF($F62=0,#N/A,$F62) -> #N/A | R27: =IFERROR(P27/($J27),#N/A) -> #N/A | S27: =IFERROR(Q27/($J27),#N/A) -> #N/A | T27: =P27 -> #N/A | U27: =Q27 -> #N/A | V27: =T27/$J27 -> #N/A | W27: =U27/$J27 -> #N/A | X27: 14.514474 | Y27: 14.514474 | Z27: =IF($G62=0,#N/A,$G62) -> #N/A | AA27: =IF($H62=0,#N/A,$H62) -> #N/A | AB27: =Z27/J27 -> #N/A | AC27: =AA27/J27 -> #N/A | AE27: =AE26+X27 -> 66.894249 | AF27: =AF26+Y27 -> 66.894249 | AG27: =AG26+Z27 -> #N/A | AH27: =AH26+AA27 -> #N/A | AI27: =AI26+N27 -> 7.9410554 | AJ27: =AJ26+O27 -> 7.9410554 | AK27: =AK26+P27 -> #N/A | AL27: =AL26+Q27 -> #N/A
B28: 8 | C28: 133.74125 | F28: 4562.8495 | G28: 4562.8495 | I28: =H28+M28 -> 0 | J28: =IF($C63=0,#N/A,$C63) -> #N/A | L28: =IF($D63=0,#N/A,$D63) -> #N/A | N28: 3.7106447 | O28: 3.7106447 | P28: =IF($E63=0,#N/A,$E63) -> #N/A | Q28: =IF($F63=0,#N/A,$F63) -> #N/A | R28: =IFERROR(P28/($J28),#N/A) -> #N/A | S28: =IFERROR(Q28/($J28),#N/A) -> #N/A | T28: =P28 -> #N/A | U28: =Q28 -> #N/A | V28: =T28/$J28 -> #N/A | W28: =U28/$J28 -> #N/A | X28: 12.693546 | Y28: 12.693546 | Z28: =IF($G63=0,#N/A,$G63) -> #N/A | AA28: =IF($H63=0,#N/A,$H63) -> #N/A | AB28: =Z28/J28 -> #N/A | AC28: =AA28/J28 -> #N/A | AE28: =AE27+X28 -> 79.587795 | AF28: =AF27+Y28 -> 79.587795 | AG28: =AG27+Z28 -> #N/A | AH28: =AH27+AA28 -> #N/A | AI28: =AI27+N28 -> 11.6517 | AJ28: =AJ27+O28 -> 11.6517 | AK28: =AK27+P28 -> #N/A | AL28: =AL27+Q28 -> #N/A
B29: 9 | C29: 139.83157 | F29: 4774.6231 | G29: 4774.6231 | I29: =H29+M29 -> 0 | J29: =IF($C64=0,#N/A,$C64) -> #N/A | L29: =IF($D64=0,#N/A,$D64) -> #N/A | N29: 4.58904 | O29: 4.58904 | P29: =IF($E64=0,#N/A,$E64) -> #N/A | Q29: =IF($F64=0,#N/A,$F64) -> #N/A | R29: =IFERROR(P29/($J29),#N/A) -> #N/A | S29: =IFERROR(Q29/($J29),#N/A) -> #N/A | T29: =P29 -> #N/A | U29: =Q29 -> #N/A | V29: =T29/$J29 -> #N/A | W29: =U29/$J29 -> #N/A | X29: 13.428733 | Y29: 13.428733 | Z29: =IF($G64=0,#N/A,$G64) -> #N/A | AA29: =IF($H64=0,#N/A,$H64) -> #N/A | AB29: =Z29/J29 -> #N/A | AC29: =AA29/J29 -> #N/A | AE29: =AE28+X29 -> 93.016529 | AF29: =AF28+Y29 -> 93.016529 | AG29: =AG28+Z29 -> #N/A | AH29: =AH28+AA29 -> #N/A | AI29: =AI28+N29 -> 16.24074 | AJ29: =AJ28+O29 -> 16.24074 | AK29: =AK28+P29 -> #N/A | AL29: =AL28+Q29 -> #N/A
B30: 10 | C30: 130.38258 | F30: 4468.6263 | G30: 4468.6263 | I30: =H30+M30 -> 0 | J30: =IF($C65=0,#N/A,$C65) -> #N/A | L30: =IF($D65=0,#N/A,$D65) -> #N/A | N30: 2.8661667 | O30: 2.8661667 | P30: =IF($E65=0,#N/A,$E65) -> #N/A | Q30: =IF($F65=0,#N/A,$F65) -> #N/A | R30: =IFERROR(P30/($J30),#N/A) -> #N/A | S30: =IFERROR(Q30/($J30),#N/A) -> #N/A | T30: =P30 -> #N/A | U30: =Q30 -> #N/A | V30: =T30/$J30 -> #N/A | W30: =U30/$J30 -> #N/A | X30: 11.690488 | Y30: 11.690488 | Z30: =IF($G65=0,#N/A,$G65) -> #N/A | AA30: =IF($H65=0,#N/A,$H65) -> #N/A | AB30: =Z30/J30 -> #N/A | AC30: =AA30/J30 -> #N/A | AE30: =AE29+X30 -> 104.70702 | AF30: =AF29+Y30 -> 104.70702 | AG30: =AG29+Z30 -> #N/A | AH30: =AH29+AA30 -> #N/A | AI30: =AI29+N30 -> 19.106907 | AJ30: =AJ29+O30 -> 19.106907 | AK30: =AK29+P30 -> #N/A | AL30: =AL29+Q30 -> #N/A
B31: 11 | C31: 138.06137 | F31: 4720.2431 | G31: 4720.2431 | I31: =H31+M31 -> 0 | J31: =IF($C66=0,#N/A,$C66) -> #N/A | L31: =IF($D66=0,#N/A,$D66) -> #N/A | N31: 5.7344809 | O31: 5.7344809 | P31: =IF($E66=0,#N/A,$E66) -> #N/A | Q31: =IF($F66=0,#N/A,$F66) -> #N/A | R31: =IFERROR(P31/($J31),#N/A) -> #N/A | S31: =IFERROR(Q31/($J31),#N/A) -> #N/A | T31: =P31 -> #N/A | U31: =Q31 -> #N/A | V31: =T31/$J31 -> #N/A | W31: =U31/$J31 -> #N/A | X31: 14.535438 | Y31: 14.535438 | Z31: =IF($G66=0,#N/A,$G66) -> #N/A | AA31: =IF($H66=0,#N/A,$H66) -> #N/A | AB31: =Z31/J31 -> #N/A | AC31: =AA31/J31 -> #N/A | AE31: =AE30+X31 -> 119.24245 | AF31: =AF30+Y31 -> 119.24245 | AG31: =AG30+Z31 -> #N/A | AH31: =AH30+AA31 -> #N/A | AI31: =AI30+N31 -> 24.841388 | AJ31: =AJ30+O31 -> 24.841388 | AK31: =AK30+P31 -> #N/A | AL31: =AL30+Q31 -> #N/A
B32: 12 | C32: 139.43048 | F32: 4784.5204 | G32: 4784.5204 | I32: =H32+M32 -> 0 | J32: =IF($C67=0,#N/A,$C67) -> #N/A | L32: =IF($D67=0,#N/A,$D67) -> #N/A | N32: 2.9676891 | O32: 2.9676891 | P32: =IF($E67=0,#N/A,$E67) -> #N/A | Q32: =IF($F67=0,#N/A,$F67) -> #N/A | R32: =IFERROR(P32/($J32),#N/A) -> #N/A | S32: =IFERROR(Q32/($J32),#N/A) -> #N/A | T32: =P32 -> #N/A | U32: =Q32 -> #N/A | V32: =T32/$J32 -> #N/A | W32: =U32/$J32 -> #N/A | X32: 11.562532 | Y32: 11.562532 | Z32: =IF($G67=0,#N/A,$G67) -> #N/A | AA32: =IF($H67=0,#N/A,$H67) -> #N/A | AB32: =Z32/J32 -> #N/A | AC32: =AA32/J32 -> #N/A | AE32: =AE31+X32 -> 130.80499 | AF32: =AF31+Y32 -> 130.80499 | AG32: =AG31+Z32 -> #N/A | AH32: =AH31+AA32 -> #N/A | AI32: =AI31+N32 -> 27.809077 | AJ32: =AJ31+O32 -> 27.809077 | AK32: =AK31+P32 -> #N/A | AL32: =AL31+Q32 -> #N/A
B33: Lũy kế 2025 | C33: =SUM(C21:C32) -> 1615.6501 | D33: =SUM(D25:D32) -> 0 | E33: =SUM(E25:E32) -> 0 | F33: =SUM(F21:F32) -> 55000 | G33: =SUM(G21:G32) -> 55000 | H33: =SUM(H21:H32) -> 0 | I33: =SUM(I21:I32) -> 0 | J33: =SUMIFS(J$21:J$32,J$21:J$32,"<>"&"#n/a") -> 714.79383 | K33: =SUMIFS(K$21:K$32,K$21:K$32,"<>"&"#n/a") -> 0 | L33: =SUMIFS(L$21:L$32,L$21:L$32,"<>"&"#n/a") -> 24231.775 | M33: =SUM(M21:M32) -> 0 | N33: =SUM(N21:N32) -> 27.809077 | O33: =SUM(O21:O32) -> 27.809077 | P33: =SUMIFS(P$21:P$32,P$21:P$32,"<>"&"#n/a") -> -2.8469015 | Q33: =SUMIFS(Q$21:Q$32,Q$21:Q$32,"<>"&"#n/a") -> -2.8469015 | R33: =IFERROR(P33/($J33),#N/A) -> -0.0039828288 | S33: =IFERROR(Q33/($J33),#N/A) -> -0.0039828288 | T33: =SUM(T21:T32) -> #N/A | U33: =SUM(U21:U32) -> #N/A | V33: =SUM(V21:V32) -> #N/A | W33: =SUM(W21:W32) -> #N/A | X33: =SUM(X21:X32) -> 130.80499 | Y33: =SUM(Y21:Y32) -> 130.80499 | Z33: =SUM(Z21:Z32) -> #N/A | AA33: =SUM(AA21:AA32) -> #N/A | ... AC33: =SUM(AC21:AC32) -> #N/A | AE33: =AE32 -> 130.80499 | AF33: =AF32 -> 130.80499 | AG33: =AG32 -> #N/A | AI33: =AI32 -> 27.809077 | AJ33: =AJ32 -> 27.809077 | AK33: =AK32 -> #N/A | AL33: =AL32 -> #N/A
B34: FC 12T | C34: 1 | D34: =C33-J33-K33 -> 900.85625 | J34: =J33/C33 -> 0.44241871 | K34: =K33/C33 -> 0 | L34: =G33 -> 55000 | M34: =F33-L33-M33 -> 30768.225 | N34: 1 | O34: 1 | P34: =P33/N33 -> -0.1023731 | Q34: =Q33/O33 -> -0.1023731 | T34: =V33 -> #N/A | X34: =X33/($C$33*10^3) -> 8.096121e-05 | Z34: =Z33/(J33*10^3) -> #N/A
B35: Mục Tiêu 2024 | F35: =F33/$F$33 -> 1 | J35: =L33/$F$33 -> 0.44057773 | K35: =M33/$F$33 -> 0 | L35: =F33 -> 55000 | M35: =M34+M33+L33 -> 55000
C36: =N33/C33 -> 0.017212314 | X36: =X33/C33 -> 0.08096121
B37: TRƯỚC LOẠI TRỪ | N37: =N33/C32 -> 0.19944762
B38: Tháng | C38: T1.26 | D38: 2 | E38: 3 | F38: 4 | G38: 5 | H38: 6 | I38: 7 | J38: 8 | K38: 9 | L38: 10 | M38: 11 | N38: 12
B39: Doanh Thu | C39: =BCTC2026!D184/10^9 -> 126.09904 | D39: =BCTC2026!E184/10^9 -> 96.566805 | E39: =BCTC2026!F184/10^9 -> 173.30582 | F39: =BCTC2026!G184/10^9 -> 159.05685 | G39: =BCTC2026!H184/10^9 -> 159.76531 | H39: =BCTC2026!I184/10^9 -> 0 | I39: =BCTC2026!J184/10^9 -> 0 | J39: =BCTC2026!K184/10^9 -> 0 | ... N39: =BCTC2026!O184/10^9 -> 0
B40: Chi Phí | C40: =(BCTC2026!D160+BCTC2026!D162+BCTC2026!D163-BCTC2026!D165+BCTC2026!D166-BCTC2026!D169+BCTC2026!D170)/10^9 -> 127.7925 | D40: =(BCTC2026!E160+BCTC2026!E162+BCTC2026!E163-BCTC2026!E165+BCTC2026!E166-BCTC2026!E169+BCTC2026!E170)/10^9 -> 102.98602 | E40: =(BCTC2026!F160+BCTC2026!F162+BCTC2026!F163-BCTC2026!F165+BCTC2026!F166-BCTC2026!F169+BCTC2026!F170)/10^9 -> 180.12429 | F40: =(BCTC2026!G160+BCTC2026!G162+BCTC2026!G163-BCTC2026!G165+BCTC2026!G166-BCTC2026!G169+BCTC2026!G170)/10^9 -> 155.3531 | G40: =(BCTC2026!H160+BCTC2026!H162+BCTC2026!H163-BCTC2026!H165+BCTC2026!H166-BCTC2026!H169+BCTC2026!H170)/10^9 -> 151.58373 | H40: =(BCTC2026!I160+BCTC2026!I162+BCTC2026!I163-BCTC2026!I165+BCTC2026!I166-BCTC2026!I169+BCTC2026!I170)/10^9 -> 0 | I40: =(BCTC2026!J160+BCTC2026!J162+BCTC2026!J163-BCTC2026!J165+BCTC2026!J166-BCTC2026!J169+BCTC2026!J170)/10^9 -> 0 | J40: =(BCTC2026!K160+BCTC2026!K162+BCTC2026!K163-BCTC2026!K165+BCTC2026!K166-BCTC2026!K169+BCTC2026!K170)/10^9 -> 0 | ... N40: =(BCTC2026!O160+BCTC2026!O162+BCTC2026!O163-BCTC2026!O165+BCTC2026!O166-BCTC2026!O169+BCTC2026!O170)/10^9 -> 0
B41: Lợi nhuận | C41: =C39-C40 -> -1.6934607 | D41: =D39-D40 -> -6.4192137 | E41: =E39-E40 -> -6.8184675 | F41: =F39-F40 -> 3.7037542 | G41: =G39-G40 -> 8.1815839 | H41: =H39-H40 -> 0 | I41: =I39-I40 -> 0 | J41: =J39-J40 -> 0 | ... N41: =N39-N40 -> 0
B43: SAU LOẠI TRỪ
B44: Tháng | C44: T1.26 | D44: 2 | E44: 3 | F44: 4 | G44: 5 | H44: 6 | I44: 7 | J44: 8 | K44: 9 | L44: 10 | M44: 11 | N44: 12
B45: Doanh Thu | C45: ='BCTC2025-Sau loại trừ'!C172/10^9-'Data Chart'!C49 -> 126.09904 | D45: ='BCTC2025-Sau loại trừ'!D172/10^9-'Data Chart'!D49 -> 96.566805 | E45: ='BCTC2025-Sau loại trừ'!E172/10^9-'Data Chart'!E49 -> 173.30582 | F45: ='BCTC2025-Sau loại trừ'!F172/10^9-'Data Chart'!F49 -> 159.05685 | G45: ='BCTC2025-Sau loại trừ'!G172/10^9-'Data Chart'!G49 -> 159.76531 | H45: ='BCTC2025-Sau loại trừ'!H172/10^9-'Data Chart'!H49 -> 0 | I45: ='BCTC2025-Sau loại trừ'!I172/10^9-'Data Chart'!I49 -> 0 | J45: ='BCTC2025-Sau loại trừ'!J172/10^9-'Data Chart'!J49 -> 0 | ... N45: ='BCTC2025-Sau loại trừ'!N172/10^9-'Data Chart'!N49 -> 0
B46: Chi Phí | C46: =C45-C47 -> 127.7925 | D46: =D45-D47 -> 102.98602 | E46: =E45-E47 -> 179.97123 | F46: =F45-F47 -> 155.3531 | G46: =G45-G47 -> 151.53788 | H46: =H45-H47 -> 0 | I46: =I45-I47 -> 0 | J46: =J45-J47 -> 0 | ... N46: =N45-N47 -> 0
B47: Lợi nhuận | C47: ='BCTC2025-Sau loại trừ'!C160/10^9 -> -1.6934607 | D47: ='BCTC2025-Sau loại trừ'!D162/10^9 -> -6.4192137 | E47: ='BCTC2025-Sau loại trừ'!E162/10^9 -> -6.6654066 | F47: ='BCTC2025-Sau loại trừ'!F162/10^9 -> 3.7037542 | G47: ='BCTC2025-Sau loại trừ'!G162/10^9 -> 8.2274254 | H47: ='BCTC2025-Sau loại trừ'!H162/10^9 -> 0 | I47: ='BCTC2025-Sau loại trừ'!I162/10^9 -> 0 | J47: ='BCTC2025-Sau loại trừ'!J162/10^9 -> 0 | K47: ='BCTC2025-Sau loại trừ'!K162/10^9 -> 0 | ... N47: ='BCTC2025-Sau loại trừ'!N162/10^9 -> 0
B49: Dthu bán lại NCC (tỷ) | C49: 0 | D49: 0 | E49: 0 | F49: 0
B53: Cập nhật ô màu này
C55: DT-TH | D55: SL-TH | E55: LNST-TH | F55: LNST-Loại trừ-TH | G55: EBITDA-TH | H55: EBITDA-Loại trừ-TH
B56: 1 | C56: {=TRANSPOSE('KQKD MẪU CŨ'!D6:O6)/10^9} -> 126.09904 | D56: {=TRANSPOSE('KQKD MẪU CŨ'!D5:O5)} -> 4241.842 | E56: {=TRANSPOSE(BCTC2026!D174:O174)/10^9} -> -1.6934607 | F56: {=TRANSPOSE('BCTC2025-Sau loại trừ'!C162:N162)/10^9} -> -1.6934607 | G56: {=TRANSPOSE(BCTC2026!D176:O176)/10^9} -> 1.574238 | H56: {=TRANSPOSE('BCTC2025-Sau loại trừ'!C164:N164)/10^9} -> 1.574238
B57: 2 | C57: 96.566805 | D57: 3245.53 | E57: -6.4192137 | F57: -6.4192137 | G57: -3.2434715 | H57: -3.2434715
B58: 3 | C58: 173.30582 | D58: 6165.199 | E58: -6.6654066 | F58: -6.6654066 | G58: -4.054122 | H58: -4.054122
B59: 4 | C59: 159.05685 | D59: 5559.431 | E59: 3.7037542 | F59: 3.7037542 | G59: 6.7707201 | H59: 6.7707201
B60: 5 | C60: 159.76531 | D60: 5019.773 | E60: 8.2274254 | F60: 8.2274254 | G60: 11.229251 | H60: 11.229251 | T60: ('Data Chart'!$C$33,'Data Chart'!$J$33,'Data Chart'!$K$33)
B61: 6 | C61: 0 | D61: 0 | E61: 0 | F61: 0 | G61: 0 | H61: 0
B62: 7 | C62: 0 | D62: 0 | E62: 0 | F62: 0 | G62: 0 | H62: 0
B63: 8 | C63: 0 | D63: 0 | E63: 0 | F63: 0 | G63: 0 | H63: 0
B64: 9 | C64: 0 | D64: 0 | E64: 0 | F64: 0 | G64: 0 | H64: 0
B65: 10 | C65: 0 | D65: 0 | E65: 0 | F65: 0 | G65: 0 | H65: 0
B66: 11 | C66: 0 | D66: 0 | E66: 0 | F66: 0 | G66: 0 | H66: 0
B67: 12 | C67: 0 | D67: 0 | E67: 0 | F67: 0 | G67: 0 | H67: 0

Sheet KQKD MẪU CŨ
C1: TỔNG TÀI SẢN DTR - NGÀY 31/03/2023
C2: BÁO CÁO KẾT QUẢ KINH DOANH - NĂM 2023 | Q2: Tỷ giá
Q3: 24450 | T3: 22840
B4: Stt | C4: KẾT QUẢ KINH DOANH | D4: Tháng 01.2023 | E4: Tháng 02.2023 | F4: Tháng 03.2023 | G4: Tháng 04.2023 | H4: Tháng 05.2023 | I4: Tháng 06.2023 | J4: Tháng 07.2023 | K4: Tháng 08.2023 | L4: Tháng 09.2023 | M4: Tháng 10.2023 | N4: Tháng 11.2023 | O4: Tháng 12.2023 | P4: Lũy kế 12 tháng | Q4: $ US | R4: %/Dthu | T4: Lũy kế 2023 | U4: $ US | V4: %/Dthu
C5: Sản lượng bán (tấn) | D5: =BCTC2026!D217 -> 4241.842 | E5: =BCTC2026!E217 -> 3245.53 | F5: =BCTC2026!F217 -> 6165.199 | G5: =BCTC2026!G217 -> 5559.431 | H5: =BCTC2026!H217 -> 5019.773 | I5: =BCTC2026!I217 -> 0 | J5: =BCTC2026!J217 -> 0 | K5: =BCTC2026!K217 -> 0 | ... O5: =BCTC2026!O217 -> 0 | P5: =SUM(D5:O5) -> 24231.775 | T5: =BCTC2026!V154 -> 25012.587
B6: 1 | C6: Doanh thu | D6: =BCTC2026!D159 -> 126099036923 | E6: =BCTC2026!E159 -> 96566805360 | F6: =BCTC2026!F159 -> 173305822529 | G6: =BCTC2026!G159 -> 159056854829 | H6: =BCTC2026!H159 -> 159765309037 | I6: =BCTC2026!I159 -> 0 | J6: =BCTC2026!J159 -> 0 | K6: =BCTC2026!K159 -> 0 | ... O6: =BCTC2026!O159 -> 0 | P6: =SUM(D6:O6) -> 714793828678 | Q6: =P6/$Q$3 -> 29234921 | R6: 1 | T6: =BCTC2026!V159 -> 714793828678 | U6: =T6/$T$3 -> 31295702 | V6: =T6/$T$6 -> 1
C7: Giá vốn (chi phí sản xuất) | D7: =BCTC2026!D160 -> 115080112871 | E7: =BCTC2026!E160 -> 90411470461 | F7: =BCTC2026!F160 -> 165844739865 | G7: =BCTC2026!G160 -> 141086003219 | H7: =BCTC2026!H160 -> 137580032058 | I7: =BCTC2026!I160 -> 0 | J7: =BCTC2026!J160 -> 0 | K7: =BCTC2026!K160 -> 0 | ... O7: =BCTC2026!O160 -> 0 | P7: =SUM(D7:O7) -> 650002358474 | Q7: =P7/$Q$3 -> 26584964 | R7: =Q7/$Q$6 -> 0.90935642 | T7: =BCTC2026!V160 -> 650002358474 | U7: =T7/$T$3 -> 28458947 | V7: =T7/$T$6 -> 0.90935642
B8: 2 | C8: Lãi gộp | D8: =BCTC2026!D161 -> 11018924052 | E8: =BCTC2026!E161 -> 6155334899 | F8: =BCTC2026!F161 -> 7461082664 | G8: =BCTC2026!G161 -> 17970851610 | H8: =BCTC2026!H161 -> 22185276979 | I8: =BCTC2026!I161 -> 0 | J8: =BCTC2026!J161 -> 0 | K8: =BCTC2026!K161 -> 0 | ... O8: =BCTC2026!O161 -> 0 | P8: =SUM(D8:O8) -> 64791470204 | Q8: =P8/$Q$3 -> 2649957.9 | R8: =Q8/$Q$6 -> 0.090643578 | T8: =BCTC2026!V161 -> 64791470204 | U8: =T8/$T$3 -> 2836754.4 | V8: =T8/$T$6 -> 0.090643578
C9: Chi phí bán hàng | D9: =BCTC2026!D162 -> 3731798004 | E9: =BCTC2026!E162 -> 3202645336 | F9: =BCTC2026!F162 -> 6245695788 | G9: =BCTC2026!G162 -> 5821309126 | H9: =BCTC2026!H162 -> 5915805090 | I9: =BCTC2026!I162 -> 0 | J9: =BCTC2026!J162 -> 0 | K9: =BCTC2026!K162 -> 0 | ... O9: =BCTC2026!O162 -> 0 | P9: =SUM(D9:O9) -> 24917253344 | Q9: =P9/$Q$3 -> 1019110.6 | R9: =Q9/$Q$6 -> 0.034859357 | T9: =BCTC2026!V162 -> 24917253344 | U9: =T9/$T$3 -> 1090948 | V9: =T9/$T$6 -> 0.034859357
C10: Chi phí quản lý chung | D10: =BCTC2026!D163 -> 8394130638 | E10: =BCTC2026!E163 -> 7959394332 | F10: =BCTC2026!F163 -> 7329810589 | G10: =BCTC2026!G163 -> 8148952142 | H10: =BCTC2026!H163 -> 8010802475 | I10: =BCTC2026!I163 -> 0 | J10: =BCTC2026!J163 -> 0 | K10: =BCTC2026!K163 -> 0 | ... O10: =BCTC2026!O163 -> 0 | P10: =SUM(D10:O10) -> 39843090176 | Q10: =P10/$Q$3 -> 1629574.2 | R10: =Q10/$Q$6 -> 0.055740675 | T10: =BCTC2026!V163 -> 39843090176 | U10: =T10/$T$3 -> 1744443.5 | V10: =T10/$T$6 -> 0.055740675
B11: 3 | C11: Lợi nhuận sản xuất kinh doanh | D11: =D8-D9-D10 -> -1107004590 | E11: =E8-E9-E10 -> -5006704769 | F11: =F8-F9-F10 -> -6114423713 | G11: =G8-G9-G10 -> 4000590342 | H11: =H8-H9-H10 -> 8258669414 | I11: =I8-I9-I10 -> 0 | J11: =J8-J9-J10 -> 0 | K11: =K8-K9-K10 -> 0 | ... O11: =O8-O9-O10 -> 0 | P11: =SUM(D11:O11) -> 31126684 | Q11: =P11/$Q$3 -> 1273.075 | R11: =Q11/$Q$6 -> 4.354638e-05 | T11: =T8-T9-T10 -> 31126684 | U11: =T11/$T$3 -> 1362.8145 | V11: =T11/$T$6 -> 4.354638e-05
C12: Chi phí lãi vay ngân hàng | D12: =BCTC2026!D166 -> 1532817392 | E12: =BCTC2026!E166 -> 1569283837 | F12: =BCTC2026!F166 -> 1510605035 | G12: =BCTC2026!G166 -> 1998884061 | H12: =BCTC2026!H166 -> 1208736058 | I12: =BCTC2026!I166 -> 0 | J12: =BCTC2026!J166 -> 0 | K12: =BCTC2026!K166 -> 0 | ... O12: =BCTC2026!O166 -> 0 | P12: =SUM(D12:O12) -> 7820326383 | Q12: =P12/$Q$3 -> 319849.75 | R12: =Q12/$Q$6 -> 0.010940674 | T12: =BCTC2026!V166 -> 7820326383 | U12: =T12/$T$3 -> 342396.08 | V12: =T12/$T$6 -> 0.010940674
C13: Thu nhập lãi cho vay | D13: =BCTC2026!D165 -> 1053165322 | E13: =BCTC2026!E165 -> 307705069 | F13: =BCTC2026!F165 -> 839416558 | G13: =BCTC2026!G165 -> 1767937439 | H13: =BCTC2026!H165 -> 1261651212 | I13: =BCTC2026!I165 -> 0 | J13: =BCTC2026!J165 -> 0 | K13: =BCTC2026!K165 -> 0 | ... O13: =BCTC2026!O165 -> 0 | P13: =SUM(D13:O13) -> 5229875600 | Q13: =P13/$Q$3 -> 213900.84 | R13: =Q13/$Q$6 -> 0.0073166211 | T13: =BCTC2026!V165 -> 5229875600 | U13: =T13/$T$3 -> 228978.79 | V13: =T13/$T$6 -> 0.0073166211
C14: Thu nhập khác (tài trợ Coca, Nestle) | D14: =BCTC2026!D171 -> -106804076 | E14: =BCTC2026!E171 -> -150930201 | F14: =BCTC2026!F171 -> -32855301 | G14: =BCTC2026!G171 -> -65889508 | H14: =BCTC2026!H171 -> -130000650 | I14: =BCTC2026!I171 -> 0 | J14: =BCTC2026!J171 -> 0 | K14: =BCTC2026!K171 -> 0 | ... O14: =BCTC2026!O171 -> 0 | P14: =SUM(D14:O14) -> -486479736 | Q14: =P14/$Q$3 -> -19896.922 | R14: =Q14/$Q$6 -> -0.00068058749 | T14: =BCTC2026!V169 -> 11703115 | U14: =T14/$T$3 -> 512.39558 | V14: =T14/$T$6 -> 1.6372714e-05
B15: 4 | C15: Tổng Lợi nhuận trước thuế | D15: =D11-D12+D13+D14 -> -1693460736 | E15: =E11-E12+E13+E14 -> -6419213738 | F15: =F11-F12+F13+F14 -> -6818467491 | G15: =G11-G12+G13+G14 -> 3703754212 | H15: =H11-H12+H13+H14 -> 8181583918 | I15: =I11-I12+I13+I14 -> 0 | J15: =J11-J12+J13+J14 -> 0 | K15: =K11-K12+K13+K14 -> 0 | ... O15: =O11-O12+O13+O14 -> 0 | P15: =SUM(D15:O15) -> -3045803835 | Q15: =P15/$Q$3 -> -124572.75 | R15: =Q15/$Q$6 -> -0.0042610942 | T15: =T11-T12+T13+T14 -> -2547620984 | U15: =T15/$T$3 -> -111542.07 | V15: =T15/$T$6 -> -0.003564134
C16: Thuế thu nhập doanh nghiệp | D16: =BCTC2026!D173 -> 0 | E16: =BCTC2026!E173 -> 0 | F16: =BCTC2026!F173 -> -153060867 | G16: =BCTC2026!G173 -> 0 | H16: =BCTC2026!H173 -> -45841499 | I16: =BCTC2026!I173 -> 0 | J16: =BCTC2026!J173 -> 0 | K16: =BCTC2026!K173 -> 0 | ... O16: =BCTC2026!O173 -> 0 | P16: =SUM(D16:O16) -> -198902366 | Q16: =P16/$Q$3 -> -8135.0661 | R16: =Q16/$Q$6 -> -0.00027826537 | T16: =BCTC2026!V173 -> -198902366 | U16: =T16/$T$3 -> -8708.5099 | V16: =T16/$T$6 -> -0.00027826537
B17: 5 | C17: Lợi nhuận sau thuế | D17: =BCTC2026!D174 -> -1693460736 | E17: =BCTC2026!E174 -> -6419213738 | F17: =BCTC2026!F174 -> -6665406624 | G17: =BCTC2026!G174 -> 3703754212 | H17: =BCTC2026!H174 -> 8227425417 | I17: =BCTC2026!I174 -> 0 | J17: =BCTC2026!J174 -> 0 | K17: =BCTC2026!K174 -> 0 | ... O17: =BCTC2026!O174 -> 0 | P17: =SUM(D17:O17) -> -2846901469 | Q17: =P17/$Q$3 -> -116437.69 | R17: =Q17/$Q$6 -> -0.0039828288 | T17: =T15-T16 -> -2348718618 | U17: =T17/$T$3 -> -102833.56 | V17: =T17/$T$6 -> -0.0032858686
C18: Khấu hao | D18: =BCTC2026!D214 -> 2133968845 | E18: =BCTC2026!E214 -> 2103008488 | F18: =BCTC2026!F214 -> 2118111558 | G18: =BCTC2026!G214 -> 2277961573 | H18: =BCTC2026!H214 -> 2330977557 | I18: =BCTC2026!I214 -> 0 | J18: =BCTC2026!J214 -> 0 | K18: =BCTC2026!K214 -> 0 | ... O18: =BCTC2026!O214 -> 0 | P18: =SUM(D18:O18) -> 10964028021 | Q18: =P18/$Q$3 -> 448426.5 | R18: =Q18/$Q$6 -> 0.015338728
B19: 6 | C19: EBITDA (không gồm Lãi cho vay, Tài trợ) | D19: =BCTC2026!D176 -> 1574237997 | E19: =BCTC2026!E176 -> -3243471474 | F19: =BCTC2026!F176 -> -4054122006 | G19: =BCTC2026!G176 -> 6770720053 | H19: =BCTC2026!H176 -> 11229250758 | I19: =BCTC2026!I176 -> 0 | J19: =BCTC2026!J176 -> 0 | K19: =BCTC2026!K176 -> 0 | ... O19: =BCTC2026!O176 -> 0 | P19: =SUM(D19:O19) -> 12276615328 | Q19: =P19/$Q$3 -> 502111.06 | R19: =Q19/$Q$6 -> 0.017175044 | T19: =BCTC2026!V176 -> 12276615328 | U19: =T19/$T$3 -> 537505.05 | V19: =T19/$T$6 -> 0.017175044
B22: Stt | C22: BẢNG CÂN ĐỐI KẾ TOÁN | D22: 44957 | E22: 44985 | F22: 45016 | G22: 45046 | H22: 45077 | I22: 45107 | J22: 45138 | K22: 45169 | L22: 45199 | M22: 45230 | N22: 45260 | O22: 45291 | P22: $ US (31/12/2023) | Q22: %/TTS | W22: Stt | X22: BẢNG CÂN ĐỐI KẾ TOÁN | Y22: 44957 | Z22: 44985 | AA22: 45016 | AB22: 45046 | AC22: 45077 | AD22: 45107 | AE22: 45138 | AF22: 45169 | AG22: 45199 | AH22: 45230 | AI22: 45260 | AJ22: 45291 | AK22: $ US | AL22: %/TTS
C23: Phải thu cho vay ngắn hạn TGĐ và khác | D23: =BCTC2026!#REF! -> #REF! | E23: =BCTC2026!#REF! -> #REF! | F23: =BCTC2026!#REF! -> #REF! | G23: =BCTC2026!#REF! -> #REF! | H23: =BCTC2026!#REF! -> #REF! | I23: =BCTC2026!#REF! -> #REF! | J23: =BCTC2026!#REF! -> #REF! | K23: =BCTC2026!#REF! -> #REF! | ... O23: =BCTC2026!#REF! -> #REF! | P23: =H23/$Q$3 -> #REF! | Q23: =P23/$P$39 -> #REF!
B24: A | C24: TÀI SẢN NGẮN HẠN | D24: =SUM(D25:D30) -> #REF! | E24: =SUM(E25:E30) -> #REF! | F24: =SUM(F25:F30) -> #REF! | G24: =SUM(G25:G30) -> #REF! | H24: =SUM(H25:H30) -> #REF! | I24: =SUM(I25:I30) -> #REF! | J24: =SUM(J25:J30) -> #REF! | K24: =SUM(K25:K30) -> #REF! | ... O24: =SUM(O25:O30) -> #REF! | P24: =H24/$Q$3 -> #REF! | Q24: =P24/$P$39 -> #REF! | W24: A | X24: NỢ PHẢI TRẢ | Y24: =BCTC2026!D78-Y31 -> 332763448171 | Z24: =BCTC2026!E78-Z31 -> 360618515191 | AA24: =BCTC2026!F78-AA31 -> 326345040700 | AB24: =BCTC2026!G78-AB31 -> 303579055875 | AC24: =BCTC2026!H78-AC31 -> 374252871584 | AD24: =BCTC2026!I78-AD31 -> 0 | AE24: =BCTC2026!J78-AE31 -> 0 | AF24: =BCTC2026!K78-AF31 -> 0 | ... AJ24: =BCTC2026!O78-AJ31 -> 0 | AK24: =AC24/$Q$3 -> 15306866 | AL24: =AK24/AK$39 -> 0.29894733
B25: 1 | C25: Hàng tồn kho | D25: =BCTC2026!D20 -> 534105826237 | E25: =BCTC2026!E20 -> 502545827363 | F25: =BCTC2026!F20 -> 425450972162 | G25: =BCTC2026!G20 -> 370413533224 | H25: =BCTC2026!H20 -> 361880765551 | I25: =BCTC2026!I20 -> 0 | J25: =BCTC2026!J20 -> 0 | K25: =BCTC2026!K20 -> 0 | ... O25: =BCTC2026!O20 -> 0 | P25: =H25/$Q$3 -> 14800849 | Q25: =P25/$P$39 -> #REF! | W25: 1 | X25: Vay dài hạn ngân hàng | Y25: =BCTC2026!D95 -> 49472841415 | Z25: =BCTC2026!E95 -> 71400341415 | AA25: =BCTC2026!F95 -> 80100341415 | AB25: =BCTC2026!G95 -> 80100341415 | AC25: =BCTC2026!H95 -> 154933236415 | AD25: =BCTC2026!I95 -> 0 | AE25: =BCTC2026!J95 -> 0 | AF25: =BCTC2026!K95 -> 0 | ... AJ25: =BCTC2026!O95 -> 0 | AK25: =AC25/$Q$3 -> 6336737.7 | AL25: =AK25/AK$39 -> 0.12375824
B26: 2 | C26: Phải thu khách hàng | D26: =BCTC2026!D13 -> 132649296167 | E26: =BCTC2026!E13 -> 140446291758 | F26: =BCTC2026!F13 -> 153248625708 | G26: =BCTC2026!G13 -> 178191270169 | H26: =BCTC2026!H13 -> 178005616424 | I26: =BCTC2026!I13 -> 0 | J26: =BCTC2026!J13 -> 0 | K26: =BCTC2026!K13 -> 0 | ... O26: =BCTC2026!O13 -> 0 | P26: =H26/$Q$3 -> 7280393.3 | Q26: =P26/$P$39 -> #REF! | W26: 2 | X26: Vay ngắn hạn ngân hàng | Y26: =BCTC2026!#REF! -> #REF! | Z26: =BCTC2026!#REF! -> #REF! | AA26: =BCTC2026!#REF! -> #REF! | AB26: =BCTC2026!#REF! -> #REF! | AC26: =BCTC2026!#REF! -> #REF! | AD26: =BCTC2026!#REF! -> #REF! | AE26: =BCTC2026!#REF! -> #REF! | AF26: =BCTC2026!#REF! -> #REF! | ... AJ26: =BCTC2026!#REF! -> #REF! | AK26: =AC26/$Q$3 -> #REF! | AL26: =AK26/AK$39 -> #REF!
B27: 3 | C27: Thuế GTGT được khấu trừ | D27: =BCTC2026!D29 -> 14900314879 | E27: =BCTC2026!E29 -> 18117486770 | F27: =BCTC2026!F29 -> 18457562435 | G27: =BCTC2026!G29 -> 18721692095 | H27: =BCTC2026!H29 -> 23467402224 | I27: =BCTC2026!I29 -> 0 | J27: =BCTC2026!J29 -> 0 | K27: =BCTC2026!K29 -> 0 | ... O27: =BCTC2026!O29 -> 0 | P27: =H27/$Q$3 -> 959811.95 | Q27: =P27/$P$39 -> #REF! | W27: 3 | X27: Phải trả nhà cung cấp | Y27: =BCTC2026!D94 -> 0 | Z27: =BCTC2026!E94 -> 0 | AA27: =BCTC2026!F94 -> 0 | AB27: =BCTC2026!G94 -> 0 | AC27: =BCTC2026!H94 -> 0 | AD27: =BCTC2026!I94 -> 0 | AE27: =BCTC2026!J94 -> 0 | AF27: =BCTC2026!K94 -> 0 | ... AJ27: =BCTC2026!O94 -> 0 | AK27: =AC27/$Q$3 -> 0 | AL27: =AK27/AK$39 -> 0
B28: 4 | C28: Trả trước cho nhà cung cấp, nhà thầu | D28: =BCTC2026!D14 -> 75878310145 | E28: =BCTC2026!E14 -> 82113512006 | F28: =BCTC2026!F14 -> 95312309944 | G28: =BCTC2026!G14 -> 77634941776 | H28: =BCTC2026!H14 -> 162931057926 | I28: =BCTC2026!I14 -> 0 | J28: =BCTC2026!J14 -> 0 | K28: =BCTC2026!K14 -> 0 | ... O28: =BCTC2026!O14 -> 0 | P28: =H28/$Q$3 -> 6663846.9 | Q28: =P28/$P$39 -> #REF! | W28: 4 | X28: Thuế phải nộp Nhà nước | Y28: =BCTC2026!#REF! -> #REF! | Z28: =BCTC2026!#REF! -> #REF! | AA28: =BCTC2026!#REF! -> #REF! | AB28: =BCTC2026!#REF! -> #REF! | AC28: =BCTC2026!#REF! -> #REF! | AD28: =BCTC2026!#REF! -> #REF! | AE28: =BCTC2026!#REF! -> #REF! | AF28: =BCTC2026!#REF! -> #REF! | ... AJ28: =BCTC2026!#REF! -> #REF! | AK28: =AC28/$Q$3 -> #REF! | AL28: =AK28/AK$39 -> #REF!
B29: 5 | C29: Tiền gửi ngân hàng | D29: =BCTC2026!D5 -> 42126572011 | E29: =BCTC2026!E5 -> 45981412915 | F29: =BCTC2026!F5 -> 33613094972 | G29: =BCTC2026!G5 -> 47135211556 | H29: =BCTC2026!H5 -> 41014004605 | I29: =BCTC2026!I5 -> 0 | J29: =BCTC2026!J5 -> 0 | K29: =BCTC2026!K5 -> 0 | ... O29: =BCTC2026!O5 -> 0 | P29: =H29/$Q$3 -> 1677464.4 | Q29: =P29/$P$39 -> #REF! | W29: 5 | X29: Phải trả người lao động | Y29: =BCTC2026!#REF! -> #REF! | Z29: =BCTC2026!#REF! -> #REF! | AA29: =BCTC2026!#REF! -> #REF! | AB29: =BCTC2026!#REF! -> #REF! | AC29: =BCTC2026!#REF! -> #REF! | AD29: =BCTC2026!#REF! -> #REF! | AE29: =BCTC2026!#REF! -> #REF! | AF29: =BCTC2026!#REF! -> #REF! | ... AJ29: =BCTC2026!#REF! -> #REF! | AK29: =AC29/$Q$3 -> #REF! | AL29: =AK29/AK$39 -> #REF!
B30: 6 | C30: Tài sản ngắn hạn khác | D30: =BCTC2026!D4-D23-SUM(D25:D29) -> #REF! | E30: =BCTC2026!E4-E23-SUM(E25:E29) -> #REF! | F30: =BCTC2026!F4-F23-SUM(F25:F29) -> #REF! | G30: =BCTC2026!G4-G23-SUM(G25:G29) -> #REF! | H30: =BCTC2026!H4-H23-SUM(H25:H29) -> #REF! | I30: =BCTC2026!I4-I23-SUM(I25:I29) -> #REF! | J30: =BCTC2026!J4-J23-SUM(J25:J29) -> #REF! | K30: =BCTC2026!K4-K23-SUM(K25:K29) -> #REF! | ... O30: =BCTC2026!O4-O23-SUM(O25:O29) -> #REF! | P30: =H30/$Q$3 -> #REF! | Q30: =P30/$P$39 -> #REF! | W30: 6 | X30: Phải trả khác | Y30: =Y24-SUM(Y25:Y29) -> #REF! | Z30: =Z24-SUM(Z25:Z29) -> #REF! | AA30: =AA24-SUM(AA25:AA29) -> #REF! | AB30: =AB24-SUM(AB25:AB29) -> #REF! | AC30: =AC24-SUM(AC25:AC29) -> #REF! | AD30: =AD24-SUM(AD25:AD29) -> #REF! | AE30: =AE24-SUM(AE25:AE29) -> #REF! | AF30: =AF24-SUM(AF25:AF29) -> #REF! | ... AJ30: =AJ24-SUM(AJ25:AJ29) -> #REF! | AK30: =AC30/$Q$3 -> #REF! | AL30: =AK30/AK$39 -> #REF!
P31: =H31/$Q$3 -> 0 | AK31: =AC31/$Q$3 -> 0
B32: B | C32: TÀI SẢN DÀI HẠN | D32: =BCTC2026!D33 -> 317415705891 | E32: =BCTC2026!E33 -> 337499929442 | F32: =BCTC2026!F33 -> 343594894451 | G32: =BCTC2026!G33 -> 365048803536 | H32: =BCTC2026!H33 -> 365314011891 | I32: =BCTC2026!I33 -> 0 | J32: =BCTC2026!J33 -> 0 | K32: =BCTC2026!K33 -> 0 | ... O32: =BCTC2026!O33 -> 0 | P32: =H32/$Q$3 -> 14941268 | Q32: =P32/$P$39 -> #REF! | W32: B | X32: VỐN CHỦ SỞ HỮU | Y32: =BCTC2026!D110 -> 878802950065 | Z32: =BCTC2026!E110 -> 872383736327 | AA32: =BCTC2026!F110 -> 865718329703 | AB32: =BCTC2026!G110 -> 869422083915 | AC32: =BCTC2026!H110 -> 877649509332 | AD32: =BCTC2026!I110 -> 0 | AE32: =BCTC2026!J110 -> 0 | AF32: =BCTC2026!K110 -> 0 | ... AJ32: =BCTC2026!O110 -> 0 | AK32: =AC32/$Q$3 -> 35895685 | AL32: =AK32/AK$39 -> 0.70105267
B33: 1 | C33: Nguyên giá máy móc, hạ tầng kỹ thuật | D33: =BCTC2026!D43-D34 -> 346257196159 | E33: =BCTC2026!E43-E34 -> 349675687977 | F33: =BCTC2026!F43-F34 -> 372614337286 | G33: =BCTC2026!G43-G34 -> 379332503103 | H33: =BCTC2026!H43-H34 -> 379507503103 | I33: =BCTC2026!I43-I34 -> 0 | J33: =BCTC2026!J43-J34 -> 0 | K33: =BCTC2026!K43-K34 -> 0 | ... O33: =BCTC2026!O43-O34 -> 0 | P33: =H33/$Q$3 -> 15521779 | Q33: =P33/$P$39 -> #REF! | W33: 1 | X33: Vốn góp của chủ sở hữu | Y33: =BCTC2026!D112 -> 650000000000 | Z33: =BCTC2026!E112 -> 650000000000 | AA33: =BCTC2026!F112 -> 650000000000 | AB33: =BCTC2026!G112 -> 650000000000 | AC33: =BCTC2026!H112 -> 650000000000 | AD33: =BCTC2026!I112 -> 0 | AE33: =BCTC2026!J112 -> 0 | AF33: =BCTC2026!K112 -> 0 | ... AJ33: =BCTC2026!O112 -> 0 | AK33: =AC33/$Q$3 -> 26584867 | AL33: =AK33/AK$39 -> 0.51920981
B34: 2 | C34: Nguyên giá nhà xưởng, kho | E34: =D34 -> 0 | F34: =E34 -> 0 | G34: =F34 -> 0 | H34: =G34 -> 0 | I34: =H34 -> 0 | J34: =I34 -> 0 | K34: =J34 -> 0 | L34: =K34 -> 0 | ... O34: =N34 -> 0 | P34: =H34/$Q$3 -> 0 | Q34: =P34/$P$39 -> #REF! | W34: 2 | X34: Quỹ đầu tư phát triển | Y34: =BCTC2026!D121 -> 0 | Z34: =BCTC2026!E121 -> 0 | AA34: =BCTC2026!F121 -> 0 | AB34: =BCTC2026!G121 -> 0 | AC34: =BCTC2026!H121 -> 0 | AD34: =BCTC2026!I121 -> 0 | AE34: =BCTC2026!J121 -> 0 | AF34: =BCTC2026!K121 -> 0 | ... AJ34: =BCTC2026!O121 -> 0 | AK34: =AC34/$Q$3 -> 0 | AL34: =AK34/AK$39 -> 0
B35: 3 | C35: Xây dựng nhà xưởng, công trình dở dang | D35: =BCTC2026!D65 -> 61387421408 | E35: =BCTC2026!E65 -> 80647695075 | F35: =BCTC2026!F65 -> 66362060607 | G35: =BCTC2026!G65 -> 83813282245 | H35: =BCTC2026!H65 -> 86222726568 | I35: =BCTC2026!I65 -> 0 | J35: =BCTC2026!J65 -> 0 | K35: =BCTC2026!K65 -> 0 | ... O35: =BCTC2026!O65 -> 0 | P35: =H35/$Q$3 -> 3526491.9 | Q35: =P35/$P$39 -> #REF! | W35: 3 | X35: Lợi nhuận sau thuế | Y35: =BCTC2026!D124 -> 230496410801 | Z35: =BCTC2026!E124 -> 228802950065 | AA35: =BCTC2026!F124 -> 222383736327 | AB35: =BCTC2026!G124 -> 215718329703 | AC35: =BCTC2026!H124 -> 219422083915 | AD35: =BCTC2026!I124 -> 0 | AE35: =BCTC2026!J124 -> 0 | AF35: =BCTC2026!K124 -> 0 | ... AJ35: =BCTC2026!O124 -> 0 | AK35: =AC35/$Q$3 -> 8974318.4 | AL35: =AK35/AK$39 -> 0.17527092
B36: 4 | C36: Nguyên giá quyền sử dụng đất | D36: =BCTC2026!D49 -> 6032562739 | E36: =BCTC2026!E49 -> 6032562739 | F36: =BCTC2026!F49 -> 6032562739 | G36: =BCTC2026!G49 -> 6032562739 | H36: =BCTC2026!H49 -> 6032562739 | I36: =BCTC2026!I49 -> 0 | J36: =BCTC2026!J49 -> 0 | K36: =BCTC2026!K49 -> 0 | ... O36: =BCTC2026!O49 -> 0 | P36: =H36/$Q$3 -> 246730.58 | Q36: =P36/$P$39 -> #REF! | AK36: =AC36/$Q$3 -> 0
B37: 5 | C37: Chi phí trả trước đang phân bổ dài hạn | D37: =BCTC2026!D73 -> 7062502744 | E37: =BCTC2026!E73 -> 6570969298 | F37: =BCTC2026!F73 -> 6131031024 | G37: =BCTC2026!G73 -> 5693514228 | H37: =BCTC2026!H73 -> 5705255817 | I37: =BCTC2026!I73 -> 0 | J37: =BCTC2026!J73 -> 0 | K37: =BCTC2026!K73 -> 0 | ... O37: =BCTC2026!O73 -> 0 | P37: =H37/$Q$3 -> 233343.8 | Q37: =P37/$P$39 -> #REF! | AK37: =AC37/$Q$3 -> 0
B38: 6 | C38: Khấu hao lũy kế | D38: =BCTC2026!D44+BCTC2026!D50 -> -126324177398 | E38: =BCTC2026!E44+BCTC2026!E50 -> -128292700599 | F38: =BCTC2026!F44+BCTC2026!F50 -> -130276326863 | G38: =BCTC2026!G44+BCTC2026!G50 -> -132419803140 | H38: =BCTC2026!H44+BCTC2026!H50 -> -134616295410 | I38: =BCTC2026!I44+BCTC2026!I50 -> 0 | J38: =BCTC2026!J44+BCTC2026!J50 -> 0 | K38: =BCTC2026!K44+BCTC2026!K50 -> 0 | ... O38: =BCTC2026!O44+BCTC2026!O50 -> 0 | P38: =H38/$Q$3 -> -5505779 | Q38: =P38/$P$39 -> #REF! | AK38: =AC38/$Q$3 -> 0
C39: TỔNG TÀI SẢN | D39: =D32+D24+D23 -> #REF! | E39: =E32+E24+E23 -> #REF! | F39: =F32+F24+F23 -> #REF! | G39: =G32+G24+G23 -> #REF! | H39: =H32+H24+H23 -> #REF! | I39: =I32+I24+I23 -> #REF! | J39: =J32+J24+J23 -> #REF! | K39: =K32+K24+K23 -> #REF! | ... O39: =O32+O24+O23 -> #REF! | P39: =H39/$Q$3 -> #REF! | Q39: =P39/$P$39 -> #REF! | X39: TỔNG NGUỒN VỐN | Y39: =Y32+Y24 -> 1211566398236 | Z39: =Z32+Z24 -> 1233002251518 | AA39: =AA32+AA24 -> 1192063370403 | AB39: =AB32+AB24 -> 1173001139790 | AC39: =AC32+AC24 -> 1251902380916 | AD39: =AD32+AD24 -> 0 | AE39: =AE32+AE24 -> 0 | AF39: =AF32+AF24 -> 0 | ... AJ39: =AJ32+AJ24 -> 0 | AK39: =AC39/$Q$3 -> 51202551 | AL39: =AK39/$AK$39 -> 1
Y40: =Y39-D39 -> #REF! | Z40: =Z39-E39 -> #REF!
AK43: Người lập
C46: Tài sản ngắn hạn | D46: =P24 -> #REF! | E46: =D46/$D$49 -> #REF!
C47: Tài sản dài hạn | D47: =P32 -> 14941268 | E47: =D47/$D$49 -> #REF!
C48: TGĐ mượn và cho vay khác | D48: =P23 -> #REF! | E48: =D48/$D$49 -> #REF!
C49: Tổng tài sản | D49: =SUM(D46:D48) -> #REF! | E49: =D49/$D$49 -> #REF!
C51: Vốn chủ sở hữu | D51: =AK33 -> 26584867 | E51: =AL33 -> 0.51920981
C52: Nợ vay ngân hàng | D52: =AK25+AK26 -> #REF! | E52: =AL25+AL26 -> #REF!
C53: Nợ phải trả | D53: =AK27+AK28+AK29+AK30 -> #REF! | E53: =AL27+AL28+AL29+AL30 -> #REF!
C54: Lợi nhuận | D54: =AK34+AK35 -> 8974318.4 | E54: =AL32-AL33 -> 0.18184286
C55: Tổng | D55: =SUM(D51:D54) -> #REF! | E55: =SUM(E51:E54) -> #REF!
P69: =73+17+7+4 -> 101

Sheet BCTC2026
D1: BÁO CÁO TÀI CHÍNH NĂM 2026
S2: =MONTH(TODAY())-1 -> 5 | W2: 26000
B3: BÁO CÁO TÌNH HÌNH TÀI CHÍNH | D3: T01.2026 | E3: T02.2026 | F3: T03.2026 | G3: T04.2026 | H3: T05.2026 | I3: T06.2026 | J3: T07.2026 | K3: T08.2026 | L3: T09.2026 | M3: T10.2026 | N3: T11.2026 | O3: T12.2026 | Q3: Q01.2026 | R3: Q02.2026 | S3: Q03.2026 | T3: Q04.2026 | V3: Lũy kế năm 2026 | W3: US $ | X3: %/Tổng TS
B4: A-TÀI SẢN NGẮN HẠN | D4: =D5+D8+D12+D20+D23+D27 -> 894150692345 | E4: =E5+E8+E12+E20+E23+E27 -> 895502322076 | F4: =F5+F8+F12+F20+F23+F27 -> 848468475952 | G4: =G5+G8+G12+G20+G23+G27 -> 807952336254 | H4: =H5+H8+H12+H20+H23+H27 -> 886588369025 | Q4: =F4 -> 848468475952 | R4: =H4 -> 886588369025 | S4: =L4 -> 0 | T4: =O4 -> 0 | V4: =H4 -> 886588369025 | W4: =V4/$W$2 -> 34099553 | X4: =V4/$V$77 -> 0.70819289 | Y4: =V4-H4 -> 0 | Z4: =R4-H4 -> 0
B5: I.Tiền và các khoản tương đương tiền | D5: =SUM(D6:D7) -> 42126572011 | E5: =SUM(E6:E7) -> 45981412915 | F5: =SUM(F6:F7) -> 33613094972 | G5: =SUM(G6:G7) -> 47135211556 | H5: =SUM(H6:H7) -> 41014004605 | Q5: =F5 -> 33613094972 | R5: =H5 -> 41014004605 | S5: =L5 -> 0 | T5: =O5 -> 0 | V5: =H5 -> 41014004605 | W5: =V5/$W$2 -> 1577461.7 | X5: =V5/$V$77 -> 0.032761344 | Y5: =V5-H5 -> 0 | Z5: =R5-H5 -> 0
B6: 1.Tiền | D6: =CĐKT!D4 -> 42126572011 | E6: =CĐKT!E4 -> 45981412915 | F6: =CĐKT!F4 -> 27413094972 | G6: =CĐKT!G4 -> 28835211556 | H6: =CĐKT!H4 -> 30714004605 | Q6: =F6 -> 27413094972 | R6: =H6 -> 30714004605 | S6: =L6 -> 0 | T6: =O6 -> 0 | V6: =H6 -> 30714004605 | W6: =V6/$W$2 -> 1181307.9 | X6: =V6/$V$77 -> 0.024533865 | Y6: =V6-H6 -> 0 | Z6: =R6-H6 -> 0
B7: 2.Các khoản tương đương tiền | D7: =CĐKT!D5 -> 0 | E7: =CĐKT!E5 -> 0 | F7: =CĐKT!F5 -> 6200000000 | G7: =CĐKT!G5 -> 18300000000 | H7: =CĐKT!H5 -> 10300000000 | Q7: =F7 -> 6200000000 | R7: =H7 -> 10300000000 | S7: =L7 -> 0 | T7: =O7 -> 0 | V7: =H7 -> 10300000000 | W7: =V7/$W$2 -> 396153.85 | X7: =V7/$V$77 -> 0.0082274786 | Y7: =V7-H7 -> 0 | Z7: =R7-H7 -> 0
B8: II.Các khoản đầu tư tài chính ngắn hạn | D8: =SUM(D9:D11) -> 32840000000 | E8: =SUM(E9:E11) -> 32840000000 | F8: =SUM(F9:F11) -> 32840000000 | G8: =SUM(G9:G11) -> 34340000000 | H8: =SUM(H9:H11) -> 34340000000 | Q8: =F8 -> 32840000000 | R8: =H8 -> 34340000000 | S8: =L8 -> 0 | T8: =O8 -> 0 | V8: =H8 -> 34340000000 | W8: =V8/$W$2 -> 1320769.2 | X8: =V8/$V$77 -> 0.027430254 | Y8: =V8-H8 -> 0 | Z8: =R8-H8 -> 0
B9: 1.Chứng khoán kinh doanh | Q9: =F9 -> 0 | R9: =H9 -> 0 | S9: =L9 -> 0 | T9: =O9 -> 0 | V9: =H9 -> 0 | W9: =V9/$W$2 -> 0 | X9: =V9/$V$77 -> 0 | Y9: =V9-H9 -> 0 | Z9: =R9-H9 -> 0
B10: 2.Dự phòng giảm giá chứng khoán kinh doanh (*) | Q10: =F10 -> 0 | R10: =H10 -> 0 | S10: =L10 -> 0 | T10: =O10 -> 0 | V10: =H10 -> 0 | W10: =V10/$W$2 -> 0 | X10: =V10/$V$77 -> 0 | Y10: =V10-H10 -> 0 | Z10: =R10-H10 -> 0
B11: 3.Đầu tư nắm giữ đến ngày đáo hạn | D11: =CĐKT!D9 -> 32840000000 | E11: =CĐKT!E9 -> 32840000000 | F11: =CĐKT!F9 -> 32840000000 | G11: =CĐKT!G9 -> 34340000000 | H11: =CĐKT!H9 -> 34340000000 | Q11: =F11 -> 32840000000 | R11: =H11 -> 34340000000 | S11: =L11 -> 0 | T11: =O11 -> 0 | V11: =H11 -> 34340000000 | W11: =V11/$W$2 -> 1320769.2 | X11: =V11/$V$77 -> 0.027430254 | Y11: =V11-H11 -> 0 | Z11: =R11-H11 -> 0
B12: III.Các khoản phải thu | D12: =SUM(D13:D19) -> 263624916145 | E12: =SUM(E13:E19) -> 289980302579 | F12: =SUM(F13:F19) -> 331342767193 | G12: =SUM(G13:G19) -> 329741435832 | H12: =SUM(H13:H19) -> 417392857129 | Q12: =F12 -> 331342767193 | R12: =H12 -> 417392857129 | S12: =L12 -> 0 | T12: =O12 -> 0 | V12: =H12 -> 417392857129 | W12: =V12/$W$2 -> 16053571 | X12: =V12/$V$77 -> 0.33340687 | Y12: =V12-H12 -> 0 | Z12: =R12-H12 -> 0
B13: 1.Phải thu ngắn hạn của khách hàng | D13: =CĐKT!D11 -> 132649296167 | E13: =CĐKT!E11 -> 140446291758 | F13: =CĐKT!F11 -> 153248625708 | G13: =CĐKT!G11 -> 178191270169 | H13: =CĐKT!H11 -> 178005616424 | Q13: =F13 -> 153248625708 | R13: =H13 -> 178005616424 | S13: =L13 -> 0 | T13: =O13 -> 0 | V13: =H13 -> 178005616424 | W13: =V13/$W$2 -> 6846369.9 | X13: =V13/$V$77 -> 0.1421881 | Y13: =V13-H13 -> 0 | Z13: =R13-H13 -> 0
B14: 2.Trả trước cho người bán ngắn hạn | D14: =CĐKT!D12 -> 75878310145 | E14: =CĐKT!E12 -> 82113512006 | F14: =CĐKT!F12 -> 95312309944 | G14: =CĐKT!G12 -> 77634941776 | H14: =CĐKT!H12 -> 162931057926 | Q14: =F14 -> 95312309944 | R14: =H14 -> 162931057926 | S14: =L14 -> 0 | T14: =O14 -> 0 | V14: =H14 -> 162931057926 | W14: =V14/$W$2 -> 6266579.2 | X14: =V14/$V$77 -> 0.13014678 | Y14: =V14-H14 -> 0 | Z14: =R14-H14 -> 0
B15: 3.Phải thu nội bộ ngắn hạn | Q15: =F15 -> 0 | R15: =H15 -> 0 | S15: =L15 -> 0 | T15: =O15 -> 0 | V15: =H15 -> 0 | W15: =V15/$W$2 -> 0 | X15: =V15/$V$77 -> 0 | Y15: =V15-H15 -> 0 | Z15: =R15-H15 -> 0
B16: 4.Phải thu theo tiến độ kế hoạch hợp đồng XD | Q16: =F16 -> 0 | R16: =H16 -> 0 | S16: =L16 -> 0 | T16: =O16 -> 0 | V16: =H16 -> 0 | W16: =V16/$W$2 -> 0 | X16: =V16/$V$77 -> 0 | Y16: =V16-H16 -> 0 | Z16: =R16-H16 -> 0
B17: 5.Phải thu ngắn hạn khác | D17: =CĐKT!D15+CĐKT!D16 -> 54586491575 | E17: =CĐKT!E15+CĐKT!E16 -> 66773872669 | F17: =CĐKT!F15+CĐKT!F16 -> 82135205395 | G17: =CĐKT!G15+CĐKT!G16 -> 73268597741 | H17: =CĐKT!H15+CĐKT!H16 -> 76382324781 | Q17: =F17 -> 82135205395 | R17: =H17 -> 76382324781 | S17: =L17 -> 0 | T17: =O17 -> 0 | V17: =H17 -> 76382324781 | W17: =V17/$W$2 -> 2937781.7 | X17: =V17/$V$77 -> 0.061013004 | Y17: =V17-H17 -> 0 | Z17: =R17-H17 -> 0
B18: 6.Dự phòng phải thu ngắn hạn khó đòi(*) | D18: =CĐKT!D17 -> -609095700 | E18: =CĐKT!E17 -> -609095700 | F18: =CĐKT!F17 -> -609095700 | G18: =CĐKT!G17 -> -609095700 | H18: =CĐKT!H17 -> -609095700 | Q18: =F18 -> -609095700 | R18: =H18 -> -609095700 | S18: =L18 -> 0 | T18: =O18 -> 0 | V18: =H18 -> -609095700 | W18: =V18/$W$2 -> -23426.758 | X18: =V18/$V$77 -> -0.0004865361 | Y18: =V18-H18 -> 0 | Z18: =R18-H18 -> 0
B19: 7.Tài sản thiếu chờ xử lý | D19: =CĐKT!D18 -> 1119913958 | E19: =CĐKT!E18 -> 1255721846 | F19: =CĐKT!F18 -> 1255721846 | G19: =CĐKT!G18 -> 1255721846 | H19: =CĐKT!H18 -> 682953698 | Q19: =F19 -> 1255721846 | R19: =H19 -> 682953698 | S19: =L19 -> 0 | T19: =O19 -> 0 | V19: =H19 -> 682953698 | W19: =V19/$W$2 -> 26267.45 | X19: =V19/$V$77 -> 0.00054553271 | Y19: =V19-H19 -> 0 | Z19: =R19-H19 -> 0
B20: IV. Hàng tồn kho | D20: =SUM(D21:D22) -> 534105826237 | E20: =SUM(E21:E22) -> 502545827363 | F20: =SUM(F21:F22) -> 425450972162 | G20: =SUM(G21:G22) -> 370413533224 | H20: =SUM(H21:H22) -> 361880765551 | Q20: =F20 -> 425450972162 | R20: =H20 -> 361880765551 | S20: =L20 -> 0 | T20: =O20 -> 0 | V20: =H20 -> 361880765551 | W20: =V20/$W$2 -> 13918491 | X20: =V20/$V$77 -> 0.28906468 | Y20: =V20-H20 -> 0 | Z20: =R20-H20 -> 0
B21: 1.Hàng tồn kho | D21: =CĐKT!D20 -> 534105826237 | E21: =CĐKT!E20 -> 502545827363 | F21: =CĐKT!F20 -> 425450972162 | G21: =CĐKT!G20 -> 370413533224 | H21: =CĐKT!H20 -> 361880765551 | Q21: =F21 -> 425450972162 | R21: =H21 -> 361880765551 | S21: =L21 -> 0 | T21: =O21 -> 0 | V21: =H21 -> 361880765551 | W21: =V21/$W$2 -> 13918491 | X21: =V21/$V$77 -> 0.28906468 | Y21: =V21-H21 -> 0 | Z21: =R21-H21 -> 0
B22: 2.Dự phòng giảm giá hàng tồn kho (*) | Q22: =F22 -> 0 | R22: =H22 -> 0 | S22: =L22 -> 0 | T22: =O22 -> 0 | V22: =H22 -> 0 | W22: =V22/$W$2 -> 0 | X22: =V22/$V$77 -> 0 | Y22: =V22-H22 -> 0 | Z22: =R22-H22 -> 0
B23: V. Tài sản sinh học ngắn hạn | D23: =SUM(D24:D26) -> 0 | E23: =SUM(E24:E26) -> 0 | F23: =SUM(F24:F26) -> 0 | G23: =SUM(G24:G26) -> 0 | Q23: =F23 -> 0 | R23: =H23 -> 0 | V23: =H23 -> 0 | X23: =V23/$V$77 -> 0 | Y23: =V23-H23 -> 0 | Z23: =R23-H23 -> 0
B24: 1.Súc vật nuôi lấy sản phẩm một lần ngắn hạn | Q24: =F24 -> 0 | R24: =H24 -> 0 | V24: =H24 -> 0 | X24: =V24/$V$77 -> 0 | Y24: =V24-H24 -> 0 | Z24: =R24-H24 -> 0
B25: 2.Cây trồng theo mùa vụ hoặc lấy sản phẩm một lần ngắn hạn | Q25: =F25 -> 0 | R25: =H25 -> 0 | V25: =H25 -> 0 | X25: =V25/$V$77 -> 0 | Y25: =V25-H25 -> 0 | Z25: =R25-H25 -> 0
B26: 3.Dự phòng tổn thất tài sản sinh học ngắn hạn (*) | Q26: =F26 -> 0 | R26: =H26 -> 0 | V26: =H26 -> 0 | X26: =V26/$V$77 -> 0 | Y26: =V26-H26 -> 0 | Z26: =R26-H26 -> 0
B27: VI. Tài sản ngắn hạn khác | D27: =SUM(D28:D32) -> 21453377952 | E27: =SUM(E28:E32) -> 24154779219 | F27: =SUM(F28:F32) -> 25221641625 | G27: =SUM(G28:G32) -> 26322155642 | H27: =SUM(H28:H32) -> 31960741740 | Q27: =F27 -> 25221641625 | R27: =H27 -> 31960741740 | S27: =L27 -> 0 | T27: =O27 -> 0 | V27: =H27 -> 31960741740 | W27: =V27/$W$2 -> 1229259.3 | X27: =V27/$V$77 -> 0.02552974 | Y27: =V27-H27 -> 0 | Z27: =R27-H27 -> 0
B28: 1.Chi phí chờ phân bổ ngắn hạn | D28: =CĐKT!D23 -> 6232956370 | E28: =CĐKT!E23 -> 5669668845 | F28: =CĐKT!F23 -> 6281586071 | G28: =CĐKT!G23 -> 7111878966 | H28: =CĐKT!H23 -> 7978130611 | Q28: =F28 -> 6281586071 | R28: =H28 -> 7978130611 | S28: =L28 -> 0 | T28: =O28 -> 0 | V28: =H28 -> 7978130611 | W28: =V28/$W$2 -> 306851.18 | X28: =V28/$V$77 -> 0.0063728057 | Y28: =V28-H28 -> 0 | Z28: =R28-H28 -> 0
B29: 2.Thuế GTGT được khấu trừ | D29: =CĐKT!D24 -> 14900314879 | E29: =CĐKT!E24 -> 18117486770 | F29: =CĐKT!F24 -> 18457562435 | G29: =CĐKT!G24 -> 18721692095 | H29: =CĐKT!H24 -> 23467402224 | Q29: =F29 -> 18457562435 | R29: =H29 -> 23467402224 | S29: =L29 -> 0 | T29: =O29 -> 0 | V29: =H29 -> 23467402224 | W29: =V29/$W$2 -> 902592.39 | X29: =V29/$V$77 -> 0.018745393 | Y29: =V29-H29 -> 0 | Z29: =R29-H29 -> 0
B30: 3.Thuế và các khoản khác phải thu Nhà nước | D30: =CĐKT!D25 -> 320106703 | E30: =CĐKT!E25 -> 367623604 | F30: =CĐKT!F25 -> 482493119 | G30: =CĐKT!G25 -> 488584581 | H30: =CĐKT!H25 -> 515208905 | Q30: =F30 -> 482493119 | R30: =H30 -> 515208905 | S30: =L30 -> 0 | T30: =O30 -> 0 | V30: =H30 -> 515208905 | W30: =V30/$W$2 -> 19815.727 | X30: =V30/$V$77 -> 0.0004115408 | Y30: =V30-H30 -> 0 | Z30: =R30-H30 -> 0
B31: 4.Giao dịch mua bán lại trái phiếu Nhà nước | Q31: =F31 -> 0 | R31: =H31 -> 0 | S31: =L31 -> 0 | T31: =O31 -> 0 | V31: =H31 -> 0 | W31: =V31/$W$2 -> 0 | X31: =V31/$V$77 -> 0 | Y31: =V31-H31 -> 0 | Z31: =R31-H31 -> 0
B32: 5.Tài sản ngắn hạn khác | Q32: =F32 -> 0 | R32: =H32 -> 0 | S32: =L32 -> 0 | T32: =O32 -> 0 | V32: =H32 -> 0 | W32: =V32/$W$2 -> 0 | X32: =V32/$V$77 -> 0 | Y32: =V32-H32 -> 0 | Z32: =R32-H32 -> 0
B33: B-TÀI SẢN DÀI HẠN | D33: =D34+D41+D51+D60+D63+D66+D72 -> 317415705891 | E33: =E34+E41+E51+E60+E63+E66+E72 -> 337499929442 | F33: =F34+F41+F51+F60+F63+F66+F72 -> 343594894451 | G33: =G34+G41+G51+G60+G63+G66+G72 -> 365048803536 | H33: =H34+H41+H51+H60+H63+H66+H72 -> 365314011891 | Q33: =F33 -> 343594894451 | R33: =H33 -> 365314011891 | S33: =L33 -> 0 | T33: =O33 -> 0 | V33: =H33 -> 365314011891 | W33: =V33/$W$2 -> 14050539 | X33: =V33/$V$77 -> 0.29180711 | Y33: =V33-H33 -> 0 | Z33: =R33-H33 -> 0
B34: I- Các khoản phải thu dài hạn | D34: =SUM(D35:D40) -> 5315314211 | E34: =SUM(E35:E40) -> 5315314211 | F34: =SUM(F35:F40) -> 5315314211 | G34: =SUM(G35:G40) -> 5315314210 | H34: =SUM(H35:H40) -> 5315314210 | Q34: =F34 -> 5315314211 | R34: =H34 -> 5315314210 | S34: =L34 -> 0 | T34: =O34 -> 0 | V34: =H34 -> 5315314210 | W34: =V34/$W$2 -> 204435.16 | X34: =V34/$V$77 -> 0.0042457897 | Y34: =V34-H34 -> 0 | Z34: =R34-H34 -> 0
B35: 1.Phải thu dài hạn của khách hàng | Q35: =F35 -> 0 | R35: =H35 -> 0 | S35: =L35 -> 0 | T35: =O35 -> 0 | V35: =H35 -> 0 | W35: =V35/$W$2 -> 0 | X35: =V35/$V$77 -> 0 | Y35: =V35-H35 -> 0 | Z35: =R35-H35 -> 0
B36: 2.Trả trước cho người bán dài hạn | Q36: =F36 -> 0 | R36: =H36 -> 0 | S36: =L36 -> 0 | T36: =O36 -> 0 | V36: =H36 -> 0 | W36: =V36/$W$2 -> 0 | X36: =V36/$V$77 -> 0 | Y36: =V36-H36 -> 0 | Z36: =R36-H36 -> 0
B37: 3.Vốn kinh doanh ở đơn vị trực thuộc | Q37: =F37 -> 0 | R37: =H37 -> 0 | S37: =L37 -> 0 | T37: =O37 -> 0 | V37: =H37 -> 0 | W37: =V37/$W$2 -> 0 | X37: =V37/$V$77 -> 0 | Y37: =V37-H37 -> 0 | Z37: =R37-H37 -> 0
B38: 4.Phải thu nội bộ dài hạn | Q38: =F38 -> 0 | R38: =H38 -> 0 | S38: =L38 -> 0 | T38: =O38 -> 0 | V38: =H38 -> 0 | W38: =V38/$W$2 -> 0 | X38: =V38/$V$77 -> 0 | Y38: =V38-H38 -> 0 | Z38: =R38-H38 -> 0
B39: 5.Phải thu dài hạn khác | D39: =CĐKT!D35 -> 5315314211 | E39: =CĐKT!E35 -> 5315314211 | F39: =CĐKT!F35 -> 5315314211 | G39: =CĐKT!G35 -> 5315314210 | H39: =CĐKT!H35 -> 5315314210 | Q39: =F39 -> 5315314211 | R39: =H39 -> 5315314210 | S39: =L39 -> 0 | T39: =O39 -> 0 | V39: =H39 -> 5315314210 | W39: =V39/$W$2 -> 204435.16 | X39: =V39/$V$77 -> 0.0042457897 | Y39: =V39-H39 -> 0 | Z39: =R39-H39 -> 0
B40: 6.Dự phòng phải thu dài hạn khó đòi (*) | Q40: =F40 -> 0 | R40: =H40 -> 0 | S40: =L40 -> 0 | T40: =O40 -> 0 | V40: =H40 -> 0 | W40: =V40/$W$2 -> 0 | X40: =V40/$V$77 -> 0 | Y40: =V40-H40 -> 0 | Z40: =R40-H40 -> 0
B41: II.Tài sản cố định | D41: =D42+D45+D48 -> 243650467528 | E41: =E42+E45+E48 -> 244965950858 | F41: =F42+F45+F48 -> 265786488609 | G41: =G42+G45+G48 -> 270226692853 | H41: =H42+H45+H48 -> 268070715296 | Q41: =F41 -> 265786488609 | R41: =H41 -> 268070715296 | S41: =L41 -> 0 | T41: =O41 -> 0 | V41: =H41 -> 268070715296 | W41: =V41/$W$2 -> 10310412 | X41: =V41/$V$77 -> 0.21413069 | Y41: =V41-H41 -> 0 | Z41: =R41-H41 -> 0
B42: 1.Tài sản cố định hữu hình | D42: =SUM(D43:D44) -> 222439215846 | E42: =SUM(E43:E44) -> 223939131389 | F42: =SUM(F43:F44) -> 244944101358 | G42: =SUM(G43:G44) -> 249568737825 | H42: =SUM(H43:H44) -> 247597192480 | Q42: =F42 -> 244944101358 | R42: =H42 -> 247597192480 | S42: =L42 -> 0 | T42: =O42 -> 0 | V42: =H42 -> 247597192480 | W42: =V42/$W$2 -> 9522968.9 | X42: =V42/$V$77 -> 0.19777676 | Y42: =V42-H42 -> 0 | Z42: =R42-H42 -> 0
B43: Nguyên giá TSCĐ HH | D43: =CĐKT!D39 -> 346257196159 | E43: =CĐKT!E39 -> 349675687977 | F43: =CĐKT!F39 -> 372614337286 | G43: =CĐKT!G39 -> 379332503103 | H43: =CĐKT!H39 -> 379507503103 | Q43: =F43 -> 372614337286 | R43: =H43 -> 379507503103 | S43: =L43 -> 0 | T43: =O43 -> 0 | V43: =H43 -> 379507503103 | W43: =V43/$W$2 -> 14596442 | X43: =V43/$V$77 -> 0.30314465 | Y43: =V43-H43 -> 0 | Z43: =R43-H43 -> 0
B44: Giá trị hao mòn luỹ kế TSCĐ HH(*) | D44: =CĐKT!D40 -> -123817980313 | E44: =CĐKT!E40 -> -125736556588 | F44: =CĐKT!F40 -> -127670235928 | G44: =CĐKT!G40 -> -129763765278 | H44: =CĐKT!H40 -> -131910310623 | Q44: =F44 -> -127670235928 | R44: =H44 -> -131910310623 | S44: =L44 -> 0 | T44: =O44 -> 0 | V44: =H44 -> -131910310623 | W44: =V44/$W$2 -> -5073473.5 | X44: =V44/$V$77 -> -0.10536789 | Y44: =V44-H44 -> 0 | Z44: =R44-H44 -> 0
B45: 2. Tài sản cố định thuê tài chính | D45: =SUM(D46:D47) -> 17684886028 | E45: =SUM(E46:E47) -> 17550400741 | F45: =SUM(F46:F47) -> 17415915447 | G45: =SUM(G46:G47) -> 17281430151 | H45: =SUM(H46:H47) -> 17146944864 | Q45: =F45 -> 17415915447 | R45: =H45 -> 17146944864 | S45: =L45 -> 0 | T45: =O45 -> 0 | V45: =H45 -> 17146944864 | W45: =V45/$W$2 -> 659497.88 | X45: =V45/$V$77 -> 0.013696711 | Y45: =V45-H45 -> 0 | Z45: =R45-H45 -> 0
B46: Nguyên giá TSCĐ thuê tài chính | D46: =CĐKT!D42 -> 24160519140 | E46: =CĐKT!E42 -> 24160519140 | F46: =CĐKT!F42 -> 24160519140 | G46: =CĐKT!G42 -> 24160519140 | H46: =CĐKT!H42 -> 24160519140 | Q46: =F46 -> 24160519140 | R46: =H46 -> 24160519140 | S46: =L46 -> 0 | T46: =O46 -> 0 | V46: =H46 -> 24160519140 | W46: =V46/$W$2 -> 929250.74 | X46: =V46/$V$77 -> 0.019299044 | Y46: =V46-H46 -> 0 | Z46: =R46-H46 -> 0
B47: Giá trị hao mòn luỹ kế TSCĐ thuê tài chính | D47: =CĐKT!D43 -> -6475633112 | E47: =CĐKT!E43 -> -6610118399 | F47: =CĐKT!F43 -> -6744603693 | G47: =CĐKT!G43 -> -6879088989 | H47: =CĐKT!H43 -> -7013574276 | Q47: =F47 -> -6744603693 | R47: =H47 -> -7013574276 | S47: =L47 -> 0 | T47: =O47 -> 0 | V47: =H47 -> -7013574276 | W47: =V47/$W$2 -> -269752.86 | X47: =V47/$V$77 -> -0.0056023332 | Y47: =V47-H47 -> 0 | Z47: =R47-H47 -> 0
B48: 3. Tài sản cố định vô hình | D48: =SUM(D49:D50) -> 3526365654 | E48: =SUM(E49:E50) -> 3476418728 | F48: =SUM(F49:F50) -> 3426471804 | G48: =SUM(G49:G50) -> 3376524877 | H48: =SUM(H49:H50) -> 3326577952 | Q48: =F48 -> 3426471804 | R48: =H48 -> 3326577952 | S48: =L48 -> 0 | T48: =O48 -> 0 | V48: =H48 -> 3326577952 | W48: =V48/$W$2 -> 127945.31 | X48: =V48/$V$77 -> 0.0026572183 | Y48: =V48-H48 -> 0 | Z48: =R48-H48 -> 0
B49: Nguyên giá TSCĐ vô hình | D49: =CĐKT!D45 -> 6032562739 | E49: =CĐKT!E45 -> 6032562739 | F49: =CĐKT!F45 -> 6032562739 | G49: =CĐKT!G45 -> 6032562739 | H49: =CĐKT!H45 -> 6032562739 | Q49: =F49 -> 6032562739 | R49: =H49 -> 6032562739 | S49: =L49 -> 0 | T49: =O49 -> 0 | V49: =H49 -> 6032562739 | W49: =V49/$W$2 -> 232021.64 | X49: =V49/$V$77 -> 0.0048187166 | Y49: =V49-H49 -> 0 | Z49: =R49-H49 -> 0
B50: Giá trị hao mòn luỹ kế TSCĐ vô hình(*) | D50: =CĐKT!D46 -> -2506197085 | E50: =CĐKT!E46 -> -2556144011 | F50: =CĐKT!F46 -> -2606090935 | G50: =CĐKT!G46 -> -2656037862 | H50: =CĐKT!H46 -> -2705984787 | Q50: =F50 -> -2606090935 | R50: =H50 -> -2705984787 | S50: =L50 -> 0 | T50: =O50 -> 0 | V50: =H50 -> -2705984787 | W50: =V50/$W$2 -> -104076.34 | X50: =V50/$V$77 -> -0.0021614982 | Y50: =V50-H50 -> 0 | Z50: =R50-H50 -> 0
B51: III.Tài sản sinh học dài hạn | D51: =SUM(D52:D59) -> 0 | E51: =SUM(E52:E59) -> 0 | F51: =SUM(F52:F59) -> 0 | G51: =SUM(G52:G59) -> 0 | Q51: =F51 -> 0 | R51: =H51 -> 0 | V51: =H51 -> 0 | X51: =V51/$V$77 -> 0 | Y51: =V51-H51 -> 0 | Z51: =R51-H51 -> 0
B52: 1.Súc vật nuôi cho sản phẩm định kỳ | Q52: =F52 -> 0 | R52: =H52 -> 0 | V52: =H52 -> 0 | X52: =V52/$V$77 -> 0 | Y52: =V52-H52 -> 0 | Z52: =R52-H52 -> 0
B53: a)Súc vật nuôi cho sản phẩm định kỳ chưa đến giai đoạn trưởng thành | Q53: =F53 -> 0 | R53: =H53 -> 0 | V53: =H53 -> 0 | X53: =V53/$V$77 -> 0 | Y53: =V53-H53 -> 0 | Z53: =R53-H53 -> 0
B54: b)Súc vật nuôi cho sản phẩm định kỳ đến giai đoạn trưởng thành | Q54: =F54 -> 0 | R54: =H54 -> 0 | V54: =H54 -> 0 | X54: =V54/$V$77 -> 0 | Y54: =V54-H54 -> 0 | Z54: =R54-H54 -> 0
B55: Nguyên giá | Q55: =F55 -> 0 | R55: =H55 -> 0 | V55: =H55 -> 0 | X55: =V55/$V$77 -> 0 | Y55: =V55-H55 -> 0 | Z55: =R55-H55 -> 0
B56: Giá trị khấu hao lũy kế (*) | Q56: =F56 -> 0 | R56: =H56 -> 0 | V56: =H56 -> 0 | X56: =V56/$V$77 -> 0 | Y56: =V56-H56 -> 0 | Z56: =R56-H56 -> 0
B57: 2.Súc vật nuôi lấy sản phẩm một lần dài hạn | Q57: =F57 -> 0 | R57: =H57 -> 0 | V57: =H57 -> 0 | X57: =V57/$V$77 -> 0 | Y57: =V57-H57 -> 0 | Z57: =R57-H57 -> 0
B58: 3.Cây trồng theo mùa vụ hoặc lấy sản phẩm một lần dài hạn | Q58: =F58 -> 0 | R58: =H58 -> 0 | V58: =H58 -> 0 | X58: =V58/$V$77 -> 0 | Y58: =V58-H58 -> 0 | Z58: =R58-H58 -> 0
B59: 4.Dự phòng tổn thất tài sản sinh học dài hạn | Q59: =F59 -> 0 | R59: =H59 -> 0 | V59: =H59 -> 0 | X59: =V59/$V$77 -> 0 | Y59: =V59-H59 -> 0 | Z59: =R59-H59 -> 0
B60: IV. Bất động sản đầu tư | D60: =SUM(D61:D62) -> 0 | E60: =SUM(E61:E62) -> 0 | F60: =SUM(F61:F62) -> 0 | G60: =SUM(G61:G62) -> 0 | Q60: =F60 -> 0 | R60: =H60 -> 0 | S60: =L60 -> 0 | T60: =O60 -> 0 | V60: =H60 -> 0 | W60: =V60/$W$2 -> 0 | X60: =V60/$V$77 -> 0 | Y60: =V60-H60 -> 0 | Z60: =R60-H60 -> 0
B61: Nguyên giá bất động sản đầu tư | Q61: =F61 -> 0 | R61: =H61 -> 0 | S61: =L61 -> 0 | T61: =O61 -> 0 | V61: =H61 -> 0 | W61: =V61/$W$2 -> 0 | X61: =V61/$V$77 -> 0 | Y61: =V61-H61 -> 0 | Z61: =R61-H61 -> 0
B62: Giá trị hao mòn luỹ kế BĐSĐT(*) | Q62: =F62 -> 0 | R62: =H62 -> 0 | S62: =L62 -> 0 | T62: =O62 -> 0 | V62: =H62 -> 0 | W62: =V62/$W$2 -> 0 | X62: =V62/$V$77 -> 0 | Y62: =V62-H62 -> 0 | Z62: =R62-H62 -> 0
B63: V.Tài sản dở dang dài hạn | D63: =SUM(D64:D65) -> 61387421408 | E63: =SUM(E64:E65) -> 80647695075 | F63: =SUM(F64:F65) -> 66362060607 | G63: =SUM(G64:G65) -> 83813282245 | H63: =SUM(H64:H65) -> 86222726568 | Q63: =F63 -> 66362060607 | R63: =H63 -> 86222726568 | S63: =L63 -> 0 | T63: =O63 -> 0 | V63: =H63 -> 86222726568 | W63: =V63/$W$2 -> 3316258.7 | X63: =V63/$V$77 -> 0.068873363 | Y63: =V63-H63 -> 0 | Z63: =R63-H63 -> 0
B64: 1.Chi phí sản xuất, kinh doanh dở dang dài hạn | Q64: =F64 -> 0 | R64: =H64 -> 0 | S64: =L64 -> 0 | T64: =O64 -> 0 | V64: =H64 -> 0 | W64: =V64/$W$2 -> 0 | X64: =V64/$V$77 -> 0 | Y64: =V64-H64 -> 0 | Z64: =R64-H64 -> 0
B65: 2.Chi phí xây dựng cơ bản dở dang | D65: =CĐKT!D52 -> 61387421408 | E65: =CĐKT!E52 -> 80647695075 | F65: =CĐKT!F52 -> 66362060607 | G65: =CĐKT!G52 -> 83813282245 | H65: =CĐKT!H52 -> 86222726568 | Q65: =F65 -> 66362060607 | R65: =H65 -> 86222726568 | S65: =L65 -> 0 | T65: =O65 -> 0 | V65: =H65 -> 86222726568 | W65: =V65/$W$2 -> 3316258.7 | X65: =V65/$V$77 -> 0.068873363 | Y65: =V65-H65 -> 0 | Z65: =R65-H65 -> 0
B66: VI.Đầu tư tài chính dài hạn | D66: =SUM(D67:D71) -> 0 | E66: =SUM(E67:E71) -> 0 | F66: =SUM(F67:F71) -> 0 | G66: =SUM(G67:G71) -> 0 | Q66: =F66 -> 0 | R66: =H66 -> 0 | S66: =L66 -> 0 | T66: =O66 -> 0 | V66: =H66 -> 0 | W66: =V66/$W$2 -> 0 | X66: =V66/$V$77 -> 0 | Y66: =V66-H66 -> 0 | Z66: =R66-H66 -> 0
B67: 1.Đầu tư vào công ty con | Q67: =F67 -> 0 | R67: =H67 -> 0 | S67: =L67 -> 0 | T67: =O67 -> 0 | V67: =H67 -> 0 | W67: =V67/$W$2 -> 0 | X67: =V67/$V$77 -> 0 | Y67: =V67-H67 -> 0 | Z67: =R67-H67 -> 0
B68: 2.Đầu tư vào công ty liên kết, liên doanh | Q68: =F68 -> 0 | R68: =H68 -> 0 | S68: =L68 -> 0 | T68: =O68 -> 0 | V68: =H68 -> 0 | W68: =V68/$W$2 -> 0 | X68: =V68/$V$77 -> 0 | Y68: =V68-H68 -> 0 | Z68: =R68-H68 -> 0
B69: 3.Đầu tư góp vốn vào đơn vị khác | Q69: =F69 -> 0 | R69: =H69 -> 0 | S69: =L69 -> 0 | T69: =O69 -> 0 | V69: =H69 -> 0 | W69: =V69/$W$2 -> 0 | X69: =V69/$V$77 -> 0 | Y69: =V69-H69 -> 0 | Z69: =R69-H69 -> 0
B70: 4.Dự phòng giảm giá đầu tư tài chính dài hạn(*) | Q70: =F70 -> 0 | R70: =H70 -> 0 | S70: =L70 -> 0 | T70: =O70 -> 0 | V70: =H70 -> 0 | W70: =V70/$W$2 -> 0 | X70: =V70/$V$77 -> 0 | Y70: =V70-H70 -> 0 | Z70: =R70-H70 -> 0
B71: 5.Đầu tư nắm giữ đến ngày đáo hạn | Q71: =F71 -> 0 | R71: =H71 -> 0 | S71: =L71 -> 0 | T71: =O71 -> 0 | V71: =H71 -> 0 | W71: =V71/$W$2 -> 0 | X71: =V71/$V$77 -> 0 | Y71: =V71-H71 -> 0 | Z71: =R71-H71 -> 0
B72: VII.Tài sản dài hạn khác | D72: =SUM(D73:D76) -> 7062502744 | E72: =SUM(E73:E76) -> 6570969298 | F72: =SUM(F73:F76) -> 6131031024 | G72: =SUM(G73:G76) -> 5693514228 | H72: =SUM(H73:H76) -> 5705255817 | Q72: =F72 -> 6131031024 | R72: =H72 -> 5705255817 | S72: =L72 -> 0 | T72: =O72 -> 0 | V72: =H72 -> 5705255817 | W72: =V72/$W$2 -> 219432.92 | X72: =V72/$V$77 -> 0.0045572689 | Y72: =V72-H72 -> 0 | Z72: =R72-H72 -> 0
B73: 1.Chi phí chờ phân bổ dài hạn | D73: =CĐKT!D60 -> 7062502744 | E73: =CĐKT!E60 -> 6570969298 | F73: =CĐKT!F60 -> 6131031024 | G73: =CĐKT!G60 -> 5693514228 | H73: =CĐKT!H60 -> 5705255817 | Q73: =F73 -> 6131031024 | R73: =H73 -> 5705255817 | S73: =L73 -> 0 | T73: =O73 -> 0 | V73: =H73 -> 5705255817 | W73: =V73/$W$2 -> 219432.92 | X73: =V73/$V$77 -> 0.0045572689 | Y73: =V73-H73 -> 0 | Z73: =R73-H73 -> 0
B74: 2.Tài sản thuế thu nhập hoãn lại | Q74: =F74 -> 0 | R74: =H74 -> 0 | S74: =L74 -> 0 | T74: =O74 -> 0 | V74: =H74 -> 0 | W74: =V74/$W$2 -> 0 | X74: =V74/$V$77 -> 0 | Y74: =V74-H74 -> 0 | Z74: =R74-H74 -> 0
B75: 3.Thiết bị, vật tư, phụ tùng thay thế dài hạn | Q75: =F75 -> 0 | R75: =H75 -> 0 | S75: =L75 -> 0 | T75: =O75 -> 0 | V75: =H75 -> 0 | W75: =V75/$W$2 -> 0 | X75: =V75/$V$77 -> 0 | Y75: =V75-H75 -> 0 | Z75: =R75-H75 -> 0
B76: 4.Tài sản dài hạn khác | Q76: =F76 -> 0 | R76: =H76 -> 0 | S76: =L76 -> 0 | T76: =O76 -> 0 | V76: =H76 -> 0 | W76: =V76/$W$2 -> 0 | X76: =V76/$V$77 -> 0 | Y76: =V76-H76 -> 0 | Z76: =R76-H76 -> 0
B77: TỔNG TÀI SẢN | D77: =D33+D4 -> 1211566398236 | E77: =E33+E4 -> 1233002251518 | F77: =F33+F4 -> 1192063370403 | G77: =G33+G4 -> 1173001139790 | H77: =H33+H4 -> 1251902380916 | Q77: =F77 -> 1192063370403 | R77: =H77 -> 1251902380916 | S77: =L77 -> 0 | T77: =O77 -> 0 | V77: =H77 -> 1251902380916 | W77: =V77/$W$2 -> 48150092 | X77: =V77/$V$77 -> 1 | Y77: =V77-H77 -> 0 | Z77: =R77-H77 -> 0
B78: A-NỢ PHẢI TRẢ | D78: =D79+D95 -> 332763448171 | E78: =E79+E95 -> 360618515191 | F78: =F79+F95 -> 326345040700 | G78: =G79+G95 -> 303579055875 | H78: =H79+H95 -> 374252871584 | Q78: =F78 -> 326345040700 | R78: =H78 -> 374252871584 | S78: =L78 -> 0 | T78: =O78 -> 0 | V78: =H78 -> 374252871584 | W78: =V78/$W$2 -> 14394341 | X78: =V78/$V$129 -> 0.29894733 | Y78: =V78-H78 -> 0 | Z78: =R78-H78 -> 0
B79: I.Nợ ngắn hạn | D79: =SUM(D80:D94) -> 283290606756 | E79: =SUM(E80:E94) -> 289218173776 | F79: =SUM(F80:F94) -> 246244699285 | G79: =SUM(G80:G94) -> 223478714460 | H79: =SUM(H80:H94) -> 219319635169 | Q79: =F79 -> 246244699285 | R79: =H79 -> 219319635169 | S79: =L79 -> 0 | T79: =O79 -> 0 | V79: =H79 -> 219319635169 | W79: =V79/$W$2 -> 8435370.6 | X79: =V79/$V$129 -> 0.17518909 | Y79: =V79-H79 -> 0 | Z79: =R79-H79 -> 0
B80: 1.Phải trả người bán ngắn hạn | D80: =CĐKT!D67 -> 12939623311 | E80: =CĐKT!E67 -> 16340093986 | F80: =CĐKT!F67 -> 28822406885 | G80: =CĐKT!G67 -> 28647773855 | H80: =CĐKT!H67 -> 51638550700 | Q80: =F80 -> 28822406885 | R80: =H80 -> 51638550700 | S80: =L80 -> 0 | T80: =O80 -> 0 | V80: =H80 -> 51638550700 | W80: =V80/$W$2 -> 1986098.1 | X80: =V80/$V$129 -> 0.041248065 | Y80: =V80-H80 -> 0 | Z80: =R80-H80 -> 0
B81: 2.Người mua trả tiền trước ngắn hạn | D81: =CĐKT!D68 -> 11995200530 | E81: =CĐKT!E68 -> 6213138401 | F81: =CĐKT!F68 -> 6298509550 | G81: =CĐKT!G68 -> 10025771454 | H81: =CĐKT!H68 -> 14080108614 | Q81: =F81 -> 6298509550 | R81: =H81 -> 14080108614 | S81: =L81 -> 0 | T81: =O81 -> 0 | V81: =H81 -> 14080108614 | W81: =V81/$W$2 -> 541542.64 | X81: =V81/$V$129 -> 0.01124697 | Y81: =V81-H81 -> 0 | Z81: =R81-H81 -> 0
B82: 3.Phải trả cổ tức, lợi nhuận | Q82: =F82 -> 0 | R82: =H82 -> 0 | S82: =L82 -> 0 | T82: =O82 -> 0 | V82: =H82 -> 0 | W82: =V82/$W$2 -> 0 | X82: =V82/$V$129 -> 0 | Y82: =V82-H82 -> 0 | Z82: =R82-H82 -> 0
B83: 4.Thuế và các khoản phải nộp Nhà nước ngắn hạn | D83: =CĐKT!D69 -> 2125485230 | E83: =CĐKT!E69 -> 2202657518 | F83: =CĐKT!F69 -> 687237014 | G83: =CĐKT!G69 -> 681723426 | H83: =CĐKT!H69 -> 841764804 | Q83: =F83 -> 687237014 | R83: =H83 -> 841764804 | S83: =L83 -> 0 | T83: =O83 -> 0 | V83: =H83 -> 841764804 | W83: =V83/$W$2 -> 32375.569 | X83: =V83/$V$129 -> 0.00067238853 | Y83: =V83-H83 -> 0 | Z83: =R83-H83 -> 0
B84: 5.Phải trả người lao động | D84: =CĐKT!D70 -> 17091977517 | E84: =CĐKT!E70 -> 8616217662 | F84: =CĐKT!F70 -> 8622933213 | G84: =CĐKT!G70 -> 10380484365 | H84: =CĐKT!H70 -> 8734302003 | Q84: =F84 -> 8622933213 | R84: =H84 -> 8734302003 | S84: =L84 -> 0 | T84: =O84 -> 0 | V84: =H84 -> 8734302003 | W84: =V84/$W$2 -> 335934.69 | X84: =V84/$V$129 -> 0.0069768235 | Y84: =V84-H84 -> 0 | Z84: =R84-H84 -> 0
B85: 6.Chi phí phải trả ngắn hạn | D85: =CĐKT!D71 -> 17463423609 | E85: =CĐKT!E71 -> 17173577929 | F85: =CĐKT!F71 -> 16192573933 | G85: =CĐKT!G71 -> 20408777583 | H85: =CĐKT!H71 -> 21161124363 | Q85: =F85 -> 16192573933 | R85: =H85 -> 21161124363 | S85: =L85 -> 0 | T85: =O85 -> 0 | V85: =H85 -> 21161124363 | W85: =V85/$W$2 -> 813889.4 | X85: =V85/$V$129 -> 0.016903174 | Y85: =V85-H85 -> 0 | Z85: =R85-H85 -> 0
B86: 7.Phải trả nội bộ ngắn hạn | Q86: =F86 -> 0 | R86: =H86 -> 0 | S86: =L86 -> 0 | T86: =O86 -> 0 | V86: =H86 -> 0 | W86: =V86/$W$2 -> 0 | X86: 0 | Y86: =V86-H86 -> 0 | Z86: =R86-H86 -> 0
B87: 8.Phải trả theo tiến độ hợp đồng xây dựng ngắn hạn | Q87: =F87 -> 0 | R87: =H87 -> 0 | S87: =L87 -> 0 | T87: =O87 -> 0 | V87: =H87 -> 0 | W87: =V87/$W$2 -> 0 | X87: 0 | Y87: =V87-H87 -> 0 | Z87: =R87-H87 -> 0
B88: 9.Doanh thu chờ phân bổ ngắn hạn | Q88: =F88 -> 0 | R88: =H88 -> 0 | S88: =L88 -> 0 | T88: =O88 -> 0 | V88: =H88 -> 0 | W88: =V88/$W$2 -> 0 | X88: =V88/$V$129 -> 0 | Y88: =V88-H88 -> 0 | Z88: =R88-H88 -> 0
B89: 10.Phải trả ngắn hạn khác | D89: =CĐKT!D75 -> 3689065948 | E89: =CĐKT!E75 -> 5696728028 | F89: =CĐKT!F75 -> 3793714105 | G89: =CĐKT!G75 -> 3685561052 | H89: =CĐKT!H75 -> 4140002885 | Q89: =F89 -> 3793714105 | R89: =H89 -> 4140002885 | S89: =L89 -> 0 | T89: =O89 -> 0 | V89: =H89 -> 4140002885 | W89: =V89/$W$2 -> 159230.88 | X89: =V89/$V$129 -> 0.0033069694 | Y89: =V89-H89 -> 0 | Z89: =R89-H89 -> 0
B90: 11.Vay và nợ thuê tài chính ngắn hạn | D90: =CĐKT!D76 -> 216818798145 | E90: =CĐKT!E76 -> 231846507077 | F90: =CĐKT!F76 -> 179737111410 | G90: =CĐKT!G76 -> 147514569550 | H90: =CĐKT!H76 -> 116595603825 | Q90: =F90 -> 179737111410 | R90: =H90 -> 116595603825 | S90: =L90 -> 0 | T90: =O90 -> 0 | V90: =H90 -> 116595603825 | W90: =V90/$W$2 -> 4484446.3 | X90: =V90/$V$129 -> 0.093134741 | Y90: =V90-H90 -> 0 | Z90: =R90-H90 -> 0
B91: 12.Dự phòng phải trả ngắn hạn | Q91: =F91 -> 0 | R91: =H91 -> 0 | S91: =L91 -> 0 | T91: =O91 -> 0 | V91: =H91 -> 0 | W91: =V91/$W$2 -> 0 | X91: =V91/$V$129 -> 0 | Y91: =V91-H91 -> 0 | Z91: =R91-H91 -> 0
B92: 13.Quỹ khen thưởng, phúc lợi | D92: =CĐKT!D78 -> 1167032466 | E92: =CĐKT!E78 -> 1129253175 | F92: =CĐKT!F78 -> 2090213175 | G92: =CĐKT!G78 -> 2134053175 | H92: =CĐKT!H78 -> 2128177975 | Q92: =F92 -> 2090213175 | R92: =H92 -> 2128177975 | S92: =L92 -> 0 | T92: =O92 -> 0 | V92: =H92 -> 2128177975 | W92: =V92/$W$2 -> 81852.999 | X92: =V92/$V$129 -> 0.0016999552 | Y92: =V92-H92 -> 0 | Z92: =R92-H92 -> 0
B93: 14.Quỹ bình ổn giá | Q93: =F93 -> 0 | R93: =H93 -> 0 | S93: =L93 -> 0 | T93: =O93 -> 0 | V93: =H93 -> 0 | W93: =V93/$W$2 -> 0 | X93: 0 | Y93: =V93-H93 -> 0 | Z93: =R93-H93 -> 0
B94: 15.Giao dịch mua bán lại trái phiếu Chính phủ | Q94: =F94 -> 0 | R94: =H94 -> 0 | S94: =L94 -> 0 | T94: =O94 -> 0 | V94: =H94 -> 0 | W94: =V94/$W$2 -> 0 | X94: =V94/$V$129 -> 0 | Y94: =V94-H94 -> 0 | Z94: =R94-H94 -> 0
B95: II.Nợ dài hạn | D95: =SUM(D96:D109) -> 49472841415 | E95: =SUM(E96:E109) -> 71400341415 | F95: =SUM(F96:F109) -> 80100341415 | G95: =SUM(G96:G109) -> 80100341415 | H95: =SUM(H96:H109) -> 154933236415 | Q95: =F95 -> 80100341415 | R95: =H95 -> 154933236415 | S95: =L95 -> 0 | T95: =O95 -> 0 | V95: =H95 -> 154933236415 | W95: =V95/$W$2 -> 5958970.6 | X95: =V95/$V$129 -> 0.12375824 | Y95: =V95-H95 -> 0 | Z95: =R95-H95 -> 0
B96: 1.Phải trả người bán dài hạn | Q96: =F96 -> 0 | R96: =H96 -> 0 | S96: =L96 -> 0 | T96: =O96 -> 0 | V96: =H96 -> 0 | W96: =V96/$W$2 -> 0 | X96: 0 | Y96: =V96-H96 -> 0 | Z96: =R96-H96 -> 0
B97: 2.Người mua trả tiền trước dài hạn | Q97: =F97 -> 0 | R97: =H97 -> 0 | S97: =L97 -> 0 | T97: =O97 -> 0 | V97: =H97 -> 0 | W97: =V97/$W$2 -> 0 | X97: 0 | Y97: =V97-H97 -> 0 | Z97: =R97-H97 -> 0
B98: 3.Thuế và các khoản phải nộp Nhà nước dài hạn | Q98: =F98 -> 0 | R98: =H98 -> 0 | S98: =L98 -> 0 | T98: =O98 -> 0 | V98: =H98 -> 0 | W98: =V98/$W$2 -> 0 | X98: 0 | Y98: =V98-H98 -> 0 | Z98: =R98-H98 -> 0
B99: 4.Chi phí phải trả dài hạn | Q99: =F99 -> 0 | R99: =H99 -> 0 | S99: =L99 -> 0 | T99: =O99 -> 0 | V99: =H99 -> 0 | W99: =V99/$W$2 -> 0 | X99: 0 | Y99: =V99-H99 -> 0 | Z99: =R99-H99 -> 0
B100: 5.Phải trả nội bộ về vốn kinh doanh | Q100: =F100 -> 0 | R100: =H100 -> 0 | S100: =L100 -> 0 | T100: =O100 -> 0 | V100: =H100 -> 0 | W100: =V100/$W$2 -> 0 | X100: 0 | Y100: =V100-H100 -> 0 | Z100: =R100-H100 -> 0
...

Sheet Tình hình tài chính
B1: CTY CP NHỰA TÁI CHẾ DUY TÂN
B2: VND
A3: Index BS | B3: PHẦN I-BÁO CÁO TÌNH HÌNH TÀI CHÍNH | C3: TenCongTyID | D3: T1.2021 | E3: T02.2021 | F3: T03.2021 | G3: T04.2021 | H3: T05.2021 | I3: T06.2021 | J3: T07.2021 | K3: T08.2021 | L3: T09.2021 | M3: T10.2021 | N3: T11.2021 | O3: T12.2021 | P3: T1.2022 | Q3: T02.2022 | R3: T03.2022 | S3: T04.2022 | T3: T05.2022 | U3: T06.2022 | V3: T07.2022 | W3: T08.2022 | X3: T09.2022 | Y3: T10.2022 | Z3: T11.2022 | AA3: T12.2022 | AB3: T1.2023 | AC3: T02.2023 | AD3: T03.2023 | AE3: T04.2023 | AF3: T05.2023 | AG3: T06.2023 | AH3: T07.2023 | AI3: T08.2023 | AJ3: T09.2023 | AK3: T10.2023 | AL3: T11.2023 | AM3: T12.2023 | AN3: T01.2024 | AO3: T02.2024 | AP3: T03.2024 | AQ3: T04.2024 | AR3: T05.2024 | AS3: T06.2024 | AT3: T07.2024 | AU3: T08.2024 | AV3: T09.2024 | AW3: T10.2024 | AX3: T11.2024 | AY3: T12.2024 | AZ3: T01.2025 | BA3: T02.2025 | BB3: T03.2025 | BC3: T04.2025 | BD3: T05.2025 | BE3: T06.2025 | BF3: T07.2025 | BG3: T08.2025 | BH3: T09.2025 | BI3: T10.2025 | BJ3: T11.2025 | BK3: T12.2025 | BL3: T01.2026 | BM3: T02.2026 | BN3: T03.2026 | BO3: T04.2026 | BP3: T05.2026 | BQ3: T06.2026 | BR3: T07.2026 | BS3: T08.2026 | BT3: T09.2026 | BU3: T10.2026 | BV3: T11.2026 | BW3: T12.2026
A4: 1 | B4: A-TÀI SẢN NGẮN HẠN | C4: 5 | D4: 614299663363 | E4: 609691312919 | F4: 615298026209 | G4: 628174770356 | H4: 633634093227 | I4: 634442148116 | J4: 641465222117 | K4: 461269303491 | L4: 464335451361 | M4: 465446434421 | N4: 474566713935 | O4: 483715466637 | P4: 491203268636 | Q4: 495110335063 | R4: 506410020272 | S4: 541090328555 | T4: 557182730957 | U4: 567579171386 | V4: 553380198104 | W4: 575629704487 | X4: 581428641960 | Y4: 579326744202 | Z4: 570154808236 | AA4: 646788980449 | AB4: 630392907077 | AC4: 635811337862 | AD4: 615592156470 | AE4: 589633117559 | AF4: 574650354873 | AG4: 627637203928 | AH4: 645144940465 | AI4: 624618100412 | AJ4: 607904625059 | AK4: 655561441656 | AL4: 691663318215 | AM4: 723466020980 | AN4: 782481934423 | AO4: 768590764263 | AP4: 815465869041 | AQ4: 877414026420 | AR4: 928155716736 | AS4: 956563222023 | AT4: 906133879099 | AU4: 849218290026 | AV4: 891170346476 | AW4: 912165489717 | AX4: 989601612249 | AY4: 969587265880 | AZ4: 894788032291 | BA4: 814157821775 | BB4: 866303373135 | BC4: 929599762285 | BD4: 981599372849 | BE4: 1010794698754 | BF4: 999811801439 | BG4: 1060333071975 | BH4: 1040577598634 | BI4: 982848510813 | BJ4: 959373053576 | BK4: 953625133537 | BL4: 897731457175
A5: 2 | B5: I.Tiền và các khoản tương đương tiền | C5: 5 | D5: 3447839862 | E5: 4753297265 | F5: 3470025524 | G5: 7213551570 | H5: 6428796497 | I5: 6637859615 | J5: 6692002174 | K5: 17171442096 | L5: 20706415997 | M5: 18510700926 | N5: 9217053448 | O5: 9537238483 | P5: 7841551973 | Q5: 25742652312 | R5: 10229505276 | S5: 23153084677 | T5: 15475133505 | U5: 6070662597 | V5: 5025380377 | W5: 25956322209 | X5: 31102397335 | Y5: 12848278176 | Z5: 10250965252 | AA5: 13274374142 | AB5: 16792099757 | AC5: 15908187368 | AD5: 16078630986 | AE5: 51289665216 | AF5: 23427390962 | AG5: 21288636707 | AH5: 22472091319 | AI5: 2490582158 | AJ5: 10148364108 | AK5: 9841817259 | AL5: 4968558361 | AM5: 6353042534 | AN5: 31037848308 | AO5: 22669663716 | AP5: 6664945115 | AQ5: 15574807889 | AR5: 16007340290 | AS5: 3678057757 | AT5: 36916493026 | AU5: 16748498285 | AV5: 33251814637 | AW5: 56773964959 | AX5: 43420355696 | AY5: 39805017284 | AZ5: 76486895109 | BA5: 33258200889 | BB5: 23555271373 | BC5: 37590058839 | BD5: 21868727527 | BE5: 32470900772 | BF5: 30661632458 | BG5: 29770776625 | BH5: 64296693910 | BI5: 53646701293 | BJ5: 55165406320 | BK5: 36834893155 | BL5: 42126572011
A6: 3 | B6: 1.Tiền | C6: 5 | D6: 3447839862 | E6: 4753297265 | F6: 3470025524 | G6: 7213551570 | H6: 6428796497 | I6: 6637859615 | J6: 6692002174 | K6: 4471442096 | L6: 5006415997 | M6: 5810700926 | N6: 9217053448 | O6: 9537238483 | P6: 7841551973 | Q6: 25742652312 | R6: 10229505276 | S6: 23153084677 | T6: 15475133505 | U6: 6070662597 | V6: 5025380377 | W6: 25956322209 | X6: 31102397335 | Y6: 12848278176 | Z6: 10250965252 | AA6: 13274374142 | AB6: 16792099757 | AC6: 15908187368 | AD6: 16078630986 | AE6: 36289665216 | AF6: 23427390962 | AG6: 21288636707 | AH6: 22472091319 | AI6: 2490582158 | AJ6: 10148364108 | AK6: 7001817259 | AL6: 2128558361 | AM6: 3513042534 | AN6: 28197848308 | AO6: 19829663716 | AP6: 5834945115 | AQ6: 14744807889 | AR6: 15177340290 | AS6: 2848057757 | AT6: 36086493026 | AU6: 15918498285 | AV6: 33251814637 | AW6: 56773964959 | AX6: 43420355696 | AY6: 29805017284 | AZ6: 73646895109 | BA6: 30418200889 | BB6: 23555271373 | BC6: 37590058839 | BD6: 21868727527 | BE6: 32470900772 | BF6: 30661632458 | BG6: 29770776625 | BH6: 64296693910 | BI6: 33646701293 | BJ6: 35165406320 | BK6: 36834893155 | BL6: 42126572011
A7: 4 | B7: 2.Các khoản tương đương tiền | C7: 5 | K7: 12700000000 | L7: 15700000000 | M7: 12700000000 | P7: 0 | Q7: 0 | R7: 0 | S7: 0 | T7: 0 | W7: 0 | X7: 0 | Y7: 0 | AA7: 0 | AE7: 15000000000 | AG7: 0 | AH7: 0 | AJ7: 0 | AK7: 2840000000 | AL7: 2840000000 | AM7: 2840000000 | AN7: 2840000000 | AO7: 2840000000 | AP7: 830000000 | AQ7: 830000000 | AR7: 830000000 | AS7: 830000000 | AT7: 830000000 | AU7: 830000000 | AV7: 0 | AW7: 0 | AX7: 0 | AY7: 10000000000 | AZ7: 2840000000 | BA7: 2840000000 | BB7: 0 | BC7: 0 | BD7: 0 | BE7: 0 | BF7: 0 | BG7: 0 | BH7: 0 | BI7: 20000000000 | BJ7: 20000000000
A8: 5 | B8: II.Đầu tư tài chính ngắn hạn | C8: 5 | D8: 1000000000 | E8: 550000000000 | F8: 550000000000 | G8: 545000000000 | H8: 545000000000 | I8: 545000000000 | J8: 545000000000 | K8: 348000000000 | L8: 347009021921 | M8: 340009021921 | N8: 340009021921 | O8: 322972364387 | P8: 305609021921 | Q8: 285609021921 | R8: 285609021921 | S8: 265812329757 | T8: 227609021921 | U8: 227609021921 | V8: 215609021921 | W8: 215609021921 | X8: 215609021921 | Y8: 215609021921 | Z8: 185609021921 | AA8: 5609021921 | AB8: 5609021921 | AC8: 5609021921 | AD8: 195619021921 | AE8: 157619021921 | AF8: 157619021921 | AG8: 157619021921 | AH8: 157619021921 | AI8: 157619021921 | AJ8: 157619021921 | AK8: 157619021921 | AL8: 157619021921 | AM8: 137869021921 | AN8: 107849581921 | AO8: 107839861921 | AP8: 107830141921 | AQ8: 97320421921 | AR8: 97310701921 | AS8: 77300981921 | AT8: 57791261921 | AU8: 57781541921 | AV8: 58611541921 | AW8: 58592101921 | AX8: 98592101921 | AY8: 78572661921 | AZ8: 75713221921 | BA8: 61213221921 | BB8: 101053221921 | BC8: 125553221921 | BD8: 135524061921 | BE8: 135504621921 | BF8: 120504621921 | BG8: 120699021921 | BH8: 108699021921 | BI8: 88699021921 | BJ8: 78699021921 | BK8: 73699021921 | BL8: 32840000000
A9: 6 | B9: 1.Chứng khoán kinh doanh | C9: 5 | D9: 0 | E9: 0 | F9: 0 | G9: 0 | H9: 0 | I9: 0 | J9: 0 | K9: 0 | L9: 0 | M9: 0 | N9: 0 | O9: 0 | P9: 0 | Q9: 0 | R9: 0 | S9: 0 | T9: 0 | W9: 0 | X9: 0 | Y9: 0 | AA9: 0 | AG9: 0 | AH9: 0 | AJ9: 0 | AN9: 0 | AO9: 0 | AP9: 0 | AQ9: 0 | AR9: 0 | AS9: 0 | AT9: 0 | AU9: 0 | AV9: 0 | AW9: 0 | AX9: 0 | AY9: 0 | AZ9: 0 | BA9: 0 | BB9: 0 | BC9: 0 | BD9: 0 | BE9: 0 | BF9: 0 | BG9: 0 | BH9: 0 | BI9: 0 | BJ9: 0
A10: 7 | B10: 2.Dự phòng giảm giá chứng khoán kinh doanh (*) | C10: 5 | D10: 0 | E10: 0 | F10: 0 | G10: 0 | H10: 0 | I10: 0 | J10: 0 | K10: 0 | L10: 0 | M10: 0 | N10: 0 | O10: 0 | P10: 0 | Q10: 0 | R10: 0 | S10: 0 | T10: 0 | W10: 0 | X10: 0 | Y10: 0 | AA10: 0 | AG10: 0 | AH10: 0 | AJ10: 0 | AN10: 0 | AO10: 0 | AP10: 0 | AQ10: 0 | AR10: 0 | AS10: 0 | AT10: 0 | AU10: 0 | AV10: 0 | AW10: 0 | AX10: 0 | AY10: 0 | AZ10: 0 | BA10: 0 | BB10: 0 | BC10: 0 | BD10: 0 | BE10: 0 | BF10: 0 | BG10: 0 | BH10: 0 | BI10: 0 | BJ10: 0
A11: 8 | B11: 3.Đầu tư nắm giữ đến ngày đáo hạn ngắn hạn | C11: 5 | D11: 1000000000 | E11: 550000000000 | F11: 550000000000 | G11: 545000000000 | H11: 545000000000 | I11: 545000000000 | J11: 545000000000 | K11: 348000000000 | L11: 347009021921 | M11: 340009021921 | N11: 340009021921 | O11: 322972364387 | P11: 305609021921 | Q11: 285609021921 | R11: 285609021921 | S11: 265812329757 | T11: 227609021921 | U11: 227609021921 | V11: 215609021921 | W11: 215609021921 | X11: 215609021921 | Y11: 215609021921 | Z11: 185609021921 | AA11: 5609021921 | AB11: 5609021921 | AC11: 5609021921 | AD11: 195619021921 | AE11: 157619021921 | AF11: 157619021921 | AG11: 157619021921 | AH11: 157619021921 | AI11: 157619021921 | AJ11: 157619021921 | AK11: 157619021921 | AL11: 157619021921 | AM11: 137869021921 | AN11: 107849581921 | AO11: 107839861921 | AP11: 107830141921 | AQ11: 97320421921 | AR11: 97310701921 | AS11: 77300981921 | AT11: 57791261921 | AU11: 57781541921 | AV11: 58611541921 | AW11: 58592101921 | AX11: 98592101921 | AY11: 78572661921 | AZ11: 75713221921 | BA11: 61213221921 | BB11: 101053221921 | BC11: 125553221921 | BD11: 135524061921 | BE11: 135504621921 | BF11: 120504621921 | BG11: 120699021921 | BH11: 108699021921 | BI11: 88699021921 | BJ11: 78699021921 | BK11: 73699021921 | BL11: 32840000000
A12: 9 | B12: 4.Dự phòng đầu tư nắm giữ đến ngày đáo hạn ngắn hạn (*) | C12: 5
A13: 10 | B13: 5.Đầu tư ngắn hạn khác | C13: 5
A14: 11 | B14: 6.Dự phòng tổn thất các khoản đầu tư ngắn hạn khác (*) | C14: 5
A15: 12 | B15: III.Các khoản phải thu ngắn hạn | C15: 5 | D15: =SUM(D16:D22) -> 581896739681 | E15: =SUM(E16:E22) -> 24442097162 | F15: =SUM(F16:F22) -> 29654385119 | G15: =SUM(G16:G22) -> 35152986487 | H15: =SUM(H16:H22) -> 29090844955 | I15: =SUM(I16:I22) -> 27033698810 | J15: =SUM(J16:J22) -> 33204061657 | K15: =SUM(K16:K22) -> 23354860764 | ... BK15: =SUM(BK16:BK22) -> 258086122082 | BL15: 267472067581
A16: 13 | B16: 1.Phải thu ngắn hạn của khách hàng | C16: 5 | D16: 571116397848 | E16: 11245292216 | F16: 15856223874 | G16: 11853022983 | H16: 4837569782 | I16: 6108714016 | J16: 18273784195 | K16: 6649601466 | L16: 6537064622 | M16: 14808496229 | N16: 23891683442 | O16: 33185427033 | P16: 42838925726 | Q16: 40209422110 | R16: 42161135861 | S16: 46509292431 | T16: 53272379708 | U16: 46733674531 | V16: 46987053150 | W16: 46192969621 | X16: 46575900326 | Y16: 51157219350 | Z16: 52837953862 | AA16: 366019034353 | AB16: 346550500356 | AC16: 331740967976 | AD16: 114960287290 | AE16: 82538799028 | AF16: 76951932726 | AG16: 75528601013 | AH16: 74743149460 | AI16: 77570626810 | AJ16: 83261973464 | AK16: 111015808616 | AL16: 116221372072 | AM16: 131612253760 | AN16: 122887480695 | AO16: 127016253433 | AP16: 139011604932 | AQ16: 152040845787 | AR16: 161172642369 | AS16: 159378679498 | AT16: 97722288447 | AU16: 120989360950 | AV16: 150031537677 | AW16: 147739603288 | AX16: 148202432891 | AY16: 152669364944 | AZ16: 108322209217 | BA16: 161139219719 | BB16: 202956915270 | BC16: 159438788675 | BD16: 170977391735 | BE16: 157629418587 | BF16: 156235244643 | BG16: 193809016663 | BH16: 162064070219 | BI16: 155463444706 | BJ16: 157631834549 | BK16: 156213265219 | BL16: 134437579367
A17: 14 | B17: 2.Trả trước cho người bán ngắn hạn | C17: 5 | D17: 6330425378 | E17: 8646888491 | F17: 9301534244 | G17: 18808203504 | H17: 19752159173 | I17: 20584484794 | J17: 13954080202 | K17: 16174952449 | L17: 16056294580 | M17: 17236756406 | N17: 12406025016 | O17: 12423915823 | P17: 12572821244 | Q17: 12985734332 | R17: 18637216896 | S17: 19362255108 | T17: 34524039024 | U17: 34861611746 | V17: 34722306504 | W17: 35591679393 | X17: 39721501993 | Y17: 33128809245 | Z17: 31174041516 | AA17: 21879697062 | AB17: 20916211061 | AC17: 21954342423 | AD17: 18757049149 | AE17: 23651627792 | AF17: 22917215700 | AG17: 22524331312 | AH17: 23699255018 | AI17: 25626123009 | AJ17: 27607049863 | AK17: 35640431515 | AL17: 18752744712 | AM17: 20296401474 | AN17: 19316587120 | AO17: 17454753549 | AP17: 16813944743 | AQ17: 18608309535 | AR17: 18405763308 | AS17: 16327636020 | AT17: 15257741813 | AU17: 14294350015 | AV17: 10832801685 | AW17: 9551925778 | AX17: 10191021053 | AY17: 23997890529 | AZ17: 17386959101 | BA17: 22390625492 | BB17: 24711414335 | BC17: 29713189366 | BD17: 63705294804 | BE17: 67384127297 | BF17: 62294223986 | BG17: 80801800470 | BH17: 83665862400 | BI17: 77870421089 | BJ17: 63335376460 | BK17: 71180019646 | BL17: 77989815916
A18: 15 | B18: 3.Phải thu nội bộ ngắn hạn | C18: 5 | P18: 0 | Q18: 0 | R18: 0 | S18: 0 | T18: 0 | W18: 0 | X18: 0 | Y18: 0 | AA18: 0 | AG18: 0 | AH18: 0 | AI18: 0 | AJ18: 0 | AK18: 0 | AN18: 0 | AO18: 0 | AP18: 0 | AQ18: 0 | AR18: 0 | AS18: 0 | AT18: 0 | AU18: 0 | AV18: 0 | AW18: 0 | AX18: 0 | AY18: 0 | AZ18: 0 | BA18: 0 | BB18: 0 | BC18: 0 | BD18: 0 | BE18: 0 | BF18: 0 | BG18: 0 | BH18: 0 | BI18: 0 | BJ18: 0
A19: 16 | B19: 4.Phải thu theo tiến độ hợp đồng xây dựng | C19: 5 | P19: 0 | Q19: 0 | R19: 0 | S19: 0 | T19: 0 | W19: 0 | X19: 0 | Y19: 0 | AA19: 0 | AG19: 0 | AH19: 0 | AI19: 0 | AJ19: 0 | AK19: 0 | AN19: 0 | AO19: 0 | AP19: 0 | AQ19: 0 | AR19: 0 | AS19: 0 | AT19: 0 | AU19: 0 | AV19: 0 | AW19: 0 | AX19: 0 | AY19: 0 | AZ19: 0 | BA19: 0 | BB19: 0 | BC19: 0 | BD19: 0 | BE19: 0 | BF19: 0 | BG19: 0 | BH19: 0 | BI19: 0 | BJ19: 0
A20: 17 | B20: 5.Phải thu ngắn hạn khác | C20: 5 | D20: 4449916455 | E20: 4549916455 | F20: 4496627001 | G20: 4491760000 | H20: 4501116000 | I20: 340500000 | J20: 976197260 | K20: 530306849 | L20: 478115068 | M20: 1845669863 | N20: 3256342466 | O20: 1552462204 | P20: 4534466461 | Q20: 4523268516 | R20: 6015871256 | S20: 15769510073 | T20: 18309280789 | U20: 19499890710 | V20: 6535863406 | W20: 7591000392 | X20: 8940128830 | Y20: 10548965816 | Z20: 11965769995 | AA20: 1097240122 | AB20: 2560495408 | AC20: 2623024288 | AD20: 2742495834 | AE20: 8247003607 | AF20: 18069631982 | AG20: 36832436686 | AH20: 42711839716 | AI20: 44591918971 | AJ20: 14244184664 | AK20: 15945886911 | AL20: 20872038625 | AM20: 18750173864 | AN20: 46764622066 | AO20: 27943709260 | AP20: 27858493605 | AQ20: 29813780601 | AR20: 30122908774 | AS20: 58238993334 | AT20: 32233253798 | AU20: 32323992820 | AV20: 33056493468 | AW20: 33538634472 | AX20: 69594326344 | AY20: 39636792557 | AZ20: 18610706275 | BA20: 20015503421 | BB20: 8163190691 | BC20: 8309812149 | BD20: 8184293212 | BE20: 9742642764 | BF20: 9880722889 | BG20: 44051581104 | BH20: 13574048303 | BI20: 12569225200 | BJ20: 12601973422 | BK20: 31124828873 | BL20: 54356749996
A21: 18 | B21: 6.Dự phòng phải thu ngắn hạn khó đòi (*) | C21: 5 | P21: 0 | Q21: 0 | R21: 0 | S21: 0 | T21: 0 | W21: 0 | X21: 0 | Y21: 0 | AA21: -1743698927 | AB21: -1743698927 | AC21: -1743698927 | AD21: -1743698927 | AE21: -1743698927 | AF21: -1743698927 | AG21: -1743698927 | AH21: -1743698927 | AI21: 0 | AJ21: 0 | AK21: 0 | AM21: 0 | AN21: 0 | AO21: 0 | AP21: 0 | AQ21: 0 | AR21: 0 | AS21: 0 | AT21: 0 | AU21: 0 | AV21: 0 | AW21: 0 | AX21: 0 | AY21: 0 | AZ21: 0 | BA21: 0 | BB21: 0 | BC21: 0 | BD21: 0 | BE21: 0 | BF21: 0 | BG21: 0 | BH21: 0 | BI21: 0 | BJ21: 0 | BK21: -609095700 | BL21: -609095700
A22: 19 | B22: 7.Tài sản thiếu chờ xử lý | C22: 5 | O22: 0 | P22: 3711179054 | Q22: 3711179054 | R22: 3711179054 | S22: 3711179054 | T22: 3711179054 | U22: 3711179054 | V22: 3711179054 | W22: 3711179054 | X22: 3711179054 | Y22: 3711179054 | Z22: 3711179054 | AA22: 0 | AB22: -13447877629 | AC22: -13447877629 | AD22: -13447877629 | AE22: -13447877629 | AF22: -13447877629 | AG22: 0 | AH22: 0 | AI22: 0 | AJ22: 0 | AK22: 0 | AM22: 0 | AN22: -524609275 | AO22: -524609275 | AP22: 7901392144 | AQ22: 7901392144 | AR22: -524609275 | AS22: -524609275 | AT22: -524609275 | AU22: -524609275 | AV22: -524609275 | AW22: -524609275 | AX22: -524609275 | AY22: 0 | AZ22: 0 | BA22: 0 | BB22: 0 | BC22: 0 | BD22: 0 | BE22: 0 | BF22: 0 | BG22: 0 | BH22: 0 | BI22: 0 | BJ22: 0 | BK22: 177104044 | BL22: 1297018002
A23: 20 | B23: IV. Hàng tồn kho | C23: 5 | D23: 22640840422 | E23: 24415218988 | F23: 26498172124 | G23: 34682793625 | H23: 44709711264 | I23: 47275848380 | J23: 47653018372 | K23: 46032587439 | L23: 46148656772 | M23: 45809647414 | N23: 56906779913 | O23: 73486425075 | P23: 82706082474 | Q23: 90142332135 | R23: 106212278520 | S23: 129998785280 | T23: 163378971965 | U23: 185439599732 | V23: 195978830536 | W23: 195205377630 | X23: 187734490096 | Y23: 200852894094 | Z23: 219068154486 | AA23: 202471258527 | AB23: 214379170076 | AC23: 232092273214 | AD23: 237508877159 | AE23: 241821396518 | AF23: 247116136805 | AG23: 268484485479 | AH23: 275251336485 | AI23: 264624812102 | AJ23: 265818411834 | AK23: 273657995114 | AL23: 314192815161 | AM23: 344175758556 | AN23: 406821244018 | AO23: 413788449441 | AP23: 455747162045 | AQ23: 496057122616 | AR23: 541180364701 | AS23: 600190018005 | AT23: 619776297407 | AU23: 559053982584 | AV23: 549140904407 | AW23: 546574238545 | AX23: 588008826045 | AY23: 605821152798 | AZ23: 566809475589 | BA23: 483821147048 | BB23: 468355569440 | BC23: 522665513478 | BD23: 526499028418 | BE23: 543591846704 | BF23: 548599437580 | BG23: 548273459394 | BH23: 564202481203 | BI23: 551227150950 | BJ23: 550570669746 | BK23: 565466681637 | BL23: 533824376977
A24: 21 | B24: 1.Hàng tồn kho | C24: 5 | D24: 22640840422 | E24: 24415218988 | F24: 26498172124 | G24: 34682793625 | H24: 44709711264 | I24: 47275848380 | J24: 47653018372 | K24: 46032587439 | L24: 46148656772 | M24: 45809647414 | N24: 56906779913 | O24: 73486425075 | P24: 82706082474 | Q24: 90142332135 | R24: 106212278520 | S24: 129998785280 | T24: 163378971965 | U24: 185439599732 | V24: 195978830536 | W24: 195205377630 | X24: 187734490096 | Y24: 200852894094 | Z24: 219068154486 | AA24: 202471258527 | AB24: 214379170076 | AC24: 232092273214 | AD24: 237508877159 | AE24: 241821396518 | AF24: 247116136805 | AG24: 268484485479 | AH24: 275251336485 | AI24: 264624812102 | AJ24: 265818411834 | AK24: 273657995114 | AL24: 314192815161 | AM24: 344175758556 | AN24: 406821244018 | AO24: 413788449441 | AP24: 455747162045 | AQ24: 496057122616 | AR24: 541180364701 | AS24: 600190018005 | AT24: 619776297407 | AU24: 559053982584 | AV24: 549140904407 | AW24: 546574238545 | AX24: 588008826045 | AY24: 605821152798 | AZ24: 566809475589 | BA24: 483821147048 | BB24: 468355569440 | BC24: 522665513478 | BD24: 526499028418 | BE24: 543591846704 | BF24: 548599437580 | BG24: 548273459394 | BH24: 564202481203 | BI24: 551227150950 | BJ24: 550570669746 | BK24: 565466681637 | BL24: 533824376977
A25: 22 | B25: 2.Dự phòng giảm giá hàng tồn kho (*) | C25: 5 | P25: 0 | Q25: 0 | R25: 0 | S25: 0 | T25: 0 | W25: 0 | X25: 0 | Y25: 0 | AA25: 0 | AG25: 0 | AH25: 0 | AJ25: 0 | AK25: 0 | AN25: 0 | AO25: 0 | AP25: 0 | AQ25: 0 | AR25: 0 | AS25: 0 | AT25: 0 | AU25: 0 | AV25: 0 | AW25: 0 | AX25: 0 | AY25: 0 | AZ25: 0 | BA25: 0 | BB25: 0 | BC25: 0 | BD25: 0 | BE25: 0 | BF25: 0 | BG25: 0 | BH25: 0 | BI25: 0 | BJ25: 0
A26: 23 | B26: V. Tài sản sinh học ngắn hạn | C26: 5
A27: 24 | B27: 1.Súc vật nuôi lấy sản phẩm một lần ngắn hạn | C27: 5
A28: 25 | B28: 2.Cây trồng theo mùa vụ hoặc lấy sản phẩm một lần ngắn hạn | C28: 5
A29: 26 | B29: 3.Dự phòng tổn thất tài sản sinh học ngắn hạn (*) | C29: 5
A30: 27 | B30: VI. Tài sản ngắn hạn khác | C30: 5 | D30: 5314243398 | E30: 6080699504 | F30: 5675443442 | G30: 6125438674 | H30: 8404740511 | I30: 8494741311 | J30: 8916139914 | K30: 26710413192 | L30: 27399882401 | M30: 27226141662 | N30: 28879807729 | O30: 30557633632 | P30: 31389219783 | Q30: 32186724683 | R30: 33833811488 | S30: 36773892175 | T30: 40902724991 | U30: 43653531095 | V30: 44810563156 | W30: 45772154267 | X30: 48034022405 | Y30: 51470376546 | Z30: 55537722150 | AA30: 38182053249 | AB30: 38776985054 | AC30: 41075097228 | AD30: 45117370687 | AE30: 39657180033 | AF30: 43740601333 | AG30: 47103389737 | AH30: 50391945473 | AI30: 52095015441 | AJ30: 49205619205 | AK30: 51840480320 | AL30: 59036767363 | AM30: 64409368871 | AN30: 48329179570 | AO30: 52402682218 | AP30: 53638184536 | AQ30: 60097345927 | AR30: 64480604648 | AS30: 41973464763 | AT30: 46961151962 | AU30: 48551172726 | AV30: 56769861956 | AW30: 59919630029 | AX30: 32117157574 | AY30: 29084385847 | AZ30: 31458565079 | BA30: 32319903285 | BB30: 37507790105 | BC30: 46329177857 | BD30: 54840575232 | BE30: 64471140709 | BF30: 71635917962 | BG30: 42927415798 | BH30: 44075420678 | BI30: 43372545654 | BJ30: 41368771158 | BK30: 19538414742 | BL30: 21468440606
A31: 28 | B31: 1.Chi phí chờ phân bổ ngắn hạn | C31: 5 | D31: 113920351 | E31: 94216760 | F31: 80384419 | G31: 60147078 | H31: 281847184 | I31: 255164290 | J31: 228481396 | K31: 201798502 | L31: 252235061 | M31: 260230306 | N31: 888993241 | O31: 907518876 | P31: 940252890 | Q31: 1040629462 | R31: 1046446719 | S31: 1010849671 | T31: 1471987794 | U31: 2225397509 | V31: 2354562379 | W31: 2407816714 | X31: 3022705182 | Y31: 2886832646 | Z31: 3574188446 | AA31: 2848864662 | AB31: 2433524948 | AC31: 2949595697 | AD31: 2636870885 | AE31: 2566632714 | AF31: 2509161957 | AG31: 2767731909 | AH31: 3160400459 | AI31: 3221096592 | AJ31: 3722160941 | AK31: 4095876199 | AL31: 5294410252 | AM31: 5769288291 | AN31: 6276274640 | AO31: 8206749833 | AP31: 7285401121 | AQ31: 8306063236 | AR31: 7856773292 | AS31: 9119226098 | AT31: 10668355095 | AU31: 10679688406 | AV31: 11891411206 | AW31: 10950384630 | AX31: 10029655608 | AY31: 8392710436 | AZ31: 8670624950 | BA31: 9360600777 | BB31: 8963443599 | BC31: 8040678677 | BD31: 6574180345 | BE31: 12024899748 | BF31: 13100177953 | BG31: 13938259781 | BH31: 11177477784 | BI31: 9268450110 | BJ31: 6953960350 | BK31: 6846596238 | BL31: 6232956370
A32: 29 | B32: 2.Thuế GTGT được khấu trừ | C32: 5 | D32: 4945420208 | E32: 5731579905 | F32: 5595059023 | G32: 6047726478 | H32: 8122893327 | I32: 8239577021 | J32: 8687658518 | K32: 26508614690 | L32: 27147647340 | M32: 26965911356 | N32: 27990814488 | O32: 29650114756 | P32: 30448966893 | Q32: 31146095221 | R32: 32787364769 | S32: 35763042504 | T32: 39429487284 | U32: 41426883673 | V32: 42456000777 | W32: 43364337553 | X32: 45011317223 | Y32: 48583543900 | Z32: 51963533704 | AA32: 35333188587 | AB32: 36343460106 | AC32: 38125501531 | AD32: 42480499802 | AE32: 37090547319 | AF32: 41231439376 | AG32: 44335657828 | AH32: 47231545014 | AI32: 48873918849 | AJ32: 45483458264 | AK32: 47744604121 | AL32: 53742357111 | AM32: 58640080580 | AN32: 42052904930 | AO32: 44107343223 | AP32: 46297685706 | AQ32: 51762654946 | AR32: 56579510013 | AS32: 32789088899 | AT32: 36250538837 | AU32: 37779613794 | AV32: 44829865745 | AW32: 48921405825 | AX32: 22042451541 | AY32: 20691675411 | AZ32: 22787940129 | BA32: 22955432475 | BB32: 28544346506 | BC32: 38288499180 | BD32: 48266394887 | BE32: 52446240961 | BF32: 58535740009 | BG32: 28989156017 | BH32: 32897942894 | BI32: 34104095544 | BJ32: 34414810808 | BK32: 12691818504 | BL32: 14900314879
A33: 30 | B33: 3.Thuế và các khoản khác phải thu Nhà nước | C33: 5 | D33: 254902839 | E33: 254902839 | G33: 17565118 | P33: 0 | Q33: 0 | R33: 0 | S33: 0 | T33: 1249913 | U33: 1249913 | W33: 0 | X33: 0 | Y33: 0 | AA33: 0 | AG33: 0 | AH33: 0 | AJ33: 0 | AK33: 0 | AM33: 0 | AN33: 0 | AO33: 88589162 | AP33: 55097709 | AQ33: 28627745 | AR33: 44321343 | AS33: 65149766 | AT33: 42258030 | AU33: 91870526 | AV33: 48585005 | AW33: 47839574 | AX33: 45050425 | AY33: 0 | AZ33: 0 | BA33: 3870033 | BB33: 0 | BC33: 0 | BD33: 0 | BE33: 0 | BF33: 0 | BG33: 0 | BH33: 0 | BI33: 0 | BJ33: 0 | BL33: 335169357
A34: 31 | B34: 4.Giao dịch mua bán lại trái phiếu Chính phủ | C34: 5 | P34: 0 | Q34: 0 | R34: 0 | S34: 0 | T34: 0 | W34: 0 | X34: 0 | Y34: 0 | AA34: 0 | AG34: 0 | AH34: 0 | AJ34: 0 | AK34: 0 | AM34: 0 | AN34: 0 | AO34: 0 | AP34: 0 | AQ34: 0 | AR34: 0 | AS34: 0 | AT34: 0 | AU34: 0 | AV34: 0 | AW34: 0 | AX34: 0 | AY34: 0 | AZ34: 0 | BA34: 0 | BB34: 0 | BC34: 0 | BD34: 0 | BE34: 0 | BF34: 0 | BG34: 0 | BH34: 0 | BI34: 0 | BJ34: 0
A35: 32 | B35: 5.Tài sản ngắn hạn khác | C35: 5 | D35: 0 | E35: 0 | F35: 0 | G35: 0 | H35: 0 | I35: 0 | J35: 0 | K35: 0 | L35: 0 | M35: 0 | N35: 0 | O35: 0 | P35: 0 | Q35: 0 | R35: 0 | S35: 0 | T35: 0 | W35: 0 | X35: 0 | Y35: 0 | AA35: 0 | AG35: 0 | AH35: 0 | AJ35: 0 | AK35: 0 | AM35: 0 | AN35: 0 | AO35: 0 | AP35: 0 | AQ35: 0 | AR35: 0 | AS35: 0 | AT35: 0 | AU35: 0 | AV35: 0 | AW35: 0 | AX35: 0 | AY35: 0 | AZ35: 0 | BA35: 0 | BB35: 0 | BC35: 0 | BD35: 0 | BE35: 0 | BF35: 0 | BG35: 0 | BH35: 0 | BI35: 0 | BJ35: 0
A36: 33 | B36: B-TÀI SẢN DÀI HẠN | C36: 5 | D36: 86880633442 | E36: 94747583376 | F36: 96067304286 | G36: 96848533626 | H36: 101230167312 | I36: 102383852541 | J36: 114536712032 | K36: 291833091169 | L36: 294902635908 | M36: 293648092565 | N36: 295080352755 | O36: 298192814164 | P36: 303264863543 | Q36: 303407795286 | R36: 301700774855 | S36: 308774390060 | T36: 316298750510 | U36: 323784583220 | V36: 329223426456 | W36: 334959181760 | X36: 349795170793 | Y36: 365984624129 | Z36: 378041902934 | AA36: 203608355507 | AB36: 208231581626 | AC36: 210978078121 | AD36: 216766563234 | AE36: 221271328748 | AF36: 239086746684 | AG36: 241129920093 | AH36: 246491575279 | AI36: 248549355566 | AJ36: 249140138170 | AK36: 260911120719 | AL36: 268719490169 | AM36: 275488564192 | AN36: 274621596882 | AO36: 272305827313 | AP36: 271200317966 | AQ36: 270901849246 | AR36: 269904363409 | AS36: 270744122708 | AT36: 268776242104 | AU36: 274331457085 | AV36: 273131457642 | AW36: 272293558516 | AX36: 273153529742 | AY36: 285939000851 | AZ36: 289379194755 | BA36: 285515570351 | BB36: 287407502163 | BC36: 294777015341 | BD36: 299380289162 | BE36: 300166972168 | BF36: 296753996838 | BG36: 296192973827 | BH36: 304334630215 | BI36: 316482947135 | BJ36: 315796830828 | BK36: 320800563599 | BL36: 317415705891
A37: 34 | B37: I.Các khoản phải thu dài hạn | C37: 5 | D37: 0 | E37: 0 | F37: 0 | G37: 0 | H37: 0 | I37: 0 | J37: 0 | K37: 0 | L37: 0 | M37: 0 | N37: 0 | O37: 0 | P37: 0 | Q37: 0 | R37: 0 | S37: 0 | T37: 0 | W37: 0 | X37: 0 | Y37: 0 | AA37: 0 | AG37: 0 | AH37: 0 | AJ37: 0 | AK37: 0 | AN37: 0 | AO37: 0 | AP37: 0 | AQ37: 0 | AR37: 0 | AS37: 0 | AT37: 0 | AU37: 0 | AV37: 0 | AW37: 0 | AX37: 0 | AY37: 5600000000 | AZ37: 5600000000 | BA37: 5600000000 | BB37: 5600000000 | BC37: 5600000000 | BD37: 5600000000 | BE37: 5600000000 | BF37: 5600000000 | BG37: 5600000000 | BH37: 5600000000 | BI37: 5600000000 | BJ37: 5600000000 | BK37: 5600000000 | BL37: 5315314211
A38: 35 | B38: 1.Phải thu dài hạn của khách hàng | C38: 5 | P38: 0 | Q38: 0 | R38: 0 | S38: 0 | T38: 0 | W38: 0 | X38: 0 | Y38: 0 | AA38: 0 | AG38: 0 | AH38: 0 | AJ38: 0 | AK38: 0 | AN38: 0 | AO38: 0 | AP38: 0 | AQ38: 0 | AR38: 0 | AS38: 0 | AT38: 0 | AU38: 0 | AV38: 0 | AW38: 0 | AX38: 0 | AY38: 0 | AZ38: 0 | BA38: 0 | BB38: 0 | BC38: 0 | BD38: 0 | BE38: 0 | BF38: 0 | BG38: 0 | BH38: 0 | BI38: 0 | BJ38: 0
A39: 36 | B39: 2.Trả trước cho người bán dài hạn | C39: 5 | P39: 0 | Q39: 0 | R39: 0 | S39: 0 | T39: 0 | W39: 0 | X39: 0 | Y39: 0 | AA39: 0 | AG39: 0 | AH39: 0 | AJ39: 0 | AK39: 0 | AN39: 0 | AO39: 0 | AP39: 0 | AQ39: 0 | AR39: 0 | AS39: 0 | AT39: 0 | AU39: 0 | AV39: 0 | AW39: 0 | AX39: 0 | AY39: 0 | AZ39: 0 | BA39: 0 | BB39: 0 | BC39: 0 | BD39: 0 | BE39: 0 | BF39: 0 | BG39: 0 | BH39: 0 | BI39: 0 | BJ39: 0
A40: 37 | B40: 3.Vốn kinh doanh ở đơn vị trực thuộc | C40: 5 | D40: 0 | E40: 0 | F40: 0 | G40: 0 | H40: 0 | I40: 0 | J40: 0 | K40: 0 | L40: 0 | M40: 0 | N40: 0 | O40: 0 | P40: 0 | Q40: 0 | R40: 0 | S40: 0 | T40: 0 | W40: 0 | X40: 0 | Y40: 0 | AA40: 0 | AG40: 0 | AH40: 0 | AJ40: 0 | AK40: 0 | AN40: 0 | AO40: 0 | AP40: 0 | AQ40: 0 | AR40: 0 | AS40: 0 | AT40: 0 | AU40: 0 | AV40: 0 | AW40: 0 | AX40: 0 | AY40: 0 | AZ40: 0 | BA40: 0 | BB40: 0 | BC40: 0 | BD40: 0 | BE40: 0 | BF40: 0 | BG40: 0 | BH40: 0 | BI40: 0 | BJ40: 0
A41: 38 | B41: 4.Phải thu nội bộ dài hạn | C41: 5 | D41: 0 | E41: 0 | F41: 0 | G41: 0 | H41: 0 | I41: 0 | J41: 0 | K41: 0 | L41: 0 | M41: 0 | N41: 0 | O41: 0 | P41: 0 | Q41: 0 | R41: 0 | S41: 0 | T41: 0 | W41: 0 | X41: 0 | Y41: 0 | AA41: 0 | AG41: 0 | AH41: 0 | AJ41: 0 | AK41: 0 | AN41: 0 | AO41: 0 | AP41: 0 | AQ41: 0 | AR41: 0 | AS41: 0 | AT41: 0 | AU41: 0 | AV41: 0 | AW41: 0 | AX41: 0 | AY41: 0 | AZ41: 0 | BA41: 0 | BB41: 0 | BC41: 0 | BD41: 0 | BE41: 0 | BF41: 0 | BG41: 0 | BH41: 0 | BI41: 0 | BJ41: 0
A42: 39 | B42: 5.Phải thu dài hạn khác | C42: 5 | D42: 0 | E42: 0 | P42: 0 | Q42: 0 | R42: 0 | S42: 0 | T42: 0 | W42: 0 | X42: 0 | Y42: 0 | AA42: 0 | AG42: 0 | AH42: 0 | AJ42: 0 | AK42: 0 | AN42: 0 | AO42: 0 | AP42: 0 | AQ42: 0 | AR42: 0 | AS42: 0 | AT42: 0 | AU42: 0 | AV42: 0 | AW42: 0 | AX42: 0 | AY42: 5600000000 | AZ42: 5600000000 | BA42: 5600000000 | BB42: 5600000000 | BC42: 5600000000 | BD42: 5600000000 | BE42: 5600000000 | BF42: 5600000000 | BG42: 5600000000 | BH42: 5600000000 | BI42: 5600000000 | BJ42: 5600000000 | BK42: 5600000000 | BL42: 5315314211
A43: 40 | B43: 6.Dự phòng phải thu dài hạn khó đòi (*) | C43: 5 | D43: 0 | E43: 0 | F43: 0 | G43: 0 | H43: 0 | I43: 0 | J43: 0 | K43: 0 | L43: 0 | M43: 0 | N43: 0 | O43: 0 | P43: 0 | Q43: 0 | R43: 0 | S43: 0 | T43: 0 | W43: 0 | X43: 0 | Y43: 0 | AA43: 0 | AG43: 0 | AH43: 0 | AJ43: 0 | AK43: 0 | AN43: 0 | AO43: 0 | AP43: 0 | AQ43: 0 | AR43: 0 | AS43: 0 | AT43: 0 | AU43: 0 | AV43: 0 | AW43: 0 | AX43: 0 | AY43: 0 | AZ43: 0 | BA43: 0 | BB43: 0 | BC43: 0 | BD43: 0 | BE43: 0 | BF43: 0 | BG43: 0 | BH43: 0 | BI43: 0 | BJ43: 0
A44: 41 | B44: II.Tài sản cố định | C44: 5 | D44: 23619009901 | E44: 25016088100 | F44: 49763948248 | G44: 49597223876 | H44: 50829042712 | I44: 50629108185 | J44: 54890399597 | K44: 279071774641 | L44: 277032713430 | M44: 275778170087 | N44: 274130750226 | O44: 273205262317 | P44: 272377973790 | Q44: 270848160447 | R44: 268942944958 | S44: 267946903929 | T44: 267871693079 | U44: 267032884293 | V44: 269059796516 | W44: 293069402978 | X44: 299352041110 | Y44: 300083341706 | Z44: 314989042853 | AA44: 173057943349 | AB44: 172057873371 | AC44: 181414144601 | AD44: 185247648433 | AE44: 185119661882 | AF44: 183550835427 | AG44: 186791426572 | AH44: 186554681855 | AI44: 186140017498 | AJ44: 199458548244 | AK44: 197701621914 | AL44: 200439002848 | AM44: 200719408974 | AN44: 198013903445 | AO44: 195010544683 | AP44: 225730823955 | AQ44: 226001461052 | AR44: 224673388970 | AS44: 221428232280 | AT44: 219409735799 | AU44: 226228538916 | AV44: 223962123590 | AW44: 223016683107 | AX44: 238599188942 | AY44: 236902591180 | AZ44: 233135637012 | BA44: 239769028633 | BB44: 244837616747 | BC44: 241369190811 | BD44: 237349552865 | BE44: 233717444711 | BF44: 229848858132 | BG44: 248058151289 | BH44: 245902729429 | BI44: 244514286341 | BJ44: 247438859420 | BK44: 243859258508 | BL44: 243650467528
A45: 42 | B45: 1.Tài sản cố định hữu hình | C45: 5 | D45: 5012175397 | E45: 6450972956 | F45: 31240552464 | G45: 31115547451 | H45: 32389085647 | I45: 32230870480 | J45: 36533881252 | K45: 260026108687 | L45: 258041154411 | M45: 256840718004 | N45: 255247405079 | O45: 254376024104 | P45: 253602842513 | Q45: 252127136105 | R45: 250276027552 | S45: 249334093459 | T45: 249227840376 | U45: 248450879361 | V45: 250539639353 | W45: 274611093583 | X45: 279416322079 | Y45: 280229879304 | Z45: 295217837077 | AA45: 171016283429 | AB45: 170056750719 | AC45: 179334759218 | AD45: 183268200317 | AE45: 183240151035 | AF45: 181704121014 | AG45: 184977508596 | AH45: 184719690314 | AI45: 184338819984 | AJ45: 197691144757 | AK45: 195968012455 | AL45: 198739187416 | AM45: 199053387570 | AN45: 196381676069 | AO45: 193412111334 | AP45: 223734884594 | AQ45: 224051296275 | AR45: 222768998777 | AS45: 219569616674 | AT45: 217596894777 | AU45: 224461472477 | AV45: 222240831735 | AW45: 221341165837 | AX45: 211514900800 | AY45: 209868609863 | AZ45: 206695783278 | BA45: 213923302488 | BB45: 219098407403 | BC45: 216237653798 | BD45: 212825688182 | BE45: 209801252360 | BF45: 206540338107 | BG45: 225357303593 | BH45: 221869598924 | BI45: 221127752277 | BJ45: 224698921799 | BK45: 221765917329 | BL45: 222439215846
A46: 43 | B46: Nguyên giá TSCĐ HH | C46: 5 | D46: 5353388782 | E46: 6876588782 | F46: 31771457543 | G46: 31843457543 | H46: 33336565043 | I46: 33399597043 | J46: 37978137919 | K46: 263570241170 | L46: 263683741170 | M46: 264603933170 | N46: 265129717020 | O46: 266402126632 | P46: 267785616064 | Q46: 268472854155 | R46: 268718067155 | S46: 269962587155 | T46: 272070177155 | U46: 273525793231 | V46: 277899672525 | W46: 304387081496 | X46: 311617096499 | Y46: 314922878251 | Z46: 332557727634 | AA46: 198950740617 | AB46: 199952126517 | AC46: 211350395220 | AD46: 217541022153 | AE46: 219918087838 | AF46: 220804558523 | AG46: 226533976537 | AH46: 228841919294 | AI46: 231167379866 | AJ46: 247327983466 | AK46: 248447356880 | AL46: 254065544433 | AM46: 257373867714 | AN46: 257666841694 | AO46: 257666841694 | AP46: 290954799860 | AQ46: 294406461356 | AR46: 296317113552 | AS46: 296312396885 | AT46: 297568396885 | AU46: 307504902865 | AV46: 308673199161 | AW46: 311019813374 | AX46: 288613480028 | AY46: 290150220028 | AZ46: 290186420028 | BA46: 300624510263 | BB46: 309208121569 | BC46: 309236016561 | BD46: 309308233601 | BE46: 309763593785 | BF46: 309740464757 | BG46: 331642753074 | BH46: 331956337304 | BI46: 334828750908 | BJ46: 342175274548 | BK46: 343037991979 | BL46: 346257196159
A47: 44 | B47: Giá trị hao mòn luỹ kế TSCĐ HH(*) | C47: 5 | D47: -341213385 | E47: -425615826 | F47: -530905079 | G47: -727910092 | H47: -947479396 | I47: -1168726563 | J47: -1444256667 | K47: -3544132483 | L47: -5642586759 | M47: -7763215166 | N47: -9882311941 | O47: -12026102528 | P47: -14182773551 | Q47: -16345718050 | R47: -18442039603 | S47: -20628493696 | T47: -22842336779 | U47: -25074913870 | V47: -27360033172 | W47: -29775987913 | X47: -32200774420 | Y47: -34692998947 | Z47: -37339890557 | AA47: -27934457188 | AB47: -29895375798 | AC47: -32015636002 | AD47: -34272821836 | AE47: -36677936803 | AF47: -39100437509 | AG47: -41556467941 | AH47: -44122228980 | AI47: -46828559882 | AJ47: -49636838709 | AK47: -52479344425 | AL47: -55326357017 | AM47: -58320480144 | AN47: -61285165625 | AO47: -64254730360 | AP47: -67219915266 | AQ47: -70355165081 | AR47: -73548114775 | AS47: -76742780211 | AT47: -79971502108 | AU47: -83043430388 | AV47: -86432367426 | AW47: -89678647537 | AX47: -77098579228 | AY47: -80281610165 | AZ47: -83490636750 | BA47: -86701207775 | BB47: -90109714166 | BC47: -92998362763 | BD47: -96482545419 | BE47: -99962341425 | BF47: -103200126650 | BG47: -106285449481 | BH47: -110086738380 | BI47: -113700998631 | BJ47: -117476352749 | BK47: -121272074650 | BL47: -123817980313
A48: 45 | B48: 2. Tài sản cố định thuê tài chính | C48: 5 | P48: 0 | Q48: 0 | R48: 0 | S48: 0 | T48: 0 | W48: 0 | X48: 0 | Y48: 0 | AA48: 0 | AG48: 0 | AH48: 0 | AJ48: 0 | AK48: 0 | AM48: 0 | AN48: 0 | AO48: 0 | AP48: 0 | AQ48: 0 | AR48: 0 | AS48: 0 | AT48: 0 | AU48: 0 | AV48: 0 | AW48: 0 | AX48: 25454545455 | AY48: 24920890315 | AZ48: 24387235175 | BA48: 23853580028 | BB48: 23319924886 | BC48: 22786269743 | BD48: 22252614599 | BE48: 21718959455 | BF48: 21185304314 | BG48: 20651649171 | BH48: 20117994030 | BI48: 19584338888 | BJ48: 19050683744 | BK48: 18517028601 | BL48: 17684886028
A49: 46 | B49: Nguyên giá TSCĐ thuê tài chính | C49: 5 | P49: 0 | Q49: 0 | R49: 0 | S49: 0 | T49: 0 | W49: 0 | X49: 0 | Y49: 0 | AA49: 0 | AG49: 0 | AH49: 0 | AJ49: 0 | AK49: 0 | AM49: 0 | AN49: 0 | AO49: 0 | AP49: 0 | AQ49: 0 | AR49: 0 | AS49: 0 | AT49: 0 | AU49: 0 | AV49: 0 | AW49: 0 | AX49: 25454545455 | AY49: 25454545455 | AZ49: 25454545455 | BA49: 25454545455 | BB49: 25454545455 | BC49: 25454545455 | BD49: 25454545455 | BE49: 25454545455 | BF49: 25454545455 | BG49: 25454545455 | BH49: 25454545455 | BI49: 25454545455 | BJ49: 25454545455 | BK49: 25454545455 | BL49: 24160519140
A50: 47 | B50: Giá trị hao mòn luỹ kế TSCĐ thuê tài chính | C50: 5 | D50: 0 | E50: 0 | F50: 0 | G50: 0 | H50: 0 | I50: 0 | J50: 0 | K50: 0 | L50: 0 | M50: 0 | N50: 0 | O50: 0 | P50: 0 | Q50: 0 | R50: 0 | S50: 0 | T50: 0 | W50: 0 | X50: 0 | Y50: 0 | AA50: 0 | AG50: 0 | AH50: 0 | AJ50: 0 | AK50: 0 | AM50: 0 | AN50: 0 | AO50: 0 | AP50: 0 | AQ50: 0 | AR50: 0 | AS50: 0 | AT50: 0 | AU50: 0 | AV50: 0 | AW50: 0 | AX50: 0 | AY50: -533655140 | AZ50: -1067310280 | BA50: -1600965427 | BB50: -2134620569 | BC50: -2668275712 | BD50: -3201930856 | BE50: -3735586000 | BF50: -4269241141 | BG50: -4802896284 | BH50: -5336551425 | BI50: -5870206567 | BJ50: -6403861711 | BK50: -6937516854 | BL50: -6475633112
A51: 48 | B51: 3. Tài sản cố định vô hình | C51: 5 | D51: 18606834504 | E51: 18565115144 | F51: 18523395784 | G51: 18481676425 | H51: 18439957065 | I51: 18398237705 | J51: 18356518345 | K51: 19045665954 | L51: 18991559019 | M51: 18937452083 | N51: 18883345147 | O51: 18829238213 | P51: 18775131277 | Q51: 18721024342 | R51: 18666917406 | S51: 18612810470 | T51: 18643852703 | U51: 18582004932 | V51: 18520157163 | W51: 18458309395 | X51: 19935719031 | Y51: 19853462402 | Z51: 19771205776 | AA51: 2041659920 | AB51: 2001122652 | AC51: 2079385383 | AD51: 1979448116 | AE51: 1879510847 | AF51: 1846714413 | AG51: 1813917976 | AH51: 1834991541 | AI51: 1801197514 | AJ51: 1767403487 | AK51: 1733609459 | AL51: 1699815432 | AM51: 1666021404 | AN51: 1632227376 | AO51: 1598433349 | AP51: 1995939361 | AQ51: 1950164777 | AR51: 1904390193 | AS51: 1858615606 | AT51: 1812841022 | AU51: 1767066439 | AV51: 1721291855 | AW51: 1675517270 | AX51: 1629742687 | AY51: 2113091002 | AZ51: 2052618559 | BA51: 1992146117 | BB51: 2419284458 | BC51: 2345267270 | BD51: 2271250084 | BE51: 2197232896 | BF51: 2123215711 | BG51: 2049198525 | BH51: 3915136475 | BI51: 3802195176 | BJ51: 3689253877 | BK51: 3576312578 | BL51: 3526365654
A52: 49 | B52: Nguyên giá TSCĐ vô hình | C52: 5 | D52: 24061372141 | E52: 24061372141 | F52: 24061372141 | G52: 24061372141 | H52: 24061372141 | I52: 24061372141 | J52: 24061372141 | K52: 24804626686 | L52: 24804626686 | M52: 24804626686 | N52: 24804626686 | O52: 24804626686 | P52: 24804626686 | Q52: 24804626686 | R52: 24804626686 | S52: 24804626686 | T52: 24897516686 | U52: 24897516686 | V52: 24897516686 | W52: 24897516686 | X52: 26457182951 | Y52: 26457182951 | Z52: 26457182951 | AA52: 2473365060 | AB52: 2473365060 | AC52: 2592165060 | AD52: 2592165060 | AE52: 2592165060 | AF52: 2592165060 | AG52: 2592165060 | AH52: 2646035060 | AI52: 2646035060 | AJ52: 2646035060 | AK52: 2646035060 | AL52: 2646035060 | AM52: 2646035060 | AN52: 2646035060 | AO52: 2646035060 | AP52: 3077335099 | AQ52: 3077335099 | AR52: 3077335099 | AS52: 3077335099 | AT52: 3077335099 | AU52: 3077335099 | AV52: 3077335099 | AW52: 3077335099 | AX52: 3077335099 | AY52: 3606457998 | AZ52: 3606457998 | BA52: 3606457998 | BB52: 4094068781 | BC52: 4094068781 | BD52: 4094068781 | BE52: 4094068781 | BF52: 4094068781 | BG52: 4094068781 | BH52: 6032562739 | BI52: 6032562739 | BJ52: 6032562739 | BK52: 6032562739 | BL52: 6032562739
A53: 50 | B53: Giá trị hao mòn luỹ kế TSCĐ vô hình(*) | C53: 5 | D53: -5454537637 | E53: -5496256997 | F53: -5537976357 | G53: -5579695716 | H53: -5621415076 | I53: -5663134436 | J53: -5704853796 | K53: -5758960732 | L53: -5813067667 | M53: -5867174603 | N53: -5921281539 | O53: -5975388473 | P53: -6029495409 | Q53: -6083602344 | R53: -6137709280 | S53: -6191816216 | T53: -6253663983 | U53: -6315511754 | V53: -6377359523 | W53: -6439207291 | X53: -6521463920 | Y53: -6603720549 | Z53: -6685977175 | AA53: -431705140 | AB53: -472242408 | AC53: -512779677 | AD53: -612716944 | AE53: -712654213 | AF53: -745450647 | AG53: -778247084 | AH53: -811043519 | AI53: -844837546 | AJ53: -878631573 | AK53: -912425601 | AL53: -946219628 | AM53: -980013656 | AN53: -1013807684 | AO53: -1047601711 | AP53: -1081395738 | AQ53: -1127170322 | AR53: -1172944906 | AS53: -1218719493 | AT53: -1264494077 | AU53: -1310268660 | AV53: -1356043244 | AW53: -1401817829 | AX53: -1447592412 | AY53: -1493366996 | AZ53: -1553839439 | BA53: -1614311881 | BB53: -1674784323 | BC53: -1748801511 | BD53: -1822818697 | BE53: -1896835885 | BF53: -1970853070 | BG53: -2044870256 | BH53: -2117426264 | BI53: -2230367563 | BJ53: -2343308862 | BK53: -2456250161 | BL53: -2506197085
A54: 51 | B54: III.Tài sản sinh học dài hạn | C54: 5
A55: 52 | B55: 1.Súc vật nuôi cho sản phẩm định kỳ | C55: 5
A56: 53 | B56: a)Súc vật nuôi cho sản phẩm định kỳ chưa đến giai đoạn trưởng thành | C56: 5
A57: 54 | B57: b)Súc vật nuôi cho sản phẩm định kỳ đến giai đoạn trưởng thành | C57: 5
A58: 55 | B58: Nguyên giá | C58: 5
A59: 56 | B59: Giá trị khấu hao lũy kế (*) | C59: 5
A60: 57 | B60: 2.Súc vật nuôi lấy sản phẩm một lần dài hạn | C60: 5
A61: 58 | B61: 3.Cây trồng theo mùa vụ hoặc lấy sản phẩm một lần dài hạn | C61: 5
A62: 59 | B62: 4.Dự phòng tổn thất tài sản sinh học dài hạn | C62: 5
A63: 60 | B63: IV. Bất động sản đầu tư | C63: 5 | P63: 0 | Q63: 0 | R63: 0 | S63: 0 | T63: 0 | W63: 0 | X63: 0 | Y63: 0 | AA63: 0 | AG63: 0 | AH63: 0 | AJ63: 0 | AK63: 0 | AN63: 0 | AO63: 0 | AP63: 0 | AQ63: 0 | AR63: 0 | AS63: 0 | AT63: 0 | AU63: 0 | AV63: 0 | AW63: 0 | AX63: 0 | AY63: 0 | AZ63: 0 | BA63: 0 | BB63: 0 | BC63: 0 | BD63: 0 | BE63: 0 | BF63: 0 | BG63: 0 | BH63: 0 | BI63: 0 | BJ63: 0
A64: 61 | B64: Nguyên giá bất động sản đầu tư | C64: 5 | P64: 0 | Q64: 0 | R64: 0 | S64: 0 | T64: 0 | W64: 0 | X64: 0 | Y64: 0 | AA64: 0 | AG64: 0 | AH64: 0 | AJ64: 0 | AK64: 0 | AN64: 0 | AO64: 0 | AP64: 0 | AQ64: 0 | AR64: 0 | AS64: 0 | AT64: 0 | AU64: 0 | AV64: 0 | AW64: 0 | AX64: 0 | AY64: 0 | AZ64: 0 | BA64: 0 | BB64: 0 | BC64: 0 | BD64: 0 | BE64: 0 | BF64: 0 | BG64: 0 | BH64: 0 | BI64: 0 | BJ64: 0
A65: 62 | B65: Giá trị hao mòn luỹ kế BĐSĐT(*) | C65: 5 | P65: 0 | Q65: 0 | R65: 0 | S65: 0 | T65: 0 | W65: 0 | X65: 0 | Y65: 0 | AA65: 0 | AG65: 0 | AH65: 0 | AJ65: 0 | AK65: 0 | AN65: 0 | AO65: 0 | AP65: 0 | AQ65: 0 | AR65: 0 | AS65: 0 | AT65: 0 | AU65: 0 | AV65: 0 | AW65: 0 | AX65: 0 | AY65: 0 | AZ65: 0 | BA65: 0 | BB65: 0 | BC65: 0 | BD65: 0 | BE65: 0 | BF65: 0 | BG65: 0 | BH65: 0 | BI65: 0 | BJ65: 0
A66: 63 | B66: V.Tài sản dở dang dài hạn | C66: 5 | D66: 61751961263 | E66: 68221832998 | F66: 44793693760 | G66: 45741647472 | H66: 48891462322 | I66: 50245082078 | J66: 58136650157 | K66: 11251654250 | L66: 16360260200 | M66: 16360260200 | N66: 20131868795 | O66: 24169818113 | P66: 30194961209 | Q66: 31930608890 | R66: 32191706543 | S66: 40090979735 | T66: 47026331183 | U66: 54919027899 | V66: 58371749132 | W66: 39889442104 | X66: 48178201294 | Y66: 62098571186 | Z66: 59494515240 | AA66: 26659764617 | AB66: 32447867606 | AC66: 25783380098 | AD66: 27949001939 | AE66: 32782480397 | AF66: 52004302806 | AG66: 50723798252 | AH66: 56309319260 | AI66: 58915049461 | AJ66: 46377188834 | AK66: 60040058006 | AL66: 65105287777 | AM66: 70079611431 | AN66: 72052358400 | AO66: 72977509919 | AP66: 40125847239 | AQ66: 39227080324 | AR66: 39862871198 | AS66: 44058539845 | AT66: 43896047774 | AU66: 41656644401 | AV66: 42945632903 | AW66: 43281195517 | AX66: 28334087272 | AY66: 36580186980 | AZ66: 46014474364 | BA66: 32023614794 | BB66: 27191404987 | BC66: 38355899298 | BD66: 47426115769 | BE66: 51797910397 | BF66: 52765546898 | BG66: 34461951167 | BH66: 44577925963 | BI66: 57717770751 | BJ66: 54221172817 | BK66: 63080533813 | BL66: 61387421408
A67: 64 | B67: 1.Chi phí sản xuất, kinh doanh dở dang dài hạn | C67: 5 | P67: 0 | Q67: 0 | R67: 0 | S67: 0 | T67: 0 | W67: 0 | X67: 0 | Y67: 0 | AA67: 0 | AG67: 0 | AH67: 0 | AJ67: 0 | AK67: 0 | AL67: 0 | AM67: 0 | AN67: 0 | AO67: 0 | AP67: 0 | AQ67: 0 | AR67: 0 | AS67: 0 | AT67: 0 | AU67: 0 | AV67: 0 | AW67: 0 | AX67: 0 | AY67: 0 | AZ67: 0 | BA67: 0 | BB67: 0 | BC67: 0 | BD67: 0 | BE67: 0 | BF67: 0 | BG67: 0 | BH67: 0 | BI67: 0 | BJ67: 0 | BK67: 0
A68: 65 | B68: 2.Chi phí xây dựng cơ bản dở dang | C68: 5 | D68: 61751961263 | E68: 68221832998 | F68: 44793693760 | G68: 45741647472 | H68: 48891462322 | I68: 50245082078 | J68: 58136650157 | K68: 11251654250 | L68: 16360260200 | M68: 16360260200 | N68: 20131868795 | O68: 24169818113 | P68: 30194961209 | Q68: 31930608890 | R68: 32191706543 | S68: 40090979735 | T68: 47026331183 | U68: 54919027899 | V68: 58371749132 | W68: 39889442104 | X68: 48178201294 | Y68: 62098571186 | Z68: 59494515240 | AA68: 26659764617 | AB68: 32447867606 | AC68: 25783380098 | AD68: 27949001939 | AE68: 32782480397 | AF68: 52004302806 | AG68: 50723798252 | AH68: 56309319260 | AI68: 58915049461 | AJ68: 46377188834 | AK68: 60040058006 | AL68: 65105287777 | AM68: 70079611431 | AN68: 72052358400 | AO68: 72977509919 | AP68: 40125847239 | AQ68: 39227080324 | AR68: 39862871198 | AS68: 44058539845 | AT68: 43896047774 | AU68: 41656644401 | AV68: 42945632903 | AW68: 43281195517 | AX68: 28334087272 | AY68: 36580186980 | AZ68: 46014474364 | BA68: 32023614794 | BB68: 27191404987 | BC68: 38355899298 | BD68: 47426115769 | BE68: 51797910397 | BF68: 52765546898 | BG68: 34461951167 | BH68: 44577925963 | BI68: 57717770751 | BJ68: 54221172817 | BK68: 63080533813 | BL68: 61387421408
A69: 66 | B69: VI.Đầu tư tài chính dài hạn | C69: 5 | P69: 0 | Q69: 0 | R69: 0 | S69: 0 | T69: 0 | W69: 0 | X69: 0 | Y69: 0 | AA69: 0 | AG69: 0 | AH69: 0 | AJ69: 0 | AK69: 0 | AN69: 0 | AO69: 0 | AP69: 0 | AQ69: 0 | AR69: 0 | AS69: 0 | AT69: 0 | AU69: 0 | AV69: 0 | AW69: 0 | AX69: 0 | AY69: 0 | AZ69: 0 | BA69: 0 | BB69: 0 | BC69: 0 | BD69: 0 | BE69: 0 | BF69: 0 | BG69: 0 | BH69: 0 | BI69: 0 | BJ69: 0
A70: 67 | B70: 1.Đầu tư vào công ty con | C70: 5 | P70: 0 | Q70: 0 | R70: 0 | S70: 0 | T70: 0 | W70: 0 | X70: 0 | Y70: 0 | AA70: 0 | AG70: 0 | AH70: 0 | AJ70: 0 | AK70: 0 | AN70: 0 | AO70: 0 | AP70: 0 | AQ70: 0 | AR70: 0 | AS70: 0 | AT70: 0 | AU70: 0 | AV70: 0 | AW70: 0 | AX70: 0 | AY70: 0 | AZ70: 0 | BA70: 0 | BB70: 0 | BC70: 0 | BD70: 0 | BE70: 0 | BF70: 0 | BG70: 0 | BH70: 0 | BI70: 0 | BJ70: 0
A71: 68 | B71: 2.Đầu tư vào công ty liên doanh, liên kết | C71: 5 | P71: 0 | Q71: 0 | R71: 0 | S71: 0 | T71: 0 | W71: 0 | X71: 0 | Y71: 0 | AA71: 0 | AG71: 0 | AH71: 0 | AJ71: 0 | AK71: 0 | AN71: 0 | AO71: 0 | AP71: 0 | AQ71: 0 | AR71: 0 | AS71: 0 | AT71: 0 | AU71: 0 | AV71: 0 | AW71: 0 | AX71: 0 | AY71: 0 | AZ71: 0 | BA71: 0 | BB71: 0 | BC71: 0 | BD71: 0 | BE71: 0 | BF71: 0 | BG71: 0 | BH71: 0 | BI71: 0 | BJ71: 0
A72: 69 | B72: 3.Đầu tư góp vốn vào đơn vị khác | C72: 5 | P72: 0 | Q72: 0 | R72: 0 | S72: 0 | T72: 0 | W72: 0 | X72: 0 | Y72: 0 | AA72: 0 | AG72: 0 | AH72: 0 | AJ72: 0 | AK72: 0 | AN72: 0 | AO72: 0 | AP72: 0 | AQ72: 0 | AR72: 0 | AS72: 0 | AT72: 0 | AU72: 0 | AV72: 0 | AW72: 0 | AX72: 0 | AY72: 0 | AZ72: 0 | BA72: 0 | BB72: 0 | BC72: 0 | BD72: 0 | BE72: 0 | BF72: 0 | BG72: 0 | BH72: 0 | BI72: 0 | BJ72: 0
A73: 70 | B73: 4.Dự phòng tổn thất đầu tư vào đơn vị khác dài hạn(*) | C73: 5 | P73: 0 | Q73: 0 | R73: 0 | S73: 0 | T73: 0 | W73: 0 | X73: 0 | Y73: 0 | AA73: 0 | AG73: 0 | AH73: 0 | AJ73: 0 | AK73: 0 | AN73: 0 | AO73: 0 | AP73: 0 | AQ73: 0 | AR73: 0 | AS73: 0 | AT73: 0 | AU73: 0 | AV73: 0 | AW73: 0 | AX73: 0 | AY73: 0 | AZ73: 0 | BA73: 0 | BB73: 0 | BC73: 0 | BD73: 0 | BE73: 0 | BF73: 0 | BG73: 0 | BH73: 0 | BI73: 0 | BJ73: 0
A74: 71 | B74: 5.Đầu tư nắm giữ đến ngày đáo hạn dài hạn | C74: 5 | P74: 0 | Q74: 0 | R74: 0 | S74: 0 | T74: 0 | W74: 0 | X74: 0 | Y74: 0 | AA74: 0 | AG74: 0 | AH74: 0 | AJ74: 0 | AK74: 0 | AN74: 0 | AO74: 0 | AP74: 0 | AQ74: 0 | AR74: 0 | AS74: 0 | AT74: 0 | AU74: 0 | AV74: 0 | AW74: 0 | AX74: 0 | AY74: 0 | AZ74: 0 | BA74: 0 | BB74: 0 | BC74: 0 | BD74: 0 | BE74: 0 | BF74: 0 | BG74: 0 | BH74: 0 | BI74: 0 | BJ74: 0
A75: 72 | B75: 6.Dự phòng đầu tư nắm giữ đến ngày đáo hạn dài hạn (*) | C75: 5
A76: 73 | B76: VII.Tài sản dài hạn khác | C76: 5 | D76: 1509662278 | E76: 1509662278 | F76: 1509662278 | G76: 1509662278 | H76: 1509662278 | I76: 1509662278 | J76: 1509662278 | K76: 1509662278 | L76: 1509662278 | M76: 1509662278 | N76: 817733734 | O76: 817733734 | P76: 691928544 | Q76: 629025949 | R76: 566123354 | S76: 736506396 | T76: 1400726248 | U76: 1832671028 | V76: 1791880808 | W76: 2000336678 | X76: 2264928389 | Y76: 3802711237 | Z76: 3558344841 | AA76: 3890647541 | AB76: 3725840649 | AC76: 3780553422 | AD76: 3569912862 | AE76: 3369186469 | AF76: 3531608451 | AG76: 3614695269 | AH76: 3627574164 | AI76: 3494288607 | AJ76: 3304401092 | AK76: 3169440799 | AL76: 3175199544 | AM76: 4689543787 | AN76: 4555335037 | AO76: 4317772711 | AP76: 5343646772 | AQ76: 5673307870 | AR76: 5368103241 | AS76: 5257350583 | AT76: 5470458531 | AU76: 6446273768 | AV76: 6223701149 | AW76: 5995679892 | AX76: 6220253528 | AY76: 6856222691 | AZ76: 4629083379 | BA76: 8122926924 | BB76: 9778480429 | BC76: 9451925232 | BD76: 9004620528 | BE76: 9051617060 | BF76: 8539591808 | BG76: 8072871371 | BH76: 8253974823 | BI76: 8650890043 | BJ76: 8536798591 | BK76: 8260771278 | BL76: 7062502744
A77: 74 | B77: 1.Chi phí chờ phân bổ dài hạn | C77: 5 | D77: 1509662278 | E77: 1509662278 | F77: 1509662278 | G77: 1509662278 | H77: 1509662278 | I77: 1509662278 | J77: 1509662278 | K77: 1509662278 | L77: 1509662278 | M77: 1509662278 | N77: 817733734 | O77: 817733734 | P77: 691928544 | Q77: 629025949 | R77: 566123354 | S77: 736506396 | T77: 1400726248 | U77: 1832671028 | V77: 1791880808 | W77: 2000336678 | X77: 2264928389 | Y77: 3802711237 | Z77: 3558344841 | AA77: 3890647541 | AB77: 3725840649 | AC77: 3780553422 | AD77: 3569912862 | AE77: 3369186469 | AF77: 3531608451 | AG77: 3614695269 | AH77: 3627574164 | AI77: 3494288607 | AJ77: 3304401092 | AK77: 3169440799 | AL77: 3175199544 | AM77: 4689543787 | AN77: 4555335037 | AO77: 4317772711 | AP77: 5343646772 | AQ77: 5673307870 | AR77: 5368103241 | AS77: 5257350583 | AT77: 5470458531 | AU77: 6446273768 | AV77: 6223701149 | AW77: 5995679892 | AX77: 6220253528 | AY77: 6856222691 | AZ77: 6468024689 | BA77: 9953825234 | BB77: 9749118739 | BC77: 9422563542 | BD77: 8975258838 | BE77: 9022255370 | BF77: 8539591808 | BG77: 8072871371 | BH77: 8253974823 | BI77: 8650890043 | BJ77: 8536798591 | BK77: 8260771278 | BL77: 7062502744
A78: 75 | B78: 2.Tài sản thuế thu nhập hoãn lại | C78: 5 | P78: 0 | Q78: 0 | R78: 0 | S78: 0 | T78: 0 | W78: 0 | X78: 0 | Y78: 0 | AA78: 0 | AG78: 0 | AH78: 0 | AJ78: 0 | AK78: 0 | AM78: 0 | AN78: 0 | AO78: 0 | AP78: 0 | AQ78: 0 | AR78: 0 | AS78: 0 | AT78: 0 | AU78: 0 | AV78: 0 | AW78: 0 | AX78: 0 | AY78: 0 | AZ78: -1838941310 | BA78: -1830898310 | BB78: 29361690 | BC78: 29361690 | BD78: 29361690 | BE78: 29361690 | BF78: 0 | BG78: 0 | BH78: 0 | BI78: 0 | BJ78: 0
A79: 76 | B79: 3.Thiết bị, vật tư, phụ tùng thay thế dài hạn | C79: 5 | P79: 0 | Q79: 0 | R79: 0 | S79: 0 | T79: 0 | W79: 0 | X79: 0 | Y79: 0 | AA79: 0 | AG79: 0 | AH79: 0 | AJ79: 0 | AK79: 0 | AM79: 0 | AN79: 0 | AO79: 0 | AP79: 0 | AQ79: 0 | AR79: 0 | AS79: 0 | AT79: 0 | AU79: 0 | AV79: 0 | AW79: 0 | AX79: 0 | AY79: 0 | AZ79: 0 | BA79: 0 | BB79: 0 | BC79: 0 | BD79: 0 | BE79: 0 | BF79: 0 | BG79: 0 | BH79: 0 | BI79: 0 | BJ79: 0
A80: 77 | B80: 4.Tài sản dài hạn khác | C80: 5 | P80: 0 | Q80: 0 | R80: 0 | S80: 0 | T80: 0 | W80: 0 | X80: 0 | Y80: 0 | AA80: 0 | AG80: 0 | AH80: 0 | AJ80: 0 | AK80: 0 | AM80: 0 | AN80: 0 | AO80: 0 | AP80: 0 | AQ80: 0 | AR80: 0 | AS80: 0 | AT80: 0 | AU80: 0 | AV80: 0 | AW80: 0 | AX80: 0 | AY80: 0 | AZ80: 0 | BA80: 0 | BB80: 0 | BC80: 0 | BD80: 0 | BE80: 0 | BF80: 0 | BG80: 0 | BH80: 0 | BI80: 0 | BJ80: 0
A81: 78 | B81: TỔNG TÀI SẢN | C81: 5 | D81: 701180296805 | E81: 704438896295 | F81: 711365330495 | G81: 725023303982 | H81: 734864260539 | I81: 736826000657 | J81: 756001934149 | K81: 753102394660 | L81: 759238087269 | M81: 759094526986 | N81: 769647066690 | O81: 781908280801 | P81: 794468132179 | Q81: 798518130349 | R81: 808110795127 | S81: 849864718615 | T81: 873481481467 | U81: 891363754606 | V81: 882603624560 | W81: 910588886247 | X81: 931223812753 | Y81: 945311368331 | Z81: 948196711170 | AA81: 850397335956 | AB81: 838624488703 | AC81: 846789415983 | AD81: 832358719704 | AE81: 810904446307 | AF81: 813737101557 | AG81: 868767124021 | AH81: 891636515744 | AI81: 873167455978 | AJ81: 857044763229 | AK81: 916472562375 | AL81: 960382808384 | AM81: 998954585172 | AN81: 1057103531305 | AO81: 1040896591576 | AP81: 1086666187007 | AQ81: 1148315875666 | AR81: 1198060080145 | AS81: 1227307344731 | AT81: 1174910121203 | AU81: 1123549747111 | AV81: 1164301804118 | AW81: 1184459048233 | AX81: 1262755141991 | AY81: 1255526266731 | AZ81: 1184167227046 | BA81: 1099673392126 | BB81: 1153710875298 | BC81: 1224376777626 | BD81: 1280979662011 | BE81: 1310961670922 | BF81: 1296565798277 | BG81: 1356526045802 | BH81: 1344912228849 | BI81: 1299331457948 | BJ81: 1275169884404 | BK81: 1274425697136 | BL81: 1215147163066
A82: 79 | B82: C-NỢ PHẢI TRẢ | C82: 5 | D82: 42982794217 | E82: 46503259825 | F82: 51936187191 | G82: 64581605720 | H82: 74649626597 | I82: 76327765276 | J82: 85793742139 | K82: 82040230454 | L82: 86472678622 | M82: 85633998961 | N82: 96197297015 | O82: 105661390145 | P82: 114601504988 | Q82: 119840072424 | R82: 130816310637 | S82: 171755491613 | T82: 193542715071 | U82: 209713594152 | V82: 199759487210 | W82: 224940558967 | X82: 244427684089 | Y82: 258051659625 | Z82: 258833539302 | AA82: 102922118948 | AB82: 141014447770 | AC82: 151834160869 | AD82: 144628084931 | AE82: 126119627307 | AF82: 126169458433 | AG82: 147974835173 | AH82: 167301049807 | AI82: 140236955320 | AJ82: 105855921290 | AK82: 151212128852 | AL82: 187762513610 | AM82: 204541142149 | AN82: 253938447634 | AO82: 243002156702 | AP82: 291731061734 | AQ82: 350905503653 | AR82: 404803110472 | AS82: 444265823125 | AT82: 405393285090 | AU82: 362315858983 | AV82: 393394647873 | AW82: 418527112069 | AX82: 500065225953 | AY82: 400766610864 | AZ82: 324510490627 | BA82: 222615858978 | BB82: 269555093091 | BC82: 336470011934 | BD82: 383542692015 | BE82: 412452200169 | BF82: 397016809667 | BG82: 456883837461 | BH82: 455472175159 | BI82: 414576062308 | BJ82: 397334986611 | BK82: 382374404972 | BL82: 334787042678
A83: 80 | B83: I.Nợ ngắn hạn | C83: 5 | D83: 14975246605 | E83: 14166425263 | F83: 18701743229 | G83: 25308204205 | H83: 25548631423 | I83: 25462777121 | J83: 28622839037 | K83: 24869327352 | L83: 29301775520 | M83: 24093386856 | N83: 29498540050 | O83: 30943320231 | P83: 32049566896 | Q83: 31096887926 | R83: 31185669667 | S83: 54884247810 | T83: 55358789337 | U83: 62344222537 | V83: 47996414480 | W83: 66485378318 | X83: 71872814743 | Y83: 69673599368 | Z83: 70455479045 | AA83: 102922118948 | AB83: 141014447770 | AC83: 148365334599 | AD83: 134352230661 | AE83: 108648773037 | AF83: 94749206163 | AG83: 113785582903 | AH83: 129423797537 | AI83: 97934191050 | AJ83: 58979157020 | AK83: 94467364582 | AL83: 119896937340 | AM83: 134304565879 | AN83: 176322036564 | AO83: 165479805632 | AP83: 214267710664 | AQ83: 273737345975 | AR83: 329588242794 | AS83: 367721787447 | AT83: 328736442804 | AU83: 286316076697 | AV83: 316799865587 | AW83: 341708523175 | AX83: 396620697059 | AY83: 316029265342 | AZ83: 216100148681 | BA83: 118453354810 | BB83: 166229366701 | BC83: 234217256714 | BD83: 285537774573 | BE83: 335330408775 | BF83: 320967989443 | BG83: 382420327015 | BH83: 381845442491 | BI83: 346002928366 | BJ83: 327703613669 | BK83: 331992150618 | BL83: 285314201263
A84: 81 | B84: 1.Phải trả người bán ngắn hạn | C84: 5 | D84: 12004818370 | E84: 11167301295 | F84: 9384469882 | G84: 14083960588 | H84: 21369809301 | I84: 20879785099 | J84: 21923728968 | K84: 18499116244 | L84: 22304923039 | M84: 18478287536 | N84: 21665123801 | O84: 24257335887 | P84: 18933200262 | Q84: 16637008012 | R84: 14159563168 | S84: 12827193363 | T84: 21388038259 | U84: 30408231864 | V84: 25546344426 | W84: 22632581849 | X84: 33200101862 | Y84: 34152280248 | Z84: 34183119345 | AA84: 53389397041 | AB84: 37263084219 | AC84: 45267228558 | AD84: 55217890739 | AE84: 48398479428 | AF84: 52963055109 | AG84: 63609921991 | AH84: 75516302247 | AI84: 72059615531 | AJ84: 23842169712 | AK84: 35852278853 | AL84: 31442797226 | AM84: 53983394350 | AN84: 54353400004 | AO84: 57459904781 | AP84: 71666676062 | AQ84: 72717166254 | AR84: 82570066775 | AS84: 116097944870 | AT84: 90497312556 | AU84: 104998329522 | AV84: 141548339763 | AW84: 140860659227 | AX84: 150120296949 | AY84: 38854336196 | AZ84: 17080396612 | BA84: 15854922544 | BB84: 36651877076 | BC84: 36646554722 | BD84: 36688096679 | BE84: 50235234736 | BF84: 4297727379 | BG84: 15019964770 | BH84: 22979794050 | BI84: 34152918116 | BJ84: 22550645996 | BK84: 19268613080 | BL84: 15051129082
A85: 82 | B85: 2.Người mua trả tiền trước ngắn hạn | C85: 5 | P85: 0 | Q85: 0 | R85: 0 | S85: 0 | T85: 0 | W85: 17818880422 | X85: 11349591484 | Y85: 7264641138 | Z85: 5998683900 | AA85: 0 | AD85: 7673599840 | AE85: 32041236730 | AF85: 24658895322 | AG85: 24848124028 | AH85: 25851353102 | AI85: 218095380 | AJ85: 1665987985 | AK85: 1665987985 | AL85: 23030226075 | AM85: 10724313600 | AN85: 4031903040 | AO85: 0 | AP85: -540918440 | AQ85: 4278155246 | AR85: 14749203650 | AS85: 36030101433 | AT85: 34757495667 | AU85: 14991723009 | AV85: 39469513 | AW85: 9371572336 | AX85: 34895916928 | AY85: 41546475913 | AZ85: 33988016157 | BA85: 18937903421 | BB85: 15058088135 | BC85: 3447698110 | BD85: 75365353 | BE85: 14926125753 | BF85: 23340035157 | BG85: 20961721533 | BH85: 14431985238 | BI85: 8912711658 | BJ85: 5995670638 | BK85: 17620714714 | BL85: 12106522730
A86: 83 | B86: 3.Phải trả cổ tức, lợi nhuận | C86: 5
A87: 84 | B87: 4.Thuế và các khoản phải nộp Nhà nước ngắn hạn | C87: 5 | D87: 134897786 | E87: 169163266 | F87: 285299970 | G87: 371612610 | H87: 407631656 | I87: 491580057 | J87: 2926207394 | K87: 3089788816 | L87: 3517318240 | M87: 709335738 | N87: 741628871 | O87: 1456740676 | P87: 1022113431 | Q87: 988086773 | R87: 942371452 | S87: 1129056403 | T87: 1640392841 | U87: 1852669874 | V87: 1157754100 | W87: 1921380863 | X87: 2208331209 | Y87: 1347620221 | Z87: 1891903018 | AA87: 17079905656 | AB87: 20836801057 | AC87: 7647112567 | AD87: 7762547005 | AE87: 1009669135 | AF87: 954253281 | AG87: 6213189599 | AH87: 7102515762 | AI87: 9645423417 | AJ87: 14204655610 | AK87: 17701750695 | AL87: 19515317671 | AM87: 19803529161 | AN87: 8898739732 | AO87: 1567041590 | AP87: 1567041590 | AQ87: 145412873 | AR87: 2526331 | AS87: 17283890 | AT87: 0 | AU87: 0 | AV87: 0 | AW87: 0 | AX87: 0 | AY87: 7646385732 | AZ87: 2773116077 | BA87: 4518229531 | BB87: 6886686516 | BC87: 7470833894 | BD87: 12458087898 | BE87: 9494100798 | BF87: 5591611785 | BG87: 5843676544 | BH87: 4494183632 | BI87: 3950455452 | BJ87: 3074628856 | BK87: 5633872560 | BL87: 2125485230
A88: 85 | B88: 5.Phải trả người lao động | C88: 5 | D88: 554968182 | E88: 697343066 | F88: 721543641 | G88: 1063497666 | H88: 993181301 | I88: 785433523 | J88: 462948488 | K88: 321083094 | L88: 355426673 | M88: 831001268 | N88: 1220531394 | O88: 1349347609 | P88: 350104810 | Q88: 1486935780 | R88: 1822214959 | S88: 2326143380 | T88: 2370944746 | U88: 2642569462 | V88: 2437166002 | W88: 2934192885 | X88: 3166789067 | Y88: 3369909455 | Z88: 3625277741 | AA88: 7350805078 | AB88: 4202914580 | AC88: 4010590788 | AD88: 4184221690 | AE88: 5033150240 | AF88: 5048649993 | AG88: 5133281084 | AH88: 5076894562 | AI88: 0 | AJ88: 5397181503 | AK88: 5352208319 | AL88: 5475786153 | AM88: 4844290117 | AN88: 10128031033 | AO88: 6218009406 | AP88: 6555513609 | AQ88: 7649364322 | AR88: 7249642948 | AS88: 7169425301 | AT88: 6912460758 | AU88: 456962693 | AV88: 7439470114 | AW88: 7375957571 | AX88: 7548660274 | AY88: 11760267089 | AZ88: 7452851745 | BA88: 7981672191 | BB88: 8135040430 | BC88: 505632229 | BD88: 9296428166 | BE88: 9543385489 | BF88: 9205268728 | BG88: 9535380096 | BH88: 10074815641 | BI88: 9365267323 | BJ88: 9132322907 | BK88: 9289786517 | BL88: 17091977517
A89: 86 | B89: 6.Chi phí phải trả ngắn hạn | C89: 5 | D89: 683467481 | E89: 468739600 | F89: 4880030620 | G89: 5018671303 | H89: 835966829 | I89: 999809780 | J89: 1109469583 | K89: 1221142152 | L89: 1272568188 | M89: 2211932934 | N89: 2026624454 | O89: 1554389263 | P89: 1064762807 | Q89: 1289758349 | R89: 2474115112 | S89: 5062905478 | T89: 3538939169 | U89: 1614653991 | V89: 2578607052 | W89: 2478285320 | X89: 3238570913 | Y89: 3906544866 | Z89: 4511880014 | AA89: 286472451 | AB89: 776003978 | AC89: 1754256892 | AD89: 2747112908 | AE89: 3088774819 | AF89: 4260551218 | AG89: 4913789642 | AH89: 5981449353 | AI89: 7240095424 | AJ89: 8362193377 | AK89: 9183985999 | AL89: 11973366181 | AM89: 14393919534 | AN89: 15355121373 | AO89: 22067539102 | AP89: 6522564543 | AQ89: 16391725866 | AR89: 25887367165 | AS89: 8854068160 | AT89: 18522703687 | AU89: 31289196795 | AV89: 16810846632 | AW89: 24050388306 | AX89: 32028968920 | AY89: 16521426792 | AZ89: 12992485838 | BA89: 18140837282 | BB89: -6247336694 | BC89: -4221870182 | BD89: -636813506 | BE89: 209989120 | BF89: 16596396339 | BG89: 22300697137 | BH89: 15233456716 | BI89: 21020315535 | BJ89: 25722544862 | BK89: 13142865120 | BL89: 17598276940
A90: 87 | B90: 7.Phải trả nội bộ ngắn hạn | C90: 5 | P90: 0 | Q90: 0 | R90: 0 | S90: 0 | T90: 0 | W90: 0 | X90: 0 | Y90: 0 | AA90: 0 | AG90: 0 | AH90: 0 | AI90: 0 | AJ90: 0 | AK90: 0 | AN90: 0 | AO90: 0 | AP90: 0 | AQ90: 0 | AR90: 0 | AS90: 0 | AT90: 0 | AU90: 0 | AV90: 0 | AW90: 0 | AX90: 0 | AY90: 0 | AZ90: 0 | BA90: 0 | BB90: 0 | BC90: 0 | BD90: 0 | BE90: 0 | BF90: 0 | BG90: 0 | BH90: 0 | BI90: 0 | BJ90: 0 | BK90: 0
A91: 88 | B91: 8.Phải trả theo tiến độ hợp đồng xây dựng ngắn hạn | C91: 5 | P91: 0 | Q91: 0 | R91: 0 | S91: 0 | T91: 0 | W91: 0 | X91: 0 | Y91: 0 | AA91: 0 | AG91: 0 | AH91: 0 | AI91: 0 | AJ91: 0 | AK91: 0 | AN91: 0 | AO91: 0 | AP91: 0 | AQ91: 0 | AR91: 0 | AS91: 0 | AT91: 0 | AU91: 0 | AV91: 0 | AW91: 0 | AX91: 0 | AY91: 0 | AZ91: 0 | BA91: 0 | BC91: 0 | BD91: 0 | BE91: 0 | BF91: 0 | BG91: 0 | BH91: 0 | BI91: 0 | BJ91: 0 | BK91: 0
A92: 89 | B92: 9.Doanh thu chờ phân bổ ngắn hạn | C92: 5 | P92: 0 | Q92: 0 | R92: 0 | S92: 0 | T92: 0 | W92: 0 | X92: 0 | Y92: 0 | AA92: 0 | AG92: 0 | AH92: 0 | AI92: 0 | AJ92: 0 | AK92: 0 | AN92: 0 | AO92: 0 | AP92: 0 | AQ92: 0 | AR92: 0 | AS92: 0 | AT92: 0 | AU92: 0 | AV92: 0 | AW92: 0 | AX92: 0 | AY92: 0 | AZ92: 0 | BA92: 0 | BB92: 0 | BC92: 0 | BD92: 0 | BE92: 0 | BF92: 0 | BG92: 0 | BH92: 0 | BI92: 0 | BJ92: 0 | BK92: 0
A93: 90 | B93: 10.Phải trả ngắn hạn khác | C93: 5 | D93: 100376455 | E93: 167159705 | F93: 1933680785 | G93: 3273743707 | H93: 445324005 | I93: 809450331 | J93: 703766273 | K93: 241478715 | L93: 354821049 | M93: 366111049 | N93: 2347913199 | O93: 828788465 | P93: 5202594805 | Q93: 5218308231 | R93: 6310614195 | S93: 28027064445 | T93: 20908589581 | U93: 20314212605 | V93: 6764658159 | W93: 9188172238 | X93: 10197545467 | Y93: 11120718699 | Z93: 11732730286 | AA93: 19303653981 | AB93: 76788925605 | AC93: 79268841408 | AD93: 43184479917 | AE93: 5718178285 | AF93: 6180566740 | AG93: 8625319144 | AH93: 9705497644 | AI93: 3967521436 | AJ93: 4407617246 | AK93: 19650158527 | AL93: 14984940324 | AM93: 17367766224 | AN93: 20355282311 | AO93: 20072661932 | AP93: 26417436937 | AQ93: 27331419185 | AR93: 19976705931 | AS93: 8557631012 | AT93: 8921341505 | AU93: 8305034290 | AV93: 10611497755 | AW93: 3332301431 | AX93: 5092624624 | AY93: 5848302182 | AZ93: 5950478281 | BA93: 8480710843 | BB93: 6827325037 | BC93: 16529834801 | BD93: 26083619575 | BE93: 11626227888 | BF93: 10463806809 | BG93: 13245650719 | BH93: 3578074988 | BI93: 3829811224 | BJ93: 5090463265 | BK93: 3375786923 | BL93: 3354979153
A94: 91 | B94: 11.Vay và nợ thuê tài chính ngắn hạn | C94: 5 | P94: 4330072450 | Q94: 4330072450 | R94: 4330072450 | S94: 4365166410 | T94: 4365166410 | U94: 4365166410 | V94: 8365166410 | W94: 8365166410 | X94: 7365166410 | Y94: 7365166410 | Z94: 7365166410 | AA94: 4365166410 | AC94: 9270586055 | AD94: 12435660231 | AE94: 12435660231 | AG94: 0 | AH94: 0 | AI94: 3428447309 | AJ94: 0 | AK94: 4244366780 | AL94: 12931910250 | AM94: 12931910250 | AN94: 62822745245 | AO94: 57847834995 | AP94: 101832582537 | AQ94: 144977288403 | AR94: 178905916168 | AS94: 190748518955 | AT94: 168894814805 | AU94: 126048766562 | AV94: 139654417984 | AW94: 155306260478 | AX94: 165536679982 | AY94: 192629821718 | AZ94: 134925554251 | BA94: 43611829278 | BB94: 98003020481 | BC94: 172928907420 | BD94: 200666324688 | BE94: 238388679271 | BF94: 250573370780 | BG94: 294832243750 | BH94: 309616499760 | BI94: 263334816592 | BJ94: 254700704679 | BK94: 262225979238 | BL94: 216818798145
A95: 92 | B95: 12.Dự phòng phải trả ngắn hạn | C95: 5 | P95: 0 | Q95: 0 | R95: 0 | S95: 0 | T95: 0 | W95: 0 | X95: 0 | Y95: 0 | AA95: 0 | AG95: 0 | AH95: 0 | AI95: 0 | AJ95: 0 | AK95: 0 | AM95: 0 | AN95: 0 | AO95: 0 | AP95: 0 | AQ95: 0 | AR95: 0 | AS95: 0 | AT95: 0 | AU95: 0 | AV95: 0 | AW95: 0 | AX95: 0 | AY95: 0 | AZ95: 0 | BA95: 0 | BB95: 0 | BC95: 0 | BD95: 0 | BE95: 0 | BF95: 0 | BG95: 0 | BH95: 0 | BI95: 0 | BJ95: 0 | BK95: 0
A96: 93 | B96: 13.Quỹ khen thưởng, phúc lợi | C96: 5 | D96: 1496718331 | E96: 1496718331 | F96: 1496718331 | G96: 1496718331 | H96: 1496718331 | I96: 1496718331 | J96: 1496718331 | K96: 1496718331 | L96: 1496718331 | M96: 1496718331 | N96: 1496718331 | O96: 1496718331 | P96: 1146718331 | Q96: 1146718331 | R96: 1146718331 | S96: 1146718331 | T96: 1146718331 | U96: 1146718331 | V96: 1146718331 | W96: 1146718331 | X96: 1146718331 | Y96: 1146718331 | Z96: 1146718331 | AA96: 1146718331 | AB96: 1146718331 | AC96: 1146718331 | AD96: 1146718331 | AE96: 923624169 | AF96: 683234500 | AG96: 441957415 | AH96: 189784867 | AI96: 1374992553 | AJ96: 1099351587 | AK96: 816627424 | AL96: 542593460 | AM96: 255442643 | AN96: 376813826 | AO96: 246813826 | AP96: 246813826 | AQ96: 246813826 | AR96: 246813826 | AS96: 246813826 | AT96: 230313826 | AU96: 226063826 | AV96: 695823826 | AW96: 1411383826 | AX96: 1397549382 | AY96: 1222249720 | AZ96: 937249720 | BA96: 927249720 | BB96: 914665720 | BC96: 909665720 | BD96: 906665720 | BE96: 906665720 | BF96: 899772466 | BG96: 680992466 | BH96: 1436632466 | BI96: 1436632466 | BJ96: 1436632466 | BK96: 1434532466 | BL96: 1167032466
A97: 94 | B97: 14.Quỹ bình ổn giá | C97: 5 | P97: 0 | Q97: 0 | R97: 0 | S97: 0 | T97: 0 | W97: 0 | X97: 0 | Y97: 0 | AA97: 0 | AG97: 0 | AH97: 0 | AI97: 0 | AJ97: 0 | AK97: 0 | AM97: 0 | AN97: 0 | AO97: 0 | AP97: 0 | AQ97: 0 | AR97: 0 | AS97: 0 | AT97: 0 | AU97: 0 | AV97: 0 | AW97: 0 | AX97: 0 | AY97: 0 | AZ97: 0 | BA97: 0 | BB97: 0 | BC97: 0 | BD97: 0 | BE97: 0 | BF97: 0 | BG97: 0 | BH97: 0 | BI97: 0 | BJ97: 0
A98: 95 | B98: 15.Giao dịch mua bán lại trái phiếu Chính phủ | C98: 5 | P98: 0 | Q98: 0 | R98: 0 | S98: 0 | T98: 0 | W98: 0 | X98: 0 | Y98: 0 | AA98: 0 | AG98: 0 | AH98: 0 | AI98: 0 | AJ98: 0 | AK98: 0 | AM98: 0 | AN98: 0 | AO98: 0 | AP98: 0 | AQ98: 0 | AR98: 0 | AS98: 0 | AT98: 0 | AU98: 0 | AV98: 0 | AW98: 0 | AX98: 0 | AY98: 0 | AZ98: 0 | BA98: 0 | BB98: 0 | BC98: 0 | BD98: 0 | BE98: 0 | BF98: 0 | BG98: 0 | BH98: 0 | BI98: 0 | BJ98: 0
A99: 96 | B99: II.Nợ dài hạn | C99: 5 | D99: 28007547612 | E99: 32336834562 | F99: 33234443962 | G99: 39273401515 | H99: 49100995174 | I99: 50864988155 | J99: 57170903102 | K99: 57170903102 | L99: 57170903102 | M99: 61540612105 | N99: 66698756965 | O99: 74718069914 | P99: 82551938092 | Q99: 88743184498 | R99: 99630640970 | S99: 116871243803 | T99: 138183925734 | U99: 147369371615 | V99: 151763072730 | W99: 158455180649 | X99: 172554869346 | Y99: 188378060257 | Z99: 188378060257 | AA99: 0 | AC99: 3468826270 | AD99: 10275854270 | AE99: 17470854270 | AF99: 31420252270 | AG99: 34189252270 | AH99: 37877252270 | AI99: 42302764270 | AJ99: 46876764270 | AK99: 56744764270 | AL99: 67865576270 | AM99: 70236576270 | AN99: 77616411070 | AO99: 77522351070 | AP99: 77463351070 | AQ99: 77168157678 | AR99: 75214867678 | AS99: 76544035678 | AT99: 76656842286 | AU99: 75999782286 | AV99: 76594782286 | AW99: 76818588894 | AX99: 103444528894 | AY99: 84737345522 | AZ99: 108410341946 | BA99: 104162504168 | BB99: 103325726390 | BC99: 102252755220 | BD99: 98004917442 | BE99: 77121791394 | BF99: 76048820224 | BG99: 74463510446 | BH99: 73626732668 | BI99: 68573133942 | BJ99: 69631372942 | BK99: 50382254354 | BL99: 49472841415
A100: 97 | B100: 1.Phải trả người bán dài hạn | C100: 5 | P100: 0 | Q100: 0 | R100: 0 | S100: 0 | T100: 0 | W100: 0 | X100: 0 | Y100: 0 | AA100: 0 | AG100: 0 | AH100: 0 | AI100: 0 | AJ100: 0 | AK100: 0 | AN100: 0 | AO100: 0 | AP100: 0 | AQ100: 0 | AR100: 0 | AS100: 0 | AT100: 0 | AU100: 0 | AV100: 0 | AW100: 0 | AX100: 0 | AY100: 0 | AZ100: 0 | BA100: 0 | BB100: 0 | BC100: 0 | BD100: 0 | BE100: 0 | BF100: 0 | BG100: 0 | BH100: 0 | BI100: 0 | BJ100: 0 | BK100: 0
...

Sheet Kết quả kinh doanh
B1: CTY CP NHỰA TÁI CHẾ DUY TÂN
B2: VND
A3: Index PL | B3: PHẦN II-KẾT QUẢ HOẠT ĐỘNG KINH DOANH | C3: TenCongTyID | D3: T1.2021 | E3: T02.2021 | F3: T03.2021 | G3: T04.2021 | H3: T05.2021 | I3: T06.2021 | J3: T07.2021 | K3: T08.2021 | L3: T09.2021 | M3: T10.2021 | N3: T11.2021 | O3: T12.2021 | P3: T1.2022 | Q3: T02.2022 | R3: T03.2022 | S3: T04.2022 | T3: T05.2022 | U3: T06.2022 | V3: T07.2022 | W3: T08.2022 | X3: T09.2022 | Y3: T10.2022 | Z3: T11.2022 | AA3: T12.2022 | AB3: T1.2023 | AC3: T02.2023 | AD3: T03.2023 | AE3: T04.2023 | AF3: T05.2023 | AG3: T06.2023 | AH3: T07.2023 | AI3: T08.2023 | AJ3: T09.2023 | AK3: T10.2023 | AL3: T11.2023 | AM3: T12.2023 | AN3: T01.2024 | AO3: T02.2024 | AP3: T03.2024 | AQ3: T04.2024 | AR3: T05.2024 | AS3: T06.2024 | AT3: T07.2024 | AU3: T08.2024 | AV3: T09.2024 | AW3: T10.2024 | AX3: T11.2024 | AY3: T12.2024 | AZ3: T01.2025 | BA3: T02.2025 | BB3: T03.2025 | BC3: T04.2025 | BD3: T05.2025 | BE3: T06.2025 | BF3: T07.2025 | BG3: T08.2025 | BH3: T09.2025 | BI3: T10.2025 | BJ3: T11.2025 | BK3: T12.2025 | BL3: T01.2026 | BM3: T02.2026 | BN3: T03.2026 | BO3: T04.2026 | BP3: T05.2026 | BQ3: T06.2026 | BR3: T07.2026 | BS3: T08.2026 | BT3: T09.2026 | BU3: T10.2026 | BV3: T11.2026 | BW3: T12.2026
A4: 1 | B4: Sản lượng sản phẩm chính(kg) | C4: 5 | D4: 76.025 | E4: 61 | F4: 303.8 | G4: 215.35 | H4: 35.93 | I4: 30.437 | J4: 87.5 | K4: 69.2 | L4: 115.5 | M4: 262.5 | N4: 284.8 | O4: 589.92 | P4: 250.8 | Q4: 242 | R4: 707.8 | S4: 757.7 | T4: 578.208 | U4: 678.9 | V4: 421.5 | W4: 1104.468 | X4: 1030.32 | Y4: 1178.275 | Z4: 981.1 | AA4: 1860 | AB4: 651.8 | AC4: 653.07 | AD4: 1860.64 | AE4: 1792.575 | AF4: 1632.75 | AG4: 1573.975 | AH4: 1591.575 | AI4: 2445.175 | AJ4: 1647 | AK4: 2259.525 | AL4: 1979.8 | AM4: 3063.25 | AN4: 3143.325 | AO4: 2064.375 | AP4: 2908.4 | AQ4: 3200.75 | AR4: 3201.51 | AS4: 1881.75 | AT4: 1784.225 | AU4: 4611.4182 | AV4: 4683.6 | AW4: 3573.525 | AX4: 1971.925 | AY4: 2839.35 | AZ4: 3575.9993 | BA4: 5476.675 | BB4: 4580.05 | BC4: 3850.925 | BD4: 4586.0243 | BE4: 3673.208 | BF4: 4560.4241 | BG4: 5189.368 | BH4: 2657.043 | BI4: 3219.195 | BJ4: 2510.415 | BK4: 2781.111 | BL4: =4227212/1000 -> 4227.212
A5: 2 | B5: 1.Doanh thu bán hàng và cung cấp dịch vụ | C5: 5 | D5: 2192940600 | E5: 1791822000 | F5: 8682084600 | G5: 6264332700 | H5: 1376973402 | I5: 904631370 | J5: 3085582842 | K5: 2036756400 | L5: 4007834643 | M5: 8372308560 | N5: 8615033640 | O5: 13231975164 | P5: 7498036216 | Q5: 6876982200 | R5: 22637626231 | S5: 27424133378 | T5: 18350378815 | U5: 21902018748 | V5: 15882148168 | W5: 38706132850 | X5: 36809694250 | Y5: 41577847270 | Z5: 34741567940 | AA5: 58684343202 | AB5: 24985455241 | AC5: 23042319009 | AD5: 59212986698 | AE5: 54287237375 | AF5: 57641008821 | AG5: 50922412416 | AH5: 53533092198 | AI5: 78282463651 | AJ5: 64916176630 | AK5: 84671529098 | AL5: 62903041444 | AM5: 99555993730 | AN5: 95961616736 | AO5: 70105871996 | AP5: 92109508133 | AQ5: 97489092894 | AR5: 102501453344 | AS5: 68093170109 | AT5: 56451269692 | AU5: 160372945473 | AV5: 161501484254 | AW5: 119734804022 | AX5: 76175498864 | AY5: 110890509220 | AZ5: 114976445897 | BA5: 188477338235 | BB5: 150730683132 | BC5: 125734240353 | BD5: 153674258114 | BE5: 119843310993 | BF5: 138018360641 | BG5: 169442946928 | BH5: 91484253567 | BI5: 108928556660 | BJ5: 89826973802 | BK5: 100861213901 | BL5: 126786913920
A6: 3 | B6: 2.Các khoản giảm trừ doanh thu | C6: 5 | D6: 0 | E6: 0 | F6: 0 | G6: 0 | H6: 0 | I6: 36461250 | J6: 0 | K6: 686000 | L6: 0 | M6: 0 | N6: 0 | O6: 31203900 | R6: 0 | V6: 3076000 | W6: 346771999 | Y6: 0 | Z6: 43346500 | AA6: 0 | AB6: 0 | AC6: 0 | AD6: 453218 | AE6: 195177 | AF6: 9024000 | AG6: 18714230 | AH6: 6765000 | AI6: 0 | AJ6: 0 | AK6: 0 | AL6: 0 | AM6: 0 | AN6: 0 | AO6: 1166125000 | AP6: 0 | AQ6: 0 | AR6: 136455000 | AS6: 0 | AT6: 0 | AU6: 6345077301 | AV6: 4671587529 | AW6: 2922205276 | AX6: 49359030 | AY6: 4680420540 | AZ6: 513935495 | BA6: 477877176 | BB6: 477350452 | BC6: 304590498 | BD6: 1607115262 | BE6: 708638196 | BF6: 26953743 | BG6: 1000293545 | BH6: 6773818500 | BI6: 0 | BJ6: 1479093000 | BK6: -573868680 | BL6: 687876997
A7: 4 | B7: 3.Doanh thu thuần về bán hàng và cung cấp dịch vụ | C7: 5 | D7: 2192940600 | E7: 1791822000 | F7: 8682084600 | G7: 6264332700 | H7: 1376973402 | I7: 868170120 | J7: 3085582842 | K7: 2036070400 | L7: 4007834643 | M7: 8372308560 | N7: 8615033640 | O7: 13200771264 | P7: 7498036216 | Q7: 6111323505 | R7: 22637626231 | S7: 27424133378 | T7: 18350378815 | U7: 21902018748 | V7: 15879072168 | W7: 38359360851 | X7: 36809694250 | Y7: 41577847270 | Z7: 34698221440 | AA7: 58684343202 | AB7: 24985455241 | AC7: 23042319009 | AD7: 59212533480 | AE7: 54287042198 | AF7: 57631984821 | AG7: 50903698186 | AH7: 53526327198 | AI7: 78282463651 | AJ7: 64916176630 | AK7: 84671529098 | AL7: 62903041444 | AM7: 99555993730 | AN7: 95961616736 | AO7: 68939746996 | AP7: 92109508133 | AQ7: 97489092894 | AR7: 102364998344 | AS7: 68093170109 | AT7: 56451269692 | AU7: 154027868172 | AV7: 156829896725 | AW7: 116812598746 | AX7: 76126139834 | AY7: 106210088680 | AZ7: 114462510402 | BA7: 187999461059 | BB7: 150253332680 | BC7: 125429649855 | BD7: 152067142852 | BE7: 119134672797 | BF7: 137991406898 | BG7: 168442653383 | BH7: 84710435067 | BI7: 108928556660 | BJ7: 88347880802 | BK7: 101435082581 | BL7: 126099036923
A8: 5 | B8: 4.Giá vốn hàng bán | C8: 5 | D8: 1714389259 | E8: 1513381552 | F8: 6687623393 | G8: 4774057263 | H8: 1087102095 | I8: 807656278 | J8: 2716172489 | K8: 4315716140 | L8: 4265960659 | M8: 7443114351 | N8: 7773986301 | O8: 12401370308 | P8: 6843552810 | Q8: 6912963718 | R8: 19836366360 | S8: 21907875072 | T8: 15580244606 | U8: 18312738285 | V8: 12006617281 | W8: 32529935445 | X8: 32281385317 | Y8: 38377094489 | Z8: 30963456194 | AA8: 55697416598 | AB8: 20792367485 | AC8: 21918378947 | AD8: 61251223688 | AE8: 53942190282 | AF8: 50245648463 | AG8: 7904131770 | AH8: 44797235508 | AI8: 62222051344 | AJ8: 37728980820 | AK8: 61940025172 | AL8: 49113504898 | AM8: 70869596847 | AN8: 85841765176 | AO8: 68748321616 | AP8: 86824377307 | AQ8: 85475594862 | AR8: 99208228636 | AS8: 69795611979 | AT8: 61217801757 | AU8: 147970813832 | AV8: 132769623597 | AW8: 112138441893 | AX8: 70998442117 | AY8: -22758768790 | AZ8: 96299447936 | BA8: 154570631505 | BB8: 129509315823 | BC8: 109641808151 | BD8: 129906078108 | BE8: 105463649620 | BF8: 128673842020 | BG8: 155101842643 | BH8: 83113314505 | BI8: 99966937216 | BJ8: 80940600844 | BK8: 70308328665 | BL8: 115080112871
A9: 6 | B9: 5.Lợi nhuận gộp về bán hàng | C9: 5 | D9: 478551341 | E9: 278440448 | F9: 1994461207 | G9: 1490275437 | H9: 289871307 | I9: 60513842 | J9: 369410353 | K9: -2279645740 | L9: -258126016 | M9: 929194209 | N9: 841047339 | O9: 799400956 | P9: 654483406 | Q9: -801640213 | R9: 2801259871 | S9: 5516258306 | T9: 2770134209 | U9: 3589280463 | V9: 3872454887 | W9: 5829425406 | X9: 4528308933 | Y9: 3200752781 | Z9: 3734765246 | AA9: 2986926604 | AB9: 4193087756 | AC9: 1123940062 | AD9: -2038690208 | AE9: 344851916 | AF9: 7386336358 | AG9: 42999566416 | AH9: 8729091690 | AI9: 16060412307 | AJ9: 27187195810 | AK9: 22731503926 | AL9: 13789536546 | AM9: 28686396883 | AN9: 10119851560 | AO9: 191425380 | AP9: 5285130826 | AQ9: 12013498032 | AR9: 3156769708 | AS9: -1702441870 | AT9: -4766532065 | AU9: 6057054340 | AV9: 24060273128 | AW9: 4674156853 | AX9: 5127697717 | AY9: 128968857470 | AZ9: 18163062466 | BA9: 33428829554 | BB9: 20744016857 | BC9: 15787841704 | BD9: 22161064744 | BE9: 13671023177 | BF9: 9317564878 | BG9: 13340810740 | BH9: 1597120562 | BI9: 8961619444 | BJ9: 7407279958 | BK9: 31126753916 | BL9: 11018924052
A10: 7 | B10: 6.Lãi/lỗ của hoạt động bán, thanh lý bất động sản đầu tư | C10: 5
A11: 8 | B11: 7.Doanh thu hoạt động tài chính | C11: 5 | D11: 1228117 | E11: 1370668 | F11: 503786 | G11: 991223 | H11: 924399 | I11: 2721429 | J11: 5630167167 | K11: 4552274821 | L11: 4006107516 | M11: 1404451824 | N11: 1487413089 | O11: 1249240389 | P11: 1479346434 | Q11: 1527456177 | R11: 1512346597 | S11: 1655612808 | T11: 2665641339 | U11: 1264179580 | V11: 1129143854 | W11: 1236134244 | X11: 1420307305 | Y11: 1826774837 | Z11: 1006924842 | AA11: 726365830 | AB11: 23897328 | AC11: 190776336 | AD11: 16660712 | AE11: 967330723 | AF11: 867791673 | AG11: 866039044 | AH11: 810000497 | AI11: 1331407010 | AJ11: 1045754825 | AK11: 1146315118 | AL11: 946685267 | AM11: 1110704514 | AN11: 702840610 | AO11: 1100851130 | AP11: 994712341 | AQ11: 1735368123 | AR11: 1021938222 | AS11: 578784271 | AT11: 343643819 | AU11: 1242477440 | AV11: 1549112434 | AW11: 2779237425 | AX11: 865910053 | AY11: 2184218732 | AZ11: 773999253 | BA11: 1788435256 | BB11: 931124505 | BC11: 1307926421 | BD11: 2429341904 | BE11: 1641453607 | BF11: 1393514763 | BG11: 1498736488 | BH11: 1228780215 | BI11: 2716737103 | BJ11: 515476780 | BK11: 680982457 | BL11: 1053165322
A12: 9 | B12: 8.Chi phí tài chính | C12: 5 | D12: 167606071 | E12: 221668883 | F12: 208008837 | G12: 262181583 | H12: 294284803 | I12: 376440316 | J12: 341383390 | K12: 424333601 | L12: 404885911 | M12: 376140889 | N12: 457278692 | O12: 459173961 | P12: 566186825 | Q12: 636770194 | R12: 622676693 | S12: 508923847 | T12: 611802389 | U12: 151684906 | V12: 632905650 | W12: 700652271 | X12: 1025151505 | Y12: 1107933886 | Z12: 1595489167 | AA12: 941628595 | AB12: 74107271 | AC12: 30659803 | AD12: 220600896 | AE12: 69167924 | AF12: 49408830 | AG12: 124156445 | AH12: 311284353 | AI12: 709793834 | AJ12: 328510530 | AK12: 475535318 | AL12: 86442609 | AM12: 584468484 | AN12: 801399604 | AO12: 695500231 | AP12: 663502461 | AQ12: 1555671370 | AR12: 936492932 | AS12: 1103852896 | AT12: 1608708972 | AU12: 1489581015 | AV12: 1372261307 | AW12: 636041020 | AX12: 1257673070 | AY12: 993026233 | AZ12: 1529745602 | BA12: 1349010483 | BB12: 902730488 | BC12: 1450570894 | BD12: 858169737 | BE12: 1483876982 | BF12: 1315247967 | BG12: 1366041150 | BH12: 1603769193 | BI12: 2900732378 | BJ12: 1301741764 | BK12: 2479436989 | BL12: 1532817392
A13: 10 | B13: Trong đó: Chi phí lãi vay | C13: 5 | D13: 167603935 | E13: 221659846 | F13: 208008837 | G13: 262170575 | H13: 294134531 | I13: 375347816 | J13: 340813568 | K13: 399256526 | L13: 400979485 | M13: 368636370 | N13: 424483338 | O13: 466515776 | P13: 517655739 | Q13: 651086182 | R13: 617884939 | S13: 507919165 | T13: 603465663 | U13: 147007916 | V13: 631302971 | W13: 699695123 | X13: 854484433 | Y13: 862022364 | Z13: 1093552795 | AA13: 539758786 | AB13: 44321388 | AC13: 0 | AD13: 48722388 | AE13: 76187496 | AF13: 68801482 | AG13: 28249626 | AH13: 91396439 | AI13: 93845376 | AJ13: 109400024 | AK13: 129996535 | AL13: 157601782 | AM13: 316883990 | AN13: 460461775 | AO13: 563909516 | AP13: 587315920 | AQ13: 905708142 | AR13: 974310029 | AS13: 1115056080 | AT13: 1160823006 | AU13: 939585045 | AV13: 859444105 | AW13: 840165515 | AX13: 889159081 | AY13: 1032562923 | AZ13: 1114824276 | BA13: 928379281 | BB13: 673966789 | BC13: 888393452 | BD13: 1186588729 | BE13: 1448899822 | BF13: 1242023326 | BG13: 1303560910 | BH13: 1595764355 | BI13: 1368802426 | BJ13: 1256132292 | BK13: 1256103396 | BL13: 1240115065
A14: 11 | B14: 9.Chi phí bán hàng | C14: 5 | K14: 251616145 | L14: 680077987 | M14: 546329598 | N14: 967543289 | O14: 563525432 | P14: 496681104 | Q14: 38696800 | R14: 1520204587 | S14: 3287497220 | T14: 563902784 | U14: 802923682 | V14: 1108487180 | W14: 819028904 | X14: 1282383810 | Y14: 1073636694 | Z14: 1462938929 | AA14: 1937395163 | AB14: 645459129 | AC14: 991254056 | AD14: 1883160244 | AE14: 1145404547 | AF14: 1970368365 | AG14: 1459341885 | AH14: 1450399092 | AI14: 2363556660 | AJ14: 1466584216 | AK14: 2298997918 | AL14: 1849124450 | AM14: 3137962877 | AN14: 2846219487 | AO14: 1219456854 | AP14: 3715738043 | AQ14: 4585159549 | AR14: 1693810954 | AS14: 2407466874 | AT14: 2300964337 | AU14: 8205607205 | AV14: 7036529523 | AW14: 4608951194 | AX14: 1949627546 | AY14: 10266748080 | AZ14: 4006424849 | BA14: 6313682258 | BB14: 5091544776 | BC14: 4077126734 | BD14: 4686536575 | BE14: 4796729528 | BF14: 3449972349 | BG14: 4949095751 | BH14: 2811598286 | BI14: 6688603934 | BJ14: 3413749635 | BK14: 4816680917 | BL14: 3731798004
A15: 12 | B15: 10.Chi phí quản lý doanh nghiệp | C15: 5 | D15: 457415751 | E15: 619384345 | F15: 707076077 | G15: 816715935 | H15: 827613489 | I15: 624184259 | J15: 510720411 | K15: 569609208 | L15: 536039299 | M15: 941857345 | N15: 876385366 | O15: 924977009 | P15: 1435430845 | Q15: 1479188151 | R15: 1624743284 | S15: 1725353483 | T15: 1803134313 | U15: 1872200320 | V15: 1881447518 | W15: 2444716491 | X15: 2755381317 | Y15: 3239626198 | Z15: 3143544394 | AA15: 7358907248 | AB15: 2772788125 | AC15: 2947588122 | AD15: 3098829707 | AE15: 3036290770 | AF15: 3448026712 | AG15: 3261800788 | AH15: 3348437381 | AI15: 1910475796 | AJ15: 3536419913 | AK15: 3592592574 | AL15: 3600549435 | AM15: 4108415230 | AN15: 5241377343 | AO15: 4647980221 | AP15: 4838115306 | AQ15: 5132788494 | AR15: 5665606587 | AS15: 5470797521 | AT15: 5239042307 | AU15: 6065017937 | AV15: 7524726581 | AW15: 7016385931 | AX15: 7426888275 | AY15: 5833487838 | AZ15: 7638868570 | BA15: 7013534740 | BB15: 7332584934 | BC15: 7155903324 | BD15: 7948694673 | BE15: 7721648228 | BF15: 7616453256 | BG15: 7931593154 | BH15: 9422194647 | BI15: 3775611792 | BJ15: 9875644458 | BK15: 15417291967 | BL15: 8394130638
A16: 13 | B16: 11.Lợi nhuận thuần từ hoạt động kinh doanh | C16: 5 | D16: -145242364 | E16: -561242112 | F16: 1079880079 | G16: 412369142 | H16: -831102586 | I16: -937389304 | J16: 5147473719 | K16: 1027070127 | L16: 2126978303 | M16: 469318201 | N16: 27253081 | O16: 100964943 | P16: -364468934 | Q16: -1428839181 | R16: 545981904 | S16: 1650096564 | T16: 2457668110 | U16: 2026651135 | V16: 1378758393 | W16: 3101161984 | X16: 885699606 | Y16: -393669160 | Z16: -1460282402 | AA16: -6524638572 | AB16: 724630559 | AC16: -2654785583 | AD16: -7224620343 | AE16: -2938680602 | AF16: 2786324124 | AG16: 39020306342 | AH16: 4428971361 | AI16: 12407993027 | AJ16: 22901435976 | AK16: 17510693234 | AL16: 9200105319 | AM16: 21966254806 | AN16: 1933695736 | AO16: -5270660796 | AP16: -2937512643 | AQ16: 2475246742 | AR16: -4117202543 | AS16: -10105774890 | AT16: -13571603862 | AU16: -8460674377 | AV16: 9675868151 | AW16: -4807983867 | AX16: -4640581121 | AY16: 114059814051 | AZ16: 5762022698 | BA16: 20541037329 | BB16: 8348281164 | BC16: 4412167173 | BD16: 11097005663 | BE16: 1310222046 | BF16: -1670593931 | BG16: 592817173 | BH16: -11011661349 | BI16: -1686591557 | BJ16: -6668379119 | BK16: 9094326500 | BL16: -1586656660
A17: 14 | B17: 12.Thu nhập khác | C17: 5 | E17: 299375994 | F17: 787003464 | G17: 853324557 | H17: 610174630 | I17: 1291891103 | J17: 8989972067 | K17: 40395118 | L17: 2077248 | M17: 399581022 | N17: 2510200174 | O17: 3395436283 | P17: 5351841304 | Q17: 240544660 | R17: 164167319 | S17: 0 | T17: 397562937 | U17: 263298162 | V17: 116035636 | W17: 406946130 | X17: 1142849269 | Y17: 973159654 | Z17: 4531212183 | AA17: 79168640905 | AB17: 332026 | AC17: 0 | AD17: 2 | AE17: 1 | AG17: 425 | AH17: 0 | AI17: 0 | AJ17: 0 | AK17: 0 | AL17: 8116 | AM17: 17050592 | AN17: 1945 | AO17: 12000 | AP17: 0 | AQ17: 0 | AR17: 203 | AS17: 58510228 | AT17: 52918371 | AU17: 177726993 | AV17: 999 | AW17: 196700 | AX17: 1398763491 | AY17: 1216439 | AZ17: 500207 | BA17: 2492480 | BB17: 2600082 | BC17: 33918440 | BD17: 115000000 | BE17: 2020926 | BF17: 9788652 | BG17: 244500606 | BH17: 742 | BI17: 819591 | BJ17: 110446 | BK17: 42486461 | BL17: 4505
A18: 15 | B18: 13.Chi phí khác | C18: 5 | D18: 77565 | H18: 6136364 | J18: 2000000000 | N18: 2548211605 | Q18: 274745 | R18: 2093722658 | S18: 631668424 | T18: 567391744 | U18: 150706725 | V18: 2322906 | W18: 1880704 | X18: 593797145 | Y18: 15441 | Z18: 441600828 | AA18: 3945908 | AB18: 1 | AC18: 236 | AD18: 0 | AE18: 7135172 | AF18: 3500000 | AG18: 99064 | AH18: 0 | AI18: -36000 | AJ18: 0 | AK18: 0 | AL18: 0 | AM18: 187595749 | AN18: 7958068 | AO18: 1 | AP18: 21796958 | AQ18: 2 | AR18: 36200000 | AS18: 168183405 | AT18: 6000002 | AU18: 601 | AV18: 2601033 | AW18: 170398064 | AX18: 202496 | AY18: 8657082896 | AZ18: 1251667 | BA18: 130033300 | BB18: 0 | BC18: 17808640 | BD18: 600 | BE18: 50477376 | BF18: 130663204 | BG18: 539898446 | BH18: 539664890 | BI18: 3515574706 | BJ18: 1106262251 | BK18: 1603033842 | BL18: 106808581
A19: 16 | B19: 14.Lợi nhuận khác | C19: 5 | D19: -77565 | E19: 299375994 | F19: 787003464 | G19: 853324557 | H19: 604038266 | I19: 1291891103 | J19: 6989972067 | K19: 40395118 | L19: 2077248 | M19: 399581022 | N19: -38011431 | O19: 3395436283 | P19: 5351841304 | Q19: 240269915 | R19: -1929555339 | S19: -631668424 | T19: -169828807 | U19: 112591437 | V19: 113712730 | W19: 405065426 | X19: 549052124 | Y19: 973144213 | Z19: 4089611355 | AA19: 79164694997 | AB19: 332025 | AC19: -236 | AD19: 2 | AE19: -7135171 | AF19: -3500000 | AG19: -98639 | AH19: 0 | AI19: 36000 | AJ19: 0 | AK19: 0 | AL19: 8116 | AM19: -170545157 | AN19: -7956123 | AO19: 11999 | AP19: -21796958 | AQ19: -2 | AR19: -36199797 | AS19: -109673177 | AT19: 46918369 | AU19: 177726392 | AV19: -2600034 | AW19: -170201364 | AX19: 1398560995 | AY19: -8655866457 | AZ19: -751460 | BA19: -127540820 | BB19: 2600082 | BC19: 16109800 | BD19: 114999400 | BE19: -48456450 | BF19: -120874552 | BG19: -295397840 | BH19: -539664148 | BI19: -3514755115 | BJ19: -1106151805 | BK19: -1560547381 | BL19: -106804076
A20: 17 | B20: 15.Tổng lợi nhuận kế toán trước thuế | C20: 5 | D20: -145319929 | E20: -261866118 | F20: 1866883543 | G20: 1265693699 | H20: -227064320 | I20: 354501799 | J20: 12137445786 | K20: 1067465245 | L20: 2129055551 | M20: 868899223 | N20: -10758350 | O20: 3496401226 | P20: 4987372370 | Q20: -1188569266 | R20: -1383573435 | S20: 1018428140 | T20: 2287107255 | U20: 2139242572 | V20: 1492471123 | W20: 3506227410 | X20: 1434751730 | Y20: 579475053 | Z20: 2629328953 | AA20: 72640056425 | AB20: 724962584 | AC20: -2654785819 | AD20: -7224620341 | AE20: -2945815773 | AF20: 2782824124 | AG20: 39020207703 | AH20: 4428971361 | AI20: 12408029027 | AJ20: 22901435976 | AK20: 17510693234 | AL20: 9200113435 | AM20: 21795709649 | AN20: 1925739613 | AO20: -5270648797 | AP20: -2959309601 | AQ20: 2475246740 | AR20: -4153402340 | AS20: -10215448067 | AT20: -13524685493 | AU20: -8282947985 | AV20: 9673268117 | AW20: -4978185231 | AX20: -3242020126 | AY20: 105403947594 | AZ20: 5761271238 | BA20: 20413496509 | BB20: 8350881246 | BC20: 4428276973 | BD20: 11212005063 | BE20: 1261765596 | BF20: -1791468483 | BG20: 297419333 | BH20: -11551325497 | BI20: -5201346672 | BJ20: -7774530924 | BK20: 7533779119 | BL20: -1693460736
A21: 18 | B21: 16.Chi phí thuế TNDN hiện hành | C21: 5 | F21: 373376709 | G21: 253138740 | I21: 70900360 | J21: 2427489157 | K21: 213493049 | L21: 425811110 | M21: 173779845 | O21: 699280245 | P21: 997474474 | Q21: 0 | R21: 0 | S21: 203685628 | T21: 457567861 | U21: 427848514 | V21: 298494225 | W21: 701245482 | X21: 286950346 | Y21: 115895011 | Z21: 525865791 | AA21: 14528011285 | AB21: 144992517 | AC21: 0 | AG21: 5795561979 | AH21: 885794272 | AI21: 2481605805 | AJ21: 4580287195 | AK21: 3502138647 | AL21: 1840022687 | AM21: 0 | AN21: 0 | AP21: 0 | AQ21: 0 | AR21: 0 | AS21: 0 | AT21: 0 | AU21: 0 | AV21: 0 | AX21: 0 | AY21: 11495266455 | AZ21: 864190686 | BA21: 3020742780 | BB21: 1252632187 | BC21: 677293488 | BD21: 1681800759 | BE21: 189264839 | BF21: -1000088030 | BG21: 204199602 | BH21: -1349170846 | BI21: -516688622 | BJ21: -854033077 | BK21: 3315095788 | BL21: 0
A22: 19 | B22: 17.Chi phí thuế TNDN hoãn lại | C22: 5 | Q22: 0 | R22: 0 | S22: 0 | X22: 0 | Z22: 0 | AA22: 0 | AC22: 0 | AD22: 0 | AE22: 0 | AG22: 0 | AH22: 0 | AI22: 0 | AJ22: 0 | AK22: 0 | AL22: 0 | AM22: 0 | AN22: 0 | AO22: 0 | AP22: 0 | AQ22: 0 | AR22: 0 | AS22: 0 | AT22: 0 | AU22: 0 | AV22: 0 | AX22: 0 | AY22: 1838941310 | AZ22: 0 | BA22: -8043000 | BB22: 0 | BC22: 0 | BE22: 0 | BF22: -1830898310 | BG22: 0 | BH22: 0 | BI22: 0 | BJ22: 0 | BK22: 0 | BL22: 0
A23: 20 | B23: 18.Lợi nhuận sau thuế thu nhập doanh nghiệp | C23: 5 | D23: -145319929 | E23: -261866118 | F23: 1493506834 | G23: 1012554959 | H23: -227064320 | I23: 283601439 | J23: 9709956629 | K23: 853972196 | L23: 1703244441 | M23: 695119378 | N23: -10758350 | O23: 2797120981 | P23: 3989897896 | Q23: -1188569266 | R23: -1383573435 | S23: 814742512 | T23: 1829539394 | U23: 1711394058 | V23: 1193976898 | W23: 2804981928 | X23: 1147801384 | Y23: 463580042 | Z23: 2103463162 | AA23: 58112045140 | AB23: 579970067 | AC23: -2654785819 | AD23: -7224620341 | AE23: -2945815773 | AF23: 2782824124 | AG23: 33224645724 | AH23: 3543177089 | AI23: 9926423222 | AJ23: 18321148781 | AK23: 14008554587 | AL23: 7360090748 | AM23: 21795709649 | AN23: 1925739613 | AO23: -5270648797 | AP23: -2959309601 | AQ23: 2475246740 | AR23: -4153402340 | AS23: -10215448067 | AT23: -13524685493 | AU23: -8282947985 | AV23: 9673268117 | AW23: -4978185231 | AX23: -3242020126 | AY23: 92069739829 | AZ23: 4897080552 | BA23: 17400796729 | BB23: 7098249059 | BC23: 3750983485 | BD23: 9530204304 | BE23: 1072500757 | BF23: 1039517857 | BG23: 93219731 | BH23: -10202154651 | BI23: -4684658050 | BJ23: -6920497847 | BK23: 4218683331 | BL23: -1693460736

Sheet BCTC2025-Sau loại trừ
E1: BÁO CÁO TÀI CHÍNH NĂM 2025
R2: =MONTH(TODAY())-1 -> 5 | V2: 25000
B3: BẢNG CÂN ĐỐI KẾ TOÁN | C3: T01.2025 | D3: T02.2025 | E3: T03.2025 | F3: T04.2025 | G3: T05.2025 | H3: T06.2025 | I3: T07.2025 | J3: T08.2025 | K3: T09.2025 | L3: T10.2025 | M3: T11.2025 | N3: T12.2025 | P3: Q01.2025 | Q3: Q02.2025 | R3: Q03.2025 | S3: Q04.2025 | U3: Lũy kế năm 2025 | V3: US $ | W3: %/Tổng TS
B4: A-TÀI SẢN NGẮN HẠN | C4: =C5+C8+C12+C21+C24 -> #REF! | D4: =D5+D8+D12+D21+D24 -> #REF! | E4: =E5+E8+E12+E21+E24 -> #REF! | F4: =F5+F8+F12+F21+F24 -> #REF! | G4: =G5+G8+G12+G21+G24 -> #REF! | H4: =H5+H8+H12+H21+H24 -> #REF! | I4: =I5+I8+I12+I21+I24 -> #REF! | J4: =J5+J8+J12+J21+J24 -> #REF! | ... N4: =N5+N8+N12+N21+N24 -> #REF! | P4: =C4 -> #REF! | Q4: =H4 -> #REF! | R4: =K4 -> #REF! | S4: =N4 -> #REF! | U4: =C4 -> #REF! | V4: =U4/$V$2 -> #REF! | W4: =U4/$U$66 -> #REF! | X4: =U4-BCTC2026!V4 -> #REF!
B5: I.Tiền và các khoản tương đương tiền | C5: =SUM(C6:C7) -> 42126572011 | D5: =SUM(D6:D7) -> 45981412915 | E5: =SUM(E6:E7) -> 33613094972 | F5: =SUM(F6:F7) -> 47135211556 | G5: =SUM(G6:G7) -> 41014004605 | H5: =SUM(H6:H7) -> 0 | I5: =SUM(I6:I7) -> 0 | J5: =SUM(J6:J7) -> 0 | ... N5: =SUM(N6:N7) -> 0 | P5: =C5 -> 42126572011 | Q5: =H5 -> 0 | R5: =K5 -> 0 | S5: =N5 -> 0 | U5: =C5 -> 42126572011 | V5: =U5/$V$2 -> 1685062.9 | W5: =U5/$U$66 -> #REF! | X5: =U5-BCTC2026!V5 -> 1112567406
B6: 1.Tiền | C6: =BCTC2026!D6 -> 42126572011 | D6: =BCTC2026!E6 -> 45981412915 | E6: =BCTC2026!F6 -> 27413094972 | F6: =BCTC2026!G6 -> 28835211556 | G6: =BCTC2026!H6 -> 30714004605 | H6: =BCTC2026!I6 -> 0 | I6: =BCTC2026!J6 -> 0 | J6: =BCTC2026!K6 -> 0 | ... N6: =BCTC2026!O6 -> 0 | P6: =C6 -> 42126572011 | Q6: =H6 -> 0 | R6: =K6 -> 0 | S6: =N6 -> 0 | U6: =C6 -> 42126572011 | V6: =U6/$V$2 -> 1685062.9 | W6: =U6/$U$66 -> #REF! | X6: =U6-BCTC2026!V6 -> 11412567406
B7: 2.Các khoản tương đương tiền | C7: =BCTC2026!D7 -> 0 | D7: =BCTC2026!E7 -> 0 | E7: =BCTC2026!F7 -> 6200000000 | F7: =BCTC2026!G7 -> 18300000000 | G7: =BCTC2026!H7 -> 10300000000 | H7: =BCTC2026!I7 -> 0 | I7: =BCTC2026!J7 -> 0 | J7: =BCTC2026!K7 -> 0 | ... L7: =BCTC2026!M7 -> 0 | N7: =BCTC2026!O7 -> 0 | P7: =C7 -> 0 | Q7: =H7 -> 0 | R7: =K7 -> 0 | S7: =N7 -> 0 | U7: =C7 -> 0 | V7: =U7/$V$2 -> 0 | W7: 0 | X7: =U7-BCTC2026!V7 -> -10300000000
B8: II.Các khoản đầu tư tài chính ngắn hạn | C8: =SUM(C9:C11) -> 32840000000 | D8: =SUM(D9:D11) -> 32840000000 | E8: =SUM(E9:E11) -> 32840000000 | F8: =SUM(F9:F11) -> 34340000000 | G8: =SUM(G9:G11) -> 34340000000 | H8: =SUM(H9:H11) -> 0 | I8: =SUM(I9:I11) -> 0 | J8: =SUM(J9:J11) -> 0 | ... N8: =SUM(N9:N11) -> 0 | P8: =C8 -> 32840000000 | Q8: =H8 -> 0 | R8: =K8 -> 0 | S8: =N8 -> 0 | U8: =C8 -> 32840000000 | V8: =U8/$V$2 -> 1313600 | W8: 0 | X8: =U8-BCTC2026!V8 -> -1500000000
B9: 1.Chứng khoán kinh doanh | C9: =BCTC2026!D9 -> 0 | D9: =BCTC2026!E9 -> 0 | E9: =BCTC2026!F9 -> 0 | F9: =BCTC2026!G9 -> 0 | G9: =BCTC2026!H9 -> 0 | H9: =BCTC2026!I9 -> 0 | I9: =BCTC2026!J9 -> 0 | J9: =BCTC2026!K9 -> 0 | ... L9: =BCTC2026!M9 -> 0 | P9: =C9 -> 0 | Q9: =H9 -> 0 | R9: =K9 -> 0 | S9: =N9 -> 0 | U9: =C9 -> 0 | V9: =U9/$V$2 -> 0 | W9: 0 | X9: =U9-BCTC2026!V9 -> 0
B10: 2.Dự phòng giảm giá chứng khoán kinh doanh (*) | C10: =BCTC2026!D10 -> 0 | D10: =BCTC2026!E10 -> 0 | E10: =BCTC2026!F10 -> 0 | F10: =BCTC2026!G10 -> 0 | G10: =BCTC2026!H10 -> 0 | H10: =BCTC2026!I10 -> 0 | I10: =BCTC2026!J10 -> 0 | J10: =BCTC2026!K10 -> 0 | ... L10: =BCTC2026!M10 -> 0 | P10: =C10 -> 0 | Q10: =H10 -> 0 | R10: =K10 -> 0 | S10: =N10 -> 0 | U10: =C10 -> 0 | V10: =U10/$V$2 -> 0 | W10: 0 | X10: =U10-BCTC2026!V10 -> 0
B11: 3.Đầu tư nắm giữ đến ngày đáo hạn | C11: =BCTC2026!D11 -> 32840000000 | D11: =BCTC2026!E11 -> 32840000000 | E11: =BCTC2026!F11 -> 32840000000 | F11: =BCTC2026!G11 -> 34340000000 | G11: =BCTC2026!H11 -> 34340000000 | H11: =BCTC2026!I11 -> 0 | I11: =BCTC2026!J11 -> 0 | J11: =BCTC2026!K11 -> 0 | ... N11: =BCTC2026!O11 -> 0 | P11: =C11 -> 32840000000 | Q11: =H11 -> 0 | R11: =K11 -> 0 | S11: =N11 -> 0 | U11: =C11 -> 32840000000 | V11: =U11/$V$2 -> 1313600 | W11: 0 | X11: =U11-BCTC2026!V11 -> -1500000000
B12: III.Các khoản phải thu | C12: =SUM(C13:C20) -> #REF! | D12: =SUM(D13:D20) -> #REF! | E12: =SUM(E13:E20) -> #REF! | F12: =SUM(F13:F20) -> #REF! | G12: =SUM(G13:G20) -> #REF! | H12: =SUM(H13:H20) -> #REF! | I12: =SUM(I13:I20) -> #REF! | J12: =SUM(J13:J20) -> #REF! | ... N12: =SUM(N13:N20) -> #REF! | P12: =C12 -> #REF! | Q12: =H12 -> #REF! | R12: =K12 -> #REF! | S12: =N12 -> #REF! | U12: =C12 -> #REF! | V12: =U12/$V$2 -> #REF! | W12: =U12/$U$66 -> #REF! | X12: =U12-BCTC2026!V12 -> #REF!
B13: 1.Phải thu ngắn hạn của khách hàng | C13: =BCTC2026!D13 -> 132649296167 | D13: =BCTC2026!E13 -> 140446291758 | E13: =BCTC2026!F13 -> 153248625708 | F13: =BCTC2026!G13 -> 178191270169 | G13: =BCTC2026!H13 -> 178005616424 | H13: =BCTC2026!I13 -> 0 | I13: =BCTC2026!J13 -> 0 | J13: =BCTC2026!K13 -> 0 | ... N13: =BCTC2026!O13 -> 0 | P13: =C13 -> 132649296167 | Q13: =H13 -> 0 | R13: =K13 -> 0 | S13: =N13 -> 0 | U13: =C13 -> 132649296167 | V13: =U13/$V$2 -> 5305971.8 | W13: =U13/$U$66 -> #REF! | X13: =U13-BCTC2026!V13 -> -45356320257
B14: 2.Trả trước cho người bán ngắn hạn | C14: =BCTC2026!D14 -> 75878310145 | D14: =BCTC2026!E14 -> 82113512006 | E14: =BCTC2026!F14 -> 95312309944 | F14: =BCTC2026!G14 -> 77634941776 | G14: =BCTC2026!H14 -> 162931057926 | H14: =BCTC2026!I14 -> 0 | I14: =BCTC2026!J14 -> 0 | J14: =BCTC2026!K14 -> 0 | ... N14: =BCTC2026!O14 -> 0 | P14: =C14 -> 75878310145 | Q14: =H14 -> 0 | R14: =K14 -> 0 | S14: =N14 -> 0 | U14: =C14 -> 75878310145 | V14: =U14/$V$2 -> 3035132.4 | W14: =U14/$U$66 -> #REF! | X14: =U14-BCTC2026!V14 -> -87052747781
B15: 3.Phải thu nội bộ ngắn hạn | C15: =BCTC2026!D15 -> 0 | D15: =BCTC2026!E15 -> 0 | E15: =BCTC2026!F15 -> 0 | F15: =BCTC2026!G15 -> 0 | G15: =BCTC2026!H15 -> 0 | H15: =BCTC2026!I15 -> 0 | I15: =BCTC2026!J15 -> 0 | J15: =BCTC2026!K15 -> 0 | ... L15: =BCTC2026!M15 -> 0 | M15: 0 | P15: =C15 -> 0 | Q15: =H15 -> 0 | R15: =K15 -> 0 | S15: =N15 -> 0 | U15: =C15 -> 0 | V15: =U15/$V$2 -> 0 | W15: 0 | X15: =U15-BCTC2026!V15 -> 0
B16: 4.Phải thu theo tiến độ kế hoạch hợp đồng XD | C16: =BCTC2026!D16 -> 0 | D16: =BCTC2026!E16 -> 0 | E16: =BCTC2026!F16 -> 0 | F16: =BCTC2026!G16 -> 0 | G16: =BCTC2026!H16 -> 0 | H16: =BCTC2026!I16 -> 0 | I16: =BCTC2026!J16 -> 0 | J16: =BCTC2026!K16 -> 0 | ... L16: =BCTC2026!M16 -> 0 | M16: 0 | P16: =C16 -> 0 | Q16: =H16 -> 0 | R16: =K16 -> 0 | S16: =N16 -> 0 | U16: =C16 -> 0 | V16: =U16/$V$2 -> 0 | W16: 0 | X16: =U16-BCTC2026!V16 -> 0
B17: 5.Phải thu về cho vay ngắn hạn | C17: =BCTC2026!#REF! -> #REF! | D17: =BCTC2026!#REF! -> #REF! | E17: =BCTC2026!#REF! -> #REF! | F17: =BCTC2026!#REF! -> #REF! | G17: =BCTC2026!#REF! -> #REF! | H17: =BCTC2026!#REF! -> #REF! | I17: =BCTC2026!#REF! -> #REF! | J17: =BCTC2026!#REF! -> #REF! | ... N17: =BCTC2026!#REF! -> #REF! | P17: =C17 -> #REF! | Q17: =H17 -> #REF! | R17: =K17 -> #REF! | S17: =N17 -> #REF! | U17: =C17 -> #REF! | V17: =U17/$V$2 -> #REF! | W17: =U17/$U$66 -> #REF! | X17: =U17-BCTC2026!#REF! -> #REF!
B18: 6.Phải thu ngắn hạn khác | C18: =BCTC2026!D17 -> 54586491575 | D18: =BCTC2026!E17 -> 66773872669 | E18: =BCTC2026!F17 -> 82135205395 | F18: =BCTC2026!G17 -> 73268597741 | G18: =BCTC2026!H17 -> 76382324781 | H18: =BCTC2026!I17 -> 0 | I18: =BCTC2026!J17 -> 0 | J18: =BCTC2026!K17 -> 0 | ... N18: =BCTC2026!O17 -> 0 | P18: =C18 -> 54586491575 | Q18: =H18 -> 0 | R18: =K18 -> 0 | S18: =N18 -> 0 | U18: =C18 -> 54586491575 | V18: =U18/$V$2 -> 2183459.7 | W18: =U18/$U$66 -> #REF! | X18: =U18-BCTC2026!V17 -> -21795833206
B19: 7.Dự phòng phải thu ngắn hạn khó đòi(*) | C19: =BCTC2026!D18 -> -609095700 | D19: =BCTC2026!E18 -> -609095700 | E19: =BCTC2026!F18 -> -609095700 | F19: =BCTC2026!G18 -> -609095700 | G19: =BCTC2026!H18 -> -609095700 | H19: =BCTC2026!I18 -> 0 | I19: =BCTC2026!J18 -> 0 | J19: =BCTC2026!K18 -> 0 | ... L19: =BCTC2026!M18 -> 0 | M19: 0 | P19: =C19 -> -609095700 | Q19: =H19 -> 0 | R19: =K19 -> 0 | S19: =N19 -> 0 | U19: =C19 -> -609095700 | V19: =U19/$V$2 -> -24363.828 | W19: 0 | X19: =U19-BCTC2026!V18 -> 0
B20: 8.Tài sản thiếu chờ xử lý | C20: =BCTC2026!D19 -> 1119913958 | D20: =BCTC2026!E19 -> 1255721846 | E20: =BCTC2026!F19 -> 1255721846 | F20: =BCTC2026!G19 -> 1255721846 | G20: =BCTC2026!H19 -> 682953698 | H20: =BCTC2026!I19 -> 0 | I20: =BCTC2026!J19 -> 0 | J20: =BCTC2026!K19 -> 0 | ... N20: =BCTC2026!O19 -> 0 | P20: =C20 -> 1119913958 | Q20: =H20 -> 0 | R20: =K20 -> 0 | S20: =N20 -> 0 | U20: =C20 -> 1119913958 | V20: =U20/$V$2 -> 44796.558 | W20: =U20/$U$66 -> #REF! | X20: =U20-BCTC2026!V19 -> 436960260
B21: IV. Hàng tồn kho | C21: =SUM(C22:C23) -> 534105826237 | D21: =SUM(D22:D23) -> 502545827363 | E21: =SUM(E22:E23) -> 425450972162 | F21: =SUM(F22:F23) -> 370413533224 | G21: =SUM(G22:G23) -> 361880765551 | H21: =SUM(H22:H23) -> 0 | I21: =SUM(I22:I23) -> 0 | J21: =SUM(J22:J23) -> 0 | ... N21: =SUM(N22:N23) -> 0 | P21: =C21 -> 534105826237 | Q21: =H21 -> 0 | R21: =K21 -> 0 | S21: =N21 -> 0 | U21: =C21 -> 534105826237 | V21: =U21/$V$2 -> 21364233 | W21: =U21/$U$66 -> #REF! | X21: =U21-BCTC2026!V20 -> 172225060686
B22: 1.Hàng tồn kho | C22: =BCTC2026!D21 -> 534105826237 | D22: =BCTC2026!E21 -> 502545827363 | E22: =BCTC2026!F21 -> 425450972162 | F22: =BCTC2026!G21 -> 370413533224 | G22: =BCTC2026!H21 -> 361880765551 | H22: =BCTC2026!I21 -> 0 | I22: =BCTC2026!J21 -> 0 | J22: =BCTC2026!K21 -> 0 | ... N22: =BCTC2026!O21 -> 0 | P22: =C22 -> 534105826237 | Q22: =H22 -> 0 | R22: =K22 -> 0 | S22: =N22 -> 0 | U22: =C22 -> 534105826237 | V22: =U22/$V$2 -> 21364233 | W22: =U22/$U$66 -> #REF! | X22: =U22-BCTC2026!V21 -> 172225060686
B23: 2.Dự phòng giảm giá hàng tồn kho (*) | C23: =BCTC2026!D22 -> 0 | D23: =BCTC2026!E22 -> 0 | E23: =BCTC2026!F22 -> 0 | F23: =BCTC2026!G22 -> 0 | G23: =BCTC2026!H22 -> 0 | H23: =BCTC2026!I22 -> 0 | I23: =BCTC2026!J22 -> 0 | J23: =BCTC2026!K22 -> 0 | ... L23: =BCTC2026!M22 -> 0 | P23: =C23 -> 0 | Q23: =H23 -> 0 | R23: =K23 -> 0 | S23: =N23 -> 0 | U23: =C23 -> 0 | V23: =U23/$V$2 -> 0 | W23: 0 | X23: =U23-BCTC2026!V22 -> 0
B24: V. Tài sản ngắn hạn khác | C24: =SUM(C25:C29) -> 21453377952 | D24: =SUM(D25:D29) -> 24154779219 | E24: =SUM(E25:E29) -> 25221641625 | F24: =SUM(F25:F29) -> 26322155642 | G24: =SUM(G25:G29) -> 31960741740 | H24: =SUM(H25:H29) -> 0 | I24: =SUM(I25:I29) -> 0 | J24: =SUM(J25:J29) -> 0 | ... N24: =SUM(N25:N29) -> 0 | P24: =C24 -> 21453377952 | Q24: =H24 -> 0 | R24: =K24 -> 0 | S24: =N24 -> 0 | U24: =C24 -> 21453377952 | V24: =U24/$V$2 -> 858135.12 | W24: =U24/$U$66 -> #REF! | X24: =U24-BCTC2026!V27 -> -10507363788
B25: 1.Chi phí trả trước ngắn hạn | C25: =BCTC2026!D28 -> 6232956370 | D25: =BCTC2026!E28 -> 5669668845 | E25: =BCTC2026!F28 -> 6281586071 | F25: =BCTC2026!G28 -> 7111878966 | G25: =BCTC2026!H28 -> 7978130611 | H25: =BCTC2026!I28 -> 0 | I25: =BCTC2026!J28 -> 0 | J25: =BCTC2026!K28 -> 0 | ... N25: =BCTC2026!O28 -> 0 | P25: =C25 -> 6232956370 | Q25: =H25 -> 0 | R25: =K25 -> 0 | S25: =N25 -> 0 | U25: =C25 -> 6232956370 | V25: =U25/$V$2 -> 249318.25 | W25: =U25/$U$66 -> #REF! | X25: =U25-BCTC2026!V28 -> -1745174241
B26: 2.Thuế GTGT được khấu trừ | C26: =BCTC2026!D29 -> 14900314879 | D26: =BCTC2026!E29 -> 18117486770 | E26: =BCTC2026!F29 -> 18457562435 | F26: =BCTC2026!G29 -> 18721692095 | G26: =BCTC2026!H29 -> 23467402224 | H26: =BCTC2026!I29 -> 0 | I26: =BCTC2026!J29 -> 0 | J26: =BCTC2026!K29 -> 0 | ... N26: =BCTC2026!O29 -> 0 | P26: =C26 -> 14900314879 | Q26: =H26 -> 0 | R26: =K26 -> 0 | S26: =N26 -> 0 | U26: =C26 -> 14900314879 | V26: =U26/$V$2 -> 596012.6 | W26: =U26/$U$66 -> #REF! | X26: =U26-BCTC2026!V29 -> -8567087345
B27: 3.Thuế và các khoản khác phải thu Nhà nước | C27: =BCTC2026!D30 -> 320106703 | D27: =BCTC2026!E30 -> 367623604 | E27: =BCTC2026!F30 -> 482493119 | F27: =BCTC2026!G30 -> 488584581 | G27: =BCTC2026!H30 -> 515208905 | H27: =BCTC2026!I30 -> 0 | I27: =BCTC2026!J30 -> 0 | J27: =BCTC2026!K30 -> 0 | ... N27: =BCTC2026!O30 -> 0 | P27: =C27 -> 320106703 | Q27: =H27 -> 0 | R27: =K27 -> 0 | S27: =N27 -> 0 | U27: =C27 -> 320106703 | V27: =U27/$V$2 -> 12804.268 | W27: 0 | X27: =U27-BCTC2026!V30 -> -195102202
B28: 4.Giao dịch mua bán lại trái phiếu Nhà nước | C28: =BCTC2026!D31 -> 0 | D28: =BCTC2026!E31 -> 0 | E28: =BCTC2026!F31 -> 0 | F28: =BCTC2026!G31 -> 0 | G28: =BCTC2026!H31 -> 0 | H28: =BCTC2026!I31 -> 0 | I28: =BCTC2026!J31 -> 0 | J28: =BCTC2026!K31 -> 0 | ... L28: =BCTC2026!M31 -> 0 | P28: =C28 -> 0 | Q28: =H28 -> 0 | R28: =K28 -> 0 | S28: =N28 -> 0 | U28: =C28 -> 0 | V28: =U28/$V$2 -> 0 | W28: 0 | X28: =U28-BCTC2026!V31 -> 0
B29: 5.Tài sản ngắn hạn khác | C29: =BCTC2026!D32 -> 0 | D29: =BCTC2026!E32 -> 0 | E29: =BCTC2026!F32 -> 0 | F29: =BCTC2026!G32 -> 0 | G29: =BCTC2026!H32 -> 0 | H29: =BCTC2026!I32 -> 0 | I29: =BCTC2026!J32 -> 0 | J29: =BCTC2026!K32 -> 0 | ... L29: =BCTC2026!M32 -> 0 | P29: =C29 -> 0 | Q29: =H29 -> 0 | R29: =K29 -> 0 | S29: =N29 -> 0 | U29: =C29 -> 0 | V29: =U29/$V$2 -> 0 | W29: 0 | X29: =U29-BCTC2026!V32 -> 0
B30: B-TÀI SẢN DÀI HẠN | C30: =C31+C39+C49+C52+C55+C61 -> #REF! | D30: =D31+D39+D49+D52+D55+D61 -> 332184615231 | E30: =E31+E39+E49+E52+E55+E61 -> 338279580240 | F30: =F31+F39+F49+F52+F55+F61 -> 359733489326 | G30: =G31+G39+G49+G52+G55+G61 -> 359998697681 | H30: =H31+H39+H49+H52+H55+H61 -> 0 | I30: =I31+I39+I49+I52+I55+I61 -> 0 | J30: =J31+J39+J49+J52+J55+J61 -> 0 | ... N30: =N31+N39+N49+N52+N55+N61 -> 0 | P30: =C30 -> #REF! | Q30: =H30 -> 0 | R30: =K30 -> 0 | S30: =N30 -> 0 | U30: =C30 -> #REF! | V30: =U30/$V$2 -> #REF! | W30: =U30/$U$66 -> #REF! | X30: =U30-BCTC2026!V33 -> #REF!
B31: I- Các khoản phải thu dài hạn | C31: =SUM(C32:C38) -> #REF! | D31: 0 | E31: 0 | F31: 0 | G31: 0 | H31: 0 | I31: 0 | J31: 0 | K31: 0 | L31: 0 | P31: =C31 -> #REF! | Q31: =H31 -> 0 | R31: =K31 -> 0 | S31: =N31 -> 0 | U31: =C31 -> #REF! | V31: =U31/$V$2 -> #REF! | X31: =U31-BCTC2026!V34 -> #REF!
B32: 1.Phải thu dài hạn của khách hàng | C32: =BCTC2026!D35 -> 0 | D32: =BCTC2026!E35 -> 0 | E32: =BCTC2026!F35 -> 0 | F32: =BCTC2026!G35 -> 0 | G32: =BCTC2026!H35 -> 0 | H32: =BCTC2026!I35 -> 0 | I32: =BCTC2026!J35 -> 0 | J32: =BCTC2026!K35 -> 0 | ... L32: =BCTC2026!M35 -> 0 | P32: =C32 -> 0 | Q32: =H32 -> 0 | R32: =K32 -> 0 | S32: =N32 -> 0 | U32: =C32 -> 0 | V32: =U32/$V$2 -> 0 | X32: =U32-BCTC2026!V35 -> 0
B33: 2.Trả trước cho người bán dài hạn | C33: =BCTC2026!D36 -> 0 | D33: =BCTC2026!E36 -> 0 | E33: =BCTC2026!F36 -> 0 | F33: =BCTC2026!G36 -> 0 | G33: =BCTC2026!H36 -> 0 | H33: =BCTC2026!I36 -> 0 | I33: =BCTC2026!J36 -> 0 | J33: =BCTC2026!K36 -> 0 | ... L33: =BCTC2026!M36 -> 0 | P33: =C33 -> 0 | Q33: =H33 -> 0 | R33: =K33 -> 0 | S33: =N33 -> 0 | U33: =C33 -> 0 | V33: =U33/$V$2 -> 0 | X33: =U33-BCTC2026!V36 -> 0
B34: 3.Vốn kinh doanh ở đơn vị trực thuộc | C34: =BCTC2026!D37 -> 0 | D34: =BCTC2026!E37 -> 0 | E34: =BCTC2026!F37 -> 0 | F34: =BCTC2026!G37 -> 0 | G34: =BCTC2026!H37 -> 0 | H34: =BCTC2026!I37 -> 0 | I34: =BCTC2026!J37 -> 0 | J34: =BCTC2026!K37 -> 0 | ... L34: =BCTC2026!M37 -> 0 | P34: =C34 -> 0 | Q34: =H34 -> 0 | R34: =K34 -> 0 | S34: =N34 -> 0 | U34: =C34 -> 0 | V34: =U34/$V$2 -> 0 | W34: 0 | X34: =U34-BCTC2026!V37 -> 0
B35: 4.Phải thu dài hạn nội bộ | C35: =BCTC2026!D38 -> 0 | D35: =BCTC2026!E38 -> 0 | E35: =BCTC2026!F38 -> 0 | F35: =BCTC2026!G38 -> 0 | G35: =BCTC2026!H38 -> 0 | H35: =BCTC2026!I38 -> 0 | I35: =BCTC2026!J38 -> 0 | J35: =BCTC2026!K38 -> 0 | ... L35: =BCTC2026!M38 -> 0 | P35: =C35 -> 0 | Q35: =H35 -> 0 | R35: =K35 -> 0 | S35: =N35 -> 0 | U35: =C35 -> 0 | V35: =U35/$V$2 -> 0 | W35: 0 | X35: =U35-BCTC2026!V38 -> 0
B36: 5.Phải thu về cho vay dài hạn | C36: =BCTC2026!#REF! -> #REF! | D36: =BCTC2026!#REF! -> #REF! | E36: =BCTC2026!#REF! -> #REF! | F36: =BCTC2026!#REF! -> #REF! | G36: =BCTC2026!#REF! -> #REF! | H36: =BCTC2026!#REF! -> #REF! | I36: =BCTC2026!#REF! -> #REF! | J36: =BCTC2026!#REF! -> #REF! | ... L36: =BCTC2026!#REF! -> #REF! | P36: =C36 -> #REF! | Q36: =H36 -> #REF! | R36: =K36 -> #REF! | S36: =N36 -> 0 | U36: =C36 -> #REF! | V36: =U36/$V$2 -> #REF! | W36: 0 | X36: =U36-BCTC2026!#REF! -> #REF!
B37: 6.Phải thu dài hạn khác | C37: =BCTC2026!D39 -> 5315314211 | D37: =BCTC2026!E39 -> 5315314211 | E37: =BCTC2026!F39 -> 5315314211 | F37: =BCTC2026!G39 -> 5315314210 | G37: =BCTC2026!H39 -> 5315314210 | H37: =BCTC2026!I39 -> 0 | I37: =BCTC2026!J39 -> 0 | J37: =BCTC2026!K39 -> 0 | ... L37: =BCTC2026!M39 -> 0 | P37: =C37 -> 5315314211 | Q37: =H37 -> 0 | R37: =K37 -> 0 | S37: =N37 -> 0 | U37: =C37 -> 5315314211 | V37: =U37/$V$2 -> 212612.57 | X37: =U37-BCTC2026!V39 -> 1
B38: 7.Dự phòng phải thu dài hạn khó đòi (*) | C38: =BCTC2026!D40 -> 0 | D38: =BCTC2026!E40 -> 0 | E38: =BCTC2026!F40 -> 0 | F38: =BCTC2026!G40 -> 0 | G38: =BCTC2026!H40 -> 0 | H38: =BCTC2026!I40 -> 0 | I38: =BCTC2026!J40 -> 0 | J38: =BCTC2026!K40 -> 0 | ... L38: =BCTC2026!M40 -> 0 | P38: =C38 -> 0 | Q38: =H38 -> 0 | R38: =K38 -> 0 | S38: =N38 -> 0 | U38: =C38 -> 0 | V38: =U38/$V$2 -> 0 | W38: 0 | X38: =U38-BCTC2026!V40 -> 0
B39: II.Tài sản cố định | C39: =C40+C43+C46 -> 243650467528 | D39: =D40+D43+D46 -> 244965950858 | E39: =E40+E43+E46 -> 265786488609 | F39: =F40+F43+F46 -> 270226692853 | G39: =G40+G43+G46 -> 268070715296 | H39: =H40+H43+H46 -> 0 | I39: =I40+I43+I46 -> 0 | J39: =J40+J43+J46 -> 0 | ... N39: =N40+N43+N46 -> 0 | P39: =C39 -> 243650467528 | Q39: =H39 -> 0 | R39: =K39 -> 0 | S39: =N39 -> 0 | U39: =C39 -> 243650467528 | V39: =U39/$V$2 -> 9746018.7 | W39: =U39/$U$66 -> #REF! | X39: =U39-BCTC2026!V41 -> -24420247768
B40: 1.Tài sản cố định hữu hình | C40: =SUM(C41:C42) -> 222439215846 | D40: =SUM(D41:D42) -> 223939131389 | E40: =SUM(E41:E42) -> 244944101358 | F40: =SUM(F41:F42) -> 249568737825 | G40: =SUM(G41:G42) -> 247597192480 | H40: =SUM(H41:H42) -> 0 | I40: =SUM(I41:I42) -> 0 | J40: =SUM(J41:J42) -> 0 | ... N40: =SUM(N41:N42) -> 0 | P40: =C40 -> 222439215846 | Q40: =H40 -> 0 | R40: =K40 -> 0 | S40: =N40 -> 0 | U40: =C40 -> 222439215846 | V40: =U40/$V$2 -> 8897568.6 | W40: =U40/$U$66 -> #REF! | X40: =U40-BCTC2026!V42 -> -25157976634
B41: Nguyên giá TSCĐ HH | C41: =BCTC2026!D43 -> 346257196159 | D41: =BCTC2026!E43 -> 349675687977 | E41: =BCTC2026!F43 -> 372614337286 | F41: =BCTC2026!G43 -> 379332503103 | G41: =BCTC2026!H43 -> 379507503103 | H41: =BCTC2026!I43 -> 0 | I41: =BCTC2026!J43 -> 0 | J41: =BCTC2026!K43 -> 0 | ... N41: =BCTC2026!O43 -> 0 | P41: =C41 -> 346257196159 | Q41: =H41 -> 0 | R41: =K41 -> 0 | S41: =N41 -> 0 | U41: =C41 -> 346257196159 | V41: =U41/$V$2 -> 13850288 | W41: =U41/$U$66 -> #REF! | X41: =U41-BCTC2026!V43 -> -33250306944
B42: Giá trị hao mòn luỹ kế TSCĐ HH(*) | C42: =BCTC2026!D44 -> -123817980313 | D42: =BCTC2026!E44 -> -125736556588 | E42: =BCTC2026!F44 -> -127670235928 | F42: =BCTC2026!G44 -> -129763765278 | G42: =BCTC2026!H44 -> -131910310623 | H42: =BCTC2026!I44 -> 0 | I42: =BCTC2026!J44 -> 0 | J42: =BCTC2026!K44 -> 0 | ... N42: =BCTC2026!O44 -> 0 | P42: =C42 -> -123817980313 | Q42: =H42 -> 0 | R42: =K42 -> 0 | S42: =N42 -> 0 | U42: =C42 -> -123817980313 | V42: =U42/$V$2 -> -4952719.2 | W42: =U42/$U$66 -> #REF! | X42: =U42-BCTC2026!V44 -> 8092330310
B43: 2. Tài sản cố định thuê tài chính | C43: =SUM(C44:C45) -> 17684886028 | D43: =SUM(D44:D45) -> 17550400741 | E43: =SUM(E44:E45) -> 17415915447 | F43: =SUM(F44:F45) -> 17281430151 | G43: =SUM(G44:G45) -> 17146944864 | H43: =SUM(H44:H45) -> 0 | I43: =SUM(I44:I45) -> 0 | J43: =SUM(J44:J45) -> 0 | ... N43: =SUM(N44:N45) -> 0 | P43: =C43 -> 17684886028 | Q43: =H43 -> 0 | R43: =K43 -> 0 | S43: =N43 -> 0 | U43: =C43 -> 17684886028 | V43: =U43/$V$2 -> 707395.44 | W43: 0 | X43: =U43-BCTC2026!V45 -> 537941164
B44: Nguyên giá TSCĐ thuê tài chính | C44: =BCTC2026!D46 -> 24160519140 | D44: =BCTC2026!E46 -> 24160519140 | E44: =BCTC2026!F46 -> 24160519140 | F44: =BCTC2026!G46 -> 24160519140 | G44: =BCTC2026!H46 -> 24160519140 | H44: =BCTC2026!I46 -> 0 | I44: =BCTC2026!J46 -> 0 | J44: =BCTC2026!K46 -> 0 | ... N44: =BCTC2026!O46 -> 0 | P44: =C44 -> 24160519140 | Q44: =H44 -> 0 | R44: =K44 -> 0 | S44: =N44 -> 0 | U44: =C44 -> 24160519140 | V44: =U44/$V$2 -> 966420.77 | W44: 0 | X44: =U44-BCTC2026!V46 -> 0
B45: Giá trị hao mòn luỹ kế TSCĐ thuê tài chính | C45: =BCTC2026!D47 -> -6475633112 | D45: =BCTC2026!E47 -> -6610118399 | E45: =BCTC2026!F47 -> -6744603693 | F45: =BCTC2026!G47 -> -6879088989 | G45: =BCTC2026!H47 -> -7013574276 | H45: =BCTC2026!I47 -> 0 | I45: =BCTC2026!J47 -> 0 | J45: =BCTC2026!K47 -> 0 | ... L45: =BCTC2026!M47 -> 0 | N45: =BCTC2026!O47 -> 0 | P45: =C45 -> -6475633112 | Q45: =H45 -> 0 | R45: =K45 -> 0 | S45: =N45 -> 0 | U45: =C45 -> -6475633112 | V45: =U45/$V$2 -> -259025.32 | W45: 0 | X45: =U45-BCTC2026!V47 -> 537941164
B46: 3. Tài sản cố định vô hình | C46: =SUM(C47:C48) -> 3526365654 | D46: =SUM(D47:D48) -> 3476418728 | E46: =SUM(E47:E48) -> 3426471804 | F46: =SUM(F47:F48) -> 3376524877 | G46: =SUM(G47:G48) -> 3326577952 | H46: =SUM(H47:H48) -> 0 | I46: =SUM(I47:I48) -> 0 | J46: =SUM(J47:J48) -> 0 | ... N46: =SUM(N47:N48) -> 0 | P46: =C46 -> 3526365654 | Q46: =H46 -> 0 | R46: =K46 -> 0 | S46: =N46 -> 0 | U46: =C46 -> 3526365654 | V46: =U46/$V$2 -> 141054.63 | W46: =U46/$U$66 -> #REF! | X46: =U46-BCTC2026!V48 -> 199787702
B47: Nguyên giá TSCĐ vô hình | C47: =BCTC2026!D49 -> 6032562739 | D47: =BCTC2026!E49 -> 6032562739 | E47: =BCTC2026!F49 -> 6032562739 | F47: =BCTC2026!G49 -> 6032562739 | G47: =BCTC2026!H49 -> 6032562739 | H47: =BCTC2026!I49 -> 0 | I47: =BCTC2026!J49 -> 0 | J47: =BCTC2026!K49 -> 0 | ... N47: =BCTC2026!O49 -> 0 | P47: =C47 -> 6032562739 | Q47: =H47 -> 0 | R47: =K47 -> 0 | S47: =N47 -> 0 | U47: =C47 -> 6032562739 | V47: =U47/$V$2 -> 241302.51 | W47: =U47/$U$66 -> #REF! | X47: =U47-BCTC2026!V49 -> 0
B48: Giá trị hao mòn luỹ kế TSCĐ vô hình(*) | C48: =BCTC2026!D50 -> -2506197085 | D48: =BCTC2026!E50 -> -2556144011 | E48: =BCTC2026!F50 -> -2606090935 | F48: =BCTC2026!G50 -> -2656037862 | G48: =BCTC2026!H50 -> -2705984787 | H48: =BCTC2026!I50 -> 0 | I48: =BCTC2026!J50 -> 0 | J48: =BCTC2026!K50 -> 0 | ... N48: =BCTC2026!O50 -> 0 | P48: =C48 -> -2506197085 | Q48: =H48 -> 0 | R48: =K48 -> 0 | S48: =N48 -> 0 | U48: =C48 -> -2506197085 | V48: =U48/$V$2 -> -100247.88 | W48: =U48/$U$66 -> #REF! | X48: =U48-BCTC2026!V50 -> 199787702
B49: III. Bất động sản đầu tư | C49: =SUM(C50:C51) -> 0 | D49: =SUM(D50:D51) -> 0 | E49: =SUM(E50:E51) -> 0 | F49: =SUM(F50:F51) -> 0 | G49: =SUM(G50:G51) -> 0 | H49: =SUM(H50:H51) -> 0 | I49: =SUM(I50:I51) -> 0 | J49: =SUM(J50:J51) -> 0 | ... M49: =SUM(M50:M51) -> 0 | N49: =BCTC2026!O60 -> 0 | P49: =C49 -> 0 | Q49: =H49 -> 0 | R49: =K49 -> 0 | S49: =N49 -> 0 | U49: =C49 -> 0 | V49: =U49/$V$2 -> 0 | W49: 0 | X49: =U49-BCTC2026!V60 -> 0
B50: Nguyên giá bất động sản đầu tư | C50: =BCTC2026!D61 -> 0 | D50: 0 | E50: 0 | F50: 0 | G50: 0 | H50: 0 | I50: 0 | J50: 0 | K50: 0 | L50: 0 | N50: =BCTC2026!O61 -> 0 | P50: =C50 -> 0 | Q50: =H50 -> 0 | R50: =K50 -> 0 | S50: =N50 -> 0 | U50: =C50 -> 0 | V50: =U50/$V$2 -> 0 | W50: 0 | X50: =U50-BCTC2026!V61 -> 0
B51: Giá trị hao mòn luỹ kế BĐSĐT(*) | C51: =BCTC2026!D62 -> 0 | D51: 0 | E51: 0 | F51: 0 | G51: 0 | H51: 0 | I51: 0 | J51: 0 | K51: 0 | L51: 0 | N51: =BCTC2026!O62 -> 0 | P51: =C51 -> 0 | Q51: =H51 -> 0 | R51: =K51 -> 0 | S51: =N51 -> 0 | U51: =C51 -> 0 | V51: =U51/$V$2 -> 0 | W51: 0 | X51: =U51-BCTC2026!V62 -> 0
B52: IV.Tài sản dở dang dài hạn | C52: =SUM(C53:C54) -> 61387421408 | D52: =SUM(D53:D54) -> 80647695075 | E52: =SUM(E53:E54) -> 66362060607 | F52: =SUM(F53:F54) -> 83813282245 | G52: =SUM(G53:G54) -> 86222726568 | H52: =SUM(H53:H54) -> 0 | I52: =SUM(I53:I54) -> 0 | J52: =SUM(J53:J54) -> 0 | ... N52: =SUM(N53:N54) -> 0 | P52: =C52 -> 61387421408 | Q52: =H52 -> 0 | R52: =K52 -> 0 | S52: =N52 -> 0 | U52: =C52 -> 61387421408 | V52: =U52/$V$2 -> 2455496.9 | W52: =U52/$U$66 -> #REF! | X52: =U52-BCTC2026!V63 -> -24835305160
B53: 1.Chi phí sản xuất, kinh doanh dở dang dài hạn | C53: =BCTC2026!D64 -> 0 | D53: =BCTC2026!E64 -> 0 | E53: =BCTC2026!F64 -> 0 | F53: =BCTC2026!G64 -> 0 | G53: =BCTC2026!H64 -> 0 | H53: =BCTC2026!I64 -> 0 | I53: =BCTC2026!J64 -> 0 | J53: =BCTC2026!K64 -> 0 | ... L53: =BCTC2026!M64 -> 0 | P53: =C53 -> 0 | Q53: =H53 -> 0 | R53: =K53 -> 0 | S53: =N53 -> 0 | U53: =C53 -> 0 | V53: =U53/$V$2 -> 0 | W53: 0 | X53: =U53-BCTC2026!V64 -> 0
B54: 2.Chi phí xây dựng cơ bản dở dang | C54: =BCTC2026!D65 -> 61387421408 | D54: =BCTC2026!E65 -> 80647695075 | E54: =BCTC2026!F65 -> 66362060607 | F54: =BCTC2026!G65 -> 83813282245 | G54: =BCTC2026!H65 -> 86222726568 | H54: =BCTC2026!I65 -> 0 | I54: =BCTC2026!J65 -> 0 | J54: =BCTC2026!K65 -> 0 | ... N54: =BCTC2026!O65 -> 0 | P54: =C54 -> 61387421408 | Q54: =H54 -> 0 | R54: =K54 -> 0 | S54: =N54 -> 0 | U54: =C54 -> 61387421408 | V54: =U54/$V$2 -> 2455496.9 | W54: =U54/$U$66 -> #REF! | X54: =U54-BCTC2026!V65 -> -24835305160
B55: V.Đầu tư tài chính dài hạn | C55: 0 | D55: 0 | E55: 0 | F55: 0 | G55: 0 | H55: 0 | I55: 0 | J55: 0 | K55: 0 | L55: 0 | N55: =BCTC2026!O66 -> 0 | P55: =C55 -> 0 | Q55: =H55 -> 0 | R55: =K55 -> 0 | S55: =N55 -> 0 | U55: =C55 -> 0 | V55: =U55/$V$2 -> 0 | W55: 0 | X55: =U55-BCTC2026!V66 -> 0
B56: 1.Đầu tư vào công ty con | C56: =BCTC2026!D67 -> 0 | D56: =BCTC2026!E67 -> 0 | E56: =BCTC2026!F67 -> 0 | F56: =BCTC2026!G67 -> 0 | G56: =BCTC2026!H67 -> 0 | H56: =BCTC2026!I67 -> 0 | I56: =BCTC2026!J67 -> 0 | J56: =BCTC2026!K67 -> 0 | ... L56: =BCTC2026!M67 -> 0 | N56: =BCTC2026!O67 -> 0 | P56: =C56 -> 0 | Q56: =H56 -> 0 | R56: =K56 -> 0 | S56: =N56 -> 0 | U56: =C56 -> 0 | V56: =U56/$V$2 -> 0 | W56: 0 | X56: =U56-BCTC2026!V67 -> 0
B57: 2.Đầu tư vào công ty liên kết, liên doanh | C57: =BCTC2026!D68 -> 0 | D57: =BCTC2026!E68 -> 0 | E57: =BCTC2026!F68 -> 0 | F57: =BCTC2026!G68 -> 0 | G57: =BCTC2026!H68 -> 0 | H57: =BCTC2026!I68 -> 0 | I57: =BCTC2026!J68 -> 0 | J57: =BCTC2026!K68 -> 0 | ... L57: =BCTC2026!M68 -> 0 | N57: =BCTC2026!O68 -> 0 | P57: =C57 -> 0 | Q57: =H57 -> 0 | R57: =K57 -> 0 | S57: =N57 -> 0 | U57: =C57 -> 0 | V57: =U57/$V$2 -> 0 | W57: 0 | X57: =U57-BCTC2026!V68 -> 0
B58: 3.Đầu tư góp vốn vào đơn vị khác | C58: =BCTC2026!D69 -> 0 | D58: =BCTC2026!E69 -> 0 | E58: =BCTC2026!F69 -> 0 | F58: =BCTC2026!G69 -> 0 | G58: =BCTC2026!H69 -> 0 | H58: =BCTC2026!I69 -> 0 | I58: =BCTC2026!J69 -> 0 | J58: =BCTC2026!K69 -> 0 | ... L58: =BCTC2026!M69 -> 0 | N58: =BCTC2026!O69 -> 0 | P58: =C58 -> 0 | Q58: =H58 -> 0 | R58: =K58 -> 0 | S58: =N58 -> 0 | U58: =C58 -> 0 | V58: =U58/$V$2 -> 0 | W58: 0 | X58: =U58-BCTC2026!V69 -> 0
B59: 4.Dự phòng giảm giá đầu tư tài chính dài hạn(*) | C59: =BCTC2026!D70 -> 0 | D59: =BCTC2026!E70 -> 0 | E59: =BCTC2026!F70 -> 0 | F59: =BCTC2026!G70 -> 0 | G59: =BCTC2026!H70 -> 0 | H59: =BCTC2026!I70 -> 0 | I59: =BCTC2026!J70 -> 0 | J59: =BCTC2026!K70 -> 0 | ... L59: =BCTC2026!M70 -> 0 | N59: =BCTC2026!O70 -> 0 | P59: =C59 -> 0 | Q59: =H59 -> 0 | R59: =K59 -> 0 | S59: =N59 -> 0 | U59: =C59 -> 0 | V59: =U59/$V$2 -> 0 | W59: 0 | X59: =U59-BCTC2026!V70 -> 0
B60: 5.Đầu tư nắm giữ đến ngày đáo hạn | C60: =BCTC2026!D71 -> 0 | D60: =BCTC2026!E71 -> 0 | E60: =BCTC2026!F71 -> 0 | F60: =BCTC2026!G71 -> 0 | G60: =BCTC2026!H71 -> 0 | H60: =BCTC2026!I71 -> 0 | I60: =BCTC2026!J71 -> 0 | J60: =BCTC2026!K71 -> 0 | ... L60: =BCTC2026!M71 -> 0 | N60: =BCTC2026!O71 -> 0 | P60: =C60 -> 0 | Q60: =H60 -> 0 | R60: =K60 -> 0 | S60: =N60 -> 0 | U60: =C60 -> 0 | V60: =U60/$V$2 -> 0 | W60: 0 | X60: =U60-BCTC2026!V71 -> 0
B61: VI.Tài sản dài hạn khác | C61: =SUM(C62:C65) -> 7062502744 | D61: =SUM(D62:D65) -> 6570969298 | E61: =SUM(E62:E65) -> 6131031024 | F61: =SUM(F62:F65) -> 5693514228 | G61: =SUM(G62:G65) -> 5705255817 | H61: =SUM(H62:H65) -> 0 | I61: =SUM(I62:I65) -> 0 | J61: =SUM(J62:J65) -> 0 | ... N61: =SUM(N62:N65) -> 0 | P61: =C61 -> 7062502744 | Q61: =H61 -> 0 | R61: =K61 -> 0 | S61: =N61 -> 0 | U61: =C61 -> 7062502744 | V61: =U61/$V$2 -> 282500.11 | W61: =U61/$U$66 -> #REF! | X61: =U61-BCTC2026!V72 -> 1357246927
B62: 1.Chi phí trả trước dài hạn | C62: =BCTC2026!D73 -> 7062502744 | D62: =BCTC2026!E73 -> 6570969298 | E62: =BCTC2026!F73 -> 6131031024 | F62: =BCTC2026!G73 -> 5693514228 | G62: =BCTC2026!H73 -> 5705255817 | H62: =BCTC2026!I73 -> 0 | I62: =BCTC2026!J73 -> 0 | J62: =BCTC2026!K73 -> 0 | ... N62: =BCTC2026!O73 -> 0 | P62: =C62 -> 7062502744 | Q62: =H62 -> 0 | R62: =K62 -> 0 | S62: =N62 -> 0 | U62: =C62 -> 7062502744 | V62: =U62/$V$2 -> 282500.11 | W62: =U62/$U$66 -> #REF! | X62: =U62-BCTC2026!V73 -> 1357246927
B63: 2.Tài sản thuế thu nhập hoãn lại | C63: =BCTC2026!D74 -> 0 | D63: =BCTC2026!E74 -> 0 | E63: =BCTC2026!F74 -> 0 | F63: =BCTC2026!G74 -> 0 | G63: =BCTC2026!H74 -> 0 | H63: =BCTC2026!I74 -> 0 | I63: =BCTC2026!J74 -> 0 | J63: =BCTC2026!K74 -> 0 | ... L63: =BCTC2026!M74 -> 0 | N63: =BCTC2026!O74 -> 0 | P63: =C63 -> 0 | Q63: =H63 -> 0 | R63: =K63 -> 0 | S63: =N63 -> 0 | U63: =C63 -> 0 | V63: =U63/$V$2 -> 0 | W63: 0 | X63: =U63-BCTC2026!V74 -> 0
B64: 3.Thiết bị, vật tư, phụ tùng thay thế dài hạn | C64: =BCTC2026!D75 -> 0 | D64: =BCTC2026!E75 -> 0 | E64: =BCTC2026!F75 -> 0 | F64: =BCTC2026!G75 -> 0 | G64: =BCTC2026!H75 -> 0 | H64: =BCTC2026!I75 -> 0 | I64: =BCTC2026!J75 -> 0 | J64: =BCTC2026!K75 -> 0 | ... L64: =BCTC2026!M75 -> 0 | N64: =BCTC2026!O75 -> 0 | P64: =C64 -> 0 | Q64: =H64 -> 0 | R64: =K64 -> 0 | S64: =N64 -> 0 | U64: =C64 -> 0 | V64: =U64/$V$2 -> 0 | W64: 0 | X64: =U64-BCTC2026!V75 -> 0
B65: 4.Tài sản dài hạn khác | C65: =BCTC2026!D76 -> 0 | D65: =BCTC2026!E76 -> 0 | E65: =BCTC2026!F76 -> 0 | F65: =BCTC2026!G76 -> 0 | G65: =BCTC2026!H76 -> 0 | H65: =BCTC2026!I76 -> 0 | I65: =BCTC2026!J76 -> 0 | J65: =BCTC2026!K76 -> 0 | ... L65: =BCTC2026!M76 -> 0 | N65: =BCTC2026!O76 -> 0 | P65: =C65 -> 0 | Q65: =H65 -> 0 | R65: =K65 -> 0 | S65: =N65 -> 0 | U65: =C65 -> 0 | V65: =U65/$V$2 -> 0 | W65: 0 | X65: =U65-BCTC2026!V76 -> 0
B66: TỔNG TÀI SẢN | C66: =C30+C4 -> #REF! | D66: =D30+D4 -> #REF! | E66: =E30+E4 -> #REF! | F66: =F30+F4 -> #REF! | G66: =G30+G4 -> #REF! | H66: =H30+H4 -> #REF! | I66: =I30+I4 -> #REF! | J66: =J30+J4 -> #REF! | ... N66: =N30+N4 -> #REF! | P66: =C66 -> #REF! | Q66: =H66 -> #REF! | R66: =K66 -> #REF! | S66: =N66 -> #REF! | U66: =C66 -> #REF! | V66: =U66/$V$2 -> #REF! | W66: =U66/$U$118 -> #REF! | X66: =U66-BCTC2026!V77 -> #REF!
B67: A-NỢ PHẢI TRẢ | C67: =C68+C83 -> #REF! | D67: =D68+D83 -> #REF! | E67: =E68+E83 -> #REF! | F67: =F68+F83 -> #REF! | G67: =G68+G83 -> #REF! | H67: =H68+H83 -> #REF! | I67: =I68+I83 -> #REF! | J67: =J68+J83 -> #REF! | ... N67: =N68+N83 -> #REF! | P67: =C67 -> #REF! | Q67: =H67 -> #REF! | R67: =K67 -> #REF! | S67: =N67 -> #REF! | U67: =C67 -> #REF! | V67: =U67/$V$2 -> #REF! | W67: =U67/$U$118 -> #REF! | X67: =U67-BCTC2026!V78 -> #REF!
B68: I.Nợ ngắn hạn | C68: =SUM(C69:C82) -> #REF! | D68: =SUM(D69:D82) -> #REF! | E68: =SUM(E69:E82) -> #REF! | F68: =SUM(F69:F82) -> #REF! | G68: =SUM(G69:G82) -> #REF! | H68: =SUM(H69:H82) -> #REF! | I68: =SUM(I69:I82) -> #REF! | J68: =SUM(J69:J82) -> #REF! | ... N68: =SUM(N69:N82) -> #REF! | P68: =C68 -> #REF! | Q68: =H68 -> #REF! | R68: =K68 -> #REF! | S68: =N68 -> #REF! | U68: =C68 -> #REF! | V68: =U68/$V$2 -> #REF! | W68: =U68/$U$118 -> #REF! | X68: =U68-BCTC2026!V79 -> #REF!
B69: 1.Phải trả người bán ngắn hạn | C69: =BCTC2026!D94+'BCTC2025-Sau loại trừ'!C206 -> 0 | D69: =BCTC2026!E94+'BCTC2025-Sau loại trừ'!D206 -> 0 | E69: =BCTC2026!F94+'BCTC2025-Sau loại trừ'!E206 -> 0 | F69: =BCTC2026!G94+'BCTC2025-Sau loại trừ'!F206 -> 0 | G69: =BCTC2026!H94+'BCTC2025-Sau loại trừ'!G206 -> 0 | H69: =BCTC2026!I94+'BCTC2025-Sau loại trừ'!H206 -> 0 | I69: =BCTC2026!J94+'BCTC2025-Sau loại trừ'!I206 -> 0 | J69: =BCTC2026!K94+'BCTC2025-Sau loại trừ'!J206 -> 0 | ... M69: =BCTC2026!N94+'BCTC2025-Sau loại trừ'!M206 -> 0 | N69: =BCTC2026!O94+'BCTC2025-Sau loại trừ'!N206-N209 -> 0 | P69: =C69 -> 0 | Q69: =H69 -> 0 | R69: =K69 -> 0 | S69: =N69 -> 0 | U69: =C69 -> 0 | V69: =U69/$V$2 -> 0 | W69: =U69/$U$118 -> #REF! | X69: =U69-BCTC2026!V94 -> 0
B70: 2.Người mua trả tiền trước ngắn hạn | C70: =BCTC2026!#REF! -> #REF! | D70: =BCTC2026!#REF! -> #REF! | E70: =BCTC2026!#REF! -> #REF! | F70: =BCTC2026!#REF! -> #REF! | G70: =BCTC2026!#REF! -> #REF! | H70: =BCTC2026!#REF! -> #REF! | I70: =BCTC2026!#REF! -> #REF! | J70: =BCTC2026!#REF! -> #REF! | ... N70: =BCTC2026!#REF! -> #REF! | P70: =C70 -> #REF! | Q70: =H70 -> #REF! | R70: =K70 -> #REF! | S70: =N70 -> #REF! | U70: =C70 -> #REF! | V70: =U70/$V$2 -> #REF! | W70: 0 | X70: =U70-BCTC2026!#REF! -> #REF!
B71: 3.Thuế và các khoản phải nộp Nhà nước | C71: =BCTC2026!#REF! -> #REF! | D71: =BCTC2026!#REF! -> #REF! | E71: =BCTC2026!#REF! -> #REF! | F71: =BCTC2026!#REF! -> #REF! | G71: =BCTC2026!#REF! -> #REF! | H71: =BCTC2026!#REF! -> #REF! | I71: =BCTC2026!#REF! -> #REF! | J71: =BCTC2026!#REF! -> #REF! | ... N71: =BCTC2026!#REF! -> #REF! | P71: =C71 -> #REF! | Q71: =H71 -> #REF! | R71: =K71 -> #REF! | S71: =N71 -> #REF! | U71: =C71 -> #REF! | V71: =U71/$V$2 -> #REF! | W71: =U71/$U$118 -> #REF! | X71: =U71-BCTC2026!#REF! -> #REF!
B72: 4.Phải trả người lao động | C72: =BCTC2026!#REF! -> #REF! | D72: =BCTC2026!#REF! -> #REF! | E72: =BCTC2026!#REF! -> #REF! | F72: =BCTC2026!#REF! -> #REF! | G72: =BCTC2026!#REF! -> #REF! | H72: =BCTC2026!#REF! -> #REF! | I72: =BCTC2026!#REF! -> #REF! | J72: =BCTC2026!#REF! -> #REF! | ... N72: =BCTC2026!#REF! -> #REF! | P72: =C72 -> #REF! | Q72: =H72 -> #REF! | R72: =K72 -> #REF! | S72: =N72 -> #REF! | U72: =C72 -> #REF! | V72: =U72/$V$2 -> #REF! | W72: =U72/$U$118 -> #REF! | X72: =U72-BCTC2026!#REF! -> #REF!
B73: 5.Chi phí phải trả ngắn hạn | C73: =BCTC2026!#REF! -> #REF! | D73: =BCTC2026!#REF! -> #REF! | E73: =BCTC2026!#REF! -> #REF! | F73: =BCTC2026!#REF! -> #REF! | G73: =BCTC2026!#REF! -> #REF! | H73: =BCTC2026!#REF! -> #REF! | I73: =BCTC2026!#REF! -> #REF! | J73: =BCTC2026!#REF! -> #REF! | ... M73: =BCTC2026!#REF! -> #REF! | N73: =BCTC2026!#REF!+N209 -> #REF! | P73: =C73 -> #REF! | Q73: =H73 -> #REF! | R73: =K73 -> #REF! | S73: =N73 -> #REF! | U73: =C73 -> #REF! | V73: =U73/$V$2 -> #REF! | W73: =U73/$U$118 -> #REF! | X73: =U73-BCTC2026!#REF! -> #REF!
B74: 6.Phải trả nội bộ ngắn hạn | C74: =BCTC2026!#REF! -> #REF! | D74: =BCTC2026!#REF! -> #REF! | E74: =BCTC2026!#REF! -> #REF! | F74: =BCTC2026!#REF! -> #REF! | G74: =BCTC2026!#REF! -> #REF! | H74: =BCTC2026!#REF! -> #REF! | I74: =BCTC2026!#REF! -> #REF! | J74: =BCTC2026!#REF! -> #REF! | ... M74: =BCTC2026!#REF! -> #REF! | P74: =C74 -> #REF! | Q74: =H74 -> #REF! | R74: =K74 -> #REF! | S74: =N74 -> 0 | U74: =C74 -> #REF! | V74: =U74/$V$2 -> #REF! | W74: 0 | X74: =U74-BCTC2026!#REF! -> #REF!
B75: 7.Phải trả theo tiến độ kế hoạch HĐ XD | C75: =BCTC2026!#REF! -> #REF! | D75: =BCTC2026!#REF! -> #REF! | E75: =BCTC2026!#REF! -> #REF! | F75: =BCTC2026!#REF! -> #REF! | G75: =BCTC2026!#REF! -> #REF! | H75: =BCTC2026!#REF! -> #REF! | I75: =BCTC2026!#REF! -> #REF! | J75: =BCTC2026!#REF! -> #REF! | ... M75: =BCTC2026!#REF! -> #REF! | P75: =C75 -> #REF! | Q75: =H75 -> #REF! | R75: =K75 -> #REF! | S75: =N75 -> 0 | U75: =C75 -> #REF! | V75: =U75/$V$2 -> #REF! | W75: 0 | X75: =U75-BCTC2026!#REF! -> #REF!
B76: 8.Doanh thu chưa thực hiện ngắn hạn | C76: =BCTC2026!#REF! -> #REF! | D76: =BCTC2026!#REF! -> #REF! | E76: =BCTC2026!#REF! -> #REF! | F76: =BCTC2026!#REF! -> #REF! | G76: =BCTC2026!#REF! -> #REF! | H76: =BCTC2026!#REF! -> #REF! | I76: =BCTC2026!#REF! -> #REF! | J76: =BCTC2026!#REF! -> #REF! | ... M76: =BCTC2026!#REF! -> #REF! | P76: =C76 -> #REF! | Q76: =H76 -> #REF! | R76: =K76 -> #REF! | S76: =N76 -> 0 | U76: =C76 -> #REF! | V76: =U76/$V$2 -> #REF! | W76: 0 | X76: =U76-BCTC2026!#REF! -> #REF!
B77: 9.Phải trả ngắn hạn khác | C77: =BCTC2026!#REF! -> #REF! | D77: =BCTC2026!#REF! -> #REF! | E77: =BCTC2026!#REF! -> #REF! | F77: =BCTC2026!#REF! -> #REF! | G77: =BCTC2026!#REF! -> #REF! | H77: =BCTC2026!#REF! -> #REF! | I77: =BCTC2026!#REF! -> #REF! | J77: =BCTC2026!#REF! -> #REF! | ... N77: =BCTC2026!#REF! -> #REF! | P77: =C77 -> #REF! | Q77: =H77 -> #REF! | R77: =K77 -> #REF! | S77: =N77 -> #REF! | U77: =C77 -> #REF! | V77: =U77/$V$2 -> #REF! | W77: =U77/$U$118 -> #REF! | X77: =U77-BCTC2026!#REF! -> #REF!
B78: 10.Vay và nợ thuê tài chính ngắn hạn | C78: =BCTC2026!#REF! -> #REF! | D78: =BCTC2026!#REF! -> #REF! | E78: =BCTC2026!#REF! -> #REF! | F78: =BCTC2026!#REF! -> #REF! | G78: =BCTC2026!#REF! -> #REF! | H78: =BCTC2026!#REF! -> #REF! | I78: =BCTC2026!#REF! -> #REF! | J78: =BCTC2026!#REF! -> #REF! | ... N78: =BCTC2026!#REF! -> #REF! | P78: =C78 -> #REF! | Q78: =H78 -> #REF! | R78: =K78 -> #REF! | S78: =N78 -> #REF! | U78: =C78 -> #REF! | V78: =U78/$V$2 -> #REF! | W78: =U78/$U$118 -> #REF! | X78: =U78-BCTC2026!#REF! -> #REF!
B79: 11.Dự phòng phải trả ngắn hạn | C79: =BCTC2026!#REF! -> #REF! | D79: =BCTC2026!#REF! -> #REF! | E79: =BCTC2026!#REF! -> #REF! | F79: =BCTC2026!#REF! -> #REF! | G79: =BCTC2026!#REF! -> #REF! | H79: =BCTC2026!#REF! -> #REF! | I79: =BCTC2026!#REF! -> #REF! | J79: =BCTC2026!#REF! -> #REF! | ... M79: =BCTC2026!#REF! -> #REF! | P79: =C79 -> #REF! | Q79: =H79 -> #REF! | R79: =K79 -> #REF! | S79: =N79 -> 0 | U79: =C79 -> #REF! | V79: =U79/$V$2 -> #REF! | W79: 0 | X79: =U79-BCTC2026!#REF! -> #REF!
B80: 12.Quỹ khen thưởng, phúc lợi | C80: =BCTC2026!#REF! -> #REF! | D80: =BCTC2026!#REF! -> #REF! | E80: =BCTC2026!#REF! -> #REF! | F80: =BCTC2026!#REF! -> #REF! | G80: =BCTC2026!#REF! -> #REF! | H80: =BCTC2026!#REF! -> #REF! | I80: =BCTC2026!#REF! -> #REF! | J80: =BCTC2026!#REF! -> #REF! | ... N80: =BCTC2026!#REF! -> #REF! | P80: =C80 -> #REF! | Q80: =H80 -> #REF! | R80: =K80 -> #REF! | S80: =N80 -> #REF! | U80: =C80 -> #REF! | V80: =U80/$V$2 -> #REF! | W80: =U80/$U$118 -> #REF! | X80: =U80-BCTC2026!#REF! -> #REF!
