Workbook
Name \T: #REF!
Name __dao1: #REF!
Name __dao2: #REF!
Name __dap2: #REF!
Name __day1: #REF!
Name __day2: #REF!
Name __dbu1: #REF!
Name __dbu2: #REF!
Name __doi3: #REF!
Name __E99999: #REF!
Name __Jan02: #REF!
Name __lap1: #REF!
Name __lap2: #REF!
Name __vc1: #REF!
Name __vc2: #REF!
Name __vc3: #REF!
Name _01_01_99: #REF!
Name _01_02_99: #REF!
Name _01_03_99: #REF!
Name _01_04_99: #REF!
Name _01_05_99: #REF!
Name _01_06_99: #REF!
Name _01_07_99: #REF!
Name _01_08_1999: #REF!
Name _1CAP002: #REF!
Name _2STREO7: #REF!
Name _4GOIC01: #REF!
Name _4OSLCTT: #REF!
Name _6BNTTTH: #REF!
Name _6DCTTBO: #REF!
Name _6DD24TT: #REF!
Name _6FCOTBU: #REF!
Name _6LATUBU: #REF!
Name _6SDTT24: #REF!
Name _6TBUDTT: #REF!
Name _6TDDDTT: #REF!
Name _6TLTTTH: #REF!
Name _6TUBUTT: #REF!
Name _6UCLVIS: #REF!
Name _7DNCABC: #REF!
Name _7HDCTBU: #REF!
Name _7PKTUBU: #REF!
Name _7TBHT20: #REF!
Name _7TBHT30: #REF!
Name _7TDCABC: #REF!
Name _dao1: #REF!
Name _dao2: #REF!
Name _dap2: #REF!
Name _day1: #REF!
Name _day2: #REF!
Name _dbu1: #REF!
Name _dbu2: #REF!
Name _doi3: #REF!
Name _E99999: #REF!
Name _Jan02: #REF!
Name _lap1: #REF!
Name _lap2: #REF!
Name _vc1: #REF!
Name _vc2: #REF!
Name _vc3: #REF!

Sheet TH
A3: BẢNG TRÌNH GIÁ BÁN SẢN PHẨM DÂY ĐAI 2026
I4: Hiệu lực từ ngày | K4: tới ngày
A5: STT | B5: Mã | C5: Tên | D5: Quy cách (mm x …..) | E5: Trọng lượng (Cuộn) | F5: Đơn giá vốn (Vnđ/Kg) | G5: Giá bán EXW đề nghị (VND/Kg) | H5: Đơn giá vốn (Vnđ/Cuộn) | I5: Giá bán EXW đề nghị (VND/Cuộn) | J5: Lợi nhuận sau thuế (VND/Cuộn) | K5: % Lợi nhuận sau thuế (VND/Cuộn) | L5: Ghi chú
A6: 1 | C6: Dây đai RPE1609 | D6: 16 mm x 0.9 mm | E6: 20 | F6: =+'DĐ RPE1609'!J105 -> 23578.231 | G6: 25000 | H6: =F6*E6 -> 471564.62 | I6: =G6*E6 -> 500000 | J6: =+I6-H6 -> 28435.38 | K6: =+J6/I6 -> 0.056870761 | N6: 24000
A7: 2 | C7: Dây đai RPE1909 | D7: 19 mm x 0.9 mm | E7: 20 | F7: =+'DĐ RPE1909'!J105 -> 23578.231 | G7: 25000 | H7: =F7*E7 -> 471564.62 | I7: =G7*E7 -> 500000 | J7: =+I7-H7 -> 28435.38 | K7: =+J7/I7 -> 0.056870761 | N7: 25000
A8: 3 | C8: Dây đai RPEXXXX | D8: XX mm x XX mm | E8: 20 | F8: =+'DĐ RPE1609'!J105 -> 23578.231 | G8: 25000 | H8: =F8*E8 -> 471564.62 | I8: =G8*E8 -> 500000 | J8: =+I8-H8 -> 28435.38 | K8: =+J8/I8 -> 0.056870761 | N8: 26000
A9: 4 | J9: =+I9-H9 -> 0 | K9: =+J9/I9 -> #DIV/0!
A10: 5 | J10: =+I10-H10 -> 0 | K10: =+J10/I10 -> #DIV/0!
A11: 6 | J11: =+I11-H11 -> 0 | K11: =+J11/I11 -> #DIV/0!
C15: Phê Duyệt | D15: Xem xét | F15: Xem xét | H15: Người kiểm tra | J15: Người kiểm tra | L15: Người lập
C20: TGĐ | D20: GĐTC | F20: P.TGĐ SX | H20: GĐĐH Trạm | J20: GĐ Đại Lộc | L20: KTT Đại Lộc
C21: Huỳnh Ngọc Thạch | D21: Lê Hoành Cư | F21: Lê Xuân Huy Vũ | H21: Lê Đức Thắng | J21: Lưu Song Hùng | L21: Trần Thị Hương

Sheet Chart
C1: GIÁ SẢN PHẨM DÂY ĐAI 2026
D3: Quy cách đóng gói | E3: =+'DĐ RPE1609'!K5 -> 20 | I3: ='DĐ RPE1909'!K5 -> 20 | M3: ='DĐ RPEXXXX'!K5 -> 20 | Q3: ĐIỂM HÒA VỐN
E4: =TH!C6 -> Dây đai RPE1609 | I4: =TH!C7 -> Dây đai RPE1909 | M4: =TH!C8 -> Dây đai RPEXXXX | Q4: =D22 -> 23578.231
A5: No. | B5: SAP | C5: Chi phí Cost Items | D5: Chi phí VNĐ /Kg | E5: Đơn giá VND /Cuộn | F5: Cơ cấu % chi phí /Giá | H5: Chi phí VNĐ /Kg | I5: Đơn giá VND /Cuộn | J5: Cơ cấu % chi phí /Giá | L5: Chi phí VNĐ /Kg | M5: Đơn giá VND /Cuộn | N5: Cơ cấu % chi phí /Giá
A6: A | B6: 1521 | C6: Chi phí nguyên vật liệu | D6: =+SUM(D7:D7) -> 13296.279 | E6: =D6*E$3 -> 265925.58 | F6: =E6/$E$25 -> 0.53185116 | H6: =+SUM(H7:H7) -> 13296.279 | I6: =H6*$E$3 -> 265925.58 | J6: =I6/$E$25 -> 0.53185116 | L6: =+SUM(L7:L7) -> 13296.279 | M6: =L6*$E$3 -> 265925.58 | N6: =M6/$E$25 -> 0.53185116
A7: 1 | B7: 1521 | C7: Chi phí Vảy GCDĐ | D7: =+SUMIFS('DĐ RPE1609'!J:J,'DĐ RPE1609'!D:D,Chart!B7) -> 13296.279 | E7: =D7*E$3 -> 265925.58 | F7: =E7/$E$25 -> 0.53185116 | H7: =+SUMIFS('DĐ RPE1909'!J:J,'DĐ RPE1909'!D:D,Chart!B7) -> 13296.279 | I7: =H7*$E$3 -> 265925.58 | J7: =I7/$E$25 -> 0.53185116 | L7: =+SUMIFS('DĐ RPEXXXX'!J:J,'DĐ RPEXXXX'!D:D,Chart!B7) -> 13296.279 | M7: =L7*$E$3 -> 265925.58 | N7: =M7/$E$25 -> 0.53185116
A8: B | B8: 1522 | C8: Hao hụt về tiền | D8: =+SUMIFS('DĐ RPE1609'!J:J,'DĐ RPE1609'!D:D,Chart!B8) -> 1820 | E8: =D8*E$3 -> 36400 | F8: =E8/$E$25 -> 0.0728 | H8: =+SUMIFS('DĐ RPE1909'!J:J,'DĐ RPE1909'!D:D,Chart!B8) -> 1820 | I8: =H8*$E$3 -> 36400 | J8: =I8/$E$25 -> 0.0728 | L8: =+SUMIFS('DĐ RPEXXXX'!J:J,'DĐ RPEXXXX'!D:D,Chart!B8) -> 1820 | M8: =L8*$E$3 -> 36400 | N8: =M8/$E$25 -> 0.0728
A9: C | C9: Chi phí sản xuất | D9: =SUM(D10:D16) -> 5961.9519 | E9: =D9*E$3 -> 119239.04 | F9: =E9/$E$25 -> 0.23847808 | H9: =SUM(H10:H16) -> 5961.9519 | I9: =H9*$E$3 -> 119239.04 | J9: =I9/$E$25 -> 0.23847808 | L9: =SUM(L10:L16) -> 5961.9519 | M9: =L9*$E$3 -> 119239.04 | N9: =M9/$E$25 -> 0.23847808
A10: 2 | B10: LAB | C10: Chi phí nhân công | D10: =+SUMIFS('DĐ RPE1609'!J:J,'DĐ RPE1609'!D:D,Chart!B10) -> 901.08204 | E10: =D10*E$3 -> 18021.641 | F10: =E10/$E$25 -> 0.036043282 | H10: =+SUMIFS('DĐ RPE1909'!J:J,'DĐ RPE1909'!D:D,Chart!B10) -> 901.08204 | I10: =H10*$E$3 -> 18021.641 | J10: =I10/$E$25 -> 0.036043282 | L10: =+SUMIFS('DĐ RPEXXXX'!J:J,'DĐ RPEXXXX'!D:D,Chart!B10) -> 901.08204 | M10: =L10*$E$3 -> 18021.641 | N10: =M10/$E$25 -> 0.036043282
A11: =+A10+1 -> 3 | B11: DEP | C11: Khấu hao | D11: =+SUMIFS('DĐ RPE1609'!J:J,'DĐ RPE1609'!D:D,Chart!B11) -> 326.55786 | E11: =D11*E$3 -> 6531.1572 | F11: =E11/$E$25 -> 0.013062314 | H11: =+SUMIFS('DĐ RPE1909'!J:J,'DĐ RPE1909'!D:D,Chart!B11) -> 326.55786 | I11: =H11*$E$3 -> 6531.1572 | J11: =I11/$E$25 -> 0.013062314 | L11: =+SUMIFS('DĐ RPEXXXX'!J:J,'DĐ RPEXXXX'!D:D,Chart!B11) -> 326.55786 | M11: =L11*$E$3 -> 6531.1572 | N11: =M11/$E$25 -> 0.013062314
A12: =+A11+1 -> 4 | B12: ELEC | C12: Chi phí gián tiếp | D12: =+SUMIFS('DĐ RPE1609'!J:J,'DĐ RPE1609'!D:D,Chart!B12) -> 2569.7674 | E12: =D12*E$3 -> 51395.349 | F12: =E12/$E$25 -> 0.1027907 | H12: =+SUMIFS('DĐ RPE1909'!J:J,'DĐ RPE1909'!D:D,Chart!B12) -> 2569.7674 | I12: =H12*$E$3 -> 51395.349 | J12: =I12/$E$25 -> 0.1027907 | L12: =+SUMIFS('DĐ RPEXXXX'!J:J,'DĐ RPEXXXX'!D:D,Chart!B12) -> 2569.7674 | M12: =L12*$E$3 -> 51395.349 | N12: =M12/$E$25 -> 0.1027907
A13: =+A12+1 -> 5 | B13: OTH | C13: Điện | D13: =+SUMIFS('DĐ RPE1609'!J:J,'DĐ RPE1609'!D:D,Chart!B13) -> 2164.5446 | E13: =D13*E$3 -> 43290.891 | F13: =E13/$E$25 -> 0.086581783 | H13: =+SUMIFS('DĐ RPE1909'!J:J,'DĐ RPE1909'!D:D,Chart!B13) -> 2164.5446 | I13: =H13*$E$3 -> 43290.891 | J13: =I13/$E$25 -> 0.086581783 | L13: =+SUMIFS('DĐ RPEXXXX'!J:J,'DĐ RPEXXXX'!D:D,Chart!B13) -> 2164.5446 | M13: =L13*$E$3 -> 43290.891 | N13: =M13/$E$25 -> 0.086581783
A14: =+A13+1 -> 6 | B14: BAG | C14: Đóng gói | D14: =+SUMIFS('DĐ RPE1609'!J:J,'DĐ RPE1609'!D:D,Chart!B14) -> 0 | E14: =D14*E$3 -> 0 | F14: =E14/$E$25 -> 0 | H14: =+SUMIFS('DĐ RPE1909'!J:J,'DĐ RPE1909'!D:D,Chart!B14) -> 0 | I14: =H14*$E$3 -> 0 | J14: =I14/$E$25 -> 0 | L14: =+SUMIFS('DĐ RPEXXXX'!J:J,'DĐ RPEXXXX'!D:D,Chart!B14) -> 0 | M14: =L14*$E$3 -> 0 | N14: =M14/$E$25 -> 0
A15: =+A14+1 -> 7 | B15: CHE | C15: Hóa chất | D15: =+SUMIFS('DĐ RPE1609'!J:J,'DĐ RPE1609'!D:D,Chart!B15) -> 0 | E15: =D15*E$3 -> 0 | F15: =E15/$E$25 -> 0 | H15: =+SUMIFS('DĐ RPE1909'!J:J,'DĐ RPE1909'!D:D,Chart!B15) -> 0 | I15: =H15*$E$3 -> 0 | J15: =I15/$E$25 -> 0 | L15: =+SUMIFS('DĐ RPEXXXX'!J:J,'DĐ RPEXXXX'!D:D,Chart!B15) -> 0 | M15: =L15*$E$3 -> 0 | N15: =M15/$E$25 -> 0
A16: =+A15+1 -> 8 | B16: H2O | C16: Nước | D16: =+SUMIFS('DĐ RPE1609'!J:J,'DĐ RPE1609'!D:D,Chart!B16) -> 0 | E16: =D16*E$3 -> 0 | F16: =E16/$E$25 -> 0 | H16: =+SUMIFS('DĐ RPE1909'!J:J,'DĐ RPE1909'!D:D,Chart!B16) -> 0 | I16: =H16*$E$3 -> 0 | J16: =I16/$E$25 -> 0 | L16: =+SUMIFS('DĐ RPEXXXX'!J:J,'DĐ RPEXXXX'!D:D,Chart!B16) -> 0 | M16: =L16*$E$3 -> 0 | N16: =M16/$E$25 -> 0
A17: D | C17: Giá thành (A+B+C) | D17: =SUM(D7:D9) -> 21078.231 | E17: =D17*E$3 -> 421564.62 | F17: =E17/$E$25 -> 0.84312924 | H17: =SUM(H7:H9) -> 21078.231 | I17: =H17*$E$3 -> 421564.62 | J17: =I17/$E$25 -> 0.84312924 | L17: =SUM(L7:L9) -> 21078.231 | M17: =L17*$E$3 -> 421564.62 | N17: =M17/$E$25 -> 0.84312924
A18: E | C18: CP quản lý, bán hàng, lãi vay | D18: =+SUM(D19:D21) -> 2500 | E18: =D18*E$3 -> 50000 | F18: =E18/$E$25 -> 0.1 | H18: =+SUM(H19:H21) -> 2500 | I18: =H18*$E$3 -> 50000 | J18: =I18/$E$25 -> 0.1 | L18: =+SUM(L19:L21) -> 2500 | M18: =L18*$E$3 -> 50000 | N18: =M18/$E$25 -> 0.1
A19: 9 | B19: 641 | C19: Chi phí bán hàng | D19: =+SUMIFS('DĐ RPE1609'!J:J,'DĐ RPE1609'!D:D,Chart!B19) -> 1750 | E19: =D19*E$3 -> 35000 | F19: =E19/$E$25 -> 0.07 | H19: =+SUMIFS('DĐ RPE1909'!J:J,'DĐ RPE1909'!D:D,Chart!B19) -> 1750 | I19: =H19*$E$3 -> 35000 | J19: =I19/$E$25 -> 0.07 | L19: =+SUMIFS('DĐ RPEXXXX'!J:J,'DĐ RPEXXXX'!D:D,Chart!B19) -> 1750 | M19: =L19*$E$3 -> 35000 | N19: =M19/$E$25 -> 0.07
A20: 10 | B20: 642 | C20: Chi phí quản lý | D20: =+SUMIFS('DĐ RPE1609'!J:J,'DĐ RPE1609'!D:D,Chart!B20) -> 500 | E20: =D20*E$3 -> 10000 | F20: =E20/$E$25 -> 0.02 | H20: =+SUMIFS('DĐ RPE1909'!J:J,'DĐ RPE1909'!D:D,Chart!B20) -> 500 | I20: =H20*$E$3 -> 10000 | J20: =I20/$E$25 -> 0.02 | L20: =+SUMIFS('DĐ RPEXXXX'!J:J,'DĐ RPEXXXX'!D:D,Chart!B20) -> 500 | M20: =L20*$E$3 -> 10000 | N20: =M20/$E$25 -> 0.02
A21: 11 | B21: 635 | C21: Chi phí lãi vay | D21: =+SUMIFS('DĐ RPE1609'!J:J,'DĐ RPE1609'!D:D,Chart!B21) -> 250 | E21: =D21*E$3 -> 5000 | F21: =E21/$E$25 -> 0.01 | H21: =+SUMIFS('DĐ RPE1909'!J:J,'DĐ RPE1909'!D:D,Chart!B21) -> 250 | I21: =H21*$E$3 -> 5000 | J21: =I21/$E$25 -> 0.01 | L21: =+SUMIFS('DĐ RPEXXXX'!J:J,'DĐ RPEXXXX'!D:D,Chart!B21) -> 250 | M21: =L21*$E$3 -> 5000 | N21: =M21/$E$25 -> 0.01
A22: F | C22: Điểm hòa vốn (D+E) | D22: =+D17+D18 -> 23578.231 | E22: =D22*E$3 -> 471564.62 | F22: =E22/$E$25 -> 0.94312924 | H22: =+H17+H18 -> 23578.231 | I22: =H22*$E$3 -> 471564.62 | J22: =I22/$E$25 -> 0.94312924 | L22: =+L17+L18 -> 23578.231 | M22: =L22*$E$3 -> 471564.62 | N22: =M22/$E$25 -> 0.94312924
A23: 12 | B23: TAX | C23: Thuế thu nhập | D23: =+SUMIFS('DĐ RPE1609'!J:J,'DĐ RPE1609'!D:D,Chart!B23) -> 236.9615 | E23: =D23*E$3 -> 4739.23 | F23: =E23/$E$25 -> 0.0094784601 | H23: =+SUMIFS('DĐ RPE1909'!J:J,'DĐ RPE1909'!D:D,Chart!B23) -> 236.9615 | I23: =H23*$E$3 -> 4739.23 | J23: =I23/$E$25 -> 0.0094784601 | L23: =+SUMIFS('DĐ RPEXXXX'!J:J,'DĐ RPEXXXX'!D:D,Chart!B23) -> 236.9615 | M23: =L23*$E$3 -> 4739.23 | N23: =M23/$E$25 -> 0.0094784601
A24: G | B24: LN | C24: Lợi nhuận sau thuế | D24: =+SUMIFS('DĐ RPE1609'!J:J,'DĐ RPE1609'!D:D,Chart!B24) -> 1184.8075 | E24: =D24*E$3 -> 23696.15 | F24: =E24/$E$25 -> 0.0473923 | H24: =+SUMIFS('DĐ RPE1909'!J:J,'DĐ RPE1909'!D:D,Chart!B24) -> 1184.8075 | I24: =H24*$E$3 -> 23696.15 | J24: =I24/$E$25 -> 0.0473923 | L24: =+SUMIFS('DĐ RPEXXXX'!J:J,'DĐ RPEXXXX'!D:D,Chart!B24) -> 1184.8075 | M24: =L24*$E$3 -> 23696.15 | N24: =M24/$E$25 -> 0.0473923
A25: H | C25: Giá bán | D25: =+D22+D23+D24 -> 25000 | E25: =D25*E$3 -> 500000 | F25: =E25/$E$25 -> 1 | H25: =+H22+H23+H24 -> 25000 | I25: =H25*$E$3 -> 500000 | J25: =I25/$E$25 -> 1 | L25: =+L22+L23+L24 -> 25000 | M25: =L25*$E$3 -> 500000 | N25: =M25/$E$25 -> 1
C26: % Lãi gộp nguyên liệu/Giá bán | F26: =F25-F6-F8 -> 0.39534884 | J26: =J25-J6-J8 -> 0.39534884 | N26: =N25-N6-N8 -> 0.39534884
D27: ="ĐIỂM HÒA VỐN "&ROUND(D22,0)&" Đ" -> ĐIỂM HÒA VỐN 23578 Đ | H27: ="ĐIỂM HÒA VỐN "&ROUND(H22,0)&" Đ" -> ĐIỂM HÒA VỐN 23578 Đ | L27: ="ĐIỂM HÒA VỐN "&ROUND(L22,0)&" Đ" -> ĐIỂM HÒA VỐN 23578 Đ

Sheet DĐ RPE1609
A1: Danh mục | C1: 1
C2: PHƯƠNG ÁN SẢN XUẤT DĐ 1
C4: Nguyên liệu: | D4: NL 1
C5: Thành phẩm: | D5: =TH!C6 -> Dây đai RPE1609 | J5: Quy cách đóng gói: | K5: =TH!E6 -> 20
C6: Quy cách: | D6: =TH!D6 -> 16 mm x 0.9 mm
C7: No. | D7: Nhóm | E7: Mã SAP | F7: Chi phí Cost Items | G7: Đơn vị tính Unit | H7: Định mức Standard | I7: Đơn giá (VNĐ) | J7: Chi phí đơn vị (VNĐ /Kg) | K7: Đơn giá (VND /Cuộn) | L7: % giá bán | M7: Cơ sở tính
C8: A | D8: CÔNG ĐOẠN TẠO VẢY GCDĐ:
B9: Vảy GCDĐ | C9: I | F9: Vảy GCDĐ | G9: vnđ /Kg | H9: 1 | I9: 12000 | J9: =I9 -> 12000 | K9: =J9*$K$5 -> 240000 | L9: =J9/$J$58 -> 0.92307692
B10: Hao hụt | C10: II | F10: Hao hụt | G10: % | H10: =SUM(H11:H20) -> 0 | J10: =SUM(J11:J20) -> 0 | K10: =J10*$K$5 -> 0 | L10: =J10/$J$58 -> 0
G11: % | J11: =+($J$9-I11)*H11 -> 0 | K11: =J11*$K$5 -> 0 | L11: =J11/$J$58 -> 0
G12: % | J12: =+($J$9-I12)*H12 -> 0 | K12: =J12*$K$5 -> 0 | L12: =J12/$J$58 -> 0
G13: % | J13: =+($J$9-I13)*H13 -> 0 | K13: =J13*$K$5 -> 0 | L13: =J13/$J$58 -> 0
G14: % | J14: =+($J$9-I14)*H14 -> 0 | K14: =J14*$K$5 -> 0 | L14: =J14/$J$58 -> 0
G15: % | J15: =+($J$9-I15)*H15 -> 0 | K15: =J15*$K$5 -> 0 | L15: =J15/$J$58 -> 0
G16: % | J16: =+($J$9-I16)*H16 -> 0 | K16: =J16*$K$5 -> 0 | L16: =J16/$J$58 -> 0
G17: % | J17: =+($J$9-I17)*H17 -> 0 | K17: =J17*$K$5 -> 0 | L17: =J17/$J$58 -> 0
G18: % | J18: =+($J$9-I18)*H18 -> 0 | K18: =J18*$K$5 -> 0 | L18: =J18/$J$58 -> 0
G19: % | J19: =+($J$9-I19)*H19 -> 0 | K19: =J19*$K$5 -> 0 | L19: =J19/$J$58 -> 0
A20: Mất đi | F20: Hao hụt n | G20: % | J20: =+($J$9-I20)*H20 -> 0 | K20: =J20*$K$5 -> 0 | L20: =J20/$J$58 -> 0 | M20: Hao hụt mất đi
C21: III | F21: Chi phí VC | J21: =SUM(J22:J33) -> 0 | K21: =J21*$K$5 -> 0 | L21: =J21/$J$58 -> 0
C22: 0 | D22: REL01 | F22: Công suất máy (capacity) | G22: Kg /h | K22: =J22*$K$5 -> 0
F23: Hiệu suất máy | G23: % | K23: =J23*$K$5 -> 0
K24: =J24*$K$5 -> 0 | L24: =J24/$J$58 -> 0
K25: =J25*$K$5 -> 0 | L25: =J25/$J$58 -> 0
K26: =J26*$K$5 -> 0 | L26: =J26/$J$58 -> 0
K27: =J27*$K$5 -> 0 | L27: =J27/$J$58 -> 0
K28: =J28*$K$5 -> 0 | L28: =J28/$J$58 -> 0
K29: =J29*$K$5 -> 0 | L29: =J29/$J$58 -> 0
K30: =J30*$K$5 -> 0 | L30: =J30/$J$58 -> 0
K31: =J31*$K$5 -> 0 | L31: =J31/$J$58 -> 0
K32: =J32*$K$5 -> 0 | L32: =J32/$J$58 -> 0
C33: =+C28+1 -> 1 | D33: OTH | E33: 6277.6278 | F33: Chi phí bằng tiền khác | G33: VND | K33: =J33*$K$5 -> 0 | L33: =J33/$J$58 -> 0
D34: Cộng giá thành Vảy GCDĐ (I+II+III) | J34: =J9+J10+J21 -> 12000 | K34: =J34*$K$5 -> 240000 | L34: =J34/$J$58 -> 0.92307692
C35: B | D35: CÔNG ĐOẠN TẠO VẢY MIXED: | K35: =J35*$K$5 -> 0
C36: IV | F36: Chi phí Vảy GCDĐ | G36: Kg | H36: 1 | I36: =+J34 -> 12000 | J36: =+H36*I36 -> 12000 | K36: =J36*$K$5 -> 240000 | L36: =J36/$J$58 -> 0.92307692
C37: V | F37: Chi phí mixed màu | J37: =SUM(J40:J57) -> 1000 | K37: =J37*$K$5 -> 20000 | L37: =J37/$J$58 -> 0.076923077
C38: 0 | D38: VBAL1 | F38: Công suất máy (capacity) | G38: Kg /h | K38: =J38*$K$5 -> 0
F39: Hiệu suất máy | G39: % | K39: =J39*$K$5 -> 0
B40: Vảy GCDĐ | J40: =+($J$34-I40)*H40 -> 0 | K40: =J40*$K$5 -> 0 | L40: =J40/$J$58 -> 0
B41: Hao hụt | J41: =+($J$34-I41)*H41 -> 0 | K41: =J41*$K$5 -> 0 | L41: =J41/$J$58 -> 0
J42: =+($J$34-I42)*H42 -> 0 | K42: =J42*$K$5 -> 0 | L42: =J42/$J$58 -> 0
J43: =+($J$34-I43)*H43 -> 0 | K43: =J43*$K$5 -> 0 | L43: =J43/$J$58 -> 0
J44: =+H44*I44 -> 0 | K44: =J44*$K$5 -> 0 | L44: =J44/$J$58 -> 0
J45: =+H45*I45 -> 0 | K45: =J45*$K$5 -> 0 | L45: =J45/$J$58 -> 0
J46: =+H46*I46 -> 0 | K46: =J46*$K$5 -> 0 | L46: =J46/$J$58 -> 0
K47: =J47*$K$5 -> 0 | L47: =J47/$J$58 -> 0
K48: =J48*$K$5 -> 0 | L48: =J48/$J$58 -> 0
K49: =J49*$K$5 -> 0 | L49: =J49/$J$58 -> 0
K50: =J50*$K$5 -> 0 | L50: =J50/$J$58 -> 0
K51: =J51*$K$5 -> 0 | L51: =J51/$J$58 -> 0
K52: =J52*$K$5 -> 0 | L52: =J52/$J$58 -> 0
K53: =J53*$K$5 -> 0 | L53: =J53/$J$58 -> 0
K54: =J54*$K$5 -> 0 | L54: =J54/$J$58 -> 0
K55: =J55*$K$5 -> 0 | L55: =J55/$J$58 -> 0
K56: =J56*$K$5 -> 0 | L56: =J56/$J$58 -> 0
F57: Hạt màu | I57: 1000 | J57: =I57 -> 1000 | K57: =J57*$K$5 -> 20000 | L57: =J57/$J$58 -> 0.076923077
D58: Giá thành Vảy GCDĐ Mixed (IV+V): | J58: =J36+J37 -> 13000 | K58: =J58*$K$5 -> 260000 | L58: =J58/$J$58 -> 1
C59: C | D59: CÔNG ĐOẠN TẠO CUỘN: | K59: =J59*$K$5 -> 0
C60: I | F60: Vảy GCDĐ Mixed | H60: 1 | J60: =+J58 -> 13000 | K60: =J60*$K$5 -> 260000 | L60: =J60/$J$109 -> 0.52
C61: II | F61: Chi phí sản xuất dây đai | J61: =SUM(J62:J79) -> 20911.564 | K61: =J61*$K$5 -> 418231.29 | L61: =J61/$J$109 -> 0.83646257
A62: Tạo cuộn | C62: 0 | D62: REL01 | F62: Công suất máy (capacity) | G62: Kg /h | H62: 300 | K62: =J62*$K$5 -> 0 | M62: Công suất máy 6000 (CW1: 1500, CW2:1500, Boretech 3000)
A63: Tạo cuộn | F63: Hiệu suất máy | G63: % | H63: 0.75 | K63: =J63*$K$5 -> 0 | M63: Bình quân 3 tháng liền kề theo BI
A64: Đầu keo | B64: Hao hụt | C64: =+C63+1 -> 1 | D64: 1521 | F64: Vảy GCDĐ Mixed | G64: % | H64: =1/'[3]2.Hao hut'!$E$29 -> 1.1627907 | I64: 13000 | J64: =+(J$60-I614)*H64-J68 -> 13296.279 | K64: =J64*$K$5 -> 265925.58 | L64: =J64/$J$109 -> 0.53185116 | M64: Thu hồi theo giá thị trường | N64: 4.0389911 | O64: =+K64-N64 -> 265921.54
A65: HAD | B65: Hao hụt | C65: =+C64+1 -> 2 | G65: % | J65: =+(J$60-I65)*H65 -> 0 | K65: =J65*$K$5 -> 0 | L65: =J65/$J$109 -> 0 | M65: Thu hồi theo giá thị trường | N65: 3.6668698 | O65: =+K65-N65 -> -3.6668698
A66: Bụi | B66: Hao hụt | C66: =+C65+1 -> 3 | G66: % | J66: =+(J$60-I66)*H66 -> 0 | K66: =J66*$K$5 -> 0 | L66: =J66/$J$109 -> 0 | M66: Thu hồi theo giá thị trường | N66: 0 | O66: =+K66-N66 -> 0
A67: PP Hạt | B67: Hao hụt | C67: =+C66+1 -> 4 | G67: % | J67: =+(J$60-I67)*H67 -> 0 | K67: =J67*$K$5 -> 0 | L67: =J67/$J$109 -> 0 | M67: Thu hồi theo giá thị trường | N67: 2.5970685 | O67: =+K67-N67 -> -2.5970685
A68: Mất đi | B68: Hao hụt | C68: =+C67+1 -> 5 | D68: 1522 | F68: Hao hụt | G68: % | H68: ='[3]2.Hao hut'!$E$11 -> 0.14 | I68: 10000 | J68: =+(J$60)*H68 -> 1820 | K68: =J68*$K$5 -> 36400 | L68: =J68/$J$109 -> 0.0728 | M68: Hao hụt mất đi | N68: 1.7145151 | O68: =+K68-N68 -> 36398.285
B69: Phụ gia | C69: =+C68+1 -> 6 | D69: CHE | E69: 120003033 | F69: Phụ gia | G69: % | J69: =+H69*I69 -> 0 | K69: =J69*$K$5 -> 0 | L69: =J69/$J$109 -> 0 | M69: Hóa chất theo BOM | N69: 3.7365765 | O69: =+K69-N69 -> -3.7365765
A70: Tạo cuộn | B70: NCTT | C70: =+C69+1 -> 7 | D70: LAB | E70: 622 | F70: Chi phí nhân công trực tiếp | G70: tháng | H70: 1 | I70: ='[3]Dinh muc'!$I$6 -> 335.91731 | J70: =H70*I70 -> 335.91731 | K70: =J70*$K$5 -> 6718.3463 | L70: =J70/$J$109 -> 0.013436693 | N70: 2.3146075 | O70: =+K70-N70 -> 6716.0316
A71: Tạo cuộn | B71: NCGT | C71: =+C70+1 -> 8 | D71: LAB | E71: 6271 | F71: Chi phí nhân công gián tiếp | G71: tháng | H71: 1 | I71: ='[3]Dinh muc'!$I$10 -> 565.16473 | J71: =H71*I71 -> 565.16473 | K71: =J71*$K$5 -> 11303.295 | L71: =J71/$J$109 -> 0.022606589 | M71: Lương trưởng ca, hành chính, tổ trưởng, quản lý sản xuất gián tiếp như QC, Kỹ thuật | N71: 10.418755 | O71: =+K71-N71 -> 11292.876
A72: Tạo cuộn | B72: VTPX | C72: =+C71+1 -> 9 | D72: OTH | E72: 6272 | F72: Chi phí vật tư phân xưởng | G72: tháng | H72: 1 | I72: ='[3]Dinh muc'!$K$15 -> 1997.8779 | J72: =H72*I72 -> 1997.8779 | K72: =J72*$K$5 -> 39957.558 | L72: =J72/$J$109 -> 0.079915116 | M72: Chi phí thực tế bình quân 3 tháng liền kề | N72: 2.6427307 | O72: =+K72-N72 -> 39954.915
A73: Tạo cuộn | B73: CCDC | C73: =+C72+1 -> 10 | D73: OTH | E73: 6273 | F73: Chi phí CCDC, bảo trì | G73: tháng | H73: 1 | J73: =H73*I73 -> 0 | K73: =J73*$K$5 -> 0 | L73: =J73/$J$109 -> 0 | M73: Chi phí thực tế bình quân 3 tháng liền kề | N73: 6.0380666 | O73: =+K73-N73 -> -6.0380666
A74: Tạo cuộn | B74: KH | C74: =+C73+1 -> 11 | D74: DEP | E74: 6274.1 | F74: Chi phí khấu hao MMTB chính | G74: tháng | H74: 1 | I74: ='[3]PB_TSCD DC'!$AR$32 -> 326.55786 | J74: =H74*I74 -> 326.55786 | K74: =J74*$K$5 -> 6531.1572 | L74: =J74/$J$109 -> 0.013062314 | M74: Chi phí thực tế bình quân 3 tháng liền kề theo danh sách TSCĐ | N74: 20.249816 | O74: =+K74-N74 -> 6510.9074
A75: Tạo cuộn | B75: KH | C75: =+C74+1 -> 12 | D75: DEP | E75: 6274.2 | F75: Chi phí khấu hao MMTB phụ | G75: tháng | H75: 1 | J75: =H75*I75 -> 0 | K75: =J75*$K$5 -> 0 | L75: =J75/$J$109 -> 0 | M75: Chi phí thực tế bình quân 3 tháng liền kề theo danh sách TSCĐ | N75: 1.8659215 | O75: =+K75-N75 -> -1.8659215
A76: Tạo cuộn | B76: KH | C76: =+C75+1 -> 13 | D76: DEP | E76: 6274.3 | F76: Chi phí khấu hao MMTB dùng chung | G76: tháng | H76: 1 | J76: =H76*I76 -> 0 | K76: =J76*$K$5 -> 0 | L76: =J76/$J$109 -> 0 | M76: Chi phí thực tế bình quân 3 tháng liền kề theo danh sách TSCĐ | N76: 2.1907838 | O76: =+K76-N76 -> -2.1907838
A77: Tạo cuộn | B77: KH | C77: =+C76+1 -> 14 | D77: DEP | E77: 6274.4 | F77: Chi phí khấu hao nhà xưởng | G77: tháng | H77: 1 | J77: =H77*I77 -> 0 | K77: =J77*$K$5 -> 0 | L77: =J77/$J$109 -> 0 | M77: Chi phí thực tế bình quân 3 tháng liền kề theo danh sách TSCĐ | N77: 2.8399046 | O77: =+K77-N77 -> -2.8399046
A78: Tạo cuộn | B78: Điện | C78: =+C74+1 -> 12 | D78: ELEC | E78: 6275 | F78: Điện (electronic) Starlinger | G78: Kwh | H78: 1 | I78: ='[3]Dinh muc'!$G$14 -> 2569.7674 | J78: =H78*I78 -> 2569.7674 | K78: =J78*$K$5 -> 51395.349 | L78: =J78/$J$109 -> 0.1027907 | M78: Chi phí thực tế bình quân 3 tháng liền kề. CW1: 752 Kwh, CW2: 752 Kwh, Boretech: 1254 Kwh | N78: 15.547201 | O78: =+K78-N78 -> 51379.802
A79: Tạo cuộn | B79: Khác | C79: =+C78+1 -> 13 | D79: OTH | E79: 6277.6278 | F79: Chi phí bằng tiền khác | G79: tháng | H79: 1 | J79: =H79*I79 -> 0 | K79: =J79*$K$5 -> 0 | L79: =J79/$J$109 -> 0 | M79: Chi phí thực tế bình quân 3 tháng liền kề | N79: 5.1172085 | O79: =+K79-N79 -> -5.1172085
D80: Giá thành dây đai(III+IV) | J80: =+J61 -> 20911.564 | K80: =J80*$K$5 -> 418231.29 | L80: =J80/$J$109 -> 0.83646257
C81: D | D81: CÔNG ĐOẠN ĐÓNG GÓI: | K81: =J81*$K$5 -> 0
C82: III | F82: Cuộn dây đai RPE1609 | J82: =J80 -> 20911.564 | K82: =J82*$K$5 -> 418231.29 | L82: =J82/$J$109 -> 0.83646257
C83: IV | F83: Chi phí đóng gói | J83: =SUM(J84:J98) -> 166.66667 | K83: =J83*$K$5 -> 3333.3333 | L83: =J83/$J$109 -> 0.0066666667
A84: Nâng IV 10H | C84: 0 | D84: REL01 | F84: Công suất máy (capacity) | G84: Kg /h | K84: =J84*$K$5 -> 0 | M84: Công suất máy 3492 (SSP-01: 1092, SSP-02: 2400)
A85: Nâng IV 10H | F85: Hiệu suất máy | G85: % | K85: =J85*$K$5 -> 0 | M85: Bình quân 3 tháng liền kề theo BI
B86: Bao bì | C86: =+C85+1 -> 1 | D86: BAG | F86: Pallet D4-1137R không nút-GC | G86: cái | H86: 1 | J86: =(I86*H86)/1100 -> 0 | K86: =J86*$K$5 -> 0 | L86: =J86/$J$109 -> 0 | M86: Giao trong nước pallet đen, giao xuất khẩu pallet gỗ
B87: Bao bì | C87: =+C86+1 -> 2 | D87: BAG | F87: Bao jumbo 105Lx105Wx150H (cm) đựng vảy | G87: cái | H87: 1 | J87: =(I87*H87)/1100 -> 0 | K87: =J87*$K$5 -> 0 | L87: =J87/$J$109 -> 0 | M87: 1100 kg hạt/bao
B88: Bao bì | C88: =+C87+1 -> 3 | D88: BAG | F88: Bao PE lót ngoài bao Jumbo | G88: cái | H88: 1 | J88: =(I88*H88)/1100 -> 0 | K88: =J88*$K$5 -> 0 | L88: =J88/$J$109 -> 0 | M88: 1100 kg hạt/bao
A89: Nâng IV | B89: NCTT | C89: =+C88+1 -> 4 | D89: LAB | E89: 622 | F89: Chi phí nhân công trực tiếp | G89: tháng | H89: 1 | K89: =J89*$K$5 -> 0 | L89: =J89/$J$109 -> 0 | M89: Nạp liệu 1, đóng gói 1, xe nâng 1
A90: Nâng IV | B90: NCGT | C90: =+C89+1 -> 5 | D90: LAB | E90: 6271 | F90: Chi phí nhân công gián tiếp | G90: tháng | H90: 1 | K90: =J90*$K$5 -> 0 | L90: =J90/$J$109 -> 0 | M90: Lương trưởng ca, hành chính, tổ trưởng, quản lý sản xuất gián tiếp như QC, Kỹ thuật
A91: Nâng IV | B91: VTPX | C91: =+C90+1 -> 6 | D91: OTH | E91: 6272 | F91: Chi phí vật tư phân xưởng | G91: tháng | H91: 1 | I91: ='[3]Dinh muc'!$G$18 -> 166.66667 | J91: =H91*I91 -> 166.66667 | K91: =J91*$K$5 -> 3333.3333 | L91: =J91/$J$109 -> 0.0066666667 | M91: Chi phí thực tế bình quân 3 tháng liền kề
A92: Nâng IV | B92: CCDC | C92: =+C91+1 -> 7 | D92: OTH | E92: 6273 | G92: tháng | H92: 1 | K92: =J92*$K$5 -> 0 | L92: =J92/$J$109 -> 0 | M92: Chi phí thực tế bình quân 3 tháng liền kề
A93: Nâng IV | B93: KH | C93: =+C92+1 -> 8 | D93: DEP | E93: 6274.1 | G93: tháng | H93: 1 | K93: =J93*$K$5 -> 0 | L93: =J93/$J$109 -> 0 | M93: Chi phí thực tế bình quân 3 tháng liền kề theo danh sách TSCĐ
A94: Nâng IV | B94: KH | C94: =+C93+1 -> 9 | D94: DEP | E94: 6274.2 | G94: tháng | H94: 1 | K94: =J94*$K$5 -> 0 | L94: =J94/$J$109 -> 0 | M94: Chi phí thực tế bình quân 3 tháng liền kề theo danh sách TSCĐ
A95: Nâng IV | B95: KH | C95: =+C94+1 -> 10 | D95: DEP | E95: 6274.3 | G95: tháng | H95: 1 | K95: =J95*$K$5 -> 0 | L95: =J95/$J$109 -> 0 | M95: Chi phí thực tế bình quân 3 tháng liền kề theo danh sách TSCĐ
A96: Nâng IV | B96: KH | C96: =+C95+1 -> 11 | D96: DEP | E96: 6274.4 | G96: tháng | H96: 1 | K96: =J96*$K$5 -> 0 | L96: =J96/$J$109 -> 0 | M96: Chi phí thực tế bình quân 3 tháng liền kề theo danh sách TSCĐ
A97: Nâng IV | B97: Điện | C97: =+C93+1 -> 9 | D97: ELEC | E97: 6275 | G97: tháng | H97: 1 | K97: =J97*$K$5 -> 0 | L97: =J97/$J$109 -> 0 | M97: Chi phí thực tế bình quân 3 tháng liền kề. CW1: 946 Kwh, Boretech: 487 Kwh
A98: Nâng IV | B98: Khác | C98: =+C97+1 -> 10 | D98: OTH | E98: 6277.6278 | G98: tháng | H98: 1 | K98: =J98*$K$5 -> 0 | L98: =J98/$J$109 -> 0 | M98: Chi phí thực tế bình quân 3 tháng liền kề
C99: V | F99: Chi phí quản lý (BH, QL,TC) | J99: =SUM(J100:J104) -> 2500 | K99: =J99*$K$5 -> 50000 | L99: =J99/$J$109 -> 0.1
A100: LuongBH | B100: 641 | C100: 1 | D100: 641 | F100: Chi phí nhân sự bán hàng | G100: tháng | H100: 1 | I100: =7%*TH!G6 -> 1750 | J100: =H100*I100 -> 1750 | K100: =J100*$K$5 -> 35000 | L100: =J100/$J$109 -> 0.07 | M100: Chi phí lương BGĐ, kế toán, HCNS, bán hàng…
A101: LuongQL | B101: 642 | C101: =+C100+1 -> 2 | D101: 642 | F101: Chi phí nhân sự quản lý | G101: tháng | H101: 1 | I101: =2%*TH!G7 -> 500 | J101: =H101*I101 -> 500 | K101: =J101*$K$5 -> 10000 | L101: =J101/$J$109 -> 0.02 | M101: Chi phí lương BGĐ, kế toán, HCNS, bán hàng…
...

Sheet DĐ RPE1909
A1: Danh mục | C1: 1
C2: PHƯƠNG ÁN SẢN XUẤT DĐ 2
C4: Nguyên liệu: | D4: NL 2
C5: Thành phẩm: | D5: =TH!C7 -> Dây đai RPE1909 | J5: Quy cách đóng gói: | K5: =TH!E7 -> 20
C6: Quy cách: | D6: =TH!D7 -> 19 mm x 0.9 mm
C7: No. | D7: Nhóm | E7: Mã SAP | F7: Chi phí Cost Items | G7: Đơn vị tính Unit | H7: Định mức Standard | I7: Đơn giá (VNĐ) | J7: Chi phí đơn vị (VNĐ /Kg) | K7: Đơn giá (VND /Cuộn) | L7: % giá bán | M7: Cơ sở tính
C8: A | D8: CÔNG ĐOẠN TẠO VẢY GCDĐ:
B9: Vảy GCDĐ | C9: I | F9: Vảy GCDĐ | G9: vnđ /Kg | H9: 1 | I9: 12000 | J9: =I9 -> 12000 | K9: =J9*$K$5 -> 240000 | L9: =J9/$J$58 -> 0.92307692
B10: Hao hụt | C10: II | F10: Hao hụt | G10: % | H10: =SUM(H11:H20) -> 0 | J10: =SUM(J11:J20) -> 0 | K10: =J10*$K$5 -> 0 | L10: =J10/$J$58 -> 0
G11: % | J11: =+($J$9-I11)*H11 -> 0 | K11: =J11*$K$5 -> 0 | L11: =J11/$J$58 -> 0
G12: % | J12: =+($J$9-I12)*H12 -> 0 | K12: =J12*$K$5 -> 0 | L12: =J12/$J$58 -> 0
G13: % | J13: =+($J$9-I13)*H13 -> 0 | K13: =J13*$K$5 -> 0 | L13: =J13/$J$58 -> 0
G14: % | J14: =+($J$9-I14)*H14 -> 0 | K14: =J14*$K$5 -> 0 | L14: =J14/$J$58 -> 0
G15: % | J15: =+($J$9-I15)*H15 -> 0 | K15: =J15*$K$5 -> 0 | L15: =J15/$J$58 -> 0
G16: % | J16: =+($J$9-I16)*H16 -> 0 | K16: =J16*$K$5 -> 0 | L16: =J16/$J$58 -> 0
G17: % | J17: =+($J$9-I17)*H17 -> 0 | K17: =J17*$K$5 -> 0 | L17: =J17/$J$58 -> 0
G18: % | J18: =+($J$9-I18)*H18 -> 0 | K18: =J18*$K$5 -> 0 | L18: =J18/$J$58 -> 0
G19: % | J19: =+($J$9-I19)*H19 -> 0 | K19: =J19*$K$5 -> 0 | L19: =J19/$J$58 -> 0
A20: Mất đi | F20: Hao hụt n | G20: % | J20: =+($J$9-I20)*H20 -> 0 | K20: =J20*$K$5 -> 0 | L20: =J20/$J$58 -> 0 | M20: Hao hụt mất đi
C21: III | F21: Chi phí VC | J21: =SUM(J22:J33) -> 0 | K21: =J21*$K$5 -> 0 | L21: =J21/$J$58 -> 0
C22: 0 | D22: REL01 | F22: Công suất máy (capacity) | G22: Kg /h | K22: =J22*$K$5 -> 0
F23: Hiệu suất máy | G23: % | K23: =J23*$K$5 -> 0
K24: =J24*$K$5 -> 0 | L24: =J24/$J$58 -> 0
K25: =J25*$K$5 -> 0 | L25: =J25/$J$58 -> 0
K26: =J26*$K$5 -> 0 | L26: =J26/$J$58 -> 0
K27: =J27*$K$5 -> 0 | L27: =J27/$J$58 -> 0
K28: =J28*$K$5 -> 0 | L28: =J28/$J$58 -> 0
K29: =J29*$K$5 -> 0 | L29: =J29/$J$58 -> 0
K30: =J30*$K$5 -> 0 | L30: =J30/$J$58 -> 0
K31: =J31*$K$5 -> 0 | L31: =J31/$J$58 -> 0
K32: =J32*$K$5 -> 0 | L32: =J32/$J$58 -> 0
C33: =+C28+1 -> 1 | D33: OTH | E33: 6277.6278 | F33: Chi phí bằng tiền khác | G33: VND | K33: =J33*$K$5 -> 0 | L33: =J33/$J$58 -> 0
D34: Cộng giá thành Vảy GCDĐ (I+II+III) | J34: =J9+J10+J21 -> 12000 | K34: =J34*$K$5 -> 240000 | L34: =J34/$J$58 -> 0.92307692
C35: B | D35: CÔNG ĐOẠN TẠO VẢY MIXED: | K35: =J35*$K$5 -> 0
C36: IV | F36: Chi phí Vảy GCDĐ | G36: Kg | H36: 1 | I36: =+J34 -> 12000 | J36: =+H36*I36 -> 12000 | K36: =J36*$K$5 -> 240000 | L36: =J36/$J$58 -> 0.92307692
C37: V | F37: Chi phí mixed màu | J37: =SUM(J40:J57) -> 1000 | K37: =J37*$K$5 -> 20000 | L37: =J37/$J$58 -> 0.076923077
C38: 0 | D38: VBAL1 | F38: Công suất máy (capacity) | G38: Kg /h | K38: =J38*$K$5 -> 0
F39: Hiệu suất máy | G39: % | K39: =J39*$K$5 -> 0
B40: Vảy GCDĐ | J40: =+($J$34-I40)*H40 -> 0 | K40: =J40*$K$5 -> 0 | L40: =J40/$J$58 -> 0
B41: Hao hụt | J41: =+($J$34-I41)*H41 -> 0 | K41: =J41*$K$5 -> 0 | L41: =J41/$J$58 -> 0
J42: =+($J$34-I42)*H42 -> 0 | K42: =J42*$K$5 -> 0 | L42: =J42/$J$58 -> 0
J43: =+($J$34-I43)*H43 -> 0 | K43: =J43*$K$5 -> 0 | L43: =J43/$J$58 -> 0
J44: =+H44*I44 -> 0 | K44: =J44*$K$5 -> 0 | L44: =J44/$J$58 -> 0
J45: =+H45*I45 -> 0 | K45: =J45*$K$5 -> 0 | L45: =J45/$J$58 -> 0
J46: =+H46*I46 -> 0 | K46: =J46*$K$5 -> 0 | L46: =J46/$J$58 -> 0
K47: =J47*$K$5 -> 0 | L47: =J47/$J$58 -> 0
K48: =J48*$K$5 -> 0 | L48: =J48/$J$58 -> 0
K49: =J49*$K$5 -> 0 | L49: =J49/$J$58 -> 0
K50: =J50*$K$5 -> 0 | L50: =J50/$J$58 -> 0
K51: =J51*$K$5 -> 0 | L51: =J51/$J$58 -> 0
K52: =J52*$K$5 -> 0 | L52: =J52/$J$58 -> 0
K53: =J53*$K$5 -> 0 | L53: =J53/$J$58 -> 0
K54: =J54*$K$5 -> 0 | L54: =J54/$J$58 -> 0
K55: =J55*$K$5 -> 0 | L55: =J55/$J$58 -> 0
K56: =J56*$K$5 -> 0 | L56: =J56/$J$58 -> 0
F57: Hạt màu | I57: 1000 | J57: =I57 -> 1000 | K57: =J57*$K$5 -> 20000 | L57: =J57/$J$58 -> 0.076923077
D58: Giá thành Vảy GCDĐ Mixed (IV+V): | J58: =J36+J37 -> 13000 | K58: =J58*$K$5 -> 260000 | L58: =J58/$J$58 -> 1
C59: C | D59: CÔNG ĐOẠN TẠO CUỘN: | K59: =J59*$K$5 -> 0
C60: I | F60: Vảy GCDĐ Mixed | H60: 1 | J60: =+J58 -> 13000 | K60: =J60*$K$5 -> 260000 | L60: =J60/$J$109 -> 0.52
C61: II | F61: Chi phí sản xuất dây đai | J61: =SUM(J62:J79) -> 20911.564 | K61: =J61*$K$5 -> 418231.29 | L61: =J61/$J$109 -> 0.83646257
A62: Tạo cuộn | C62: 0 | D62: REL01 | F62: Công suất máy (capacity) | G62: Kg /h | H62: 300 | K62: =J62*$K$5 -> 0 | M62: Công suất máy 6000 (CW1: 1500, CW2:1500, Boretech 3000)
A63: Tạo cuộn | F63: Hiệu suất máy | G63: % | H63: 0.75 | K63: =J63*$K$5 -> 0 | M63: Bình quân 3 tháng liền kề theo BI
A64: Đầu keo | B64: Hao hụt | C64: =+C63+1 -> 1 | D64: 1521 | F64: Vảy GCDĐ Mixed | G64: % | H64: =1/'[3]2.Hao hut'!$E$29 -> 1.1627907 | I64: 13000 | J64: =+(J$60-I614)*H64-J68 -> 13296.279 | K64: =J64*$K$5 -> 265925.58 | L64: =J64/$J$109 -> 0.53185116 | M64: Thu hồi theo giá thị trường | N64: 4.0389911 | O64: =+K64-N64 -> 265921.54
A65: HAD | B65: Hao hụt | C65: =+C64+1 -> 2 | G65: % | J65: =+(J$60-I65)*H65 -> 0 | K65: =J65*$K$5 -> 0 | L65: =J65/$J$109 -> 0 | M65: Thu hồi theo giá thị trường | N65: 3.6668698 | O65: =+K65-N65 -> -3.6668698
A66: Bụi | B66: Hao hụt | C66: =+C65+1 -> 3 | G66: % | J66: =+(J$60-I66)*H66 -> 0 | K66: =J66*$K$5 -> 0 | L66: =J66/$J$109 -> 0 | M66: Thu hồi theo giá thị trường | N66: 0 | O66: =+K66-N66 -> 0
A67: PP Hạt | B67: Hao hụt | C67: =+C66+1 -> 4 | G67: % | J67: =+(J$60-I67)*H67 -> 0 | K67: =J67*$K$5 -> 0 | L67: =J67/$J$109 -> 0 | M67: Thu hồi theo giá thị trường | N67: 2.5970685 | O67: =+K67-N67 -> -2.5970685
A68: Mất đi | B68: Hao hụt | C68: =+C67+1 -> 5 | D68: 1522 | F68: Hao hụt | G68: % | H68: ='[3]2.Hao hut'!$E$11 -> 0.14 | I68: 10000 | J68: =+(J$60)*H68 -> 1820 | K68: =J68*$K$5 -> 36400 | L68: =J68/$J$109 -> 0.0728 | M68: Hao hụt mất đi | N68: 1.7145151 | O68: =+K68-N68 -> 36398.285
B69: Phụ gia | C69: =+C68+1 -> 6 | D69: CHE | E69: 120003033 | F69: Phụ gia | G69: % | J69: =+H69*I69 -> 0 | K69: =J69*$K$5 -> 0 | L69: =J69/$J$109 -> 0 | M69: Hóa chất theo BOM | N69: 3.7365765 | O69: =+K69-N69 -> -3.7365765
A70: Tạo cuộn | B70: NCTT | C70: =+C69+1 -> 7 | D70: LAB | E70: 622 | F70: Chi phí nhân công trực tiếp | G70: tháng | H70: 1 | I70: ='[3]Dinh muc'!$I$6 -> 335.91731 | J70: =H70*I70 -> 335.91731 | K70: =J70*$K$5 -> 6718.3463 | L70: =J70/$J$109 -> 0.013436693 | N70: 2.3146075 | O70: =+K70-N70 -> 6716.0316
A71: Tạo cuộn | B71: NCGT | C71: =+C70+1 -> 8 | D71: LAB | E71: 6271 | F71: Chi phí nhân công gián tiếp | G71: tháng | H71: 1 | I71: ='[3]Dinh muc'!$I$10 -> 565.16473 | J71: =H71*I71 -> 565.16473 | K71: =J71*$K$5 -> 11303.295 | L71: =J71/$J$109 -> 0.022606589 | M71: Lương trưởng ca, hành chính, tổ trưởng, quản lý sản xuất gián tiếp như QC, Kỹ thuật | N71: 10.418755 | O71: =+K71-N71 -> 11292.876
A72: Tạo cuộn | B72: VTPX | C72: =+C71+1 -> 9 | D72: OTH | E72: 6272 | F72: Chi phí vật tư phân xưởng | G72: tháng | H72: 1 | I72: ='[3]Dinh muc'!$K$15 -> 1997.8779 | J72: =H72*I72 -> 1997.8779 | K72: =J72*$K$5 -> 39957.558 | L72: =J72/$J$109 -> 0.079915116 | M72: Chi phí thực tế bình quân 3 tháng liền kề | N72: 2.6427307 | O72: =+K72-N72 -> 39954.915
A73: Tạo cuộn | B73: CCDC | C73: =+C72+1 -> 10 | D73: OTH | E73: 6273 | F73: Chi phí CCDC, bảo trì | G73: tháng | H73: 1 | J73: =H73*I73 -> 0 | K73: =J73*$K$5 -> 0 | L73: =J73/$J$109 -> 0 | M73: Chi phí thực tế bình quân 3 tháng liền kề | N73: 6.0380666 | O73: =+K73-N73 -> -6.0380666
A74: Tạo cuộn | B74: KH | C74: =+C73+1 -> 11 | D74: DEP | E74: 6274.1 | F74: Chi phí khấu hao MMTB chính | G74: tháng | H74: 1 | I74: ='[3]PB_TSCD DC'!$AR$32 -> 326.55786 | J74: =H74*I74 -> 326.55786 | K74: =J74*$K$5 -> 6531.1572 | L74: =J74/$J$109 -> 0.013062314 | M74: Chi phí thực tế bình quân 3 tháng liền kề theo danh sách TSCĐ | N74: 20.249816 | O74: =+K74-N74 -> 6510.9074
A75: Tạo cuộn | B75: KH | C75: =+C74+1 -> 12 | D75: DEP | E75: 6274.2 | F75: Chi phí khấu hao MMTB phụ | G75: tháng | H75: 1 | J75: =H75*I75 -> 0 | K75: =J75*$K$5 -> 0 | L75: =J75/$J$109 -> 0 | M75: Chi phí thực tế bình quân 3 tháng liền kề theo danh sách TSCĐ | N75: 1.8659215 | O75: =+K75-N75 -> -1.8659215
A76: Tạo cuộn | B76: KH | C76: =+C75+1 -> 13 | D76: DEP | E76: 6274.3 | F76: Chi phí khấu hao MMTB dùng chung | G76: tháng | H76: 1 | J76: =H76*I76 -> 0 | K76: =J76*$K$5 -> 0 | L76: =J76/$J$109 -> 0 | M76: Chi phí thực tế bình quân 3 tháng liền kề theo danh sách TSCĐ | N76: 2.1907838 | O76: =+K76-N76 -> -2.1907838
A77: Tạo cuộn | B77: KH | C77: =+C76+1 -> 14 | D77: DEP | E77: 6274.4 | F77: Chi phí khấu hao nhà xưởng | G77: tháng | H77: 1 | J77: =H77*I77 -> 0 | K77: =J77*$K$5 -> 0 | L77: =J77/$J$109 -> 0 | M77: Chi phí thực tế bình quân 3 tháng liền kề theo danh sách TSCĐ | N77: 2.8399046 | O77: =+K77-N77 -> -2.8399046
A78: Tạo cuộn | B78: Điện | C78: =+C74+1 -> 12 | D78: ELEC | E78: 6275 | F78: Điện (electronic) Starlinger | G78: Kwh | H78: 1 | I78: ='[3]Dinh muc'!$G$14 -> 2569.7674 | J78: =H78*I78 -> 2569.7674 | K78: =J78*$K$5 -> 51395.349 | L78: =J78/$J$109 -> 0.1027907 | M78: Chi phí thực tế bình quân 3 tháng liền kề. CW1: 752 Kwh, CW2: 752 Kwh, Boretech: 1254 Kwh | N78: 15.547201 | O78: =+K78-N78 -> 51379.802
A79: Tạo cuộn | B79: Khác | C79: =+C78+1 -> 13 | D79: OTH | E79: 6277.6278 | F79: Chi phí bằng tiền khác | G79: tháng | H79: 1 | J79: =H79*I79 -> 0 | K79: =J79*$K$5 -> 0 | L79: =J79/$J$109 -> 0 | M79: Chi phí thực tế bình quân 3 tháng liền kề | N79: 5.1172085 | O79: =+K79-N79 -> -5.1172085
D80: Giá thành dây đai(III+IV) | J80: =+J61 -> 20911.564 | K80: =J80*$K$5 -> 418231.29 | L80: =J80/$J$109 -> 0.83646257
C81: D | D81: CÔNG ĐOẠN ĐÓNG GÓI: | K81: =J81*$K$5 -> 0
C82: III | F82: Cuộn dây đai r RPE1909 | J82: =J80 -> 20911.564 | K82: =J82*$K$5 -> 418231.29 | L82: =J82/$J$109 -> 0.83646257
C83: IV | F83: Chi phí đóng gói | J83: =SUM(J84:J98) -> 166.66667 | K83: =J83*$K$5 -> 3333.3333 | L83: =J83/$J$109 -> 0.0066666667
A84: Nâng IV 10H | C84: 0 | D84: REL01 | F84: Công suất máy (capacity) | G84: Kg /h | K84: =J84*$K$5 -> 0 | M84: Công suất máy 3492 (SSP-01: 1092, SSP-02: 2400)
A85: Nâng IV 10H | F85: Hiệu suất máy | G85: % | K85: =J85*$K$5 -> 0 | M85: Bình quân 3 tháng liền kề theo BI
B86: Bao bì | C86: =+C85+1 -> 1 | D86: BAG | F86: Pallet D4-1137R không nút-GC | G86: cái | H86: 1 | J86: =(I86*H86)/1100 -> 0 | K86: =J86*$K$5 -> 0 | L86: =J86/$J$109 -> 0 | M86: Giao trong nước pallet đen, giao xuất khẩu pallet gỗ
B87: Bao bì | C87: =+C86+1 -> 2 | D87: BAG | F87: Bao jumbo 105Lx105Wx150H (cm) đựng vảy | G87: cái | H87: 1 | J87: =(I87*H87)/1100 -> 0 | K87: =J87*$K$5 -> 0 | L87: =J87/$J$109 -> 0 | M87: 1100 kg hạt/bao
B88: Bao bì | C88: =+C87+1 -> 3 | D88: BAG | F88: Bao PE lót ngoài bao Jumbo | G88: cái | H88: 1 | J88: =(I88*H88)/1100 -> 0 | K88: =J88*$K$5 -> 0 | L88: =J88/$J$109 -> 0 | M88: 1100 kg hạt/bao
A89: Nâng IV | B89: NCTT | C89: =+C88+1 -> 4 | D89: LAB | E89: 622 | F89: Chi phí nhân công trực tiếp | G89: tháng | H89: 1 | K89: =J89*$K$5 -> 0 | L89: =J89/$J$109 -> 0 | M89: Nạp liệu 1, đóng gói 1, xe nâng 1
A90: Nâng IV | B90: NCGT | C90: =+C89+1 -> 5 | D90: LAB | E90: 6271 | F90: Chi phí nhân công gián tiếp | G90: tháng | H90: 1 | K90: =J90*$K$5 -> 0 | L90: =J90/$J$109 -> 0 | M90: Lương trưởng ca, hành chính, tổ trưởng, quản lý sản xuất gián tiếp như QC, Kỹ thuật
A91: Nâng IV | B91: VTPX | C91: =+C90+1 -> 6 | D91: OTH | E91: 6272 | F91: Chi phí vật tư phân xưởng | G91: tháng | H91: 1 | I91: ='[3]Dinh muc'!$G$18 -> 166.66667 | J91: =H91*I91 -> 166.66667 | K91: =J91*$K$5 -> 3333.3333 | L91: =J91/$J$109 -> 0.0066666667 | M91: Chi phí thực tế bình quân 3 tháng liền kề
A92: Nâng IV | B92: CCDC | C92: =+C91+1 -> 7 | D92: OTH | E92: 6273 | G92: tháng | H92: 1 | K92: =J92*$K$5 -> 0 | L92: =J92/$J$109 -> 0 | M92: Chi phí thực tế bình quân 3 tháng liền kề
A93: Nâng IV | B93: KH | C93: =+C92+1 -> 8 | D93: DEP | E93: 6274.1 | G93: tháng | H93: 1 | K93: =J93*$K$5 -> 0 | L93: =J93/$J$109 -> 0 | M93: Chi phí thực tế bình quân 3 tháng liền kề theo danh sách TSCĐ
A94: Nâng IV | B94: KH | C94: =+C93+1 -> 9 | D94: DEP | E94: 6274.2 | G94: tháng | H94: 1 | K94: =J94*$K$5 -> 0 | L94: =J94/$J$109 -> 0 | M94: Chi phí thực tế bình quân 3 tháng liền kề theo danh sách TSCĐ
A95: Nâng IV | B95: KH | C95: =+C94+1 -> 10 | D95: DEP | E95: 6274.3 | G95: tháng | H95: 1 | K95: =J95*$K$5 -> 0 | L95: =J95/$J$109 -> 0 | M95: Chi phí thực tế bình quân 3 tháng liền kề theo danh sách TSCĐ
A96: Nâng IV | B96: KH | C96: =+C95+1 -> 11 | D96: DEP | E96: 6274.4 | G96: tháng | H96: 1 | K96: =J96*$K$5 -> 0 | L96: =J96/$J$109 -> 0 | M96: Chi phí thực tế bình quân 3 tháng liền kề theo danh sách TSCĐ
A97: Nâng IV | B97: Điện | C97: =+C93+1 -> 9 | D97: ELEC | E97: 6275 | G97: tháng | H97: 1 | K97: =J97*$K$5 -> 0 | L97: =J97/$J$109 -> 0 | M97: Chi phí thực tế bình quân 3 tháng liền kề. CW1: 946 Kwh, Boretech: 487 Kwh
A98: Nâng IV | B98: Khác | C98: =+C97+1 -> 10 | D98: OTH | E98: 6277.6278 | G98: tháng | H98: 1 | K98: =J98*$K$5 -> 0 | L98: =J98/$J$109 -> 0 | M98: Chi phí thực tế bình quân 3 tháng liền kề
C99: V | F99: Chi phí quản lý | J99: =SUM(J100:J104) -> 2500 | K99: =J99*$K$5 -> 50000 | L99: =J99/$J$109 -> 0.1
A100: LuongBH | B100: 641 | C100: 1 | D100: 641 | F100: Chi phí nhân sự bán hàng | G100: tháng | H100: 1 | I100: =7%*TH!G6 -> 1750 | J100: =H100*I100 -> 1750 | K100: =J100*$K$5 -> 35000 | L100: =J100/$J$109 -> 0.07 | M100: Chi phí lương BGĐ, kế toán, HCNS, bán hàng…
A101: LuongQL | B101: 642 | C101: =+C100+1 -> 2 | D101: 642 | F101: Chi phí nhân sự quản lý | G101: tháng | H101: 1 | I101: =2%*TH!G7 -> 500 | J101: =H101*I101 -> 500 | K101: =J101*$K$5 -> 10000 | L101: =J101/$J$109 -> 0.02 | M101: Chi phí lương BGĐ, kế toán, HCNS, bán hàng…
...

Sheet DĐ RPEXXXX
A1: Danh mục | C1: 1
C2: PHƯƠNG ÁN SẢN XUẤT DĐ 3
C4: Nguyên liệu: | D4: NL 3 | J4: Bảng | K4: Kg
C5: Thành phẩm: | D5: =TH!C8 -> Dây đai RPEXXXX | J5: Quy cách đóng gói: | K5: =TH!E8 -> 20
C6: Quy cách: | D6: =TH!D8 -> XX mm x XX mm
C7: No. | D7: Nhóm | E7: Mã SAP | F7: Chi phí Cost Items | G7: Đơn vị tính Unit | H7: Định mức Standard | I7: Đơn giá (VNĐ) | J7: Chi phí đơn vị (VNĐ /Kg) | K7: Đơn giá (VND /Cuộn) | L7: % giá bán | M7: Cơ sở tính
C8: A | D8: CÔNG ĐOẠN TẠO VẢY GCDĐ:
B9: Vảy GCDĐ | C9: I | F9: Vảy GCDĐ | G9: vnđ /Kg | H9: 1 | I9: 12000 | J9: =I9 -> 12000 | K9: =J9*$K$5 -> 240000 | L9: =J9/$J$58 -> 0.92307692
B10: Hao hụt | C10: II | F10: Hao hụt | G10: % | H10: =SUM(H11:H20) -> 0 | J10: =SUM(J11:J20) -> 0 | K10: =J10*$K$5 -> 0 | L10: =J10/$J$58 -> 0
G11: % | J11: =+($J$9-I11)*H11 -> 0 | K11: =J11*$K$5 -> 0 | L11: =J11/$J$58 -> 0
G12: % | J12: =+($J$9-I12)*H12 -> 0 | K12: =J12*$K$5 -> 0 | L12: =J12/$J$58 -> 0
G13: % | J13: =+($J$9-I13)*H13 -> 0 | K13: =J13*$K$5 -> 0 | L13: =J13/$J$58 -> 0
G14: % | J14: =+($J$9-I14)*H14 -> 0 | K14: =J14*$K$5 -> 0 | L14: =J14/$J$58 -> 0
G15: % | J15: =+($J$9-I15)*H15 -> 0 | K15: =J15*$K$5 -> 0 | L15: =J15/$J$58 -> 0
G16: % | J16: =+($J$9-I16)*H16 -> 0 | K16: =J16*$K$5 -> 0 | L16: =J16/$J$58 -> 0
G17: % | J17: =+($J$9-I17)*H17 -> 0 | K17: =J17*$K$5 -> 0 | L17: =J17/$J$58 -> 0
G18: % | J18: =+($J$9-I18)*H18 -> 0 | K18: =J18*$K$5 -> 0 | L18: =J18/$J$58 -> 0
G19: % | J19: =+($J$9-I19)*H19 -> 0 | K19: =J19*$K$5 -> 0 | L19: =J19/$J$58 -> 0
A20: Mất đi | F20: Hao hụt n | G20: % | J20: =+($J$9-I20)*H20 -> 0 | K20: =J20*$K$5 -> 0 | L20: =J20/$J$58 -> 0 | M20: Hao hụt mất đi
C21: III | F21: Chi phí VC | J21: =SUM(J22:J33) -> 0 | K21: =J21*$K$5 -> 0 | L21: =J21/$J$58 -> 0
C22: 0 | D22: REL01 | F22: Công suất máy (capacity) | G22: Kg /h | K22: =J22*$K$5 -> 0
F23: Hiệu suất máy | G23: % | K23: =J23*$K$5 -> 0
K24: =J24*$K$5 -> 0 | L24: =J24/$J$58 -> 0
K25: =J25*$K$5 -> 0 | L25: =J25/$J$58 -> 0
K26: =J26*$K$5 -> 0 | L26: =J26/$J$58 -> 0
K27: =J27*$K$5 -> 0 | L27: =J27/$J$58 -> 0
K28: =J28*$K$5 -> 0 | L28: =J28/$J$58 -> 0
K29: =J29*$K$5 -> 0 | L29: =J29/$J$58 -> 0
K30: =J30*$K$5 -> 0 | L30: =J30/$J$58 -> 0
K31: =J31*$K$5 -> 0 | L31: =J31/$J$58 -> 0
K32: =J32*$K$5 -> 0 | L32: =J32/$J$58 -> 0
C33: =+C28+1 -> 1 | D33: OTH | E33: 6277.6278 | F33: Chi phí bằng tiền khác | G33: VND | K33: =J33*$K$5 -> 0 | L33: =J33/$J$58 -> 0
D34: Cộng giá thành Vảy GCDĐ (I+II+III) | J34: =J9+J10+J21 -> 12000 | K34: =J34*$K$5 -> 240000 | L34: =J34/$J$58 -> 0.92307692
C35: B | D35: CÔNG ĐOẠN TẠO VẢY MIXED: | K35: =J35*$K$5 -> 0
C36: IV | F36: Chi phí Vảy GCDĐ | G36: Kg | H36: 1 | I36: =+J34 -> 12000 | J36: =+H36*I36 -> 12000 | K36: =J36*$K$5 -> 240000 | L36: =J36/$J$58 -> 0.92307692
C37: V | F37: Chi phí mixed màu | J37: =SUM(J40:J57) -> 1000 | K37: =J37*$K$5 -> 20000 | L37: =J37/$J$58 -> 0.076923077
A38: Rửa | C38: 0 | D38: VBAL1 | F38: Công suất máy (capacity) | G38: Kg /h | K38: =J38*$K$5 -> 0
A39: Rửa | F39: Hiệu suất máy | G39: % | K39: =J39*$K$5 -> 0
B40: Vảy GCDĐ | J40: =+($J$34-I40)*H40 -> 0 | K40: =J40*$K$5 -> 0 | L40: =J40/$J$58 -> 0
B41: Hao hụt | J41: =+($J$34-I41)*H41 -> 0 | K41: =J41*$K$5 -> 0 | L41: =J41/$J$58 -> 0
J42: =+($J$34-I42)*H42 -> 0 | K42: =J42*$K$5 -> 0 | L42: =J42/$J$58 -> 0
J43: =+($J$34-I43)*H43 -> 0 | K43: =J43*$K$5 -> 0 | L43: =J43/$J$58 -> 0
J44: =+H44*I44 -> 0 | K44: =J44*$K$5 -> 0 | L44: =J44/$J$58 -> 0
J45: =+H45*I45 -> 0 | K45: =J45*$K$5 -> 0 | L45: =J45/$J$58 -> 0
J46: =+H46*I46 -> 0 | K46: =J46*$K$5 -> 0 | L46: =J46/$J$58 -> 0
K47: =J47*$K$5 -> 0 | L47: =J47/$J$58 -> 0
K48: =J48*$K$5 -> 0 | L48: =J48/$J$58 -> 0
K49: =J49*$K$5 -> 0 | L49: =J49/$J$58 -> 0
K50: =J50*$K$5 -> 0 | L50: =J50/$J$58 -> 0
K51: =J51*$K$5 -> 0 | L51: =J51/$J$58 -> 0
K52: =J52*$K$5 -> 0 | L52: =J52/$J$58 -> 0
K53: =J53*$K$5 -> 0 | L53: =J53/$J$58 -> 0
K54: =J54*$K$5 -> 0 | L54: =J54/$J$58 -> 0
K55: =J55*$K$5 -> 0 | L55: =J55/$J$58 -> 0
K56: =J56*$K$5 -> 0 | L56: =J56/$J$58 -> 0
F57: Hạt màu | I57: 1000 | J57: =I57 -> 1000 | K57: =J57*$K$5 -> 20000 | L57: =J57/$J$58 -> 0.076923077
D58: Giá thành Vảy GCDĐ Mixed (IV+V): | J58: =J36+J37 -> 13000 | K58: =J58*$K$5 -> 260000 | L58: =J58/$J$58 -> 1
C59: C | D59: CÔNG ĐOẠN TẠO CUỘN: | K59: =J59*$K$5 -> 0
C60: I | F60: Vảy GCDĐ Mixed | H60: 1 | J60: =+J58 -> 13000 | K60: =J60*$K$5 -> 260000 | L60: =J60/$J$109 -> 0.52
C61: II | F61: Chi phí sản xuất dây đai | J61: =SUM(J62:J79) -> 20911.564 | K61: =J61*$K$5 -> 418231.29 | L61: =J61/$J$109 -> 0.83646257
A62: Tạo cuộn | C62: 0 | D62: REL01 | F62: Công suất máy (capacity) | G62: Kg /h | H62: 300 | K62: =J62*$K$5 -> 0 | M62: Công suất máy 6000 (CW1: 1500, CW2:1500, Boretech 3000)
A63: Tạo cuộn | F63: Hiệu suất máy | G63: % | H63: 0.75 | K63: =J63*$K$5 -> 0 | M63: Bình quân 3 tháng liền kề theo BI
A64: Đầu keo | B64: Hao hụt | C64: =+C63+1 -> 1 | D64: 1521 | F64: Vảy GCDĐ Mixed | G64: % | H64: =1/'[3]2.Hao hut'!$E$29 -> 1.1627907 | I64: 13000 | J64: =+(J$60-I614)*H64-J68 -> 13296.279 | K64: =J64*$K$5 -> 265925.58 | L64: =J64/$J$109 -> 0.53185116 | M64: Thu hồi theo giá thị trường | N64: 4.0389911 | O64: =+K64-N64 -> 265921.54
A65: HAD | B65: Hao hụt | C65: =+C64+1 -> 2 | G65: % | J65: =+(J$60-I65)*H65 -> 0 | K65: =J65*$K$5 -> 0 | L65: =J65/$J$109 -> 0 | M65: Thu hồi theo giá thị trường | N65: 3.6668698 | O65: =+K65-N65 -> -3.6668698
A66: Bụi | B66: Hao hụt | C66: =+C65+1 -> 3 | G66: % | J66: =+(J$60-I66)*H66 -> 0 | K66: =J66*$K$5 -> 0 | L66: =J66/$J$109 -> 0 | M66: Thu hồi theo giá thị trường | N66: 0 | O66: =+K66-N66 -> 0
A67: PP Hạt | B67: Hao hụt | C67: =+C66+1 -> 4 | G67: % | J67: =+(J$60-I67)*H67 -> 0 | K67: =J67*$K$5 -> 0 | L67: =J67/$J$109 -> 0 | M67: Thu hồi theo giá thị trường | N67: 2.5970685 | O67: =+K67-N67 -> -2.5970685
A68: Mất đi | B68: Hao hụt | C68: =+C67+1 -> 5 | D68: 1522 | F68: Hao hụt | G68: % | H68: ='[3]2.Hao hut'!$E$11 -> 0.14 | I68: 10000 | J68: =+(J$60)*H68 -> 1820 | K68: =J68*$K$5 -> 36400 | L68: =J68/$J$109 -> 0.0728 | M68: Hao hụt mất đi | N68: 1.7145151 | O68: =+K68-N68 -> 36398.285
B69: Phụ gia | C69: =+C68+1 -> 6 | D69: CHE | E69: 120003033 | F69: Phụ gia | G69: % | J69: =+H69*I69 -> 0 | K69: =J69*$K$5 -> 0 | L69: =J69/$J$109 -> 0 | M69: Hóa chất theo BOM | N69: 3.7365765 | O69: =+K69-N69 -> -3.7365765
A70: Tạo cuộn | B70: NCTT | C70: =+C69+1 -> 7 | D70: LAB | E70: 622 | F70: Chi phí nhân công trực tiếp | G70: tháng | H70: 1 | I70: ='[3]Dinh muc'!$I$6 -> 335.91731 | J70: =H70*I70 -> 335.91731 | K70: =J70*$K$5 -> 6718.3463 | L70: =J70/$J$109 -> 0.013436693 | N70: 2.3146075 | O70: =+K70-N70 -> 6716.0316
A71: Tạo cuộn | B71: NCGT | C71: =+C70+1 -> 8 | D71: LAB | E71: 6271 | F71: Chi phí nhân công gián tiếp | G71: tháng | H71: 1 | I71: ='[3]Dinh muc'!$I$10 -> 565.16473 | J71: =H71*I71 -> 565.16473 | K71: =J71*$K$5 -> 11303.295 | L71: =J71/$J$109 -> 0.022606589 | M71: Lương trưởng ca, hành chính, tổ trưởng, quản lý sản xuất gián tiếp như QC, Kỹ thuật | N71: 10.418755 | O71: =+K71-N71 -> 11292.876
A72: Tạo cuộn | B72: VTPX | C72: =+C71+1 -> 9 | D72: OTH | E72: 6272 | F72: Chi phí vật tư phân xưởng | G72: tháng | H72: 1 | I72: ='[3]Dinh muc'!$K$15 -> 1997.8779 | J72: =H72*I72 -> 1997.8779 | K72: =J72*$K$5 -> 39957.558 | L72: =J72/$J$109 -> 0.079915116 | M72: Chi phí thực tế bình quân 3 tháng liền kề | N72: 2.6427307 | O72: =+K72-N72 -> 39954.915
A73: Tạo cuộn | B73: CCDC | C73: =+C72+1 -> 10 | D73: OTH | E73: 6273 | F73: Chi phí CCDC, bảo trì | G73: tháng | H73: 1 | J73: =H73*I73 -> 0 | K73: =J73*$K$5 -> 0 | L73: =J73/$J$109 -> 0 | M73: Chi phí thực tế bình quân 3 tháng liền kề | N73: 6.0380666 | O73: =+K73-N73 -> -6.0380666
A74: Tạo cuộn | B74: KH | C74: =+C73+1 -> 11 | D74: DEP | E74: 6274.1 | F74: Chi phí khấu hao MMTB chính | G74: tháng | H74: 1 | I74: ='[3]PB_TSCD DC'!$AR$32 -> 326.55786 | J74: =H74*I74 -> 326.55786 | K74: =J74*$K$5 -> 6531.1572 | L74: =J74/$J$109 -> 0.013062314 | M74: Chi phí thực tế bình quân 3 tháng liền kề theo danh sách TSCĐ | N74: 20.249816 | O74: =+K74-N74 -> 6510.9074
A75: Tạo cuộn | B75: KH | C75: =+C74+1 -> 12 | D75: DEP | E75: 6274.2 | F75: Chi phí khấu hao MMTB phụ | G75: tháng | H75: 1 | J75: =H75*I75 -> 0 | K75: =J75*$K$5 -> 0 | L75: =J75/$J$109 -> 0 | M75: Chi phí thực tế bình quân 3 tháng liền kề theo danh sách TSCĐ | N75: 1.8659215 | O75: =+K75-N75 -> -1.8659215
A76: Tạo cuộn | B76: KH | C76: =+C75+1 -> 13 | D76: DEP | E76: 6274.3 | F76: Chi phí khấu hao MMTB dùng chung | G76: tháng | H76: 1 | J76: =H76*I76 -> 0 | K76: =J76*$K$5 -> 0 | L76: =J76/$J$109 -> 0 | M76: Chi phí thực tế bình quân 3 tháng liền kề theo danh sách TSCĐ | N76: 2.1907838 | O76: =+K76-N76 -> -2.1907838
A77: Tạo cuộn | B77: KH | C77: =+C76+1 -> 14 | D77: DEP | E77: 6274.4 | F77: Chi phí khấu hao nhà xưởng | G77: tháng | H77: 1 | J77: =H77*I77 -> 0 | K77: =J77*$K$5 -> 0 | L77: =J77/$J$109 -> 0 | M77: Chi phí thực tế bình quân 3 tháng liền kề theo danh sách TSCĐ | N77: 2.8399046 | O77: =+K77-N77 -> -2.8399046
A78: Tạo cuộn | B78: Điện | C78: =+C74+1 -> 12 | D78: ELEC | E78: 6275 | F78: Điện (electronic) | G78: Kwh | H78: 1 | I78: ='[3]Dinh muc'!$G$14 -> 2569.7674 | J78: =H78*I78 -> 2569.7674 | K78: =J78*$K$5 -> 51395.349 | L78: =J78/$J$109 -> 0.1027907 | M78: Chi phí thực tế bình quân 3 tháng liền kề. CW1: 752 Kwh, CW2: 752 Kwh, Boretech: 1254 Kwh | N78: 15.547201 | O78: =+K78-N78 -> 51379.802
A79: Tạo cuộn | B79: Khác | C79: =+C78+1 -> 13 | D79: OTH | E79: 6277.6278 | F79: Chi phí bằng tiền khác | G79: tháng | H79: 1 | J79: =H79*I79 -> 0 | K79: =J79*$K$5 -> 0 | L79: =J79/$J$109 -> 0 | M79: Chi phí thực tế bình quân 3 tháng liền kề | N79: 5.1172085 | O79: =+K79-N79 -> -5.1172085
D80: Giá thành dây đai(III+IV) | J80: =+J61 -> 20911.564 | K80: =J80*$K$5 -> 418231.29 | L80: =J80/$J$109 -> 0.83646257
C81: D | D81: CÔNG ĐOẠN ĐÓNG GÓI: | K81: =J81*$K$5 -> 0
C82: III | F82: Cuộn dây đai rPET RPEXXXX | J82: =J80 -> 20911.564 | K82: =J82*$K$5 -> 418231.29 | L82: =J82/$J$109 -> 0.83646257
C83: IV | F83: Chi phí đóng gói | J83: =SUM(J84:J98) -> 166.66667 | K83: =J83*$K$5 -> 3333.3333 | L83: =J83/$J$109 -> 0.0066666667
A84: Nâng IV 10H | C84: 0 | D84: REL01 | F84: Công suất máy (capacity) | G84: Kg /h | K84: =J84*$K$5 -> 0 | M84: Công suất máy 3492 (SSP-01: 1092, SSP-02: 2400)
A85: Nâng IV 10H | F85: Hiệu suất máy | G85: % | K85: =J85*$K$5 -> 0 | M85: Bình quân 3 tháng liền kề theo BI
B86: Bao bì | C86: =+C85+1 -> 1 | D86: BAG | F86: Pallet D4-1137R không nút-GC | G86: cái | H86: 1 | J86: =(I86*H86)/1100 -> 0 | K86: =J86*$K$5 -> 0 | L86: =J86/$J$109 -> 0 | M86: Giao trong nước pallet đen, giao xuất khẩu pallet gỗ
B87: Bao bì | C87: =+C86+1 -> 2 | D87: BAG | F87: Bao jumbo 105Lx105Wx150H (cm) đựng vảy | G87: cái | H87: 1 | J87: =(I87*H87)/1100 -> 0 | K87: =J87*$K$5 -> 0 | L87: =J87/$J$109 -> 0 | M87: 1100 kg hạt/bao
B88: Bao bì | C88: =+C87+1 -> 3 | D88: BAG | F88: Bao PE lót ngoài bao Jumbo | G88: cái | H88: 1 | J88: =(I88*H88)/1100 -> 0 | K88: =J88*$K$5 -> 0 | L88: =J88/$J$109 -> 0 | M88: 1100 kg hạt/bao
A89: Nâng IV | B89: NCTT | C89: =+C88+1 -> 4 | D89: LAB | E89: 622 | F89: Chi phí nhân công trực tiếp | G89: tháng | H89: 1 | K89: =J89*$K$5 -> 0 | L89: =J89/$J$109 -> 0 | M89: Nạp liệu 1, đóng gói 1, xe nâng 1
A90: Nâng IV | B90: NCGT | C90: =+C89+1 -> 5 | D90: LAB | E90: 6271 | F90: Chi phí nhân công gián tiếp | G90: tháng | H90: 1 | K90: =J90*$K$5 -> 0 | L90: =J90/$J$109 -> 0 | M90: Lương trưởng ca, hành chính, tổ trưởng, quản lý sản xuất gián tiếp như QC, Kỹ thuật
A91: Nâng IV | B91: VTPX | C91: =+C90+1 -> 6 | D91: OTH | E91: 6272 | F91: Chi phí vật tư phân xưởng | G91: tháng | H91: 1 | I91: ='[3]Dinh muc'!$G$18 -> 166.66667 | J91: =H91*I91 -> 166.66667 | K91: =J91*$K$5 -> 3333.3333 | L91: =J91/$J$109 -> 0.0066666667 | M91: Chi phí thực tế bình quân 3 tháng liền kề
A92: Nâng IV | B92: CCDC | C92: =+C91+1 -> 7 | D92: OTH | E92: 6273 | G92: tháng | H92: 1 | K92: =J92*$K$5 -> 0 | L92: =J92/$J$109 -> 0 | M92: Chi phí thực tế bình quân 3 tháng liền kề
A93: Nâng IV | B93: KH | C93: =+C92+1 -> 8 | D93: DEP | E93: 6274.1 | G93: tháng | H93: 1 | K93: =J93*$K$5 -> 0 | L93: =J93/$J$109 -> 0 | M93: Chi phí thực tế bình quân 3 tháng liền kề theo danh sách TSCĐ
A94: Nâng IV | B94: KH | C94: =+C93+1 -> 9 | D94: DEP | E94: 6274.2 | G94: tháng | H94: 1 | K94: =J94*$K$5 -> 0 | L94: =J94/$J$109 -> 0 | M94: Chi phí thực tế bình quân 3 tháng liền kề theo danh sách TSCĐ
A95: Nâng IV | B95: KH | C95: =+C94+1 -> 10 | D95: DEP | E95: 6274.3 | G95: tháng | H95: 1 | K95: =J95*$K$5 -> 0 | L95: =J95/$J$109 -> 0 | M95: Chi phí thực tế bình quân 3 tháng liền kề theo danh sách TSCĐ
A96: Nâng IV | B96: KH | C96: =+C95+1 -> 11 | D96: DEP | E96: 6274.4 | G96: tháng | H96: 1 | K96: =J96*$K$5 -> 0 | L96: =J96/$J$109 -> 0 | M96: Chi phí thực tế bình quân 3 tháng liền kề theo danh sách TSCĐ
A97: Nâng IV | B97: Điện | C97: =+C93+1 -> 9 | D97: ELEC | E97: 6275 | G97: tháng | H97: 1 | K97: =J97*$K$5 -> 0 | L97: =J97/$J$109 -> 0 | M97: Chi phí thực tế bình quân 3 tháng liền kề. CW1: 946 Kwh, Boretech: 487 Kwh
A98: Nâng IV | B98: Khác | C98: =+C97+1 -> 10 | D98: OTH | E98: 6277.6278 | G98: tháng | H98: 1 | K98: =J98*$K$5 -> 0 | L98: =J98/$J$109 -> 0 | M98: Chi phí thực tế bình quân 3 tháng liền kề
C99: V | F99: Chi phí quản lý | J99: =SUM(J100:J104) -> 2500 | K99: =J99*$K$5 -> 50000 | L99: =J99/$J$109 -> 0.1
A100: LuongBH | B100: 641 | C100: 1 | D100: 641 | F100: Chi phí nhân sự bán hàng | G100: tháng | H100: 1 | I100: =7%*TH!G6 -> 1750 | J100: =H100*I100 -> 1750 | K100: =J100*$K$5 -> 35000 | L100: =J100/$J$109 -> 0.07 | M100: Chi phí lương BGĐ, kế toán, HCNS, bán hàng…
A101: LuongQL | B101: 642 | C101: =+C100+1 -> 2 | D101: 642 | F101: Chi phí nhân sự quản lý | G101: tháng | H101: 1 | I101: =2%*TH!G7 -> 500 | J101: =H101*I101 -> 500 | K101: =J101*$K$5 -> 10000 | L101: =J101/$J$109 -> 0.02 | M101: Chi phí lương BGĐ, kế toán, HCNS, bán hàng…
...
