Workbook
Name _1: #REF!
Name _2: #REF!
Name _3: #REF!
Name _4: #REF!
Name _5: #REF!
Name a: #REF!
Name Accounts: #REF!
Name Activity_Reports: #REF!
Name ADM: #REF!
Name Application: #REF!
Name B: #REF!
Name back: #REF!
Name Calendar: #REF!
Name Catalogue_xls: #REF!
Name CompanyCode: #REF!
Name Contractingdiv: #REF!
Name corporate_affairs: #REF!
Name CTY: #REF!
Name Data_Values: #REF!
Name DATA13: #REF!
Name DATA14: #REF!
Name DATA15: #REF!
Name DATA16: #REF!
Name DATA17: #REF!
Name DATA18: #REF!
Name DATA19: #REF!
Name DATA20: #REF!
Name DATA21: #REF!
Name DATA22: #REF!
Name DATA23: #REF!
Name DATA24: #REF!
Name DATA25: #REF!
Name DATA26: #REF!
Name DATA27: #REF!
Name DATA28: #REF!
Name DATA29: #REF!
Name DATA30: #REF!
Name DATA31: #REF!
Name DATA32: #REF!
Name DATA33: #REF!
Name DATA34: #REF!
Name DATA35: #REF!
Name DATA36: #REF!
Name DATA37: #REF!
Name Date_of_separation: #REF!
Name DeptCode: #REF!
Name dinhbien2021: #REF!
Name DivisionCode: #REF!
Name DoCty: #REF!
Name DoDM: #REF!
Name DoMD: #REF!
Name dow: #REF!
Name DT: #REF!
Name ERP: #REF!
Name Excise: #REF!
Name Expectations: #REF!
Name EXR: #REF!
Name EXR: #REF!
Name fdg: #REF!
Name Finanacialsys: #REF!

Sheet Timeline & PIC
B1: DUY TAN GROUP
B2: =IF(B3="EN","Schedule Annual Plan 2025","Lịch lập NGÂN SÁCH năm 2026") -> #REF! | D2: =IF(B3="EN","Start:","Bắt đầu:") -> #REF! | E2: 45915
B3: =#REF! -> #REF! | D3: =IF(B3="EN","Finish:","Kết thúc:") -> #REF! | E3: =G22 -> 45990 | G3: =E3-E2 -> 75
D4: =IF(B3="en","SENDER","Đơn vị gửi") -> #REF! | E4: =IF(B3="EN","RECEIVER","Đơn vị nhận") -> #REF! | G4: Deadline | H4: THÁNG 09 | AM4: THÁNG 10 | BR4: THÁNG 11
B5: No. | C5: =IF(B3="EN","PROCESS","TRÌNH TỰ THỰC HIỆN") -> #REF! | F5: Thời gian | H5: 1 | I5: 2 | J5: 3 | K5: 4 | L5: 5 | M5: 6 | N5: 7 | O5: 8 | P5: 9 | Q5: 10 | R5: 11 | S5: 12 | T5: 13 | U5: 14 | V5: 15 | W5: 16 | X5: 17 | Y5: 18 | Z5: 19 | AA5: 20 | AB5: 21 | AC5: 22 | AD5: 23 | AE5: 24 | AF5: 25 | AG5: 26 | AH5: 27 | AI5: 28 | AJ5: 29 | AK5: 30 | AL5: 31 | AM5: 1 | AN5: 2 | AO5: 3 | AP5: 4 | AQ5: 5 | AR5: 6 | AS5: 7 | AT5: 8 | AU5: 9 | AV5: 10 | AW5: 11 | AX5: 12 | AY5: 13 | AZ5: 14 | BA5: 15 | BB5: 16 | BC5: 17 | BD5: 18 | BE5: 19 | BF5: 20 | BG5: 21 | BH5: 22 | BI5: 23 | BJ5: 24 | BK5: 25 | BL5: 26 | BM5: 27 | BN5: 28 | BO5: 29 | BP5: 30 | BQ5: 31 | BR5: 1 | BS5: =BR5+1 -> 2 | BT5: =BS5+1 -> 3 | BU5: =BT5+1 -> 4 | BV5: =BU5+1 -> 5 | BW5: =BV5+1 -> 6 | BX5: =BW5+1 -> 7 | BY5: =BX5+1 -> 8 | BZ5: =BY5+1 -> 9 | ... CT5: =CS5+1 -> 29 | CU5: 30
F6: (Ngày) | H6: M | I6: T | J6: W | K6: TH | L6: F | M6: Sa | N6: Su | O6: M | P6: T | Q6: W | R6: TH | S6: F | T6: Sa | U6: Su | V6: M | W6: T | X6: W | Y6: TH | Z6: F | AA6: Sa | AB6: Su | AC6: M | AD6: T | AE6: W | AF6: TH | AG6: F | AH6: Sa | AI6: Su | AJ6: M | AK6: T | AL6: W | AM6: TH | AN6: F | AO6: Sa | AP6: Su | AQ6: M | AR6: T | AS6: W | AT6: TH | AU6: F | AV6: Sa | AW6: Su | AX6: M | AY6: T | AZ6: W | BA6: TH | BB6: F | BC6: Sa | BD6: Su | BE6: M | BF6: T | BG6: W | BH6: TH | BI6: F | BJ6: Sa | BK6: Su | BL6: M | BM6: T | BN6: W | BO6: TH | BP6: F | BQ6: Sa | BR6: Su | BS6: M | BT6: T | BU6: W | BV6: TH | BW6: F | BX6: Sa | BY6: Su | BZ6: M | CA6: T | CB6: W | CC6: TH | CD6: F | CE6: Sa | CF6: Su | CG6: M | CH6: T | CI6: W | CJ6: TH | CK6: F | CL6: Sa | CM6: Su | CN6: M | CO6: T | CP6: W | CQ6: TH | CR6: F | CS6: Sa | CT6: Su | CU6: M
B7: 1 | C7: Khởi động | D7: GĐTC holding | E7: =IF(B3="EN","All","Tất cả") -> #REF! | G7: =E2 -> 45915
B8: 2 | C8: Kế hoạch Doanh thu / Sản lượng | D8: =IF(B3="EN","Sales team","Phòng kinh doanh") -> #REF! | E8: =IF(B3="EN","Acct.","Kế toán") -> #REF! | F8: 15 | G8: =F8+$G$7 -> 45930
B9: 3 | C9: Kế hoạch giá cả nguyên vật liệu | D9: =IF(B2="EN","Supply chain","Chuỗi cung ứng") -> #REF! | E9: =E8 -> #REF! | F9: 15 | G9: =F9+$G$7 -> 45930
B10: =B9+1 -> 4 | C10: Kế hoạch chi phí vận chuyển, cước xuất khẩu,... | D10: =IF(B3="EN","Supply chain","Chuổi cung ứng") -> #REF! | E10: =E9 -> #REF! | F10: 15 | G10: =F10+$G$7 -> 45930
B11: =B10+1 -> 5 | C11: Kế hoạch sản xuất | D11: =IF(B3="EN","Production","Bộ phận sản xuất") -> #REF! | E11: =E10 -> #REF! | F11: 20 | G11: =F11+$G$7 -> 45935
B12: =B11+1 -> 6 | C12: Kế hoạch biến phí sản xuất | D12: =E12 -> #REF! | E12: =E11 -> #REF! | F12: 20 | G12: =F12+$G$7 -> 45935
B13: =B12+1 -> 7 | C13: Kế hoạch nhân sự (số lượng nhân sự, quỹ lương, chi phí đào tạo,...) | D13: =IF(B3="EN","HR","Phòng nhân sự") -> #REF! | E13: =E12 -> #REF! | F13: 30 | G13: =F13+$G$7 -> 45945
B14: =B13+1 -> 8 | C14: Ngân sách đầu tư | D14: =E7 -> #REF! | E14: =E13 -> #REF! | F14: 30 | G14: =F14+$G$7 -> 45945
B15: =B14+1 -> 9 | C15: Ngân sách chi phí sản xuất (không bao gồm lương) | D15: =D11 -> #REF! | E15: =E14 -> #REF! | F15: 30 | G15: =F15+$G$7 -> 45945
B16: =B15+1 -> 10 | C16: Ngân sách chi phí bán hàng & chí phí quản lý (không bao gồm lương) | D16: =D14 -> #REF! | E16: =E15 -> #REF! | F16: 30 | G16: =F16+$G$7 -> 45945
B17: =B16+1 -> 11 | C17: Tổng hợp kết quả ngân sách mỗi công ty | D17: Kế toán quản trị | E17: KTT/GĐTC | F17: 45 | G17: =F17+$G$7 -> 45960
B18: 12 | C18: Trình bày kết quả ngân sách của mỗi công ty đến TGĐ (Bottom up) | D18: KTT/GĐTC | E18: TGĐ | F18: 50 | G18: =F18+$G$7 -> 45965
B19: 13 | C19: Trình bày kết quả ngân sách của mỗi công ty đến TGĐ (Top down) | D19: KTT/GĐTC | E19: TGĐ | F19: 55 | G19: =F19+$G$7 -> 45970
B20: 14 | C20: Trình bày kết quả ngân sách của mỗi công ty đến TGĐ (Chính thức) | D20: KTT/GĐTC | E20: TGĐ | F20: 62 | G20: =F20+$G$7 -> 45977
B21: 15 | C21: Hợp nhất ngân sách cho toàn bộ DT Group | D21: KTQT holding | E21: GĐTC holding | F21: 70 | G21: =F21+$G$7 -> 45985
B22: 16 | C22: Trình bày kết quả ngân sách hợp nhất cho toàn bộ DT Group | D22: GĐTC holding | E22: TGĐ | F22: 75 | G22: =F22+$G$7 -> 45990

Sheet Thongtin
B2: STT | C2: Nội dung | D2: Nguồn cung cấp dữ liệu | E2: Nguồn thông tin liên quan | F2: Thời gian cần dữ liệu | H2: STT | I2: Màu sheet | J2: Thông tin
B3: 1 | C3: Ban hành Nhóm-Loại NVL Trạm thu mua | D3: GĐĐH Trạm - DTR | E3: 1. BGĐ DTR 2. Phòng cung ứng DTR | F3: 45940 | H3: 1 | J3: Kết quả kinh doanh tổng hợp
B4: 2 | C4: Ban hành Sản lượng Trạm thu mua | D4: GĐĐH Trạm - DTR | E4: 1. BGĐ DTR 2. Phòng cung ứng DTR | F4: 45940 | H4: 2 | J4: Kết quả kinh doanh PET và HD
B5: 3 | C5: Ban hành đơn giá MUA từng loại NVL | D5: GĐĐH Trạm - DTR | E5: 1. Phòng cung ứng DTR đề xuất KH năm 2026 (Dữ liệu theo từng tháng) 2. KTT các trạm cung cấp đơn giá bình quân thực tế mua theo từng tháng ( Dữ liệu năm 2023-2024-2025) 3. Đơn giá BGĐ-DTR duyệt mua trong năm 2025 (Dữ liệu theo từng tháng) | F5: 45940 | H5: 3 | J5: Kết quả kinh doanh PET và HD
B6: 4 | C6: Ban hành đơn giá BÁN từng loại thành phẩm | D6: GĐĐH Trạm - DTR | E6: 1. BGĐ DTR 2. Phòng cung ứng DTR | F6: 45940 | H6: 4 | J6: Ban hành Định mức về Công suất MMTB - Định mức về CP phục vụ sản xuất - Định biên Nhân sự
B7: 5 | C7: Kế hoạch đầu tư CAPEX tại Trạm => Ảnh hưởng đến Sản phẩm và TCKT Trạm cung cấp đến DTR | D7: GĐĐH Trạm - DTR | E7: 1. BGĐ DTR 2. Phòng kỹ thuật DTR 3. Phòng mua hàng DTR | F7: 45940 | H7: 5 | J7: Ban hành sản lượng - đơn giá - Cơ cấu về: NVL - Thành phẩm - Hao hụt - Bán hàng
H8: 6 | J8: Nhóm Chi phí:CP Sản xuất - CP Bán hàng - CP Quản lý (Công thức từ: Định mức - Lương - PB_TSCD - PB_CPTT - nhóm NVL - Phát sinh trực tiếp)
H9: 7 | J9: Cập nhật TSCĐ - CPTT năm trước chuyển sang và Capex 2026
H10: 8 | I10: … | J10: Thông tin khác

Sheet KH hanh dong
A3: KẾ HOẠCH KINH DOANH 2026
A4: Nguồn yêu cầu: GĐTC-DTR
A5: STT | B5: Nhóm công việc | C5: Kế hoạch hành động | D5: Người thực hiện | E5: Thời gian hoàn thành tính toán và xác lập mục tiêu 2026 | F5: Hiện trạng / vướng mắt / giải pháp (tại thời điểm tháng 10/2025) | G5: Mục tiêu 2026 (rolling hàng tháng) | U5: KHNS 2026 | V5: Thực hiện 2025 | W5: Tăng/giảm vs KHNS 2026
G6: Đánh giá KQ đạt được (cập nhật đến thời điểm báo cáo) | H6: Mục tiêu T1 | I6: Mục tiêu T2 | J6: Mục tiêu T3 | K6: Mục tiêu T4 | L6: Mục tiêu T5 | M6: Mục tiêu T6 | N6: Mục tiêu T7 | O6: Mục tiêu T8 | P6: Mục tiêu T9 | Q6: Mục tiêu T10 | R6: Mục tiêu T11 | S6: Mục tiêu T12 | T6: Dự báo KQ 2026 | W6: Theo số tiền phát sinh | X6: Theo mức độ hoạt động | Y6: %
A7: A | B7: HOẠT ĐỘNG MUA HÀNG
A8: 1 | B8: Đáp ứng sản lượng mua cho Trạm | C8: Lập mục tiêu sản lượng mua để Trạm đạt hòa vốn và có lãi.
C9: Xây dựng các trạm vệ tinh để tăng lượng chai về Trạm.
C10: Phát triển thêm các NCC liên kết ở tỉnh.
C11: Đàm phán tăng sản lượng mua từ các NCC đang giao dịch.
A12: 2 | B12: Cải thiện dịch vụ khách hàng | C12: Cải thiện thời gian nhận hàng
C13: Thanh toán trong ngày và cuối tuần
A14: B | B14: HOẠT ĐỘNG BÁN HÀNG
A15: 1 | B15: Giá bán về DTR | C15: Áp dụng cơ cấu giá mới từ Tháng 9/2025
A16: 2 | B16: Kiểm soát tồn kho thành phẩm | C16: Lập KH giao hàng về DTR hàng ngày, ngày cuối tháng không để tồn kho và xuất hóa đơn 100%
A17: 3 | B17: Chi phí thuê xe vận chuyển | C17: - Đàm phán giảm giá, đề nghị NCC sử dụng phương tiện vận chuyển hiệu quả. - Tìm NCC mới cạnh tranh.
A18: C | B18: HOẠT ĐỘNG CẢI TIẾN CHI PHÍ
A19: I | B19: Chi phí nguyên vật liệu
A20: 1 | B20: Kiểm soát lượng mua, giá mua | C20: - Lập mục tiêu tồn kho tối thiểu 10 ngày sản xuất và phối hợp P.Cung ứng lập KH mua hàng theo tuần. - Kiểm soát giá mua tương ứng với từng mức chất lượng chai.
A21: 2 | B21: Kiểm soát chất lượng NVL, hao hụt | C21: Kiểm soát chất lượng chai (tỷ lệ chai nguyên liệu - Chai xá/xô tuyển, thành phần chai sau phân loại, tỷ lệ tạp chất).
A22: 3 | B22: Kiểm soát định mức vật tư sản xuất (hóa chất, dây đai, vật tư kỹ thuật …) | C22: - Thống kê và thực hiện cải tiến tiêu hao. - Mua tập trung tại P.Mua hàng DTR.
A23: 4 | B23: Xử lý phế liệu, phó sản thu hồi | C23: Phân loại phế liệu thành 2 nhóm: - Nhóm hàng hóa (nhãn, bao jumbo, kim loại,…): tìm đơn vị thu mua giá cao - Nhóm rác thải công nghiệp (bùn, hỗn hợp tạp chất): thuê thu gom
A24: II | B24: Chi phí nhân công
A25: 1 | B25: Định mức NCTT | C25: - Kiểm soát định mức NCTT theo chuyền/công đoạn. - Thực hiện tiêu chuẩn hóa/tự động hóa MMTB để giảm nhân công, tăng năng suất. - Tăng số lượng lao động thời vụ. - Tính toán phương án trả lương/ thưởng theo sản lượng.
A26: 2 | B26: Năng suất lao động | C26: - Lập mục tiêu tăng thời gian sản xuất từ 8 giờ/ngày -> 12 giờ -> 16 giờ -> 24 giờ.
A27: III | B27: Chi phí sản xuất chung
A28: 1 | B28: Chi phí điện | C28: - Phối hợp kỹ thuật bảo trì MMTB đảm bảo hoạt động liên tục -> tăng hiệu quả sử dụng điện và tăng năng suất lao động.
A29: 2 | B29: Chi phí xe nâng | C29: - Chuyển dần xe nâng dầu từ DTR về các Trạm (các xe của trạm sửa chữa nhiều sẽ thanh lý)
A30: 3 | B30: Chi phí khấu hao TSCĐ, CCDC, chi phí phân bổ khác | C30: - Thống kê, đánh giá lại hiệu quả sử dụng tất cả TS. - Tách chi phí khấu hao/phân bổ không phục vụ trực tiếp hoạt động để đánh giá hiệu quả KD thực của trạm.
A31: 4 | B31: Chi phí thuê xưởng | C31: - Tìm vị trí và đề xuất phương án di dời nhà máy để giảm tiền thu, tăng hiệu quả thu mua.
A32: IV | B32: Chi phí quản lý
A33: 1 | B33: Chi phí lương (gồm gián tiếp SX) | C33: Soát xét định biên và kế hoạch tuyển dụng, lập mục tiêu giảm định biên đến cuối 2026
A34: 2 | B34: Chi phí theo mục phí (ngoài chi phí lương) | C34: - Lập danh mục chi phí dịch vụ thuê/mua trả tiền định kỳ (nhóm dịch vụ/phòng ban quản lý, tên NCC, hợp đồng mới nhất, tiền trả định kỳ tháng/quý/năm, thời hạn công nợ) -> đàm phán từng NC giảm giá và tìm NCC mới cạnh tranh - XD định mức chi phí cho các khoản mục có thể xác lập định mức - Phân tích chi phí, nguyên nhân tăng/giảm và giải pháp cải tiến.
A35: V | B35: Mục tiêu lợi nhuận
A36: 1 | B36: Lợi nhuận kế hoạch đến cuối năm 2026 | C36: Sau khi đánh giá, xác lập các mục tiêu bên trên, tính toán lợi nhuận kế hoạch đến cuối năm 2026

Sheet KQKD Tong hop
B3: KẾ HOẠCH KINH DOANH NĂM 2026 | S3: ĐVT: Triệu đồng
B4: STT | C4: Mục phí | D4: Thực tế năm 2023 | E4: Thực tế năm 2024 | F4: Thực tế năm 2025 | G4: T1 | H4: T2 | I4: T3 | J4: T4 | K4: T5 | L4: T6 | M4: T7 | N4: T8 | O4: T9 | P4: T10 | Q4: T11 | R4: T12 | S4: 10/03/2026 DTR
C5: SẢN LƯỢNG NVL MUA VÀO (Tấn) | D5: 3173 | E5: 4044 | F5: 6481062 | G5: ='1.NVL Chai'!G16 -> 780000 | H5: ='1.NVL Chai'!H16 -> 450000 | I5: ='1.NVL Chai'!I16 -> 1040000 | J5: ='1.NVL Chai'!J16 -> 1250000 | K5: ='1.NVL Chai'!K16 -> 1250000 | L5: ='1.NVL Chai'!L16 -> 1300000 | M5: ='1.NVL Chai'!M16 -> 1350000 | N5: ='1.NVL Chai'!N16 -> 1300000 | ... S5: ='1.NVL Chai'!S16 -> 13870000 | T5: =S5/F5 -> 2.1400814
B6: 1 | C6: SẢN LƯỢNG BÁN (TẤN) | D6: 3125610.5 | E6: 4267466 | F6: 5702390 | G6: =G7+G8+G9 -> 689520 | H6: =H7+H8+H9 -> 397800 | I6: =I7+I8+I9 -> 918840 | J6: =J7+J8+J9 -> 1025362.5 | K6: =K7+K8+K9 -> 1025362.5 | L6: =L7+L8+L9 -> 1066377 | M6: =M7+M8+M9 -> 1107391.5 | N6: =N7+N8+N9 -> 1066377 | ... R6: =R7+R8+R9 -> 1107391.5 | S6: =SUM(G6:R6) -> 11521524 | T6: =S6/F6 -> 2.0204728
B7: 1.1 | C7: Chai PET | D7: 2879091.5 | E7: 3867466 | F7: 5702390 | G7: ='4.Doanh thu'!F$22 -> 689520 | H7: ='4.Doanh thu'!G$22 -> 397800 | I7: ='4.Doanh thu'!H$22 -> 918840 | J7: ='4.Doanh thu'!I$22 -> 35312.5 | K7: ='4.Doanh thu'!J$22 -> 35312.5 | L7: ='4.Doanh thu'!K$22 -> 36725 | M7: ='4.Doanh thu'!L$22 -> 38137.5 | N7: ='4.Doanh thu'!M$22 -> 36725 | ... R7: ='4.Doanh thu'!Q$22 -> 38137.5 | S7: =SUM(G7:R7) -> 2333860
B8: 1.2 | C8: Vảy PET | D8: 0 | E8: 400000 | F8: 0 | G8: ='4.Doanh thu'!F$80 -> 0 | H8: ='4.Doanh thu'!G$80 -> 0 | I8: ='4.Doanh thu'!H$80 -> 0 | J8: ='4.Doanh thu'!I$80 -> 990050 | K8: ='4.Doanh thu'!J$80 -> 990050 | L8: ='4.Doanh thu'!K$80 -> 1029652 | M8: ='4.Doanh thu'!L$80 -> 1069254 | N8: ='4.Doanh thu'!M$80 -> 1029652 | ... R8: ='4.Doanh thu'!Q$80 -> 1069254 | S8: =SUM(G8:R8) -> 9187664 | T8: =S8/S6 -> 0.79743478
B9: 1.3 | C9: Vảy HD | D9: 246519 | E9: 0 | F9: 0 | S9: =SUM(G9:R9) -> 0
B10: 2 | C10: DOANH THU | D10: 44482013609 | E10: 63950445550 | F10: 96184706621 | G10: =G11+G12+G13+G14 -> 9705618000 | H10: =H11+H12+H13+H14 -> 5599395000 | I10: =I11+I12+I13+I14 -> 12929826000 | J10: =J11+J12+J13+J14 -> 16437125000 | K10: =K11+K12+K13+K14 -> 16437125000 | L10: =L11+L12+L13+L14 -> 17094610000 | M10: =M11+M12+M13+M14 -> 17752095000 | N10: =N11+N12+N13+N14 -> 17094610000 | ... R10: =R11+R12+R13+R14 -> 17752095000 | S10: =SUM(G10:R10) -> 180771359000 | T10: =S10/F10 -> 1.8794189 | U10: =F10/F$10 -> 1 | V10: =G10/G$10 -> 1
B11: 2.1 | C11: Chai PET | D11: 39992361315 | E11: 58441845550 | F11: 96184706621 | G11: ='4.Doanh thu'!F$60 -> 9705618000 | H11: ='4.Doanh thu'!G$60 -> 5599395000 | I11: ='4.Doanh thu'!H$60 -> 12929826000 | J11: ='4.Doanh thu'!I$60 -> 367687500 | K11: ='4.Doanh thu'!J$60 -> 367687500 | L11: ='4.Doanh thu'!K$60 -> 382395000 | M11: ='4.Doanh thu'!L$60 -> 397102500 | N11: ='4.Doanh thu'!M$60 -> 382395000 | ... R11: ='4.Doanh thu'!Q$60 -> 397102500 | S11: =SUM(G11:R11) -> 31646979000 | T11: =S11/F11 -> 0.32902298 | U11: =F11/F$10 -> 1 | V11: =G11/G$10 -> 1
B12: 2.2 | C12: Vảy PET | D12: 0 | E12: 5508600000 | F12: 0 | G12: ='4.Doanh thu'!F$118 -> 0 | H12: ='4.Doanh thu'!G$118 -> 0 | I12: ='4.Doanh thu'!H$118 -> 0 | J12: ='4.Doanh thu'!I$118 -> 16069437500 | K12: ='4.Doanh thu'!J$118 -> 16069437500 | L12: ='4.Doanh thu'!K$118 -> 16712215000 | M12: ='4.Doanh thu'!L$118 -> 17354992500 | N12: ='4.Doanh thu'!M$118 -> 16712215000 | ... R12: ='4.Doanh thu'!Q$118 -> 17354992500 | S12: =SUM(G12:R12) -> 149124380000 | T12: =S12/F12 -> #DIV/0! | U12: =F12/F$10 -> 0 | V12: =G12/G$10 -> 0 | W12: =S12/S10 -> 0.82493367
B13: 2.3 | C13: Vảy HD | D13: 4489652294 | E13: 0 | F13: 0 | S13: =SUM(G13:R13) -> 0 | T13: =S13/F13 -> #DIV/0! | U13: =F13/F$10 -> 0 | V13: =G13/G$10 -> 0
B14: 2.4 | C14: Khác | D14: 0 | E14: 0 | F14: 0 | S14: =SUM(G14:R14) -> 0 | T14: =S14/F14 -> #DIV/0! | U14: =F14/F$10 -> 0 | V14: =G14/G$10 -> 0
B15: 3 | C15: BIẾN PHÍ | D15: 4.3469013e+10 | E15: 60363389060 | F15: 85223230750 | G15: =G16+G24 -> 8.5772159e+09 | H15: =H16+H24 -> 5.0796935e+09 | I15: =I16+I24 -> 1.1828102e+10 | J15: =J16+J24 -> 1.492362e+10 | K15: =K16+K24 -> 1.5012357e+10 | L15: =L16+L24 -> 1.5598926e+10 | M15: =M16+M24 -> 1.6158965e+10 | N15: =N16+N24 -> 1.5586374e+10 | ... R15: =R16+R24 -> 1.6158093e+10 | S15: =SUM(G15:R15) -> 1.6455282e+11 | T15: =S15/F15 -> 1.9308447 | U15: =F15/F$10 -> 0.88603723 | V15: =G15/G$10 -> 0.88373723
B16: 3.1 | C16: BIẾN PHÍ SẢN XUẤT | D16: 4.2103863e+10 | E16: 59322702660 | F16: 83097930750 | G16: =G17+G21+G22+G23 -> 8.3014079e+09 | H16: =H17+H21+H22+H23 -> 4.9205735e+09 | I16: =I17+I21+I22+I23 -> 1.1460566e+10 | J16: =J17+J21+J22+J23 -> 1.4592679e+10 | K16: =K17+K21+K22+K23 -> 1.4681416e+10 | L16: =L17+L21+L22+L23 -> 1.5254748e+10 | M16: =M17+M21+M22+M23 -> 1.5801549e+10 | N16: =N17+N21+N22+N23 -> 1.5242196e+10 | ... R16: =R17+R21+R22+R23 -> 1.5800677e+10 | S16: =SUM(G16:R16) -> 1.6067923e+11 | T16: =S16/F16 -> 1.9336129 | U16: =F16/F$10 -> 0.8639412 | V16: =G16/G$10 -> 0.85531987
B17: 3.1.1 | C17: Nguyên vật liệu chính (nhựa, gồm hao hụt) | D17: 38732631964 | E17: 56030510590 | F17: 78338746231 | G17: ='1.NVL Chai'!G$42 -> 7566000000 | H17: ='1.NVL Chai'!H$42 -> 4275000000 | I17: ='1.NVL Chai'!I$42 -> 10400000000 | J17: ='1.NVL Chai'!J$42 -> 12500000000 | K17: ='1.NVL Chai'!K$42 -> 12500000000 | L17: ='1.NVL Chai'!L$42 -> 13000000000 | M17: ='1.NVL Chai'!M$42 -> 13500000000 | N17: ='1.NVL Chai'!N$42 -> 13000000000 | ... R17: ='1.NVL Chai'!R$42 -> 13500000000 | S17: =SUM(G17:R17) -> 138241000000 | T17: =S17/F17 -> 1.7646568 | U17: =F17/F$10 -> 0.81446156 | V17: =G17/G$10 -> 0.7795485
B18: 3.1.2 | C18: Trong đó: i/ Hao hụt CĐ phân loại chai | D18: 2260066610 | E18: 4917236579 | F18: 8584125746 | G18: =('3.Thanh pham'!G$187+'3.Thanh pham'!G$188)*'1.NVL Chai'!G$34 -> 877656000 | H18: =('3.Thanh pham'!H$187+'3.Thanh pham'!H$188)*'1.NVL Chai'!H$34 -> 495900000 | I18: =('3.Thanh pham'!I$187+'3.Thanh pham'!I$188)*'1.NVL Chai'!I$34 -> 1211600000 | J18: =('3.Thanh pham'!J$187+'3.Thanh pham'!J$188)*'1.NVL Chai'!J$34 -> 1456250000 | K18: =('3.Thanh pham'!K$187+'3.Thanh pham'!K$188)*'1.NVL Chai'!K$34 -> 1456250000 | L18: =('3.Thanh pham'!L$187+'3.Thanh pham'!L$188)*'1.NVL Chai'!L$34 -> 1514500000 | M18: =('3.Thanh pham'!M$187+'3.Thanh pham'!M$188)*'1.NVL Chai'!M$34 -> 1572750000 | N18: =('3.Thanh pham'!N$187+'3.Thanh pham'!N$188)*'1.NVL Chai'!N$34 -> 1514500000 | ... R18: =('3.Thanh pham'!R$187+'3.Thanh pham'!R$188)*'1.NVL Chai'!R$34 -> 1572750000 | S18: =SUM(G18:R18) -> 16099156000 | T18: =S18/F18 -> 1.8754567 | U18: =F18/F$10 -> 0.089246264 | V18: =G18/G$10 -> 0.090427627
C19: ii/ Hao hụt CĐ băm vảy | D19: 0 | E19: 0 | F19: 0 | G19: =('3.Thanh pham'!G$190)*'1.NVL Chai'!G$34 -> 0 | H19: =('3.Thanh pham'!H$190)*'1.NVL Chai'!H$34 -> 0 | I19: =('3.Thanh pham'!I$190)*'1.NVL Chai'!I$34 -> 0 | J19: =('3.Thanh pham'!J$190)*'1.NVL Chai'!J$34 -> 790125000 | K19: =('3.Thanh pham'!K$190)*'1.NVL Chai'!K$34 -> 790125000 | L19: =('3.Thanh pham'!L$190)*'1.NVL Chai'!L$34 -> 821730000 | M19: =('3.Thanh pham'!M$190)*'1.NVL Chai'!M$34 -> 853335000 | N19: =('3.Thanh pham'!N$190)*'1.NVL Chai'!N$34 -> 821730000 | ... R19: =('3.Thanh pham'!R$190)*'1.NVL Chai'!R$34 -> 853335000 | S19: =SUM(G19:R19) -> 7332360000 | T19: =S19/F19 -> #DIV/0! | U19: =F19/F$10 -> 0 | V19: =G19/G$10 -> 0
B20: 3.1.3 | C20: % chi phí nguyên liệu/doanh thu | D20: 0.87074817 | E20: 0.87615512 | F20: 0.81446156 | G20: =G17/G10 -> 0.7795485 | H20: =H17/H10 -> 0.76347534 | I20: =I17/I10 -> 0.80434184 | J20: =J17/J10 -> 0.76047362 | K20: =K17/K10 -> 0.76047362 | L20: =L17/L10 -> 0.76047362 | M20: =M17/M10 -> 0.76047362 | N20: =N17/N10 -> 0.76047362 | ... S20: =S17/S10 -> 0.76472844 | T20: =S20/F20 -> 0.93893743 | U20: =F20/F$10 -> 8.4676825e-12 | V20: =G20/G$10 -> 8.0319306e-11 | W20: =F20-S20 -> 0.049733117
B21: 3.1.4 | C21: Nguyên vật liệu phụ | D21: 638275817 | E21: 511506981 | F21: 995011960 | G21: =SUM(CPSX!K$41:K$47)+SUM(CPSX!K$63:K$69) -> 1.3614546e+08 | H21: =SUM(CPSX!L$41:L$47)+SUM(CPSX!L$63:L$69) -> 1.0901108e+08 | I21: =SUM(CPSX!M$41:M$47)+SUM(CPSX!M$63:M$69) -> 2.2271629e+08 | J21: =SUM(CPSX!N$41:N$47)+SUM(CPSX!N$63:N$69) -> 8.2920734e+08 | K21: =SUM(CPSX!O$41:O$47)+SUM(CPSX!O$63:O$69) -> 9.3259777e+08 | L21: =SUM(CPSX!P$41:P$47)+SUM(CPSX!P$63:P$69) -> 9.6958168e+08 | M21: =SUM(CPSX!Q$41:Q$47)+SUM(CPSX!Q$63:Q$69) -> 1.0065656e+09 | N21: =SUM(CPSX!R$41:R$47)+SUM(CPSX!R$63:R$69) -> 9.6958168e+08 | ... R21: =SUM(CPSX!V$41:V$47)+SUM(CPSX!V$63:V$69) -> 1.0065656e+09 | S21: =SUM(G21:R21) -> 9.0167497e+09 | T21: =S21/F21 -> 9.0619511 | U21: =F21/F$10 -> 0.010344804 | V21: =G21/G$10 -> 0.01402749
B22: 3.1.5 | C22: Điện sản xuất | D22: 160219300 | E22: 225768346 | F22: 424175130 | G22: =CPSX!K$40+CPSX!K$62 -> 1.6538864e+08 | H22: =CPSX!L$40+CPSX!L$62 -> 95416522 | I22: =CPSX!M$40+CPSX!M$62 -> 2.2716263e+08 | J22: =CPSX!N$40+CPSX!N$62 -> 5.4235736e+08 | K22: =CPSX!O$40+CPSX!O$62 -> 5.4235736e+08 | L22: =CPSX!P$40+CPSX!P$62 -> 5.6405166e+08 | M22: =CPSX!Q$40+CPSX!Q$62 -> 5.8574595e+08 | N22: =CPSX!R$40+CPSX!R$62 -> 5.6405166e+08 | ... R22: =CPSX!V$40+CPSX!V$62 -> 5.8574595e+08 | S22: =SUM(G22:R22) -> 5.5210441e+09 | T22: =S22/F22 -> 13.015954 | U22: =F22/F$10 -> 0.004410006 | V22: =G22/G$10 -> 0.017040506
B23: 3.1.6 | C23: Nhân công trực tiếp | D23: 2.5727363e+09 | E23: 2554916743 | F23: 3339997429 | G23: =SUM(CPSX!K$28:K$39)+SUM(CPSX!K$50:K$61) -> 433873828 | H23: =SUM(CPSX!L$28:L$39)+SUM(CPSX!L$50:L$61) -> 441145879 | I23: =SUM(CPSX!M$28:M$39)+SUM(CPSX!M$50:M$61) -> 6.1068742e+08 | J23: =SUM(CPSX!N$28:N$39)+SUM(CPSX!N$50:N$61) -> 7.2111449e+08 | K23: =SUM(CPSX!O$28:O$39)+SUM(CPSX!O$50:O$61) -> 7.0646051e+08 | L23: =SUM(CPSX!P$28:P$39)+SUM(CPSX!P$50:P$61) -> 7.2111449e+08 | M23: =SUM(CPSX!Q$28:Q$39)+SUM(CPSX!Q$50:Q$61) -> 7.0923764e+08 | N23: =SUM(CPSX!R$28:R$39)+SUM(CPSX!R$50:R$61) -> 7.0856235e+08 | ... R23: =SUM(CPSX!V$28:V$39)+SUM(CPSX!V$50:V$61) -> 7.0836539e+08 | S23: =SUM(G23:R23) -> 7.9004329e+09 | T23: =S23/F23 -> 2.3654009 | U23: =F23/F$10 -> 0.034724828 | V23: =G23/G$10 -> 0.04470337
B24: 3.2 | C24: BIẾN PHÍ BÁN HÀNG | D24: 1365150000 | E24: 1040686400 | F24: 2125300000 | G24: =G25 -> 275808000 | H24: =H25 -> 159120000 | I24: =I25 -> 367536000 | J24: =J25 -> 330941000 | K24: =K25 -> 330941000 | L24: =L25 -> 344178640 | M24: =M25 -> 357416280 | N24: =N25 -> 344178640 | ... R24: =R25 -> 357416280 | S24: =SUM(G24:R24) -> 3873596480 | T24: =S24/F24 -> 1.8226116 | U24: =F24/F$10 -> 0.022096028 | V24: =G24/G$10 -> 0.028417356
C25: Chi phí vận chuyển | D25: 1365150000 | E25: 1040686400 | F25: 2125300000 | G25: =CPBH!K$8 -> 275808000 | H25: =CPBH!L$8 -> 159120000 | I25: =CPBH!M$8 -> 367536000 | J25: =CPBH!N$8 -> 330941000 | K25: =CPBH!O$8 -> 330941000 | L25: =CPBH!P$8 -> 344178640 | M25: =CPBH!Q$8 -> 357416280 | N25: =CPBH!R$8 -> 344178640 | ... R25: =CPBH!V$8 -> 357416280 | S25: =SUM(G25:R25) -> 3873596480 | T25: =S25/F25 -> 1.8226116 | U25: =F25/F$10 -> 0.022096028 | V25: =G25/G$10 -> 0.028417356
B26: 4 | C26: LÃI SAU BIẾN PHÍ | D26: 1.0130002e+09 | E26: 3587056490 | F26: 10961475871 | G26: =G10-G15 -> 1.1284021e+09 | H26: =H10-H15 -> 5.1970152e+08 | I26: =I10-I15 -> 1.1017237e+09 | J26: =J10-J15 -> 1.5135048e+09 | K26: =K10-K15 -> 1.4247684e+09 | L26: =L10-L15 -> 1.4956835e+09 | M26: =M10-M15 -> 1.5931295e+09 | N26: =N10-N15 -> 1.5082357e+09 | ... R26: =R10-R15 -> 1.5940018e+09 | S26: =SUM(G26:R26) -> 1.6218536e+10 | T26: =S26/F26 -> 1.4795942 | U26: =F26/F$10 -> 0.11396277 | V26: =G26/G$10 -> 0.11626277
B27: 4.1 | C27: % lãi biến phí/doanh thu | D27: 0.022773255 | E27: 0.056091188 | F27: 0.11396277 | G27: =G26/G10 -> 0.11626277 | H27: =H26/H10 -> 0.09281387 | I27: =I26/I10 -> 0.085207926 | J27: =J26/J10 -> 0.092078439 | K27: =K26/K10 -> 0.086679901 | L27: =L26/L10 -> 0.087494452 | M27: =M26/M10 -> 0.089743185 | N27: =N26/N10 -> 0.088228727 | ... S27: =S26/S10 -> 0.089718503 | T27: =S27/F27 -> 0.7872615 | U27: =F27/F$10 -> 1.1848326e-12 | V27: =G27/G$10 -> 1.1978915e-11
B28: 5 | C28: CHI PHÍ SẢN XUẤT CHUNG | D28: 5.0983022e+08 | E28: 1164487071 | F28: 1910944638 | G28: =G29+G30+G31 -> 3.2322006e+08 | H28: =H29+H30+H31 -> 3.3603316e+08 | I28: =I29+I30+I31 -> 4.0538112e+08 | J28: =J29+J30+J31 -> 8.3610333e+08 | K28: =K29+K30+K31 -> 8.8479654e+08 | L28: =L29+L30+L31 -> 9.0511612e+08 | M28: =M29+M30+M31 -> 9.4733996e+08 | N28: =N29+N30+N31 -> 9.4917077e+08 | ... R28: =R29+R30+R31 -> 9.4405953e+08 | S28: =SUM(G28:R28) -> 9.3982891e+09 | T28: =S28/F28 -> 4.9181378 | U28: =F28/F$10 -> 0.019867448 | V28: =G28/G$10 -> 0.033302367
B29: 5.1 | C29: Lương gián tiếp Sản xuất | D29: 3.9856833e+08 | E29: 530657837 | F29: 1201415069 | G29: =SUM(CPSX!K$72:K$83) -> 2.2119959e+08 | H29: =SUM(CPSX!L$72:L$83) -> 2.1904187e+08 | I29: =SUM(CPSX!M$72:M$83) -> 2.0794514e+08 | J29: =SUM(CPSX!N$72:N$83) -> 378400505 | K29: =SUM(CPSX!O$72:O$83) -> 365430740 | L29: =SUM(CPSX!P$72:P$83) -> 378400505 | M29: =SUM(CPSX!Q$72:Q$83) -> 368841683 | N29: =SUM(CPSX!R$72:R$83) -> 368646707 | ... R29: =SUM(CPSX!V$72:V$83) -> 368589849 | S29: =SUM(G29:R29) -> 3.9940596e+09 | T29: =S29/F29 -> 3.3244627 | U29: =F29/F$10 -> 0.012490708 | V29: =G29/G$10 -> 0.022790882
B30: 5.2 | C30: Chi phí thuê xưởng | G30: =CPSX!K$88 -> 0 | H30: =CPSX!L$88 -> 0 | I30: =CPSX!M$88 -> 0 | J30: =CPSX!N$88 -> 1.9260139e+08 | K30: =CPSX!O$88 -> 1.9260139e+08 | L30: =CPSX!P$88 -> 1.9260139e+08 | M30: =CPSX!Q$88 -> 1.9260139e+08 | N30: =CPSX!R$88 -> 1.9260139e+08 | ... R30: =CPSX!V$88 -> 1.9260139e+08 | S30: =SUM(G30:R30) -> 1.7334125e+09 | T30: =S30/F30 -> #DIV/0! | U30: =F30/F$10 -> 0 | V30: =G30/G$10 -> 0
B31: 5.3 | C31: Chi phí sản xuất (Ngoài lương, BOM, thuê xưởng, khấu hao) | D31: 1.1126189e+08 | E31: 633829234 | F31: 709529569 | G31: =SUM(CPSX!K$84:K$98)-CPSX!K88 -> 1.0202046e+08 | H31: =SUM(CPSX!L$84:L$98)-CPSX!L88 -> 116991288 | I31: =SUM(CPSX!M$84:M$98)-CPSX!M88 -> 1.9743597e+08 | J31: =SUM(CPSX!N$84:N$98)-CPSX!N88 -> 2.6510144e+08 | K31: =SUM(CPSX!O$84:O$98)-CPSX!O88 -> 3.2676442e+08 | L31: =SUM(CPSX!P$84:P$98)-CPSX!P88 -> 3.3411423e+08 | M31: =SUM(CPSX!Q$84:Q$98)-CPSX!Q88 -> 3.8589689e+08 | N31: =SUM(CPSX!R$84:R$98)-CPSX!R88 -> 3.8792268e+08 | ... R31: =SUM(CPSX!V$84:V$98)-CPSX!V88 -> 3.8286829e+08 | S31: =SUM(G31:R31) -> 3.6708171e+09 | T31: =S31/F31 -> 5.1735928 | U31: =F31/F$10 -> 0.00737674 | V31: =G31/G$10 -> 0.010511485
B32: 6 | C32: CHI PHÍ KHẤU HAO | D32: 2815366932 | E32: 3970082577 | F32: 3851337229 | G32: =PB_TSCD!AF$46 -> 2.0364185e+08 | H32: =PB_TSCD!AG$46 -> 2.0900296e+08 | I32: =PB_TSCD!AH$46 -> 2.1483629e+08 | J32: =PB_TSCD!AI$46 -> 2.406974e+08 | K32: =PB_TSCD!AJ$46 -> 2.406974e+08 | L32: =PB_TSCD!AK$46 -> 2.406974e+08 | M32: =PB_TSCD!AL$46 -> 2.406974e+08 | N32: =PB_TSCD!AM$46 -> 2.406974e+08 | ... R32: =PB_TSCD!AQ$46 -> 2.3458629e+08 | S32: =SUM(G32:R32) -> 2.7876466e+09 | T32: =S32/F32 -> 0.72381265 | U32: =F32/F$10 -> 0.040041056 | V32: =G32/G$10 -> 0.020981853
B33: 7 | C33: LỢI NHUẬN GỘP | D33: -2.3121969e+09 | E33: -1547513158 | F33: 5199194004 | G33: =G26-G28-G32 -> 6.0154017e+08 | H33: =H26-H28-H32 -> -25334598 | I33: =I26-I28-I32 -> 4.8150625e+08 | J33: =J26-J28-J32 -> 4.3670407e+08 | K33: =K26-K28-K32 -> 2.9927442e+08 | L33: =L26-L28-L32 -> 3.4987001e+08 | M33: =M26-M28-M32 -> 4.0509218e+08 | N33: =N26-N28-N32 -> 3.183675e+08 | ... R33: =R26-R28-R32 -> 4.1535597e+08 | S33: =SUM(G33:R33) -> 4.0326e+09 | T33: =S33/F33 -> 0.77562023 | U33: =F33/F$10 -> 0.054054269 | V33: =G33/G$10 -> 0.061978554
B34: 7.1 | C34: % lãi gộp/doanh thu | D34: -0.051980491 | E34: -0.02419863 | F34: 0.054054269 | G34: =G33/G10 -> 0.061978554 | H34: =H33/H10 -> -0.0045245242 | I34: =I33/I10 -> 0.037239964 | J34: =J33/J10 -> 0.026568154 | K34: =K33/K10 -> 0.018207224 | L34: =L33/L10 -> 0.020466685 | M34: =M33/M10 -> 0.022819401 | N34: =N33/N10 -> 0.018623853 | ... S34: =S33/S10 -> 0.022307738 | T34: =S34/F34 -> 0.41269151 | U34: =F34/F$10 -> 5.6198403e-13 | V34: =G34/G$10 -> 6.3858431e-12 | W34: ='[1]KE30-DongLam'!$BV$2 -> 0.11073334
B35: 8 | C35: CHI PHÍ BÁN HÀNG & MKT & R&D | D35: 0 | E35: 0 | F35: 0 | G35: =G36+G37+G38 -> 0 | H35: =H36+H37+H38 -> 0 | I35: =I36+I37+I38 -> 0 | J35: =J36+J37+J38 -> 0 | K35: =K36+K37+K38 -> 0 | L35: =L36+L37+L38 -> 0 | M35: =M36+M37+M38 -> 0 | N35: =N36+N37+N38 -> 0 | ... R35: =R36+R37+R38 -> 0 | S35: =SUM(G35:R35) -> 0 | T35: =S35/F35 -> #DIV/0! | U35: =F35/F$10 -> 0 | V35: =G35/G$10 -> 0
B36: 8.1 | C36: Lương | D36: 0 | E36: 0 | F36: 0 | S36: =SUM(G36:R36) -> 0 | T36: =S36/F36 -> #DIV/0! | U36: =F36/F$10 -> 0 | V36: =G36/G$10 -> 0
B37: 8.2 | C37: Chi phí bán hàng (ngoài lương, khấu hao) | D37: 0 | E37: 0 | F37: 0 | S37: =SUM(G37:R37) -> 0 | T37: =S37/F37 -> #DIV/0! | U37: =F37/F$10 -> 0 | V37: =G37/G$10 -> 0
B38: 8.3 | C38: Khấu hao tài sản | D38: 0 | E38: 0 | F38: 0 | S38: =SUM(G38:R38) -> 0 | T38: =S38/F38 -> #DIV/0! | U38: =F38/F$10 -> 0 | V38: =G38/G$10 -> 0
B39: 9 | C39: CHI PHÍ QUẢN LÝ | D39: 1920530080 | E39: 1657750500 | F39: 2232089956 | G39: =G40+G41+G42 -> 299930825 | H39: =H40+H41+H42 -> 364454832 | I39: =I40+I41+I42 -> 320241950 | J39: =J40+J41+J42 -> 351665309 | K39: =K40+K41+K42 -> 345531727 | L39: =L40+L41+L42 -> 3.5930345e+08 | M39: =M40+M41+M42 -> 3.7807215e+08 | N39: =N40+N41+N42 -> 6.5296212e+08 | ... R39: =R40+R41+R42 -> 3.771277e+08 | S39: =SUM(G39:R39) -> 4.5496361e+09 | T39: =S39/F39 -> 2.0382853 | U39: =F39/F$10 -> 0.023206288 | V39: =G39/G$10 -> 0.030902805
B40: 9.1 | C40: Lương | D40: 545455272 | E40: 507934414 | F40: 1445606425 | G40: =SUM(CPQL!K$5:K$16) -> 210647270 | H40: =SUM(CPQL!L$5:L$16) -> 213418574 | I40: =SUM(CPQL!M$5:M$16) -> 1.9799139e+08 | J40: =SUM(CPQL!N$5:N$16) -> 230329766 | K40: =SUM(CPQL!O$5:O$16) -> 221578000 | L40: =SUM(CPQL!P$5:P$16) -> 230329766 | M40: =SUM(CPQL!Q$5:Q$16) -> 224351483 | N40: =SUM(CPQL!R$5:R$16) -> 224328197 | ... R40: =SUM(CPQL!V$5:V$16) -> 223960871 | S40: =SUM(G40:R40) -> 2.6568794e+09 | T40: =S40/F40 -> 1.8378996 | U40: =F40/F$10 -> 0.015029483 | V40: =G40/G$10 -> 0.021703643
B41: 9.2 | C41: Chi phí quản lý (ngoài lương, khấu hao) | D41: 985729687 | E41: 1135468262 | F41: 599521967 | G41: =SUM(CPQL!K$17:K$62) -> 80445799 | H41: =SUM(CPQL!L$17:L$62) -> 142198502 | I41: =SUM(CPQL!M$17:M$62) -> 1.1341281e+08 | J41: =SUM(CPQL!N$17:N$62) -> 1.0999779e+08 | K41: =SUM(CPQL!O$17:O$62) -> 1.1261597e+08 | L41: =SUM(CPQL!P$17:P$62) -> 1.1763592e+08 | M41: =SUM(CPQL!Q$17:Q$62) -> 1.4238291e+08 | N41: =SUM(CPQL!R$17:R$62) -> 4.1729617e+08 | ... R41: =SUM(CPQL!V$17:V$62) -> 1.4182907e+08 | S41: =SUM(G41:R41) -> 1.7642036e+09 | T41: =S41/F41 -> 2.9426838 | U41: =F41/F$10 -> 0.006233028 | V41: =G41/G$10 -> 0.0082885808
B42: 9.3 | C42: Khấu hao tài sản | D42: 389345121 | E42: 14347824 | F42: 186961564 | G42: =PB_TSCD!AF$47 -> 8837756 | H42: =PB_TSCD!AG$47 -> 8837756 | I42: =PB_TSCD!AH$47 -> 8837756 | J42: =PB_TSCD!AI$47 -> 11337756 | K42: =PB_TSCD!AJ$47 -> 11337756 | L42: =PB_TSCD!AK$47 -> 11337756 | M42: =PB_TSCD!AL$47 -> 11337756 | N42: =PB_TSCD!AM$47 -> 11337756 | ... R42: =PB_TSCD!AQ$47 -> 11337756 | S42: =SUM(G42:R42) -> 128553072 | T42: =S42/F42 -> 0.68759091 | U42: =F42/F$10 -> 0.0019437764 | V42: =G42/G$10 -> 0.00091058148
B43: 10 | C43: DOANH THU/CHI PHÍ KHÁC | D43: 0 | E43: 0 | F43: 87340287 | S43: =SUM(G43:R43) -> 0 | T43: =S43/F43 -> 0 | U43: =F43/F$10 -> 0.00090804755 | V43: =G43/G$10 -> 0
B44: 11 | C44: LỢI NHUẬN THUẦN TỪ HOẠT ĐỘNG KINH DOANH | D44: -4.232727e+09 | E44: -3205263658 | F44: 3054444335 | G44: =G33-G35-G39+G43 -> 3.0160934e+08 | H44: =H33-H35-H39+H43 -> -3.8978943e+08 | I44: =I33-I35-I39+I43 -> 1.612643e+08 | J44: =J33-J35-J39+J43 -> 85038765 | K44: =K33-K35-K39+K43 -> -46257309 | L44: =L33-L35-L39+L43 -> -9433439.1 | M44: =M33-M35-M39+M43 -> 27020031 | N44: =N33-N35-N39+N43 -> -3.3459462e+08 | ... R44: =R33-R35-R39+R43 -> 38228271 | S44: =SUM(G44:R44) -> -5.1703601e+08 | T44: =S44/F44 -> -0.16927334 | U44: =F44/F$10 -> 0.031756029 | V44: =G44/G$10 -> 0.031075748
B45: 12 | C45: DOANH THU TÀI CHÍNH | D45: 27142139 | E45: 52016376 | F45: 318990785 | G45: 20000000 | H45: 20000000 | I45: 20000000 | J45: 10000000 | K45: 10000000 | L45: 10000000 | M45: 10000000 | N45: 10000000 | O45: 10000000 | P45: 10000000 | Q45: 10000000 | R45: 10000000 | S45: =SUM(G45:R45) -> 150000000 | T45: =S45/F45 -> 0.47023302 | U45: =F45/F$10 -> 0.0033164398 | V45: =G45/G$10 -> 0.0020606622
B46: 13 | C46: CHI PHÍ TÀI CHÍNH | D46: 0 | E46: 0 | F46: 3187200 | S46: =SUM(G46:R46) -> 0 | T46: =S46/F46 -> 0 | U46: =F46/F$10 -> 3.3136245e-05 | V46: =G46/G$10 -> 0
B47: 13.1 | C47: Trong đó: chi phí lãi vay | D47: 0 | E47: 0 | F47: 3187200 | S47: =SUM(G47:R47) -> 0 | T47: =S47/F47 -> 0 | U47: =F47/F$10 -> 3.3136245e-05 | V47: =G47/G$10 -> 0
B48: 14 | C48: LỢI NHUẬN TRƯỚC THUẾ | D48: -4.2055849e+09 | E48: -3153247282 | F48: 3370247920 | G48: =G44+G45-G46 -> 3.2160934e+08 | H48: =H44+H45-H46 -> -3.6978943e+08 | I48: =I44+I45-I46 -> 1.812643e+08 | J48: =J44+J45-J46 -> 95038765 | K48: =K44+K45-K46 -> -36257309 | L48: =L44+L45-L46 -> 566560.92 | M48: =M44+M45-M46 -> 37020031 | N48: =N44+N45-N46 -> -3.2459462e+08 | ... R48: =R44+R45-R46 -> 48228271 | S48: =SUM(G48:R48) -> -3.6703601e+08 | T48: =S48/F48 -> -0.10890475 | U48: =F48/F$10 -> 0.035039333 | V48: =G48/G$10 -> 0.03313641
B49: 15 | C49: THUẾ TNDN | D49: 0 | E49: 0 | F49: 0 | S49: =SUM(G49:R49) -> 0 | T49: =S49/F49 -> #DIV/0! | U49: =F49/F$10 -> 0 | V49: =G49/G$10 -> 0
B50: 16 | C50: LỢI NHUẬN SAU THUẾ | D50: -4.2055849e+09 | E50: -3153247282 | F50: 3370247920 | G50: =G48-G49 -> 3.2160934e+08 | H50: =H48-H49 -> -3.6978943e+08 | I50: =I48-I49 -> 1.812643e+08 | J50: =J48-J49 -> 95038765 | K50: =K48-K49 -> -36257309 | L50: =L48-L49 -> 566560.92 | M50: =M48-M49 -> 37020031 | N50: =N48-N49 -> -3.2459462e+08 | ... R50: =R48-R49 -> 48228271 | S50: =SUM(G50:R50) -> -3.6703601e+08 | T50: =S50/F50 -> -0.10890475 | U50: =F50/F$10 -> 0.035039333 | V50: =G50/G$10 -> 0.03313641
B51: 16.1 | C51: % LNST/doanh thu | D51: -0.094545739 | E51: -0.049307667 | F51: 0.035039333 | G51: =G50/G10 -> 0.03313641 | H51: =H50/H10 -> -0.066040962 | I51: =I50/I10 -> 0.014019083 | J51: =J50/J10 -> 0.0057819579 | K51: =K50/K10 -> -0.0022058182 | L51: =L50/L10 -> 3.3142665e-05 | M51: =M50/M10 -> 0.0020853894 | N51: =N50/N10 -> -0.018988127 | ... S51: =S50/S10 -> -0.0020303881 | T51: =S51/F51 -> -0.057945969 | U51: =F51/F$10 -> 3.6429214e-13 | V51: =G51/G$10 -> 3.4141474e-12
B52: 17 | C52: Khấu hao tài sản | D52: 2904227598 | E52: 3977819339 | F52: 4038298793 | G52: =G32+G42 -> 2.124796e+08 | H52: =H32+H42 -> 2.1784071e+08 | I52: =I32+I42 -> 2.2367405e+08 | J52: =J32+J42 -> 2.5203516e+08 | K52: =K32+K42 -> 2.5203516e+08 | L52: =L32+L42 -> 2.5203516e+08 | M52: =M32+M42 -> 2.5203516e+08 | N52: =N32+N42 -> 2.5203516e+08 | ... R52: =R32+R42 -> 2.4592405e+08 | S52: =SUM(G52:R52) -> 2.9161997e+09 | T52: =S52/F52 -> 0.72213569 | U52: =F52/F$10 -> 0.041984832 | V52: =G52/G$10 -> 0.021892434
B53: 18 | C53: LỢI NHUẬN KHÔNG BAO GỒM KHẤU HAO, LÃI VAY | D53: -1.3013573e+09 | E53: 824572057 | F53: 7408546713 | G53: =G50+G52 -> 5.3408895e+08 | H53: =H50+H52 -> -1.5194872e+08 | I53: =I50+I52 -> 4.0493835e+08 | J53: =J50+J52 -> 3.4707392e+08 | K53: =K50+K52 -> 2.1577785e+08 | L53: =L50+L52 -> 2.5260172e+08 | M53: =M50+M52 -> 2.8905519e+08 | N53: =N50+N52 -> -72559459 | ... R53: =R50+R52 -> 2.9415232e+08 | S53: =SUM(G53:R53) -> 2.5491637e+09 | T53: =S53/F53 -> 0.34408417 | U53: =F53/F$10 -> 0.077024165 | V53: =G53/G$10 -> 0.055028845
B54: 18.1 | C54: % LN không gồm khấu hao/doanh thu | D54: -0.029255808 | E54: 0.012893922 | F54: 0.077024165 | G54: =G53/G10 -> 0.055028845 | H54: =H53/H10 -> -0.027136631 | I54: =I53/I10 -> 0.031318159 | J54: =J53/J10 -> 0.021115245 | K54: =K53/K10 -> 0.013127469 | L54: =L53/L10 -> 0.014776688 | M54: =M53/M10 -> 0.016282878 | N54: =N53/N10 -> -0.0042445811 | ... S54: =S53/S10 -> 0.01410159 | T54: =S54/F54 -> 0.18308008 | U54: =F54/F$10 -> 8.007943e-13 | V54: =G54/G$10 -> 5.669793e-12
B57: 1. Hòa vốn (Bao gồm khấu hao) | D57: =D4 -> Thực tế năm 2023 | E57: =E4 -> Thực tế năm 2024 | F57: =F4 -> Thực tế năm 2025 | G57: =G4 -> T1 | H57: =H4 -> T2 | I57: =I4 -> T3 | J57: =J4 -> T4 | K57: =K4 -> T5 | ... S57: =S4 -> 10/03/2026 DTR
B58: Sản lượng NVL hòa vốn (tấn) | D58: =IFERROR(D$59*(1+(D$18+D$19)/D$17),0) -> 17130125 | E58: =IFERROR(E$59*(1+(E$18+E$19)/E$17),0) -> 8789882.7 | F58: =IFERROR(F$59*(1+(F$18+F$19)/F$17),0) -> 4614553.4 | G58: =G$59*(1+(G$18+G$19)/G$17) -> 563824.36 | H58: =H$59*(1+(H$18+H$19)/H$17) -> 776914.75 | I58: =I$59*(1+(I$18+I$19)/I$17) -> 875721.43 | J58: =J$59*(1+(J$18+J$19)/J$17) -> 1141665.3 | K58: =K$59*(1+(K$18+K$19)/K$17) -> 1248902.9 | L58: =L$59*(1+(L$18+L$19)/L$17) -> 1265950.1 | M58: =M$59*(1+(M$18+M$19)/M$17) -> 1284243.8 | N58: =N$59*(1+(N$18+N$19)/N$17) -> 1537100.1 | ... S58: =S$59*(1+(S$18+S$19)/S$17) -> 13903949
B59: Sản lượng thành phẩm hòa vốn (tấn) | D59: =IFERROR((D$28+D$32+D$35+D$39)/(D$26/D$6),0) -> 16185683 | E59: =IFERROR((E$28+E$32+E$35+E$39)/(E$26/E$6),0) -> 8080718.9 | F59: =IFERROR((F$28+F$32+F$35+F$39)/(F$26/F$6),0) -> 4158840.1 | G59: =(G$28+G$32+G$35+G$39)/(G$26/G$6) -> 505218.96 | H59: =(H$28+H$32+H$35+H$39)/(H$26/H$6) -> 696160.17 | I59: =(I$28+I$32+I$35+I$39)/(I$26/I$6) -> 784345.21 | J59: =(J$28+J$32+J$35+J$39)/(J$26/J$6) -> 967750.82 | K59: =(K$28+K$32+K$35+K$39)/(K$26/K$6) -> 1058652.5 | L59: =(L$28+L$32+L$35+L$39)/(L$26/L$6) -> 1073102.8 | M59: =(M$28+M$32+M$35+M$39)/(M$26/M$6) -> 1088609.8 | N59: =(N$28+N$32+N$35+N$39)/(N$26/N$6) -> 1302947.5 | ... S59: =(S$28+S$32+S$35+S$39)/(S$26/S$6) -> 11888822
B60: Doanh thu hòa vốn (triệu đồng) | D60: =IFERROR(D$59*(D$10/D$6),0) -> 2.3034596e+11 | E60: =IFERROR(E$59*(E$10/E$6),0) -> 1.2109425e+11 | F60: =IFERROR(F$59*(F$10/F$6),0) -> 7.0148976e+10 | G60: =G$59*(G$10/G$6) -> 7.1114141e+09 | H60: =H$59*(H$10/H$6) -> 9.7990845e+09 | I60: =I$59*(I$10/I$6) -> 1.1037229e+10 | J60: =J$59*(J$10/J$6) -> 1.5513578e+10 | K60: =K$59*(K$10/K$6) -> 1.6970782e+10 | L60: =L$59*(L$10/L$6) -> 1.7202428e+10 | M60: =M$59*(M$10/M$6) -> 1.7451013e+10 | N60: =N$59*(N$10/N$6) -> 2.0886965e+10 | ... S60: =S$59*(S$10/S$6) -> 1.8653423e+11
B61: 2. Hòa vốn (Không bao gồm khấu hao) | D61: =D57 -> Thực tế năm 2023 | E61: =E57 -> Thực tế năm 2024 | F61: =F57 -> Thực tế năm 2025 | G61: =G57 -> T1 | H61: =H57 -> T2 | I61: =I57 -> T3 | J61: =J57 -> T4 | K61: =K57 -> T5 | ... S61: =S57 -> 10/03/2026 DTR
B62: Sản lượng NVL hòa vốn (tấn) | D62: =IFERROR(D$63*(1+(D$18+D$19)/D$17),0) -> 7646257.3 | E62: =IFERROR(E$63*(1+(E$18+E$19)/E$17),0) -> 3642221.1 | F62: =IFERROR(F$63*(1+(F$18+F$19)/F$17),0) -> 2283545.3 | G62: =G$63*(1+(G$18+G$19)/G$17) -> 418925.68 | H62: =H$63*(1+(H$18+H$19)/H$17) -> 590828.61 | I62: =I$63*(1+(I$18+I$19)/I$17) -> 667444.32 | J62: =J$63*(1+(J$18+J$19)/J$17) -> 940232.6 | K62: =K$63*(1+(K$18+K$19)/K$17) -> 1034924.7 | L62: =L$63*(1+(L$18+L$19)/L$17) -> 1053963.9 | M62: =M$63*(1+(M$18+M$19)/M$17) -> 1077569.5 | N62: =N$63*(1+(N$18+N$19)/N$17) -> 1326878.2 | ... S62: =S$63*(1+(S$18+S$19)/S$17) -> 11481164
B63: Sản lượng thành phẩm hòa vốn (tấn) | D63: =IFERROR((D$28+D$32+D$35+D$39-D52)/(D$26/D$6),0) -> 7224693.2 | E63: =IFERROR((E$28+E$32+E$35+E$39-E52)/(E$26/E$6),0) -> 3348368.4 | F63: =IFERROR((F$28+F$32+F$35+F$39-F52)/(F$26/F$6),0) -> 2058032.3 | G63: =(G$28+G$32+G$35+G$39-G52)/(G$26/G$6) -> 375381.43 | H63: =(H$28+H$32+H$35+H$39-H52)/(H$26/H$6) -> 529416.32 | I63: =(I$28+I$32+I$35+I$39-I52)/(I$26/I$6) -> 597800.56 | J63: =(J$28+J$32+J$35+J$39-J52)/(J$26/J$6) -> 797003.16 | K63: =(K$28+K$32+K$35+K$39-K52)/(K$26/K$6) -> 877270.43 | L63: =(L$28+L$32+L$35+L$39-L52)/(L$26/L$6) -> 893409.33 | M63: =(M$28+M$32+M$35+M$39-M52)/(M$26/M$6) -> 913418.98 | N63: =(N$28+N$32+N$35+N$39-N52)/(N$26/N$6) -> 1124749.5 | ... S63: =(S$28+S$32+S$35+S$39-S52)/(S$26/S$6) -> 9817176.4
B64: Doanh thu hòa vốn (triệu đồng) | D64: =IFERROR(D$63*(D$10/D$6),0) -> 1.0281796e+11 | E64: =IFERROR(E$63*(E$10/E$6),0) -> 5.0177236e+10 | F64: =IFERROR(F$63*(F$10/F$6),0) -> 3.4713731e+10 | G64: =G$63*(G$10/G$6) -> 5.2838334e+09 | H64: =H$63*(H$10/H$6) -> 7.4520138e+09 | I64: =I$63*(I$10/I$6) -> 8.4121906e+09 | J64: =J$63*(J$10/J$6) -> 1.2776399e+10 | K64: =K$63*(K$10/K$6) -> 1.4063128e+10 | L64: =L$63*(L$10/L$6) -> 1.4321843e+10 | M64: =M$63*(M$10/M$6) -> 1.4642609e+10 | N64: =N$63*(N$10/N$6) -> 1.8030354e+10 | ... S64: =S$63*(S$10/S$6) -> 1.5403035e+11

Sheet Gia dinh
Q1: Định biên về nhân sự
B2: Phương án 1 | R2: =B6 -> Chuyền PL cũ | T2: =B9 -> Chuyền rework | V2: =B7 -> Chuyền AI 1 | X2: =B8 -> Chuyền AI 2 | Z2: =B10 -> Chuyền băm vảy | AC2: SXC
R3: Ca 1 | S3: Ca 2 | T3: Ca 1 | U3: Ca 2 | V3: Ca 1 | W3: Ca 2 | X3: Ca 1 | Y3: Ca 2 | Z3: Ca 1 | AA3: Ca 2 | AB3: Ca 3 | AC3: Ca 1 | AD3: Ca 2
B4: Công suất máy | O4: Tấn / giờ | Q4: Chi tiết phân bổ Công nhân trực tiếp SX
B5: Chuyền máy | C5: T1 | D5: T2 | E5: T3 | F5: T4 | G5: T5 | H5: T6 | I5: T7 | J5: T8 | K5: T9 | L5: T10 | M5: T11 | N5: T12 | O5: 2026 | Q5: Công nhân trực tiếp sản xuất - Phân loại | R5: =R6+R17+R21 -> 14 | S5: =S6+S17+S21 -> 14 | T5: =T6+T17+T21 -> 6 | U5: =U6+U17+U21 -> 6 | V5: =V6+V17+V21 -> 11 | W5: =W6+W17+W21 -> 11 | X5: =X6+X17+X21 -> 10 | Y5: =Y6+Y17+Y21 -> 10 | ... AD5: =AD6+AD17+AD21 -> 3
B6: Chuyền PL cũ | C6: 1100 | D6: 1100 | E6: 1100 | Q6: SX chai PET - Chuyền phân loại | R6: =SUM(R7:R12) -> 14 | S6: =SUM(S7:S12) -> 14 | T6: =SUM(T7:T12) -> 6 | U6: =SUM(U7:U12) -> 6 | V6: =SUM(V7:V12) -> 11 | W6: =SUM(W7:W12) -> 11 | X6: =SUM(X7:X12) -> 10 | Y6: =SUM(Y7:Y12) -> 10 | AC6: =SUM(AC7:AC12) -> 0 | AD6: =SUM(AD7:AD12) -> 0
B7: Chuyền AI 1 | C7: 1500 | D7: 1500 | E7: 1500 | F7: 1500 | G7: 1500 | H7: 1500 | I7: 1500 | J7: 1500 | K7: 1500 | L7: 1500 | M7: 1500 | N7: 1500 | Q7: Công đoạn 1: Cấp liệu | R7: 1 | S7: 1 | T7: 1 | U7: 1 | V7: 2 | W7: 2 | X7: 1 | Y7: 1
B8: Chuyền AI 2 | F8: 1500 | G8: 1500 | H8: 1500 | I8: 1500 | J8: 1500 | K8: 1500 | L8: 1500 | M8: 1500 | N8: 1500 | Q8: Công đoạn 2: Phân loại trước tách nhãn | R8: 5 | S8: 5 | T8: 2 | U8: 2 | V8: 3 | W8: 3 | X8: 3 | Y8: 3
B9: Chuyền rework | C9: =(C6+C7+C8)*40% -> 1040 | D9: =(D6+D7+D8)*40% -> 1040 | E9: =(E6+E7+E8)*40% -> 1040 | F9: =(F6+F7+F8)*40% -> 1200 | G9: =(G6+G7+G8)*40% -> 1200 | H9: =(H6+H7+H8)*40% -> 1200 | I9: =(I6+I7+I8)*40% -> 1200 | J9: =(J6+J7+J8)*40% -> 1200 | ... N9: =(N6+N7+N8)*40% -> 1200 | Q9: Công đoạn 3: Phân loại sau tách nhãn | R9: 4 | S9: 4 | T9: 1 | U9: 1 | V9: 3 | W9: 3 | X9: 3 | Y9: 3
B10: Chuyền băm vảy | C10: 2000 | D10: 2000 | E10: 2000 | F10: 2000 | G10: 2000 | H10: 2000 | I10: 2000 | J10: 2000 | K10: 2000 | L10: 2000 | M10: 2000 | N10: 2000 | Q10: Nhân viên vệ sinh kim loại nam châm - theo yêu cầu KSNB đảm bảo nam châm sạch | R10: 1 | S10: 1 | V10: 1 | W10: 1 | X10: 1 | Y10: 1
Q11: Nhân viên kéo bao, bì tạp | R11: 2 | S11: 2 | T11: 1 | U11: 1 | V11: 1 | W11: 1 | X11: 1 | Y11: 1
B12: Công suất định mức | Q12: Nhân viên Ép kiện | R12: 1 | S12: 1 | T12: 1 | U12: 1 | V12: 1 | W12: 1 | X12: 1 | Y12: 1
B13: Phân loại | C13: =C6+C7+C8 -> 2600 | D13: =D6+D7+D8 -> 2600 | E13: =E6+E7+E8 -> 2600 | F13: =F6+F7+F8 -> 3000 | G13: =G6+G7+G8 -> 3000 | H13: =H6+H7+H8 -> 3000 | I13: =I6+I7+I8 -> 3000 | J13: =J6+J7+J8 -> 3000 | ... N13: =N6+N7+N8 -> 3000 | Q13: SX băm vảy PET | Z13: =SUM(Z14:Z16) -> 4 | AA13: =SUM(AA14:AA16) -> 4 | AB13: =SUM(AB14:AB16) -> 4
B14: Băm vảy | D14: =D10 -> 2000 | E14: =E10 -> 2000 | F14: =F10 -> 2000 | G14: =G10 -> 2000 | H14: =H10 -> 2000 | I14: =I10 -> 2000 | J14: =J10 -> 2000 | K14: =K10 -> 2000 | ... N14: =N10 -> 2000 | Q14: Công đoạn 1: Cấp liệu | Z14: 1 | AA14: 1 | AB14: 1
Q15: Nhân viên PL trước băm | Z15: 2 | AA15: 2 | AB15: 2
B16: Hiệu suất máy | Q16: Nhân viên đóng gói TP | Z16: 1 | AA16: 1 | AB16: 1
B17: Phân loại | C17: 0.75 | D17: 0.75 | E17: 0.75 | F17: 0.75 | G17: 0.75 | H17: 0.75 | I17: 0.75 | J17: 0.75 | K17: 0.75 | L17: 0.75 | M17: 0.75 | N17: 0.75 | Q17: Sản xuất chung | R17: =SUM(R18:R20) -> 0 | S17: =SUM(S18:S20) -> 0 | T17: =SUM(T18:T20) -> 0 | U17: =SUM(U18:U20) -> 0 | V17: =SUM(V18:V20) -> 0 | W17: =SUM(W18:W20) -> 0 | X17: =SUM(X18:X20) -> 0 | Y17: =SUM(Y18:Y20) -> 0 | ... AD17: =SUM(AD18:AD20) -> 3
B18: Băm vảy | D18: 1 | E18: 1 | F18: 1 | G18: 1 | H18: 1 | I18: 1 | J18: 1 | K18: 1 | L18: 1 | M18: 1 | N18: 1 | Q18: Nhân viên lái xe nâng | AC18: 2 | AD18: 1
Q19: Nhân viên giao bì tạp | AC19: 1 | AD19: 1
B20: Sản lượng SX / ngày (24 giờ) x hiệu suất 75% | Q20: Nhân viên ghi số liệu | AC20: 1 | AD20: 1
B21: Phân loại | C21: =(C13*(24-2))*C17 -> 42900 | D21: =(D13*(24-2))*D17 -> 42900 | E21: =(E13*(24-2))*E17 -> 42900 | F21: =(F13*(24-2))*F17 -> 49500 | G21: =(G13*(24-2))*G17 -> 49500 | H21: =(H13*(24-2))*H17 -> 49500 | I21: =(I13*(24-2))*I17 -> 49500 | J21: =(J13*(24-2))*J17 -> 49500 | ... N21: =(N13*(24-2))*N17 -> 49500 | Q21: Xử lý phó sản - Thời vụ | AC21: =SUM(AC22:AC23) -> 5 | AD21: =SUM(AD22:AD23) -> 0
B22: Băm vảy | C22: =(C14*(24-2))*C18 -> 0 | D22: =(D14*(24-2))*D18 -> 44000 | E22: =(E14*(24-2))*E18 -> 44000 | F22: =(F14*(24-2))*F18 -> 44000 | G22: =(G14*(24-2))*G18 -> 44000 | H22: =(H14*(24-2))*H18 -> 44000 | I22: =(I14*(24-2))*I18 -> 44000 | J22: =(J14*(24-2))*J18 -> 44000 | ... N22: =(N14*(24-2))*N18 -> 44000 | Q22: Nhân viên xử lý nắp, cổ chai,… | AC22: 4
Q23: Nhân viên vệ sinh xưởng | AC23: 1
B24: Thành phẩm
B25: TP chai | C25: =C21*88% -> 37752 | D25: =D21*88% -> 37752 | E25: =E21*88% -> 37752 | F25: =F21*88% -> 43560 | G25: =G21*88% -> 43560 | H25: =H21*88% -> 43560 | I25: =I21*88% -> 43560 | J25: =J21*88% -> 43560 | ... N25: =N21*88% -> 43560
B26: TP băm | C26: =C22*88% -> 0 | D26: =D22*88% -> 38720 | E26: =E22*88% -> 38720 | F26: =F22*88% -> 38720 | G26: =G22*88% -> 38720 | H26: =H22*88% -> 38720 | I26: =I22*88% -> 38720 | J26: =J22*88% -> 38720 | ... N26: =N22*88% -> 38720
B27: TP chai bán | C27: =C21*5% -> 2145 | D27: =D21*5% -> 2145 | E27: =E21*5% -> 2145 | F27: =F21*5% -> 2475 | G27: =G21*5% -> 2475 | H27: =H21*5% -> 2475 | I27: =I21*5% -> 2475 | J27: =J21*5% -> 2475 | ... N27: =N21*5% -> 2475

Sheet Cong suat
B3: CÔNG SUẤT
B4: I - CÔNG SUẤT CHUYỀN LỰA CHAI - CHAI ÉP KIỆN - PLENMA | J4: Loại CN k đứng chuyền
B5: STT | C5: Công đoạn sản xuất | D5: Cấp liệu | E5: Lồng tách tạp chất | F5: Lựa phân loại chai | G5: Tách nhãn | H5: Lựa phân loại chai sau tách nhãn | I5: Ép kiện | J5: Công suất thành phẩm cả chuyền
B6: 1 | C6: Năng suất THIẾT KẾ (Kg NVL đầu vào / giờ) | D6: 1100 | E6: 1500 | F6: 1500 | G6: 1.100-1.500 | H6: 1100 | I6: 1400 | J6: =1200*(100%-$D$14) -> 1056
B7: 2 | C7: Năng suất ĐỊNH MỨC (Kg NVL đầu vào / giờ) | D7: 1100 | E7: =D7 -> 1100 | F7: =E7 -> 1100 | G7: =F7 -> 1100 | H7: =G7 -> 1100 | I7: 1300 | J7: =E15 -> 968
B8: 3 | C8: Định mức nhân công (Số NV / Ca8) | D8: ='Dinh bien_HCNS'!$W$60 -> 1 | F8: ='Dinh bien_HCNS'!$W$61 -> 5 | G8: ='Dinh bien_HCNS'!$W$63 -> 2 | H8: ='Dinh bien_HCNS'!$W$62 -> 5 | I8: ='Dinh bien_HCNS'!$W$64 -> 1 | J8: =SUM(D8:I8) -> 14
C9: Diễn giải
B11: STT | C11: Chỉ tiêu định mức | D11: ĐVT | E11: ĐM 1 giờ | F11: ĐM 1 Ca8 | G11: ĐM 1 Ca12 | H11: ĐM 2 Ca8 | I11: ĐM 2 Ca12
B12: 1 | C12: Tổng nhân sự: | D12: Người | E12: =J8 -> 14 | F12: =$E12 -> 14 | G12: =$F12*1.5 -> 21 | H12: =$F12*2 -> 28 | I12: =$G12*2 -> 42
B13: 2 | C13: Định mức NVL đầu vào: | D13: kg/giờ | E13: =$D$7 -> 1100 | F13: =$E13*8 -> 8800 | G13: =$F13*1.5 -> 13200 | H13: =$F13*2 -> 17600 | I13: =$G13*2 -> 26400
B14: 3 | C14: Hao hụt: | D14: ='2.Hao hut & % chai '!$M$14 -> 0.12 | E14: =E13*$D$14 -> 132 | F14: =$E14*8 -> 1056 | G14: =$E14*12 -> 1584 | H14: =$F14*2 -> 2112 | I14: =$G14*2 -> 3168
B15: 4 | C15: Định mức thành phẩm: | D15: kg/giờ | E15: =E13-E14 -> 968 | F15: =$E15*8 -> 7744 | G15: =$F15*1.5 -> 11616 | H15: =$F15*2 -> 15488 | I15: =$G15*2 -> 23232
B16: 5 | C16: Định mức thành phẩm/người: | D16: kg/giờ/người | E16: =E15/J8 -> 69.142857 | F16: =$E16*8 -> 553.14286 | G16: =$F16*1.5 -> 829.71429 | H16: =$F16*2 -> 1106.2857 | I16: =$G16*2 -> 1659.4286
B18: II - CÔNG SUẤT CHUYỀN LỰA CHAI - AI số 1
B19: STT | C19: Công đoạn sản xuất | D19: Cấp liệu | E19: Phá kiện | F19: Lựa phân loại chai | G19: Tách nhãn | H19: Lựa phân loại chai sau tách nhãn | I19: Ép kiện | J19: Công suất thành phẩm cả chuyền
B20: 1 | C20: Năng suất THIẾT KẾ (Kg NVL đầu vào / giờ) | D20: 1500-2000 | E20: 1500 | F20: 1500 | G20: 1.100-1.500 | H20: 1100 | I20: 1400 | J20: =2000*(100%-$D$14) -> 1760
B21: 2 | C21: Năng suất ĐỊNH MỨC (Kg NVL đầu vào / giờ) | D21: 1800 | E21: =D21 -> 1800 | F21: =E21 -> 1800 | G21: =F21 -> 1800 | H21: =G21 -> 1800 | I21: 1300 | J21: =$E$29 -> 1602
B22: 3 | C22: Định mức nhân công (Số NV / Ca8) | D22: ='Dinh bien_HCNS'!$U$60 -> 2 | F22: ='Dinh bien_HCNS'!$U$61 -> 3 | G22: ='Dinh bien_HCNS'!$U$63 -> 1 | H22: ='Dinh bien_HCNS'!$U$62 -> 3 | I22: ='Dinh bien_HCNS'!$U$64 -> 1 | J22: =SUM(D22:I22) -> 10
C23: Diễn giải
B25: STT | C25: Chỉ tiêu định mức | D25: ĐVT | E25: ĐM 1 giờ | F25: ĐM 1 Ca8 | G25: ĐM 1 Ca12 | H25: ĐM 2 Ca8 | I25: ĐM 2 Ca12
B26: 1 | C26: Tổng nhân sự: | D26: Người | E26: =J22 -> 10 | F26: =$E26 -> 10 | G26: =$F26*1.5 -> 15 | H26: =$F26*2 -> 20 | I26: =$G26*2 -> 30
B27: 2 | C27: Định mức NVL đầu vào: | D27: kg/giờ | E27: =G21 -> 1800 | F27: =$E27*8 -> 14400 | G27: =$F27*1.5 -> 21600 | H27: =$F27*2 -> 28800 | I27: =$G27*2 -> 43200
B28: 3 | C28: Hao hụt: | D28: ='2.Hao hut & % chai '!G8 -> 0.11 | E28: =E27*$D$28 -> 198 | F28: =$E28*8 -> 1584 | G28: =$F28*1.5 -> 2376 | H28: =$F28*2 -> 3168 | I28: =$G28*2 -> 4752
B29: 4 | C29: Định mức thành phẩm: | D29: kg/giờ | E29: =E27-E28 -> 1602 | F29: =$E29*8 -> 12816 | G29: =$F29*1.5 -> 19224 | H29: =$F29*2 -> 25632 | I29: =$G29*2 -> 38448
B30: 5 | C30: Định mức thành phẩm/người: | D30: kg/giờ/người | E30: =E29/J22 -> 160.2 | F30: =$E30*8 -> 1281.6 | G30: =$F30*1.5 -> 1922.4 | H30: =$F30*2 -> 2563.2 | I30: =$G30*2 -> 3844.8
B32: III - CÔNG SUẤT CHUYỀN LỰA CHAI - CHAI ÉP KIỆN - GIALONG
B33: STT | C33: Công đoạn sản xuất | D33: Cấp liệu | E33: Phá kiện | F33: Lựa phân loại chai | G33: Tách nhãn | H33: Lựa phân loại chai sau tách nhãn | I33: Ép kiện | J33: Công suất thành phẩm cả chuyền
B34: 1 | C34: Năng suất THIẾT KẾ (Kg NVL đầu vào / giờ) | D34: 1100 | E34: 1500 | F34: 1500 | G34: 1.100-1.500 | H34: 1100 | I34: 1400 | J34: =1200*(100%-$D$14) -> 1056
B35: 2 | C35: Năng suất ĐỊNH MỨC (Kg NVL đầu vào / giờ) | D35: 1100 | E35: =D35 -> 1100 | F35: =E35 -> 1100 | G35: =F35 -> 1100 | H35: =G35 -> 1100 | I35: 1300 | J35: =$E$43 -> 968
B36: 3 | C36: Định mức nhân công (Số NV / Ca8) | D36: ='Dinh bien_HCNS'!$W$60 -> 1 | F36: ='Dinh bien_HCNS'!$W$61 -> 5 | G36: ='Dinh bien_HCNS'!$W$63 -> 2 | H36: ='Dinh bien_HCNS'!$W$62 -> 5 | I36: ='Dinh bien_HCNS'!$W$64 -> 1 | J36: =SUM(D36:I36) -> 14
C37: Diễn giải
B39: STT | C39: Chỉ tiêu định mức | D39: ĐVT | E39: ĐM 1 giờ | F39: ĐM 1 Ca8 | G39: ĐM 1 Ca12 | H39: ĐM 2 Ca8 | I39: ĐM 2 Ca12
B40: 1 | C40: Tổng nhân sự: | D40: Người | E40: =$J$36 -> 14 | F40: =$E40 -> 14 | G40: =$F40*1.5 -> 21 | H40: =$F40*2 -> 28 | I40: =$G40*2 -> 42
B41: 2 | C41: Định mức NVL đầu vào: | D41: kg/giờ | E41: =$D$35 -> 1100 | F41: =$E41*8 -> 8800 | G41: =$F41*1.5 -> 13200 | H41: =$F41*2 -> 17600 | I41: =$G41*2 -> 26400
B42: 3 | C42: Hao hụt: | D42: ='2.Hao hut & % chai '!$M$14 -> 0.12 | E42: =E41*$D$42 -> 132 | F42: =$E42*8 -> 1056 | G42: =$E42*12 -> 1584 | H42: =$F42*2 -> 2112 | I42: =$G42*2 -> 3168
B43: 4 | C43: Định mức thành phẩm: | D43: kg/giờ | E43: =E41-E42 -> 968 | F43: =$E43*8 -> 7744 | G43: =$F43*1.5 -> 11616 | H43: =$F43*2 -> 15488 | I43: =$G43*2 -> 23232
B44: 5 | C44: Định mức thành phẩm/người: | D44: kg/giờ/người | E44: =E43/J36 -> 69.142857 | F44: =$E44*8 -> 553.14286 | G44: =$F44*1.5 -> 829.71429 | H44: =$F44*2 -> 1106.2857 | I44: =$G44*2 -> 1659.4286
B46: IV - CÔNG SUẤT CHUYỀN LỰA CHAI PET ÉP KIỆN - GIA LONG => Chạy quay đầu chai B6.6; B2.2
B47: STT | C47: Công đoạn sản xuất | D47: Cấp liệu | E47: Phá kiện | F47: Lựa phân loại chai | G47: Tách nhãn | H47: Lựa phân loại chai sau tách nhãn | I47: Ép kiện | J47: Công suất thành phẩm cả chuyền
B48: 1 | C48: Năng suất THIẾT KẾ (Kg NVL đầu vào / giờ) | D48: 1100 | E48: 1500 | F48: 1500 | G48: 1.100-1.500 | H48: 1100 | I48: 1400 | J48: =D48*(100%-$D$14) -> 968
B49: 2 | C49: Năng suất ĐỊNH MỨC (Kg NVL đầu vào / giờ) | D49: 1000 | E49: =D49 -> 1000 | F49: =E49 -> 1000 | G49: =F49 -> 1000 | H49: =G49 -> 1000 | I49: 1300 | J49: =$E$57 -> 885
B50: 3 | C50: Định mức nhân công (Số NV / Ca8) | D50: ='Dinh bien_HCNS'!$Y$60 -> 0 | F50: 2 | G50: 1 | H50: 1 | I50: 1 | J50: =SUM(D50:I50) -> 5
C51: Diễn giải
B53: STT | C53: Chỉ tiêu định mức | D53: ĐVT | E53: ĐM 1 giờ | F53: ĐM 1 Ca8 | G53: ĐM 1 Ca12 | H53: ĐM 2 Ca8 | I53: ĐM 2 Ca12
B54: 1 | C54: Tổng nhân sự: | D54: Người | E54: =J50 -> 5 | F54: =$E54 -> 5 | G54: =$F54*1.5 -> 7.5 | H54: =$F54*2 -> 10 | I54: =$G54*2 -> 15
B55: 2 | C55: Định mức NVL đầu vào: | D55: kg/giờ | E55: =$D$49 -> 1000 | F55: =$E55*8 -> 8000 | G55: =$F55*1.5 -> 12000 | H55: =$F55*2 -> 16000 | I55: =$G55*2 -> 24000
B56: 3 | C56: Hao hụt: | D56: =('2.Hao hut & % chai '!G8+'2.Hao hut & % chai '!G14)/2 -> 0.115 | E56: =E55*$D$56 -> 115 | F56: =$E56*8 -> 920 | G56: =$F56*1.5 -> 1380 | H56: =$F56*2 -> 1840 | I56: =$G56*2 -> 2760
B57: 4 | C57: Định mức thành phẩm: | D57: kg/giờ | E57: =E55-E56 -> 885 | F57: =$E57*8 -> 7080 | G57: =$F57*1.5 -> 10620 | H57: =$F57*2 -> 14160 | I57: =$G57*2 -> 21240
B58: 5 | C58: Định mức thành phẩm/người: | D58: kg/giờ/người | E58: =E57/J50 -> 177 | F58: =$E58*8 -> 1416 | G58: =$F58*1.5 -> 2124 | H58: =$F58*2 -> 2832 | I58: =$G58*2 -> 4248
B60: V - CÔNG SUẤT MÁY PHÂN LOẠI CHAI PET VÀ NĂNG SUẤT LAO ĐỘNG MỤC TIÊU
B61: STT | C61: Nội dung | D61: Đơn vị tính | E61: Định mức | F61: T1 | G61: T2 | H61: T3 | I61: T4 | J61: T5 | K61: T6 | L61: T7 | M61: T8 | N61: T9 | O61: T10 | P61: T11 | Q61: T12 | R61: KHKD 2026
B62: 1 | C62: =B4 -> I - CÔNG SUẤT CHUYỀN LỰA CHAI - CHAI ÉP KIỆN - PLENMA | F62: =E62 -> 0 | G62: =F62 -> 0 | H62: =G62 -> 0 | I62: =H62 -> 0
B63: a | C63: Số nhân sự/ chuyền/ ca | D63: Người | E63: =E12 -> 14 | F63: =E63 -> 14 | G63: =F63 -> 14 | H63: =G63 -> 14 | I63: =H63 -> 14 | J63: =E63 -> 14 | K63: =J63 -> 14 | L63: =K63 -> 14 | M63: =L63 -> 14 | N63: =M63 -> 14 | O63: =N63 -> 14 | P63: =O63 -> 14 | Q63: =P63 -> 14
B64: b | C64: Công suất/ chuyền | D64: kg/giờ | E64: =E15 -> 968 | F64: =E64 -> 968 | G64: =F64 -> 968 | H64: =G64 -> 968 | I64: =H64 -> 968 | J64: =E64 -> 968 | K64: =J64 -> 968 | L64: =K64 -> 968 | M64: =L64 -> 968 | N64: =M64 -> 968 | O64: =N64 -> 968 | P64: =O64 -> 968 | Q64: =P64 -> 968
B65: c | C65: Năng suất lao động | D65: kg/giờ/người | E65: =E64/E63 -> 69.142857 | F65: =E65 -> 69.142857 | G65: =F65 -> 69.142857 | H65: =G65 -> 69.142857 | I65: =H65 -> 69.142857 | J65: =J64/J63 -> 69.142857 | K65: =K64/K63 -> 69.142857 | L65: =L64/L63 -> 69.142857 | M65: =M64/M63 -> 69.142857 | N65: =N64/N63 -> 69.142857 | O65: =O64/O63 -> 69.142857 | P65: =P64/P63 -> 69.142857 | Q65: =Q64/Q63 -> 69.142857
B66: 2 | C66: =B18 -> II - CÔNG SUẤT CHUYỀN LỰA CHAI - AI số 1 | E66: =D66 -> 0 | F66: =E66 -> 0 | G66: =F66 -> 0 | H66: =G66 -> 0 | I66: =H66 -> 0
B67: a | C67: Số nhân sự/ chuyền/ ca | D67: Người | E67: =E26 -> 10 | F67: =E67 -> 10 | G67: =F67 -> 10 | H67: =G67 -> 10 | I67: =H67 -> 10 | J67: =E67 -> 10 | K67: =J67 -> 10 | L67: =K67 -> 10 | M67: =L67 -> 10 | N67: =M67 -> 10 | O67: =N67 -> 10 | P67: =O67 -> 10 | Q67: =P67 -> 10
B68: b | C68: Công suất/chuyền (kg thành phẩm/ giờ) | D68: kg/giờ | E68: =E29 -> 1602 | F68: =E68 -> 1602 | G68: =F68 -> 1602 | H68: =G68 -> 1602 | I68: =H68 -> 1602 | J68: =E68 -> 1602 | K68: =J68 -> 1602 | L68: =K68 -> 1602 | M68: =L68 -> 1602 | N68: =M68 -> 1602 | O68: =N68 -> 1602 | P68: =O68 -> 1602 | Q68: =P68 -> 1602
B69: c | C69: Năng suất lao động (kg thành phẩm/ người/ giờ): | D69: kg/giờ/người | E69: =E68/E67 -> 160.2 | F69: =E69 -> 160.2 | G69: =F69 -> 160.2 | H69: =G69 -> 160.2 | I69: =H69 -> 160.2 | J69: =J68/J67 -> 160.2 | K69: =K68/K67 -> 160.2 | L69: =L68/L67 -> 160.2 | M69: =M68/M67 -> 160.2 | N69: =N68/N67 -> 160.2 | O69: =O68/O67 -> 160.2 | P69: =P68/P67 -> 160.2 | Q69: =Q68/Q67 -> 160.2
B70: 3 | C70: =B32 -> III - CÔNG SUẤT CHUYỀN LỰA CHAI - CHAI ÉP KIỆN - GIALONG | E70: =D70 -> 0 | F70: =E70 -> 0 | G70: =F70 -> 0 | H70: =G70 -> 0 | I70: =H70 -> 0
B71: a | C71: Số nhân sự/ chuyền/ ca | D71: Người | E71: =E40 -> 14 | F71: =E71 -> 14 | G71: =F71 -> 14 | H71: =G71 -> 14 | I71: =H71 -> 14 | J71: =E71 -> 14 | K71: =J71 -> 14 | L71: =K71 -> 14 | M71: =L71 -> 14 | N71: =M71 -> 14 | O71: =N71 -> 14 | P71: =O71 -> 14 | Q71: =P71 -> 14
B72: b | C72: Công suất/chuyền (kg thành phẩm/ giờ) | D72: kg/giờ | E72: =E43 -> 968 | F72: =E72 -> 968 | G72: =F72 -> 968 | H72: =G72 -> 968 | I72: =H72 -> 968 | J72: =E72 -> 968 | K72: =J72 -> 968 | L72: =K72 -> 968 | M72: =L72 -> 968 | N72: =M72 -> 968 | O72: =N72 -> 968 | P72: =O72 -> 968 | Q72: =P72 -> 968
B73: c | C73: Năng suất lao động (kg thành phẩm/ người/ giờ): | D73: kg/giờ/người | E73: =E72/E71 -> 69.142857 | F73: =E73 -> 69.142857 | G73: =F73 -> 69.142857 | H73: =G73 -> 69.142857 | I73: =H73 -> 69.142857 | J73: =J72/J71 -> 69.142857 | K73: =K72/K71 -> 69.142857 | L73: =L72/L71 -> 69.142857 | M73: =M72/M71 -> 69.142857 | N73: =N72/N71 -> 69.142857 | O73: =O72/O71 -> 69.142857 | P73: =P72/P71 -> 69.142857 | Q73: =Q72/Q71 -> 69.142857
B74: 4 | C74: =B46 -> IV - CÔNG SUẤT CHUYỀN LỰA CHAI PET ÉP KIỆN - GIA LONG => Chạy quay đầu chai B6.6; B2.2 | F74: =E74 -> 0 | G74: =F74 -> 0 | H74: =G74 -> 0 | I74: =H74 -> 0
B75: a | C75: Số nhân sự/ chuyền/ ca | D75: Người | E75: =E54 -> 5 | F75: =E75 -> 5 | G75: =F75 -> 5 | H75: =G75 -> 5 | I75: =H75 -> 5 | J75: =E75 -> 5 | K75: =J75 -> 5 | L75: =K75 -> 5 | M75: =L75 -> 5 | N75: =M75 -> 5 | O75: =N75 -> 5 | P75: =O75 -> 5 | Q75: =P75 -> 5
B76: b | C76: Công suất/chuyền (kg thành phẩm/ giờ) | D76: kg/giờ | E76: =E57 -> 885 | F76: =E76 -> 885 | G76: =F76 -> 885 | H76: =G76 -> 885 | I76: =H76 -> 885 | J76: =E76 -> 885 | K76: =J76 -> 885 | L76: =K76 -> 885 | M76: =L76 -> 885 | N76: =M76 -> 885 | O76: =N76 -> 885 | P76: =O76 -> 885 | Q76: =P76 -> 885
B77: c | C77: Năng suất lao động (kg thành phẩm/ người/ giờ): | D77: kg/giờ/người | E77: =E76/E75 -> 177 | F77: =E77 -> 177 | G77: =F77 -> 177 | H77: =G77 -> 177 | I77: =H77 -> 177 | J77: =J76/J75 -> 177 | K77: =K76/K75 -> 177 | L77: =L76/L75 -> 177 | M77: =M76/M75 -> 177 | N77: =N76/N75 -> 177 | O77: =O76/O75 -> 177 | P77: =P76/P75 -> 177 | Q77: =Q76/Q75 -> 177
B79: VI - TỔNG CÔNG SUẤT MÁY PHÂN LOẠI CHAI PET và NĂNG SUẤT LĐ | E79: 30 | F79: 30 | G79: 22 | H79: 31 | I79: 29 | J79: 30 | K79: 30 | L79: 31 | M79: 31 | N79: 28 | O79: 31 | P79: 30 | Q79: 31
B80: i | C80: Tổng công suất HT máy phân loại chai PET/giờ | D80: kg/giờ | E80: Định mức | F80: T1 | G80: T2 | H80: T3 | I80: T4 | J80: T5 | K80: T6 | L80: T7 | M80: T8 | N80: T9 | O80: T10 | P80: T11 | Q80: T12 | R80: KHKD 2026
B81: 1 | C81: Công suất máy - Tính trên NVL đầu vào | D81: Tấn/giờ | E81: =$E$27+$E$41 -> 2900 | F81: =$E$13+$E$41 -> 2200 | G81: =$E$13+$E$41 -> 2200 | H81: =$E$13+$E$27 -> 2900 | I81: =$E$13+$E$27 -> 2900 | J81: =$E$13+$E$27 -> 2900 | K81: =$E$13+$E$27 -> 2900 | L81: =$E$13+$E$27 -> 2900 | M81: =$E$13+$E$27 -> 2900 | N81: =$E$13+$E$27 -> 2900 | O81: =$E$13+$E$27 -> 2900 | ... Q81: =$E$13+$E$27 -> 2900 | R81: =Q81 -> 2900
B82: 2 | C82: Công suất máy - Tính trên Thành phẩm SX | D82: Tấn/giờ | E82: =$E$29+$E$43 -> 2570 | F82: =$E$15+$E$43 -> 1936 | G82: =$E$15+$E$43 -> 1936 | H82: =$E$15+$E$29 -> 2570 | I82: =$E$15+$E$29 -> 2570 | J82: =$E$15+$E$29 -> 2570 | K82: =$E$15+$E$29 -> 2570 | L82: =$E$15+$E$29 -> 2570 | M82: =$E$15+$E$29 -> 2570 | N82: =$E$15+$E$29 -> 2570 | O82: =$E$15+$E$29 -> 2570 | ... Q82: =$E$15+$E$29 -> 2570 | R82: =Q82 -> 2570
B83: ii | C83: Tổng công suất HT máy phân loại chai PET/tháng (8hx3caxsố ngày của tháng) | D83: kg/tháng | E83: Định mức | F83: T1 | G83: T2 | H83: T3 | I83: T4 | J83: T5 | K83: T6 | L83: T7 | M83: T8 | N83: T9 | O83: T10 | P83: T11 | Q83: T12 | R83: KHKD 2026
B84: 1 | C84: Công suất máy - Tính trên NVL đầu vào | D84: Tấn/tháng | E84: =Q84 -> 2157600 | F84: =F81*8*3*F79 -> 1584000 | G84: =G81*8*3*G79 -> 1161600 | H84: =H81*8*3*H79 -> 2157600 | I84: =I81*8*3*I79 -> 2018400 | J84: =J81*8*3*J79 -> 2088000 | K84: =K81*8*3*K79 -> 2088000 | L84: =L81*8*3*L79 -> 2157600 | M84: =M81*8*3*M79 -> 2157600 | ... Q84: =Q81*8*3*Q79 -> 2157600 | R84: =SUM(F84:Q84) -> 23764800
B85: 2 | C85: Công suất máy - Tính trên Thành phẩm SX | D85: Tấn/tháng | E85: =Q85 -> 1912080 | F85: =F82*8*3*F79 -> 1393920 | G85: =G82*8*3*G79 -> 1022208 | H85: =H82*8*3*H79 -> 1912080 | I85: =I82*8*3*I79 -> 1788720 | J85: =J82*8*3*J79 -> 1850400 | K85: =K82*8*3*K79 -> 1850400 | L85: =L82*8*3*L79 -> 1912080 | M85: =M82*8*3*M79 -> 1912080 | ... Q85: =Q82*8*3*Q79 -> 1912080 | R85: =SUM(F85:Q85) -> 21043488
B86: iii | C86: Năng suất lao động (CNTT) | E86: Định mức | F86: T1 | G86: T2 | H86: T3 | I86: T4 | J86: T5 | K86: T6 | L86: T7 | M86: T8 | N86: T9 | O86: T10 | P86: T11 | Q86: T12 | R86: KHKD 2026
B87: 1 | C87: Năng suất lao động - Tấn/người/ngày | D87: Tấn/người/ngày | E87: =Q87 -> 1063.4483 | F87: =F88/F$79 -> 801.10345 | G87: =G88/G$79 -> 801.10345 | H87: =H88/H$79 -> 1063.4483 | I87: =I88/I$79 -> 1063.4483 | J87: =J88/J$79 -> 1063.4483 | K87: =K88/K$79 -> 1063.4483 | L87: =L88/L$79 -> 1063.4483 | M87: =M88/M$79 -> 1063.4483 | ... Q87: =Q88/Q$79 -> 1063.4483
B88: 2 | C88: Năng suất lao động - Tấn/người/tháng | D88: Tấn/người/tháng | E88: =Q88 -> 32966.897 | F88: =F85/(F$63+F$67+F$75)/2 -> 24033.103 | G88: =G85/(G$63+G$67+G$75)/2 -> 17624.276 | H88: =H85/(H$63+H$67+H$75)/2 -> 32966.897 | I88: =I85/(I$63+I$67+I$75)/2 -> 30840 | J88: =J85/(J$63+J$67+J$75)/2 -> 31903.448 | K88: =K85/(K$63+K$67+K$75)/2 -> 31903.448 | L88: =L85/(L$63+L$67+L$75)/2 -> 32966.897 | M88: =M85/(M$63+M$67+M$75)/2 -> 32966.897 | ... Q88: =Q85/(Q$63+Q$67+Q$75)/2 -> 32966.897
B90: VII. Hiệu suất máy - CĐ phân loại chai PET (8h x 3ca x số ngày của tháng)
B91: STT | C91: Loại chai nguyên liệu | D91: ĐVT | E91: Thực tế năm 2024 | F91: KQKD 2025 | G91: T1 | H91: T2 | I91: T3 | J91: T4 | K91: T5 | L91: T6 | M91: T7 | N91: T8 | O91: T9 | P91: T10 | Q91: T11 | R91: T12 | S91: KHKD 2026
B92: i | C92: Hiệu suất máy - Tính trên NVL đầu vào | D92: % | E92: =E93/E94 -> 0.32253086 | F92: =F93/F94 -> 0.46296057 | G92: =G93/G94 -> 0.49242424 | H92: =H93/H94 -> 0.38739669 | I92: =I93/I94 -> 0.48201706 | J92: =J93/J94 -> 0.61930242 | K92: =K93/K94 -> 0.598659 | L92: =L93/L94 -> 0.62260536 | ... S92: =S93/S94 -> 0.5836363
B93: 1 | C93: Thực tế: Tổng sản lượng chai mua vào | D93: Tấn/ Tháng | E93: 4180 | F93: ='1.NVL Chai'!F16 -> 6199968 | G93: ='1.NVL Chai'!G16 -> 780000 | H93: ='1.NVL Chai'!H16 -> 450000 | I93: ='1.NVL Chai'!I16 -> 1040000 | J93: ='1.NVL Chai'!J16 -> 1250000 | K93: ='1.NVL Chai'!K16 -> 1250000 | L93: ='1.NVL Chai'!L16 -> 1300000 | M93: ='1.NVL Chai'!M16 -> 1350000 | ... R93: ='1.NVL Chai'!R16 -> 1350000 | S93: =SUM(G93:R93) -> 13870000
B94: 2 | C94: Định mức: Tổng công suất máy (NVL) | D94: Tấn/ Tháng | E94: 12960 | F94: =1800*24*310 -> 13392000 | G94: ='Cong suat'!F$84 -> 1584000 | H94: ='Cong suat'!G$84 -> 1161600 | I94: ='Cong suat'!H$84 -> 2157600 | J94: ='Cong suat'!I$84 -> 2018400 | K94: ='Cong suat'!J$84 -> 2088000 | L94: ='Cong suat'!K$84 -> 2088000 | M94: ='Cong suat'!L$84 -> 2157600 | N94: ='Cong suat'!M$84 -> 2157600 | ... R94: ='Cong suat'!Q$84 -> 2157600 | S94: =SUM(G94:R94) -> 23764800
B95: ii | C95: Hiệu suất máy - Tính trên Thành phẩm SX | D95: % | E95: =E96/E97 -> 0.32253086 | F95: =F96/F97 -> 0 | G95: =G96/G97 -> 0.49466253 | H95: =H96/H97 -> 0.38915759 | I95: =I96/I97 -> 0.48054475 | J95: =J96/J97 -> 0.61741077 | K95: =K96/K97 -> 0.59683042 | L95: =L96/L97 -> 0.62070363 | ... S95: =S96/S97 -> 0.58235403
B96: 1 | C96: Thực tế: Tổng sản lượng Thành phẩm SX | D96: Tấn/ Tháng | E96: =E93*90% -> 3762 | F96: =CPSX!AK2 -> 0 | G96: ='3.Thanh pham'!G78 -> 689520 | H96: ='3.Thanh pham'!H78 -> 397800 | I96: ='3.Thanh pham'!I78 -> 918840 | J96: ='3.Thanh pham'!J78 -> 1104375 | K96: ='3.Thanh pham'!K78 -> 1104375 | L96: ='3.Thanh pham'!L78 -> 1148550 | M96: ='3.Thanh pham'!M78 -> 1192725 | N96: ='3.Thanh pham'!N78 -> 1148550 | ... R96: ='3.Thanh pham'!R78 -> 1192725 | S96: =SUM(G96:R96) -> 12254760
B97: 2 | C97: Định mức: Tổng công suất máy (thành phẩm) | D97: Tấn/ Tháng | E97: =E94*90% -> 11664 | F97: =(1800*88%)*24*310 -> 11784960 | G97: ='Cong suat'!F$85 -> 1393920 | H97: ='Cong suat'!G$85 -> 1022208 | I97: ='Cong suat'!H$85 -> 1912080 | J97: ='Cong suat'!I$85 -> 1788720 | K97: ='Cong suat'!J$85 -> 1850400 | L97: ='Cong suat'!K$85 -> 1850400 | M97: ='Cong suat'!L$85 -> 1912080 | N97: ='Cong suat'!M$85 -> 1912080 | ... R97: ='Cong suat'!Q$85 -> 1912080 | S97: =SUM(G97:R97) -> 21043488
B99: VII - CÔNG SUẤT CHUYỀN BĂM VẢY PET
B100: STT | C100: Công đoạn sản xuất | D100: Cấp liệu | E100: XXX | F100: Phân loại trước băm | G100: Băm vảy | H100: Lựa phân loại chai sau tách nhãn | I100: Đóng gói | J100: Xử lý phó sản | K100: Công suất thành phẩm cả chuyền
B101: 1 | C101: Năng suất THIẾT KẾ (Kg NVL đầu vào / giờ) | D101: 2000 | F101: 1500 | G101: 1.100-1.500 | K101: =D101*(100%-$D$109) -> 1852.1836
B102: 2 | C102: Năng suất ĐỊNH MỨC (Kg NVL đầu vào / giờ) | D102: 1800 | E102: =D102 -> 1800 | F102: =E102 -> 1800 | G102: =F102 -> 1800 | H102: =G102 -> 1800 | I102: =D102*93% -> 1674 | K102: =D102*(100%-$D$109) -> 1666.9652
B103: 3 | C103: Định mức nhân công (Số NV / Ca8) | D103: ='Dinh bien_HCNS'!$AC$66 -> 1 | F103: ='Dinh bien_HCNS'!$AC$67 -> 1 | I103: ='Dinh bien_HCNS'!$AC$68 -> 1 | K103: =SUM(D103:J103) -> 3
C104: Diễn giải
B106: STT | C106: Chỉ tiêu định mức | D106: ĐVT | E106: ĐM 1 giờ | F106: ĐM 1 Ca 8h/ngày | G106: ĐM 1 Ca 12h/ngày | H106: ĐM 2 Ca 16h/ngày | I106: ĐM 2 Ca 24h/ngày
B107: 1 | C107: Tổng nhân sự: | D107: Người | E107: =K103 -> 3 | F107: =$E107 -> 3 | G107: =$F107*1.5 -> 4.5 | H107: =$F107*2 -> 6 | I107: =$G107*2 -> 9
B108: 2 | C108: Định mức NVL đầu vào: | D108: Kg | E108: =D102 -> 1800 | F108: =$E108*8 -> 14400 | G108: =$F108*1.5 -> 21600 | H108: =$F108*2 -> 28800 | I108: =$G108*2 -> 43200
B109: 3 | C109: Hao hụt: | D109: ='2.Hao hut & % chai '!$S$145 -> 0.073908214 | E109: =E108*$D$109 -> 133.03479 | F109: =$E109*8 -> 1064.2783 | G109: =$F109*1.5 -> 1596.4174 | H109: =$F109*2 -> 2128.5566 | I109: =$G109*2 -> 3192.8348
B110: 4 | C110: Định mức thành phẩm: | D110: Kg | E110: =E108-E109 -> 1666.9652 | F110: =$E110*8 -> 13335.722 | G110: =$F110*1.5 -> 20003.583 | H110: =$F110*2 -> 26671.443 | I110: =$G110*2 -> 40007.165
B111: 5 | C111: Định mức thành phẩm/người: | D111: kg/người | E111: =E110/E107 -> 555.65507 | F111: =$E111*8 -> 4445.2406 | G111: =$F111*1.5 -> 6667.8609 | H111: =$F111*2 -> 8890.4811 | I111: =$G111*2 -> 13335.722
B114: STT | C114: Loại chai nguyên liệu | D114: ĐVT | E114: T1 | F114: T2 | G114: T3 | H114: T4 | I114: T5 | J114: T6 | K114: T7 | L114: T8 | M114: T9 | N114: T10 | O114: T11 | P114: T12 | Q114: KHKD 2026
B115: i | C115: Hiệu suất máy - Tính trên NVL đầu vào | D115: % | E115: =E116/E117 -> 0 | F115: =F116/F117 -> 0 | G115: =G116/G117 -> 0 | H115: =H116/H117 -> 0.97524402 | I115: =I116/I117 -> 0.94273589 | J115: =J116/J117 -> 0.98044533 | K115: =K116/K117 -> 0.98531106 | L115: =L116/L117 -> 0.94881806 | ... Q115: =Q116/Q117 -> 0.96847849
B116: 1 | C116: Thực tế: Tổng SL chai PET đưa vào băm vảy PET | D116: Tấn/ Tháng | E116: ='3.Thanh pham'!G$117 -> 0 | F116: ='3.Thanh pham'!H$117 -> 0 | G116: ='3.Thanh pham'!I$117 -> 0 | H116: ='3.Thanh pham'!J$117 -> 1069062.5 | I116: ='3.Thanh pham'!K$117 -> 1069062.5 | J116: ='3.Thanh pham'!L$117 -> 1111825 | K116: ='3.Thanh pham'!M$117 -> 1154587.5 | L116: ='3.Thanh pham'!N$117 -> 1111825 | ... Q116: ='3.Thanh pham'!S$117 -> 9920900
...

Sheet Dinh muc
B3: ĐỊNH MỨC CHI PHÍ
B4: I - ĐỊNH MỨC TIÊU HAO VẬT TƯ - PHÂN LOẠI CHAI PET
B5: STT | C5: Mục phí | D5: ĐVT | E5: Định mức | F5: Đơn giá | G5: Chi phí/1kg thành phẩm | H5: Diễn giải | K5: =87*80% -> 69.6
C6: Công suất lựa chai | E6: ='Cong suat'!$H$82 -> 2570 | H6: Thành phẩm chai PET sau phân loại, tách nhãn
B7: 1 | C7: Chi phí nhân công trực tiếp (giờ công lao động)
B8: a | C8: LĐ định biên | D8: Giờ công/ca 8
B9: b | C9: LĐ thời vụ | D9: Giờ công/ca 8 | J9: Chuyền AI số 1
B10: 1 | C10: Điện sản xuất | D10: Kw/1 chuyền/1kg thành phẩm | E10: =K16+K17+K16 -> 201.9 | F10: 2300 | G10: =E10*F10/'Cong suat'!F$82 -> 239.86054 | J10: Tên MMTB sử dụng điện | K10: Số điện sử dụng kwh/ giờ
B11: 2 | C11: Điện sản xuất | D11: Kw/1 chuyền/1kg thành phẩm | E11: =$K$18 -> 276.25 | F11: 2300 | G11: =E11*F11/$E$6 -> 247.22763 | J11: Máy nén khí phân loại 80% | K11: =90*80% -> 72
B12: 3 | C12: Dao tách nhãn chai PET | D12: Bộ | E12: =1/1500000*(('Cong suat'!$E$81)/2) -> 0.00096666667 | F12: 165000000 | G12: =E12*F12/$E$6 -> 62.062257 | H12: Công suất thiết kế: 1500 tấn chai PET-B0 | J12: Tách nhãn BRT | K12: 57
B13: 4 | C13: Dây đai | E13: 0.35 | F13: 51000 | G13: =E13*F13/230 -> 77.608696 | J13: Hệ thống máy Sort + TB phụ | K13: 85
B14: 5 | C14: Bao jumbo | E14: =200/3000 -> 0.066666667 | F14: 75000 | G14: =E14*F14/$E$6 -> 1.9455253 | H14: 1 bao để được 30kg NV | J14: Định mức thiết kế HT AI | K14: =SUM(K11:K13) -> 214
B15: 6 | C15: Hóa chất | J15: Chuyền AI số 1 (thực hiện 70%) | K15: =K14*70% -> 149.8
B16: 7 | C16: Chi phí xử lý nhãn chai PET | D16: Kg | E16: 1 | F16: 300 | G16: =(('Cong suat'!$E$28+'Cong suat'!$E$14)*50%)*F16/$E$6 -> 19.2607 | H16: NCC Á Châu - TGĐ duyệt CP xử lý nhãn ở mức 300d/kg | J16: Chuyền PL TN | K16: =((87*80%)+31)*75% -> 75.45
B17: 8 | C17: Dầu xe nâng | D17: Lít/giờ hoạt động | E17: 3.2 | F17: 22000 | G17: =E17*F17/$E$6 -> 27.392996 | H17: Định mức: 1 xe nâng sử dụng 3,2 lít dầu / giờ hoạt động | J17: Chuyền rework | K17: =31+20 -> 51
B18: 9 | C18: Chi phí vận chuyển | D18: Chuyến/8 tấn | E18: 1 | F18: 3200000 | G18: =F18/8000 -> 400 | J18: Tổng | K18: =K15+K16+K17 -> 276.25
B20: II - ĐỊNH MỨC TIÊU HAO VẬT TƯ - BĂM VẢY PET GIAI ĐOẠN 1 - BĂM THÔ
B21: STT | C21: Mục phí | D21: ĐVT | E21: ĐM 1 giờ | F21: Đơn giá | G21: Chi phí/1kg thành phẩm | H21: Diễn giải
C22: Công suất băm PET | E22: ='Cong suat'!$E$110 -> 1666.9652
B23: 1 | C23: Chi phí nhân công trực tiếp
B24: a | C24: LĐ định biên | D24: Giờ công/ca 8
B25: b | C25: LĐ thời vụ | D25: Giờ công/ca 8
B26: c | C26: Tiền ăn giữa Ca | D26: Đồng/người | J26: =C27 -> Điện sản xuất | O26: =C28 -> Dao băm vảy PET | X26: =$C$32 -> Chi phí xử lý nước thải, môi trường | Y26: Tìm phương án xử lý tối ưu
B27: 2 | C27: Điện sản xuất | D27: Kw/1chuyền/1giờ hoạt động | E27: =$K$33 -> 197.16 | F27: =$F$11 -> 2300 | G27: =E27*F27/$E$22 -> 272.03207 | H27: Máy chính: 255kwh/giờ - Máy phụ: 90kwh/giờ | J27: Tên MMTB sử dụng điện | K27: Số điện sử dụng kwh/ giờ | O27: Nội dung | P27: Đơn vị tính | Q27: Số lượng | R27: Đơn giá | S27: Sản lượng SX / 1 lưỡi dao (Tấn/1 lưỡi dao) | T27: Sản lượng SX / 1 bộ dao (Tấn/1 bộ dao) | U27: Tổng CP | V27: Đồng/kg | X27: Nội dung | Y27: Đơn vị tính | Z27: Số lượng | AA27: Đơn giá | AB27: Đồng/kg
B28: 3 | C28: Dao băm vảy PET | F28: =U33 -> 72336000 | G28: =$V$33 -> 104.4295 | H28: Công suất thiết kế: 150 tấn | J28: Máy nén khí phân loại 20% | K28: =90*20% -> 18 | O28: Dao băm động - chiều dài 60cm | P28: Cái | Q28: 14 | R28: 2400000 | S28: 46 | T28: =Q28*S28 -> 644 | U28: =Q28*R28 -> 33600000 | V28: =(Q28*R28)/T28/1000 -> 52.173913 | X28: Nước thủy cục | Y28: lít/giờ | Z28: 3000 | AA28: =12000/1000 -> 12 | AB28: =(Z28*AA28)/$E$22 -> 21.596132
B29: 4 | C29: Dây đai | J29: Hệ thống băm thô | K29: 255 | O29: Dao băm tĩnh - chiều dài 120cm | P29: Cái | Q29: 6 | R29: 6000000 | S29: 324 | T29: =Q29*S29 -> 1944 | U29: =Q29*R29 -> 36000000 | V29: =(Q29*R29)/T29/1000 -> 18.518519 | X29: Vận chuyển nước thải (50/50) | Y29: lít/giờ | Z29: =Z28*50% -> 1500 | AA29: 500 | AB29: =(Z29*AA29)/$E$22 -> 449.91941
B30: 5 | C30: Bao jumbo | E30: 1 | F30: 150000 | G30: =E30*F30/450/2 -> 166.66667 | H30: 1 cái bao đựng được 450kg vảy PET băm thô => quay đầu 2 lần/tháng | J30: Thiết bị phụ trợ: Bơm nước, HT li tâm | K30: 20 | O30: Bu long M20x110 | P30: Con | Q30: 28 | R30: 23000 | T30: =2*T28 -> 1288 | U30: =Q30*R30 -> 644000 | V30: =(Q30*R30)/T30/1000 -> 0.5
B31: 6 | C31: Hóa chất | J31: Máy phá kiện | K31: 25 | O31: Bu long M20x70 | P31: Con | Q31: 28 | R31: 25000 | T31: 1288 | U31: =Q31*R31 -> 700000 | V31: =(Q31*R31)/T31/1000 -> 0.54347826
B32: 7 | C32: Chi phí xử lý nước thải, môi trường | D32: m3/h | G32: =$AB$33 -> 471.51554 | H32: PA1: Vận chuyển DTR xử lý: 500 đ/lit nước thải PA2: CTy Dịch vụ xử lý: 1.500 đ/lit nước thải | J32: Định mức thiết kế | K32: =SUM(K28:K31) -> 318 | O32: Đá mài dao | P32: Viên | Q32: 3 | R32: 464000 | T32: =(Q28*Q32)+(Q29*3) -> 60 | U32: =Q32*R32 -> 1392000 | V32: =(Q32*R32)/T32/1000 -> 23.2
B33: 8 | C33: Dầu xe nâng | E33: 3.2 | F33: 19000 | G33: =E33*F33/$E$22 -> 36.473467 | H33: Định mức: 1 xe nâng sử dụng 3,2 lít dầu / giờ hoạt động | J33: Thực hiện 62% | K33: =K32*62% -> 197.16 | O33: Tổng cộng | U33: =SUM(U28:U32) -> 72336000 | V33: =SUM(V28:V32)*110% -> 104.4295 | X33: Tổng cộng | AB33: =SUM(AB28:AB32) -> 471.51554
B34: 9 | C34: Chi phí vận chuyển | D34: Chuyến | E34: 10000 | F34: 3200000 | G34: =F34/E34 -> 320
B36: III - ĐỊNH MỨC TIÊU HAO VẬT TƯ - BĂM VẢY PET GIAI ĐOẠN 2 - RỬA NƯỚC
B37: STT | C37: Mục phí | D37: ĐVT | E37: Định mức | F37: Đơn giá | G37: Chi phí/1kg thành phẩm | H37: Diễn giải
C38: Công suất băm HD
B39: 1 | C39: Chi phí nhân công trực tiếp
B40: a | C40: LĐ định biên
B41: b | C41: LĐ thời vụ
B42: c | C42: Tiền ăn giữa Ca
B43: 2 | C43: Điện sản xuất
B44: 3 | C44: Dao băm vảy HD
B45: 4 | C45: Dây đai
B46: 5 | C46: Bao jumbo
B47: 6 | C47: Hóa chất
B48: 7 | C48: Chi phí xử lý nước thải, môi trường
B49: 8 | C49: Dầu xe nâng
B50: 9 | C50: Chi phí vận chuyển
H54: Ngày …
C55: Duyệt | D55: Xem xét | E55: Xem xét | G55: Xem xét | H55: Người lập
C56: GĐĐH DTR | D56: GĐTC DTR | E56: GĐ các trạm | G56: Trưởng Trạm | H56: Kế toán trưởng

Sheet Dinh bien_HCNS
B1: #VALUE!
B3: I - ĐINH BIÊN NHÂN SỰ - PET | D3: SLSX | E3: 6192451 | F3: ='1.NVL Chai'!G16 -> 780000 | G3: ='1.NVL Chai'!H16 -> 450000 | H3: ='1.NVL Chai'!I16 -> 1040000 | I3: ='1.NVL Chai'!J16 -> 1250000 | J3: ='1.NVL Chai'!K16 -> 1250000 | K3: ='1.NVL Chai'!L16 -> 1300000 | L3: ='1.NVL Chai'!M16 -> 1350000 | M3: ='1.NVL Chai'!N16 -> 1300000 | ... R3: ='1.NVL Chai'!S16 -> 13870000
F4: C1: Ca 8h+8h C2: Ca 8h+8h | G4: C1: Ca 8h+8h C2: Ca 8h+8h | H4: C1: Ca 8h+8h+2h C2: Ca 8h+8h C3: Ca 8h+8h | I4: C1: Ca 8h+8h+2h C2: Ca 8h+8h C3: Ca 8h+8h | J4: C1: Ca 8h+8h+2h C2: Ca 8h+8h C3: Ca 8h+8h | K4: C1: Ca 8h+8h+2h C2: Ca 8h+8h C3: Ca 8h+8h | L4: C1: Ca 8h+8h+2h C2: Ca 8h+8h C3: Ca 8h+8h | M4: C1: Ca 8h+8h+2h C2: Ca 8h+8h C3: Ca 8h+8h | N4: C1: Ca 8h+8h+2h C2: Ca 8h+8h C3: Ca 8h+8h | O4: C1: Ca 8h+8h+2h C2: Ca 8h+8h C3: Ca 8h+8h | P4: C1: Ca 8h+8h+2h C2: Ca 8h+8h C3: Ca 8h+8h | Q4: C1: Ca 8h+8h+2h C2: Ca 8h+8h C3: Ca 8h+8h
B5: STT | C5: Phòng ban | D5: Tài khoản | E5: KQKD 2025 | F5: T1 | G5: T2 | H5: T3 | I5: T4 | J5: T5 | K5: T6 | L5: T7 | M5: T8 | N5: T9 | O5: T10 | P5: T11 | Q5: T12 | R5: Mục tiêu 2026
B6: 1 | C6: Ban giám đốc | D6: 642 | E6: =E7+E8 -> 1 | F6: =F7+F8 -> 1 | G6: =G7+G8 -> 1 | H6: =H7+H8 -> 1 | I6: =I7+I8 -> 1 | J6: =J7+J8 -> 1 | K6: =K7+K8 -> 1 | L6: =L7+L8 -> 1 | ... R6: =R7+R8 -> 1
B7: 1.1 | C7: Giám đốc Trạm | R7: =Q7 -> 0
B8: 1.2 | C8: Trưởng trạm thu mua | E8: 1 | F8: 1 | G8: 1 | H8: 1 | I8: 1 | J8: 1 | K8: 1 | L8: 1 | M8: 1 | N8: 1 | O8: 1 | P8: 1 | Q8: 1 | R8: =Q8 -> 1
B9: 2 | C9: Phòng Hành chánh nhân sự | D9: 642 | E9: =SUM(E10:E16) -> 2 | F9: =SUM(F10:F16) -> 3 | G9: =SUM(G10:G16) -> 3 | H9: =SUM(H10:H16) -> 3 | I9: =SUM(I10:I16) -> 3 | J9: =SUM(J10:J16) -> 3 | K9: =SUM(K10:K16) -> 3 | L9: =SUM(L10:L16) -> 3 | ... R9: =SUM(R10:R16) -> 3
B10: 2.1 | C10: Trưởng phòng nhân sự | R10: =Q10 -> 0
B11: 2.1 | C11: Nhân viên hành chính | R11: =Q11 -> 0
B12: 2.2 | C12: Nhân viên nhân sự | E12: 1 | F12: 1 | G12: 1 | H12: 1 | I12: 1 | J12: 1 | K12: 1 | L12: 1 | M12: 1 | N12: 1 | O12: 1 | P12: 1 | Q12: 1 | R12: =Q12 -> 1
B13: 2.3 | C13: Tuyển dụng | R13: =Q13 -> 0
B14: 2.4 | C14: Nhân viên tạp vụ | E14: 1 | F14: 1 | G14: 1 | H14: 1 | I14: 1 | J14: 1 | K14: 1 | L14: 1 | M14: 1 | N14: 1 | O14: 1 | P14: 1 | Q14: 1 | R14: =Q14 -> 1
B15: 2.5 | C15: Bảo vệ | R15: =Q15 -> 0
B16: 2.6 | C16: Nhân viên chăm sóc cây xanh | F16: 1 | G16: 1 | H16: 1 | I16: 1 | J16: 1 | K16: 1 | L16: 1 | M16: 1 | N16: 1 | O16: 1 | P16: 1 | Q16: 1 | R16: =Q16 -> 1
B17: 3 | C17: Phòng Kế toán | D17: 642 | E17: =SUM(E18:E21) -> 3 | F17: =SUM(F18:F21) -> 4 | G17: =SUM(G18:G21) -> 4 | H17: =SUM(H18:H21) -> 4 | I17: =SUM(I18:I21) -> 4 | J17: =SUM(J18:J21) -> 4 | K17: =SUM(K18:K21) -> 4 | L17: =SUM(L18:L21) -> 4 | ... R17: =SUM(R18:R21) -> 4
B18: 3.1 | C18: Kế toán trưởng | E18: 1 | F18: 1 | G18: 1 | H18: 1 | I18: 1 | J18: 1 | K18: 1 | L18: 1 | M18: 1 | N18: 1 | O18: 1 | P18: 1 | Q18: 1 | R18: =Q18 -> 1
B19: 3.2 | C19: Kế toán tổng hợp | E19: 1 | F19: 2 | G19: 2 | H19: 2 | I19: 2 | J19: 2 | K19: 2 | L19: 2 | M19: 2 | N19: 2 | O19: 2 | P19: 2 | Q19: 2 | R19: =Q19 -> 2
B20: 3.3 | C20: Kế toán kho | E20: 1 | F20: 1 | G20: 1 | H20: 1 | I20: 1 | J20: 1 | K20: 1 | L20: 1 | M20: 1 | N20: 1 | O20: 1 | P20: 1 | Q20: 1 | R20: =Q20 -> 1
B21: 3.4 | C21: Kế toán viên | R21: =Q21 -> 0
B22: 4 | C22: Phòng Mua hàng (Bao gồm NVL + Vật tư) | D22: 642 | E22: =E23 -> 1 | F22: =F23 -> 1 | G22: =G23 -> 1 | H22: =H23 -> 1 | I22: =I23 -> 1 | J22: =J23 -> 1 | K22: =K23 -> 1 | L22: =L23 -> 1 | ... R22: =R23 -> 1
B23: 4.1 | C23: Nhân viên mua hàng | E23: 1 | F23: 1 | G23: 1 | H23: 1 | I23: 1 | J23: 1 | K23: 1 | L23: 1 | M23: 1 | N23: 1 | O23: 1 | P23: 1 | Q23: 1 | R23: 1
B24: 5 | C24: Ban dự án XDCB | D24: 642 | E24: =E25 -> 0 | F24: =F25 -> 0 | G24: =G25 -> 0 | H24: =H25 -> 0 | I24: =I25 -> 0 | J24: =J25 -> 0 | K24: =K25 -> 0 | L24: =L25 -> 0 | ... Q24: =Q25 -> 0
B25: 5.1 | C25: Nhân viên
B26: 6 | C26: Phòng Quản Trị Hệ Thống | D26: 642 | E26: =E27 -> 0 | F26: =F27 -> 0 | G26: =G27 -> 0 | H26: =H27 -> 0 | I26: =I27 -> 0 | J26: =J27 -> 0 | K26: =K27 -> 0 | L26: =L27 -> 0 | ... Q26: =Q27 -> 0
B27: 6.1 | C27: Nhân viên quản trị hệ thống
B28: 7 | C28: Phòng 5S & an toàn | D28: 642 | E28: =E29 -> 0 | F28: =F29 -> 1 | G28: =G29 -> 1 | H28: =H29 -> 1 | I28: =I29 -> 1 | J28: =J29 -> 1 | K28: =K29 -> 1 | L28: =L29 -> 1 | ... Q28: =Q29 -> 1 | R28: =Q28 -> 1
B29: 7.1 | C29: Nhân viên 5S & an toàn | F29: 1 | G29: 1 | H29: 1 | I29: 1 | J29: 1 | K29: 1 | L29: 1 | M29: 1 | N29: 1 | O29: 1 | P29: 1 | Q29: 1 | R29: =Q29 -> 1
B30: 8 | C30: Phòng Cung ứng | D30: 642 | E30: =E31 -> 0 | F30: =F31 -> 0 | G30: =G31 -> 0 | H30: =H31 -> 0 | I30: =I31 -> 0 | J30: =J31 -> 0 | K30: =K31 -> 0 | L30: =L31 -> 0 | ... Q30: =Q31 -> 0 | R30: =Q30 -> 0
B31: 8.1 | C31: Nhân viên | R31: =Q31 -> 0
B32: 9 | C32: Phòng mua XNK | D32: 642 | E32: =E33 -> 0 | F32: =F33 -> 0 | G32: =G33 -> 0 | H32: =H33 -> 0 | I32: =I33 -> 0 | J32: =J33 -> 0 | K32: =K33 -> 0 | L32: =L33 -> 0 | ... Q32: =Q33 -> 0 | R32: =Q32 -> 0
B33: 9.1 | C33: Nhân viên mua hàng | R33: =Q33 -> 0
B34: 10 | C34: Tư Vấn Dịch Vụ | D34: 642 | E34: =E35 -> 0 | F34: =F35 -> 0 | G34: =G35 -> 0 | H34: =H35 -> 0 | I34: =I35 -> 0 | J34: =J35 -> 0 | K34: =K35 -> 0 | L34: =L35 -> 0 | ... Q34: =Q35 -> 0 | R34: =Q34 -> 0
B35: 10.1 | C35: Nhân viên | R35: =Q35 -> 0
B36: 11 | C36: Phòng Nghiên Cứu & Phát Triển | D36: 627 | E36: =E37 -> 0 | F36: =F37 -> 0 | G36: =G37 -> 0 | H36: =H37 -> 0 | I36: =I37 -> 0 | J36: =J37 -> 0 | K36: =K37 -> 0 | L36: =L37 -> 0 | ... Q36: =Q37 -> 0 | R36: =Q36 -> 0
B37: 11.1 | C37: Nhân viên | R37: =Q37 -> 0
B38: 12 | C38: Phòng Kiểm soát chất lượng | D38: 627 | E38: =SUM(E39:E41) -> 2 | F38: =SUM(F39:F41) -> 4 | G38: =SUM(G39:G41) -> 4 | H38: =SUM(H39:H41) -> 4 | I38: =SUM(I39:I41) -> 4 | J38: =SUM(J39:J41) -> 4 | K38: =SUM(K39:K41) -> 4 | L38: =SUM(L39:L41) -> 4 | ... R38: =SUM(R39:R41) -> 4
B39: 12.1 | C39: Tổ trưởng Kiểm soát chất lượng | R39: =Q39 -> 0
B40: 12.2 | C40: Kiểm soát NVL - 1 ca Hành chánh | E40: 2 | F40: 2 | G40: 2 | H40: 2 | I40: 2 | J40: 2 | K40: 2 | L40: 2 | M40: 2 | N40: 2 | O40: 2 | P40: 2 | Q40: 2 | R40: =Q40 -> 2
B41: 12.3 | C41: Kiểm soát thành phẩm - 2 Ca | F41: 2 | G41: 2 | H41: 2 | I41: 2 | J41: 2 | K41: 2 | L41: 2 | M41: 2 | N41: 2 | O41: 2 | P41: 2 | Q41: 2 | R41: =Q41 -> 2
B42: 13 | C42: Phòng Kỹ thuật | D42: 627 | E42: =SUM(E43:E51) -> 2 | F42: =SUM(F43:F51) -> 3 | G42: =SUM(G43:G51) -> 3 | H42: =SUM(H43:H51) -> 3 | I42: =SUM(I43:I51) -> 10 | J42: =SUM(J43:J51) -> 10 | K42: =SUM(K43:K51) -> 10 | L42: =SUM(L43:L51) -> 10 | ... R42: =SUM(R43:R51) -> 10
B43: 13.1 | C43: Quản lý kỹ thuật | I43: 1 | J43: 1 | K43: 1 | L43: 1 | M43: 1 | N43: 1 | O43: 1 | P43: 1 | Q43: 1 | R43: =Q43 -> 1
B44: 13.2 | C44: Tổ trưởng kỹ thuật | I44: 1 | J44: 1 | K44: 1 | L44: 1 | M44: 1 | N44: 1 | O44: 1 | P44: 1 | Q44: 1 | R44: =Q44 -> 1
B45: 13.3 | C45: Nhân viên vận hành chuyền phân loại chai PET -2 Ca | F45: 3 | G45: 3 | H45: 3 | I45: 2 | J45: 2 | K45: 2 | L45: 2 | M45: 2 | N45: 2 | O45: 2 | P45: 2 | Q45: 2 | R45: =Q45 -> 2
B46: 13.4 | C46: Nhân viên vận hành chuyền băm vảy PET - 3 ca | I46: 3 | J46: 3 | K46: 3 | L46: 3 | M46: 3 | N46: 3 | O46: 3 | P46: 3 | Q46: 3 | R46: =Q46 -> 3
B47: 13.5 | C47: Nhân viên bảo trì (1 điện; 1 cơ; 1 thay dao chuyền băm vảy) - 1 ca | E47: 2 | I47: 3 | J47: 3 | K47: 3 | L47: 3 | M47: 3 | N47: 3 | O47: 3 | P47: 3 | Q47: 3 | R47: =Q47 -> 3
B48: 13.6 | C48: Nhân viên xử lý nước thải (24/24) | R48: =Q48 -> 0
B49: 13.5 | R49: =Q49 -> 0
B50: 13.6 | R50: =Q50 -> 0
B51: 13.7
B52: 14 | C52: Phòng Sản xuất | E52: =E53+E58+E79 -> 48 | F52: =F53+F58+F79 -> 49 | G52: =G53+G58+G79 -> 53 | H52: =H53+H58+H79 -> 74 | I52: =I53+I58+I79 -> 80 | J52: =J53+J58+J79 -> 80 | K52: =K53+K58+K79 -> 80 | L52: =L53+L58+L79 -> 80 | ... R52: =R53+R58+R79 -> 80
B53: 14.1 | C53: Bộ phận quản lý sản xuất | D53: 627 | E53: =SUM(E54:E57) -> 2 | F53: =SUM(F54:F57) -> 2 | G53: =SUM(G54:G57) -> 2 | H53: =SUM(H54:H57) -> 2 | I53: =SUM(I54:I57) -> 4 | J53: =SUM(J54:J57) -> 4 | K53: =SUM(K54:K57) -> 4 | L53: =SUM(L54:L57) -> 4 | ... R53: =SUM(R54:R57) -> 4
B54: 14.1.1 | C54: Quản lý sản xuất | E54: 1 | I54: 1 | J54: 1 | K54: 1 | L54: 1 | M54: 1 | N54: 1 | O54: 1 | P54: 1 | Q54: 1 | R54: =Q54 -> 1
B55: 14.1.2 | C55: Giám sát sản xuất | R55: =Q55 -> 0 | U55: Chuyền AI 1 | W55: Chuyền PLEN-01 | Y55: Chuyền rework | AA55: Chuyền PLEN-02 (Dùng T1-3/2026) | AC55: Chuyền băm vảy | AF55: SXC
B56: 14.1.3 | C56: Tổ trưởng sản xuất - 2 ca | E56: 1 | F56: 1 | G56: 1 | H56: 1 | I56: 2 | J56: 2 | K56: 2 | L56: 2 | M56: 2 | N56: 2 | O56: 2 | P56: 2 | Q56: 2 | R56: =Q56 -> 2 | U56: Ca 1 | V56: Ca 2 | W56: Ca 1 | X56: Ca 2 | Y56: Ca 1 | Z56: Ca 2 | AA56: Ca 1 | AB56: Ca 2 | AC56: Ca 1 | AD56: Ca 2 | AE56: Ca 3 | AF56: Ca 1 | AG56: Ca 2 | AH56: Ca 3
B57: 14.1.4 | C57: Thống kê sản xuất | F57: 1 | G57: 1 | H57: 1 | I57: 1 | J57: 1 | K57: 1 | L57: 1 | M57: 1 | N57: 1 | O57: 1 | P57: 1 | Q57: 1 | R57: =Q57 -> 1 | T57: Chi tiết phân bổ Công nhân trực tiếp SX
B58: 14.2 | C58: Công nhân trực tiếp sản xuất - Phân loại | D58: 622 | E58: =E59+E72 -> 46 | F58: =F59+F72 -> 47 | G58: =G59+G72 -> 47 | H58: =H59+H72 -> 68 | I58: =I59+I72 -> 66 | J58: =J59+J72 -> 66 | K58: =K59+K72 -> 66 | L58: =L59+L72 -> 66 | ... R58: =R59+R72 -> 66 | T58: Công nhân trực tiếp sản xuất - Phân loại | U58: =U59+U69+U74 -> 10 | V58: =V59+V69+V74 -> 10 | W58: =W59+W69+W74 -> 14 | X58: =X59+X69+X74 -> 14 | Y58: =Y59+Y69+Y74 -> 5 | Z58: =Z59+Z69+Z74 -> 5 | AA58: =AA59+AA69+AA74 -> 13 | AB58: =AB59+AB69+AB74 -> 13 | ... AH58: =AH59+AH69+AH74 -> 2
C59: Định biên | D59: 60% | E59: =SUM(E60:E71) -> 20 | F59: 41 | G59: 41 | H59: 41 | I59: 44 | J59: 44 | K59: 44 | L59: 44 | M59: 44 | N59: 44 | O59: 44 | P59: 44 | Q59: 44 | R59: =Q59 -> 44 | T59: SX chai PET - Chuyền phân loại | U59: =SUM(U60:U64) -> 10 | V59: =SUM(V60:V64) -> 10 | W59: =SUM(W60:W64) -> 14 | X59: =SUM(X60:X64) -> 14 | Y59: =SUM(Y60:Y64) -> 5 | Z59: =SUM(Z60:Z64) -> 5 | AA59: =SUM(AA60:AA64) -> 13 | AB59: =SUM(AB60:AB64) -> 13 | AF59: =SUM(AF60:AF64) -> 0 | AG59: =SUM(AG60:AG64) -> 0 | AH59: =SUM(AH60:AH64) -> 0
B60: 14.2.1 | C60: Nhân viên phân loại | F60: =F59-F61-F66 -> 0 | G60: =G59-G61-G66 -> 0 | H60: =H59-H61-H66 -> 0 | I60: =I59-I61-I66 -> 0 | J60: =J59-J61-J66 -> 0 | K60: =K59-K61-K66 -> 0 | L60: =L59-L61-L66 -> 0 | M60: =M59-M61-M66 -> 0 | ... Q60: =Q59-Q61-Q66 -> 0 | R60: =Q60 -> 0 | T60: Công đoạn 1: Cấp liệu | U60: 2 | V60: 2 | W60: 1 | X60: 1 | AA60: 1 | AB60: 1
C61: TỔNG NHÂN VIÊN - CA 1 (6-14 giờ) | F61: =SUM(F62:F65) -> 23 | G61: =SUM(G62:G65) -> 23 | H61: =SUM(H62:H65) -> 23 | I61: =SUM(I62:I65) -> 26 | J61: =SUM(J62:J65) -> 26 | K61: =SUM(K62:K65) -> 26 | L61: =SUM(L62:L65) -> 26 | M61: =SUM(M62:M65) -> 26 | ... R61: =SUM(R62:R65) -> 26 | T61: Công đoạn 2: PL trước tách nhãn | U61: 3 | V61: 3 | W61: 5 | X61: 5 | Y61: 1 | Z61: 1 | AA61: 5 | AB61: 5
B62: 14.2.1 | C62: Nhân viên phân loại | E62: 16 | F62: 16 | G62: 16 | H62: 16 | I62: 19 | J62: 19 | K62: 19 | L62: 19 | M62: 19 | N62: 19 | O62: 19 | P62: 19 | Q62: 19 | R62: 19 | T62: Công đoạn 3: PL sau tách nhãn | U62: 3 | V62: 3 | W62: 5 | X62: 5 | Y62: 2 | Z62: 2 | AA62: 5 | AB62: 5
B63: 14.2.2 | C63: Nhân viên ép kiện | F63: 2 | G63: 2 | H63: 2 | I63: 2 | J63: 2 | K63: 2 | L63: 2 | M63: 2 | N63: 2 | O63: 2 | P63: 2 | Q63: 2 | R63: 2 | T63: Nhân viên kéo bao, bì tạp | U63: 1 | V63: 1 | W63: 2 | X63: 2 | Y63: 1 | Z63: 1 | AA63: 2 | AB63: 2
B64: 14.2.3 | C64: Nhân viên SXC | E64: 2 | F64: 3 | G64: 3 | H64: 3 | I64: 3 | J64: 3 | K64: 3 | L64: 3 | M64: 3 | N64: 3 | O64: 3 | P64: 3 | Q64: 3 | R64: 3 | T64: Nhân viên Ép kiện | U64: 1 | V64: 1 | W64: 1 | X64: 1 | Y64: 1 | Z64: 1
B65: 14.2.4 | C65: Nhân viên lái xe nâng | E65: 2 | F65: 2 | G65: 2 | H65: 2 | I65: 2 | J65: 2 | K65: 2 | L65: 2 | M65: 2 | N65: 2 | O65: 2 | P65: 2 | Q65: 2 | R65: 2 | T65: SX băm vảy PET | AC65: =SUM(AC66:AC68) -> 3 | AD65: =SUM(AD66:AD68) -> 3 | AE65: =SUM(AE66:AE68) -> 3
C66: TỔNG NHÂN VIÊN - CA 2 (14-22 giờ) | F66: =SUM(F67:F70) -> 18 | G66: =SUM(G67:G70) -> 18 | H66: =SUM(H67:H70) -> 18 | I66: =SUM(I67:I70) -> 18 | J66: =SUM(J67:J70) -> 18 | K66: =SUM(K67:K70) -> 18 | L66: =SUM(L67:L70) -> 18 | M66: =SUM(M67:M70) -> 18 | ... R66: =SUM(R67:R70) -> 18 | T66: Công đoạn 1: Cấp liệu | AC66: 1 | AD66: 1 | AE66: 1
B67: 14.2.1 | C67: Nhân viên phân loại | F67: 11 | G67: 11 | H67: 11 | I67: 11 | J67: 11 | K67: 11 | L67: 11 | M67: 11 | N67: 11 | O67: 11 | P67: 11 | Q67: 11 | R67: 11 | T67: Công đoạn 2: PL trước băm vảy | AC67: 1 | AD67: 1 | AE67: 1
B68: 14.2.2 | C68: Nhân viên ép kiện | F68: 2 | G68: 2 | H68: 2 | I68: 2 | J68: 2 | K68: 2 | L68: 2 | M68: 2 | N68: 2 | O68: 2 | P68: 2 | Q68: 2 | R68: 2 | T68: Nhân viên đóng gói TP | AC68: 1 | AD68: 1 | AE68: 1
B69: 14.2.3 | C69: Nhân viên SXC | F69: 3 | G69: 3 | H69: 3 | I69: 3 | J69: 3 | K69: 3 | L69: 3 | M69: 3 | N69: 3 | O69: 3 | P69: 3 | Q69: 3 | R69: 3 | T69: Sản xuất chung | U69: =SUM(U70:U73) -> 0 | V69: =SUM(V70:V73) -> 0 | W69: =SUM(W70:W73) -> 0 | X69: =SUM(X70:X73) -> 0 | Y69: =SUM(Y70:Y73) -> 0 | Z69: =SUM(Z70:Z73) -> 0 | AA69: =SUM(AA70:AA73) -> 0 | AB69: =SUM(AB70:AB73) -> 0 | ... AH69: =SUM(AH70:AH73) -> 1
B70: 14.2.4 | C70: Nhân viên lái xe nâng | F70: 2 | G70: 2 | H70: 2 | I70: 2 | J70: 2 | K70: 2 | L70: 2 | M70: 2 | N70: 2 | O70: 2 | P70: 2 | Q70: 2 | R70: 2 | T70: Nhân viên lái xe nâng | AF70: 2 | AG70: 2 | AH70: 1
R71: =Q71 -> 0 | T71: Nhân viên chuyển tem nhãn | AF71: 1 | AG71: 1
C72: Thuê ngoài | D72: 40% | E72: =SUM(E74:E75) -> 26 | F72: =SUM(F74:F77) -> 6 | G72: =SUM(G74:G77) -> 6 | H72: =SUM(H74:H77) -> 27 | I72: =SUM(I74:I77) -> 22 | J72: =SUM(J74:J77) -> 22 | K72: =SUM(K74:K77) -> 22 | L72: =SUM(L74:L77) -> 22 | M72: =SUM(M74:M77) -> 22 | ... Q72: =SUM(Q74:Q77) -> 22 | R72: =Q72 -> 22 | T72: Nhân viên giao bì tạp | AF72: 1 | AG72: 1
C73: TỔNG NHÂN VIÊN - CA 1 (6-14 giờ) | F73: =SUM(F74:F76) -> 6 | G73: =SUM(G74:G76) -> 6 | H73: =SUM(H74:H76) -> 27 | I73: =SUM(I74:I75) -> 22 | J73: =SUM(J74:J75) -> 22 | K73: =SUM(K74:K75) -> 22 | L73: =SUM(L74:L75) -> 22 | M73: =SUM(M74:M75) -> 22 | N73: =SUM(N74:N75) -> 22 | O73: =SUM(O74:O75) -> 22 | P73: =SUM(P74:P75) -> 22 | Q73: =SUM(Q74:Q75) -> 22 | R73: =Q73 -> 22 | T73: Nhân viên ghi số liệu | AF73: 1 | AG73: 1
B74: 14.2.4 | C74: Nhân viên phân loại | E74: 22 | H74: 21 | I74: 16 | J74: 16 | K74: 16 | L74: 16 | M74: 16 | N74: 16 | O74: 16 | P74: 16 | Q74: 16 | R74: 16 | T74: Xử lý phó sản - Thời vụ | AF74: =SUM(AF75:AF76) -> 5 | AG74: =SUM(AG75:AG76) -> 1 | AH74: =SUM(AH75:AH76) -> 1
B75: 14.2.5 | C75: Nhân viên xử lý phó sản | E75: 4 | F75: 6 | G75: 6 | H75: 6 | I75: 6 | J75: 6 | K75: 6 | L75: 6 | M75: 6 | N75: 6 | O75: 6 | P75: 6 | Q75: 6 | R75: 6 | T75: Nhân viên xử lý nắp, cổ chai,… | AF75: 4
R76: =Q76 -> 0 | T76: Nhân viên vệ sinh xưởng | AF76: 1 | AG76: 1 | AH76: 1
W78: T 1 - 2 - 3 : 2 ca (Ca 2 không tính rework)
B79: 14.3 | C79: Công nhân trực tiếp sản xuất - Băm vảy PET | D79: 622 | E79: =E80+E90 -> 0 | F79: =F81+F87 -> 0 | G79: =G81+G87 -> 4 | H79: =H81+H87 -> 4 | I79: =I81+I87 -> 10 | J79: =J81+J87 -> 10 | K79: =K81+K87 -> 10 | L79: =L81+L87 -> 10 | M79: =M81+M87 -> 10 | ... Q79: =Q81+Q87 -> 10 | R79: =Q79 -> 10 | W79: T3 về sau 2 ca + tăng ca 2 tiếng
B80: 14.3.1 | C80: Nhân viên băm vảy | G80: =G81+G87 -> 4 | H80: =H81+H87 -> 4 | I80: =I81+I87 -> 10 | J80: =J81+J87 -> 10 | K80: =K81+K87 -> 10 | L80: =L81+L87 -> 10 | M80: =M81+M87 -> 10 | N80: =N81+N87 -> 10 | ... Q80: =Q81+Q87 -> 10 | R80: =Q80 -> 10
C81: Định biên | G81: =SUM(G82:G84) -> 4 | H81: =SUM(H82:H84) -> 4 | I81: =SUM(I82:I84) -> 4 | J81: =SUM(J82:J84) -> 4 | K81: =SUM(K82:K84) -> 4 | L81: =SUM(L82:L84) -> 4 | M81: =SUM(M82:M84) -> 4 | N81: =SUM(N82:N84) -> 4 | ... Q81: =SUM(Q82:Q84) -> 4 | R81: =Q81 -> 4
C82: Tổng nhân viên - Ca 1 (6-14 giờ) | G82: 1 | H82: 1 | I82: 1 | J82: 1 | K82: 1 | L82: 1 | M82: 1 | N82: 1 | O82: 1 | P82: 1 | Q82: 1 | R82: 1
C83: Tổng nhân viên - Ca 2 (14-22 giờ) | G83: 1 | H83: 1 | I83: 1 | J83: 1 | K83: 1 | L83: 1 | M83: 1 | N83: 1 | O83: 1 | P83: 1 | Q83: 1 | R83: 1
C84: Tổng nhân viên - Ca 3 (22-06 giờ) | G84: 2 | H84: 2 | I84: 2 | J84: 2 | K84: 2 | L84: 2 | M84: 2 | N84: 2 | O84: 2 | P84: 2 | Q84: 2 | R84: 2
C85: Nhân viên băm vảy - Ca 3 (22-06 giờ) | G85: 1 | H85: 1 | I85: 1 | J85: 1 | K85: 1 | L85: 1 | M85: 1 | N85: 1 | O85: 1 | P85: 1 | Q85: 1 | R85: 1
C86: Nhân viên lái xe nâng - Ca 3 (22-06 giờ) | G86: 1 | H86: 1 | I86: 1 | J86: 1 | K86: 1 | L86: 1 | M86: 1 | N86: 1 | O86: 1 | P86: 1 | Q86: 1 | R86: 1
C87: Thuê ngoài | G87: =SUM(G88:G90) -> 0 | H87: =SUM(H88:H90) -> 0 | I87: =SUM(I88:I90) -> 6 | J87: =SUM(J88:J90) -> 6 | K87: =SUM(K88:K90) -> 6 | L87: =SUM(L88:L90) -> 6 | M87: =SUM(M88:M90) -> 6 | N87: =SUM(N88:N90) -> 6 | ... Q87: =SUM(Q88:Q90) -> 6 | R87: =Q87 -> 6
C88: Tổng nhân viên - Ca 1 (6-14 giờ) | I88: 2 | J88: 2 | K88: 2 | L88: 2 | M88: 2 | N88: 2 | O88: 2 | P88: 2 | Q88: 2 | R88: =Q88 -> 2
C89: Tổng nhân viên - Ca 2 (14-22 giờ) | I89: 2 | J89: 2 | K89: 2 | L89: 2 | M89: 2 | N89: 2 | O89: 2 | P89: 2 | Q89: 2 | R89: =Q89 -> 2
C90: Tổng nhân viên - Ca 3 (22-06 giờ) | I90: 2 | J90: 2 | K90: 2 | L90: 2 | M90: 2 | N90: 2 | O90: 2 | P90: 2 | Q90: 2 | R90: =Q90 -> 2
B91: 15 | C91: Phòng Kho vận | D91: 627 | E91: =SUM(E92:E95) -> 6 | F91: =SUM(F92:F95) -> 8 | G91: =SUM(G92:G95) -> 8 | H91: =SUM(H92:H95) -> 8 | I91: =SUM(I92:I95) -> 8 | J91: =SUM(J92:J95) -> 8 | K91: =SUM(K92:K95) -> 8 | L91: =SUM(L92:L95) -> 8 | ... R91: =SUM(R92:R95) -> 8
B92: 15.1 | C92: Thủ kho | E92: 1 | F92: 1 | G92: 1 | H92: 1 | I92: 1 | J92: 1 | K92: 1 | L92: 1 | M92: 1 | N92: 1 | O92: 1 | P92: 1 | Q92: 1 | R92: =Q92 -> 1
B93: 15.2 | C93: Tổ Trưởng Kho - Xuất nhập | E93: 1 | F93: 1 | G93: 1 | H93: 1 | I93: 1 | J93: 1 | K93: 1 | L93: 1 | M93: 1 | N93: 1 | O93: 1 | P93: 1 | Q93: 1 | R93: =Q93 -> 1
B94: 15.3 | C94: Nhân viên Nhập - Xuất hàng | E94: 2 | F94: 4 | G94: 4 | H94: 4 | I94: 4 | J94: 4 | K94: 4 | L94: 4 | M94: 4 | N94: 4 | O94: 4 | P94: 4 | Q94: 4 | R94: =Q94 -> 4
B95: 15.4 | C95: Nhân Viên Lái Xe Nâng | E95: 2 | F95: 2 | G95: 2 | H95: 2 | I95: 2 | J95: 2 | K95: 2 | L95: 2 | M95: 2 | N95: 2 | O95: 2 | P95: 2 | Q95: 2 | R95: =Q95 -> 2
C97: Thuê ngoài | E97: 2 | R97: =Q97 -> 0
B98: 16 | C98: Trạm cấp 2 - Kiên Giang | D98: 642 | E98: =E99 -> 0 | F98: =F99 -> 0 | G98: =G99 -> 0 | H98: =H99 -> 0 | I98: =I99 -> 0 | J98: =J99 -> 0 | K98: =K99 -> 0 | L98: =L99 -> 0 | ... Q98: =Q99 -> 0
B99: 16.1 | C99: Nhân viên
B100: 17 | C100: Trạm cấp 2 - Cà Mau | D100: 642 | E100: =E101 -> 0 | F100: =F101 -> 0 | G100: =G101 -> 0 | H100: =H101 -> 0 | I100: =I101 -> 0 | J100: =J101 -> 0 | K100: =K101 -> 0 | L100: =L101 -> 0 | ... Q100: =Q101 -> 0
B101: 17.1 | C101: Nhân viên
B102: 18 | C102: Trạm cấp 2 - Gia Lai | D102: 642 | E102: =E103 -> 0 | F102: =F103 -> 0 | G102: =G103 -> 0 | H102: =H103 -> 0 | I102: =I103 -> 0 | J102: =J103 -> 0 | K102: =K103 -> 0 | L102: =L103 -> 0 | ... Q102: =Q103 -> 0
B103: 18.1 | C103: Nhân viên
...

Sheet 4.Doanh thu
B3: DOANH THU
B4: I - DOANH THU CHAI PET
B5: 1. Sản lượng bán chai
B6: STT | C6: Thành phẩm (chai sau phân loại) | D6: ĐVT | E6: Tỷ lệ | F6: T1 | G6: T2 | H6: T3 | I6: T4 | J6: T5 | K6: T6 | L6: T7 | M6: T8 | N6: T9 | O6: T10 | P6: T11 | Q6: T12 | R6: KHKD 2026 | T6: T1 | U6: T2 | V6: T3 | W6: T4 | X6: T5 | Y6: T6 | Z6: T7 | AA6: T8 | AB6: T9 | AC6: T10 | AD6: T11 | AE6: T12 | AF6: KQKD 2025 | AH6: KQKD 2024 | AJ6: KQKD 2023 | AL6: +/- 2026 sv 2025 | AM6: +/- % | AX6: Thành phẩm (chai sau phân loại) | AY6: T1 | AZ6: T2 | BA6: T3 | BB6: T4 | BC6: T5 | BD6: T6 | BE6: T7 | BF6: T8 | BG6: T9 | BH6: T10 | BI6: T11 | BJ6: T12 | BK6: Mục tiêu 2026
B7: 1 | C7: Chai PET B1 | D7: Tấn | F7: ='3.Thanh pham'!G82 -> 0 | G7: ='3.Thanh pham'!H82 -> 0 | H7: ='3.Thanh pham'!I82 -> 0 | I7: ='3.Thanh pham'!J82 -> 0 | J7: ='3.Thanh pham'!K82 -> 0 | K7: ='3.Thanh pham'!L82 -> 0 | L7: ='3.Thanh pham'!M82 -> 0 | M7: ='3.Thanh pham'!N82 -> 0 | ... Q7: ='3.Thanh pham'!R82 -> 0 | R7: =SUM(F7:Q7) -> 0 | T7: 0 | U7: 19813 | V7: 50178 | W7: 69677 | X7: 35669 | Y7: 78235 | Z7: 67196 | AA7: 50812 | AB7: 6793 | AC7: 2192 | AD7: 0 | AE7: 0 | AF7: =SUM(T7:AE7) -> 380565 | AH7: 30193 | AJ7: 1038416 | AL7: =IFERROR(R7-AF7,0) -> -380565 | AM7: =IFERROR((R7/AF7)-1,0) -> -1 | AX7: Chai PET B1 | AY7: ='3.Thanh pham'!G63 -> 0 | AZ7: ='3.Thanh pham'!H63 -> 0 | BA7: ='3.Thanh pham'!I63 -> 0 | BB7: ='3.Thanh pham'!J63 -> 0 | BC7: ='3.Thanh pham'!K63 -> 0 | BD7: ='3.Thanh pham'!L63 -> 0 | BE7: ='3.Thanh pham'!M63 -> 0 | BF7: ='3.Thanh pham'!N63 -> 0 | ... BJ7: ='3.Thanh pham'!R63 -> 0 | BK7: =SUM(AY7:BJ7) -> 0
B8: 2 | C8: Chai PET B1 Không Phân Loại | D8: Tấn | F8: ='3.Thanh pham'!G83 -> 365040 | G8: ='3.Thanh pham'!H83 -> 210600 | H8: ='3.Thanh pham'!I83 -> 485680 | I8: ='3.Thanh pham'!J83 -> 0 | J8: ='3.Thanh pham'!K83 -> 0 | K8: ='3.Thanh pham'!L83 -> 0 | L8: ='3.Thanh pham'!M83 -> 0 | M8: ='3.Thanh pham'!N83 -> 0 | ... Q8: ='3.Thanh pham'!R83 -> 0 | R8: =SUM(F8:Q8) -> 1061320 | T8: 61839 | U8: 45562 | V8: 45024 | W8: 92622 | X8: 197273 | Y8: 271254 | Z8: 339955 | AA8: 389507 | AB8: 346544 | AC8: 287638 | AD8: 228800 | AE8: 246400 | AF8: =SUM(T8:AE8) -> 2552418 | AH8: 2139028 | AJ8: 504421.5 | AL8: =IFERROR(R8-AF8,0) -> -1491098 | AM8: =IFERROR((R8/AF8)-1,0) -> -0.58419036 | AX8: Chai PET B1 Không Phân Loại | AY8: ='3.Thanh pham'!G64 -> 365040 | AZ8: ='3.Thanh pham'!H64 -> 210600 | BA8: ='3.Thanh pham'!I64 -> 485680 | BB8: ='3.Thanh pham'!J64 -> 583750 | BC8: ='3.Thanh pham'!K64 -> 583750 | BD8: ='3.Thanh pham'!L64 -> 607100 | BE8: ='3.Thanh pham'!M64 -> 630450 | BF8: ='3.Thanh pham'!N64 -> 607100 | ... BJ8: ='3.Thanh pham'!R64 -> 630450 | BK8: =SUM(AY8:BJ8) -> 6478520
B9: 3 | C9: Chai PET B1.3 | D9: Tấn | F9: ='3.Thanh pham'!G84 -> 0 | G9: ='3.Thanh pham'!H84 -> 0 | H9: ='3.Thanh pham'!I84 -> 0 | I9: ='3.Thanh pham'!J84 -> 0 | J9: ='3.Thanh pham'!K84 -> 0 | K9: ='3.Thanh pham'!L84 -> 0 | L9: ='3.Thanh pham'!M84 -> 0 | M9: ='3.Thanh pham'!N84 -> 0 | ... Q9: ='3.Thanh pham'!R84 -> 0 | R9: =SUM(F9:Q9) -> 0 | T9: 5075 | U9: 82000 | V9: 96416 | W9: 83716 | X9: 5130 | Y9: 0 | Z9: 0 | AA9: 0 | AB9: 0 | AD9: 0 | AE9: 0 | AF9: =SUM(T9:AE9) -> 272337 | AL9: =IFERROR(R9-AF9,0) -> -272337 | AM9: =IFERROR((R9/AF9)-1,0) -> -1 | AX9: Chai PET B1.3 | AY9: ='3.Thanh pham'!G65 -> 0 | AZ9: ='3.Thanh pham'!H65 -> 0 | BA9: ='3.Thanh pham'!I65 -> 0 | BB9: ='3.Thanh pham'!J65 -> 0 | BC9: ='3.Thanh pham'!K65 -> 0 | BD9: ='3.Thanh pham'!L65 -> 0 | BE9: ='3.Thanh pham'!M65 -> 0 | BF9: ='3.Thanh pham'!N65 -> 0 | ... BJ9: ='3.Thanh pham'!R65 -> 0 | BK9: =SUM(AY9:BJ9) -> 0
B10: 4 | C10: Chai PET B2.1 | D10: Tấn | F10: ='3.Thanh pham'!G85 -> 0 | G10: ='3.Thanh pham'!H85 -> 0 | H10: ='3.Thanh pham'!I85 -> 0 | I10: ='3.Thanh pham'!J85 -> 0 | J10: ='3.Thanh pham'!K85 -> 0 | K10: ='3.Thanh pham'!L85 -> 0 | L10: ='3.Thanh pham'!M85 -> 0 | M10: ='3.Thanh pham'!N85 -> 0 | ... Q10: ='3.Thanh pham'!R85 -> 0 | R10: =SUM(F10:Q10) -> 0 | AF10: =SUM(T10:AE10) -> 0 | AJ10: 118971.5 | AL10: =IFERROR(R10-AF10,0) -> 0 | AM10: =IFERROR((R10/AF10)-1,0) -> 0 | AX10: Chai PET B2.1 | AY10: ='3.Thanh pham'!G66 -> 0 | AZ10: ='3.Thanh pham'!H66 -> 0 | BA10: ='3.Thanh pham'!I66 -> 0 | BB10: ='3.Thanh pham'!J66 -> 0 | BC10: ='3.Thanh pham'!K66 -> 0 | BD10: ='3.Thanh pham'!L66 -> 0 | BE10: ='3.Thanh pham'!M66 -> 0 | BF10: ='3.Thanh pham'!N66 -> 0 | ... BJ10: ='3.Thanh pham'!R66 -> 0 | BK10: =SUM(AY10:BJ10) -> 0
B11: 5 | C11: Chai PET B2.2 | D11: Tấn | F11: ='3.Thanh pham'!G86 -> 71760 | G11: ='3.Thanh pham'!H86 -> 41400 | H11: ='3.Thanh pham'!I86 -> 95420 | I11: ='3.Thanh pham'!J86 -> 0 | J11: ='3.Thanh pham'!K86 -> 0 | K11: ='3.Thanh pham'!L86 -> 0 | L11: ='3.Thanh pham'!M86 -> 0 | M11: ='3.Thanh pham'!N86 -> 0 | ... Q11: ='3.Thanh pham'!R86 -> 0 | R11: =SUM(F11:Q11) -> 208580 | T11: 18417 | U11: 31641 | V11: 38478 | W11: 37699 | X11: 42997 | Y11: 48246 | Z11: 57835 | AA11: 56659 | AB11: 65618 | AC11: 43052 | AD11: 36608 | AE11: 39424 | AF11: =SUM(T11:AE11) -> 516674 | AH11: 314556 | AJ11: 200084.5 | AL11: =IFERROR(R11-AF11,0) -> -308094 | AM11: =IFERROR((R11/AF11)-1,0) -> -0.5963025 | AX11: Chai PET B2.2 | AY11: ='3.Thanh pham'!G67 -> 71760 | AZ11: ='3.Thanh pham'!H67 -> 41400 | BA11: ='3.Thanh pham'!I67 -> 95420 | BB11: ='3.Thanh pham'!J67 -> 114687.5 | BC11: ='3.Thanh pham'!K67 -> 114687.5 | BD11: ='3.Thanh pham'!L67 -> 119275 | BE11: ='3.Thanh pham'!M67 -> 123862.5 | BF11: ='3.Thanh pham'!N67 -> 119275 | ... BJ11: ='3.Thanh pham'!R67 -> 123862.5 | BK11: =SUM(AY11:BJ11) -> 1272880
B12: 6 | C12: Chai PET B3 | D12: Tấn | F12: ='3.Thanh pham'!G87 -> 0 | G12: ='3.Thanh pham'!H87 -> 0 | H12: ='3.Thanh pham'!I87 -> 0 | I12: ='3.Thanh pham'!J87 -> 0 | J12: ='3.Thanh pham'!K87 -> 0 | K12: ='3.Thanh pham'!L87 -> 0 | L12: ='3.Thanh pham'!M87 -> 0 | M12: ='3.Thanh pham'!N87 -> 0 | ... Q12: ='3.Thanh pham'!R87 -> 0 | R12: =SUM(F12:Q12) -> 0 | AF12: =SUM(T12:AE12) -> 0 | AH12: 7397 | AJ12: 456068 | AL12: =IFERROR(R12-AF12,0) -> 0 | AM12: =IFERROR((R12/AF12)-1,0) -> 0 | AX12: Chai PET B3 | AY12: ='3.Thanh pham'!G68 -> 0 | AZ12: ='3.Thanh pham'!H68 -> 0 | BA12: ='3.Thanh pham'!I68 -> 0 | BB12: ='3.Thanh pham'!J68 -> 0 | BC12: ='3.Thanh pham'!K68 -> 0 | BD12: ='3.Thanh pham'!L68 -> 0 | BE12: ='3.Thanh pham'!M68 -> 0 | BF12: ='3.Thanh pham'!N68 -> 0 | ... BJ12: ='3.Thanh pham'!R68 -> 0 | BK12: =SUM(AY12:BJ12) -> 0
B13: 7 | C13: Chai PET B4 | D13: Tấn | F13: ='3.Thanh pham'!G88 -> 7800 | G13: ='3.Thanh pham'!H88 -> 4500 | H13: ='3.Thanh pham'!I88 -> 10400 | I13: ='3.Thanh pham'!J88 -> 12500 | J13: ='3.Thanh pham'!K88 -> 12500 | K13: ='3.Thanh pham'!L88 -> 13000 | L13: ='3.Thanh pham'!M88 -> 13500 | M13: ='3.Thanh pham'!N88 -> 13000 | ... Q13: ='3.Thanh pham'!R88 -> 13500 | R13: =SUM(F13:Q13) -> 138700 | T13: 2791 | U13: 8071 | V13: 7396 | W13: 7448 | X13: 8251 | Y13: 10584 | Z13: 12937 | AA13: 15317 | AB13: 13032 | AC13: 11431 | AD13: 9152 | AE13: 9856 | AF13: =SUM(T13:AE13) -> 116266 | AH13: 83788 | AJ13: 41816 | AL13: =IFERROR(R13-AF13,0) -> 22434 | AM13: =IFERROR((R13/AF13)-1,0) -> 0.19295409 | AX13: Chai PET B4 | AY13: ='3.Thanh pham'!G69 -> 7800 | AZ13: ='3.Thanh pham'!H69 -> 4500 | BA13: ='3.Thanh pham'!I69 -> 10400 | BB13: ='3.Thanh pham'!J69 -> 12500 | BC13: ='3.Thanh pham'!K69 -> 12500 | BD13: ='3.Thanh pham'!L69 -> 13000 | BE13: ='3.Thanh pham'!M69 -> 13500 | BF13: ='3.Thanh pham'!N69 -> 13000 | ... BJ13: ='3.Thanh pham'!R69 -> 13500 | BK13: =SUM(AY13:BJ13) -> 138700
B14: 8 | C14: Chai PET B5 | D14: Tấn | F14: ='3.Thanh pham'!G89 -> 5460 | G14: ='3.Thanh pham'!H89 -> 3150 | H14: ='3.Thanh pham'!I89 -> 7020 | I14: ='3.Thanh pham'!J89 -> 8437.5 | J14: ='3.Thanh pham'!K89 -> 8437.5 | K14: ='3.Thanh pham'!L89 -> 8775 | L14: ='3.Thanh pham'!M89 -> 9112.5 | M14: ='3.Thanh pham'!N89 -> 8775 | ... Q14: ='3.Thanh pham'!R89 -> 9112.5 | R14: =SUM(F14:Q14) -> 93930 | T14: 2880 | U14: 3962 | V14: 3496 | W14: 5074 | X14: 4257 | Y14: 6909 | Z14: 7918 | AA14: 7614 | AB14: 7373 | AC14: 6270 | AD14: 6864 | AE14: 7392 | AF14: =SUM(T14:AE14) -> 70009 | AH14: 57204 | AJ14: 31798 | AL14: =IFERROR(R14-AF14,0) -> 23921 | AM14: =IFERROR((R14/AF14)-1,0) -> 0.34168464 | AX14: Chai PET B5 | AY14: ='3.Thanh pham'!G70 -> 5460 | AZ14: ='3.Thanh pham'!H70 -> 3150 | BA14: ='3.Thanh pham'!I70 -> 7020 | BB14: ='3.Thanh pham'!J70 -> 8437.5 | BC14: ='3.Thanh pham'!K70 -> 8437.5 | BD14: ='3.Thanh pham'!L70 -> 8775 | BE14: ='3.Thanh pham'!M70 -> 9112.5 | BF14: ='3.Thanh pham'!N70 -> 8775 | ... BJ14: ='3.Thanh pham'!R70 -> 9112.5 | BK14: =SUM(AY14:BJ14) -> 93930
B15: 9 | C15: Chai PET B6.1 | D15: Tấn | F15: ='3.Thanh pham'!G90 -> 0 | G15: ='3.Thanh pham'!H90 -> 0 | H15: ='3.Thanh pham'!I90 -> 0 | I15: ='3.Thanh pham'!J90 -> 0 | J15: ='3.Thanh pham'!K90 -> 0 | K15: ='3.Thanh pham'!L90 -> 0 | L15: ='3.Thanh pham'!M90 -> 0 | M15: ='3.Thanh pham'!N90 -> 0 | ... Q15: ='3.Thanh pham'!R90 -> 0 | R15: =SUM(F15:Q15) -> 0 | AF15: =SUM(T15:AE15) -> 0 | AH15: 30358 | AJ15: 39633 | AL15: =IFERROR(R15-AF15,0) -> 0 | AM15: =IFERROR((R15/AF15)-1,0) -> 0 | AX15: Chai PET B6.1 | AY15: ='3.Thanh pham'!G71 -> 0 | AZ15: ='3.Thanh pham'!H71 -> 0 | BA15: ='3.Thanh pham'!I71 -> 0 | BB15: ='3.Thanh pham'!J71 -> 0 | BC15: ='3.Thanh pham'!K71 -> 0 | BD15: ='3.Thanh pham'!L71 -> 0 | BE15: ='3.Thanh pham'!M71 -> 0 | BF15: ='3.Thanh pham'!N71 -> 0 | ... BJ15: ='3.Thanh pham'!R71 -> 0 | BK15: =SUM(AY15:BJ15) -> 0
B16: 10 | C16: Chai PET B6.2 | D16: Tấn | F16: ='3.Thanh pham'!G91 -> 215280 | G16: ='3.Thanh pham'!H91 -> 124200 | H16: ='3.Thanh pham'!I91 -> 287560 | I16: ='3.Thanh pham'!J91 -> 0 | J16: ='3.Thanh pham'!K91 -> 0 | K16: ='3.Thanh pham'!L91 -> 0 | L16: ='3.Thanh pham'!M91 -> 0 | M16: ='3.Thanh pham'!N91 -> 0 | ... Q16: ='3.Thanh pham'!R91 -> 0 | R16: =SUM(F16:Q16) -> 627040 | T16: 44511 | U16: 92490 | V16: 111409 | W16: 120159 | X16: 113344 | Y16: 152528 | Z16: 189088 | AA16: 203837 | AB16: 208687 | AC16: 132973 | AD16: 114400 | AE16: 123200 | AF16: =SUM(T16:AE16) -> 1606626 | AH16: 1142923 | AJ16: 447883 | AL16: =IFERROR(R16-AF16,0) -> -979586 | AM16: =IFERROR((R16/AF16)-1,0) -> -0.60971626 | AX16: Chai PET B6.2 | AY16: ='3.Thanh pham'!G72 -> 215280 | AZ16: ='3.Thanh pham'!H72 -> 124200 | BA16: ='3.Thanh pham'!I72 -> 287560 | BB16: ='3.Thanh pham'!J72 -> 345625 | BC16: ='3.Thanh pham'!K72 -> 345625 | BD16: ='3.Thanh pham'!L72 -> 359450 | BE16: ='3.Thanh pham'!M72 -> 373275 | BF16: ='3.Thanh pham'!N72 -> 359450 | ... BJ16: ='3.Thanh pham'!R72 -> 373275 | BK16: =SUM(AY16:BJ16) -> 3834440
B17: 11 | C17: Chai PET B7.1 | D17: Tấn | F17: ='3.Thanh pham'!G92 -> 0 | G17: ='3.Thanh pham'!H92 -> 0 | H17: ='3.Thanh pham'!I92 -> 0 | I17: ='3.Thanh pham'!J92 -> 0 | J17: ='3.Thanh pham'!K92 -> 0 | K17: ='3.Thanh pham'!L92 -> 0 | L17: ='3.Thanh pham'!M92 -> 0 | M17: ='3.Thanh pham'!N92 -> 0 | ... Q17: ='3.Thanh pham'!R92 -> 0 | R17: =SUM(F17:Q17) -> 0 | AF17: =SUM(T17:AE17) -> 0 | AL17: =IFERROR(R17-AF17,0) -> 0 | AM17: =IFERROR((R17/AF17)-1,0) -> 0 | AX17: Chai PET B7.1 | AY17: ='3.Thanh pham'!G73 -> 0 | AZ17: ='3.Thanh pham'!H73 -> 0 | BA17: ='3.Thanh pham'!I73 -> 0 | BB17: ='3.Thanh pham'!J73 -> 0 | BC17: ='3.Thanh pham'!K73 -> 0 | BD17: ='3.Thanh pham'!L73 -> 0 | BE17: ='3.Thanh pham'!M73 -> 0 | BF17: ='3.Thanh pham'!N73 -> 0 | ... BJ17: ='3.Thanh pham'!R73 -> 0 | BK17: =SUM(AY17:BJ17) -> 0
B18: 12 | C18: Chai PET B7.2 | D18: Tấn | F18: ='3.Thanh pham'!G93 -> 0 | G18: ='3.Thanh pham'!H93 -> 0 | H18: ='3.Thanh pham'!I93 -> 0 | I18: ='3.Thanh pham'!J93 -> 0 | J18: ='3.Thanh pham'!K93 -> 0 | K18: ='3.Thanh pham'!L93 -> 0 | L18: ='3.Thanh pham'!M93 -> 0 | M18: ='3.Thanh pham'!N93 -> 0 | ... Q18: ='3.Thanh pham'!R93 -> 0 | R18: =SUM(F18:Q18) -> 0 | T18: 0 | U18: 0 | V18: 3301 | W18: 0 | X18: 0 | Y18: 0 | Z18: 0 | AA18: 0 | AB18: 0 | AD18: 0 | AE18: 0 | AF18: =SUM(T18:AE18) -> 3301 | AL18: =IFERROR(R18-AF18,0) -> -3301 | AM18: =IFERROR((R18/AF18)-1,0) -> -1 | AX18: Chai PET B7.2 | AY18: ='3.Thanh pham'!G74 -> 0 | AZ18: ='3.Thanh pham'!H74 -> 0 | BA18: ='3.Thanh pham'!I74 -> 0 | BB18: ='3.Thanh pham'!J74 -> 0 | BC18: ='3.Thanh pham'!K74 -> 0 | BD18: ='3.Thanh pham'!L74 -> 0 | BE18: ='3.Thanh pham'!M74 -> 0 | BF18: ='3.Thanh pham'!N74 -> 0 | ... BJ18: ='3.Thanh pham'!R74 -> 0 | BK18: =SUM(AY18:BJ18) -> 0
B19: 13 | C19: Cổ Chai PET | D19: Tấn | F19: ='3.Thanh pham'!G94 -> 7800 | G19: ='3.Thanh pham'!H94 -> 4500 | H19: ='3.Thanh pham'!I94 -> 10400 | I19: ='3.Thanh pham'!J94 -> 0 | J19: ='3.Thanh pham'!K94 -> 0 | K19: ='3.Thanh pham'!L94 -> 0 | L19: ='3.Thanh pham'!M94 -> 0 | M19: ='3.Thanh pham'!N94 -> 0 | ... Q19: ='3.Thanh pham'!R94 -> 0 | R19: =SUM(F19:Q19) -> 22700 | T19: 356 | U19: 0 | V19: 0 | W19: 1086 | X19: 1332 | Y19: 1946 | Z19: 2513 | AA19: 5514 | AB19: 3737 | AC19: 3478 | AD19: 2288 | AE19: 2464 | AF19: =SUM(T19:AE19) -> 24714 | AH19: 9282 | AL19: =IFERROR(R19-AF19,0) -> -2014 | AM19: =IFERROR((R19/AF19)-1,0) -> -0.081492272 | AX19: Cổ Chai PET | AY19: ='3.Thanh pham'!G75 -> 7800 | AZ19: ='3.Thanh pham'!H75 -> 4500 | BA19: ='3.Thanh pham'!I75 -> 10400 | BB19: ='3.Thanh pham'!J75 -> 12500 | BC19: ='3.Thanh pham'!K75 -> 12500 | BD19: ='3.Thanh pham'!L75 -> 13000 | BE19: ='3.Thanh pham'!M75 -> 13500 | BF19: ='3.Thanh pham'!N75 -> 13000 | ... BJ19: ='3.Thanh pham'!R75 -> 13500 | BK19: =SUM(AY19:BJ19) -> 138700
B20: 14 | C20: Nắp HD ép các màu | D20: Tấn | F20: ='3.Thanh pham'!G95 -> 7800 | G20: ='3.Thanh pham'!H95 -> 4500 | H20: ='3.Thanh pham'!I95 -> 10400 | I20: ='3.Thanh pham'!J95 -> 0 | J20: ='3.Thanh pham'!K95 -> 0 | K20: ='3.Thanh pham'!L95 -> 0 | L20: ='3.Thanh pham'!M95 -> 0 | M20: ='3.Thanh pham'!N95 -> 0 | ... Q20: ='3.Thanh pham'!R95 -> 0 | R20: =SUM(F20:Q20) -> 22700 | T20: 948 | U20: 0 | V20: 0 | W20: 4052 | X20: 2196 | Y20: 1974 | Z20: 3990 | AA20: 6926 | AB20: 6078 | AC20: 6894 | AD20: 4118 | AE20: 4435 | AF20: =SUM(T20:AE20) -> 41611 | AH20: 21056 | AJ20: 15900 | AL20: =IFERROR(R20-AF20,0) -> -18911 | AM20: =IFERROR((R20/AF20)-1,0) -> -0.45447117 | AX20: Nắp HD ép các màu | AY20: ='3.Thanh pham'!G76 -> 7800 | AZ20: ='3.Thanh pham'!H76 -> 4500 | BA20: ='3.Thanh pham'!I76 -> 10400 | BB20: ='3.Thanh pham'!J76 -> 12500 | BC20: ='3.Thanh pham'!K76 -> 12500 | BD20: ='3.Thanh pham'!L76 -> 13000 | BE20: ='3.Thanh pham'!M76 -> 13500 | BF20: ='3.Thanh pham'!N76 -> 13000 | ... BJ20: ='3.Thanh pham'!R76 -> 13500 | BK20: =SUM(AY20:BJ20) -> 138700
B21: 15 | C21: Khác | D21: Tấn | F21: ='3.Thanh pham'!G96 -> 8580 | G21: ='3.Thanh pham'!H96 -> 4950 | H21: ='3.Thanh pham'!I96 -> 11960 | I21: ='3.Thanh pham'!J96 -> 14375 | J21: ='3.Thanh pham'!K96 -> 14375 | K21: ='3.Thanh pham'!L96 -> 14950 | L21: ='3.Thanh pham'!M96 -> 15525 | M21: ='3.Thanh pham'!N96 -> 14950 | ... Q21: ='3.Thanh pham'!R96 -> 15525 | R21: =SUM(F21:Q21) -> 158890 | Y21: 910 | AB21: 2266 | AF21: =SUM(T21:AE21) -> 3176 | AH21: 31681 | AJ21: =230621-2 -> 230619 | AL21: =IFERROR(R21-AF21,0) -> 155714 | AM21: =IFERROR((R21/AF21)-1,0) -> 49.028338 | AX21: Khác | AY21: ='3.Thanh pham'!G77 -> 8580 | AZ21: ='3.Thanh pham'!H77 -> 4950 | BA21: ='3.Thanh pham'!I77 -> 11960 | BB21: ='3.Thanh pham'!J77 -> 14375 | BC21: ='3.Thanh pham'!K77 -> 14375 | BD21: ='3.Thanh pham'!L77 -> 14950 | BE21: ='3.Thanh pham'!M77 -> 15525 | BF21: ='3.Thanh pham'!N77 -> 14950 | ... BJ21: ='3.Thanh pham'!R77 -> 15525 | BK21: =SUM(AY21:BJ21) -> 158890
C22: TỔNG: | E22: =SUM(E7:E21) -> 0 | F22: =SUM(F7:F21) -> 689520 | G22: =SUM(G7:G21) -> 397800 | H22: =SUM(H7:H21) -> 918840 | I22: =SUM(I7:I21) -> 35312.5 | J22: =SUM(J7:J21) -> 35312.5 | K22: =SUM(K7:K21) -> 36725 | L22: =SUM(L7:L21) -> 38137.5 | ... Q22: =SUM(Q7:Q21) -> 38137.5 | R22: =SUM(F22:Q22) -> 2333860 | T22: =SUM(T7:T21) -> 136817 | U22: =SUM(U7:U21) -> 283539 | V22: =SUM(V7:V21) -> 355698 | W22: =SUM(W7:W21) -> 421533 | X22: =SUM(X7:X21) -> 410449 | Y22: =SUM(Y7:Y21) -> 572586 | Z22: =SUM(Z7:Z21) -> 681432 | AA22: =SUM(AA7:AA21) -> 736186 | ... AE22: =SUM(AE7:AE21) -> 433171 | AF22: =SUM(T22:AE22) -> 5587697 | AH22: =SUM(AH7:AH21) -> 3867466 | AJ22: =SUM(AJ7:AJ21) -> 3125610.5 | AL22: =IFERROR(R22-AF22,0) -> -3253837 | AM22: =IFERROR((R22/AF22)-1,0) -> -0.58232166 | AX22: TỔNG: | AY22: =SUM(AY7:AY21) -> 689520 | AZ22: =SUM(AZ7:AZ21) -> 397800 | BA22: =SUM(BA7:BA21) -> 918840 | BB22: =SUM(BB7:BB21) -> 1104375 | BC22: =SUM(BC7:BC21) -> 1104375 | BD22: =SUM(BD7:BD21) -> 1148550 | BE22: =SUM(BE7:BE21) -> 1192725 | BF22: =SUM(BF7:BF21) -> 1148550 | ... BJ22: =SUM(BJ7:BJ21) -> 1192725 | BK22: =SUM(AY22:BJ22) -> 12254760
B24: 2. Giá bán chai
B25: STT | C25: Thành phẩm (chai sau phân loại) | D25: ĐVT | E25: Tỷ lệ | F25: T1 | G25: T2 | H25: T3 | I25: T4 | J25: T5 | K25: T6 | L25: T7 | M25: T8 | N25: T9 | O25: T10 | P25: T11 | Q25: T12 | R25: KHKD 2026 | T25: T1 | U25: T2 | V25: T3 | W25: T4 | X25: T5 | Y25: T6 | Z25: T7 | AA25: T8 | AB25: T9 | AC25: T10 | AD25: T11 | AE25: T12 | AF25: KQKD 2025 | AH25: KQKD 2024 | AJ25: KQKD 2023 | AL25: +/- 2026 sv 2025 | AM25: +/- % | AO25: Nhóm chai PET | AP25: Thành phần chai PET sau phân loại | AQ25: Đơn giá PET-B0 | AR25: Hao hụt | AT25: GAP (đảm bảo chi phí và lợi nhuận) | AU25: Đơn giá bán theo công thức | AV25: 12/02/2026 | AX25: Thành phẩm (chai sau phân loại) | AY25: T1 | AZ25: T2 | BA25: T3 | BB25: T4 | BC25: T5 | BD25: T6 | BE25: T7 | BF25: T8 | BG25: T9 | BH25: T10 | BI25: T11 | BJ25: T12 | BK25: Mục tiêu 2026
B26: 1 | C26: Chai PET B1 | D26: Đồng/kg | F26: =$AV$27 -> 15000 | G26: =$AV$27 -> 15000 | H26: =$AV$27 -> 15000 | I26: =$AV$27 -> 15000 | J26: =$AV$27 -> 15000 | K26: =$AV$27 -> 15000 | L26: =$AV$27 -> 15000 | M26: =$AV$27 -> 15000 | ... Q26: =$AV$27 -> 15000 | R26: =IFERROR(R45/R7,0) -> 0 | T26: =IFERROR(T45/T7,0) -> 0 | U26: =IFERROR(U45/U7,0) -> 17415.063 | V26: =IFERROR(V45/V7,0) -> 18894.146 | W26: =IFERROR(W45/W7,0) -> 18960 | X26: =IFERROR(X45/X7,0) -> 18960 | Y26: =IFERROR(Y45/Y7,0) -> 18839.17 | Z26: =IFERROR(Z45/Z7,0) -> 19314.771 | AA26: =IFERROR(AA45/AA7,0) -> 19332.546 | ... AF26: =IFERROR(AF45/AF7,0) -> 18864.934 | AH26: =IFERROR(AH45/AH7,0) -> 16542.278 | AJ26: =IFERROR(AJ45/AJ7,0) -> 14954.941 | AL26: =IFERROR(R26-AF26,0) -> -18864.934 | AM26: =IFERROR((R26/AF26)-1,0) -> -1 | AR26: Tỷ lệ | AS26: Quy ra tiền | AX26: Chai PET B1 | AY26: =$AU$27 -> 15100 | AZ26: =$AU$27 -> 15100 | BA26: =$AU$27 -> 15100 | BB26: =$AU$27 -> 15100 | BC26: =$AU$27 -> 15100 | BD26: =$AU$27 -> 15100 | BE26: =$AU$27 -> 15100 | BF26: =$AU$27 -> 15100 | ... BJ26: =$AU$27 -> 15100 | BK26: =IFERROR(BK45/BK7,0) -> 0
B27: 2 | C27: Chai PET B1 Không Phân Loại | D27: Đồng/kg | F27: =$AV$27 -> 15000 | G27: =$AV$27 -> 15000 | H27: =$AV$27 -> 15000 | I27: =$AV$27 -> 15000 | J27: =$AV$27 -> 15000 | K27: =$AV$27 -> 15000 | L27: =$AV$27 -> 15000 | M27: =$AV$27 -> 15000 | ... Q27: =$AV$27 -> 15000 | R27: =IFERROR(R46/R8,0) -> 15000 | T27: =IFERROR(T46/T8,0) -> 17464.77 | U27: =IFERROR(U46/U8,0) -> 17227.522 | V27: =IFERROR(V46/V8,0) -> 17821.682 | W27: =IFERROR(W46/W8,0) -> 18313.937 | X27: =IFERROR(X46/X8,0) -> 18191.374 | Y27: =IFERROR(Y46/Y8,0) -> 18407.874 | Z27: =IFERROR(Z46/Z8,0) -> 18932.929 | AA27: =IFERROR(AA46/AA8,0) -> 18795.802 | ... AF27: =IFERROR(AF46/AF8,0) -> 17083.655 | AH27: =IFERROR(AH46/AH8,0) -> 17097.977 | AJ27: =IFERROR(AJ46/AJ8,0) -> 15966.232 | AL27: =IFERROR(R27-AF27,0) -> -2083.6554 | AM27: =IFERROR((R27/AF27)-1,0) -> -0.12196777 | AO27: Chai PET nhóm 1 | AP27: B1.1 + B1.2 + B1.3 + B2.1 + B3 | AQ27: ='1.NVL Chai'!G25 -> 9700 | AR27: =14% -> 0.14 | AS27: =AQ27*AR27 -> 1358 | AT27: 4000 | AU27: =ROUND(AQ27+AS27+AT27,-2) -> 15100 | AV27: 15000 | AX27: Chai PET B1 Không Phân Loại | AY27: =$AU$27 -> 15100 | AZ27: =$AU$27 -> 15100 | BA27: =$AU$27 -> 15100 | BB27: =$AU$27 -> 15100 | BC27: =$AU$27 -> 15100 | BD27: =$AU$27 -> 15100 | BE27: =$AU$27 -> 15100 | BF27: =$AU$27 -> 15100 | ... BJ27: =$AU$27 -> 15100 | BK27: =IFERROR(BK46/BK8,0) -> 15100
B28: 3 | C28: Chai PET B1.3 | D28: Đồng/kg | F28: =$AV$27 -> 15000 | G28: =$AV$27 -> 15000 | H28: =$AV$27 -> 15000 | I28: =$AV$27 -> 15000 | J28: =$AV$27 -> 15000 | K28: =$AV$27 -> 15000 | L28: =$AV$27 -> 15000 | M28: =$AV$27 -> 15000 | ... Q28: =$AV$27 -> 15000 | R28: =IFERROR(R47/R9,0) -> 0 | T28: =IFERROR(T47/T9,0) -> 17030 | U28: =IFERROR(U47/U9,0) -> 17358.906 | V28: =IFERROR(V47/V9,0) -> 17625.14 | W28: =IFERROR(W47/W9,0) -> 18866.961 | X28: =IFERROR(X47/X9,0) -> 8157.9873 | Y28: =IFERROR(Y47/Y9,0) -> 0 | Z28: =IFERROR(Z47/Z9,0) -> 0 | AA28: =IFERROR(AA47/AA9,0) -> 0 | ... AF28: =IFERROR(AF47/AF9,0) -> 17737.289 | AH28: =IFERROR(AH47/AH9,0) -> 0 | AJ28: =IFERROR(AJ47/AJ9,0) -> 0 | AL28: =IFERROR(R28-AF28,0) -> -17737.289 | AM28: =IFERROR((R28/AF28)-1,0) -> -1 | AO28: Chai PET nhóm 2 | AP28: B4 + B5 | AQ28: =$AQ$27 -> 9700 | AR28: =14% -> 0.14 | AS28: =AQ28*AR28 -> 1358 | AT28: 1000 | AU28: =ROUND(AQ28+AS28+AT28,-2) -> 12100 | AV28: 12000 | AX28: Chai PET B1.3 | AY28: =$AU$27 -> 15100 | AZ28: =$AU$27 -> 15100 | BA28: =$AU$27 -> 15100 | BB28: =$AU$27 -> 15100 | BC28: =$AU$27 -> 15100 | BD28: =$AU$27 -> 15100 | BE28: =$AU$27 -> 15100 | BF28: =$AU$27 -> 15100 | ... BJ28: =$AU$27 -> 15100 | BK28: =IFERROR(BK47/BK9,0) -> 0
B29: 4 | C29: Chai PET B2.1 | D29: Đồng/kg | F29: =$AV$27 -> 15000 | G29: =$AV$27 -> 15000 | H29: =$AV$27 -> 15000 | I29: =$AV$27 -> 15000 | J29: =$AV$27 -> 15000 | K29: =$AV$27 -> 15000 | L29: =$AV$27 -> 15000 | M29: =$AV$27 -> 15000 | ... Q29: =$AV$27 -> 15000 | R29: =IFERROR(R48/R10,0) -> 0 | T29: =IFERROR(T48/T10,0) -> 0 | U29: =IFERROR(U48/U10,0) -> 0 | V29: =IFERROR(V48/V10,0) -> 0 | W29: =IFERROR(W48/W10,0) -> 0 | X29: =IFERROR(X48/X10,0) -> 0 | Y29: =IFERROR(Y48/Y10,0) -> 0 | Z29: =IFERROR(Z48/Z10,0) -> 0 | AA29: =IFERROR(AA48/AA10,0) -> 0 | ... AF29: =IFERROR(AF48/AF10,0) -> 0 | AH29: =IFERROR(AH48/AH10,0) -> 0 | AJ29: =IFERROR(AJ48/AJ10,0) -> 10409.382 | AL29: =IFERROR(R29-AF29,0) -> 0 | AM29: =IFERROR((R29/AF29)-1,0) -> 0 | AO29: Chai PET nhóm 3 | AP29: B2.2 + B6.1 + B6.2 | AQ29: =$AQ$27 -> 9700 | AR29: =14% -> 0.14 | AS29: =AQ29*AR29 -> 1358 | AT29: 2500 | AU29: =ROUND(AQ29+AS29+AT29,-2) -> 13600 | AV29: 13500 | AX29: Chai PET B2.1 | AY29: =$AU$27 -> 15100 | AZ29: =$AU$27 -> 15100 | BA29: =$AU$27 -> 15100 | BB29: =$AU$27 -> 15100 | BC29: =$AU$27 -> 15100 | BD29: =$AU$27 -> 15100 | BE29: =$AU$27 -> 15100 | BF29: =$AU$27 -> 15100 | ... BJ29: =$AU$27 -> 15100 | BK29: =IFERROR(BK48/BK10,0) -> 0
B30: 5 | C30: Chai PET B2.2 | D30: Đồng/kg | F30: =$AV$29 -> 13500 | G30: =$AV$29 -> 13500 | H30: =$AV$29 -> 13500 | I30: =$AV$29 -> 13500 | J30: =$AV$29 -> 13500 | K30: =$AV$29 -> 13500 | L30: =$AV$29 -> 13500 | M30: =$AV$29 -> 13500 | ... Q30: =$AV$29 -> 13500 | R30: =IFERROR(R49/R11,0) -> 13500 | T30: =IFERROR(T49/T11,0) -> 15267.218 | U30: =IFERROR(U49/U11,0) -> 17241.658 | V30: =IFERROR(V49/V11,0) -> 17748.461 | W30: =IFERROR(W49/W11,0) -> 18437.939 | X30: =IFERROR(X49/X11,0) -> 17951.257 | Y30: =IFERROR(Y49/Y11,0) -> 18418.044 | Z30: =IFERROR(Z49/Z11,0) -> 18913.05 | AA30: =IFERROR(AA49/AA11,0) -> 18803.792 | ... AF30: =IFERROR(AF49/AF11,0) -> 16601.673 | AH30: =IFERROR(AH49/AH11,0) -> 13447.393 | AJ30: =IFERROR(AJ49/AJ11,0) -> 11104.765 | AL30: =IFERROR(R30-AF30,0) -> -3101.6729 | AM30: =IFERROR((R30/AF30)-1,0) -> -0.18682894 | AO30: Chai PET nhóm 4 | AP30: Nắp HD ép, cổ chai, PP (Quai) | AQ30: =$AQ$27 -> 9700 | AR30: =14% -> 0.14 | AS30: =AQ30*AR30 -> 1358 | AT30: -4000 | AU30: =ROUND(AQ30+AS30+AT30,-2) -> 7100 | AV30: 8100 | AX30: Chai PET B2.2 | AY30: =$AU$29 -> 13600 | AZ30: =$AU$29 -> 13600 | BA30: =$AU$29 -> 13600 | BB30: =$AU$29 -> 13600 | BC30: =$AU$29 -> 13600 | BD30: =$AU$29 -> 13600 | BE30: =$AU$29 -> 13600 | BF30: =$AU$29 -> 13600 | ... BJ30: =$AU$29 -> 13600 | BK30: =IFERROR(BK49/BK11,0) -> 13600
B31: 6 | C31: Chai PET B3 | D31: Đồng/kg | F31: =$AV$27 -> 15000 | G31: =$AV$27 -> 15000 | H31: =$AV$27 -> 15000 | I31: =$AV$27 -> 15000 | J31: =$AV$27 -> 15000 | K31: =$AV$27 -> 15000 | L31: =$AV$27 -> 15000 | M31: =$AV$27 -> 15000 | ... Q31: =$AV$27 -> 15000 | R31: =IFERROR(R50/R12,0) -> 0 | T31: =IFERROR(T50/T12,0) -> 0 | U31: =IFERROR(U50/U12,0) -> 0 | V31: =IFERROR(V50/V12,0) -> 0 | W31: =IFERROR(W50/W12,0) -> 0 | X31: =IFERROR(X50/X12,0) -> 0 | Y31: =IFERROR(Y50/Y12,0) -> 0 | Z31: =IFERROR(Z50/Z12,0) -> 0 | AA31: =IFERROR(AA50/AA12,0) -> 0 | ... AF31: =IFERROR(AF50/AF12,0) -> 0 | AH31: =IFERROR(AH50/AH12,0) -> 16500 | AJ31: =IFERROR(AJ50/AJ12,0) -> 15775.951 | AL31: =IFERROR(R31-AF31,0) -> 0 | AM31: =IFERROR((R31/AF31)-1,0) -> 0 | AO31: Chai PET nhóm 4 | AP31: Phó sản | AQ31: =$AQ$27 -> 9700 | AR31: =14% -> 0.14 | AS31: =AQ31*AR31 -> 1358 | AT31: -9400 | AU31: =ROUND(AQ31+AS31+AT31,-2) -> 1700 | AV31: =AU31 -> 1700 | AX31: Chai PET B3 | AY31: =$AU$27 -> 15100 | AZ31: =$AU$27 -> 15100 | BA31: =$AU$27 -> 15100 | BB31: =$AU$27 -> 15100 | BC31: =$AU$27 -> 15100 | BD31: =$AU$27 -> 15100 | BE31: =$AU$27 -> 15100 | BF31: =$AU$27 -> 15100 | ... BJ31: =$AU$27 -> 15100 | BK31: =IFERROR(BK50/BK12,0) -> 0
B32: 7 | C32: Chai PET B4 | D32: Đồng/kg | F32: =$AV$28 -> 12000 | G32: =$AV$28 -> 12000 | H32: =$AV$28 -> 12000 | I32: =$AV$28 -> 12000 | J32: =$AV$28 -> 12000 | K32: =$AV$28 -> 12000 | L32: =$AV$28 -> 12000 | M32: =$AV$28 -> 12000 | ... Q32: =$AV$28 -> 12000 | R32: =IFERROR(R51/R13,0) -> 12000 | T32: =IFERROR(T51/T13,0) -> 14300 | U32: =IFERROR(U51/U13,0) -> 17094.484 | V32: =IFERROR(V51/V13,0) -> 17612.079 | W32: =IFERROR(W51/W13,0) -> 18658.253 | X32: =IFERROR(X51/X13,0) -> 17848.039 | Y32: =IFERROR(Y51/Y13,0) -> 18451.369 | Z32: =IFERROR(Z51/Z13,0) -> 18930.368 | AA32: =IFERROR(AA51/AA13,0) -> 18792.343 | ... AF32: =IFERROR(AF51/AF13,0) -> 16073.925 | AH32: =IFERROR(AH51/AH13,0) -> 13336.365 | AJ32: =IFERROR(AJ51/AJ13,0) -> 10211.841 | AL32: =IFERROR(R32-AF32,0) -> -4073.9247 | AM32: =IFERROR((R32/AF32)-1,0) -> -0.25344928 | AX32: Chai PET B4 | AY32: =$AU$28 -> 12100 | AZ32: =$AU$28 -> 12100 | BA32: =$AU$28 -> 12100 | BB32: =$AU$28 -> 12100 | BC32: =$AU$28 -> 12100 | BD32: =$AU$28 -> 12100 | BE32: =$AU$28 -> 12100 | BF32: =$AU$28 -> 12100 | ... BJ32: =$AU$28 -> 12100 | BK32: =IFERROR(BK51/BK13,0) -> 12100
B33: 8 | C33: Chai PET B5 | D33: Đồng/kg | F33: =$AV$28 -> 12000 | G33: =$AV$28 -> 12000 | H33: =$AV$28 -> 12000 | I33: =$AV$28 -> 12000 | J33: =$AV$28 -> 12000 | K33: =$AV$28 -> 12000 | L33: =$AV$28 -> 12000 | M33: =$AV$28 -> 12000 | ... Q33: =$AV$28 -> 12000 | R33: =IFERROR(R52/R14,0) -> 12000 | T33: =IFERROR(T52/T14,0) -> 14485.792 | U33: =IFERROR(U52/U14,0) -> 17285.993 | V33: =IFERROR(V52/V14,0) -> 17661.415 | W33: =IFERROR(W52/W14,0) -> 18353.474 | X33: =IFERROR(X52/X14,0) -> 17902.203 | Y33: =IFERROR(Y52/Y14,0) -> 18482.74 | Z33: =IFERROR(Z52/Z14,0) -> 18897.672 | AA33: =IFERROR(AA52/AA14,0) -> 18787.765 | ... AF33: =IFERROR(AF52/AF14,0) -> 15955.852 | AH33: =IFERROR(AH52/AH14,0) -> 13294.751 | AJ33: =IFERROR(AJ52/AJ14,0) -> 11182.905 | AL33: =IFERROR(R33-AF33,0) -> -3955.8522 | AM33: =IFERROR((R33/AF33)-1,0) -> -0.24792485 | AX33: Chai PET B5 | AY33: =$AU$28 -> 12100 | AZ33: =$AU$28 -> 12100 | BA33: =$AU$28 -> 12100 | BB33: =$AU$28 -> 12100 | BC33: =$AU$28 -> 12100 | BD33: =$AU$28 -> 12100 | BE33: =$AU$28 -> 12100 | BF33: =$AU$28 -> 12100 | ... BJ33: =$AU$28 -> 12100 | BK33: =IFERROR(BK52/BK14,0) -> 12100
B34: 9 | C34: Chai PET B6.1 | D34: Đồng/kg | F34: =$AV$29 -> 13500 | G34: =$AV$29 -> 13500 | H34: =$AV$29 -> 13500 | I34: =$AV$29 -> 13500 | J34: =$AV$29 -> 13500 | K34: =$AV$29 -> 13500 | L34: =$AV$29 -> 13500 | M34: =$AV$29 -> 13500 | ... Q34: =$AV$29 -> 13500 | R34: =IFERROR(R53/R15,0) -> 0 | T34: =IFERROR(T53/T15,0) -> 0 | U34: =IFERROR(U53/U15,0) -> 0 | V34: =IFERROR(V53/V15,0) -> 0 | W34: =IFERROR(W53/W15,0) -> 0 | X34: =IFERROR(X53/X15,0) -> 0 | Y34: =IFERROR(Y53/Y15,0) -> 0 | Z34: =IFERROR(Z53/Z15,0) -> 0 | AA34: =IFERROR(AA53/AA15,0) -> 0 | ... AF34: =IFERROR(AF53/AF15,0) -> 0 | AH34: =IFERROR(AH53/AH15,0) -> 6233.739 | AJ34: =IFERROR(AJ53/AJ15,0) -> 10284.734 | AL34: =IFERROR(R34-AF34,0) -> 0 | AM34: =IFERROR((R34/AF34)-1,0) -> 0 | AX34: Chai PET B6.1 | AY34: =$AU$29 -> 13600 | AZ34: =$AU$29 -> 13600 | BA34: =$AU$29 -> 13600 | BB34: =$AU$29 -> 13600 | BC34: =$AU$29 -> 13600 | BD34: =$AU$29 -> 13600 | BE34: =$AU$29 -> 13600 | BF34: =$AU$29 -> 13600 | ... BJ34: =$AU$29 -> 13600 | BK34: =IFERROR(BK53/BK15,0) -> 0
B35: 10 | C35: Chai PET B6.2 | D35: Đồng/kg | F35: =$AV$29 -> 13500 | G35: =$AV$29 -> 13500 | H35: =$AV$29 -> 13500 | I35: =$AV$29 -> 13500 | J35: =$AV$29 -> 13500 | K35: =$AV$29 -> 13500 | L35: =$AV$29 -> 13500 | M35: =$AV$29 -> 13500 | ... Q35: =$AV$29 -> 13500 | R35: =IFERROR(R54/R16,0) -> 13500 | T35: =IFERROR(T54/T16,0) -> 14294.264 | U35: =IFERROR(U54/U16,0) -> 17307.649 | V35: =IFERROR(V54/V16,0) -> 17794.78 | W35: =IFERROR(W54/W16,0) -> 18572.793 | X35: =IFERROR(X54/X16,0) -> 18022.492 | Y35: =IFERROR(Y54/Y16,0) -> 18519.764 | Z35: =IFERROR(Z54/Z16,0) -> 18972.815 | AA35: =IFERROR(AA54/AA16,0) -> 18834.179 | ... AF35: =IFERROR(AF54/AF16,0) -> 16657.797 | AH35: =IFERROR(AH54/AH16,0) -> 12394.152 | AJ35: =IFERROR(AJ54/AJ16,0) -> 10189.615 | AL35: =IFERROR(R35-AF35,0) -> -3157.7973 | AM35: =IFERROR((R35/AF35)-1,0) -> -0.18956872 | AX35: Chai PET B6.2 | AY35: =$AU$29 -> 13600 | AZ35: =$AU$29 -> 13600 | BA35: =$AU$29 -> 13600 | BB35: =$AU$29 -> 13600 | BC35: =$AU$29 -> 13600 | BD35: =$AU$29 -> 13600 | BE35: =$AU$29 -> 13600 | BF35: =$AU$29 -> 13600 | ... BJ35: =$AU$29 -> 13600 | BK35: =IFERROR(BK54/BK16,0) -> 13600
B36: 11 | C36: Chai PET B7.1 | D36: Đồng/kg | F36: =$AV$28 -> 12000 | G36: =$AV$28 -> 12000 | H36: =$AV$28 -> 12000 | I36: =$AV$28 -> 12000 | J36: =$AV$28 -> 12000 | K36: =$AV$28 -> 12000 | L36: =$AV$28 -> 12000 | M36: =$AV$28 -> 12000 | ... Q36: =$AV$28 -> 12000 | R36: =IFERROR(R55/R17,0) -> 0 | T36: =IFERROR(T55/T17,0) -> 0 | U36: =IFERROR(U55/U17,0) -> 0 | V36: =IFERROR(V55/V17,0) -> 0 | W36: =IFERROR(W55/W17,0) -> 0 | X36: =IFERROR(X55/X17,0) -> 0 | Y36: =IFERROR(Y55/Y17,0) -> 0 | Z36: =IFERROR(Z55/Z17,0) -> 0 | AA36: =IFERROR(AA55/AA17,0) -> 0 | ... AF36: =IFERROR(AF55/AF17,0) -> 0 | AH36: =IFERROR(AH55/AH17,0) -> 0 | AJ36: =IFERROR(AJ55/AJ17,0) -> 0 | AL36: =IFERROR(R36-AF36,0) -> 0 | AM36: =IFERROR((R36/AF36)-1,0) -> 0 | AX36: Chai PET B7.1 | AY36: =$AU$28 -> 12100 | AZ36: =$AU$28 -> 12100 | BA36: =$AU$28 -> 12100 | BB36: =$AU$28 -> 12100 | BC36: =$AU$28 -> 12100 | BD36: =$AU$28 -> 12100 | BE36: =$AU$28 -> 12100 | BF36: =$AU$28 -> 12100 | ... BJ36: =$AU$28 -> 12100 | BK36: =IFERROR(BK55/BK17,0) -> 0
B37: 12 | C37: Chai PET B7.2 | D37: Đồng/kg | F37: =$AV$28 -> 12000 | G37: =$AV$28 -> 12000 | H37: =$AV$28 -> 12000 | I37: =$AV$28 -> 12000 | J37: =$AV$28 -> 12000 | K37: =$AV$28 -> 12000 | L37: =$AV$28 -> 12000 | M37: =$AV$28 -> 12000 | ... Q37: =$AV$28 -> 12000 | R37: =IFERROR(R56/R18,0) -> 0 | T37: =IFERROR(T56/T18,0) -> 0 | U37: =IFERROR(U56/U18,0) -> 0 | V37: =IFERROR(V56/V18,0) -> 8000 | W37: =IFERROR(W56/W18,0) -> 0 | X37: =IFERROR(X56/X18,0) -> 0 | Y37: =IFERROR(Y56/Y18,0) -> 0 | Z37: =IFERROR(Z56/Z18,0) -> 0 | AA37: =IFERROR(AA56/AA18,0) -> 0 | ... AF37: =IFERROR(AF56/AF18,0) -> 8000 | AH37: =IFERROR(AH56/AH18,0) -> 0 | AJ37: =IFERROR(AJ56/AJ18,0) -> 0 | AL37: =IFERROR(R37-AF37,0) -> -8000 | AM37: =IFERROR((R37/AF37)-1,0) -> -1 | AX37: Chai PET B7.2 | AY37: =$AU$28 -> 12100 | AZ37: =$AU$28 -> 12100 | BA37: =$AU$28 -> 12100 | BB37: =$AU$28 -> 12100 | BC37: =$AU$28 -> 12100 | BD37: =$AU$28 -> 12100 | BE37: =$AU$28 -> 12100 | BF37: =$AU$28 -> 12100 | ... BJ37: =$AU$28 -> 12100 | BK37: =IFERROR(BK56/BK18,0) -> 0
B38: 13 | C38: Cổ Chai PET | D38: Đồng/kg | F38: =$AV$30 -> 8100 | G38: =$AV$30 -> 8100 | H38: =$AV$30 -> 8100 | I38: =$AV$30 -> 8100 | J38: =$AV$30 -> 8100 | K38: =$AV$30 -> 8100 | L38: =$AV$30 -> 8100 | M38: =$AV$30 -> 8100 | ... Q38: =$AV$30 -> 8100 | R38: =IFERROR(R57/R19,0) -> 8100 | T38: =IFERROR(T57/T19,0) -> 14000 | U38: =IFERROR(U57/U19,0) -> 0 | V38: =IFERROR(V57/V19,0) -> 0 | W38: =IFERROR(W57/W19,0) -> 10000 | X38: =IFERROR(X57/X19,0) -> 10000 | Y38: =IFERROR(Y57/Y19,0) -> 10000 | Z38: =IFERROR(Z57/Z19,0) -> 10000 | AA38: =IFERROR(AA57/AA19,0) -> 10000 | ... AF38: =IFERROR(AF57/AF19,0) -> 8510.8441 | AH38: =IFERROR(AH57/AH19,0) -> 14000 | AJ38: =IFERROR(AJ57/AJ19,0) -> 0 | AL38: =IFERROR(R38-AF38,0) -> -410.84406 | AM38: =IFERROR((R38/AF38)-1,0) -> -0.04827301 | AX38: Cổ Chai PET | AY38: =$AU$30 -> 7100 | AZ38: =$AU$30 -> 7100 | BA38: =$AU$30 -> 7100 | BB38: =$AU$30 -> 7100 | BC38: =$AU$30 -> 7100 | BD38: =$AU$30 -> 7100 | BE38: =$AU$30 -> 7100 | BF38: =$AU$30 -> 7100 | ... BJ38: =$AU$30 -> 7100 | BK38: =IFERROR(BK57/BK19,0) -> 7100
B39: 14 | C39: Nắp HD ép các màu | D39: Đồng/kg | F39: =$AV$30 -> 8100 | G39: =$AV$30 -> 8100 | H39: =$AV$30 -> 8100 | I39: =$AV$30 -> 8100 | J39: =$AV$30 -> 8100 | K39: =$AV$30 -> 8100 | L39: =$AV$30 -> 8100 | M39: =$AV$30 -> 8100 | ... Q39: =$AV$30 -> 8100 | R39: =IFERROR(R58/R20,0) -> 8100 | T39: =IFERROR(T58/T20,0) -> 14300 | U39: =IFERROR(U58/U20,0) -> 0 | V39: =IFERROR(V58/V20,0) -> 0 | W39: =IFERROR(W58/W20,0) -> 10000 | X39: =IFERROR(X58/X20,0) -> 10000 | Y39: =IFERROR(Y58/Y20,0) -> 10000 | Z39: =IFERROR(Z58/Z20,0) -> 10000 | AA39: =IFERROR(AA58/AA20,0) -> 10000 | ... AF39: =IFERROR(AF58/AF20,0) -> 8416.1616 | AH39: =IFERROR(AH58/AH20,0) -> 13268.892 | AJ39: =IFERROR(AJ58/AJ20,0) -> 13000 | AL39: =IFERROR(R39-AF39,0) -> -316.16159 | AM39: =IFERROR((R39/AF39)-1,0) -> -0.037566008 | AX39: Nắp HD ép các màu | AY39: =$AU$30 -> 7100 | AZ39: =$AU$30 -> 7100 | BA39: =$AU$30 -> 7100 | BB39: =$AU$30 -> 7100 | BC39: =$AU$30 -> 7100 | BD39: =$AU$30 -> 7100 | BE39: =$AU$30 -> 7100 | BF39: =$AU$30 -> 7100 | ... BJ39: =$AU$30 -> 7100 | BK39: =IFERROR(BK58/BK20,0) -> 7100
B40: 15 | C40: Khác | D40: Đồng/kg | F40: =$AV$30 -> 8100 | G40: =$AV$30 -> 8100 | H40: =$AV$30 -> 8100 | I40: =$AV$30 -> 8100 | J40: =$AV$30 -> 8100 | K40: =$AV$30 -> 8100 | L40: =$AV$30 -> 8100 | M40: =$AV$30 -> 8100 | ... Q40: =$AV$30 -> 8100 | R40: =IFERROR(R59/R21,0) -> 8100 | T40: =IFERROR(T59/T21,0) -> 0 | U40: =IFERROR(U59/U21,0) -> 0 | V40: =IFERROR(V59/V21,0) -> 0 | W40: =IFERROR(W59/W21,0) -> 0 | X40: =IFERROR(X59/X21,0) -> 0 | Y40: =IFERROR(Y59/Y21,0) -> 15500 | Z40: =IFERROR(Z59/Z21,0) -> 0 | AA40: =IFERROR(AA59/AA21,0) -> 0 | ... AF40: =IFERROR(AF59/AF21,0) -> 16213.476 | AH40: =IFERROR(AH59/AH21,0) -> 11844.38 | AJ40: =IFERROR(AJ59/AJ21,0) -> 18571.55 | AL40: =IFERROR(R40-AF40,0) -> -8113.4761 | AM40: =IFERROR((R40/AF40)-1,0) -> -0.50041558 | AX40: Khác | AY40: =$AU$30 -> 7100 | AZ40: =$AU$30 -> 7100 | BA40: =$AU$30 -> 7100 | BB40: =$AU$30 -> 7100 | BC40: =$AU$30 -> 7100 | BD40: =$AU$30 -> 7100 | BE40: =$AU$30 -> 7100 | BF40: =$AU$30 -> 7100 | ... BJ40: =$AU$30 -> 7100 | BK40: =IFERROR(BK59/BK21,0) -> 7100
C41: Giá bán Trung bình | F41: =F60/F22 -> 14075.905 | G41: =G60/G22 -> 14075.905 | H41: =H60/H22 -> 14071.902 | I41: =I60/I22 -> 10412.389 | J41: =J60/J22 -> 10412.389 | K41: =K60/K22 -> 10412.389 | L41: =L60/L22 -> 10412.389 | M41: =M60/M22 -> 10412.389 | ... Q41: =Q60/Q22 -> 10412.389 | R41: =IFERROR(R60/R22,0) -> 13559.93 | T41: =IFERROR(T60/T22,0) -> 15963.15 | U41: =IFERROR(U60/U22,0) -> 17303.368 | V41: =IFERROR(V60/V22,0) -> 17806.27 | W41: =IFERROR(W60/W22,0) -> 18520.657 | X41: =IFERROR(X60/X22,0) -> 17980.668 | Y41: =IFERROR(Y60/Y22,0) -> 18436.991 | Z41: =IFERROR(Z60/Z22,0) -> 18894.257 | AA41: =IFERROR(AA60/AA22,0) -> 18695.304 | ... AF41: =IFERROR(AF60/AF22,0) -> 16926.353 | AH41: =IFERROR(AH60/AH22,0) -> 15111.147 | AJ41: =IFERROR(AJ60/AJ22,0) -> 14231.464 | AL41: =IFERROR(R41-AF41,0) -> -3366.4231 | AM41: =IFERROR((R41/AF41)-1,0) -> -0.19888649 | AX41: Giá bán Trung bình | AY41: =AY60/AY22 -> 14137.33 | AZ41: =AZ60/AZ22 -> 14137.33 | BA41: =BA60/BA22 -> 14132.683 | BB41: =BB60/BB22 -> 14132.683 | BC41: =BC60/BC22 -> 14132.683 | BD41: =BD60/BD22 -> 14132.683 | BE41: =BE60/BE22 -> 14132.683 | BF41: =BF60/BF22 -> 14132.683 | ... BJ41: =BJ60/BJ22 -> 14132.683 | BK41: =IFERROR(BK60/BK22,0) -> 14133.095
B43: 3. Doanh thu chai
B44: STT | C44: Thành phẩm (chai sau phân loại) | D44: ĐVT | E44: Tỷ lệ | F44: T1 | G44: T2 | H44: T3 | I44: T4 | J44: T5 | K44: T6 | L44: T7 | M44: T8 | N44: T9 | O44: T10 | P44: T11 | Q44: T12 | R44: KHKD 2026 | T44: T1 | U44: T2 | V44: T3 | W44: T4 | X44: T5 | Y44: T6 | Z44: T7 | AA44: T8 | AB44: T9 | AC44: T10 | AD44: T11 | AE44: T12 | AF44: KQKD 2025 | AH44: KQKD 2024 | AJ44: KQKD 2023 | AL44: +/- 2026 sv 2025 | AM44: +/- % | AX44: Thành phẩm (chai sau phân loại) | AY44: T1 | AZ44: T2 | BA44: T3 | BB44: T4 | BC44: T5 | BD44: T6 | BE44: T7 | BF44: T8 | BG44: T9 | BH44: T10 | BI44: T11 | BJ44: T12 | BK44: Mục tiêu 2026
B45: 1 | C45: Chai PET B1 | D45: Triệu đ | F45: =F7*F26 -> 0 | G45: =G7*G26 -> 0 | H45: =H7*H26 -> 0 | I45: =I7*I26 -> 0 | J45: =J7*J26 -> 0 | K45: =K7*K26 -> 0 | L45: =L7*L26 -> 0 | M45: =M7*M26 -> 0 | ... Q45: =Q7*Q26 -> 0 | R45: =SUM(F45:Q45) -> 0 | T45: 0 | U45: 345044643 | V45: 948070470 | W45: 1321075920 | X45: 676284240 | Y45: 1473882481 | Z45: 1297875360 | AA45: 982325340 | AB45: 101895000 | AC45: 32880000 | AD45: 0 | AE45: 0 | AF45: =SUM(T45:AE45) -> 7179333454 | AH45: 499461000 | AJ45: 15529450500 | AL45: =IFERROR(R45-AF45,0) -> -7179333454 | AM45: =IFERROR((R45/AF45)-1,0) -> -1 | AX45: Chai PET B1 | AY45: =AY7*AY26 -> 0 | AZ45: =AZ7*AZ26 -> 0 | BA45: =BA7*BA26 -> 0 | BB45: =BB7*BB26 -> 0 | BC45: =BC7*BC26 -> 0 | BD45: =BD7*BD26 -> 0 | BE45: =BE7*BE26 -> 0 | BF45: =BF7*BF26 -> 0 | ... BJ45: =BJ7*BJ26 -> 0 | BK45: =SUM(AY45:BJ45) -> 0
B46: 2 | C46: Chai PET B1 Không Phân Loại | D46: Triệu đ | F46: =F8*F27 -> 5475600000 | G46: =G8*G27 -> 3159000000 | H46: =H8*H27 -> 7285200000 | I46: =I8*I27 -> 0 | J46: =J8*J27 -> 0 | K46: =K8*K27 -> 0 | L46: =L8*L27 -> 0 | M46: =M8*M27 -> 0 | ... Q46: =Q8*Q27 -> 0 | R46: =SUM(F46:Q46) -> 15919800000 | T46: 1080003890 | U46: 784920369 | V46: 802403390 | W46: 1696273436 | X46: 3588666885 | Y46: 4993209420 | Z46: 6436343840 | AA46: 7321096440 | AB46: 5458961960 | AC46: 4314750000 | AD46: 3432000000 | AE46: 3696000000 | AF46: =SUM(T46:AE46) -> 43604629630 | AH46: 36573050700 | AJ46: 8053710750 | AL46: =IFERROR(R46-AF46,0) -> -27684829630 | AM46: =IFERROR((R46/AF46)-1,0) -> -0.63490574 | AX46: Chai PET B1 Không Phân Loại | AY46: =AY8*AY27 -> 5512104000 | AZ46: =AZ8*AZ27 -> 3180060000 | BA46: =BA8*BA27 -> 7333768000 | BB46: =BB8*BB27 -> 8814625000 | BC46: =BC8*BC27 -> 8814625000 | BD46: =BD8*BD27 -> 9167210000 | BE46: =BE8*BE27 -> 9519795000 | BF46: =BF8*BF27 -> 9167210000 | ... BJ46: =BJ8*BJ27 -> 9519795000 | BK46: =SUM(AY46:BJ46) -> 97825652000
B47: 3 | C47: Chai PET B1.3 | D47: Triệu đ | F47: =F9*F28 -> 0 | G47: =G9*G28 -> 0 | H47: =H9*H28 -> 0 | I47: =I9*I28 -> 0 | J47: =J9*J28 -> 0 | K47: =K9*K28 -> 0 | L47: =L9*L28 -> 0 | M47: =M9*M28 -> 0 | ... Q47: =Q9*Q28 -> 0 | R47: =SUM(F47:Q47) -> 0 | T47: 86427250 | U47: 1423430267 | V47: 1699345532 | W47: 1579466488 | X47: 41850475 | Y47: 0 | Z47: 0 | AA47: 0 | AB47: 0 | AD47: 0 | AE47: 0 | AF47: =SUM(T47:AE47) -> 4830520012 | AL47: =IFERROR(R47-AF47,0) -> -4830520012 | AM47: =IFERROR((R47/AF47)-1,0) -> -1 | AX47: Chai PET B1.3 | AY47: =AY9*AY28 -> 0 | AZ47: =AZ9*AZ28 -> 0 | BA47: =BA9*BA28 -> 0 | BB47: =BB9*BB28 -> 0 | BC47: =BC9*BC28 -> 0 | BD47: =BD9*BD28 -> 0 | BE47: =BE9*BE28 -> 0 | BF47: =BF9*BF28 -> 0 | ... BJ47: =BJ9*BJ28 -> 0 | BK47: =SUM(AY47:BJ47) -> 0
B48: 4 | C48: Chai PET B2.1 | D48: Triệu đ | F48: =F10*F29 -> 0 | G48: =G10*G29 -> 0 | H48: =H10*H29 -> 0 | I48: =I10*I29 -> 0 | J48: =J10*J29 -> 0 | K48: =K10*K29 -> 0 | L48: =L10*L29 -> 0 | M48: =M10*M29 -> 0 | ... Q48: =Q10*Q29 -> 0 | R48: =SUM(F48:Q48) -> 0 | AF48: =SUM(T48:AE48) -> 0 | AJ48: 1238419750 | AL48: =IFERROR(R48-AF48,0) -> 0 | AM48: =IFERROR((R48/AF48)-1,0) -> 0 | AX48: Chai PET B2.1 | AY48: =AY10*AY29 -> 0 | AZ48: =AZ10*AZ29 -> 0 | BA48: =BA10*BA29 -> 0 | BB48: =BB10*BB29 -> 0 | BC48: =BC10*BC29 -> 0 | BD48: =BD10*BD29 -> 0 | BE48: =BE10*BE29 -> 0 | BF48: =BF10*BF29 -> 0 | ... BJ48: =BJ10*BJ29 -> 0 | BK48: =SUM(AY48:BJ48) -> 0
B49: 5 | C49: Chai PET B2.2 | D49: Triệu đ | F49: =F11*F30 -> 968760000 | G49: =G11*G30 -> 558900000 | H49: =H11*H30 -> 1288170000 | I49: =I11*I30 -> 0 | J49: =J11*J30 -> 0 | K49: =K11*K30 -> 0 | L49: =L11*L30 -> 0 | M49: =M11*M30 -> 0 | ... Q49: =Q11*Q30 -> 0 | R49: =SUM(F49:Q49) -> 2815830000 | T49: 281176350 | U49: 545543305 | V49: 682925297 | W49: 695091866 | X49: 771850205 | Y49: 888596970 | Z49: 1093836230 | AA49: 1065404040 | AB49: 945594500 | AC49: 581202000 | AD49: 494208000 | AE49: 532224000 | AF49: =SUM(T49:AE49) -> 8577652763 | AH49: 4229958050 | AJ49: 2221891388 | AL49: =IFERROR(R49-AF49,0) -> -5761822763 | AM49: =IFERROR((R49/AF49)-1,0) -> -0.67172488 | AX49: Chai PET B2.2 | AY49: =AY11*AY30 -> 975936000 | AZ49: =AZ11*AZ30 -> 563040000 | BA49: =BA11*BA30 -> 1297712000 | BB49: =BB11*BB30 -> 1559750000 | BC49: =BC11*BC30 -> 1559750000 | BD49: =BD11*BD30 -> 1622140000 | BE49: =BE11*BE30 -> 1684530000 | BF49: =BF11*BF30 -> 1622140000 | ... BJ49: =BJ11*BJ30 -> 1684530000 | BK49: =SUM(AY49:BJ49) -> 17311168000
B50: 6 | C50: Chai PET B3 | D50: Triệu đ | F50: =F12*F31 -> 0 | G50: =G12*G31 -> 0 | H50: =H12*H31 -> 0 | I50: =I12*I31 -> 0 | J50: =J12*J31 -> 0 | K50: =K12*K31 -> 0 | L50: =L12*L31 -> 0 | M50: =M12*M31 -> 0 | ... Q50: =Q12*Q31 -> 0 | R50: =SUM(F50:Q50) -> 0 | AF50: =SUM(T50:AE50) -> 0 | AH50: 122050500 | AJ50: 7194906500 | AL50: =IFERROR(R50-AF50,0) -> 0 | AM50: =IFERROR((R50/AF50)-1,0) -> 0 | AX50: Chai PET B3 | AY50: =AY12*AY31 -> 0 | AZ50: =AZ12*AZ31 -> 0 | BA50: =BA12*BA31 -> 0 | BB50: =BB12*BB31 -> 0 | BC50: =BC12*BC31 -> 0 | BD50: =BD12*BD31 -> 0 | BE50: =BE12*BE31 -> 0 | BF50: =BF12*BF31 -> 0 | ... BJ50: =BJ12*BJ31 -> 0 | BK50: =SUM(AY50:BJ50) -> 0
B51: 7 | C51: Chai PET B4 | D51: Triệu đ | F51: =F13*F32 -> 93600000 | G51: =G13*G32 -> 54000000 | H51: =H13*H32 -> 124800000 | I51: =I13*I32 -> 150000000 | J51: =J13*J32 -> 150000000 | K51: =K13*K32 -> 156000000 | L51: =L13*L32 -> 162000000 | M51: =M13*M32 -> 156000000 | ... Q51: =Q13*Q32 -> 162000000 | R51: =SUM(F51:Q51) -> 1664400000 | T51: 39911300 | U51: 137969577 | V51: 130258933 | W51: 138966668 | X51: 147264170 | Y51: 195289290 | Z51: 244902170 | AA51: 287842320 | AB51: 171674500 | AC51: 137172000 | AD51: 114400000 | AE51: 123200000 | AF51: =SUM(T51:AE51) -> 1868850928 | AH51: 1117427350 | AJ51: 427018363 | AL51: =IFERROR(R51-AF51,0) -> -204450928 | AM51: =IFERROR((R51/AF51)-1,0) -> -0.10939927 | AX51: Chai PET B4 | AY51: =AY13*AY32 -> 94380000 | AZ51: =AZ13*AZ32 -> 54450000 | BA51: =BA13*BA32 -> 125840000 | BB51: =BB13*BB32 -> 151250000 | BC51: =BC13*BC32 -> 151250000 | BD51: =BD13*BD32 -> 157300000 | BE51: =BE13*BE32 -> 163350000 | BF51: =BF13*BF32 -> 157300000 | ... BJ51: =BJ13*BJ32 -> 163350000 | BK51: =SUM(AY51:BJ51) -> 1678270000
B52: 8 | C52: Chai PET B5 | D52: Triệu đ | F52: =F14*F33 -> 65520000 | G52: =G14*G33 -> 37800000 | H52: =H14*H33 -> 84240000 | I52: =I14*I33 -> 101250000 | J52: =J14*J33 -> 101250000 | K52: =K14*K33 -> 105300000 | L52: =L14*L33 -> 109350000 | M52: =M14*M33 -> 105300000 | ... Q52: =Q14*Q33 -> 109350000 | R52: =SUM(F52:Q52) -> 1127160000 | T52: 41719080 | U52: 68487104 | V52: 61744308 | W52: 93125528 | X52: 76209680 | Y52: 127697250 | Z52: 149631770 | AA52: 143050040 | AB52: 101948500 | AC52: 75240000 | AD52: 85800000 | AE52: 92400000 | AF52: =SUM(T52:AE52) -> 1117053260 | AH52: 760512950 | AJ52: 355594000 | AL52: =IFERROR(R52-AF52,0) -> 10106740 | AM52: =IFERROR((R52/AF52)-1,0) -> 0.0090476796 | AX52: Chai PET B5 | AY52: =AY14*AY33 -> 66066000 | AZ52: =AZ14*AZ33 -> 38115000 | BA52: =BA14*BA33 -> 84942000 | BB52: =BB14*BB33 -> 102093750 | BC52: =BC14*BC33 -> 102093750 | BD52: =BD14*BD33 -> 106177500 | BE52: =BE14*BE33 -> 110261250 | BF52: =BF14*BF33 -> 106177500 | ... BJ52: =BJ14*BJ33 -> 110261250 | BK52: =SUM(AY52:BJ52) -> 1136553000
B53: 9 | C53: Chai PET B6.1 | D53: Triệu đ | F53: =F15*F34 -> 0 | G53: =G15*G34 -> 0 | H53: =H15*H34 -> 0 | I53: =I15*I34 -> 0 | J53: =J15*J34 -> 0 | K53: =K15*K34 -> 0 | L53: =L15*L34 -> 0 | M53: =M15*M34 -> 0 | ... Q53: =Q15*Q34 -> 0 | R53: =SUM(F53:Q53) -> 0 | AF53: =SUM(T53:AE53) -> 0 | AH53: 189243850 | AJ53: 407614871 | AL53: =IFERROR(R53-AF53,0) -> 0 | AM53: =IFERROR((R53/AF53)-1,0) -> 0 | AX53: Chai PET B6.1 | AY53: =AY15*AY34 -> 0 | AZ53: =AZ15*AZ34 -> 0 | BA53: =BA15*BA34 -> 0 | BB53: =BB15*BB34 -> 0 | BC53: =BC15*BC34 -> 0 | BD53: =BD15*BD34 -> 0 | BE53: =BE15*BE34 -> 0 | BF53: =BF15*BF34 -> 0 | ... BJ53: =BJ15*BJ34 -> 0 | BK53: =SUM(AY53:BJ53) -> 0
B54: 10 | C54: Chai PET B6.2 | D54: Triệu đ | F54: =F16*F35 -> 2906280000 | G54: =G16*G35 -> 1676700000 | H54: =H16*H35 -> 3882060000 | I54: =I16*I35 -> 0 | J54: =J16*J35 -> 0 | K54: =K16*K35 -> 0 | L54: =L16*L35 -> 0 | M54: =M16*M35 -> 0 | ... Q54: =Q16*Q35 -> 0 | R54: =SUM(F54:Q54) -> 8465040000 | T54: 636252000 | U54: 1600784430 | V54: 1982498678 | W54: 2231688268 | X54: 2042741360 | Y54: 2824782538 | Z54: 3587531660 | AA54: 3839102560 | AB54: 3014642180 | AC54: 1795226500 | AD54: 1544400000 | AE54: 1663200000 | AF54: =SUM(T54:AE54) -> 26762850174 | AH54: 14165561550 | AJ54: 4563755193 | AL54: =IFERROR(R54-AF54,0) -> -18297810174 | AM54: =IFERROR((R54/AF54)-1,0) -> -0.68370185 | AX54: Chai PET B6.2 | AY54: =AY16*AY35 -> 2927808000 | AZ54: =AZ16*AZ35 -> 1689120000 | BA54: =BA16*BA35 -> 3910816000 | BB54: =BB16*BB35 -> 4.7005e+09 | BC54: =BC16*BC35 -> 4.7005e+09 | BD54: =BD16*BD35 -> 4.88852e+09 | BE54: =BE16*BE35 -> 5076540000 | BF54: =BF16*BF35 -> 4.88852e+09 | ... BJ54: =BJ16*BJ35 -> 5076540000 | BK54: =SUM(AY54:BJ54) -> 52148384000
B55: 11 | C55: Chai PET B7.1 | D55: Triệu đ | F55: =F17*F36 -> 0 | G55: =G17*G36 -> 0 | H55: =H17*H36 -> 0 | I55: =I17*I36 -> 0 | J55: =J17*J36 -> 0 | K55: =K17*K36 -> 0 | L55: =L17*L36 -> 0 | M55: =M17*M36 -> 0 | ... Q55: =Q17*Q36 -> 0 | R55: =SUM(F55:Q55) -> 0 | AF55: =SUM(T55:AE55) -> 0 | AL55: =IFERROR(R55-AF55,0) -> 0 | AM55: =IFERROR((R55/AF55)-1,0) -> 0 | AX55: Chai PET B7.1 | AY55: =AY17*AY36 -> 0 | AZ55: =AZ17*AZ36 -> 0 | BA55: =BA17*BA36 -> 0 | BB55: =BB17*BB36 -> 0 | BC55: =BC17*BC36 -> 0 | BD55: =BD17*BD36 -> 0 | BE55: =BE17*BE36 -> 0 | BF55: =BF17*BF36 -> 0 | ... BJ55: =BJ17*BJ36 -> 0 | BK55: =SUM(AY55:BJ55) -> 0
B56: 12 | C56: Chai PET B7.2 | D56: Triệu đ | F56: =F18*F37 -> 0 | G56: =G18*G37 -> 0 | H56: =H18*H37 -> 0 | I56: =I18*I37 -> 0 | J56: =J18*J37 -> 0 | K56: =K18*K37 -> 0 | L56: =L18*L37 -> 0 | M56: =M18*M37 -> 0 | ... Q56: =Q18*Q37 -> 0 | R56: =SUM(F56:Q56) -> 0 | T56: 0 | U56: 0 | V56: 26408000 | W56: 0 | X56: 0 | Y56: 0 | Z56: 0 | AA56: 0 | AB56: 0 | AD56: 0 | AE56: 0 | AF56: =SUM(T56:AE56) -> 26408000 | AL56: =IFERROR(R56-AF56,0) -> -26408000 | AM56: =IFERROR((R56/AF56)-1,0) -> -1 | AX56: Chai PET B7.2 | AY56: =AY18*AY37 -> 0 | AZ56: =AZ18*AZ37 -> 0 | BA56: =BA18*BA37 -> 0 | BB56: =BB18*BB37 -> 0 | BC56: =BC18*BC37 -> 0 | BD56: =BD18*BD37 -> 0 | BE56: =BE18*BE37 -> 0 | BF56: =BF18*BF37 -> 0 | ... BJ56: =BJ18*BJ37 -> 0 | BK56: =SUM(AY56:BJ56) -> 0
B57: 13 | C57: Cổ Chai PET | D57: Triệu đ | F57: =F19*F38 -> 63180000 | G57: =G19*G38 -> 36450000 | H57: =H19*H38 -> 84240000 | I57: =I19*I38 -> 0 | J57: =J19*J38 -> 0 | K57: =K19*K38 -> 0 | L57: =L19*L38 -> 0 | M57: =M19*M38 -> 0 | ... Q57: =Q19*Q38 -> 0 | R57: =SUM(F57:Q57) -> 183870000 | T57: 4984000 | U57: 0 | V57: 0 | W57: 10860000 | X57: 13320000 | Y57: 19460000 | Z57: 25130000 | AA57: 55140000 | AB57: 27948000 | AC57: 22607000 | AD57: 14872000 | AE57: 16016000 | AF57: =SUM(T57:AE57) -> 210337000 | AH57: 129948000 | AL57: =IFERROR(R57-AF57,0) -> -26467000 | AM57: =IFERROR((R57/AF57)-1,0) -> -0.1258314 | AX57: Cổ Chai PET | AY57: =AY19*AY38 -> 55380000 | AZ57: =AZ19*AZ38 -> 31950000 | BA57: =BA19*BA38 -> 73840000 | BB57: =BB19*BB38 -> 88750000 | BC57: =BC19*BC38 -> 88750000 | BD57: =BD19*BD38 -> 92300000 | BE57: =BE19*BE38 -> 95850000 | BF57: =BF19*BF38 -> 92300000 | ... BJ57: =BJ19*BJ38 -> 95850000 | BK57: =SUM(AY57:BJ57) -> 984770000
B58: 14 | C58: Nắp HD ép các màu | D58: Triệu đ | F58: =F20*F39 -> 63180000 | G58: =G20*G39 -> 36450000 | H58: =H20*H39 -> 84240000 | I58: =I20*I39 -> 0 | J58: =J20*J39 -> 0 | K58: =K20*K39 -> 0 | L58: =L20*L39 -> 0 | M58: =M20*M39 -> 0 | ... Q58: =Q20*Q39 -> 0 | R58: =SUM(F58:Q58) -> 183870000 | T58: 13556400 | U58: 0 | V58: 0 | W58: 40520000 | X58: 21960000 | Y58: 19740000 | Z58: 39900000 | AA58: 69260000 | AB58: 44863000 | AC58: 44811000 | AD58: 26767000 | AE58: 28827500 | AF58: =SUM(T58:AE58) -> 350204900 | AH58: 279389800 | AJ58: 206700000 | AL58: =IFERROR(R58-AF58,0) -> -166334900 | AM58: =IFERROR((R58/AF58)-1,0) -> -0.47496451 | AX58: Nắp HD ép các màu | AY58: =AY20*AY39 -> 55380000 | AZ58: =AZ20*AZ39 -> 31950000 | BA58: =BA20*BA39 -> 73840000 | BB58: =BB20*BB39 -> 88750000 | BC58: =BC20*BC39 -> 88750000 | BD58: =BD20*BD39 -> 92300000 | BE58: =BE20*BE39 -> 95850000 | BF58: =BF20*BF39 -> 92300000 | ... BJ58: =BJ20*BJ39 -> 95850000 | BK58: =SUM(AY58:BJ58) -> 984770000
B59: 15 | C59: Khác | D59: Triệu đ | F59: =F21*F40 -> 69498000 | G59: =G21*G40 -> 40095000 | H59: =H21*H40 -> 96876000 | I59: =I21*I40 -> 116437500 | J59: =J21*J40 -> 116437500 | K59: =K21*K40 -> 121095000 | L59: =L21*L40 -> 125752500 | M59: =M21*M40 -> 121095000 | ... Q59: =Q21*Q40 -> 125752500 | R59: =SUM(F59:Q59) -> 1287009000 | Y59: 14105000 | AB59: 37389000 | AF59: =SUM(T59:AE59) -> 51494000 | AH59: 375241800 | AJ59: =4293673776-10721482 -> 4282952294 | AL59: =IFERROR(R59-AF59,0) -> 1235515000 | AM59: =IFERROR((R59/AF59)-1,0) -> 23.993378 | AX59: Khác | AY59: =AY21*AY40 -> 60918000 | AZ59: =AZ21*AZ40 -> 35145000 | BA59: =BA21*BA40 -> 84916000 | BB59: =BB21*BB40 -> 102062500 | BC59: =BC21*BC40 -> 102062500 | BD59: =BD21*BD40 -> 106145000 | BE59: =BE21*BE40 -> 110227500 | BF59: =BF21*BF40 -> 106145000 | ... BJ59: =BJ21*BJ40 -> 110227500 | BK59: =SUM(AY59:BJ59) -> 1128119000
C60: TỔNG: | E60: =SUM(E45:E59) -> 0 | F60: =SUM(F45:F59) -> 9705618000 | G60: =SUM(G45:G59) -> 5599395000 | H60: =SUM(H45:H59) -> 12929826000 | I60: =SUM(I45:I59) -> 367687500 | J60: =SUM(J45:J59) -> 367687500 | K60: =SUM(K45:K59) -> 382395000 | L60: =SUM(L45:L59) -> 397102500 | ... Q60: =SUM(Q45:Q59) -> 397102500 | R60: =SUM(F60:Q60) -> 31646979000 | T60: =SUM(T45:T59) -> 2184030270 | U60: =SUM(U45:U59) -> 4906179695 | V60: =SUM(V45:V59) -> 6333654608 | W60: =SUM(W45:W59) -> 7807068174 | X60: =SUM(X45:X59) -> 7380147015 | Y60: =SUM(Y45:Y59) -> 10556762949 | Z60: =SUM(Z45:Z59) -> 12875151030 | AA60: =SUM(AA45:AA59) -> 13763220740 | ... AE60: =SUM(AE45:AE59) -> 6151867500 | AF60: =SUM(T60:AE60) -> 94579334121 | AH60: =SUM(AH45:AH59) -> 58441845550 | AJ60: =SUM(AJ45:AJ59) -> 44482013609 | AL60: =IFERROR(R60-AF60,0) -> -62932355121 | AM60: =IFERROR((R60/AF60)-1,0) -> -0.66539224 | AX60: TỔNG: | AY60: =SUM(AY45:AY59) -> 9747972000 | AZ60: =SUM(AZ45:AZ59) -> 5623830000 | BA60: =SUM(BA45:BA59) -> 12985674000 | BB60: =SUM(BB45:BB59) -> 15607781250 | BC60: =SUM(BC45:BC59) -> 15607781250 | BD60: =SUM(BD45:BD59) -> 16232092500 | BE60: =SUM(BE45:BE59) -> 16856403750 | BF60: =SUM(BF45:BF59) -> 16232092500 | ... BJ60: =SUM(BJ45:BJ59) -> 16856403750 | BK60: =SUM(AY60:BJ60) -> 173197686000
B62: II - DOANH THU VẢY PET
B63: 1. Sản lượng vảy
B64: STT | C64: Thành phẩm (Vảy PET sau khi băm) | D64: ĐVT | E64: Tỷ lệ | F64: T1 | G64: T2 | H64: T3 | I64: T4 | J64: T5 | K64: T6 | L64: T7 | M64: T8 | N64: T9 | O64: T10 | P64: T11 | Q64: T12 | R64: KHKD 2026 | T64: T1 | U64: T2 | V64: T3 | W64: T4 | X64: T5 | Y64: T6 | Z64: T7 | AA64: T8 | AB64: T9 | AC64: T10 | AD64: T11 | AE64: T12 | AF64: KQKD 2025 | AH64: KQKD 2024 | AJ64: KQKD 2023 | AL64: +/- 2026 sv 2025 | AM64: +/- %
B65: 1 | C65: Vảy PET B1 | D65: Tấn | F65: ='3.Thanh pham'!G121 -> 0 | G65: ='3.Thanh pham'!H121 -> 0 | H65: ='3.Thanh pham'!I121 -> 0 | I65: ='3.Thanh pham'!J121 -> 0 | J65: ='3.Thanh pham'!K121 -> 0 | K65: ='3.Thanh pham'!L121 -> 0 | L65: ='3.Thanh pham'!M121 -> 0 | M65: ='3.Thanh pham'!N121 -> 0 | ... Q65: ='3.Thanh pham'!R121 -> 0 | R65: =SUM(F65:Q65) -> 0 | AL65: =IFERROR(R65-AF65,0) -> 0 | AM65: =IFERROR((R65/AF65)-1,0) -> 0
B66: 2 | C66: Vảy PET B1 Không Phân Loại | D66: Tấn | F66: ='3.Thanh pham'!G122 -> 0 | G66: ='3.Thanh pham'!H122 -> 0 | H66: ='3.Thanh pham'!I122 -> 0 | I66: ='3.Thanh pham'!J122 -> 548725 | J66: ='3.Thanh pham'!K122 -> 548725 | K66: ='3.Thanh pham'!L122 -> 570674 | L66: ='3.Thanh pham'!M122 -> 592623 | M66: ='3.Thanh pham'!N122 -> 570674 | ... Q66: ='3.Thanh pham'!R122 -> 592623 | R66: =SUM(F66:Q66) -> 5092168 | AL66: =IFERROR(R66-AF66,0) -> 5092168 | AM66: =IFERROR((R66/AF66)-1,0) -> 0
B67: 3 | C67: Vảy PET B1.3 | D67: Tấn | F67: ='3.Thanh pham'!G123 -> 0 | G67: ='3.Thanh pham'!H123 -> 0 | H67: ='3.Thanh pham'!I123 -> 0 | I67: ='3.Thanh pham'!J123 -> 0 | J67: ='3.Thanh pham'!K123 -> 0 | K67: ='3.Thanh pham'!L123 -> 0 | L67: ='3.Thanh pham'!M123 -> 0 | M67: ='3.Thanh pham'!N123 -> 0 | ... Q67: ='3.Thanh pham'!R123 -> 0 | R67: =SUM(F67:Q67) -> 0 | AL67: =IFERROR(R67-AF67,0) -> 0 | AM67: =IFERROR((R67/AF67)-1,0) -> 0
B68: 4 | C68: Vảy PET B2.1 | D68: Tấn | F68: ='3.Thanh pham'!G124 -> 0 | G68: ='3.Thanh pham'!H124 -> 0 | H68: ='3.Thanh pham'!I124 -> 0 | I68: ='3.Thanh pham'!J124 -> 0 | J68: ='3.Thanh pham'!K124 -> 0 | K68: ='3.Thanh pham'!L124 -> 0 | L68: ='3.Thanh pham'!M124 -> 0 | M68: ='3.Thanh pham'!N124 -> 0 | ... Q68: ='3.Thanh pham'!R124 -> 0 | R68: =SUM(F68:Q68) -> 0 | AL68: =IFERROR(R68-AF68,0) -> 0 | AM68: =IFERROR((R68/AF68)-1,0) -> 0
B69: 5 | C69: Vảy PET B2.2 | D69: Tấn | F69: ='3.Thanh pham'!G125 -> 0 | G69: ='3.Thanh pham'!H125 -> 0 | H69: ='3.Thanh pham'!I125 -> 0 | I69: ='3.Thanh pham'!J125 -> 105512.5 | J69: ='3.Thanh pham'!K125 -> 105512.5 | K69: ='3.Thanh pham'!L125 -> 109733 | L69: ='3.Thanh pham'!M125 -> 113953.5 | M69: ='3.Thanh pham'!N125 -> 109733 | ... Q69: ='3.Thanh pham'!R125 -> 113953.5 | R69: =SUM(F69:Q69) -> 979156 | AL69: =IFERROR(R69-AF69,0) -> 979156 | AM69: =IFERROR((R69/AF69)-1,0) -> 0
B70: 6 | C70: Vảy PET B3 | D70: Tấn | F70: ='3.Thanh pham'!G126 -> 0 | G70: ='3.Thanh pham'!H126 -> 0 | H70: ='3.Thanh pham'!I126 -> 0 | I70: ='3.Thanh pham'!J126 -> 0 | J70: ='3.Thanh pham'!K126 -> 0 | K70: ='3.Thanh pham'!L126 -> 0 | L70: ='3.Thanh pham'!M126 -> 0 | M70: ='3.Thanh pham'!N126 -> 0 | ... Q70: ='3.Thanh pham'!R126 -> 0 | R70: =SUM(F70:Q70) -> 0 | AL70: =IFERROR(R70-AF70,0) -> 0 | AM70: =IFERROR((R70/AF70)-1,0) -> 0
B71: 7 | C71: Vảy PET B4 | D71: Tấn | F71: ='3.Thanh pham'!G127 -> 0 | G71: ='3.Thanh pham'!H127 -> 0 | H71: ='3.Thanh pham'!I127 -> 0 | I71: ='3.Thanh pham'!J127 -> 0 | J71: ='3.Thanh pham'!K127 -> 0 | K71: ='3.Thanh pham'!L127 -> 0 | L71: ='3.Thanh pham'!M127 -> 0 | M71: ='3.Thanh pham'!N127 -> 0 | ... Q71: ='3.Thanh pham'!R127 -> 0 | R71: =SUM(F71:Q71) -> 0 | AL71: =IFERROR(R71-AF71,0) -> 0 | AM71: =IFERROR((R71/AF71)-1,0) -> 0
B72: 8 | C72: Vảy PET B5 | D72: Tấn | F72: ='3.Thanh pham'!G128 -> 0 | G72: ='3.Thanh pham'!H128 -> 0 | H72: ='3.Thanh pham'!I128 -> 0 | I72: ='3.Thanh pham'!J128 -> 0 | J72: ='3.Thanh pham'!K128 -> 0 | K72: ='3.Thanh pham'!L128 -> 0 | L72: ='3.Thanh pham'!M128 -> 0 | M72: ='3.Thanh pham'!N128 -> 0 | ... Q72: ='3.Thanh pham'!R128 -> 0 | R72: =SUM(F72:Q72) -> 0 | AL72: =IFERROR(R72-AF72,0) -> 0 | AM72: =IFERROR((R72/AF72)-1,0) -> 0
B73: 9 | C73: Vảy PET B6.1 | D73: Tấn | F73: ='3.Thanh pham'!G129 -> 0 | G73: ='3.Thanh pham'!H129 -> 0 | H73: ='3.Thanh pham'!I129 -> 0 | I73: ='3.Thanh pham'!J129 -> 0 | J73: ='3.Thanh pham'!K129 -> 0 | K73: ='3.Thanh pham'!L129 -> 0 | L73: ='3.Thanh pham'!M129 -> 0 | M73: ='3.Thanh pham'!N129 -> 0 | ... Q73: ='3.Thanh pham'!R129 -> 0 | R73: =SUM(F73:Q73) -> 0 | AL73: =IFERROR(R73-AF73,0) -> 0 | AM73: =IFERROR((R73/AF73)-1,0) -> 0
B74: 10 | C74: Vảy PET B6.2 | D74: Tấn | F74: ='3.Thanh pham'!G130 -> 0 | G74: ='3.Thanh pham'!H130 -> 0 | H74: ='3.Thanh pham'!I130 -> 0 | I74: ='3.Thanh pham'!J130 -> 311062.5 | J74: ='3.Thanh pham'!K130 -> 311062.5 | K74: ='3.Thanh pham'!L130 -> 323505 | L74: ='3.Thanh pham'!M130 -> 335947.5 | M74: ='3.Thanh pham'!N130 -> 323505 | ... Q74: ='3.Thanh pham'!R130 -> 335947.5 | R74: =SUM(F74:Q74) -> 2886660 | AL74: =IFERROR(R74-AF74,0) -> 2886660 | AM74: =IFERROR((R74/AF74)-1,0) -> 0
B75: 11 | C75: Vảy PET B7.1 | D75: Tấn | F75: ='3.Thanh pham'!G131 -> 0 | G75: ='3.Thanh pham'!H131 -> 0 | H75: ='3.Thanh pham'!I131 -> 0 | I75: ='3.Thanh pham'!J131 -> 0 | J75: ='3.Thanh pham'!K131 -> 0 | K75: ='3.Thanh pham'!L131 -> 0 | L75: ='3.Thanh pham'!M131 -> 0 | M75: ='3.Thanh pham'!N131 -> 0 | ... Q75: ='3.Thanh pham'!R131 -> 0 | AL75: =IFERROR(R75-AF75,0) -> 0 | AM75: =IFERROR((R75/AF75)-1,0) -> 0
B76: 12 | C76: Vảy PET B7.2 | D76: Tấn | F76: ='3.Thanh pham'!G132 -> 0 | G76: ='3.Thanh pham'!H132 -> 0 | H76: ='3.Thanh pham'!I132 -> 0 | I76: ='3.Thanh pham'!J132 -> 0 | J76: ='3.Thanh pham'!K132 -> 0 | K76: ='3.Thanh pham'!L132 -> 0 | L76: ='3.Thanh pham'!M132 -> 0 | M76: ='3.Thanh pham'!N132 -> 0 | ... Q76: ='3.Thanh pham'!R132 -> 0 | R76: =SUM(F76:Q76) -> 0 | AL76: =IFERROR(R76-AF76,0) -> 0 | AM76: =IFERROR((R76/AF76)-1,0) -> 0
B77: 13 | C77: Vảy cổ chai PET | D77: Tấn | F77: ='3.Thanh pham'!G133 -> 0 | G77: ='3.Thanh pham'!H133 -> 0 | H77: ='3.Thanh pham'!I133 -> 0 | I77: ='3.Thanh pham'!J133 -> 12375 | J77: ='3.Thanh pham'!K133 -> 12375 | K77: ='3.Thanh pham'!L133 -> 12870 | L77: ='3.Thanh pham'!M133 -> 13365 | M77: ='3.Thanh pham'!N133 -> 12870 | ... Q77: ='3.Thanh pham'!R133 -> 13365 | R77: =SUM(F77:Q77) -> 114840 | AL77: =IFERROR(R77-AF77,0) -> 114840 | AM77: =IFERROR((R77/AF77)-1,0) -> 0
B78: 14 | C78: Vảy Nắp HD ép các màu | D78: Tấn | F78: ='3.Thanh pham'!G134 -> 0 | G78: ='3.Thanh pham'!H134 -> 0 | H78: ='3.Thanh pham'!I134 -> 0 | I78: ='3.Thanh pham'!J134 -> 12375 | J78: ='3.Thanh pham'!K134 -> 12375 | K78: ='3.Thanh pham'!L134 -> 12870 | L78: ='3.Thanh pham'!M134 -> 13365 | M78: ='3.Thanh pham'!N134 -> 12870 | ... Q78: ='3.Thanh pham'!R134 -> 13365 | R78: =SUM(F78:Q78) -> 114840 | AL78: =IFERROR(R78-AF78,0) -> 114840 | AM78: =IFERROR((R78/AF78)-1,0) -> 0
B79: 15 | C79: Khác | D79: Tấn | F79: ='3.Thanh pham'!G135 -> 0 | G79: ='3.Thanh pham'!H135 -> 0 | H79: ='3.Thanh pham'!I135 -> 0 | I79: ='3.Thanh pham'!J135 -> 0 | J79: ='3.Thanh pham'!K135 -> 0 | K79: ='3.Thanh pham'!L135 -> 0 | L79: ='3.Thanh pham'!M135 -> 0 | M79: ='3.Thanh pham'!N135 -> 0 | ... Q79: ='3.Thanh pham'!R135 -> 0 | R79: =SUM(F79:Q79) -> 0 | AH79: 400000 | AL79: =IFERROR(R79-AF79,0) -> 0 | AM79: =IFERROR((R79/AF79)-1,0) -> 0
C80: TỔNG: | E80: =SUM(E65:E79) -> 0 | F80: =SUM(F65:F79) -> 0 | G80: =SUM(G65:G79) -> 0 | H80: =SUM(H65:H79) -> 0 | I80: =SUM(I65:I79) -> 990050 | J80: =SUM(J65:J79) -> 990050 | K80: =SUM(K65:K79) -> 1029652 | L80: =SUM(L65:L79) -> 1069254 | ... Q80: =SUM(Q65:Q79) -> 1069254 | R80: =SUM(F80:Q80) -> 9187664 | T80: =SUM(T65:T79) -> 0 | U80: =SUM(U65:U79) -> 0 | V80: =SUM(V65:V79) -> 0 | W80: =SUM(W65:W79) -> 0 | X80: =SUM(X65:X79) -> 0 | Y80: =SUM(Y65:Y79) -> 0 | Z80: =SUM(Z65:Z79) -> 0 | AA80: =SUM(AA65:AA79) -> 0 | ... AE80: =SUM(AE65:AE79) -> 0 | AF80: =SUM(T80:AE80) -> 0 | AH80: =SUM(AH65:AH79) -> 400000 | AJ80: =SUM(AJ65:AJ79) -> 0 | AL80: =IFERROR(R80-AF80,0) -> 9187664 | AM80: =IFERROR((R80/AF80)-1,0) -> 0
B82: 2. Giá bán vảy
B83: STT | C83: Thành phẩm (Vảy PET sau khi băm) | D83: ĐVT | E83: Tỷ lệ | F83: T1 | G83: T2 | H83: T3 | I83: T4 | J83: T5 | K83: T6 | L83: T7 | M83: T8 | N83: T9 | O83: T10 | P83: T11 | Q83: T12 | R83: KHKD 2026 | T83: T1 | U83: T2 | V83: T3 | W83: T4 | X83: T5 | Y83: T6 | Z83: T7 | AA83: T8 | AB83: T9 | AC83: T10 | AD83: T11 | AE83: T12 | AF83: KQKD 2025 | AH83: KQKD 2024 | AJ83: KQKD 2023 | AL83: +/- 2026 sv 2025 | AM83: +/- % | AO83: Nhóm vảy PET | AP83: Thành phẩm vảy PET sau khi băm | AQ83: Đơn giá chai PET sau khi phân loại | AR83: Hao hụt | AT83: GAP (đảm bảo chi phí và lợi nhuận) | AU83: Đơn giá bán theo công thức | AV83: 12/02/2026
B84: 1 | C84: Vảy PET B1 | D84: Đồng/kg | F84: =$AV$85 -> 16500 | G84: =$AV$85 -> 16500 | H84: =$AV$85 -> 16500 | I84: =$AV$85 -> 16500 | J84: =$AV$85 -> 16500 | K84: =$AV$85 -> 16500 | L84: =$AV$85 -> 16500 | M84: =$AV$85 -> 16500 | ... Q84: =$AV$85 -> 16500 | R84: =IFERROR(R103/R65,0) -> 0 | AL84: =IFERROR(R84-AF84,0) -> 0 | AM84: =IFERROR((R84/AF84)-1,0) -> 0 | AR84: Tỷ lệ | AS84: Quy ra tiền
B85: 2 | C85: Vảy PET B1 Không Phân Loại | D85: Đồng/kg | F85: =$AV$85 -> 16500 | G85: =$AV$85 -> 16500 | H85: =$AV$85 -> 16500 | I85: =$AV$85 -> 16500 | J85: =$AV$85 -> 16500 | K85: =$AV$85 -> 16500 | L85: =$AV$85 -> 16500 | M85: =$AV$85 -> 16500 | ... Q85: =$AV$85 -> 16500 | R85: =IFERROR(R104/R66,0) -> 16500 | AL85: =IFERROR(R85-AF85,0) -> 16500 | AM85: =IFERROR((R85/AF85)-1,0) -> 0 | AO85: Nhóm 1 - Vảy B1.1 | AP85: B1.1 + B1.2 + B1.3 + B2.1 + B3 | AQ85: =AV27 -> 15000 | AR85: ='2.Hao hut & % chai '!G130 -> 0.06 | AS85: =AQ85*AR85 -> 900 | AT85: 1500 | AU85: =ROUND(AQ85+AS85+AT85,-2) -> 17400 | AV85: 16500
B86: 3 | C86: Vảy PET B1.3 | D86: Đồng/kg | F86: =$AV$85 -> 16500 | G86: =$AV$85 -> 16500 | H86: =$AV$85 -> 16500 | I86: =$AV$85 -> 16500 | J86: =$AV$85 -> 16500 | K86: =$AV$85 -> 16500 | L86: =$AV$85 -> 16500 | M86: =$AV$85 -> 16500 | ... Q86: =$AV$85 -> 16500 | R86: =IFERROR(R105/R67,0) -> 0 | AL86: =IFERROR(R86-AF86,0) -> 0 | AM86: =IFERROR((R86/AF86)-1,0) -> 0 | AO86: Nhóm 2 - Vảy B4; B5 | AP86: B4 + B5 | AQ86: =AV28 -> 12000 | AR86: ='2.Hao hut & % chai '!G136 -> 0.08 | AU86: 16000
B87: 4 | C87: Vảy PET B2.1 | D87: Đồng/kg | F87: =$AV$85 -> 16500 | G87: =$AV$85 -> 16500 | H87: =$AV$85 -> 16500 | I87: =$AV$85 -> 16500 | J87: =$AV$85 -> 16500 | K87: =$AV$85 -> 16500 | L87: =$AV$85 -> 16500 | M87: =$AV$85 -> 16500 | ... Q87: =$AV$85 -> 16500 | R87: =IFERROR(R106/R68,0) -> 0 | AL87: =IFERROR(R87-AF87,0) -> 0 | AM87: =IFERROR((R87/AF87)-1,0) -> 0 | AO87: Nhóm 3 - Vảy B2.2 | AP87: B2.2 | AQ87: =AV29 -> 13500 | AR87: ='2.Hao hut & % chai '!G138 -> 0.1 | AS87: =AQ87*AR87 -> 1350 | AT87: 1000 | AU87: =ROUND(AQ87+AS87+AT87,-2) -> 15900 | AV87: 15500
B88: 5 | C88: Vảy PET B2.2 | D88: Đồng/kg | F88: =$AV$87 -> 15500 | G88: =$AV$87 -> 15500 | H88: =$AV$87 -> 15500 | I88: =$AV$87 -> 15500 | J88: =$AV$87 -> 15500 | K88: =$AV$87 -> 15500 | L88: =$AV$87 -> 15500 | M88: =$AV$87 -> 15500 | ... Q88: =$AV$87 -> 15500 | R88: =IFERROR(R107/R69,0) -> 15500 | AL88: =IFERROR(R88-AF88,0) -> 15500 | AM88: =IFERROR((R88/AF88)-1,0) -> 0 | AO88: Nhóm 4 - Vảy B6.2 | AP88: B6.2 | AQ88: =AV29 -> 13500 | AR88: ='2.Hao hut & % chai '!G139 -> 0.1 | AS88: =AQ88*AR88 -> 1350 | AT88: 1000 | AU88: =ROUND(AQ88+AS88+AT88,-2) -> 15900 | AV88: 16500
B89: 6 | C89: Vảy PET B3 | D89: Đồng/kg | F89: =$AV$85 -> 16500 | G89: =$AV$85 -> 16500 | H89: =$AV$85 -> 16500 | I89: =$AV$85 -> 16500 | J89: =$AV$85 -> 16500 | K89: =$AV$85 -> 16500 | L89: =$AV$85 -> 16500 | M89: =$AV$85 -> 16500 | ... Q89: =$AV$85 -> 16500 | R89: =IFERROR(R108/R70,0) -> 0 | AL89: =IFERROR(R89-AF89,0) -> 0 | AM89: =IFERROR((R89/AF89)-1,0) -> 0 | AO89: Nhóm 5 - Cổ chai, nắp HD | AP89: Nắp HD ép, cổ chai, PP (Quai) | AQ89: =AV30 -> 8100 | AR89: ='2.Hao hut & % chai '!G143 -> 0.01 | AS89: =AQ89*AR89 -> 81 | AT89: 2500 | AU89: =ROUND(AQ89+AS89+AT89,-2) -> 10700 | AV89: 10000
B90: 7 | C90: Vảy PET B4 | D90: Đồng/kg | F90: =$AV$86 -> 0 | G90: =$AV$86 -> 0 | H90: =$AV$86 -> 0 | I90: =$AV$86 -> 0 | J90: =$AV$86 -> 0 | K90: =$AV$86 -> 0 | L90: =$AV$86 -> 0 | M90: =$AV$86 -> 0 | ... Q90: =$AV$86 -> 0 | R90: =IFERROR(R109/R71,0) -> 0 | AL90: =IFERROR(R90-AF90,0) -> 0 | AM90: =IFERROR((R90/AF90)-1,0) -> 0
B91: 8 | C91: Vảy PET B5 | D91: Đồng/kg | F91: =$AV$86 -> 0 | G91: =$AV$86 -> 0 | H91: =$AV$86 -> 0 | I91: =$AV$86 -> 0 | J91: =$AV$86 -> 0 | K91: =$AV$86 -> 0 | L91: =$AV$86 -> 0 | M91: =$AV$86 -> 0 | ... Q91: =$AV$86 -> 0 | R91: =IFERROR(R110/R72,0) -> 0 | AL91: =IFERROR(R91-AF91,0) -> 0 | AM91: =IFERROR((R91/AF91)-1,0) -> 0
B92: 9 | C92: Vảy PET B6.1 | D92: Đồng/kg | F92: =$AV$88 -> 16500 | G92: =$AV$88 -> 16500 | H92: =$AV$88 -> 16500 | I92: =$AV$88 -> 16500 | J92: =$AV$88 -> 16500 | K92: =$AV$88 -> 16500 | L92: =$AV$88 -> 16500 | M92: =$AV$88 -> 16500 | ... Q92: =$AV$88 -> 16500 | R92: =IFERROR(R111/R73,0) -> 0 | AL92: =IFERROR(R92-AF92,0) -> 0 | AM92: =IFERROR((R92/AF92)-1,0) -> 0
B93: 10 | C93: Vảy PET B6.2 | D93: Đồng/kg | F93: =$AV$88 -> 16500 | G93: =$AV$88 -> 16500 | H93: =$AV$88 -> 16500 | I93: =$AV$88 -> 16500 | J93: =$AV$88 -> 16500 | K93: =$AV$88 -> 16500 | L93: =$AV$88 -> 16500 | M93: =$AV$88 -> 16500 | ... Q93: =$AV$88 -> 16500 | R93: =IFERROR(R112/R74,0) -> 16500 | AL93: =IFERROR(R93-AF93,0) -> 16500 | AM93: =IFERROR((R93/AF93)-1,0) -> 0
B94: 11 | C94: Vảy PET B7.1 | D94: Đồng/kg | F94: =$AV$86 -> 0 | G94: =$AV$86 -> 0 | H94: =$AV$86 -> 0 | I94: =$AV$86 -> 0 | J94: =$AV$86 -> 0 | K94: =$AV$86 -> 0 | L94: =$AV$86 -> 0 | M94: =$AV$86 -> 0 | ... Q94: =$AV$86 -> 0 | R94: =IFERROR(R113/R75,0) -> 0 | AL94: =IFERROR(R94-AF94,0) -> 0 | AM94: =IFERROR((R94/AF94)-1,0) -> 0
B95: 12 | C95: Vảy PET B7.2 | D95: Đồng/kg | F95: =$AV$86 -> 0 | G95: =$AV$86 -> 0 | H95: =$AV$86 -> 0 | I95: =$AV$86 -> 0 | J95: =$AV$86 -> 0 | K95: =$AV$86 -> 0 | L95: =$AV$86 -> 0 | M95: =$AV$86 -> 0 | ... Q95: =$AV$86 -> 0 | R95: =IFERROR(R114/R76,0) -> 0 | AL95: =IFERROR(R95-AF95,0) -> 0 | AM95: =IFERROR((R95/AF95)-1,0) -> 0
B96: 13 | C96: Vảy cổ chai PET | D96: Đồng/kg | F96: =$AV$89 -> 10000 | G96: =$AV$89 -> 10000 | H96: =$AV$89 -> 10000 | I96: =$AV$89 -> 10000 | J96: =$AV$89 -> 10000 | K96: =$AV$89 -> 10000 | L96: =$AV$89 -> 10000 | M96: =$AV$89 -> 10000 | ... Q96: =$AV$89 -> 10000 | R96: =IFERROR(R115/R77,0) -> 10000 | AL96: =IFERROR(R96-AF96,0) -> 10000 | AM96: =IFERROR((R96/AF96)-1,0) -> 0
B97: 14 | C97: Vảy Nắp HD ép các màu | D97: Đồng/kg | F97: =$AV$89 -> 10000 | G97: =$AV$89 -> 10000 | H97: =$AV$89 -> 10000 | I97: =$AV$89 -> 10000 | J97: =$AV$89 -> 10000 | K97: =$AV$89 -> 10000 | L97: =$AV$89 -> 10000 | M97: =$AV$89 -> 10000 | ... Q97: =$AV$89 -> 10000 | R97: =IFERROR(R116/R78,0) -> 10000 | AL97: =IFERROR(R97-AF97,0) -> 10000 | AM97: =IFERROR((R97/AF97)-1,0) -> 0
B98: 15 | C98: Khác | D98: Đồng/kg | F98: =$AV$89 -> 10000 | G98: =$AV$89 -> 10000 | H98: =$AV$89 -> 10000 | I98: =$AV$89 -> 10000 | J98: =$AV$89 -> 10000 | K98: =$AV$89 -> 10000 | L98: =$AV$89 -> 10000 | M98: =$AV$89 -> 10000 | ... Q98: =$AV$89 -> 10000 | R98: =IFERROR(R117/R79,0) -> 0 | AH98: =IFERROR(AH117/AH79,0) -> 13771.5 | AL98: =IFERROR(R98-AF98,0) -> 0 | AM98: =IFERROR((R98/AF98)-1,0) -> 0
C99: Giá bán Trung bình | F99: =IFERROR(F118/F80,0) -> 0 | G99: =IFERROR(G118/G80,0) -> 0 | H99: =IFERROR(H118/H80,0) -> 0 | I99: =IFERROR(I118/I80,0) -> 16230.935 | J99: =IFERROR(J118/J80,0) -> 16230.935 | K99: =IFERROR(K118/K80,0) -> 16230.935 | L99: =IFERROR(L118/L80,0) -> 16230.935 | M99: =IFERROR(M118/M80,0) -> 16230.935 | ... R99: =IFERROR(R118/R80,0) -> 16230.935 | AH99: =IFERROR(AH118/AH80,0) -> 13771.5 | AL99: =IFERROR(R99-AF99,0) -> 16230.935 | AM99: =IFERROR((R99/AF99)-1,0) -> 0
B101: 3. Doanh thu vảy PET
B102: STT | C102: Thành phẩm (Vảy PET sau khi băm) | D102: ĐVT | E102: Tỷ lệ | F102: T1 | G102: T2 | H102: T3 | I102: T4 | J102: T5 | K102: T6 | L102: T7 | M102: T8 | N102: T9 | O102: T10 | P102: T11 | Q102: T12 | R102: KHKD 2026 | T102: T1 | U102: T2 | V102: T3 | W102: T4 | X102: T5 | Y102: T6 | Z102: T7 | AA102: T8 | AB102: T9 | AC102: T10 | AD102: T11 | AE102: T12 | AF102: KQKD 2025 | AH102: KQKD 2024 | AJ102: KQKD 2023 | AL102: +/- 2026 sv 2025 | AM102: +/- %
B103: 1 | C103: Vảy PET B1 | D103: Triệu đ | F103: =F65*F84 -> 0 | G103: =G65*G84 -> 0 | H103: =H65*H84 -> 0 | I103: =I65*I84 -> 0 | J103: =J65*J84 -> 0 | K103: =K65*K84 -> 0 | L103: =L65*L84 -> 0 | M103: =M65*M84 -> 0 | ... Q103: =Q65*Q84 -> 0 | R103: =SUM(F103:Q103) -> 0 | AF103: =SUM(T103:AE103) -> 0 | AL103: =IFERROR(R103-AF103,0) -> 0 | AM103: =IFERROR((R103/AF103)-1,0) -> 0
B104: 2 | C104: Vảy PET B1 Không Phân Loại | D104: Triệu đ | F104: =F66*F85 -> 0 | G104: =G66*G85 -> 0 | H104: =H66*H85 -> 0 | I104: =I66*I85 -> 9053962500 | J104: =J66*J85 -> 9053962500 | K104: =K66*K85 -> 9416121000 | L104: =L66*L85 -> 9778279500 | M104: =M66*M85 -> 9416121000 | ... Q104: =Q66*Q85 -> 9778279500 | R104: =SUM(F104:Q104) -> 84020772000 | AF104: =SUM(T104:AE104) -> 0 | AL104: =IFERROR(R104-AF104,0) -> 84020772000 | AM104: =IFERROR((R104/AF104)-1,0) -> 0
B105: 3 | C105: Vảy PET B1.3 | D105: Triệu đ | F105: =F67*F86 -> 0 | G105: =G67*G86 -> 0 | H105: =H67*H86 -> 0 | I105: =I67*I86 -> 0 | J105: =J67*J86 -> 0 | K105: =K67*K86 -> 0 | L105: =L67*L86 -> 0 | M105: =M67*M86 -> 0 | ... Q105: =Q67*Q86 -> 0 | R105: =SUM(F105:Q105) -> 0 | AF105: =SUM(T105:AE105) -> 0 | AL105: =IFERROR(R105-AF105,0) -> 0 | AM105: =IFERROR((R105/AF105)-1,0) -> 0
B106: 4 | C106: Vảy PET B2.1 | D106: Triệu đ | F106: =F68*F87 -> 0 | G106: =G68*G87 -> 0 | H106: =H68*H87 -> 0 | I106: =I68*I87 -> 0 | J106: =J68*J87 -> 0 | K106: =K68*K87 -> 0 | L106: =L68*L87 -> 0 | M106: =M68*M87 -> 0 | ... Q106: =Q68*Q87 -> 0 | R106: =SUM(F106:Q106) -> 0 | AF106: =SUM(T106:AE106) -> 0 | AL106: =IFERROR(R106-AF106,0) -> 0 | AM106: =IFERROR((R106/AF106)-1,0) -> 0
B107: 5 | C107: Vảy PET B2.2 | D107: Triệu đ | F107: =F69*F88 -> 0 | G107: =G69*G88 -> 0 | H107: =H69*H88 -> 0 | I107: =I69*I88 -> 1635443750 | J107: =J69*J88 -> 1635443750 | K107: =K69*K88 -> 1700861500 | L107: =L69*L88 -> 1766279250 | M107: =M69*M88 -> 1700861500 | ... Q107: =Q69*Q88 -> 1766279250 | R107: =SUM(F107:Q107) -> 15176918000 | AF107: =SUM(T107:AE107) -> 0 | AL107: =IFERROR(R107-AF107,0) -> 15176918000 | AM107: =IFERROR((R107/AF107)-1,0) -> 0
...

Sheet 1.NVL Chai
F1: SL mua/Ngày | G1: 30000 | H1: 30000 | I1: 40000 | J1: 50000 | K1: 50000 | L1: 50000 | M1: 50000 | N1: 50000 | O1: 50000 | P1: 50000 | Q1: 50000 | R1: 50000 | S1: =AVERAGE(G1:R1) -> 45833.333
B3: NHU CẦU MUA NGUYÊN VẬT LIỆU CHAI
B4: 1. Số lượng | F4: Số ngày MH | G4: =31-5 -> 26 | H4: =28-13 -> 15 | I4: =31-5 -> 26 | J4: =30-5 -> 25 | K4: =31-6 -> 25 | L4: =30-4 -> 26 | M4: =31-4 -> 27 | N4: =31-5 -> 26 | O4: =30-6 -> 24 | P4: =31-4 -> 27 | Q4: =30-5 -> 25 | R4: =31-4 -> 27
B5: STT | C5: Loại chai nguyên liệu | D5: ĐVT | E5: Thực tế năm 2024 | F5: KQKD 2025 | G5: T1 | H5: T2 | I5: T3 | J5: T4 | K5: T5 | L5: T6 | M5: T7 | N5: T8 | O5: T9 | P5: T10 | Q5: T11 | R5: T12 | S5: KHKD 2026
B6: i. Tỷ lệ chai
B7: 1 | C7: Chai B0 - Xá tròn | D7: % | F7: =F13/$F$16 -> 0.49435416 | G7: 0.4 | H7: 0.4 | I7: 0.35 | J7: 0.35 | K7: 0.35 | L7: 0.35 | M7: 0.35 | N7: 0.35 | O7: 0.35 | P7: 0.35 | Q7: 0.35 | R7: 0.35 | S7: =AVERAGE(G7:R7) -> 0.35833333
B8: 2 | C8: Chai B0 - Ép kiện | D8: % | F8: =F14/$F$16 -> 0.42217653 | G8: 0.6 | H8: 0.6 | I8: 0.65 | J8: 0.65 | K8: 0.65 | L8: 0.65 | M8: 0.65 | N8: 0.65 | O8: 0.65 | P8: 0.65 | Q8: 0.65 | R8: 0.65 | S8: =AVERAGE(G8:R8) -> 0.64166667
B9: 3 | C9: Chai B1.4 (xô tuyển -> ép kiện) | D9: % | F9: =F15/$F$16 -> 0.083469302 | G9: 0 | H9: 0 | I9: 0 | J9: 0 | K9: 0 | L9: 0 | M9: 0 | N9: 0 | O9: 0 | P9: 0 | Q9: 0 | R9: 0 | S9: 0
C10: Tổng: | F10: =F7+F8+F9 -> 1 | G10: =G7+G8+G9 -> 1 | H10: =H7+H8+H9 -> 1 | I10: =I7+I8+I9 -> 1 | J10: =J7+J8+J9 -> 1 | K10: 1 | L10: 1 | M10: 1 | N10: 1 | O10: 1 | P10: 1 | Q10: 1 | R10: 1 | S10: =S7+S8+S9 -> 1
B12: ii Số lượng chai
B13: 1 | C13: Chai B0 - Xá tròn | D13: Tấn | F13: =2744980+320000 -> 3064980 | G13: =G7*G$16 -> 312000 | H13: =H7*H$16 -> 180000 | I13: =I7*I$16 -> 364000 | J13: =J7*J$16 -> 437500 | K13: =K7*K$16 -> 437500 | L13: =L7*L$16 -> 455000 | M13: =M7*M$16 -> 472500 | N13: =N7*N$16 -> 455000 | ... R13: =R7*R$16 -> 472500 | S13: =SUM(G13:R13) -> 4916000
B14: 2 | C14: Chai B0 - Ép kiện | D14: Tấn | F14: =2117481+500000 -> 2617481 | G14: =G8*G$16 -> 468000 | H14: =H8*H$16 -> 270000 | I14: =I8*I$16 -> 676000 | J14: =J8*J$16 -> 812500 | K14: =K8*K$16 -> 812500 | L14: =L8*L$16 -> 845000 | M14: =M8*M$16 -> 877500 | N14: =N8*N$16 -> 845000 | ... R14: =R8*R$16 -> 877500 | S14: =SUM(G14:R14) -> 8954000
B15: 3 | C15: Chai B1.4 (xô tuyển -> ép kiện) | D15: Tấn | F15: 517507 | G15: =G9*G$16 -> 0 | H15: =H9*H$16 -> 0 | I15: =I9*I$16 -> 0 | J15: =J9*J$16 -> 0 | K15: =K9*K$16 -> 0 | L15: =L9*L$16 -> 0 | M15: =M9*M$16 -> 0 | N15: =N9*N$16 -> 0 | ... R15: =R9*R$16 -> 0 | S15: =SUM(G15:R15) -> 0
C16: Tổng: | D16: Tấn | F16: =SUM(F13:F15) -> 6199968 | G16: =G$4*G1 -> 780000 | H16: =H$4*H1 -> 450000 | I16: =I$4*I1 -> 1040000 | J16: =J$4*J1 -> 1250000 | K16: =K$4*K1 -> 1250000 | L16: =L$4*L1 -> 1300000 | M16: =M$4*M1 -> 1350000 | N16: =N$4*N1 -> 1300000 | ... R16: =R$4*R1 -> 1350000 | S16: =SUM(G16:R16) -> 13870000
S17: =S16/12 -> 1155833.3
B18: iii Số lượng và giá trị mua vảy HD
B19: 1 | C19: Lượng mua NVL vảy HD | D19: Tấn | S19: =SUM(G19:R19) -> 0
B20: 2 | C20: Giá mua vảy HD | D20: Đồng/kg | G20: 15000 | H20: 15000 | I20: 15000 | J20: 15000 | K20: 15000 | L20: 15000 | M20: 15000 | N20: 15000 | O20: 15000 | P20: 15000 | Q20: 15000 | R20: 15000
B21: 3 | C21: Tổng giá trị HD | D21: Triệu đ | F21: =F19*F20 -> 0 | G21: =G19*G20 -> 0 | H21: =H19*H20 -> 0 | I21: =I19*I20 -> 0 | J21: =J19*J20 -> 0 | K21: =K19*K20 -> 0 | L21: =L19*L20 -> 0 | M21: =M19*M20 -> 0 | ... R21: =R19*R20 -> 0 | S21: =SUM(G21:R21) -> 0
B23: 2. Giá mua
B24: STT | C24: Loại chai nguyên liệu | D24: ĐVT | E24: Thực tế năm 2024 | F24: KQKD 2025 | G24: T1 | H24: T2 | I24: T3 | J24: T4 | K24: T5 | L24: T6 | M24: T7 | N24: T8 | O24: T9 | P24: T10 | Q24: T11 | R24: T12 | S24: KHKD 2026
B25: 1 | C25: Chai B0 - Xá tròn | D25: Đồng/kg | F25: 12200 | G25: =G26+G27 -> 9700 | H25: =H26+H27 -> 9500 | I25: =I26+I27 -> 10000 | J25: =J26+J27 -> 10000 | K25: =K26+K27 -> 10000 | L25: =L26+L27 -> 10000 | M25: =M26+M27 -> 10000 | N25: =N26+N27 -> 10000 | ... S25: =S26+S27 -> 0
B26: a | C26: Giá chai | G26: 9700 | H26: 9500 | I26: 10000 | J26: 10000 | K26: 10000 | L26: 10000 | M26: 10000 | N26: 10000 | O26: 10000 | P26: 10000 | Q26: 10000 | R26: 10000
B27: b | C27: Chi phí mua (các chính sách mua hàng)
B28: 2 | C28: Chai B0 - Ép kiện | D28: Đồng/kg | F28: 12450 | G28: =G29+G30 -> 9700 | H28: =H29+H30 -> 9500 | I28: =I29+I30 -> 10000 | J28: =J29+J30 -> 10000 | K28: =K29+K30 -> 10000 | L28: =L29+L30 -> 10000 | M28: =M29+M30 -> 10000 | N28: =N29+N30 -> 10000 | ... S28: =S29+S30 -> 0
B29: a | C29: Giá chai | G29: 9700 | H29: 9500 | I29: 10000 | J29: 10000 | K29: 10000 | L29: 10000 | M29: 10000 | N29: 10000 | O29: 10000 | P29: 10000 | Q29: 10000 | R29: 10000
B30: b | C30: Chi phí mua (các chính sách mua hàng)
B31: 3 | C31: Chai B1.4 (xô tuyển) | D31: Đồng/kg | F31: 16000 | G31: =G32+G33 -> 13500 | H31: =H32+H33 -> 13500 | I31: =I32+I33 -> 13500 | J31: =J32+J33 -> 13500 | K31: =K32+K33 -> 13500 | L31: =L32+L33 -> 13500 | M31: =M32+M33 -> 13500 | N31: =N32+N33 -> 13500 | ... S31: =S32+S33 -> 0
B32: a | C32: Giá chai | G32: 13500 | H32: 13500 | I32: 13500 | J32: 13500 | K32: 13500 | L32: 13500 | M32: 13500 | N32: 13500 | O32: 13500 | P32: 13500 | Q32: 13500 | R32: 13500
B33: b | C33: Chi phí mua (các chính sách mua hàng)
C34: Giá mua bình quân | D34: Đồng/kg | G34: =G42/G16 -> 9700 | H34: =H42/H16 -> 9500 | I34: =I42/I16 -> 10000 | J34: =J42/J16 -> 10000 | K34: =K42/K16 -> 10000 | L34: =L42/L16 -> 10000 | M34: =M42/M16 -> 10000 | N34: =N42/N16 -> 10000 | ... R34: =R42/R16 -> 10000
B36: 3. Tổng giá trị mua
B37: STT | C37: Loại chai nguyên liệu | D37: ĐVT | E37: Thực tế năm 2024 | F37: KQKD 2025 | G37: T1 | H37: T2 | I37: T3 | J37: T4 | K37: T5 | L37: T6 | M37: T7 | N37: T8 | O37: T9 | P37: T10 | Q37: T11 | R37: T12 | S37: KHKD 2026
B38: 1 | C38: Chai B0 - Xá tròn | D38: Triệu đ | F38: =F$13*F$25 -> 37392756000 | G38: =G$13*G$25 -> 3026400000 | H38: =H$13*H$25 -> 1710000000 | I38: =I$13*I$25 -> 3640000000 | J38: =J$13*J$25 -> 4375000000 | K38: =K$13*K$25 -> 4375000000 | L38: =L$13*L$25 -> 4550000000 | M38: =M$13*M$25 -> 4.725e+09 | ... R38: =R$13*R$25 -> 4.725e+09 | S38: =SUM(G38:R38) -> 48976400000
B39: 2 | C39: Chai B0 - Ép kiện | D39: Triệu đ | F39: =F$14*F$28 -> 32587638450 | G39: =G$14*G$28 -> 4539600000 | H39: =H$14*H$28 -> 2565000000 | I39: =I$14*I$28 -> 6760000000 | J39: =J$14*J$28 -> 8125000000 | K39: =K$14*K$28 -> 8125000000 | L39: =L$14*L$28 -> 8450000000 | M39: =M$14*M$28 -> 8775000000 | ... R39: =R$14*R$28 -> 8775000000 | S39: =SUM(G39:R39) -> 89264600000
B40: 3 | C40: Chai B1.4 (xô tuyển -> ép kiện) | D40: Triệu đ | F40: =F$15*F$31 -> 8280112000 | G40: =G$15*G$31 -> 0 | H40: =H$15*H$31 -> 0 | I40: =I$15*I$31 -> 0 | J40: =J$15*J$31 -> 0 | K40: =K$15*K$31 -> 0 | L40: =L$15*L$31 -> 0 | M40: =M$15*M$31 -> 0 | ... R40: =R$15*R$31 -> 0 | S40: =SUM(G40:R40) -> 0
S41: =SUM(G41:R41) -> 0
C42: Tổng: | D42: Triệu đ | F42: =SUM(F38:F41) -> 78260506450 | G42: =SUM(G38:G41) -> 7566000000 | H42: =SUM(H38:H41) -> 4275000000 | I42: =SUM(I38:I41) -> 10400000000 | J42: =SUM(J38:J41) -> 12500000000 | K42: =SUM(K38:K41) -> 12500000000 | L42: =SUM(L38:L41) -> 13000000000 | M42: =SUM(M38:M41) -> 13500000000 | ... R42: =SUM(R38:R41) -> 13500000000 | S42: =SUM(G42:R42) -> 138241000000
B44: 4. Hiệu suất máy (1ca 8giờ x 3ca 1 ngày x 30 ngày 1 tháng)
B45: STT | C45: Loại chai nguyên liệu | D45: ĐVT | E45: Thực tế năm 2024 | F45: KQKD 2025 | G45: T1 | H45: T2 | I45: T3 | J45: T4 | K45: T5 | L45: T6 | M45: T7 | N45: T8 | O45: T9 | P45: T10 | Q45: T11 | R45: T12 | S45: KHKD 2026
B46: i | C46: Hiệu suất máy - Tính trên NVL đầu vào | G46: =G47/G48 -> 0.49242424 | H46: =H47/H48 -> 0.38739669 | I46: =I47/I48 -> 0.48201706 | J46: =J47/J48 -> 0.61930242 | K46: =K47/K48 -> 0.598659 | L46: =L47/L48 -> 0.62260536 | M46: =M47/M48 -> 0.62569522 | N46: =N47/N48 -> 0.60252132 | ... S46: =S47/S48 -> 0.5836363
B47: 1 | C47: Tổng sản lượng chai mua vào | D47: Tấn | F47: =F16 -> 6199968 | G47: =G16 -> 780000 | H47: =H16 -> 450000 | I47: =I16 -> 1040000 | J47: =J16 -> 1250000 | K47: =K16 -> 1250000 | L47: =L16 -> 1300000 | M47: =M16 -> 1350000 | ... R47: =R16 -> 1350000 | S47: =SUM(G47:R47) -> 13870000
B48: 2 | C48: Tổng công suất máy (NVL) | D48: Tấn | G48: ='Cong suat'!F$84 -> 1584000 | H48: ='Cong suat'!G$84 -> 1161600 | I48: ='Cong suat'!H$84 -> 2157600 | J48: ='Cong suat'!I$84 -> 2018400 | K48: ='Cong suat'!J$84 -> 2088000 | L48: ='Cong suat'!K$84 -> 2088000 | M48: ='Cong suat'!L$84 -> 2157600 | N48: ='Cong suat'!M$84 -> 2157600 | ... R48: ='Cong suat'!Q$84 -> 2157600 | S48: =SUM(G48:R48) -> 23764800
B49: ii | C49: Hiệu suất máy - Tính trên Thành phẩm SX | G49: =G50/G51 -> 0.49466253 | H49: =H50/H51 -> 0.38915759 | I49: =I50/I51 -> 0.48054475 | J49: =J50/J51 -> 0.61741077 | K49: =K50/K51 -> 0.59683042 | L49: =L50/L51 -> 0.62070363 | M49: =M50/M51 -> 0.62378405 | N49: =N50/N51 -> 0.60068093 | ... S49: =S50/S51 -> 0.58235403
B50: 1 | C50: Tổng sản lượng Thành phẩm SX | D50: Tấn | G50: ='3.Thanh pham'!G78 -> 689520 | H50: ='3.Thanh pham'!H78 -> 397800 | I50: ='3.Thanh pham'!I78 -> 918840 | J50: ='3.Thanh pham'!J78 -> 1104375 | K50: ='3.Thanh pham'!K78 -> 1104375 | L50: ='3.Thanh pham'!L78 -> 1148550 | M50: ='3.Thanh pham'!M78 -> 1192725 | N50: ='3.Thanh pham'!N78 -> 1148550 | ... R50: ='3.Thanh pham'!R78 -> 1192725 | S50: =SUM(G50:R50) -> 12254760
B51: 2 | C51: Tổng công suất máy (thành phẩm) | D51: Tấn | G51: ='Cong suat'!F$85 -> 1393920 | H51: ='Cong suat'!G$85 -> 1022208 | I51: ='Cong suat'!H$85 -> 1912080 | J51: ='Cong suat'!I$85 -> 1788720 | K51: ='Cong suat'!J$85 -> 1850400 | L51: ='Cong suat'!K$85 -> 1850400 | M51: ='Cong suat'!L$85 -> 1912080 | N51: ='Cong suat'!M$85 -> 1912080 | ... R51: ='Cong suat'!Q$85 -> 1912080 | S51: =SUM(G51:R51) -> 21043488
B53: 5. Năng suất lao động (kg/người/tháng)
B54: STT | C54: Loại chai nguyên liệu | D54: ĐVT | E54: Thực tế năm 2024 | F54: KQKD 2025 | G54: T1 | H54: T2 | I54: T3 | J54: T4 | K54: T5 | L54: T6 | M54: T7 | N54: T8 | O54: T9 | P54: T10 | Q54: T11 | R54: T12 | S54: KHKD 2026
C55: Năng suất lao động (Thực tế/ Định mức) | D55: % | G55: =G56/G57 -> 0.61043462 | H55: =H56/H57 -> 0.48023702 | I55: =I56/I57 -> 0.4098764 | J55: =J56/J57 -> 0.5425731 | K55: =K56/K57 -> 0.52448733 | L55: =L56/L57 -> 0.54546683 | M55: =M56/M57 -> 0.54817386 | N55: =N56/N57 -> 0.52787112 | ... S55: =S56/S57 -> 0.52899315
B56: 1 | C56: Năng suất lao động - Thực tế (tấn/người/tháng) | D56: Tấn/ người/ tháng | G56: =G50/'Dinh bien_HCNS'!F58 -> 14670.638 | H56: =H50/'Dinh bien_HCNS'!G58 -> 8463.8298 | I56: =I50/'Dinh bien_HCNS'!H58 -> 13512.353 | J56: =J50/'Dinh bien_HCNS'!I58 -> 16732.955 | K56: =K50/'Dinh bien_HCNS'!J58 -> 16732.955 | L56: =L50/'Dinh bien_HCNS'!K58 -> 17402.273 | M56: =M50/'Dinh bien_HCNS'!L58 -> 18071.591 | N56: =N50/'Dinh bien_HCNS'!M58 -> 17402.273 | ... R56: =R50/'Dinh bien_HCNS'!Q58 -> 18071.591 | S56: =AVERAGE(G56:R56) -> 15994.053
B57: 2 | C57: Năng suất lao động - Định mức (tấn/người/tháng) | D57: Tấn/ người/ tháng | G57: ='Cong suat'!F88 -> 24033.103 | H57: ='Cong suat'!G88 -> 17624.276 | I57: ='Cong suat'!H88 -> 32966.897 | J57: ='Cong suat'!I88 -> 30840 | K57: ='Cong suat'!J88 -> 31903.448 | L57: ='Cong suat'!K88 -> 31903.448 | M57: ='Cong suat'!L88 -> 32966.897 | N57: ='Cong suat'!M88 -> 32966.897 | ... R57: ='Cong suat'!Q88 -> 32966.897 | S57: =AVERAGE(G57:R57) -> 30234.897

Sheet 2.Hao hut & % chai 
B3: I - TỶ LỆ HAO HỤT CHAI PET
B4: 1 | C4: CHAI B0 - Xá tròn | D4: ĐVT | E4: KQKD 2024 | F4: KQKD 2025 | G4: T1 | H4: T2 | I4: T3 | J4: T4 | K4: T5 | L4: T6 | M4: T7 | N4: T8 | O4: T9 | P4: T10 | Q4: T11 | R4: T12 | S4: KHKD 2026
B5: 1 | C5: Nhãn | E5: 0.05 | F5: 0.055 | G5: 0.055 | H5: 0.055 | I5: 0.055 | J5: 0.055 | K5: 0.055 | L5: 0.055 | M5: 0.055 | N5: 0.055 | O5: 0.055 | P5: 0.055 | Q5: 0.055 | R5: 0.055
B6: 2 | C6: Hao hụt vô hình (nước, đất, ..) | E6: 0.04 | F6: 0.061 | G6: 0.055 | H6: 0.055 | I6: 0.055 | J6: 0.055 | K6: 0.055 | L6: 0.055 | M6: 0.055 | N6: 0.055 | O6: 0.055 | P6: 0.055 | Q6: 0.055 | R6: 0.055
C7: Tạp chất (ly mũ, ống hút, PET màu, trắng sữa, chai dín nhớt, nylong ….: loại trên chuyền)
C8: Tổng | E8: =SUM(E5:E7) -> 0.09 | F8: =SUM(F5:F7) -> 0.116 | G8: =SUM(G5:G7) -> 0.11 | H8: =SUM(H5:H7) -> 0.11 | I8: =SUM(I5:I7) -> 0.11 | J8: =SUM(J5:J7) -> 0.11 | K8: =SUM(K5:K7) -> 0.11 | L8: =SUM(L5:L7) -> 0.11 | ... R8: =SUM(R5:R7) -> 0.11
B10: 2 | C10: CHAI B0 - Ép kiện | D10: ĐVT | E10: =$E$4 -> KQKD 2024 | F10: KQKD 2025 | G10: T1 | H10: T2 | I10: T3 | J10: T4 | K10: T5 | L10: T6 | M10: T7 | N10: T8 | O10: T9 | P10: T10 | Q10: T11 | R10: T12 | S10: KHKD 2026
B11: 1 | C11: Nhãn | E11: 0.05 | F11: 0.055 | G11: 0.055 | H11: 0.055 | I11: 0.055 | J11: 0.055 | K11: 0.055 | L11: 0.055 | M11: 0.055 | N11: 0.055 | O11: 0.055 | P11: 0.055 | Q11: 0.055 | R11: 0.055
B12: 2 | C12: Hao hụt vô hình (nước, đất, ..) | E12: 0.06 | F12: 0.067 | G12: 0.055 | H12: 0.055 | I12: 0.055 | J12: 0.055 | K12: 0.055 | L12: 0.055 | M12: 0.055 | N12: 0.055 | O12: 0.055 | P12: 0.055 | Q12: 0.055 | R12: 0.055
B13: 3 | C13: Tạp chất (ly mũ, ống hút, PET màu, trắng sữa, chai dín nhớt, nylong ….: loại trên chuyền) | E13: 0.005 | F13: 0.02 | G13: 0.01 | H13: 0.01 | I13: 0.01 | J13: 0.01 | K13: 0.01 | L13: 0.01 | M13: 0.01 | N13: 0.01 | O13: 0.01 | P13: 0.01 | Q13: 0.01 | R13: 0.01
C14: Tổng | E14: =SUM(E11:E13) -> 0.115 | F14: =SUM(F11:F13) -> 0.142 | G14: =SUM(G11:G13) -> 0.12 | H14: =SUM(H11:H13) -> 0.12 | I14: =SUM(I11:I13) -> 0.12 | J14: =SUM(J11:J13) -> 0.12 | K14: =SUM(K11:K13) -> 0.12 | L14: =SUM(L11:L13) -> 0.12 | ... R14: =SUM(R11:R13) -> 0.12
B16: 3 | C16: CHAI B1.4 (XÔ TUYỂN) | D16: ĐVT | E16: KQKD 2024 | F16: KQKD 2025 | G16: T1 | H16: T2 | I16: T3 | J16: T4 | K16: T5 | L16: T6 | M16: T7 | N16: T8 | O16: T9 | P16: T10 | Q16: T11 | R16: T12 | S16: KHKD 2026
C17: Nhãn | F17: 0.005 | G17: 0.005 | H17: 0.005 | I17: 0.005 | J17: 0.005 | K17: 0.005 | L17: 0.005 | M17: 0.005 | N17: 0.005 | O17: 0.005 | P17: 0.005 | Q17: 0.005 | R17: 0.005
C18: Hao hụt vô hình (nước, đất, ..) | F18: 0.045 | G18: 0.055 | H18: 0.055 | I18: 0.055 | J18: 0.055 | K18: 0.055 | L18: 0.055 | M18: 0.055 | N18: 0.055 | O18: 0.055 | P18: 0.055 | Q18: 0.055 | R18: 0.055
C19: Tạp chất (ly mũ, ống hút, PET màu, trắng sữa, chai dín nhớt, nylong ….: loại trên chuyền)
C20: Tổng | E20: =SUM(E17:E19) -> 0 | F20: =SUM(F17:F19) -> 0.05 | G20: =SUM(G17:G19) -> 0.06 | H20: =SUM(H17:H19) -> 0.06 | I20: =SUM(I17:I19) -> 0.06 | J20: =SUM(J17:J19) -> 0.06 | K20: =SUM(K17:K19) -> 0.06 | L20: =SUM(L17:L19) -> 0.06 | ... R20: =SUM(R17:R19) -> 0.06
B22: II - TỶ LỆ HAO HỤT VẢY PET
B23: 1 | C23: Vảy - Băm B1 | D23: ĐVT | E23: KQKD 2024 | F23: KQKD 2025 | G23: T1 | H23: T2 | I23: T3 | J23: T4 | K23: T5 | L23: T6 | M23: T7 | N23: T8 | O23: T9 | P23: T10 | Q23: T11 | R23: T12 | S23: KHKD 2026
C24: Nắp tuyển nổi
C25: Bụi cám + nhãn | G25: 0.03 | H25: 0.03 | I25: 0.03 | J25: 0.03 | K25: 0.03 | L25: 0.03 | M25: 0.03 | N25: 0.03 | O25: 0.03 | P25: 0.03 | Q25: 0.03 | R25: 0.03
C26: Mấy kg | G26: 0.03 | H26: 0.03 | I26: 0.03 | J26: 0.03 | K26: 0.03 | L26: 0.03 | M26: 0.03 | N26: 0.03 | O26: 0.03 | P26: 0.03 | Q26: 0.03 | R26: 0.03
C27: Tổng hao hụt | G27: =SUM(G24:G26) -> 0.06 | H27: =SUM(H24:H26) -> 0.06 | I27: =SUM(I24:I26) -> 0.06 | J27: =SUM(J24:J26) -> 0.06 | K27: =SUM(K24:K26) -> 0.06 | L27: =SUM(L24:L26) -> 0.06 | M27: =SUM(M24:M26) -> 0.06 | N27: =SUM(N24:N26) -> 0.06 | ... R27: =SUM(R24:R26) -> 0.06
C28: Tỷ lệ vảy thành phẩm | G28: =1-G27 -> 0.94 | H28: =1-H27 -> 0.94 | I28: =1-I27 -> 0.94 | J28: =1-J27 -> 0.94 | K28: =1-K27 -> 0.94 | L28: =1-L27 -> 0.94 | M28: =1-M27 -> 0.94 | N28: =1-N27 -> 0.94 | ... R28: =1-R27 -> 0.94
B30: 2 | C30: Vảy - Băm B2/B3/B4/B5 | D30: ĐVT | E30: KQKD 2024 | F30: KQKD 2025 | G30: T1 | H30: T2 | I30: T3 | J30: T4 | K30: T5 | L30: T6 | M30: T7 | N30: T8 | O30: T9 | P30: T10 | Q30: T11 | R30: T12 | S30: KHKD 2026
C31: Nắp tuyển nổi
C32: Bụi cám + nhãn | G32: 0.04 | H32: 0.04 | I32: 0.04 | J32: 0.04 | K32: 0.04 | L32: 0.04 | M32: 0.04 | N32: 0.04 | O32: 0.04 | P32: 0.04 | Q32: 0.04 | R32: 0.04
C33: Mấy kg | G33: 0.04 | H33: 0.04 | I33: 0.04 | J33: 0.04 | K33: 0.04 | L33: 0.04 | M33: 0.04 | N33: 0.04 | O33: 0.04 | P33: 0.04 | Q33: 0.04 | R33: 0.04
C34: Tổng hao hụt | E34: =SUM(E31:E33) -> 0 | F34: =SUM(F31:F33) -> 0 | G34: =SUM(G31:G33) -> 0.08 | H34: =SUM(H31:H33) -> 0.08 | I34: =SUM(I31:I33) -> 0.08 | J34: =SUM(J31:J33) -> 0.08 | K34: =SUM(K31:K33) -> 0.08 | L34: =SUM(L31:L33) -> 0.08 | ... R34: =SUM(R31:R33) -> 0.08
C35: Tỷ lệ vảy thành phẩm | G35: =1-G34 -> 0.92 | H35: =1-H34 -> 0.92 | I35: =1-I34 -> 0.92 | J35: =1-J34 -> 0.92 | K35: =1-K34 -> 0.92 | L35: =1-L34 -> 0.92 | M35: =1-M34 -> 0.92 | N35: =1-N34 -> 0.92 | ... R35: =1-R34 -> 0.92
B37: 3 | C37: Vảy - Băm B6/B7 | D37: ĐVT | E37: KQKD 2024 | F37: KQKD 2025 | G37: T1 | H37: T2 | I37: T3 | J37: T4 | K37: T5 | L37: T6 | M37: T7 | N37: T8 | O37: T9 | P37: T10 | Q37: T11 | R37: T12 | S37: KHKD 2026
C38: Nắp tuyển nổi
C39: Bụi cám + nhãn | G39: 0.05 | H39: 0.05 | I39: 0.05 | J39: 0.05 | K39: 0.05 | L39: 0.05 | M39: 0.05 | N39: 0.05 | O39: 0.05 | P39: 0.05 | Q39: 0.05 | R39: 0.05
C40: Mấy kg | G40: 0.05 | H40: 0.05 | I40: 0.05 | J40: 0.05 | K40: 0.05 | L40: 0.05 | M40: 0.05 | N40: 0.05 | O40: 0.05 | P40: 0.05 | Q40: 0.05 | R40: 0.05
C41: Tổng hao hụt | E41: =SUM(E38:E40) -> 0 | F41: =SUM(F38:F40) -> 0 | G41: =SUM(G38:G40) -> 0.1 | H41: =SUM(H38:H40) -> 0.1 | I41: =SUM(I38:I40) -> 0.1 | J41: =SUM(J38:J40) -> 0.1 | K41: =SUM(K38:K40) -> 0.1 | L41: =SUM(L38:L40) -> 0.1 | ... R41: =SUM(R38:R40) -> 0.1
C42: Tỷ lệ vảy thành phẩm | G42: =1-G41 -> 0.9 | H42: =1-H41 -> 0.9 | I42: =1-I41 -> 0.9 | J42: =1-J41 -> 0.9 | K42: =1-K41 -> 0.9 | L42: =1-L41 -> 0.9 | M42: =1-M41 -> 0.9 | N42: =1-N41 -> 0.9 | ... R42: =1-R41 -> 0.9
B44: 4 | C44: Vảy - HD | D44: ĐVT | E44: KQKD 2024 | F44: KQKD 2025 | G44: T1 | H44: T2 | I44: T3 | J44: T4 | K44: T5 | L44: T6 | M44: T7 | N44: T8 | O44: T9 | P44: T10 | Q44: T11 | R44: T12 | S44: KHKD 2026
C45: Nắp tuyển nổi
C46: Bụi cám + nhãn
C47: Mấy kg | G47: 0.01 | H47: 0.01 | I47: 0.01 | J47: 0.01 | K47: 0.01 | L47: 0.01 | M47: 0.01 | N47: 0.01 | O47: 0.01 | P47: 0.01 | Q47: 0.01 | R47: 0.01
C48: Tổng hao hụt | G48: =SUM(G45:G47) -> 0.01 | H48: =SUM(H45:H47) -> 0.01 | I48: =SUM(I45:I47) -> 0.01 | J48: =SUM(J45:J47) -> 0.01 | K48: =SUM(K45:K47) -> 0.01 | L48: =SUM(L45:L47) -> 0.01 | M48: =SUM(M45:M47) -> 0.01 | N48: =SUM(N45:N47) -> 0.01 | ... R48: =SUM(R45:R47) -> 0.01
C49: Tỷ lệ vảy thành phẩm | G49: =1-G48 -> 0.99 | H49: =1-H48 -> 0.99 | I49: =1-I48 -> 0.99 | J49: =1-J48 -> 0.99 | K49: =1-K48 -> 0.99 | L49: =1-L48 -> 0.99 | M49: =1-M48 -> 0.99 | N49: =1-N48 -> 0.99 | ... R49: =1-R48 -> 0.99
B51: III - TỶ LỆ THÀNH PHẨM SAU KHI PHÂN LOẠI CHAI PET
B52: 1. Sản xuất từ chai PET B0 - Xá tròn
B53: STT | C53: Thành phẩm (chai sau phân loại) | D53: ĐVT | E53: KQKD 2024 | F53: KQKD 2025 | G53: T1 | H53: T2 | I53: T3 | J53: T4 | K53: T5 | L53: T6 | M53: T7 | N53: T8 | O53: T9 | P53: T10 | Q53: T11 | R53: T12 | S53: KHKD 2026
B54: 1 | C54: Chai PET B1
B55: 2 | C55: Chai PET B1 Không Phân Loại | E55: 0.506 | F55: 0.498 | G55: 0.48 | H55: 0.48 | I55: 0.48 | J55: 0.48 | K55: 0.48 | L55: 0.48 | M55: 0.48 | N55: 0.48 | O55: 0.48 | P55: 0.48 | Q55: 0.48 | R55: 0.48
B56: 3 | C56: Chai PET B1.3
B57: 4 | C57: Chai PET B2.1
B58: 5 | C58: Chai PET B2.2 | E58: 0.088 | F58: 0.085 | G58: 0.095 | H58: 0.095 | I58: 0.095 | J58: 0.095 | K58: 0.095 | L58: 0.095 | M58: 0.095 | N58: 0.095 | O58: 0.095 | P58: 0.095 | Q58: 0.095 | R58: 0.095
B59: 6 | C59: Chai PET B3
B60: 7 | C60: Chai PET B4 | E60: 0.021 | F60: 0.021 | G60: 0.01 | H60: 0.01 | I60: 0.01 | J60: 0.01 | K60: 0.01 | L60: 0.01 | M60: 0.01 | N60: 0.01 | O60: 0.01 | P60: 0.01 | Q60: 0.01 | R60: 0.01
B61: 8 | C61: Chai PET B5 | E61: 0.015 | F61: 0.012 | G61: 0.01 | H61: 0.01 | I61: 0.01 | J61: 0.01 | K61: 0.01 | L61: 0.01 | M61: 0.01 | N61: 0.01 | O61: 0.01 | P61: 0.01 | Q61: 0.01 | R61: 0.01
B62: 9 | C62: Chai PET B6.1
B63: 10 | C63: Chai PET B6.2 | E63: 0.274 | F63: 0.256 | G63: 0.27 | H63: 0.27 | I63: 0.27 | J63: 0.27 | K63: 0.27 | L63: 0.27 | M63: 0.27 | N63: 0.27 | O63: 0.27 | P63: 0.27 | Q63: 0.27 | R63: 0.27
B64: 11 | C64: Chai PET B7.1
B65: 12 | C65: Chai PET B7.2
B66: 13 | C66: Cổ Chai PET | F66: 0.005 | G66: 0.01 | H66: 0.01 | I66: 0.01 | J66: 0.01 | K66: 0.01 | L66: 0.01 | M66: 0.01 | N66: 0.01 | O66: 0.01 | P66: 0.01 | Q66: 0.01 | R66: 0.01
B67: 14 | C67: Nắp HD ép các màu | E67: 0.006 | F67: 0.005 | G67: 0.01 | H67: 0.01 | I67: 0.01 | J67: 0.01 | K67: 0.01 | L67: 0.01 | M67: 0.01 | N67: 0.01 | O67: 0.01 | P67: 0.01 | Q67: 0.01 | R67: 0.01
B68: 15 | C68: Khác | F68: 0.002 | G68: 0.005 | H68: 0.005 | I68: 0.005 | J68: 0.005 | K68: 0.005 | L68: 0.005 | M68: 0.005 | N68: 0.005 | O68: 0.005 | P68: 0.005 | Q68: 0.005 | R68: 0.005
C69: TỔNG: | E69: =SUM(E54:E67) -> 0.91 | F69: =SUM(F54:F68) -> 0.884 | G69: =SUM(G54:G68) -> 0.89 | H69: =SUM(H54:H68) -> 0.89 | I69: =SUM(I54:I68) -> 0.89 | J69: =SUM(J54:J68) -> 0.89 | K69: =SUM(K54:K68) -> 0.89 | L69: =SUM(L54:L68) -> 0.89 | M69: =SUM(M54:M68) -> 0.89 | ... R69: =SUM(R54:R68) -> 0.89
G70: =100%-G69-G8 -> 0 | H70: =100%-H69-H8 -> 0 | I70: =100%-I69-I8 -> 0 | J70: =100%-J69-J8 -> 0 | K70: =100%-K69-K8 -> 0 | L70: =100%-L69-L8 -> 0 | M70: =100%-M69-M8 -> 0 | N70: =100%-N69-N8 -> 0 | ... R70: =100%-R69-R8 -> 0
B71: 2. Sản xuất từ chai PET B0 - Ép kiện
B72: STT | C72: Thành phẩm (chai sau phân loại) | D72: ĐVT | E72: KQKD 2024 | F72: KQKD 2025 | G72: T1 | H72: T2 | I72: T3 | J72: T4 | K72: T5 | L72: T6 | M72: T7 | N72: T8 | O72: T9 | P72: T10 | Q72: T11 | R72: T12 | S72: KHKD 2026
B73: 1 | C73: Chai PET B1
B74: 2 | C74: Chai PET B1 Không Phân Loại | E74: 0.444 | F74: 0.473 | G74: 0.46 | H74: 0.46 | I74: 0.46 | J74: 0.46 | K74: 0.46 | L74: 0.46 | M74: 0.46 | N74: 0.46 | O74: 0.46 | P74: 0.46 | Q74: 0.46 | R74: 0.46
B75: 3 | C75: Chai PET B1.3
B76: 4 | C76: Chai PET B2.1
B77: 5 | C77: Chai PET B2.2 | E77: 0.095 | F77: =9.4%-1.6% -> 0.078 | G77: 0.09 | H77: 0.09 | I77: 0.09 | J77: 0.09 | K77: 0.09 | L77: 0.09 | M77: 0.09 | N77: 0.09 | O77: 0.09 | P77: 0.09 | Q77: 0.09 | R77: 0.09
B78: 6 | C78: Chai PET B3
B79: 7 | C79: Chai PET B4 | E79: 0.02 | F79: 0.019 | G79: 0.01 | H79: 0.01 | I79: 0.01 | J79: 0.01 | K79: 0.01 | L79: 0.01 | M79: 0.01 | N79: 0.01 | O79: 0.01 | P79: 0.01 | Q79: 0.01 | R79: 0.01
B80: 8 | C80: Chai PET B5 | E80: 0.015 | F80: 0.01 | G80: 0.005 | H80: 0.005 | I80: 0.005 | J80: 0.005 | K80: 0.005 | L80: 0.005 | M80: 0.005 | N80: 0.005 | O80: 0.005 | P80: 0.005 | Q80: 0.005 | R80: 0.005
B81: 9 | C81: Chai PET B6.1
B82: 10 | C82: Chai PET B6.2 | E82: 0.305 | F82: 0.265 | G82: 0.28 | H82: 0.28 | I82: 0.28 | J82: 0.28 | K82: 0.28 | L82: 0.28 | M82: 0.28 | N82: 0.28 | O82: 0.28 | P82: 0.28 | Q82: 0.28 | R82: 0.28
B83: 11 | C83: Chai PET B7.1
B84: 12 | C84: Chai PET B7.2
B85: 13 | C85: Cổ Chai PET | F85: 0.004 | G85: 0.01 | H85: 0.01 | I85: 0.01 | J85: 0.01 | K85: 0.01 | L85: 0.01 | M85: 0.01 | N85: 0.01 | O85: 0.01 | P85: 0.01 | Q85: 0.01 | R85: 0.01
B86: 14 | C86: Nắp HD ép các màu | E86: 0.006 | F86: 0.006 | G86: 0.01 | H86: 0.01 | I86: 0.01 | J86: 0.01 | K86: 0.01 | L86: 0.01 | M86: 0.01 | N86: 0.01 | O86: 0.01 | P86: 0.01 | Q86: 0.01 | R86: 0.01
B87: 15 | C87: Khác | F87: 0.003 | G87: 0.015 | H87: 0.015 | I87: 0.015 | J87: 0.015 | K87: 0.015 | L87: 0.015 | M87: 0.015 | N87: 0.015 | O87: 0.015 | P87: 0.015 | Q87: 0.015 | R87: 0.015
C88: TỔNG: | E88: =SUM(E73:E86) -> 0.885 | F88: =SUM(F73:F87) -> 0.858 | G88: =SUM(G73:G87) -> 0.88 | H88: =SUM(H73:H87) -> 0.88 | I88: =SUM(I73:I87) -> 0.88 | J88: =SUM(J73:J87) -> 0.88 | K88: =SUM(K73:K87) -> 0.88 | L88: =SUM(L73:L87) -> 0.88 | M88: =SUM(M73:M87) -> 0.88 | ... R88: =SUM(R73:R87) -> 0.88
F89: =100%-F88-F14 -> 0 | G89: =100%-G88-G14 -> -1.110223e-16 | H89: =100%-H88-H14 -> -1.110223e-16 | I89: =100%-I88-I14 -> -1.110223e-16 | J89: =100%-J88-J14 -> -1.110223e-16 | K89: =100%-K88-K14 -> -1.110223e-16 | L89: =100%-L88-L14 -> -1.110223e-16 | M89: =100%-M88-M14 -> -1.110223e-16 | ... R89: =100%-R88-R14 -> -1.110223e-16
B90: 3. Sản xuất từ chai PET B1.4 (tuyển xô)
B91: STT | C91: Thành phẩm (chai sau phân loại) | D91: ĐVT | E91: KQKD 2024 | F91: KQKD 2025 | G91: T1 | H91: T2 | I91: T3 | J91: T4 | K91: T5 | L91: T6 | M91: T7 | N91: T8 | O91: T9 | P91: T10 | Q91: T11 | R91: T12 | S91: Mục tiêu 2026
B92: 1 | C92: Chai PET B1 | G92: 0.65 | H92: 0.65 | I92: 0.65 | J92: 0.65 | K92: 0.65 | L92: 0.65 | M92: 0.65 | N92: 0.65 | O92: 0.65 | P92: 0.65 | Q92: 0.65 | R92: 0.65
B93: 2 | C93: Chai PET B1 Không Phân Loại
B94: 3 | C94: Chai PET B1.3
B95: 4 | C95: Chai PET B2.1
B96: 5 | C96: Chai PET B2.2
B97: 6 | C97: Chai PET B3
B98: 7 | C98: Chai PET B4
B99: 8 | C99: Chai PET B5
B100: 9 | C100: Chai PET B6.1
B101: 10 | C101: Chai PET B6.2 | G101: 0.28 | H101: 0.28 | I101: 0.28 | J101: 0.28 | K101: 0.28 | L101: 0.28 | M101: 0.28 | N101: 0.28 | O101: 0.28 | P101: 0.28 | Q101: 0.28 | R101: 0.28
B102: 11 | C102: Chai PET B7.1
B103: 12 | C103: Chai PET B7.2
B104: 13 | C104: Cổ Chai PET | G104: 0.005 | H104: 0.005 | I104: 0.005 | J104: 0.005 | K104: 0.005 | L104: 0.005 | M104: 0.005 | N104: 0.005 | O104: 0.005 | P104: 0.005 | Q104: 0.005 | R104: 0.005
B105: 14 | C105: Nắp HD ép các màu | G105: 0.005 | H105: 0.005 | I105: 0.005 | J105: 0.005 | K105: 0.005 | L105: 0.005 | M105: 0.005 | N105: 0.005 | O105: 0.005 | P105: 0.005 | Q105: 0.005 | R105: 0.005
B106: 15 | C106: Khác
C107: TỔNG: | E107: =SUM(E92:E105) -> 0 | F107: =SUM(F92:F105) -> 0 | G107: =SUM(G92:G106) -> 0.94 | H107: =SUM(H92:H106) -> 0.94 | I107: =SUM(I92:I106) -> 0.94 | J107: =SUM(J92:J106) -> 0.94 | K107: =SUM(K92:K106) -> 0.94 | L107: =SUM(L92:L106) -> 0.94 | M107: =SUM(M92:M106) -> 0.94 | N107: =SUM(N92:N106) -> 0.94 | ... R107: =SUM(R92:R106) -> 0.94
G108: =1-G107-G20 -> -5.5511151e-17 | H108: =1-H107-H20 -> -5.5511151e-17 | I108: =1-I107-I20 -> -5.5511151e-17 | J108: =1-J107-J20 -> -5.5511151e-17 | K108: =1-K107-K20 -> -5.5511151e-17 | L108: =1-L107-L20 -> -5.5511151e-17 | M108: =1-M107-M20 -> -5.5511151e-17 | N108: =1-N107-N20 -> -5.5511151e-17 | ... R108: =1-R107-R20 -> -5.5511151e-17
B109: IV - TỶ LỆ CHAI PET CHUYỂN VÀO BĂM VẢY PET
...

Sheet 3.Thanh pham
B3: I - THÀNH PHẨM SAU PHÂN LOẠI CHAI PET
B4: 1.1 Sản xuất từ chai PET B0 - Xá tròn | S4: ĐVT: Tấn
B5: STT | C5: Thành phẩm (chai sau phân loại) | D5: ĐVT | E5: Thực tế năm 2024 | F5: KQKD 2025 | G5: T1 | H5: T2 | I5: T3 | J5: T4 | K5: T5 | L5: T6 | M5: T7 | N5: T8 | O5: T9 | P5: T10 | Q5: T11 | R5: T12 | S5: Mục tiêu 2026
B6: 1 | C6: Chai PET B1 | G6: ='1.NVL Chai'!G$13*'2.Hao hut & % chai '!G54 -> 0 | H6: ='1.NVL Chai'!H$13*'2.Hao hut & % chai '!H54 -> 0 | I6: ='1.NVL Chai'!I$13*'2.Hao hut & % chai '!I54 -> 0 | J6: ='1.NVL Chai'!J$13*'2.Hao hut & % chai '!J54 -> 0 | K6: ='1.NVL Chai'!K$13*'2.Hao hut & % chai '!K54 -> 0 | L6: ='1.NVL Chai'!L$13*'2.Hao hut & % chai '!L54 -> 0 | M6: ='1.NVL Chai'!M$13*'2.Hao hut & % chai '!M54 -> 0 | N6: ='1.NVL Chai'!N$13*'2.Hao hut & % chai '!N54 -> 0 | ... R6: ='1.NVL Chai'!R$13*'2.Hao hut & % chai '!R54 -> 0 | S6: =SUM(G6:R6) -> 0
B7: 2 | C7: Chai PET B1 Không Phân Loại | F7: 1250112.9 | G7: ='1.NVL Chai'!G$13*'2.Hao hut & % chai '!G55 -> 149760 | H7: ='1.NVL Chai'!H$13*'2.Hao hut & % chai '!H55 -> 86400 | I7: ='1.NVL Chai'!I$13*'2.Hao hut & % chai '!I55 -> 174720 | J7: ='1.NVL Chai'!J$13*'2.Hao hut & % chai '!J55 -> 210000 | K7: ='1.NVL Chai'!K$13*'2.Hao hut & % chai '!K55 -> 210000 | L7: ='1.NVL Chai'!L$13*'2.Hao hut & % chai '!L55 -> 218400 | M7: ='1.NVL Chai'!M$13*'2.Hao hut & % chai '!M55 -> 226800 | N7: ='1.NVL Chai'!N$13*'2.Hao hut & % chai '!N55 -> 218400 | ... R7: ='1.NVL Chai'!R$13*'2.Hao hut & % chai '!R55 -> 226800 | S7: =SUM(G7:R7) -> 2359680
B8: 3 | C8: Chai PET B1.3 | F8: 134630.93 | G8: ='1.NVL Chai'!G$13*'2.Hao hut & % chai '!G56 -> 0 | H8: ='1.NVL Chai'!H$13*'2.Hao hut & % chai '!H56 -> 0 | I8: ='1.NVL Chai'!I$13*'2.Hao hut & % chai '!I56 -> 0 | J8: ='1.NVL Chai'!J$13*'2.Hao hut & % chai '!J56 -> 0 | K8: ='1.NVL Chai'!K$13*'2.Hao hut & % chai '!K56 -> 0 | L8: ='1.NVL Chai'!L$13*'2.Hao hut & % chai '!L56 -> 0 | M8: ='1.NVL Chai'!M$13*'2.Hao hut & % chai '!M56 -> 0 | N8: ='1.NVL Chai'!N$13*'2.Hao hut & % chai '!N56 -> 0 | ... R8: ='1.NVL Chai'!R$13*'2.Hao hut & % chai '!R56 -> 0 | S8: =SUM(G8:R8) -> 0
B9: 4 | C9: Chai PET B2.1 | F9: 0 | G9: ='1.NVL Chai'!G$13*'2.Hao hut & % chai '!G57 -> 0 | H9: ='1.NVL Chai'!H$13*'2.Hao hut & % chai '!H57 -> 0 | I9: ='1.NVL Chai'!I$13*'2.Hao hut & % chai '!I57 -> 0 | J9: ='1.NVL Chai'!J$13*'2.Hao hut & % chai '!J57 -> 0 | K9: ='1.NVL Chai'!K$13*'2.Hao hut & % chai '!K57 -> 0 | L9: ='1.NVL Chai'!L$13*'2.Hao hut & % chai '!L57 -> 0 | M9: ='1.NVL Chai'!M$13*'2.Hao hut & % chai '!M57 -> 0 | N9: ='1.NVL Chai'!N$13*'2.Hao hut & % chai '!N57 -> 0 | ... R9: ='1.NVL Chai'!R$13*'2.Hao hut & % chai '!R57 -> 0 | S9: =SUM(G9:R9) -> 0
B10: 5 | C10: Chai PET B2.2 | F10: 255018.53 | G10: ='1.NVL Chai'!G$13*'2.Hao hut & % chai '!G58 -> 29640 | H10: ='1.NVL Chai'!H$13*'2.Hao hut & % chai '!H58 -> 17100 | I10: ='1.NVL Chai'!I$13*'2.Hao hut & % chai '!I58 -> 34580 | J10: ='1.NVL Chai'!J$13*'2.Hao hut & % chai '!J58 -> 41562.5 | K10: ='1.NVL Chai'!K$13*'2.Hao hut & % chai '!K58 -> 41562.5 | L10: ='1.NVL Chai'!L$13*'2.Hao hut & % chai '!L58 -> 43225 | M10: ='1.NVL Chai'!M$13*'2.Hao hut & % chai '!M58 -> 44887.5 | N10: ='1.NVL Chai'!N$13*'2.Hao hut & % chai '!N58 -> 43225 | ... R10: ='1.NVL Chai'!R$13*'2.Hao hut & % chai '!R58 -> 44887.5 | S10: =SUM(G10:R10) -> 467020
B11: 6 | C11: Chai PET B3 | F11: 0 | G11: ='1.NVL Chai'!G$13*'2.Hao hut & % chai '!G59 -> 0 | H11: ='1.NVL Chai'!H$13*'2.Hao hut & % chai '!H59 -> 0 | I11: ='1.NVL Chai'!I$13*'2.Hao hut & % chai '!I59 -> 0 | J11: ='1.NVL Chai'!J$13*'2.Hao hut & % chai '!J59 -> 0 | K11: ='1.NVL Chai'!K$13*'2.Hao hut & % chai '!K59 -> 0 | L11: ='1.NVL Chai'!L$13*'2.Hao hut & % chai '!L59 -> 0 | M11: ='1.NVL Chai'!M$13*'2.Hao hut & % chai '!M59 -> 0 | N11: ='1.NVL Chai'!N$13*'2.Hao hut & % chai '!N59 -> 0 | ... R11: ='1.NVL Chai'!R$13*'2.Hao hut & % chai '!R59 -> 0 | S11: =SUM(G11:R11) -> 0
B12: 7 | C12: Chai PET B4 | F12: 57045.999 | G12: ='1.NVL Chai'!G$13*'2.Hao hut & % chai '!G60 -> 3120 | H12: ='1.NVL Chai'!H$13*'2.Hao hut & % chai '!H60 -> 1800 | I12: ='1.NVL Chai'!I$13*'2.Hao hut & % chai '!I60 -> 3640 | J12: ='1.NVL Chai'!J$13*'2.Hao hut & % chai '!J60 -> 4375 | K12: ='1.NVL Chai'!K$13*'2.Hao hut & % chai '!K60 -> 4375 | L12: ='1.NVL Chai'!L$13*'2.Hao hut & % chai '!L60 -> 4550 | M12: ='1.NVL Chai'!M$13*'2.Hao hut & % chai '!M60 -> 4725 | N12: ='1.NVL Chai'!N$13*'2.Hao hut & % chai '!N60 -> 4550 | ... R12: ='1.NVL Chai'!R$13*'2.Hao hut & % chai '!R60 -> 4725 | S12: =SUM(G12:R12) -> 49160
B13: 8 | C13: Chai PET B5 | F13: 35424.925 | G13: ='1.NVL Chai'!G$13*'2.Hao hut & % chai '!G61 -> 3120 | H13: ='1.NVL Chai'!H$13*'2.Hao hut & % chai '!H61 -> 1800 | I13: ='1.NVL Chai'!I$13*'2.Hao hut & % chai '!I61 -> 3640 | J13: ='1.NVL Chai'!J$13*'2.Hao hut & % chai '!J61 -> 4375 | K13: ='1.NVL Chai'!K$13*'2.Hao hut & % chai '!K61 -> 4375 | L13: ='1.NVL Chai'!L$13*'2.Hao hut & % chai '!L61 -> 4550 | M13: ='1.NVL Chai'!M$13*'2.Hao hut & % chai '!M61 -> 4725 | N13: ='1.NVL Chai'!N$13*'2.Hao hut & % chai '!N61 -> 4550 | ... R13: ='1.NVL Chai'!R$13*'2.Hao hut & % chai '!R61 -> 4725 | S13: =SUM(G13:R13) -> 49160
B14: 9 | C14: Chai PET B6.1 | F14: 0 | G14: ='1.NVL Chai'!G$13*'2.Hao hut & % chai '!G62 -> 0 | H14: ='1.NVL Chai'!H$13*'2.Hao hut & % chai '!H62 -> 0 | I14: ='1.NVL Chai'!I$13*'2.Hao hut & % chai '!I62 -> 0 | J14: ='1.NVL Chai'!J$13*'2.Hao hut & % chai '!J62 -> 0 | K14: ='1.NVL Chai'!K$13*'2.Hao hut & % chai '!K62 -> 0 | L14: ='1.NVL Chai'!L$13*'2.Hao hut & % chai '!L62 -> 0 | M14: ='1.NVL Chai'!M$13*'2.Hao hut & % chai '!M62 -> 0 | N14: ='1.NVL Chai'!N$13*'2.Hao hut & % chai '!N62 -> 0 | ... R14: ='1.NVL Chai'!R$13*'2.Hao hut & % chai '!R62 -> 0 | S14: =SUM(G14:R14) -> 0
B15: 10 | C15: Chai PET B6.2 | F15: 795960.63 | G15: ='1.NVL Chai'!G$13*'2.Hao hut & % chai '!G63 -> 84240 | H15: ='1.NVL Chai'!H$13*'2.Hao hut & % chai '!H63 -> 48600 | I15: ='1.NVL Chai'!I$13*'2.Hao hut & % chai '!I63 -> 98280 | J15: ='1.NVL Chai'!J$13*'2.Hao hut & % chai '!J63 -> 118125 | K15: ='1.NVL Chai'!K$13*'2.Hao hut & % chai '!K63 -> 118125 | L15: ='1.NVL Chai'!L$13*'2.Hao hut & % chai '!L63 -> 122850 | M15: ='1.NVL Chai'!M$13*'2.Hao hut & % chai '!M63 -> 127575 | N15: ='1.NVL Chai'!N$13*'2.Hao hut & % chai '!N63 -> 122850 | ... R15: ='1.NVL Chai'!R$13*'2.Hao hut & % chai '!R63 -> 127575 | S15: =SUM(G15:R15) -> 1327320
B16: 11 | C16: Chai PET B7.1 | F16: 0 | G16: ='1.NVL Chai'!G$13*'2.Hao hut & % chai '!G64 -> 0 | H16: ='1.NVL Chai'!H$13*'2.Hao hut & % chai '!H64 -> 0 | I16: ='1.NVL Chai'!I$13*'2.Hao hut & % chai '!I64 -> 0 | J16: ='1.NVL Chai'!J$13*'2.Hao hut & % chai '!J64 -> 0 | K16: ='1.NVL Chai'!K$13*'2.Hao hut & % chai '!K64 -> 0 | L16: ='1.NVL Chai'!L$13*'2.Hao hut & % chai '!L64 -> 0 | M16: ='1.NVL Chai'!M$13*'2.Hao hut & % chai '!M64 -> 0 | N16: ='1.NVL Chai'!N$13*'2.Hao hut & % chai '!N64 -> 0 | ... R16: ='1.NVL Chai'!R$13*'2.Hao hut & % chai '!R64 -> 0 | S16: =SUM(G16:R16) -> 0
B17: 12 | C17: Chai PET B7.2 | F17: 1631.8631 | G17: ='1.NVL Chai'!G$13*'2.Hao hut & % chai '!G65 -> 0 | H17: ='1.NVL Chai'!H$13*'2.Hao hut & % chai '!H65 -> 0 | I17: ='1.NVL Chai'!I$13*'2.Hao hut & % chai '!I65 -> 0 | J17: ='1.NVL Chai'!J$13*'2.Hao hut & % chai '!J65 -> 0 | K17: ='1.NVL Chai'!K$13*'2.Hao hut & % chai '!K65 -> 0 | L17: ='1.NVL Chai'!L$13*'2.Hao hut & % chai '!L65 -> 0 | M17: ='1.NVL Chai'!M$13*'2.Hao hut & % chai '!M65 -> 0 | N17: ='1.NVL Chai'!N$13*'2.Hao hut & % chai '!N65 -> 0 | ... R17: ='1.NVL Chai'!R$13*'2.Hao hut & % chai '!R65 -> 0 | S17: =SUM(G17:R17) -> 0
B18: 13 | C18: Cổ Chai PET | F18: 0 | G18: ='1.NVL Chai'!G$13*'2.Hao hut & % chai '!G66 -> 3120 | H18: ='1.NVL Chai'!H$13*'2.Hao hut & % chai '!H66 -> 1800 | I18: ='1.NVL Chai'!I$13*'2.Hao hut & % chai '!I66 -> 3640 | J18: ='1.NVL Chai'!J$13*'2.Hao hut & % chai '!J66 -> 4375 | K18: ='1.NVL Chai'!K$13*'2.Hao hut & % chai '!K66 -> 4375 | L18: ='1.NVL Chai'!L$13*'2.Hao hut & % chai '!L66 -> 4550 | M18: ='1.NVL Chai'!M$13*'2.Hao hut & % chai '!M66 -> 4725 | N18: ='1.NVL Chai'!N$13*'2.Hao hut & % chai '!N66 -> 4550 | ... R18: ='1.NVL Chai'!R$13*'2.Hao hut & % chai '!R66 -> 4725 | S18: =SUM(G18:R18) -> 49160
... B20: 15 | C20: Khác | F20: 11803.2 | G20: ='1.NVL Chai'!G$13*'2.Hao hut & % chai '!G68 -> 1560 | H20: ='1.NVL Chai'!H$13*'2.Hao hut & % chai '!H68 -> 900 | I20: ='1.NVL Chai'!I$13*'2.Hao hut & % chai '!I68 -> 1820 | J20: ='1.NVL Chai'!J$13*'2.Hao hut & % chai '!J68 -> 2187.5 | K20: ='1.NVL Chai'!K$13*'2.Hao hut & % chai '!K68 -> 2187.5 | L20: ='1.NVL Chai'!L$13*'2.Hao hut & % chai '!L68 -> 2275 | M20: ='1.NVL Chai'!M$13*'2.Hao hut & % chai '!M68 -> 2362.5 | N20: ='1.NVL Chai'!N$13*'2.Hao hut & % chai '!N68 -> 2275 | ... R20: ='1.NVL Chai'!R$13*'2.Hao hut & % chai '!R68 -> 2362.5 | S20: =SUM(G20:R20) -> 24580
C21: TỔNG: | F21: =SUM(F6:F20) -> 2560511.3 | G21: =SUM(G6:G20) -> 277680 | H21: =SUM(H6:H20) -> 160200 | I21: =SUM(I6:I20) -> 323960 | J21: =SUM(J6:J20) -> 389375 | K21: =SUM(K6:K20) -> 389375 | L21: =SUM(L6:L20) -> 404950 | M21: =SUM(M6:M20) -> 420525 | ... S21: =SUM(S6:S20) -> 4375240
B23: 1.2 Sản xuất từ chai PET B0 - Ép kiện | S23: ĐVT: Tấn
B24: STT | C24: Thành phẩm (chai sau phân loại) | D24: ĐVT | E24: Thực tế năm 2024 | F24: KQKD 2025 | G24: T1 | H24: T2 | I24: T3 | J24: T4 | K24: T5 | L24: T6 | M24: T7 | N24: T8 | O24: T9 | P24: T10 | Q24: T11 | R24: T12 | S24: Mục tiêu 2026
B25: 1 | C25: Chai PET B1 | G25: ='1.NVL Chai'!G$14*'2.Hao hut & % chai '!G73 -> 0 | H25: ='1.NVL Chai'!H$14*'2.Hao hut & % chai '!H73 -> 0 | I25: ='1.NVL Chai'!I$14*'2.Hao hut & % chai '!I73 -> 0 | J25: ='1.NVL Chai'!J$14*'2.Hao hut & % chai '!J73 -> 0 | K25: ='1.NVL Chai'!K$14*'2.Hao hut & % chai '!K73 -> 0 | L25: ='1.NVL Chai'!L$14*'2.Hao hut & % chai '!L73 -> 0 | M25: ='1.NVL Chai'!M$14*'2.Hao hut & % chai '!M73 -> 0 | N25: ='1.NVL Chai'!N$14*'2.Hao hut & % chai '!N73 -> 0 | ... R25: ='1.NVL Chai'!R$14*'2.Hao hut & % chai '!R73 -> 0 | S25: =SUM(G25:R25) -> 0
B26: 2 | C26: Chai PET B1 Không Phân Loại | F26: 1067591.6 | G26: ='1.NVL Chai'!G$14*'2.Hao hut & % chai '!G74 -> 215280 | H26: ='1.NVL Chai'!H$14*'2.Hao hut & % chai '!H74 -> 124200 | I26: ='1.NVL Chai'!I$14*'2.Hao hut & % chai '!I74 -> 310960 | J26: ='1.NVL Chai'!J$14*'2.Hao hut & % chai '!J74 -> 373750 | K26: ='1.NVL Chai'!K$14*'2.Hao hut & % chai '!K74 -> 373750 | L26: ='1.NVL Chai'!L$14*'2.Hao hut & % chai '!L74 -> 388700 | M26: ='1.NVL Chai'!M$14*'2.Hao hut & % chai '!M74 -> 403650 | N26: ='1.NVL Chai'!N$14*'2.Hao hut & % chai '!N74 -> 388700 | ... R26: ='1.NVL Chai'!R$14*'2.Hao hut & % chai '!R74 -> 403650 | S26: =SUM(G26:R26) -> 4118840
B27: 3 | C27: Chai PET B1.3 | F27: 114974.29 | G27: ='1.NVL Chai'!G$14*'2.Hao hut & % chai '!G75 -> 0 | H27: ='1.NVL Chai'!H$14*'2.Hao hut & % chai '!H75 -> 0 | I27: ='1.NVL Chai'!I$14*'2.Hao hut & % chai '!I75 -> 0 | J27: ='1.NVL Chai'!J$14*'2.Hao hut & % chai '!J75 -> 0 | K27: ='1.NVL Chai'!K$14*'2.Hao hut & % chai '!K75 -> 0 | L27: ='1.NVL Chai'!L$14*'2.Hao hut & % chai '!L75 -> 0 | M27: ='1.NVL Chai'!M$14*'2.Hao hut & % chai '!M75 -> 0 | N27: ='1.NVL Chai'!N$14*'2.Hao hut & % chai '!N75 -> 0 | ... R27: ='1.NVL Chai'!R$14*'2.Hao hut & % chai '!R75 -> 0 | S27: =SUM(G27:R27) -> 0
B28: 4 | C28: Chai PET B2.1 | F28: 0 | G28: ='1.NVL Chai'!G$14*'2.Hao hut & % chai '!G76 -> 0 | H28: ='1.NVL Chai'!H$14*'2.Hao hut & % chai '!H76 -> 0 | I28: ='1.NVL Chai'!I$14*'2.Hao hut & % chai '!I76 -> 0 | J28: ='1.NVL Chai'!J$14*'2.Hao hut & % chai '!J76 -> 0 | K28: ='1.NVL Chai'!K$14*'2.Hao hut & % chai '!K76 -> 0 | L28: ='1.NVL Chai'!L$14*'2.Hao hut & % chai '!L76 -> 0 | M28: ='1.NVL Chai'!M$14*'2.Hao hut & % chai '!M76 -> 0 | N28: ='1.NVL Chai'!N$14*'2.Hao hut & % chai '!N76 -> 0 | ... R28: ='1.NVL Chai'!R$14*'2.Hao hut & % chai '!R76 -> 0 | S28: =SUM(G28:R28) -> 0
B29: 5 | C29: Chai PET B2.2 | F29: 217784.83 | G29: ='1.NVL Chai'!G$14*'2.Hao hut & % chai '!G77 -> 42120 | H29: ='1.NVL Chai'!H$14*'2.Hao hut & % chai '!H77 -> 24300 | I29: ='1.NVL Chai'!I$14*'2.Hao hut & % chai '!I77 -> 60840 | J29: ='1.NVL Chai'!J$14*'2.Hao hut & % chai '!J77 -> 73125 | K29: ='1.NVL Chai'!K$14*'2.Hao hut & % chai '!K77 -> 73125 | L29: ='1.NVL Chai'!L$14*'2.Hao hut & % chai '!L77 -> 76050 | M29: ='1.NVL Chai'!M$14*'2.Hao hut & % chai '!M77 -> 78975 | N29: ='1.NVL Chai'!N$14*'2.Hao hut & % chai '!N77 -> 76050 | ... R29: ='1.NVL Chai'!R$14*'2.Hao hut & % chai '!R77 -> 78975 | S29: =SUM(G29:R29) -> 805860
