Workbook
Name _1: #REF!
Name _1: #REF!
Name _1: #REF!
Name _2: #REF!
Name _2: #REF!
Name _2: #REF!
Name _3: #REF!
Name _3: #REF!
Name _3: #REF!
Name _4: #REF!
Name _4: #REF!
Name _4: #REF!
Name _5: #REF!
Name _5: #REF!
Name _5: #REF!
Name a: #REF!
Name a: #REF!
Name a: #REF!
Name Accounts: #REF!
Name Accounts: #REF!
Name Accounts: #REF!
Name Activity_Reports: #REF!
Name Activity_Reports: #REF!
Name Activity_Reports: #REF!
Name ADM: #REF!
Name ADM: #REF!
Name ADM: #REF!
Name Application: [6]!Table6[Application]
Name B: #REF!
Name B: #REF!
Name B: #REF!
Name back: #REF!
Name back: #REF!
Name back: #REF!
Name Calendar: #REF!
Name Calendar: #REF!
Name Calendar: #REF!
Name Catalogue_xls: #REF!
Name Catalogue_xls: #REF!
Name Catalogue_xls: #REF!
Name CompanyCode: [11]CompanyCode!$A$2:$A$5
Name Contractingdiv: #REF!
Name Contractingdiv: #REF!
Name Contractingdiv: #REF!
Name corporate_affairs: #REF!
Name corporate_affairs: #REF!
Name corporate_affairs: #REF!
Name CTY: '[12]0.CTY'!$D:$D
Name Data_Values: '[16]Single Measure Analysis'!$B$29:$M$30
Name DATA13: '[17]2.1Raw material_details'!#REF!
Name DATA13: '[17]2.1Raw material_details'!#REF!
Name DATA13: '[17]2.1Raw material_details'!#REF!
Name DATA14: '[17]2.1Raw material_details'!#REF!
Name DATA14: '[17]2.1Raw material_details'!#REF!
Name DATA14: '[17]2.1Raw material_details'!#REF!
Name DATA15: '[17]2.1Raw material_details'!#REF!
Name DATA15: '[17]2.1Raw material_details'!#REF!
Name DATA15: '[17]2.1Raw material_details'!#REF!
Name DATA16: '[17]2.1Raw material_details'!#REF!
Name DATA16: '[17]2.1Raw material_details'!#REF!

Sheet KQKD Day Dai
B3: MỤC TIÊU KẾT QUẢ KINH DOANH NĂM 2026 | P3: ĐVT: Triệu đồng
B4: STT | C4: Mục phí | D4: T1 | E4: T2 | F4: T3 | G4: T4 | H4: T5 | I4: T6 | J4: T7 | K4: T8 | L4: T9 | M4: T10 | N4: T11 | O4: T12 | P4: KH 2026
B5: 1 | C5: SẢN LƯỢNG BÁN (TẤN) | D5: =SUM(D6:D7) -> 0 | E5: =SUM(E6:E7) -> 0 | F5: =SUM(F6:F7) -> 0 | G5: =SUM(G6:G7) -> 142416 | H5: =SUM(H6:H7) -> 142416 | I5: =SUM(I6:I7) -> 142416 | J5: =SUM(J6:J7) -> 142416 | K5: =SUM(K6:K7) -> 142416 | ... O5: =SUM(O6:O7) -> 142416 | P5: =SUM(D5:O5) -> 1281744
B6: 1.1 | C6: Dây Đai PET | D6: ='4.Doanh thu'!F7 -> 0 | E6: ='4.Doanh thu'!G7 -> 0 | F6: ='4.Doanh thu'!H7 -> 0 | G6: ='4.Doanh thu'!I7 -> 142416 | H6: ='4.Doanh thu'!J7 -> 142416 | I6: ='4.Doanh thu'!K7 -> 142416 | J6: ='4.Doanh thu'!L7 -> 142416 | K6: ='4.Doanh thu'!M7 -> 142416 | ... O6: ='4.Doanh thu'!Q7 -> 142416 | P6: =SUM(D6:O6) -> 1281744
B7: 1.2 | P7: =SUM(D7:O7) -> 0
B8: 2 | C8: DOANH THU | D8: =SUM(D9:D11) -> 0 | E8: =SUM(E9:E11) -> 0 | F8: =SUM(F9:F11) -> 0 | G8: =SUM(G9:G11) -> 2848320000 | H8: =SUM(H9:H11) -> 2848320000 | I8: =SUM(I9:I11) -> 2848320000 | J8: =SUM(J9:J11) -> 2848320000 | K8: =SUM(K9:K11) -> 2848320000 | ... O8: =SUM(O9:O11) -> 2848320000 | P8: =SUM(D8:O8) -> 25634880000
B9: 2.1 | C9: Dây Đai PET | D9: ='4.Doanh thu'!F27 -> 0 | E9: ='4.Doanh thu'!G27 -> 0 | F9: ='4.Doanh thu'!H27 -> 0 | G9: ='4.Doanh thu'!I27 -> 2848320000 | H9: ='4.Doanh thu'!J27 -> 2848320000 | I9: ='4.Doanh thu'!K27 -> 2848320000 | J9: ='4.Doanh thu'!L27 -> 2848320000 | K9: ='4.Doanh thu'!M27 -> 2848320000 | ... O9: ='4.Doanh thu'!Q27 -> 2848320000 | P9: =SUM(D9:O9) -> 25634880000
B10: 2.2
B11: 2.4 | C11: Khác | P11: =SUM(D11:O11) -> 0
B12: 3 | C12: BIẾN PHÍ | D12: =D13+D21 -> 0 | E12: =E13+E21 -> 0 | F12: =F13+F21 -> 0 | G12: =G13+G21 -> 2.9881254e+09 | H12: =H13+H21 -> 2.9881254e+09 | I12: =I13+I21 -> 2.9881254e+09 | J12: =J13+J21 -> 2.9881254e+09 | K12: =K13+K21 -> 2.9881254e+09 | ... O12: =O13+O21 -> 2.9881254e+09 | P12: =SUM(D12:O12) -> 2.6893128e+10
B13: 3.1 | C13: BIẾN PHÍ SẢN XUẤT | D13: =D14+D18+D19+D20 -> 0 | E13: =E14+E18+E19+E20 -> 0 | F13: =F14+F18+F19+F20 -> 0 | G13: =G14+G18+G19+G20 -> 2.9299722e+09 | H13: =H14+H18+H19+H20 -> 2.9299722e+09 | I13: =I14+I18+I19+I20 -> 2.9299722e+09 | J13: =J14+J18+J19+J20 -> 2.9299722e+09 | K13: =K14+K18+K19+K20 -> 2.9299722e+09 | ... O13: =O14+O18+O19+O20 -> 2.9299722e+09 | P13: =SUM(D13:O13) -> 2.6369749e+10
B14: 3.1.1 | C14: Nguyên vật liệu chính (nhựa, gồm hao hụt) | D14: ='1.NVL'!H27 -> 0 | E14: ='1.NVL'!I27 -> 0 | F14: ='1.NVL'!J27 -> 0 | G14: ='1.NVL'!K27 -> 2220420000 | H14: ='1.NVL'!L27 -> 2220420000 | I14: ='1.NVL'!M27 -> 2220420000 | J14: ='1.NVL'!N27 -> 2220420000 | K14: ='1.NVL'!O27 -> 2220420000 | ... O14: ='1.NVL'!S27 -> 2220420000 | P14: =SUM(D14:O14) -> 19983780000
B15: 3.1.2 | C15: Trong đó: i/ Hao hụt CĐ phân loại chai | D15: =SUM('[27]KH DAY DAI'!E26,'[27]KH DAY DAI'!E33) -> 0 | E15: =SUM('[27]KH DAY DAI'!F26,'[27]KH DAY DAI'!F33) -> 0 | F15: =SUM('[27]KH DAY DAI'!G26,'[27]KH DAY DAI'!G33) -> 0 | G15: =SUM('[27]KH DAY DAI'!H26,'[27]KH DAY DAI'!H33) -> 0 | H15: =SUM('[27]KH DAY DAI'!I26,'[27]KH DAY DAI'!I33) -> 0 | I15: =SUM('[27]KH DAY DAI'!J26,'[27]KH DAY DAI'!J33) -> 0 | J15: =SUM('[27]KH DAY DAI'!K26,'[27]KH DAY DAI'!K33) -> 0 | K15: =SUM('[27]KH DAY DAI'!L26,'[27]KH DAY DAI'!L33) -> 0 | ... O15: =SUM('[27]KH DAY DAI'!P26,'[27]KH DAY DAI'!P33) -> 0 | P15: =SUM(D15:O15) -> 0
C16: ii/ Hao hụt CĐ băm vảy | P16: =SUM(D16:O16) -> 0
B17: 3.1.3 | C17: % chi phí nguyên liệu/doanh thu | D17: =IFERROR(D14/D8,) -> 0 | E17: =IFERROR(E14/E8,) -> 0 | F17: =IFERROR(F14/F8,) -> 0 | G17: =IFERROR(G14/G8,) -> 0.77955426 | H17: =IFERROR(H14/H8,) -> 0.77955426 | I17: =IFERROR(I14/I8,) -> 0.77955426 | J17: =IFERROR(J14/J8,) -> 0.77955426 | K17: =IFERROR(K14/K8,) -> 0.77955426 | ... P17: =IFERROR(P14/P8,) -> 0.77955426
B18: 3.1.4 | C18: Nguyên vật liệu phụ (Lõi giấy, Màng PE, | D18: =SUM(CPSX!K19:K25) -> 0 | E18: =SUM(CPSX!L19:L25) -> 0 | F18: =SUM(CPSX!M19:M25) -> 0 | G18: =SUM(CPSX!N19:N25) -> 2.9573615e+08 | H18: =SUM(CPSX!O19:O25) -> 2.9573615e+08 | I18: =SUM(CPSX!P19:P25) -> 2.9573615e+08 | J18: =SUM(CPSX!Q19:Q25) -> 2.9573615e+08 | K18: =SUM(CPSX!R19:R25) -> 2.9573615e+08 | ... O18: =SUM(CPSX!V19:V25) -> 2.9573615e+08 | P18: =SUM(D18:O18) -> 2.6616254e+09
B19: 3.1.5 | C19: Điện sản xuất | D19: =CPSX!K18 -> 0 | E19: =CPSX!L18 -> 0 | F19: =CPSX!M18 -> 0 | G19: =CPSX!N18 -> 365976000 | H19: =CPSX!O18 -> 365976000 | I19: =CPSX!P18 -> 365976000 | J19: =CPSX!Q18 -> 365976000 | K19: =CPSX!R18 -> 365976000 | ... O19: =CPSX!V18 -> 365976000 | P19: =SUM(D19:O19) -> 3293784000
B20: 3.1.6 | C20: Nhân công trực tiếp | D20: =SUM(CPSX!K6:K17) -> 0 | E20: =SUM(CPSX!L6:L17) -> 0 | F20: =SUM(CPSX!M6:M17) -> 0 | G20: =SUM(CPSX!N6:N17) -> 47840000 | H20: =SUM(CPSX!O6:O17) -> 47840000 | I20: =SUM(CPSX!P6:P17) -> 47840000 | J20: =SUM(CPSX!Q6:Q17) -> 47840000 | K20: =SUM(CPSX!R6:R17) -> 47840000 | ... O20: =SUM(CPSX!V6:V17) -> 47840000 | P20: =SUM(D20:O20) -> 4.3056e+08
B21: 3.2 | C21: BIẾN PHÍ BÁN HÀNG | D21: =CPBH!K5 -> 0 | E21: =CPBH!L5 -> 0 | F21: =CPBH!M5 -> 0 | G21: =CPBH!N5 -> 58153200 | H21: =CPBH!O5 -> 58153200 | I21: =CPBH!P5 -> 58153200 | J21: =CPBH!Q5 -> 58153200 | K21: =CPBH!R5 -> 58153200 | ... O21: =CPBH!V5 -> 58153200 | P21: =SUM(D21:O21) -> 523378800
C22: Chi phí vận chuyển | D22: =CPSX!K27 -> 0 | E22: =CPSX!L27 -> 0 | F22: =CPSX!M27 -> 0 | G22: =CPSX!N27 -> 0 | H22: =CPSX!O27 -> 0 | I22: =CPSX!P27 -> 0 | J22: =CPSX!Q27 -> 0 | K22: =CPSX!R27 -> 0 | ... O22: =CPSX!V27 -> 0 | P22: =SUM(D22:O22) -> 0
B23: 4 | C23: LÃI SAU BIẾN PHÍ | D23: =D8-D12 -> 0 | E23: =E8-E12 -> 0 | F23: =F8-F12 -> 0 | G23: =G8-G12 -> -1.3980535e+08 | H23: =H8-H12 -> -1.3980535e+08 | I23: =I8-I12 -> -1.3980535e+08 | J23: =J8-J12 -> -1.3980535e+08 | K23: =K8-K12 -> -1.3980535e+08 | ... O23: =O8-O12 -> -1.3980535e+08 | P23: =SUM(D23:O23) -> -1.2582482e+09
B24: 4.1 | C24: % lãi biến phí/doanh thu | D24: =IFERROR(D23/D8,) -> 0 | E24: =IFERROR(E23/E8,) -> 0 | F24: =IFERROR(F23/F8,) -> 0 | G24: =IFERROR(G23/G8,) -> -0.049083443 | H24: =IFERROR(H23/H8,) -> -0.049083443 | I24: =IFERROR(I23/I8,) -> -0.049083443 | J24: =IFERROR(J23/J8,) -> -0.049083443 | K24: =IFERROR(K23/K8,) -> -0.049083443 | ... P24: =IFERROR(P23/P8,) -> -0.049083443
B25: 5 | C25: CHI PHÍ SẢN XUẤT CHUNG | D25: =D26+D27+D28 -> 0 | E25: =E26+E27+E28 -> 0 | F25: =F26+F27+F28 -> 0 | G25: =G26+G27+G28 -> 80488500 | H25: =H26+H27+H28 -> 80488500 | I25: =I26+I27+I28 -> 80488500 | J25: =J26+J27+J28 -> 80488500 | K25: =K26+K27+K28 -> 80488500 | ... O25: =O26+O27+O28 -> 80488500 | P25: =SUM(D25:O25) -> 724396500
B26: 5.1 | C26: Lương gián tiếp Sản xuất | D26: =SUM(CPSX!K29:K40) -> 0 | E26: =SUM(CPSX!L29:L40) -> 0 | F26: =SUM(CPSX!M29:M40) -> 0 | G26: =SUM(CPSX!N29:N40) -> 80488500 | H26: =SUM(CPSX!O29:O40) -> 80488500 | I26: =SUM(CPSX!P29:P40) -> 80488500 | J26: =SUM(CPSX!Q29:Q40) -> 80488500 | K26: =SUM(CPSX!R29:R40) -> 80488500 | ... O26: =SUM(CPSX!V29:V40) -> 80488500 | P26: =SUM(D26:O26) -> 724396500
B27: 5.2 | C27: Chi phí thuê xưởng | P27: =SUM(D27:O27) -> 0
B28: 5.3 | C28: Chi phí sản xuất (Ngoài lương, BOM, thuê xưởng, khấu hao) | D28: =SUM('[27]KH DAY DAI'!E30) -> 0 | E28: =SUM('[27]KH DAY DAI'!F30) -> 0 | F28: =SUM('[27]KH DAY DAI'!G30) -> 0 | G28: =SUM('[27]KH DAY DAI'!H30) -> 0 | H28: =SUM('[27]KH DAY DAI'!I30) -> 0 | I28: =SUM('[27]KH DAY DAI'!J30) -> 0 | J28: =SUM('[27]KH DAY DAI'!K30) -> 0 | K28: =SUM('[27]KH DAY DAI'!L30) -> 0 | ... O28: =SUM('[27]KH DAY DAI'!P30) -> 0 | P28: =SUM(D28:O28) -> 0
B29: 6 | C29: CHI PHÍ KHẤU HAO, CCDC | D29: =CPSX!K56 -> 0 | E29: =CPSX!L56 -> 0 | F29: =CPSX!M56 -> 0 | G29: =CPSX!N56 -> 46507064 | H29: =CPSX!O56 -> 46507064 | I29: =CPSX!P56 -> 46507064 | J29: =CPSX!Q56 -> 46507064 | K29: =CPSX!R56 -> 46507064 | ... O29: =CPSX!V56 -> 46507064 | P29: =SUM(D29:O29) -> 4.1856358e+08
B30: 7 | C30: LỢI NHUẬN GỘP | D30: =D23-D25-D29 -> 0 | E30: =E23-E25-E29 -> 0 | F30: =F23-F25-F29 -> 0 | G30: =G23-G25-G29 -> -2.6680092e+08 | H30: =H23-H25-H29 -> -2.6680092e+08 | I30: =I23-I25-I29 -> -2.6680092e+08 | J30: =J23-J25-J29 -> -2.6680092e+08 | K30: =K23-K25-K29 -> -2.6680092e+08 | ... O30: =O23-O25-O29 -> -2.6680092e+08 | P30: =SUM(D30:O30) -> -2.4012082e+09
B31: 7.1 | C31: % lãi gộp/doanh thu | D31: =IFERROR(D30/D8,) -> 0 | E31: =IFERROR(E30/E8,) -> 0 | F31: =IFERROR(F30/F8,) -> 0 | G31: =IFERROR(G30/G8,) -> -0.093669572 | H31: =IFERROR(H30/H8,) -> -0.093669572 | I31: =IFERROR(I30/I8,) -> -0.093669572 | J31: =IFERROR(J30/J8,) -> -0.093669572 | K31: =IFERROR(K30/K8,) -> -0.093669572 | ... P31: =IFERROR(P30/P8,) -> -0.093669572
B32: 8 | C32: CHI PHÍ BÁN HÀNG & MKT & R&D | D32: =D34+D35+D36 -> 0 | E32: =E34+E35+E36 -> 0 | F32: =F34+F35+F36 -> 0 | G32: =G34+G35+G36 -> 854496000 | H32: =H34+H35+H36 -> 854496000 | I32: =I34+I35+I36 -> 854496000 | J32: =J34+J35+J36 -> 854496000 | K32: =K34+K35+K36 -> 854496000 | ... O32: =O34+O35+O36 -> 854496000 | P32: =SUM(D32:O32) -> 7690464000
B33: 8.1 | C33: % CPBH/doanh thu | D33: =IFERROR(D32/D$8,) -> 0 | E33: =IFERROR(E32/E$8,) -> 0 | F33: =IFERROR(F32/F$8,) -> 0 | G33: =IFERROR(G32/G$8,) -> 0.3 | H33: =IFERROR(H32/H$8,) -> 0.3 | I33: =IFERROR(I32/I$8,) -> 0.3 | J33: =IFERROR(J32/J$8,) -> 0.3 | K33: =IFERROR(K32/K$8,) -> 0.3 | ... P33: =IFERROR(P32/P$8,) -> 0.3
B34: 8.1 | C34: Lương | D34: =CPBH!K7 -> 0 | E34: =CPBH!L7 -> 0 | F34: =CPBH!M7 -> 0 | G34: =CPBH!N7 -> 284832000 | H34: =CPBH!O7 -> 284832000 | I34: =CPBH!P7 -> 284832000 | J34: =CPBH!Q7 -> 284832000 | K34: =CPBH!R7 -> 284832000 | ... O34: =CPBH!V7 -> 284832000 | P34: =SUM(D34:O34) -> 2563488000
B35: 8.2 | C35: Chi phí bán hàng (ngoài lương, khấu hao) | D35: =SUM(CPBH!K8:K10) -> 0 | E35: =SUM(CPBH!L8:L10) -> 0 | F35: =SUM(CPBH!M8:M10) -> 0 | G35: =SUM(CPBH!N8:N10) -> 569664000 | H35: =SUM(CPBH!O8:O10) -> 569664000 | I35: =SUM(CPBH!P8:P10) -> 569664000 | J35: =SUM(CPBH!Q8:Q10) -> 569664000 | K35: =SUM(CPBH!R8:R10) -> 569664000 | ... O35: =SUM(CPBH!V8:V10) -> 569664000 | P35: =SUM(D35:O35) -> 5126976000
B36: 8.3 | C36: Khấu hao tài sản | P36: =SUM(D36:O36) -> 0
B37: 9 | C37: CHI PHÍ QUẢN LÝ | D37: =D39+D40+D41 -> 0 | E37: =E39+E40+E41 -> 0 | F37: =F39+F40+F41 -> 0 | G37: =G39+G40+G41 -> 0 | H37: =H39+H40+H41 -> 0 | I37: =I39+I40+I41 -> 0 | J37: =J39+J40+J41 -> 0 | K37: =K39+K40+K41 -> 0 | ... O37: =O39+O40+O41 -> 0 | P37: =SUM(D37:O37) -> 0
B38: 9.1 | C38: % CPQL/doanh thu | D38: =IFERROR(D37/D$8,) -> 0 | E38: =IFERROR(E37/E$8,) -> 0 | F38: =IFERROR(F37/F$8,) -> 0 | G38: =IFERROR(G37/G$8,) -> 0 | H38: =IFERROR(H37/H$8,) -> 0 | I38: =IFERROR(I37/I$8,) -> 0 | J38: =IFERROR(J37/J$8,) -> 0 | K38: =IFERROR(K37/K$8,) -> 0 | ... P38: =IFERROR(P37/P$8,) -> 0
B39: 9.1 | C39: Lương | P39: =SUM(D39:O39) -> 0
B40: 9.2 | C40: Chi phí quản lý (ngoài lương, khấu hao) | P40: =SUM(D40:O40) -> 0
B41: 9.3 | C41: Khấu hao tài sản | P41: =SUM(D41:O41) -> 0
B42: 10 | C42: DOANH THU/CHI PHÍ KHÁC | P42: =SUM(D42:O42) -> 0
B43: 11 | C43: LỢI NHUẬN THUẦN TỪ HOẠT ĐỘNG KINH DOANH | D43: =D30-D32-D37+D42 -> 0 | E43: =E30-E32-E37+E42 -> 0 | F43: =F30-F32-F37+F42 -> 0 | G43: =G30-G32-G37+G42 -> -1.1212969e+09 | H43: =H30-H32-H37+H42 -> -1.1212969e+09 | I43: =I30-I32-I37+I42 -> -1.1212969e+09 | J43: =J30-J32-J37+J42 -> -1.1212969e+09 | K43: =K30-K32-K37+K42 -> -1.1212969e+09 | ... O43: =O30-O32-O37+O42 -> -1.1212969e+09 | P43: =SUM(D43:O43) -> -1.0091672e+10
B44: 12 | C44: DOANH THU TÀI CHÍNH | P44: =SUM(D44:O44) -> 0
B45: 13 | C45: CHI PHÍ TÀI CHÍNH | P45: =SUM(D45:O45) -> 0
B46: 13.1 | C46: Trong đó: chi phí lãi vay | P46: =SUM(D46:O46) -> 0
B47: 14 | C47: LỢI NHUẬN TRƯỚC THUẾ | D47: =D43+D44-D45 -> 0 | E47: =E43+E44-E45 -> 0 | F47: =F43+F44-F45 -> 0 | G47: =G43+G44-G45 -> -1.1212969e+09 | H47: =H43+H44-H45 -> -1.1212969e+09 | I47: =I43+I44-I45 -> -1.1212969e+09 | J47: =J43+J44-J45 -> -1.1212969e+09 | K47: =K43+K44-K45 -> -1.1212969e+09 | ... O47: =O43+O44-O45 -> -1.1212969e+09 | P47: =SUM(D47:O47) -> -1.0091672e+10
B48: 15 | C48: THUẾ TNDN | P48: =SUM(D48:O48) -> 0
B49: 16 | C49: LỢI NHUẬN SAU THUẾ | D49: =D47-D48 -> 0 | E49: =E47-E48 -> 0 | F49: =F47-F48 -> 0 | G49: =G47-G48 -> -1.1212969e+09 | H49: =H47-H48 -> -1.1212969e+09 | I49: =I47-I48 -> -1.1212969e+09 | J49: =J47-J48 -> -1.1212969e+09 | K49: =K47-K48 -> -1.1212969e+09 | ... O49: =O47-O48 -> -1.1212969e+09 | P49: =SUM(D49:O49) -> -1.0091672e+10
B50: 16.1 | C50: % LNST/doanh thu | D50: =IFERROR(D49/D8,) -> 0 | E50: =IFERROR(E49/E8,) -> 0 | F50: =IFERROR(F49/F8,) -> 0 | G50: =IFERROR(G49/G8,) -> -0.39366957 | H50: =IFERROR(H49/H8,) -> -0.39366957 | I50: =IFERROR(I49/I8,) -> -0.39366957 | J50: =IFERROR(J49/J8,) -> -0.39366957 | K50: =IFERROR(K49/K8,) -> -0.39366957 | ... P50: =IFERROR(P49/P8,) -> -0.39366957
B51: 17 | C51: Khấu hao tài sản | D51: =D29 -> 0 | E51: =E29 -> 0 | F51: =F29 -> 0 | G51: =G29 -> 46507064 | H51: =H29 -> 46507064 | I51: =I29 -> 46507064 | J51: =J29 -> 46507064 | K51: =K29 -> 46507064 | ... O51: =O29 -> 46507064 | P51: =SUM(D51:O51) -> 4.1856358e+08
B52: 18 | C52: LỢI NHUẬN KHÔNG BAO GỒM KHẤU HAO, LÃI VAY | D52: =D49+D51 -> 0 | E52: =E49+E51 -> 0 | F52: =F49+F51 -> 0 | G52: =G49+G51 -> -1.0747899e+09 | H52: =H49+H51 -> -1.0747899e+09 | I52: =I49+I51 -> -1.0747899e+09 | J52: =J49+J51 -> -1.0747899e+09 | K52: =K49+K51 -> -1.0747899e+09 | ... O52: =O49+O51 -> -1.0747899e+09 | P52: =SUM(D52:O52) -> -9.6731087e+09
B53: 18.1 | C53: % LN không gồm khấu hao/doanh thu | D53: =IFERROR(D52/D8,) -> 0 | E53: =IFERROR(E52/E8,) -> 0 | F53: =IFERROR(F52/F8,) -> 0 | G53: =IFERROR(G52/G8,) -> -0.37734168 | H53: =IFERROR(H52/H8,) -> -0.37734168 | I53: =IFERROR(I52/I8,) -> -0.37734168 | J53: =IFERROR(J52/J8,) -> -0.37734168 | K53: =IFERROR(K52/K8,) -> -0.37734168 | ... P53: =IFERROR(P52/P8,) -> -0.37734168

Sheet Cong suat
B3: CÔNG SUẤT
B4: I - CÔNG SUẤT CHUYỀN SẢN XUẤT DÂY ĐAI
B5: STT | C5: Công đoạn sản xuất | D5: Cấp liệu | J5: Công suất thành phẩm cả chuyền | K5: Công suất thành phẩm cả chuyền
B6: 1 | C6: Năng suất THIẾT KẾ (Kg NVL đầu vào / giờ) | D6: 300 | J6: =D6 -> 300 | K6: =D6*(100%-$D$15) -> 258
B7: 2 | C7: Năng suất ĐỊNH MỨC (Kg NVL đầu vào / giờ) | D7: 300
B8: 3 | C8: Định mức nhân công (Số NV / Ca12) | D8: 3 | J8: =SUM(C8:I8) -> 3 | K8: =SUM(D8:J8) -> 6
C9: Định mức kỹ thuật vận hành (Số NV / Ca12) | D9: 1.5 | J9: =SUM(C9:I9) -> 1.5 | K9: =SUM(D9:J9) -> 3
C10: Diễn giải
B12: STT | C12: Chỉ tiêu định mức | D12: ĐVT | E12: ĐM 1 giờ | F12: ĐM 1 Ca8 | G12: ĐM 1 Ca12 | H12: ĐM 2 Ca8 | I12: ĐM 2 Ca12
B13: 1 | C13: Tổng nhân sự: | D13: Người | E13: =K8 -> 6 | F13: =$E13 -> 6 | G13: 5 | H13: 9 | I13: 9
B14: 2 | C14: Định mức NVL đầu vào: | D14: kg/giờ | E14: =D7 -> 300 | F14: =$E14*8 -> 2400 | G14: =$F14*1.5 -> 3600 | H14: =$F14*2 -> 4800 | I14: =$G14*2 -> 7200
B15: 3 | C15: Hao hụt: | D15: ='2.Hao hut'!$E$11 -> 0.14 | E15: =E14*$D$15 -> 42 | F15: =$E15*8 -> 336 | G15: =$E15*12 -> 504 | H15: =$F15*2 -> 672 | I15: =$G15*2 -> 1008
B16: 4 | C16: Định mức thành phẩm: | D16: kg/giờ | E16: =E14-E15 -> 258 | F16: =$E16*8 -> 2064 | G16: =$F16*1.5 -> 3096 | H16: =$F16*2 -> 4128 | I16: =$G16*2 -> 6192
B17: 5 | C17: Định mức thành phẩm/người: | D17: kg/giờ/người | E17: =E16/K8 -> 43 | F17: =$E17*8 -> 344 | G17: =$F17*1.5 -> 516 | H17: =$F17*2 -> 688 | I17: =$G17*2 -> 1032
B19: VI - CÔNG SUẤT MÁY VÀ NĂNG SUẤT LAO ĐỘNG MỤC TIÊU
B20: 1 | C20: CHUYỀN DÂY ĐAI | E20: Định mức | F20: T1 | G20: T2 | H20: T3 | I20: T4 | J20: T5 | K20: T6 | L20: T7 | M20: T8 | N20: T9 | O20: T10 | P20: T11 | Q20: T12 | R20: Mục tiêu 2026
B21: a | C21: Số nhân sự/ chuyền/ ca | D21: Người | E21: =G13 -> 5 | I21: =$E21 -> 5 | J21: =$E21 -> 5 | K21: =$E21 -> 5 | L21: =$E21 -> 5 | M21: =$E21 -> 5 | N21: =$E21 -> 5 | O21: =$E21 -> 5 | P21: =$E21 -> 5 | Q21: =$E21 -> 5
B22: b | C22: Công suất/ chuyền | D22: kg/giờ | E22: =G14 -> 3600 | I22: =$E22 -> 3600 | J22: =$E22 -> 3600 | K22: =$E22 -> 3600 | L22: =$E22 -> 3600 | M22: =$E22 -> 3600 | N22: =$E22 -> 3600 | O22: =$E22 -> 3600 | P22: =$E22 -> 3600 | Q22: =$E22 -> 3600
B23: c | C23: Năng suất lao động | D23: kg/giờ/người | E23: =E22/E21 -> 720 | I23: =$E23 -> 720 | J23: =$E23 -> 720 | K23: =$E23 -> 720 | L23: =$E23 -> 720 | M23: =$E23 -> 720 | N23: =$E23 -> 720 | O23: =$E23 -> 720 | P23: =$E23 -> 720 | Q23: =$E23 -> 720
B27: VII - TỔNG CÔNG SUẤT MÁY PET và NĂNG SUẤT LAO ĐỘNG
B28: i | C28: Tổng công suất PET/giờ | D28: kg/giờ | E28: Định mức | F28: T1 | G28: T2 | H28: T3 | I28: T4 | J28: T5 | K28: T6 | L28: T7 | M28: T8 | N28: T9 | O28: T10 | P28: T11 | Q28: T12 | R28: Mục tiêu 2026
B29: 1 | C29: Công suất máy - Tính trên NVL đầu vào | D29: Tấn/giờ | E29: =E14 -> 300 | I29: =$E29 -> 300 | J29: =$E29 -> 300 | K29: =$E29 -> 300 | L29: =$E29 -> 300 | M29: =$E29 -> 300 | N29: =$E29 -> 300 | O29: =$E29 -> 300 | P29: =$E29 -> 300 | Q29: =$E29 -> 300 | R29: =AVERAGE(F29:Q29) -> 300
B30: 2 | C30: Công suất máy - Tính trên Thành phẩm SX | D30: Tấn/giờ | E30: =E16 -> 258 | I30: =$E30 -> 258 | J30: =$E30 -> 258 | K30: =$E30 -> 258 | L30: =$E30 -> 258 | M30: =$E30 -> 258 | N30: =$E30 -> 258 | O30: =$E30 -> 258 | P30: =$E30 -> 258 | Q30: =$E30 -> 258 | R30: =AVERAGE(F30:Q30) -> 258
B31: ii | C31: Tổng công suất PET/tháng (8hx2cax30 ngày) | D31: kg/tháng | E31: Định mức | J31: T5 | K31: T6 | L31: T7 | M31: T8 | N31: T9 | O31: T10 | P31: T11 | Q31: T12
B32: 1 | C32: Công suất máy - Tính trên NVL đầu vào | D32: Tấn/tháng | E32: =G14*2*30 -> 216000 | F32: =F29*7*2*30 -> 0 | G32: =G29*7*2*30 -> 0 | H32: =H29*7*2*30 -> 0 | I32: =$E32 -> 216000 | J32: =$E32 -> 216000 | K32: =$E32 -> 216000 | L32: =$E32 -> 216000 | M32: =$E32 -> 216000 | N32: =$E32 -> 216000 | O32: =$E32 -> 216000 | P32: =$E32 -> 216000 | Q32: =$E32 -> 216000 | R32: =AVERAGE(F32:Q32) -> 162000
B33: 2 | C33: Công suất máy - Tính trên Thành phẩm SX | D33: Tấn/tháng | E33: =G16*2*30 -> 185760 | F33: =F30*7*2*30 -> 0 | G33: =G30*7*2*30 -> 0 | H33: =H30*7*2*30 -> 0 | I33: =$E33 -> 185760 | J33: =$E33 -> 185760 | K33: =$E33 -> 185760 | L33: =$E33 -> 185760 | M33: =$E33 -> 185760 | N33: =$E33 -> 185760 | O33: =$E33 -> 185760 | P33: =$E33 -> 185760 | Q33: =$E33 -> 185760 | R33: =AVERAGE(F33:Q33) -> 139320
B34: iii | C34: Năng suất lao động (CNTT) | E34: Định mức | J34: T5 | K34: T6 | L34: T7 | M34: T8 | N34: T9 | O34: T10 | P34: T11 | Q34: T12
B35: 1 | C35: Năng suất lao động - Tấn/người/ngày | D35: Tấn/người/ngày | E35: =E36/30 -> 619.2 | I35: =I36/30 -> 619.2 | J35: =J36/30 -> 619.2 | K35: =K36/30 -> 619.2 | L35: =L36/30 -> 619.2 | M35: =M36/30 -> 619.2 | N35: =N36/30 -> 619.2 | O35: =O36/30 -> 619.2 | P35: =P36/30 -> 619.2 | Q35: =Q36/30 -> 619.2 | R35: =AVERAGE(F35:Q35) -> 619.2
B36: 2 | C36: Năng suất lao động - Tấn/người/tháng | D36: Tấn/người/tháng | E36: =E33/E21/2 -> 18576 | I36: =I33/I21/2 -> 18576 | J36: =J33/J21/2 -> 18576 | K36: =K33/K21/2 -> 18576 | L36: =L33/L21/2 -> 18576 | M36: =M33/M21/2 -> 18576 | N36: =N33/N21/2 -> 18576 | O36: =O33/O21/2 -> 18576 | P36: =P33/P21/2 -> 18576 | Q36: =Q33/Q21/2 -> 18576 | R36: =AVERAGE(F36:Q36) -> 18576

Sheet Dinh muc
B3: ĐỊNH MỨC CHI PHÍ
B4: I - ĐỊNH MỨC SẢN XUẤT DÂY ĐAI | G4: =SUM(G6:G22) -> 6206.3755
B5: STT | C5: Mục phí | D5: ĐVT | E5: Định mức | F5: Đơn giá | G5: Chi phí/1kg thành phẩm | H5: Diễn giải
B6: 1 | C6: Nhân sự trực tiếp (CNSX) | I6: =SUM(G8:G9) -> 335.91731
B7: a | C7: LĐ định biên | D7: Giờ công/ca 12
B8: b | C8: LĐ thời vụ | D8: Giờ công/ca 12 | E8: 2 | F8: 470000 | G8: =E8*F8/'Cong suat'!$G$16 -> 303.61757
B9: c | C9: Tiền ăn giữa Ca | D9: Đồng/người/ngày công | E9: =E8 -> 2 | F9: 50000 | G9: =E9*F9/'Cong suat'!$G$16 -> 32.299742
B10: 2 | C10: Nhân sự gián tiếp sản xuất | I10: =SUM(G11:G13) -> 565.16473
B11: a | C11: LĐ định biên - Kỹ Thuật | D11: Giờ công/ca 12 | E11: 1.5 | F11: 712700 | G11: =E11*F11/'Cong suat'!$G$16 -> 345.30039 | H11: Tăng thêm 1 nhân sự: để vệ sinh lõi lọc so với ban đầu
B12: b | C12: LĐ định biên - QC | D12: Giờ công/ca 12 | E12: 1 | F12: 555700 | G12: =E12*F12/'Cong suat'!$G$16 -> 179.48966
B13: c | C13: Tiền ăn giữa Ca | D13: Đồng/người/ngày công | E13: 2.5 | F13: 50000 | G13: =E13*F13/'Cong suat'!$G$16 -> 40.374677
B14: 3 | C14: Điện sản xuất | D14: Kw/1chuyền/1giờ hoạt động | E14: =500*60% -> 300 | F14: =ROUND(2100*1.05,-1) -> 2210 | G14: =E14*F14/'Cong suat'!$E$16 -> 2569.7674 | H14: Hiệu suất: 60% | K14: CP SX
B15: 4 | C15: Nước đầu vào | D15: m3/h | E15: 2 | F15: 11500 | G15: =E15*F15/'Cong suat'!$E$16 -> 89.147287 | I15: =G15+G16 -> 162.64806 | K15: =SUM(G17,G19,G20,G21) -> 1997.8779
B16: 5 | C16: Nước đầu ra | D16: m3/h | E16: =E15*80% -> 1.6 | F16: 11852 | G16: =E16*F16/'Cong suat'!$E$16 -> 73.500775
C17: VTTH: Ron | D17: Cái | E17: 2 | F17: =2*26500 -> 53000 | G17: =(E17*F17)/(1600*86%) -> 77.034884 | H17: 4h thay 1 bộ
B18: 6 | C18: Cuộn màng PE/PVC (3kg) | E18: 1 | F18: 250000 | G18: =(E18*F18)/1500 -> 166.66667 | H18: 1 cuộn SX 2.5 tấn
B19: 7 | C19: Lõi giấy Æ406 | E19: 1 | F19: 20000 | G19: =E19*F19/20 -> 1000 | H19: 1 Cuộn sử dụng 1 lõi
B20: 8 | C20: Pallet rHD D4-0986 DTR | D20: Cái | E20: 1 | F20: 539000 | G20: =E20*F20/(40*20) -> 673.75 | H20: 1 pallet chứa 40 cuộn
B21: 9 | C21: Dầu xe nâng | D21: Lít/giờ hoạt động | E21: =2.5*85% -> 2.125 | F21: 30000 | G21: =E21*F21/'Cong suat'!$E$16 -> 247.09302
B22: 10 | C22: Chi phí vận chuyển | D22: Chuyến/9 tấn | E22: 1 | F22: 4900000 | G22: =F22/12000 -> 408.33333 | H22: Cơ sở tính: tham chiếu CP chở chai tại trạm
B23: 11 | C23: Chi phí chiết khấu bán hàng: 10% doanh thu
B24: 13 | C24: Chi phí hoa hồng bán hàng 5% doanh thu
B25: 14 | C25: Cp đội ngũ sale bán hàng: 10% Doanh thu | H25: Lương KD, adm, nv giao hàng
B26: 15 | C26: Cp Maketing: 5% doanh thu | H26: Bộ nhận diện thương hiệu, tem nhãn, sale kit, TDS, dây mẫu
H28: Ngày …
C29: Duyệt | D29: Xem xét | E29: Xem xét | G29: Xem xét | H29: Người lập
C30: GĐĐH DTR | D30: GĐTC DTR | E30: GĐ các trạm | G30: Trưởng Trạm | H30: Kế toán trưởng

Sheet CPSX
B3: I - CHI PHÍ SẢN XUẤT PET | W3: ĐVT: Triệu đồng
B4: STT | C4: Dự phòng | D4: Mã tài khoản (Mã Chi phí_L4) | E4: Tên tài khoản (Cost elements 2) | F4: Chi Phí_L5 (Cost Group 2) | G4: Chi tiết | H4: Phòng ban | I4: Tham chiếu | J4: % CP/DT 2026 | K4: T1 | L4: T2 | M4: T3 | N4: T4 | O4: T5 | P4: T6 | Q4: T7 | R4: T8 | S4: T9 | T4: T10 | U4: T11 | V4: T12 | W4: KH 2026
B5: 1.1 | E5: BIẾN PHÍ | J5: =SUM(J6:J27) -> 0 | K5: =SUM(K6:K27) -> 0 | L5: =SUM(L6:L27) -> 0 | M5: =SUM(M6:M27) -> 0 | N5: =SUM(N6:N27) -> 7.4474215e+08 | O5: =SUM(O6:O27) -> 7.4474215e+08 | P5: =SUM(P6:P27) -> 7.4474215e+08 | Q5: =SUM(Q6:Q27) -> 7.4474215e+08 | ... W5: =SUM(W6:W27) -> 6.7026794e+09
B6: 1 | D6: 6220002601 | E6: Chi phí lương chính - Trực tiếp | F6: Salary and Wages - Direct | G6: Chi phí lương chính - Trực tiếp | H6: Phòng Hành chánh nhân sự | I6: LUONG | K6: ='Dinh muc'!$G$8*'3.Thanh pham'!F$10 -> 0 | L6: ='Dinh muc'!$G$8*'3.Thanh pham'!G$10 -> 0 | M6: ='Dinh muc'!$G$8*'3.Thanh pham'!H$10 -> 0 | N6: ='Dinh muc'!$G$8*'3.Thanh pham'!I$10 -> 43240000 | O6: ='Dinh muc'!$G$8*'3.Thanh pham'!J$10 -> 43240000 | P6: ='Dinh muc'!$G$8*'3.Thanh pham'!K$10 -> 43240000 | Q6: ='Dinh muc'!$G$8*'3.Thanh pham'!L$10 -> 43240000 | R6: ='Dinh muc'!$G$8*'3.Thanh pham'!M$10 -> 43240000 | ... V6: ='Dinh muc'!$G$8*'3.Thanh pham'!Q$10 -> 43240000 | W6: =SUM(K6:V6) -> 3.8916e+08
B7: 2 | D7: 6220002602 | E7: Chi phí lương T13, phép năm - Trực tiếp | F7: Salary and Wages - Direct | G7: Chi phí lương T13, phép năm - Trực tiếp | H7: Phòng Hành chánh nhân sự | I7: LUONG | W7: =SUM(K7:V7) -> 0
B8: 3 | D8: 6220002802 | E8: Chi phí khen thưởng - Trực tiếp | F8: Employee Welfare | G8: Chi phí khen thưởng - Trực tiếp | H8: Phòng Hành chánh nhân sự | I8: LUONG | W8: =SUM(K8:V8) -> 0
B9: 4 | D9: 6220002806 | E9: Thưởng danh hiệu - Trực tiếp | F9: Salary and Wages - Direct | G9: Thưởng danh hiệu - Trực tiếp | H9: Phòng Hành chánh nhân sự | I9: LUONG | W9: =SUM(K9:V9) -> 0
B10: 5 | D10: 6220007202 | E10: Chi phí khen thưởng, bồi dưỡng khác | F10: Employee Welfare | G10: Chi phí khen thưởng, bồi dưỡng khác | H10: Phòng Hành chánh nhân sự | I10: LUONG | W10: =SUM(K10:V10) -> 0
B11: 6 | D11: 6220003201 | E11: Tiền ăn giữa ca - Trực tiếp | F11: Employee Welfare | G11: Tiền ăn giữa ca - Trực tiếp | H11: Phòng Hành chánh nhân sự | I11: LUONG | K11: ='Dinh muc'!$G$9*'3.Thanh pham'!F$10 -> 0 | L11: ='Dinh muc'!$G$9*'3.Thanh pham'!G$10 -> 0 | M11: ='Dinh muc'!$G$9*'3.Thanh pham'!H$10 -> 0 | N11: ='Dinh muc'!$G$9*'3.Thanh pham'!I$10 -> 4600000 | O11: ='Dinh muc'!$G$9*'3.Thanh pham'!J$10 -> 4600000 | P11: ='Dinh muc'!$G$9*'3.Thanh pham'!K$10 -> 4600000 | Q11: ='Dinh muc'!$G$9*'3.Thanh pham'!L$10 -> 4600000 | R11: ='Dinh muc'!$G$9*'3.Thanh pham'!M$10 -> 4600000 | ... V11: ='Dinh muc'!$G$9*'3.Thanh pham'!Q$10 -> 4600000 | W11: =SUM(K11:V11) -> 41400000
B12: 7 | D12: 6220002603 | E12: Phụ cấp ca đêm - Trực tiếp | F12: Salary and Wages - Direct | G12: Phụ cấp ca đêm - Trực tiếp | H12: Phòng Hành chánh nhân sự | I12: LUONG | W12: =SUM(K12:V12) -> 0
B13: 8 | D13: 6220003401 | E13: BHXH, BHYT, KPCĐ, BHTN - Trực tiếp | F13: Employee Welfare | G13: BHXH, BHYT, KPCĐ, BHTN - Trực tiếp | H13: Phòng Hành chánh nhân sự | I13: LUONG | W13: =SUM(K13:V13) -> 0
B14: 9 | D14: 6220002701 | E14: Chi phí lương ngoài giờ - Trực tiếp | F14: Salary and Wages - Direct | G14: Chi phí lương ngoài giờ - Trực tiếp | H14: Phòng Hành chánh nhân sự | I14: LUONG | W14: =SUM(K14:V14) -> 0
B15: 10 | D15: 6220002901 | E15: Chi phí trợ cấp thôi việc - Trực tiếp | F15: Employee Benefits Expenses | G15: Chi phí trợ cấp thôi việc - Trực tiếp | H15: Phòng Hành chánh nhân sự | I15: LUONG | W15: =SUM(K15:V15) -> 0
B16: 11 | D16: 6220003001 | E16: Chi phí đồng phục | F16: Employee Welfare | G16: Chi phí đồng phục | H16: Phòng Hành chánh nhân sự | I16: Phan bo | W16: =SUM(K16:V16) -> 0
B17: 12 | E17: Chi phí y tế, BH sức khỏe | F17: Employee Welfare | G17: Chi Phí Y Tế, BH Sức Khỏe, BH 24/24 | H17: Phòng Hành chánh nhân sự | I17: Phan bo | W17: =SUM(K17:V17) -> 0
B18: 13 | D18: 6275001801 | E18: Chi phí điện sản xuất | F18: Direct Cost of Goods sold | G18: Chi phí điện sản xuất | H18: Phòng Kỹ thuật | I18: Dinh muc | K18: ='Dinh muc'!$G$14*'3.Thanh pham'!F$10 -> 0 | L18: ='Dinh muc'!$G$14*'3.Thanh pham'!G$10 -> 0 | M18: ='Dinh muc'!$G$14*'3.Thanh pham'!H$10 -> 0 | N18: ='Dinh muc'!$G$14*'3.Thanh pham'!I$10 -> 365976000 | O18: ='Dinh muc'!$G$14*'3.Thanh pham'!J$10 -> 365976000 | P18: ='Dinh muc'!$G$14*'3.Thanh pham'!K$10 -> 365976000 | Q18: ='Dinh muc'!$G$14*'3.Thanh pham'!L$10 -> 365976000 | R18: ='Dinh muc'!$G$14*'3.Thanh pham'!M$10 -> 365976000 | ... V18: ='Dinh muc'!$G$14*'3.Thanh pham'!Q$10 -> 365976000 | W18: =SUM(K18:V18) -> 3293784000
B19: 14 | D19: 6272000100 | E19: Chi phí vật liệu phục vụ SX | F19: Operating Supplies | H19: Phòng Kỹ thuật | I19: Dinh muc | W19: =SUM(K19:V19) -> 0
B20: 15 | D20: 6272000100 | E20: Chi phí vật liệu phục vụ SX | F20: Operating Supplies | G20: Lõi lọc - Màng … | H20: Phòng Sản xuất | I20: Dinh muc | W20: =SUM(K20:V20) -> 0 | X20: Trường hợp sản xuất 2 công đoạn: Phân loại chai và băm vảy thì chỉ tính sản lượng chai dùng dây đai
B21: 16 | D21: 6272000100 | E21: Chi phí vật liệu phục vụ SX | F21: Operating Supplies | G21: Cuộn Màng PE | H21: Phòng Sản xuất | I21: Dinh muc | K21: ='Dinh muc'!$G$18*'3.Thanh pham'!F$10 -> 0 | L21: ='Dinh muc'!$G$18*'3.Thanh pham'!G$10 -> 0 | M21: ='Dinh muc'!$G$18*'3.Thanh pham'!H$10 -> 0 | N21: ='Dinh muc'!$G$18*'3.Thanh pham'!I$10 -> 23736000 | O21: ='Dinh muc'!$G$18*'3.Thanh pham'!J$10 -> 23736000 | P21: ='Dinh muc'!$G$18*'3.Thanh pham'!K$10 -> 23736000 | Q21: ='Dinh muc'!$G$18*'3.Thanh pham'!L$10 -> 23736000 | R21: ='Dinh muc'!$G$18*'3.Thanh pham'!M$10 -> 23736000 | ... V21: ='Dinh muc'!$G$18*'3.Thanh pham'!Q$10 -> 23736000 | W21: =SUM(K21:V21) -> 213624000
B22: 17 | D22: 6272000100 | E22: Chi phí vật liệu phục vụ SX | F22: Operating Supplies | G22: Lõi giấy | H22: Phòng Sản xuất | I22: Dinh muc | K22: ='Dinh muc'!$G$19*'3.Thanh pham'!F$10 -> 0 | L22: ='Dinh muc'!$G$19*'3.Thanh pham'!G$10 -> 0 | M22: ='Dinh muc'!$G$19*'3.Thanh pham'!H$10 -> 0 | N22: ='Dinh muc'!$G$19*'3.Thanh pham'!I$10 -> 142416000 | O22: ='Dinh muc'!$G$19*'3.Thanh pham'!J$10 -> 142416000 | P22: ='Dinh muc'!$G$19*'3.Thanh pham'!K$10 -> 142416000 | Q22: ='Dinh muc'!$G$19*'3.Thanh pham'!L$10 -> 142416000 | R22: ='Dinh muc'!$G$19*'3.Thanh pham'!M$10 -> 142416000 | ... V22: ='Dinh muc'!$G$19*'3.Thanh pham'!Q$10 -> 142416000 | W22: =SUM(K22:V22) -> 1281744000
B23: 18 | D23: 6272000100 | E23: Chi phí vật liệu phục vụ SX | F23: Operating Supplies | G23: Pallet rHD D4-0986 DTR | H23: Phòng Sản xuất | I23: Dinh muc | K23: ='Dinh muc'!$G$20*'3.Thanh pham'!F$10 -> 0 | L23: ='Dinh muc'!$G$20*'3.Thanh pham'!G$10 -> 0 | M23: ='Dinh muc'!$G$20*'3.Thanh pham'!H$10 -> 0 | N23: ='Dinh muc'!$G$20*'3.Thanh pham'!I$10 -> 95952780 | O23: ='Dinh muc'!$G$20*'3.Thanh pham'!J$10 -> 95952780 | P23: ='Dinh muc'!$G$20*'3.Thanh pham'!K$10 -> 95952780 | Q23: ='Dinh muc'!$G$20*'3.Thanh pham'!L$10 -> 95952780 | R23: ='Dinh muc'!$G$20*'3.Thanh pham'!M$10 -> 95952780 | ... V23: ='Dinh muc'!$G$20*'3.Thanh pham'!Q$10 -> 95952780 | W23: =SUM(K23:V23) -> 863575020
B24: 19 | D24: 6272002101 | E24: Chi phí vật tư phân xưởng | F24: Operating Supplies | G24: Chi phí vật tư phân xưởng (ron) | K24: =SUM('Dinh muc'!$G$17:$G$20)*'3.Thanh pham'!F10 -> 0 | L24: =SUM('Dinh muc'!$G$17:$G$20)*'3.Thanh pham'!G10 -> 0 | M24: =SUM('Dinh muc'!$G$17:$G$20)*'3.Thanh pham'!H10 -> 0 | N24: =ROUND('Dinh muc'!$G$16*'3.Thanh pham'!I$10,0) -> 10467686 | O24: =ROUND('Dinh muc'!$G$16*'3.Thanh pham'!J$10,0) -> 10467686 | P24: =ROUND('Dinh muc'!$G$16*'3.Thanh pham'!K$10,0) -> 10467686 | Q24: =ROUND('Dinh muc'!$G$16*'3.Thanh pham'!L$10,0) -> 10467686 | R24: =ROUND('Dinh muc'!$G$16*'3.Thanh pham'!M$10,0) -> 10467686 | S24: =ROUND('Dinh muc'!$G$16*'3.Thanh pham'!N$10,0) -> 10467686 | T24: =ROUND('Dinh muc'!$G$16*'3.Thanh pham'!O$10,0) -> 10467686 | U24: =ROUND('Dinh muc'!$G$16*'3.Thanh pham'!P$10,0) -> 10467686 | V24: =ROUND('Dinh muc'!$G$16*'3.Thanh pham'!Q$10,0) -> 10467686 | W24: =SUM(K24:V24) -> 94209174
B25: 19 | D25: 6272002101 | E25: Chi phí vật tư phân xưởng | F25: Operating Supplies | G25: Cp nước | K25: =SUM('Dinh muc'!$G$15:$G$16)*'3.Thanh pham'!F$10 -> 0 | L25: =SUM('Dinh muc'!$G$15:$G$16)*'3.Thanh pham'!G$10 -> 0 | M25: =SUM('Dinh muc'!$G$15:$G$16)*'3.Thanh pham'!H$10 -> 0 | N25: =SUM('Dinh muc'!$G$15:$G$16)*'3.Thanh pham'!I$10 -> 23163686 | O25: =SUM('Dinh muc'!$G$15:$G$16)*'3.Thanh pham'!J$10 -> 23163686 | P25: =SUM('Dinh muc'!$G$15:$G$16)*'3.Thanh pham'!K$10 -> 23163686 | Q25: =SUM('Dinh muc'!$G$15:$G$16)*'3.Thanh pham'!L$10 -> 23163686 | R25: =SUM('Dinh muc'!$G$15:$G$16)*'3.Thanh pham'!M$10 -> 23163686 | ... V25: =SUM('Dinh muc'!$G$15:$G$16)*'3.Thanh pham'!Q$10 -> 23163686 | W25: =SUM(K25:V25) -> 2.0847318e+08
B26: 20 | D26: 6272003502 | E26: Chi phí xăng dầu xe du lịch, xe gắn máy, xe nâng | F26: Energy Expenses | G26: Xăng dầu xe nâng | H26: Phòng Kho vận | I26: Dinh muc | K26: ='Dinh muc'!$G$21*'3.Thanh pham'!F$10 -> 0 | L26: ='Dinh muc'!$G$21*'3.Thanh pham'!G$10 -> 0 | M26: ='Dinh muc'!$G$21*'3.Thanh pham'!H$10 -> 0 | N26: ='Dinh muc'!$G$21*'3.Thanh pham'!I$10 -> 35190000 | O26: ='Dinh muc'!$G$21*'3.Thanh pham'!J$10 -> 35190000 | P26: ='Dinh muc'!$G$21*'3.Thanh pham'!K$10 -> 35190000 | Q26: ='Dinh muc'!$G$21*'3.Thanh pham'!L$10 -> 35190000 | R26: ='Dinh muc'!$G$21*'3.Thanh pham'!M$10 -> 35190000 | ... V26: ='Dinh muc'!$G$21*'3.Thanh pham'!Q$10 -> 35190000 | W26: =SUM(K26:V26) -> 316710000
B28: II | E28: ĐỊNH PHÍ | J28: =SUM(J29:J57) -> 0 | K28: =SUM(K29:K57) -> 0 | L28: =SUM(L29:L57) -> 0 | M28: =SUM(M29:M57) -> 0 | N28: =SUM(N29:N57) -> 1.3030806e+08 | O28: =SUM(O29:O57) -> 1.3030806e+08 | P28: =SUM(P29:P57) -> 1.3030806e+08 | Q28: =SUM(Q29:Q57) -> 1.3030806e+08 | ... W28: =SUM(W29:W57) -> 1.1727726e+09
B29: 1 | D29: 6271002604 | E29: Chi phí lương chính - Gián tiếp | F29: Salary and Wages - Support | G29: Chi phí lương chính - Gián tiếp | H29: Phòng Hành chánh nhân sự | I29: LUONG | K29: =SUM('Dinh muc'!$G$11:$G$12)*'3.Thanh pham'!F$10 -> 0 | L29: =SUM('Dinh muc'!$G$11:$G$12)*'3.Thanh pham'!G$10 -> 0 | M29: =SUM('Dinh muc'!$G$11:$G$12)*'3.Thanh pham'!H$10 -> 0 | N29: =SUM('Dinh muc'!$G$11:$G$12)*'3.Thanh pham'!I$10 -> 74738500 | O29: =SUM('Dinh muc'!$G$11:$G$12)*'3.Thanh pham'!J$10 -> 74738500 | P29: =SUM('Dinh muc'!$G$11:$G$12)*'3.Thanh pham'!K$10 -> 74738500 | Q29: =SUM('Dinh muc'!$G$11:$G$12)*'3.Thanh pham'!L$10 -> 74738500 | R29: =SUM('Dinh muc'!$G$11:$G$12)*'3.Thanh pham'!M$10 -> 74738500 | ... V29: =SUM('Dinh muc'!$G$11:$G$12)*'3.Thanh pham'!Q$10 -> 74738500 | W29: =SUM(K29:V29) -> 672646500
B30: 2 | D30: 6271002605 | E30: Chi phí lương T13, phép năm - Gián tiếp | F30: Salary and Wages - Support | G30: Chi phí lương T13, phép năm - Gián tiếp | H30: Phòng Hành chánh nhân sự | I30: LUONG | W30: =SUM(K30:V30) -> 0
B31: 3 | D31: 6271002802 | E31: Chi phí khen thưởng - Gián tiếp | F31: Employee Welfare | G31: Chi phí khen thưởng - Gián tiếp | H31: Phòng Hành chánh nhân sự | I31: LUONG | W31: =SUM(K31:V31) -> 0
B32: 4 | D32: 6271002806 | E32: Thưởng danh hiệu - Gián tiếp | F32: Salary and Wages - Support | G32: Thưởng danh hiệu - Gián tiếp | H32: Phòng Hành chánh nhân sự | I32: LUONG | W32: =SUM(K32:V32) -> 0
B33: 5 | D33: 6271007202 | E33: Chi phí khen thưởng, bồi dưỡng khác | F33: Employee Welfare | G33: Chi phí khen thưởng, bồi dưỡng khác | H33: Phòng Hành chánh nhân sự | I33: LUONG | W33: =SUM(K33:V33) -> 0
B34: 6 | D34: 6271003202 | E34: Tiền ăn giữa ca - Gián tiếp | F34: Employee Welfare | G34: Tiền ăn giữa ca - Gián tiếp | H34: Phòng Hành chánh nhân sự | I34: LUONG | K34: ='Dinh muc'!$G$13*'3.Thanh pham'!F$10 -> 0 | L34: ='Dinh muc'!$G$13*'3.Thanh pham'!G$10 -> 0 | M34: ='Dinh muc'!$G$13*'3.Thanh pham'!H$10 -> 0 | N34: ='Dinh muc'!$G$13*'3.Thanh pham'!I$10 -> 5750000 | O34: ='Dinh muc'!$G$13*'3.Thanh pham'!J$10 -> 5750000 | P34: ='Dinh muc'!$G$13*'3.Thanh pham'!K$10 -> 5750000 | Q34: ='Dinh muc'!$G$13*'3.Thanh pham'!L$10 -> 5750000 | R34: ='Dinh muc'!$G$13*'3.Thanh pham'!M$10 -> 5750000 | ... V34: ='Dinh muc'!$G$13*'3.Thanh pham'!Q$10 -> 5750000 | W34: =SUM(K34:V34) -> 51750000
B35: 7 | D35: 6271002603 | E35: Phụ cấp ca đêm - Gián tiếp | F35: Salary and Wages - Support | G35: Phụ cấp ca đêm - Gián tiếp | H35: Phòng Hành chánh nhân sự | I35: LUONG | W35: =SUM(K35:V35) -> 0
B36: 8 | D36: 6271003401 | E36: BHXH, BHYT, KPCĐ, BHTN - Gián tiếp | F36: Employee Welfare | G36: BHXH, BHYT, KPCĐ, BHTN - Gián tiếp | H36: Phòng Hành chánh nhân sự | I36: LUONG | W36: =SUM(K36:V36) -> 0
B37: 9 | D37: 6271002703 | E37: Chi phí lương ngoài giờ - Gián tiếp | F37: Salary and Wages - Support | G37: Chi phí lương ngoài giờ - Gián tiếp | H37: Phòng Hành chánh nhân sự | I37: LUONG | W37: =SUM(K37:V37) -> 0
B38: 10 | D38: 6220002901 | E38: Chi phí trợ cấp thôi việc - Trực tiếp | F38: Employee Benefits Expenses | G38: Chi phí trợ cấp thôi việc - Trực tiếp | H38: Phòng Hành chánh nhân sự | I38: BP Phat sinh | W38: =SUM(K38:V38) -> 0
B39: 11 | D39: 6271003001 | E39: Chi phí đồng phục | F39: Employee Welfare | G39: Chi phí đồng phục | H39: Phòng Hành chánh nhân sự | I39: Phan bo | W39: =SUM(K39:V39) -> 0
B40: 12 | D40: 6277003101 | E40: Chi phí y tế, BH sức khỏe | F40: Employee Welfare | G40: Chi Phí Y Tế, BH Sức Khỏe, BH 24/24 | H40: Phòng Hành chánh nhân sự | I40: Phan bo | W40: =SUM(K40:V40) -> 0
B41: 13 | D41: 6273000100 | E41: Chi phí công cụ dụng cụ phục vụ SX | F41: Tools and Equipments | G41: Chi phí công cụ dụng cụ phục vụ SX | H41: Phòng Sản xuất | I41: BP Phat sinh | N41: =2*750*26500/12 -> 3312500 | O41: =2*750*26500/12 -> 3312500 | P41: =2*750*26500/12 -> 3312500 | Q41: =2*750*26500/12 -> 3312500 | R41: =2*750*26500/12 -> 3312500 | S41: =2*750*26500/12 -> 3312500 | T41: =2*750*26500/12 -> 3312500 | U41: =2*750*26500/12 -> 3312500 | V41: =2*750*26500/12 -> 3312500 | W41: =SUM(K41:V41) -> 29812500
B42: 14 | D42: 6275001803 | E42: Chi phí nước sinh hoạt | F42: Energy Expenses | G42: Chi phí nước sinh hoạt | H42: Phòng Sản xuất | I42: BP Phat sinh | W42: =SUM(K42:V42) -> 0
B43: 15 | D43: 6277002804 | E43: Tiền nước uống | F43: Miscellaneous Expenses | G43: Tiền nước uống | H43: Phòng Hành chánh nhân sự | I43: BP Phat sinh | W43: =SUM(K43:V43) -> 0
B44: 16 | D44: 6277003702 | E44: Chi phí dịch vụ môi trường | F44: Environmental Expenses | G44: Chi phí dịch vụ môi trường | H44: Ban giám đốc | I44: Phan bo | W44: =SUM(K44:V44) -> 0
B45: 17 | D45: 6277005001 | E45: Chi phí thuê nhà, văn phòng, xưởng, kho | F45: Building and structures rent | G45: Chi phí thuê nhà, văn phòng, xưởng, kho | H45: Ban giám đốc | I45: Dinh muc | W45: =SUM(K45:V45) -> 0
B46: 18 | D46: 6278007201 | E46: Chi phí bằng tiền khác | F46: Miscellaneous Expenses | G46: Chi phí bằng tiền khác | H46: Phòng Sản xuất | I46: BP Phat sinh | W46: =SUM(K46:V46) -> 0
B47: 19 | D47: 6272002201 | E47: Chi phí sửa chữa nhỏ | F47: Repairs and Maintenance Expenses | G47: Chi phí sửa chữa máy móc giá trị nhỏ | H47: Phòng Kỹ thuật | I47: BP Phat sinh | W47: =SUM(K47:V47) -> 0
B48: 20 | D48: 6273006501 | E48: Chi Phí Bảo Trì | F48: Repairs and Maintenance Expenses | G48: Chi phí bảo trì - Xuất vật tư | H48: Phòng Kỹ thuật | I48: Phan bo | W48: =SUM(K48:V48) -> 0
B49: 21 | D49: 6277004904 | E49: Bảo trì IT | F49: Information Technology - IT | G49: Bảo trì IT | H49: Ban giám đốc | I49: Phan bo | W49: =SUM(K49:V49) -> 0
B50: 22 | D50: 6277006501 | E50: Chi Phí Bảo Trì. | F50: Repairs and Maintenance Expenses | G50: Chi phí bảo trì - DV bên ngoài | H50: Phòng Kỹ thuật | I50: BP Phat sinh | W50: =SUM(K50:V50) -> 0
B51: 23 | D51: 6273002001 | E51: Xây Dựng, Sửa Chữa | F51: Repairs and Maintenance Expenses | G51: Chi phí xây dựng, sửa chữa nhà xưởng, văn phòng | H51: Ban dự án XDCB | I51: Phan bo | W51: =SUM(K51:V51) -> 0
B52: 24 | D52: 6277002204 | E52: Chi phi sửa chữa | F52: Repairs and Maintenance Expenses | G52: Chi phí sửa chữa, bảo trì phương tiện vận tải | H52: Phòng Kho vận | I52: Phan bo | W52: =SUM(K52:V52) -> 0
B53: 25 | D53: 6277002301 | E53: Chi phí bảo hiểm tài sản | F53: Insurance Expenses | G53: Chi phí bảo hiểm tài sản | H53: Phòng Kế toán | I53: Phan bo | W53: =SUM(K53:V53) -> 0
B54: 26 | D54: 6273001908 | E54: Phân bổ công cụ dụng cụ | F54: Tools and Equipments | G54: Phân bổ công cụ dụng cụ | H54: Phòng Kế toán | I54: Phan bo | W54: =SUM(K54:V54) -> 0
B55: 27 | D55: 6277003803 | E55: Phí kiểm định kỹ thuật | F55: Calibration,Testing&Quality Control Exp. | G55: Phí kiểm định kỹ thuật | W55: =SUM(K55:V55) -> 0
B56: 28 | E56: Chi phí Khấu hao | F56: Depreciation | G56: Chi phí Khấu hao | H56: Phòng Kế toán | I56: Khau hao | K56: ='PB_TSCD DC'!AF27 -> 0 | L56: ='PB_TSCD DC'!AG27 -> 0 | M56: ='PB_TSCD DC'!AH27 -> 0 | N56: ='PB_TSCD DC'!AI27 -> 46507064 | O56: ='PB_TSCD DC'!AJ27 -> 46507064 | P56: ='PB_TSCD DC'!AK27 -> 46507064 | Q56: ='PB_TSCD DC'!AL27 -> 46507064 | R56: ='PB_TSCD DC'!AM27 -> 46507064 | ... V56: ='PB_TSCD DC'!AQ27 -> 46507064 | W56: =SUM(K56:V56) -> 4.1856358e+08
B58: I+II | E58: Tổng CP_Sản xuất | J58: =J28+#REF! -> #REF! | K58: =SUM(K5,K28) -> 0 | L58: =SUM(L5,L28) -> 0 | M58: =SUM(M5,M28) -> 0 | N58: =SUM(N5,N28) -> 8.7505022e+08 | O58: =SUM(O5,O28) -> 8.7505022e+08 | P58: =SUM(P5,P28) -> 8.7505022e+08 | Q58: =SUM(Q5,Q28) -> 8.7505022e+08 | R58: =SUM(R5,R28) -> 8.7505022e+08 | ... W58: =SUM(W5,W28) -> 7.8754519e+09

Sheet CPSX Kg
B3: I - CHI PHÍ SẢN XUẤT PET | W3: ĐVT: Đồng/kg
B4: STT | C4: Dự phòng | D4: Mã tài khoản (Mã Chi phí_L4) | E4: Tên tài khoản (Cost elements 2) | F4: Chi Phí_L5 (Cost Group 2) | G4: Chi tiết | H4: Phòng ban | I4: Tham chiếu | J4: % CP/DT 2026 | K4: T1 | L4: T2 | M4: T3 | N4: T4 | O4: T5 | P4: T6 | Q4: T7 | R4: T8 | S4: T9 | T4: T10 | U4: T11 | V4: T12 | W4: KH 2026
B5: 1.1 | E5: BIẾN PHÍ | J5: =SUM(J6:J27) -> 0 | K5: =SUM(K6:K27) -> 0 | L5: =SUM(L6:L27) -> 0 | M5: =SUM(M6:M27) -> 0 | N5: =SUM(N6:N27) -> 5231 | O5: =SUM(O6:O27) -> 5231 | P5: =SUM(P6:P27) -> 5231 | Q5: =SUM(Q6:Q27) -> 5231 | ... W5: =SUM(W6:W27) -> 5231
B6: 1 | D6: 6220002601 | E6: Chi phí lương chính - Trực tiếp | F6: Salary and Wages - Direct | G6: Chi phí lương chính - Trực tiếp | H6: Phòng Hành chánh nhân sự | I6: LUONG | K6: ='Dinh muc'!$G$8*'3.Thanh pham'!F$10 -> 0 | L6: ='Dinh muc'!$G$8*'3.Thanh pham'!G$10 -> 0 | M6: ='Dinh muc'!$G$8*'3.Thanh pham'!H$10 -> 0 | N6: =ROUND(CPSX!N6/'4.Doanh thu'!I$11,0) -> 304 | O6: =ROUND(CPSX!O6/'4.Doanh thu'!J$11,0) -> 304 | P6: =ROUND(CPSX!P6/'4.Doanh thu'!K$11,0) -> 304 | Q6: =ROUND(CPSX!Q6/'4.Doanh thu'!L$11,0) -> 304 | R6: =ROUND(CPSX!R6/'4.Doanh thu'!M$11,0) -> 304 | S6: =ROUND(CPSX!S6/'4.Doanh thu'!N$11,0) -> 304 | T6: =ROUND(CPSX!T6/'4.Doanh thu'!O$11,0) -> 304 | U6: =ROUND(CPSX!U6/'4.Doanh thu'!P$11,0) -> 304 | V6: =ROUND(CPSX!V6/'4.Doanh thu'!Q$11,0) -> 304 | W6: =AVERAGE(N6:V6) -> 304
B7: 2 | D7: 6220002602 | E7: Chi phí lương T13, phép năm - Trực tiếp | F7: Salary and Wages - Direct | G7: Chi phí lương T13, phép năm - Trực tiếp | H7: Phòng Hành chánh nhân sự | I7: LUONG | N7: =ROUND(CPSX!N7/'4.Doanh thu'!I$11,0) -> 0 | O7: =ROUND(CPSX!O7/'4.Doanh thu'!J$11,0) -> 0 | P7: =ROUND(CPSX!P7/'4.Doanh thu'!K$11,0) -> 0 | Q7: =ROUND(CPSX!Q7/'4.Doanh thu'!L$11,0) -> 0 | R7: =ROUND(CPSX!R7/'4.Doanh thu'!M$11,0) -> 0 | S7: =ROUND(CPSX!S7/'4.Doanh thu'!N$11,0) -> 0 | T7: =ROUND(CPSX!T7/'4.Doanh thu'!O$11,0) -> 0 | U7: =ROUND(CPSX!U7/'4.Doanh thu'!P$11,0) -> 0 | V7: =ROUND(CPSX!V7/'4.Doanh thu'!Q$11,0) -> 0 | W7: =AVERAGE(N7:V7) -> 0
B8: 3 | D8: 6220002802 | E8: Chi phí khen thưởng - Trực tiếp | F8: Employee Welfare | G8: Chi phí khen thưởng - Trực tiếp | H8: Phòng Hành chánh nhân sự | I8: LUONG | N8: =ROUND(CPSX!N8/'4.Doanh thu'!I$11,0) -> 0 | O8: =ROUND(CPSX!O8/'4.Doanh thu'!J$11,0) -> 0 | P8: =ROUND(CPSX!P8/'4.Doanh thu'!K$11,0) -> 0 | Q8: =ROUND(CPSX!Q8/'4.Doanh thu'!L$11,0) -> 0 | R8: =ROUND(CPSX!R8/'4.Doanh thu'!M$11,0) -> 0 | S8: =ROUND(CPSX!S8/'4.Doanh thu'!N$11,0) -> 0 | T8: =ROUND(CPSX!T8/'4.Doanh thu'!O$11,0) -> 0 | U8: =ROUND(CPSX!U8/'4.Doanh thu'!P$11,0) -> 0 | V8: =ROUND(CPSX!V8/'4.Doanh thu'!Q$11,0) -> 0 | W8: =AVERAGE(N8:V8) -> 0
B9: 4 | D9: 6220002806 | E9: Thưởng danh hiệu - Trực tiếp | F9: Salary and Wages - Direct | G9: Thưởng danh hiệu - Trực tiếp | H9: Phòng Hành chánh nhân sự | I9: LUONG | N9: =ROUND(CPSX!N9/'4.Doanh thu'!I$11,0) -> 0 | O9: =ROUND(CPSX!O9/'4.Doanh thu'!J$11,0) -> 0 | P9: =ROUND(CPSX!P9/'4.Doanh thu'!K$11,0) -> 0 | Q9: =ROUND(CPSX!Q9/'4.Doanh thu'!L$11,0) -> 0 | R9: =ROUND(CPSX!R9/'4.Doanh thu'!M$11,0) -> 0 | S9: =ROUND(CPSX!S9/'4.Doanh thu'!N$11,0) -> 0 | T9: =ROUND(CPSX!T9/'4.Doanh thu'!O$11,0) -> 0 | U9: =ROUND(CPSX!U9/'4.Doanh thu'!P$11,0) -> 0 | V9: =ROUND(CPSX!V9/'4.Doanh thu'!Q$11,0) -> 0 | W9: =AVERAGE(N9:V9) -> 0
B10: 5 | D10: 6220007202 | E10: Chi phí khen thưởng, bồi dưỡng khác | F10: Employee Welfare | G10: Chi phí khen thưởng, bồi dưỡng khác | H10: Phòng Hành chánh nhân sự | I10: LUONG | N10: =ROUND(CPSX!N10/'4.Doanh thu'!I$11,0) -> 0 | O10: =ROUND(CPSX!O10/'4.Doanh thu'!J$11,0) -> 0 | P10: =ROUND(CPSX!P10/'4.Doanh thu'!K$11,0) -> 0 | Q10: =ROUND(CPSX!Q10/'4.Doanh thu'!L$11,0) -> 0 | R10: =ROUND(CPSX!R10/'4.Doanh thu'!M$11,0) -> 0 | S10: =ROUND(CPSX!S10/'4.Doanh thu'!N$11,0) -> 0 | T10: =ROUND(CPSX!T10/'4.Doanh thu'!O$11,0) -> 0 | U10: =ROUND(CPSX!U10/'4.Doanh thu'!P$11,0) -> 0 | V10: =ROUND(CPSX!V10/'4.Doanh thu'!Q$11,0) -> 0 | W10: =AVERAGE(N10:V10) -> 0
B11: 6 | D11: 6220003201 | E11: Tiền ăn giữa ca - Trực tiếp | F11: Employee Welfare | G11: Tiền ăn giữa ca - Trực tiếp | H11: Phòng Hành chánh nhân sự | I11: LUONG | K11: ='Dinh muc'!$G$9*'3.Thanh pham'!F$10 -> 0 | L11: ='Dinh muc'!$G$9*'3.Thanh pham'!G$10 -> 0 | M11: ='Dinh muc'!$G$9*'3.Thanh pham'!H$10 -> 0 | N11: =ROUND(CPSX!N11/'4.Doanh thu'!I$11,0) -> 32 | O11: =ROUND(CPSX!O11/'4.Doanh thu'!J$11,0) -> 32 | P11: =ROUND(CPSX!P11/'4.Doanh thu'!K$11,0) -> 32 | Q11: =ROUND(CPSX!Q11/'4.Doanh thu'!L$11,0) -> 32 | R11: =ROUND(CPSX!R11/'4.Doanh thu'!M$11,0) -> 32 | S11: =ROUND(CPSX!S11/'4.Doanh thu'!N$11,0) -> 32 | T11: =ROUND(CPSX!T11/'4.Doanh thu'!O$11,0) -> 32 | U11: =ROUND(CPSX!U11/'4.Doanh thu'!P$11,0) -> 32 | V11: =ROUND(CPSX!V11/'4.Doanh thu'!Q$11,0) -> 32 | W11: =AVERAGE(N11:V11) -> 32
B12: 7 | D12: 6220002603 | E12: Phụ cấp ca đêm - Trực tiếp | F12: Salary and Wages - Direct | G12: Phụ cấp ca đêm - Trực tiếp | H12: Phòng Hành chánh nhân sự | I12: LUONG | N12: =ROUND(CPSX!N12/'4.Doanh thu'!I$11,0) -> 0 | O12: =ROUND(CPSX!O12/'4.Doanh thu'!J$11,0) -> 0 | P12: =ROUND(CPSX!P12/'4.Doanh thu'!K$11,0) -> 0 | Q12: =ROUND(CPSX!Q12/'4.Doanh thu'!L$11,0) -> 0 | R12: =ROUND(CPSX!R12/'4.Doanh thu'!M$11,0) -> 0 | S12: =ROUND(CPSX!S12/'4.Doanh thu'!N$11,0) -> 0 | T12: =ROUND(CPSX!T12/'4.Doanh thu'!O$11,0) -> 0 | U12: =ROUND(CPSX!U12/'4.Doanh thu'!P$11,0) -> 0 | V12: =ROUND(CPSX!V12/'4.Doanh thu'!Q$11,0) -> 0 | W12: =AVERAGE(N12:V12) -> 0
B13: 8 | D13: 6220003401 | E13: BHXH, BHYT, KPCĐ, BHTN - Trực tiếp | F13: Employee Welfare | G13: BHXH, BHYT, KPCĐ, BHTN - Trực tiếp | H13: Phòng Hành chánh nhân sự | I13: LUONG | N13: =ROUND(CPSX!N13/'4.Doanh thu'!I$11,0) -> 0 | O13: =ROUND(CPSX!O13/'4.Doanh thu'!J$11,0) -> 0 | P13: =ROUND(CPSX!P13/'4.Doanh thu'!K$11,0) -> 0 | Q13: =ROUND(CPSX!Q13/'4.Doanh thu'!L$11,0) -> 0 | R13: =ROUND(CPSX!R13/'4.Doanh thu'!M$11,0) -> 0 | S13: =ROUND(CPSX!S13/'4.Doanh thu'!N$11,0) -> 0 | T13: =ROUND(CPSX!T13/'4.Doanh thu'!O$11,0) -> 0 | U13: =ROUND(CPSX!U13/'4.Doanh thu'!P$11,0) -> 0 | V13: =ROUND(CPSX!V13/'4.Doanh thu'!Q$11,0) -> 0 | W13: =AVERAGE(N13:V13) -> 0
B14: 9 | D14: 6220002701 | E14: Chi phí lương ngoài giờ - Trực tiếp | F14: Salary and Wages - Direct | G14: Chi phí lương ngoài giờ - Trực tiếp | H14: Phòng Hành chánh nhân sự | I14: LUONG | N14: =ROUND(CPSX!N14/'4.Doanh thu'!I$11,0) -> 0 | O14: =ROUND(CPSX!O14/'4.Doanh thu'!J$11,0) -> 0 | P14: =ROUND(CPSX!P14/'4.Doanh thu'!K$11,0) -> 0 | Q14: =ROUND(CPSX!Q14/'4.Doanh thu'!L$11,0) -> 0 | R14: =ROUND(CPSX!R14/'4.Doanh thu'!M$11,0) -> 0 | S14: =ROUND(CPSX!S14/'4.Doanh thu'!N$11,0) -> 0 | T14: =ROUND(CPSX!T14/'4.Doanh thu'!O$11,0) -> 0 | U14: =ROUND(CPSX!U14/'4.Doanh thu'!P$11,0) -> 0 | V14: =ROUND(CPSX!V14/'4.Doanh thu'!Q$11,0) -> 0 | W14: =AVERAGE(N14:V14) -> 0
B15: 10 | D15: 6220002901 | E15: Chi phí trợ cấp thôi việc - Trực tiếp | F15: Employee Benefits Expenses | G15: Chi phí trợ cấp thôi việc - Trực tiếp | H15: Phòng Hành chánh nhân sự | I15: LUONG | N15: =ROUND(CPSX!N15/'4.Doanh thu'!I$11,0) -> 0 | O15: =ROUND(CPSX!O15/'4.Doanh thu'!J$11,0) -> 0 | P15: =ROUND(CPSX!P15/'4.Doanh thu'!K$11,0) -> 0 | Q15: =ROUND(CPSX!Q15/'4.Doanh thu'!L$11,0) -> 0 | R15: =ROUND(CPSX!R15/'4.Doanh thu'!M$11,0) -> 0 | S15: =ROUND(CPSX!S15/'4.Doanh thu'!N$11,0) -> 0 | T15: =ROUND(CPSX!T15/'4.Doanh thu'!O$11,0) -> 0 | U15: =ROUND(CPSX!U15/'4.Doanh thu'!P$11,0) -> 0 | V15: =ROUND(CPSX!V15/'4.Doanh thu'!Q$11,0) -> 0 | W15: =AVERAGE(N15:V15) -> 0
B16: 11 | D16: 6220003001 | E16: Chi phí đồng phục | F16: Employee Welfare | G16: Chi phí đồng phục | H16: Phòng Hành chánh nhân sự | I16: Phan bo | N16: =ROUND(CPSX!N16/'4.Doanh thu'!I$11,0) -> 0 | O16: =ROUND(CPSX!O16/'4.Doanh thu'!J$11,0) -> 0 | P16: =ROUND(CPSX!P16/'4.Doanh thu'!K$11,0) -> 0 | Q16: =ROUND(CPSX!Q16/'4.Doanh thu'!L$11,0) -> 0 | R16: =ROUND(CPSX!R16/'4.Doanh thu'!M$11,0) -> 0 | S16: =ROUND(CPSX!S16/'4.Doanh thu'!N$11,0) -> 0 | T16: =ROUND(CPSX!T16/'4.Doanh thu'!O$11,0) -> 0 | U16: =ROUND(CPSX!U16/'4.Doanh thu'!P$11,0) -> 0 | V16: =ROUND(CPSX!V16/'4.Doanh thu'!Q$11,0) -> 0 | W16: =AVERAGE(N16:V16) -> 0
B17: 12 | E17: Chi phí y tế, BH sức khỏe | F17: Employee Welfare | G17: Chi Phí Y Tế, BH Sức Khỏe, BH 24/24 | H17: Phòng Hành chánh nhân sự | I17: Phan bo | N17: =ROUND(CPSX!N17/'4.Doanh thu'!I$11,0) -> 0 | O17: =ROUND(CPSX!O17/'4.Doanh thu'!J$11,0) -> 0 | P17: =ROUND(CPSX!P17/'4.Doanh thu'!K$11,0) -> 0 | Q17: =ROUND(CPSX!Q17/'4.Doanh thu'!L$11,0) -> 0 | R17: =ROUND(CPSX!R17/'4.Doanh thu'!M$11,0) -> 0 | S17: =ROUND(CPSX!S17/'4.Doanh thu'!N$11,0) -> 0 | T17: =ROUND(CPSX!T17/'4.Doanh thu'!O$11,0) -> 0 | U17: =ROUND(CPSX!U17/'4.Doanh thu'!P$11,0) -> 0 | V17: =ROUND(CPSX!V17/'4.Doanh thu'!Q$11,0) -> 0 | W17: =AVERAGE(N17:V17) -> 0
B18: 13 | D18: 6275001801 | E18: Chi phí điện sản xuất | F18: Direct Cost of Goods sold | G18: Chi phí điện sản xuất | H18: Phòng Kỹ thuật | I18: Dinh muc | K18: ='Dinh muc'!$G$14*'3.Thanh pham'!F$10 -> 0 | L18: ='Dinh muc'!$G$14*'3.Thanh pham'!G$10 -> 0 | M18: ='Dinh muc'!$G$14*'3.Thanh pham'!H$10 -> 0 | N18: =ROUND(CPSX!N18/'4.Doanh thu'!I$11,0) -> 2570 | O18: =ROUND(CPSX!O18/'4.Doanh thu'!J$11,0) -> 2570 | P18: =ROUND(CPSX!P18/'4.Doanh thu'!K$11,0) -> 2570 | Q18: =ROUND(CPSX!Q18/'4.Doanh thu'!L$11,0) -> 2570 | R18: =ROUND(CPSX!R18/'4.Doanh thu'!M$11,0) -> 2570 | S18: =ROUND(CPSX!S18/'4.Doanh thu'!N$11,0) -> 2570 | T18: =ROUND(CPSX!T18/'4.Doanh thu'!O$11,0) -> 2570 | U18: =ROUND(CPSX!U18/'4.Doanh thu'!P$11,0) -> 2570 | V18: =ROUND(CPSX!V18/'4.Doanh thu'!Q$11,0) -> 2570 | W18: =AVERAGE(N18:V18) -> 2570
B19: 14 | D19: 6272000100 | E19: Chi phí vật liệu phục vụ SX | F19: Operating Supplies | H19: Phòng Kỹ thuật | I19: Dinh muc | N19: =ROUND(CPSX!N19/'4.Doanh thu'!I$11,0) -> 0 | O19: =ROUND(CPSX!O19/'4.Doanh thu'!J$11,0) -> 0 | P19: =ROUND(CPSX!P19/'4.Doanh thu'!K$11,0) -> 0 | Q19: =ROUND(CPSX!Q19/'4.Doanh thu'!L$11,0) -> 0 | R19: =ROUND(CPSX!R19/'4.Doanh thu'!M$11,0) -> 0 | S19: =ROUND(CPSX!S19/'4.Doanh thu'!N$11,0) -> 0 | T19: =ROUND(CPSX!T19/'4.Doanh thu'!O$11,0) -> 0 | U19: =ROUND(CPSX!U19/'4.Doanh thu'!P$11,0) -> 0 | V19: =ROUND(CPSX!V19/'4.Doanh thu'!Q$11,0) -> 0 | W19: =AVERAGE(N19:V19) -> 0
B20: 15 | D20: 6272000100 | E20: Chi phí vật liệu phục vụ SX | F20: Operating Supplies | G20: Lõi lọc - Màng … | H20: Phòng Sản xuất | I20: Dinh muc | N20: =ROUND(CPSX!N20/'4.Doanh thu'!I$11,0) -> 0 | O20: =ROUND(CPSX!O20/'4.Doanh thu'!J$11,0) -> 0 | P20: =ROUND(CPSX!P20/'4.Doanh thu'!K$11,0) -> 0 | Q20: =ROUND(CPSX!Q20/'4.Doanh thu'!L$11,0) -> 0 | R20: =ROUND(CPSX!R20/'4.Doanh thu'!M$11,0) -> 0 | S20: =ROUND(CPSX!S20/'4.Doanh thu'!N$11,0) -> 0 | T20: =ROUND(CPSX!T20/'4.Doanh thu'!O$11,0) -> 0 | U20: =ROUND(CPSX!U20/'4.Doanh thu'!P$11,0) -> 0 | V20: =ROUND(CPSX!V20/'4.Doanh thu'!Q$11,0) -> 0 | W20: =AVERAGE(N20:V20) -> 0 | X20: Trường hợp sản xuất 2 công đoạn: Phân loại chai và băm vảy thì chỉ tính sản lượng chai dùng dây đai
B21: 16 | D21: 6272000100 | E21: Chi phí vật liệu phục vụ SX | F21: Operating Supplies | G21: Cuộn Màng PE | H21: Phòng Sản xuất | I21: Dinh muc | K21: ='Dinh muc'!$G$18*'3.Thanh pham'!F$10 -> 0 | L21: ='Dinh muc'!$G$18*'3.Thanh pham'!G$10 -> 0 | M21: ='Dinh muc'!$G$18*'3.Thanh pham'!H$10 -> 0 | N21: =ROUND(CPSX!N21/'4.Doanh thu'!I$11,0) -> 167 | O21: =ROUND(CPSX!O21/'4.Doanh thu'!J$11,0) -> 167 | P21: =ROUND(CPSX!P21/'4.Doanh thu'!K$11,0) -> 167 | Q21: =ROUND(CPSX!Q21/'4.Doanh thu'!L$11,0) -> 167 | R21: =ROUND(CPSX!R21/'4.Doanh thu'!M$11,0) -> 167 | S21: =ROUND(CPSX!S21/'4.Doanh thu'!N$11,0) -> 167 | T21: =ROUND(CPSX!T21/'4.Doanh thu'!O$11,0) -> 167 | U21: =ROUND(CPSX!U21/'4.Doanh thu'!P$11,0) -> 167 | V21: =ROUND(CPSX!V21/'4.Doanh thu'!Q$11,0) -> 167 | W21: =AVERAGE(N21:V21) -> 167
B22: 17 | D22: 6272000100 | E22: Chi phí vật liệu phục vụ SX | F22: Operating Supplies | G22: Lõi giấy | H22: Phòng Sản xuất | I22: Dinh muc | K22: ='Dinh muc'!$G$19*'3.Thanh pham'!F$10 -> 0 | L22: ='Dinh muc'!$G$19*'3.Thanh pham'!G$10 -> 0 | M22: ='Dinh muc'!$G$19*'3.Thanh pham'!H$10 -> 0 | N22: =ROUND(CPSX!N22/'4.Doanh thu'!I$11,0) -> 1000 | O22: =ROUND(CPSX!O22/'4.Doanh thu'!J$11,0) -> 1000 | P22: =ROUND(CPSX!P22/'4.Doanh thu'!K$11,0) -> 1000 | Q22: =ROUND(CPSX!Q22/'4.Doanh thu'!L$11,0) -> 1000 | R22: =ROUND(CPSX!R22/'4.Doanh thu'!M$11,0) -> 1000 | S22: =ROUND(CPSX!S22/'4.Doanh thu'!N$11,0) -> 1000 | T22: =ROUND(CPSX!T22/'4.Doanh thu'!O$11,0) -> 1000 | U22: =ROUND(CPSX!U22/'4.Doanh thu'!P$11,0) -> 1000 | V22: =ROUND(CPSX!V22/'4.Doanh thu'!Q$11,0) -> 1000 | W22: =AVERAGE(N22:V22) -> 1000
B23: 18 | D23: 6272000100 | E23: Chi phí vật liệu phục vụ SX | F23: Operating Supplies | G23: Pallet rHD D4-0986 DTR | H23: Phòng Sản xuất | I23: Dinh muc | K23: ='Dinh muc'!$G$20*'3.Thanh pham'!F$10 -> 0 | L23: ='Dinh muc'!$G$20*'3.Thanh pham'!G$10 -> 0 | M23: ='Dinh muc'!$G$20*'3.Thanh pham'!H$10 -> 0 | N23: =ROUND(CPSX!N23/'4.Doanh thu'!I$11,0) -> 674 | O23: =ROUND(CPSX!O23/'4.Doanh thu'!J$11,0) -> 674 | P23: =ROUND(CPSX!P23/'4.Doanh thu'!K$11,0) -> 674 | Q23: =ROUND(CPSX!Q23/'4.Doanh thu'!L$11,0) -> 674 | R23: =ROUND(CPSX!R23/'4.Doanh thu'!M$11,0) -> 674 | S23: =ROUND(CPSX!S23/'4.Doanh thu'!N$11,0) -> 674 | T23: =ROUND(CPSX!T23/'4.Doanh thu'!O$11,0) -> 674 | U23: =ROUND(CPSX!U23/'4.Doanh thu'!P$11,0) -> 674 | V23: =ROUND(CPSX!V23/'4.Doanh thu'!Q$11,0) -> 674 | W23: =AVERAGE(N23:V23) -> 674
B24: 19 | D24: 6272002101 | E24: Chi phí vật tư phân xưởng | F24: Operating Supplies | G24: Chi phí vật tư phân xưởng (ron) | K24: =SUM('Dinh muc'!$G$17:$G$20)*'3.Thanh pham'!F10 -> 0 | L24: =SUM('Dinh muc'!$G$17:$G$20)*'3.Thanh pham'!G10 -> 0 | M24: =SUM('Dinh muc'!$G$17:$G$20)*'3.Thanh pham'!H10 -> 0 | N24: =ROUND(CPSX!N24/'4.Doanh thu'!I$11,0) -> 74 | O24: =ROUND(CPSX!O24/'4.Doanh thu'!J$11,0) -> 74 | P24: =ROUND(CPSX!P24/'4.Doanh thu'!K$11,0) -> 74 | Q24: =ROUND(CPSX!Q24/'4.Doanh thu'!L$11,0) -> 74 | R24: =ROUND(CPSX!R24/'4.Doanh thu'!M$11,0) -> 74 | S24: =ROUND(CPSX!S24/'4.Doanh thu'!N$11,0) -> 74 | T24: =ROUND(CPSX!T24/'4.Doanh thu'!O$11,0) -> 74 | U24: =ROUND(CPSX!U24/'4.Doanh thu'!P$11,0) -> 74 | V24: =ROUND(CPSX!V24/'4.Doanh thu'!Q$11,0) -> 74 | W24: =AVERAGE(N24:V24) -> 74
B25: 19 | D25: 6272002101 | E25: Chi phí vật tư phân xưởng | F25: Operating Supplies | G25: Cp nước | K25: =SUM('Dinh muc'!$G$15:$G$16)*'3.Thanh pham'!F$10 -> 0 | L25: =SUM('Dinh muc'!$G$15:$G$16)*'3.Thanh pham'!G$10 -> 0 | M25: =SUM('Dinh muc'!$G$15:$G$16)*'3.Thanh pham'!H$10 -> 0 | N25: =ROUND(CPSX!N25/'4.Doanh thu'!I$11,0) -> 163 | O25: =ROUND(CPSX!O25/'4.Doanh thu'!J$11,0) -> 163 | P25: =ROUND(CPSX!P25/'4.Doanh thu'!K$11,0) -> 163 | Q25: =ROUND(CPSX!Q25/'4.Doanh thu'!L$11,0) -> 163 | R25: =ROUND(CPSX!R25/'4.Doanh thu'!M$11,0) -> 163 | S25: =ROUND(CPSX!S25/'4.Doanh thu'!N$11,0) -> 163 | T25: =ROUND(CPSX!T25/'4.Doanh thu'!O$11,0) -> 163 | U25: =ROUND(CPSX!U25/'4.Doanh thu'!P$11,0) -> 163 | V25: =ROUND(CPSX!V25/'4.Doanh thu'!Q$11,0) -> 163 | W25: =AVERAGE(N25:V25) -> 163
B26: 20 | D26: 6272003502 | E26: Chi phí xăng dầu xe du lịch, xe gắn máy, xe nâng | F26: Energy Expenses | G26: Xăng dầu xe nâng | H26: Phòng Kho vận | I26: Dinh muc | K26: ='Dinh muc'!$G$21*'3.Thanh pham'!F$10 -> 0 | L26: ='Dinh muc'!$G$21*'3.Thanh pham'!G$10 -> 0 | M26: ='Dinh muc'!$G$21*'3.Thanh pham'!H$10 -> 0 | N26: =ROUND(CPSX!N26/'4.Doanh thu'!I$11,0) -> 247 | O26: =ROUND(CPSX!O26/'4.Doanh thu'!J$11,0) -> 247 | P26: =ROUND(CPSX!P26/'4.Doanh thu'!K$11,0) -> 247 | Q26: =ROUND(CPSX!Q26/'4.Doanh thu'!L$11,0) -> 247 | R26: =ROUND(CPSX!R26/'4.Doanh thu'!M$11,0) -> 247 | S26: =ROUND(CPSX!S26/'4.Doanh thu'!N$11,0) -> 247 | T26: =ROUND(CPSX!T26/'4.Doanh thu'!O$11,0) -> 247 | U26: =ROUND(CPSX!U26/'4.Doanh thu'!P$11,0) -> 247 | V26: =ROUND(CPSX!V26/'4.Doanh thu'!Q$11,0) -> 247 | W26: =AVERAGE(N26:V26) -> 247
B28: II | E28: ĐỊNH PHÍ | J28: =SUM(J29:J57) -> 0 | K28: =SUM(K29:K57) -> 0 | L28: =SUM(L29:L57) -> 0 | M28: =SUM(M29:M57) -> 0 | N28: =SUM(N29:N57) -> 915 | O28: =SUM(O29:O57) -> 915 | P28: =SUM(P29:P57) -> 915 | Q28: =SUM(Q29:Q57) -> 915 | ... W28: =SUM(W29:W57) -> 915
B29: 1 | D29: 6271002604 | E29: Chi phí lương chính - Gián tiếp | F29: Salary and Wages - Support | G29: Chi phí lương chính - Gián tiếp | H29: Phòng Hành chánh nhân sự | I29: LUONG | K29: =SUM('Dinh muc'!$G$11:$G$12)*'3.Thanh pham'!F$10 -> 0 | L29: =SUM('Dinh muc'!$G$11:$G$12)*'3.Thanh pham'!G$10 -> 0 | M29: =SUM('Dinh muc'!$G$11:$G$12)*'3.Thanh pham'!H$10 -> 0 | N29: =ROUND(CPSX!N29/'4.Doanh thu'!I$11,0) -> 525 | O29: =ROUND(CPSX!O29/'4.Doanh thu'!J$11,0) -> 525 | P29: =ROUND(CPSX!P29/'4.Doanh thu'!K$11,0) -> 525 | Q29: =ROUND(CPSX!Q29/'4.Doanh thu'!L$11,0) -> 525 | R29: =ROUND(CPSX!R29/'4.Doanh thu'!M$11,0) -> 525 | S29: =ROUND(CPSX!S29/'4.Doanh thu'!N$11,0) -> 525 | T29: =ROUND(CPSX!T29/'4.Doanh thu'!O$11,0) -> 525 | U29: =ROUND(CPSX!U29/'4.Doanh thu'!P$11,0) -> 525 | V29: =ROUND(CPSX!V29/'4.Doanh thu'!Q$11,0) -> 525 | W29: =AVERAGE(N29:V29) -> 525
B30: 2 | D30: 6271002605 | E30: Chi phí lương T13, phép năm - Gián tiếp | F30: Salary and Wages - Support | G30: Chi phí lương T13, phép năm - Gián tiếp | H30: Phòng Hành chánh nhân sự | I30: LUONG | N30: =ROUND(CPSX!N30/'4.Doanh thu'!I$11,0) -> 0 | O30: =ROUND(CPSX!O30/'4.Doanh thu'!J$11,0) -> 0 | P30: =ROUND(CPSX!P30/'4.Doanh thu'!K$11,0) -> 0 | Q30: =ROUND(CPSX!Q30/'4.Doanh thu'!L$11,0) -> 0 | R30: =ROUND(CPSX!R30/'4.Doanh thu'!M$11,0) -> 0 | S30: =ROUND(CPSX!S30/'4.Doanh thu'!N$11,0) -> 0 | T30: =ROUND(CPSX!T30/'4.Doanh thu'!O$11,0) -> 0 | U30: =ROUND(CPSX!U30/'4.Doanh thu'!P$11,0) -> 0 | V30: =ROUND(CPSX!V30/'4.Doanh thu'!Q$11,0) -> 0 | W30: =AVERAGE(N30:V30) -> 0
B31: 3 | D31: 6271002802 | E31: Chi phí khen thưởng - Gián tiếp | F31: Employee Welfare | G31: Chi phí khen thưởng - Gián tiếp | H31: Phòng Hành chánh nhân sự | I31: LUONG | N31: =ROUND(CPSX!N31/'4.Doanh thu'!I$11,0) -> 0 | O31: =ROUND(CPSX!O31/'4.Doanh thu'!J$11,0) -> 0 | P31: =ROUND(CPSX!P31/'4.Doanh thu'!K$11,0) -> 0 | Q31: =ROUND(CPSX!Q31/'4.Doanh thu'!L$11,0) -> 0 | R31: =ROUND(CPSX!R31/'4.Doanh thu'!M$11,0) -> 0 | S31: =ROUND(CPSX!S31/'4.Doanh thu'!N$11,0) -> 0 | T31: =ROUND(CPSX!T31/'4.Doanh thu'!O$11,0) -> 0 | U31: =ROUND(CPSX!U31/'4.Doanh thu'!P$11,0) -> 0 | V31: =ROUND(CPSX!V31/'4.Doanh thu'!Q$11,0) -> 0 | W31: =AVERAGE(N31:V31) -> 0
B32: 4 | D32: 6271002806 | E32: Thưởng danh hiệu - Gián tiếp | F32: Salary and Wages - Support | G32: Thưởng danh hiệu - Gián tiếp | H32: Phòng Hành chánh nhân sự | I32: LUONG | N32: =ROUND(CPSX!N32/'4.Doanh thu'!I$11,0) -> 0 | O32: =ROUND(CPSX!O32/'4.Doanh thu'!J$11,0) -> 0 | P32: =ROUND(CPSX!P32/'4.Doanh thu'!K$11,0) -> 0 | Q32: =ROUND(CPSX!Q32/'4.Doanh thu'!L$11,0) -> 0 | R32: =ROUND(CPSX!R32/'4.Doanh thu'!M$11,0) -> 0 | S32: =ROUND(CPSX!S32/'4.Doanh thu'!N$11,0) -> 0 | T32: =ROUND(CPSX!T32/'4.Doanh thu'!O$11,0) -> 0 | U32: =ROUND(CPSX!U32/'4.Doanh thu'!P$11,0) -> 0 | V32: =ROUND(CPSX!V32/'4.Doanh thu'!Q$11,0) -> 0 | W32: =AVERAGE(N32:V32) -> 0
B33: 5 | D33: 6271007202 | E33: Chi phí khen thưởng, bồi dưỡng khác | F33: Employee Welfare | G33: Chi phí khen thưởng, bồi dưỡng khác | H33: Phòng Hành chánh nhân sự | I33: LUONG | N33: =ROUND(CPSX!N33/'4.Doanh thu'!I$11,0) -> 0 | O33: =ROUND(CPSX!O33/'4.Doanh thu'!J$11,0) -> 0 | P33: =ROUND(CPSX!P33/'4.Doanh thu'!K$11,0) -> 0 | Q33: =ROUND(CPSX!Q33/'4.Doanh thu'!L$11,0) -> 0 | R33: =ROUND(CPSX!R33/'4.Doanh thu'!M$11,0) -> 0 | S33: =ROUND(CPSX!S33/'4.Doanh thu'!N$11,0) -> 0 | T33: =ROUND(CPSX!T33/'4.Doanh thu'!O$11,0) -> 0 | U33: =ROUND(CPSX!U33/'4.Doanh thu'!P$11,0) -> 0 | V33: =ROUND(CPSX!V33/'4.Doanh thu'!Q$11,0) -> 0 | W33: =AVERAGE(N33:V33) -> 0
B34: 6 | D34: 6271003202 | E34: Tiền ăn giữa ca - Gián tiếp | F34: Employee Welfare | G34: Tiền ăn giữa ca - Gián tiếp | H34: Phòng Hành chánh nhân sự | I34: LUONG | K34: ='Dinh muc'!$G$13*'3.Thanh pham'!F$10 -> 0 | L34: ='Dinh muc'!$G$13*'3.Thanh pham'!G$10 -> 0 | M34: ='Dinh muc'!$G$13*'3.Thanh pham'!H$10 -> 0 | N34: =ROUND(CPSX!N34/'4.Doanh thu'!I$11,0) -> 40 | O34: =ROUND(CPSX!O34/'4.Doanh thu'!J$11,0) -> 40 | P34: =ROUND(CPSX!P34/'4.Doanh thu'!K$11,0) -> 40 | Q34: =ROUND(CPSX!Q34/'4.Doanh thu'!L$11,0) -> 40 | R34: =ROUND(CPSX!R34/'4.Doanh thu'!M$11,0) -> 40 | S34: =ROUND(CPSX!S34/'4.Doanh thu'!N$11,0) -> 40 | T34: =ROUND(CPSX!T34/'4.Doanh thu'!O$11,0) -> 40 | U34: =ROUND(CPSX!U34/'4.Doanh thu'!P$11,0) -> 40 | V34: =ROUND(CPSX!V34/'4.Doanh thu'!Q$11,0) -> 40 | W34: =AVERAGE(N34:V34) -> 40
B35: 7 | D35: 6271002603 | E35: Phụ cấp ca đêm - Gián tiếp | F35: Salary and Wages - Support | G35: Phụ cấp ca đêm - Gián tiếp | H35: Phòng Hành chánh nhân sự | I35: LUONG | N35: =ROUND(CPSX!N35/'4.Doanh thu'!I$11,0) -> 0 | O35: =ROUND(CPSX!O35/'4.Doanh thu'!J$11,0) -> 0 | P35: =ROUND(CPSX!P35/'4.Doanh thu'!K$11,0) -> 0 | Q35: =ROUND(CPSX!Q35/'4.Doanh thu'!L$11,0) -> 0 | R35: =ROUND(CPSX!R35/'4.Doanh thu'!M$11,0) -> 0 | S35: =ROUND(CPSX!S35/'4.Doanh thu'!N$11,0) -> 0 | T35: =ROUND(CPSX!T35/'4.Doanh thu'!O$11,0) -> 0 | U35: =ROUND(CPSX!U35/'4.Doanh thu'!P$11,0) -> 0 | V35: =ROUND(CPSX!V35/'4.Doanh thu'!Q$11,0) -> 0 | W35: =AVERAGE(N35:V35) -> 0
B36: 8 | D36: 6271003401 | E36: BHXH, BHYT, KPCĐ, BHTN - Gián tiếp | F36: Employee Welfare | G36: BHXH, BHYT, KPCĐ, BHTN - Gián tiếp | H36: Phòng Hành chánh nhân sự | I36: LUONG | N36: =ROUND(CPSX!N36/'4.Doanh thu'!I$11,0) -> 0 | O36: =ROUND(CPSX!O36/'4.Doanh thu'!J$11,0) -> 0 | P36: =ROUND(CPSX!P36/'4.Doanh thu'!K$11,0) -> 0 | Q36: =ROUND(CPSX!Q36/'4.Doanh thu'!L$11,0) -> 0 | R36: =ROUND(CPSX!R36/'4.Doanh thu'!M$11,0) -> 0 | S36: =ROUND(CPSX!S36/'4.Doanh thu'!N$11,0) -> 0 | T36: =ROUND(CPSX!T36/'4.Doanh thu'!O$11,0) -> 0 | U36: =ROUND(CPSX!U36/'4.Doanh thu'!P$11,0) -> 0 | V36: =ROUND(CPSX!V36/'4.Doanh thu'!Q$11,0) -> 0 | W36: =AVERAGE(N36:V36) -> 0
B37: 9 | D37: 6271002703 | E37: Chi phí lương ngoài giờ - Gián tiếp | F37: Salary and Wages - Support | G37: Chi phí lương ngoài giờ - Gián tiếp | H37: Phòng Hành chánh nhân sự | I37: LUONG | N37: =ROUND(CPSX!N37/'4.Doanh thu'!I$11,0) -> 0 | O37: =ROUND(CPSX!O37/'4.Doanh thu'!J$11,0) -> 0 | P37: =ROUND(CPSX!P37/'4.Doanh thu'!K$11,0) -> 0 | Q37: =ROUND(CPSX!Q37/'4.Doanh thu'!L$11,0) -> 0 | R37: =ROUND(CPSX!R37/'4.Doanh thu'!M$11,0) -> 0 | S37: =ROUND(CPSX!S37/'4.Doanh thu'!N$11,0) -> 0 | T37: =ROUND(CPSX!T37/'4.Doanh thu'!O$11,0) -> 0 | U37: =ROUND(CPSX!U37/'4.Doanh thu'!P$11,0) -> 0 | V37: =ROUND(CPSX!V37/'4.Doanh thu'!Q$11,0) -> 0 | W37: =AVERAGE(N37:V37) -> 0
B38: 10 | D38: 6220002901 | E38: Chi phí trợ cấp thôi việc - Trực tiếp | F38: Employee Benefits Expenses | G38: Chi phí trợ cấp thôi việc - Trực tiếp | H38: Phòng Hành chánh nhân sự | I38: BP Phat sinh | N38: =ROUND(CPSX!N38/'4.Doanh thu'!I$11,0) -> 0 | O38: =ROUND(CPSX!O38/'4.Doanh thu'!J$11,0) -> 0 | P38: =ROUND(CPSX!P38/'4.Doanh thu'!K$11,0) -> 0 | Q38: =ROUND(CPSX!Q38/'4.Doanh thu'!L$11,0) -> 0 | R38: =ROUND(CPSX!R38/'4.Doanh thu'!M$11,0) -> 0 | S38: =ROUND(CPSX!S38/'4.Doanh thu'!N$11,0) -> 0 | T38: =ROUND(CPSX!T38/'4.Doanh thu'!O$11,0) -> 0 | U38: =ROUND(CPSX!U38/'4.Doanh thu'!P$11,0) -> 0 | V38: =ROUND(CPSX!V38/'4.Doanh thu'!Q$11,0) -> 0 | W38: =AVERAGE(N38:V38) -> 0
B39: 11 | D39: 6271003001 | E39: Chi phí đồng phục | F39: Employee Welfare | G39: Chi phí đồng phục | H39: Phòng Hành chánh nhân sự | I39: Phan bo | N39: =ROUND(CPSX!N39/'4.Doanh thu'!I$11,0) -> 0 | O39: =ROUND(CPSX!O39/'4.Doanh thu'!J$11,0) -> 0 | P39: =ROUND(CPSX!P39/'4.Doanh thu'!K$11,0) -> 0 | Q39: =ROUND(CPSX!Q39/'4.Doanh thu'!L$11,0) -> 0 | R39: =ROUND(CPSX!R39/'4.Doanh thu'!M$11,0) -> 0 | S39: =ROUND(CPSX!S39/'4.Doanh thu'!N$11,0) -> 0 | T39: =ROUND(CPSX!T39/'4.Doanh thu'!O$11,0) -> 0 | U39: =ROUND(CPSX!U39/'4.Doanh thu'!P$11,0) -> 0 | V39: =ROUND(CPSX!V39/'4.Doanh thu'!Q$11,0) -> 0 | W39: =AVERAGE(N39:V39) -> 0
B40: 12 | D40: 6277003101 | E40: Chi phí y tế, BH sức khỏe | F40: Employee Welfare | G40: Chi Phí Y Tế, BH Sức Khỏe, BH 24/24 | H40: Phòng Hành chánh nhân sự | I40: Phan bo | N40: =ROUND(CPSX!N40/'4.Doanh thu'!I$11,0) -> 0 | O40: =ROUND(CPSX!O40/'4.Doanh thu'!J$11,0) -> 0 | P40: =ROUND(CPSX!P40/'4.Doanh thu'!K$11,0) -> 0 | Q40: =ROUND(CPSX!Q40/'4.Doanh thu'!L$11,0) -> 0 | R40: =ROUND(CPSX!R40/'4.Doanh thu'!M$11,0) -> 0 | S40: =ROUND(CPSX!S40/'4.Doanh thu'!N$11,0) -> 0 | T40: =ROUND(CPSX!T40/'4.Doanh thu'!O$11,0) -> 0 | U40: =ROUND(CPSX!U40/'4.Doanh thu'!P$11,0) -> 0 | V40: =ROUND(CPSX!V40/'4.Doanh thu'!Q$11,0) -> 0 | W40: =AVERAGE(N40:V40) -> 0
B41: 13 | D41: 6273000100 | E41: Chi phí công cụ dụng cụ phục vụ SX | F41: Tools and Equipments | G41: Chi phí công cụ dụng cụ phục vụ SX | H41: Phòng Sản xuất | I41: BP Phat sinh | N41: =ROUND(CPSX!N41/'4.Doanh thu'!I$11,0) -> 23 | O41: =ROUND(CPSX!O41/'4.Doanh thu'!J$11,0) -> 23 | P41: =ROUND(CPSX!P41/'4.Doanh thu'!K$11,0) -> 23 | Q41: =ROUND(CPSX!Q41/'4.Doanh thu'!L$11,0) -> 23 | R41: =ROUND(CPSX!R41/'4.Doanh thu'!M$11,0) -> 23 | S41: =ROUND(CPSX!S41/'4.Doanh thu'!N$11,0) -> 23 | T41: =ROUND(CPSX!T41/'4.Doanh thu'!O$11,0) -> 23 | U41: =ROUND(CPSX!U41/'4.Doanh thu'!P$11,0) -> 23 | V41: =ROUND(CPSX!V41/'4.Doanh thu'!Q$11,0) -> 23 | W41: =AVERAGE(N41:V41) -> 23
B42: 14 | D42: 6275001803 | E42: Chi phí nước sinh hoạt | F42: Energy Expenses | G42: Chi phí nước sinh hoạt | H42: Phòng Sản xuất | I42: BP Phat sinh | N42: =ROUND(CPSX!N42/'4.Doanh thu'!I$11,0) -> 0 | O42: =ROUND(CPSX!O42/'4.Doanh thu'!J$11,0) -> 0 | P42: =ROUND(CPSX!P42/'4.Doanh thu'!K$11,0) -> 0 | Q42: =ROUND(CPSX!Q42/'4.Doanh thu'!L$11,0) -> 0 | R42: =ROUND(CPSX!R42/'4.Doanh thu'!M$11,0) -> 0 | S42: =ROUND(CPSX!S42/'4.Doanh thu'!N$11,0) -> 0 | T42: =ROUND(CPSX!T42/'4.Doanh thu'!O$11,0) -> 0 | U42: =ROUND(CPSX!U42/'4.Doanh thu'!P$11,0) -> 0 | V42: =ROUND(CPSX!V42/'4.Doanh thu'!Q$11,0) -> 0 | W42: =AVERAGE(N42:V42) -> 0
B43: 15 | D43: 6277002804 | E43: Tiền nước uống | F43: Miscellaneous Expenses | G43: Tiền nước uống | H43: Phòng Hành chánh nhân sự | I43: BP Phat sinh | N43: =ROUND(CPSX!N43/'4.Doanh thu'!I$11,0) -> 0 | O43: =ROUND(CPSX!O43/'4.Doanh thu'!J$11,0) -> 0 | P43: =ROUND(CPSX!P43/'4.Doanh thu'!K$11,0) -> 0 | Q43: =ROUND(CPSX!Q43/'4.Doanh thu'!L$11,0) -> 0 | R43: =ROUND(CPSX!R43/'4.Doanh thu'!M$11,0) -> 0 | S43: =ROUND(CPSX!S43/'4.Doanh thu'!N$11,0) -> 0 | T43: =ROUND(CPSX!T43/'4.Doanh thu'!O$11,0) -> 0 | U43: =ROUND(CPSX!U43/'4.Doanh thu'!P$11,0) -> 0 | V43: =ROUND(CPSX!V43/'4.Doanh thu'!Q$11,0) -> 0 | W43: =AVERAGE(N43:V43) -> 0
B44: 16 | D44: 6277003702 | E44: Chi phí dịch vụ môi trường | F44: Environmental Expenses | G44: Chi phí dịch vụ môi trường | H44: Ban giám đốc | I44: Phan bo | N44: =ROUND(CPSX!N44/'4.Doanh thu'!I$11,0) -> 0 | O44: =ROUND(CPSX!O44/'4.Doanh thu'!J$11,0) -> 0 | P44: =ROUND(CPSX!P44/'4.Doanh thu'!K$11,0) -> 0 | Q44: =ROUND(CPSX!Q44/'4.Doanh thu'!L$11,0) -> 0 | R44: =ROUND(CPSX!R44/'4.Doanh thu'!M$11,0) -> 0 | S44: =ROUND(CPSX!S44/'4.Doanh thu'!N$11,0) -> 0 | T44: =ROUND(CPSX!T44/'4.Doanh thu'!O$11,0) -> 0 | U44: =ROUND(CPSX!U44/'4.Doanh thu'!P$11,0) -> 0 | V44: =ROUND(CPSX!V44/'4.Doanh thu'!Q$11,0) -> 0 | W44: =AVERAGE(N44:V44) -> 0
B45: 17 | D45: 6277005001 | E45: Chi phí thuê nhà, văn phòng, xưởng, kho | F45: Building and structures rent | G45: Chi phí thuê nhà, văn phòng, xưởng, kho | H45: Ban giám đốc | I45: Dinh muc | N45: =ROUND(CPSX!N45/'4.Doanh thu'!I$11,0) -> 0 | O45: =ROUND(CPSX!O45/'4.Doanh thu'!J$11,0) -> 0 | P45: =ROUND(CPSX!P45/'4.Doanh thu'!K$11,0) -> 0 | Q45: =ROUND(CPSX!Q45/'4.Doanh thu'!L$11,0) -> 0 | R45: =ROUND(CPSX!R45/'4.Doanh thu'!M$11,0) -> 0 | S45: =ROUND(CPSX!S45/'4.Doanh thu'!N$11,0) -> 0 | T45: =ROUND(CPSX!T45/'4.Doanh thu'!O$11,0) -> 0 | U45: =ROUND(CPSX!U45/'4.Doanh thu'!P$11,0) -> 0 | V45: =ROUND(CPSX!V45/'4.Doanh thu'!Q$11,0) -> 0 | W45: =AVERAGE(N45:V45) -> 0
B46: 18 | D46: 6278007201 | E46: Chi phí bằng tiền khác | F46: Miscellaneous Expenses | G46: Chi phí bằng tiền khác | H46: Phòng Sản xuất | I46: BP Phat sinh | N46: =ROUND(CPSX!N46/'4.Doanh thu'!I$11,0) -> 0 | O46: =ROUND(CPSX!O46/'4.Doanh thu'!J$11,0) -> 0 | P46: =ROUND(CPSX!P46/'4.Doanh thu'!K$11,0) -> 0 | Q46: =ROUND(CPSX!Q46/'4.Doanh thu'!L$11,0) -> 0 | R46: =ROUND(CPSX!R46/'4.Doanh thu'!M$11,0) -> 0 | S46: =ROUND(CPSX!S46/'4.Doanh thu'!N$11,0) -> 0 | T46: =ROUND(CPSX!T46/'4.Doanh thu'!O$11,0) -> 0 | U46: =ROUND(CPSX!U46/'4.Doanh thu'!P$11,0) -> 0 | V46: =ROUND(CPSX!V46/'4.Doanh thu'!Q$11,0) -> 0 | W46: =AVERAGE(N46:V46) -> 0
B47: 19 | D47: 6272002201 | E47: Chi phí sửa chữa nhỏ | F47: Repairs and Maintenance Expenses | G47: Chi phí sửa chữa máy móc giá trị nhỏ | H47: Phòng Kỹ thuật | I47: BP Phat sinh | N47: =ROUND(CPSX!N47/'4.Doanh thu'!I$11,0) -> 0 | O47: =ROUND(CPSX!O47/'4.Doanh thu'!J$11,0) -> 0 | P47: =ROUND(CPSX!P47/'4.Doanh thu'!K$11,0) -> 0 | Q47: =ROUND(CPSX!Q47/'4.Doanh thu'!L$11,0) -> 0 | R47: =ROUND(CPSX!R47/'4.Doanh thu'!M$11,0) -> 0 | S47: =ROUND(CPSX!S47/'4.Doanh thu'!N$11,0) -> 0 | T47: =ROUND(CPSX!T47/'4.Doanh thu'!O$11,0) -> 0 | U47: =ROUND(CPSX!U47/'4.Doanh thu'!P$11,0) -> 0 | V47: =ROUND(CPSX!V47/'4.Doanh thu'!Q$11,0) -> 0 | W47: =AVERAGE(N47:V47) -> 0
B48: 20 | D48: 6273006501 | E48: Chi Phí Bảo Trì | F48: Repairs and Maintenance Expenses | G48: Chi phí bảo trì - Xuất vật tư | H48: Phòng Kỹ thuật | I48: Phan bo | N48: =ROUND(CPSX!N48/'4.Doanh thu'!I$11,0) -> 0 | O48: =ROUND(CPSX!O48/'4.Doanh thu'!J$11,0) -> 0 | P48: =ROUND(CPSX!P48/'4.Doanh thu'!K$11,0) -> 0 | Q48: =ROUND(CPSX!Q48/'4.Doanh thu'!L$11,0) -> 0 | R48: =ROUND(CPSX!R48/'4.Doanh thu'!M$11,0) -> 0 | S48: =ROUND(CPSX!S48/'4.Doanh thu'!N$11,0) -> 0 | T48: =ROUND(CPSX!T48/'4.Doanh thu'!O$11,0) -> 0 | U48: =ROUND(CPSX!U48/'4.Doanh thu'!P$11,0) -> 0 | V48: =ROUND(CPSX!V48/'4.Doanh thu'!Q$11,0) -> 0 | W48: =AVERAGE(N48:V48) -> 0
B49: 21 | D49: 6277004904 | E49: Bảo trì IT | F49: Information Technology - IT | G49: Bảo trì IT | H49: Ban giám đốc | I49: Phan bo | N49: =ROUND(CPSX!N49/'4.Doanh thu'!I$11,0) -> 0 | O49: =ROUND(CPSX!O49/'4.Doanh thu'!J$11,0) -> 0 | P49: =ROUND(CPSX!P49/'4.Doanh thu'!K$11,0) -> 0 | Q49: =ROUND(CPSX!Q49/'4.Doanh thu'!L$11,0) -> 0 | R49: =ROUND(CPSX!R49/'4.Doanh thu'!M$11,0) -> 0 | S49: =ROUND(CPSX!S49/'4.Doanh thu'!N$11,0) -> 0 | T49: =ROUND(CPSX!T49/'4.Doanh thu'!O$11,0) -> 0 | U49: =ROUND(CPSX!U49/'4.Doanh thu'!P$11,0) -> 0 | V49: =ROUND(CPSX!V49/'4.Doanh thu'!Q$11,0) -> 0 | W49: =AVERAGE(N49:V49) -> 0
B50: 22 | D50: 6277006501 | E50: Chi Phí Bảo Trì. | F50: Repairs and Maintenance Expenses | G50: Chi phí bảo trì - DV bên ngoài | H50: Phòng Kỹ thuật | I50: BP Phat sinh | N50: =ROUND(CPSX!N50/'4.Doanh thu'!I$11,0) -> 0 | O50: =ROUND(CPSX!O50/'4.Doanh thu'!J$11,0) -> 0 | P50: =ROUND(CPSX!P50/'4.Doanh thu'!K$11,0) -> 0 | Q50: =ROUND(CPSX!Q50/'4.Doanh thu'!L$11,0) -> 0 | R50: =ROUND(CPSX!R50/'4.Doanh thu'!M$11,0) -> 0 | S50: =ROUND(CPSX!S50/'4.Doanh thu'!N$11,0) -> 0 | T50: =ROUND(CPSX!T50/'4.Doanh thu'!O$11,0) -> 0 | U50: =ROUND(CPSX!U50/'4.Doanh thu'!P$11,0) -> 0 | V50: =ROUND(CPSX!V50/'4.Doanh thu'!Q$11,0) -> 0 | W50: =AVERAGE(N50:V50) -> 0
B51: 23 | D51: 6273002001 | E51: Xây Dựng, Sửa Chữa | F51: Repairs and Maintenance Expenses | G51: Chi phí xây dựng, sửa chữa nhà xưởng, văn phòng | H51: Ban dự án XDCB | I51: Phan bo | N51: =ROUND(CPSX!N51/'4.Doanh thu'!I$11,0) -> 0 | O51: =ROUND(CPSX!O51/'4.Doanh thu'!J$11,0) -> 0 | P51: =ROUND(CPSX!P51/'4.Doanh thu'!K$11,0) -> 0 | Q51: =ROUND(CPSX!Q51/'4.Doanh thu'!L$11,0) -> 0 | R51: =ROUND(CPSX!R51/'4.Doanh thu'!M$11,0) -> 0 | S51: =ROUND(CPSX!S51/'4.Doanh thu'!N$11,0) -> 0 | T51: =ROUND(CPSX!T51/'4.Doanh thu'!O$11,0) -> 0 | U51: =ROUND(CPSX!U51/'4.Doanh thu'!P$11,0) -> 0 | V51: =ROUND(CPSX!V51/'4.Doanh thu'!Q$11,0) -> 0 | W51: =AVERAGE(N51:V51) -> 0
B52: 24 | D52: 6277002204 | E52: Chi phi sửa chữa | F52: Repairs and Maintenance Expenses | G52: Chi phí sửa chữa, bảo trì phương tiện vận tải | H52: Phòng Kho vận | I52: Phan bo | N52: =ROUND(CPSX!N52/'4.Doanh thu'!I$11,0) -> 0 | O52: =ROUND(CPSX!O52/'4.Doanh thu'!J$11,0) -> 0 | P52: =ROUND(CPSX!P52/'4.Doanh thu'!K$11,0) -> 0 | Q52: =ROUND(CPSX!Q52/'4.Doanh thu'!L$11,0) -> 0 | R52: =ROUND(CPSX!R52/'4.Doanh thu'!M$11,0) -> 0 | S52: =ROUND(CPSX!S52/'4.Doanh thu'!N$11,0) -> 0 | T52: =ROUND(CPSX!T52/'4.Doanh thu'!O$11,0) -> 0 | U52: =ROUND(CPSX!U52/'4.Doanh thu'!P$11,0) -> 0 | V52: =ROUND(CPSX!V52/'4.Doanh thu'!Q$11,0) -> 0 | W52: =AVERAGE(N52:V52) -> 0
B53: 25 | D53: 6277002301 | E53: Chi phí bảo hiểm tài sản | F53: Insurance Expenses | G53: Chi phí bảo hiểm tài sản | H53: Phòng Kế toán | I53: Phan bo | N53: =ROUND(CPSX!N53/'4.Doanh thu'!I$11,0) -> 0 | O53: =ROUND(CPSX!O53/'4.Doanh thu'!J$11,0) -> 0 | P53: =ROUND(CPSX!P53/'4.Doanh thu'!K$11,0) -> 0 | Q53: =ROUND(CPSX!Q53/'4.Doanh thu'!L$11,0) -> 0 | R53: =ROUND(CPSX!R53/'4.Doanh thu'!M$11,0) -> 0 | S53: =ROUND(CPSX!S53/'4.Doanh thu'!N$11,0) -> 0 | T53: =ROUND(CPSX!T53/'4.Doanh thu'!O$11,0) -> 0 | U53: =ROUND(CPSX!U53/'4.Doanh thu'!P$11,0) -> 0 | V53: =ROUND(CPSX!V53/'4.Doanh thu'!Q$11,0) -> 0 | W53: =AVERAGE(N53:V53) -> 0
B54: 26 | D54: 6273001908 | E54: Phân bổ công cụ dụng cụ | F54: Tools and Equipments | G54: Phân bổ công cụ dụng cụ | H54: Phòng Kế toán | I54: Phan bo | N54: =ROUND(CPSX!N54/'4.Doanh thu'!I$11,0) -> 0 | O54: =ROUND(CPSX!O54/'4.Doanh thu'!J$11,0) -> 0 | P54: =ROUND(CPSX!P54/'4.Doanh thu'!K$11,0) -> 0 | Q54: =ROUND(CPSX!Q54/'4.Doanh thu'!L$11,0) -> 0 | R54: =ROUND(CPSX!R54/'4.Doanh thu'!M$11,0) -> 0 | S54: =ROUND(CPSX!S54/'4.Doanh thu'!N$11,0) -> 0 | T54: =ROUND(CPSX!T54/'4.Doanh thu'!O$11,0) -> 0 | U54: =ROUND(CPSX!U54/'4.Doanh thu'!P$11,0) -> 0 | V54: =ROUND(CPSX!V54/'4.Doanh thu'!Q$11,0) -> 0 | W54: =AVERAGE(N54:V54) -> 0
B55: 27 | D55: 6277003803 | E55: Phí kiểm định kỹ thuật | F55: Calibration,Testing&Quality Control Exp. | G55: Phí kiểm định kỹ thuật | N55: =ROUND(CPSX!N55/'4.Doanh thu'!I$11,0) -> 0 | O55: =ROUND(CPSX!O55/'4.Doanh thu'!J$11,0) -> 0 | P55: =ROUND(CPSX!P55/'4.Doanh thu'!K$11,0) -> 0 | Q55: =ROUND(CPSX!Q55/'4.Doanh thu'!L$11,0) -> 0 | R55: =ROUND(CPSX!R55/'4.Doanh thu'!M$11,0) -> 0 | S55: =ROUND(CPSX!S55/'4.Doanh thu'!N$11,0) -> 0 | T55: =ROUND(CPSX!T55/'4.Doanh thu'!O$11,0) -> 0 | U55: =ROUND(CPSX!U55/'4.Doanh thu'!P$11,0) -> 0 | V55: =ROUND(CPSX!V55/'4.Doanh thu'!Q$11,0) -> 0 | W55: =AVERAGE(N55:V55) -> 0
B56: 28 | E56: Chi phí Khấu hao | F56: Depreciation | G56: Chi phí Khấu hao | H56: Phòng Kế toán | I56: Khau hao | K56: ='PB_TSCD DC'!AF27 -> 0 | L56: ='PB_TSCD DC'!AG27 -> 0 | M56: ='PB_TSCD DC'!AH27 -> 0 | N56: =ROUND(CPSX!N56/'4.Doanh thu'!I$11,0) -> 327 | O56: =ROUND(CPSX!O56/'4.Doanh thu'!J$11,0) -> 327 | P56: =ROUND(CPSX!P56/'4.Doanh thu'!K$11,0) -> 327 | Q56: =ROUND(CPSX!Q56/'4.Doanh thu'!L$11,0) -> 327 | R56: =ROUND(CPSX!R56/'4.Doanh thu'!M$11,0) -> 327 | S56: =ROUND(CPSX!S56/'4.Doanh thu'!N$11,0) -> 327 | T56: =ROUND(CPSX!T56/'4.Doanh thu'!O$11,0) -> 327 | U56: =ROUND(CPSX!U56/'4.Doanh thu'!P$11,0) -> 327 | V56: =ROUND(CPSX!V56/'4.Doanh thu'!Q$11,0) -> 327 | W56: =AVERAGE(N56:V56) -> 327
B58: I+II | E58: Tổng CP_Sản xuất | J58: =J28+#REF! -> #REF! | K58: =SUM(K5,K28) -> 0 | L58: =SUM(L5,L28) -> 0 | M58: =SUM(M5,M28) -> 0 | N58: =SUM(N5,N28) -> 6146 | O58: =SUM(O5,O28) -> 6146 | P58: =SUM(P5,P28) -> 6146 | Q58: =SUM(Q5,Q28) -> 6146 | R58: =SUM(R5,R28) -> 6146 | ... W58: =SUM(W5,W28) -> 6146

Sheet CPBH
B3: I - CHI PHÍ BÁN HÀNG PET | W3: ĐVT: Triệu đồng
B4: STT | C4: Dự phòng | D4: Mã tài khoản (Mã Chi phí_L4) | E4: Tên tài khoản (Cost elements 2) | F4: Chi Phí_L5 (Cost Group 2) | G4: Chi tiết | H4: Phòng ban | I4: Tham chiếu | J4: % CP/DT 2026 | K4: T1 | L4: T2 | M4: T3 | N4: T4 | O4: T5 | P4: T6 | Q4: T7 | R4: T8 | S4: T9 | T4: T10 | U4: T11 | V4: T12 | W4: KH 2026 | Y4: T1 | Z4: T2 | AA4: T3 | AB4: T4 | AC4: T5 | AD4: T6 | AE4: T7 | AF4: T8 | AG4: T9 | AH4: T10 | AI4: T11 | AJ4: T12 | AK4: KQKD 2025 | AM4: KQKD 2024 | AO4: KQKD 2023 | AQ4: +/- 2026 sv 2025 | AR4: +/- %
B5: 1 | D5: 6417003602 | E5: Thuê xe giao hàng | F5: Domestic Freight | G5: Thuê xe vận chuyển bán Chai PET | H5: Phòng Kho vận | I5: Dinh muc | K5: ='Dinh muc'!$G$22*'4.Doanh thu'!F11 -> 0 | L5: ='Dinh muc'!$G$22*'4.Doanh thu'!G11 -> 0 | M5: ='Dinh muc'!$G$22*'4.Doanh thu'!H11 -> 0 | N5: ='Dinh muc'!$G$22*'4.Doanh thu'!I11 -> 58153200 | O5: ='Dinh muc'!$G$22*'4.Doanh thu'!J11 -> 58153200 | P5: ='Dinh muc'!$G$22*'4.Doanh thu'!K11 -> 58153200 | Q5: ='Dinh muc'!$G$22*'4.Doanh thu'!L11 -> 58153200 | R5: ='Dinh muc'!$G$22*'4.Doanh thu'!M11 -> 58153200 | ... V5: ='Dinh muc'!$G$22*'4.Doanh thu'!Q11 -> 58153200 | W5: =SUM(K5:V5) -> 523378800 | Y5: 91100000 | Z5: 139700000 | AA5: 291900000 | AB5: 255100000 | AC5: 287700000 | AD5: 330500000 | AE5: 365500000 | AF5: 358900000 | AG5: 327900000 | AH5: 2.3705173e+08 | AI5: 2.3705173e+08 | AJ5: 2.3705173e+08 | AK5: =SUM(Y5:AJ5) -> 3.1594552e+09 | AM5: 1908089700 | AO5: 1657669600 | AQ5: =IFERROR(W5-AK5,0) -> -2.6360764e+09 | AR5: =IFERROR((W5/AK5)-1,0) -> -0.83434524
B6: 2 | D6: 6417003602 | E6: Thuê xe giao hàng | F6: Domestic Freight | W6: =SUM(K6:V6) -> 0 | AK6: =SUM(Y6:AJ6) -> 0 | AQ6: =IFERROR(W6-AK6,0) -> 0 | AR6: =IFERROR((W6/AK6)-1,0) -> 0
B7: 3 | E7: Cp đội ngũ sale bán hàng: 10% Doanh thu | G7: Cp đội ngũ sale bán hàng: 10% Doanh thu | K7: ='4.Doanh thu'!F27*10% -> 0 | L7: ='4.Doanh thu'!G27*10% -> 0 | M7: ='4.Doanh thu'!H27*10% -> 0 | N7: ='4.Doanh thu'!I27*10% -> 284832000 | O7: ='4.Doanh thu'!J27*10% -> 284832000 | P7: ='4.Doanh thu'!K27*10% -> 284832000 | Q7: ='4.Doanh thu'!L27*10% -> 284832000 | R7: ='4.Doanh thu'!M27*10% -> 284832000 | ... V7: ='4.Doanh thu'!Q27*10% -> 284832000 | W7: =SUM(K7:V7) -> 2563488000 | AQ7: =IFERROR(W7-AK7,0) -> 2563488000 | AR7: =IFERROR((W7/AK7)-1,0) -> 0
B8: 3 | E8: Chi phí chiết khấu bán hàng: 10% doanh thu | G8: Chi phí chiết khấu bán hàng: 10% doanh thu | K8: ='4.Doanh thu'!F27*10% -> 0 | L8: ='4.Doanh thu'!G27*10% -> 0 | M8: ='4.Doanh thu'!H27*10% -> 0 | N8: ='4.Doanh thu'!I27*10% -> 284832000 | O8: ='4.Doanh thu'!J27*10% -> 284832000 | P8: ='4.Doanh thu'!K27*10% -> 284832000 | Q8: ='4.Doanh thu'!L27*10% -> 284832000 | R8: ='4.Doanh thu'!M27*10% -> 284832000 | ... V8: ='4.Doanh thu'!Q27*10% -> 284832000 | W8: =SUM(K8:V8) -> 2563488000 | AQ8: =IFERROR(W8-AK8,0) -> 2563488000 | AR8: =IFERROR((W8/AK8)-1,0) -> 0
B9: 3 | E9: Chi phí hoa hồng bán hàng 5% doanh thu | G9: Chi phí hoa hồng bán hàng 5% doanh thu | K9: ='4.Doanh thu'!F27*5% -> 0 | L9: ='4.Doanh thu'!G27*5% -> 0 | M9: ='4.Doanh thu'!H27*5% -> 0 | N9: ='4.Doanh thu'!I27*5% -> 142416000 | O9: ='4.Doanh thu'!J27*5% -> 142416000 | P9: ='4.Doanh thu'!K27*5% -> 142416000 | Q9: ='4.Doanh thu'!L27*5% -> 142416000 | R9: ='4.Doanh thu'!M27*5% -> 142416000 | ... V9: ='4.Doanh thu'!Q27*5% -> 142416000 | W9: =SUM(K9:V9) -> 1281744000 | AQ9: =IFERROR(W9-AK9,0) -> 1281744000 | AR9: =IFERROR((W9/AK9)-1,0) -> 0
B10: 3 | E10: Cp Maketing: 5% doanh thu | G10: Cp Maketing: 5% doanh thu | K10: ='4.Doanh thu'!F27*5% -> 0 | L10: ='4.Doanh thu'!G27*5% -> 0 | M10: ='4.Doanh thu'!H27*5% -> 0 | N10: ='4.Doanh thu'!I27*5% -> 142416000 | O10: ='4.Doanh thu'!J27*5% -> 142416000 | P10: ='4.Doanh thu'!K27*5% -> 142416000 | Q10: ='4.Doanh thu'!L27*5% -> 142416000 | R10: ='4.Doanh thu'!M27*5% -> 142416000 | ... V10: ='4.Doanh thu'!Q27*5% -> 142416000 | W10: =SUM(K10:V10) -> 1281744000 | AQ10: =IFERROR(W10-AK10,0) -> 1281744000 | AR10: =IFERROR((W10/AK10)-1,0) -> 0
B11: 3 | W11: =SUM(K11:V11) -> 0 | AQ11: =IFERROR(W11-AK11,0) -> 0 | AR11: =IFERROR((W11/AK11)-1,0) -> 0
B12: 3 | W12: =SUM(K12:V12) -> 0 | AQ12: =IFERROR(W12-AK12,0) -> 0 | AR12: =IFERROR((W12/AK12)-1,0) -> 0
G13: Tổng CP_Bán hàng | J13: =SUM(J5:J6) -> 0 | K13: =SUM(K5:K12) -> 0 | L13: =SUM(L5:L12) -> 0 | M13: =SUM(M5:M12) -> 0 | N13: =SUM(N5:N12) -> 912649200 | O13: =SUM(O5:O12) -> 912649200 | P13: =SUM(P5:P12) -> 912649200 | Q13: =SUM(Q5:Q12) -> 912649200 | R13: =SUM(R5:R12) -> 912649200 | ... W13: =SUM(W5:W12) -> 8213842800 | Y13: =SUM(Y5:Y12) -> 91100000 | Z13: =SUM(Z5:Z12) -> 139700000 | AA13: =SUM(AA5:AA12) -> 291900000 | AB13: =SUM(AB5:AB12) -> 255100000 | AC13: =SUM(AC5:AC12) -> 287700000 | AD13: =SUM(AD5:AD12) -> 330500000 | AE13: =SUM(AE5:AE12) -> 365500000 | AF13: =SUM(AF5:AF12) -> 358900000 | ... AK13: =SUM(AK5:AK12) -> 3.1594552e+09 | AM13: =SUM(AM5:AM12) -> 1908089700 | AO13: =SUM(AO5:AO12) -> 1657669600 | AQ13: =IFERROR(W13-AK13,0) -> 5054387600 | AR13: =IFERROR((W13/AK13)-1,0) -> 1.5997656
B15: II - CHI PHÍ BÁN HÀNG HD | W15: ĐVT: Triệu đồng
B16: STT | C16: Dự phòng | D16: Mã tài khoản (Mã Chi phí_L4) | E16: Tên tài khoản (Cost elements 2) | F16: Chi Phí_L5 (Cost Group 2) | G16: Chi tiết | H16: Phòng ban | I16: Tham chiếu | J16: % CP/DT 2026 | K16: T1 | L16: T2 | M16: T3 | N16: T4 | O16: T5 | P16: T6 | Q16: T7 | R16: T8 | S16: T9 | T16: T10 | U16: T11 | V16: T12 | W16: Mục tiêu 2026 | Y16: T1 | Z16: T2 | AA16: T3 | AB16: T4 | AC16: T5 | AD16: T6 | AE16: T7 | AF16: T8 | AG16: T9 | AH16: T10 | AI16: T11 | AJ16: T12 | AK16: KQKD 2025 | AM16: KQKD 2024 | AO16: KQKD 2023 | AQ16: +/- 2026 sv 2025 | AR16: +/- %
B17: 1 | D17: 6417003602 | E17: Thuê xe giao hàng | F17: Domestic Freight | G17: Thuê xe vận chuyển bán vảy HD | H17: Phòng Kho vận | I17: Dinh muc | AK17: =SUM(Y17:AJ17) -> 0 | AQ17: =IFERROR(W17-AK17,0) -> 0 | AR17: =IFERROR((W17/AK17)-1,0) -> 0
AK18: =SUM(Y18:AJ18) -> 0 | AQ18: =IFERROR(W18-AK18,0) -> 0 | AR18: =IFERROR((W18/AK18)-1,0) -> 0
G19: Tổng CP_Bán hàng | J19: =SUM(J17:J18) -> 0 | K19: =SUM(K17:K18) -> 0 | L19: =SUM(L17:L18) -> 0 | M19: =SUM(M17:M18) -> 0 | N19: =SUM(N17:N18) -> 0 | O19: =SUM(O17:O18) -> 0 | P19: =SUM(P17:P18) -> 0 | Q19: =SUM(Q17:Q18) -> 0 | ... W19: =SUM(W17:W18) -> 0 | Y19: =SUM(Y17:Y18) -> 0 | Z19: =SUM(Z17:Z18) -> 0 | AA19: =SUM(AA17:AA18) -> 0 | AB19: =SUM(AB17:AB18) -> 0 | AC19: =SUM(AC17:AC18) -> 0 | AD19: =SUM(AD17:AD18) -> 0 | AE19: =SUM(AE17:AE18) -> 0 | AF19: =SUM(AF17:AF18) -> 0 | ... AK19: =SUM(AK17:AK18) -> 0 | AM19: =SUM(AM17:AM18) -> 0 | AO19: =SUM(AO17:AO18) -> 0 | AQ19: =IFERROR(W19-AK19,0) -> 0 | AR19: =IFERROR((W19/AK19)-1,0) -> 0

Sheet CPBH Kg
B3: I - CHI PHÍ BÁN HÀNG PET | W3: ĐVT: đồng/kg
B4: STT | C4: Dự phòng | D4: Mã tài khoản (Mã Chi phí_L4) | E4: Tên tài khoản (Cost elements 2) | F4: Chi Phí_L5 (Cost Group 2) | G4: Chi tiết | H4: Phòng ban | I4: Tham chiếu | J4: % CP/DT 2026 | K4: T1 | L4: T2 | M4: T3 | N4: T4 | O4: T5 | P4: T6 | Q4: T7 | R4: T8 | S4: T9 | T4: T10 | U4: T11 | V4: T12 | W4: KH 2026 | Y4: T1 | Z4: T2 | AA4: T3 | AB4: T4 | AC4: T5 | AD4: T6 | AE4: T7 | AF4: T8 | AG4: T9 | AH4: T10 | AI4: T11 | AJ4: T12 | AK4: KQKD 2025 | AM4: KQKD 2024 | AO4: KQKD 2023 | AQ4: +/- 2026 sv 2025 | AR4: +/- %
B5: 1 | D5: 6417003602 | E5: Thuê xe giao hàng | F5: Domestic Freight | G5: Thuê xe vận chuyển bán Chai PET | H5: Phòng Kho vận | I5: Dinh muc | K5: ='Dinh muc'!$G$22*'4.Doanh thu'!F11 -> 0 | L5: ='Dinh muc'!$G$22*'4.Doanh thu'!G11 -> 0 | M5: ='Dinh muc'!$G$22*'4.Doanh thu'!H11 -> 0 | N5: =CPBH!N5/'4.Doanh thu'!I$11 -> 408.33333 | O5: =CPBH!O5/'4.Doanh thu'!J$11 -> 408.33333 | P5: =CPBH!P5/'4.Doanh thu'!K$11 -> 408.33333 | Q5: =CPBH!Q5/'4.Doanh thu'!L$11 -> 408.33333 | R5: =CPBH!R5/'4.Doanh thu'!M$11 -> 408.33333 | S5: =CPBH!S5/'4.Doanh thu'!N$11 -> 408.33333 | T5: =CPBH!T5/'4.Doanh thu'!O$11 -> 408.33333 | U5: =CPBH!U5/'4.Doanh thu'!P$11 -> 408.33333 | V5: =CPBH!V5/'4.Doanh thu'!Q$11 -> 408.33333 | W5: =AVERAGE(N5:V5) -> 408.33333 | Y5: 91100000 | Z5: 139700000 | AA5: 291900000 | AB5: 255100000 | AC5: 287700000 | AD5: 330500000 | AE5: 365500000 | AF5: 358900000 | AG5: 327900000 | AH5: 2.3705173e+08 | AI5: 2.3705173e+08 | AJ5: 2.3705173e+08 | AK5: =SUM(Y5:AJ5) -> 3.1594552e+09 | AM5: 1908089700 | AO5: 1657669600 | AQ5: =IFERROR(W5-AK5,0) -> -3.1594548e+09 | AR5: =IFERROR((W5/AK5)-1,0) -> -0.99999987
B6: 3 | E6: Cp đội ngũ sale bán hàng: 10% Doanh thu | G6: Cp đội ngũ sale bán hàng: 10% Doanh thu | K6: ='4.Doanh thu'!F27*10% -> 0 | L6: ='4.Doanh thu'!G27*10% -> 0 | M6: ='4.Doanh thu'!H27*10% -> 0 | N6: =CPBH!N7/'4.Doanh thu'!I$11 -> 2000 | O6: =CPBH!O7/'4.Doanh thu'!J$11 -> 2000 | P6: =CPBH!P7/'4.Doanh thu'!K$11 -> 2000 | Q6: =CPBH!Q7/'4.Doanh thu'!L$11 -> 2000 | R6: =CPBH!R7/'4.Doanh thu'!M$11 -> 2000 | S6: =CPBH!S7/'4.Doanh thu'!N$11 -> 2000 | T6: =CPBH!T7/'4.Doanh thu'!O$11 -> 2000 | U6: =CPBH!U7/'4.Doanh thu'!P$11 -> 2000 | V6: =CPBH!V7/'4.Doanh thu'!Q$11 -> 2000 | W6: =AVERAGE(N6:V6) -> 2000 | AQ6: =IFERROR(W6-AK6,0) -> 2000 | AR6: =IFERROR((W6/AK6)-1,0) -> 0
B7: 3 | E7: Chi phí chiết khấu bán hàng: 10% doanh thu | G7: Chi phí chiết khấu bán hàng: 10% doanh thu | K7: ='4.Doanh thu'!F27*10% -> 0 | L7: ='4.Doanh thu'!G27*10% -> 0 | M7: ='4.Doanh thu'!H27*10% -> 0 | N7: =CPBH!N8/'4.Doanh thu'!I$11 -> 2000 | O7: =CPBH!O8/'4.Doanh thu'!J$11 -> 2000 | P7: =CPBH!P8/'4.Doanh thu'!K$11 -> 2000 | Q7: =CPBH!Q8/'4.Doanh thu'!L$11 -> 2000 | R7: =CPBH!R8/'4.Doanh thu'!M$11 -> 2000 | S7: =CPBH!S8/'4.Doanh thu'!N$11 -> 2000 | T7: =CPBH!T8/'4.Doanh thu'!O$11 -> 2000 | U7: =CPBH!U8/'4.Doanh thu'!P$11 -> 2000 | V7: =CPBH!V8/'4.Doanh thu'!Q$11 -> 2000 | W7: =AVERAGE(N7:V7) -> 2000 | AQ7: =IFERROR(W7-AK7,0) -> 2000 | AR7: =IFERROR((W7/AK7)-1,0) -> 0
B8: 3 | E8: Chi phí hoa hồng bán hàng 5% doanh thu | G8: Chi phí hoa hồng bán hàng 5% doanh thu | K8: ='4.Doanh thu'!F27*5% -> 0 | L8: ='4.Doanh thu'!G27*5% -> 0 | M8: ='4.Doanh thu'!H27*5% -> 0 | N8: =CPBH!N9/'4.Doanh thu'!I$11 -> 1000 | O8: =CPBH!O9/'4.Doanh thu'!J$11 -> 1000 | P8: =CPBH!P9/'4.Doanh thu'!K$11 -> 1000 | Q8: =CPBH!Q9/'4.Doanh thu'!L$11 -> 1000 | R8: =CPBH!R9/'4.Doanh thu'!M$11 -> 1000 | S8: =CPBH!S9/'4.Doanh thu'!N$11 -> 1000 | T8: =CPBH!T9/'4.Doanh thu'!O$11 -> 1000 | U8: =CPBH!U9/'4.Doanh thu'!P$11 -> 1000 | V8: =CPBH!V9/'4.Doanh thu'!Q$11 -> 1000 | W8: =AVERAGE(N8:V8) -> 1000 | AQ8: =IFERROR(W8-AK8,0) -> 1000 | AR8: =IFERROR((W8/AK8)-1,0) -> 0
B9: 3 | E9: Cp Maketing: 5% doanh thu | G9: Cp Maketing: 5% doanh thu | K9: ='4.Doanh thu'!F27*5% -> 0 | L9: ='4.Doanh thu'!G27*5% -> 0 | M9: ='4.Doanh thu'!H27*5% -> 0 | N9: =CPBH!N10/'4.Doanh thu'!I$11 -> 1000 | O9: =CPBH!O10/'4.Doanh thu'!J$11 -> 1000 | P9: =CPBH!P10/'4.Doanh thu'!K$11 -> 1000 | Q9: =CPBH!Q10/'4.Doanh thu'!L$11 -> 1000 | R9: =CPBH!R10/'4.Doanh thu'!M$11 -> 1000 | S9: =CPBH!S10/'4.Doanh thu'!N$11 -> 1000 | T9: =CPBH!T10/'4.Doanh thu'!O$11 -> 1000 | U9: =CPBH!U10/'4.Doanh thu'!P$11 -> 1000 | V9: =CPBH!V10/'4.Doanh thu'!Q$11 -> 1000 | W9: =AVERAGE(N9:V9) -> 1000 | AQ9: =IFERROR(W9-AK9,0) -> 1000 | AR9: =IFERROR((W9/AK9)-1,0) -> 0
B10: 3 | N10: =CPBH!N11/'4.Doanh thu'!I$11 -> 0 | O10: =CPBH!O11/'4.Doanh thu'!J$11 -> 0 | P10: =CPBH!P11/'4.Doanh thu'!K$11 -> 0 | Q10: =CPBH!Q11/'4.Doanh thu'!L$11 -> 0 | R10: =CPBH!R11/'4.Doanh thu'!M$11 -> 0 | S10: =CPBH!S11/'4.Doanh thu'!N$11 -> 0 | T10: =CPBH!T11/'4.Doanh thu'!O$11 -> 0 | U10: =CPBH!U11/'4.Doanh thu'!P$11 -> 0 | V10: =CPBH!V11/'4.Doanh thu'!Q$11 -> 0 | W10: =SUM(K10:V10) -> 0 | AQ10: =IFERROR(W10-AK10,0) -> 0 | AR10: =IFERROR((W10/AK10)-1,0) -> 0
B11: 3 | W11: =SUM(K11:V11) -> 0 | AQ11: =IFERROR(W11-AK11,0) -> 0 | AR11: =IFERROR((W11/AK11)-1,0) -> 0
G12: Tổng CP_Bán hàng | J12: =SUM(J5:J5) -> 0 | K12: =SUM(K5:K11) -> 0 | L12: =SUM(L5:L11) -> 0 | M12: =SUM(M5:M11) -> 0 | N12: =SUM(N5:N11) -> 6408.3333 | O12: =SUM(O5:O11) -> 6408.3333 | P12: =SUM(P5:P11) -> 6408.3333 | Q12: =SUM(Q5:Q11) -> 6408.3333 | R12: =SUM(R5:R11) -> 6408.3333 | ... W12: =SUM(W5:W11) -> 6408.3333 | Y12: =SUM(Y5:Y11) -> 91100000 | Z12: =SUM(Z5:Z11) -> 139700000 | AA12: =SUM(AA5:AA11) -> 291900000 | AB12: =SUM(AB5:AB11) -> 255100000 | AC12: =SUM(AC5:AC11) -> 287700000 | AD12: =SUM(AD5:AD11) -> 330500000 | AE12: =SUM(AE5:AE11) -> 365500000 | AF12: =SUM(AF5:AF11) -> 358900000 | ... AK12: =SUM(AK5:AK11) -> 3.1594552e+09 | AM12: =SUM(AM5:AM11) -> 1908089700 | AO12: =SUM(AO5:AO11) -> 1657669600 | AQ12: =IFERROR(W12-AK12,0) -> -3.1594488e+09 | AR12: =IFERROR((W12/AK12)-1,0) -> -0.99999797
B14: II - CHI PHÍ BÁN HÀNG HD | W14: ĐVT: Triệu đồng
B15: STT | C15: Dự phòng | D15: Mã tài khoản (Mã Chi phí_L4) | E15: Tên tài khoản (Cost elements 2) | F15: Chi Phí_L5 (Cost Group 2) | G15: Chi tiết | H15: Phòng ban | I15: Tham chiếu | J15: % CP/DT 2026 | K15: T1 | L15: T2 | M15: T3 | N15: T4 | O15: T5 | P15: T6 | Q15: T7 | R15: T8 | S15: T9 | T15: T10 | U15: T11 | V15: T12 | W15: Mục tiêu 2026 | Y15: T1 | Z15: T2 | AA15: T3 | AB15: T4 | AC15: T5 | AD15: T6 | AE15: T7 | AF15: T8 | AG15: T9 | AH15: T10 | AI15: T11 | AJ15: T12 | AK15: KQKD 2025 | AM15: KQKD 2024 | AO15: KQKD 2023 | AQ15: +/- 2026 sv 2025 | AR15: +/- %
B16: 1 | D16: 6417003602 | E16: Thuê xe giao hàng | F16: Domestic Freight | G16: Thuê xe vận chuyển bán vảy HD | H16: Phòng Kho vận | I16: Dinh muc | AK16: =SUM(Y16:AJ16) -> 0 | AQ16: =IFERROR(W16-AK16,0) -> 0 | AR16: =IFERROR((W16/AK16)-1,0) -> 0
AK17: =SUM(Y17:AJ17) -> 0 | AQ17: =IFERROR(W17-AK17,0) -> 0 | AR17: =IFERROR((W17/AK17)-1,0) -> 0
G18: Tổng CP_Bán hàng | J18: =SUM(J16:J17) -> 0 | K18: =SUM(K16:K17) -> 0 | L18: =SUM(L16:L17) -> 0 | M18: =SUM(M16:M17) -> 0 | N18: =SUM(N16:N17) -> 0 | O18: =SUM(O16:O17) -> 0 | P18: =SUM(P16:P17) -> 0 | Q18: =SUM(Q16:Q17) -> 0 | ... W18: =SUM(W16:W17) -> 0 | Y18: =SUM(Y16:Y17) -> 0 | Z18: =SUM(Z16:Z17) -> 0 | AA18: =SUM(AA16:AA17) -> 0 | AB18: =SUM(AB16:AB17) -> 0 | AC18: =SUM(AC16:AC17) -> 0 | AD18: =SUM(AD16:AD17) -> 0 | AE18: =SUM(AE16:AE17) -> 0 | AF18: =SUM(AF16:AF17) -> 0 | ... AK18: =SUM(AK16:AK17) -> 0 | AM18: =SUM(AM16:AM17) -> 0 | AO18: =SUM(AO16:AO17) -> 0 | AQ18: =IFERROR(W18-AK18,0) -> 0 | AR18: =IFERROR((W18/AK18)-1,0) -> 0

Sheet 4.Doanh thu
B3: DOANH THU
B4: I - DOANH THU CHAI PET
B5: 1. Sản lượng bán dây đai
B6: STT | C6: Thành phẩm (chai sau phân loại) | D6: ĐVT | E6: Tỷ lệ | F6: T1 | G6: T2 | H6: T3 | I6: T4 | J6: T5 | K6: T6 | L6: T7 | M6: T8 | N6: T9 | O6: T10 | P6: T11 | Q6: T12 | R6: KH 2026 | U6: +/- 2026 sv 2025 | V6: +/- %
B7: 1 | C7: Dây đai rPET RPE1610 | D7: Tấn | F7: ='3.Thanh pham'!F14 -> 0 | G7: ='3.Thanh pham'!G14 -> 0 | H7: ='3.Thanh pham'!H14 -> 0 | I7: ='3.Thanh pham'!I14 -> 142416 | J7: ='3.Thanh pham'!J14 -> 142416 | K7: ='3.Thanh pham'!K14 -> 142416 | L7: ='3.Thanh pham'!L14 -> 142416 | M7: ='3.Thanh pham'!M14 -> 142416 | ... Q7: ='3.Thanh pham'!Q14 -> 142416 | R7: =SUM(F7:Q7) -> 1281744 | U7: =IFERROR(R7-#REF!,0) -> 0 | V7: =IFERROR((R7/#REF!)-1,0) -> 0
B8: 2 | C8: Chai PET B1 Không Phân Loại | D8: Tấn | F8: ='3.Thanh pham'!F15 -> 0 | G8: ='3.Thanh pham'!G15 -> 0 | H8: ='3.Thanh pham'!H15 -> 0 | I8: ='3.Thanh pham'!I15 -> 0 | J8: ='3.Thanh pham'!J15 -> 0 | K8: ='3.Thanh pham'!K15 -> 0 | L8: ='3.Thanh pham'!L15 -> 0 | M8: ='3.Thanh pham'!M15 -> 0 | ... Q8: ='3.Thanh pham'!Q15 -> 0 | R8: =SUM(F8:Q8) -> 0 | U8: =IFERROR(R8-#REF!,0) -> 0 | V8: =IFERROR((R8/#REF!)-1,0) -> 0
B9: 3 | C9: Chai PET B1.3 | D9: Tấn | F9: ='3.Thanh pham'!F16 -> 0 | G9: ='3.Thanh pham'!G16 -> 0 | H9: ='3.Thanh pham'!H16 -> 0 | I9: ='3.Thanh pham'!I16 -> 0 | J9: ='3.Thanh pham'!J16 -> 0 | K9: ='3.Thanh pham'!K16 -> 0 | L9: ='3.Thanh pham'!L16 -> 0 | M9: ='3.Thanh pham'!M16 -> 0 | ... Q9: ='3.Thanh pham'!Q16 -> 0 | R9: =SUM(F9:Q9) -> 0 | U9: =IFERROR(R9-#REF!,0) -> 0 | V9: =IFERROR((R9/#REF!)-1,0) -> 0
B10: 4 | C10: Chai PET B2.1 | D10: Tấn | F10: ='3.Thanh pham'!F17 -> 0 | G10: ='3.Thanh pham'!G17 -> 0 | H10: ='3.Thanh pham'!H17 -> 0 | I10: ='3.Thanh pham'!I17 -> 0 | J10: ='3.Thanh pham'!J17 -> 0 | K10: ='3.Thanh pham'!K17 -> 0 | L10: ='3.Thanh pham'!L17 -> 0 | M10: ='3.Thanh pham'!M17 -> 0 | ... Q10: ='3.Thanh pham'!Q17 -> 0 | R10: =SUM(F10:Q10) -> 0 | U10: =IFERROR(R10-#REF!,0) -> 0 | V10: =IFERROR((R10/#REF!)-1,0) -> 0
C11: TỔNG: | E11: =SUM(E7:E10) -> 0 | F11: =SUM(F7:F10) -> 0 | G11: =SUM(G7:G10) -> 0 | H11: =SUM(H7:H10) -> 0 | I11: =SUM(I7:I10) -> 142416 | J11: =SUM(J7:J10) -> 142416 | K11: =SUM(K7:K10) -> 142416 | L11: =SUM(L7:L10) -> 142416 | ... Q11: =SUM(Q7:Q10) -> 142416 | R11: =SUM(F11:Q11) -> 1281744 | U11: =IFERROR(R11-#REF!,0) -> 0 | V11: =IFERROR((R11/#REF!)-1,0) -> 0
B13: 2. Giá bán
B14: STT | C14: Thành phẩm (chai sau phân loại) | D14: ĐVT | E14: Tỷ lệ | F14: T1 | G14: T2 | H14: T3 | I14: T4 | J14: T5 | K14: T6 | L14: T7 | M14: T8 | N14: T9 | O14: T10 | P14: T11 | Q14: T12 | R14: KH 2026 | U14: +/- 2026 sv 2025 | V14: +/- %
B15: 1 | C15: Dây đai rPET RPE1610 (Giá bán B&B: Ck 10%) | D15: Đồng/kg | I15: 20000 | J15: 20000 | K15: 20000 | L15: 20000 | M15: 20000 | N15: 20000 | O15: 20000 | P15: 20000 | Q15: 20000 | R15: =AVERAGE(F15:Q15) -> 20000 | U15: =IFERROR(R15-#REF!,0) -> 0 | V15: =IFERROR((R15/#REF!)-1,0) -> 0
B16: 2 | D16: Đồng/kg | U16: =IFERROR(R16-#REF!,0) -> 0 | V16: =IFERROR((R16/#REF!)-1,0) -> 0
B17: 3 | D17: Đồng/kg | U17: =IFERROR(R17-#REF!,0) -> 0 | V17: =IFERROR((R17/#REF!)-1,0) -> 0
B18: 4 | D18: Đồng/kg | U18: =IFERROR(R18-#REF!,0) -> 0 | V18: =IFERROR((R18/#REF!)-1,0) -> 0
C19: Giá bán Trung bình | F19: =F27/F11 -> #DIV/0! | G19: =G27/G11 -> #DIV/0! | H19: =H27/H11 -> #DIV/0! | I19: =I27/I11 -> 20000 | J19: =J27/J11 -> 20000 | K19: =K27/K11 -> 20000 | L19: =L27/L11 -> 20000 | M19: =M27/M11 -> 20000 | ... Q19: =Q27/Q11 -> 20000 | U19: =IFERROR(R19-#REF!,0) -> 0 | V19: =IFERROR((R19/#REF!)-1,0) -> 0
B21: 3. Doanh thu chai
B22: STT | C22: Thành phẩm (chai sau phân loại) | D22: ĐVT | E22: Tỷ lệ | F22: T1 | G22: T2 | H22: T3 | I22: T4 | J22: T5 | K22: T6 | L22: T7 | M22: T8 | N22: T9 | O22: T10 | P22: T11 | Q22: T12 | R22: KH 2026 | U22: +/- 2026 sv 2025 | V22: +/- %
B23: 1 | C23: Dây đai rPET RPE1610 | D23: Triệu đ | F23: =F7*F15 -> 0 | G23: =G7*G15 -> 0 | H23: =H7*H15 -> 0 | I23: =I7*I15 -> 2848320000 | J23: =J7*J15 -> 2848320000 | K23: =K7*K15 -> 2848320000 | L23: =L7*L15 -> 2848320000 | M23: =M7*M15 -> 2848320000 | ... Q23: =Q7*Q15 -> 2848320000 | R23: =SUM(F23:Q23) -> 25634880000 | U23: =IFERROR(R23-#REF!,0) -> 0 | V23: =IFERROR((R23/#REF!)-1,0) -> 0
B24: 2 | D24: Triệu đ | F24: =F8*F16 -> 0 | G24: =G8*G16 -> 0 | H24: =H8*H16 -> 0 | I24: =I8*I16 -> 0 | J24: =J8*J16 -> 0 | K24: =K8*K16 -> 0 | L24: =L8*L16 -> 0 | M24: =M8*M16 -> 0 | ... Q24: =Q8*Q16 -> 0 | R24: =SUM(F24:Q24) -> 0 | U24: =IFERROR(R24-#REF!,0) -> 0 | V24: =IFERROR((R24/#REF!)-1,0) -> 0
B25: 3 | D25: Triệu đ | F25: =F9*F17 -> 0 | G25: =G9*G17 -> 0 | H25: =H9*H17 -> 0 | I25: =I9*I17 -> 0 | J25: =J9*J17 -> 0 | K25: =K9*K17 -> 0 | L25: =L9*L17 -> 0 | M25: =M9*M17 -> 0 | ... Q25: =Q9*Q17 -> 0 | R25: =SUM(F25:Q25) -> 0 | U25: =IFERROR(R25-#REF!,0) -> 0 | V25: =IFERROR((R25/#REF!)-1,0) -> 0
B26: 4 | D26: Triệu đ | F26: =F10*F18 -> 0 | G26: =G10*G18 -> 0 | H26: =H10*H18 -> 0 | I26: =I10*I18 -> 0 | J26: =J10*J18 -> 0 | K26: =K10*K18 -> 0 | L26: =L10*L18 -> 0 | M26: =M10*M18 -> 0 | ... Q26: =Q10*Q18 -> 0 | R26: =SUM(F26:Q26) -> 0 | U26: =IFERROR(R26-#REF!,0) -> 0 | V26: =IFERROR((R26/#REF!)-1,0) -> 0
C27: TỔNG: | E27: =SUM(E23:E26) -> 0 | F27: =SUM(F23:F26) -> 0 | G27: =SUM(G23:G26) -> 0 | H27: =SUM(H23:H26) -> 0 | I27: =SUM(I23:I26) -> 2848320000 | J27: =SUM(J23:J26) -> 2848320000 | K27: =SUM(K23:K26) -> 2848320000 | L27: =SUM(L23:L26) -> 2848320000 | ... Q27: =SUM(Q23:Q26) -> 2848320000 | R27: =SUM(F27:Q27) -> 25634880000 | U27: =IFERROR(R27-#REF!,0) -> 0 | V27: =IFERROR((R27/#REF!)-1,0) -> 0

Sheet 1.NVL
B1: Logo CTY
B3: NHU CẦU MUA NGUYÊN VẬT LIỆU CHAI
B4: 1. Số lượng | H4: =SUM(H12:H13)/1000 -> 0 | I4: =SUM(I12:I13)/1000 -> 0 | J4: =SUM(J12:J13)/1000 -> 0 | K4: =SUM(K12:K13)/1000 -> 165.6 | L4: =SUM(L12:L13)/1000 -> 165.6 | M4: =SUM(M12:M13)/1000 -> 165.6 | N4: =SUM(N12:N13)/1000 -> 165.6 | O4: =SUM(O12:O13)/1000 -> 165.6 | ... S4: =SUM(S12:S13)/1000 -> 165.6
B5: STT | C5: Loại chai nguyên liệu | D5: ĐVT | E5: Thực tế năm 2023 | F5: Thực tế năm 2024 | G5: KQKD 2025 | H5: T1 | I5: T2 | J5: T3 | K5: T4 | L5: T5 | M5: T6 | N5: T7 | O5: T8 | P5: T9 | Q5: T10 | R5: T11 | S5: T12 | T5: KH 2026
B6: i. Tỷ lệ chai
B7: 1 | C7: Vảy PET Dây Đai Mixed | D7: % | G7: =G12/$G$14 -> 0.24307792 | H7: 1 | I7: 1 | J7: 1 | K7: 1 | L7: 1 | M7: 1 | N7: 1 | O7: 1 | P7: 1 | Q7: 1 | R7: 1 | S7: 1 | T7: 1
B8: 3 | C8: Hạt màu | D8: % | G8: =#REF!/$G$14 -> #REF!
C9: Tổng: | E9: =E7+#REF!+E8 -> #REF! | F9: =F7+#REF!+F8 -> #REF! | G9: =G7+#REF!+G8 -> #REF! | H9: 1 | I9: 1 | J9: 1 | K9: 1 | L9: 1 | M9: 1 | N9: 1 | O9: 1 | P9: 1 | Q9: 1 | R9: 1 | S9: 1 | T9: 1
B11: ii Số lượng chai
B12: 1 | C12: Vảy PET Dây Đai Mixed | D12: Tấn | G12: 2584077 | K12: =300*24*23 -> 165600 | L12: =300*24*23 -> 165600 | M12: =300*24*23 -> 165600 | N12: =300*24*23 -> 165600 | O12: =300*24*23 -> 165600 | P12: =300*24*23 -> 165600 | Q12: =300*24*23 -> 165600 | R12: =300*24*23 -> 165600 | S12: =300*24*23 -> 165600 | T12: =SUM(H12:S12) -> 1490400
B13: 2 | D13: Tấn | G13: 5699155 | T13: =SUM(H13:S13) -> 0
C14: Tổng: | D14: Tấn | G14: 10630653 | K14: =SUM(K12:K13) -> 165600 | L14: =SUM(L12:L13) -> 165600 | M14: =SUM(M12:M13) -> 165600 | N14: =SUM(N12:N13) -> 165600 | O14: =SUM(O12:O13) -> 165600 | P14: =SUM(P12:P13) -> 165600 | Q14: =SUM(Q12:Q13) -> 165600 | R14: =SUM(R12:R13) -> 165600 | S14: =SUM(S12:S13) -> 165600 | T14: =SUM(H14:S14) -> 1490400 | U14: <= Nhập sản lượng
H15: =H14/1000 -> 0 | I15: =I14/1000 -> 0 | J15: =J14/1000 -> 0 | K15: =K14/1000 -> 165.6 | L15: =L14/1000 -> 165.6 | M15: =M14/1000 -> 165.6 | N15: =N14/1000 -> 165.6 | O15: =O14/1000 -> 165.6 | ... S15: =S14/1000 -> 165.6
B16: 2. Giá mua
B17: STT | C17: Loại chai nguyên liệu | D17: ĐVT | E17: Thực tế năm 2023 | F17: Thực tế năm 2024 | G17: KQKD 2025 | H17: T1 | I17: T2 | J17: T3 | K17: T4 | L17: T5 | M17: T6 | N17: T7 | O17: T8 | P17: T9 | Q17: T10 | R17: T11 | S17: T12 | T17: KH 2026
B18: 1 | C18: Vảy PET Dây Đai Mixed | D18: Đồng/kg | H18: =SUM(H19:H20) -> 0 | I18: =SUM(I19:I20) -> 0 | J18: =SUM(J19:J20) -> 0 | K18: =SUM(K19:K20) -> 13408.333 | L18: =SUM(L19:L20) -> 13408.333 | M18: =SUM(M19:M20) -> 13408.333 | N18: =SUM(N19:N20) -> 13408.333 | O18: =SUM(O19:O20) -> 13408.333 | ... S18: =SUM(S19:S20) -> 13408.333 | T18: =T19+T20 -> 13306.25
B19: a | C19: Vảy PET Dây Đai Mixed | K19: 13000 | L19: 13000 | M19: 13000 | N19: 13000 | O19: 13000 | P19: 13000 | Q19: 13000 | R19: 13000 | S19: 13000 | T19: =AVERAGE(H19:S19) -> 13000
B20: b | C20: Chi phí mua (các chính sách mua hàng) | H20: 0 | I20: 0 | J20: 0 | K20: =4900000/12000 -> 408.33333 | L20: =4900000/12000 -> 408.33333 | M20: =4900000/12000 -> 408.33333 | N20: =4900000/12000 -> 408.33333 | O20: =4900000/12000 -> 408.33333 | P20: =4900000/12000 -> 408.33333 | Q20: =4900000/12000 -> 408.33333 | R20: =4900000/12000 -> 408.33333 | S20: =4900000/12000 -> 408.33333 | T20: =AVERAGE(H20:S20) -> 306.25
C21: Giá mua bình quân | D21: Đồng/kg | K21: =K27/K14 -> 13408.333 | L21: =L27/L14 -> 13408.333 | M21: =M27/M14 -> 13408.333 | N21: =N27/N14 -> 13408.333 | O21: =O27/O14 -> 13408.333 | P21: =P27/P14 -> 13408.333 | Q21: =Q27/Q14 -> 13408.333 | R21: =R27/R14 -> 13408.333 | S21: =S27/S14 -> 13408.333
B23: 3. Tổng giá trị mua
B24: STT | C24: Loại chai nguyên liệu | D24: ĐVT | E24: Thực tế năm 2023 | F24: Thực tế năm 2024 | G24: KQKD 2025 | H24: T1 | I24: T2 | J24: T3 | K24: T4 | L24: T5 | M24: T6 | N24: T7 | O24: T8 | P24: T9 | Q24: T10 | R24: T11 | S24: T12 | T24: KH 2026
B25: 1 | C25: Vảy PET Dây Đai Mixed | D25: Triệu đ | H25: =H$12*H$18 -> 0 | I25: =I$12*I$18 -> 0 | J25: =J$12*J$18 -> 0 | K25: =K$12*K$18 -> 2220420000 | L25: =L$12*L$18 -> 2220420000 | M25: =M$12*M$18 -> 2220420000 | N25: =N$12*N$18 -> 2220420000 | O25: =O$12*O$18 -> 2220420000 | ... S25: =S$12*S$18 -> 2220420000 | T25: =SUM(H25:S25) -> 19983780000
T26: =SUM(H26:S26) -> 0
C27: Tổng: | D27: Triệu đ | E27: =SUM(E25:E26) -> 0 | F27: =SUM(F25:F26) -> 0 | G27: =SUM(G25:G26) -> 0 | H27: =SUM(H25:H26) -> 0 | I27: =SUM(I25:I26) -> 0 | J27: =SUM(J25:J26) -> 0 | K27: =SUM(K25:K26) -> 2220420000 | L27: =SUM(L25:L26) -> 2220420000 | ... S27: =SUM(S25:S26) -> 2220420000 | T27: =SUM(H27:S27) -> 19983780000
B29: 4. Hiệu suất máy (1ca 12giờ x 2ca 1 ngày x 30 ngày 1 tháng)
B30: STT | C30: Loại chai nguyên liệu | D30: ĐVT | E30: Thực tế năm 2023 | F30: Thực tế năm 2024 | G30: KQKD 2025 | H30: T1 | I30: T2 | J30: T3 | K30: T4 | L30: T5 | M30: T6 | N30: T7 | O30: T8 | P30: T9 | Q30: T10 | R30: T11 | S30: T12 | T30: KH 2026
B31: 1 | C31: Tổng sản lượng chai mua vào | D31: Tấn | H31: =H14 -> 0 | I31: =I14 -> 0 | J31: =J14 -> 0 | K31: =K14 -> 165600 | L31: =L14 -> 165600 | M31: =M14 -> 165600 | N31: =N14 -> 165600 | O31: =O14 -> 165600 | ... S31: =S14 -> 165600 | T31: =SUM(H31:S31) -> 1490400
B32: 2 | C32: Tổng công suất máy (NVL) | D32: Tấn | L32: ='Cong suat'!J$32 -> 216000 | M32: ='Cong suat'!K$32 -> 216000 | N32: ='Cong suat'!L$32 -> 216000 | O32: ='Cong suat'!M$32 -> 216000 | P32: ='Cong suat'!N$32 -> 216000 | Q32: ='Cong suat'!O$32 -> 216000 | R32: ='Cong suat'!P$32 -> 216000 | S32: ='Cong suat'!Q$32 -> 216000 | T32: =SUM(H32:S32) -> 1728000

Sheet 2.Hao hut
B3: I - TỶ LỆ HAO HỤT DÂY ĐAI
B4: 1 | C4: SẢN XUẤT DÂY ĐAI | D4: ĐVT | E4: Định Mức | F4: T1 | G4: T2 | H4: T3 | I4: T4 | J4: T5 | K4: T6 | L4: T7 | M4: T8 | N4: T9 | O4: T10 | P4: T11 | Q4: T12 | R4: KH 2026
B5: 1 | C5: Đầu Keo Dây Đai PET Chưa Băm | E5: 0.01 | I5: =$E5 -> 0.01 | J5: =$E5 -> 0.01 | K5: =$E5 -> 0.01 | L5: =$E5 -> 0.01 | M5: =$E5 -> 0.01 | N5: =$E5 -> 0.01 | O5: =$E5 -> 0.01 | P5: =$E5 -> 0.01 | Q5: =$E5 -> 0.01 | R5: =AVERAGE(F5:Q5) -> 0.01
C6: Phó Sản PET HAD | E6: 0.05 | I6: =$E6 -> 0.05 | J6: =$E6 -> 0.05 | K6: =$E6 -> 0.05 | L6: =$E6 -> 0.05 | M6: =$E6 -> 0.05 | N6: =$E6 -> 0.05 | O6: =$E6 -> 0.05 | P6: =$E6 -> 0.05 | Q6: =$E6 -> 0.05 | R6: =AVERAGE(F6:Q6) -> 0.05
C7: Phó Sản PET Bụi Vảy | E7: 0.01 | I7: =$E7 -> 0.01 | J7: =$E7 -> 0.01 | K7: =$E7 -> 0.01 | L7: =$E7 -> 0.01 | M7: =$E7 -> 0.01 | N7: =$E7 -> 0.01 | O7: =$E7 -> 0.01 | P7: =$E7 -> 0.01 | Q7: =$E7 -> 0.01 | R7: =AVERAGE(F7:Q7) -> 0.01
C8: Phó Sản Dây Đai PET Chưa Băm | E8: 0.03 | I8: =$E8 -> 0.03 | J8: =$E8 -> 0.03 | K8: =$E8 -> 0.03 | L8: =$E8 -> 0.03 | M8: =$E8 -> 0.03 | N8: =$E8 -> 0.03 | O8: =$E8 -> 0.03 | P8: =$E8 -> 0.03 | Q8: =$E8 -> 0.03 | R8: =AVERAGE(F8:Q8) -> 0.03
B9: 2 | C9: Hao hụt vô hình (nước…) | E9: 0.04 | I9: 0.04 | J9: 0.04 | K9: 0.04 | L9: 0.04 | M9: 0.04 | N9: 0.04 | O9: 0.04 | P9: 0.04 | Q9: 0.04 | R9: =AVERAGE(F9:Q9) -> 0.04
C10: Tạp chất (ly mũ, ống hút, PET màu, trắng sữa, chai dín nhớt, nylong ….: loại trên chuyền) | E10: 0 | I10: 0 | J10: 0 | K10: 0 | L10: 0 | M10: 0 | N10: 0 | O10: 0 | P10: 0 | Q10: 0 | R10: =AVERAGE(F10:Q10) -> 0
C11: Tổng | E11: =SUM(E5:E10) -> 0.14 | I11: =SUM(I5:I10) -> 0.14 | J11: =SUM(J5:J10) -> 0.14 | K11: =SUM(K5:K10) -> 0.14 | L11: =SUM(L5:L10) -> 0.14 | M11: =SUM(M5:M10) -> 0.14 | N11: =SUM(N5:N10) -> 0.14 | O11: =SUM(O5:O10) -> 0.14 | P11: =SUM(P5:P10) -> 0.14 | Q11: =SUM(Q5:Q10) -> 0.14 | R11: =AVERAGE(F11:Q11) -> 0.14
B14: II - TỶ LỆ HAO HỤT DÂY ĐAI
B15: 1 | C15: Vảy - Băm B1 | D15: ĐVT | E15: Định Mức | F15: T1 | G15: T2 | H15: T3 | I15: T4 | J15: T5 | K15: T6 | L15: T7 | M15: T8 | N15: T9 | O15: T10 | P15: T11 | Q15: T12 | R15: KH 2026
C16: Đầu Keo Dây Đai PET Chưa Băm | E16: 0.01 | I16: =$E16 -> 0.01 | J16: =$E16 -> 0.01 | K16: =$E16 -> 0.01 | L16: =$E16 -> 0.01 | M16: =$E16 -> 0.01 | N16: =$E16 -> 0.01 | O16: =$E16 -> 0.01 | P16: =$E16 -> 0.01 | Q16: =$E16 -> 0.01 | R16: =AVERAGE(F16:Q16) -> 0.01
C17: Phó Sản PET HAD | E17: 0.05 | I17: =$E17 -> 0.05 | J17: =$E17 -> 0.05 | K17: =$E17 -> 0.05 | L17: =$E17 -> 0.05 | M17: =$E17 -> 0.05 | N17: =$E17 -> 0.05 | O17: =$E17 -> 0.05 | P17: =$E17 -> 0.05 | Q17: =$E17 -> 0.05 | R17: =AVERAGE(F17:Q17) -> 0.05
C18: Phó Sản PET Bụi Vảy | E18: 0.01 | I18: =$E18 -> 0.01 | J18: =$E18 -> 0.01 | K18: =$E18 -> 0.01 | L18: =$E18 -> 0.01 | M18: =$E18 -> 0.01 | N18: =$E18 -> 0.01 | O18: =$E18 -> 0.01 | P18: =$E18 -> 0.01 | Q18: =$E18 -> 0.01 | R18: =AVERAGE(F18:Q18) -> 0.01
C19: Phó Sản Dây Đai PET Chưa Băm | E19: 0.03 | I19: =$E19 -> 0.03 | J19: =$E19 -> 0.03 | K19: =$E19 -> 0.03 | L19: =$E19 -> 0.03 | M19: =$E19 -> 0.03 | N19: =$E19 -> 0.03 | O19: =$E19 -> 0.03 | P19: =$E19 -> 0.03 | Q19: =$E19 -> 0.03 | R19: =AVERAGE(F19:Q19) -> 0.03
C20: Mấy kg | E20: 0.04 | I20: =I9 -> 0.04 | J20: =J9 -> 0.04 | K20: =K9 -> 0.04 | L20: =L9 -> 0.04 | M20: =M9 -> 0.04 | N20: =N9 -> 0.04 | O20: =O9 -> 0.04 | P20: =P9 -> 0.04 | Q20: =Q9 -> 0.04 | R20: =AVERAGE(F20:Q20) -> 0.04
C21: Tổng hao hụt | I21: =SUM(I16:I20) -> 0.14 | J21: =SUM(J16:J20) -> 0.14 | K21: =SUM(K16:K20) -> 0.14 | L21: =SUM(L16:L20) -> 0.14 | M21: =SUM(M16:M20) -> 0.14 | N21: =SUM(N16:N20) -> 0.14 | O21: =SUM(O16:O20) -> 0.14 | P21: =SUM(P16:P20) -> 0.14 | Q21: =SUM(Q16:Q20) -> 0.14 | R21: =AVERAGE(F21:Q21) -> 0.14
C22: Tỷ lệ vảy thành phẩm | I22: =1-I21 -> 0.86 | J22: =1-J21 -> 0.86 | K22: =1-K21 -> 0.86 | L22: =1-L21 -> 0.86 | M22: =1-M21 -> 0.86 | N22: =1-N21 -> 0.86 | O22: =1-O21 -> 0.86 | P22: =1-P21 -> 0.86 | Q22: =1-Q21 -> 0.86 | R22: =AVERAGE(F22:Q22) -> 0.86
B26: III - TỶ LỆ THÀNH PHẨM SAU KHI PHÂN LOẠI CHAI PET
B27: 1. Sản xuất từ chai PET B0 - Xá tròn
B28: STT | C28: Thành phẩm | D28: ĐVT | E28: Định Mức | F28: T1 | G28: T2 | H28: T3 | I28: T4 | J28: T5 | K28: T6 | L28: T7 | M28: T8 | N28: T9 | O28: T10 | P28: T11 | Q28: T12 | R28: KH 2026
B29: 1 | C29: Vảy PET Dây Đai Mixed | E29: 0.86 | I29: =$E29 -> 0.86 | J29: =$E29 -> 0.86 | K29: =$E29 -> 0.86 | L29: =$E29 -> 0.86 | M29: =$E29 -> 0.86 | N29: =$E29 -> 0.86 | O29: =$E29 -> 0.86 | P29: =$E29 -> 0.86 | Q29: =$E29 -> 0.86
B30: 2 | I30: =$E30 -> 0 | J30: =$E30 -> 0 | K30: =$E30 -> 0 | L30: =$E30 -> 0 | M30: =$E30 -> 0 | N30: =$E30 -> 0 | O30: =$E30 -> 0 | P30: =$E30 -> 0 | Q30: =$E30 -> 0
B31: 3 | I31: =$E31 -> 0 | J31: =$E31 -> 0 | K31: =$E31 -> 0 | L31: =$E31 -> 0 | M31: =$E31 -> 0 | N31: =$E31 -> 0 | O31: =$E31 -> 0 | P31: =$E31 -> 0 | Q31: =$E31 -> 0
B32: 4 | I32: =$E32 -> 0 | J32: =$E32 -> 0 | K32: =$E32 -> 0 | L32: =$E32 -> 0 | M32: =$E32 -> 0 | N32: =$E32 -> 0 | O32: =$E32 -> 0 | P32: =$E32 -> 0 | Q32: =$E32 -> 0
B33: 5 | I33: =$E33 -> 0 | J33: =$E33 -> 0 | K33: =$E33 -> 0 | L33: =$E33 -> 0 | M33: =$E33 -> 0 | N33: =$E33 -> 0 | O33: =$E33 -> 0 | P33: =$E33 -> 0 | Q33: =$E33 -> 0
B34: 6
C35: TỔNG: | E35: =SUM(E29:E34) -> 0.86 | F35: =SUM(F29:F34) -> 0 | G35: =SUM(G29:G34) -> 0 | H35: =SUM(H29:H34) -> 0 | I35: =SUM(I29:I34) -> 0.86 | J35: =SUM(J29:J34) -> 0.86 | K35: =SUM(K29:K34) -> 0.86 | L35: =SUM(L29:L34) -> 0.86 | ... Q35: =SUM(Q29:Q34) -> 0.86

Sheet 3.Thanh pham
B3: I - THÀNH PHẨM SAU PHÂN LOẠI CHAI PET
B4: 1.1 Sản lượng sản xuất dây đai | R4: ĐVT: Tấn | AF4: ĐVT: Tấn
B5: STT | C5: Thành phẩm (chai sau phân loại) | D5: ĐVT | E5: KQKD 2025 | F5: T1 | G5: T2 | H5: T3 | I5: T4 | J5: T5 | K5: T6 | L5: T7 | M5: T8 | N5: T9 | O5: T10 | P5: T11 | Q5: T12 | R5: KH 2026 | T5: T1 | U5: T2 | V5: T3 | W5: T4 | X5: T5 | Y5: T6 | Z5: T7 | AA5: T8 | AB5: T9 | AC5: T10 | AD5: T11 | AE5: T12 | AF5: KQKD 2025
B6: 1 | C6: Dây đai rPET RPE1610 | F6: ='1.NVL'!H$12*'2.Hao hut'!F29 -> 0 | G6: ='1.NVL'!I$12*'2.Hao hut'!G29 -> 0 | H6: ='1.NVL'!J$12*'2.Hao hut'!H29 -> 0 | I6: ='1.NVL'!K$12*'2.Hao hut'!I29 -> 142416 | J6: ='1.NVL'!L$12*'2.Hao hut'!J29 -> 142416 | K6: ='1.NVL'!M$12*'2.Hao hut'!K29 -> 142416 | L6: ='1.NVL'!N$12*'2.Hao hut'!L29 -> 142416 | M6: ='1.NVL'!O$12*'2.Hao hut'!M29 -> 142416 | ... Q6: ='1.NVL'!S$12*'2.Hao hut'!Q29 -> 142416 | R6: =SUM(F6:Q6) -> 1281744 | AF6: =SUM(T6:AE6) -> 0
B7: 2 | F7: ='1.NVL'!H$12*'2.Hao hut'!F30 -> 0 | G7: ='1.NVL'!I$12*'2.Hao hut'!G30 -> 0 | H7: ='1.NVL'!J$12*'2.Hao hut'!H30 -> 0 | I7: ='1.NVL'!K$12*'2.Hao hut'!I30 -> 0 | J7: ='1.NVL'!L$12*'2.Hao hut'!J30 -> 0 | K7: ='1.NVL'!M$12*'2.Hao hut'!K30 -> 0 | L7: ='1.NVL'!N$12*'2.Hao hut'!L30 -> 0 | M7: ='1.NVL'!O$12*'2.Hao hut'!M30 -> 0 | ... Q7: ='1.NVL'!S$12*'2.Hao hut'!Q30 -> 0 | R7: =SUM(F7:Q7) -> 0 | AF7: =SUM(T7:AE7) -> 0
B8: 3 | F8: ='1.NVL'!H$12*'2.Hao hut'!F31 -> 0 | G8: ='1.NVL'!I$12*'2.Hao hut'!G31 -> 0 | H8: ='1.NVL'!J$12*'2.Hao hut'!H31 -> 0 | I8: ='1.NVL'!K$12*'2.Hao hut'!I31 -> 0 | J8: ='1.NVL'!L$12*'2.Hao hut'!J31 -> 0 | K8: ='1.NVL'!M$12*'2.Hao hut'!K31 -> 0 | L8: ='1.NVL'!N$12*'2.Hao hut'!L31 -> 0 | M8: ='1.NVL'!O$12*'2.Hao hut'!M31 -> 0 | ... Q8: ='1.NVL'!S$12*'2.Hao hut'!Q31 -> 0 | R8: =SUM(F8:Q8) -> 0 | AF8: =SUM(T8:AE8) -> 0
B9: 4 | F9: ='1.NVL'!H$12*'2.Hao hut'!F32 -> 0 | G9: ='1.NVL'!I$12*'2.Hao hut'!G32 -> 0 | H9: ='1.NVL'!J$12*'2.Hao hut'!H32 -> 0 | I9: ='1.NVL'!K$12*'2.Hao hut'!I32 -> 0 | J9: ='1.NVL'!L$12*'2.Hao hut'!J32 -> 0 | K9: ='1.NVL'!M$12*'2.Hao hut'!K32 -> 0 | L9: ='1.NVL'!N$12*'2.Hao hut'!L32 -> 0 | M9: ='1.NVL'!O$12*'2.Hao hut'!M32 -> 0 | ... Q9: ='1.NVL'!S$12*'2.Hao hut'!Q32 -> 0 | R9: =SUM(F9:Q9) -> 0 | AF9: =SUM(T9:AE9) -> 0
C10: TỔNG: | E10: =SUM(E6:E9) -> 0 | F10: =SUM(F6:F9) -> 0 | G10: =SUM(G6:G9) -> 0 | H10: =SUM(H6:H9) -> 0 | I10: =SUM(I6:I9) -> 142416 | J10: =SUM(J6:J9) -> 142416 | K10: =SUM(K6:K9) -> 142416 | L10: =SUM(L6:L9) -> 142416 | ... R10: =SUM(R6:R9) -> 1281744 | T10: =SUM(T6:T9) -> 0 | U10: =SUM(U6:U9) -> 0 | V10: =SUM(V6:V9) -> 0 | W10: =SUM(W6:W9) -> 0 | X10: =SUM(X6:X9) -> 0 | Y10: =SUM(Y6:Y9) -> 0 | Z10: =SUM(Z6:Z9) -> 0 | AA10: =SUM(AA6:AA9) -> 0 | ... AF10: =SUM(AF6:AF9) -> 0
B12: 1.5 Thành phẩm Xuất bán
B13: STT | C13: Thành phẩm (chai sau phân loại) | D13: ĐVT | E13: KQKD 2025 | F13: T1 | G13: T2 | H13: T3 | I13: T4 | J13: T5 | K13: T6 | L13: T7 | M13: T8 | N13: T9 | O13: T10 | P13: T11 | Q13: T12 | R13: KH 2026 | T13: T1 | U13: T2 | V13: T3 | W13: T4 | X13: T5 | Y13: T6 | Z13: T7 | AA13: T8 | AB13: T9 | AC13: T10 | AD13: T11 | AE13: T12 | AF13: KQKD 2025
B14: 1 | C14: Dây đai rPET RPE1610 | F14: =F6 -> 0 | G14: =G6 -> 0 | H14: =H6 -> 0 | I14: =I6 -> 142416 | J14: =J6 -> 142416 | K14: =K6 -> 142416 | L14: =L6 -> 142416 | M14: =M6 -> 142416 | ... Q14: =Q6 -> 142416 | R14: =SUM(F14:Q14) -> 1281744 | AF14: =SUM(T14:AE14) -> 0
B15: 2 | F15: =F7 -> 0 | G15: =G7 -> 0 | H15: =H7 -> 0 | I15: =I7 -> 0 | J15: =J7 -> 0 | K15: =K7 -> 0 | L15: =L7 -> 0 | M15: =M7 -> 0 | ... Q15: =Q7 -> 0 | R15: =SUM(F15:Q15) -> 0 | AF15: =SUM(T15:AE15) -> 0
B16: 3 | F16: =F8 -> 0 | G16: =G8 -> 0 | H16: =H8 -> 0 | I16: =I8 -> 0 | J16: =J8 -> 0 | K16: =K8 -> 0 | L16: =L8 -> 0 | M16: =M8 -> 0 | ... Q16: =Q8 -> 0 | R16: =SUM(F16:Q16) -> 0 | AF16: =SUM(T16:AE16) -> 0
B17: 4 | F17: =F9 -> 0 | G17: =G9 -> 0 | H17: =H9 -> 0 | I17: =I9 -> 0 | J17: =J9 -> 0 | K17: =K9 -> 0 | L17: =L9 -> 0 | M17: =M9 -> 0 | ... Q17: =Q9 -> 0 | R17: =SUM(F17:Q17) -> 0 | AF17: =SUM(T17:AE17) -> 0
C18: TỔNG | F18: =SUM(F14:F17) -> 0 | G18: =SUM(G14:G17) -> 0 | H18: =SUM(H14:H17) -> 0 | I18: =SUM(I14:I17) -> 142416 | J18: =SUM(J14:J17) -> 142416 | K18: =SUM(K14:K17) -> 142416 | L18: =SUM(L14:L17) -> 142416 | M18: =SUM(M14:M17) -> 142416 | ... R18: =SUM(R14:R17) -> 1281744 | T18: =SUM(T14:T17) -> 0 | U18: =SUM(U14:U17) -> 0 | V18: =SUM(V14:V17) -> 0 | W18: =SUM(W14:W17) -> 0 | X18: =SUM(X14:X17) -> 0 | Y18: =SUM(Y14:Y17) -> 0 | Z18: =SUM(Z14:Z17) -> 0 | AA18: =SUM(AA14:AA17) -> 0 | ... AF18: =SUM(AF14:AF17) -> 0
F19: =F18/1000 -> 0 | G19: =G18/1000 -> 0 | H19: =H18/1000 -> 0 | I19: =I18/1000 -> 142.416 | J19: =J18/1000 -> 142.416 | K19: =K18/1000 -> 142.416 | L19: =L18/1000 -> 142.416 | M19: =M18/1000 -> 142.416 | ... Q19: =Q18/1000 -> 142.416

Sheet PB_TSCD DC
D1: Công Ty TNHH Thu Mua Phế Liệu Đại Lộc
D2: KẾ HOẠCH NGÂN SÁCH 2026
D3: NGÂN SÁCH CAPEX VÀ XÂY DỰNG CƠ BẢN
L5: Tỷ giá | M5: 26500
B6: Xem MD | D6: Xem MD | H6: Xem MD | S6: Xem MD | Z6: Xem DATA Phan bo | AA6: Xem DATA Phan bo | AB6: Xem DATA Phan bo | BC6: =SUM(#REF!) -> #REF!
A7: STT | B7: Phòng ban yêu cầu | C7: Bộ phận thực hiện | D7: Loại tài sản | E7: Mục đích | F7: Dự án cấp 1 | G7: Dự án cấp 2 | H7: Phân loại (Nội địa/ Nhập khẩu) | I7: Nhà cung cấp | J7: Đơn giá ( chưa bao gồm VAT) | K7: Số lượng | L7: Tổng giá trị (VND) | M7: Tổng giá trị (USD) | N7: Thời điểm đưa vào sử dụng | O7: Thời gian khấu hao (tháng) | P7: Phân loại tài sản trong BCĐKT | Q7: Tài khoản COA chi phí khấu hao | R7: Mã Cost Center | S7: Tên Cost Center | T7: Hiệu máy | U7: Lý do đầu tư | V7: Khả năng đầu tư (%) | W7: Thời điểm ký hợp đồng | X7: Tên tài sản | Y7: Nhóm tài khoản | Z7: Mã tài khoản (Mã Chi phí_L4) | AA7: Tên tài khoản (Cost elements 2) | AB7: Chi Phí_L5 (Cost Group 2) | AC7: Giá trị nguyên giá | AD7: Giá trị đã khấu hao | AE7: Giá trị còn lại | AF7: T1 | AG7: T2 | AH7: T3 | AI7: T4 | AJ7: T5 | AK7: T6 | AL7: T7 | AM7: T8 | AN7: T9 | AO7: T10 | AP7: T11 | AQ7: T12 | AR7: Mục tiêu 2026 | AS7: Giá trị còn lại cuối năm 2026 | AU7: Time KH | AV7: Time đã khấu hao | AW7: Time còn lại | AX7: ĐC time KH | AY7: YEAR | AZ7: mounth | BB7: Time KH còn lại đc
A8: 2.2 | B8: BGD | C8: Kỹ Thuật | N8: 46023 | O8: =12*12 -> 144 | P8: TSCĐ hữu hình | S8: Chuyên Dây Đai PET | X8: Chuyên Dây Đai PET | Y8: 627 | Z8: 6274001903 | AA8: Khấu hao máy móc thiết bị chính | AB8: Depreciation-PPE-Machinery and equipment | AC8: =SUM(AC9:AC21) -> 6697017215 | AD8: =AC8-AE8 -> 0 | AE8: =CAPEX_202512[[#This Row],[Giá trị nguyên giá]] -> 6697017215 | AF8: =SUM(AF9:AF21) -> 0 | AG8: =SUM(AG9:AG21) -> 0 | AH8: =SUM(AH9:AH21) -> 0 | AI8: =SUM(AI9:AI21) -> 46507064 | AJ8: =SUM(AJ9:AJ21) -> 46507064 | AK8: =SUM(AK9:AK21) -> 46507064 | AL8: =SUM(AL9:AL21) -> 46507064 | AM8: =SUM(AM9:AM21) -> 46507064 | ... AQ8: =SUM(AQ9:AQ21) -> 46507064 | AR8: =SUM(AF8:AQ8) -> 4.1856358e+08
H9: Nhập Khẩu | I9: JWELL | N9: 46023 | O9: 120 | P9: TSCĐ hữu hình | T9: JEWLL | U9: Tạo dây Dai PET | V9: 1 | W9: 45901 | X9: Chuyên Dây Đai JWELL | Z9: 6274001903 | AA9: Khấu hao máy móc thiết bị chính | AB9: Depreciation-PPE-Machinery and equipment | AC9: 3945000000 | AD9: =AC9-AE9 -> 0 | AE9: =CAPEX_202512[[#This Row],[Giá trị nguyên giá]] -> 3945000000 | AI9: =CAPEX_202512[[#This Row],[Giá trị nguyên giá]]/144 -> 27395833 | AJ9: =CAPEX_202512[[#This Row],[Giá trị nguyên giá]]/144 -> 27395833 | AK9: =CAPEX_202512[[#This Row],[Giá trị nguyên giá]]/144 -> 27395833 | AL9: =CAPEX_202512[[#This Row],[Giá trị nguyên giá]]/144 -> 27395833 | AM9: =CAPEX_202512[[#This Row],[Giá trị nguyên giá]]/144 -> 27395833 | AN9: =CAPEX_202512[[#This Row],[Giá trị nguyên giá]]/144 -> 27395833 | AO9: =CAPEX_202512[[#This Row],[Giá trị nguyên giá]]/144 -> 27395833 | AP9: =CAPEX_202512[[#This Row],[Giá trị nguyên giá]]/144 -> 27395833 | AQ9: =CAPEX_202512[[#This Row],[Giá trị nguyên giá]]/144 -> 27395833 | AR9: =SUM(AF9:AQ9) -> 2.465625e+08
H10: Nhập Khẩu | I10: Sesotec | N10: 46023 | O10: 120 | P10: TSCĐ hữu hình | T10: SESOTEC | W10: 45962 | X10: Máy tách kim loại SESOTEC Vario FS-100-PP | Z10: 6274001903 | AA10: Khấu hao máy móc thiết bị chính | AB10: Depreciation-PPE-Machinery and equipment | AC10: 276150000 | AD10: =AC10-AE10 -> 0 | AE10: =CAPEX_202512[[#This Row],[Giá trị nguyên giá]] -> 276150000 | AI10: =CAPEX_202512[[#This Row],[Giá trị nguyên giá]]/144 -> 1917708.3 | AJ10: =CAPEX_202512[[#This Row],[Giá trị nguyên giá]]/144 -> 1917708.3 | AK10: =CAPEX_202512[[#This Row],[Giá trị nguyên giá]]/144 -> 1917708.3 | AL10: =CAPEX_202512[[#This Row],[Giá trị nguyên giá]]/144 -> 1917708.3 | AM10: =CAPEX_202512[[#This Row],[Giá trị nguyên giá]]/144 -> 1917708.3 | AN10: =CAPEX_202512[[#This Row],[Giá trị nguyên giá]]/144 -> 1917708.3 | AO10: =CAPEX_202512[[#This Row],[Giá trị nguyên giá]]/144 -> 1917708.3 | AP10: =CAPEX_202512[[#This Row],[Giá trị nguyên giá]]/144 -> 1917708.3 | AQ10: =CAPEX_202512[[#This Row],[Giá trị nguyên giá]]/144 -> 1917708.3 | AR10: =SUM(AF10:AQ10) -> 17259375
H11: Nhập Khẩu | I11: Sesotec | N11: 46023 | O11: 120 | P11: TSCĐ hữu hình | T11: Dongguan | W11: 45962 | X11: Máy kiểm tra chất luongj dây đai thành phẩm | Z11: 6274001903 | AA11: Khấu hao máy móc thiết bị chính | AB11: Depreciation-PPE-Machinery and equipment | AC11: 101255000 | AD11: =AC11-AE11 -> 0 | AE11: =CAPEX_202512[[#This Row],[Giá trị nguyên giá]] -> 101255000 | AI11: =CAPEX_202512[[#This Row],[Giá trị nguyên giá]]/144 -> 703159.72 | AJ11: =CAPEX_202512[[#This Row],[Giá trị nguyên giá]]/144 -> 703159.72 | AK11: =CAPEX_202512[[#This Row],[Giá trị nguyên giá]]/144 -> 703159.72 | AL11: =CAPEX_202512[[#This Row],[Giá trị nguyên giá]]/144 -> 703159.72 | AM11: =CAPEX_202512[[#This Row],[Giá trị nguyên giá]]/144 -> 703159.72 | AN11: =CAPEX_202512[[#This Row],[Giá trị nguyên giá]]/144 -> 703159.72 | AO11: =CAPEX_202512[[#This Row],[Giá trị nguyên giá]]/144 -> 703159.72 | AP11: =CAPEX_202512[[#This Row],[Giá trị nguyên giá]]/144 -> 703159.72 | AQ11: =CAPEX_202512[[#This Row],[Giá trị nguyên giá]]/144 -> 703159.72 | AR11: =SUM(AF11:AQ11) -> 6328437.5
H12: Nội Địa | I12: Hoàng Tiến Phát | N12: 46023 | O12: 120 | P12: TSCĐ hữu hình | T12: Hoàng TIến Phát | W12: 45962 | X12: Bồn trộn 10m3 (3.5 tấn vảy | Z12: 6274001903 | AA12: Khấu hao máy móc thiết bị chính | AB12: Depreciation-PPE-Machinery and equipment | AC12: 931989999 | AD12: =AC12-AE12 -> 0 | AE12: =CAPEX_202512[[#This Row],[Giá trị nguyên giá]] -> 931989999 | AI12: =CAPEX_202512[[#This Row],[Giá trị nguyên giá]]/144 -> 6472152.8 | AJ12: =CAPEX_202512[[#This Row],[Giá trị nguyên giá]]/144 -> 6472152.8 | AK12: =CAPEX_202512[[#This Row],[Giá trị nguyên giá]]/144 -> 6472152.8 | AL12: =CAPEX_202512[[#This Row],[Giá trị nguyên giá]]/144 -> 6472152.8 | AM12: =CAPEX_202512[[#This Row],[Giá trị nguyên giá]]/144 -> 6472152.8 | AN12: =CAPEX_202512[[#This Row],[Giá trị nguyên giá]]/144 -> 6472152.8 | AO12: =CAPEX_202512[[#This Row],[Giá trị nguyên giá]]/144 -> 6472152.8 | AP12: =CAPEX_202512[[#This Row],[Giá trị nguyên giá]]/144 -> 6472152.8 | AQ12: =CAPEX_202512[[#This Row],[Giá trị nguyên giá]]/144 -> 6472152.8 | AR12: =SUM(AF12:AQ12) -> 58249375
H13: Nội Địa | I13: Thịnh Phát, AE | N13: 46023 | O13: 120 | P13: TSCĐ hữu hình | T13: Thịnh Phát, AE | W13: 45962 | X13: Hệ thống điện | Z13: 6274001903 | AA13: Khấu hao máy móc thiết bị chính | AC13: 411189335 | AD13: =AC13-AE13 -> 0 | AE13: =CAPEX_202512[[#This Row],[Giá trị nguyên giá]] -> 411189335 | AI13: =CAPEX_202512[[#This Row],[Giá trị nguyên giá]]/144 -> 2855481.5 | AJ13: =CAPEX_202512[[#This Row],[Giá trị nguyên giá]]/144 -> 2855481.5 | AK13: =CAPEX_202512[[#This Row],[Giá trị nguyên giá]]/144 -> 2855481.5 | AL13: =CAPEX_202512[[#This Row],[Giá trị nguyên giá]]/144 -> 2855481.5 | AM13: =CAPEX_202512[[#This Row],[Giá trị nguyên giá]]/144 -> 2855481.5 | AN13: =CAPEX_202512[[#This Row],[Giá trị nguyên giá]]/144 -> 2855481.5 | AO13: =CAPEX_202512[[#This Row],[Giá trị nguyên giá]]/144 -> 2855481.5 | AP13: =CAPEX_202512[[#This Row],[Giá trị nguyên giá]]/144 -> 2855481.5 | AQ13: =CAPEX_202512[[#This Row],[Giá trị nguyên giá]]/144 -> 2855481.5 | AR13: =SUM(AF13:AQ13) -> 25699333
H14: Nội Địa | I14: Khang Thành, Lê Quốc | N14: 46023 | O14: 120 | P14: TSCĐ hữu hình | T14: Khang Thành, Lê Quốc | W14: 45962 | X14: Hệ thống hơi | Z14: 6274001903 | AA14: Khấu hao máy móc thiết bị chính | AC14: 379743553 | AD14: =AC14-AE14 -> 0 | AE14: =CAPEX_202512[[#This Row],[Giá trị nguyên giá]] -> 379743553 | AI14: =CAPEX_202512[[#This Row],[Giá trị nguyên giá]]/144 -> 2637108 | AJ14: =CAPEX_202512[[#This Row],[Giá trị nguyên giá]]/144 -> 2637108 | AK14: =CAPEX_202512[[#This Row],[Giá trị nguyên giá]]/144 -> 2637108 | AL14: =CAPEX_202512[[#This Row],[Giá trị nguyên giá]]/144 -> 2637108 | AM14: =CAPEX_202512[[#This Row],[Giá trị nguyên giá]]/144 -> 2637108 | AN14: =CAPEX_202512[[#This Row],[Giá trị nguyên giá]]/144 -> 2637108 | AO14: =CAPEX_202512[[#This Row],[Giá trị nguyên giá]]/144 -> 2637108 | AP14: =CAPEX_202512[[#This Row],[Giá trị nguyên giá]]/144 -> 2637108 | AQ14: =CAPEX_202512[[#This Row],[Giá trị nguyên giá]]/144 -> 2637108 | AR14: =SUM(AF14:AQ14) -> 23733972
H15: Nội Địa | I15: Hoàng Tấn An | N15: 46023 | O15: 120 | P15: TSCĐ hữu hình | T15: Hoàng Tấn An | W15: 45962 | X15: Hệ thống nước | Z15: 6274001903 | AA15: Khấu hao máy móc thiết bị chính | AC15: 172119328 | AD15: =AC15-AE15 -> 0 | AE15: =CAPEX_202512[[#This Row],[Giá trị nguyên giá]] -> 172119328 | AI15: =CAPEX_202512[[#This Row],[Giá trị nguyên giá]]/144 -> 1195273.1 | AJ15: =CAPEX_202512[[#This Row],[Giá trị nguyên giá]]/144 -> 1195273.1 | AK15: =CAPEX_202512[[#This Row],[Giá trị nguyên giá]]/144 -> 1195273.1 | AL15: =CAPEX_202512[[#This Row],[Giá trị nguyên giá]]/144 -> 1195273.1 | AM15: =CAPEX_202512[[#This Row],[Giá trị nguyên giá]]/144 -> 1195273.1 | AN15: =CAPEX_202512[[#This Row],[Giá trị nguyên giá]]/144 -> 1195273.1 | AO15: =CAPEX_202512[[#This Row],[Giá trị nguyên giá]]/144 -> 1195273.1 | AP15: =CAPEX_202512[[#This Row],[Giá trị nguyên giá]]/144 -> 1195273.1 | AQ15: =CAPEX_202512[[#This Row],[Giá trị nguyên giá]]/144 -> 1195273.1 | AR15: =SUM(AF15:AQ15) -> 10757458
H16: Nội Địa | N16: 46023 | O16: 120 | P16: TSCĐ hữu hình | W16: 45962 | X16: Chi phí lắp đăth | Z16: 6274001903 | AA16: Khấu hao máy móc thiết bị chính | AC16: 114000000 | AD16: =AC16-AE16 -> 0 | AE16: =CAPEX_202512[[#This Row],[Giá trị nguyên giá]] -> 114000000 | AI16: =CAPEX_202512[[#This Row],[Giá trị nguyên giá]]/144 -> 791666.67 | AJ16: =CAPEX_202512[[#This Row],[Giá trị nguyên giá]]/144 -> 791666.67 | AK16: =CAPEX_202512[[#This Row],[Giá trị nguyên giá]]/144 -> 791666.67 | AL16: =CAPEX_202512[[#This Row],[Giá trị nguyên giá]]/144 -> 791666.67 | AM16: =CAPEX_202512[[#This Row],[Giá trị nguyên giá]]/144 -> 791666.67 | AN16: =CAPEX_202512[[#This Row],[Giá trị nguyên giá]]/144 -> 791666.67 | AO16: =CAPEX_202512[[#This Row],[Giá trị nguyên giá]]/144 -> 791666.67 | AP16: =CAPEX_202512[[#This Row],[Giá trị nguyên giá]]/144 -> 791666.67 | AQ16: =CAPEX_202512[[#This Row],[Giá trị nguyên giá]]/144 -> 791666.67 | AR16: =SUM(AF16:AQ16) -> 7125000
H17: Nội Địa | N17: 46023 | O17: 120 | P17: TSCĐ hữu hình | W17: 45962 | X17: Chi Phí chuyên gia | Z17: 6274001903 | AA17: Khấu hao máy móc thiết bị chính | AC17: 43650000 | AD17: =AC17-AE17 -> 0 | AE17: =CAPEX_202512[[#This Row],[Giá trị nguyên giá]] -> 43650000 | AI17: =CAPEX_202512[[#This Row],[Giá trị nguyên giá]]/144 -> 303125 | AJ17: =CAPEX_202512[[#This Row],[Giá trị nguyên giá]]/144 -> 303125 | AK17: =CAPEX_202512[[#This Row],[Giá trị nguyên giá]]/144 -> 303125 | AL17: =CAPEX_202512[[#This Row],[Giá trị nguyên giá]]/144 -> 303125 | AM17: =CAPEX_202512[[#This Row],[Giá trị nguyên giá]]/144 -> 303125 | AN17: =CAPEX_202512[[#This Row],[Giá trị nguyên giá]]/144 -> 303125 | AO17: =CAPEX_202512[[#This Row],[Giá trị nguyên giá]]/144 -> 303125 | AP17: =CAPEX_202512[[#This Row],[Giá trị nguyên giá]]/144 -> 303125 | AQ17: =CAPEX_202512[[#This Row],[Giá trị nguyên giá]]/144 -> 303125 | AR17: =SUM(AF17:AQ17) -> 2728125
H18: Nội Địa | N18: 46023 | O18: 120 | P18: TSCĐ hữu hình | W18: 45962 | X18: Chi phí vận hành | Z18: 6274001903 | AA18: Khấu hao máy móc thiết bị chính | AC18: 23670000 | AD18: =AC18-AE18 -> 0 | AE18: =CAPEX_202512[[#This Row],[Giá trị nguyên giá]] -> 23670000 | AI18: =CAPEX_202512[[#This Row],[Giá trị nguyên giá]]/144 -> 164375 | AJ18: =CAPEX_202512[[#This Row],[Giá trị nguyên giá]]/144 -> 164375 | AK18: =CAPEX_202512[[#This Row],[Giá trị nguyên giá]]/144 -> 164375 | AL18: =CAPEX_202512[[#This Row],[Giá trị nguyên giá]]/144 -> 164375 | AM18: =CAPEX_202512[[#This Row],[Giá trị nguyên giá]]/144 -> 164375 | AN18: =CAPEX_202512[[#This Row],[Giá trị nguyên giá]]/144 -> 164375 | AO18: =CAPEX_202512[[#This Row],[Giá trị nguyên giá]]/144 -> 164375 | AP18: =CAPEX_202512[[#This Row],[Giá trị nguyên giá]]/144 -> 164375 | AQ18: =CAPEX_202512[[#This Row],[Giá trị nguyên giá]]/144 -> 164375 | AR18: =SUM(AF18:AQ18) -> 1479375
X19: Máy vệ sinh lõi lọc | AC19: =(8500+2000)*26500+8000000+7000000+5000000 -> 298250000 | AD19: =AC19-AE19 -> 0 | AE19: =CAPEX_202512[[#This Row],[Giá trị nguyên giá]] -> 298250000 | AI19: =CAPEX_202512[[#This Row],[Giá trị nguyên giá]]/144 -> 2071180.6 | AJ19: =CAPEX_202512[[#This Row],[Giá trị nguyên giá]]/144 -> 2071180.6 | AK19: =CAPEX_202512[[#This Row],[Giá trị nguyên giá]]/144 -> 2071180.6 | AL19: =CAPEX_202512[[#This Row],[Giá trị nguyên giá]]/144 -> 2071180.6 | AM19: =CAPEX_202512[[#This Row],[Giá trị nguyên giá]]/144 -> 2071180.6 | AN19: =CAPEX_202512[[#This Row],[Giá trị nguyên giá]]/144 -> 2071180.6 | AO19: =CAPEX_202512[[#This Row],[Giá trị nguyên giá]]/144 -> 2071180.6 | AP19: =CAPEX_202512[[#This Row],[Giá trị nguyên giá]]/144 -> 2071180.6 | AQ19: =CAPEX_202512[[#This Row],[Giá trị nguyên giá]]/144 -> 2071180.6 | AR19: =SUM(AF19:AQ19) -> 18640625
AD20: =AC20-AE20 -> 0 | AR20: =SUM(AF20:AQ20) -> 0
AD21: =AC21-AE21 -> 0 | AR21: =SUM(AF21:AQ21) -> 0
AR22: =SUM(AF22:AQ22) -> 0 | AS22: =AE22-AR22 -> 0
C23: TỔNG CỘNG KHẤU HAO TSCĐ_SX | Y23: 627 | AC23: =SUMIFS($AC$8:$AC$22,$Y$8:$Y$22,$Y23) -> 6697017215 | AD23: =SUMIFS(AD$8:AD$22,$Y$8:$Y$22,$Y23) -> 0 | AE23: =SUMIFS(AE$8:AE$22,$Y$8:$Y$22,$Y23) -> 6697017215 | AF23: =AF8 -> 0 | AG23: =AG8 -> 0 | AH23: =AH8 -> 0 | AI23: =AI8 -> 46507064 | AJ23: =AJ8 -> 46507064 | AK23: =AK8 -> 46507064 | AL23: =AL8 -> 46507064 | AM23: =AM8 -> 46507064 | ... AQ23: =AQ8 -> 46507064 | AR23: =SUMIFS(AR$8:AR$22,$Y$8:$Y$22,$Y23) -> 4.1856358e+08 | AS23: =AE23-AR23 -> 6.2784536e+09
C24: Khấu Hao chuyền Phân loại | X24: Khấu Hao chuyền Phân loại | AA24: Khấu Hao chuyền Phân loại
C25: Khấu hao chuyền Băm PET | X25: Khấu hao chuyền Băm PET | AA25: Khấu hao chuyền Băm PET
C26: Khấu hao chuyền Băm HD | X26: Khấu hao chuyền Băm HD | AA26: Khấu hao chuyền Băm HD
C27: Khấu hao chuyền Dây Đai | X27: Khấu hao chuyền Dây Đai | AA27: Khấu hao chuyền Dây Đai | AC27: =SUM(AC8) -> 6697017215 | AD27: =SUM(AD8) -> 0 | AE27: =SUM(AE8) -> 6697017215 | AF27: =SUM(AF8) -> 0 | AG27: =SUM(AG8) -> 0 | AH27: =SUM(AH8) -> 0 | AI27: =SUM(AI8) -> 46507064 | AJ27: =SUM(AJ8) -> 46507064 | ... AR27: =SUM(AR8) -> 4.1856358e+08 | AS27: =AE27-AR27 -> 6.2784536e+09
C28: Khấu Hao xưởng | X28: Khấu Hao xưởng | AA28: Khấu Hao xưởng | AS28: =AE28-AR28 -> 0
C29: TỔNG CỘNG KHẤU HAO TSCĐ_QL | Y29: 642 | AC29: =SUMIFS($AC$8:$AC$22,$Y$8:$Y$22,$Y29) -> 0 | AD29: =SUMIFS(AD$8:AD$22,$Y$8:$Y$22,$Y29) -> 0 | AE29: =SUMIFS(AE$8:AE$22,$Y$8:$Y$22,$Y29) -> 0 | AF29: =SUMIFS(AF$8:AF$22,$Y$8:$Y$22,$Y29) -> 0 | AG29: =SUMIFS(AG$8:AG$22,$Y$8:$Y$22,$Y29) -> 0 | AH29: =SUMIFS(AH$8:AH$22,$Y$8:$Y$22,$Y29) -> 0 | AI29: =SUMIFS(AI$8:AI$22,$Y$8:$Y$22,$Y29) -> 0 | AJ29: =SUMIFS(AJ$8:AJ$22,$Y$8:$Y$22,$Y29) -> 0 | AK29: =SUMIFS(AK$8:AK$22,$Y$8:$Y$22,$Y29) -> 0 | ... AR29: =SUMIFS(AR$8:AR$22,$Y$8:$Y$22,$Y29) -> 0 | AS29: =AE29-AR29 -> 0
C30: TỔNG CỘNG KHẤU HAO TSCĐ | AC30: =AC23+AC29 -> 6697017215 | AD30: =AD23+AD29 -> 0 | AE30: =AE23+AE29 -> 6697017215 | AF30: =AF23+AF29 -> 0 | AG30: =AG23+AG29 -> 0 | AH30: =AH23+AH29 -> 0 | AI30: =AI23+AI29 -> 46507064 | AJ30: =AJ23+AJ29 -> 46507064 | ... AS30: =AS23+AS29 -> 6.2784536e+09
AI31: ='3.Thanh pham'!I10 -> 142416 | AJ31: ='3.Thanh pham'!J10 -> 142416 | AK31: ='3.Thanh pham'!K10 -> 142416 | AL31: ='3.Thanh pham'!L10 -> 142416 | AM31: ='3.Thanh pham'!M10 -> 142416 | AN31: ='3.Thanh pham'!N10 -> 142416 | AO31: ='3.Thanh pham'!O10 -> 142416 | AP31: ='3.Thanh pham'!P10 -> 142416 | ... AS31: ='3.Thanh pham'!S10 -> 0
AI32: =AI30/AI31 -> 326.55786 | AJ32: =AJ30/AJ31 -> 326.55786 | AK32: =AK30/AK31 -> 326.55786 | AL32: =AL30/AL31 -> 326.55786 | AM32: =AM30/AM31 -> 326.55786 | AN32: =AN30/AN31 -> 326.55786 | AO32: =AO30/AO31 -> 326.55786 | AP32: =AP30/AP31 -> 326.55786 | ... AS32: =AS30/AS31 -> #DIV/0!
