Workbook
Name Capacity: 'Cover Page'!$F$28
Name Currency: 'Cover Page'!$A$33
Name EXR: 'Cover Page'!$F$10
Name Inflation: 'Cover Page'!$F$9
Name Opt1_WACC: 'Cover Page'!$H$23
Name Opt2_CAPEX: 'Cover Page'!$K$6
Name Opt2_CPSX: 'Cover Page'!$K$7
Name Opt2_EXW: 'Cover Page'!$K$10
Name Opt2_WACC: 'Cover Page'!$K$23
Name Opt3_CAPEX: 'Cover Page'!$N$6
Name Opt3_CPSX: 'Cover Page'!$N$7
Name Opt3_WACC: 'Cover Page'!$W$23
Name Opt4_CAPEX: 'Cover Page'!$Q$6
Name Opt4_CPSX: 'Cover Page'!$Q$7
Name Opt5_CAPEX: 'Cover Page'!$T$6
Name Opt5_CPSX: 'Cover Page'!$T$7
Name Opt6_CAPEX: 'Cover Page'!$W$6
Name Opt6_CPSX: 'Cover Page'!$W$7
Name PHOI_KG: 'Cover Page'!$F$30
Name Slicer_Currency: #N/A
Name Tax_rate: 'Cover Page'!$F$11
Name WACC: 'Cover Page'!$F$23

Sheet Timeline

Sheet >>PowerPoint

Sheet Trình bày giả định
A2: CÁC GIẢ ĐỊNH CỦA DỰ ÁN
A4: STT | B4: GIẢ ĐỊNH | C4: GIÁ TRỊ | D4: ĐVT/Ghi chú | F4: STT | G4: GIẢ ĐỊNH | H4: GIÁ TRỊ | I4: ĐVT/Ghi chú
A5: 1 | B5: Thông tin chung | F5: 4 | G5: Hiệu suất sử dụng máy | H5: ='W3'!$L$23 -> 0.88
A6: 1.1 | B6: Chủ đầu tư | C6: DTR
A7: 1.2 | B7: Thời gian khai thác | C7: 25 | D7: Năm | F7: 5 | G7: Sản lượng sản xuất tối đa | H7: ='W3'!U27/10^3 -> 6194.175 | I7: tấn/năm
A8: 1.3 | B8: Tổng dự toán đầu tư máy móc thiết bị (VND) | C8: =IF(Currency="VND",'W1'!$I$60,'W1'!$I$60*EXR) -> 300749800000 | D8: VND | H8: ='W3'!U28 -> 4.12945e+08 | I8: phôi/năm
A9: 1.4 | B9: Tổng dự toán đầu tư máy móc thiết bị (USD) | C9: =IF(Currency="VND",'W1'!$I$60/EXR,'W1'!$I$60) -> 11567300 | D9: USD
A10: 1.5 | B10: Thời gian khấu hao (PP đường thẳng) | C10: ='W1'!G13 -> 12 | D10: Năm | F10: 6 | G10: Sản lượng bán | H10: (tấn)
A11: 1.6 | B11: Tỷ giá | C11: =EXR -> 26000 | F11: 6.1 | G11: Sản lượng bán năm 1 | H11: ='W3'!L27/10^3 -> 3097.0875 | I11: 50.0% Sản lượng sản xuất tối đa
A12: 1.7 | B12: Lạm phát | C12: =Inflation -> 0.05 | F12: 6.2 | G12: Sản lượng bán năm 2 | H12: ='W3'!M27/10^3 -> 4335.9225 | I12: 70.0% Sản lượng sản xuất tối đa
F13: 6.3 | G13: Sản lượng bán năm 3 | H13: ='W3'!N27/10^3 -> 6194.175 | I13: 100.0% Sản lượng sản xuất tối đa
A14: 2 | B14: Nguồn nguyên vật liệu: Vảy sạch từ chai B1 | F14: 6.4 | G14: Từ năm thứ 4 trở đi bằng với năm 3
A15: 2.1 | B15: Đơn giá chai B1 | C15: 16600 | D15: đ/kg
A16: 2.2 | B16: Đơn giá vảy sạch cho dự án | C16: =IF(Currency="VND",'W2'!$M$56,'W2'!$M$56*EXR) -> 24960 | D16: đ/kg
A17: 2.3 | B17: Tỷ lệ hao hụt FtoP | C17: ='W2'!M41 -> 0.07 | F17: 7 | G17: Giá bán | H17: ='Cover Page'!H13 -> 45.333333 | I17: tr.đ/tấn
A18: 2.4 | B18: Liều lượng phụ gia | C18: ='W2'!M60 -> 0.0002 | H18: ='Cover Page'!H15 -> 1743.5897 | I18: USD/tấn
A19: 2.5 | B19: Đơn giá phụ gia | C19: ='W2'!M64 -> 949542 | D19: VND/kg | H19: ='Cover Page'!H14 -> 680 | I19: VND/phôi
F20: 8 | G20: Tỷ lệ chiết khấu/cơ cấu vay
A21: 3 | B21: Chi phí sản xuất | F21: 8.1 | G21: Vốn vay | H21: ='Cover Page'!H21 -> 0.7
A22: 3.1 | B22: Nhân công trực tiếp (2 người x 3 ca) | C22: =IF(Currency="VND",'W2'!$M$13,'W2'!$M$13*EXR) -> 982800000 | D22: VND/năm | F22: 8.2 | G22: Vốn tự có | H22: =1-H21 -> 0.3
A23: 3.2 | B23: Nhân viên kỹ thuật, QC, kho | C23: =IF(Currency="VND",'W2'!$M$17,'W2'!$M$17*EXR) -> 5028660000 | D23: VND/năm | F23: 8.3 | G23: Lãi vay trung dài hạn | H23: ='Cover Page'!H19 -> 0.07
A24: 3.3 | B24: Chi phí điện | C24: ='W2'!M45 -> 765 | D24: kwh | F24: 8.4 | G24: Thuế suất thuế TNDN | H24: =Tax_rate -> 0.2
A25: 3.4 | B25: Đơn giá điện | C25: =IF(Currency="VND",'W2'!$M$46,'W2'!$M$46*EXR) -> 1950 | D25: đ/kwh | F25: 8.5 | G25: Tỷ lệ chiết khấu = WACC | H25: =Opt1_WACC -> 0.07266
A26: 3.5 | B26: Chi phí sửa chữa bảo trì | C26: =IF(Currency="VND",'W2'!$M$28,'W2'!$M$28*EXR) -> 9022494000 | D26: VND/năm
A27: 3.6 | B27: Chi phí vận hành xe điện | C27: =IF(Currency="VND",'W2'!$M$37,'W2'!$M$37*EXR) -> 552000000 | D27: VND/năm
B28: (Số xe thuê: 2 với đơn giá thuê 20 triệu/tháng, chi phí điện 3 triệu/xe/tháng) | G28: Dự án chưa tính giá trị đầu tư xưởng (khoảng 150 tỷ đồng ~ 6 triệu USD)
A29: 3.7 | B29: Chi phí bao bì | C29: =IF(Currency="VND",'W2'!$M$48,'W2'!$M$48*EXR) -> 314.81481 | D29: đ/kg thành phẩm
A30: 3.8 | B30: Chi phí thuê xưởng | C30: =IF(Currency="VND",'W2'!$M$33,'W2'!$M$33*EXR) -> 2400000000 | D30: VND/năm
A31: 3.9 | B31: Chi phí bảo hiểm | C31: ='W2'!L73 -> 0.002 | D31: /tổng tài sản
A32: 3.10 | B32: Chi phí vận chuyển | C32: ='W2'!$M$77 -> 4000000 | D32: VND/chuyến

Sheet W1-Trình bày
A2: STT | B2: HẠNG MỤC | C2: Số lượng | E2: Đơn giá | F2: Giá trị đầu tư | G2: Giá trị đầu tư | M2: Thời gian khấu hao | N2: Khấu hao
C3: (cái,m2) | E3: (VND) | F3: (VND) | G3: (USD) | M3: (Năm) | N3: (VND/năm)
A5: 1 | B5: MÁY MÓC THIẾT BỊ | F5: 284499800000 | G5: =F5/26000 -> 10942300 | N5: 2.3708317e+10
A7: 1.1 | B7: Máy móc thiết bị chính | F7: 2.46389e+11 | G7: =F7/26000 -> 9476500 | N7: 2.0532417e+10
A8: 1.1.01 | B8: NGR : LSP 1200 | C8: 1 | E8: 128180000000 | F8: 128180000000 | G8: =F8/26000 -> 4930000 | M8: 12 | N8: 1.0681667e+10
A9: 1.1.02 | B9: HyPET400 HPP5e rMtP P120/120 | C9: 1 | E9: 6.727793e+10 | F9: 6.727793e+10 | G9: =F9/26000 -> 2587612.7 | M9: 12 | N9: 5.6064942e+09
A10: 1.1.03 | B10: Khuôn 15g PCO 1881 128 cavtiy | C10: 1 | E10: 3.932207e+10 | F10: 3.932207e+10 | G10: =F10/26000 -> 1512387.3 | M10: 12 | N10: 3.2768391e+09
A11: 1.1.04 | B11: Chi phí vận chuyển | C11: 1 | E11: 2600000000 | F11: 2600000000 | G11: =F11/26000 -> 100000 | M11: 12 | N11: 2.1666667e+08
A12: 1.1.05 | B12: Chi phí lắp đặt | C12: 1 | E12: 8580000000 | F12: 8580000000 | G12: =F12/26000 -> 330000 | M12: 12 | N12: 715000000
A13: 1.1.06 | B13: Thuế nhà thầu | C13: 1 | E13: 429000000 | F13: 429000000 | G13: =F13/26000 -> 16500 | M13: 12 | N13: 35750000
A15: 1.2 | B15: Máy móc thiết bị phụ | F15: 38110800000 | G15: =F15/26000 -> 1465800 | N15: 3175900000
A16: 1.2.06 | B16: Hệ thống nước, khí nén | C16: 1 | E16: 7800000000 | F16: 7800000000 | G16: =F16/26000 -> 300000 | M16: 12 | N16: 650000000
A17: 1.2.07 | B17: Hệ thống điện | C17: 1 | E17: 7800000000 | F17: 7800000000 | G17: =F17/26000 -> 300000 | M17: 12 | N17: 650000000
A18: 1.2.08 | B18: Pump system | C18: 1 | E18: 3900000000 | F18: 3900000000 | G18: =F18/26000 -> 150000 | M18: 12 | N18: 325000000
A19: 1.2.09 | B19: Camera online check | C19: 1 | E19: 3250000000 | F19: 3250000000 | G19: =F19/26000 -> 125000 | M19: 12 | N19: 2.7083333e+08
A20: 1.2.10 | B20: Chiller | C20: 1 | E20: 2600000000 | F20: 2600000000 | G20: =F20/26000 -> 100000 | M20: 12 | N20: 2.1666667e+08
A21: 1.2.11 | B21: Trạm điện | C21: 1 | E21: 2600000000 | F21: 2600000000 | G21: =F21/26000 -> 100000 | M21: 12 | N21: 2.1666667e+08
A22: 1.2.12 | B22: Overhead crane | C22: 1 | E22: 2600000000 | F22: 2600000000 | G22: =F22/26000 -> 100000 | M22: 12 | N22: 2.1666667e+08
A23: 1.2.13 | B23: Hệ thống điện dự phòng | C23: 1 | E23: 2080000000 | F23: 2080000000 | G23: =F23/26000 -> 80000 | M23: 12 | N23: 1.7333333e+08
A24: 1.2.14 | B24: Hệ thống IT | C24: 1 | E24: 2080000000 | F24: 2080000000 | G24: =F24/26000 -> 80000 | M24: 12 | N24: 1.7333333e+08
A25: 1.2.15 | B25: Lock unloading preform | C25: 1 | E25: 1352000000 | F25: 1352000000 | G25: =F25/26000 -> 52000 | M25: 12 | N25: 1.1266667e+08
A26: 1.2.16 | B26: Máy nén khí | C26: 1 | E26: 1248000000 | F26: 1248000000 | G26: =F26/26000 -> 48000 | M26: 12 | N26: 104000000
A27: 1.2.17 | B27: Cooling tower | C27: 1 | E27: 780000000 | F27: 780000000 | G27: =F27/26000 -> 30000 | M27: 12 | N27: 65000000
A28: 1.2.18 | B28: Máy scan | C28: 1 | E28: 20800000 | F28: 20800000 | G28: =F28/26000 -> 800 | M28: 12 | N28: 1733333.3
B30: CHI PHÍ XÂY DỰNG XƯỞNG SẢN XUẤT | C30: 2000 | F30: 0 | N30: 0
B31: Xưởng sản xuất | C31: 1900 | E31: 75000000 | F31: 0 | M31: 25 | N31: 0
B32: Phòng QC | C32: 100 | E32: 75000000 | F32: 0 | M32: 25 | N32: 0
A34: 2. | B34: MÁY MÓC THIẾT BỊ PHÒNG LAB | F34: 16250000000 | G34: =F34/26000 -> 625000 | N34: 1.3541667e+09
A35: 2.01 | B35: Máy đo IV PSL IV 4603 | C35: 1 | E35: 5200000000 | F35: 5200000000 | G35: =F35/26000 -> 200000 | M35: 12 | N35: 4.3333333e+08
A36: 2.02 | B36: Máy đo kích thước tự động Gawis 4D | C36: 1 | E36: 5200000000 | F36: 5200000000 | G36: =F36/26000 -> 200000 | M36: 12 | N36: 4.3333333e+08
A37: 2.03 | B37: Máy đo AA Piovan Inspecta | C37: 1 | E37: 3042000000 | F37: 3042000000 | G37: =F37/26000 -> 117000 | M37: 12 | N37: 253500000
A38: 2.04 | B38: Colorimeter/Spectrophotometer | C38: 1 | E38: 650000000 | F38: 650000000 | G38: =F38/26000 -> 25000 | M38: 12 | N38: 54166667
A39: 2.05 | B39: Melt Flow Index Tester | C39: 1 | E39: 442000000 | F39: 442000000 | G39: =F39/26000 -> 17000 | M39: 12 | N39: 36833333
A40: 2.06 | B40: Light Polarizer | C40: 1 | E40: 260000000 | F40: 260000000 | G40: =F40/26000 -> 10000 | M40: 12 | N40: 21666667
A41: 2.07 | B41: Moisture analyzer | C41: 1 | E41: 143000000 | F41: 143000000 | G41: =F41/26000 -> 5500 | M41: 12 | N41: 11916667
A42: 2.08 | B42: Perpendicular Prefrom Thickness Gauge | C42: 1 | E42: 130000000 | F42: 130000000 | G42: =F42/26000 -> 5000 | M42: 12 | N42: 10833333
A43: 2.09 | B43: Calipers with data output | C43: 1 | E43: 130000000 | F43: 130000000 | G43: =F43/26000 -> 5000 | M43: 12 | N43: 10833333
A44: 2.10 | B44: Radius gauges | C44: 1 | E44: 130000000 | F44: 130000000 | G44: =F44/26000 -> 5000 | M44: 12 | N44: 10833333
A45: 2.11 | B45: Torque tester | C45: 1 | E45: 130000000 | F45: 130000000 | G45: =F45/26000 -> 5000 | M45: 12 | N45: 10833333
A46: 2.12 | B46: Pitch gauges | C46: 1 | E46: 130000000 | F46: 130000000 | G46: =F46/26000 -> 5000 | M46: 12 | N46: 10833333
... A53: 2.19 | B53: Black Ligth/UV light | C53: 1 | E53: 26000000 | F53: 26000000 | G53: =F53/26000 -> 1000 | M53: 12 | N53: 2166666.7
A55: TỔNG ĐẦU TƯ BAN ĐẦU | F55: 300749800000 | G55: =F55/26000 -> 11567300 | N55: 2.5062483e+10
A59: STT | B59: HẠNG MỤC | C59: Số lượng | E59: Đơn giá | F59: Giá trị đầu tư | G59: Giá trị đầu tư
C60: (cái,m2) | E60: (VND) | F60: (VND) | G60: (USD)
A61: 2. | B61: MÁY MÓC THIẾT BỊ PHÒNG LAB | F61: 16250000000 | G61: 625000
A62: 2.01 | B62: Máy đo IV PSL IV 4603 | C62: 1 | E62: 5200000000 | F62: 5200000000 | G62: 200000
A63: 2.02 | B63: Máy đo kích thước tự động Gawis 4D | C63: 1 | E63: 5200000000 | F63: 5200000000 | G63: 200000
A64: 2.03 | B64: Máy đo AA Piovan Inspecta | C64: 1 | E64: 3042000000 | F64: 3042000000 | G64: 117000
A65: 2.04 | B65: Colorimeter/Spectrophotometer | C65: 1 | E65: 650000000 | F65: 650000000 | G65: 25000
A66: 2.05 | B66: Melt Flow Index Tester | C66: 1 | E66: 442000000 | F66: 442000000 | G66: 17000
A67: 2.06 | B67: Light Polarizer | C67: 1 | E67: 260000000 | F67: 260000000 | G67: 10000
A68: 2.07 | B68: Moisture analyzer | C68: 1 | E68: 143000000 | F68: 143000000 | G68: 5500
A69: 2.08 | B69: Perpendicular Prefrom Thickness Gauge | C69: 1 | E69: 130000000 | F69: 130000000 | G69: 5000
A70: 2.09 | B70: Calipers with data output | C70: 1 | E70: 130000000 | F70: 130000000 | G70: 5000
A71: 2.10 | B71: Radius gauges | C71: 1 | E71: 130000000 | F71: 130000000 | G71: 5000
A72: 2.11 | B72: Torque tester | C72: 1 | E72: 130000000 | F72: 130000000 | G72: 5000
A73: 2.12 | B73: Pitch gauges | C73: 1 | E73: 130000000 | F73: 130000000 | G73: 5000
... A80: 2.19 | B80: Black Ligth/UV light | C80: 1 | E80: 26000000 | F80: 26000000 | G80: 1000

Sheet USD.Tấn
A3: No. | B3: SAP | C3: Chi phí Cost Items | D3: Chi phí USD/tấn | E3: Cơ cấu % chi phí /Giá
A4: A | B4: 1521 | C4: Chi phí nguyên vật liệu | D4: 979.2 | E4: 0.5616
C5: Vảy sạch | D5: 979.2 | E5: 0.5616
A6: B | B6: 1522 | C6: Hao hụt về tiền | D6: 73.703226 | E6: 0.042270968
A7: C | C7: Chi phí biến đổi | D7: 512.52452 | E7: 0.29394789
A8: 1 | B8: LAB | C8: Chi phí nhân công | D8: 39.193355 | E8: 0.022478542
A9: 2 | B9: DEP | C9: Khấu hao | D9: 155.62067 | E9: 0.089253032
A10: 3 | B10: OTH | C10: Chi phí gián tiếp | D10: 89.499728 | E10: 0.051330727
A11: 4 | B11: ELEC | C11: Điện | D11: 132.27565 | E11: 0.075863976
A12: 5 | B12: QLC | C12: Chi phí quản lý | D12: 74.974798 | E12: 0.043000252
A13: 6 | B13: BAG | C13: Đóng gói | D13: 12.713675 | E13: 0.0072916667
A14: 7 | B14: CHE | C14: Hóa chất | D14: 8.2466427 | E14: 0.0047296921
A15: 8 | B15: H2O | C15: Nước | D15: 0 | E15: 0
A16: 9 | C16: Giá thành | D16: 1565.4277 | E16: 0.89781886
A17: 10 | B17: TAX | C17: Thuế thu nhập | D17: 35.632399 | E17: 0.020436229
A18: D | B18: LN | C18: Lợi nhuận | D18: 142.5296 | E18: 0.081744916
A19: A+B+C+D | C19: Giá bán | D19: 1743.5897 | E19: 1
C20: % Lãi gộp nguyên liệu/Giá bán | E20: 0.4384

Sheet VND.Phôi
A3: No. | B3: SAP | C3: Chi phí Cost Items | D3: Chi phí VNĐ / Phôi | E3: Cơ cấu % chi phí /Giá
A4: A | B4: 1521 | C4: Chi phí nguyên vật liệu | D4: 381.888 | E4: 0.5616
B5: 1521 | C5: Vảy sạch | D5: 381.888 | E5: 0.5616
A6: B | B6: 1522 | C6: Hao hụt về tiền | D6: 28.744258 | E6: 0.042270968
A7: C | C7: Chi phí biến đổi | D7: 199.88456 | E7: 0.29394789
A8: 1 | B8: LAB | C8: Chi phí nhân công | D8: 15.285409 | E8: 0.022478542
A9: 2 | B9: DEP | C9: Khấu hao | D9: 60.692062 | E9: 0.089253032
A10: 3 | B10: QLC | C10: Chi phí quản lý | D10: 34.904894 | E10: 0.051330727
A11: 4 | B11: OTH | C11: Chi phí gián tiếp | D11: 51.587504 | E11: 0.075863976
A12: 5 | B12: ELEC | C12: Điện | D12: 29.240171 | E12: 0.043000252
A13: 6 | B13: BAG | C13: Đóng gói | D13: 4.9583333 | E13: 0.0072916667
A14: 7 | B14: CHE | C14: Hóa chất | D14: 3.2161906 | E14: 0.0047296921
A15: 8 | B15: H2O | C15: Nước | D15: 0 | E15: 0
A16: 9 | C16: Giá thành | D16: 610.51682 | E16: 0.89781886
A17: 10 | B17: TAX | C17: Thuế thu nhập | D17: 13.896636 | E17: 0.020436229
A18: D | B18: LN | C18: Lợi nhuận | D18: 55.586543 | E18: 0.081744916
A19: A+B+C+D | C19: Giá bán | D19: 680 | E19: 1
C20: % Lãi gộp nguyên liệu/Giá bán | E20: 0.4384

Sheet Sheet3
B2: STT | C2: Hạng mục | D2: Đvt | E2: 2026 | F2: 2027 | G2: 2028 | H2: 2029 | I2: 2030 | J2: 2031 | K2: 2032 | L2: 2033 | M2: 2034 | N2: 2035 | O2: 2036 | P2: 2037 | Q2: 2038 | R2: 2039 | S2: 2040 | T2: 2041 | U2: 2042 | V2: 2043 | W2: 2044 | X2: 2045 | Y2: 2046 | Z2: 2047 | AA2: 2048 | AB2: 2049 | AC2: 2050 | AD2: 2051
B4: =IF(C4<>"",SUBTOTAL(3,C$4:C4),"") -> 1 | C4: SỐ LƯỢNG SẢN XUẤT/BÁN
B5: =IF(C5<>"",SUBTOTAL(3,C$4:C5),"") -> 2 | C5: Sản lượng công suất máy | D5: kg/năm | F5: 7568640 | G5: 7568640 | H5: 7568640 | I5: 7568640 | J5: 7568640 | K5: 7568640 | L5: 7568640 | M5: 7568640 | N5: 7568640 | O5: 7568640 | P5: 7568640 | Q5: 7568640 | R5: 7568640 | S5: 7568640 | T5: 7568640 | U5: 7568640 | V5: 7568640 | W5: 7568640 | X5: 7568640 | Y5: 7568640 | Z5: 7568640 | AA5: 7568640 | AB5: 7568640 | AC5: 7568640 | AD5: 7568640
B6: =IF(C6<>"",SUBTOTAL(3,C$4:C6),"") -> 3 | C6: Sản lượng công suất máy | D6: phôi/năm | F6: 7568640 | G6: 7568640 | H6: 7568640 | I6: 7568640 | J6: 7568640 | K6: 7568640 | L6: 7568640 | M6: 7568640 | N6: 7568640 | O6: 7568640 | P6: 7568640 | Q6: 7568640 | R6: 7568640 | S6: 7568640 | T6: 7568640 | U6: 7568640 | V6: 7568640 | W6: 7568640 | X6: 7568640 | Y6: 7568640 | Z6: 7568640 | AA6: 7568640 | AB6: 7568640 | AC6: 7568640 | AD6: 7568640
B7: =IF(C7<>"",SUBTOTAL(3,C$4:C7),"") -> 4 | C7: Hiệu suất sử dụng tối đa | F7: 0.88 | G7: 0.88 | H7: 0.88 | I7: 0.88 | J7: 0.88 | K7: 0.88 | L7: 0.88 | M7: 0.88 | N7: 0.88 | O7: 0.88 | P7: 0.88 | Q7: 0.88 | R7: 0.88 | S7: 0.88 | T7: 0.88 | U7: 0.88 | V7: 0.88 | W7: 0.88 | X7: 0.88 | Y7: 0.88 | Z7: 0.88 | AA7: 0.88 | AB7: 0.88 | AC7: 0.88 | AD7: 0.88
B8: =IF(C8<>"",SUBTOTAL(3,C$4:C8),"") -> 5 | C8: Hệ số điều chỉnh sản xuất | F8: 0.5 | G8: 0.7 | H8: 1 | I8: 1 | J8: 1 | K8: 1 | L8: 1 | M8: 1 | N8: 1 | O8: 1 | P8: 1 | Q8: 1 | R8: 1 | S8: 1 | T8: 1 | U8: 1 | V8: 1 | W8: 1 | X8: 1 | Y8: 1 | Z8: 1 | AA8: 1 | AB8: 1 | AC8: 1 | AD8: 1
B9: =IF(C9<>"",SUBTOTAL(3,C$4:C9),"") -> 6 | C9: Tỷ lệ hao hụt | F9: 0.07 | G9: 0.07 | H9: 0.07 | I9: 0.07 | J9: 0.07 | K9: 0.07 | L9: 0.07 | M9: 0.07 | N9: 0.07 | O9: 0.07 | P9: 0.07 | Q9: 0.07 | R9: 0.07 | S9: 0.07 | T9: 0.07 | U9: 0.07 | V9: 0.07 | W9: 0.07 | X9: 0.07 | Y9: 0.07 | Z9: 0.07 | AA9: 0.07 | AB9: 0.07 | AC9: 0.07 | AD9: 0.07
B10: =IF(C10<>"",SUBTOTAL(3,C$4:C10),"") -> 7 | C10: Số ngày hoạt động | F10: 160.6 | G10: 224.84 | H10: 321.2 | I10: 321.2 | J10: 321.2 | K10: 321.2 | L10: 321.2 | M10: 321.2 | N10: 321.2 | O10: 321.2 | P10: 321.2 | Q10: 321.2 | R10: 321.2 | S10: 321.2 | T10: 321.2 | U10: 321.2 | V10: 321.2 | W10: 321.2 | X10: 321.2 | Y10: 321.2 | Z10: 321.2 | AA10: 321.2 | AB10: 321.2 | AC10: 321.2 | AD10: 321.2
B11: =IF(C11<>"",SUBTOTAL(3,C$4:C11),"") -> 8 | C11: Sản lượng sản xuất | D11: kg/năm | F11: 3097087.5 | G11: 4335922.5 | H11: 6194175 | I11: 6194175 | J11: 6194175 | K11: 6194175 | L11: 6194175 | M11: 6194175 | N11: 6194175 | O11: 6194175 | P11: 6194175 | Q11: 6194175 | R11: 6194175 | S11: 6194175 | T11: 6194175 | U11: 6194175 | V11: 6194175 | W11: 6194175 | X11: 6194175 | Y11: 6194175 | Z11: 6194175 | AA11: 6194175 | AB11: 6194175 | AC11: 6194175 | AD11: 6194175
B12: =IF(C12<>"",SUBTOTAL(3,C$4:C12),"") -> 9 | C12: Sản lượng sản xuất | D12: phôi/năm | F12: 2.064725e+08 | G12: 2.890615e+08 | H12: 4.12945e+08 | I12: 4.12945e+08 | J12: 4.12945e+08 | K12: 4.12945e+08 | L12: 4.12945e+08 | M12: 4.12945e+08 | N12: 4.12945e+08 | O12: 4.12945e+08 | P12: 4.12945e+08 | Q12: 4.12945e+08 | R12: 4.12945e+08 | S12: 4.12945e+08 | T12: 4.12945e+08 | U12: 4.12945e+08 | V12: 4.12945e+08 | W12: 4.12945e+08 | X12: 4.12945e+08 | Y12: 4.12945e+08 | Z12: 4.12945e+08 | AA12: 4.12945e+08 | AB12: 4.12945e+08 | AC12: 4.12945e+08 | AD12: 4.12945e+08
B13: =IF(C13<>"",SUBTOTAL(3,C$4:C13),"")
B14: =IF(C14<>"",SUBTOTAL(3,C$4:C14),"") -> 10 | C14: DOANH THU | D14: tr. VND | F14: 140401.3 | G14: 200493.06 | H14: 292147.02 | I14: 297989.96 | J14: 303949.76 | K14: 310028.76 | L14: 316229.33 | M14: 322553.92 | N14: 329005 | O14: 335585.1 | P14: 342296.8 | Q14: 349142.74 | R14: 356125.59 | S14: 363248.1 | T14: 370513.07 | U14: 377923.33 | V14: 385481.79 | W14: 393191.43 | X14: 401055.26 | Y14: 409076.36 | Z14: 417257.89 | AA14: 425603.05 | AB14: 434115.11 | AC14: 442797.41 | AD14: 451653.36
B15: =IF(C15<>"",SUBTOTAL(3,C$4:C15),"")
B16: =IF(C16<>"",SUBTOTAL(3,C$4:C16),"") -> 11 | C16: Định phí sản xuất | D16: tr. VND | E16: 0 | F16: -43649.937 | G16: -43649.937 | H16: -44549.235 | I16: -45493.497 | J16: -46484.973 | K16: -47526.022 | L16: -48619.124 | M16: -49766.881 | N16: -50972.026 | O16: -52237.429 | P16: -53566.101 | Q16: -54961.207 | R16: -31363.585 | S16: -32901.689 | T16: -34516.698 | U16: -36212.458 | V16: -37993.006 | W16: -39862.582 | X16: -41825.636 | Y16: -43886.842 | Z16: -46051.11 | AA16: -48323.59 | AB16: -50709.695 | AC16: -53215.104 | AD16: -55845.785
B17: =IF(C17<>"",SUBTOTAL(3,C$4:C17),"") -> 12 | C17: Khấu hao | D17: tr. VND | F17: -25062.483 | G17: -25062.483 | H17: -25062.483 | I17: -25062.483 | J17: -25062.483 | K17: -25062.483 | L17: -25062.483 | M17: -25062.483 | N17: -25062.483 | O17: -25062.483 | P17: -25062.483 | Q17: -25062.483 | R17: 0 | S17: 0 | T17: 0 | U17: 0 | V17: 0 | W17: 0 | X17: 0 | Y17: 0 | Z17: 0 | AA17: 0 | AB17: 0 | AC17: 0 | AD17: 0
B18: =IF(C18<>"",SUBTOTAL(3,C$4:C18),"") -> 13 | C18: Lương | D18: tr. VND | E18: 0 | F18: -6011.46 | G18: -6011.46 | H18: -6312.033 | I18: -6627.6346 | J18: -6959.0164 | K18: -7306.9672 | L18: -7672.3156 | M18: -8055.9313 | N18: -8458.7279 | O18: -8881.6643 | P18: -9325.7475 | Q18: -9792.0349 | R18: -10281.637 | S18: -10795.718 | T18: -11335.504 | U18: -11902.28 | V18: -12497.394 | W18: -13122.263 | X18: -13778.376 | Y18: -14467.295 | Z18: -15190.66 | AA18: -15950.193 | AB18: -16747.703 | AC18: -17585.088 | AD18: -18464.342
B19: =IF(C19<>"",SUBTOTAL(3,C$4:C19),"") -> 14 | C19: - Nhân công trực tiếp | D19: tr. VND | F19: -982.8 | G19: -982.8 | H19: -1031.94 | I19: -1083.537 | J19: -1137.7139 | K19: -1194.5995 | L19: -1254.3295 | M19: -1317.046 | N19: -1382.8983 | O19: -1452.0432 | P19: -1524.6454 | Q19: -1600.8776 | R19: -1680.9215 | S19: -1764.9676 | T19: -1853.216 | U19: -1945.8768 | V19: -2043.1706 | W19: -2145.3291 | X19: -2252.5956 | Y19: -2365.2254 | Z19: -2483.4867 | AA19: -2607.661 | AB19: -2738.044 | AC19: -2874.9462 | AD19: -3018.6935
B20: =IF(C20<>"",SUBTOTAL(3,C$4:C20),"") -> 15 | C20: - Nhân công gián tiếp | D20: tr. VND | F20: -5028.66 | G20: -5028.66 | H20: -5280.093 | I20: -5544.0976 | J20: -5821.3025 | K20: -6112.3677 | L20: -6417.986 | M20: -6738.8853 | N20: -7075.8296 | O20: -7429.6211 | P20: -7801.1021 | Q20: -8191.1573 | R20: -8600.7151 | S20: -9030.7509 | T20: -9482.2884 | U20: -9956.4028 | V20: -10454.223 | W20: -10976.934 | X20: -11525.781 | Y20: -12102.07 | Z20: -12707.173 | AA20: -13342.532 | AB20: -14009.659 | AC20: -14710.142 | AD20: -15445.649
B21: =IF(C21<>"",SUBTOTAL(3,C$4:C21),"") -> 16 | C21: Thuê kho,xưởng | D21: tr. VND | F21: -2400 | G21: -2400 | H21: -2520 | I21: -2646 | J21: -2778.3 | K21: -2917.215 | L21: -3063.0758 | M21: -3216.2295 | N21: -3377.041 | O21: -3545.8931 | P21: -3723.1877 | Q21: -3909.3471 | R21: -4104.8145 | S21: -4310.0552 | T21: -4525.5579 | U21: -4751.8358 | V21: -4989.4276 | W21: -5238.899 | X21: -5500.844 | Y21: -5775.8862 | Z21: -6064.6805 | AA21: -6367.9145 | AB21: -6686.3102 | AC21: -7020.6257 | AD21: -7371.657
B22: =IF(C22<>"",SUBTOTAL(3,C$4:C22),"") -> 17 | C22: Bảo trì | D22: tr. VND | F22: -9022.494 | G22: -9022.494 | H22: -9473.6187 | I22: -9947.2996 | J22: -10444.665 | K22: -10966.898 | L22: -11515.243 | M22: -12091.005 | N22: -12695.555 | O22: -13330.333 | P22: -13996.85 | Q22: -14696.692 | R22: -15431.527 | S22: -16203.103 | T22: -17013.258 | U22: -17863.921 | V22: -18757.117 | W22: -19694.973 | X22: -20679.722 | Y22: -21713.708 | Z22: -22799.393 | AA22: -23939.363 | AB22: -25136.331 | AC22: -26393.147 | AD22: -27712.805
B23: =IF(C23<>"",SUBTOTAL(3,C$4:C23),"") -> 18 | C23: Vận hành xe điện | D23: tr. VND | F23: -552 | G23: -552 | H23: -579.6 | I23: -608.58 | J23: -639.009 | K23: -670.95945 | L23: -704.50742 | M23: -739.73279 | N23: -776.71943 | O23: -815.5554 | P23: -856.33318 | Q23: -899.14983 | R23: -944.10733 | S23: -991.31269 | T23: -1040.8783 | U23: -1092.9222 | V23: -1147.5684 | W23: -1204.9468 | X23: -1265.1941 | Y23: -1328.4538 | Z23: -1394.8765 | AA23: -1464.6203 | AB23: -1537.8513 | AC23: -1614.7439 | AD23: -1695.4811
B24: =IF(C24<>"",SUBTOTAL(3,C$4:C24),"") -> 19 | C24: Bảo hiểm tài sản | D24: tr. VND | F24: -601.4996 | G24: -601.4996 | H24: -601.4996 | I24: -601.4996 | J24: -601.4996 | K24: -601.4996 | L24: -601.4996 | M24: -601.4996 | N24: -601.4996 | O24: -601.4996 | P24: -601.4996 | Q24: -601.4996 | R24: -601.4996 | S24: -601.4996 | T24: -601.4996 | U24: -601.4996 | V24: -601.4996 | W24: -601.4996 | X24: -601.4996 | Y24: -601.4996 | Z24: -601.4996 | AA24: -601.4996 | AB24: -601.4996 | AC24: -601.4996 | AD24: -601.4996
B25: =IF(C25<>"",SUBTOTAL(3,C$4:C25),"")
B26: =IF(C26<>"",SUBTOTAL(3,C$4:C26),"") -> 20 | C26: Biến phí sản xuất | D26: tr. VND | E26: 0 | F26: -92494.065 | G26: -128793.29 | H26: -187365.6 | I26: -191595.5 | J26: -195935.15 | K26: -200388 | L26: -204957.65 | M26: -209647.81 | N26: -214462.35 | O26: -219405.29 | P26: -224480.8 | Q26: -229693.22 | R26: -234044.55 | S26: -239544.48 | T26: -245195.38 | U26: -251002.33 | V26: -256970.6 | W26: -263105.66 | X26: -269413.23 | Y26: -275899.25 | Z26: -282569.91 | AA26: -289431.63 | AB26: -296491.13 | AC26: -303755.39 | AD26: -311231.67
B27: =IF(C27<>"",SUBTOTAL(3,C$4:C27),"") -> 21 | C27: Nguyên vật liệu | D27: tr. VND | E27: 0 | F27: -83121.832 | G27: -116370.56 | H27: -169568.54 | I27: -172959.91 | J27: -176419.11 | K27: -179947.49 | L27: -183546.44 | M27: -187217.37 | N27: -190961.71 | O27: -194780.95 | P27: -198676.57 | Q27: -202650.1 | R27: -206703.1 | S27: -210837.16 | T27: -215053.91 | U27: -219354.98 | V27: -223742.08 | W27: -228216.93 | X27: -232781.26 | Y27: -237436.89 | Z27: -242185.63 | AA27: -247029.34 | AB27: -251969.93 | AC27: -257009.32 | AD27: -262149.51
B28: =IF(C28<>"",SUBTOTAL(3,C$4:C28),"") -> 22 | C28: Vảy sạch | D28: tr. VND | F28: -77303.304 | G28: -108224.63 | H28: -157698.74 | I28: -160852.71 | J28: -164069.77 | K28: -167351.16 | L28: -170698.19 | M28: -174112.15 | N28: -177594.39 | O28: -181146.28 | P28: -184769.21 | Q28: -188464.59 | R28: -192233.88 | S28: -196078.56 | T28: -200000.13 | U28: -204000.14 | V28: -208080.14 | W28: -212241.74 | X28: -216486.58 | Y28: -220816.31 | Z28: -225232.63 | AA28: -229737.29 | AB28: -234332.03 | AC28: -239018.67 | AD28: -243799.05
B29: =IF(C29<>"",SUBTOTAL(3,C$4:C29),"") -> 23 | C29: Hao hụt | D29: tr. VND | F29: -5818.5282 | G29: -8145.9395 | H29: -11869.798 | I29: -12107.194 | J29: -12349.337 | K29: -12596.324 | L29: -12848.251 | M29: -13105.216 | N29: -13367.32 | O29: -13634.666 | P29: -13907.36 | Q29: -14185.507 | R29: -14469.217 | S29: -14758.601 | T29: -15053.773 | U29: -15354.849 | V29: -15661.946 | W29: -15975.185 | X29: -16294.688 | Y29: -16620.582 | Z29: -16952.994 | AA29: -17292.054 | AB29: -17637.895 | AC29: -17990.653 | AD29: -18350.466
B30: =IF(C30<>"",SUBTOTAL(3,C$4:C30),"") -> 24 | C30: Màu, phụ gia | D30: tr. VND | E30: 0 | F30: -632.43326 | G30: -885.40656 | H30: -1328.1098 | I30: -1394.5153 | J30: -1464.2411 | K30: -1537.4532 | L30: -1614.3258 | M30: -1695.0421 | N30: -1779.7942 | O30: -1868.7839 | P30: -1962.2231 | Q30: -2060.3343 | R30: -2163.351 | S30: -2271.5185 | T30: -2385.0945 | U30: -2504.3492 | V30: -2629.5666 | W30: -2761.045 | X30: -2899.0972 | Y30: -3044.0521 | Z30: -3196.2547 | AA30: -3356.0674 | AB30: -3523.8708 | AC30: -3700.0643 | AD30: -3885.0675
B31: =IF(C31<>"",SUBTOTAL(3,C$4:C31),"") -> 25 | C31: Màu Toner AY090 | D31: tr. VND | F31: -632.43326 | G31: -885.40656 | H31: -1328.1098 | I31: -1394.5153 | J31: -1464.2411 | K31: -1537.4532 | L31: -1614.3258 | M31: -1695.0421 | N31: -1779.7942 | O31: -1868.7839 | P31: -1962.2231 | Q31: -2060.3343 | R31: -2163.351 | S31: -2271.5185 | T31: -2385.0945 | U31: -2504.3492 | V31: -2629.5666 | W31: -2761.045 | X31: -2899.0972 | Y31: -3044.0521 | Z31: -3196.2547 | AA31: -3356.0674 | AB31: -3523.8708 | AC31: -3700.0643 | AD31: -3885.0675
B32: =IF(C32<>"",SUBTOTAL(3,C$4:C32),"") -> 26 | C32: Phụ gia AA Scavenger | D32: tr. VND | F32: 0 | G32: 0 | H32: 0 | I32: 0 | J32: 0 | K32: 0 | L32: 0 | M32: 0 | N32: 0 | O32: 0 | P32: 0 | Q32: 0 | R32: 0 | S32: 0 | T32: 0 | U32: 0 | V32: 0 | W32: 0 | X32: 0 | Y32: 0 | Z32: 0 | AA32: 0 | AB32: 0 | AC32: 0 | AD32: 0
B33: =IF(C33<>"",SUBTOTAL(3,C$4:C33),"") -> 27 | C33: Chi phí tạo phôi | D33: tr. VND | E33: 0 | F33: -8739.8001 | G33: -11537.321 | H33: -16468.955 | I33: -17241.075 | J33: -18051.8 | K33: -18903.063 | L33: -19796.888 | M33: -20735.404 | N33: -21720.846 | O33: -22755.561 | P33: -23842.011 | Q33: -24982.783 | R33: -25178.095 | S33: -26435.797 | T33: -27756.384 | U33: -29143 | V33: -30598.947 | W33: -32127.691 | X33: -33732.873 | Y33: -35418.314 | Z33: -37188.026 | AA33: -39046.225 | AB33: -40997.333 | AC33: -43045.996 | AD33: -45197.093
B34: =IF(C34<>"",SUBTOTAL(3,C$4:C34),"") -> 28 | C34: Chi phí điện | D34: tr. VND | F34: -5749.8012 | G34: -8049.7217 | H34: -12074.583 | I34: -12678.312 | J34: -13312.227 | K34: -13977.839 | L34: -14676.731 | M34: -15410.567 | N34: -16181.095 | O34: -16990.15 | P34: -17839.658 | Q34: -18731.641 | R34: -19668.223 | S34: -20651.634 | T34: -21684.215 | U34: -22768.426 | V34: -23906.847 | W34: -25102.19 | X34: -26357.299 | Y34: -27675.164 | Z34: -29058.923 | AA34: -30511.869 | AB34: -32037.462 | AC34: -33639.335 | AD34: -35321.302
B35: =IF(C35<>"",SUBTOTAL(3,C$4:C35),"") -> 29 | C35: Chi phí đóng bao bì | D35: tr. VND | F35: -975.00902 | G35: -1365.0126 | H35: -2047.519 | I35: -2149.8949 | J35: -2257.3896 | K35: -2370.2591 | L35: -2488.7721 | M35: -2613.2107 | N35: -2743.8712 | O35: -2881.0648 | P35: -3025.118 | Q35: -3176.3739 | R35: -3335.1926 | S35: -3501.9522 | T35: -3677.0499 | U35: -3860.9024 | V35: -4053.9475 | W35: -4256.6448 | X35: -4469.4771 | Y35: -4692.9509 | Z35: -4927.5985 | AA35: -5173.9784 | AB35: -5432.6773 | AC35: -5704.3112 | AD35: -5989.5268
B36: =IF(C36<>"",SUBTOTAL(3,C$4:C36),"") -> 30 | C36: Chi phí bằng tiền khác | D36: tr. VND | F36: -2014.9899 | G36: -2122.5868 | H36: -2346.8534 | I36: -2412.8682 | J36: -2482.1836 | K36: -2554.9648 | L36: -2631.3851 | M36: -2711.6264 | N36: -2795.8797 | O36: -2884.3457 | P36: -2977.2351 | Q36: -3074.7688 | R36: -2174.68 | S36: -2282.211 | T36: -2395.1185 | U36: -2513.6715 | V36: -2638.152 | W36: -2768.8566 | X36: -2906.0965 | Y36: -3050.1983 | Z36: -3201.5052 | AA36: -3360.3775 | AB36: -3527.1934 | AC36: -3702.35 | AD36: -3886.2645
B37: =IF(C37<>"",SUBTOTAL(3,C$4:C37),"")
B38: =IF(C38<>"",SUBTOTAL(3,C$4:C38),"") -> 31 | C38: TỔNG CHI PHÍ SẢN XUẤT | D38: tr. VND | E38: 0 | F38: -136144 | G38: -172443.23 | H38: -231914.84 | I38: -237089 | J38: -242420.12 | K38: -247914.03 | L38: -253576.78 | M38: -259414.69 | N38: -265434.38 | O38: -271642.72 | P38: -278046.9 | Q38: -284654.42 | R38: -265408.13 | S38: -272446.17 | T38: -279712.08 | U38: -287214.79 | V38: -294963.6 | W38: -302968.24 | X38: -311238.87 | Y38: -319786.1 | Z38: -328621.02 | AA38: -337755.22 | AB38: -347200.82 | AC38: -356970.49 | AD38: -367077.46
B39: =IF(C39<>"",SUBTOTAL(3,C$4:C39),"")
B40: =IF(C40<>"",SUBTOTAL(3,C$4:C40),"") -> 32 | C40: Chi phí vận chuyển | D40: tr. VND | F40: -2752.9667 | G40: -3854.1533 | H40: -5781.23 | I40: -6070.2915 | J40: -6373.8061 | K40: -6692.4964 | L40: -7027.1212 | M40: -7378.4772 | N40: -7747.4011 | O40: -8134.7711 | P40: -8541.5097 | Q40: -8968.5852 | R40: -9417.0144 | S40: -9887.8652 | T40: -10382.258 | U40: -10901.371 | V40: -11446.44 | W40: -12018.762 | X40: -12619.7 | Y40: -13250.685 | Z40: -13913.219 | AA40: -14608.88 | AB40: -15339.324 | AC40: -16106.29 | AD40: -16911.605
B41: =IF(C41<>"",SUBTOTAL(3,C$4:C41),"") -> 33 | C41: Chi phí nhân sự BH,QLDN | D41: tr. VND | F41: 0 | G41: 0 | H41: 0 | I41: 0 | J41: 0 | K41: 0 | L41: 0 | M41: 0 | N41: 0 | O41: 0 | P41: 0 | Q41: 0 | R41: 0 | S41: 0 | T41: 0 | U41: 0 | V41: 0 | W41: 0 | X41: 0 | Y41: 0 | Z41: 0 | AA41: 0 | AB41: 0 | AC41: 0 | AD41: 0
B42: =IF(C42<>"",SUBTOTAL(3,C$4:C42),"") -> 34 | C42: Chi phí quản lý chung | D42: tr. VND | F42: 0 | G42: 0 | H42: 0 | I42: 0 | J42: 0 | K42: 0 | L42: 0 | M42: 0 | N42: 0 | O42: 0 | P42: 0 | Q42: 0 | R42: 0 | S42: 0 | T42: 0 | U42: 0 | V42: 0 | W42: 0 | X42: 0 | Y42: 0 | Z42: 0 | AA42: 0 | AB42: 0 | AC42: 0 | AD42: 0
B43: =IF(C43<>"",SUBTOTAL(3,C$4:C43),"") -> 35 | C43: Chi phí lãi vay | D43: tr. VND | F43: -14736.74 | G43: -14580.731 | H43: -14413.801 | I43: -14235.187 | J43: -14044.069 | K43: -13839.573 | L43: -13620.762 | M43: -13386.634 | N43: -13136.118 | O43: -12868.065 | P43: -12581.249 | Q43: -12274.355 | R43: -11945.979 | S43: -11594.617 | T43: -11218.659 | U43: -10816.385 | V43: -10385.951 | W43: -9925.3863 | X43: -9432.5825 | Y43: -8905.2824 | Z43: -8341.0712 | AA43: -7737.3653 | AB43: -7091.4 | AC43: -6400.2171 | AD43: -5660.6514
B44: =IF(C44<>"",SUBTOTAL(3,C$4:C44),"")
B45: =IF(C45<>"",SUBTOTAL(3,C$4:C45),"") -> 36 | C45: TỔNG CHI PHÍ | D45: tr. VND | E45: 0 | F45: -153633.71 | G45: -190878.11 | H45: -252109.87 | I45: -257394.47 | J45: -262838 | K45: -268446.1 | L45: -274224.66 | M45: -280179.81 | N45: -286317.9 | O45: -292645.56 | P45: -299169.66 | Q45: -305897.36 | R45: -286771.13 | S45: -293928.65 | T45: -301313 | U45: -308932.55 | V45: -316795.99 | W45: -324912.39 | X45: -333291.15 | Y45: -341942.06 | Z45: -350875.31 | AA45: -360101.47 | AB45: -369631.55 | AC45: -379477 | AD45: -389649.71
B46: =IF(C46<>"",SUBTOTAL(3,C$4:C46),"")
B47: =IF(C47<>"",SUBTOTAL(3,C$4:C47),"") -> 37 | C47: LNTT | D47: tr. VND | F47: -13232.41 | G47: 9614.9418 | H47: 40037.156 | I47: 40595.491 | J47: 41111.768 | K47: 41582.664 | L47: 42004.675 | M47: 42374.115 | N47: 42687.099 | O47: 42939.541 | P47: 43127.141 | Q47: 43245.374 | R47: 69354.467 | S47: 69319.455 | T47: 69200.066 | U47: 68990.78 | V47: 68685.8 | W47: 68279.038 | X47: 67764.106 | Y47: 67134.299 | Z47: 66382.583 | AA47: 65501.581 | AB47: 64483.561 | AC47: 63320.414 | AD47: 62003.647
B48: =IF(C48<>"",SUBTOTAL(3,C$4:C48),"") -> 38 | C48: %LNTT | F48: -0.09424706 | G48: 0.047956483 | H48: 0.13704455 | I48: 0.13623107 | J48: 0.13525843 | K48: 0.13412518 | L48: 0.13282979 | M48: 0.13137064 | N48: 0.12974605 | O48: 0.12795425 | P48: 0.12599341 | Q48: 0.12386159 | R48: 0.19474721 | S48: 0.19083225 | T48: 0.18676822 | U48: 0.18255232 | V48: 0.1781817 | W48: 0.17365342 | X48: 0.16896451 | Y48: 0.1641119 | Z48: 0.15909246 | AA48: 0.15390299 | AB48: 0.14854024 | AC48: 0.14300087 | AD48: 0.13728149
B49: =IF(C49<>"",SUBTOTAL(3,C$4:C49),"") -> 39 | C49: LNST | D49: tr. VND | F49: -10585.928 | G49: 7691.9535 | H49: 32029.725 | I49: 32476.393 | J49: 32889.415 | K49: 33266.131 | L49: 33603.74 | M49: 33899.292 | N49: 34149.679 | O49: 34351.633 | P49: 34501.712 | Q49: 34596.299 | R49: 55483.573 | S49: 55455.564 | T49: 55360.052 | U49: 55192.624 | V49: 54948.64 | W49: 54623.231 | X49: 54211.285 | Y49: 53707.439 | Z49: 53106.066 | AA49: 52401.265 | AB49: 51586.849 | AC49: 50656.331 | AD49: 49602.917
B50: =IF(C50<>"",SUBTOTAL(3,C$4:C50),"") -> 40 | C50: %LNST | F50: -0.075397648 | G50: 0.038365186 | H50: 0.10963564 | I50: 0.10898485 | J50: 0.10820675 | K50: 0.10730015 | L50: 0.10626383 | M50: 0.10509651 | N50: 0.10379684 | O50: 0.1023634 | P50: 0.10079473 | Q50: 0.09908927 | R50: 0.15579777 | S50: 0.1526658 | T50: 0.14941458 | U50: 0.14604186 | V50: 0.14254536 | W50: 0.13892274 | X50: 0.13517161 | Y50: 0.13128952 | Z50: 0.12727397 | AA50: 0.12312239 | AB50: 0.11883219 | AC50: 0.11440069 | AD50: 0.10982519

Sheet Sheet4
A3: Năm | B3: Dòng tiền | C3: Dòng tiền chiết khấu | D3: Dòng tiền chiết khấu Lũy kế
A4: 2026 | B4: {=TRANSPOSE('W3'!K168:AJ168)} -> -300749.8 | C4: {=TRANSPOSE('W3'!K170:AJ170)} -> -300749.8 | D4: =SUM(C$4:C4) -> -300749.8
A5: =A4+1 -> 2027 | B5: 26265.948 | C5: 24486.741 | D5: =SUM(C$4:C5) -> -276263.06
A6: =A5+1 -> 2028 | B6: 44419.022 | C6: 38605.112 | D6: =SUM(C$4:C6) -> -237657.95
A7: =A6+1 -> 2029 | B7: 68623.249 | C7: 55601.309 | D7: =SUM(C$4:C7) -> -182056.64
A8: =A7+1 -> 2030 | B8: 68927.026 | C8: 52064.439 | D8: =SUM(C$4:C8) -> -129992.2
A9: =A8+1 -> 2031 | B9: 69187.153 | C9: 48720.87 | D9: =SUM(C$4:C9) -> -81271.329
A10: =A9+1 -> 2032 | B10: 69400.272 | C10: 45560.519 | D10: =SUM(C$4:C10) -> -35710.81
A11: =A10+1 -> 2033 | B11: 69562.833 | C11: 42573.824 | D11: =SUM(C$4:C11) -> 6863.014
A12: =A11+1 -> 2034 | B12: 69671.083 | C12: 39751.715 | D12: =SUM(C$4:C12) -> 46614.729
A13: =A12+1 -> 2035 | B13: 69721.057 | C13: 37085.59 | D13: =SUM(C$4:C13) -> 83700.319
A14: =A13+1 -> 2036 | B14: 69708.569 | C14: 34567.288 | D14: =SUM(C$4:C14) -> 118267.61
A15: =A14+1 -> 2037 | B15: 69629.195 | C15: 32189.07 | D15: =SUM(C$4:C15) -> 150456.68
A16: =A15+1 -> 2038 | B16: 69478.267 | C16: 29943.595 | D16: =SUM(C$4:C16) -> 180400.27
... A29: =A28+1 -> 2051 | B29: 54131.439 | C29: 9373.4059 | D29: =SUM(C$4:C29) -> 399543.43

Sheet ||

Sheet Summary-cũ
B1: Công ty CP Nhựa tái chế Duy Tân
B2: Đơn vị: Kế toán quản trị
B3: DỰ ÁN FLAKES TO PREFORM SUNTORY - PEPSICO
B4: MỘT SỐ CHỈ TIÊU TRỌNG YẾU
B5: 15gr Hotfill | H5: GIÁ ĐỀ XUẤT - THÁNG 12/2025 : | I5: 680
A7: STT | B7: CHỈ TIÊU | C7: Đvt | E7: BÁO GIÁ LẦN 1-CÓ TÍNH ĐẦU TƯ XƯỞNG | F7: BÁO GIÁ LẦN 2 - CÓ TÍNH ĐẦU TƯ XƯỞNG | H7: CẬP NHẬT THÁNG 12 / 2025 | K7: CƠ SỞ
H8: TÍNH ĐẦU TƯ XƯỞNG | I8: KHÔNG TÍNH ĐẦU TƯ XƯỞNG | K8: KHÔNG TÍNH ĐẦU TƯ XƯỞNG
E9: Tháng 10/2024 | F9: Tháng 02/2025
A10: 1 | B10: Đơn giá bán phôi | C10: USD/tấn | E10: =E11*(1000000/'Cover Page'!$F$25)/EXR -> 1893.5897 | F10: =F11*(1000000/'Cover Page'!$F$25)/EXR -> 1843.5897 | H10: =H11*(1000000/'Cover Page'!$F$25)/EXR -> 1743.5897 | I10: =I11*(1000000/'Cover Page'!$F$25)/EXR -> 1743.5897 | K10: =K11*(1000000/'Cover Page'!$F$25)/EXR -> 1743.5897
A11: 2 | B11: Đơn giá bán phôi | C11: VND/phôi | E11: ='W5'!G4 -> 738.5 | F11: ='W5'!I4 -> 719 | H11: =I5 -> 680 | I11: =H11 -> 680 | K11: =I5 -> 680
A12: 3 | B12: Giá thành phôi | C12: USD/tấn | E12: =E13*(1000000/'Cover Page'!$F$25)/EXR -> 1777.0703 | F12: =F13*(1000000/'Cover Page'!$F$25)/EXR -> 1777.0703 | H12: =H13*(1000000/'Cover Page'!$F$25)/EXR -> 1722.3214 | I12: =I13*(1000000/'Cover Page'!$F$25)/EXR -> 1630.4375 | K12: =K13*(1000000/'Cover Page'!$F$25)/EXR -> 1565.4277
A13: 4 | B13: Giá thành phôi | C13: VND/phôi | E13: ='W5'!G6 -> 693.05742 | F13: ='W5'!I6 -> 693.05742 | H13: ='W5'!M6 -> 671.70535 | I13: ='W5'!O6 -> 635.87063 | K13: ='W5'!E6 -> 610.51682
A14: 5 | B14: Lợi nhuận sau thuế | C14: USD/tấn | E14: =E15*(1000000/'Cover Page'!$F$25)/EXR -> 93.215542 | F14: =F15*(1000000/'Cover Page'!$F$25)/EXR -> 53.215542 | H14: =H15*(1000000/'Cover Page'!$F$25)/EXR -> 17.014676 | I14: =I15*(1000000/'Cover Page'!$F$25)/EXR -> 90.521787 | K14: =K15*(1000000/'Cover Page'!$F$25)/EXR -> 142.5296
A15: 6 | B15: Lợi nhuận sau thuế | C15: VND/phôi | E15: ='W5'!G8 -> 36.354061 | F15: ='W5'!I8 -> 20.754061 | H15: ='W5'!M8 -> 6.6357236 | I15: ='W5'!O8 -> 35.303497 | K15: ='W5'!E8 -> 55.586543
B16: %LN sau thuế | E16: ='W5'!G10 -> 0.049226894 | F16: ='W5'!I10 -> 0.028865176 | H16: ='W5'!M10 -> 0.0097584171 | I16: ='W5'!O10 -> 0.051916907 | K16: ='W5'!E10 -> 0.081744916
A17: 7 | B17: Chi phí đầu tư | C17: USD | E17: =IF(Currency="USD",'W1'!$N$60,'W1'!$N$60/EXR) -> 18708231 | F17: =IF(Currency="USD",'W1'!$S$60,'W1'!$S$60/EXR) -> 18708231 | H17: =IF(Currency="USD",'W1'!$AC$60,'W1'!$AC$60/EXR) -> 17884231 | I17: =IF(Currency="USD",'W1'!$AH$60,'W1'!$AH$60/EXR) -> 12115000 | K17: =IF(Currency="USD",'W1'!$I$60,'W1'!$I$60/EXR) -> 11567300
A18: 8 | B18: Đầu tư | C18: tỷ VND | E18: =E17*EXR/10^9 -> 486.414 | F18: =F17*EXR/10^9 -> 486.414 | H18: =H17*EXR/10^9 -> 464.99 | I18: =I17*EXR/10^9 -> 314.99 | K18: =K17*EXR/10^9 -> 300.7498
A19: 9 | B19: NPV | C19: tỷ VND | E19: ='W5'!G15/10^3 -> 293.02276 | F19: ='W5'!I15/10^3 -> 214.92889 | H19: ='W5'!M15/10^3 -> 258.1737 | I19: ='W5'!O15/10^3 -> 131.84102 | K19: ='W5'!E15/10^3 -> 399.54343
A20: 10 | B20: Thời gian hoàn vốn | C20: năm | E20: ='W5'!G13 -> 10 năm 04 tháng | F20: ='W5'!I13 -> 11 năm 08 tháng | H20: ='W5'!M13 -> 13 năm 08 tháng | I20: ='W5'!O13 -> 8 năm 02 tháng | K20: ='W5'!E13 -> 6 năm 11 tháng
A21: 11 | B21: % Lãi gộp nguyên liệu/Giá bán | C21: % | E21: ='W5'!H108 -> 0.4648998 | F21: ='W5'!J108 -> 0.45038734 | H21: ='W5'!N108 -> 0.4384 | I21: ='W5'!P108 -> 0.4384 | K21: ='W5'!F108 -> 0.4384
B23: Ghi chú: Tất cả trường hợp đều có khuôn

Sheet Summary
B1: Công ty CP Nhựa tái chế Duy Tân
B2: Đơn vị: Kế toán quản trị
B3: DỰ ÁN FLAKES TO PREFORM SUNTORY - PEPSICO
B4: MỘT SỐ CHỈ TIÊU TRỌNG YẾU
B5: 15gr Hotfill | H5: GIÁ ĐỀ XUẤT - THÁNG 12/2025 :
I6: 680
E7: Paste chết | F7: Paste chết | N7: Paste chết | O7: Paste chết
A8: STT | B8: CHỈ TIÊU | C8: Đvt | E8: BÁO GIÁ LẦN 1-CÓ TÍNH ĐẦU TƯ XƯỞNG | F8: BÁO GIÁ LẦN 2 - CÓ TÍNH ĐẦU TƯ XƯỞNG | H8: CƠ SỞ | K8: CẬP NHẬT THÁNG 12 / 2025 - BÁO GIÁ | N8: CƠ SỞ-BÁO GIÁ L1- KHÔNG TÍNH ĐẦU TƯ XƯỞNG | O8: CƠ SỞ-BÁO GIÁ L2- KHÔNG TÍNH ĐẦU TƯ XƯỞNG
H9: KHÔNG TÍNH ĐẦU TƯ XƯỞNG | I9: CÓ TÍNH ĐẦU TƯ XƯỞNG | K9: KHÔNG TÍNH ĐẦU TƯ XƯỞNG | L9: TÍNH ĐẦU TƯ XƯỞNG
E10: Tháng 10/2024 | F10: Tháng 02/2025 | N10: Tháng 10/2024 | O10: Tháng 02/2025
A11: 1 | B11: Đơn giá bán phôi | C11: USD/tấn | E11: 1969.3333 | F11: 1916 | H11: =H12*(1000000/'Cover Page'!$F$25)/EXR -> 1743.5897 | I11: =I12*(1000000/'Cover Page'!$F$25)/EXR -> 1743.5897 | K11: =K12*(1000000/'Cover Page'!$F$25)/EXR -> 1743.5897 | L11: =L12*(1000000/'Cover Page'!$F$25)/EXR -> 1743.5897 | N11: 1941.3333 | O11: 1941.3333
A12: 2 | B12: Đơn giá bán phôi | C12: VND/phôi | E12: 738.5 | F12: 718.5 | H12: =I6 -> 680 | I12: =I6 -> 680 | K12: =L12 -> 680 | L12: =I6 -> 680 | N12: 728 | O12: 728
A13: 3 | B13: Giá thành phôi | C13: USD/tấn | E13: 1860.577 | F13: 1793.6349 | H13: =H14*(1000000/'Cover Page'!$F$25)/EXR -> 1565.4277 | I13: =I14*(1000000/'Cover Page'!$F$25)/EXR -> 1650.7494 | K13: =K14*(1000000/'Cover Page'!$F$25)/EXR -> 1630.4375 | L13: =L14*(1000000/'Cover Page'!$F$25)/EXR -> 1722.3214 | N13: 1669.9635 | O13: 1609.1598
A14: 4 | B14: Giá thành phôi | C14: VND/phôi | E14: 697.71636 | F14: 672.61307 | H14: ='W5'!E6 -> 610.51682 | I14: ='W5'!K6 -> 643.79228 | K14: ='W5'!O6 -> 635.87063 | L14: ='W5'!M6 -> 671.70535 | N14: 626.2363 | O14: 603.43491
A15: 5 | B15: Lợi nhuận sau thuế | C15: USD/tấn | E15: 87.005099 | F15: 97.892107 | H15: =H16*(1000000/'Cover Page'!$F$25)/EXR -> 142.5296 | I15: =I16*(1000000/'Cover Page'!$F$25)/EXR -> 74.272251 | K15: =K16*(1000000/'Cover Page'!$F$25)/EXR -> 90.521787 | L15: =L16*(1000000/'Cover Page'!$F$25)/EXR -> 17.014676 | N15: 199.32165 | O15: 247.96461
A16: 6 | B16: Lợi nhuận sau thuế | C16: VND/phôi | E16: 32.626912 | F16: 36.70954 | H16: ='W5'!E8 -> 55.586543 | I16: ='W5'!K8 -> 28.966178 | K16: ='W5'!O8 -> 35.303497 | L16: ='W5'!M8 -> 6.6357236 | N16: 74.745621 | O16: 92.986729
B17: %LN sau thuế | E17: 0.044179976 | F17: 0.051091914 | H17: ='W5'!E10 -> 0.081744916 | I17: ='W5'!K10 -> 0.04259732 | K17: ='W5'!O10 -> 0.051916907 | L17: ='W5'!M10 -> 0.0097584171 | N17: 0.11182825 | O17: 0.12772902
A18: 7 | B18: Chi phí đầu tư | C18: USD | E18: 17070000 | F18: 17070000 | H18: =IF(Currency="USD",'W1'!$I$60,'W1'!$I$60/EXR) -> 11567300 | I18: =IF(Currency="USD",'W1'!$X$60,'W1'!$X$60/EXR) -> 17336531 | K18: =IF(Currency="USD",'W1'!$AH$60,'W1'!$AH$60/EXR) -> 12115000 | L18: =IF(Currency="USD",'W1'!$AC$60,'W1'!$AC$60/EXR) -> 17884231 | N18: 10054913 | O18: 10054913
A19: 8 | B19: Đầu tư | C19: tỷ VND | E19: 426.75 | F19: 426.75 | H19: =H18*EXR/10^9 -> 300.7498 | I19: =I18*EXR/10^9 -> 450.7498 | K19: =K18*EXR/10^9 -> 314.99 | L19: =L18*EXR/10^9 -> 464.99 | N19: 251.37282 | O19: 251.37282
A20: 9 | B20: NPV | C20: tỷ VND | E20: 284.37183 | F20: 240.81878 | H20: ='W5'!E15/10^3 -> 399.54343 | I20: ='W5'!K15/10^3 -> 258.1737 | K20: ='W5'!O15/10^3 -> 131.84102 | L20: ='W5'!M15/10^3 -> 258.1737 | N20: 491.97502 | O20: 487.89218
A21: 10 | B21: Thời gian hoàn vốn | C21: năm | E21: 9 năm 08 tháng | F21: 10 năm 08 tháng | H21: ='W5'!E13 -> 6 năm 11 tháng | I21: ='W5'!K13 -> 10 năm 11 tháng | K21: ='W5'!O13 -> 8 năm 02 tháng | L21: ='W5'!M13 -> 13 năm 08 tháng | N21: 5 năm 05 tháng | O21: 5 năm 07 tháng
A22: 11 | B22: % Lãi gộp nguyên liệu/Giá bán | C22: % | E22: 0.4648998 | F22: 0.45000487 | H22: ='W5'!F108 -> 0.4384 | I22: ='W5'!L108 -> 0.4384 | K22: ='W5'!P108 -> 0.4384 | L22: ='W5'!N108 -> 0.4384 | N22: 0.45718201 | O22: 0.45718201
B26: Đầu tư khuôn | H26: x | I26: x | K26: x | L26: x
B27: Đầu tư xưởng | E27: x | F27: x | I27: x | L27: x
B29: Vảy sạch | E29: 1033 | F29: 1033

Sheet Cover Page
D3: COVER PAGE
D4: CHỈ TIÊU | H4: Base | K4: BÁO GIÁ L1 | N4: BÁO GIÁ L2 | Q4: Base-CÓ XƯỞNG | T4: UPDATED T12.25 | W4: UPDATED T12.25-KHÔNG CÓ THUÊ XƯỜNG | Z4: Công suất máy
C5: STT | D5: GIẢ ĐỊNH | E5: Đvt | F5: CHUNG | H5: OPTION 1 | K5: OPTION 2 | N5: OPTION 3 | Q5: OPTION 4 | T5: OPTION 5 | W5: OPTION 6 | Z5: Công suất máy
C6: 1 | D6: CAPEX | H6: Thực tế | K6: 0.07 | N6: 0.07 | Q6: 0 | T6: 0 | W6: 0
C7: 2 | D7: Chi phí sản xuất | H7: Thực tế | K7: 0.05 | N7: 0.05 | Q7: 0 | T7: 0.05 | W7: 0.05
D8: Chi phí vảy tăng | H8: 0.02 | K8: 0.02 | N8: 0.02 | Q8: 0.02 | T8: 0.02 | W8: 0.02
C9: 3 | D9: Lạm Phát | F9: 0.05
C10: 4 | D10: Tỷ giá | F10: 26000
C11: 5 | D11: Thuế suất TNDN: | F11: 0.2
C12: 6 | D12: Mark-up giá bán | H12: =5%/(1-Tax_rate-5%) -> 0.066666667 | K12: =5%/(1-Tax_rate-5%) -> 0.066666667 | N12: =5%/(1-Tax_rate-5%) -> 0.066666667 | Q12: =5%/(1-Tax_rate-5%) -> 0.066666667 | T12: =5%/(1-Tax_rate-5%) -> 0.066666667 | W12: =5%/(1-Tax_rate-5%) -> 0.066666667
C13: 7.1 | D13: Đơn giá ban đầu | E13: tr. VND/tấn | H13: =H14*PHOI_KG*10^3/10^6 -> 45.333333 | K13: =K14*PHOI_KG*10^3/10^6 -> 49.233333 | N13: =N14*PHOI_KG*10^3/10^6 -> 47.933333 | Q13: =Q14*PHOI_KG*10^3/10^6 -> 45.333333 | T13: =T14*PHOI_KG*10^3/10^6 -> 45.333333 | W13: =W14*PHOI_KG*10^3/10^6 -> 45.333333
C14: 7.2 | D14: Đơn giá ban đầu | E14: VND/phôi | H14: ='W5'!U2 -> 680 | K14: ='W5'!V2 -> 738.5 | N14: ='W5'!W2 -> 719 | Q14: ='W5'!X2 -> 680 | T14: ='W5'!Y2 -> 680 | W14: ='W5'!Z2 -> 680 | Y14: Lấy số từ W5
C15: 7.3 | D15: Đơn giá ban đầu | E15: USD/tấn | H15: =H13/EXR*10^6 -> 1743.5897 | K15: =K13/EXR*10^6 -> 1893.5897 | N15: =N13/EXR*10^6 -> 1843.5897 | Q15: =Q13/EXR*10^6 -> 1743.5897 | T15: =T13/EXR*10^6 -> 1743.5897 | W15: =W13/EXR*10^6 -> 1743.5897
C16: 7.4 | D16: Đơn giá ban đầu | E16: USD/1.000 phôi | H16: =H15/PHOI_KG -> 26.153846 | K16: =K15/PHOI_KG -> 28.403846 | W16: =W15/PHOI_KG -> 26.153846
C17: 8 | D17: Tỷ lệ tăng đơn giá | H17: 0.02 | K17: 0.02 | N17: 0.02 | Q17: 0.02 | T17: 0.02 | W17: 0.02 | Y17: tăng mỗi năm
C19: 9.1 | D19: Lãi suất đi vay: | H19: 0.07 | K19: 0.08 | N19: 0.08 | Q19: 0.07 | T19: 0.08 | W19: 0.08
C20: 9.2 | D20: Lợi nhuận mong muốn cổ đông: | H20: 0.1 | K20: 0.1 | N20: 0.1 | Q20: 0.1 | T20: 0.1 | W20: 0.1
C21: 9.3 | D21: Cơ cấu vay mong muốn: | H21: 0.7 | K21: 0.7 | N21: 0.7 | Q21: 0.7 | T21: 0.7 | W21: 0.7
C22: 9.4 | D22: Cơ cấu VCSH: | H22: =1-H21 -> 0.3 | K22: =1-K21 -> 0.3 | N22: =1-N21 -> 0.3 | Q22: =1-Q21 -> 0.3 | T22: =1-T21 -> 0.3 | W22: =1-W21 -> 0.3
C23: 9.5 | D23: WACC: | H23: =(H19*H21*(1-Tax_rate)+H20*H22)*(1+Inflation) -> 0.07266 | K23: =(K19*K21*(1-Tax_rate)+K20*K22)*(1+Inflation) -> 0.07854 | N23: =(N19*N21*(1-Tax_rate)+N20*N22)*(1+Inflation) -> 0.07854 | Q23: =(Q19*Q21*(1-Tax_rate)+Q20*Q22)*(1+Inflation) -> 0.07266 | T23: =(T19*T21*(1-Tax_rate)+T20*T22)*(1+Inflation) -> 0.07854 | W23: =(W19*W21*(1-Tax_rate)+W20*W22)*(1+Inflation) -> 0.07854
C25: 10.1 | D25: Khuôn phôi | E25: gram | F25: 15
C26: 10.2 | D26: Số lượng phôi/chu kỳ: | E26: phôi/chu kỳ | F26: 128
C27: 10.3 | D27: Chu kỳ | E27: giây | F27: 8
C28: 10.4 | D28: Công suất | E28: kg/giờ | F28: =60*60/F27*F26*F25/10^3 -> 864
C29: 10.5 | D29: Công suất | E29: phôi/giờ | F29: =Capacity/F25*10^3 -> 57600
C30: 10.6 | D30: Số phôi/kg | E30: phôi/kg | F30: =1000/F25 -> 66.666667
A33: =MD!A7 -> VND | D33: KẾT QUẢ
A34: =IF(Currency="USD",1,0.000001) -> 1e-06 | C34: 11 | D34: Tổng mức đầu tư | E34: =IF(Currency="USD","USD","triệu VND") -> triệu VND | H34: ='W1'!I60*$A$34 -> 300749.8 | K34: ='W1'!N60*$A$34 -> 486414 | N34: ='W1'!S60*$A$34 -> 486414 | Q34: ='W1'!X60*$A$34 -> 450749.8 | T34: ='W1'!AC60*$A$34 -> 464990 | W34: ='W1'!AH60*$A$34 -> 314990
B35: DPP | C35: 12 | D35: Thời gian thu hồi vốn | E35: năm | H35: =SUMIFS('W3'!$K$18:$K$1018,'W3'!$A$18:$A$1018,H$5,'W3'!$D$18:$D$1018,$B$35) -> 6.9 | K35: =SUMIFS('W3'!$K$18:$K$1018,'W3'!$A$18:$A$1018,K$5,'W3'!$D$18:$D$1018,$B$35) -> 10.3 | N35: =SUMIFS('W3'!$K$18:$K$1018,'W3'!$A$18:$A$1018,N$5,'W3'!$D$18:$D$1018,$B$35) -> 11.7 | Q35: =SUMIFS('W3'!$K$18:$K$1018,'W3'!$A$18:$A$1018,Q$5,'W3'!$D$18:$D$1018,$B$35) -> 10.9 | T35: =SUMIFS('W3'!$K$18:$K$1018,'W3'!$A$18:$A$1018,T$5,'W3'!$D$18:$D$1018,$B$35) -> 13.7 | W35: =SUMIFS('W3'!$K$18:$K$1018,'W3'!$A$18:$A$1018,W$5,'W3'!$D$18:$D$1018,$B$35) -> 8.2
H36: =INT(H35)&" năm "&IF(MOD(H35,1)*12=0,,TEXT(MOD(H35,1)*12,"00")&" tháng") -> 6 năm 11 tháng | K36: =INT(K35)&" năm "&IF(MOD(K35,1)*12=0,,TEXT(MOD(K35,1)*12,"00")&" tháng") -> 10 năm 04 tháng | N36: =INT(N35)&" năm "&IF(MOD(N35,1)*12=0,,TEXT(MOD(N35,1)*12,"00")&" tháng") -> 11 năm 08 tháng | Q36: =INT(Q35)&" năm "&IF(MOD(Q35,1)*12=0,,TEXT(MOD(Q35,1)*12,"00")&" tháng") -> 10 năm 11 tháng | T36: =INT(T35)&" năm "&IF(MOD(T35,1)*12=0,,TEXT(MOD(T35,1)*12,"00")&" tháng") -> 13 năm 08 tháng | W36: =INT(W35)&" năm "&IF(MOD(W35,1)*12=0,,TEXT(MOD(W35,1)*12,"00")&" tháng") -> 8 năm 02 tháng
B37: IRR | C37: 13 | D37: Tỷ suất hoàn vốn nội bộ (IRR) | E37: % | H37: =SUMIFS('W3'!$K$18:$K$1018,'W3'!$A$18:$A$1018,H$5,'W3'!$D$18:$D$1018,$B$37) -> 0.19092375 | K37: =SUMIFS('W3'!$K$18:$K$1018,'W3'!$A$18:$A$1018,K$5,'W3'!$D$18:$D$1018,$B$37) -> 0.13870388 | N37: =SUMIFS('W3'!$K$18:$K$1018,'W3'!$A$18:$A$1018,N$5,'W3'!$D$18:$D$1018,$B$37) -> 0.12432694 | Q37: =SUMIFS('W3'!$K$18:$K$1018,'W3'!$A$18:$A$1018,Q$5,'W3'!$D$18:$D$1018,$B$37) -> 0.1285189 | T37: =SUMIFS('W3'!$K$18:$K$1018,'W3'!$A$18:$A$1018,T$5,'W3'!$D$18:$D$1018,$B$37) -> 0.10937322 | W37: =SUMIFS('W3'!$K$18:$K$1018,'W3'!$A$18:$A$1018,W$5,'W3'!$D$18:$D$1018,$B$37) -> 0.16522194
D39: Đơn giá năm đầu | E39: VND/phôi | H39: =H14 -> 680 | K39: =K14 -> 738.5 | N39: =N14 -> 719 | Q39: =Q14 -> 680 | T39: =T14 -> 680 | W39: =W14 -> 680
D40: Đơn giá năm đầu | E40: USD/tấn | H40: =H15 -> 1743.5897 | K40: =K15 -> 1893.5897 | N40: =N15 -> 1843.5897 | Q40: =Q15 -> 1743.5897 | T40: =T15 -> 1743.5897 | W40: =W15 -> 1743.5897
B42: NPV | C42: 14 | D42: Dòng tiền chiết khẩu | E42: =IF(Currency="USD","USD","triệu VND") -> triệu VND | H42: =SUM(H43:H68) -> 399543.43 | K42: =SUM(K43:K68) -> 293022.76 | N42: =SUM(N43:N68) -> 214928.89 | Q42: =SUM(Q43:Q68) -> 258173.7 | T42: =SUM(T43:T68) -> 131841.02 | W42: =SUM(W43:W68) -> 273643.27
D43: 0 | E43: =IF(Currency="USD","USD","triệu VND") -> triệu VND | H43: {=SUMPRODUCT('W3'!$K$18:$AJ$1018*('W3'!$A$18:$A$1018=H$5)*('W3'!$D$18:$D$1018=$B$42)*('W3'!$K$14:$AJ$14='Cover Page'!$D43))} -> -300749.8 | K43: {=SUMPRODUCT('W3'!$K$18:$AJ$1018*('W3'!$A$18:$A$1018=K$5)*('W3'!$D$18:$D$1018=$B$42)*('W3'!$K$14:$AJ$14='Cover Page'!$D43))} -> -486414 | N43: {=SUMPRODUCT('W3'!$K$18:$AJ$1018*('W3'!$A$18:$A$1018=N$5)*('W3'!$D$18:$D$1018=$B$42)*('W3'!$K$14:$AJ$14='Cover Page'!$D43))} -> -486414 | Q43: {=SUMPRODUCT('W3'!$K$18:$AJ$1018*('W3'!$A$18:$A$1018=Q$5)*('W3'!$D$18:$D$1018=$B$42)*('W3'!$K$14:$AJ$14='Cover Page'!$D43))} -> -450749.8 | T43: {=SUMPRODUCT('W3'!$K$18:$AJ$1018*('W3'!$A$18:$A$1018=T$5)*('W3'!$D$18:$D$1018=$B$42)*('W3'!$K$14:$AJ$14='Cover Page'!$D43))} -> -464990 | W43: {=SUMPRODUCT('W3'!$K$18:$AJ$1018*('W3'!$A$18:$A$1018=W$5)*('W3'!$D$18:$D$1018=$B$42)*('W3'!$K$14:$AJ$14='Cover Page'!$D43))} -> -314990 | AH43: Giả định: sau 25 năm thì giá trị các tài sản còn lại =0
D44: 1 | E44: =IF(Currency="USD","USD","triệu VND") -> triệu VND | H44: {=SUMPRODUCT('W3'!$K$18:$AJ$1018*('W3'!$A$18:$A$1018=H$5)*('W3'!$D$18:$D$1018=$B$42)*('W3'!$K$14:$AJ$14='Cover Page'!$D44))} -> 24486.741 | K44: {=SUMPRODUCT('W3'!$K$18:$AJ$1018*('W3'!$A$18:$A$1018=K$5)*('W3'!$D$18:$D$1018=$B$42)*('W3'!$K$14:$AJ$14='Cover Page'!$D44))} -> 28874.473 | N44: {=SUMPRODUCT('W3'!$K$18:$AJ$1018*('W3'!$A$18:$A$1018=N$5)*('W3'!$D$18:$D$1018=$B$42)*('W3'!$K$14:$AJ$14='Cover Page'!$D44))} -> 25888.055 | Q44: {=SUMPRODUCT('W3'!$K$18:$AJ$1018*('W3'!$A$18:$A$1018=Q$5)*('W3'!$D$18:$D$1018=$B$42)*('W3'!$K$14:$AJ$14='Cover Page'!$D44))} -> 25193.769 | T44: {=SUMPRODUCT('W3'!$K$18:$AJ$1018*('W3'!$A$18:$A$1018=T$5)*('W3'!$D$18:$D$1018=$B$42)*('W3'!$K$14:$AJ$14='Cover Page'!$D44))} -> 22047.471 | W44: {=SUMPRODUCT('W3'!$K$18:$AJ$1018*('W3'!$A$18:$A$1018=W$5)*('W3'!$D$18:$D$1018=$B$42)*('W3'!$K$14:$AJ$14='Cover Page'!$D44))} -> 21344.298
D45: 2 | E45: =IF(Currency="USD","USD","triệu VND") -> triệu VND | H45: {=SUMPRODUCT('W3'!$K$18:$AJ$1018*('W3'!$A$18:$A$1018=H$5)*('W3'!$D$18:$D$1018=$B$42)*('W3'!$K$14:$AJ$14='Cover Page'!$D45))} -> 38605.112 | K45: {=SUMPRODUCT('W3'!$K$18:$AJ$1018*('W3'!$A$18:$A$1018=K$5)*('W3'!$D$18:$D$1018=$B$42)*('W3'!$K$14:$AJ$14='Cover Page'!$D45))} -> 44790.183 | N45: {=SUMPRODUCT('W3'!$K$18:$AJ$1018*('W3'!$A$18:$A$1018=N$5)*('W3'!$D$18:$D$1018=$B$42)*('W3'!$K$14:$AJ$14='Cover Page'!$D45))} -> 40836.129 | Q45: {=SUMPRODUCT('W3'!$K$18:$AJ$1018*('W3'!$A$18:$A$1018=Q$5)*('W3'!$D$18:$D$1018=$B$42)*('W3'!$K$14:$AJ$14='Cover Page'!$D45))} -> 39264.247 | T45: {=SUMPRODUCT('W3'!$K$18:$AJ$1018*('W3'!$A$18:$A$1018=T$5)*('W3'!$D$18:$D$1018=$B$42)*('W3'!$K$14:$AJ$14='Cover Page'!$D45))} -> 35572.147 | W45: {=SUMPRODUCT('W3'!$K$18:$AJ$1018*('W3'!$A$18:$A$1018=W$5)*('W3'!$D$18:$D$1018=$B$42)*('W3'!$K$14:$AJ$14='Cover Page'!$D45))} -> 34920.18
D46: 3 | E46: =IF(Currency="USD","USD","triệu VND") -> triệu VND | H46: {=SUMPRODUCT('W3'!$K$18:$AJ$1018*('W3'!$A$18:$A$1018=H$5)*('W3'!$D$18:$D$1018=$B$42)*('W3'!$K$14:$AJ$14='Cover Page'!$D46))} -> 55601.309 | K46: {=SUMPRODUCT('W3'!$K$18:$AJ$1018*('W3'!$A$18:$A$1018=K$5)*('W3'!$D$18:$D$1018=$B$42)*('W3'!$K$14:$AJ$14='Cover Page'!$D46))} -> 63999.38 | N46: {=SUMPRODUCT('W3'!$K$18:$AJ$1018*('W3'!$A$18:$A$1018=N$5)*('W3'!$D$18:$D$1018=$B$42)*('W3'!$K$14:$AJ$14='Cover Page'!$D46))} -> 58657.324 | Q46: {=SUMPRODUCT('W3'!$K$18:$AJ$1018*('W3'!$A$18:$A$1018=Q$5)*('W3'!$D$18:$D$1018=$B$42)*('W3'!$K$14:$AJ$14='Cover Page'!$D46))} -> 56215.796 | T46: {=SUMPRODUCT('W3'!$K$18:$AJ$1018*('W3'!$A$18:$A$1018=T$5)*('W3'!$D$18:$D$1018=$B$42)*('W3'!$K$14:$AJ$14='Cover Page'!$D46))} -> 51421.521 | W46: {=SUMPRODUCT('W3'!$K$18:$AJ$1018*('W3'!$A$18:$A$1018=W$5)*('W3'!$D$18:$D$1018=$B$42)*('W3'!$K$14:$AJ$14='Cover Page'!$D46))} -> 50817.03
D47: 4 | E47: =IF(Currency="USD","USD","triệu VND") -> triệu VND | H47: {=SUMPRODUCT('W3'!$K$18:$AJ$1018*('W3'!$A$18:$A$1018=H$5)*('W3'!$D$18:$D$1018=$B$42)*('W3'!$K$14:$AJ$14='Cover Page'!$D47))} -> 52064.439 | K47: {=SUMPRODUCT('W3'!$K$18:$AJ$1018*('W3'!$A$18:$A$1018=K$5)*('W3'!$D$18:$D$1018=$B$42)*('W3'!$K$14:$AJ$14='Cover Page'!$D47))} -> 59609.212 | N47: {=SUMPRODUCT('W3'!$K$18:$AJ$1018*('W3'!$A$18:$A$1018=N$5)*('W3'!$D$18:$D$1018=$B$42)*('W3'!$K$14:$AJ$14='Cover Page'!$D47))} -> 54557.108 | Q47: {=SUMPRODUCT('W3'!$K$18:$AJ$1018*('W3'!$A$18:$A$1018=Q$5)*('W3'!$D$18:$D$1018=$B$42)*('W3'!$K$14:$AJ$14='Cover Page'!$D47))} -> 52637.301 | T47: {=SUMPRODUCT('W3'!$K$18:$AJ$1018*('W3'!$A$18:$A$1018=T$5)*('W3'!$D$18:$D$1018=$B$42)*('W3'!$K$14:$AJ$14='Cover Page'!$D47))} -> 47715.111 | W47: {=SUMPRODUCT('W3'!$K$18:$AJ$1018*('W3'!$A$18:$A$1018=W$5)*('W3'!$D$18:$D$1018=$B$42)*('W3'!$K$14:$AJ$14='Cover Page'!$D47))} -> 47154.64
D48: 5 | E48: =IF(Currency="USD","USD","triệu VND") -> triệu VND | H48: {=SUMPRODUCT('W3'!$K$18:$AJ$1018*('W3'!$A$18:$A$1018=H$5)*('W3'!$D$18:$D$1018=$B$42)*('W3'!$K$14:$AJ$14='Cover Page'!$D48))} -> 48720.87 | K48: {=SUMPRODUCT('W3'!$K$18:$AJ$1018*('W3'!$A$18:$A$1018=K$5)*('W3'!$D$18:$D$1018=$B$42)*('W3'!$K$14:$AJ$14='Cover Page'!$D48))} -> 55484.945 | N48: {=SUMPRODUCT('W3'!$K$18:$AJ$1018*('W3'!$A$18:$A$1018=N$5)*('W3'!$D$18:$D$1018=$B$42)*('W3'!$K$14:$AJ$14='Cover Page'!$D48))} -> 50707.054 | Q48: {=SUMPRODUCT('W3'!$K$18:$AJ$1018*('W3'!$A$18:$A$1018=Q$5)*('W3'!$D$18:$D$1018=$B$42)*('W3'!$K$14:$AJ$14='Cover Page'!$D48))} -> 49254.927 | T48: {=SUMPRODUCT('W3'!$K$18:$AJ$1018*('W3'!$A$18:$A$1018=T$5)*('W3'!$D$18:$D$1018=$B$42)*('W3'!$K$14:$AJ$14='Cover Page'!$D48))} -> 44237.28 | W48: {=SUMPRODUCT('W3'!$K$18:$AJ$1018*('W3'!$A$18:$A$1018=W$5)*('W3'!$D$18:$D$1018=$B$42)*('W3'!$K$14:$AJ$14='Cover Page'!$D48))} -> 43717.622
D49: 6 | E49: =IF(Currency="USD","USD","triệu VND") -> triệu VND | H49: {=SUMPRODUCT('W3'!$K$18:$AJ$1018*('W3'!$A$18:$A$1018=H$5)*('W3'!$D$18:$D$1018=$B$42)*('W3'!$K$14:$AJ$14='Cover Page'!$D49))} -> 45560.519 | K49: {=SUMPRODUCT('W3'!$K$18:$AJ$1018*('W3'!$A$18:$A$1018=K$5)*('W3'!$D$18:$D$1018=$B$42)*('W3'!$K$14:$AJ$14='Cover Page'!$D49))} -> 51611.17 | N49: {=SUMPRODUCT('W3'!$K$18:$AJ$1018*('W3'!$A$18:$A$1018=N$5)*('W3'!$D$18:$D$1018=$B$42)*('W3'!$K$14:$AJ$14='Cover Page'!$D49))} -> 47092.609 | Q49: {=SUMPRODUCT('W3'!$K$18:$AJ$1018*('W3'!$A$18:$A$1018=Q$5)*('W3'!$D$18:$D$1018=$B$42)*('W3'!$K$14:$AJ$14='Cover Page'!$D49))} -> 46058.4 | T49: {=SUMPRODUCT('W3'!$K$18:$AJ$1018*('W3'!$A$18:$A$1018=T$5)*('W3'!$D$18:$D$1018=$B$42)*('W3'!$K$14:$AJ$14='Cover Page'!$D49))} -> 40974.663 | W49: {=SUMPRODUCT('W3'!$K$18:$AJ$1018*('W3'!$A$18:$A$1018=W$5)*('W3'!$D$18:$D$1018=$B$42)*('W3'!$K$14:$AJ$14='Cover Page'!$D49))} -> 40492.847
D50: 7 | E50: =IF(Currency="USD","USD","triệu VND") -> triệu VND | H50: {=SUMPRODUCT('W3'!$K$18:$AJ$1018*('W3'!$A$18:$A$1018=H$5)*('W3'!$D$18:$D$1018=$B$42)*('W3'!$K$14:$AJ$14='Cover Page'!$D50))} -> 42573.824 | K50: {=SUMPRODUCT('W3'!$K$18:$AJ$1018*('W3'!$A$18:$A$1018=K$5)*('W3'!$D$18:$D$1018=$B$42)*('W3'!$K$14:$AJ$14='Cover Page'!$D50))} -> 47973.359 | N50: {=SUMPRODUCT('W3'!$K$18:$AJ$1018*('W3'!$A$18:$A$1018=N$5)*('W3'!$D$18:$D$1018=$B$42)*('W3'!$K$14:$AJ$14='Cover Page'!$D50))} -> 43700.052 | Q50: {=SUMPRODUCT('W3'!$K$18:$AJ$1018*('W3'!$A$18:$A$1018=Q$5)*('W3'!$D$18:$D$1018=$B$42)*('W3'!$K$14:$AJ$14='Cover Page'!$D50))} -> 43037.98 | T50: {=SUMPRODUCT('W3'!$K$18:$AJ$1018*('W3'!$A$18:$A$1018=T$5)*('W3'!$D$18:$D$1018=$B$42)*('W3'!$K$14:$AJ$14='Cover Page'!$D50))} -> 37914.665 | W50: {=SUMPRODUCT('W3'!$K$18:$AJ$1018*('W3'!$A$18:$A$1018=W$5)*('W3'!$D$18:$D$1018=$B$42)*('W3'!$K$14:$AJ$14='Cover Page'!$D50))} -> 37467.936
D51: 8 | E51: =IF(Currency="USD","USD","triệu VND") -> triệu VND | H51: {=SUMPRODUCT('W3'!$K$18:$AJ$1018*('W3'!$A$18:$A$1018=H$5)*('W3'!$D$18:$D$1018=$B$42)*('W3'!$K$14:$AJ$14='Cover Page'!$D51))} -> 39751.715 | K51: {=SUMPRODUCT('W3'!$K$18:$AJ$1018*('W3'!$A$18:$A$1018=K$5)*('W3'!$D$18:$D$1018=$B$42)*('W3'!$K$14:$AJ$14='Cover Page'!$D51))} -> 44557.813 | N51: {=SUMPRODUCT('W3'!$K$18:$AJ$1018*('W3'!$A$18:$A$1018=N$5)*('W3'!$D$18:$D$1018=$B$42)*('W3'!$K$14:$AJ$14='Cover Page'!$D51))} -> 40516.45 | Q51: {=SUMPRODUCT('W3'!$K$18:$AJ$1018*('W3'!$A$18:$A$1018=Q$5)*('W3'!$D$18:$D$1018=$B$42)*('W3'!$K$14:$AJ$14='Cover Page'!$D51))} -> 40184.43 | T51: {=SUMPRODUCT('W3'!$K$18:$AJ$1018*('W3'!$A$18:$A$1018=T$5)*('W3'!$D$18:$D$1018=$B$42)*('W3'!$K$14:$AJ$14='Cover Page'!$D51))} -> 35045.414 | W51: {=SUMPRODUCT('W3'!$K$18:$AJ$1018*('W3'!$A$18:$A$1018=W$5)*('W3'!$D$18:$D$1018=$B$42)*('W3'!$K$14:$AJ$14='Cover Page'!$D51))} -> 34631.215
D52: 9 | E52: =IF(Currency="USD","USD","triệu VND") -> triệu VND | H52: {=SUMPRODUCT('W3'!$K$18:$AJ$1018*('W3'!$A$18:$A$1018=H$5)*('W3'!$D$18:$D$1018=$B$42)*('W3'!$K$14:$AJ$14='Cover Page'!$D52))} -> 37085.59 | K52: {=SUMPRODUCT('W3'!$K$18:$AJ$1018*('W3'!$A$18:$A$1018=K$5)*('W3'!$D$18:$D$1018=$B$42)*('W3'!$K$14:$AJ$14='Cover Page'!$D52))} -> 41351.618 | N52: {=SUMPRODUCT('W3'!$K$18:$AJ$1018*('W3'!$A$18:$A$1018=N$5)*('W3'!$D$18:$D$1018=$B$42)*('W3'!$K$14:$AJ$14='Cover Page'!$D52))} -> 37529.608 | Q52: {=SUMPRODUCT('W3'!$K$18:$AJ$1018*('W3'!$A$18:$A$1018=Q$5)*('W3'!$D$18:$D$1018=$B$42)*('W3'!$K$14:$AJ$14='Cover Page'!$D52))} -> 37488.993 | T52: {=SUMPRODUCT('W3'!$K$18:$AJ$1018*('W3'!$A$18:$A$1018=T$5)*('W3'!$D$18:$D$1018=$B$42)*('W3'!$K$14:$AJ$14='Cover Page'!$D52))} -> 32355.718 | W52: {=SUMPRODUCT('W3'!$K$18:$AJ$1018*('W3'!$A$18:$A$1018=W$5)*('W3'!$D$18:$D$1018=$B$42)*('W3'!$K$14:$AJ$14='Cover Page'!$D52))} -> 31971.682
D53: 10 | E53: =IF(Currency="USD","USD","triệu VND") -> triệu VND | H53: {=SUMPRODUCT('W3'!$K$18:$AJ$1018*('W3'!$A$18:$A$1018=H$5)*('W3'!$D$18:$D$1018=$B$42)*('W3'!$K$14:$AJ$14='Cover Page'!$D53))} -> 34567.288 | K53: {=SUMPRODUCT('W3'!$K$18:$AJ$1018*('W3'!$A$18:$A$1018=K$5)*('W3'!$D$18:$D$1018=$B$42)*('W3'!$K$14:$AJ$14='Cover Page'!$D53))} -> 38342.595 | N53: {=SUMPRODUCT('W3'!$K$18:$AJ$1018*('W3'!$A$18:$A$1018=N$5)*('W3'!$D$18:$D$1018=$B$42)*('W3'!$K$14:$AJ$14='Cover Page'!$D53))} -> 34728.032 | Q53: {=SUMPRODUCT('W3'!$K$18:$AJ$1018*('W3'!$A$18:$A$1018=Q$5)*('W3'!$D$18:$D$1018=$B$42)*('W3'!$K$14:$AJ$14='Cover Page'!$D53))} -> 34943.365 | T53: {=SUMPRODUCT('W3'!$K$18:$AJ$1018*('W3'!$A$18:$A$1018=T$5)*('W3'!$D$18:$D$1018=$B$42)*('W3'!$K$14:$AJ$14='Cover Page'!$D53))} -> 29835.032 | W53: {=SUMPRODUCT('W3'!$K$18:$AJ$1018*('W3'!$A$18:$A$1018=W$5)*('W3'!$D$18:$D$1018=$B$42)*('W3'!$K$14:$AJ$14='Cover Page'!$D53))} -> 29478.961
D54: 11 | E54: =IF(Currency="USD","USD","triệu VND") -> triệu VND | H54: {=SUMPRODUCT('W3'!$K$18:$AJ$1018*('W3'!$A$18:$A$1018=H$5)*('W3'!$D$18:$D$1018=$B$42)*('W3'!$K$14:$AJ$14='Cover Page'!$D54))} -> 32189.07 | K54: {=SUMPRODUCT('W3'!$K$18:$AJ$1018*('W3'!$A$18:$A$1018=K$5)*('W3'!$D$18:$D$1018=$B$42)*('W3'!$K$14:$AJ$14='Cover Page'!$D54))} -> 35519.262 | N54: {=SUMPRODUCT('W3'!$K$18:$AJ$1018*('W3'!$A$18:$A$1018=N$5)*('W3'!$D$18:$D$1018=$B$42)*('W3'!$K$14:$AJ$14='Cover Page'!$D54))} -> 32100.887 | Q54: {=SUMPRODUCT('W3'!$K$18:$AJ$1018*('W3'!$A$18:$A$1018=Q$5)*('W3'!$D$18:$D$1018=$B$42)*('W3'!$K$14:$AJ$14='Cover Page'!$D54))} -> 32539.673 | T54: {=SUMPRODUCT('W3'!$K$18:$AJ$1018*('W3'!$A$18:$A$1018=T$5)*('W3'!$D$18:$D$1018=$B$42)*('W3'!$K$14:$AJ$14='Cover Page'!$D54))} -> 27473.412 | W54: {=SUMPRODUCT('W3'!$K$18:$AJ$1018*('W3'!$A$18:$A$1018=W$5)*('W3'!$D$18:$D$1018=$B$42)*('W3'!$K$14:$AJ$14='Cover Page'!$D54))} -> 27143.271
D55: 12 | E55: =IF(Currency="USD","USD","triệu VND") -> triệu VND | H55: {=SUMPRODUCT('W3'!$K$18:$AJ$1018*('W3'!$A$18:$A$1018=H$5)*('W3'!$D$18:$D$1018=$B$42)*('W3'!$K$14:$AJ$14='Cover Page'!$D55))} -> 29943.595 | K55: {=SUMPRODUCT('W3'!$K$18:$AJ$1018*('W3'!$A$18:$A$1018=K$5)*('W3'!$D$18:$D$1018=$B$42)*('W3'!$K$14:$AJ$14='Cover Page'!$D55))} -> 32870.792 | N55: {=SUMPRODUCT('W3'!$K$18:$AJ$1018*('W3'!$A$18:$A$1018=N$5)*('W3'!$D$18:$D$1018=$B$42)*('W3'!$K$14:$AJ$14='Cover Page'!$D55))} -> 29637.956 | Q55: {=SUMPRODUCT('W3'!$K$18:$AJ$1018*('W3'!$A$18:$A$1018=Q$5)*('W3'!$D$18:$D$1018=$B$42)*('W3'!$K$14:$AJ$14='Cover Page'!$D55))} -> 30270.449 | T55: {=SUMPRODUCT('W3'!$K$18:$AJ$1018*('W3'!$A$18:$A$1018=T$5)*('W3'!$D$18:$D$1018=$B$42)*('W3'!$K$14:$AJ$14='Cover Page'!$D55))} -> 25261.491 | W55: {=SUMPRODUCT('W3'!$K$18:$AJ$1018*('W3'!$A$18:$A$1018=W$5)*('W3'!$D$18:$D$1018=$B$42)*('W3'!$K$14:$AJ$14='Cover Page'!$D55))} -> 24955.391
... D68: 25 | E68: =IF(Currency="USD","USD","triệu VND") -> triệu VND | H68: {=SUMPRODUCT('W3'!$K$18:$AJ$1018*('W3'!$A$18:$A$1018=H$5)*('W3'!$D$18:$D$1018=$B$42)*('W3'!$K$14:$AJ$14='Cover Page'!$D68))} -> 9373.4059 | K68: {=SUMPRODUCT('W3'!$K$18:$AJ$1018*('W3'!$A$18:$A$1018=K$5)*('W3'!$D$18:$D$1018=$B$42)*('W3'!$K$14:$AJ$14='Cover Page'!$D68))} -> 9703.0541 | N68: {=SUMPRODUCT('W3'!$K$18:$AJ$1018*('W3'!$A$18:$A$1018=N$5)*('W3'!$D$18:$D$1018=$B$42)*('W3'!$K$14:$AJ$14='Cover Page'!$D68))} -> 8138.0535 | Q68: {=SUMPRODUCT('W3'!$K$18:$AJ$1018*('W3'!$A$18:$A$1018=Q$5)*('W3'!$D$18:$D$1018=$B$42)*('W3'!$K$14:$AJ$14='Cover Page'!$D68))} -> 9504.7305 | T68: {=SUMPRODUCT('W3'!$K$18:$AJ$1018*('W3'!$A$18:$A$1018=T$5)*('W3'!$D$18:$D$1018=$B$42)*('W3'!$K$14:$AJ$14='Cover Page'!$D68))} -> 6058.6908 | W68: {=SUMPRODUCT('W3'!$K$18:$AJ$1018*('W3'!$A$18:$A$1018=W$5)*('W3'!$D$18:$D$1018=$B$42)*('W3'!$K$14:$AJ$14='Cover Page'!$D68))} -> 5944.1416
I70: %Dthu | L70: %Dthu | O70: %Dthu | R70: %Dthu | U70: %Dthu | X70: %Dthu
B71: LNST | C71: 15 | D71: LNST | E71: =IF(Currency="USD","USD","triệu VND") -> triệu VND | H71: =SUM(H72:H96) -> 1029205.9 | I71: =IFERROR(H71/H98,0) -> 0.11738387 | K71: =SUM(K72:K96) -> 914820.17 | L71: =IFERROR(K71/K98,0) -> 0.09607277 | N71: =SUM(N72:N96) -> 713675.04 | O71: =IFERROR(N71/N98,0) -> 0.076981559 | Q71: =SUM(Q72:Q96) -> 785179.14 | R71: =IFERROR(Q71/Q98,0) -> 0.089551924 | T71: =SUM(T72:T96) -> 485708.6 | U71: =IFERROR(T71/T98,0) -> 0.055396454 | W71: =SUM(W72:W96) -> 749077.84 | X71: =IFERROR(W71/W98,0) -> 0.085434467
D72: 1 | E72: =IF(Currency="USD","USD","triệu VND") -> triệu VND | H72: {=SUMPRODUCT('W3'!$K$18:$AJ$1018*('W3'!$A$18:$A$1018=H$5)*('W3'!$D$18:$D$1018=$B$71)*('W3'!$K$14:$AJ$14='Cover Page'!$D72))} -> -10585.928 | I72: =IFERROR(H72/H99,0) -> -0.075397648 | K72: {=SUMPRODUCT('W3'!$K$18:$AJ$1018*('W3'!$A$18:$A$1018=K$5)*('W3'!$D$18:$D$1018=$B$71)*('W3'!$K$14:$AJ$14='Cover Page'!$D72))} -> -24683.574 | L72: =IFERROR(K72/K99,0) -> -0.16188079 | N72: {=SUMPRODUCT('W3'!$K$18:$AJ$1018*('W3'!$A$18:$A$1018=N$5)*('W3'!$D$18:$D$1018=$B$71)*('W3'!$K$14:$AJ$14='Cover Page'!$D72))} -> -27904.545 | O72: =IFERROR(N72/N99,0) -> -0.18796796 | Q72: {=SUMPRODUCT('W3'!$K$18:$AJ$1018*('W3'!$A$18:$A$1018=Q$5)*('W3'!$D$18:$D$1018=$B$71)*('W3'!$K$14:$AJ$14='Cover Page'!$D72))} -> -21707.528 | R72: =IFERROR(Q72/Q99,0) -> -0.15461059 | T72: {=SUMPRODUCT('W3'!$K$18:$AJ$1018*('W3'!$A$18:$A$1018=T$5)*('W3'!$D$18:$D$1018=$B$71)*('W3'!$K$14:$AJ$14='Cover Page'!$D72))} -> -29301.64 | U72: =IFERROR(T72/T99,0) -> -0.20869921 | W72: {=SUMPRODUCT('W3'!$K$18:$AJ$1018*('W3'!$A$18:$A$1018=W$5)*('W3'!$D$18:$D$1018=$B$71)*('W3'!$K$14:$AJ$14='Cover Page'!$D72))} -> -17340.04 | X72: =IFERROR(W72/W99,0) -> -0.12350341 | Z72: {=TRANSPOSE('W3'!L23:AJ23*'W3'!L24:AJ24)} -> 0.44
D73: 2 | E73: =IF(Currency="USD","USD","triệu VND") -> triệu VND | H73: {=SUMPRODUCT('W3'!$K$18:$AJ$1018*('W3'!$A$18:$A$1018=H$5)*('W3'!$D$18:$D$1018=$B$71)*('W3'!$K$14:$AJ$14='Cover Page'!$D73))} -> 7691.9535 | I73: =IFERROR(H73/H100,0) -> 0.038365186 | K73: {=SUMPRODUCT('W3'!$K$18:$AJ$1018*('W3'!$A$18:$A$1018=K$5)*('W3'!$D$18:$D$1018=$B$71)*('W3'!$K$14:$AJ$14='Cover Page'!$D73))} -> -3531.3713 | L73: =IFERROR(K73/K100,0) -> -0.016218193 | N73: {=SUMPRODUCT('W3'!$K$18:$AJ$1018*('W3'!$A$18:$A$1018=N$5)*('W3'!$D$18:$D$1018=$B$71)*('W3'!$K$14:$AJ$14='Cover Page'!$D73))} -> -8130.9179 | O73: =IFERROR(N73/N100,0) -> -0.038354848 | Q73: {=SUMPRODUCT('W3'!$K$18:$AJ$1018*('W3'!$A$18:$A$1018=Q$5)*('W3'!$D$18:$D$1018=$B$71)*('W3'!$K$14:$AJ$14='Cover Page'!$D73))} -> -3367.3985 | R73: =IFERROR(Q73/Q100,0) -> -0.016795587 | T73: {=SUMPRODUCT('W3'!$K$18:$AJ$1018*('W3'!$A$18:$A$1018=T$5)*('W3'!$D$18:$D$1018=$B$71)*('W3'!$K$14:$AJ$14='Cover Page'!$D73))} -> -11517.582 | U73: =IFERROR(T73/T100,0) -> -0.057446287 | W73: {=SUMPRODUCT('W3'!$K$18:$AJ$1018*('W3'!$A$18:$A$1018=W$5)*('W3'!$D$18:$D$1018=$B$71)*('W3'!$K$14:$AJ$14='Cover Page'!$D73))} -> 384.69798 | X73: =IFERROR(W73/W100,0) -> 0.0019187596 | Z73: 0.616
D74: 3 | E74: =IF(Currency="USD","USD","triệu VND") -> triệu VND | H74: {=SUMPRODUCT('W3'!$K$18:$AJ$1018*('W3'!$A$18:$A$1018=H$5)*('W3'!$D$18:$D$1018=$B$71)*('W3'!$K$14:$AJ$14='Cover Page'!$D74))} -> 32029.725 | I74: =IFERROR(H74/H101,0) -> 0.10963564 | K74: {=SUMPRODUCT('W3'!$K$18:$AJ$1018*('W3'!$A$18:$A$1018=K$5)*('W3'!$D$18:$D$1018=$B$71)*('W3'!$K$14:$AJ$14='Cover Page'!$D74))} -> 24868.531 | L74: =IFERROR(K74/K101,0) -> 0.078380329 | N74: {=SUMPRODUCT('W3'!$K$18:$AJ$1018*('W3'!$A$18:$A$1018=N$5)*('W3'!$D$18:$D$1018=$B$71)*('W3'!$K$14:$AJ$14='Cover Page'!$D74))} -> 18166.335 | O74: =IFERROR(N74/N101,0) -> 0.058809281 | Q74: {=SUMPRODUCT('W3'!$K$18:$AJ$1018*('W3'!$A$18:$A$1018=Q$5)*('W3'!$D$18:$D$1018=$B$71)*('W3'!$K$14:$AJ$14='Cover Page'!$D74))} -> 21036.978 | R74: =IFERROR(Q74/Q101,0) -> 0.072008189 | T74: {=SUMPRODUCT('W3'!$K$18:$AJ$1018*('W3'!$A$18:$A$1018=T$5)*('W3'!$D$18:$D$1018=$B$71)*('W3'!$K$14:$AJ$14='Cover Page'!$D74))} -> 11815.729 | U74: =IFERROR(T74/T101,0) -> 0.040444461 | W74: {=SUMPRODUCT('W3'!$K$18:$AJ$1018*('W3'!$A$18:$A$1018=W$5)*('W3'!$D$18:$D$1018=$B$71)*('W3'!$K$14:$AJ$14='Cover Page'!$D74))} -> 23653.943 | X74: =IFERROR(W74/W101,0) -> 0.080965886 | Z74: 0.88
D75: 4 | E75: =IF(Currency="USD","USD","triệu VND") -> triệu VND | H75: {=SUMPRODUCT('W3'!$K$18:$AJ$1018*('W3'!$A$18:$A$1018=H$5)*('W3'!$D$18:$D$1018=$B$71)*('W3'!$K$14:$AJ$14='Cover Page'!$D75))} -> 32476.393 | I75: =IFERROR(H75/H102,0) -> 0.10898485 | K75: {=SUMPRODUCT('W3'!$K$18:$AJ$1018*('W3'!$A$18:$A$1018=K$5)*('W3'!$D$18:$D$1018=$B$71)*('W3'!$K$14:$AJ$14='Cover Page'!$D75))} -> 25458.671 | L75: =IFERROR(K75/K102,0) -> 0.078666985 | N75: {=SUMPRODUCT('W3'!$K$18:$AJ$1018*('W3'!$A$18:$A$1018=N$5)*('W3'!$D$18:$D$1018=$B$71)*('W3'!$K$14:$AJ$14='Cover Page'!$D75))} -> 18622.431 | O75: =IFERROR(N75/N102,0) -> 0.059103711 | Q75: {=SUMPRODUCT('W3'!$K$18:$AJ$1018*('W3'!$A$18:$A$1018=Q$5)*('W3'!$D$18:$D$1018=$B$71)*('W3'!$K$14:$AJ$14='Cover Page'!$D75))} -> 21554.914 | R75: =IFERROR(Q75/Q102,0) -> 0.072334363 | T75: {=SUMPRODUCT('W3'!$K$18:$AJ$1018*('W3'!$A$18:$A$1018=T$5)*('W3'!$D$18:$D$1018=$B$71)*('W3'!$K$14:$AJ$14='Cover Page'!$D75))} -> 12081.826 | U75: =IFERROR(T75/T102,0) -> 0.040544404 | W75: {=SUMPRODUCT('W3'!$K$18:$AJ$1018*('W3'!$A$18:$A$1018=W$5)*('W3'!$D$18:$D$1018=$B$71)*('W3'!$K$14:$AJ$14='Cover Page'!$D75))} -> 23850.848 | X75: =IFERROR(W75/W102,0) -> 0.080039098 | Z75: 0.88
D76: 5 | E76: =IF(Currency="USD","USD","triệu VND") -> triệu VND | H76: {=SUMPRODUCT('W3'!$K$18:$AJ$1018*('W3'!$A$18:$A$1018=H$5)*('W3'!$D$18:$D$1018=$B$71)*('W3'!$K$14:$AJ$14='Cover Page'!$D76))} -> 32889.415 | I76: =IFERROR(H76/H103,0) -> 0.10820675 | K76: {=SUMPRODUCT('W3'!$K$18:$AJ$1018*('W3'!$A$18:$A$1018=K$5)*('W3'!$D$18:$D$1018=$B$71)*('W3'!$K$14:$AJ$14='Cover Page'!$D76))} -> 26016.979 | L76: =IFERROR(K76/K103,0) -> 0.078815832 | N76: {=SUMPRODUCT('W3'!$K$18:$AJ$1018*('W3'!$A$18:$A$1018=N$5)*('W3'!$D$18:$D$1018=$B$71)*('W3'!$K$14:$AJ$14='Cover Page'!$D76))} -> 19044.014 | O76: =IFERROR(N76/N103,0) -> 0.059256595 | Q76: {=SUMPRODUCT('W3'!$K$18:$AJ$1018*('W3'!$A$18:$A$1018=Q$5)*('W3'!$D$18:$D$1018=$B$71)*('W3'!$K$14:$AJ$14='Cover Page'!$D76))} -> 22044.192 | R76: =IFERROR(Q76/Q103,0) -> 0.072525776 | T76: {=SUMPRODUCT('W3'!$K$18:$AJ$1018*('W3'!$A$18:$A$1018=T$5)*('W3'!$D$18:$D$1018=$B$71)*('W3'!$K$14:$AJ$14='Cover Page'!$D76))} -> 12308.824 | U76: =IFERROR(T76/T103,0) -> 0.040496245 | W76: {=SUMPRODUCT('W3'!$K$18:$AJ$1018*('W3'!$A$18:$A$1018=W$5)*('W3'!$D$18:$D$1018=$B$71)*('W3'!$K$14:$AJ$14='Cover Page'!$D76))} -> 24003.12 | X76: =IFERROR(W76/W103,0) -> 0.078970681 | Z76: 0.88
D77: 6 | E77: =IF(Currency="USD","USD","triệu VND") -> triệu VND | H77: {=SUMPRODUCT('W3'!$K$18:$AJ$1018*('W3'!$A$18:$A$1018=H$5)*('W3'!$D$18:$D$1018=$B$71)*('W3'!$K$14:$AJ$14='Cover Page'!$D77))} -> 33266.131 | I77: =IFERROR(H77/H104,0) -> 0.10730015 | K77: {=SUMPRODUCT('W3'!$K$18:$AJ$1018*('W3'!$A$18:$A$1018=K$5)*('W3'!$D$18:$D$1018=$B$71)*('W3'!$K$14:$AJ$14='Cover Page'!$D77))} -> 26541.039 | L77: =IFERROR(K77/K104,0) -> 0.078826884 | N77: {=SUMPRODUCT('W3'!$K$18:$AJ$1018*('W3'!$A$18:$A$1018=N$5)*('W3'!$D$18:$D$1018=$B$71)*('W3'!$K$14:$AJ$14='Cover Page'!$D77))} -> 19428.615 | O77: =IFERROR(N77/N104,0) -> 0.059267947 | Q77: {=SUMPRODUCT('W3'!$K$18:$AJ$1018*('W3'!$A$18:$A$1018=Q$5)*('W3'!$D$18:$D$1018=$B$71)*('W3'!$K$14:$AJ$14='Cover Page'!$D77))} -> 22502.503 | R77: =IFERROR(Q77/Q104,0) -> 0.072581986 | T77: {=SUMPRODUCT('W3'!$K$18:$AJ$1018*('W3'!$A$18:$A$1018=T$5)*('W3'!$D$18:$D$1018=$B$71)*('W3'!$K$14:$AJ$14='Cover Page'!$D77))} -> 12494.107 | U77: =IFERROR(T77/T104,0) -> 0.040299834 | W77: {=SUMPRODUCT('W3'!$K$18:$AJ$1018*('W3'!$A$18:$A$1018=W$5)*('W3'!$D$18:$D$1018=$B$71)*('W3'!$K$14:$AJ$14='Cover Page'!$D77))} -> 24107.699 | X77: =IFERROR(W77/W104,0) -> 0.077759556 | Z77: 0.88
D78: 7 | E78: =IF(Currency="USD","USD","triệu VND") -> triệu VND | H78: {=SUMPRODUCT('W3'!$K$18:$AJ$1018*('W3'!$A$18:$A$1018=H$5)*('W3'!$D$18:$D$1018=$B$71)*('W3'!$K$14:$AJ$14='Cover Page'!$D78))} -> 33603.74 | I78: =IFERROR(H78/H105,0) -> 0.10626383 | K78: {=SUMPRODUCT('W3'!$K$18:$AJ$1018*('W3'!$A$18:$A$1018=K$5)*('W3'!$D$18:$D$1018=$B$71)*('W3'!$K$14:$AJ$14='Cover Page'!$D78))} -> 27028.334 | L78: =IFERROR(K78/K105,0) -> 0.078700145 | N78: {=SUMPRODUCT('W3'!$K$18:$AJ$1018*('W3'!$A$18:$A$1018=N$5)*('W3'!$D$18:$D$1018=$B$71)*('W3'!$K$14:$AJ$14='Cover Page'!$D78))} -> 19773.661 | O78: =IFERROR(N78/N105,0) -> 0.059137771 | Q78: {=SUMPRODUCT('W3'!$K$18:$AJ$1018*('W3'!$A$18:$A$1018=Q$5)*('W3'!$D$18:$D$1018=$B$71)*('W3'!$K$14:$AJ$14='Cover Page'!$D78))} -> 22927.419 | R78: =IFERROR(Q78/Q105,0) -> 0.072502504 | T78: {=SUMPRODUCT('W3'!$K$18:$AJ$1018*('W3'!$A$18:$A$1018=T$5)*('W3'!$D$18:$D$1018=$B$71)*('W3'!$K$14:$AJ$14='Cover Page'!$D78))} -> 12634.946 | U78: =IFERROR(T78/T105,0) -> 0.039955008 | W78: {=SUMPRODUCT('W3'!$K$18:$AJ$1018*('W3'!$A$18:$A$1018=W$5)*('W3'!$D$18:$D$1018=$B$71)*('W3'!$K$14:$AJ$14='Cover Page'!$D78))} -> 24161.376 | X78: =IFERROR(W78/W105,0) -> 0.0764046 | Z78: 0.88
D79: 8 | E79: =IF(Currency="USD","USD","triệu VND") -> triệu VND | H79: {=SUMPRODUCT('W3'!$K$18:$AJ$1018*('W3'!$A$18:$A$1018=H$5)*('W3'!$D$18:$D$1018=$B$71)*('W3'!$K$14:$AJ$14='Cover Page'!$D79))} -> 33899.292 | I79: =IFERROR(H79/H106,0) -> 0.10509651 | K79: {=SUMPRODUCT('W3'!$K$18:$AJ$1018*('W3'!$A$18:$A$1018=K$5)*('W3'!$D$18:$D$1018=$B$71)*('W3'!$K$14:$AJ$14='Cover Page'!$D79))} -> 27476.235 | L79: =IFERROR(K79/K106,0) -> 0.078435617 | N79: {=SUMPRODUCT('W3'!$K$18:$AJ$1018*('W3'!$A$18:$A$1018=N$5)*('W3'!$D$18:$D$1018=$B$71)*('W3'!$K$14:$AJ$14='Cover Page'!$D79))} -> 20076.469 | O79: =IFERROR(N79/N106,0) -> 0.058866068 | Q79: {=SUMPRODUCT('W3'!$K$18:$AJ$1018*('W3'!$A$18:$A$1018=Q$5)*('W3'!$D$18:$D$1018=$B$71)*('W3'!$K$14:$AJ$14='Cover Page'!$D79))} -> 23316.388 | R79: =IFERROR(Q79/Q106,0) -> 0.072286791 | T79: {=SUMPRODUCT('W3'!$K$18:$AJ$1018*('W3'!$A$18:$A$1018=T$5)*('W3'!$D$18:$D$1018=$B$71)*('W3'!$K$14:$AJ$14='Cover Page'!$D79))} -> 12728.493 | U79: =IFERROR(T79/T106,0) -> 0.039461596 | W79: {=SUMPRODUCT('W3'!$K$18:$AJ$1018*('W3'!$A$18:$A$1018=W$5)*('W3'!$D$18:$D$1018=$B$71)*('W3'!$K$14:$AJ$14='Cover Page'!$D79))} -> 24160.789 | X79: =IFERROR(W79/W106,0) -> 0.074904651 | Z79: 0.88
D80: 9 | E80: =IF(Currency="USD","USD","triệu VND") -> triệu VND | H80: {=SUMPRODUCT('W3'!$K$18:$AJ$1018*('W3'!$A$18:$A$1018=H$5)*('W3'!$D$18:$D$1018=$B$71)*('W3'!$K$14:$AJ$14='Cover Page'!$D80))} -> 34149.679 | I80: =IFERROR(H80/H107,0) -> 0.10379684 | K80: {=SUMPRODUCT('W3'!$K$18:$AJ$1018*('W3'!$A$18:$A$1018=K$5)*('W3'!$D$18:$D$1018=$B$71)*('W3'!$K$14:$AJ$14='Cover Page'!$D80))} -> 27882.008 | L80: =IFERROR(K80/K107,0) -> 0.078033298 | N80: {=SUMPRODUCT('W3'!$K$18:$AJ$1018*('W3'!$A$18:$A$1018=N$5)*('W3'!$D$18:$D$1018=$B$71)*('W3'!$K$14:$AJ$14='Cover Page'!$D80))} -> 20334.246 | O80: =IFERROR(N80/N107,0) -> 0.058452838 | Q80: {=SUMPRODUCT('W3'!$K$18:$AJ$1018*('W3'!$A$18:$A$1018=Q$5)*('W3'!$D$18:$D$1018=$B$71)*('W3'!$K$14:$AJ$14='Cover Page'!$D80))} -> 23666.732 | R80: =IFERROR(Q80/Q107,0) -> 0.071934263 | T80: {=SUMPRODUCT('W3'!$K$18:$AJ$1018*('W3'!$A$18:$A$1018=T$5)*('W3'!$D$18:$D$1018=$B$71)*('W3'!$K$14:$AJ$14='Cover Page'!$D80))} -> 12771.783 | U80: =IFERROR(T80/T107,0) -> 0.038819421 | W80: {=SUMPRODUCT('W3'!$K$18:$AJ$1018*('W3'!$A$18:$A$1018=W$5)*('W3'!$D$18:$D$1018=$B$71)*('W3'!$K$14:$AJ$14='Cover Page'!$D80))} -> 24102.415 | X80: =IFERROR(W80/W107,0) -> 0.073258507 | Z80: 0.88
D81: 10 | E81: =IF(Currency="USD","USD","triệu VND") -> triệu VND | H81: {=SUMPRODUCT('W3'!$K$18:$AJ$1018*('W3'!$A$18:$A$1018=H$5)*('W3'!$D$18:$D$1018=$B$71)*('W3'!$K$14:$AJ$14='Cover Page'!$D81))} -> 34351.633 | I81: =IFERROR(H81/H108,0) -> 0.1023634 | K81: {=SUMPRODUCT('W3'!$K$18:$AJ$1018*('W3'!$A$18:$A$1018=K$5)*('W3'!$D$18:$D$1018=$B$71)*('W3'!$K$14:$AJ$14='Cover Page'!$D81))} -> 28242.804 | L81: =IFERROR(K81/K108,0) -> 0.077493193 | N81: {=SUMPRODUCT('W3'!$K$18:$AJ$1018*('W3'!$A$18:$A$1018=N$5)*('W3'!$D$18:$D$1018=$B$71)*('W3'!$K$14:$AJ$14='Cover Page'!$D81))} -> 20544.087 | O81: =IFERROR(N81/N108,0) -> 0.057898085 | Q81: {=SUMPRODUCT('W3'!$K$18:$AJ$1018*('W3'!$A$18:$A$1018=Q$5)*('W3'!$D$18:$D$1018=$B$71)*('W3'!$K$14:$AJ$14='Cover Page'!$D81))} -> 23975.64 | R81: =IFERROR(Q81/Q108,0) -> 0.071444291 | T81: {=SUMPRODUCT('W3'!$K$18:$AJ$1018*('W3'!$A$18:$A$1018=T$5)*('W3'!$D$18:$D$1018=$B$71)*('W3'!$K$14:$AJ$14='Cover Page'!$D81))} -> 12761.732 | U81: =IFERROR(T81/T108,0) -> 0.038028303 | W81: {=SUMPRODUCT('W3'!$K$18:$AJ$1018*('W3'!$A$18:$A$1018=W$5)*('W3'!$D$18:$D$1018=$B$71)*('W3'!$K$14:$AJ$14='Cover Page'!$D81))} -> 23982.565 | X81: =IFERROR(W81/W108,0) -> 0.071464929 | Z81: 0.88
D82: 11 | E82: =IF(Currency="USD","USD","triệu VND") -> triệu VND | H82: {=SUMPRODUCT('W3'!$K$18:$AJ$1018*('W3'!$A$18:$A$1018=H$5)*('W3'!$D$18:$D$1018=$B$71)*('W3'!$K$14:$AJ$14='Cover Page'!$D82))} -> 34501.712 | I82: =IFERROR(H82/H109,0) -> 0.10079473 | K82: {=SUMPRODUCT('W3'!$K$18:$AJ$1018*('W3'!$A$18:$A$1018=K$5)*('W3'!$D$18:$D$1018=$B$71)*('W3'!$K$14:$AJ$14='Cover Page'!$D82))} -> 28555.663 | L82: =IFERROR(K82/K109,0) -> 0.076815315 | N82: {=SUMPRODUCT('W3'!$K$18:$AJ$1018*('W3'!$A$18:$A$1018=N$5)*('W3'!$D$18:$D$1018=$B$71)*('W3'!$K$14:$AJ$14='Cover Page'!$D82))} -> 20702.971 | O82: =IFERROR(N82/N109,0) -> 0.057201822 | Q82: {=SUMPRODUCT('W3'!$K$18:$AJ$1018*('W3'!$A$18:$A$1018=Q$5)*('W3'!$D$18:$D$1018=$B$71)*('W3'!$K$14:$AJ$14='Cover Page'!$D82))} -> 24240.159 | R82: =IFERROR(Q82/Q109,0) -> 0.070816202 | T82: {=SUMPRODUCT('W3'!$K$18:$AJ$1018*('W3'!$A$18:$A$1018=T$5)*('W3'!$D$18:$D$1018=$B$71)*('W3'!$K$14:$AJ$14='Cover Page'!$D82))} -> 12695.128 | U82: =IFERROR(T82/T109,0) -> 0.03708807 | W82: {=SUMPRODUCT('W3'!$K$18:$AJ$1018*('W3'!$A$18:$A$1018=W$5)*('W3'!$D$18:$D$1018=$B$71)*('W3'!$K$14:$AJ$14='Cover Page'!$D82))} -> 23797.38 | X82: =IFERROR(W82/W109,0) -> 0.069522647 | Z82: 0.88
D83: 12 | E83: =IF(Currency="USD","USD","triệu VND") -> triệu VND | H83: {=SUMPRODUCT('W3'!$K$18:$AJ$1018*('W3'!$A$18:$A$1018=H$5)*('W3'!$D$18:$D$1018=$B$71)*('W3'!$K$14:$AJ$14='Cover Page'!$D83))} -> 34596.299 | I83: =IFERROR(H83/H110,0) -> 0.09908927 | K83: {=SUMPRODUCT('W3'!$K$18:$AJ$1018*('W3'!$A$18:$A$1018=K$5)*('W3'!$D$18:$D$1018=$B$71)*('W3'!$K$14:$AJ$14='Cover Page'!$D83))} -> 28817.509 | L83: =IFERROR(K83/K110,0) -> 0.075999693 | N83: {=SUMPRODUCT('W3'!$K$18:$AJ$1018*('W3'!$A$18:$A$1018=N$5)*('W3'!$D$18:$D$1018=$B$71)*('W3'!$K$14:$AJ$14='Cover Page'!$D83))} -> 20807.764 | O83: =IFERROR(N83/N110,0) -> 0.056364079 | Q83: {=SUMPRODUCT('W3'!$K$18:$AJ$1018*('W3'!$A$18:$A$1018=Q$5)*('W3'!$D$18:$D$1018=$B$71)*('W3'!$K$14:$AJ$14='Cover Page'!$D83))} -> 24457.197 | R83: =IFERROR(Q83/Q110,0) -> 0.07004928 | T83: {=SUMPRODUCT('W3'!$K$18:$AJ$1018*('W3'!$A$18:$A$1018=T$5)*('W3'!$D$18:$D$1018=$B$71)*('W3'!$K$14:$AJ$14='Cover Page'!$D83))} -> 12568.635 | U83: =IFERROR(T83/T110,0) -> 0.035998559 | W83: {=SUMPRODUCT('W3'!$K$18:$AJ$1018*('W3'!$A$18:$A$1018=W$5)*('W3'!$D$18:$D$1018=$B$71)*('W3'!$K$14:$AJ$14='Cover Page'!$D83))} -> 23542.819 | X83: =IFERROR(W83/W110,0) -> 0.067430357 | Z83: 0.88
D84: 13 | E84: =IF(Currency="USD","USD","triệu VND") -> triệu VND | H84: {=SUMPRODUCT('W3'!$K$18:$AJ$1018*('W3'!$A$18:$A$1018=H$5)*('W3'!$D$18:$D$1018=$B$71)*('W3'!$K$14:$AJ$14='Cover Page'!$D84))} -> 55483.573 | I84: =IFERROR(H84/H111,0) -> 0.15579777 | K84: {=SUMPRODUCT('W3'!$K$18:$AJ$1018*('W3'!$A$18:$A$1018=K$5)*('W3'!$D$18:$D$1018=$B$71)*('W3'!$K$14:$AJ$14='Cover Page'!$D84))} -> 52349.855 | L84: =IFERROR(K84/K111,0) -> 0.13535388 | N84: {=SUMPRODUCT('W3'!$K$18:$AJ$1018*('W3'!$A$18:$A$1018=N$5)*('W3'!$D$18:$D$1018=$B$71)*('W3'!$K$14:$AJ$14='Cover Page'!$D84))} -> 44179.915 | O84: =IFERROR(N84/N111,0) -> 0.11732801 | Q84: {=SUMPRODUCT('W3'!$K$18:$AJ$1018*('W3'!$A$18:$A$1018=Q$5)*('W3'!$D$18:$D$1018=$B$71)*('W3'!$K$14:$AJ$14='Cover Page'!$D84))} -> 45475.495 | R84: =IFERROR(Q84/Q111,0) -> 0.1276951 | T84: {=SUMPRODUCT('W3'!$K$18:$AJ$1018*('W3'!$A$18:$A$1018=T$5)*('W3'!$D$18:$D$1018=$B$71)*('W3'!$K$14:$AJ$14='Cover Page'!$D84))} -> 34218.098 | U84: =IFERROR(T84/T111,0) -> 0.096084354 | W84: {=SUMPRODUCT('W3'!$K$18:$AJ$1018*('W3'!$A$18:$A$1018=W$5)*('W3'!$D$18:$D$1018=$B$71)*('W3'!$K$14:$AJ$14='Cover Page'!$D84))} -> 45053.968 | X84: =IFERROR(W84/W111,0) -> 0.12651146 | Z84: 0.88
... D96: 25 | E96: =IF(Currency="USD","USD","triệu VND") -> triệu VND | H96: {=SUMPRODUCT('W3'!$K$18:$AJ$1018*('W3'!$A$18:$A$1018=H$5)*('W3'!$D$18:$D$1018=$B$71)*('W3'!$K$14:$AJ$14='Cover Page'!$D96))} -> 49602.917 | I96: =IFERROR(H96/H123,0) -> 0.10982519 | K96: {=SUMPRODUCT('W3'!$K$18:$AJ$1018*('W3'!$A$18:$A$1018=K$5)*('W3'!$D$18:$D$1018=$B$71)*('W3'!$K$14:$AJ$14='Cover Page'!$D96))} -> 49293.014 | L96: =IFERROR(K96/K123,0) -> 0.10049363 | N96: {=SUMPRODUCT('W3'!$K$18:$AJ$1018*('W3'!$A$18:$A$1018=N$5)*('W3'!$D$18:$D$1018=$B$71)*('W3'!$K$14:$AJ$14='Cover Page'!$D96))} -> 38931.554 | O96: =IFERROR(N96/N123,0) -> 0.081522318 | Q96: {=SUMPRODUCT('W3'!$K$18:$AJ$1018*('W3'!$A$18:$A$1018=Q$5)*('W3'!$D$18:$D$1018=$B$71)*('W3'!$K$14:$AJ$14='Cover Page'!$D96))} -> 42102.702 | R96: =IFERROR(Q96/Q123,0) -> 0.093219061 | T96: {=SUMPRODUCT('W3'!$K$18:$AJ$1018*('W3'!$A$18:$A$1018=T$5)*('W3'!$D$18:$D$1018=$B$71)*('W3'!$K$14:$AJ$14='Cover Page'!$D96))} -> 25558.767 | U96: =IFERROR(T96/T123,0) -> 0.056589344 | W96: {=SUMPRODUCT('W3'!$K$18:$AJ$1018*('W3'!$A$18:$A$1018=W$5)*('W3'!$D$18:$D$1018=$B$71)*('W3'!$K$14:$AJ$14='Cover Page'!$D96))} -> 33559.858 | X96: =IFERROR(W96/W123,0) -> 0.074304458 | Z96: 0.88
B98: Dthu | C98: 16 | D98: Doanh thu | E98: =IF(Currency="USD","USD","triệu VND") -> triệu VND | H98: =SUM(H99:H123) -> 8767864.5 | K98: =SUM(K99:K123) -> 9522158.7 | N98: =SUM(N99:N123) -> 9270727.3 | Q98: =SUM(Q99:Q123) -> 8767864.5 | T98: =SUM(T99:T123) -> 8767864.5 | W98: =SUM(W99:W123) -> 8767864.5
D99: 1 | E99: =IF(Currency="USD","USD","triệu VND") -> triệu VND | H99: {=SUMPRODUCT('W3'!$K$18:$AJ$1018*('W3'!$A$18:$A$1018=H$5)*('W3'!$D$18:$D$1018=$B$98)*('W3'!$K$14:$AJ$14='Cover Page'!$D99))} -> 140401.3 | K99: {=SUMPRODUCT('W3'!$K$18:$AJ$1018*('W3'!$A$18:$A$1018=K$5)*('W3'!$D$18:$D$1018=$B$98)*('W3'!$K$14:$AJ$14='Cover Page'!$D99))} -> 152479.94 | N99: {=SUMPRODUCT('W3'!$K$18:$AJ$1018*('W3'!$A$18:$A$1018=N$5)*('W3'!$D$18:$D$1018=$B$98)*('W3'!$K$14:$AJ$14='Cover Page'!$D99))} -> 148453.73 | Q99: {=SUMPRODUCT('W3'!$K$18:$AJ$1018*('W3'!$A$18:$A$1018=Q$5)*('W3'!$D$18:$D$1018=$B$98)*('W3'!$K$14:$AJ$14='Cover Page'!$D99))} -> 140401.3 | T99: {=SUMPRODUCT('W3'!$K$18:$AJ$1018*('W3'!$A$18:$A$1018=T$5)*('W3'!$D$18:$D$1018=$B$98)*('W3'!$K$14:$AJ$14='Cover Page'!$D99))} -> 140401.3 | W99: {=SUMPRODUCT('W3'!$K$18:$AJ$1018*('W3'!$A$18:$A$1018=W$5)*('W3'!$D$18:$D$1018=$B$98)*('W3'!$K$14:$AJ$14='Cover Page'!$D99))} -> 140401.3
D100: 2 | E100: =IF(Currency="USD","USD","triệu VND") -> triệu VND | H100: {=SUMPRODUCT('W3'!$K$18:$AJ$1018*('W3'!$A$18:$A$1018=H$5)*('W3'!$D$18:$D$1018=$B$98)*('W3'!$K$14:$AJ$14='Cover Page'!$D100))} -> 200493.06 | K100: {=SUMPRODUCT('W3'!$K$18:$AJ$1018*('W3'!$A$18:$A$1018=K$5)*('W3'!$D$18:$D$1018=$B$98)*('W3'!$K$14:$AJ$14='Cover Page'!$D100))} -> 217741.36 | N100: {=SUMPRODUCT('W3'!$K$18:$AJ$1018*('W3'!$A$18:$A$1018=N$5)*('W3'!$D$18:$D$1018=$B$98)*('W3'!$K$14:$AJ$14='Cover Page'!$D100))} -> 211991.92 | Q100: {=SUMPRODUCT('W3'!$K$18:$AJ$1018*('W3'!$A$18:$A$1018=Q$5)*('W3'!$D$18:$D$1018=$B$98)*('W3'!$K$14:$AJ$14='Cover Page'!$D100))} -> 200493.06 | T100: {=SUMPRODUCT('W3'!$K$18:$AJ$1018*('W3'!$A$18:$A$1018=T$5)*('W3'!$D$18:$D$1018=$B$98)*('W3'!$K$14:$AJ$14='Cover Page'!$D100))} -> 200493.06 | W100: {=SUMPRODUCT('W3'!$K$18:$AJ$1018*('W3'!$A$18:$A$1018=W$5)*('W3'!$D$18:$D$1018=$B$98)*('W3'!$K$14:$AJ$14='Cover Page'!$D100))} -> 200493.06
D101: 3 | E101: =IF(Currency="USD","USD","triệu VND") -> triệu VND | H101: {=SUMPRODUCT('W3'!$K$18:$AJ$1018*('W3'!$A$18:$A$1018=H$5)*('W3'!$D$18:$D$1018=$B$98)*('W3'!$K$14:$AJ$14='Cover Page'!$D101))} -> 292147.02 | K101: {=SUMPRODUCT('W3'!$K$18:$AJ$1018*('W3'!$A$18:$A$1018=K$5)*('W3'!$D$18:$D$1018=$B$98)*('W3'!$K$14:$AJ$14='Cover Page'!$D101))} -> 317280.26 | N101: {=SUMPRODUCT('W3'!$K$18:$AJ$1018*('W3'!$A$18:$A$1018=N$5)*('W3'!$D$18:$D$1018=$B$98)*('W3'!$K$14:$AJ$14='Cover Page'!$D101))} -> 308902.51 | Q101: {=SUMPRODUCT('W3'!$K$18:$AJ$1018*('W3'!$A$18:$A$1018=Q$5)*('W3'!$D$18:$D$1018=$B$98)*('W3'!$K$14:$AJ$14='Cover Page'!$D101))} -> 292147.02 | T101: {=SUMPRODUCT('W3'!$K$18:$AJ$1018*('W3'!$A$18:$A$1018=T$5)*('W3'!$D$18:$D$1018=$B$98)*('W3'!$K$14:$AJ$14='Cover Page'!$D101))} -> 292147.02 | W101: {=SUMPRODUCT('W3'!$K$18:$AJ$1018*('W3'!$A$18:$A$1018=W$5)*('W3'!$D$18:$D$1018=$B$98)*('W3'!$K$14:$AJ$14='Cover Page'!$D101))} -> 292147.02
D102: 4 | E102: =IF(Currency="USD","USD","triệu VND") -> triệu VND | H102: {=SUMPRODUCT('W3'!$K$18:$AJ$1018*('W3'!$A$18:$A$1018=H$5)*('W3'!$D$18:$D$1018=$B$98)*('W3'!$K$14:$AJ$14='Cover Page'!$D102))} -> 297989.96 | K102: {=SUMPRODUCT('W3'!$K$18:$AJ$1018*('W3'!$A$18:$A$1018=K$5)*('W3'!$D$18:$D$1018=$B$98)*('W3'!$K$14:$AJ$14='Cover Page'!$D102))} -> 323625.87 | N102: {=SUMPRODUCT('W3'!$K$18:$AJ$1018*('W3'!$A$18:$A$1018=N$5)*('W3'!$D$18:$D$1018=$B$98)*('W3'!$K$14:$AJ$14='Cover Page'!$D102))} -> 315080.57 | Q102: {=SUMPRODUCT('W3'!$K$18:$AJ$1018*('W3'!$A$18:$A$1018=Q$5)*('W3'!$D$18:$D$1018=$B$98)*('W3'!$K$14:$AJ$14='Cover Page'!$D102))} -> 297989.96 | T102: {=SUMPRODUCT('W3'!$K$18:$AJ$1018*('W3'!$A$18:$A$1018=T$5)*('W3'!$D$18:$D$1018=$B$98)*('W3'!$K$14:$AJ$14='Cover Page'!$D102))} -> 297989.96 | W102: {=SUMPRODUCT('W3'!$K$18:$AJ$1018*('W3'!$A$18:$A$1018=W$5)*('W3'!$D$18:$D$1018=$B$98)*('W3'!$K$14:$AJ$14='Cover Page'!$D102))} -> 297989.96
D103: 5 | E103: =IF(Currency="USD","USD","triệu VND") -> triệu VND | H103: {=SUMPRODUCT('W3'!$K$18:$AJ$1018*('W3'!$A$18:$A$1018=H$5)*('W3'!$D$18:$D$1018=$B$98)*('W3'!$K$14:$AJ$14='Cover Page'!$D103))} -> 303949.76 | K103: {=SUMPRODUCT('W3'!$K$18:$AJ$1018*('W3'!$A$18:$A$1018=K$5)*('W3'!$D$18:$D$1018=$B$98)*('W3'!$K$14:$AJ$14='Cover Page'!$D103))} -> 330098.38 | N103: {=SUMPRODUCT('W3'!$K$18:$AJ$1018*('W3'!$A$18:$A$1018=N$5)*('W3'!$D$18:$D$1018=$B$98)*('W3'!$K$14:$AJ$14='Cover Page'!$D103))} -> 321382.18 | Q103: {=SUMPRODUCT('W3'!$K$18:$AJ$1018*('W3'!$A$18:$A$1018=Q$5)*('W3'!$D$18:$D$1018=$B$98)*('W3'!$K$14:$AJ$14='Cover Page'!$D103))} -> 303949.76 | T103: {=SUMPRODUCT('W3'!$K$18:$AJ$1018*('W3'!$A$18:$A$1018=T$5)*('W3'!$D$18:$D$1018=$B$98)*('W3'!$K$14:$AJ$14='Cover Page'!$D103))} -> 303949.76 | W103: {=SUMPRODUCT('W3'!$K$18:$AJ$1018*('W3'!$A$18:$A$1018=W$5)*('W3'!$D$18:$D$1018=$B$98)*('W3'!$K$14:$AJ$14='Cover Page'!$D103))} -> 303949.76
D104: 6 | E104: =IF(Currency="USD","USD","triệu VND") -> triệu VND | H104: {=SUMPRODUCT('W3'!$K$18:$AJ$1018*('W3'!$A$18:$A$1018=H$5)*('W3'!$D$18:$D$1018=$B$98)*('W3'!$K$14:$AJ$14='Cover Page'!$D104))} -> 310028.76 | K104: {=SUMPRODUCT('W3'!$K$18:$AJ$1018*('W3'!$A$18:$A$1018=K$5)*('W3'!$D$18:$D$1018=$B$98)*('W3'!$K$14:$AJ$14='Cover Page'!$D104))} -> 336700.35 | N104: {=SUMPRODUCT('W3'!$K$18:$AJ$1018*('W3'!$A$18:$A$1018=N$5)*('W3'!$D$18:$D$1018=$B$98)*('W3'!$K$14:$AJ$14='Cover Page'!$D104))} -> 327809.82 | Q104: {=SUMPRODUCT('W3'!$K$18:$AJ$1018*('W3'!$A$18:$A$1018=Q$5)*('W3'!$D$18:$D$1018=$B$98)*('W3'!$K$14:$AJ$14='Cover Page'!$D104))} -> 310028.76 | T104: {=SUMPRODUCT('W3'!$K$18:$AJ$1018*('W3'!$A$18:$A$1018=T$5)*('W3'!$D$18:$D$1018=$B$98)*('W3'!$K$14:$AJ$14='Cover Page'!$D104))} -> 310028.76 | W104: {=SUMPRODUCT('W3'!$K$18:$AJ$1018*('W3'!$A$18:$A$1018=W$5)*('W3'!$D$18:$D$1018=$B$98)*('W3'!$K$14:$AJ$14='Cover Page'!$D104))} -> 310028.76
D105: 7 | E105: =IF(Currency="USD","USD","triệu VND") -> triệu VND | H105: {=SUMPRODUCT('W3'!$K$18:$AJ$1018*('W3'!$A$18:$A$1018=H$5)*('W3'!$D$18:$D$1018=$B$98)*('W3'!$K$14:$AJ$14='Cover Page'!$D105))} -> 316229.33 | K105: {=SUMPRODUCT('W3'!$K$18:$AJ$1018*('W3'!$A$18:$A$1018=K$5)*('W3'!$D$18:$D$1018=$B$98)*('W3'!$K$14:$AJ$14='Cover Page'!$D105))} -> 343434.36 | N105: {=SUMPRODUCT('W3'!$K$18:$AJ$1018*('W3'!$A$18:$A$1018=N$5)*('W3'!$D$18:$D$1018=$B$98)*('W3'!$K$14:$AJ$14='Cover Page'!$D105))} -> 334366.02 | Q105: {=SUMPRODUCT('W3'!$K$18:$AJ$1018*('W3'!$A$18:$A$1018=Q$5)*('W3'!$D$18:$D$1018=$B$98)*('W3'!$K$14:$AJ$14='Cover Page'!$D105))} -> 316229.33 | T105: {=SUMPRODUCT('W3'!$K$18:$AJ$1018*('W3'!$A$18:$A$1018=T$5)*('W3'!$D$18:$D$1018=$B$98)*('W3'!$K$14:$AJ$14='Cover Page'!$D105))} -> 316229.33 | W105: {=SUMPRODUCT('W3'!$K$18:$AJ$1018*('W3'!$A$18:$A$1018=W$5)*('W3'!$D$18:$D$1018=$B$98)*('W3'!$K$14:$AJ$14='Cover Page'!$D105))} -> 316229.33
D106: 8 | E106: =IF(Currency="USD","USD","triệu VND") -> triệu VND | H106: {=SUMPRODUCT('W3'!$K$18:$AJ$1018*('W3'!$A$18:$A$1018=H$5)*('W3'!$D$18:$D$1018=$B$98)*('W3'!$K$14:$AJ$14='Cover Page'!$D106))} -> 322553.92 | K106: {=SUMPRODUCT('W3'!$K$18:$AJ$1018*('W3'!$A$18:$A$1018=K$5)*('W3'!$D$18:$D$1018=$B$98)*('W3'!$K$14:$AJ$14='Cover Page'!$D106))} -> 350303.04 | N106: {=SUMPRODUCT('W3'!$K$18:$AJ$1018*('W3'!$A$18:$A$1018=N$5)*('W3'!$D$18:$D$1018=$B$98)*('W3'!$K$14:$AJ$14='Cover Page'!$D106))} -> 341053.34 | Q106: {=SUMPRODUCT('W3'!$K$18:$AJ$1018*('W3'!$A$18:$A$1018=Q$5)*('W3'!$D$18:$D$1018=$B$98)*('W3'!$K$14:$AJ$14='Cover Page'!$D106))} -> 322553.92 | T106: {=SUMPRODUCT('W3'!$K$18:$AJ$1018*('W3'!$A$18:$A$1018=T$5)*('W3'!$D$18:$D$1018=$B$98)*('W3'!$K$14:$AJ$14='Cover Page'!$D106))} -> 322553.92 | W106: {=SUMPRODUCT('W3'!$K$18:$AJ$1018*('W3'!$A$18:$A$1018=W$5)*('W3'!$D$18:$D$1018=$B$98)*('W3'!$K$14:$AJ$14='Cover Page'!$D106))} -> 322553.92
D107: 9 | E107: =IF(Currency="USD","USD","triệu VND") -> triệu VND | H107: {=SUMPRODUCT('W3'!$K$18:$AJ$1018*('W3'!$A$18:$A$1018=H$5)*('W3'!$D$18:$D$1018=$B$98)*('W3'!$K$14:$AJ$14='Cover Page'!$D107))} -> 329005 | K107: {=SUMPRODUCT('W3'!$K$18:$AJ$1018*('W3'!$A$18:$A$1018=K$5)*('W3'!$D$18:$D$1018=$B$98)*('W3'!$K$14:$AJ$14='Cover Page'!$D107))} -> 357309.11 | N107: {=SUMPRODUCT('W3'!$K$18:$AJ$1018*('W3'!$A$18:$A$1018=N$5)*('W3'!$D$18:$D$1018=$B$98)*('W3'!$K$14:$AJ$14='Cover Page'!$D107))} -> 347874.4 | Q107: {=SUMPRODUCT('W3'!$K$18:$AJ$1018*('W3'!$A$18:$A$1018=Q$5)*('W3'!$D$18:$D$1018=$B$98)*('W3'!$K$14:$AJ$14='Cover Page'!$D107))} -> 329005 | T107: {=SUMPRODUCT('W3'!$K$18:$AJ$1018*('W3'!$A$18:$A$1018=T$5)*('W3'!$D$18:$D$1018=$B$98)*('W3'!$K$14:$AJ$14='Cover Page'!$D107))} -> 329005 | W107: {=SUMPRODUCT('W3'!$K$18:$AJ$1018*('W3'!$A$18:$A$1018=W$5)*('W3'!$D$18:$D$1018=$B$98)*('W3'!$K$14:$AJ$14='Cover Page'!$D107))} -> 329005
D108: 10 | E108: =IF(Currency="USD","USD","triệu VND") -> triệu VND | H108: {=SUMPRODUCT('W3'!$K$18:$AJ$1018*('W3'!$A$18:$A$1018=H$5)*('W3'!$D$18:$D$1018=$B$98)*('W3'!$K$14:$AJ$14='Cover Page'!$D108))} -> 335585.1 | K108: {=SUMPRODUCT('W3'!$K$18:$AJ$1018*('W3'!$A$18:$A$1018=K$5)*('W3'!$D$18:$D$1018=$B$98)*('W3'!$K$14:$AJ$14='Cover Page'!$D108))} -> 364455.29 | N108: {=SUMPRODUCT('W3'!$K$18:$AJ$1018*('W3'!$A$18:$A$1018=N$5)*('W3'!$D$18:$D$1018=$B$98)*('W3'!$K$14:$AJ$14='Cover Page'!$D108))} -> 354831.89 | Q108: {=SUMPRODUCT('W3'!$K$18:$AJ$1018*('W3'!$A$18:$A$1018=Q$5)*('W3'!$D$18:$D$1018=$B$98)*('W3'!$K$14:$AJ$14='Cover Page'!$D108))} -> 335585.1 | T108: {=SUMPRODUCT('W3'!$K$18:$AJ$1018*('W3'!$A$18:$A$1018=T$5)*('W3'!$D$18:$D$1018=$B$98)*('W3'!$K$14:$AJ$14='Cover Page'!$D108))} -> 335585.1 | W108: {=SUMPRODUCT('W3'!$K$18:$AJ$1018*('W3'!$A$18:$A$1018=W$5)*('W3'!$D$18:$D$1018=$B$98)*('W3'!$K$14:$AJ$14='Cover Page'!$D108))} -> 335585.1
D109: 11 | E109: =IF(Currency="USD","USD","triệu VND") -> triệu VND | H109: {=SUMPRODUCT('W3'!$K$18:$AJ$1018*('W3'!$A$18:$A$1018=H$5)*('W3'!$D$18:$D$1018=$B$98)*('W3'!$K$14:$AJ$14='Cover Page'!$D109))} -> 342296.8 | K109: {=SUMPRODUCT('W3'!$K$18:$AJ$1018*('W3'!$A$18:$A$1018=K$5)*('W3'!$D$18:$D$1018=$B$98)*('W3'!$K$14:$AJ$14='Cover Page'!$D109))} -> 371744.39 | N109: {=SUMPRODUCT('W3'!$K$18:$AJ$1018*('W3'!$A$18:$A$1018=N$5)*('W3'!$D$18:$D$1018=$B$98)*('W3'!$K$14:$AJ$14='Cover Page'!$D109))} -> 361928.53 | Q109: {=SUMPRODUCT('W3'!$K$18:$AJ$1018*('W3'!$A$18:$A$1018=Q$5)*('W3'!$D$18:$D$1018=$B$98)*('W3'!$K$14:$AJ$14='Cover Page'!$D109))} -> 342296.8 | T109: {=SUMPRODUCT('W3'!$K$18:$AJ$1018*('W3'!$A$18:$A$1018=T$5)*('W3'!$D$18:$D$1018=$B$98)*('W3'!$K$14:$AJ$14='Cover Page'!$D109))} -> 342296.8 | W109: {=SUMPRODUCT('W3'!$K$18:$AJ$1018*('W3'!$A$18:$A$1018=W$5)*('W3'!$D$18:$D$1018=$B$98)*('W3'!$K$14:$AJ$14='Cover Page'!$D109))} -> 342296.8
D110: 12 | E110: =IF(Currency="USD","USD","triệu VND") -> triệu VND | H110: {=SUMPRODUCT('W3'!$K$18:$AJ$1018*('W3'!$A$18:$A$1018=H$5)*('W3'!$D$18:$D$1018=$B$98)*('W3'!$K$14:$AJ$14='Cover Page'!$D110))} -> 349142.74 | K110: {=SUMPRODUCT('W3'!$K$18:$AJ$1018*('W3'!$A$18:$A$1018=K$5)*('W3'!$D$18:$D$1018=$B$98)*('W3'!$K$14:$AJ$14='Cover Page'!$D110))} -> 379179.28 | N110: {=SUMPRODUCT('W3'!$K$18:$AJ$1018*('W3'!$A$18:$A$1018=N$5)*('W3'!$D$18:$D$1018=$B$98)*('W3'!$K$14:$AJ$14='Cover Page'!$D110))} -> 369167.1 | Q110: {=SUMPRODUCT('W3'!$K$18:$AJ$1018*('W3'!$A$18:$A$1018=Q$5)*('W3'!$D$18:$D$1018=$B$98)*('W3'!$K$14:$AJ$14='Cover Page'!$D110))} -> 349142.74 | T110: {=SUMPRODUCT('W3'!$K$18:$AJ$1018*('W3'!$A$18:$A$1018=T$5)*('W3'!$D$18:$D$1018=$B$98)*('W3'!$K$14:$AJ$14='Cover Page'!$D110))} -> 349142.74 | W110: {=SUMPRODUCT('W3'!$K$18:$AJ$1018*('W3'!$A$18:$A$1018=W$5)*('W3'!$D$18:$D$1018=$B$98)*('W3'!$K$14:$AJ$14='Cover Page'!$D110))} -> 349142.74
... D123: 25 | E123: =IF(Currency="USD","USD","triệu VND") -> triệu VND | H123: {=SUMPRODUCT('W3'!$K$18:$AJ$1018*('W3'!$A$18:$A$1018=H$5)*('W3'!$D$18:$D$1018=$B$98)*('W3'!$K$14:$AJ$14='Cover Page'!$D123))} -> 451653.36 | K123: {=SUMPRODUCT('W3'!$K$18:$AJ$1018*('W3'!$A$18:$A$1018=K$5)*('W3'!$D$18:$D$1018=$B$98)*('W3'!$K$14:$AJ$14='Cover Page'!$D123))} -> 490508.83 | N123: {=SUMPRODUCT('W3'!$K$18:$AJ$1018*('W3'!$A$18:$A$1018=N$5)*('W3'!$D$18:$D$1018=$B$98)*('W3'!$K$14:$AJ$14='Cover Page'!$D123))} -> 477557.01 | Q123: {=SUMPRODUCT('W3'!$K$18:$AJ$1018*('W3'!$A$18:$A$1018=Q$5)*('W3'!$D$18:$D$1018=$B$98)*('W3'!$K$14:$AJ$14='Cover Page'!$D123))} -> 451653.36 | T123: {=SUMPRODUCT('W3'!$K$18:$AJ$1018*('W3'!$A$18:$A$1018=T$5)*('W3'!$D$18:$D$1018=$B$98)*('W3'!$K$14:$AJ$14='Cover Page'!$D123))} -> 451653.36 | W123: {=SUMPRODUCT('W3'!$K$18:$AJ$1018*('W3'!$A$18:$A$1018=W$5)*('W3'!$D$18:$D$1018=$B$98)*('W3'!$K$14:$AJ$14='Cover Page'!$D123))} -> 451653.36

Sheet W1
D1: Công ty CP Nhựa tái chế Duy Tân
D2: Đơn vị: Kế toán quản trị
D3: DỰ ÁN FLAKES TO PREFORM SUNTORY - PEPSICO
D4: TỔNG CHI PHÍ ĐẦU TƯ
D5: =Currency -> VND | N5: (không tăng chi phí xây dựng nhà xưởng) - Roundup | S5: (không tăng chi phí xây dựng nhà xưởng) | X5: (không tăng chi phí xây dựng nhà xưởng) | AC5: (không tăng chi phí xây dựng nhà xưởng) | AH5: (không tăng chi phí xây dựng nhà xưởng)
D6: =IF(D5="VND",1,EXR) -> 1 | I6: Option 1 | J6: BASE | N6: Option 2 | O6: =Opt2_CAPEX -> 0.07 | S6: Option 3 | T6: =Opt3_CAPEX -> 0.07 | X6: Option 4 | Y6: =Opt4_CAPEX -> 0 | AC6: Option 5 | AD6: =Opt5_CAPEX -> 0 | AH6: Option 6 | AI6: =Opt6_CAPEX -> 0
C7: STT | D7: HẠNG MỤC | E7: Số lượng | G7: Thời gian khấu hao | H7: Đơn giá | I7: Giá trị đầu tư | J7: Khấu hao | L7: Thời gian khấu hao | M7: Đơn giá | N7: Giá trị đầu tư | O7: Khấu hao | Q7: Thời gian khấu hao | R7: Đơn giá | S7: Giá trị đầu tư | T7: Khấu hao | V7: Thời gian khấu hao | W7: Đơn giá | X7: Giá trị đầu tư | Y7: Khấu hao | AA7: Thời gian khấu hao | AB7: Đơn giá | AC7: Giá trị đầu tư | AD7: Khấu hao | AF7: Thời gian khấu hao | AG7: Đơn giá | AH7: Giá trị đầu tư | AI7: Khấu hao | AK7: NHẬP KHẨU TỪ | AL7: Nguồn: | AM7: Ghi chú - Nếu dừng dự án thì Suntory mua lại | AO7: Option 1 | AP7: =AO7 -> Option 1 | AQ7: =AP7 -> Option 1 | AR7: =AQ7 -> Option 1 | AS7: =AR7 -> Option 1 | AT7: =AS7 -> Option 1 | AU7: =AT7 -> Option 1 | AV7: =AU7 -> Option 1 | AW7: =AV7 -> Option 1 | ... BR7: =BQ7 -> Option 1 | BT7: Option 2 | BU7: =BT7 -> Option 2 | BV7: =BU7 -> Option 2 | BW7: =BV7 -> Option 2 | BX7: =BW7 -> Option 2 | BY7: =BX7 -> Option 2 | BZ7: =BY7 -> Option 2 | CA7: =BZ7 -> Option 2 | CB7: =CA7 -> Option 2 | ... CW7: =CV7 -> Option 2 | CY7: Option 3 | CZ7: Option 3 | DA7: Option 3 | DB7: Option 3 | DC7: Option 3 | DD7: Option 3 | DE7: Option 3 | DF7: Option 3 | DG7: Option 3 | DH7: Option 3 | DI7: Option 3 | DJ7: Option 3 | DK7: Option 3 | DL7: Option 3 | DM7: Option 3 | DN7: Option 3 | DO7: Option 3 | DP7: Option 3 | DQ7: Option 3 | DR7: Option 3 | DS7: Option 3 | DT7: Option 3 | DU7: Option 3 | DV7: Option 3 | DW7: Option 3 | DX7: Option 3 | DY7: Option 3 | DZ7: Option 3 | EA7: Option 3 | EB7: Option 3 | ED7: Option 4 | EE7: Option 4 | EF7: Option 4 | EG7: Option 4 | EH7: Option 4 | EI7: Option 4 | EJ7: Option 4 | EK7: Option 4 | EL7: Option 4 | EM7: Option 4 | EN7: Option 4 | EO7: Option 4 | EP7: Option 4 | EQ7: Option 4 | ER7: Option 4 | ES7: Option 4 | ET7: Option 4 | EU7: Option 4 | EV7: Option 4 | EW7: Option 4 | EX7: Option 4 | EY7: Option 4 | EZ7: Option 4 | FA7: Option 4 | FB7: Option 4 | FC7: Option 4 | FD7: Option 4 | FE7: Option 4 | FF7: Option 4 | FG7: Option 4 | FI7: Option 5 | FJ7: Option 5 | FK7: Option 5 | FL7: Option 5 | FM7: Option 5 | FN7: Option 5 | FO7: Option 5 | FP7: Option 5 | FQ7: Option 5 | FR7: Option 5 | FS7: Option 5 | FT7: Option 5 | FU7: Option 5 | FV7: Option 5 | FW7: Option 5 | FX7: Option 5 | FY7: Option 5 | FZ7: Option 5 | GA7: Option 5 | GB7: Option 5 | GC7: Option 5 | GD7: Option 5 | GE7: Option 5 | GF7: Option 5 | GG7: Option 5 | GH7: Option 5 | GI7: Option 5 | GJ7: Option 5 | GK7: Option 5 | GL7: Option 5 | GN7: Option 6 | GO7: Option 6 | GP7: Option 6 | GQ7: Option 6 | GR7: Option 6 | GS7: Option 6 | GT7: Option 6 | GU7: Option 6 | GV7: Option 6 | GW7: Option 6 | GX7: Option 6 | GY7: Option 6 | GZ7: Option 6 | HA7: Option 6 | HB7: Option 6 | HC7: Option 6 | HD7: Option 6 | HE7: Option 6 | HF7: Option 6 | HG7: Option 6 | HH7: Option 6 | HI7: Option 6 | HJ7: Option 6 | HK7: Option 6 | HL7: Option 6 | HM7: Option 6 | HN7: Option 6 | HO7: Option 6 | HP7: Option 6 | HQ7: Option 6
A8: Link qua W3 | B8: Link qua Sun-W6 | E8: (cái,m2) | G8: (Năm) | H8: ="("&$D$5&")" -> (VND) | I8: ="("&$D$5&")" -> (VND) | J8: ="("&$D$5&"/năm)" -> (VND/năm) | L8: (Năm) | M8: ="("&$D$5&")" -> (VND) | N8: ="("&$D$5&")" -> (VND) | O8: ="("&$D$5&"/năm)" -> (VND/năm) | Q8: (Năm) | R8: ="("&$D$5&")" -> (VND) | S8: ="("&$D$5&")" -> (VND) | T8: ="("&$D$5&"/năm)" -> (VND/năm) | V8: (Năm) | W8: ="("&$D$5&")" -> (VND) | X8: ="("&$D$5&")" -> (VND) | Y8: ="("&$D$5&"/năm)" -> (VND/năm) | AA8: (Năm) | AB8: ="("&$D$5&")" -> (VND) | AC8: ="("&$D$5&")" -> (VND) | AD8: ="("&$D$5&"/năm)" -> (VND/năm) | AF8: (Năm) | AG8: ="("&$D$5&")" -> (VND) | AH8: ="("&$D$5&")" -> (VND) | AI8: ="("&$D$5&"/năm)" -> (VND/năm) | AO8: 1 | AP8: 2 | AQ8: 3 | AR8: 4 | AS8: 5 | AT8: 6 | AU8: 7 | AV8: 8 | AW8: 9 | AX8: 10 | AY8: 11 | AZ8: 12 | BA8: 13 | BB8: 14 | BC8: 15 | BD8: 16 | BE8: 17 | BF8: 18 | BG8: 19 | BH8: 20 | BI8: 21 | BJ8: 22 | BK8: 23 | BL8: 24 | BM8: 25 | BN8: 26 | BO8: 27 | BP8: 28 | BQ8: 29 | BR8: 30 | BT8: 1 | BU8: 2 | BV8: 3 | BW8: 4 | BX8: 5 | BY8: 6 | BZ8: 7 | CA8: 8 | CB8: 9 | CC8: 10 | CD8: 11 | CE8: 12 | CF8: 13 | CG8: 14 | CH8: 15 | CI8: 16 | CJ8: 17 | CK8: 18 | CL8: 19 | CM8: 20 | CN8: 21 | CO8: 22 | CP8: 23 | CQ8: 24 | CR8: 25 | CS8: 26 | CT8: 27 | CU8: 28 | CV8: 29 | CW8: 30 | CY8: 1 | CZ8: 2 | DA8: 3 | DB8: 4 | DC8: 5 | DD8: 6 | DE8: 7 | DF8: 8 | DG8: 9 | DH8: 10 | DI8: 11 | DJ8: 12 | DK8: 13 | DL8: 14 | DM8: 15 | DN8: 16 | DO8: 17 | DP8: 18 | DQ8: 19 | DR8: 20 | DS8: 21 | DT8: 22 | DU8: 23 | DV8: 24 | DW8: 25 | DX8: 26 | DY8: 27 | DZ8: 28 | EA8: 29 | EB8: 30 | ED8: 1 | EE8: 2 | EF8: 3 | EG8: 4 | EH8: 5 | EI8: 6 | EJ8: 7 | EK8: 8 | EL8: 9 | EM8: 10 | EN8: 11 | EO8: 12 | EP8: 13 | EQ8: 14 | ER8: 15 | ES8: 16 | ET8: 17 | EU8: 18 | EV8: 19 | EW8: 20 | EX8: 21 | EY8: 22 | EZ8: 23 | FA8: 24 | FB8: 25 | FC8: 26 | FD8: 27 | FE8: 28 | FF8: 29 | FG8: 30 | FI8: 1 | FJ8: 2 | FK8: 3 | FL8: 4 | FM8: 5 | FN8: 6 | FO8: 7 | FP8: 8 | FQ8: 9 | FR8: 10 | FS8: 11 | FT8: 12 | FU8: 13 | FV8: 14 | FW8: 15 | FX8: 16 | FY8: 17 | FZ8: 18 | GA8: 19 | GB8: 20 | GC8: 21 | GD8: 22 | GE8: 23 | GF8: 24 | GG8: 25 | GH8: 26 | GI8: 27 | GJ8: 28 | GK8: 29 | GL8: 30 | GN8: 1 | GO8: 2 | GP8: 3 | GQ8: 4 | GR8: 5 | GS8: 6 | GT8: 7 | GU8: 8 | GV8: 9 | GW8: 10 | GX8: 11 | GY8: 12 | GZ8: 13 | HA8: 14 | HB8: 15 | HC8: 16 | HD8: 17 | HE8: 18 | HF8: 19 | HG8: 20 | HH8: 21 | HI8: 22 | HJ8: 23 | HK8: 24 | HL8: 25 | HM8: 26 | HN8: 27 | HO8: 28 | HP8: 29 | HQ8: 30
C10: 1 | D10: MÁY MÓC THIẾT BỊ | I10: =I12+I20 -> 284499800000 | J10: =J12+J20 -> 2.3708317e+10 | N10: =N12+N20 -> 318760000000 | O10: =O12+O20 -> 2.6563333e+10 | S10: =S12+S20 -> 318760000000 | T10: =T12+T20 -> 2.6563333e+10 | X10: =X12+X20 -> 284499800000 | Y10: =Y12+Y20 -> 2.3708317e+10 | AC10: =AC12+AC20 -> 298714000000 | AD10: =AD12+AD20 -> 2.4892833e+10 | AH10: =AH12+AH20 -> 298714000000 | AI10: =AI12+AI20 -> 2.4892833e+10 | AO10: =AO12+AO20 -> 2.3708317e+10 | AP10: =AP12+AP20 -> 2.3708317e+10 | AQ10: =AQ12+AQ20 -> 2.3708317e+10 | AR10: =AR12+AR20 -> 2.3708317e+10 | AS10: =AS12+AS20 -> 2.3708317e+10 | AT10: =AT12+AT20 -> 2.3708317e+10 | AU10: =AU12+AU20 -> 2.3708317e+10 | AV10: =AV12+AV20 -> 2.3708317e+10 | ... BR10: =BR12+BR20 -> 0 | BT10: =BT12+BT20 -> 2.6563333e+10 | BU10: =BU12+BU20 -> 2.6563333e+10 | BV10: =BV12+BV20 -> 2.6563333e+10 | BW10: =BW12+BW20 -> 2.6563333e+10 | BX10: =BX12+BX20 -> 2.6563333e+10 | BY10: =BY12+BY20 -> 2.6563333e+10 | BZ10: =BZ12+BZ20 -> 2.6563333e+10 | CA10: =CA12+CA20 -> 2.6563333e+10 | ... CW10: =CW12+CW20 -> 0 | CY10: =CY12+CY20 -> 2.6563333e+10 | CZ10: =CZ12+CZ20 -> 2.6563333e+10 | DA10: =DA12+DA20 -> 2.6563333e+10 | DB10: =DB12+DB20 -> 2.6563333e+10 | DC10: =DC12+DC20 -> 2.6563333e+10 | DD10: =DD12+DD20 -> 2.6563333e+10 | DE10: =DE12+DE20 -> 2.6563333e+10 | DF10: =DF12+DF20 -> 2.6563333e+10 | ... EB10: =EB12+EB20 -> 0 | ED10: =ED12+ED20 -> 2.3708317e+10 | EE10: =EE12+EE20 -> 2.3708317e+10 | EF10: =EF12+EF20 -> 2.3708317e+10 | EG10: =EG12+EG20 -> 2.3708317e+10 | EH10: =EH12+EH20 -> 2.3708317e+10 | EI10: =EI12+EI20 -> 2.3708317e+10 | EJ10: =EJ12+EJ20 -> 2.3708317e+10 | EK10: =EK12+EK20 -> 2.3708317e+10 | ... FG10: =FG12+FG20 -> 0 | FI10: =FI12+FI20 -> 2.4892833e+10 | FJ10: =FJ12+FJ20 -> 2.4892833e+10 | FK10: =FK12+FK20 -> 2.4892833e+10 | FL10: =FL12+FL20 -> 2.4892833e+10 | FM10: =FM12+FM20 -> 2.4892833e+10 | FN10: =FN12+FN20 -> 2.4892833e+10 | FO10: =FO12+FO20 -> 2.4892833e+10 | FP10: =FP12+FP20 -> 2.4892833e+10 | ... GL10: =GL12+GL20 -> 0 | GN10: =GN12+GN20 -> 2.4892833e+10 | GO10: =GO12+GO20 -> 2.4892833e+10 | GP10: =GP12+GP20 -> 2.4892833e+10 | GQ10: =GQ12+GQ20 -> 2.4892833e+10 | GR10: =GR12+GR20 -> 2.4892833e+10 | GS10: =GS12+GS20 -> 2.4892833e+10 | GT10: =GT12+GT20 -> 2.4892833e+10 | GU10: =GU12+GU20 -> 2.4892833e+10 | ... HQ10: =HQ12+HQ20 -> 0
A12: CAPEX-MAIN | C12: 1.1 | D12: Máy móc thiết bị chính | I12: =SUM(I13:I18) -> 2.46389e+11 | J12: =SUM(J13:J18) -> 2.0532417e+10 | N12: =SUM(N13:N18) -> 277888000000 | O12: =SUM(O13:O18) -> 2.3157333e+10 | S12: =SUM(S13:S18) -> 277888000000 | T12: =SUM(T13:T18) -> 2.3157333e+10 | X12: =SUM(X13:X18) -> 2.46389e+11 | Y12: =SUM(Y13:Y18) -> 2.0532417e+10 | AC12: =SUM(AC13:AC18) -> 260598000000 | AD12: =SUM(AD13:AD18) -> 21716500000 | AH12: =SUM(AH13:AH18) -> 260598000000 | AI12: =SUM(AI13:AI18) -> 21716500000 | AO12: =SUM(AO13:AO18) -> 2.0532417e+10 | AP12: =SUM(AP13:AP18) -> 2.0532417e+10 | AQ12: =SUM(AQ13:AQ18) -> 2.0532417e+10 | AR12: =SUM(AR13:AR18) -> 2.0532417e+10 | AS12: =SUM(AS13:AS18) -> 2.0532417e+10 | AT12: =SUM(AT13:AT18) -> 2.0532417e+10 | AU12: =SUM(AU13:AU18) -> 2.0532417e+10 | AV12: =SUM(AV13:AV18) -> 2.0532417e+10 | ... BR12: =SUM(BR13:BR18) -> 0 | BT12: =SUM(BT13:BT18) -> 2.3157333e+10 | BU12: =SUM(BU13:BU18) -> 2.3157333e+10 | BV12: =SUM(BV13:BV18) -> 2.3157333e+10 | BW12: =SUM(BW13:BW18) -> 2.3157333e+10 | BX12: =SUM(BX13:BX18) -> 2.3157333e+10 | BY12: =SUM(BY13:BY18) -> 2.3157333e+10 | BZ12: =SUM(BZ13:BZ18) -> 2.3157333e+10 | CA12: =SUM(CA13:CA18) -> 2.3157333e+10 | ... CW12: =SUM(CW13:CW18) -> 0 | CY12: =SUM(CY13:CY18) -> 2.3157333e+10 | CZ12: =SUM(CZ13:CZ18) -> 2.3157333e+10 | DA12: =SUM(DA13:DA18) -> 2.3157333e+10 | DB12: =SUM(DB13:DB18) -> 2.3157333e+10 | DC12: =SUM(DC13:DC18) -> 2.3157333e+10 | DD12: =SUM(DD13:DD18) -> 2.3157333e+10 | DE12: =SUM(DE13:DE18) -> 2.3157333e+10 | DF12: =SUM(DF13:DF18) -> 2.3157333e+10 | ... EB12: =SUM(EB13:EB18) -> 0 | ED12: =SUM(ED13:ED18) -> 2.0532417e+10 | EE12: =SUM(EE13:EE18) -> 2.0532417e+10 | EF12: =SUM(EF13:EF18) -> 2.0532417e+10 | EG12: =SUM(EG13:EG18) -> 2.0532417e+10 | EH12: =SUM(EH13:EH18) -> 2.0532417e+10 | EI12: =SUM(EI13:EI18) -> 2.0532417e+10 | EJ12: =SUM(EJ13:EJ18) -> 2.0532417e+10 | EK12: =SUM(EK13:EK18) -> 2.0532417e+10 | ... FG12: =SUM(FG13:FG18) -> 0 | FI12: =SUM(FI13:FI18) -> 21716500000 | FJ12: =SUM(FJ13:FJ18) -> 21716500000 | FK12: =SUM(FK13:FK18) -> 21716500000 | FL12: =SUM(FL13:FL18) -> 21716500000 | FM12: =SUM(FM13:FM18) -> 21716500000 | FN12: =SUM(FN13:FN18) -> 21716500000 | FO12: =SUM(FO13:FO18) -> 21716500000 | FP12: =SUM(FP13:FP18) -> 21716500000 | ... GL12: =SUM(GL13:GL18) -> 0 | GN12: =SUM(GN13:GN18) -> 21716500000 | GO12: =SUM(GO13:GO18) -> 21716500000 | GP12: =SUM(GP13:GP18) -> 21716500000 | GQ12: =SUM(GQ13:GQ18) -> 21716500000 | GR12: =SUM(GR13:GR18) -> 21716500000 | GS12: =SUM(GS13:GS18) -> 21716500000 | GT12: =SUM(GT13:GT18) -> 21716500000 | GU12: =SUM(GU13:GU18) -> 21716500000 | ... HQ12: =SUM(HQ13:HQ18) -> 0
B13: NGR system | C13: 1.1.01 | D13: NGR : LSP 1200 | E13: 1 | G13: 12 | H13: =(123250000000/$D$6)*1.04 -> 128180000000 | I13: =$E13*$H13 -> 128180000000 | J13: =I13/G13 -> 1.0681667e+10 | L13: 12 | M13: =IF(Currency="USD",ROUNDUP($E13*$H13*(1+O$6),-3),ROUNDUP($E13*$H13*(1+O$6)/EXR,-3)*EXR) -> 137176000000 | N13: =$E13*M13 -> 137176000000 | O13: =N13/L13 -> 1.1431333e+10 | Q13: 12 | R13: =IF(Currency="USD",ROUNDUP($E13*$H13*(1+T$6),-3),ROUNDUP($E13*$H13*(1+T$6)/EXR,-3)*EXR) -> 137176000000 | S13: =$E13*R13 -> 137176000000 | T13: =S13/Q13 -> 1.1431333e+10 | V13: 12 | W13: =H13 -> 128180000000 | X13: =$E13*W13 -> 128180000000 | Y13: =X13/V13 -> 1.0681667e+10 | AA13: 12 | AB13: =IF(Currency="USD",ROUNDUP($E13*$H13*(1+AD$6),-3),ROUNDUP($E13*$H13*(1+AD$6)/EXR,-3)*EXR) -> 128180000000 | AC13: =$E13*AB13 -> 128180000000 | AD13: =AC13/AA13 -> 1.0681667e+10 | AF13: 12 | AG13: =IF(Currency="USD",ROUNDUP($E13*$H13*(1+AI$6),-3),ROUNDUP($E13*$H13*(1+AI$6)/EXR,-3)*EXR) -> 128180000000 | AH13: =$E13*AG13 -> 128180000000 | AI13: =AH13/AF13 -> 1.0681667e+10 | AK13: Áo | AL13: A. Quân | AM13: Gía trị bán lại = giá trị ban đầu - khấu hao * sản lượng sx | AO13: =IF($G13>=AO$8,$J13,0) -> 1.0681667e+10 | AP13: =IF($G13>=AP$8,$J13,0) -> 1.0681667e+10 | AQ13: =IF($G13>=AQ$8,$J13,0) -> 1.0681667e+10 | AR13: =IF($G13>=AR$8,$J13,0) -> 1.0681667e+10 | AS13: =IF($G13>=AS$8,$J13,0) -> 1.0681667e+10 | AT13: =IF($G13>=AT$8,$J13,0) -> 1.0681667e+10 | AU13: =IF($G13>=AU$8,$J13,0) -> 1.0681667e+10 | AV13: =IF($G13>=AV$8,$J13,0) -> 1.0681667e+10 | ... BR13: =IF($G13>=BR$8,$J13,0) -> 0 | BT13: =IF($L13>=BT$8,$O13,0) -> 1.1431333e+10 | BU13: =IF($L13>=BU$8,$O13,0) -> 1.1431333e+10 | BV13: =IF($L13>=BV$8,$O13,0) -> 1.1431333e+10 | BW13: =IF($L13>=BW$8,$O13,0) -> 1.1431333e+10 | BX13: =IF($L13>=BX$8,$O13,0) -> 1.1431333e+10 | BY13: =IF($L13>=BY$8,$O13,0) -> 1.1431333e+10 | BZ13: =IF($L13>=BZ$8,$O13,0) -> 1.1431333e+10 | CA13: =IF($L13>=CA$8,$O13,0) -> 1.1431333e+10 | ... CW13: =IF($L13>=CW$8,$O13,0) -> 0 | CY13: =IF($Q13>=CY$8,$T13,0) -> 1.1431333e+10 | CZ13: =IF($Q13>=CZ$8,$T13,0) -> 1.1431333e+10 | DA13: =IF($Q13>=DA$8,$T13,0) -> 1.1431333e+10 | DB13: =IF($Q13>=DB$8,$T13,0) -> 1.1431333e+10 | DC13: =IF($Q13>=DC$8,$T13,0) -> 1.1431333e+10 | DD13: =IF($Q13>=DD$8,$T13,0) -> 1.1431333e+10 | DE13: =IF($Q13>=DE$8,$T13,0) -> 1.1431333e+10 | DF13: =IF($Q13>=DF$8,$T13,0) -> 1.1431333e+10 | ... EB13: =IF($Q13>=EB$8,$T13,0) -> 0 | ED13: =IF($V13>=ED$8,$Y13,0) -> 1.0681667e+10 | EE13: =IF($V13>=EE$8,$Y13,0) -> 1.0681667e+10 | EF13: =IF($V13>=EF$8,$Y13,0) -> 1.0681667e+10 | EG13: =IF($V13>=EG$8,$Y13,0) -> 1.0681667e+10 | EH13: =IF($V13>=EH$8,$Y13,0) -> 1.0681667e+10 | EI13: =IF($V13>=EI$8,$Y13,0) -> 1.0681667e+10 | EJ13: =IF($V13>=EJ$8,$Y13,0) -> 1.0681667e+10 | EK13: =IF($V13>=EK$8,$Y13,0) -> 1.0681667e+10 | ... FG13: =IF($V13>=FG$8,$Y13,0) -> 0 | FI13: =IF($AA13>=FI$8,$AD13,0) -> 1.0681667e+10 | FJ13: =IF($AA13>=FJ$8,$AD13,0) -> 1.0681667e+10 | FK13: =IF($AA13>=FK$8,$AD13,0) -> 1.0681667e+10 | FL13: =IF($AA13>=FL$8,$AD13,0) -> 1.0681667e+10 | FM13: =IF($AA13>=FM$8,$AD13,0) -> 1.0681667e+10 | FN13: =IF($AA13>=FN$8,$AD13,0) -> 1.0681667e+10 | FO13: =IF($AA13>=FO$8,$AD13,0) -> 1.0681667e+10 | FP13: =IF($AA13>=FP$8,$AD13,0) -> 1.0681667e+10 | ... GL13: =IF($AA13>=GL$8,$AD13,0) -> 0 | GN13: =IF($AF13>=GN$8,$AI13,0) -> 1.0681667e+10 | GO13: =IF($AF13>=GO$8,$AI13,0) -> 1.0681667e+10 | GP13: =IF($AF13>=GP$8,$AI13,0) -> 1.0681667e+10 | GQ13: =IF($AF13>=GQ$8,$AI13,0) -> 1.0681667e+10 | GR13: =IF($AF13>=GR$8,$AI13,0) -> 1.0681667e+10 | GS13: =IF($AF13>=GS$8,$AI13,0) -> 1.0681667e+10 | GT13: =IF($AF13>=GT$8,$AI13,0) -> 1.0681667e+10 | GU13: =IF($AF13>=GU$8,$AI13,0) -> 1.0681667e+10 | ... HQ13: =IF($AF13>=HQ$8,$AI13,0) -> 0
B14: Husky 128 cavs Injection Machine | C14: 1.1.02 | D14: HyPET400 HPP5e rMtP P120/120 | E14: 1 | G14: 12 | H14: =(80500000000/$D$6*(1-0.196393571148569))*1.04 -> 6.727793e+10 | I14: =$E14*$H14 -> 6.727793e+10 | J14: =I14/G14 -> 5.6064942e+09 | L14: 12 | M14: =IF(Currency="USD",ROUNDUP($E14*$H14*(1+O$6),-3),ROUNDUP($E14*$H14*(1+O$6)/EXR,-3)*EXR)+IF(Currency="USD",250000,250000*EXR) -> 78494000000 | N14: =$E14*M14 -> 78494000000 | O14: =N14/L14 -> 6.5411667e+09 | Q14: 12 | R14: =IF(Currency="USD",ROUNDUP($E14*$H14*(1+T$6),-3),ROUNDUP($E14*$H14*(1+T$6)/EXR,-3)*EXR)+IF(Currency="USD",250000,250000*EXR) -> 78494000000 | S14: =$E14*R14 -> 78494000000 | T14: =S14/Q14 -> 6.5411667e+09 | V14: 12 | W14: =H14 -> 6.727793e+10 | X14: =$E14*W14 -> 6.727793e+10 | Y14: =X14/V14 -> 5.6064942e+09 | AA14: 12 | AB14: =IF(Currency="USD",ROUNDUP($E14*$H14*(1+AD$6),-3),ROUNDUP($E14*$H14*(1+AD$6)/EXR,-3)*EXR)+IF(Currency="USD",250000,250000*EXR) -> 73788000000 | AC14: =$E14*AB14 -> 73788000000 | AD14: =AC14/AA14 -> 6149000000 | AF14: 12 | AG14: =IF(Currency="USD",ROUNDUP($E14*$H14*(1+AI$6),-3),ROUNDUP($E14*$H14*(1+AI$6)/EXR,-3)*EXR)+IF(Currency="USD",250000,250000*EXR) -> 73788000000 | AH14: =$E14*AG14 -> 73788000000 | AI14: =AH14/AF14 -> 6149000000 | AK14: Canada | AL14: A. Quân | AM14: Gía trị bán lại = giá trị ban đầu - khấu hao * sản lượng sx | AO14: =IF($G14>=AO$8,$J14,0) -> 5.6064942e+09 | AP14: =IF($G14>=AP$8,$J14,0) -> 5.6064942e+09 | AQ14: =IF($G14>=AQ$8,$J14,0) -> 5.6064942e+09 | AR14: =IF($G14>=AR$8,$J14,0) -> 5.6064942e+09 | AS14: =IF($G14>=AS$8,$J14,0) -> 5.6064942e+09 | AT14: =IF($G14>=AT$8,$J14,0) -> 5.6064942e+09 | AU14: =IF($G14>=AU$8,$J14,0) -> 5.6064942e+09 | AV14: =IF($G14>=AV$8,$J14,0) -> 5.6064942e+09 | ... BR14: =IF($G14>=BR$8,$J14,0) -> 0 | BT14: =IF($L14>=BT$8,$O14,0) -> 6.5411667e+09 | BU14: =IF($L14>=BU$8,$O14,0) -> 6.5411667e+09 | BV14: =IF($L14>=BV$8,$O14,0) -> 6.5411667e+09 | BW14: =IF($L14>=BW$8,$O14,0) -> 6.5411667e+09 | BX14: =IF($L14>=BX$8,$O14,0) -> 6.5411667e+09 | BY14: =IF($L14>=BY$8,$O14,0) -> 6.5411667e+09 | BZ14: =IF($L14>=BZ$8,$O14,0) -> 6.5411667e+09 | CA14: =IF($L14>=CA$8,$O14,0) -> 6.5411667e+09 | ... CW14: =IF($L14>=CW$8,$O14,0) -> 0 | CY14: =IF($Q14>=CY$8,$T14,0) -> 6.5411667e+09 | CZ14: =IF($Q14>=CZ$8,$T14,0) -> 6.5411667e+09 | DA14: =IF($Q14>=DA$8,$T14,0) -> 6.5411667e+09 | DB14: =IF($Q14>=DB$8,$T14,0) -> 6.5411667e+09 | DC14: =IF($Q14>=DC$8,$T14,0) -> 6.5411667e+09 | DD14: =IF($Q14>=DD$8,$T14,0) -> 6.5411667e+09 | DE14: =IF($Q14>=DE$8,$T14,0) -> 6.5411667e+09 | DF14: =IF($Q14>=DF$8,$T14,0) -> 6.5411667e+09 | ... EB14: =IF($Q14>=EB$8,$T14,0) -> 0 | ED14: =IF($V14>=ED$8,$Y14,0) -> 5.6064942e+09 | EE14: =IF($V14>=EE$8,$Y14,0) -> 5.6064942e+09 | EF14: =IF($V14>=EF$8,$Y14,0) -> 5.6064942e+09 | EG14: =IF($V14>=EG$8,$Y14,0) -> 5.6064942e+09 | EH14: =IF($V14>=EH$8,$Y14,0) -> 5.6064942e+09 | EI14: =IF($V14>=EI$8,$Y14,0) -> 5.6064942e+09 | EJ14: =IF($V14>=EJ$8,$Y14,0) -> 5.6064942e+09 | EK14: =IF($V14>=EK$8,$Y14,0) -> 5.6064942e+09 | ... FG14: =IF($V14>=FG$8,$Y14,0) -> 0 | FI14: =IF($AA14>=FI$8,$AD14,0) -> 6149000000 | FJ14: =IF($AA14>=FJ$8,$AD14,0) -> 6149000000 | FK14: =IF($AA14>=FK$8,$AD14,0) -> 6149000000 | FL14: =IF($AA14>=FL$8,$AD14,0) -> 6149000000 | FM14: =IF($AA14>=FM$8,$AD14,0) -> 6149000000 | FN14: =IF($AA14>=FN$8,$AD14,0) -> 6149000000 | FO14: =IF($AA14>=FO$8,$AD14,0) -> 6149000000 | FP14: =IF($AA14>=FP$8,$AD14,0) -> 6149000000 | ... GL14: =IF($AA14>=GL$8,$AD14,0) -> 0 | GN14: =IF($AF14>=GN$8,$AI14,0) -> 6149000000 | GO14: =IF($AF14>=GO$8,$AI14,0) -> 6149000000 | GP14: =IF($AF14>=GP$8,$AI14,0) -> 6149000000 | GQ14: =IF($AF14>=GQ$8,$AI14,0) -> 6149000000 | GR14: =IF($AF14>=GR$8,$AI14,0) -> 6149000000 | GS14: =IF($AF14>=GS$8,$AI14,0) -> 6149000000 | GT14: =IF($AF14>=GT$8,$AI14,0) -> 6149000000 | GU14: =IF($AF14>=GU$8,$AI14,0) -> 6149000000 | ... HQ14: =IF($AF14>=HQ$8,$AI14,0) -> 0
B15: Husky 128 cavs Injection Machine | C15: 1.1.03 | D15: Khuôn 15g PCO 1881 128 cavtiy | E15: 1 | G15: 12 | H15: =(47050000000/$D$6*(1-0.196393571148569))*1.04 -> 3.932207e+10 | I15: =$E15*$H15 -> 3.932207e+10 | J15: =I15/G15 -> 3.2768391e+09 | L15: 12 | M15: =(IF(Currency="USD",ROUNDUP($E15*$H15*(1+O$6),-3),ROUNDUP($E15*$H15*(1+O$6)/EXR,-3)*EXR)+IF(Currency="USD",250000,250000*EXR)) -> 48594000000 | N15: =$E15*M15 -> 48594000000 | O15: =N15/L15 -> 4049500000 | Q15: 12 | R15: =(IF(Currency="USD",ROUNDUP($E15*$H15*(1+T$6),-3),ROUNDUP($E15*$H15*(1+T$6)/EXR,-3)*EXR)+IF(Currency="USD",250000,250000*EXR)) -> 48594000000 | S15: =$E15*R15 -> 48594000000 | T15: =S15/Q15 -> 4049500000 | V15: 12 | W15: =H15 -> 3.932207e+10 | X15: =$E15*W15 -> 3.932207e+10 | Y15: =X15/V15 -> 3.2768391e+09 | AA15: 12 | AB15: =(IF(Currency="USD",ROUNDUP($E15*$H15*(1+AD$6),-3),ROUNDUP($E15*$H15*(1+AD$6)/EXR,-3)*EXR)+IF(Currency="USD",250000,250000*EXR)) -> 45838000000 | AC15: =$E15*AB15 -> 45838000000 | AD15: =AC15/AA15 -> 3.8198333e+09 | AF15: 12 | AG15: =(IF(Currency="USD",ROUNDUP($E15*$H15*(1+AI$6),-3),ROUNDUP($E15*$H15*(1+AI$6)/EXR,-3)*EXR)+IF(Currency="USD",250000,250000*EXR)) -> 45838000000 | AH15: =$E15*AG15 -> 45838000000 | AI15: =AH15/AF15 -> 3.8198333e+09 | AK15: Canada | AL15: A. Quân | AM15: Gía trị bán lại = giá trị ban đầu - khấu hao * sản lượng sx | AO15: =IF($G15>=AO$8,$J15,0) -> 3.2768391e+09 | AP15: =IF($G15>=AP$8,$J15,0) -> 3.2768391e+09 | AQ15: =IF($G15>=AQ$8,$J15,0) -> 3.2768391e+09 | AR15: =IF($G15>=AR$8,$J15,0) -> 3.2768391e+09 | AS15: =IF($G15>=AS$8,$J15,0) -> 3.2768391e+09 | AT15: =IF($G15>=AT$8,$J15,0) -> 3.2768391e+09 | AU15: =IF($G15>=AU$8,$J15,0) -> 3.2768391e+09 | AV15: =IF($G15>=AV$8,$J15,0) -> 3.2768391e+09 | ... BR15: =IF($G15>=BR$8,$J15,0) -> 0 | BT15: =IF($L15>=BT$8,$O15,0) -> 4049500000 | BU15: =IF($L15>=BU$8,$O15,0) -> 4049500000 | BV15: =IF($L15>=BV$8,$O15,0) -> 4049500000 | BW15: =IF($L15>=BW$8,$O15,0) -> 4049500000 | BX15: =IF($L15>=BX$8,$O15,0) -> 4049500000 | BY15: =IF($L15>=BY$8,$O15,0) -> 4049500000 | BZ15: =IF($L15>=BZ$8,$O15,0) -> 4049500000 | CA15: =IF($L15>=CA$8,$O15,0) -> 4049500000 | ... CW15: =IF($L15>=CW$8,$O15,0) -> 0 | CY15: =IF($Q15>=CY$8,$T15,0) -> 4049500000 | CZ15: =IF($Q15>=CZ$8,$T15,0) -> 4049500000 | DA15: =IF($Q15>=DA$8,$T15,0) -> 4049500000 | DB15: =IF($Q15>=DB$8,$T15,0) -> 4049500000 | DC15: =IF($Q15>=DC$8,$T15,0) -> 4049500000 | DD15: =IF($Q15>=DD$8,$T15,0) -> 4049500000 | DE15: =IF($Q15>=DE$8,$T15,0) -> 4049500000 | DF15: =IF($Q15>=DF$8,$T15,0) -> 4049500000 | ... EB15: =IF($Q15>=EB$8,$T15,0) -> 0 | ED15: =IF($V15>=ED$8,$Y15,0) -> 3.2768391e+09 | EE15: =IF($V15>=EE$8,$Y15,0) -> 3.2768391e+09 | EF15: =IF($V15>=EF$8,$Y15,0) -> 3.2768391e+09 | EG15: =IF($V15>=EG$8,$Y15,0) -> 3.2768391e+09 | EH15: =IF($V15>=EH$8,$Y15,0) -> 3.2768391e+09 | EI15: =IF($V15>=EI$8,$Y15,0) -> 3.2768391e+09 | EJ15: =IF($V15>=EJ$8,$Y15,0) -> 3.2768391e+09 | EK15: =IF($V15>=EK$8,$Y15,0) -> 3.2768391e+09 | ... FG15: =IF($V15>=FG$8,$Y15,0) -> 0 | FI15: =IF($AA15>=FI$8,$AD15,0) -> 3.8198333e+09 | FJ15: =IF($AA15>=FJ$8,$AD15,0) -> 3.8198333e+09 | FK15: =IF($AA15>=FK$8,$AD15,0) -> 3.8198333e+09 | FL15: =IF($AA15>=FL$8,$AD15,0) -> 3.8198333e+09 | FM15: =IF($AA15>=FM$8,$AD15,0) -> 3.8198333e+09 | FN15: =IF($AA15>=FN$8,$AD15,0) -> 3.8198333e+09 | FO15: =IF($AA15>=FO$8,$AD15,0) -> 3.8198333e+09 | FP15: =IF($AA15>=FP$8,$AD15,0) -> 3.8198333e+09 | ... GL15: =IF($AA15>=GL$8,$AD15,0) -> 0 | GN15: =IF($AF15>=GN$8,$AI15,0) -> 3.8198333e+09 | GO15: =IF($AF15>=GO$8,$AI15,0) -> 3.8198333e+09 | GP15: =IF($AF15>=GP$8,$AI15,0) -> 3.8198333e+09 | GQ15: =IF($AF15>=GQ$8,$AI15,0) -> 3.8198333e+09 | GR15: =IF($AF15>=GR$8,$AI15,0) -> 3.8198333e+09 | GS15: =IF($AF15>=GS$8,$AI15,0) -> 3.8198333e+09 | GT15: =IF($AF15>=GT$8,$AI15,0) -> 3.8198333e+09 | GU15: =IF($AF15>=GU$8,$AI15,0) -> 3.8198333e+09 | ... HQ15: =IF($AF15>=HQ$8,$AI15,0) -> 0
B16: Installing & delivery cost | C16: 1.1.04 | D16: Chi phí vận chuyển | E16: 1 | G16: 12 | H16: =(2500000000/$D$6)*1.04 -> 2600000000 | I16: =$E16*$H16 -> 2600000000 | J16: =I16/G16 -> 2.1666667e+08 | L16: 12 | M16: =ROUNDUP($E16*$H16*(1+O$6),-3)+IF(Currency="USD",45000,45000*EXR) -> 3952000000 | N16: =$E16*M16 -> 3952000000 | O16: =N16/L16 -> 3.2933333e+08 | Q16: 12 | R16: =ROUNDUP($E16*$H16*(1+T$6),-3)+IF(Currency="USD",45000,45000*EXR) -> 3952000000 | S16: =$E16*R16 -> 3952000000 | T16: =S16/Q16 -> 3.2933333e+08 | V16: 12 | W16: =H16 -> 2600000000 | X16: =$E16*W16 -> 2600000000 | Y16: =X16/V16 -> 2.1666667e+08 | AA16: 12 | AB16: =ROUNDUP($E16*$H16*(1+AD$6),-3)+IF(Currency="USD",45000,45000*EXR) -> 3770000000 | AC16: =$E16*AB16 -> 3770000000 | AD16: =AC16/AA16 -> 3.1416667e+08 | AF16: 12 | AG16: =ROUNDUP($E16*$H16*(1+AI$6),-3)+IF(Currency="USD",45000,45000*EXR) -> 3770000000 | AH16: =$E16*AG16 -> 3770000000 | AI16: =AH16/AF16 -> 3.1416667e+08 | AL16: A. Quân | AM16: Gía trị bán lại = giá trị ban đầu - khấu hao * sản lượng sx | AO16: =IF($G16>=AO$8,$J16,0) -> 2.1666667e+08 | AP16: =IF($G16>=AP$8,$J16,0) -> 2.1666667e+08 | AQ16: =IF($G16>=AQ$8,$J16,0) -> 2.1666667e+08 | AR16: =IF($G16>=AR$8,$J16,0) -> 2.1666667e+08 | AS16: =IF($G16>=AS$8,$J16,0) -> 2.1666667e+08 | AT16: =IF($G16>=AT$8,$J16,0) -> 2.1666667e+08 | AU16: =IF($G16>=AU$8,$J16,0) -> 2.1666667e+08 | AV16: =IF($G16>=AV$8,$J16,0) -> 2.1666667e+08 | ... BR16: =IF($G16>=BR$8,$J16,0) -> 0 | BT16: =IF($L16>=BT$8,$O16,0) -> 3.2933333e+08 | BU16: =IF($L16>=BU$8,$O16,0) -> 3.2933333e+08 | BV16: =IF($L16>=BV$8,$O16,0) -> 3.2933333e+08 | BW16: =IF($L16>=BW$8,$O16,0) -> 3.2933333e+08 | BX16: =IF($L16>=BX$8,$O16,0) -> 3.2933333e+08 | BY16: =IF($L16>=BY$8,$O16,0) -> 3.2933333e+08 | BZ16: =IF($L16>=BZ$8,$O16,0) -> 3.2933333e+08 | CA16: =IF($L16>=CA$8,$O16,0) -> 3.2933333e+08 | ... CW16: =IF($L16>=CW$8,$O16,0) -> 0 | CY16: =IF($Q16>=CY$8,$T16,0) -> 3.2933333e+08 | CZ16: =IF($Q16>=CZ$8,$T16,0) -> 3.2933333e+08 | DA16: =IF($Q16>=DA$8,$T16,0) -> 3.2933333e+08 | DB16: =IF($Q16>=DB$8,$T16,0) -> 3.2933333e+08 | DC16: =IF($Q16>=DC$8,$T16,0) -> 3.2933333e+08 | DD16: =IF($Q16>=DD$8,$T16,0) -> 3.2933333e+08 | DE16: =IF($Q16>=DE$8,$T16,0) -> 3.2933333e+08 | DF16: =IF($Q16>=DF$8,$T16,0) -> 3.2933333e+08 | ... EB16: =IF($Q16>=EB$8,$T16,0) -> 0 | ED16: =IF($V16>=ED$8,$Y16,0) -> 2.1666667e+08 | EE16: =IF($V16>=EE$8,$Y16,0) -> 2.1666667e+08 | EF16: =IF($V16>=EF$8,$Y16,0) -> 2.1666667e+08 | EG16: =IF($V16>=EG$8,$Y16,0) -> 2.1666667e+08 | EH16: =IF($V16>=EH$8,$Y16,0) -> 2.1666667e+08 | EI16: =IF($V16>=EI$8,$Y16,0) -> 2.1666667e+08 | EJ16: =IF($V16>=EJ$8,$Y16,0) -> 2.1666667e+08 | EK16: =IF($V16>=EK$8,$Y16,0) -> 2.1666667e+08 | ... FG16: =IF($V16>=FG$8,$Y16,0) -> 0 | FI16: =IF($AA16>=FI$8,$AD16,0) -> 3.1416667e+08 | FJ16: =IF($AA16>=FJ$8,$AD16,0) -> 3.1416667e+08 | FK16: =IF($AA16>=FK$8,$AD16,0) -> 3.1416667e+08 | FL16: =IF($AA16>=FL$8,$AD16,0) -> 3.1416667e+08 | FM16: =IF($AA16>=FM$8,$AD16,0) -> 3.1416667e+08 | FN16: =IF($AA16>=FN$8,$AD16,0) -> 3.1416667e+08 | FO16: =IF($AA16>=FO$8,$AD16,0) -> 3.1416667e+08 | FP16: =IF($AA16>=FP$8,$AD16,0) -> 3.1416667e+08 | ... GL16: =IF($AA16>=GL$8,$AD16,0) -> 0 | GN16: =IF($AF16>=GN$8,$AI16,0) -> 3.1416667e+08 | GO16: =IF($AF16>=GO$8,$AI16,0) -> 3.1416667e+08 | GP16: =IF($AF16>=GP$8,$AI16,0) -> 3.1416667e+08 | GQ16: =IF($AF16>=GQ$8,$AI16,0) -> 3.1416667e+08 | GR16: =IF($AF16>=GR$8,$AI16,0) -> 3.1416667e+08 | GS16: =IF($AF16>=GS$8,$AI16,0) -> 3.1416667e+08 | GT16: =IF($AF16>=GT$8,$AI16,0) -> 3.1416667e+08 | GU16: =IF($AF16>=GU$8,$AI16,0) -> 3.1416667e+08 | ... HQ16: =IF($AF16>=HQ$8,$AI16,0) -> 0
B17: Installing & delivery cost | C17: 1.1.05 | D17: Chi phí lắp đặt | E17: 1 | G17: 12 | H17: =(8250000000/$D$6)*1.04 -> 8580000000 | I17: =$E17*$H17 -> 8580000000 | J17: =I17/G17 -> 715000000 | L17: 12 | M17: =IF(Currency="USD",ROUNDUP($E17*$H17*(1+O$6),-3),ROUNDUP($E17*$H17*(1+O$6)/EXR,-3)*EXR) -> 9204000000 | N17: =$E17*M17 -> 9204000000 | O17: =N17/L17 -> 767000000 | Q17: 12 | R17: =IF(Currency="USD",ROUNDUP($E17*$H17*(1+T$6),-3),ROUNDUP($E17*$H17*(1+T$6)/EXR,-3)*EXR) -> 9204000000 | S17: =$E17*R17 -> 9204000000 | T17: =S17/Q17 -> 767000000 | V17: 12 | W17: =H17 -> 8580000000 | X17: =$E17*W17 -> 8580000000 | Y17: =X17/V17 -> 715000000 | AA17: 12 | AB17: =IF(Currency="USD",ROUNDUP($E17*$H17*(1+AD$6),-3),ROUNDUP($E17*$H17*(1+AD$6)/EXR,-3)*EXR) -> 8580000000 | AC17: =$E17*AB17 -> 8580000000 | AD17: =AC17/AA17 -> 715000000 | AF17: 12 | AG17: =IF(Currency="USD",ROUNDUP($E17*$H17*(1+AI$6),-3),ROUNDUP($E17*$H17*(1+AI$6)/EXR,-3)*EXR) -> 8580000000 | AH17: =$E17*AG17 -> 8580000000 | AI17: =AH17/AF17 -> 715000000 | AL17: A. Quân | AM17: Gía trị bán lại = giá trị ban đầu - khấu hao * sản lượng sx | AO17: =IF($G17>=AO$8,$J17,0) -> 715000000 | AP17: =IF($G17>=AP$8,$J17,0) -> 715000000 | AQ17: =IF($G17>=AQ$8,$J17,0) -> 715000000 | AR17: =IF($G17>=AR$8,$J17,0) -> 715000000 | AS17: =IF($G17>=AS$8,$J17,0) -> 715000000 | AT17: =IF($G17>=AT$8,$J17,0) -> 715000000 | AU17: =IF($G17>=AU$8,$J17,0) -> 715000000 | AV17: =IF($G17>=AV$8,$J17,0) -> 715000000 | ... BR17: =IF($G17>=BR$8,$J17,0) -> 0 | BT17: =IF($L17>=BT$8,$O17,0) -> 767000000 | BU17: =IF($L17>=BU$8,$O17,0) -> 767000000 | BV17: =IF($L17>=BV$8,$O17,0) -> 767000000 | BW17: =IF($L17>=BW$8,$O17,0) -> 767000000 | BX17: =IF($L17>=BX$8,$O17,0) -> 767000000 | BY17: =IF($L17>=BY$8,$O17,0) -> 767000000 | BZ17: =IF($L17>=BZ$8,$O17,0) -> 767000000 | CA17: =IF($L17>=CA$8,$O17,0) -> 767000000 | ... CW17: =IF($L17>=CW$8,$O17,0) -> 0 | CY17: =IF($Q17>=CY$8,$T17,0) -> 767000000 | CZ17: =IF($Q17>=CZ$8,$T17,0) -> 767000000 | DA17: =IF($Q17>=DA$8,$T17,0) -> 767000000 | DB17: =IF($Q17>=DB$8,$T17,0) -> 767000000 | DC17: =IF($Q17>=DC$8,$T17,0) -> 767000000 | DD17: =IF($Q17>=DD$8,$T17,0) -> 767000000 | DE17: =IF($Q17>=DE$8,$T17,0) -> 767000000 | DF17: =IF($Q17>=DF$8,$T17,0) -> 767000000 | ... EB17: =IF($Q17>=EB$8,$T17,0) -> 0 | ED17: =IF($V17>=ED$8,$Y17,0) -> 715000000 | EE17: =IF($V17>=EE$8,$Y17,0) -> 715000000 | EF17: =IF($V17>=EF$8,$Y17,0) -> 715000000 | EG17: =IF($V17>=EG$8,$Y17,0) -> 715000000 | EH17: =IF($V17>=EH$8,$Y17,0) -> 715000000 | EI17: =IF($V17>=EI$8,$Y17,0) -> 715000000 | EJ17: =IF($V17>=EJ$8,$Y17,0) -> 715000000 | EK17: =IF($V17>=EK$8,$Y17,0) -> 715000000 | ... FG17: =IF($V17>=FG$8,$Y17,0) -> 0 | FI17: =IF($AA17>=FI$8,$AD17,0) -> 715000000 | FJ17: =IF($AA17>=FJ$8,$AD17,0) -> 715000000 | FK17: =IF($AA17>=FK$8,$AD17,0) -> 715000000 | FL17: =IF($AA17>=FL$8,$AD17,0) -> 715000000 | FM17: =IF($AA17>=FM$8,$AD17,0) -> 715000000 | FN17: =IF($AA17>=FN$8,$AD17,0) -> 715000000 | FO17: =IF($AA17>=FO$8,$AD17,0) -> 715000000 | FP17: =IF($AA17>=FP$8,$AD17,0) -> 715000000 | ... GL17: =IF($AA17>=GL$8,$AD17,0) -> 0 | GN17: =IF($AF17>=GN$8,$AI17,0) -> 715000000 | GO17: =IF($AF17>=GO$8,$AI17,0) -> 715000000 | GP17: =IF($AF17>=GP$8,$AI17,0) -> 715000000 | GQ17: =IF($AF17>=GQ$8,$AI17,0) -> 715000000 | GR17: =IF($AF17>=GR$8,$AI17,0) -> 715000000 | GS17: =IF($AF17>=GS$8,$AI17,0) -> 715000000 | GT17: =IF($AF17>=GT$8,$AI17,0) -> 715000000 | GU17: =IF($AF17>=GU$8,$AI17,0) -> 715000000 | ... HQ17: =IF($AF17>=HQ$8,$AI17,0) -> 0
B18: Installing & delivery cost | C18: 1.1.06 | D18: Thuế nhà thầu | E18: 1 | G18: 12 | H18: =(8250000000*5%/$D$6)*1.04 -> 429000000 | I18: =$E18*$H18 -> 429000000 | J18: =I18/G18 -> 35750000 | L18: 12 | M18: =IF(Currency="USD",ROUNDUP($E18*$H18*(1+O$6),-3),ROUNDUP($E18*$H18*(1+O$6)/EXR,-3)*EXR) -> 468000000 | N18: =$E18*M18 -> 468000000 | O18: =N18/L18 -> 39000000 | Q18: 12 | R18: =IF(Currency="USD",ROUNDUP($E18*$H18*(1+T$6),-3),ROUNDUP($E18*$H18*(1+T$6)/EXR,-3)*EXR) -> 468000000 | S18: =$E18*R18 -> 468000000 | T18: =S18/Q18 -> 39000000 | V18: 12 | W18: =H18 -> 429000000 | X18: =$E18*W18 -> 429000000 | Y18: =X18/V18 -> 35750000 | AA18: 12 | AB18: =IF(Currency="USD",ROUNDUP($E18*$H18*(1+AD$6),-3),ROUNDUP($E18*$H18*(1+AD$6)/EXR,-3)*EXR) -> 442000000 | AC18: =$E18*AB18 -> 442000000 | AD18: =AC18/AA18 -> 36833333 | AF18: 12 | AG18: =IF(Currency="USD",ROUNDUP($E18*$H18*(1+AI$6),-3),ROUNDUP($E18*$H18*(1+AI$6)/EXR,-3)*EXR) -> 442000000 | AH18: =$E18*AG18 -> 442000000 | AI18: =AH18/AF18 -> 36833333 | AO18: =IF($G18>=AO$8,$J18,0) -> 35750000 | AP18: =IF($G18>=AP$8,$J18,0) -> 35750000 | AQ18: =IF($G18>=AQ$8,$J18,0) -> 35750000 | AR18: =IF($G18>=AR$8,$J18,0) -> 35750000 | AS18: =IF($G18>=AS$8,$J18,0) -> 35750000 | AT18: =IF($G18>=AT$8,$J18,0) -> 35750000 | AU18: =IF($G18>=AU$8,$J18,0) -> 35750000 | AV18: =IF($G18>=AV$8,$J18,0) -> 35750000 | ... BR18: =IF($G18>=BR$8,$J18,0) -> 0 | BT18: =IF($L18>=BT$8,$O18,0) -> 39000000 | BU18: =IF($L18>=BU$8,$O18,0) -> 39000000 | BV18: =IF($L18>=BV$8,$O18,0) -> 39000000 | BW18: =IF($L18>=BW$8,$O18,0) -> 39000000 | BX18: =IF($L18>=BX$8,$O18,0) -> 39000000 | BY18: =IF($L18>=BY$8,$O18,0) -> 39000000 | BZ18: =IF($L18>=BZ$8,$O18,0) -> 39000000 | CA18: =IF($L18>=CA$8,$O18,0) -> 39000000 | ... CW18: =IF($L18>=CW$8,$O18,0) -> 0 | CY18: =IF($Q18>=CY$8,$T18,0) -> 39000000 | CZ18: =IF($Q18>=CZ$8,$T18,0) -> 39000000 | DA18: =IF($Q18>=DA$8,$T18,0) -> 39000000 | DB18: =IF($Q18>=DB$8,$T18,0) -> 39000000 | DC18: =IF($Q18>=DC$8,$T18,0) -> 39000000 | DD18: =IF($Q18>=DD$8,$T18,0) -> 39000000 | DE18: =IF($Q18>=DE$8,$T18,0) -> 39000000 | DF18: =IF($Q18>=DF$8,$T18,0) -> 39000000 | ... EB18: =IF($Q18>=EB$8,$T18,0) -> 0 | ED18: =IF($V18>=ED$8,$Y18,0) -> 35750000 | EE18: =IF($V18>=EE$8,$Y18,0) -> 35750000 | EF18: =IF($V18>=EF$8,$Y18,0) -> 35750000 | EG18: =IF($V18>=EG$8,$Y18,0) -> 35750000 | EH18: =IF($V18>=EH$8,$Y18,0) -> 35750000 | EI18: =IF($V18>=EI$8,$Y18,0) -> 35750000 | EJ18: =IF($V18>=EJ$8,$Y18,0) -> 35750000 | EK18: =IF($V18>=EK$8,$Y18,0) -> 35750000 | ... FG18: =IF($V18>=FG$8,$Y18,0) -> 0 | FI18: =IF($AA18>=FI$8,$AD18,0) -> 36833333 | FJ18: =IF($AA18>=FJ$8,$AD18,0) -> 36833333 | FK18: =IF($AA18>=FK$8,$AD18,0) -> 36833333 | FL18: =IF($AA18>=FL$8,$AD18,0) -> 36833333 | FM18: =IF($AA18>=FM$8,$AD18,0) -> 36833333 | FN18: =IF($AA18>=FN$8,$AD18,0) -> 36833333 | FO18: =IF($AA18>=FO$8,$AD18,0) -> 36833333 | FP18: =IF($AA18>=FP$8,$AD18,0) -> 36833333 | ... GL18: =IF($AA18>=GL$8,$AD18,0) -> 0 | GN18: =IF($AF18>=GN$8,$AI18,0) -> 36833333 | GO18: =IF($AF18>=GO$8,$AI18,0) -> 36833333 | GP18: =IF($AF18>=GP$8,$AI18,0) -> 36833333 | GQ18: =IF($AF18>=GQ$8,$AI18,0) -> 36833333 | GR18: =IF($AF18>=GR$8,$AI18,0) -> 36833333 | GS18: =IF($AF18>=GS$8,$AI18,0) -> 36833333 | GT18: =IF($AF18>=GT$8,$AI18,0) -> 36833333 | GU18: =IF($AF18>=GU$8,$AI18,0) -> 36833333 | ... HQ18: =IF($AF18>=HQ$8,$AI18,0) -> 0
A20: CAPEX-SUB | C20: 1.2 | D20: Máy móc thiết bị phụ | I20: =SUM(I21:I33) -> 38110800000 | J20: =SUM(J21:J33) -> 3175900000 | N20: =SUM(N21:N33) -> 40872000000 | O20: =SUM(O21:O33) -> 3.406e+09 | S20: =SUM(S21:S33) -> 40872000000 | T20: =SUM(T21:T33) -> 3.406e+09 | X20: =SUM(X21:X33) -> 38110800000 | Y20: =SUM(Y21:Y33) -> 3175900000 | AC20: =SUM(AC21:AC33) -> 38116000000 | AD20: =SUM(AD21:AD33) -> 3.1763333e+09 | AH20: =SUM(AH21:AH33) -> 38116000000 | AI20: =SUM(AI21:AI33) -> 3.1763333e+09 | AO20: =SUM(AO21:AO33) -> 3175900000 | AP20: =SUM(AP21:AP33) -> 3175900000 | AQ20: =SUM(AQ21:AQ33) -> 3175900000 | AR20: =SUM(AR21:AR33) -> 3175900000 | AS20: =SUM(AS21:AS33) -> 3175900000 | AT20: =SUM(AT21:AT33) -> 3175900000 | AU20: =SUM(AU21:AU33) -> 3175900000 | AV20: =SUM(AV21:AV33) -> 3175900000 | ... BR20: =SUM(BR21:BR33) -> 0 | BT20: =SUM(BT21:BT33) -> 3.406e+09 | BU20: =SUM(BU21:BU33) -> 3.406e+09 | BV20: =SUM(BV21:BV33) -> 3.406e+09 | BW20: =SUM(BW21:BW33) -> 3.406e+09 | BX20: =SUM(BX21:BX33) -> 3.406e+09 | BY20: =SUM(BY21:BY33) -> 3.406e+09 | BZ20: =SUM(BZ21:BZ33) -> 3.406e+09 | CA20: =SUM(CA21:CA33) -> 3.406e+09 | ... CW20: =SUM(CW21:CW33) -> 0 | CY20: =SUM(CY21:CY33) -> 3.406e+09 | CZ20: =SUM(CZ21:CZ33) -> 3.406e+09 | DA20: =SUM(DA21:DA33) -> 3.406e+09 | DB20: =SUM(DB21:DB33) -> 3.406e+09 | DC20: =SUM(DC21:DC33) -> 3.406e+09 | DD20: =SUM(DD21:DD33) -> 3.406e+09 | DE20: =SUM(DE21:DE33) -> 3.406e+09 | DF20: =SUM(DF21:DF33) -> 3.406e+09 | ... EB20: =SUM(EB21:EB33) -> 0 | ED20: =SUM(ED21:ED33) -> 3175900000 | EE20: =SUM(EE21:EE33) -> 3175900000 | EF20: =SUM(EF21:EF33) -> 3175900000 | EG20: =SUM(EG21:EG33) -> 3175900000 | EH20: =SUM(EH21:EH33) -> 3175900000 | EI20: =SUM(EI21:EI33) -> 3175900000 | EJ20: =SUM(EJ21:EJ33) -> 3175900000 | EK20: =SUM(EK21:EK33) -> 3175900000 | ... FG20: =SUM(FG21:FG33) -> 0 | FI20: =SUM(FI21:FI33) -> 3.1763333e+09 | FJ20: =SUM(FJ21:FJ33) -> 3.1763333e+09 | FK20: =SUM(FK21:FK33) -> 3.1763333e+09 | FL20: =SUM(FL21:FL33) -> 3.1763333e+09 | FM20: =SUM(FM21:FM33) -> 3.1763333e+09 | FN20: =SUM(FN21:FN33) -> 3.1763333e+09 | FO20: =SUM(FO21:FO33) -> 3.1763333e+09 | FP20: =SUM(FP21:FP33) -> 3.1763333e+09 | ... GL20: =SUM(GL21:GL33) -> 0 | GN20: =SUM(GN21:GN33) -> 3.1763333e+09 | GO20: =SUM(GO21:GO33) -> 3.1763333e+09 | GP20: =SUM(GP21:GP33) -> 3.1763333e+09 | GQ20: =SUM(GQ21:GQ33) -> 3.1763333e+09 | GR20: =SUM(GR21:GR33) -> 3.1763333e+09 | GS20: =SUM(GS21:GS33) -> 3.1763333e+09 | GT20: =SUM(GT21:GT33) -> 3.1763333e+09 | GU20: =SUM(GU21:GU33) -> 3.1763333e+09 | ... HQ20: =SUM(HQ21:HQ33) -> 0
B21: Auxiliary Equipment | C21: 1.2.06 | D21: Hệ thống nước, khí nén | E21: 1 | G21: 12 | H21: =(7500000000/$D$6)*1.04 -> 7800000000 | I21: =$E21*$H21 -> 7800000000 | J21: =I21/G21 -> 650000000 | L21: 12 | M21: =IF(Currency="USD",ROUNDUP($E21*$H21*(1+O$6),-3),ROUNDUP($E21*$H21*(1+O$6)/EXR,-3)*EXR) -> 8346000000 | N21: =$E21*M21 -> 8346000000 | O21: =N21/L21 -> 695500000 | Q21: 12 | R21: =IF(Currency="USD",ROUNDUP($E21*$H21*(1+T$6),-3),ROUNDUP($E21*$H21*(1+T$6)/EXR,-3)*EXR) -> 8346000000 | S21: =$E21*R21 -> 8346000000 | T21: =S21/Q21 -> 695500000 | V21: 12 | W21: =H21 -> 7800000000 | X21: =$E21*W21 -> 7800000000 | Y21: =X21/V21 -> 650000000 | AA21: 12 | AB21: =IF(Currency="USD",ROUNDUP($E21*$H21*(1+AD$6),-3),ROUNDUP($E21*$H21*(1+AD$6)/EXR,-3)*EXR) -> 7800000000 | AC21: =$E21*AB21 -> 7800000000 | AD21: =AC21/AA21 -> 650000000 | AF21: 12 | AG21: =IF(Currency="USD",ROUNDUP($E21*$H21*(1+AI$6),-3),ROUNDUP($E21*$H21*(1+AI$6)/EXR,-3)*EXR) -> 7800000000 | AH21: =$E21*AG21 -> 7800000000 | AI21: =AH21/AF21 -> 650000000 | AL21: A. Quân | AM21: Đàm phán | AO21: =IF($G21>=AO$8,$J21,0) -> 650000000 | AP21: =IF($G21>=AP$8,$J21,0) -> 650000000 | AQ21: =IF($G21>=AQ$8,$J21,0) -> 650000000 | AR21: =IF($G21>=AR$8,$J21,0) -> 650000000 | AS21: =IF($G21>=AS$8,$J21,0) -> 650000000 | AT21: =IF($G21>=AT$8,$J21,0) -> 650000000 | AU21: =IF($G21>=AU$8,$J21,0) -> 650000000 | AV21: =IF($G21>=AV$8,$J21,0) -> 650000000 | ... BR21: =IF($G21>=BR$8,$J21,0) -> 0 | BT21: =IF($L21>=BT$8,$O21,0) -> 695500000 | BU21: =IF($L21>=BU$8,$O21,0) -> 695500000 | BV21: =IF($L21>=BV$8,$O21,0) -> 695500000 | BW21: =IF($L21>=BW$8,$O21,0) -> 695500000 | BX21: =IF($L21>=BX$8,$O21,0) -> 695500000 | BY21: =IF($L21>=BY$8,$O21,0) -> 695500000 | BZ21: =IF($L21>=BZ$8,$O21,0) -> 695500000 | CA21: =IF($L21>=CA$8,$O21,0) -> 695500000 | ... CW21: =IF($L21>=CW$8,$O21,0) -> 0 | CY21: =IF($Q21>=CY$8,$T21,0) -> 695500000 | CZ21: =IF($Q21>=CZ$8,$T21,0) -> 695500000 | DA21: =IF($Q21>=DA$8,$T21,0) -> 695500000 | DB21: =IF($Q21>=DB$8,$T21,0) -> 695500000 | DC21: =IF($Q21>=DC$8,$T21,0) -> 695500000 | DD21: =IF($Q21>=DD$8,$T21,0) -> 695500000 | DE21: =IF($Q21>=DE$8,$T21,0) -> 695500000 | DF21: =IF($Q21>=DF$8,$T21,0) -> 695500000 | ... EB21: =IF($Q21>=EB$8,$T21,0) -> 0 | ED21: =IF($V21>=ED$8,$Y21,0) -> 650000000 | EE21: =IF($V21>=EE$8,$Y21,0) -> 650000000 | EF21: =IF($V21>=EF$8,$Y21,0) -> 650000000 | EG21: =IF($V21>=EG$8,$Y21,0) -> 650000000 | EH21: =IF($V21>=EH$8,$Y21,0) -> 650000000 | EI21: =IF($V21>=EI$8,$Y21,0) -> 650000000 | EJ21: =IF($V21>=EJ$8,$Y21,0) -> 650000000 | EK21: =IF($V21>=EK$8,$Y21,0) -> 650000000 | ... FG21: =IF($V21>=FG$8,$Y21,0) -> 0 | FI21: =IF($AA21>=FI$8,$AD21,0) -> 650000000 | FJ21: =IF($AA21>=FJ$8,$AD21,0) -> 650000000 | FK21: =IF($AA21>=FK$8,$AD21,0) -> 650000000 | FL21: =IF($AA21>=FL$8,$AD21,0) -> 650000000 | FM21: =IF($AA21>=FM$8,$AD21,0) -> 650000000 | FN21: =IF($AA21>=FN$8,$AD21,0) -> 650000000 | FO21: =IF($AA21>=FO$8,$AD21,0) -> 650000000 | FP21: =IF($AA21>=FP$8,$AD21,0) -> 650000000 | ... GL21: =IF($AA21>=GL$8,$AD21,0) -> 0 | GN21: =IF($AF21>=GN$8,$AI21,0) -> 650000000 | GO21: =IF($AF21>=GO$8,$AI21,0) -> 650000000 | GP21: =IF($AF21>=GP$8,$AI21,0) -> 650000000 | GQ21: =IF($AF21>=GQ$8,$AI21,0) -> 650000000 | GR21: =IF($AF21>=GR$8,$AI21,0) -> 650000000 | GS21: =IF($AF21>=GS$8,$AI21,0) -> 650000000 | GT21: =IF($AF21>=GT$8,$AI21,0) -> 650000000 | GU21: =IF($AF21>=GU$8,$AI21,0) -> 650000000 | ... HQ21: =IF($AF21>=HQ$8,$AI21,0) -> 0
B22: Auxiliary Equipment | C22: 1.2.07 | D22: Hệ thống điện | E22: 1 | G22: 12 | H22: =(7500000000/$D$6)*1.04 -> 7800000000 | I22: =$E22*$H22 -> 7800000000 | J22: =I22/G22 -> 650000000 | L22: 12 | M22: =IF(Currency="USD",ROUNDUP($E22*$H22*(1+O$6),-3),ROUNDUP($E22*$H22*(1+O$6)/EXR,-3)*EXR) -> 8346000000 | N22: =$E22*M22 -> 8346000000 | O22: =N22/L22 -> 695500000 | Q22: 12 | R22: =IF(Currency="USD",ROUNDUP($E22*$H22*(1+T$6),-3),ROUNDUP($E22*$H22*(1+T$6)/EXR,-3)*EXR) -> 8346000000 | S22: =$E22*R22 -> 8346000000 | T22: =S22/Q22 -> 695500000 | V22: 12 | W22: =H22 -> 7800000000 | X22: =$E22*W22 -> 7800000000 | Y22: =X22/V22 -> 650000000 | AA22: 12 | AB22: =IF(Currency="USD",ROUNDUP($E22*$H22*(1+AD$6),-3),ROUNDUP($E22*$H22*(1+AD$6)/EXR,-3)*EXR) -> 7800000000 | AC22: =$E22*AB22 -> 7800000000 | AD22: =AC22/AA22 -> 650000000 | AF22: 12 | AG22: =IF(Currency="USD",ROUNDUP($E22*$H22*(1+AI$6),-3),ROUNDUP($E22*$H22*(1+AI$6)/EXR,-3)*EXR) -> 7800000000 | AH22: =$E22*AG22 -> 7800000000 | AI22: =AH22/AF22 -> 650000000 | AL22: A. Quân | AM22: Đàm phán | AO22: =IF($G22>=AO$8,$J22,0) -> 650000000 | AP22: =IF($G22>=AP$8,$J22,0) -> 650000000 | AQ22: =IF($G22>=AQ$8,$J22,0) -> 650000000 | AR22: =IF($G22>=AR$8,$J22,0) -> 650000000 | AS22: =IF($G22>=AS$8,$J22,0) -> 650000000 | AT22: =IF($G22>=AT$8,$J22,0) -> 650000000 | AU22: =IF($G22>=AU$8,$J22,0) -> 650000000 | AV22: =IF($G22>=AV$8,$J22,0) -> 650000000 | ... BR22: =IF($G22>=BR$8,$J22,0) -> 0 | BT22: =IF($L22>=BT$8,$O22,0) -> 695500000 | BU22: =IF($L22>=BU$8,$O22,0) -> 695500000 | BV22: =IF($L22>=BV$8,$O22,0) -> 695500000 | BW22: =IF($L22>=BW$8,$O22,0) -> 695500000 | BX22: =IF($L22>=BX$8,$O22,0) -> 695500000 | BY22: =IF($L22>=BY$8,$O22,0) -> 695500000 | BZ22: =IF($L22>=BZ$8,$O22,0) -> 695500000 | CA22: =IF($L22>=CA$8,$O22,0) -> 695500000 | ... CW22: =IF($L22>=CW$8,$O22,0) -> 0 | CY22: =IF($Q22>=CY$8,$T22,0) -> 695500000 | CZ22: =IF($Q22>=CZ$8,$T22,0) -> 695500000 | DA22: =IF($Q22>=DA$8,$T22,0) -> 695500000 | DB22: =IF($Q22>=DB$8,$T22,0) -> 695500000 | DC22: =IF($Q22>=DC$8,$T22,0) -> 695500000 | DD22: =IF($Q22>=DD$8,$T22,0) -> 695500000 | DE22: =IF($Q22>=DE$8,$T22,0) -> 695500000 | DF22: =IF($Q22>=DF$8,$T22,0) -> 695500000 | ... EB22: =IF($Q22>=EB$8,$T22,0) -> 0 | ED22: =IF($V22>=ED$8,$Y22,0) -> 650000000 | EE22: =IF($V22>=EE$8,$Y22,0) -> 650000000 | EF22: =IF($V22>=EF$8,$Y22,0) -> 650000000 | EG22: =IF($V22>=EG$8,$Y22,0) -> 650000000 | EH22: =IF($V22>=EH$8,$Y22,0) -> 650000000 | EI22: =IF($V22>=EI$8,$Y22,0) -> 650000000 | EJ22: =IF($V22>=EJ$8,$Y22,0) -> 650000000 | EK22: =IF($V22>=EK$8,$Y22,0) -> 650000000 | ... FG22: =IF($V22>=FG$8,$Y22,0) -> 0 | FI22: =IF($AA22>=FI$8,$AD22,0) -> 650000000 | FJ22: =IF($AA22>=FJ$8,$AD22,0) -> 650000000 | FK22: =IF($AA22>=FK$8,$AD22,0) -> 650000000 | FL22: =IF($AA22>=FL$8,$AD22,0) -> 650000000 | FM22: =IF($AA22>=FM$8,$AD22,0) -> 650000000 | FN22: =IF($AA22>=FN$8,$AD22,0) -> 650000000 | FO22: =IF($AA22>=FO$8,$AD22,0) -> 650000000 | FP22: =IF($AA22>=FP$8,$AD22,0) -> 650000000 | ... GL22: =IF($AA22>=GL$8,$AD22,0) -> 0 | GN22: =IF($AF22>=GN$8,$AI22,0) -> 650000000 | GO22: =IF($AF22>=GO$8,$AI22,0) -> 650000000 | GP22: =IF($AF22>=GP$8,$AI22,0) -> 650000000 | GQ22: =IF($AF22>=GQ$8,$AI22,0) -> 650000000 | GR22: =IF($AF22>=GR$8,$AI22,0) -> 650000000 | GS22: =IF($AF22>=GS$8,$AI22,0) -> 650000000 | GT22: =IF($AF22>=GT$8,$AI22,0) -> 650000000 | GU22: =IF($AF22>=GU$8,$AI22,0) -> 650000000 | ... HQ22: =IF($AF22>=HQ$8,$AI22,0) -> 0
B23: Auxiliary Equipment | C23: 1.2.08 | D23: Pump system | E23: 1 | G23: 12 | H23: =(3750000000/$D$6)*1.04 -> 3900000000 | I23: =$E23*$H23 -> 3900000000 | J23: =I23/G23 -> 325000000 | L23: 12 | M23: =IF(Currency="USD",ROUNDUP($E23*$H23*(1+O$6),-3),ROUNDUP($E23*$H23*(1+O$6)/EXR,-3)*EXR) -> 4186000000 | N23: =$E23*M23 -> 4186000000 | O23: =N23/L23 -> 3.4883333e+08 | Q23: 12 | R23: =IF(Currency="USD",ROUNDUP($E23*$H23*(1+T$6),-3),ROUNDUP($E23*$H23*(1+T$6)/EXR,-3)*EXR) -> 4186000000 | S23: =$E23*R23 -> 4186000000 | T23: =S23/Q23 -> 3.4883333e+08 | V23: 12 | W23: =H23 -> 3900000000 | X23: =$E23*W23 -> 3900000000 | Y23: =X23/V23 -> 325000000 | AA23: 12 | AB23: =IF(Currency="USD",ROUNDUP($E23*$H23*(1+AD$6),-3),ROUNDUP($E23*$H23*(1+AD$6)/EXR,-3)*EXR) -> 3900000000 | AC23: =$E23*AB23 -> 3900000000 | AD23: =AC23/AA23 -> 325000000 | AF23: 12 | AG23: =IF(Currency="USD",ROUNDUP($E23*$H23*(1+AI$6),-3),ROUNDUP($E23*$H23*(1+AI$6)/EXR,-3)*EXR) -> 3900000000 | AH23: =$E23*AG23 -> 3900000000 | AI23: =AH23/AF23 -> 325000000 | AL23: A. Quân | AM23: Đàm phán | AO23: =IF($G23>=AO$8,$J23,0) -> 325000000 | AP23: =IF($G23>=AP$8,$J23,0) -> 325000000 | AQ23: =IF($G23>=AQ$8,$J23,0) -> 325000000 | AR23: =IF($G23>=AR$8,$J23,0) -> 325000000 | AS23: =IF($G23>=AS$8,$J23,0) -> 325000000 | AT23: =IF($G23>=AT$8,$J23,0) -> 325000000 | AU23: =IF($G23>=AU$8,$J23,0) -> 325000000 | AV23: =IF($G23>=AV$8,$J23,0) -> 325000000 | ... BR23: =IF($G23>=BR$8,$J23,0) -> 0 | BT23: =IF($L23>=BT$8,$O23,0) -> 3.4883333e+08 | BU23: =IF($L23>=BU$8,$O23,0) -> 3.4883333e+08 | BV23: =IF($L23>=BV$8,$O23,0) -> 3.4883333e+08 | BW23: =IF($L23>=BW$8,$O23,0) -> 3.4883333e+08 | BX23: =IF($L23>=BX$8,$O23,0) -> 3.4883333e+08 | BY23: =IF($L23>=BY$8,$O23,0) -> 3.4883333e+08 | BZ23: =IF($L23>=BZ$8,$O23,0) -> 3.4883333e+08 | CA23: =IF($L23>=CA$8,$O23,0) -> 3.4883333e+08 | ... CW23: =IF($L23>=CW$8,$O23,0) -> 0 | CY23: =IF($Q23>=CY$8,$T23,0) -> 3.4883333e+08 | CZ23: =IF($Q23>=CZ$8,$T23,0) -> 3.4883333e+08 | DA23: =IF($Q23>=DA$8,$T23,0) -> 3.4883333e+08 | DB23: =IF($Q23>=DB$8,$T23,0) -> 3.4883333e+08 | DC23: =IF($Q23>=DC$8,$T23,0) -> 3.4883333e+08 | DD23: =IF($Q23>=DD$8,$T23,0) -> 3.4883333e+08 | DE23: =IF($Q23>=DE$8,$T23,0) -> 3.4883333e+08 | DF23: =IF($Q23>=DF$8,$T23,0) -> 3.4883333e+08 | ... EB23: =IF($Q23>=EB$8,$T23,0) -> 0 | ED23: =IF($V23>=ED$8,$Y23,0) -> 325000000 | EE23: =IF($V23>=EE$8,$Y23,0) -> 325000000 | EF23: =IF($V23>=EF$8,$Y23,0) -> 325000000 | EG23: =IF($V23>=EG$8,$Y23,0) -> 325000000 | EH23: =IF($V23>=EH$8,$Y23,0) -> 325000000 | EI23: =IF($V23>=EI$8,$Y23,0) -> 325000000 | EJ23: =IF($V23>=EJ$8,$Y23,0) -> 325000000 | EK23: =IF($V23>=EK$8,$Y23,0) -> 325000000 | ... FG23: =IF($V23>=FG$8,$Y23,0) -> 0 | FI23: =IF($AA23>=FI$8,$AD23,0) -> 325000000 | FJ23: =IF($AA23>=FJ$8,$AD23,0) -> 325000000 | FK23: =IF($AA23>=FK$8,$AD23,0) -> 325000000 | FL23: =IF($AA23>=FL$8,$AD23,0) -> 325000000 | FM23: =IF($AA23>=FM$8,$AD23,0) -> 325000000 | FN23: =IF($AA23>=FN$8,$AD23,0) -> 325000000 | FO23: =IF($AA23>=FO$8,$AD23,0) -> 325000000 | FP23: =IF($AA23>=FP$8,$AD23,0) -> 325000000 | ... GL23: =IF($AA23>=GL$8,$AD23,0) -> 0 | GN23: =IF($AF23>=GN$8,$AI23,0) -> 325000000 | GO23: =IF($AF23>=GO$8,$AI23,0) -> 325000000 | GP23: =IF($AF23>=GP$8,$AI23,0) -> 325000000 | GQ23: =IF($AF23>=GQ$8,$AI23,0) -> 325000000 | GR23: =IF($AF23>=GR$8,$AI23,0) -> 325000000 | GS23: =IF($AF23>=GS$8,$AI23,0) -> 325000000 | GT23: =IF($AF23>=GT$8,$AI23,0) -> 325000000 | GU23: =IF($AF23>=GU$8,$AI23,0) -> 325000000 | ... HQ23: =IF($AF23>=HQ$8,$AI23,0) -> 0
B24: Auxiliary Equipment | C24: 1.2.09 | D24: Camera online check | E24: 1 | G24: 12 | H24: =(3125000000/$D$6)*1.04 -> 3250000000 | I24: =$E24*$H24 -> 3250000000 | J24: =I24/G24 -> 2.7083333e+08 | L24: 12 | M24: =IF(Currency="USD",ROUNDUP($E24*$H24*(1+O$6),-3),ROUNDUP($E24*$H24*(1+O$6)/EXR,-3)*EXR) -> 3484000000 | N24: =$E24*M24 -> 3484000000 | O24: =N24/L24 -> 2.9033333e+08 | Q24: 12 | R24: =IF(Currency="USD",ROUNDUP($E24*$H24*(1+T$6),-3),ROUNDUP($E24*$H24*(1+T$6)/EXR,-3)*EXR) -> 3484000000 | S24: =$E24*R24 -> 3484000000 | T24: =S24/Q24 -> 2.9033333e+08 | V24: 12 | W24: =H24 -> 3250000000 | X24: =$E24*W24 -> 3250000000 | Y24: =X24/V24 -> 2.7083333e+08 | AA24: 12 | AB24: =IF(Currency="USD",ROUNDUP($E24*$H24*(1+AD$6),-3),ROUNDUP($E24*$H24*(1+AD$6)/EXR,-3)*EXR) -> 3250000000 | AC24: =$E24*AB24 -> 3250000000 | AD24: =AC24/AA24 -> 2.7083333e+08 | AF24: 12 | AG24: =IF(Currency="USD",ROUNDUP($E24*$H24*(1+AI$6),-3),ROUNDUP($E24*$H24*(1+AI$6)/EXR,-3)*EXR) -> 3250000000 | AH24: =$E24*AG24 -> 3250000000 | AI24: =AH24/AF24 -> 2.7083333e+08 | AL24: A. Quân | AM24: Gía trị bán lại = giá trị ban đầu - khấu hao * sản lượng sx | AO24: =IF($G24>=AO$8,$J24,0) -> 2.7083333e+08 | AP24: =IF($G24>=AP$8,$J24,0) -> 2.7083333e+08 | AQ24: =IF($G24>=AQ$8,$J24,0) -> 2.7083333e+08 | AR24: =IF($G24>=AR$8,$J24,0) -> 2.7083333e+08 | AS24: =IF($G24>=AS$8,$J24,0) -> 2.7083333e+08 | AT24: =IF($G24>=AT$8,$J24,0) -> 2.7083333e+08 | AU24: =IF($G24>=AU$8,$J24,0) -> 2.7083333e+08 | AV24: =IF($G24>=AV$8,$J24,0) -> 2.7083333e+08 | ... BR24: =IF($G24>=BR$8,$J24,0) -> 0 | BT24: =IF($L24>=BT$8,$O24,0) -> 2.9033333e+08 | BU24: =IF($L24>=BU$8,$O24,0) -> 2.9033333e+08 | BV24: =IF($L24>=BV$8,$O24,0) -> 2.9033333e+08 | BW24: =IF($L24>=BW$8,$O24,0) -> 2.9033333e+08 | BX24: =IF($L24>=BX$8,$O24,0) -> 2.9033333e+08 | BY24: =IF($L24>=BY$8,$O24,0) -> 2.9033333e+08 | BZ24: =IF($L24>=BZ$8,$O24,0) -> 2.9033333e+08 | CA24: =IF($L24>=CA$8,$O24,0) -> 2.9033333e+08 | ... CW24: =IF($L24>=CW$8,$O24,0) -> 0 | CY24: =IF($Q24>=CY$8,$T24,0) -> 2.9033333e+08 | CZ24: =IF($Q24>=CZ$8,$T24,0) -> 2.9033333e+08 | DA24: =IF($Q24>=DA$8,$T24,0) -> 2.9033333e+08 | DB24: =IF($Q24>=DB$8,$T24,0) -> 2.9033333e+08 | DC24: =IF($Q24>=DC$8,$T24,0) -> 2.9033333e+08 | DD24: =IF($Q24>=DD$8,$T24,0) -> 2.9033333e+08 | DE24: =IF($Q24>=DE$8,$T24,0) -> 2.9033333e+08 | DF24: =IF($Q24>=DF$8,$T24,0) -> 2.9033333e+08 | ... EB24: =IF($Q24>=EB$8,$T24,0) -> 0 | ED24: =IF($V24>=ED$8,$Y24,0) -> 2.7083333e+08 | EE24: =IF($V24>=EE$8,$Y24,0) -> 2.7083333e+08 | EF24: =IF($V24>=EF$8,$Y24,0) -> 2.7083333e+08 | EG24: =IF($V24>=EG$8,$Y24,0) -> 2.7083333e+08 | EH24: =IF($V24>=EH$8,$Y24,0) -> 2.7083333e+08 | EI24: =IF($V24>=EI$8,$Y24,0) -> 2.7083333e+08 | EJ24: =IF($V24>=EJ$8,$Y24,0) -> 2.7083333e+08 | EK24: =IF($V24>=EK$8,$Y24,0) -> 2.7083333e+08 | ... FG24: =IF($V24>=FG$8,$Y24,0) -> 0 | FI24: =IF($AA24>=FI$8,$AD24,0) -> 2.7083333e+08 | FJ24: =IF($AA24>=FJ$8,$AD24,0) -> 2.7083333e+08 | FK24: =IF($AA24>=FK$8,$AD24,0) -> 2.7083333e+08 | FL24: =IF($AA24>=FL$8,$AD24,0) -> 2.7083333e+08 | FM24: =IF($AA24>=FM$8,$AD24,0) -> 2.7083333e+08 | FN24: =IF($AA24>=FN$8,$AD24,0) -> 2.7083333e+08 | FO24: =IF($AA24>=FO$8,$AD24,0) -> 2.7083333e+08 | FP24: =IF($AA24>=FP$8,$AD24,0) -> 2.7083333e+08 | ... GL24: =IF($AA24>=GL$8,$AD24,0) -> 0 | GN24: =IF($AF24>=GN$8,$AI24,0) -> 2.7083333e+08 | GO24: =IF($AF24>=GO$8,$AI24,0) -> 2.7083333e+08 | GP24: =IF($AF24>=GP$8,$AI24,0) -> 2.7083333e+08 | GQ24: =IF($AF24>=GQ$8,$AI24,0) -> 2.7083333e+08 | GR24: =IF($AF24>=GR$8,$AI24,0) -> 2.7083333e+08 | GS24: =IF($AF24>=GS$8,$AI24,0) -> 2.7083333e+08 | GT24: =IF($AF24>=GT$8,$AI24,0) -> 2.7083333e+08 | GU24: =IF($AF24>=GU$8,$AI24,0) -> 2.7083333e+08 | ... HQ24: =IF($AF24>=HQ$8,$AI24,0) -> 0
B25: Auxiliary Equipment | C25: 1.2.10 | D25: Chiller | E25: 1 | G25: 12 | H25: =(2500000000/$D$6)*1.04 -> 2600000000 | I25: =$E25*$H25 -> 2600000000 | J25: =I25/G25 -> 2.1666667e+08 | L25: 12 | M25: =IF(Currency="USD",ROUNDUP($E25*$H25*(1+O$6),-3),ROUNDUP($E25*$H25*(1+O$6)/EXR,-3)*EXR) -> 2782000000 | N25: =$E25*M25 -> 2782000000 | O25: =N25/L25 -> 2.3183333e+08 | Q25: 12 | R25: =IF(Currency="USD",ROUNDUP($E25*$H25*(1+T$6),-3),ROUNDUP($E25*$H25*(1+T$6)/EXR,-3)*EXR) -> 2782000000 | S25: =$E25*R25 -> 2782000000 | T25: =S25/Q25 -> 2.3183333e+08 | V25: 12 | W25: =H25 -> 2600000000 | X25: =$E25*W25 -> 2600000000 | Y25: =X25/V25 -> 2.1666667e+08 | AA25: 12 | AB25: =IF(Currency="USD",ROUNDUP($E25*$H25*(1+AD$6),-3),ROUNDUP($E25*$H25*(1+AD$6)/EXR,-3)*EXR) -> 2600000000 | AC25: =$E25*AB25 -> 2600000000 | AD25: =AC25/AA25 -> 2.1666667e+08 | AF25: 12 | AG25: =IF(Currency="USD",ROUNDUP($E25*$H25*(1+AI$6),-3),ROUNDUP($E25*$H25*(1+AI$6)/EXR,-3)*EXR) -> 2600000000 | AH25: =$E25*AG25 -> 2600000000 | AI25: =AH25/AF25 -> 2.1666667e+08 | AL25: A. Quân | AM25: Đàm phán | AO25: =IF($G25>=AO$8,$J25,0) -> 2.1666667e+08 | AP25: =IF($G25>=AP$8,$J25,0) -> 2.1666667e+08 | AQ25: =IF($G25>=AQ$8,$J25,0) -> 2.1666667e+08 | AR25: =IF($G25>=AR$8,$J25,0) -> 2.1666667e+08 | AS25: =IF($G25>=AS$8,$J25,0) -> 2.1666667e+08 | AT25: =IF($G25>=AT$8,$J25,0) -> 2.1666667e+08 | AU25: =IF($G25>=AU$8,$J25,0) -> 2.1666667e+08 | AV25: =IF($G25>=AV$8,$J25,0) -> 2.1666667e+08 | ... BR25: =IF($G25>=BR$8,$J25,0) -> 0 | BT25: =IF($L25>=BT$8,$O25,0) -> 2.3183333e+08 | BU25: =IF($L25>=BU$8,$O25,0) -> 2.3183333e+08 | BV25: =IF($L25>=BV$8,$O25,0) -> 2.3183333e+08 | BW25: =IF($L25>=BW$8,$O25,0) -> 2.3183333e+08 | BX25: =IF($L25>=BX$8,$O25,0) -> 2.3183333e+08 | BY25: =IF($L25>=BY$8,$O25,0) -> 2.3183333e+08 | BZ25: =IF($L25>=BZ$8,$O25,0) -> 2.3183333e+08 | CA25: =IF($L25>=CA$8,$O25,0) -> 2.3183333e+08 | ... CW25: =IF($L25>=CW$8,$O25,0) -> 0 | CY25: =IF($Q25>=CY$8,$T25,0) -> 2.3183333e+08 | CZ25: =IF($Q25>=CZ$8,$T25,0) -> 2.3183333e+08 | DA25: =IF($Q25>=DA$8,$T25,0) -> 2.3183333e+08 | DB25: =IF($Q25>=DB$8,$T25,0) -> 2.3183333e+08 | DC25: =IF($Q25>=DC$8,$T25,0) -> 2.3183333e+08 | DD25: =IF($Q25>=DD$8,$T25,0) -> 2.3183333e+08 | DE25: =IF($Q25>=DE$8,$T25,0) -> 2.3183333e+08 | DF25: =IF($Q25>=DF$8,$T25,0) -> 2.3183333e+08 | ... EB25: =IF($Q25>=EB$8,$T25,0) -> 0 | ED25: =IF($V25>=ED$8,$Y25,0) -> 2.1666667e+08 | EE25: =IF($V25>=EE$8,$Y25,0) -> 2.1666667e+08 | EF25: =IF($V25>=EF$8,$Y25,0) -> 2.1666667e+08 | EG25: =IF($V25>=EG$8,$Y25,0) -> 2.1666667e+08 | EH25: =IF($V25>=EH$8,$Y25,0) -> 2.1666667e+08 | EI25: =IF($V25>=EI$8,$Y25,0) -> 2.1666667e+08 | EJ25: =IF($V25>=EJ$8,$Y25,0) -> 2.1666667e+08 | EK25: =IF($V25>=EK$8,$Y25,0) -> 2.1666667e+08 | ... FG25: =IF($V25>=FG$8,$Y25,0) -> 0 | FI25: =IF($AA25>=FI$8,$AD25,0) -> 2.1666667e+08 | FJ25: =IF($AA25>=FJ$8,$AD25,0) -> 2.1666667e+08 | FK25: =IF($AA25>=FK$8,$AD25,0) -> 2.1666667e+08 | FL25: =IF($AA25>=FL$8,$AD25,0) -> 2.1666667e+08 | FM25: =IF($AA25>=FM$8,$AD25,0) -> 2.1666667e+08 | FN25: =IF($AA25>=FN$8,$AD25,0) -> 2.1666667e+08 | FO25: =IF($AA25>=FO$8,$AD25,0) -> 2.1666667e+08 | FP25: =IF($AA25>=FP$8,$AD25,0) -> 2.1666667e+08 | ... GL25: =IF($AA25>=GL$8,$AD25,0) -> 0 | GN25: =IF($AF25>=GN$8,$AI25,0) -> 2.1666667e+08 | GO25: =IF($AF25>=GO$8,$AI25,0) -> 2.1666667e+08 | GP25: =IF($AF25>=GP$8,$AI25,0) -> 2.1666667e+08 | GQ25: =IF($AF25>=GQ$8,$AI25,0) -> 2.1666667e+08 | GR25: =IF($AF25>=GR$8,$AI25,0) -> 2.1666667e+08 | GS25: =IF($AF25>=GS$8,$AI25,0) -> 2.1666667e+08 | GT25: =IF($AF25>=GT$8,$AI25,0) -> 2.1666667e+08 | GU25: =IF($AF25>=GU$8,$AI25,0) -> 2.1666667e+08 | ... HQ25: =IF($AF25>=HQ$8,$AI25,0) -> 0
B26: Auxiliary Equipment | C26: 1.2.11 | D26: Trạm điện | E26: 1 | G26: 12 | H26: =(2500000000/$D$6)*1.04 -> 2600000000 | I26: =$E26*$H26 -> 2600000000 | J26: =I26/G26 -> 2.1666667e+08 | L26: 12 | M26: =IF(Currency="USD",ROUNDUP($E26*$H26*(1+O$6),-3),ROUNDUP($E26*$H26*(1+O$6)/EXR,-3)*EXR) -> 2782000000 | N26: =$E26*M26 -> 2782000000 | O26: =N26/L26 -> 2.3183333e+08 | Q26: 12 | R26: =IF(Currency="USD",ROUNDUP($E26*$H26*(1+T$6),-3),ROUNDUP($E26*$H26*(1+T$6)/EXR,-3)*EXR) -> 2782000000 | S26: =$E26*R26 -> 2782000000 | T26: =S26/Q26 -> 2.3183333e+08 | V26: 12 | W26: =H26 -> 2600000000 | X26: =$E26*W26 -> 2600000000 | Y26: =X26/V26 -> 2.1666667e+08 | AA26: 12 | AB26: =IF(Currency="USD",ROUNDUP($E26*$H26*(1+AD$6),-3),ROUNDUP($E26*$H26*(1+AD$6)/EXR,-3)*EXR) -> 2600000000 | AC26: =$E26*AB26 -> 2600000000 | AD26: =AC26/AA26 -> 2.1666667e+08 | AF26: 12 | AG26: =IF(Currency="USD",ROUNDUP($E26*$H26*(1+AI$6),-3),ROUNDUP($E26*$H26*(1+AI$6)/EXR,-3)*EXR) -> 2600000000 | AH26: =$E26*AG26 -> 2600000000 | AI26: =AH26/AF26 -> 2.1666667e+08 | AL26: A. Quân | AM26: Đàm phán | AO26: =IF($G26>=AO$8,$J26,0) -> 2.1666667e+08 | AP26: =IF($G26>=AP$8,$J26,0) -> 2.1666667e+08 | AQ26: =IF($G26>=AQ$8,$J26,0) -> 2.1666667e+08 | AR26: =IF($G26>=AR$8,$J26,0) -> 2.1666667e+08 | AS26: =IF($G26>=AS$8,$J26,0) -> 2.1666667e+08 | AT26: =IF($G26>=AT$8,$J26,0) -> 2.1666667e+08 | AU26: =IF($G26>=AU$8,$J26,0) -> 2.1666667e+08 | AV26: =IF($G26>=AV$8,$J26,0) -> 2.1666667e+08 | ... BR26: =IF($G26>=BR$8,$J26,0) -> 0 | BT26: =IF($L26>=BT$8,$O26,0) -> 2.3183333e+08 | BU26: =IF($L26>=BU$8,$O26,0) -> 2.3183333e+08 | BV26: =IF($L26>=BV$8,$O26,0) -> 2.3183333e+08 | BW26: =IF($L26>=BW$8,$O26,0) -> 2.3183333e+08 | BX26: =IF($L26>=BX$8,$O26,0) -> 2.3183333e+08 | BY26: =IF($L26>=BY$8,$O26,0) -> 2.3183333e+08 | BZ26: =IF($L26>=BZ$8,$O26,0) -> 2.3183333e+08 | CA26: =IF($L26>=CA$8,$O26,0) -> 2.3183333e+08 | ... CW26: =IF($L26>=CW$8,$O26,0) -> 0 | CY26: =IF($Q26>=CY$8,$T26,0) -> 2.3183333e+08 | CZ26: =IF($Q26>=CZ$8,$T26,0) -> 2.3183333e+08 | DA26: =IF($Q26>=DA$8,$T26,0) -> 2.3183333e+08 | DB26: =IF($Q26>=DB$8,$T26,0) -> 2.3183333e+08 | DC26: =IF($Q26>=DC$8,$T26,0) -> 2.3183333e+08 | DD26: =IF($Q26>=DD$8,$T26,0) -> 2.3183333e+08 | DE26: =IF($Q26>=DE$8,$T26,0) -> 2.3183333e+08 | DF26: =IF($Q26>=DF$8,$T26,0) -> 2.3183333e+08 | ... EB26: =IF($Q26>=EB$8,$T26,0) -> 0 | ED26: =IF($V26>=ED$8,$Y26,0) -> 2.1666667e+08 | EE26: =IF($V26>=EE$8,$Y26,0) -> 2.1666667e+08 | EF26: =IF($V26>=EF$8,$Y26,0) -> 2.1666667e+08 | EG26: =IF($V26>=EG$8,$Y26,0) -> 2.1666667e+08 | EH26: =IF($V26>=EH$8,$Y26,0) -> 2.1666667e+08 | EI26: =IF($V26>=EI$8,$Y26,0) -> 2.1666667e+08 | EJ26: =IF($V26>=EJ$8,$Y26,0) -> 2.1666667e+08 | EK26: =IF($V26>=EK$8,$Y26,0) -> 2.1666667e+08 | ... FG26: =IF($V26>=FG$8,$Y26,0) -> 0 | FI26: =IF($AA26>=FI$8,$AD26,0) -> 2.1666667e+08 | FJ26: =IF($AA26>=FJ$8,$AD26,0) -> 2.1666667e+08 | FK26: =IF($AA26>=FK$8,$AD26,0) -> 2.1666667e+08 | FL26: =IF($AA26>=FL$8,$AD26,0) -> 2.1666667e+08 | FM26: =IF($AA26>=FM$8,$AD26,0) -> 2.1666667e+08 | FN26: =IF($AA26>=FN$8,$AD26,0) -> 2.1666667e+08 | FO26: =IF($AA26>=FO$8,$AD26,0) -> 2.1666667e+08 | FP26: =IF($AA26>=FP$8,$AD26,0) -> 2.1666667e+08 | ... GL26: =IF($AA26>=GL$8,$AD26,0) -> 0 | GN26: =IF($AF26>=GN$8,$AI26,0) -> 2.1666667e+08 | GO26: =IF($AF26>=GO$8,$AI26,0) -> 2.1666667e+08 | GP26: =IF($AF26>=GP$8,$AI26,0) -> 2.1666667e+08 | GQ26: =IF($AF26>=GQ$8,$AI26,0) -> 2.1666667e+08 | GR26: =IF($AF26>=GR$8,$AI26,0) -> 2.1666667e+08 | GS26: =IF($AF26>=GS$8,$AI26,0) -> 2.1666667e+08 | GT26: =IF($AF26>=GT$8,$AI26,0) -> 2.1666667e+08 | GU26: =IF($AF26>=GU$8,$AI26,0) -> 2.1666667e+08 | ... HQ26: =IF($AF26>=HQ$8,$AI26,0) -> 0
B27: Auxiliary Equipment | C27: 1.2.12 | D27: Overhead crane | E27: 1 | G27: 12 | H27: =(2500000000/$D$6)*1.04 -> 2600000000 | I27: =$E27*$H27 -> 2600000000 | J27: =I27/G27 -> 2.1666667e+08 | L27: 12 | M27: =IF(Currency="USD",ROUNDUP($E27*$H27*(1+O$6),-3),ROUNDUP($E27*$H27*(1+O$6)/EXR,-3)*EXR) -> 2782000000 | N27: =$E27*M27 -> 2782000000 | O27: =N27/L27 -> 2.3183333e+08 | Q27: 12 | R27: =IF(Currency="USD",ROUNDUP($E27*$H27*(1+T$6),-3),ROUNDUP($E27*$H27*(1+T$6)/EXR,-3)*EXR) -> 2782000000 | S27: =$E27*R27 -> 2782000000 | T27: =S27/Q27 -> 2.3183333e+08 | V27: 12 | W27: =H27 -> 2600000000 | X27: =$E27*W27 -> 2600000000 | Y27: =X27/V27 -> 2.1666667e+08 | AA27: 12 | AB27: =IF(Currency="USD",ROUNDUP($E27*$H27*(1+AD$6),-3),ROUNDUP($E27*$H27*(1+AD$6)/EXR,-3)*EXR) -> 2600000000 | AC27: =$E27*AB27 -> 2600000000 | AD27: =AC27/AA27 -> 2.1666667e+08 | AF27: 12 | AG27: =IF(Currency="USD",ROUNDUP($E27*$H27*(1+AI$6),-3),ROUNDUP($E27*$H27*(1+AI$6)/EXR,-3)*EXR) -> 2600000000 | AH27: =$E27*AG27 -> 2600000000 | AI27: =AH27/AF27 -> 2.1666667e+08 | AL27: A. Quân | AM27: Đàm phán | AO27: =IF($G27>=AO$8,$J27,0) -> 2.1666667e+08 | AP27: =IF($G27>=AP$8,$J27,0) -> 2.1666667e+08 | AQ27: =IF($G27>=AQ$8,$J27,0) -> 2.1666667e+08 | AR27: =IF($G27>=AR$8,$J27,0) -> 2.1666667e+08 | AS27: =IF($G27>=AS$8,$J27,0) -> 2.1666667e+08 | AT27: =IF($G27>=AT$8,$J27,0) -> 2.1666667e+08 | AU27: =IF($G27>=AU$8,$J27,0) -> 2.1666667e+08 | AV27: =IF($G27>=AV$8,$J27,0) -> 2.1666667e+08 | ... BR27: =IF($G27>=BR$8,$J27,0) -> 0 | BT27: =IF($L27>=BT$8,$O27,0) -> 2.3183333e+08 | BU27: =IF($L27>=BU$8,$O27,0) -> 2.3183333e+08 | BV27: =IF($L27>=BV$8,$O27,0) -> 2.3183333e+08 | BW27: =IF($L27>=BW$8,$O27,0) -> 2.3183333e+08 | BX27: =IF($L27>=BX$8,$O27,0) -> 2.3183333e+08 | BY27: =IF($L27>=BY$8,$O27,0) -> 2.3183333e+08 | BZ27: =IF($L27>=BZ$8,$O27,0) -> 2.3183333e+08 | CA27: =IF($L27>=CA$8,$O27,0) -> 2.3183333e+08 | ... CW27: =IF($L27>=CW$8,$O27,0) -> 0 | CY27: =IF($Q27>=CY$8,$T27,0) -> 2.3183333e+08 | CZ27: =IF($Q27>=CZ$8,$T27,0) -> 2.3183333e+08 | DA27: =IF($Q27>=DA$8,$T27,0) -> 2.3183333e+08 | DB27: =IF($Q27>=DB$8,$T27,0) -> 2.3183333e+08 | DC27: =IF($Q27>=DC$8,$T27,0) -> 2.3183333e+08 | DD27: =IF($Q27>=DD$8,$T27,0) -> 2.3183333e+08 | DE27: =IF($Q27>=DE$8,$T27,0) -> 2.3183333e+08 | DF27: =IF($Q27>=DF$8,$T27,0) -> 2.3183333e+08 | ... EB27: =IF($Q27>=EB$8,$T27,0) -> 0 | ED27: =IF($V27>=ED$8,$Y27,0) -> 2.1666667e+08 | EE27: =IF($V27>=EE$8,$Y27,0) -> 2.1666667e+08 | EF27: =IF($V27>=EF$8,$Y27,0) -> 2.1666667e+08 | EG27: =IF($V27>=EG$8,$Y27,0) -> 2.1666667e+08 | EH27: =IF($V27>=EH$8,$Y27,0) -> 2.1666667e+08 | EI27: =IF($V27>=EI$8,$Y27,0) -> 2.1666667e+08 | EJ27: =IF($V27>=EJ$8,$Y27,0) -> 2.1666667e+08 | EK27: =IF($V27>=EK$8,$Y27,0) -> 2.1666667e+08 | ... FG27: =IF($V27>=FG$8,$Y27,0) -> 0 | FI27: =IF($AA27>=FI$8,$AD27,0) -> 2.1666667e+08 | FJ27: =IF($AA27>=FJ$8,$AD27,0) -> 2.1666667e+08 | FK27: =IF($AA27>=FK$8,$AD27,0) -> 2.1666667e+08 | FL27: =IF($AA27>=FL$8,$AD27,0) -> 2.1666667e+08 | FM27: =IF($AA27>=FM$8,$AD27,0) -> 2.1666667e+08 | FN27: =IF($AA27>=FN$8,$AD27,0) -> 2.1666667e+08 | FO27: =IF($AA27>=FO$8,$AD27,0) -> 2.1666667e+08 | FP27: =IF($AA27>=FP$8,$AD27,0) -> 2.1666667e+08 | ... GL27: =IF($AA27>=GL$8,$AD27,0) -> 0 | GN27: =IF($AF27>=GN$8,$AI27,0) -> 2.1666667e+08 | GO27: =IF($AF27>=GO$8,$AI27,0) -> 2.1666667e+08 | GP27: =IF($AF27>=GP$8,$AI27,0) -> 2.1666667e+08 | GQ27: =IF($AF27>=GQ$8,$AI27,0) -> 2.1666667e+08 | GR27: =IF($AF27>=GR$8,$AI27,0) -> 2.1666667e+08 | GS27: =IF($AF27>=GS$8,$AI27,0) -> 2.1666667e+08 | GT27: =IF($AF27>=GT$8,$AI27,0) -> 2.1666667e+08 | GU27: =IF($AF27>=GU$8,$AI27,0) -> 2.1666667e+08 | ... HQ27: =IF($AF27>=HQ$8,$AI27,0) -> 0
B28: Auxiliary Equipment | C28: 1.2.13 | D28: Hệ thống điện dự phòng | E28: 1 | G28: 12 | H28: =(2000000000/$D$6)*1.04 -> 2080000000 | I28: =$E28*$H28 -> 2080000000 | J28: =I28/G28 -> 1.7333333e+08 | L28: 12 | M28: =IF(Currency="USD",ROUNDUP($E28*$H28*(1+O$6),-3),ROUNDUP($E28*$H28*(1+O$6)/EXR,-3)*EXR) -> 2236000000 | N28: =$E28*M28 -> 2236000000 | O28: =N28/L28 -> 1.8633333e+08 | Q28: 12 | R28: =IF(Currency="USD",ROUNDUP($E28*$H28*(1+T$6),-3),ROUNDUP($E28*$H28*(1+T$6)/EXR,-3)*EXR) -> 2236000000 | S28: =$E28*R28 -> 2236000000 | T28: =S28/Q28 -> 1.8633333e+08 | V28: 12 | W28: =H28 -> 2080000000 | X28: =$E28*W28 -> 2080000000 | Y28: =X28/V28 -> 1.7333333e+08 | AA28: 12 | AB28: =IF(Currency="USD",ROUNDUP($E28*$H28*(1+AD$6),-3),ROUNDUP($E28*$H28*(1+AD$6)/EXR,-3)*EXR) -> 2080000000 | AC28: =$E28*AB28 -> 2080000000 | AD28: =AC28/AA28 -> 1.7333333e+08 | AF28: 12 | AG28: =IF(Currency="USD",ROUNDUP($E28*$H28*(1+AI$6),-3),ROUNDUP($E28*$H28*(1+AI$6)/EXR,-3)*EXR) -> 2080000000 | AH28: =$E28*AG28 -> 2080000000 | AI28: =AH28/AF28 -> 1.7333333e+08 | AL28: A. Quân | AM28: Đàm phán | AO28: =IF($G28>=AO$8,$J28,0) -> 1.7333333e+08 | AP28: =IF($G28>=AP$8,$J28,0) -> 1.7333333e+08 | AQ28: =IF($G28>=AQ$8,$J28,0) -> 1.7333333e+08 | AR28: =IF($G28>=AR$8,$J28,0) -> 1.7333333e+08 | AS28: =IF($G28>=AS$8,$J28,0) -> 1.7333333e+08 | AT28: =IF($G28>=AT$8,$J28,0) -> 1.7333333e+08 | AU28: =IF($G28>=AU$8,$J28,0) -> 1.7333333e+08 | AV28: =IF($G28>=AV$8,$J28,0) -> 1.7333333e+08 | ... BR28: =IF($G28>=BR$8,$J28,0) -> 0 | BT28: =IF($L28>=BT$8,$O28,0) -> 1.8633333e+08 | BU28: =IF($L28>=BU$8,$O28,0) -> 1.8633333e+08 | BV28: =IF($L28>=BV$8,$O28,0) -> 1.8633333e+08 | BW28: =IF($L28>=BW$8,$O28,0) -> 1.8633333e+08 | BX28: =IF($L28>=BX$8,$O28,0) -> 1.8633333e+08 | BY28: =IF($L28>=BY$8,$O28,0) -> 1.8633333e+08 | BZ28: =IF($L28>=BZ$8,$O28,0) -> 1.8633333e+08 | CA28: =IF($L28>=CA$8,$O28,0) -> 1.8633333e+08 | ... CW28: =IF($L28>=CW$8,$O28,0) -> 0 | CY28: =IF($Q28>=CY$8,$T28,0) -> 1.8633333e+08 | CZ28: =IF($Q28>=CZ$8,$T28,0) -> 1.8633333e+08 | DA28: =IF($Q28>=DA$8,$T28,0) -> 1.8633333e+08 | DB28: =IF($Q28>=DB$8,$T28,0) -> 1.8633333e+08 | DC28: =IF($Q28>=DC$8,$T28,0) -> 1.8633333e+08 | DD28: =IF($Q28>=DD$8,$T28,0) -> 1.8633333e+08 | DE28: =IF($Q28>=DE$8,$T28,0) -> 1.8633333e+08 | DF28: =IF($Q28>=DF$8,$T28,0) -> 1.8633333e+08 | ... EB28: =IF($Q28>=EB$8,$T28,0) -> 0 | ED28: =IF($V28>=ED$8,$Y28,0) -> 1.7333333e+08 | EE28: =IF($V28>=EE$8,$Y28,0) -> 1.7333333e+08 | EF28: =IF($V28>=EF$8,$Y28,0) -> 1.7333333e+08 | EG28: =IF($V28>=EG$8,$Y28,0) -> 1.7333333e+08 | EH28: =IF($V28>=EH$8,$Y28,0) -> 1.7333333e+08 | EI28: =IF($V28>=EI$8,$Y28,0) -> 1.7333333e+08 | EJ28: =IF($V28>=EJ$8,$Y28,0) -> 1.7333333e+08 | EK28: =IF($V28>=EK$8,$Y28,0) -> 1.7333333e+08 | ... FG28: =IF($V28>=FG$8,$Y28,0) -> 0 | FI28: =IF($AA28>=FI$8,$AD28,0) -> 1.7333333e+08 | FJ28: =IF($AA28>=FJ$8,$AD28,0) -> 1.7333333e+08 | FK28: =IF($AA28>=FK$8,$AD28,0) -> 1.7333333e+08 | FL28: =IF($AA28>=FL$8,$AD28,0) -> 1.7333333e+08 | FM28: =IF($AA28>=FM$8,$AD28,0) -> 1.7333333e+08 | FN28: =IF($AA28>=FN$8,$AD28,0) -> 1.7333333e+08 | FO28: =IF($AA28>=FO$8,$AD28,0) -> 1.7333333e+08 | FP28: =IF($AA28>=FP$8,$AD28,0) -> 1.7333333e+08 | ... GL28: =IF($AA28>=GL$8,$AD28,0) -> 0 | GN28: =IF($AF28>=GN$8,$AI28,0) -> 1.7333333e+08 | GO28: =IF($AF28>=GO$8,$AI28,0) -> 1.7333333e+08 | GP28: =IF($AF28>=GP$8,$AI28,0) -> 1.7333333e+08 | GQ28: =IF($AF28>=GQ$8,$AI28,0) -> 1.7333333e+08 | GR28: =IF($AF28>=GR$8,$AI28,0) -> 1.7333333e+08 | GS28: =IF($AF28>=GS$8,$AI28,0) -> 1.7333333e+08 | GT28: =IF($AF28>=GT$8,$AI28,0) -> 1.7333333e+08 | GU28: =IF($AF28>=GU$8,$AI28,0) -> 1.7333333e+08 | ... HQ28: =IF($AF28>=HQ$8,$AI28,0) -> 0
B29: Auxiliary Equipment | C29: 1.2.14 | D29: Hệ thống IT | E29: 1 | G29: 12 | H29: =(2000000000/$D$6)*1.04 -> 2080000000 | I29: =$E29*$H29 -> 2080000000 | J29: =I29/G29 -> 1.7333333e+08 | L29: 12 | M29: =IF(Currency="USD",ROUNDUP($E29*$H29*(1+O$6),-3),ROUNDUP($E29*$H29*(1+O$6)/EXR,-3)*EXR) -> 2236000000 | N29: =$E29*M29 -> 2236000000 | O29: =N29/L29 -> 1.8633333e+08 | Q29: 12 | R29: =IF(Currency="USD",ROUNDUP($E29*$H29*(1+T$6),-3),ROUNDUP($E29*$H29*(1+T$6)/EXR,-3)*EXR) -> 2236000000 | S29: =$E29*R29 -> 2236000000 | T29: =S29/Q29 -> 1.8633333e+08 | V29: 12 | W29: =H29 -> 2080000000 | X29: =$E29*W29 -> 2080000000 | Y29: =X29/V29 -> 1.7333333e+08 | AA29: 12 | AB29: =IF(Currency="USD",ROUNDUP($E29*$H29*(1+AD$6),-3),ROUNDUP($E29*$H29*(1+AD$6)/EXR,-3)*EXR) -> 2080000000 | AC29: =$E29*AB29 -> 2080000000 | AD29: =AC29/AA29 -> 1.7333333e+08 | AF29: 12 | AG29: =IF(Currency="USD",ROUNDUP($E29*$H29*(1+AI$6),-3),ROUNDUP($E29*$H29*(1+AI$6)/EXR,-3)*EXR) -> 2080000000 | AH29: =$E29*AG29 -> 2080000000 | AI29: =AH29/AF29 -> 1.7333333e+08 | AL29: A. Quân | AM29: Đàm phán | AO29: =IF($G29>=AO$8,$J29,0) -> 1.7333333e+08 | AP29: =IF($G29>=AP$8,$J29,0) -> 1.7333333e+08 | AQ29: =IF($G29>=AQ$8,$J29,0) -> 1.7333333e+08 | AR29: =IF($G29>=AR$8,$J29,0) -> 1.7333333e+08 | AS29: =IF($G29>=AS$8,$J29,0) -> 1.7333333e+08 | AT29: =IF($G29>=AT$8,$J29,0) -> 1.7333333e+08 | AU29: =IF($G29>=AU$8,$J29,0) -> 1.7333333e+08 | AV29: =IF($G29>=AV$8,$J29,0) -> 1.7333333e+08 | ... BR29: =IF($G29>=BR$8,$J29,0) -> 0 | BT29: =IF($L29>=BT$8,$O29,0) -> 1.8633333e+08 | BU29: =IF($L29>=BU$8,$O29,0) -> 1.8633333e+08 | BV29: =IF($L29>=BV$8,$O29,0) -> 1.8633333e+08 | BW29: =IF($L29>=BW$8,$O29,0) -> 1.8633333e+08 | BX29: =IF($L29>=BX$8,$O29,0) -> 1.8633333e+08 | BY29: =IF($L29>=BY$8,$O29,0) -> 1.8633333e+08 | BZ29: =IF($L29>=BZ$8,$O29,0) -> 1.8633333e+08 | CA29: =IF($L29>=CA$8,$O29,0) -> 1.8633333e+08 | ... CW29: =IF($L29>=CW$8,$O29,0) -> 0 | CY29: =IF($Q29>=CY$8,$T29,0) -> 1.8633333e+08 | CZ29: =IF($Q29>=CZ$8,$T29,0) -> 1.8633333e+08 | DA29: =IF($Q29>=DA$8,$T29,0) -> 1.8633333e+08 | DB29: =IF($Q29>=DB$8,$T29,0) -> 1.8633333e+08 | DC29: =IF($Q29>=DC$8,$T29,0) -> 1.8633333e+08 | DD29: =IF($Q29>=DD$8,$T29,0) -> 1.8633333e+08 | DE29: =IF($Q29>=DE$8,$T29,0) -> 1.8633333e+08 | DF29: =IF($Q29>=DF$8,$T29,0) -> 1.8633333e+08 | ... EB29: =IF($Q29>=EB$8,$T29,0) -> 0 | ED29: =IF($V29>=ED$8,$Y29,0) -> 1.7333333e+08 | EE29: =IF($V29>=EE$8,$Y29,0) -> 1.7333333e+08 | EF29: =IF($V29>=EF$8,$Y29,0) -> 1.7333333e+08 | EG29: =IF($V29>=EG$8,$Y29,0) -> 1.7333333e+08 | EH29: =IF($V29>=EH$8,$Y29,0) -> 1.7333333e+08 | EI29: =IF($V29>=EI$8,$Y29,0) -> 1.7333333e+08 | EJ29: =IF($V29>=EJ$8,$Y29,0) -> 1.7333333e+08 | EK29: =IF($V29>=EK$8,$Y29,0) -> 1.7333333e+08 | ... FG29: =IF($V29>=FG$8,$Y29,0) -> 0 | FI29: =IF($AA29>=FI$8,$AD29,0) -> 1.7333333e+08 | FJ29: =IF($AA29>=FJ$8,$AD29,0) -> 1.7333333e+08 | FK29: =IF($AA29>=FK$8,$AD29,0) -> 1.7333333e+08 | FL29: =IF($AA29>=FL$8,$AD29,0) -> 1.7333333e+08 | FM29: =IF($AA29>=FM$8,$AD29,0) -> 1.7333333e+08 | FN29: =IF($AA29>=FN$8,$AD29,0) -> 1.7333333e+08 | FO29: =IF($AA29>=FO$8,$AD29,0) -> 1.7333333e+08 | FP29: =IF($AA29>=FP$8,$AD29,0) -> 1.7333333e+08 | ... GL29: =IF($AA29>=GL$8,$AD29,0) -> 0 | GN29: =IF($AF29>=GN$8,$AI29,0) -> 1.7333333e+08 | GO29: =IF($AF29>=GO$8,$AI29,0) -> 1.7333333e+08 | GP29: =IF($AF29>=GP$8,$AI29,0) -> 1.7333333e+08 | GQ29: =IF($AF29>=GQ$8,$AI29,0) -> 1.7333333e+08 | GR29: =IF($AF29>=GR$8,$AI29,0) -> 1.7333333e+08 | GS29: =IF($AF29>=GS$8,$AI29,0) -> 1.7333333e+08 | GT29: =IF($AF29>=GT$8,$AI29,0) -> 1.7333333e+08 | GU29: =IF($AF29>=GU$8,$AI29,0) -> 1.7333333e+08 | ... HQ29: =IF($AF29>=HQ$8,$AI29,0) -> 0
B30: Auxiliary Equipment | C30: 1.2.15 | D30: Lock unloading preform | E30: 1 | G30: 12 | H30: =(1300000000/$D$6)*1.04 -> 1352000000 | I30: =$E30*$H30 -> 1352000000 | J30: =I30/G30 -> 1.1266667e+08 | L30: 12 | M30: =IF(Currency="USD",ROUNDUP($E30*$H30*(1+O$6),-3),ROUNDUP($E30*$H30*(1+O$6)/EXR,-3)*EXR) -> 1456000000 | N30: =$E30*M30 -> 1456000000 | O30: =N30/L30 -> 1.2133333e+08 | Q30: 12 | R30: =IF(Currency="USD",ROUNDUP($E30*$H30*(1+T$6),-3),ROUNDUP($E30*$H30*(1+T$6)/EXR,-3)*EXR) -> 1456000000 | S30: =$E30*R30 -> 1456000000 | T30: =S30/Q30 -> 1.2133333e+08 | V30: 12 | W30: =H30 -> 1352000000 | X30: =$E30*W30 -> 1352000000 | Y30: =X30/V30 -> 1.1266667e+08 | AA30: 12 | AB30: =IF(Currency="USD",ROUNDUP($E30*$H30*(1+AD$6),-3),ROUNDUP($E30*$H30*(1+AD$6)/EXR,-3)*EXR) -> 1352000000 | AC30: =$E30*AB30 -> 1352000000 | AD30: =AC30/AA30 -> 1.1266667e+08 | AF30: 12 | AG30: =IF(Currency="USD",ROUNDUP($E30*$H30*(1+AI$6),-3),ROUNDUP($E30*$H30*(1+AI$6)/EXR,-3)*EXR) -> 1352000000 | AH30: =$E30*AG30 -> 1352000000 | AI30: =AH30/AF30 -> 1.1266667e+08 | AL30: A. Quân | AM30: Gía trị bán lại = giá trị ban đầu - khấu hao * sản lượng sx | AO30: =IF($G30>=AO$8,$J30,0) -> 1.1266667e+08 | AP30: =IF($G30>=AP$8,$J30,0) -> 1.1266667e+08 | AQ30: =IF($G30>=AQ$8,$J30,0) -> 1.1266667e+08 | AR30: =IF($G30>=AR$8,$J30,0) -> 1.1266667e+08 | AS30: =IF($G30>=AS$8,$J30,0) -> 1.1266667e+08 | AT30: =IF($G30>=AT$8,$J30,0) -> 1.1266667e+08 | AU30: =IF($G30>=AU$8,$J30,0) -> 1.1266667e+08 | AV30: =IF($G30>=AV$8,$J30,0) -> 1.1266667e+08 | ... BR30: =IF($G30>=BR$8,$J30,0) -> 0 | BT30: =IF($L30>=BT$8,$O30,0) -> 1.2133333e+08 | BU30: =IF($L30>=BU$8,$O30,0) -> 1.2133333e+08 | BV30: =IF($L30>=BV$8,$O30,0) -> 1.2133333e+08 | BW30: =IF($L30>=BW$8,$O30,0) -> 1.2133333e+08 | BX30: =IF($L30>=BX$8,$O30,0) -> 1.2133333e+08 | BY30: =IF($L30>=BY$8,$O30,0) -> 1.2133333e+08 | BZ30: =IF($L30>=BZ$8,$O30,0) -> 1.2133333e+08 | CA30: =IF($L30>=CA$8,$O30,0) -> 1.2133333e+08 | ... CW30: =IF($L30>=CW$8,$O30,0) -> 0 | CY30: =IF($Q30>=CY$8,$T30,0) -> 1.2133333e+08 | CZ30: =IF($Q30>=CZ$8,$T30,0) -> 1.2133333e+08 | DA30: =IF($Q30>=DA$8,$T30,0) -> 1.2133333e+08 | DB30: =IF($Q30>=DB$8,$T30,0) -> 1.2133333e+08 | DC30: =IF($Q30>=DC$8,$T30,0) -> 1.2133333e+08 | DD30: =IF($Q30>=DD$8,$T30,0) -> 1.2133333e+08 | DE30: =IF($Q30>=DE$8,$T30,0) -> 1.2133333e+08 | DF30: =IF($Q30>=DF$8,$T30,0) -> 1.2133333e+08 | ... EB30: =IF($Q30>=EB$8,$T30,0) -> 0 | ED30: =IF($V30>=ED$8,$Y30,0) -> 1.1266667e+08 | EE30: =IF($V30>=EE$8,$Y30,0) -> 1.1266667e+08 | EF30: =IF($V30>=EF$8,$Y30,0) -> 1.1266667e+08 | EG30: =IF($V30>=EG$8,$Y30,0) -> 1.1266667e+08 | EH30: =IF($V30>=EH$8,$Y30,0) -> 1.1266667e+08 | EI30: =IF($V30>=EI$8,$Y30,0) -> 1.1266667e+08 | EJ30: =IF($V30>=EJ$8,$Y30,0) -> 1.1266667e+08 | EK30: =IF($V30>=EK$8,$Y30,0) -> 1.1266667e+08 | ... FG30: =IF($V30>=FG$8,$Y30,0) -> 0 | FI30: =IF($AA30>=FI$8,$AD30,0) -> 1.1266667e+08 | FJ30: =IF($AA30>=FJ$8,$AD30,0) -> 1.1266667e+08 | FK30: =IF($AA30>=FK$8,$AD30,0) -> 1.1266667e+08 | FL30: =IF($AA30>=FL$8,$AD30,0) -> 1.1266667e+08 | FM30: =IF($AA30>=FM$8,$AD30,0) -> 1.1266667e+08 | FN30: =IF($AA30>=FN$8,$AD30,0) -> 1.1266667e+08 | FO30: =IF($AA30>=FO$8,$AD30,0) -> 1.1266667e+08 | FP30: =IF($AA30>=FP$8,$AD30,0) -> 1.1266667e+08 | ... GL30: =IF($AA30>=GL$8,$AD30,0) -> 0 | GN30: =IF($AF30>=GN$8,$AI30,0) -> 1.1266667e+08 | GO30: =IF($AF30>=GO$8,$AI30,0) -> 1.1266667e+08 | GP30: =IF($AF30>=GP$8,$AI30,0) -> 1.1266667e+08 | GQ30: =IF($AF30>=GQ$8,$AI30,0) -> 1.1266667e+08 | GR30: =IF($AF30>=GR$8,$AI30,0) -> 1.1266667e+08 | GS30: =IF($AF30>=GS$8,$AI30,0) -> 1.1266667e+08 | GT30: =IF($AF30>=GT$8,$AI30,0) -> 1.1266667e+08 | GU30: =IF($AF30>=GU$8,$AI30,0) -> 1.1266667e+08 | ... HQ30: =IF($AF30>=HQ$8,$AI30,0) -> 0
B31: Auxiliary Equipment | C31: 1.2.16 | D31: Máy nén khí | E31: 1 | G31: 12 | H31: =(1200000000/$D$6)*1.04 -> 1248000000 | I31: =$E31*$H31 -> 1248000000 | J31: =I31/G31 -> 104000000 | L31: 12 | M31: =IF(Currency="USD",ROUNDUP($E31*$H31*(1+O$6),-3),ROUNDUP($E31*$H31*(1+O$6)/EXR,-3)*EXR) -> 1352000000 | N31: =$E31*M31 -> 1352000000 | O31: =N31/L31 -> 1.1266667e+08 | Q31: 12 | R31: =IF(Currency="USD",ROUNDUP($E31*$H31*(1+T$6),-3),ROUNDUP($E31*$H31*(1+T$6)/EXR,-3)*EXR) -> 1352000000 | S31: =$E31*R31 -> 1352000000 | T31: =S31/Q31 -> 1.1266667e+08 | V31: 12 | W31: =H31 -> 1248000000 | X31: =$E31*W31 -> 1248000000 | Y31: =X31/V31 -> 104000000 | AA31: 12 | AB31: =IF(Currency="USD",ROUNDUP($E31*$H31*(1+AD$6),-3),ROUNDUP($E31*$H31*(1+AD$6)/EXR,-3)*EXR) -> 1248000000 | AC31: =$E31*AB31 -> 1248000000 | AD31: =AC31/AA31 -> 104000000 | AF31: 12 | AG31: =IF(Currency="USD",ROUNDUP($E31*$H31*(1+AI$6),-3),ROUNDUP($E31*$H31*(1+AI$6)/EXR,-3)*EXR) -> 1248000000 | AH31: =$E31*AG31 -> 1248000000 | AI31: =AH31/AF31 -> 104000000 | AL31: A. Quân | AM31: Đàm phán | AO31: =IF($G31>=AO$8,$J31,0) -> 104000000 | AP31: =IF($G31>=AP$8,$J31,0) -> 104000000 | AQ31: =IF($G31>=AQ$8,$J31,0) -> 104000000 | AR31: =IF($G31>=AR$8,$J31,0) -> 104000000 | AS31: =IF($G31>=AS$8,$J31,0) -> 104000000 | AT31: =IF($G31>=AT$8,$J31,0) -> 104000000 | AU31: =IF($G31>=AU$8,$J31,0) -> 104000000 | AV31: =IF($G31>=AV$8,$J31,0) -> 104000000 | ... BR31: =IF($G31>=BR$8,$J31,0) -> 0 | BT31: =IF($L31>=BT$8,$O31,0) -> 1.1266667e+08 | BU31: =IF($L31>=BU$8,$O31,0) -> 1.1266667e+08 | BV31: =IF($L31>=BV$8,$O31,0) -> 1.1266667e+08 | BW31: =IF($L31>=BW$8,$O31,0) -> 1.1266667e+08 | BX31: =IF($L31>=BX$8,$O31,0) -> 1.1266667e+08 | BY31: =IF($L31>=BY$8,$O31,0) -> 1.1266667e+08 | BZ31: =IF($L31>=BZ$8,$O31,0) -> 1.1266667e+08 | CA31: =IF($L31>=CA$8,$O31,0) -> 1.1266667e+08 | ... CW31: =IF($L31>=CW$8,$O31,0) -> 0 | CY31: =IF($Q31>=CY$8,$T31,0) -> 1.1266667e+08 | CZ31: =IF($Q31>=CZ$8,$T31,0) -> 1.1266667e+08 | DA31: =IF($Q31>=DA$8,$T31,0) -> 1.1266667e+08 | DB31: =IF($Q31>=DB$8,$T31,0) -> 1.1266667e+08 | DC31: =IF($Q31>=DC$8,$T31,0) -> 1.1266667e+08 | DD31: =IF($Q31>=DD$8,$T31,0) -> 1.1266667e+08 | DE31: =IF($Q31>=DE$8,$T31,0) -> 1.1266667e+08 | DF31: =IF($Q31>=DF$8,$T31,0) -> 1.1266667e+08 | ... EB31: =IF($Q31>=EB$8,$T31,0) -> 0 | ED31: =IF($V31>=ED$8,$Y31,0) -> 104000000 | EE31: =IF($V31>=EE$8,$Y31,0) -> 104000000 | EF31: =IF($V31>=EF$8,$Y31,0) -> 104000000 | EG31: =IF($V31>=EG$8,$Y31,0) -> 104000000 | EH31: =IF($V31>=EH$8,$Y31,0) -> 104000000 | EI31: =IF($V31>=EI$8,$Y31,0) -> 104000000 | EJ31: =IF($V31>=EJ$8,$Y31,0) -> 104000000 | EK31: =IF($V31>=EK$8,$Y31,0) -> 104000000 | ... FG31: =IF($V31>=FG$8,$Y31,0) -> 0 | FI31: =IF($AA31>=FI$8,$AD31,0) -> 104000000 | FJ31: =IF($AA31>=FJ$8,$AD31,0) -> 104000000 | FK31: =IF($AA31>=FK$8,$AD31,0) -> 104000000 | FL31: =IF($AA31>=FL$8,$AD31,0) -> 104000000 | FM31: =IF($AA31>=FM$8,$AD31,0) -> 104000000 | FN31: =IF($AA31>=FN$8,$AD31,0) -> 104000000 | FO31: =IF($AA31>=FO$8,$AD31,0) -> 104000000 | FP31: =IF($AA31>=FP$8,$AD31,0) -> 104000000 | ... GL31: =IF($AA31>=GL$8,$AD31,0) -> 0 | GN31: =IF($AF31>=GN$8,$AI31,0) -> 104000000 | GO31: =IF($AF31>=GO$8,$AI31,0) -> 104000000 | GP31: =IF($AF31>=GP$8,$AI31,0) -> 104000000 | GQ31: =IF($AF31>=GQ$8,$AI31,0) -> 104000000 | GR31: =IF($AF31>=GR$8,$AI31,0) -> 104000000 | GS31: =IF($AF31>=GS$8,$AI31,0) -> 104000000 | GT31: =IF($AF31>=GT$8,$AI31,0) -> 104000000 | GU31: =IF($AF31>=GU$8,$AI31,0) -> 104000000 | ... HQ31: =IF($AF31>=HQ$8,$AI31,0) -> 0
B32: Auxiliary Equipment | C32: 1.2.17 | D32: Cooling tower | E32: 1 | G32: 12 | H32: =(750000000/$D$6)*1.04 -> 780000000 | I32: =$E32*$H32 -> 780000000 | J32: =I32/G32 -> 65000000 | L32: 12 | M32: =IF(Currency="USD",ROUNDUP($E32*$H32*(1+O$6),-3),ROUNDUP($E32*$H32*(1+O$6)/EXR,-3)*EXR) -> 858000000 | N32: =$E32*M32 -> 858000000 | O32: =N32/L32 -> 71500000 | Q32: 12 | R32: =IF(Currency="USD",ROUNDUP($E32*$H32*(1+T$6),-3),ROUNDUP($E32*$H32*(1+T$6)/EXR,-3)*EXR) -> 858000000 | S32: =$E32*R32 -> 858000000 | T32: =S32/Q32 -> 71500000 | V32: 12 | W32: =H32 -> 780000000 | X32: =$E32*W32 -> 780000000 | Y32: =X32/V32 -> 65000000 | AA32: 12 | AB32: =IF(Currency="USD",ROUNDUP($E32*$H32*(1+AD$6),-3),ROUNDUP($E32*$H32*(1+AD$6)/EXR,-3)*EXR) -> 780000000 | AC32: =$E32*AB32 -> 780000000 | AD32: =AC32/AA32 -> 65000000 | AF32: 12 | AG32: =IF(Currency="USD",ROUNDUP($E32*$H32*(1+AI$6),-3),ROUNDUP($E32*$H32*(1+AI$6)/EXR,-3)*EXR) -> 780000000 | AH32: =$E32*AG32 -> 780000000 | AI32: =AH32/AF32 -> 65000000 | AL32: A. Quân | AM32: Đàm phán | AO32: =IF($G32>=AO$8,$J32,0) -> 65000000 | AP32: =IF($G32>=AP$8,$J32,0) -> 65000000 | AQ32: =IF($G32>=AQ$8,$J32,0) -> 65000000 | AR32: =IF($G32>=AR$8,$J32,0) -> 65000000 | AS32: =IF($G32>=AS$8,$J32,0) -> 65000000 | AT32: =IF($G32>=AT$8,$J32,0) -> 65000000 | AU32: =IF($G32>=AU$8,$J32,0) -> 65000000 | AV32: =IF($G32>=AV$8,$J32,0) -> 65000000 | ... BR32: =IF($G32>=BR$8,$J32,0) -> 0 | BT32: =IF($L32>=BT$8,$O32,0) -> 71500000 | BU32: =IF($L32>=BU$8,$O32,0) -> 71500000 | BV32: =IF($L32>=BV$8,$O32,0) -> 71500000 | BW32: =IF($L32>=BW$8,$O32,0) -> 71500000 | BX32: =IF($L32>=BX$8,$O32,0) -> 71500000 | BY32: =IF($L32>=BY$8,$O32,0) -> 71500000 | BZ32: =IF($L32>=BZ$8,$O32,0) -> 71500000 | CA32: =IF($L32>=CA$8,$O32,0) -> 71500000 | ... CW32: =IF($L32>=CW$8,$O32,0) -> 0 | CY32: =IF($Q32>=CY$8,$T32,0) -> 71500000 | CZ32: =IF($Q32>=CZ$8,$T32,0) -> 71500000 | DA32: =IF($Q32>=DA$8,$T32,0) -> 71500000 | DB32: =IF($Q32>=DB$8,$T32,0) -> 71500000 | DC32: =IF($Q32>=DC$8,$T32,0) -> 71500000 | DD32: =IF($Q32>=DD$8,$T32,0) -> 71500000 | DE32: =IF($Q32>=DE$8,$T32,0) -> 71500000 | DF32: =IF($Q32>=DF$8,$T32,0) -> 71500000 | ... EB32: =IF($Q32>=EB$8,$T32,0) -> 0 | ED32: =IF($V32>=ED$8,$Y32,0) -> 65000000 | EE32: =IF($V32>=EE$8,$Y32,0) -> 65000000 | EF32: =IF($V32>=EF$8,$Y32,0) -> 65000000 | EG32: =IF($V32>=EG$8,$Y32,0) -> 65000000 | EH32: =IF($V32>=EH$8,$Y32,0) -> 65000000 | EI32: =IF($V32>=EI$8,$Y32,0) -> 65000000 | EJ32: =IF($V32>=EJ$8,$Y32,0) -> 65000000 | EK32: =IF($V32>=EK$8,$Y32,0) -> 65000000 | ... FG32: =IF($V32>=FG$8,$Y32,0) -> 0 | FI32: =IF($AA32>=FI$8,$AD32,0) -> 65000000 | FJ32: =IF($AA32>=FJ$8,$AD32,0) -> 65000000 | FK32: =IF($AA32>=FK$8,$AD32,0) -> 65000000 | FL32: =IF($AA32>=FL$8,$AD32,0) -> 65000000 | FM32: =IF($AA32>=FM$8,$AD32,0) -> 65000000 | FN32: =IF($AA32>=FN$8,$AD32,0) -> 65000000 | FO32: =IF($AA32>=FO$8,$AD32,0) -> 65000000 | FP32: =IF($AA32>=FP$8,$AD32,0) -> 65000000 | ... GL32: =IF($AA32>=GL$8,$AD32,0) -> 0 | GN32: =IF($AF32>=GN$8,$AI32,0) -> 65000000 | GO32: =IF($AF32>=GO$8,$AI32,0) -> 65000000 | GP32: =IF($AF32>=GP$8,$AI32,0) -> 65000000 | GQ32: =IF($AF32>=GQ$8,$AI32,0) -> 65000000 | GR32: =IF($AF32>=GR$8,$AI32,0) -> 65000000 | GS32: =IF($AF32>=GS$8,$AI32,0) -> 65000000 | GT32: =IF($AF32>=GT$8,$AI32,0) -> 65000000 | GU32: =IF($AF32>=GU$8,$AI32,0) -> 65000000 | ... HQ32: =IF($AF32>=HQ$8,$AI32,0) -> 0
B33: Auxiliary Equipment | C33: 1.2.18 | D33: Máy scan | E33: 1 | G33: 12 | H33: =(20000000/$D$6)*1.04 -> 20800000 | I33: =$E33*$H33 -> 20800000 | J33: =I33/G33 -> 1733333.3 | L33: 12 | M33: =IF(Currency="USD",ROUNDUP($E33*$H33*(1+O$6),-3),ROUNDUP($E33*$H33*(1+O$6)/EXR,-3)*EXR) -> 26000000 | N33: =$E33*M33 -> 26000000 | O33: =N33/L33 -> 2166666.7 | Q33: 12 | R33: =IF(Currency="USD",ROUNDUP($E33*$H33*(1+T$6),-3),ROUNDUP($E33*$H33*(1+T$6)/EXR,-3)*EXR) -> 26000000 | S33: =$E33*R33 -> 26000000 | T33: =S33/Q33 -> 2166666.7 | V33: 12 | W33: =H33 -> 20800000 | X33: =$E33*W33 -> 20800000 | Y33: =X33/V33 -> 1733333.3 | AA33: 12 | AB33: =IF(Currency="USD",ROUNDUP($E33*$H33*(1+AD$6),-3),ROUNDUP($E33*$H33*(1+AD$6)/EXR,-3)*EXR) -> 26000000 | AC33: =$E33*AB33 -> 26000000 | AD33: =AC33/AA33 -> 2166666.7 | AF33: 12 | AG33: =IF(Currency="USD",ROUNDUP($E33*$H33*(1+AI$6),-3),ROUNDUP($E33*$H33*(1+AI$6)/EXR,-3)*EXR) -> 26000000 | AH33: =$E33*AG33 -> 26000000 | AI33: =AH33/AF33 -> 2166666.7 | AL33: A. Quân | AM33: Đàm phán | AO33: =IF($G33>=AO$8,$J33,0) -> 1733333.3 | AP33: =IF($G33>=AP$8,$J33,0) -> 1733333.3 | AQ33: =IF($G33>=AQ$8,$J33,0) -> 1733333.3 | AR33: =IF($G33>=AR$8,$J33,0) -> 1733333.3 | AS33: =IF($G33>=AS$8,$J33,0) -> 1733333.3 | AT33: =IF($G33>=AT$8,$J33,0) -> 1733333.3 | AU33: =IF($G33>=AU$8,$J33,0) -> 1733333.3 | AV33: =IF($G33>=AV$8,$J33,0) -> 1733333.3 | ... BR33: =IF($G33>=BR$8,$J33,0) -> 0 | BT33: =IF($L33>=BT$8,$O33,0) -> 2166666.7 | BU33: =IF($L33>=BU$8,$O33,0) -> 2166666.7 | BV33: =IF($L33>=BV$8,$O33,0) -> 2166666.7 | BW33: =IF($L33>=BW$8,$O33,0) -> 2166666.7 | BX33: =IF($L33>=BX$8,$O33,0) -> 2166666.7 | BY33: =IF($L33>=BY$8,$O33,0) -> 2166666.7 | BZ33: =IF($L33>=BZ$8,$O33,0) -> 2166666.7 | CA33: =IF($L33>=CA$8,$O33,0) -> 2166666.7 | ... CW33: =IF($L33>=CW$8,$O33,0) -> 0 | CY33: =IF($Q33>=CY$8,$T33,0) -> 2166666.7 | CZ33: =IF($Q33>=CZ$8,$T33,0) -> 2166666.7 | DA33: =IF($Q33>=DA$8,$T33,0) -> 2166666.7 | DB33: =IF($Q33>=DB$8,$T33,0) -> 2166666.7 | DC33: =IF($Q33>=DC$8,$T33,0) -> 2166666.7 | DD33: =IF($Q33>=DD$8,$T33,0) -> 2166666.7 | DE33: =IF($Q33>=DE$8,$T33,0) -> 2166666.7 | DF33: =IF($Q33>=DF$8,$T33,0) -> 2166666.7 | ... EB33: =IF($Q33>=EB$8,$T33,0) -> 0 | ED33: =IF($V33>=ED$8,$Y33,0) -> 1733333.3 | EE33: =IF($V33>=EE$8,$Y33,0) -> 1733333.3 | EF33: =IF($V33>=EF$8,$Y33,0) -> 1733333.3 | EG33: =IF($V33>=EG$8,$Y33,0) -> 1733333.3 | EH33: =IF($V33>=EH$8,$Y33,0) -> 1733333.3 | EI33: =IF($V33>=EI$8,$Y33,0) -> 1733333.3 | EJ33: =IF($V33>=EJ$8,$Y33,0) -> 1733333.3 | EK33: =IF($V33>=EK$8,$Y33,0) -> 1733333.3 | ... FG33: =IF($V33>=FG$8,$Y33,0) -> 0 | FI33: =IF($AA33>=FI$8,$AD33,0) -> 2166666.7 | FJ33: =IF($AA33>=FJ$8,$AD33,0) -> 2166666.7 | FK33: =IF($AA33>=FK$8,$AD33,0) -> 2166666.7 | FL33: =IF($AA33>=FL$8,$AD33,0) -> 2166666.7 | FM33: =IF($AA33>=FM$8,$AD33,0) -> 2166666.7 | FN33: =IF($AA33>=FN$8,$AD33,0) -> 2166666.7 | FO33: =IF($AA33>=FO$8,$AD33,0) -> 2166666.7 | FP33: =IF($AA33>=FP$8,$AD33,0) -> 2166666.7 | ... GL33: =IF($AA33>=GL$8,$AD33,0) -> 0 | GN33: =IF($AF33>=GN$8,$AI33,0) -> 2166666.7 | GO33: =IF($AF33>=GO$8,$AI33,0) -> 2166666.7 | GP33: =IF($AF33>=GP$8,$AI33,0) -> 2166666.7 | GQ33: =IF($AF33>=GQ$8,$AI33,0) -> 2166666.7 | GR33: =IF($AF33>=GR$8,$AI33,0) -> 2166666.7 | GS33: =IF($AF33>=GS$8,$AI33,0) -> 2166666.7 | GT33: =IF($AF33>=GT$8,$AI33,0) -> 2166666.7 | GU33: =IF($AF33>=GU$8,$AI33,0) -> 2166666.7 | ... HQ33: =IF($AF33>=HQ$8,$AI33,0) -> 0
A35: CAPEX-FACTORY | C35: 2. | D35: CHI PHÍ XÂY DỰNG XƯỞNG SẢN XUẤT | E35: =SUM(E36:E37) -> 2000 | I35: =SUM(I36:I37) -> 0 | J35: =SUM(J36:J37) -> 0 | N35: =SUM(N36:N37) -> 150000000000 | O35: =SUM(O36:O37) -> 6000000000 | S35: =SUM(S36:S37) -> 150000000000 | T35: =SUM(T36:T37) -> 6000000000 | X35: =SUM(X36:X37) -> 150000000000 | Y35: =SUM(Y36:Y37) -> 6000000000 | AC35: =SUM(AC36:AC37) -> 150000000000 | AD35: =SUM(AD36:AD37) -> 6000000000 | AH35: =SUM(AH36:AH37) -> 0 | AI35: =SUM(AI36:AI37) -> 0 | AO35: =SUM(AO36:AO37) -> 0 | AP35: =SUM(AP36:AP37) -> 0 | AQ35: =SUM(AQ36:AQ37) -> 0 | AR35: =SUM(AR36:AR37) -> 0 | AS35: =SUM(AS36:AS37) -> 0 | AT35: =SUM(AT36:AT37) -> 0 | AU35: =SUM(AU36:AU37) -> 0 | AV35: =SUM(AV36:AV37) -> 0 | ... BR35: =SUM(BR36:BR37) -> 0 | BT35: =SUM(BT36:BT37) -> 6000000000 | BU35: =SUM(BU36:BU37) -> 6000000000 | BV35: =SUM(BV36:BV37) -> 6000000000 | BW35: =SUM(BW36:BW37) -> 6000000000 | BX35: =SUM(BX36:BX37) -> 6000000000 | BY35: =SUM(BY36:BY37) -> 6000000000 | BZ35: =SUM(BZ36:BZ37) -> 6000000000 | CA35: =SUM(CA36:CA37) -> 6000000000 | ... CW35: =SUM(CW36:CW37) -> 0 | CY35: =SUM(CY36:CY37) -> 6000000000 | CZ35: =SUM(CZ36:CZ37) -> 6000000000 | DA35: =SUM(DA36:DA37) -> 6000000000 | DB35: =SUM(DB36:DB37) -> 6000000000 | DC35: =SUM(DC36:DC37) -> 6000000000 | DD35: =SUM(DD36:DD37) -> 6000000000 | DE35: =SUM(DE36:DE37) -> 6000000000 | DF35: =SUM(DF36:DF37) -> 6000000000 | ... EB35: =SUM(EB36:EB37) -> 0 | ED35: =SUM(ED36:ED37) -> 6000000000 | EE35: =SUM(EE36:EE37) -> 6000000000 | EF35: =SUM(EF36:EF37) -> 6000000000 | EG35: =SUM(EG36:EG37) -> 6000000000 | EH35: =SUM(EH36:EH37) -> 6000000000 | EI35: =SUM(EI36:EI37) -> 6000000000 | EJ35: =SUM(EJ36:EJ37) -> 6000000000 | EK35: =SUM(EK36:EK37) -> 6000000000 | ... FG35: =SUM(FG36:FG37) -> 0 | FI35: =SUM(FI36:FI37) -> 6000000000 | FJ35: =SUM(FJ36:FJ37) -> 6000000000 | FK35: =SUM(FK36:FK37) -> 6000000000 | FL35: =SUM(FL36:FL37) -> 6000000000 | FM35: =SUM(FM36:FM37) -> 6000000000 | FN35: =SUM(FN36:FN37) -> 6000000000 | FO35: =SUM(FO36:FO37) -> 6000000000 | FP35: =SUM(FP36:FP37) -> 6000000000 | ... GL35: =SUM(GL36:GL37) -> 0 | GN35: =SUM(GN36:GN37) -> 0 | GO35: =SUM(GO36:GO37) -> 0 | GP35: =SUM(GP36:GP37) -> 0 | GQ35: =SUM(GQ36:GQ37) -> 0 | GR35: =SUM(GR36:GR37) -> 0 | GS35: =SUM(GS36:GS37) -> 0 | GT35: =SUM(GT36:GT37) -> 0 | GU35: =SUM(GU36:GU37) -> 0 | ... HQ35: =SUM(HQ36:HQ37) -> 0
B36: Factory | C36: 2.01 | D36: Xưởng sản xuất | E36: 1900 | G36: 25 | H36: =(75000000/$D$6) -> 75000000 | I36: =$E36*$H36*0 -> 0 | J36: =I36/G36 -> 0 | L36: 25 | M36: =75000000/$D$6 -> 75000000 | N36: =$E36*M36 -> 142500000000 | O36: =N36/L36 -> 5700000000 | Q36: 25 | R36: =75000000/$D$6 -> 75000000 | S36: =$E36*R36 -> 142500000000 | T36: =S36/Q36 -> 5700000000 | V36: 25 | W36: =H36 -> 75000000 | X36: =$E36*W36 -> 142500000000 | Y36: =X36/V36 -> 5700000000 | AA36: 25 | AB36: =75000000/$D$6 -> 75000000 | AC36: =$E36*AB36 -> 142500000000 | AD36: =AC36/AA36 -> 5700000000 | AF36: 25 | AG36: =75000000/$D$6 -> 75000000 | AH36: =$E36*AG36*0 -> 0 | AI36: =AH36/AF36 -> 0 | AM36: Đàm phán | AO36: =IF($G36>=AO$8,$J36,0) -> 0 | AP36: =IF($G36>=AP$8,$J36,0) -> 0 | AQ36: =IF($G36>=AQ$8,$J36,0) -> 0 | AR36: =IF($G36>=AR$8,$J36,0) -> 0 | AS36: =IF($G36>=AS$8,$J36,0) -> 0 | AT36: =IF($G36>=AT$8,$J36,0) -> 0 | AU36: =IF($G36>=AU$8,$J36,0) -> 0 | AV36: =IF($G36>=AV$8,$J36,0) -> 0 | ... BR36: =IF($G36>=BR$8,$J36,0) -> 0 | BT36: =IF($L36>=BT$8,$O36,0) -> 5700000000 | BU36: =IF($L36>=BU$8,$O36,0) -> 5700000000 | BV36: =IF($L36>=BV$8,$O36,0) -> 5700000000 | BW36: =IF($L36>=BW$8,$O36,0) -> 5700000000 | BX36: =IF($L36>=BX$8,$O36,0) -> 5700000000 | BY36: =IF($L36>=BY$8,$O36,0) -> 5700000000 | BZ36: =IF($L36>=BZ$8,$O36,0) -> 5700000000 | CA36: =IF($L36>=CA$8,$O36,0) -> 5700000000 | ... CW36: =IF($L36>=CW$8,$O36,0) -> 0 | CY36: =IF($Q36>=CY$8,$T36,0) -> 5700000000 | CZ36: =IF($Q36>=CZ$8,$T36,0) -> 5700000000 | DA36: =IF($Q36>=DA$8,$T36,0) -> 5700000000 | DB36: =IF($Q36>=DB$8,$T36,0) -> 5700000000 | DC36: =IF($Q36>=DC$8,$T36,0) -> 5700000000 | DD36: =IF($Q36>=DD$8,$T36,0) -> 5700000000 | DE36: =IF($Q36>=DE$8,$T36,0) -> 5700000000 | DF36: =IF($Q36>=DF$8,$T36,0) -> 5700000000 | ... EB36: =IF($Q36>=EB$8,$T36,0) -> 0 | ED36: =IF($V36>=ED$8,$Y36,0) -> 5700000000 | EE36: =IF($V36>=EE$8,$Y36,0) -> 5700000000 | EF36: =IF($V36>=EF$8,$Y36,0) -> 5700000000 | EG36: =IF($V36>=EG$8,$Y36,0) -> 5700000000 | EH36: =IF($V36>=EH$8,$Y36,0) -> 5700000000 | EI36: =IF($V36>=EI$8,$Y36,0) -> 5700000000 | EJ36: =IF($V36>=EJ$8,$Y36,0) -> 5700000000 | EK36: =IF($V36>=EK$8,$Y36,0) -> 5700000000 | ... FG36: =IF($V36>=FG$8,$Y36,0) -> 0 | FI36: =IF($AA36>=FI$8,$AD36,0) -> 5700000000 | FJ36: =IF($AA36>=FJ$8,$AD36,0) -> 5700000000 | FK36: =IF($AA36>=FK$8,$AD36,0) -> 5700000000 | FL36: =IF($AA36>=FL$8,$AD36,0) -> 5700000000 | FM36: =IF($AA36>=FM$8,$AD36,0) -> 5700000000 | FN36: =IF($AA36>=FN$8,$AD36,0) -> 5700000000 | FO36: =IF($AA36>=FO$8,$AD36,0) -> 5700000000 | FP36: =IF($AA36>=FP$8,$AD36,0) -> 5700000000 | ... GL36: =IF($AA36>=GL$8,$AD36,0) -> 0 | GN36: =IF($AF36>=GN$8,$AI36,0) -> 0 | GO36: =IF($AF36>=GO$8,$AI36,0) -> 0 | GP36: =IF($AF36>=GP$8,$AI36,0) -> 0 | GQ36: =IF($AF36>=GQ$8,$AI36,0) -> 0 | GR36: =IF($AF36>=GR$8,$AI36,0) -> 0 | GS36: =IF($AF36>=GS$8,$AI36,0) -> 0 | GT36: =IF($AF36>=GT$8,$AI36,0) -> 0 | GU36: =IF($AF36>=GU$8,$AI36,0) -> 0 | ... HQ36: =IF($AF36>=HQ$8,$AI36,0) -> 0
B37: Factory | C37: 2.02 | D37: Phòng QC | E37: 100 | G37: 25 | H37: =(75000000/$D$6) -> 75000000 | I37: =$E37*$H37*0 -> 0 | J37: =I37/G37 -> 0 | L37: 25 | M37: =75000000/$D$6 -> 75000000 | N37: =$E37*M37 -> 7500000000 | O37: =N37/L37 -> 300000000 | Q37: 25 | R37: =75000000/$D$6 -> 75000000 | S37: =$E37*R37 -> 7500000000 | T37: =S37/Q37 -> 300000000 | V37: 25 | W37: =H37 -> 75000000 | X37: =$E37*W37 -> 7500000000 | Y37: =X37/V37 -> 300000000 | AA37: 25 | AB37: =75000000/$D$6 -> 75000000 | AC37: =$E37*AB37 -> 7500000000 | AD37: =AC37/AA37 -> 300000000 | AF37: 25 | AG37: =75000000/$D$6 -> 75000000 | AH37: =$E37*AG37*0 -> 0 | AI37: =AH37/AF37 -> 0 | AM37: Đàm phán | AO37: =IF($G37>=AO$8,$J37,0) -> 0 | AP37: =IF($G37>=AP$8,$J37,0) -> 0 | AQ37: =IF($G37>=AQ$8,$J37,0) -> 0 | AR37: =IF($G37>=AR$8,$J37,0) -> 0 | AS37: =IF($G37>=AS$8,$J37,0) -> 0 | AT37: =IF($G37>=AT$8,$J37,0) -> 0 | AU37: =IF($G37>=AU$8,$J37,0) -> 0 | AV37: =IF($G37>=AV$8,$J37,0) -> 0 | ... BR37: =IF($G37>=BR$8,$J37,0) -> 0 | BT37: =IF($L37>=BT$8,$O37,0) -> 300000000 | BU37: =IF($L37>=BU$8,$O37,0) -> 300000000 | BV37: =IF($L37>=BV$8,$O37,0) -> 300000000 | BW37: =IF($L37>=BW$8,$O37,0) -> 300000000 | BX37: =IF($L37>=BX$8,$O37,0) -> 300000000 | BY37: =IF($L37>=BY$8,$O37,0) -> 300000000 | BZ37: =IF($L37>=BZ$8,$O37,0) -> 300000000 | CA37: =IF($L37>=CA$8,$O37,0) -> 300000000 | ... CW37: =IF($L37>=CW$8,$O37,0) -> 0 | CY37: =IF($Q37>=CY$8,$T37,0) -> 300000000 | CZ37: =IF($Q37>=CZ$8,$T37,0) -> 300000000 | DA37: =IF($Q37>=DA$8,$T37,0) -> 300000000 | DB37: =IF($Q37>=DB$8,$T37,0) -> 300000000 | DC37: =IF($Q37>=DC$8,$T37,0) -> 300000000 | DD37: =IF($Q37>=DD$8,$T37,0) -> 300000000 | DE37: =IF($Q37>=DE$8,$T37,0) -> 300000000 | DF37: =IF($Q37>=DF$8,$T37,0) -> 300000000 | ... EB37: =IF($Q37>=EB$8,$T37,0) -> 0 | ED37: =IF($V37>=ED$8,$Y37,0) -> 300000000 | EE37: =IF($V37>=EE$8,$Y37,0) -> 300000000 | EF37: =IF($V37>=EF$8,$Y37,0) -> 300000000 | EG37: =IF($V37>=EG$8,$Y37,0) -> 300000000 | EH37: =IF($V37>=EH$8,$Y37,0) -> 300000000 | EI37: =IF($V37>=EI$8,$Y37,0) -> 300000000 | EJ37: =IF($V37>=EJ$8,$Y37,0) -> 300000000 | EK37: =IF($V37>=EK$8,$Y37,0) -> 300000000 | ... FG37: =IF($V37>=FG$8,$Y37,0) -> 0 | FI37: =IF($AA37>=FI$8,$AD37,0) -> 300000000 | FJ37: =IF($AA37>=FJ$8,$AD37,0) -> 300000000 | FK37: =IF($AA37>=FK$8,$AD37,0) -> 300000000 | FL37: =IF($AA37>=FL$8,$AD37,0) -> 300000000 | FM37: =IF($AA37>=FM$8,$AD37,0) -> 300000000 | FN37: =IF($AA37>=FN$8,$AD37,0) -> 300000000 | FO37: =IF($AA37>=FO$8,$AD37,0) -> 300000000 | FP37: =IF($AA37>=FP$8,$AD37,0) -> 300000000 | ... GL37: =IF($AA37>=GL$8,$AD37,0) -> 0 | GN37: =IF($AF37>=GN$8,$AI37,0) -> 0 | GO37: =IF($AF37>=GO$8,$AI37,0) -> 0 | GP37: =IF($AF37>=GP$8,$AI37,0) -> 0 | GQ37: =IF($AF37>=GQ$8,$AI37,0) -> 0 | GR37: =IF($AF37>=GR$8,$AI37,0) -> 0 | GS37: =IF($AF37>=GS$8,$AI37,0) -> 0 | GT37: =IF($AF37>=GT$8,$AI37,0) -> 0 | GU37: =IF($AF37>=GU$8,$AI37,0) -> 0 | ... HQ37: =IF($AF37>=HQ$8,$AI37,0) -> 0
A39: CAPEX-LAB | C39: 3. | D39: MÁY MÓC THIẾT BỊ PHÒNG LAB | I39: =SUM(I40:I58) -> 16250000000 | J39: =SUM(J40:J58) -> 1.3541667e+09 | N39: =SUM(N40:N58) -> 17654000000 | O39: =SUM(O40:O58) -> 1.4711667e+09 | S39: =SUM(S40:S58) -> 17654000000 | T39: =SUM(T40:T58) -> 1.4711667e+09 | X39: =SUM(X40:X58) -> 16250000000 | Y39: =SUM(Y40:Y58) -> 1.3541667e+09 | AC39: =SUM(AC40:AC58) -> 16276000000 | AD39: =SUM(AD40:AD58) -> 1.3563333e+09 | AH39: =SUM(AH40:AH58) -> 16276000000 | AI39: =SUM(AI40:AI58) -> 1.3563333e+09 | AO39: =SUM(AO40:AO58) -> 1.3541667e+09 | AP39: =SUM(AP40:AP58) -> 1.3541667e+09 | AQ39: =SUM(AQ40:AQ58) -> 1.3541667e+09 | AR39: =SUM(AR40:AR58) -> 1.3541667e+09 | AS39: =SUM(AS40:AS58) -> 1.3541667e+09 | AT39: =SUM(AT40:AT58) -> 1.3541667e+09 | AU39: =SUM(AU40:AU58) -> 1.3541667e+09 | AV39: =SUM(AV40:AV58) -> 1.3541667e+09 | ... BR39: =SUM(BR40:BR58) -> 0 | BT39: =SUM(BT40:BT58) -> 1.4711667e+09 | BU39: =SUM(BU40:BU58) -> 1.4711667e+09 | BV39: =SUM(BV40:BV58) -> 1.4711667e+09 | BW39: =SUM(BW40:BW58) -> 1.4711667e+09 | BX39: =SUM(BX40:BX58) -> 1.4711667e+09 | BY39: =SUM(BY40:BY58) -> 1.4711667e+09 | BZ39: =SUM(BZ40:BZ58) -> 1.4711667e+09 | CA39: =SUM(CA40:CA58) -> 1.4711667e+09 | ... CW39: =SUM(CW40:CW58) -> 0 | CY39: =SUM(CY40:CY58) -> 1.4711667e+09 | CZ39: =SUM(CZ40:CZ58) -> 1.4711667e+09 | DA39: =SUM(DA40:DA58) -> 1.4711667e+09 | DB39: =SUM(DB40:DB58) -> 1.4711667e+09 | DC39: =SUM(DC40:DC58) -> 1.4711667e+09 | DD39: =SUM(DD40:DD58) -> 1.4711667e+09 | DE39: =SUM(DE40:DE58) -> 1.4711667e+09 | DF39: =SUM(DF40:DF58) -> 1.4711667e+09 | ... EB39: =SUM(EB40:EB58) -> 0 | ED39: =SUM(ED40:ED58) -> 1.3541667e+09 | EE39: =SUM(EE40:EE58) -> 1.3541667e+09 | EF39: =SUM(EF40:EF58) -> 1.3541667e+09 | EG39: =SUM(EG40:EG58) -> 1.3541667e+09 | EH39: =SUM(EH40:EH58) -> 1.3541667e+09 | EI39: =SUM(EI40:EI58) -> 1.3541667e+09 | EJ39: =SUM(EJ40:EJ58) -> 1.3541667e+09 | EK39: =SUM(EK40:EK58) -> 1.3541667e+09 | ... FG39: =SUM(FG40:FG58) -> 0 | FI39: =SUM(FI40:FI58) -> 1.3563333e+09 | FJ39: =SUM(FJ40:FJ58) -> 1.3563333e+09 | FK39: =SUM(FK40:FK58) -> 1.3563333e+09 | FL39: =SUM(FL40:FL58) -> 1.3563333e+09 | FM39: =SUM(FM40:FM58) -> 1.3563333e+09 | FN39: =SUM(FN40:FN58) -> 1.3563333e+09 | FO39: =SUM(FO40:FO58) -> 1.3563333e+09 | FP39: =SUM(FP40:FP58) -> 1.3563333e+09 | ... GL39: =SUM(GL40:GL58) -> 0 | GN39: =SUM(GN40:GN58) -> 1.3563333e+09 | GO39: =SUM(GO40:GO58) -> 1.3563333e+09 | GP39: =SUM(GP40:GP58) -> 1.3563333e+09 | GQ39: =SUM(GQ40:GQ58) -> 1.3563333e+09 | GR39: =SUM(GR40:GR58) -> 1.3563333e+09 | GS39: =SUM(GS40:GS58) -> 1.3563333e+09 | GT39: =SUM(GT40:GT58) -> 1.3563333e+09 | GU39: =SUM(GU40:GU58) -> 1.3563333e+09 | ... HQ39: =SUM(HQ40:HQ58) -> 0
B40: Inspection machine - Lab facilities | C40: 3.01 | D40: Máy đo IV PSL IV 4603 | E40: 1 | G40: 12 | H40: =(5000000000/$D$6)*1.04 -> 5200000000 | I40: =$E40*$H40 -> 5200000000 | J40: =I40/G40 -> 4.3333333e+08 | L40: 12 | M40: =IF(Currency="USD",ROUNDUP($E40*$H40*(1+O$6),-3),ROUNDUP($E40*$H40*(1+O$6)/EXR,-3)*EXR) -> 5564000000 | N40: =$E40*M40 -> 5564000000 | O40: =N40/L40 -> 4.6366667e+08 | Q40: 12 | R40: =IF(Currency="USD",ROUNDUP($E40*$H40*(1+T$6),-3),ROUNDUP($E40*$H40*(1+T$6)/EXR,-3)*EXR) -> 5564000000 | S40: =$E40*R40 -> 5564000000 | T40: =S40/Q40 -> 4.6366667e+08 | V40: 12 | W40: =H40 -> 5200000000 | X40: =$E40*W40 -> 5200000000 | Y40: =X40/V40 -> 4.3333333e+08 | AA40: 12 | AB40: =IF(Currency="USD",ROUNDUP($E40*$H40*(1+AD$6),-3),ROUNDUP($E40*$H40*(1+AD$6)/EXR,-3)*EXR) -> 5200000000 | AC40: =$E40*AB40 -> 5200000000 | AD40: =AC40/AA40 -> 4.3333333e+08 | AF40: 12 | AG40: =IF(Currency="USD",ROUNDUP($E40*$H40*(1+AI$6),-3),ROUNDUP($E40*$H40*(1+AI$6)/EXR,-3)*EXR) -> 5200000000 | AH40: =$E40*AG40 -> 5200000000 | AI40: =AH40/AF40 -> 4.3333333e+08 | AM40: Đàm phán | AO40: =IF($G40>=AO$8,$J40,0) -> 4.3333333e+08 | AP40: =IF($G40>=AP$8,$J40,0) -> 4.3333333e+08 | AQ40: =IF($G40>=AQ$8,$J40,0) -> 4.3333333e+08 | AR40: =IF($G40>=AR$8,$J40,0) -> 4.3333333e+08 | AS40: =IF($G40>=AS$8,$J40,0) -> 4.3333333e+08 | AT40: =IF($G40>=AT$8,$J40,0) -> 4.3333333e+08 | AU40: =IF($G40>=AU$8,$J40,0) -> 4.3333333e+08 | AV40: =IF($G40>=AV$8,$J40,0) -> 4.3333333e+08 | ... BR40: =IF($G40>=BR$8,$J40,0) -> 0 | BT40: =IF($L40>=BT$8,$O40,0) -> 4.6366667e+08 | BU40: =IF($L40>=BU$8,$O40,0) -> 4.6366667e+08 | BV40: =IF($L40>=BV$8,$O40,0) -> 4.6366667e+08 | BW40: =IF($L40>=BW$8,$O40,0) -> 4.6366667e+08 | BX40: =IF($L40>=BX$8,$O40,0) -> 4.6366667e+08 | BY40: =IF($L40>=BY$8,$O40,0) -> 4.6366667e+08 | BZ40: =IF($L40>=BZ$8,$O40,0) -> 4.6366667e+08 | CA40: =IF($L40>=CA$8,$O40,0) -> 4.6366667e+08 | ... CW40: =IF($L40>=CW$8,$O40,0) -> 0 | CY40: =IF($Q40>=CY$8,$T40,0) -> 4.6366667e+08 | CZ40: =IF($Q40>=CZ$8,$T40,0) -> 4.6366667e+08 | DA40: =IF($Q40>=DA$8,$T40,0) -> 4.6366667e+08 | DB40: =IF($Q40>=DB$8,$T40,0) -> 4.6366667e+08 | DC40: =IF($Q40>=DC$8,$T40,0) -> 4.6366667e+08 | DD40: =IF($Q40>=DD$8,$T40,0) -> 4.6366667e+08 | DE40: =IF($Q40>=DE$8,$T40,0) -> 4.6366667e+08 | DF40: =IF($Q40>=DF$8,$T40,0) -> 4.6366667e+08 | ... EB40: =IF($Q40>=EB$8,$T40,0) -> 0 | ED40: =IF($V40>=ED$8,$Y40,0) -> 4.3333333e+08 | EE40: =IF($V40>=EE$8,$Y40,0) -> 4.3333333e+08 | EF40: =IF($V40>=EF$8,$Y40,0) -> 4.3333333e+08 | EG40: =IF($V40>=EG$8,$Y40,0) -> 4.3333333e+08 | EH40: =IF($V40>=EH$8,$Y40,0) -> 4.3333333e+08 | EI40: =IF($V40>=EI$8,$Y40,0) -> 4.3333333e+08 | EJ40: =IF($V40>=EJ$8,$Y40,0) -> 4.3333333e+08 | EK40: =IF($V40>=EK$8,$Y40,0) -> 4.3333333e+08 | ... FG40: =IF($V40>=FG$8,$Y40,0) -> 0 | FI40: =IF($AA40>=FI$8,$AD40,0) -> 4.3333333e+08 | FJ40: =IF($AA40>=FJ$8,$AD40,0) -> 4.3333333e+08 | FK40: =IF($AA40>=FK$8,$AD40,0) -> 4.3333333e+08 | FL40: =IF($AA40>=FL$8,$AD40,0) -> 4.3333333e+08 | FM40: =IF($AA40>=FM$8,$AD40,0) -> 4.3333333e+08 | FN40: =IF($AA40>=FN$8,$AD40,0) -> 4.3333333e+08 | FO40: =IF($AA40>=FO$8,$AD40,0) -> 4.3333333e+08 | FP40: =IF($AA40>=FP$8,$AD40,0) -> 4.3333333e+08 | ... GL40: =IF($AA40>=GL$8,$AD40,0) -> 0 | GN40: =IF($AF40>=GN$8,$AI40,0) -> 4.3333333e+08 | GO40: =IF($AF40>=GO$8,$AI40,0) -> 4.3333333e+08 | GP40: =IF($AF40>=GP$8,$AI40,0) -> 4.3333333e+08 | GQ40: =IF($AF40>=GQ$8,$AI40,0) -> 4.3333333e+08 | GR40: =IF($AF40>=GR$8,$AI40,0) -> 4.3333333e+08 | GS40: =IF($AF40>=GS$8,$AI40,0) -> 4.3333333e+08 | GT40: =IF($AF40>=GT$8,$AI40,0) -> 4.3333333e+08 | GU40: =IF($AF40>=GU$8,$AI40,0) -> 4.3333333e+08 | ... HQ40: =IF($AF40>=HQ$8,$AI40,0) -> 0
B41: Inspection machine - Lab facilities | C41: 3.02 | D41: Máy đo kích thước tự động Gawis 4D | E41: 1 | G41: 12 | H41: =(5000000000/$D$6)*1.04 -> 5200000000 | I41: =$E41*$H41 -> 5200000000 | J41: =I41/G41 -> 4.3333333e+08 | L41: 12 | M41: =IF(Currency="USD",ROUNDUP($E41*$H41*(1+O$6),-3),ROUNDUP($E41*$H41*(1+O$6)/EXR,-3)*EXR) -> 5564000000 | N41: =$E41*M41 -> 5564000000 | O41: =N41/L41 -> 4.6366667e+08 | Q41: 12 | R41: =IF(Currency="USD",ROUNDUP($E41*$H41*(1+T$6),-3),ROUNDUP($E41*$H41*(1+T$6)/EXR,-3)*EXR) -> 5564000000 | S41: =$E41*R41 -> 5564000000 | T41: =S41/Q41 -> 4.6366667e+08 | V41: 12 | W41: =H41 -> 5200000000 | X41: =$E41*W41 -> 5200000000 | Y41: =X41/V41 -> 4.3333333e+08 | AA41: 12 | AB41: =IF(Currency="USD",ROUNDUP($E41*$H41*(1+AD$6),-3),ROUNDUP($E41*$H41*(1+AD$6)/EXR,-3)*EXR) -> 5200000000 | AC41: =$E41*AB41 -> 5200000000 | AD41: =AC41/AA41 -> 4.3333333e+08 | AF41: 12 | AG41: =IF(Currency="USD",ROUNDUP($E41*$H41*(1+AI$6),-3),ROUNDUP($E41*$H41*(1+AI$6)/EXR,-3)*EXR) -> 5200000000 | AH41: =$E41*AG41 -> 5200000000 | AI41: =AH41/AF41 -> 4.3333333e+08 | AM41: Đàm phán | AO41: =IF($G41>=AO$8,$J41,0) -> 4.3333333e+08 | AP41: =IF($G41>=AP$8,$J41,0) -> 4.3333333e+08 | AQ41: =IF($G41>=AQ$8,$J41,0) -> 4.3333333e+08 | AR41: =IF($G41>=AR$8,$J41,0) -> 4.3333333e+08 | AS41: =IF($G41>=AS$8,$J41,0) -> 4.3333333e+08 | AT41: =IF($G41>=AT$8,$J41,0) -> 4.3333333e+08 | AU41: =IF($G41>=AU$8,$J41,0) -> 4.3333333e+08 | AV41: =IF($G41>=AV$8,$J41,0) -> 4.3333333e+08 | ... BR41: =IF($G41>=BR$8,$J41,0) -> 0 | BT41: =IF($L41>=BT$8,$O41,0) -> 4.6366667e+08 | BU41: =IF($L41>=BU$8,$O41,0) -> 4.6366667e+08 | BV41: =IF($L41>=BV$8,$O41,0) -> 4.6366667e+08 | BW41: =IF($L41>=BW$8,$O41,0) -> 4.6366667e+08 | BX41: =IF($L41>=BX$8,$O41,0) -> 4.6366667e+08 | BY41: =IF($L41>=BY$8,$O41,0) -> 4.6366667e+08 | BZ41: =IF($L41>=BZ$8,$O41,0) -> 4.6366667e+08 | CA41: =IF($L41>=CA$8,$O41,0) -> 4.6366667e+08 | ... CW41: =IF($L41>=CW$8,$O41,0) -> 0 | CY41: =IF($Q41>=CY$8,$T41,0) -> 4.6366667e+08 | CZ41: =IF($Q41>=CZ$8,$T41,0) -> 4.6366667e+08 | DA41: =IF($Q41>=DA$8,$T41,0) -> 4.6366667e+08 | DB41: =IF($Q41>=DB$8,$T41,0) -> 4.6366667e+08 | DC41: =IF($Q41>=DC$8,$T41,0) -> 4.6366667e+08 | DD41: =IF($Q41>=DD$8,$T41,0) -> 4.6366667e+08 | DE41: =IF($Q41>=DE$8,$T41,0) -> 4.6366667e+08 | DF41: =IF($Q41>=DF$8,$T41,0) -> 4.6366667e+08 | ... EB41: =IF($Q41>=EB$8,$T41,0) -> 0 | ED41: =IF($V41>=ED$8,$Y41,0) -> 4.3333333e+08 | EE41: =IF($V41>=EE$8,$Y41,0) -> 4.3333333e+08 | EF41: =IF($V41>=EF$8,$Y41,0) -> 4.3333333e+08 | EG41: =IF($V41>=EG$8,$Y41,0) -> 4.3333333e+08 | EH41: =IF($V41>=EH$8,$Y41,0) -> 4.3333333e+08 | EI41: =IF($V41>=EI$8,$Y41,0) -> 4.3333333e+08 | EJ41: =IF($V41>=EJ$8,$Y41,0) -> 4.3333333e+08 | EK41: =IF($V41>=EK$8,$Y41,0) -> 4.3333333e+08 | ... FG41: =IF($V41>=FG$8,$Y41,0) -> 0 | FI41: =IF($AA41>=FI$8,$AD41,0) -> 4.3333333e+08 | FJ41: =IF($AA41>=FJ$8,$AD41,0) -> 4.3333333e+08 | FK41: =IF($AA41>=FK$8,$AD41,0) -> 4.3333333e+08 | FL41: =IF($AA41>=FL$8,$AD41,0) -> 4.3333333e+08 | FM41: =IF($AA41>=FM$8,$AD41,0) -> 4.3333333e+08 | FN41: =IF($AA41>=FN$8,$AD41,0) -> 4.3333333e+08 | FO41: =IF($AA41>=FO$8,$AD41,0) -> 4.3333333e+08 | FP41: =IF($AA41>=FP$8,$AD41,0) -> 4.3333333e+08 | ... GL41: =IF($AA41>=GL$8,$AD41,0) -> 0 | GN41: =IF($AF41>=GN$8,$AI41,0) -> 4.3333333e+08 | GO41: =IF($AF41>=GO$8,$AI41,0) -> 4.3333333e+08 | GP41: =IF($AF41>=GP$8,$AI41,0) -> 4.3333333e+08 | GQ41: =IF($AF41>=GQ$8,$AI41,0) -> 4.3333333e+08 | GR41: =IF($AF41>=GR$8,$AI41,0) -> 4.3333333e+08 | GS41: =IF($AF41>=GS$8,$AI41,0) -> 4.3333333e+08 | GT41: =IF($AF41>=GT$8,$AI41,0) -> 4.3333333e+08 | GU41: =IF($AF41>=GU$8,$AI41,0) -> 4.3333333e+08 | ... HQ41: =IF($AF41>=HQ$8,$AI41,0) -> 0
B42: Inspection machine - Lab facilities | C42: 3.03 | D42: Máy đo AA Piovan Inspecta | E42: 1 | G42: 12 | H42: =(2925000000/$D$6)*1.04 -> 3042000000 | I42: =$E42*$H42 -> 3042000000 | J42: =I42/G42 -> 253500000 | L42: 12 | M42: =IF(Currency="USD",ROUNDUP($E42*$H42*(1+O$6),-3),ROUNDUP($E42*$H42*(1+O$6)/EXR,-3)*EXR) -> 3276000000 | N42: =$E42*M42 -> 3276000000 | O42: =N42/L42 -> 273000000 | Q42: 12 | R42: =IF(Currency="USD",ROUNDUP($E42*$H42*(1+T$6),-3),ROUNDUP($E42*$H42*(1+T$6)/EXR,-3)*EXR) -> 3276000000 | S42: =$E42*R42 -> 3276000000 | T42: =S42/Q42 -> 273000000 | V42: 12 | W42: =H42 -> 3042000000 | X42: =$E42*W42 -> 3042000000 | Y42: =X42/V42 -> 253500000 | AA42: 12 | AB42: =IF(Currency="USD",ROUNDUP($E42*$H42*(1+AD$6),-3),ROUNDUP($E42*$H42*(1+AD$6)/EXR,-3)*EXR) -> 3042000000 | AC42: =$E42*AB42 -> 3042000000 | AD42: =AC42/AA42 -> 253500000 | AF42: 12 | AG42: =IF(Currency="USD",ROUNDUP($E42*$H42*(1+AI$6),-3),ROUNDUP($E42*$H42*(1+AI$6)/EXR,-3)*EXR) -> 3042000000 | AH42: =$E42*AG42 -> 3042000000 | AI42: =AH42/AF42 -> 253500000 | AM42: Đàm phán | AO42: =IF($G42>=AO$8,$J42,0) -> 253500000 | AP42: =IF($G42>=AP$8,$J42,0) -> 253500000 | AQ42: =IF($G42>=AQ$8,$J42,0) -> 253500000 | AR42: =IF($G42>=AR$8,$J42,0) -> 253500000 | AS42: =IF($G42>=AS$8,$J42,0) -> 253500000 | AT42: =IF($G42>=AT$8,$J42,0) -> 253500000 | AU42: =IF($G42>=AU$8,$J42,0) -> 253500000 | AV42: =IF($G42>=AV$8,$J42,0) -> 253500000 | ... BR42: =IF($G42>=BR$8,$J42,0) -> 0 | BT42: =IF($L42>=BT$8,$O42,0) -> 273000000 | BU42: =IF($L42>=BU$8,$O42,0) -> 273000000 | BV42: =IF($L42>=BV$8,$O42,0) -> 273000000 | BW42: =IF($L42>=BW$8,$O42,0) -> 273000000 | BX42: =IF($L42>=BX$8,$O42,0) -> 273000000 | BY42: =IF($L42>=BY$8,$O42,0) -> 273000000 | BZ42: =IF($L42>=BZ$8,$O42,0) -> 273000000 | CA42: =IF($L42>=CA$8,$O42,0) -> 273000000 | ... CW42: =IF($L42>=CW$8,$O42,0) -> 0 | CY42: =IF($Q42>=CY$8,$T42,0) -> 273000000 | CZ42: =IF($Q42>=CZ$8,$T42,0) -> 273000000 | DA42: =IF($Q42>=DA$8,$T42,0) -> 273000000 | DB42: =IF($Q42>=DB$8,$T42,0) -> 273000000 | DC42: =IF($Q42>=DC$8,$T42,0) -> 273000000 | DD42: =IF($Q42>=DD$8,$T42,0) -> 273000000 | DE42: =IF($Q42>=DE$8,$T42,0) -> 273000000 | DF42: =IF($Q42>=DF$8,$T42,0) -> 273000000 | ... EB42: =IF($Q42>=EB$8,$T42,0) -> 0 | ED42: =IF($V42>=ED$8,$Y42,0) -> 253500000 | EE42: =IF($V42>=EE$8,$Y42,0) -> 253500000 | EF42: =IF($V42>=EF$8,$Y42,0) -> 253500000 | EG42: =IF($V42>=EG$8,$Y42,0) -> 253500000 | EH42: =IF($V42>=EH$8,$Y42,0) -> 253500000 | EI42: =IF($V42>=EI$8,$Y42,0) -> 253500000 | EJ42: =IF($V42>=EJ$8,$Y42,0) -> 253500000 | EK42: =IF($V42>=EK$8,$Y42,0) -> 253500000 | ... FG42: =IF($V42>=FG$8,$Y42,0) -> 0 | FI42: =IF($AA42>=FI$8,$AD42,0) -> 253500000 | FJ42: =IF($AA42>=FJ$8,$AD42,0) -> 253500000 | FK42: =IF($AA42>=FK$8,$AD42,0) -> 253500000 | FL42: =IF($AA42>=FL$8,$AD42,0) -> 253500000 | FM42: =IF($AA42>=FM$8,$AD42,0) -> 253500000 | FN42: =IF($AA42>=FN$8,$AD42,0) -> 253500000 | FO42: =IF($AA42>=FO$8,$AD42,0) -> 253500000 | FP42: =IF($AA42>=FP$8,$AD42,0) -> 253500000 | ... GL42: =IF($AA42>=GL$8,$AD42,0) -> 0 | GN42: =IF($AF42>=GN$8,$AI42,0) -> 253500000 | GO42: =IF($AF42>=GO$8,$AI42,0) -> 253500000 | GP42: =IF($AF42>=GP$8,$AI42,0) -> 253500000 | GQ42: =IF($AF42>=GQ$8,$AI42,0) -> 253500000 | GR42: =IF($AF42>=GR$8,$AI42,0) -> 253500000 | GS42: =IF($AF42>=GS$8,$AI42,0) -> 253500000 | GT42: =IF($AF42>=GT$8,$AI42,0) -> 253500000 | GU42: =IF($AF42>=GU$8,$AI42,0) -> 253500000 | ... HQ42: =IF($AF42>=HQ$8,$AI42,0) -> 0
B43: Inspection machine - Lab facilities | C43: 3.04 | D43: Colorimeter/Spectrophotometer | E43: 1 | G43: 12 | H43: =(625000000/$D$6)*1.04 -> 650000000 | I43: =$E43*$H43 -> 650000000 | J43: =I43/G43 -> 54166667 | L43: 12 | M43: =IF(Currency="USD",ROUNDUP($E43*$H43*(1+O$6),-3),ROUNDUP($E43*$H43*(1+O$6)/EXR,-3)*EXR) -> 702000000 | N43: =$E43*M43 -> 702000000 | O43: =N43/L43 -> 58500000 | Q43: 12 | R43: =IF(Currency="USD",ROUNDUP($E43*$H43*(1+T$6),-3),ROUNDUP($E43*$H43*(1+T$6)/EXR,-3)*EXR) -> 702000000 | S43: =$E43*R43 -> 702000000 | T43: =S43/Q43 -> 58500000 | V43: 12 | W43: =H43 -> 650000000 | X43: =$E43*W43 -> 650000000 | Y43: =X43/V43 -> 54166667 | AA43: 12 | AB43: =IF(Currency="USD",ROUNDUP($E43*$H43*(1+AD$6),-3),ROUNDUP($E43*$H43*(1+AD$6)/EXR,-3)*EXR) -> 650000000 | AC43: =$E43*AB43 -> 650000000 | AD43: =AC43/AA43 -> 54166667 | AF43: 12 | AG43: =IF(Currency="USD",ROUNDUP($E43*$H43*(1+AI$6),-3),ROUNDUP($E43*$H43*(1+AI$6)/EXR,-3)*EXR) -> 650000000 | AH43: =$E43*AG43 -> 650000000 | AI43: =AH43/AF43 -> 54166667 | AM43: Đàm phán | AO43: =IF($G43>=AO$8,$J43,0) -> 54166667 | AP43: =IF($G43>=AP$8,$J43,0) -> 54166667 | AQ43: =IF($G43>=AQ$8,$J43,0) -> 54166667 | AR43: =IF($G43>=AR$8,$J43,0) -> 54166667 | AS43: =IF($G43>=AS$8,$J43,0) -> 54166667 | AT43: =IF($G43>=AT$8,$J43,0) -> 54166667 | AU43: =IF($G43>=AU$8,$J43,0) -> 54166667 | AV43: =IF($G43>=AV$8,$J43,0) -> 54166667 | ... BR43: =IF($G43>=BR$8,$J43,0) -> 0 | BT43: =IF($L43>=BT$8,$O43,0) -> 58500000 | BU43: =IF($L43>=BU$8,$O43,0) -> 58500000 | BV43: =IF($L43>=BV$8,$O43,0) -> 58500000 | BW43: =IF($L43>=BW$8,$O43,0) -> 58500000 | BX43: =IF($L43>=BX$8,$O43,0) -> 58500000 | BY43: =IF($L43>=BY$8,$O43,0) -> 58500000 | BZ43: =IF($L43>=BZ$8,$O43,0) -> 58500000 | CA43: =IF($L43>=CA$8,$O43,0) -> 58500000 | ... CW43: =IF($L43>=CW$8,$O43,0) -> 0 | CY43: =IF($Q43>=CY$8,$T43,0) -> 58500000 | CZ43: =IF($Q43>=CZ$8,$T43,0) -> 58500000 | DA43: =IF($Q43>=DA$8,$T43,0) -> 58500000 | DB43: =IF($Q43>=DB$8,$T43,0) -> 58500000 | DC43: =IF($Q43>=DC$8,$T43,0) -> 58500000 | DD43: =IF($Q43>=DD$8,$T43,0) -> 58500000 | DE43: =IF($Q43>=DE$8,$T43,0) -> 58500000 | DF43: =IF($Q43>=DF$8,$T43,0) -> 58500000 | ... EB43: =IF($Q43>=EB$8,$T43,0) -> 0 | ED43: =IF($V43>=ED$8,$Y43,0) -> 54166667 | EE43: =IF($V43>=EE$8,$Y43,0) -> 54166667 | EF43: =IF($V43>=EF$8,$Y43,0) -> 54166667 | EG43: =IF($V43>=EG$8,$Y43,0) -> 54166667 | EH43: =IF($V43>=EH$8,$Y43,0) -> 54166667 | EI43: =IF($V43>=EI$8,$Y43,0) -> 54166667 | EJ43: =IF($V43>=EJ$8,$Y43,0) -> 54166667 | EK43: =IF($V43>=EK$8,$Y43,0) -> 54166667 | ... FG43: =IF($V43>=FG$8,$Y43,0) -> 0 | FI43: =IF($AA43>=FI$8,$AD43,0) -> 54166667 | FJ43: =IF($AA43>=FJ$8,$AD43,0) -> 54166667 | FK43: =IF($AA43>=FK$8,$AD43,0) -> 54166667 | FL43: =IF($AA43>=FL$8,$AD43,0) -> 54166667 | FM43: =IF($AA43>=FM$8,$AD43,0) -> 54166667 | FN43: =IF($AA43>=FN$8,$AD43,0) -> 54166667 | FO43: =IF($AA43>=FO$8,$AD43,0) -> 54166667 | FP43: =IF($AA43>=FP$8,$AD43,0) -> 54166667 | ... GL43: =IF($AA43>=GL$8,$AD43,0) -> 0 | GN43: =IF($AF43>=GN$8,$AI43,0) -> 54166667 | GO43: =IF($AF43>=GO$8,$AI43,0) -> 54166667 | GP43: =IF($AF43>=GP$8,$AI43,0) -> 54166667 | GQ43: =IF($AF43>=GQ$8,$AI43,0) -> 54166667 | GR43: =IF($AF43>=GR$8,$AI43,0) -> 54166667 | GS43: =IF($AF43>=GS$8,$AI43,0) -> 54166667 | GT43: =IF($AF43>=GT$8,$AI43,0) -> 54166667 | GU43: =IF($AF43>=GU$8,$AI43,0) -> 54166667 | ... HQ43: =IF($AF43>=HQ$8,$AI43,0) -> 0
