Workbook
Name Capacity: 'Cover Page'!$F$28
Name Currency: 'Cover Page'!$A$33
Name EXR: 'Cover Page'!$F$10
Name Inflation: 'Cover Page'!$F$9
Name Opt1_WACC: 'Cover Page'!$H$23
Name Opt10_CAPEX: 'Cover Page'!$AI$6
Name Opt10_CPSX: 'Cover Page'!$AI$7
Name Opt2_CAPEX: 'Cover Page'!$K$6
Name Opt2_CPSX: 'Cover Page'!$K$7
Name Opt2_EXW: 'Cover Page'!$K$10
Name Opt2_WACC: 'Cover Page'!$K$23
Name Opt3_CAPEX: 'Cover Page'!$N$6
Name Opt3_CPSX: 'Cover Page'!$N$7
Name Opt3_WACC: 'Cover Page'!$W$23
Name Opt4_CAPEX: 'Cover Page'!$Q$6
Name Opt4_CPSX: 'Cover Page'!$Q$7
Name Opt5_CAPEX: 'Cover Page'!$T$6
Name Opt5_CPSX: 'Cover Page'!$T$7
Name Opt6_CAPEX: 'Cover Page'!$W$6
Name Opt6_CPSX: 'Cover Page'!$W$7
Name Opt7_CAPEX: 'Cover Page'!$Z$6
Name Opt7_CPSX: 'Cover Page'!$Z$7
Name Opt8_CAPEX: 'Cover Page'!$AC$6
Name Opt8_CPSX: 'Cover Page'!$AC$7
Name Opt9_CAPEX: 'Cover Page'!$AF$6
Name Opt9_CPSX: 'Cover Page'!$AF$7
Name PHOI_KG: 'Cover Page'!$F$30
Name Slicer_Currency: #N/A
Name Tax_rate: 'Cover Page'!$F$11
Name WACC: 'Cover Page'!$F$23

Sheet Timeline

Sheet >>PowerPoint

Sheet Trình bày giả định
A2: CÁC GIẢ ĐỊNH CỦA DỰ ÁN
A4: STT | B4: GIẢ ĐỊNH | C4: GIÁ TRỊ | D4: ĐVT/Ghi chú | F4: STT | G4: GIẢ ĐỊNH | H4: GIÁ TRỊ | I4: ĐVT/Ghi chú
A5: 1 | B5: Thông tin chung | F5: 4 | G5: Hiệu suất sử dụng máy | H5: ='W3'!$L$23 -> 0.88
A6: 1.1 | B6: Chủ đầu tư | C6: DTR
A7: 1.2 | B7: Thời gian khai thác | C7: 15 | D7: Năm | F7: 5 | G7: Sản lượng sản xuất tối đa | H7: ='W3'!U27/10^3 -> 6194.175 | I7: tấn/năm
A8: 1.3 | B8: Tổng dự toán đầu tư máy móc thiết bị (VND) | C8: =IF(Currency="VND",'W1'!$I$60,'W1'!$I$60*EXR) -> 300749800000 | D8: VND | H8: ='W3'!U28 -> 4.12945e+08 | I8: phôi/năm
A9: 1.4 | B9: Tổng dự toán đầu tư máy móc thiết bị (USD) | C9: =IF(Currency="VND",'W1'!$I$60/EXR,'W1'!$I$60) -> 11567300 | D9: USD
A10: 1.5 | B10: Thời gian khấu hao (PP đường thẳng) | C10: ='W1'!G13 -> 12 | D10: Năm | F10: 6 | G10: Sản lượng bán | H10: (tấn)
A11: 1.6 | B11: Tỷ giá | C11: =EXR -> 26000 | F11: 6.1 | G11: Sản lượng bán năm 1 | H11: ='W3'!L27/10^3 -> 3097.0875 | I11: 50.0% Sản lượng sản xuất tối đa
A12: 1.7 | B12: Lạm phát | C12: =Inflation -> 0.05 | F12: 6.2 | G12: Sản lượng bán năm 2 | H12: ='W3'!M27/10^3 -> 4335.9225 | I12: 70.0% Sản lượng sản xuất tối đa
F13: 6.3 | G13: Sản lượng bán năm 3 | H13: ='W3'!N27/10^3 -> 6194.175 | I13: 100.0% Sản lượng sản xuất tối đa
A14: 2 | B14: Nguồn nguyên vật liệu: Vảy sạch từ chai B1 | F14: 6.4 | G14: Từ năm thứ 4 trở đi bằng với năm 3
A15: 2.1 | B15: Đơn giá chai B1 | C15: 16600 | D15: đ/kg
A16: 2.2 | B16: Đơn giá vảy sạch cho dự án | C16: =IF(Currency="VND",'W2'!$M$56,'W2'!$M$56*EXR) -> 24960 | D16: đ/kg | F16: 7 | G16: Giá bán | H16: ='Cover Page'!H14 -> 680 | I16: VND/phôi
C17: =C16/EXR*10^3 -> 960 | D17: USD/tấn | H17: ='Cover Page'!H15 -> 1743.5897 | I17: USD/tấn
B18: Đơn giá vảy sạch tăng | C18: ='Cover Page'!H17 -> 0.02 | D18: /năm | G18: Đơn giá bán tăng | H18: ='Cover Page'!H17 -> 0.02 | I18: /năm
A19: 2.3 | B19: Tỷ lệ hao hụt FtoP | C19: ='W2'!M41 -> 0.07
A20: 2.4 | B20: Liều lượng phụ gia | C20: ='W2'!M60 -> 0.0002
A21: 2.5 | B21: Đơn giá phụ gia | C21: ='W2'!M64 -> 949542 | D21: VND/kg | F21: 8 | G21: Tỷ lệ chiết khấu/cơ cấu vay
F22: 8.1 | G22: Vốn vay | H22: ='Cover Page'!H21 -> 0.7
A23: 3 | B23: Chi phí sản xuất | F23: 8.2 | G23: Vốn tự có | H23: =1-H22 -> 0.3
A24: 3.1 | B24: Nhân công trực tiếp (2 người x 3 ca) | C24: =IF(Currency="VND",'W2'!$M$13,'W2'!$M$13*EXR) -> 982800000 | D24: VND/năm | F24: 8.3 | G24: Lãi vay trung dài hạn | H24: ='Cover Page'!H19 -> 0.07
A25: 3.2 | B25: Nhân viên kỹ thuật, QC, kho | C25: =IF(Currency="VND",'W2'!$M$17,'W2'!$M$17*EXR) -> 5028660000 | D25: VND/năm | F25: 8.4 | G25: Thuế suất thuế TNDN | H25: =Tax_rate -> 0.2
A26: 3.3 | B26: Chi phí điện | C26: ='W2'!M45 -> 765 | D26: kwh | F26: 8.5 | G26: Tỷ lệ chiết khấu = WACC | H26: =Opt1_WACC -> 0.07266
A27: 3.4 | B27: Đơn giá điện | C27: =IF(Currency="VND",'W2'!$M$46,'W2'!$M$46*EXR) -> 1950 | D27: đ/kwh
A28: 3.5 | B28: Chi phí sửa chữa bảo trì (3%*giá trị đầu tư) | C28: =IF(Currency="VND",'W2'!$M$28,'W2'!$M$28*EXR) -> 9022494000 | D28: VND/năm
A29: 3.6 | B29: Chi phí vận hành xe điện | C29: =IF(Currency="VND",'W2'!$M$37,'W2'!$M$37*EXR) -> 552000000 | D29: VND/năm | G29: Dự án chưa tính giá trị đầu tư xưởng (khoảng 150 tỷ đồng ~ 6 triệu USD)
B30: (Số xe thuê: 2 với đơn giá thuê 20 triệu/tháng, chi phí điện 3 triệu/xe/tháng)
A31: 3.7 | B31: Chi phí bao bì | C31: =IF(Currency="VND",'W2'!$M$48,'W2'!$M$48*EXR) -> 314.81481 | D31: đ/kg thành phẩm
A32: 3.8 | B32: Chi phí thuê xưởng (2.000 m2 * 100.000đ/m2/tháng) | C32: =IF(Currency="VND",'W2'!$M$33,'W2'!$M$33*EXR) -> 2400000000 | D32: VND/năm
A33: 3.9 | B33: Chi phí bảo hiểm | C33: ='W2'!L73 -> 0.002 | D33: /tổng tài sản
A34: 3.10 | B34: Chi phí vận chuyển | C34: ='W2'!$M$77 -> 4000000 | D34: VND/chuyến

Sheet W1-Trình bày
A2: STT | B2: HẠNG MỤC | C2: Số lượng | E2: Đơn giá | F2: Giá trị đầu tư | G2: Giá trị đầu tư | M2: Thời gian khấu hao | N2: Khấu hao
C3: (cái,m2) | E3: (VND) | F3: (VND) | G3: (USD) | M3: (Năm) | N3: (VND/năm)
A5: 1 | B5: MÁY MÓC THIẾT BỊ | F5: 284499800000 | G5: =F5/26000 -> 10942300 | N5: 2.3708317e+10
A7: 1.1 | B7: Máy móc thiết bị chính | F7: 2.46389e+11 | G7: =F7/26000 -> 9476500 | N7: 2.0532417e+10
A8: 1.1.01 | B8: NGR : LSP 1200 | C8: 1 | E8: 128180000000 | F8: 128180000000 | G8: =F8/26000 -> 4930000 | M8: 12 | N8: 1.0681667e+10
A9: 1.1.02 | B9: HyPET400 HPP5e rMtP P120/120 | C9: 1 | E9: 6.727793e+10 | F9: 6.727793e+10 | G9: =F9/26000 -> 2587612.7 | M9: 12 | N9: 5.6064942e+09
A10: 1.1.03 | B10: Khuôn 15g PCO 1881 128 cavtiy | C10: 1 | E10: 3.932207e+10 | F10: 3.932207e+10 | G10: =F10/26000 -> 1512387.3 | M10: 12 | N10: 3.2768391e+09
A11: 1.1.04 | B11: Chi phí vận chuyển | C11: 1 | E11: 2600000000 | F11: 2600000000 | G11: =F11/26000 -> 100000 | M11: 12 | N11: 2.1666667e+08
A12: 1.1.05 | B12: Chi phí lắp đặt | C12: 1 | E12: 8580000000 | F12: 8580000000 | G12: =F12/26000 -> 330000 | M12: 12 | N12: 715000000
A13: 1.1.06 | B13: Thuế nhà thầu | C13: 1 | E13: 429000000 | F13: 429000000 | G13: =F13/26000 -> 16500 | M13: 12 | N13: 35750000
A15: 1.2 | B15: Máy móc thiết bị phụ | F15: 38110800000 | G15: =F15/26000 -> 1465800 | N15: 3175900000
A16: 1.2.06 | B16: Hệ thống nước, khí nén | C16: 1 | E16: 7800000000 | F16: 7800000000 | G16: =F16/26000 -> 300000 | M16: 12 | N16: 650000000
A17: 1.2.07 | B17: Hệ thống điện | C17: 1 | E17: 7800000000 | F17: 7800000000 | G17: =F17/26000 -> 300000 | M17: 12 | N17: 650000000
A18: 1.2.08 | B18: Pump system | C18: 1 | E18: 3900000000 | F18: 3900000000 | G18: =F18/26000 -> 150000 | M18: 12 | N18: 325000000
A19: 1.2.09 | B19: Camera online check | C19: 1 | E19: 3250000000 | F19: 3250000000 | G19: =F19/26000 -> 125000 | M19: 12 | N19: 2.7083333e+08
A20: 1.2.10 | B20: Chiller | C20: 1 | E20: 2600000000 | F20: 2600000000 | G20: =F20/26000 -> 100000 | M20: 12 | N20: 2.1666667e+08
A21: 1.2.11 | B21: Trạm điện | C21: 1 | E21: 2600000000 | F21: 2600000000 | G21: =F21/26000 -> 100000 | M21: 12 | N21: 2.1666667e+08
A22: 1.2.12 | B22: Overhead crane | C22: 1 | E22: 2600000000 | F22: 2600000000 | G22: =F22/26000 -> 100000 | M22: 12 | N22: 2.1666667e+08
A23: 1.2.13 | B23: Hệ thống điện dự phòng | C23: 1 | E23: 2080000000 | F23: 2080000000 | G23: =F23/26000 -> 80000 | M23: 12 | N23: 1.7333333e+08
A24: 1.2.14 | B24: Hệ thống IT | C24: 1 | E24: 2080000000 | F24: 2080000000 | G24: =F24/26000 -> 80000 | M24: 12 | N24: 1.7333333e+08
A25: 1.2.15 | B25: Lock unloading preform | C25: 1 | E25: 1352000000 | F25: 1352000000 | G25: =F25/26000 -> 52000 | M25: 12 | N25: 1.1266667e+08
A26: 1.2.16 | B26: Máy nén khí | C26: 1 | E26: 1248000000 | F26: 1248000000 | G26: =F26/26000 -> 48000 | M26: 12 | N26: 104000000
A27: 1.2.17 | B27: Cooling tower | C27: 1 | E27: 780000000 | F27: 780000000 | G27: =F27/26000 -> 30000 | M27: 12 | N27: 65000000
A28: 1.2.18 | B28: Máy scan | C28: 1 | E28: 20800000 | F28: 20800000 | G28: =F28/26000 -> 800 | M28: 12 | N28: 1733333.3
B30: CHI PHÍ XÂY DỰNG XƯỞNG SẢN XUẤT | C30: 2000 | F30: 0 | N30: 0
B31: Xưởng sản xuất | C31: 1900 | E31: 75000000 | F31: 0 | M31: 25 | N31: 0
B32: Phòng QC | C32: 100 | E32: 75000000 | F32: 0 | M32: 25 | N32: 0
A34: 2. | B34: MÁY MÓC THIẾT BỊ PHÒNG LAB | F34: 16250000000 | G34: =F34/26000 -> 625000 | N34: 1.3541667e+09
A35: 2.01 | B35: Máy đo IV PSL IV 4603 | C35: 1 | E35: 5200000000 | F35: 5200000000 | G35: =F35/26000 -> 200000 | M35: 12 | N35: 4.3333333e+08
A36: 2.02 | B36: Máy đo kích thước tự động Gawis 4D | C36: 1 | E36: 5200000000 | F36: 5200000000 | G36: =F36/26000 -> 200000 | M36: 12 | N36: 4.3333333e+08
A37: 2.03 | B37: Máy đo AA Piovan Inspecta | C37: 1 | E37: 3042000000 | F37: 3042000000 | G37: =F37/26000 -> 117000 | M37: 12 | N37: 253500000
A38: 2.04 | B38: Colorimeter/Spectrophotometer | C38: 1 | E38: 650000000 | F38: 650000000 | G38: =F38/26000 -> 25000 | M38: 12 | N38: 54166667
A39: 2.05 | B39: Melt Flow Index Tester | C39: 1 | E39: 442000000 | F39: 442000000 | G39: =F39/26000 -> 17000 | M39: 12 | N39: 36833333
A40: 2.06 | B40: Light Polarizer | C40: 1 | E40: 260000000 | F40: 260000000 | G40: =F40/26000 -> 10000 | M40: 12 | N40: 21666667
A41: 2.07 | B41: Moisture analyzer | C41: 1 | E41: 143000000 | F41: 143000000 | G41: =F41/26000 -> 5500 | M41: 12 | N41: 11916667
A42: 2.08 | B42: Perpendicular Prefrom Thickness Gauge | C42: 1 | E42: 130000000 | F42: 130000000 | G42: =F42/26000 -> 5000 | M42: 12 | N42: 10833333
A43: 2.09 | B43: Calipers with data output | C43: 1 | E43: 130000000 | F43: 130000000 | G43: =F43/26000 -> 5000 | M43: 12 | N43: 10833333
A44: 2.10 | B44: Radius gauges | C44: 1 | E44: 130000000 | F44: 130000000 | G44: =F44/26000 -> 5000 | M44: 12 | N44: 10833333
A45: 2.11 | B45: Torque tester | C45: 1 | E45: 130000000 | F45: 130000000 | G45: =F45/26000 -> 5000 | M45: 12 | N45: 10833333
A46: 2.12 | B46: Pitch gauges | C46: 1 | E46: 130000000 | F46: 130000000 | G46: =F46/26000 -> 5000 | M46: 12 | N46: 10833333
... A53: 2.19 | B53: Black Ligth/UV light | C53: 1 | E53: 26000000 | F53: 26000000 | G53: =F53/26000 -> 1000 | M53: 12 | N53: 2166666.7
A55: TỔNG ĐẦU TƯ BAN ĐẦU | F55: 300749800000 | G55: =F55/26000 -> 11567300 | N55: 2.5062483e+10
A59: STT | B59: HẠNG MỤC | C59: Số lượng | E59: Đơn giá | F59: Giá trị đầu tư | G59: Giá trị đầu tư
C60: (cái,m2) | E60: (VND) | F60: (VND) | G60: (USD)
A61: 2. | B61: MÁY MÓC THIẾT BỊ PHÒNG LAB | F61: 16250000000 | G61: 625000
A62: 2.01 | B62: Máy đo IV PSL IV 4603 | C62: 1 | E62: 5200000000 | F62: 5200000000 | G62: 200000
A63: 2.02 | B63: Máy đo kích thước tự động Gawis 4D | C63: 1 | E63: 5200000000 | F63: 5200000000 | G63: 200000
A64: 2.03 | B64: Máy đo AA Piovan Inspecta | C64: 1 | E64: 3042000000 | F64: 3042000000 | G64: 117000
A65: 2.04 | B65: Colorimeter/Spectrophotometer | C65: 1 | E65: 650000000 | F65: 650000000 | G65: 25000
A66: 2.05 | B66: Melt Flow Index Tester | C66: 1 | E66: 442000000 | F66: 442000000 | G66: 17000
A67: 2.06 | B67: Light Polarizer | C67: 1 | E67: 260000000 | F67: 260000000 | G67: 10000
A68: 2.07 | B68: Moisture analyzer | C68: 1 | E68: 143000000 | F68: 143000000 | G68: 5500
A69: 2.08 | B69: Perpendicular Prefrom Thickness Gauge | C69: 1 | E69: 130000000 | F69: 130000000 | G69: 5000
A70: 2.09 | B70: Calipers with data output | C70: 1 | E70: 130000000 | F70: 130000000 | G70: 5000
A71: 2.10 | B71: Radius gauges | C71: 1 | E71: 130000000 | F71: 130000000 | G71: 5000
A72: 2.11 | B72: Torque tester | C72: 1 | E72: 130000000 | F72: 130000000 | G72: 5000
A73: 2.12 | B73: Pitch gauges | C73: 1 | E73: 130000000 | F73: 130000000 | G73: 5000
... A80: 2.19 | B80: Black Ligth/UV light | C80: 1 | E80: 26000000 | F80: 26000000 | G80: 1000

Sheet USD.Tấn
A3: No. | B3: SAP | C3: Chi phí Cost Items | D3: Chi phí USD/tấn | E3: Cơ cấu % chi phí /Giá
A4: A | B4: 1521 | C4: Chi phí nguyên vật liệu | D4: 979.2 | E4: 0.5616
C5: Vảy sạch | D5: 979.2 | E5: 0.5616
A6: B | B6: 1522 | C6: Hao hụt về tiền | D6: 73.703226 | E6: 0.042270968
A7: C | C7: Chi phí biến đổi | D7: 506.99204 | E7: 0.29077485
A8: 1 | B8: LAB | C8: Chi phí nhân công | D8: 39.193355 | E8: 0.022478542
A9: 2 | B9: DEP | C9: Khấu hao | D9: 155.62067 | E9: 0.089253032
A10: 3 | B10: OTH | C10: Chi phí quản lý | D10: 83.967246 | E10: 0.048157685
A11: 4 | B11: ELEC | C11: Chi phí gián tiếp | D11: 132.27565 | E11: 0.075863976
A12: 5 | B12: QLC | C12: Điện | D12: 74.974798 | E12: 0.043000252
A13: 6 | B13: BAG | C13: Đóng gói | D13: 12.713675 | E13: 0.0072916667
A14: 7 | B14: CHE | C14: Hóa chất | D14: 8.2466427 | E14: 0.0047296921
A15: 8 | B15: H2O | C15: Nước | D15: 0 | E15: 0
A16: 9 | C16: Giá thành | D16: 1559.8953 | E16: 0.89464581
A17: 10 | B17: TAX | C17: Thuế thu nhập | D17: 36.738896 | E17: 0.021070837
A18: D | B18: LN | C18: Lợi nhuận | D18: 146.95558 | E18: 0.084283349
A19: A+B+C+D | C19: Giá bán | D19: 1743.5897 | E19: 1
C20: % Lãi gộp nguyên liệu/Giá bán | E20: 0.4384

Sheet VND.Phôi
A3: No. | B3: SAP | C3: Chi phí Cost Items | D3: Chi phí VNĐ / Phôi | E3: Cơ cấu % chi phí /Giá
A4: A | B4: 1521 | C4: Chi phí nguyên vật liệu | D4: 381.888 | E4: 0.5616
C5: Vảy sạch | D5: 381.888 | E5: 0.5616
A6: B | B6: 1522 | C6: Hao hụt về tiền | D6: 28.744258 | E6: 0.042270968
A7: C | C7: Chi phí biến đổi | D7: 197.7269 | E7: 0.29077485
A8: 1 | B8: LAB | C8: Chi phí nhân công | D8: 15.285409 | E8: 0.022478542
A9: 2 | B9: DEP | C9: Khấu hao | D9: 60.692062 | E9: 0.089253032
A10: 3 | B10: QLC | C10: Chi phí quản lý | D10: 32.747226 | E10: 0.048157685
A11: 4 | B11: OTH | C11: Chi phí gián tiếp | D11: 51.587504 | E11: 0.075863976
A12: 5 | B12: ELEC | C12: Điện | D12: 29.240171 | E12: 0.043000252
A13: 6 | B13: BAG | C13: Đóng gói | D13: 4.9583333 | E13: 0.0072916667
A14: 7 | B14: CHE | C14: Hóa chất | D14: 3.2161906 | E14: 0.0047296921
A15: 8 | B15: H2O | C15: Nước | D15: 0 | E15: 0
A16: 9 | C16: Giá thành | D16: 608.35915 | E16: 0.89464581
A17: 10 | B17: TAX | C17: Thuế thu nhập | D17: 14.328169 | E17: 0.021070837
A18: D | B18: LN | C18: Lợi nhuận | D18: 57.312677 | E18: 0.084283349
A19: A+B+C+D | C19: Giá bán | D19: 680 | E19: 1
C20: % Lãi gộp nguyên liệu/Giá bán | E20: 0.4384

Sheet Sheet3
B2: STT | C2: Hạng mục | D2: Đvt | E2: 2026 | F2: 2027 | G2: 2028 | H2: 2029 | I2: 2030 | J2: 2031 | K2: 2032 | L2: 2033 | M2: 2034 | N2: 2035 | O2: 2036 | P2: 2037 | Q2: 2038 | R2: 2039 | S2: 2040 | T2: 2041
B4: =IF(C4<>"",SUBTOTAL(3,C$4:C4),"") -> 1 | C4: SỐ LƯỢNG SẢN XUẤT/BÁN
B5: =IF(C5<>"",SUBTOTAL(3,C$4:C5),"") -> 2 | C5: Sản lượng công suất máy | D5: kg/năm | F5: 7568640 | G5: 7568640 | H5: 7568640 | I5: 7568640 | J5: 7568640 | K5: 7568640 | L5: 7568640 | M5: 7568640 | N5: 7568640 | O5: 7568640 | P5: 7568640 | Q5: 7568640 | R5: 7568640 | S5: 7568640 | T5: 7568640
B6: =IF(C6<>"",SUBTOTAL(3,C$4:C6),"") -> 3 | C6: Sản lượng công suất máy | D6: phôi/năm | F6: 7568640 | G6: 7568640 | H6: 7568640 | I6: 7568640 | J6: 7568640 | K6: 7568640 | L6: 7568640 | M6: 7568640 | N6: 7568640 | O6: 7568640 | P6: 7568640 | Q6: 7568640 | R6: 7568640 | S6: 7568640 | T6: 7568640
B7: =IF(C7<>"",SUBTOTAL(3,C$4:C7),"") -> 4 | C7: Hiệu suất sử dụng tối đa | F7: 0.88 | G7: 0.88 | H7: 0.88 | I7: 0.88 | J7: 0.88 | K7: 0.88 | L7: 0.88 | M7: 0.88 | N7: 0.88 | O7: 0.88 | P7: 0.88 | Q7: 0.88 | R7: 0.88 | S7: 0.88 | T7: 0.88
B8: =IF(C8<>"",SUBTOTAL(3,C$4:C8),"") -> 5 | C8: Hệ số điều chỉnh sản xuất | F8: 0.5 | G8: 0.7 | H8: 1 | I8: 1 | J8: 1 | K8: 1 | L8: 1 | M8: 1 | N8: 1 | O8: 1 | P8: 1 | Q8: 1 | R8: 1 | S8: 1 | T8: 1
B9: =IF(C9<>"",SUBTOTAL(3,C$4:C9),"") -> 6 | C9: Tỷ lệ hao hụt | F9: 0.07 | G9: 0.07 | H9: 0.07 | I9: 0.07 | J9: 0.07 | K9: 0.07 | L9: 0.07 | M9: 0.07 | N9: 0.07 | O9: 0.07 | P9: 0.07 | Q9: 0.07 | R9: 0.07 | S9: 0.07 | T9: 0.07
B10: =IF(C10<>"",SUBTOTAL(3,C$4:C10),"") -> 7 | C10: Số ngày hoạt động | F10: 160.6 | G10: 224.84 | H10: 321.2 | I10: 321.2 | J10: 321.2 | K10: 321.2 | L10: 321.2 | M10: 321.2 | N10: 321.2 | O10: 321.2 | P10: 321.2 | Q10: 321.2 | R10: 321.2 | S10: 321.2 | T10: 321.2
B11: =IF(C11<>"",SUBTOTAL(3,C$4:C11),"") -> 8 | C11: Sản lượng sản xuất | D11: kg/năm | F11: 3097087.5 | G11: 4335922.5 | H11: 6194175 | I11: 6194175 | J11: 6194175 | K11: 6194175 | L11: 6194175 | M11: 6194175 | N11: 6194175 | O11: 6194175 | P11: 6194175 | Q11: 6194175 | R11: 6194175 | S11: 6194175 | T11: 6194175
B12: =IF(C12<>"",SUBTOTAL(3,C$4:C12),"") -> 9 | C12: Sản lượng sản xuất | D12: phôi/năm | F12: 2.064725e+08 | G12: 2.890615e+08 | H12: 4.12945e+08 | I12: 4.12945e+08 | J12: 4.12945e+08 | K12: 4.12945e+08 | L12: 4.12945e+08 | M12: 4.12945e+08 | N12: 4.12945e+08 | O12: 4.12945e+08 | P12: 4.12945e+08 | Q12: 4.12945e+08 | R12: 4.12945e+08 | S12: 4.12945e+08 | T12: 4.12945e+08
B13: =IF(C13<>"",SUBTOTAL(3,C$4:C13),"")
B14: =IF(C14<>"",SUBTOTAL(3,C$4:C14),"") -> 10 | C14: DOANH THU | D14: tr. VND | F14: 140401.3 | G14: 200493.06 | H14: 292147.02 | I14: 297989.96 | J14: 303949.76 | K14: 310028.76 | L14: 316229.33 | M14: 322553.92 | N14: 329005 | O14: 335585.1 | P14: 342296.8 | Q14: 349142.74 | R14: 356125.59 | S14: 363248.1 | T14: 370513.07
B15: =IF(C15<>"",SUBTOTAL(3,C$4:C15),"")
B16: =IF(C16<>"",SUBTOTAL(3,C$4:C16),"") -> 11 | C16: Định phí sản xuất | D16: tr. VND | E16: 0 | F16: -43649.937 | G16: -43649.937 | H16: -44549.235 | I16: -45493.497 | J16: -46484.973 | K16: -47526.022 | L16: -48619.124 | M16: -49766.881 | N16: -50972.026 | O16: -52237.429 | P16: -53566.101 | Q16: -54961.207 | R16: -31363.585 | S16: -32901.689 | T16: -34516.698
B17: =IF(C17<>"",SUBTOTAL(3,C$4:C17),"") -> 12 | C17: Khấu hao | D17: tr. VND | F17: -25062.483 | G17: -25062.483 | H17: -25062.483 | I17: -25062.483 | J17: -25062.483 | K17: -25062.483 | L17: -25062.483 | M17: -25062.483 | N17: -25062.483 | O17: -25062.483 | P17: -25062.483 | Q17: -25062.483 | R17: 0 | S17: 0 | T17: 0
B18: =IF(C18<>"",SUBTOTAL(3,C$4:C18),"") -> 13 | C18: Lương | D18: tr. VND | E18: 0 | F18: -6011.46 | G18: -6011.46 | H18: -6312.033 | I18: -6627.6346 | J18: -6959.0164 | K18: -7306.9672 | L18: -7672.3156 | M18: -8055.9313 | N18: -8458.7279 | O18: -8881.6643 | P18: -9325.7475 | Q18: -9792.0349 | R18: -10281.637 | S18: -10795.718 | T18: -11335.504
B19: =IF(C19<>"",SUBTOTAL(3,C$4:C19),"") -> 14 | C19: - Nhân công trực tiếp | D19: tr. VND | F19: -982.8 | G19: -982.8 | H19: -1031.94 | I19: -1083.537 | J19: -1137.7139 | K19: -1194.5995 | L19: -1254.3295 | M19: -1317.046 | N19: -1382.8983 | O19: -1452.0432 | P19: -1524.6454 | Q19: -1600.8776 | R19: -1680.9215 | S19: -1764.9676 | T19: -1853.216
B20: =IF(C20<>"",SUBTOTAL(3,C$4:C20),"") -> 15 | C20: - Nhân công gián tiếp | D20: tr. VND | F20: -5028.66 | G20: -5028.66 | H20: -5280.093 | I20: -5544.0976 | J20: -5821.3025 | K20: -6112.3677 | L20: -6417.986 | M20: -6738.8853 | N20: -7075.8296 | O20: -7429.6211 | P20: -7801.1021 | Q20: -8191.1573 | R20: -8600.7151 | S20: -9030.7509 | T20: -9482.2884
B21: =IF(C21<>"",SUBTOTAL(3,C$4:C21),"") -> 16 | C21: Thuê kho,xưởng | D21: tr. VND | F21: -2400 | G21: -2400 | H21: -2520 | I21: -2646 | J21: -2778.3 | K21: -2917.215 | L21: -3063.0758 | M21: -3216.2295 | N21: -3377.041 | O21: -3545.8931 | P21: -3723.1877 | Q21: -3909.3471 | R21: -4104.8145 | S21: -4310.0552 | T21: -4525.5579
B22: =IF(C22<>"",SUBTOTAL(3,C$4:C22),"") -> 17 | C22: Bảo trì | D22: tr. VND | F22: -9022.494 | G22: -9022.494 | H22: -9473.6187 | I22: -9947.2996 | J22: -10444.665 | K22: -10966.898 | L22: -11515.243 | M22: -12091.005 | N22: -12695.555 | O22: -13330.333 | P22: -13996.85 | Q22: -14696.692 | R22: -15431.527 | S22: -16203.103 | T22: -17013.258
B23: =IF(C23<>"",SUBTOTAL(3,C$4:C23),"") -> 18 | C23: Vận hành xe điện | D23: tr. VND | F23: -552 | G23: -552 | H23: -579.6 | I23: -608.58 | J23: -639.009 | K23: -670.95945 | L23: -704.50742 | M23: -739.73279 | N23: -776.71943 | O23: -815.5554 | P23: -856.33318 | Q23: -899.14983 | R23: -944.10733 | S23: -991.31269 | T23: -1040.8783
B24: =IF(C24<>"",SUBTOTAL(3,C$4:C24),"") -> 19 | C24: Bảo hiểm tài sản | D24: tr. VND | F24: -601.4996 | G24: -601.4996 | H24: -601.4996 | I24: -601.4996 | J24: -601.4996 | K24: -601.4996 | L24: -601.4996 | M24: -601.4996 | N24: -601.4996 | O24: -601.4996 | P24: -601.4996 | Q24: -601.4996 | R24: -601.4996 | S24: -601.4996 | T24: -601.4996
B25: =IF(C25<>"",SUBTOTAL(3,C$4:C25),"")
B26: =IF(C26<>"",SUBTOTAL(3,C$4:C26),"") -> 20 | C26: Biến phí sản xuất | D26: tr. VND | E26: 0 | F26: -92494.065 | G26: -128793.29 | H26: -187365.6 | I26: -191595.5 | J26: -195935.15 | K26: -200388 | L26: -204957.65 | M26: -209647.81 | N26: -214462.35 | O26: -219405.29 | P26: -224480.8 | Q26: -229693.22 | R26: -234044.55 | S26: -239544.48 | T26: -245195.38
B27: =IF(C27<>"",SUBTOTAL(3,C$4:C27),"") -> 21 | C27: Nguyên vật liệu | D27: tr. VND | E27: 0 | F27: -83121.832 | G27: -116370.56 | H27: -169568.54 | I27: -172959.91 | J27: -176419.11 | K27: -179947.49 | L27: -183546.44 | M27: -187217.37 | N27: -190961.71 | O27: -194780.95 | P27: -198676.57 | Q27: -202650.1 | R27: -206703.1 | S27: -210837.16 | T27: -215053.91
B28: =IF(C28<>"",SUBTOTAL(3,C$4:C28),"") -> 22 | C28: Vảy sạch | D28: tr. VND | F28: -77303.304 | G28: -108224.63 | H28: -157698.74 | I28: -160852.71 | J28: -164069.77 | K28: -167351.16 | L28: -170698.19 | M28: -174112.15 | N28: -177594.39 | O28: -181146.28 | P28: -184769.21 | Q28: -188464.59 | R28: -192233.88 | S28: -196078.56 | T28: -200000.13
B29: =IF(C29<>"",SUBTOTAL(3,C$4:C29),"") -> 23 | C29: Hao hụt | D29: tr. VND | F29: -5818.5282 | G29: -8145.9395 | H29: -11869.798 | I29: -12107.194 | J29: -12349.337 | K29: -12596.324 | L29: -12848.251 | M29: -13105.216 | N29: -13367.32 | O29: -13634.666 | P29: -13907.36 | Q29: -14185.507 | R29: -14469.217 | S29: -14758.601 | T29: -15053.773
B30: =IF(C30<>"",SUBTOTAL(3,C$4:C30),"") -> 24 | C30: Màu, phụ gia | D30: tr. VND | E30: 0 | F30: -632.43326 | G30: -885.40656 | H30: -1328.1098 | I30: -1394.5153 | J30: -1464.2411 | K30: -1537.4532 | L30: -1614.3258 | M30: -1695.0421 | N30: -1779.7942 | O30: -1868.7839 | P30: -1962.2231 | Q30: -2060.3343 | R30: -2163.351 | S30: -2271.5185 | T30: -2385.0945
B31: =IF(C31<>"",SUBTOTAL(3,C$4:C31),"") -> 25 | C31: Màu Toner AY090 | D31: tr. VND | F31: -632.43326 | G31: -885.40656 | H31: -1328.1098 | I31: -1394.5153 | J31: -1464.2411 | K31: -1537.4532 | L31: -1614.3258 | M31: -1695.0421 | N31: -1779.7942 | O31: -1868.7839 | P31: -1962.2231 | Q31: -2060.3343 | R31: -2163.351 | S31: -2271.5185 | T31: -2385.0945
B32: =IF(C32<>"",SUBTOTAL(3,C$4:C32),"") -> 26 | C32: Phụ gia AA Scavenger | D32: tr. VND | F32: 0 | G32: 0 | H32: 0 | I32: 0 | J32: 0 | K32: 0 | L32: 0 | M32: 0 | N32: 0 | O32: 0 | P32: 0 | Q32: 0 | R32: 0 | S32: 0 | T32: 0
B33: =IF(C33<>"",SUBTOTAL(3,C$4:C33),"") -> 27 | C33: Chi phí tạo phôi | D33: tr. VND | E33: 0 | F33: -8739.8001 | G33: -11537.321 | H33: -16468.955 | I33: -17241.075 | J33: -18051.8 | K33: -18903.063 | L33: -19796.888 | M33: -20735.404 | N33: -21720.846 | O33: -22755.561 | P33: -23842.011 | Q33: -24982.783 | R33: -25178.095 | S33: -26435.797 | T33: -27756.384
B34: =IF(C34<>"",SUBTOTAL(3,C$4:C34),"") -> 28 | C34: Chi phí điện | D34: tr. VND | F34: -5749.8012 | G34: -8049.7217 | H34: -12074.583 | I34: -12678.312 | J34: -13312.227 | K34: -13977.839 | L34: -14676.731 | M34: -15410.567 | N34: -16181.095 | O34: -16990.15 | P34: -17839.658 | Q34: -18731.641 | R34: -19668.223 | S34: -20651.634 | T34: -21684.215
B35: =IF(C35<>"",SUBTOTAL(3,C$4:C35),"") -> 29 | C35: Chi phí đóng bao bì | D35: tr. VND | F35: -975.00902 | G35: -1365.0126 | H35: -2047.519 | I35: -2149.8949 | J35: -2257.3896 | K35: -2370.2591 | L35: -2488.7721 | M35: -2613.2107 | N35: -2743.8712 | O35: -2881.0648 | P35: -3025.118 | Q35: -3176.3739 | R35: -3335.1926 | S35: -3501.9522 | T35: -3677.0499
B36: =IF(C36<>"",SUBTOTAL(3,C$4:C36),"") -> 30 | C36: Chi phí bằng tiền khác | D36: tr. VND | F36: -2014.9899 | G36: -2122.5868 | H36: -2346.8534 | I36: -2412.8682 | J36: -2482.1836 | K36: -2554.9648 | L36: -2631.3851 | M36: -2711.6264 | N36: -2795.8797 | O36: -2884.3457 | P36: -2977.2351 | Q36: -3074.7688 | R36: -2174.68 | S36: -2282.211 | T36: -2395.1185
B37: =IF(C37<>"",SUBTOTAL(3,C$4:C37),"")
B38: =IF(C38<>"",SUBTOTAL(3,C$4:C38),"") -> 31 | C38: TỔNG CHI PHÍ SẢN XUẤT | D38: tr. VND | E38: 0 | F38: -136144 | G38: -172443.23 | H38: -231914.84 | I38: -237089 | J38: -242420.12 | K38: -247914.03 | L38: -253576.78 | M38: -259414.69 | N38: -265434.38 | O38: -271642.72 | P38: -278046.9 | Q38: -284654.42 | R38: -265408.13 | S38: -272446.17 | T38: -279712.08
B39: =IF(C39<>"",SUBTOTAL(3,C$4:C39),"")
B40: =IF(C40<>"",SUBTOTAL(3,C$4:C40),"") -> 32 | C40: Chi phí vận chuyển | D40: tr. VND | F40: -2752.9667 | G40: -3854.1533 | H40: -5781.23 | I40: -6070.2915 | J40: -6373.8061 | K40: -6692.4964 | L40: -7027.1212 | M40: -7378.4772 | N40: -7747.4011 | O40: -8134.7711 | P40: -8541.5097 | Q40: -8968.5852 | R40: -9417.0144 | S40: -9887.8652 | T40: -10382.258
B41: =IF(C41<>"",SUBTOTAL(3,C$4:C41),"") -> 33 | C41: Chi phí nhân sự BH,QLDN | D41: tr. VND | F41: 0 | G41: 0 | H41: 0 | I41: 0 | J41: 0 | K41: 0 | L41: 0 | M41: 0 | N41: 0 | O41: 0 | P41: 0 | Q41: 0 | R41: 0 | S41: 0 | T41: 0
B42: =IF(C42<>"",SUBTOTAL(3,C$4:C42),"") -> 34 | C42: Chi phí quản lý chung | D42: tr. VND | F42: 0 | G42: 0 | H42: 0 | I42: 0 | J42: 0 | K42: 0 | L42: 0 | M42: 0 | N42: 0 | O42: 0 | P42: 0 | Q42: 0 | R42: 0 | S42: 0 | T42: 0
B43: =IF(C43<>"",SUBTOTAL(3,C$4:C43),"") -> 35 | C43: Chi phí lãi vay | D43: tr. VND | F43: -14736.74 | G43: -14150.297 | H43: -13522.803 | I43: -12851.384 | J43: -12132.967 | K43: -11364.259 | L43: -10541.743 | M43: -9661.6497 | N43: -8719.9503 | O43: -7712.332 | P43: -6634.1804 | Q43: -5480.5581 | R43: -4246.1824 | S43: -2925.4003 | T43: -1512.1634
B44: =IF(C44<>"",SUBTOTAL(3,C$4:C44),"")
B45: =IF(C45<>"",SUBTOTAL(3,C$4:C45),"") -> 36 | C45: TỔNG CHI PHÍ | D45: tr. VND | E45: 0 | F45: -153633.71 | G45: -190447.68 | H45: -251218.87 | I45: -256010.67 | J45: -260926.89 | K45: -265970.78 | L45: -271145.64 | M45: -276454.82 | N45: -281901.73 | O45: -287489.82 | P45: -293222.59 | Q45: -299103.57 | R45: -279071.33 | S45: -285259.43 | T45: -291606.5
B46: =IF(C46<>"",SUBTOTAL(3,C$4:C46),"")
B47: =IF(C47<>"",SUBTOTAL(3,C$4:C47),"") -> 37 | C47: LNTT | D47: tr. VND | F47: -13232.41 | G47: 10045.376 | H47: 40928.154 | I47: 41979.293 | J47: 43022.871 | K47: 44057.977 | L47: 45083.695 | M47: 46099.099 | N47: 47103.267 | O47: 48095.275 | P47: 49074.209 | Q47: 50039.171 | R47: 77054.264 | S47: 77988.671 | T47: 78906.562
B48: =IF(C48<>"",SUBTOTAL(3,C$4:C48),"") -> 38 | C48: %LNTT | F48: -0.09424706 | G48: 0.05010336 | H48: 0.14009437 | I48: 0.14087486 | J48: 0.14154599 | K48: 0.14210932 | L48: 0.14256645 | M48: 0.14291905 | N48: 0.14316885 | O48: 0.14331767 | P48: 0.14336742 | Q48: 0.1433201 | R48: 0.21636823 | S48: 0.21469808 | T48: 0.21296567
B49: =IF(C49<>"",SUBTOTAL(3,C$4:C49),"") -> 39 | C49: LNST | D49: tr. VND | F49: -10585.928 | G49: 8036.3006 | H49: 32742.523 | I49: 33583.435 | J49: 34418.296 | K49: 35246.382 | L49: 36066.956 | M49: 36879.28 | N49: 37682.613 | O49: 38476.22 | P49: 39259.367 | Q49: 40031.337 | R49: 61643.411 | S49: 62390.937 | T49: 63125.249
B50: =IF(C50<>"",SUBTOTAL(3,C$4:C50),"") -> 40 | C50: %LNST | F50: -0.075397648 | G50: 0.040082688 | H50: 0.1120755 | I50: 0.11269988 | J50: 0.11323679 | K50: 0.11368746 | L50: 0.11405316 | M50: 0.11433524 | N50: 0.11453508 | O50: 0.11465414 | P50: 0.11469394 | Q50: 0.11465608 | R50: 0.17309458 | S50: 0.17175847 | T50: 0.17037253

Sheet Sheet4
A3: Năm | B3: Dòng tiền | C3: Dòng tiền chiết khấu | D3: Dòng tiền chiết khấu Lũy kế
A4: 2026 | B4: {=TRANSPOSE('W3'!K168:AJ168)} -> -300749.8 | C4: {=TRANSPOSE('W3'!K170:AJ170)} -> -300749.8 | D4: =SUM(C$4:C4) -> -300749.8
A5: =A4+1 -> 2027 | B5: 26265.948 | C5: 24486.741 | D5: =SUM(C$4:C5) -> -276263.06
A6: =A5+1 -> 2028 | B6: 44419.022 | C6: 38605.112 | D6: =SUM(C$4:C6) -> -237657.95
A7: =A6+1 -> 2029 | B7: 68623.249 | C7: 55601.309 | D7: =SUM(C$4:C7) -> -182056.64
A8: =A7+1 -> 2030 | B8: 68927.026 | C8: 52064.439 | D8: =SUM(C$4:C8) -> -129992.2
A9: =A8+1 -> 2031 | B9: 69187.153 | C9: 48720.87 | D9: =SUM(C$4:C9) -> -81271.329
A10: =A9+1 -> 2032 | B10: 69400.272 | C10: 45560.519 | D10: =SUM(C$4:C10) -> -35710.81
A11: =A10+1 -> 2033 | B11: 69562.833 | C11: 42573.824 | D11: =SUM(C$4:C11) -> 6863.014
A12: =A11+1 -> 2034 | B12: 69671.083 | C12: 39751.715 | D12: =SUM(C$4:C12) -> 46614.729
A13: =A12+1 -> 2035 | B13: 69721.057 | C13: 37085.59 | D13: =SUM(C$4:C13) -> 83700.319
A14: =A13+1 -> 2036 | B14: 69708.569 | C14: 34567.288 | D14: =SUM(C$4:C14) -> 118267.61
A15: =A14+1 -> 2037 | B15: 69629.195 | C15: 32189.07 | D15: =SUM(C$4:C15) -> 150456.68
A16: =A15+1 -> 2038 | B16: 69478.267 | C16: 29943.595 | D16: =SUM(C$4:C16) -> 180400.27
... A29: =A28+1 -> 2051 | B29: 0 | C29: 0 | D29: =SUM(C$4:C29) -> 253244.22

Sheet Sheet2
A3: STT | B3: CHỈ TIÊU | C3: Đvt | E3: KẾ TOÁN ĐỀ XUẤT 680 VND/PHÔI | H3: GIÁ TRUNG BÌNH 650 VND/PHÔI | K3: THEO GIÁ SUNTORY YÊU CẦU 610 VND/phôi
E4: KHÔNG TÍNH ĐẦU TƯ XƯỞNG | F4: CÓ TÍNH ĐẦU TƯ XƯỞNG | H4: KHÔNG TÍNH ĐẦU TƯ XƯỞNG | I4: CÓ TÍNH ĐẦU TƯ XƯỞNG | K4: KHÔNG TÍNH ĐẦU TƯ XƯỞNG | L4: CÓ TÍNH ĐẦU TƯ XƯỞNG
A6: 1 | B6: Đơn giá bán phôi | C6: USD/tấn | E6: 1743.5897 | F6: 1743.5897 | H6: 1666.6667 | I6: 1666.6667 | K6: 1564.1026 | L6: 1564.1026
A7: 2 | B7: Đơn giá bán phôi | C7: VND/phôi | E7: 680 | F7: 680 | H7: 650 | I7: 650 | K7: 610 | L7: 610
A8: 3 | B8: Giá thành phôi | C8: USD/tấn | E8: 1559.8953 | F8: 1642.4576 | H8: 1559.8953 | I8: 1642.4576 | K8: 1559.8953 | L8: 1642.4576
A9: 4 | B9: Giá thành phôi | C9: VND/phôi | E9: 608.35915 | F9: 640.55846 | H9: 608.35915 | I9: 640.55846 | K9: 608.35915 | L9: 640.55846
A10: 5 | B10: Lợi nhuận sau thuế | C10: USD/tấn | E10: 146.95558 | F10: 80.905713 | H10: 85.417121 | I10: 19.367251 | K10: 3.3658393 | L10: -62.684031
A11: 6 | B11: Lợi nhuận sau thuế | C11: VND/phôi | E11: 57.312677 | F11: 31.553228 | H11: 33.312677 | I11: 7.553228 | K11: 1.3126773 | L11: -24.446772
B12: %LN sau thuế | E12: 0.084283349 | F12: 0.046401806 | H12: 0.051250273 | I12: 0.011620351 | K12: 0.00215193 | L12: -0.040076675
A13: 7 | B13: Chi phí đầu tư | C13: USD | E13: 11567300 | F13: 17336531 | H13: 11567300 | I13: 17336531 | K13: 11567300 | L13: 17336531
A14: 8 | B14: Chi phí đầu tư | C14: tỷ VND | E14: 300.7498 | F14: 450.7498 | H14: 300.7498 | I14: 450.7498 | K14: 300.7498 | L14: 450.7498
A15: 9 | B15: NPV | C15: tỷ VND | E15: 253.24422 | F15: 110.03709 | H15: 160.74752 | I15: 17.540395 | K15: 37.4186 | L15: -105.78853
A16: 10 | B16: Thời gian hoàn vốn | C16: năm | E16: 6 năm 11 tháng | F16: 10 năm 11 tháng | H16: 8 năm 04 tháng | I16: 14 năm 01 tháng | K16: 12 năm 02 tháng | L16: Không đạt hoàn vốn
A17: 11 | B17: % Lãi gộp nguyên liệu/Giá bán | C17: % | E17: 0.4384 | F17: 0.4384 | H17: 0.41248 | I17: 0.41248 | K17: 0.3739541 | L17: 0.3739541
B20: Đầu tư khuôn | E20: Có | F20: Có | H20: Có | I20: Có | K20: Có | L20: Có
B21: Đầu tư xưởng | F21: Có | I21: Có | L21: Có

Sheet ||

Sheet Summary
C1: Công ty CP Nhựa tái chế Duy Tân
C2: Đơn vị: Kế toán quản trị
C3: DỰ ÁN FLAKES TO PREFORM SUNTORY - PEPSICO
C4: MỘT SỐ CHỈ TIÊU TRỌNG YẾU
C5: 15gr Hotfill | L5: GIÁ ĐỀ XUẤT - THÁNG 12/2025 : | O5: GIÁ TRUNG BÌNH | R5: GIÁ ĐỀ XUẤT SUNTORY
M6: 680 | P6: 650 | S6: 610
F8: Paste chết | G8: Paste chết | I8: Paste chết | J8: Paste chết | U8: Paste chết | V8: Paste chết
B9: STT | C9: CHỈ TIÊU | D9: Đvt | F9: BÁO GIÁ LẦN 1-KHÔNG TÍNH ĐẦU TƯ XƯỞNG | G9: BÁO GIÁ LẦN 1-CÓ TÍNH ĐẦU TƯ XƯỞNG | I9: BÁO GIÁ LẦN 2 - KHÔNG TÍNH ĐẦU TƯ XƯỞNG | J9: BÁO GIÁ LẦN 2 - CÓ TÍNH ĐẦU TƯ XƯỞNG | L9: KẾ TOÁN ĐỀ XUẤT 680 VND/PHÔI | O9: GIÁ TRUNG BÌNH 650 VND/PHÔI | R9: ="SUNTORY YÊU CẦU "&$S$6&" VND/phôi" -> SUNTORY YÊU CẦU 610 VND/phôi | U9: CƠ SỞ-BÁO GIÁ L1- KHÔNG TÍNH ĐẦU TƯ XƯỞNG | V9: CƠ SỞ-BÁO GIÁ L2- KHÔNG TÍNH ĐẦU TƯ XƯỞNG
L10: KHÔNG TÍNH ĐẦU TƯ XƯỞNG | M10: CÓ TÍNH ĐẦU TƯ XƯỞNG | O10: KHÔNG TÍNH ĐẦU TƯ XƯỞNG | P10: CÓ TÍNH ĐẦU TƯ XƯỞNG | R10: KHÔNG TÍNH ĐẦU TƯ XƯỞNG | S10: CÓ TÍNH ĐẦU TƯ XƯỞNG
F11: Tháng 10/2024 | G11: Tháng 10/2024 | I11: Tháng 02/2025 | J11: Tháng 02/2025 | U11: Tháng 10/2024 | V11: Tháng 02/2025
B12: 1 | C12: Đơn giá bán phôi | D12: USD/tấn | F12: 1969.3333 | G12: 1969.3333 | I12: 1916 | J12: 1916 | L12: =L13*(1000000/'Cover Page'!$F$25)/EXR -> 1743.5897 | M12: =M13*(1000000/'Cover Page'!$F$25)/EXR -> 1743.5897 | O12: =O13*(1000000/'Cover Page'!$F$25)/EXR -> 1666.6667 | P12: =P13*(1000000/'Cover Page'!$F$25)/EXR -> 1666.6667 | R12: =R13*(1000000/'Cover Page'!$F$25)/EXR -> 1564.1026 | S12: =S13*(1000000/'Cover Page'!$F$25)/EXR -> 1564.1026 | U12: 1941.3333 | V12: 1941.3333
B13: 2 | C13: Đơn giá bán phôi | D13: VND/phôi | F13: 738.5 | G13: 738.5 | I13: 718.5 | J13: 718.5 | L13: =M6 -> 680 | M13: =M6 -> 680 | O13: =P6 -> 650 | P13: =P6 -> 650 | R13: =S6 -> 610 | S13: =S6 -> 610 | U13: 728 | V13: 728
B14: 3 | C14: Giá thành phôi | D14: USD/tấn | F14: 1757.3256 | G14: 1860.577 | I14: 1690.3835 | J14: 1793.6349 | L14: =L15*(1000000/'Cover Page'!$F$25)/EXR -> 1559.8953 | M14: =M15*(1000000/'Cover Page'!$F$25)/EXR -> 1642.4576 | O14: =O15*(1000000/'Cover Page'!$F$25)/EXR -> 1559.8953 | P14: =P15*(1000000/'Cover Page'!$F$25)/EXR -> 1642.4576 | R14: =R15*(1000000/'Cover Page'!$F$25)/EXR -> 1559.8953 | S14: =S15*(1000000/'Cover Page'!$F$25)/EXR -> 1642.4576 | U14: 1692.1813 | V14: 1631.3776
B15: 4 | C15: Giá thành phôi | D15: VND/phôi | F15: 658.9971 | G15: 697.71636 | I15: 633.89382 | J15: 672.61307 | L15: ='W5'!E6 -> 608.35915 | M15: ='W5'!G6 -> 640.55846 | O15: ='W5'!I6 -> 608.35915 | P15: ='W5'!K6 -> 640.55846 | R15: ='W5'!M6 -> 608.35915 | S15: ='W5'!O6 -> 640.55846 | U15: 634.56797 | V15: 611.76659
B16: 5 | C16: Lợi nhuận sau thuế | D16: USD/tấn | F16: 169.60618 | G16: 87.005099 | I16: 180.49319 | J16: 97.892107 | L16: =L17*(1000000/'Cover Page'!$F$25)/EXR -> 146.95558 | M16: =M17*(1000000/'Cover Page'!$F$25)/EXR -> 80.905713 | O16: =O17*(1000000/'Cover Page'!$F$25)/EXR -> 85.417121 | P16: =P17*(1000000/'Cover Page'!$F$25)/EXR -> 19.367251 | R16: =R17*(1000000/'Cover Page'!$F$25)/EXR -> 3.3658393 | S16: =S17*(1000000/'Cover Page'!$F$25)/EXR -> -62.684031 | U16: 199.32165 | V16: 247.96461
B17: 6 | C17: Lợi nhuận sau thuế | D17: VND/phôi | F17: 63.602319 | G17: 32.626912 | I17: 67.684947 | J17: 36.70954 | L17: ='W5'!E8 -> 57.312677 | M17: ='W5'!G8 -> 31.553228 | O17: ='W5'!I8 -> 33.312677 | P17: ='W5'!K8 -> 7.553228 | R17: ='W5'!M8 -> 1.3126773 | S17: ='W5'!O8 -> -24.446772 | U17: 74.745621 | V17: 92.986729
C18: %LN sau thuế | F18: 0.086123655 | G18: 0.044179976 | I18: 0.094203128 | J18: 0.051091914 | L18: ='W5'!E10 -> 0.084283349 | M18: ='W5'!G10 -> 0.046401806 | O18: ='W5'!I10 -> 0.051250273 | P18: ='W5'!K10 -> 0.011620351 | R18: ='W5'!M10 -> 0.00215193 | S18: ='W5'!O10 -> -0.040076675 | U18: 0.10267256 | V18: 0.12772902
B19: 7 | C19: Chi phí đầu tư | D19: USD | F19: 11070000 | G19: 17070000 | I19: 11070000 | J19: 17070000 | L19: =IF(Currency="USD",'W1'!$I$60,'W1'!$I$60/EXR) -> 11567300 | M19: =IF(Currency="USD",'W1'!$N$60,'W1'!$N$60/EXR) -> 17336531 | O19: =IF(Currency="USD",'W1'!$S$60,'W1'!$S$60/EXR) -> 11567300 | P19: =IF(Currency="USD",'W1'!$X$60,'W1'!$X$60/EXR) -> 17336531 | R19: =IF(Currency="USD",'W1'!$AC$60,'W1'!$AC$60/EXR) -> 11567300 | S19: =IF(Currency="USD",'W1'!$AH$60,'W1'!$AH$60/EXR) -> 17336531 | U19: 10054913 | V19: 10054913
B20: 8 | C20: Chi phí đầu tư | D20: tỷ VND | F20: 276.75 | G20: 426.75 | I20: 276.75 | J20: 426.75 | L20: =L19*EXR/10^9 -> 300.7498 | M20: =M19*EXR/10^9 -> 450.7498 | O20: =O19*EXR/10^9 -> 300.7498 | P20: =P19*EXR/10^9 -> 450.7498 | R20: =R19*EXR/10^9 -> 300.7498 | S20: =S19*EXR/10^9 -> 450.7498 | U20: 251.37282 | V20: 251.37282
B21: 9 | C21: NPV | D21: tỷ VND | F21: 426.17409 | G21: 284.37183 | I21: 382.62104 | J21: 240.81878 | L21: =IF(Currency="VND",'W5'!E15/10^3,'W5'!E15*EXR/10^9) -> 253.24422 | M21: =IF(Currency="VND",'W5'!G15/10^3,'W5'!G15*EXR/10^9) -> 110.03709 | O21: =IF(Currency="VND",'W5'!I15/10^3,'W5'!I15/10^9) -> 160.74752 | P21: =IF(Currency="VND",'W5'!K15/10^3,'W5'!K15*EXR/10^9) -> 17.540395 | R21: =IF(Currency="VND",'W5'!M15/10^3,'W5'!M15*EXR/10^9) -> 37.4186 | S21: =IF(Currency="VND",'W5'!O15/10^3,'W5'!O15*EXR/10^9) -> -105.78853 | U21: 491.97502 | V21: 487.89218
B22: 10 | C22: Thời gian hoàn vốn | D22: năm | F22: 6 năm | G22: 9 năm 08 tháng | I22: 6 năm 06 tháng | J22: 10 năm 08 tháng | L22: ='W5'!E13 -> 6 năm 11 tháng | M22: ='W5'!G13 -> 10 năm 11 tháng | O22: ='W5'!I13 -> 8 năm 04 tháng | P22: ='W5'!K13 -> 14 năm 01 tháng | R22: ='W5'!M13 -> 12 năm 02 tháng | S22: =IF('W5'!O13="0 năm","Không đạt hoàn vốn",'W5'!O13) -> Không đạt hoàn vốn | U22: 5 năm 05 tháng | V22: 5 năm 07 tháng
B23: 11 | C23: % Lãi gộp nguyên liệu/Giá bán | D23: % | F23: 0.4648998 | G23: 0.4648998 | I23: 0.45000487 | J23: 0.45000487 | L23: ='W5'!F108 -> 0.4384 | M23: ='W5'!H108 -> 0.4384 | O23: ='W5'!J108 -> 0.41248 | P23: ='W5'!L108 -> 0.41248 | R23: ='W5'!N108 -> 0.3739541 | S23: ='W5'!P108 -> 0.3739541 | U23: 0.45718201 | V23: 0.45718201
C26: DTR-Đầu tư khuôn | L26: Có | M26: Có | O26: Có | P26: Có | R26: Có | S26: Có
C27: DTR-Đầu tư xưởng | G27: Có | J27: Có | M27: Có | P27: Có | S27: Có
C29: Vảy sạch | G29: 1033 | J29: 1033

Sheet Cover Page
D3: COVER PAGE
D4: CHỈ TIÊU | H4: BASE-KHÔNG XƯỞNG | K4: BASE-CÓ XƯỞNG | N4: 650 VND/Phôi-KHÔNG XƯỞNG | Q4: 650 VND/Phôi-CÓ XƯỞNG | T4: SUNTORY-KHÔNG XƯỞNG | W4: SUNTORY-CÓ XƯỞNG | Z4: NPV=0 - KHÔNG XƯỞNG | AC4: NPV=0 - CÓ XƯỞNG | AF4: THỦ | AI4: THỦ | AL4: Công suất máy
C5: STT | D5: GIẢ ĐỊNH | E5: Đvt | F5: CHUNG | H5: OPTION 1 | K5: OPTION 2 | N5: OPTION 3 | Q5: OPTION 4 | T5: OPTION 5 | W5: OPTION 6 | Z5: OPTION 7 | AC5: OPTION 8 | AF5: OPTION 9 | AI5: OPTION 10 | AL5: Công suất máy
C6: 1 | D6: CAPEX | H6: Thực tế | Q6: 0 | T6: 0 | W6: 0 | Z6: 0 | AC6: 0 | AF6: 0 | AI6: 0
C7: 2 | D7: Chi phí sản xuất | H7: Thực tế | Q7: 0 | T7: 0 | W7: 0 | Z7: 0 | AC7: 0 | AF7: 0 | AI7: 0
D8: Chi phí vảy tăng | H8: 0.02 | K8: 0.02 | N8: 0.02 | Q8: 0.02 | T8: 0.02 | W8: 0.02 | Z8: 0.02 | AC8: 0.02 | AF8: 0.02 | AI8: 0.02
C9: 3 | D9: Lạm Phát | F9: 0.05
C10: 4 | D10: Tỷ giá | F10: 26000
C11: 5 | D11: Thuế suất TNDN: | F11: 0.2
C12: 6 | D12: Mark-up giá bán | H12: =5%/(1-Tax_rate-5%) -> 0.066666667 | K12: =5%/(1-Tax_rate-5%) -> 0.066666667 | N12: =5%/(1-Tax_rate-5%) -> 0.066666667 | Q12: =5%/(1-Tax_rate-5%) -> 0.066666667 | T12: =5%/(1-Tax_rate-5%) -> 0.066666667 | W12: =5%/(1-Tax_rate-5%) -> 0.066666667 | Z12: =5%/(1-Tax_rate-5%) -> 0.066666667 | AC12: =5%/(1-Tax_rate-5%) -> 0.066666667 | AF12: =5%/(1-Tax_rate-5%) -> 0.066666667 | AI12: =5%/(1-Tax_rate-5%) -> 0.066666667
C13: 7.1 | D13: Đơn giá ban đầu | E13: tr. VND/tấn | H13: =H14*PHOI_KG*10^3/10^6 -> 45.333333 | K13: =K14*PHOI_KG*10^3/10^6 -> 45.333333 | N13: =N14*PHOI_KG*10^3/10^6 -> 43.333333 | Q13: =Q14*PHOI_KG*10^3/10^6 -> 43.333333 | T13: =T14*PHOI_KG*10^3/10^6 -> 40.666667 | W13: =W14*PHOI_KG*10^3/10^6 -> 40.666667 | Z13: =Z14*PHOI_KG*10^3/10^6 -> 39.065014 | AC13: =AC14*PHOI_KG*10^3/10^6 -> 41.282922 | AF13: =AF14*PHOI_KG*10^3/10^6 -> 45.333333 | AI13: =AI14*PHOI_KG*10^3/10^6 -> 45.333333
C14: 7.2 | D14: Đơn giá ban đầu | E14: VND/phôi | H14: ='W5'!AC2 -> 680 | K14: ='W5'!AD2 -> 680 | N14: ='W5'!AE2 -> 650 | Q14: ='W5'!AF2 -> 650 | T14: ='W5'!AG2 -> 610 | W14: ='W5'!AH2 -> 610 | Z14: ='W5'!AI2 -> 585.97522 | AC14: ='W5'!AJ2 -> 619.24384 | AF14: ='W5'!AK2 -> 680 | AI14: ='W5'!AL2 -> 680 | AL14: Lấy số từ W5
C15: 7.3 | D15: Đơn giá ban đầu | E15: USD/tấn | H15: =H13/EXR*10^6 -> 1743.5897 | K15: =K13/EXR*10^6 -> 1743.5897 | N15: =N13/EXR*10^6 -> 1666.6667 | Q15: =Q13/EXR*10^6 -> 1666.6667 | T15: =T13/EXR*10^6 -> 1564.1026 | W15: =W13/EXR*10^6 -> 1564.1026 | Z15: =Z13/EXR*10^6 -> 1502.5006 | AC15: =AC13/EXR*10^6 -> 1587.8047 | AF15: =AF13/EXR*10^6 -> 1743.5897 | AI15: =AI13/EXR*10^6 -> 1743.5897
C16: 7.4 | D16: Đơn giá ban đầu | E16: USD/1.000 phôi | H16: =H15/PHOI_KG -> 26.153846 | K16: =K15/PHOI_KG -> 26.153846 | W16: =W15/PHOI_KG -> 23.461538 | Z16: =Z15/PHOI_KG -> 22.537508 | AC16: =AC15/PHOI_KG -> 23.817071 | AF16: =AF15/PHOI_KG -> 26.153846 | AI16: =AI15/PHOI_KG -> 26.153846
C17: 8 | D17: Tỷ lệ tăng đơn giá | H17: 0.02 | K17: 0.02 | N17: 0.02 | Q17: 0.02 | T17: 0.02 | W17: 0.02 | Z17: 0.02 | AC17: 0.02 | AF17: 0.02 | AI17: 0.02 | AL17: tăng mỗi năm
C19: 9.1 | D19: Lãi suất đi vay: | H19: 0.07 | K19: 0.07 | N19: 0.07 | Q19: 0.07 | T19: 0.07 | W19: 0.07 | Z19: 0.07 | AC19: 0.07 | AF19: 0.07 | AI19: 0.07
C20: 9.2 | D20: Lợi nhuận mong muốn cổ đông: | H20: 0.1 | K20: 0.1 | N20: 0.1 | Q20: 0.1 | T20: 0.1 | W20: 0.1 | Z20: 0.1 | AC20: 0.1 | AF20: 0.1 | AI20: 0.1
C21: 9.3 | D21: Cơ cấu vay mong muốn: | H21: 0.7 | K21: 0.7 | N21: 0.7 | Q21: 0.7 | T21: 0.7 | W21: 0.7 | Z21: 0.7 | AC21: 0.7 | AF21: 0.7 | AI21: 0.7
C22: 9.4 | D22: Cơ cấu VCSH: | H22: =1-H21 -> 0.3 | K22: =1-K21 -> 0.3 | N22: =1-N21 -> 0.3 | Q22: =1-Q21 -> 0.3 | T22: =1-T21 -> 0.3 | W22: =1-W21 -> 0.3 | Z22: =1-Z21 -> 0.3 | AC22: =1-AC21 -> 0.3 | AF22: =1-AF21 -> 0.3 | AI22: =1-AI21 -> 0.3
C23: 9.5 | D23: WACC: | H23: =(H19*H21*(1-Tax_rate)+H20*H22)*(1+Inflation) -> 0.07266 | K23: =(K19*K21*(1-Tax_rate)+K20*K22)*(1+Inflation) -> 0.07266 | N23: =(N19*N21*(1-Tax_rate)+N20*N22)*(1+Inflation) -> 0.07266 | Q23: =(Q19*Q21*(1-Tax_rate)+Q20*Q22)*(1+Inflation) -> 0.07266 | T23: =(T19*T21*(1-Tax_rate)+T20*T22)*(1+Inflation) -> 0.07266 | W23: =(W19*W21*(1-Tax_rate)+W20*W22)*(1+Inflation) -> 0.07266 | Z23: =(Z19*Z21*(1-Tax_rate)+Z20*Z22)*(1+Inflation) -> 0.07266 | AC23: =(AC19*AC21*(1-Tax_rate)+AC20*AC22)*(1+Inflation) -> 0.07266 | AF23: =(AF19*AF21*(1-Tax_rate)+AF20*AF22)*(1+Inflation) -> 0.07266 | AI23: =(AI19*AI21*(1-Tax_rate)+AI20*AI22)*(1+Inflation) -> 0.07266
C25: 10.1 | D25: Khuôn phôi | E25: gram | F25: 15
C26: 10.2 | D26: Số lượng phôi/chu kỳ: | E26: phôi/chu kỳ | F26: 128
C27: 10.3 | D27: Chu kỳ | E27: giây | F27: 8
C28: 10.4 | D28: Công suất | E28: kg/giờ | F28: =60*60/F27*F26*F25/10^3 -> 864
C29: 10.5 | D29: Công suất | E29: phôi/giờ | F29: =Capacity/F25*10^3 -> 57600
C30: 10.6 | D30: Số phôi/kg | E30: phôi/kg | F30: =1000/F25 -> 66.666667
A33: =MD!A7 -> VND | D33: KẾT QUẢ
A34: =IF(Currency="USD",1,0.000001) -> 1e-06 | C34: 11 | D34: Tổng mức đầu tư | E34: =IF(Currency="USD","USD","triệu VND") -> triệu VND | H34: ='W1'!I60*$A$34 -> 300749.8 | K34: ='W1'!N60*$A$34 -> 450749.8 | N34: ='W1'!S60*$A$34 -> 300749.8 | Q34: ='W1'!X60*$A$34 -> 450749.8 | T34: ='W1'!AC60*$A$34 -> 300749.8 | W34: ='W1'!AH60*$A$34 -> 450749.8 | Z34: ='W1'!AM60*$A$34 -> 300749.8 | AC34: ='W1'!AR60*$A$34 -> 450749.8 | AF34: ='W1'!AW60*$A$34 -> 300749.8 | AI34: ='W1'!BB60*$A$34 -> 450749.8
B35: DPP | C35: 12 | D35: Thời gian thu hồi vốn | E35: năm | H35: =SUMIFS('W3'!$K$18:$K$1670,'W3'!$A$18:$A$1670,H$5,'W3'!$D$18:$D$1670,$B$35) -> 6.9 | K35: =SUMIFS('W3'!$K$18:$K$1670,'W3'!$A$18:$A$1670,K$5,'W3'!$D$18:$D$1670,$B$35) -> 10.9 | N35: =SUMIFS('W3'!$K$18:$K$1670,'W3'!$A$18:$A$1670,N$5,'W3'!$D$18:$D$1670,$B$35) -> 8.3 | Q35: =SUMIFS('W3'!$K$18:$K$1670,'W3'!$A$18:$A$1670,Q$5,'W3'!$D$18:$D$1670,$B$35) -> 14.1 | T35: =SUMIFS('W3'!$K$18:$K$1670,'W3'!$A$18:$A$1670,T$5,'W3'!$D$18:$D$1670,$B$35) -> 12.2 | W35: =SUMIFS('W3'!$K$18:$K$1670,'W3'!$A$18:$A$1670,W$5,'W3'!$D$18:$D$1670,$B$35) -> 0 | Z35: =SUMIFS('W3'!$K$18:$K$1670,'W3'!$A$18:$A$1670,Z$5,'W3'!$D$18:$D$1670,$B$35) -> 0 | AC35: =SUMIFS('W3'!$K$18:$K$1670,'W3'!$A$18:$A$1670,AC$5,'W3'!$D$18:$D$1670,$B$35) -> 0 | AF35: =SUMIFS('W3'!$K$18:$K$1670,'W3'!$A$18:$A$1670,AF$5,'W3'!$D$18:$D$1670,$B$35) -> 6.9 | AI35: =SUMIFS('W3'!$K$18:$K$1670,'W3'!$A$18:$A$1670,AI$5,'W3'!$D$18:$D$1670,$B$35) -> 10.9
H36: =INT(H35)&" năm"&IF(MOD(H35,1)*12=0,," "&TEXT(MOD(H35,1)*12,"00")&" tháng") -> 6 năm 11 tháng | K36: =INT(K35)&" năm"&IF(MOD(K35,1)*12=0,," "&TEXT(MOD(K35,1)*12,"00")&" tháng") -> 10 năm 11 tháng | N36: =INT(N35)&" năm"&IF(MOD(N35,1)*12=0,," "&TEXT(MOD(N35,1)*12,"00")&" tháng") -> 8 năm 04 tháng | Q36: =INT(Q35)&" năm"&IF(MOD(Q35,1)*12=0,," "&TEXT(MOD(Q35,1)*12,"00")&" tháng") -> 14 năm 01 tháng | T36: =INT(T35)&" năm"&IF(MOD(T35,1)*12=0,," "&TEXT(MOD(T35,1)*12,"00")&" tháng") -> 12 năm 02 tháng | W36: =INT(W35)&" năm"&IF(MOD(W35,1)*12=0,," "&TEXT(MOD(W35,1)*12,"00")&" tháng") -> 0 năm | Z36: =INT(Z35)&" năm"&IF(MOD(Z35,1)*12=0,," "&TEXT(MOD(Z35,1)*12,"00")&" tháng") -> 0 năm | AC36: =INT(AC35)&" năm"&IF(MOD(AC35,1)*12=0,," "&TEXT(MOD(AC35,1)*12,"00")&" tháng") -> 0 năm | AF36: =INT(AF35)&" năm"&IF(MOD(AF35,1)*12=0,," "&TEXT(MOD(AF35,1)*12,"00")&" tháng") -> 6 năm 11 tháng | AI36: =INT(AI35)&" năm"&IF(MOD(AI35,1)*12=0,," "&TEXT(MOD(AI35,1)*12,"00")&" tháng") -> 10 năm 11 tháng
B37: IRR | C37: 13 | D37: Tỷ suất hoàn vốn nội bộ (IRR) | E37: % | H37: =SUMIFS('W3'!$K$18:$K$1670,'W3'!$A$18:$A$1670,H$5,'W3'!$D$18:$D$1670,$B$37) -> 0.1774592 | K37: =SUMIFS('W3'!$K$18:$K$1670,'W3'!$A$18:$A$1670,K$5,'W3'!$D$18:$D$1670,$B$37) -> 0.10663649 | N37: =SUMIFS('W3'!$K$18:$K$1670,'W3'!$A$18:$A$1670,N$5,'W3'!$D$18:$D$1670,$B$37) -> 0.14321796 | Q37: =SUMIFS('W3'!$K$18:$K$1670,'W3'!$A$18:$A$1670,Q$5,'W3'!$D$18:$D$1670,$B$37) -> 0.07840017 | T37: =SUMIFS('W3'!$K$18:$K$1670,'W3'!$A$18:$A$1670,T$5,'W3'!$D$18:$D$1670,$B$37) -> 0.090883732 | W37: =SUMIFS('W3'!$K$18:$K$1670,'W3'!$A$18:$A$1670,W$5,'W3'!$D$18:$D$1670,$B$37) -> 0.034366044 | Z37: =SUMIFS('W3'!$K$18:$K$1670,'W3'!$A$18:$A$1670,Z$5,'W3'!$D$18:$D$1670,$B$37) -> 0.053201942 | AC37: =SUMIFS('W3'!$K$18:$K$1670,'W3'!$A$18:$A$1670,AC$5,'W3'!$D$18:$D$1670,$B$37) -> 0.045414211 | AF37: =SUMIFS('W3'!$K$18:$K$1670,'W3'!$A$18:$A$1670,AF$5,'W3'!$D$18:$D$1670,$B$37) -> 0.1774592 | AI37: =SUMIFS('W3'!$K$18:$K$1670,'W3'!$A$18:$A$1670,AI$5,'W3'!$D$18:$D$1670,$B$37) -> 0.10663649
D39: Đơn giá năm đầu | E39: VND/phôi | H39: =H14 -> 680 | K39: =K14 -> 680 | N39: =N14 -> 650 | Q39: =Q14 -> 650 | T39: =T14 -> 610 | W39: =W14 -> 610 | Z39: =Z14 -> 585.97522 | AC39: =AC14 -> 619.24384 | AF39: =AF14 -> 680 | AI39: =AI14 -> 680
D40: Đơn giá năm đầu | E40: USD/tấn | H40: =H15 -> 1743.5897 | K40: =K15 -> 1743.5897 | N40: =N15 -> 1666.6667 | Q40: =Q15 -> 1666.6667 | T40: =T15 -> 1564.1026 | W40: =W15 -> 1564.1026 | Z40: =Z15 -> 1502.5006 | AC40: =AC15 -> 1587.8047 | AF40: =AF15 -> 1743.5897 | AI40: =AI15 -> 1743.5897
B42: NPV | C42: 14 | D42: Dòng tiền chiết khẩu | E42: =IF(Currency="USD","USD","triệu VND") -> triệu VND | H42: =SUM(H43:H68) -> 253244.22 | K42: =SUM(K43:K68) -> 110037.09 | N42: =SUM(N43:N68) -> 160747.52 | Q42: =SUM(Q43:Q68) -> 17540.395 | T42: =SUM(T43:T68) -> 37418.6 | W42: =SUM(W43:W68) -> -105788.53 | Z42: =SUM(Z43:Z68) -> -36655.167 | AC42: =SUM(AC43:AC68) -> -77287.721 | AF42: =SUM(AF43:AF68) -> 253244.22 | AI42: =SUM(AI43:AI68) -> 110037.09
D43: 0 | E43: =IF(Currency="USD","USD","triệu VND") -> triệu VND | H43: {=SUMPRODUCT('W3'!$K$18:$AJ$1670*('W3'!$A$18:$A$1670=H$5)*('W3'!$D$18:$D$1670=$B$42)*('W3'!$K$14:$AJ$14='Cover Page'!$D43))} -> -300749.8 | K43: {=SUMPRODUCT('W3'!$K$18:$AJ$1670*('W3'!$A$18:$A$1670=K$5)*('W3'!$D$18:$D$1670=$B$42)*('W3'!$K$14:$AJ$14='Cover Page'!$D43))} -> -450749.8 | N43: {=SUMPRODUCT('W3'!$K$18:$AJ$1670*('W3'!$A$18:$A$1670=N$5)*('W3'!$D$18:$D$1670=$B$42)*('W3'!$K$14:$AJ$14='Cover Page'!$D43))} -> -300749.8 | Q43: {=SUMPRODUCT('W3'!$K$18:$AJ$1670*('W3'!$A$18:$A$1670=Q$5)*('W3'!$D$18:$D$1670=$B$42)*('W3'!$K$14:$AJ$14='Cover Page'!$D43))} -> -450749.8 | T43: {=SUMPRODUCT('W3'!$K$18:$AJ$1670*('W3'!$A$18:$A$1670=T$5)*('W3'!$D$18:$D$1670=$B$42)*('W3'!$K$14:$AJ$14='Cover Page'!$D43))} -> -300749.8 | W43: {=SUMPRODUCT('W3'!$K$18:$AJ$1670*('W3'!$A$18:$A$1670=W$5)*('W3'!$D$18:$D$1670=$B$42)*('W3'!$K$14:$AJ$14='Cover Page'!$D43))} -> -450749.8 | Z43: {=SUMPRODUCT('W3'!$K$18:$AJ$1670*('W3'!$A$18:$A$1670=Z$5)*('W3'!$D$18:$D$1670=$B$42)*('W3'!$K$14:$AJ$14='Cover Page'!$D43))} -> -300749.8 | AC43: {=SUMPRODUCT('W3'!$K$18:$AJ$1670*('W3'!$A$18:$A$1670=AC$5)*('W3'!$D$18:$D$1670=$B$42)*('W3'!$K$14:$AJ$14='Cover Page'!$D43))} -> -450749.8 | AF43: {=SUMPRODUCT('W3'!$K$18:$AJ$1670*('W3'!$A$18:$A$1670=AF$5)*('W3'!$D$18:$D$1670=$B$42)*('W3'!$K$14:$AJ$14='Cover Page'!$D43))} -> -300749.8 | AI43: {=SUMPRODUCT('W3'!$K$18:$AJ$1670*('W3'!$A$18:$A$1670=AI$5)*('W3'!$D$18:$D$1670=$B$42)*('W3'!$K$14:$AJ$14='Cover Page'!$D43))} -> -450749.8 | AT43: Giả định: sau 25 năm thì giá trị các tài sản còn lại =0
D44: 1 | E44: =IF(Currency="USD","USD","triệu VND") -> triệu VND | H44: {=SUMPRODUCT('W3'!$K$18:$AJ$1670*('W3'!$A$18:$A$1670=H$5)*('W3'!$D$18:$D$1670=$B$42)*('W3'!$K$14:$AJ$14='Cover Page'!$D44))} -> 24486.741 | K44: {=SUMPRODUCT('W3'!$K$18:$AJ$1670*('W3'!$A$18:$A$1670=K$5)*('W3'!$D$18:$D$1670=$B$42)*('W3'!$K$14:$AJ$14='Cover Page'!$D44))} -> 25193.769 | N44: {=SUMPRODUCT('W3'!$K$18:$AJ$1670*('W3'!$A$18:$A$1670=N$5)*('W3'!$D$18:$D$1670=$B$42)*('W3'!$K$14:$AJ$14='Cover Page'!$D44))} -> 19867.067 | Q44: {=SUMPRODUCT('W3'!$K$18:$AJ$1670*('W3'!$A$18:$A$1670=Q$5)*('W3'!$D$18:$D$1670=$B$42)*('W3'!$K$14:$AJ$14='Cover Page'!$D44))} -> 20574.094 | T44: {=SUMPRODUCT('W3'!$K$18:$AJ$1670*('W3'!$A$18:$A$1670=T$5)*('W3'!$D$18:$D$1670=$B$42)*('W3'!$K$14:$AJ$14='Cover Page'!$D44))} -> 13707.501 | W44: {=SUMPRODUCT('W3'!$K$18:$AJ$1670*('W3'!$A$18:$A$1670=W$5)*('W3'!$D$18:$D$1670=$B$42)*('W3'!$K$14:$AJ$14='Cover Page'!$D44))} -> 14414.528 | Z44: {=SUMPRODUCT('W3'!$K$18:$AJ$1670*('W3'!$A$18:$A$1670=Z$5)*('W3'!$D$18:$D$1670=$B$42)*('W3'!$K$14:$AJ$14='Cover Page'!$D44))} -> 10007.945 | AC44: {=SUMPRODUCT('W3'!$K$18:$AJ$1670*('W3'!$A$18:$A$1670=AC$5)*('W3'!$D$18:$D$1670=$B$42)*('W3'!$K$14:$AJ$14='Cover Page'!$D44))} -> 15837.979 | AF44: {=SUMPRODUCT('W3'!$K$18:$AJ$1670*('W3'!$A$18:$A$1670=AF$5)*('W3'!$D$18:$D$1670=$B$42)*('W3'!$K$14:$AJ$14='Cover Page'!$D44))} -> 24486.741 | AI44: {=SUMPRODUCT('W3'!$K$18:$AJ$1670*('W3'!$A$18:$A$1670=AI$5)*('W3'!$D$18:$D$1670=$B$42)*('W3'!$K$14:$AJ$14='Cover Page'!$D44))} -> 25193.769
D45: 2 | E45: =IF(Currency="USD","USD","triệu VND") -> triệu VND | H45: {=SUMPRODUCT('W3'!$K$18:$AJ$1670*('W3'!$A$18:$A$1670=H$5)*('W3'!$D$18:$D$1670=$B$42)*('W3'!$K$14:$AJ$14='Cover Page'!$D45))} -> 38605.112 | K45: {=SUMPRODUCT('W3'!$K$18:$AJ$1670*('W3'!$A$18:$A$1670=K$5)*('W3'!$D$18:$D$1670=$B$42)*('W3'!$K$14:$AJ$14='Cover Page'!$D45))} -> 39264.247 | N45: {=SUMPRODUCT('W3'!$K$18:$AJ$1670*('W3'!$A$18:$A$1670=N$5)*('W3'!$D$18:$D$1670=$B$42)*('W3'!$K$14:$AJ$14='Cover Page'!$D45))} -> 32455.078 | Q45: {=SUMPRODUCT('W3'!$K$18:$AJ$1670*('W3'!$A$18:$A$1670=Q$5)*('W3'!$D$18:$D$1670=$B$42)*('W3'!$K$14:$AJ$14='Cover Page'!$D45))} -> 33114.213 | T45: {=SUMPRODUCT('W3'!$K$18:$AJ$1670*('W3'!$A$18:$A$1670=T$5)*('W3'!$D$18:$D$1670=$B$42)*('W3'!$K$14:$AJ$14='Cover Page'!$D45))} -> 24255.034 | W45: {=SUMPRODUCT('W3'!$K$18:$AJ$1670*('W3'!$A$18:$A$1670=W$5)*('W3'!$D$18:$D$1670=$B$42)*('W3'!$K$14:$AJ$14='Cover Page'!$D45))} -> 24914.168 | Z45: {=SUMPRODUCT('W3'!$K$18:$AJ$1670*('W3'!$A$18:$A$1670=Z$5)*('W3'!$D$18:$D$1670=$B$42)*('W3'!$K$14:$AJ$14='Cover Page'!$D45))} -> 19329.926 | AC45: {=SUMPRODUCT('W3'!$K$18:$AJ$1670*('W3'!$A$18:$A$1670=AC$5)*('W3'!$D$18:$D$1670=$B$42)*('W3'!$K$14:$AJ$14='Cover Page'!$D45))} -> 26809.165 | AF45: {=SUMPRODUCT('W3'!$K$18:$AJ$1670*('W3'!$A$18:$A$1670=AF$5)*('W3'!$D$18:$D$1670=$B$42)*('W3'!$K$14:$AJ$14='Cover Page'!$D45))} -> 38605.112 | AI45: {=SUMPRODUCT('W3'!$K$18:$AJ$1670*('W3'!$A$18:$A$1670=AI$5)*('W3'!$D$18:$D$1670=$B$42)*('W3'!$K$14:$AJ$14='Cover Page'!$D45))} -> 39264.247
D46: 3 | E46: =IF(Currency="USD","USD","triệu VND") -> triệu VND | H46: {=SUMPRODUCT('W3'!$K$18:$AJ$1670*('W3'!$A$18:$A$1670=H$5)*('W3'!$D$18:$D$1670=$B$42)*('W3'!$K$14:$AJ$14='Cover Page'!$D46))} -> 55601.309 | K46: {=SUMPRODUCT('W3'!$K$18:$AJ$1670*('W3'!$A$18:$A$1670=K$5)*('W3'!$D$18:$D$1670=$B$42)*('W3'!$K$14:$AJ$14='Cover Page'!$D46))} -> 56215.796 | N46: {=SUMPRODUCT('W3'!$K$18:$AJ$1670*('W3'!$A$18:$A$1670=N$5)*('W3'!$D$18:$D$1670=$B$42)*('W3'!$K$14:$AJ$14='Cover Page'!$D46))} -> 47246.866 | Q46: {=SUMPRODUCT('W3'!$K$18:$AJ$1670*('W3'!$A$18:$A$1670=Q$5)*('W3'!$D$18:$D$1670=$B$42)*('W3'!$K$14:$AJ$14='Cover Page'!$D46))} -> 47861.352 | T46: {=SUMPRODUCT('W3'!$K$18:$AJ$1670*('W3'!$A$18:$A$1670=T$5)*('W3'!$D$18:$D$1670=$B$42)*('W3'!$K$14:$AJ$14='Cover Page'!$D46))} -> 36107.607 | W46: {=SUMPRODUCT('W3'!$K$18:$AJ$1670*('W3'!$A$18:$A$1670=W$5)*('W3'!$D$18:$D$1670=$B$42)*('W3'!$K$14:$AJ$14='Cover Page'!$D46))} -> 36722.094 | Z46: {=SUMPRODUCT('W3'!$K$18:$AJ$1670*('W3'!$A$18:$A$1670=Z$5)*('W3'!$D$18:$D$1670=$B$42)*('W3'!$K$14:$AJ$14='Cover Page'!$D46))} -> 29417.151 | AC46: {=SUMPRODUCT('W3'!$K$18:$AJ$1670*('W3'!$A$18:$A$1670=AC$5)*('W3'!$D$18:$D$1670=$B$42)*('W3'!$K$14:$AJ$14='Cover Page'!$D46))} -> 39296.33 | AF46: {=SUMPRODUCT('W3'!$K$18:$AJ$1670*('W3'!$A$18:$A$1670=AF$5)*('W3'!$D$18:$D$1670=$B$42)*('W3'!$K$14:$AJ$14='Cover Page'!$D46))} -> 55601.309 | AI46: {=SUMPRODUCT('W3'!$K$18:$AJ$1670*('W3'!$A$18:$A$1670=AI$5)*('W3'!$D$18:$D$1670=$B$42)*('W3'!$K$14:$AJ$14='Cover Page'!$D46))} -> 56215.796
D47: 4 | E47: =IF(Currency="USD","USD","triệu VND") -> triệu VND | H47: {=SUMPRODUCT('W3'!$K$18:$AJ$1670*('W3'!$A$18:$A$1670=H$5)*('W3'!$D$18:$D$1670=$B$42)*('W3'!$K$14:$AJ$14='Cover Page'!$D47))} -> 52064.439 | K47: {=SUMPRODUCT('W3'!$K$18:$AJ$1670*('W3'!$A$18:$A$1670=K$5)*('W3'!$D$18:$D$1670=$B$42)*('W3'!$K$14:$AJ$14='Cover Page'!$D47))} -> 52637.301 | N47: {=SUMPRODUCT('W3'!$K$18:$AJ$1670*('W3'!$A$18:$A$1670=N$5)*('W3'!$D$18:$D$1670=$B$42)*('W3'!$K$14:$AJ$14='Cover Page'!$D47))} -> 44120.139 | Q47: {=SUMPRODUCT('W3'!$K$18:$AJ$1670*('W3'!$A$18:$A$1670=Q$5)*('W3'!$D$18:$D$1670=$B$42)*('W3'!$K$14:$AJ$14='Cover Page'!$D47))} -> 44693.001 | T47: {=SUMPRODUCT('W3'!$K$18:$AJ$1670*('W3'!$A$18:$A$1670=T$5)*('W3'!$D$18:$D$1670=$B$42)*('W3'!$K$14:$AJ$14='Cover Page'!$D47))} -> 33527.74 | W47: {=SUMPRODUCT('W3'!$K$18:$AJ$1670*('W3'!$A$18:$A$1670=W$5)*('W3'!$D$18:$D$1670=$B$42)*('W3'!$K$14:$AJ$14='Cover Page'!$D47))} -> 34100.602 | Z47: {=SUMPRODUCT('W3'!$K$18:$AJ$1670*('W3'!$A$18:$A$1670=Z$5)*('W3'!$D$18:$D$1670=$B$42)*('W3'!$K$14:$AJ$14='Cover Page'!$D47))} -> 27165.737 | AC47: {=SUMPRODUCT('W3'!$K$18:$AJ$1670*('W3'!$A$18:$A$1670=AC$5)*('W3'!$D$18:$D$1670=$B$42)*('W3'!$K$14:$AJ$14='Cover Page'!$D47))} -> 36548.462 | AF47: {=SUMPRODUCT('W3'!$K$18:$AJ$1670*('W3'!$A$18:$A$1670=AF$5)*('W3'!$D$18:$D$1670=$B$42)*('W3'!$K$14:$AJ$14='Cover Page'!$D47))} -> 52064.439 | AI47: {=SUMPRODUCT('W3'!$K$18:$AJ$1670*('W3'!$A$18:$A$1670=AI$5)*('W3'!$D$18:$D$1670=$B$42)*('W3'!$K$14:$AJ$14='Cover Page'!$D47))} -> 52637.301
D48: 5 | E48: =IF(Currency="USD","USD","triệu VND") -> triệu VND | H48: {=SUMPRODUCT('W3'!$K$18:$AJ$1670*('W3'!$A$18:$A$1670=H$5)*('W3'!$D$18:$D$1670=$B$42)*('W3'!$K$14:$AJ$14='Cover Page'!$D48))} -> 48720.87 | K48: {=SUMPRODUCT('W3'!$K$18:$AJ$1670*('W3'!$A$18:$A$1670=K$5)*('W3'!$D$18:$D$1670=$B$42)*('W3'!$K$14:$AJ$14='Cover Page'!$D48))} -> 49254.927 | N48: {=SUMPRODUCT('W3'!$K$18:$AJ$1670*('W3'!$A$18:$A$1670=N$5)*('W3'!$D$18:$D$1670=$B$42)*('W3'!$K$14:$AJ$14='Cover Page'!$D48))} -> 41166.579 | Q48: {=SUMPRODUCT('W3'!$K$18:$AJ$1670*('W3'!$A$18:$A$1670=Q$5)*('W3'!$D$18:$D$1670=$B$42)*('W3'!$K$14:$AJ$14='Cover Page'!$D48))} -> 41700.636 | T48: {=SUMPRODUCT('W3'!$K$18:$AJ$1670*('W3'!$A$18:$A$1670=T$5)*('W3'!$D$18:$D$1670=$B$42)*('W3'!$K$14:$AJ$14='Cover Page'!$D48))} -> 31094.191 | W48: {=SUMPRODUCT('W3'!$K$18:$AJ$1670*('W3'!$A$18:$A$1670=W$5)*('W3'!$D$18:$D$1670=$B$42)*('W3'!$K$14:$AJ$14='Cover Page'!$D48))} -> 31628.248 | Z48: {=SUMPRODUCT('W3'!$K$18:$AJ$1670*('W3'!$A$18:$A$1670=Z$5)*('W3'!$D$18:$D$1670=$B$42)*('W3'!$K$14:$AJ$14='Cover Page'!$D48))} -> 25044.517 | AC48: {=SUMPRODUCT('W3'!$K$18:$AJ$1670*('W3'!$A$18:$A$1670=AC$5)*('W3'!$D$18:$D$1670=$B$42)*('W3'!$K$14:$AJ$14='Cover Page'!$D48))} -> 33955.935 | AF48: {=SUMPRODUCT('W3'!$K$18:$AJ$1670*('W3'!$A$18:$A$1670=AF$5)*('W3'!$D$18:$D$1670=$B$42)*('W3'!$K$14:$AJ$14='Cover Page'!$D48))} -> 48720.87 | AI48: {=SUMPRODUCT('W3'!$K$18:$AJ$1670*('W3'!$A$18:$A$1670=AI$5)*('W3'!$D$18:$D$1670=$B$42)*('W3'!$K$14:$AJ$14='Cover Page'!$D48))} -> 49254.927
D49: 6 | E49: =IF(Currency="USD","USD","triệu VND") -> triệu VND | H49: {=SUMPRODUCT('W3'!$K$18:$AJ$1670*('W3'!$A$18:$A$1670=H$5)*('W3'!$D$18:$D$1670=$B$42)*('W3'!$K$14:$AJ$14='Cover Page'!$D49))} -> 45560.519 | K49: {=SUMPRODUCT('W3'!$K$18:$AJ$1670*('W3'!$A$18:$A$1670=K$5)*('W3'!$D$18:$D$1670=$B$42)*('W3'!$K$14:$AJ$14='Cover Page'!$D49))} -> 46058.4 | N49: {=SUMPRODUCT('W3'!$K$18:$AJ$1670*('W3'!$A$18:$A$1670=N$5)*('W3'!$D$18:$D$1670=$B$42)*('W3'!$K$14:$AJ$14='Cover Page'!$D49))} -> 38377.09 | Q49: {=SUMPRODUCT('W3'!$K$18:$AJ$1670*('W3'!$A$18:$A$1670=Q$5)*('W3'!$D$18:$D$1670=$B$42)*('W3'!$K$14:$AJ$14='Cover Page'!$D49))} -> 38874.971 | T49: {=SUMPRODUCT('W3'!$K$18:$AJ$1670*('W3'!$A$18:$A$1670=T$5)*('W3'!$D$18:$D$1670=$B$42)*('W3'!$K$14:$AJ$14='Cover Page'!$D49))} -> 28799.185 | W49: {=SUMPRODUCT('W3'!$K$18:$AJ$1670*('W3'!$A$18:$A$1670=W$5)*('W3'!$D$18:$D$1670=$B$42)*('W3'!$K$14:$AJ$14='Cover Page'!$D49))} -> 29297.066 | Z49: {=SUMPRODUCT('W3'!$K$18:$AJ$1670*('W3'!$A$18:$A$1670=Z$5)*('W3'!$D$18:$D$1670=$B$42)*('W3'!$K$14:$AJ$14='Cover Page'!$D49))} -> 23046.507 | AC49: {=SUMPRODUCT('W3'!$K$18:$AJ$1670*('W3'!$A$18:$A$1670=AC$5)*('W3'!$D$18:$D$1670=$B$42)*('W3'!$K$14:$AJ$14='Cover Page'!$D49))} -> 31510.48 | AF49: {=SUMPRODUCT('W3'!$K$18:$AJ$1670*('W3'!$A$18:$A$1670=AF$5)*('W3'!$D$18:$D$1670=$B$42)*('W3'!$K$14:$AJ$14='Cover Page'!$D49))} -> 45560.519 | AI49: {=SUMPRODUCT('W3'!$K$18:$AJ$1670*('W3'!$A$18:$A$1670=AI$5)*('W3'!$D$18:$D$1670=$B$42)*('W3'!$K$14:$AJ$14='Cover Page'!$D49))} -> 46058.4
D50: 7 | E50: =IF(Currency="USD","USD","triệu VND") -> triệu VND | H50: {=SUMPRODUCT('W3'!$K$18:$AJ$1670*('W3'!$A$18:$A$1670=H$5)*('W3'!$D$18:$D$1670=$B$42)*('W3'!$K$14:$AJ$14='Cover Page'!$D50))} -> 42573.824 | K50: {=SUMPRODUCT('W3'!$K$18:$AJ$1670*('W3'!$A$18:$A$1670=K$5)*('W3'!$D$18:$D$1670=$B$42)*('W3'!$K$14:$AJ$14='Cover Page'!$D50))} -> 43037.98 | N50: {=SUMPRODUCT('W3'!$K$18:$AJ$1670*('W3'!$A$18:$A$1670=N$5)*('W3'!$D$18:$D$1670=$B$42)*('W3'!$K$14:$AJ$14='Cover Page'!$D50))} -> 35743.05 | Q50: {=SUMPRODUCT('W3'!$K$18:$AJ$1670*('W3'!$A$18:$A$1670=Q$5)*('W3'!$D$18:$D$1670=$B$42)*('W3'!$K$14:$AJ$14='Cover Page'!$D50))} -> 36207.206 | T50: {=SUMPRODUCT('W3'!$K$18:$AJ$1670*('W3'!$A$18:$A$1670=T$5)*('W3'!$D$18:$D$1670=$B$42)*('W3'!$K$14:$AJ$14='Cover Page'!$D50))} -> 26635.353 | W50: {=SUMPRODUCT('W3'!$K$18:$AJ$1670*('W3'!$A$18:$A$1670=W$5)*('W3'!$D$18:$D$1670=$B$42)*('W3'!$K$14:$AJ$14='Cover Page'!$D50))} -> 27099.508 | Z50: {=SUMPRODUCT('W3'!$K$18:$AJ$1670*('W3'!$A$18:$A$1670=Z$5)*('W3'!$D$18:$D$1670=$B$42)*('W3'!$K$14:$AJ$14='Cover Page'!$D50))} -> 21165.091 | AC50: {=SUMPRODUCT('W3'!$K$18:$AJ$1670*('W3'!$A$18:$A$1670=AC$5)*('W3'!$D$18:$D$1670=$B$42)*('W3'!$K$14:$AJ$14='Cover Page'!$D50))} -> 29204.26 | AF50: {=SUMPRODUCT('W3'!$K$18:$AJ$1670*('W3'!$A$18:$A$1670=AF$5)*('W3'!$D$18:$D$1670=$B$42)*('W3'!$K$14:$AJ$14='Cover Page'!$D50))} -> 42573.824 | AI50: {=SUMPRODUCT('W3'!$K$18:$AJ$1670*('W3'!$A$18:$A$1670=AI$5)*('W3'!$D$18:$D$1670=$B$42)*('W3'!$K$14:$AJ$14='Cover Page'!$D50))} -> 43037.98
D51: 8 | E51: =IF(Currency="USD","USD","triệu VND") -> triệu VND | H51: {=SUMPRODUCT('W3'!$K$18:$AJ$1670*('W3'!$A$18:$A$1670=H$5)*('W3'!$D$18:$D$1670=$B$42)*('W3'!$K$14:$AJ$14='Cover Page'!$D51))} -> 39751.715 | K51: {=SUMPRODUCT('W3'!$K$18:$AJ$1670*('W3'!$A$18:$A$1670=K$5)*('W3'!$D$18:$D$1670=$B$42)*('W3'!$K$14:$AJ$14='Cover Page'!$D51))} -> 40184.43 | N51: {=SUMPRODUCT('W3'!$K$18:$AJ$1670*('W3'!$A$18:$A$1670=N$5)*('W3'!$D$18:$D$1670=$B$42)*('W3'!$K$14:$AJ$14='Cover Page'!$D51))} -> 33256.284 | Q51: {=SUMPRODUCT('W3'!$K$18:$AJ$1670*('W3'!$A$18:$A$1670=Q$5)*('W3'!$D$18:$D$1670=$B$42)*('W3'!$K$14:$AJ$14='Cover Page'!$D51))} -> 33688.999 | T51: {=SUMPRODUCT('W3'!$K$18:$AJ$1670*('W3'!$A$18:$A$1670=T$5)*('W3'!$D$18:$D$1670=$B$42)*('W3'!$K$14:$AJ$14='Cover Page'!$D51))} -> 24595.71 | W51: {=SUMPRODUCT('W3'!$K$18:$AJ$1670*('W3'!$A$18:$A$1670=W$5)*('W3'!$D$18:$D$1670=$B$42)*('W3'!$K$14:$AJ$14='Cover Page'!$D51))} -> 25028.424 | Z51: {=SUMPRODUCT('W3'!$K$18:$AJ$1670*('W3'!$A$18:$A$1670=Z$5)*('W3'!$D$18:$D$1670=$B$42)*('W3'!$K$14:$AJ$14='Cover Page'!$D51))} -> 19393.999 | AC51: {=SUMPRODUCT('W3'!$K$18:$AJ$1670*('W3'!$A$18:$A$1670=AC$5)*('W3'!$D$18:$D$1670=$B$42)*('W3'!$K$14:$AJ$14='Cover Page'!$D51))} -> 27029.848 | AF51: {=SUMPRODUCT('W3'!$K$18:$AJ$1670*('W3'!$A$18:$A$1670=AF$5)*('W3'!$D$18:$D$1670=$B$42)*('W3'!$K$14:$AJ$14='Cover Page'!$D51))} -> 39751.715 | AI51: {=SUMPRODUCT('W3'!$K$18:$AJ$1670*('W3'!$A$18:$A$1670=AI$5)*('W3'!$D$18:$D$1670=$B$42)*('W3'!$K$14:$AJ$14='Cover Page'!$D51))} -> 40184.43
D52: 9 | E52: =IF(Currency="USD","USD","triệu VND") -> triệu VND | H52: {=SUMPRODUCT('W3'!$K$18:$AJ$1670*('W3'!$A$18:$A$1670=H$5)*('W3'!$D$18:$D$1670=$B$42)*('W3'!$K$14:$AJ$14='Cover Page'!$D52))} -> 37085.59 | K52: {=SUMPRODUCT('W3'!$K$18:$AJ$1670*('W3'!$A$18:$A$1670=K$5)*('W3'!$D$18:$D$1670=$B$42)*('W3'!$K$14:$AJ$14='Cover Page'!$D52))} -> 37488.993 | N52: {=SUMPRODUCT('W3'!$K$18:$AJ$1670*('W3'!$A$18:$A$1670=N$5)*('W3'!$D$18:$D$1670=$B$42)*('W3'!$K$14:$AJ$14='Cover Page'!$D52))} -> 30909.038 | Q52: {=SUMPRODUCT('W3'!$K$18:$AJ$1670*('W3'!$A$18:$A$1670=Q$5)*('W3'!$D$18:$D$1670=$B$42)*('W3'!$K$14:$AJ$14='Cover Page'!$D52))} -> 31312.442 | T52: {=SUMPRODUCT('W3'!$K$18:$AJ$1670*('W3'!$A$18:$A$1670=T$5)*('W3'!$D$18:$D$1670=$B$42)*('W3'!$K$14:$AJ$14='Cover Page'!$D52))} -> 22673.637 | W52: {=SUMPRODUCT('W3'!$K$18:$AJ$1670*('W3'!$A$18:$A$1670=W$5)*('W3'!$D$18:$D$1670=$B$42)*('W3'!$K$14:$AJ$14='Cover Page'!$D52))} -> 23077.04 | Z52: {=SUMPRODUCT('W3'!$K$18:$AJ$1670*('W3'!$A$18:$A$1670=Z$5)*('W3'!$D$18:$D$1670=$B$42)*('W3'!$K$14:$AJ$14='Cover Page'!$D52))} -> 17727.293 | AC52: {=SUMPRODUCT('W3'!$K$18:$AJ$1670*('W3'!$A$18:$A$1670=AC$5)*('W3'!$D$18:$D$1670=$B$42)*('W3'!$K$14:$AJ$14='Cover Page'!$D52))} -> 24980.208 | AF52: {=SUMPRODUCT('W3'!$K$18:$AJ$1670*('W3'!$A$18:$A$1670=AF$5)*('W3'!$D$18:$D$1670=$B$42)*('W3'!$K$14:$AJ$14='Cover Page'!$D52))} -> 37085.59 | AI52: {=SUMPRODUCT('W3'!$K$18:$AJ$1670*('W3'!$A$18:$A$1670=AI$5)*('W3'!$D$18:$D$1670=$B$42)*('W3'!$K$14:$AJ$14='Cover Page'!$D52))} -> 37488.993
D53: 10 | E53: =IF(Currency="USD","USD","triệu VND") -> triệu VND | H53: {=SUMPRODUCT('W3'!$K$18:$AJ$1670*('W3'!$A$18:$A$1670=H$5)*('W3'!$D$18:$D$1670=$B$42)*('W3'!$K$14:$AJ$14='Cover Page'!$D53))} -> 34567.288 | K53: {=SUMPRODUCT('W3'!$K$18:$AJ$1670*('W3'!$A$18:$A$1670=K$5)*('W3'!$D$18:$D$1670=$B$42)*('W3'!$K$14:$AJ$14='Cover Page'!$D53))} -> 34943.365 | N53: {=SUMPRODUCT('W3'!$K$18:$AJ$1670*('W3'!$A$18:$A$1670=N$5)*('W3'!$D$18:$D$1670=$B$42)*('W3'!$K$14:$AJ$14='Cover Page'!$D53))} -> 28693.961 | Q53: {=SUMPRODUCT('W3'!$K$18:$AJ$1670*('W3'!$A$18:$A$1670=Q$5)*('W3'!$D$18:$D$1670=$B$42)*('W3'!$K$14:$AJ$14='Cover Page'!$D53))} -> 29070.039 | T53: {=SUMPRODUCT('W3'!$K$18:$AJ$1670*('W3'!$A$18:$A$1670=T$5)*('W3'!$D$18:$D$1670=$B$42)*('W3'!$K$14:$AJ$14='Cover Page'!$D53))} -> 20862.86 | W53: {=SUMPRODUCT('W3'!$K$18:$AJ$1670*('W3'!$A$18:$A$1670=W$5)*('W3'!$D$18:$D$1670=$B$42)*('W3'!$K$14:$AJ$14='Cover Page'!$D53))} -> 21238.937 | Z53: {=SUMPRODUCT('W3'!$K$18:$AJ$1670*('W3'!$A$18:$A$1670=Z$5)*('W3'!$D$18:$D$1670=$B$42)*('W3'!$K$14:$AJ$14='Cover Page'!$D53))} -> 16159.346 | AC53: {=SUMPRODUCT('W3'!$K$18:$AJ$1670*('W3'!$A$18:$A$1670=AC$5)*('W3'!$D$18:$D$1670=$B$42)*('W3'!$K$14:$AJ$14='Cover Page'!$D53))} -> 23048.673 | AF53: {=SUMPRODUCT('W3'!$K$18:$AJ$1670*('W3'!$A$18:$A$1670=AF$5)*('W3'!$D$18:$D$1670=$B$42)*('W3'!$K$14:$AJ$14='Cover Page'!$D53))} -> 34567.288 | AI53: {=SUMPRODUCT('W3'!$K$18:$AJ$1670*('W3'!$A$18:$A$1670=AI$5)*('W3'!$D$18:$D$1670=$B$42)*('W3'!$K$14:$AJ$14='Cover Page'!$D53))} -> 34943.365
D54: 11 | E54: =IF(Currency="USD","USD","triệu VND") -> triệu VND | H54: {=SUMPRODUCT('W3'!$K$18:$AJ$1670*('W3'!$A$18:$A$1670=H$5)*('W3'!$D$18:$D$1670=$B$42)*('W3'!$K$14:$AJ$14='Cover Page'!$D54))} -> 32189.07 | K54: {=SUMPRODUCT('W3'!$K$18:$AJ$1670*('W3'!$A$18:$A$1670=K$5)*('W3'!$D$18:$D$1670=$B$42)*('W3'!$K$14:$AJ$14='Cover Page'!$D54))} -> 32539.673 | N54: {=SUMPRODUCT('W3'!$K$18:$AJ$1670*('W3'!$A$18:$A$1670=N$5)*('W3'!$D$18:$D$1670=$B$42)*('W3'!$K$14:$AJ$14='Cover Page'!$D54))} -> 26604.082 | Q54: {=SUMPRODUCT('W3'!$K$18:$AJ$1670*('W3'!$A$18:$A$1670=Q$5)*('W3'!$D$18:$D$1670=$B$42)*('W3'!$K$14:$AJ$14='Cover Page'!$D54))} -> 26954.685 | T54: {=SUMPRODUCT('W3'!$K$18:$AJ$1670*('W3'!$A$18:$A$1670=T$5)*('W3'!$D$18:$D$1670=$B$42)*('W3'!$K$14:$AJ$14='Cover Page'!$D54))} -> 19157.432 | W54: {=SUMPRODUCT('W3'!$K$18:$AJ$1670*('W3'!$A$18:$A$1670=W$5)*('W3'!$D$18:$D$1670=$B$42)*('W3'!$K$14:$AJ$14='Cover Page'!$D54))} -> 19508.035 | Z54: {=SUMPRODUCT('W3'!$K$18:$AJ$1670*('W3'!$A$18:$A$1670=Z$5)*('W3'!$D$18:$D$1670=$B$42)*('W3'!$K$14:$AJ$14='Cover Page'!$D54))} -> 14684.828 | AC54: {=SUMPRODUCT('W3'!$K$18:$AJ$1670*('W3'!$A$18:$A$1670=AC$5)*('W3'!$D$18:$D$1670=$B$42)*('W3'!$K$14:$AJ$14='Cover Page'!$D54))} -> 21228.925 | AF54: {=SUMPRODUCT('W3'!$K$18:$AJ$1670*('W3'!$A$18:$A$1670=AF$5)*('W3'!$D$18:$D$1670=$B$42)*('W3'!$K$14:$AJ$14='Cover Page'!$D54))} -> 32189.07 | AI54: {=SUMPRODUCT('W3'!$K$18:$AJ$1670*('W3'!$A$18:$A$1670=AI$5)*('W3'!$D$18:$D$1670=$B$42)*('W3'!$K$14:$AJ$14='Cover Page'!$D54))} -> 32539.673
D55: 12 | E55: =IF(Currency="USD","USD","triệu VND") -> triệu VND | H55: {=SUMPRODUCT('W3'!$K$18:$AJ$1670*('W3'!$A$18:$A$1670=H$5)*('W3'!$D$18:$D$1670=$B$42)*('W3'!$K$14:$AJ$14='Cover Page'!$D55))} -> 29943.595 | K55: {=SUMPRODUCT('W3'!$K$18:$AJ$1670*('W3'!$A$18:$A$1670=K$5)*('W3'!$D$18:$D$1670=$B$42)*('W3'!$K$14:$AJ$14='Cover Page'!$D55))} -> 30270.449 | N55: {=SUMPRODUCT('W3'!$K$18:$AJ$1670*('W3'!$A$18:$A$1670=N$5)*('W3'!$D$18:$D$1670=$B$42)*('W3'!$K$14:$AJ$14='Cover Page'!$D55))} -> 24632.791 | Q55: {=SUMPRODUCT('W3'!$K$18:$AJ$1670*('W3'!$A$18:$A$1670=Q$5)*('W3'!$D$18:$D$1670=$B$42)*('W3'!$K$14:$AJ$14='Cover Page'!$D55))} -> 24959.644 | T55: {=SUMPRODUCT('W3'!$K$18:$AJ$1670*('W3'!$A$18:$A$1670=T$5)*('W3'!$D$18:$D$1670=$B$42)*('W3'!$K$14:$AJ$14='Cover Page'!$D55))} -> 17551.718 | W55: {=SUMPRODUCT('W3'!$K$18:$AJ$1670*('W3'!$A$18:$A$1670=W$5)*('W3'!$D$18:$D$1670=$B$42)*('W3'!$K$14:$AJ$14='Cover Page'!$D55))} -> 17878.572 | Z55: {=SUMPRODUCT('W3'!$K$18:$AJ$1670*('W3'!$A$18:$A$1670=Z$5)*('W3'!$D$18:$D$1670=$B$42)*('W3'!$K$14:$AJ$14='Cover Page'!$D55))} -> 13298.687 | AC55: {=SUMPRODUCT('W3'!$K$18:$AJ$1670*('W3'!$A$18:$A$1670=AC$5)*('W3'!$D$18:$D$1670=$B$42)*('W3'!$K$14:$AJ$14='Cover Page'!$D55))} -> 19514.979 | AF55: {=SUMPRODUCT('W3'!$K$18:$AJ$1670*('W3'!$A$18:$A$1670=AF$5)*('W3'!$D$18:$D$1670=$B$42)*('W3'!$K$14:$AJ$14='Cover Page'!$D55))} -> 29943.595 | AI55: {=SUMPRODUCT('W3'!$K$18:$AJ$1670*('W3'!$A$18:$A$1670=AI$5)*('W3'!$D$18:$D$1670=$B$42)*('W3'!$K$14:$AJ$14='Cover Page'!$D55))} -> 30270.449
... D68: 25 | E68: =IF(Currency="USD","USD","triệu VND") -> triệu VND | H68: {=SUMPRODUCT('W3'!$K$18:$AJ$1670*('W3'!$A$18:$A$1670=H$5)*('W3'!$D$18:$D$1670=$B$42)*('W3'!$K$14:$AJ$14='Cover Page'!$D68))} -> 0 | K68: {=SUMPRODUCT('W3'!$K$18:$AJ$1670*('W3'!$A$18:$A$1670=K$5)*('W3'!$D$18:$D$1670=$B$42)*('W3'!$K$14:$AJ$14='Cover Page'!$D68))} -> 0 | N68: {=SUMPRODUCT('W3'!$K$18:$AJ$1670*('W3'!$A$18:$A$1670=N$5)*('W3'!$D$18:$D$1670=$B$42)*('W3'!$K$14:$AJ$14='Cover Page'!$D68))} -> 0 | Q68: {=SUMPRODUCT('W3'!$K$18:$AJ$1670*('W3'!$A$18:$A$1670=Q$5)*('W3'!$D$18:$D$1670=$B$42)*('W3'!$K$14:$AJ$14='Cover Page'!$D68))} -> 0 | T68: {=SUMPRODUCT('W3'!$K$18:$AJ$1670*('W3'!$A$18:$A$1670=T$5)*('W3'!$D$18:$D$1670=$B$42)*('W3'!$K$14:$AJ$14='Cover Page'!$D68))} -> 0 | W68: {=SUMPRODUCT('W3'!$K$18:$AJ$1670*('W3'!$A$18:$A$1670=W$5)*('W3'!$D$18:$D$1670=$B$42)*('W3'!$K$14:$AJ$14='Cover Page'!$D68))} -> 0 | Z68: {=SUMPRODUCT('W3'!$K$18:$AJ$1670*('W3'!$A$18:$A$1670=Z$5)*('W3'!$D$18:$D$1670=$B$42)*('W3'!$K$14:$AJ$14='Cover Page'!$D68))} -> 0 | AC68: {=SUMPRODUCT('W3'!$K$18:$AJ$1670*('W3'!$A$18:$A$1670=AC$5)*('W3'!$D$18:$D$1670=$B$42)*('W3'!$K$14:$AJ$14='Cover Page'!$D68))} -> 0 | AF68: {=SUMPRODUCT('W3'!$K$18:$AJ$1670*('W3'!$A$18:$A$1670=AF$5)*('W3'!$D$18:$D$1670=$B$42)*('W3'!$K$14:$AJ$14='Cover Page'!$D68))} -> 0 | AI68: {=SUMPRODUCT('W3'!$K$18:$AJ$1670*('W3'!$A$18:$A$1670=AI$5)*('W3'!$D$18:$D$1670=$B$42)*('W3'!$K$14:$AJ$14='Cover Page'!$D68))} -> 0
I70: %Dthu | L70: %Dthu | O70: %Dthu | R70: %Dthu | U70: %Dthu | X70: %Dthu | AA70: %Dthu | AD70: %Dthu | AG70: %Dthu | AJ70: %Dthu
B71: LNST | C71: 15 | D71: LNST | E71: =IF(Currency="USD","USD","triệu VND") -> triệu VND | H71: =SUM(H72:H96) -> 548996.38 | I71: =IFERROR(H71/H98,0) -> 0.11858117 | K71: =SUM(K72:K96) -> 416031.15 | L71: =IFERROR(K71/K98,0) -> 0.089861178 | N71: =SUM(N72:N96) -> 385594.87 | O71: =IFERROR(N71/N98,0) -> 0.087131072 | Q71: =SUM(Q72:Q96) -> 252629.64 | R71: =IFERROR(Q71/Q98,0) -> 0.05708554 | T71: =SUM(T72:T96) -> 167726.18 | U71: =IFERROR(T71/T98,0) -> 0.040385568 | W71: =SUM(W72:W96) -> 34760.956 | X71: =IFERROR(W71/W98,0) -> 0.0083698379 | Z71: =SUM(Z72:Z96) -> 36869.983 | AA71: =IFERROR(Z71/Z98,0) -> 0.009241636 | AC71: =SUM(AC72:AC96) -> 85109.513 | AD71: =IFERROR(AC71/AC98,0) -> 0.020186991 | AF71: =SUM(AF72:AF96) -> 548996.38 | AG71: =IFERROR(AF71/AF98,0) -> 0.11858117 | AI71: =SUM(AI72:AI96) -> 416031.15 | AJ71: =IFERROR(AI71/AI98,0) -> 0.089861178
D72: 1 | E72: =IF(Currency="USD","USD","triệu VND") -> triệu VND | H72: {=SUMPRODUCT('W3'!$K$18:$AJ$1670*('W3'!$A$18:$A$1670=H$5)*('W3'!$D$18:$D$1670=$B$71)*('W3'!$K$14:$AJ$14='Cover Page'!$D72))} -> -10585.928 | I72: =IFERROR(H72/H99,0) -> -0.075397648 | K72: {=SUMPRODUCT('W3'!$K$18:$AJ$1670*('W3'!$A$18:$A$1670=K$5)*('W3'!$D$18:$D$1670=$B$71)*('W3'!$K$14:$AJ$14='Cover Page'!$D72))} -> -21707.528 | L72: =IFERROR(K72/K99,0) -> -0.15461059 | N72: {=SUMPRODUCT('W3'!$K$18:$AJ$1670*('W3'!$A$18:$A$1670=N$5)*('W3'!$D$18:$D$1670=$B$71)*('W3'!$K$14:$AJ$14='Cover Page'!$D72))} -> -15541.268 | O72: =IFERROR(N72/N99,0) -> -0.11580062 | Q72: {=SUMPRODUCT('W3'!$K$18:$AJ$1670*('W3'!$A$18:$A$1670=Q$5)*('W3'!$D$18:$D$1670=$B$71)*('W3'!$K$14:$AJ$14='Cover Page'!$D72))} -> -26662.868 | R72: =IFERROR(Q72/Q99,0) -> -0.19866954 | T72: {=SUMPRODUCT('W3'!$K$18:$AJ$1670*('W3'!$A$18:$A$1670=T$5)*('W3'!$D$18:$D$1670=$B$71)*('W3'!$K$14:$AJ$14='Cover Page'!$D72))} -> -22148.388 | U72: =IFERROR(T72/T99,0) -> -0.17585312 | W72: {=SUMPRODUCT('W3'!$K$18:$AJ$1670*('W3'!$A$18:$A$1670=W$5)*('W3'!$D$18:$D$1670=$B$71)*('W3'!$K$14:$AJ$14='Cover Page'!$D72))} -> -33269.988 | X72: =IFERROR(W72/W99,0) -> -0.26415607 | Z72: {=SUMPRODUCT('W3'!$K$18:$AJ$1670*('W3'!$A$18:$A$1670=Z$5)*('W3'!$D$18:$D$1670=$B$71)*('W3'!$K$14:$AJ$14='Cover Page'!$D72))} -> -26116.753 | AA72: =IFERROR(Z72/Z99,0) -> -0.21586276 | AC72: {=SUMPRODUCT('W3'!$K$18:$AJ$1670*('W3'!$A$18:$A$1670=AC$5)*('W3'!$D$18:$D$1670=$B$71)*('W3'!$K$14:$AJ$14='Cover Page'!$D72))} -> -31743.109 | AD72: =IFERROR(AC72/AC99,0) -> -0.24827075 | AF72: {=SUMPRODUCT('W3'!$K$18:$AJ$1670*('W3'!$A$18:$A$1670=AF$5)*('W3'!$D$18:$D$1670=$B$71)*('W3'!$K$14:$AJ$14='Cover Page'!$D72))} -> -10585.928 | AG72: =IFERROR(AF72/AF99,0) -> -0.075397648 | AI72: {=SUMPRODUCT('W3'!$K$18:$AJ$1670*('W3'!$A$18:$A$1670=AI$5)*('W3'!$D$18:$D$1670=$B$71)*('W3'!$K$14:$AJ$14='Cover Page'!$D72))} -> -21707.528 | AJ72: =IFERROR(AI72/AI99,0) -> -0.15461059 | AL72: {=TRANSPOSE('W3'!L23:AJ23*'W3'!L24:AJ24)} -> 0.44
D73: 2 | E73: =IF(Currency="USD","USD","triệu VND") -> triệu VND | H73: {=SUMPRODUCT('W3'!$K$18:$AJ$1670*('W3'!$A$18:$A$1670=H$5)*('W3'!$D$18:$D$1670=$B$71)*('W3'!$K$14:$AJ$14='Cover Page'!$D73))} -> 8036.3006 | I73: =IFERROR(H73/H100,0) -> 0.040082688 | K73: {=SUMPRODUCT('W3'!$K$18:$AJ$1670*('W3'!$A$18:$A$1670=K$5)*('W3'!$D$18:$D$1670=$B$71)*('W3'!$K$14:$AJ$14='Cover Page'!$D73))} -> -2851.307 | L73: =IFERROR(K73/K100,0) -> -0.014221475 | N73: {=SUMPRODUCT('W3'!$K$18:$AJ$1670*('W3'!$A$18:$A$1670=N$5)*('W3'!$D$18:$D$1670=$B$71)*('W3'!$K$14:$AJ$14='Cover Page'!$D73))} -> 960.07513 | O73: =IFERROR(N73/N100,0) -> 0.0050095815 | Q73: {=SUMPRODUCT('W3'!$K$18:$AJ$1670*('W3'!$A$18:$A$1670=Q$5)*('W3'!$D$18:$D$1670=$B$71)*('W3'!$K$14:$AJ$14='Cover Page'!$D73))} -> -9927.5325 | R73: =IFERROR(Q73/Q100,0) -> -0.051800928 | T73: {=SUMPRODUCT('W3'!$K$18:$AJ$1670*('W3'!$A$18:$A$1670=T$5)*('W3'!$D$18:$D$1670=$B$71)*('W3'!$K$14:$AJ$14='Cover Page'!$D73))} -> -8474.8922 | U73: =IFERROR(T73/T100,0) -> -0.047120938 | W73: {=SUMPRODUCT('W3'!$K$18:$AJ$1670*('W3'!$A$18:$A$1670=W$5)*('W3'!$D$18:$D$1670=$B$71)*('W3'!$K$14:$AJ$14='Cover Page'!$D73))} -> -19362.5 | X73: =IFERROR(W73/W100,0) -> -0.10765673 | Z73: {=SUMPRODUCT('W3'!$K$18:$AJ$1670*('W3'!$A$18:$A$1670=Z$5)*('W3'!$D$18:$D$1670=$B$71)*('W3'!$K$14:$AJ$14='Cover Page'!$D73))} -> -14141.718 | AA73: =IFERROR(Z73/Z100,0) -> -0.081852607 | AC73: {=SUMPRODUCT('W3'!$K$18:$AJ$1670*('W3'!$A$18:$A$1670=AC$5)*('W3'!$D$18:$D$1670=$B$71)*('W3'!$K$14:$AJ$14='Cover Page'!$D73))} -> -17182.118 | AD73: =IFERROR(AC73/AC100,0) -> -0.094107573 | AF73: {=SUMPRODUCT('W3'!$K$18:$AJ$1670*('W3'!$A$18:$A$1670=AF$5)*('W3'!$D$18:$D$1670=$B$71)*('W3'!$K$14:$AJ$14='Cover Page'!$D73))} -> 8036.3006 | AG73: =IFERROR(AF73/AF100,0) -> 0.040082688 | AI73: {=SUMPRODUCT('W3'!$K$18:$AJ$1670*('W3'!$A$18:$A$1670=AI$5)*('W3'!$D$18:$D$1670=$B$71)*('W3'!$K$14:$AJ$14='Cover Page'!$D73))} -> -2851.307 | AJ73: =IFERROR(AI73/AI100,0) -> -0.014221475 | AL73: 0.616
D74: 3 | E74: =IF(Currency="USD","USD","triệu VND") -> triệu VND | H74: {=SUMPRODUCT('W3'!$K$18:$AJ$1670*('W3'!$A$18:$A$1670=H$5)*('W3'!$D$18:$D$1670=$B$71)*('W3'!$K$14:$AJ$14='Cover Page'!$D74))} -> 32742.523 | I74: =IFERROR(H74/H101,0) -> 0.1120755 | K74: {=SUMPRODUCT('W3'!$K$18:$AJ$1670*('W3'!$A$18:$A$1670=K$5)*('W3'!$D$18:$D$1670=$B$71)*('W3'!$K$14:$AJ$14='Cover Page'!$D74))} -> 22105.288 | L74: =IFERROR(K74/K101,0) -> 0.075664942 | N74: {=SUMPRODUCT('W3'!$K$18:$AJ$1670*('W3'!$A$18:$A$1670=N$5)*('W3'!$D$18:$D$1670=$B$71)*('W3'!$K$14:$AJ$14='Cover Page'!$D74))} -> 22431.452 | O74: =IFERROR(N74/N101,0) -> 0.080325137 | Q74: {=SUMPRODUCT('W3'!$K$18:$AJ$1670*('W3'!$A$18:$A$1670=Q$5)*('W3'!$D$18:$D$1670=$B$71)*('W3'!$K$14:$AJ$14='Cover Page'!$D74))} -> 11794.216 | R74: =IFERROR(Q74/Q101,0) -> 0.042234093 | T74: {=SUMPRODUCT('W3'!$K$18:$AJ$1670*('W3'!$A$18:$A$1670=T$5)*('W3'!$D$18:$D$1670=$B$71)*('W3'!$K$14:$AJ$14='Cover Page'!$D74))} -> 8683.3568 | U74: =IFERROR(T74/T101,0) -> 0.033133343 | W74: {=SUMPRODUCT('W3'!$K$18:$AJ$1670*('W3'!$A$18:$A$1670=W$5)*('W3'!$D$18:$D$1670=$B$71)*('W3'!$K$14:$AJ$14='Cover Page'!$D74))} -> -1953.879 | X74: =IFERROR(W74/W101,0) -> -0.0074554742 | Z74: {=SUMPRODUCT('W3'!$K$18:$AJ$1670*('W3'!$A$18:$A$1670=Z$5)*('W3'!$D$18:$D$1670=$B$71)*('W3'!$K$14:$AJ$14='Cover Page'!$D74))} -> 425.98139 | AA74: =IFERROR(Z74/Z101,0) -> 0.0016920719 | AC74: {=SUMPRODUCT('W3'!$K$18:$AJ$1670*('W3'!$A$18:$A$1670=AC$5)*('W3'!$D$18:$D$1670=$B$71)*('W3'!$K$14:$AJ$14='Cover Page'!$D74))} -> 1223.2493 | AD74: =IFERROR(AC74/AC101,0) -> 0.0045979128 | AF74: {=SUMPRODUCT('W3'!$K$18:$AJ$1670*('W3'!$A$18:$A$1670=AF$5)*('W3'!$D$18:$D$1670=$B$71)*('W3'!$K$14:$AJ$14='Cover Page'!$D74))} -> 32742.523 | AG74: =IFERROR(AF74/AF101,0) -> 0.1120755 | AI74: {=SUMPRODUCT('W3'!$K$18:$AJ$1670*('W3'!$A$18:$A$1670=AI$5)*('W3'!$D$18:$D$1670=$B$71)*('W3'!$K$14:$AJ$14='Cover Page'!$D74))} -> 22105.288 | AJ74: =IFERROR(AI74/AI101,0) -> 0.075664942 | AL74: 0.88
D75: 4 | E75: =IF(Currency="USD","USD","triệu VND") -> triệu VND | H75: {=SUMPRODUCT('W3'!$K$18:$AJ$1670*('W3'!$A$18:$A$1670=H$5)*('W3'!$D$18:$D$1670=$B$71)*('W3'!$K$14:$AJ$14='Cover Page'!$D75))} -> 33583.435 | I75: =IFERROR(H75/H102,0) -> 0.11269988 | K75: {=SUMPRODUCT('W3'!$K$18:$AJ$1670*('W3'!$A$18:$A$1670=K$5)*('W3'!$D$18:$D$1670=$B$71)*('W3'!$K$14:$AJ$14='Cover Page'!$D75))} -> 23214.097 | L75: =IFERROR(K75/K102,0) -> 0.077902277 | N75: {=SUMPRODUCT('W3'!$K$18:$AJ$1670*('W3'!$A$18:$A$1670=N$5)*('W3'!$D$18:$D$1670=$B$71)*('W3'!$K$14:$AJ$14='Cover Page'!$D75))} -> 23066.142 | O75: =IFERROR(N75/N102,0) -> 0.080978341 | Q75: {=SUMPRODUCT('W3'!$K$18:$AJ$1670*('W3'!$A$18:$A$1670=Q$5)*('W3'!$D$18:$D$1670=$B$71)*('W3'!$K$14:$AJ$14='Cover Page'!$D75))} -> 12696.804 | R75: =IFERROR(Q75/Q102,0) -> 0.04457469 | T75: {=SUMPRODUCT('W3'!$K$18:$AJ$1670*('W3'!$A$18:$A$1670=T$5)*('W3'!$D$18:$D$1670=$B$71)*('W3'!$K$14:$AJ$14='Cover Page'!$D75))} -> 9043.0846 | U75: =IFERROR(T75/T102,0) -> 0.03382938 | W75: {=SUMPRODUCT('W3'!$K$18:$AJ$1670*('W3'!$A$18:$A$1670=W$5)*('W3'!$D$18:$D$1670=$B$71)*('W3'!$K$14:$AJ$14='Cover Page'!$D75))} -> -1326.2532 | X75: =IFERROR(W75/W102,0) -> -0.0049613959 | Z75: {=SUMPRODUCT('W3'!$K$18:$AJ$1670*('W3'!$A$18:$A$1670=Z$5)*('W3'!$D$18:$D$1670=$B$71)*('W3'!$K$14:$AJ$14='Cover Page'!$D75))} -> 620.56176 | AA75: =IFERROR(Z75/Z102,0) -> 0.002416646 | AC75: {=SUMPRODUCT('W3'!$K$18:$AJ$1670*('W3'!$A$18:$A$1670=AC$5)*('W3'!$D$18:$D$1670=$B$71)*('W3'!$K$14:$AJ$14='Cover Page'!$D75))} -> 1914.4176 | AD75: =IFERROR(AC75/AC102,0) -> 0.0070547604 | AF75: {=SUMPRODUCT('W3'!$K$18:$AJ$1670*('W3'!$A$18:$A$1670=AF$5)*('W3'!$D$18:$D$1670=$B$71)*('W3'!$K$14:$AJ$14='Cover Page'!$D75))} -> 33583.435 | AG75: =IFERROR(AF75/AF102,0) -> 0.11269988 | AI75: {=SUMPRODUCT('W3'!$K$18:$AJ$1670*('W3'!$A$18:$A$1670=AI$5)*('W3'!$D$18:$D$1670=$B$71)*('W3'!$K$14:$AJ$14='Cover Page'!$D75))} -> 23214.097 | AJ75: =IFERROR(AI75/AI102,0) -> 0.077902277 | AL75: 0.88
D76: 5 | E76: =IF(Currency="USD","USD","triệu VND") -> triệu VND | H76: {=SUMPRODUCT('W3'!$K$18:$AJ$1670*('W3'!$A$18:$A$1670=H$5)*('W3'!$D$18:$D$1670=$B$71)*('W3'!$K$14:$AJ$14='Cover Page'!$D76))} -> 34418.296 | I76: =IFERROR(H76/H103,0) -> 0.11323679 | K76: {=SUMPRODUCT('W3'!$K$18:$AJ$1670*('W3'!$A$18:$A$1670=K$5)*('W3'!$D$18:$D$1670=$B$71)*('W3'!$K$14:$AJ$14='Cover Page'!$D76))} -> 24335.609 | L76: =IFERROR(K76/K103,0) -> 0.080064577 | N76: {=SUMPRODUCT('W3'!$K$18:$AJ$1670*('W3'!$A$18:$A$1670=N$5)*('W3'!$D$18:$D$1670=$B$71)*('W3'!$K$14:$AJ$14='Cover Page'!$D76))} -> 23690.658 | O76: =IFERROR(N76/N103,0) -> 0.08154003 | Q76: {=SUMPRODUCT('W3'!$K$18:$AJ$1670*('W3'!$A$18:$A$1670=Q$5)*('W3'!$D$18:$D$1670=$B$71)*('W3'!$K$14:$AJ$14='Cover Page'!$D76))} -> 13607.971 | R76: =IFERROR(Q76/Q103,0) -> 0.046836789 | T76: {=SUMPRODUCT('W3'!$K$18:$AJ$1670*('W3'!$A$18:$A$1670=T$5)*('W3'!$D$18:$D$1670=$B$71)*('W3'!$K$14:$AJ$14='Cover Page'!$D76))} -> 9387.1395 | U76: =IFERROR(T76/T103,0) -> 0.0344279 | W76: {=SUMPRODUCT('W3'!$K$18:$AJ$1670*('W3'!$A$18:$A$1670=W$5)*('W3'!$D$18:$D$1670=$B$71)*('W3'!$K$14:$AJ$14='Cover Page'!$D76))} -> -695.54766 | X76: =IFERROR(W76/W103,0) -> -0.002550963 | Z76: {=SUMPRODUCT('W3'!$K$18:$AJ$1670*('W3'!$A$18:$A$1670=Z$5)*('W3'!$D$18:$D$1670=$B$71)*('W3'!$K$14:$AJ$14='Cover Page'!$D76))} -> 796.16611 | AA76: =IFERROR(Z76/Z103,0) -> 0.0030397057 | AC76: {=SUMPRODUCT('W3'!$K$18:$AJ$1670*('W3'!$A$18:$A$1670=AC$5)*('W3'!$D$18:$D$1670=$B$71)*('W3'!$K$14:$AJ$14='Cover Page'!$D76))} -> 2609.9366 | AD76: =IFERROR(AC76/AC103,0) -> 0.0094292113 | AF76: {=SUMPRODUCT('W3'!$K$18:$AJ$1670*('W3'!$A$18:$A$1670=AF$5)*('W3'!$D$18:$D$1670=$B$71)*('W3'!$K$14:$AJ$14='Cover Page'!$D76))} -> 34418.296 | AG76: =IFERROR(AF76/AF103,0) -> 0.11323679 | AI76: {=SUMPRODUCT('W3'!$K$18:$AJ$1670*('W3'!$A$18:$A$1670=AI$5)*('W3'!$D$18:$D$1670=$B$71)*('W3'!$K$14:$AJ$14='Cover Page'!$D76))} -> 24335.609 | AJ76: =IFERROR(AI76/AI103,0) -> 0.080064577 | AL76: 0.88
D77: 6 | E77: =IF(Currency="USD","USD","triệu VND") -> triệu VND | H77: {=SUMPRODUCT('W3'!$K$18:$AJ$1670*('W3'!$A$18:$A$1670=H$5)*('W3'!$D$18:$D$1670=$B$71)*('W3'!$K$14:$AJ$14='Cover Page'!$D77))} -> 35246.382 | I77: =IFERROR(H77/H104,0) -> 0.11368746 | K77: {=SUMPRODUCT('W3'!$K$18:$AJ$1670*('W3'!$A$18:$A$1670=K$5)*('W3'!$D$18:$D$1670=$B$71)*('W3'!$K$14:$AJ$14='Cover Page'!$D77))} -> 25470.411 | L77: =IFERROR(K77/K104,0) -> 0.082154994 | N77: {=SUMPRODUCT('W3'!$K$18:$AJ$1670*('W3'!$A$18:$A$1670=N$5)*('W3'!$D$18:$D$1670=$B$71)*('W3'!$K$14:$AJ$14='Cover Page'!$D77))} -> 24304.19 | O77: =IFERROR(N77/N104,0) -> 0.082011495 | Q77: {=SUMPRODUCT('W3'!$K$18:$AJ$1670*('W3'!$A$18:$A$1670=Q$5)*('W3'!$D$18:$D$1670=$B$71)*('W3'!$K$14:$AJ$14='Cover Page'!$D77))} -> 14528.219 | R77: =IFERROR(Q77/Q104,0) -> 0.049023686 | T77: {=SUMPRODUCT('W3'!$K$18:$AJ$1670*('W3'!$A$18:$A$1670=T$5)*('W3'!$D$18:$D$1670=$B$71)*('W3'!$K$14:$AJ$14='Cover Page'!$D77))} -> 9714.6015 | U77: =IFERROR(T77/T104,0) -> 0.034930281 | W77: {=SUMPRODUCT('W3'!$K$18:$AJ$1670*('W3'!$A$18:$A$1670=W$5)*('W3'!$D$18:$D$1670=$B$71)*('W3'!$K$14:$AJ$14='Cover Page'!$D77))} -> -61.369353 | X77: =IFERROR(W77/W104,0) -> -0.00022066255 | Z77: {=SUMPRODUCT('W3'!$K$18:$AJ$1670*('W3'!$A$18:$A$1670=Z$5)*('W3'!$D$18:$D$1670=$B$71)*('W3'!$K$14:$AJ$14='Cover Page'!$D77))} -> 951.80865 | AA77: =IFERROR(Z77/Z104,0) -> 0.0035626842 | AC77: {=SUMPRODUCT('W3'!$K$18:$AJ$1670*('W3'!$A$18:$A$1670=AC$5)*('W3'!$D$18:$D$1670=$B$71)*('W3'!$K$14:$AJ$14='Cover Page'!$D77))} -> 3310.2246 | AD77: =IFERROR(AC77/AC104,0) -> 0.011724726 | AF77: {=SUMPRODUCT('W3'!$K$18:$AJ$1670*('W3'!$A$18:$A$1670=AF$5)*('W3'!$D$18:$D$1670=$B$71)*('W3'!$K$14:$AJ$14='Cover Page'!$D77))} -> 35246.382 | AG77: =IFERROR(AF77/AF104,0) -> 0.11368746 | AI77: {=SUMPRODUCT('W3'!$K$18:$AJ$1670*('W3'!$A$18:$A$1670=AI$5)*('W3'!$D$18:$D$1670=$B$71)*('W3'!$K$14:$AJ$14='Cover Page'!$D77))} -> 25470.411 | AJ77: =IFERROR(AI77/AI104,0) -> 0.082154994 | AL77: 0.88
D78: 7 | E78: =IF(Currency="USD","USD","triệu VND") -> triệu VND | H78: {=SUMPRODUCT('W3'!$K$18:$AJ$1670*('W3'!$A$18:$A$1670=H$5)*('W3'!$D$18:$D$1670=$B$71)*('W3'!$K$14:$AJ$14='Cover Page'!$D78))} -> 36066.956 | I78: =IFERROR(H78/H105,0) -> 0.11405316 | K78: {=SUMPRODUCT('W3'!$K$18:$AJ$1670*('W3'!$A$18:$A$1670=K$5)*('W3'!$D$18:$D$1670=$B$71)*('W3'!$K$14:$AJ$14='Cover Page'!$D78))} -> 26619.171 | L78: =IFERROR(K78/K105,0) -> 0.084176793 | N78: {=SUMPRODUCT('W3'!$K$18:$AJ$1670*('W3'!$A$18:$A$1670=N$5)*('W3'!$D$18:$D$1670=$B$71)*('W3'!$K$14:$AJ$14='Cover Page'!$D78))} -> 24905.92 | O78: =IFERROR(N78/N105,0) -> 0.082394078 | Q78: {=SUMPRODUCT('W3'!$K$18:$AJ$1670*('W3'!$A$18:$A$1670=Q$5)*('W3'!$D$18:$D$1670=$B$71)*('W3'!$K$14:$AJ$14='Cover Page'!$D78))} -> 15458.136 | R78: =IFERROR(Q78/Q105,0) -> 0.051138799 | T78: {=SUMPRODUCT('W3'!$K$18:$AJ$1670*('W3'!$A$18:$A$1670=T$5)*('W3'!$D$18:$D$1670=$B$71)*('W3'!$K$14:$AJ$14='Cover Page'!$D78))} -> 10024.54 | U78: =IFERROR(T78/T105,0) -> 0.035337952 | W78: {=SUMPRODUCT('W3'!$K$18:$AJ$1670*('W3'!$A$18:$A$1670=W$5)*('W3'!$D$18:$D$1670=$B$71)*('W3'!$K$14:$AJ$14='Cover Page'!$D78))} -> 576.75549 | X78: =IFERROR(W78/W105,0) -> 0.0020331464 | Z78: {=SUMPRODUCT('W3'!$K$18:$AJ$1670*('W3'!$A$18:$A$1670=Z$5)*('W3'!$D$18:$D$1670=$B$71)*('W3'!$K$14:$AJ$14='Cover Page'!$D78))} -> 1086.4912 | AA78: =IFERROR(Z78/Z105,0) -> 0.0039870688 | AC78: {=SUMPRODUCT('W3'!$K$18:$AJ$1670*('W3'!$A$18:$A$1670=AC$5)*('W3'!$D$18:$D$1670=$B$71)*('W3'!$K$14:$AJ$14='Cover Page'!$D78))} -> 4015.7813 | AD78: =IFERROR(AC78/AC105,0) -> 0.013944891 | AF78: {=SUMPRODUCT('W3'!$K$18:$AJ$1670*('W3'!$A$18:$A$1670=AF$5)*('W3'!$D$18:$D$1670=$B$71)*('W3'!$K$14:$AJ$14='Cover Page'!$D78))} -> 36066.956 | AG78: =IFERROR(AF78/AF105,0) -> 0.11405316 | AI78: {=SUMPRODUCT('W3'!$K$18:$AJ$1670*('W3'!$A$18:$A$1670=AI$5)*('W3'!$D$18:$D$1670=$B$71)*('W3'!$K$14:$AJ$14='Cover Page'!$D78))} -> 26619.171 | AJ78: =IFERROR(AI78/AI105,0) -> 0.084176793 | AL78: 0.88
D79: 8 | E79: =IF(Currency="USD","USD","triệu VND") -> triệu VND | H79: {=SUMPRODUCT('W3'!$K$18:$AJ$1670*('W3'!$A$18:$A$1670=H$5)*('W3'!$D$18:$D$1670=$B$71)*('W3'!$K$14:$AJ$14='Cover Page'!$D79))} -> 36879.28 | I79: =IFERROR(H79/H106,0) -> 0.11433524 | K79: {=SUMPRODUCT('W3'!$K$18:$AJ$1670*('W3'!$A$18:$A$1670=K$5)*('W3'!$D$18:$D$1670=$B$71)*('W3'!$K$14:$AJ$14='Cover Page'!$D79))} -> 27782.655 | L79: =IFERROR(K79/K106,0) -> 0.086133365 | N79: {=SUMPRODUCT('W3'!$K$18:$AJ$1670*('W3'!$A$18:$A$1670=N$5)*('W3'!$D$18:$D$1670=$B$71)*('W3'!$K$14:$AJ$14='Cover Page'!$D79))} -> 25495.024 | O79: =IFERROR(N79/N106,0) -> 0.082689173 | Q79: {=SUMPRODUCT('W3'!$K$18:$AJ$1670*('W3'!$A$18:$A$1670=Q$5)*('W3'!$D$18:$D$1670=$B$71)*('W3'!$K$14:$AJ$14='Cover Page'!$D79))} -> 16398.399 | R79: =IFERROR(Q79/Q106,0) -> 0.053185674 | T79: {=SUMPRODUCT('W3'!$K$18:$AJ$1670*('W3'!$A$18:$A$1670=T$5)*('W3'!$D$18:$D$1670=$B$71)*('W3'!$K$14:$AJ$14='Cover Page'!$D79))} -> 10316.016 | U79: =IFERROR(T79/T106,0) -> 0.035652397 | W79: {=SUMPRODUCT('W3'!$K$18:$AJ$1670*('W3'!$A$18:$A$1670=W$5)*('W3'!$D$18:$D$1670=$B$71)*('W3'!$K$14:$AJ$14='Cover Page'!$D79))} -> 1219.3906 | X79: =IFERROR(W79/W106,0) -> 0.0042142433 | Z79: {=SUMPRODUCT('W3'!$K$18:$AJ$1670*('W3'!$A$18:$A$1670=Z$5)*('W3'!$D$18:$D$1670=$B$71)*('W3'!$K$14:$AJ$14='Cover Page'!$D79))} -> 1199.2059 | AA79: =IFERROR(Z79/Z106,0) -> 0.0043144068 | AC79: {=SUMPRODUCT('W3'!$K$18:$AJ$1670*('W3'!$A$18:$A$1670=AC$5)*('W3'!$D$18:$D$1670=$B$71)*('W3'!$K$14:$AJ$14='Cover Page'!$D79))} -> 4727.197 | AD79: =IFERROR(AC79/AC106,0) -> 0.016093429 | AF79: {=SUMPRODUCT('W3'!$K$18:$AJ$1670*('W3'!$A$18:$A$1670=AF$5)*('W3'!$D$18:$D$1670=$B$71)*('W3'!$K$14:$AJ$14='Cover Page'!$D79))} -> 36879.28 | AG79: =IFERROR(AF79/AF106,0) -> 0.11433524 | AI79: {=SUMPRODUCT('W3'!$K$18:$AJ$1670*('W3'!$A$18:$A$1670=AI$5)*('W3'!$D$18:$D$1670=$B$71)*('W3'!$K$14:$AJ$14='Cover Page'!$D79))} -> 27782.655 | AJ79: =IFERROR(AI79/AI106,0) -> 0.086133365 | AL79: 0.88
D80: 9 | E80: =IF(Currency="USD","USD","triệu VND") -> triệu VND | H80: {=SUMPRODUCT('W3'!$K$18:$AJ$1670*('W3'!$A$18:$A$1670=H$5)*('W3'!$D$18:$D$1670=$B$71)*('W3'!$K$14:$AJ$14='Cover Page'!$D80))} -> 37682.613 | I80: =IFERROR(H80/H107,0) -> 0.11453508 | K80: {=SUMPRODUCT('W3'!$K$18:$AJ$1670*('W3'!$A$18:$A$1670=K$5)*('W3'!$D$18:$D$1670=$B$71)*('W3'!$K$14:$AJ$14='Cover Page'!$D80))} -> 28961.729 | L80: =IFERROR(K80/K107,0) -> 0.088028234 | N80: {=SUMPRODUCT('W3'!$K$18:$AJ$1670*('W3'!$A$18:$A$1670=N$5)*('W3'!$D$18:$D$1670=$B$71)*('W3'!$K$14:$AJ$14='Cover Page'!$D80))} -> 26070.672 | O80: =IFERROR(N80/N107,0) -> 0.082898236 | Q80: {=SUMPRODUCT('W3'!$K$18:$AJ$1670*('W3'!$A$18:$A$1670=Q$5)*('W3'!$D$18:$D$1670=$B$71)*('W3'!$K$14:$AJ$14='Cover Page'!$D80))} -> 17349.788 | R80: =IFERROR(Q80/Q107,0) -> 0.055167999 | T80: {=SUMPRODUCT('W3'!$K$18:$AJ$1670*('W3'!$A$18:$A$1670=T$5)*('W3'!$D$18:$D$1670=$B$71)*('W3'!$K$14:$AJ$14='Cover Page'!$D80))} -> 10588.084 | U80: =IFERROR(T80/T107,0) -> 0.03587517 | W80: {=SUMPRODUCT('W3'!$K$18:$AJ$1670*('W3'!$A$18:$A$1670=W$5)*('W3'!$D$18:$D$1670=$B$71)*('W3'!$K$14:$AJ$14='Cover Page'!$D80))} -> 1867.1999 | X80: =IFERROR(W80/W107,0) -> 0.0063265565 | Z80: {=SUMPRODUCT('W3'!$K$18:$AJ$1670*('W3'!$A$18:$A$1670=Z$5)*('W3'!$D$18:$D$1670=$B$71)*('W3'!$K$14:$AJ$14='Cover Page'!$D80))} -> 1288.9383 | AA80: =IFERROR(Z80/Z107,0) -> 0.0045463125 | AC80: {=SUMPRODUCT('W3'!$K$18:$AJ$1670*('W3'!$A$18:$A$1670=AC$5)*('W3'!$D$18:$D$1670=$B$71)*('W3'!$K$14:$AJ$14='Cover Page'!$D80))} -> 5445.1623 | AD80: =IFERROR(AC80/AC107,0) -> 0.018174211 | AF80: {=SUMPRODUCT('W3'!$K$18:$AJ$1670*('W3'!$A$18:$A$1670=AF$5)*('W3'!$D$18:$D$1670=$B$71)*('W3'!$K$14:$AJ$14='Cover Page'!$D80))} -> 37682.613 | AG80: =IFERROR(AF80/AF107,0) -> 0.11453508 | AI80: {=SUMPRODUCT('W3'!$K$18:$AJ$1670*('W3'!$A$18:$A$1670=AI$5)*('W3'!$D$18:$D$1670=$B$71)*('W3'!$K$14:$AJ$14='Cover Page'!$D80))} -> 28961.729 | AJ80: =IFERROR(AI80/AI107,0) -> 0.088028234 | AL80: 0.88
D81: 10 | E81: =IF(Currency="USD","USD","triệu VND") -> triệu VND | H81: {=SUMPRODUCT('W3'!$K$18:$AJ$1670*('W3'!$A$18:$A$1670=H$5)*('W3'!$D$18:$D$1670=$B$71)*('W3'!$K$14:$AJ$14='Cover Page'!$D81))} -> 38476.22 | I81: =IFERROR(H81/H108,0) -> 0.11465414 | K81: {=SUMPRODUCT('W3'!$K$18:$AJ$1670*('W3'!$A$18:$A$1670=K$5)*('W3'!$D$18:$D$1670=$B$71)*('W3'!$K$14:$AJ$14='Cover Page'!$D81))} -> 30157.378 | L81: =IFERROR(K81/K108,0) -> 0.089865068 | N81: {=SUMPRODUCT('W3'!$K$18:$AJ$1670*('W3'!$A$18:$A$1670=N$5)*('W3'!$D$18:$D$1670=$B$71)*('W3'!$K$14:$AJ$14='Cover Page'!$D81))} -> 26632.04 | O81: =IFERROR(N81/N108,0) -> 0.083022789 | Q81: {=SUMPRODUCT('W3'!$K$18:$AJ$1670*('W3'!$A$18:$A$1670=Q$5)*('W3'!$D$18:$D$1670=$B$71)*('W3'!$K$14:$AJ$14='Cover Page'!$D81))} -> 18313.198 | R81: =IFERROR(Q81/Q108,0) -> 0.05708961 | T81: {=SUMPRODUCT('W3'!$K$18:$AJ$1670*('W3'!$A$18:$A$1670=T$5)*('W3'!$D$18:$D$1670=$B$71)*('W3'!$K$14:$AJ$14='Cover Page'!$D81))} -> 10839.8 | U81: =IFERROR(T81/T108,0) -> 0.036007889 | W81: {=SUMPRODUCT('W3'!$K$18:$AJ$1670*('W3'!$A$18:$A$1670=W$5)*('W3'!$D$18:$D$1670=$B$71)*('W3'!$K$14:$AJ$14='Cover Page'!$D81))} -> 2520.958 | X81: =IFERROR(W81/W108,0) -> 0.0083741747 | Z81: {=SUMPRODUCT('W3'!$K$18:$AJ$1670*('W3'!$A$18:$A$1670=Z$5)*('W3'!$D$18:$D$1670=$B$71)*('W3'!$K$14:$AJ$14='Cover Page'!$D81))} -> 1354.671 | AA81: =IFERROR(Z81/Z108,0) -> 0.0046844739 | AC81: {=SUMPRODUCT('W3'!$K$18:$AJ$1670*('W3'!$A$18:$A$1670=AC$5)*('W3'!$D$18:$D$1670=$B$71)*('W3'!$K$14:$AJ$14='Cover Page'!$D81))} -> 6170.4797 | AD81: =IFERROR(AC81/AC108,0) -> 0.020191263 | AF81: {=SUMPRODUCT('W3'!$K$18:$AJ$1670*('W3'!$A$18:$A$1670=AF$5)*('W3'!$D$18:$D$1670=$B$71)*('W3'!$K$14:$AJ$14='Cover Page'!$D81))} -> 38476.22 | AG81: =IFERROR(AF81/AF108,0) -> 0.11465414 | AI81: {=SUMPRODUCT('W3'!$K$18:$AJ$1670*('W3'!$A$18:$A$1670=AI$5)*('W3'!$D$18:$D$1670=$B$71)*('W3'!$K$14:$AJ$14='Cover Page'!$D81))} -> 30157.378 | AJ81: =IFERROR(AI81/AI108,0) -> 0.089865068 | AL81: 0.88
D82: 11 | E82: =IF(Currency="USD","USD","triệu VND") -> triệu VND | H82: {=SUMPRODUCT('W3'!$K$18:$AJ$1670*('W3'!$A$18:$A$1670=H$5)*('W3'!$D$18:$D$1670=$B$71)*('W3'!$K$14:$AJ$14='Cover Page'!$D82))} -> 39259.367 | I82: =IFERROR(H82/H109,0) -> 0.11469394 | K82: {=SUMPRODUCT('W3'!$K$18:$AJ$1670*('W3'!$A$18:$A$1670=K$5)*('W3'!$D$18:$D$1670=$B$71)*('W3'!$K$14:$AJ$14='Cover Page'!$D82))} -> 31370.711 | L82: =IFERROR(K82/K109,0) -> 0.09164769 | N82: {=SUMPRODUCT('W3'!$K$18:$AJ$1670*('W3'!$A$18:$A$1670=N$5)*('W3'!$D$18:$D$1670=$B$71)*('W3'!$K$14:$AJ$14='Cover Page'!$D82))} -> 27178.304 | O82: =IFERROR(N82/N109,0) -> 0.083064425 | Q82: {=SUMPRODUCT('W3'!$K$18:$AJ$1670*('W3'!$A$18:$A$1670=Q$5)*('W3'!$D$18:$D$1670=$B$71)*('W3'!$K$14:$AJ$14='Cover Page'!$D82))} -> 19289.647 | R82: =IFERROR(Q82/Q109,0) -> 0.058954506 | T82: {=SUMPRODUCT('W3'!$K$18:$AJ$1670*('W3'!$A$18:$A$1670=T$5)*('W3'!$D$18:$D$1670=$B$71)*('W3'!$K$14:$AJ$14='Cover Page'!$D82))} -> 11070.219 | U82: =IFERROR(T82/T109,0) -> 0.036052256 | W82: {=SUMPRODUCT('W3'!$K$18:$AJ$1670*('W3'!$A$18:$A$1670=W$5)*('W3'!$D$18:$D$1670=$B$71)*('W3'!$K$14:$AJ$14='Cover Page'!$D82))} -> 3181.5627 | X82: =IFERROR(W82/W109,0) -> 0.010361359 | Z82: {=SUMPRODUCT('W3'!$K$18:$AJ$1670*('W3'!$A$18:$A$1670=Z$5)*('W3'!$D$18:$D$1670=$B$71)*('W3'!$K$14:$AJ$14='Cover Page'!$D82))} -> 1395.3876 | AA82: =IFERROR(Z82/Z109,0) -> 0.0047306595 | AC82: {=SUMPRODUCT('W3'!$K$18:$AJ$1670*('W3'!$A$18:$A$1670=AC$5)*('W3'!$D$18:$D$1670=$B$71)*('W3'!$K$14:$AJ$14='Cover Page'!$D82))} -> 6904.0748 | AD82: =IFERROR(AC82/AC109,0) -> 0.022148783 | AF82: {=SUMPRODUCT('W3'!$K$18:$AJ$1670*('W3'!$A$18:$A$1670=AF$5)*('W3'!$D$18:$D$1670=$B$71)*('W3'!$K$14:$AJ$14='Cover Page'!$D82))} -> 39259.367 | AG82: =IFERROR(AF82/AF109,0) -> 0.11469394 | AI82: {=SUMPRODUCT('W3'!$K$18:$AJ$1670*('W3'!$A$18:$A$1670=AI$5)*('W3'!$D$18:$D$1670=$B$71)*('W3'!$K$14:$AJ$14='Cover Page'!$D82))} -> 31370.711 | AJ82: =IFERROR(AI82/AI109,0) -> 0.09164769 | AL82: 0.88
D83: 12 | E83: =IF(Currency="USD","USD","triệu VND") -> triệu VND | H83: {=SUMPRODUCT('W3'!$K$18:$AJ$1670*('W3'!$A$18:$A$1670=H$5)*('W3'!$D$18:$D$1670=$B$71)*('W3'!$K$14:$AJ$14='Cover Page'!$D83))} -> 40031.337 | I83: =IFERROR(H83/H110,0) -> 0.11465608 | K83: {=SUMPRODUCT('W3'!$K$18:$AJ$1670*('W3'!$A$18:$A$1670=K$5)*('W3'!$D$18:$D$1670=$B$71)*('W3'!$K$14:$AJ$14='Cover Page'!$D83))} -> 32602.979 | L83: =IFERROR(K83/K110,0) -> 0.093380086 | N83: {=SUMPRODUCT('W3'!$K$18:$AJ$1670*('W3'!$A$18:$A$1670=N$5)*('W3'!$D$18:$D$1670=$B$71)*('W3'!$K$14:$AJ$14='Cover Page'!$D83))} -> 27708.652 | O83: =IFERROR(N83/N110,0) -> 0.083024819 | Q83: {=SUMPRODUCT('W3'!$K$18:$AJ$1670*('W3'!$A$18:$A$1670=Q$5)*('W3'!$D$18:$D$1670=$B$71)*('W3'!$K$14:$AJ$14='Cover Page'!$D83))} -> 20280.294 | R83: =IFERROR(Q83/Q110,0) -> 0.060766859 | T83: {=SUMPRODUCT('W3'!$K$18:$AJ$1670*('W3'!$A$18:$A$1670=T$5)*('W3'!$D$18:$D$1670=$B$71)*('W3'!$K$14:$AJ$14='Cover Page'!$D83))} -> 11278.405 | U83: =IFERROR(T83/T110,0) -> 0.036010054 | W83: {=SUMPRODUCT('W3'!$K$18:$AJ$1670*('W3'!$A$18:$A$1670=W$5)*('W3'!$D$18:$D$1670=$B$71)*('W3'!$K$14:$AJ$14='Cover Page'!$D83))} -> 3850.0476 | X83: =IFERROR(W83/W110,0) -> 0.012292555 | Z83: {=SUMPRODUCT('W3'!$K$18:$AJ$1670*('W3'!$A$18:$A$1670=Z$5)*('W3'!$D$18:$D$1670=$B$71)*('W3'!$K$14:$AJ$14='Cover Page'!$D83))} -> 1410.0775 | AA83: =IFERROR(Z83/Z110,0) -> 0.0046867267 | AC83: {=SUMPRODUCT('W3'!$K$18:$AJ$1670*('W3'!$A$18:$A$1670=AC$5)*('W3'!$D$18:$D$1670=$B$71)*('W3'!$K$14:$AJ$14='Cover Page'!$D83))} -> 7647.01 | AD83: =IFERROR(AC83/AC110,0) -> 0.024051151 | AF83: {=SUMPRODUCT('W3'!$K$18:$AJ$1670*('W3'!$A$18:$A$1670=AF$5)*('W3'!$D$18:$D$1670=$B$71)*('W3'!$K$14:$AJ$14='Cover Page'!$D83))} -> 40031.337 | AG83: =IFERROR(AF83/AF110,0) -> 0.11465608 | AI83: {=SUMPRODUCT('W3'!$K$18:$AJ$1670*('W3'!$A$18:$A$1670=AI$5)*('W3'!$D$18:$D$1670=$B$71)*('W3'!$K$14:$AJ$14='Cover Page'!$D83))} -> 32602.979 | AJ83: =IFERROR(AI83/AI110,0) -> 0.093380086 | AL83: 0.88
D84: 13 | E84: =IF(Currency="USD","USD","triệu VND") -> triệu VND | H84: {=SUMPRODUCT('W3'!$K$18:$AJ$1670*('W3'!$A$18:$A$1670=H$5)*('W3'!$D$18:$D$1670=$B$71)*('W3'!$K$14:$AJ$14='Cover Page'!$D84))} -> 61643.411 | I84: =IFERROR(H84/H111,0) -> 0.17309458 | K84: {=SUMPRODUCT('W3'!$K$18:$AJ$1670*('W3'!$A$18:$A$1670=K$5)*('W3'!$D$18:$D$1670=$B$71)*('W3'!$K$14:$AJ$14='Cover Page'!$D84))} -> 54707.573 | L84: =IFERROR(K84/K111,0) -> 0.15361876 | N84: {=SUMPRODUCT('W3'!$K$18:$AJ$1670*('W3'!$A$18:$A$1670=N$5)*('W3'!$D$18:$D$1670=$B$71)*('W3'!$K$14:$AJ$14='Cover Page'!$D84))} -> 49074.272 | O84: =IFERROR(N84/N111,0) -> 0.14416049 | Q84: {=SUMPRODUCT('W3'!$K$18:$AJ$1670*('W3'!$A$18:$A$1670=Q$5)*('W3'!$D$18:$D$1670=$B$71)*('W3'!$K$14:$AJ$14='Cover Page'!$D84))} -> 42138.434 | R84: =IFERROR(Q84/Q111,0) -> 0.12378578 | T84: {=SUMPRODUCT('W3'!$K$18:$AJ$1670*('W3'!$A$18:$A$1670=T$5)*('W3'!$D$18:$D$1670=$B$71)*('W3'!$K$14:$AJ$14='Cover Page'!$D84))} -> 32315.421 | U84: =IFERROR(T84/T111,0) -> 0.10115462 | W84: {=SUMPRODUCT('W3'!$K$18:$AJ$1670*('W3'!$A$18:$A$1670=W$5)*('W3'!$D$18:$D$1670=$B$71)*('W3'!$K$14:$AJ$14='Cover Page'!$D84))} -> 25379.583 | X84: =IFERROR(W84/W111,0) -> 0.079443866 | Z84: {=SUMPRODUCT('W3'!$K$18:$AJ$1670*('W3'!$A$18:$A$1670=Z$5)*('W3'!$D$18:$D$1670=$B$71)*('W3'!$K$14:$AJ$14='Cover Page'!$D84))} -> 22249.727 | AA84: =IFERROR(Z84/Z111,0) -> 0.072502196 | AC84: {=SUMPRODUCT('W3'!$K$18:$AJ$1670*('W3'!$A$18:$A$1670=AC$5)*('W3'!$D$18:$D$1670=$B$71)*('W3'!$K$14:$AJ$14='Cover Page'!$D84))} -> 29252.484 | AD84: =IFERROR(AC84/AC111,0) -> 0.090200053 | AF84: {=SUMPRODUCT('W3'!$K$18:$AJ$1670*('W3'!$A$18:$A$1670=AF$5)*('W3'!$D$18:$D$1670=$B$71)*('W3'!$K$14:$AJ$14='Cover Page'!$D84))} -> 61643.411 | AG84: =IFERROR(AF84/AF111,0) -> 0.17309458 | AI84: {=SUMPRODUCT('W3'!$K$18:$AJ$1670*('W3'!$A$18:$A$1670=AI$5)*('W3'!$D$18:$D$1670=$B$71)*('W3'!$K$14:$AJ$14='Cover Page'!$D84))} -> 54707.573 | AJ84: =IFERROR(AI84/AI111,0) -> 0.15361876 | AL84: 0.88
... D96: 25 | E96: =IF(Currency="USD","USD","triệu VND") -> triệu VND | H96: {=SUMPRODUCT('W3'!$K$18:$AJ$1670*('W3'!$A$18:$A$1670=H$5)*('W3'!$D$18:$D$1670=$B$71)*('W3'!$K$14:$AJ$14='Cover Page'!$D96))} -> 0 | I96: =IFERROR(H96/H123,0) -> 0 | K96: {=SUMPRODUCT('W3'!$K$18:$AJ$1670*('W3'!$A$18:$A$1670=K$5)*('W3'!$D$18:$D$1670=$B$71)*('W3'!$K$14:$AJ$14='Cover Page'!$D96))} -> 0 | L96: =IFERROR(K96/K123,0) -> 0 | N96: {=SUMPRODUCT('W3'!$K$18:$AJ$1670*('W3'!$A$18:$A$1670=N$5)*('W3'!$D$18:$D$1670=$B$71)*('W3'!$K$14:$AJ$14='Cover Page'!$D96))} -> 0 | O96: =IFERROR(N96/N123,0) -> 0 | Q96: {=SUMPRODUCT('W3'!$K$18:$AJ$1670*('W3'!$A$18:$A$1670=Q$5)*('W3'!$D$18:$D$1670=$B$71)*('W3'!$K$14:$AJ$14='Cover Page'!$D96))} -> 0 | R96: =IFERROR(Q96/Q123,0) -> 0 | T96: {=SUMPRODUCT('W3'!$K$18:$AJ$1670*('W3'!$A$18:$A$1670=T$5)*('W3'!$D$18:$D$1670=$B$71)*('W3'!$K$14:$AJ$14='Cover Page'!$D96))} -> 0 | U96: =IFERROR(T96/T123,0) -> 0 | W96: {=SUMPRODUCT('W3'!$K$18:$AJ$1670*('W3'!$A$18:$A$1670=W$5)*('W3'!$D$18:$D$1670=$B$71)*('W3'!$K$14:$AJ$14='Cover Page'!$D96))} -> 0 | X96: =IFERROR(W96/W123,0) -> 0 | Z96: {=SUMPRODUCT('W3'!$K$18:$AJ$1670*('W3'!$A$18:$A$1670=Z$5)*('W3'!$D$18:$D$1670=$B$71)*('W3'!$K$14:$AJ$14='Cover Page'!$D96))} -> 0 | AA96: =IFERROR(Z96/Z123,0) -> 0 | AC96: {=SUMPRODUCT('W3'!$K$18:$AJ$1670*('W3'!$A$18:$A$1670=AC$5)*('W3'!$D$18:$D$1670=$B$71)*('W3'!$K$14:$AJ$14='Cover Page'!$D96))} -> 0 | AD96: =IFERROR(AC96/AC123,0) -> 0 | AF96: {=SUMPRODUCT('W3'!$K$18:$AJ$1670*('W3'!$A$18:$A$1670=AF$5)*('W3'!$D$18:$D$1670=$B$71)*('W3'!$K$14:$AJ$14='Cover Page'!$D96))} -> 0 | AG96: =IFERROR(AF96/AF123,0) -> 0 | AI96: {=SUMPRODUCT('W3'!$K$18:$AJ$1670*('W3'!$A$18:$A$1670=AI$5)*('W3'!$D$18:$D$1670=$B$71)*('W3'!$K$14:$AJ$14='Cover Page'!$D96))} -> 0 | AJ96: =IFERROR(AI96/AI123,0) -> 0 | AL96: 0
B98: Dthu | C98: 16 | D98: Doanh thu | E98: =IF(Currency="USD","USD","triệu VND") -> triệu VND | H98: =SUM(H99:H123) -> 4629709.5 | K98: =SUM(K99:K123) -> 4629709.5 | N98: =SUM(N99:N123) -> 4425457.6 | Q98: =SUM(Q99:Q123) -> 4425457.6 | T98: =SUM(T99:T123) -> 4153121.8 | W98: =SUM(W99:W123) -> 4153121.8 | Z98: =SUM(Z99:Z123) -> 3989551.5 | AC98: =SUM(AC99:AC123) -> 4216057.5 | AF98: =SUM(AF99:AF123) -> 4629709.5 | AI98: =SUM(AI99:AI123) -> 4629709.5
D99: 1 | E99: =IF(Currency="USD","USD","triệu VND") -> triệu VND | H99: {=SUMPRODUCT('W3'!$K$18:$AJ$1670*('W3'!$A$18:$A$1670=H$5)*('W3'!$D$18:$D$1670=$B$98)*('W3'!$K$14:$AJ$14='Cover Page'!$D99))} -> 140401.3 | K99: {=SUMPRODUCT('W3'!$K$18:$AJ$1670*('W3'!$A$18:$A$1670=K$5)*('W3'!$D$18:$D$1670=$B$98)*('W3'!$K$14:$AJ$14='Cover Page'!$D99))} -> 140401.3 | N99: {=SUMPRODUCT('W3'!$K$18:$AJ$1670*('W3'!$A$18:$A$1670=N$5)*('W3'!$D$18:$D$1670=$B$98)*('W3'!$K$14:$AJ$14='Cover Page'!$D99))} -> 134207.12 | Q99: {=SUMPRODUCT('W3'!$K$18:$AJ$1670*('W3'!$A$18:$A$1670=Q$5)*('W3'!$D$18:$D$1670=$B$98)*('W3'!$K$14:$AJ$14='Cover Page'!$D99))} -> 134207.12 | T99: {=SUMPRODUCT('W3'!$K$18:$AJ$1670*('W3'!$A$18:$A$1670=T$5)*('W3'!$D$18:$D$1670=$B$98)*('W3'!$K$14:$AJ$14='Cover Page'!$D99))} -> 125948.22 | W99: {=SUMPRODUCT('W3'!$K$18:$AJ$1670*('W3'!$A$18:$A$1670=W$5)*('W3'!$D$18:$D$1670=$B$98)*('W3'!$K$14:$AJ$14='Cover Page'!$D99))} -> 125948.22 | Z99: {=SUMPRODUCT('W3'!$K$18:$AJ$1670*('W3'!$A$18:$A$1670=Z$5)*('W3'!$D$18:$D$1670=$B$98)*('W3'!$K$14:$AJ$14='Cover Page'!$D99))} -> 120987.77 | AC99: {=SUMPRODUCT('W3'!$K$18:$AJ$1670*('W3'!$A$18:$A$1670=AC$5)*('W3'!$D$18:$D$1670=$B$98)*('W3'!$K$14:$AJ$14='Cover Page'!$D99))} -> 127856.82 | AF99: {=SUMPRODUCT('W3'!$K$18:$AJ$1670*('W3'!$A$18:$A$1670=AF$5)*('W3'!$D$18:$D$1670=$B$98)*('W3'!$K$14:$AJ$14='Cover Page'!$D99))} -> 140401.3 | AI99: {=SUMPRODUCT('W3'!$K$18:$AJ$1670*('W3'!$A$18:$A$1670=AI$5)*('W3'!$D$18:$D$1670=$B$98)*('W3'!$K$14:$AJ$14='Cover Page'!$D99))} -> 140401.3
D100: 2 | E100: =IF(Currency="USD","USD","triệu VND") -> triệu VND | H100: {=SUMPRODUCT('W3'!$K$18:$AJ$1670*('W3'!$A$18:$A$1670=H$5)*('W3'!$D$18:$D$1670=$B$98)*('W3'!$K$14:$AJ$14='Cover Page'!$D100))} -> 200493.06 | K100: {=SUMPRODUCT('W3'!$K$18:$AJ$1670*('W3'!$A$18:$A$1670=K$5)*('W3'!$D$18:$D$1670=$B$98)*('W3'!$K$14:$AJ$14='Cover Page'!$D100))} -> 200493.06 | N100: {=SUMPRODUCT('W3'!$K$18:$AJ$1670*('W3'!$A$18:$A$1670=N$5)*('W3'!$D$18:$D$1670=$B$98)*('W3'!$K$14:$AJ$14='Cover Page'!$D100))} -> 191647.77 | Q100: {=SUMPRODUCT('W3'!$K$18:$AJ$1670*('W3'!$A$18:$A$1670=Q$5)*('W3'!$D$18:$D$1670=$B$98)*('W3'!$K$14:$AJ$14='Cover Page'!$D100))} -> 191647.77 | T100: {=SUMPRODUCT('W3'!$K$18:$AJ$1670*('W3'!$A$18:$A$1670=T$5)*('W3'!$D$18:$D$1670=$B$98)*('W3'!$K$14:$AJ$14='Cover Page'!$D100))} -> 179854.06 | W100: {=SUMPRODUCT('W3'!$K$18:$AJ$1670*('W3'!$A$18:$A$1670=W$5)*('W3'!$D$18:$D$1670=$B$98)*('W3'!$K$14:$AJ$14='Cover Page'!$D100))} -> 179854.06 | Z100: {=SUMPRODUCT('W3'!$K$18:$AJ$1670*('W3'!$A$18:$A$1670=Z$5)*('W3'!$D$18:$D$1670=$B$98)*('W3'!$K$14:$AJ$14='Cover Page'!$D100))} -> 172770.53 | AC100: {=SUMPRODUCT('W3'!$K$18:$AJ$1670*('W3'!$A$18:$A$1670=AC$5)*('W3'!$D$18:$D$1670=$B$98)*('W3'!$K$14:$AJ$14='Cover Page'!$D100))} -> 182579.54 | AF100: {=SUMPRODUCT('W3'!$K$18:$AJ$1670*('W3'!$A$18:$A$1670=AF$5)*('W3'!$D$18:$D$1670=$B$98)*('W3'!$K$14:$AJ$14='Cover Page'!$D100))} -> 200493.06 | AI100: {=SUMPRODUCT('W3'!$K$18:$AJ$1670*('W3'!$A$18:$A$1670=AI$5)*('W3'!$D$18:$D$1670=$B$98)*('W3'!$K$14:$AJ$14='Cover Page'!$D100))} -> 200493.06
D101: 3 | E101: =IF(Currency="USD","USD","triệu VND") -> triệu VND | H101: {=SUMPRODUCT('W3'!$K$18:$AJ$1670*('W3'!$A$18:$A$1670=H$5)*('W3'!$D$18:$D$1670=$B$98)*('W3'!$K$14:$AJ$14='Cover Page'!$D101))} -> 292147.02 | K101: {=SUMPRODUCT('W3'!$K$18:$AJ$1670*('W3'!$A$18:$A$1670=K$5)*('W3'!$D$18:$D$1670=$B$98)*('W3'!$K$14:$AJ$14='Cover Page'!$D101))} -> 292147.02 | N101: {=SUMPRODUCT('W3'!$K$18:$AJ$1670*('W3'!$A$18:$A$1670=N$5)*('W3'!$D$18:$D$1670=$B$98)*('W3'!$K$14:$AJ$14='Cover Page'!$D101))} -> 279258.18 | Q101: {=SUMPRODUCT('W3'!$K$18:$AJ$1670*('W3'!$A$18:$A$1670=Q$5)*('W3'!$D$18:$D$1670=$B$98)*('W3'!$K$14:$AJ$14='Cover Page'!$D101))} -> 279258.18 | T101: {=SUMPRODUCT('W3'!$K$18:$AJ$1670*('W3'!$A$18:$A$1670=T$5)*('W3'!$D$18:$D$1670=$B$98)*('W3'!$K$14:$AJ$14='Cover Page'!$D101))} -> 262073.07 | W101: {=SUMPRODUCT('W3'!$K$18:$AJ$1670*('W3'!$A$18:$A$1670=W$5)*('W3'!$D$18:$D$1670=$B$98)*('W3'!$K$14:$AJ$14='Cover Page'!$D101))} -> 262073.07 | Z101: {=SUMPRODUCT('W3'!$K$18:$AJ$1670*('W3'!$A$18:$A$1670=Z$5)*('W3'!$D$18:$D$1670=$B$98)*('W3'!$K$14:$AJ$14='Cover Page'!$D101))} -> 251751.35 | AC101: {=SUMPRODUCT('W3'!$K$18:$AJ$1670*('W3'!$A$18:$A$1670=AC$5)*('W3'!$D$18:$D$1670=$B$98)*('W3'!$K$14:$AJ$14='Cover Page'!$D101))} -> 266044.48 | AF101: {=SUMPRODUCT('W3'!$K$18:$AJ$1670*('W3'!$A$18:$A$1670=AF$5)*('W3'!$D$18:$D$1670=$B$98)*('W3'!$K$14:$AJ$14='Cover Page'!$D101))} -> 292147.02 | AI101: {=SUMPRODUCT('W3'!$K$18:$AJ$1670*('W3'!$A$18:$A$1670=AI$5)*('W3'!$D$18:$D$1670=$B$98)*('W3'!$K$14:$AJ$14='Cover Page'!$D101))} -> 292147.02
D102: 4 | E102: =IF(Currency="USD","USD","triệu VND") -> triệu VND | H102: {=SUMPRODUCT('W3'!$K$18:$AJ$1670*('W3'!$A$18:$A$1670=H$5)*('W3'!$D$18:$D$1670=$B$98)*('W3'!$K$14:$AJ$14='Cover Page'!$D102))} -> 297989.96 | K102: {=SUMPRODUCT('W3'!$K$18:$AJ$1670*('W3'!$A$18:$A$1670=K$5)*('W3'!$D$18:$D$1670=$B$98)*('W3'!$K$14:$AJ$14='Cover Page'!$D102))} -> 297989.96 | N102: {=SUMPRODUCT('W3'!$K$18:$AJ$1670*('W3'!$A$18:$A$1670=N$5)*('W3'!$D$18:$D$1670=$B$98)*('W3'!$K$14:$AJ$14='Cover Page'!$D102))} -> 284843.35 | Q102: {=SUMPRODUCT('W3'!$K$18:$AJ$1670*('W3'!$A$18:$A$1670=Q$5)*('W3'!$D$18:$D$1670=$B$98)*('W3'!$K$14:$AJ$14='Cover Page'!$D102))} -> 284843.35 | T102: {=SUMPRODUCT('W3'!$K$18:$AJ$1670*('W3'!$A$18:$A$1670=T$5)*('W3'!$D$18:$D$1670=$B$98)*('W3'!$K$14:$AJ$14='Cover Page'!$D102))} -> 267314.53 | W102: {=SUMPRODUCT('W3'!$K$18:$AJ$1670*('W3'!$A$18:$A$1670=W$5)*('W3'!$D$18:$D$1670=$B$98)*('W3'!$K$14:$AJ$14='Cover Page'!$D102))} -> 267314.53 | Z102: {=SUMPRODUCT('W3'!$K$18:$AJ$1670*('W3'!$A$18:$A$1670=Z$5)*('W3'!$D$18:$D$1670=$B$98)*('W3'!$K$14:$AJ$14='Cover Page'!$D102))} -> 256786.37 | AC102: {=SUMPRODUCT('W3'!$K$18:$AJ$1670*('W3'!$A$18:$A$1670=AC$5)*('W3'!$D$18:$D$1670=$B$98)*('W3'!$K$14:$AJ$14='Cover Page'!$D102))} -> 271365.37 | AF102: {=SUMPRODUCT('W3'!$K$18:$AJ$1670*('W3'!$A$18:$A$1670=AF$5)*('W3'!$D$18:$D$1670=$B$98)*('W3'!$K$14:$AJ$14='Cover Page'!$D102))} -> 297989.96 | AI102: {=SUMPRODUCT('W3'!$K$18:$AJ$1670*('W3'!$A$18:$A$1670=AI$5)*('W3'!$D$18:$D$1670=$B$98)*('W3'!$K$14:$AJ$14='Cover Page'!$D102))} -> 297989.96
D103: 5 | E103: =IF(Currency="USD","USD","triệu VND") -> triệu VND | H103: {=SUMPRODUCT('W3'!$K$18:$AJ$1670*('W3'!$A$18:$A$1670=H$5)*('W3'!$D$18:$D$1670=$B$98)*('W3'!$K$14:$AJ$14='Cover Page'!$D103))} -> 303949.76 | K103: {=SUMPRODUCT('W3'!$K$18:$AJ$1670*('W3'!$A$18:$A$1670=K$5)*('W3'!$D$18:$D$1670=$B$98)*('W3'!$K$14:$AJ$14='Cover Page'!$D103))} -> 303949.76 | N103: {=SUMPRODUCT('W3'!$K$18:$AJ$1670*('W3'!$A$18:$A$1670=N$5)*('W3'!$D$18:$D$1670=$B$98)*('W3'!$K$14:$AJ$14='Cover Page'!$D103))} -> 290540.22 | Q103: {=SUMPRODUCT('W3'!$K$18:$AJ$1670*('W3'!$A$18:$A$1670=Q$5)*('W3'!$D$18:$D$1670=$B$98)*('W3'!$K$14:$AJ$14='Cover Page'!$D103))} -> 290540.22 | T103: {=SUMPRODUCT('W3'!$K$18:$AJ$1670*('W3'!$A$18:$A$1670=T$5)*('W3'!$D$18:$D$1670=$B$98)*('W3'!$K$14:$AJ$14='Cover Page'!$D103))} -> 272660.82 | W103: {=SUMPRODUCT('W3'!$K$18:$AJ$1670*('W3'!$A$18:$A$1670=W$5)*('W3'!$D$18:$D$1670=$B$98)*('W3'!$K$14:$AJ$14='Cover Page'!$D103))} -> 272660.82 | Z103: {=SUMPRODUCT('W3'!$K$18:$AJ$1670*('W3'!$A$18:$A$1670=Z$5)*('W3'!$D$18:$D$1670=$B$98)*('W3'!$K$14:$AJ$14='Cover Page'!$D103))} -> 261922.1 | AC103: {=SUMPRODUCT('W3'!$K$18:$AJ$1670*('W3'!$A$18:$A$1670=AC$5)*('W3'!$D$18:$D$1670=$B$98)*('W3'!$K$14:$AJ$14='Cover Page'!$D103))} -> 276792.67 | AF103: {=SUMPRODUCT('W3'!$K$18:$AJ$1670*('W3'!$A$18:$A$1670=AF$5)*('W3'!$D$18:$D$1670=$B$98)*('W3'!$K$14:$AJ$14='Cover Page'!$D103))} -> 303949.76 | AI103: {=SUMPRODUCT('W3'!$K$18:$AJ$1670*('W3'!$A$18:$A$1670=AI$5)*('W3'!$D$18:$D$1670=$B$98)*('W3'!$K$14:$AJ$14='Cover Page'!$D103))} -> 303949.76
D104: 6 | E104: =IF(Currency="USD","USD","triệu VND") -> triệu VND | H104: {=SUMPRODUCT('W3'!$K$18:$AJ$1670*('W3'!$A$18:$A$1670=H$5)*('W3'!$D$18:$D$1670=$B$98)*('W3'!$K$14:$AJ$14='Cover Page'!$D104))} -> 310028.76 | K104: {=SUMPRODUCT('W3'!$K$18:$AJ$1670*('W3'!$A$18:$A$1670=K$5)*('W3'!$D$18:$D$1670=$B$98)*('W3'!$K$14:$AJ$14='Cover Page'!$D104))} -> 310028.76 | N104: {=SUMPRODUCT('W3'!$K$18:$AJ$1670*('W3'!$A$18:$A$1670=N$5)*('W3'!$D$18:$D$1670=$B$98)*('W3'!$K$14:$AJ$14='Cover Page'!$D104))} -> 296351.02 | Q104: {=SUMPRODUCT('W3'!$K$18:$AJ$1670*('W3'!$A$18:$A$1670=Q$5)*('W3'!$D$18:$D$1670=$B$98)*('W3'!$K$14:$AJ$14='Cover Page'!$D104))} -> 296351.02 | T104: {=SUMPRODUCT('W3'!$K$18:$AJ$1670*('W3'!$A$18:$A$1670=T$5)*('W3'!$D$18:$D$1670=$B$98)*('W3'!$K$14:$AJ$14='Cover Page'!$D104))} -> 278114.03 | W104: {=SUMPRODUCT('W3'!$K$18:$AJ$1670*('W3'!$A$18:$A$1670=W$5)*('W3'!$D$18:$D$1670=$B$98)*('W3'!$K$14:$AJ$14='Cover Page'!$D104))} -> 278114.03 | Z104: {=SUMPRODUCT('W3'!$K$18:$AJ$1670*('W3'!$A$18:$A$1670=Z$5)*('W3'!$D$18:$D$1670=$B$98)*('W3'!$K$14:$AJ$14='Cover Page'!$D104))} -> 267160.54 | AC104: {=SUMPRODUCT('W3'!$K$18:$AJ$1670*('W3'!$A$18:$A$1670=AC$5)*('W3'!$D$18:$D$1670=$B$98)*('W3'!$K$14:$AJ$14='Cover Page'!$D104))} -> 282328.53 | AF104: {=SUMPRODUCT('W3'!$K$18:$AJ$1670*('W3'!$A$18:$A$1670=AF$5)*('W3'!$D$18:$D$1670=$B$98)*('W3'!$K$14:$AJ$14='Cover Page'!$D104))} -> 310028.76 | AI104: {=SUMPRODUCT('W3'!$K$18:$AJ$1670*('W3'!$A$18:$A$1670=AI$5)*('W3'!$D$18:$D$1670=$B$98)*('W3'!$K$14:$AJ$14='Cover Page'!$D104))} -> 310028.76
D105: 7 | E105: =IF(Currency="USD","USD","triệu VND") -> triệu VND | H105: {=SUMPRODUCT('W3'!$K$18:$AJ$1670*('W3'!$A$18:$A$1670=H$5)*('W3'!$D$18:$D$1670=$B$98)*('W3'!$K$14:$AJ$14='Cover Page'!$D105))} -> 316229.33 | K105: {=SUMPRODUCT('W3'!$K$18:$AJ$1670*('W3'!$A$18:$A$1670=K$5)*('W3'!$D$18:$D$1670=$B$98)*('W3'!$K$14:$AJ$14='Cover Page'!$D105))} -> 316229.33 | N105: {=SUMPRODUCT('W3'!$K$18:$AJ$1670*('W3'!$A$18:$A$1670=N$5)*('W3'!$D$18:$D$1670=$B$98)*('W3'!$K$14:$AJ$14='Cover Page'!$D105))} -> 302278.04 | Q105: {=SUMPRODUCT('W3'!$K$18:$AJ$1670*('W3'!$A$18:$A$1670=Q$5)*('W3'!$D$18:$D$1670=$B$98)*('W3'!$K$14:$AJ$14='Cover Page'!$D105))} -> 302278.04 | T105: {=SUMPRODUCT('W3'!$K$18:$AJ$1670*('W3'!$A$18:$A$1670=T$5)*('W3'!$D$18:$D$1670=$B$98)*('W3'!$K$14:$AJ$14='Cover Page'!$D105))} -> 283676.31 | W105: {=SUMPRODUCT('W3'!$K$18:$AJ$1670*('W3'!$A$18:$A$1670=W$5)*('W3'!$D$18:$D$1670=$B$98)*('W3'!$K$14:$AJ$14='Cover Page'!$D105))} -> 283676.31 | Z105: {=SUMPRODUCT('W3'!$K$18:$AJ$1670*('W3'!$A$18:$A$1670=Z$5)*('W3'!$D$18:$D$1670=$B$98)*('W3'!$K$14:$AJ$14='Cover Page'!$D105))} -> 272503.75 | AC105: {=SUMPRODUCT('W3'!$K$18:$AJ$1670*('W3'!$A$18:$A$1670=AC$5)*('W3'!$D$18:$D$1670=$B$98)*('W3'!$K$14:$AJ$14='Cover Page'!$D105))} -> 287975.1 | AF105: {=SUMPRODUCT('W3'!$K$18:$AJ$1670*('W3'!$A$18:$A$1670=AF$5)*('W3'!$D$18:$D$1670=$B$98)*('W3'!$K$14:$AJ$14='Cover Page'!$D105))} -> 316229.33 | AI105: {=SUMPRODUCT('W3'!$K$18:$AJ$1670*('W3'!$A$18:$A$1670=AI$5)*('W3'!$D$18:$D$1670=$B$98)*('W3'!$K$14:$AJ$14='Cover Page'!$D105))} -> 316229.33
D106: 8 | E106: =IF(Currency="USD","USD","triệu VND") -> triệu VND | H106: {=SUMPRODUCT('W3'!$K$18:$AJ$1670*('W3'!$A$18:$A$1670=H$5)*('W3'!$D$18:$D$1670=$B$98)*('W3'!$K$14:$AJ$14='Cover Page'!$D106))} -> 322553.92 | K106: {=SUMPRODUCT('W3'!$K$18:$AJ$1670*('W3'!$A$18:$A$1670=K$5)*('W3'!$D$18:$D$1670=$B$98)*('W3'!$K$14:$AJ$14='Cover Page'!$D106))} -> 322553.92 | N106: {=SUMPRODUCT('W3'!$K$18:$AJ$1670*('W3'!$A$18:$A$1670=N$5)*('W3'!$D$18:$D$1670=$B$98)*('W3'!$K$14:$AJ$14='Cover Page'!$D106))} -> 308323.6 | Q106: {=SUMPRODUCT('W3'!$K$18:$AJ$1670*('W3'!$A$18:$A$1670=Q$5)*('W3'!$D$18:$D$1670=$B$98)*('W3'!$K$14:$AJ$14='Cover Page'!$D106))} -> 308323.6 | T106: {=SUMPRODUCT('W3'!$K$18:$AJ$1670*('W3'!$A$18:$A$1670=T$5)*('W3'!$D$18:$D$1670=$B$98)*('W3'!$K$14:$AJ$14='Cover Page'!$D106))} -> 289349.84 | W106: {=SUMPRODUCT('W3'!$K$18:$AJ$1670*('W3'!$A$18:$A$1670=W$5)*('W3'!$D$18:$D$1670=$B$98)*('W3'!$K$14:$AJ$14='Cover Page'!$D106))} -> 289349.84 | Z106: {=SUMPRODUCT('W3'!$K$18:$AJ$1670*('W3'!$A$18:$A$1670=Z$5)*('W3'!$D$18:$D$1670=$B$98)*('W3'!$K$14:$AJ$14='Cover Page'!$D106))} -> 277953.83 | AC106: {=SUMPRODUCT('W3'!$K$18:$AJ$1670*('W3'!$A$18:$A$1670=AC$5)*('W3'!$D$18:$D$1670=$B$98)*('W3'!$K$14:$AJ$14='Cover Page'!$D106))} -> 293734.6 | AF106: {=SUMPRODUCT('W3'!$K$18:$AJ$1670*('W3'!$A$18:$A$1670=AF$5)*('W3'!$D$18:$D$1670=$B$98)*('W3'!$K$14:$AJ$14='Cover Page'!$D106))} -> 322553.92 | AI106: {=SUMPRODUCT('W3'!$K$18:$AJ$1670*('W3'!$A$18:$A$1670=AI$5)*('W3'!$D$18:$D$1670=$B$98)*('W3'!$K$14:$AJ$14='Cover Page'!$D106))} -> 322553.92
D107: 9 | E107: =IF(Currency="USD","USD","triệu VND") -> triệu VND | H107: {=SUMPRODUCT('W3'!$K$18:$AJ$1670*('W3'!$A$18:$A$1670=H$5)*('W3'!$D$18:$D$1670=$B$98)*('W3'!$K$14:$AJ$14='Cover Page'!$D107))} -> 329005 | K107: {=SUMPRODUCT('W3'!$K$18:$AJ$1670*('W3'!$A$18:$A$1670=K$5)*('W3'!$D$18:$D$1670=$B$98)*('W3'!$K$14:$AJ$14='Cover Page'!$D107))} -> 329005 | N107: {=SUMPRODUCT('W3'!$K$18:$AJ$1670*('W3'!$A$18:$A$1670=N$5)*('W3'!$D$18:$D$1670=$B$98)*('W3'!$K$14:$AJ$14='Cover Page'!$D107))} -> 314490.07 | Q107: {=SUMPRODUCT('W3'!$K$18:$AJ$1670*('W3'!$A$18:$A$1670=Q$5)*('W3'!$D$18:$D$1670=$B$98)*('W3'!$K$14:$AJ$14='Cover Page'!$D107))} -> 314490.07 | T107: {=SUMPRODUCT('W3'!$K$18:$AJ$1670*('W3'!$A$18:$A$1670=T$5)*('W3'!$D$18:$D$1670=$B$98)*('W3'!$K$14:$AJ$14='Cover Page'!$D107))} -> 295136.84 | W107: {=SUMPRODUCT('W3'!$K$18:$AJ$1670*('W3'!$A$18:$A$1670=W$5)*('W3'!$D$18:$D$1670=$B$98)*('W3'!$K$14:$AJ$14='Cover Page'!$D107))} -> 295136.84 | Z107: {=SUMPRODUCT('W3'!$K$18:$AJ$1670*('W3'!$A$18:$A$1670=Z$5)*('W3'!$D$18:$D$1670=$B$98)*('W3'!$K$14:$AJ$14='Cover Page'!$D107))} -> 283512.91 | AC107: {=SUMPRODUCT('W3'!$K$18:$AJ$1670*('W3'!$A$18:$A$1670=AC$5)*('W3'!$D$18:$D$1670=$B$98)*('W3'!$K$14:$AJ$14='Cover Page'!$D107))} -> 299609.29 | AF107: {=SUMPRODUCT('W3'!$K$18:$AJ$1670*('W3'!$A$18:$A$1670=AF$5)*('W3'!$D$18:$D$1670=$B$98)*('W3'!$K$14:$AJ$14='Cover Page'!$D107))} -> 329005 | AI107: {=SUMPRODUCT('W3'!$K$18:$AJ$1670*('W3'!$A$18:$A$1670=AI$5)*('W3'!$D$18:$D$1670=$B$98)*('W3'!$K$14:$AJ$14='Cover Page'!$D107))} -> 329005
D108: 10 | E108: =IF(Currency="USD","USD","triệu VND") -> triệu VND | H108: {=SUMPRODUCT('W3'!$K$18:$AJ$1670*('W3'!$A$18:$A$1670=H$5)*('W3'!$D$18:$D$1670=$B$98)*('W3'!$K$14:$AJ$14='Cover Page'!$D108))} -> 335585.1 | K108: {=SUMPRODUCT('W3'!$K$18:$AJ$1670*('W3'!$A$18:$A$1670=K$5)*('W3'!$D$18:$D$1670=$B$98)*('W3'!$K$14:$AJ$14='Cover Page'!$D108))} -> 335585.1 | N108: {=SUMPRODUCT('W3'!$K$18:$AJ$1670*('W3'!$A$18:$A$1670=N$5)*('W3'!$D$18:$D$1670=$B$98)*('W3'!$K$14:$AJ$14='Cover Page'!$D108))} -> 320779.87 | Q108: {=SUMPRODUCT('W3'!$K$18:$AJ$1670*('W3'!$A$18:$A$1670=Q$5)*('W3'!$D$18:$D$1670=$B$98)*('W3'!$K$14:$AJ$14='Cover Page'!$D108))} -> 320779.87 | T108: {=SUMPRODUCT('W3'!$K$18:$AJ$1670*('W3'!$A$18:$A$1670=T$5)*('W3'!$D$18:$D$1670=$B$98)*('W3'!$K$14:$AJ$14='Cover Page'!$D108))} -> 301039.57 | W108: {=SUMPRODUCT('W3'!$K$18:$AJ$1670*('W3'!$A$18:$A$1670=W$5)*('W3'!$D$18:$D$1670=$B$98)*('W3'!$K$14:$AJ$14='Cover Page'!$D108))} -> 301039.57 | Z108: {=SUMPRODUCT('W3'!$K$18:$AJ$1670*('W3'!$A$18:$A$1670=Z$5)*('W3'!$D$18:$D$1670=$B$98)*('W3'!$K$14:$AJ$14='Cover Page'!$D108))} -> 289183.16 | AC108: {=SUMPRODUCT('W3'!$K$18:$AJ$1670*('W3'!$A$18:$A$1670=AC$5)*('W3'!$D$18:$D$1670=$B$98)*('W3'!$K$14:$AJ$14='Cover Page'!$D108))} -> 305601.48 | AF108: {=SUMPRODUCT('W3'!$K$18:$AJ$1670*('W3'!$A$18:$A$1670=AF$5)*('W3'!$D$18:$D$1670=$B$98)*('W3'!$K$14:$AJ$14='Cover Page'!$D108))} -> 335585.1 | AI108: {=SUMPRODUCT('W3'!$K$18:$AJ$1670*('W3'!$A$18:$A$1670=AI$5)*('W3'!$D$18:$D$1670=$B$98)*('W3'!$K$14:$AJ$14='Cover Page'!$D108))} -> 335585.1
D109: 11 | E109: =IF(Currency="USD","USD","triệu VND") -> triệu VND | H109: {=SUMPRODUCT('W3'!$K$18:$AJ$1670*('W3'!$A$18:$A$1670=H$5)*('W3'!$D$18:$D$1670=$B$98)*('W3'!$K$14:$AJ$14='Cover Page'!$D109))} -> 342296.8 | K109: {=SUMPRODUCT('W3'!$K$18:$AJ$1670*('W3'!$A$18:$A$1670=K$5)*('W3'!$D$18:$D$1670=$B$98)*('W3'!$K$14:$AJ$14='Cover Page'!$D109))} -> 342296.8 | N109: {=SUMPRODUCT('W3'!$K$18:$AJ$1670*('W3'!$A$18:$A$1670=N$5)*('W3'!$D$18:$D$1670=$B$98)*('W3'!$K$14:$AJ$14='Cover Page'!$D109))} -> 327195.47 | Q109: {=SUMPRODUCT('W3'!$K$18:$AJ$1670*('W3'!$A$18:$A$1670=Q$5)*('W3'!$D$18:$D$1670=$B$98)*('W3'!$K$14:$AJ$14='Cover Page'!$D109))} -> 327195.47 | T109: {=SUMPRODUCT('W3'!$K$18:$AJ$1670*('W3'!$A$18:$A$1670=T$5)*('W3'!$D$18:$D$1670=$B$98)*('W3'!$K$14:$AJ$14='Cover Page'!$D109))} -> 307060.37 | W109: {=SUMPRODUCT('W3'!$K$18:$AJ$1670*('W3'!$A$18:$A$1670=W$5)*('W3'!$D$18:$D$1670=$B$98)*('W3'!$K$14:$AJ$14='Cover Page'!$D109))} -> 307060.37 | Z109: {=SUMPRODUCT('W3'!$K$18:$AJ$1670*('W3'!$A$18:$A$1670=Z$5)*('W3'!$D$18:$D$1670=$B$98)*('W3'!$K$14:$AJ$14='Cover Page'!$D109))} -> 294966.83 | AC109: {=SUMPRODUCT('W3'!$K$18:$AJ$1670*('W3'!$A$18:$A$1670=AC$5)*('W3'!$D$18:$D$1670=$B$98)*('W3'!$K$14:$AJ$14='Cover Page'!$D109))} -> 311713.51 | AF109: {=SUMPRODUCT('W3'!$K$18:$AJ$1670*('W3'!$A$18:$A$1670=AF$5)*('W3'!$D$18:$D$1670=$B$98)*('W3'!$K$14:$AJ$14='Cover Page'!$D109))} -> 342296.8 | AI109: {=SUMPRODUCT('W3'!$K$18:$AJ$1670*('W3'!$A$18:$A$1670=AI$5)*('W3'!$D$18:$D$1670=$B$98)*('W3'!$K$14:$AJ$14='Cover Page'!$D109))} -> 342296.8
D110: 12 | E110: =IF(Currency="USD","USD","triệu VND") -> triệu VND | H110: {=SUMPRODUCT('W3'!$K$18:$AJ$1670*('W3'!$A$18:$A$1670=H$5)*('W3'!$D$18:$D$1670=$B$98)*('W3'!$K$14:$AJ$14='Cover Page'!$D110))} -> 349142.74 | K110: {=SUMPRODUCT('W3'!$K$18:$AJ$1670*('W3'!$A$18:$A$1670=K$5)*('W3'!$D$18:$D$1670=$B$98)*('W3'!$K$14:$AJ$14='Cover Page'!$D110))} -> 349142.74 | N110: {=SUMPRODUCT('W3'!$K$18:$AJ$1670*('W3'!$A$18:$A$1670=N$5)*('W3'!$D$18:$D$1670=$B$98)*('W3'!$K$14:$AJ$14='Cover Page'!$D110))} -> 333739.38 | Q110: {=SUMPRODUCT('W3'!$K$18:$AJ$1670*('W3'!$A$18:$A$1670=Q$5)*('W3'!$D$18:$D$1670=$B$98)*('W3'!$K$14:$AJ$14='Cover Page'!$D110))} -> 333739.38 | T110: {=SUMPRODUCT('W3'!$K$18:$AJ$1670*('W3'!$A$18:$A$1670=T$5)*('W3'!$D$18:$D$1670=$B$98)*('W3'!$K$14:$AJ$14='Cover Page'!$D110))} -> 313201.57 | W110: {=SUMPRODUCT('W3'!$K$18:$AJ$1670*('W3'!$A$18:$A$1670=W$5)*('W3'!$D$18:$D$1670=$B$98)*('W3'!$K$14:$AJ$14='Cover Page'!$D110))} -> 313201.57 | Z110: {=SUMPRODUCT('W3'!$K$18:$AJ$1670*('W3'!$A$18:$A$1670=Z$5)*('W3'!$D$18:$D$1670=$B$98)*('W3'!$K$14:$AJ$14='Cover Page'!$D110))} -> 300866.16 | AC110: {=SUMPRODUCT('W3'!$K$18:$AJ$1670*('W3'!$A$18:$A$1670=AC$5)*('W3'!$D$18:$D$1670=$B$98)*('W3'!$K$14:$AJ$14='Cover Page'!$D110))} -> 317947.78 | AF110: {=SUMPRODUCT('W3'!$K$18:$AJ$1670*('W3'!$A$18:$A$1670=AF$5)*('W3'!$D$18:$D$1670=$B$98)*('W3'!$K$14:$AJ$14='Cover Page'!$D110))} -> 349142.74 | AI110: {=SUMPRODUCT('W3'!$K$18:$AJ$1670*('W3'!$A$18:$A$1670=AI$5)*('W3'!$D$18:$D$1670=$B$98)*('W3'!$K$14:$AJ$14='Cover Page'!$D110))} -> 349142.74
... D123: 25 | E123: =IF(Currency="USD","USD","triệu VND") -> triệu VND | H123: {=SUMPRODUCT('W3'!$K$18:$AJ$1670*('W3'!$A$18:$A$1670=H$5)*('W3'!$D$18:$D$1670=$B$98)*('W3'!$K$14:$AJ$14='Cover Page'!$D123))} -> 0 | K123: {=SUMPRODUCT('W3'!$K$18:$AJ$1670*('W3'!$A$18:$A$1670=K$5)*('W3'!$D$18:$D$1670=$B$98)*('W3'!$K$14:$AJ$14='Cover Page'!$D123))} -> 0 | N123: {=SUMPRODUCT('W3'!$K$18:$AJ$1670*('W3'!$A$18:$A$1670=N$5)*('W3'!$D$18:$D$1670=$B$98)*('W3'!$K$14:$AJ$14='Cover Page'!$D123))} -> 0 | Q123: {=SUMPRODUCT('W3'!$K$18:$AJ$1670*('W3'!$A$18:$A$1670=Q$5)*('W3'!$D$18:$D$1670=$B$98)*('W3'!$K$14:$AJ$14='Cover Page'!$D123))} -> 0 | T123: {=SUMPRODUCT('W3'!$K$18:$AJ$1670*('W3'!$A$18:$A$1670=T$5)*('W3'!$D$18:$D$1670=$B$98)*('W3'!$K$14:$AJ$14='Cover Page'!$D123))} -> 0 | W123: {=SUMPRODUCT('W3'!$K$18:$AJ$1670*('W3'!$A$18:$A$1670=W$5)*('W3'!$D$18:$D$1670=$B$98)*('W3'!$K$14:$AJ$14='Cover Page'!$D123))} -> 0 | Z123: {=SUMPRODUCT('W3'!$K$18:$AJ$1670*('W3'!$A$18:$A$1670=Z$5)*('W3'!$D$18:$D$1670=$B$98)*('W3'!$K$14:$AJ$14='Cover Page'!$D123))} -> 0 | AC123: {=SUMPRODUCT('W3'!$K$18:$AJ$1670*('W3'!$A$18:$A$1670=AC$5)*('W3'!$D$18:$D$1670=$B$98)*('W3'!$K$14:$AJ$14='Cover Page'!$D123))} -> 0 | AF123: {=SUMPRODUCT('W3'!$K$18:$AJ$1670*('W3'!$A$18:$A$1670=AF$5)*('W3'!$D$18:$D$1670=$B$98)*('W3'!$K$14:$AJ$14='Cover Page'!$D123))} -> 0 | AI123: {=SUMPRODUCT('W3'!$K$18:$AJ$1670*('W3'!$A$18:$A$1670=AI$5)*('W3'!$D$18:$D$1670=$B$98)*('W3'!$K$14:$AJ$14='Cover Page'!$D123))} -> 0

Sheet W1
D1: Công ty CP Nhựa tái chế Duy Tân
D2: Đơn vị: Kế toán quản trị
D3: DỰ ÁN FLAKES TO PREFORM SUNTORY - PEPSICO
D4: TỔNG CHI PHÍ ĐẦU TƯ
D5: =Currency -> VND | N5: (không tăng chi phí xây dựng nhà xưởng) - Roundup | S5: (không tăng chi phí xây dựng nhà xưởng) | X5: (không tăng chi phí xây dựng nhà xưởng) | AC5: (không tăng chi phí xây dựng nhà xưởng) | AH5: (không tăng chi phí xây dựng nhà xưởng)
D6: =IF(D5="VND",1,EXR) -> 1 | I6: Option 1 | J6: BASE | N6: Option 2 | O6: =Opt2_CAPEX -> 0 | S6: Option 3 | T6: =Opt3_CAPEX -> 0 | X6: Option 4 | Y6: =Opt4_CAPEX -> 0 | AC6: Option 5 | AD6: =Opt5_CAPEX -> 0 | AH6: Option 6 | AI6: =Opt6_CAPEX -> 0 | AM6: Option 7 | AN6: =Opt7_CAPEX -> 0 | AR6: Option 8 | AS6: =Opt8_CAPEX -> 0 | AW6: Option 9 | AX6: =Opt9_CAPEX -> 0 | BB6: Option 10 | BC6: =Opt10_CAPEX -> 0
C7: STT | D7: HẠNG MỤC | E7: Số lượng | G7: Thời gian khấu hao | H7: Đơn giá | I7: Giá trị đầu tư | J7: Khấu hao | L7: Thời gian khấu hao | M7: Đơn giá | N7: Giá trị đầu tư | O7: Khấu hao | Q7: Thời gian khấu hao | R7: Đơn giá | S7: Giá trị đầu tư | T7: Khấu hao | V7: Thời gian khấu hao | W7: Đơn giá | X7: Giá trị đầu tư | Y7: Khấu hao | AA7: Thời gian khấu hao | AB7: Đơn giá | AC7: Giá trị đầu tư | AD7: Khấu hao | AF7: Thời gian khấu hao | AG7: Đơn giá | AH7: Giá trị đầu tư | AI7: Khấu hao | AK7: Thời gian khấu hao | AL7: Đơn giá | AM7: Giá trị đầu tư | AN7: Khấu hao | AP7: Thời gian khấu hao | AQ7: Đơn giá | AR7: Giá trị đầu tư | AS7: Khấu hao | AU7: Thời gian khấu hao | AV7: Đơn giá | AW7: Giá trị đầu tư | AX7: Khấu hao | AZ7: Thời gian khấu hao | BA7: Đơn giá | BB7: Giá trị đầu tư | BC7: Khấu hao | BE7: NHẬP KHẨU TỪ | BF7: Nguồn: | BG7: Ghi chú - Nếu dừng dự án thì Suntory mua lại | BI7: Option 1 | BJ7: =BI7 -> Option 1 | BK7: =BJ7 -> Option 1 | BL7: =BK7 -> Option 1 | BM7: =BL7 -> Option 1 | BN7: =BM7 -> Option 1 | BO7: =BN7 -> Option 1 | BP7: =BO7 -> Option 1 | BQ7: =BP7 -> Option 1 | ... CL7: =CK7 -> Option 1 | CN7: Option 2 | CO7: =CN7 -> Option 2 | CP7: =CO7 -> Option 2 | CQ7: =CP7 -> Option 2 | CR7: =CQ7 -> Option 2 | CS7: =CR7 -> Option 2 | CT7: =CS7 -> Option 2 | CU7: =CT7 -> Option 2 | CV7: =CU7 -> Option 2 | ... DQ7: =DP7 -> Option 2 | DS7: Option 3 | DT7: Option 3 | DU7: Option 3 | DV7: Option 3 | DW7: Option 3 | DX7: Option 3 | DY7: Option 3 | DZ7: Option 3 | EA7: Option 3 | EB7: Option 3 | EC7: Option 3 | ED7: Option 3 | EE7: Option 3 | EF7: Option 3 | EG7: Option 3 | EH7: Option 3 | EI7: Option 3 | EJ7: Option 3 | EK7: Option 3 | EL7: Option 3 | EM7: Option 3 | EN7: Option 3 | EO7: Option 3 | EP7: Option 3 | EQ7: Option 3 | ER7: Option 3 | ES7: Option 3 | ET7: Option 3 | EU7: Option 3 | EV7: Option 3 | EX7: Option 4 | EY7: Option 4 | EZ7: Option 4 | FA7: Option 4 | FB7: Option 4 | FC7: Option 4 | FD7: Option 4 | FE7: Option 4 | FF7: Option 4 | FG7: Option 4 | FH7: Option 4 | FI7: Option 4 | FJ7: Option 4 | FK7: Option 4 | FL7: Option 4 | FM7: Option 4 | FN7: Option 4 | FO7: Option 4 | FP7: Option 4 | FQ7: Option 4 | FR7: Option 4 | FS7: Option 4 | FT7: Option 4 | FU7: Option 4 | FV7: Option 4 | FW7: Option 4 | FX7: Option 4 | FY7: Option 4 | FZ7: Option 4 | GA7: Option 4 | GC7: Option 5 | GD7: Option 5 | GE7: Option 5 | GF7: Option 5 | GG7: Option 5 | GH7: Option 5 | GI7: Option 5 | GJ7: Option 5 | GK7: Option 5 | GL7: Option 5 | GM7: Option 5 | GN7: Option 5 | GO7: Option 5 | GP7: Option 5 | GQ7: Option 5 | GR7: Option 5 | GS7: Option 5 | GT7: Option 5 | GU7: Option 5 | GV7: Option 5 | GW7: Option 5 | GX7: Option 5 | GY7: Option 5 | GZ7: Option 5 | HA7: Option 5 | HB7: Option 5 | HC7: Option 5 | HD7: Option 5 | HE7: Option 5 | HF7: Option 5 | HH7: Option 6 | HI7: Option 6 | HJ7: Option 6 | HK7: Option 6 | HL7: Option 6 | HM7: Option 6 | HN7: Option 6 | HO7: Option 6 | HP7: Option 6 | HQ7: Option 6 | HR7: Option 6 | HS7: Option 6 | HT7: Option 6 | HU7: Option 6 | HV7: Option 6 | HW7: Option 6 | HX7: Option 6 | HY7: Option 6 | HZ7: Option 6 | IA7: Option 6 | IB7: Option 6 | IC7: Option 6 | ID7: Option 6 | IE7: Option 6 | IF7: Option 6 | IG7: Option 6 | IH7: Option 6 | II7: Option 6 | IJ7: Option 6 | IK7: Option 6 | IM7: Option 7 | IN7: Option 7 | IO7: Option 7 | IP7: Option 7 | IQ7: Option 7 | IR7: Option 7 | IS7: Option 7 | IT7: Option 7 | IU7: Option 7 | IV7: Option 7 | IW7: Option 7 | IX7: Option 7 | IY7: Option 7 | IZ7: Option 7 | JA7: Option 7 | JB7: Option 7 | JC7: Option 7 | JD7: Option 7 | JE7: Option 7 | JF7: Option 7 | JG7: Option 7 | JH7: Option 7 | JI7: Option 7 | JJ7: Option 7 | JK7: Option 7 | JL7: Option 7 | JM7: Option 7 | JN7: Option 7 | JO7: Option 7 | JP7: Option 7 | JR7: Option 8 | JS7: Option 8 | JT7: Option 8 | JU7: Option 8 | JV7: Option 8 | JW7: Option 8 | JX7: Option 8 | JY7: Option 8 | JZ7: Option 8 | KA7: Option 8 | KB7: Option 8 | KC7: Option 8 | KD7: Option 8 | KE7: Option 8 | KF7: Option 8 | KG7: Option 8 | KH7: Option 8 | KI7: Option 8 | KJ7: Option 8 | KK7: Option 8 | KL7: Option 8 | KM7: Option 8 | KN7: Option 8 | KO7: Option 8 | KP7: Option 8 | KQ7: Option 8 | KR7: Option 8 | KS7: Option 8 | KT7: Option 8 | KU7: Option 8 | KW7: Option 9 | KX7: Option 9 | KY7: Option 9 | KZ7: Option 9 | LA7: Option 9 | LB7: Option 9 | LC7: Option 9 | LD7: Option 9 | LE7: Option 9 | LF7: Option 9 | LG7: Option 9 | LH7: Option 9 | LI7: Option 9 | LJ7: Option 9 | LK7: Option 9 | LL7: Option 9 | LM7: Option 9 | LN7: Option 9 | LO7: Option 9 | LP7: Option 9 | LQ7: Option 9 | LR7: Option 9 | LS7: Option 9 | LT7: Option 9 | LU7: Option 9 | LV7: Option 9 | LW7: Option 9 | LX7: Option 9 | LY7: Option 9 | LZ7: Option 9 | MB7: Option 10 | MC7: Option 10 | MD7: Option 10 | ME7: Option 10 | MF7: Option 10 | MG7: Option 10 | MH7: Option 10 | MI7: Option 10 | MJ7: Option 10 | MK7: Option 10 | ML7: Option 10 | MM7: Option 10 | MN7: Option 10 | MO7: Option 10 | MP7: Option 10 | MQ7: Option 10 | MR7: Option 10 | MS7: Option 10 | MT7: Option 10 | MU7: Option 10 | MV7: Option 10 | MW7: Option 10 | MX7: Option 10 | MY7: Option 10 | MZ7: Option 10 | NA7: Option 10 | NB7: Option 10 | NC7: Option 10 | ND7: Option 10 | NE7: Option 10
A8: Link qua W3 | B8: Link qua Sun-W6 | E8: (cái,m2) | G8: (Năm) | H8: ="("&$D$5&")" -> (VND) | I8: ="("&$D$5&")" -> (VND) | J8: ="("&$D$5&"/năm)" -> (VND/năm) | L8: (Năm) | M8: ="("&$D$5&")" -> (VND) | N8: ="("&$D$5&")" -> (VND) | O8: ="("&$D$5&"/năm)" -> (VND/năm) | Q8: (Năm) | R8: ="("&$D$5&")" -> (VND) | S8: ="("&$D$5&")" -> (VND) | T8: ="("&$D$5&"/năm)" -> (VND/năm) | V8: (Năm) | W8: ="("&$D$5&")" -> (VND) | X8: ="("&$D$5&")" -> (VND) | Y8: ="("&$D$5&"/năm)" -> (VND/năm) | AA8: (Năm) | AB8: ="("&$D$5&")" -> (VND) | AC8: ="("&$D$5&")" -> (VND) | AD8: ="("&$D$5&"/năm)" -> (VND/năm) | AF8: (Năm) | AG8: ="("&$D$5&")" -> (VND) | AH8: ="("&$D$5&")" -> (VND) | AI8: ="("&$D$5&"/năm)" -> (VND/năm) | AK8: (Năm) | AL8: ="("&$D$5&")" -> (VND) | AM8: ="("&$D$5&")" -> (VND) | AN8: ="("&$D$5&"/năm)" -> (VND/năm) | AP8: (Năm) | AQ8: ="("&$D$5&")" -> (VND) | AR8: ="("&$D$5&")" -> (VND) | AS8: ="("&$D$5&"/năm)" -> (VND/năm) | AU8: (Năm) | AV8: ="("&$D$5&")" -> (VND) | AW8: ="("&$D$5&")" -> (VND) | AX8: ="("&$D$5&"/năm)" -> (VND/năm) | AZ8: (Năm) | BA8: ="("&$D$5&")" -> (VND) | BB8: ="("&$D$5&")" -> (VND) | BC8: ="("&$D$5&"/năm)" -> (VND/năm) | BI8: 1 | BJ8: 2 | BK8: 3 | BL8: 4 | BM8: 5 | BN8: 6 | BO8: 7 | BP8: 8 | BQ8: 9 | BR8: 10 | BS8: 11 | BT8: 12 | BU8: 13 | BV8: 14 | BW8: 15 | BX8: 16 | BY8: 17 | BZ8: 18 | CA8: 19 | CB8: 20 | CC8: 21 | CD8: 22 | CE8: 23 | CF8: 24 | CG8: 25 | CH8: 26 | CI8: 27 | CJ8: 28 | CK8: 29 | CL8: 30 | CN8: 1 | CO8: 2 | CP8: 3 | CQ8: 4 | CR8: 5 | CS8: 6 | CT8: 7 | CU8: 8 | CV8: 9 | CW8: 10 | CX8: 11 | CY8: 12 | CZ8: 13 | DA8: 14 | DB8: 15 | DC8: 16 | DD8: 17 | DE8: 18 | DF8: 19 | DG8: 20 | DH8: 21 | DI8: 22 | DJ8: 23 | DK8: 24 | DL8: 25 | DM8: 26 | DN8: 27 | DO8: 28 | DP8: 29 | DQ8: 30 | DS8: 1 | DT8: 2 | DU8: 3 | DV8: 4 | DW8: 5 | DX8: 6 | DY8: 7 | DZ8: 8 | EA8: 9 | EB8: 10 | EC8: 11 | ED8: 12 | EE8: 13 | EF8: 14 | EG8: 15 | EH8: 16 | EI8: 17 | EJ8: 18 | EK8: 19 | EL8: 20 | EM8: 21 | EN8: 22 | EO8: 23 | EP8: 24 | EQ8: 25 | ER8: 26 | ES8: 27 | ET8: 28 | EU8: 29 | EV8: 30 | EX8: 1 | EY8: 2 | EZ8: 3 | FA8: 4 | FB8: 5 | FC8: 6 | FD8: 7 | FE8: 8 | FF8: 9 | FG8: 10 | FH8: 11 | FI8: 12 | FJ8: 13 | FK8: 14 | FL8: 15 | FM8: 16 | FN8: 17 | FO8: 18 | FP8: 19 | FQ8: 20 | FR8: 21 | FS8: 22 | FT8: 23 | FU8: 24 | FV8: 25 | FW8: 26 | FX8: 27 | FY8: 28 | FZ8: 29 | GA8: 30 | GC8: 1 | GD8: 2 | GE8: 3 | GF8: 4 | GG8: 5 | GH8: 6 | GI8: 7 | GJ8: 8 | GK8: 9 | GL8: 10 | GM8: 11 | GN8: 12 | GO8: 13 | GP8: 14 | GQ8: 15 | GR8: 16 | GS8: 17 | GT8: 18 | GU8: 19 | GV8: 20 | GW8: 21 | GX8: 22 | GY8: 23 | GZ8: 24 | HA8: 25 | HB8: 26 | HC8: 27 | HD8: 28 | HE8: 29 | HF8: 30 | HH8: 1 | HI8: 2 | HJ8: 3 | HK8: 4 | HL8: 5 | HM8: 6 | HN8: 7 | HO8: 8 | HP8: 9 | HQ8: 10 | HR8: 11 | HS8: 12 | HT8: 13 | HU8: 14 | HV8: 15 | HW8: 16 | HX8: 17 | HY8: 18 | HZ8: 19 | IA8: 20 | IB8: 21 | IC8: 22 | ID8: 23 | IE8: 24 | IF8: 25 | IG8: 26 | IH8: 27 | II8: 28 | IJ8: 29 | IK8: 30 | IM8: 1 | IN8: 2 | IO8: 3 | IP8: 4 | IQ8: 5 | IR8: 6 | IS8: 7 | IT8: 8 | IU8: 9 | IV8: 10 | IW8: 11 | IX8: 12 | IY8: 13 | IZ8: 14 | JA8: 15 | JB8: 16 | JC8: 17 | JD8: 18 | JE8: 19 | JF8: 20 | JG8: 21 | JH8: 22 | JI8: 23 | JJ8: 24 | JK8: 25 | JL8: 26 | JM8: 27 | JN8: 28 | JO8: 29 | JP8: 30 | JR8: 1 | JS8: 2 | JT8: 3 | JU8: 4 | JV8: 5 | JW8: 6 | JX8: 7 | JY8: 8 | JZ8: 9 | KA8: 10 | KB8: 11 | KC8: 12 | KD8: 13 | KE8: 14 | KF8: 15 | KG8: 16 | KH8: 17 | KI8: 18 | KJ8: 19 | KK8: 20 | KL8: 21 | KM8: 22 | KN8: 23 | KO8: 24 | KP8: 25 | KQ8: 26 | KR8: 27 | KS8: 28 | KT8: 29 | KU8: 30 | KW8: 1 | KX8: 2 | KY8: 3 | KZ8: 4 | LA8: 5 | LB8: 6 | LC8: 7 | LD8: 8 | LE8: 9 | LF8: 10 | LG8: 11 | LH8: 12 | LI8: 13 | LJ8: 14 | LK8: 15 | LL8: 16 | LM8: 17 | LN8: 18 | LO8: 19 | LP8: 20 | LQ8: 21 | LR8: 22 | LS8: 23 | LT8: 24 | LU8: 25 | LV8: 26 | LW8: 27 | LX8: 28 | LY8: 29 | LZ8: 30 | MB8: 1 | MC8: 2 | MD8: 3 | ME8: 4 | MF8: 5 | MG8: 6 | MH8: 7 | MI8: 8 | MJ8: 9 | MK8: 10 | ML8: 11 | MM8: 12 | MN8: 13 | MO8: 14 | MP8: 15 | MQ8: 16 | MR8: 17 | MS8: 18 | MT8: 19 | MU8: 20 | MV8: 21 | MW8: 22 | MX8: 23 | MY8: 24 | MZ8: 25 | NA8: 26 | NB8: 27 | NC8: 28 | ND8: 29 | NE8: 30
C10: 1 | D10: MÁY MÓC THIẾT BỊ | I10: =I12+I20 -> 284499800000 | J10: =J12+J20 -> 2.3708317e+10 | N10: =N12+N20 -> 284499800000 | O10: =O12+O20 -> 2.3708317e+10 | S10: =S12+S20 -> 284499800000 | T10: =T12+T20 -> 2.3708317e+10 | X10: =X12+X20 -> 284499800000 | Y10: =Y12+Y20 -> 2.3708317e+10 | AC10: =AC12+AC20 -> 284499800000 | AD10: =AD12+AD20 -> 2.3708317e+10 | AH10: =AH12+AH20 -> 284499800000 | AI10: =AI12+AI20 -> 2.3708317e+10 | AM10: =AM12+AM20 -> 284499800000 | AN10: =AN12+AN20 -> 2.3708317e+10 | AR10: =AR12+AR20 -> 284499800000 | AS10: =AS12+AS20 -> 2.3708317e+10 | AW10: =AW12+AW20 -> 284499800000 | AX10: =AX12+AX20 -> 2.3708317e+10 | BB10: =BB12+BB20 -> 284499800000 | BC10: =BC12+BC20 -> 2.3708317e+10 | BI10: =BI12+BI20 -> 2.3708317e+10 | BJ10: =BJ12+BJ20 -> 2.3708317e+10 | BK10: =BK12+BK20 -> 2.3708317e+10 | BL10: =BL12+BL20 -> 2.3708317e+10 | BM10: =BM12+BM20 -> 2.3708317e+10 | BN10: =BN12+BN20 -> 2.3708317e+10 | BO10: =BO12+BO20 -> 2.3708317e+10 | BP10: =BP12+BP20 -> 2.3708317e+10 | ... CL10: =CL12+CL20 -> 0 | CN10: =CN12+CN20 -> 2.3708317e+10 | CO10: =CO12+CO20 -> 2.3708317e+10 | CP10: =CP12+CP20 -> 2.3708317e+10 | CQ10: =CQ12+CQ20 -> 2.3708317e+10 | CR10: =CR12+CR20 -> 2.3708317e+10 | CS10: =CS12+CS20 -> 2.3708317e+10 | CT10: =CT12+CT20 -> 2.3708317e+10 | CU10: =CU12+CU20 -> 2.3708317e+10 | ... DQ10: =DQ12+DQ20 -> 0 | DS10: =DS12+DS20 -> 2.3708317e+10 | DT10: =DT12+DT20 -> 2.3708317e+10 | DU10: =DU12+DU20 -> 2.3708317e+10 | DV10: =DV12+DV20 -> 2.3708317e+10 | DW10: =DW12+DW20 -> 2.3708317e+10 | DX10: =DX12+DX20 -> 2.3708317e+10 | DY10: =DY12+DY20 -> 2.3708317e+10 | DZ10: =DZ12+DZ20 -> 2.3708317e+10 | ... EV10: =EV12+EV20 -> 0 | EX10: =EX12+EX20 -> 2.3708317e+10 | EY10: =EY12+EY20 -> 2.3708317e+10 | EZ10: =EZ12+EZ20 -> 2.3708317e+10 | FA10: =FA12+FA20 -> 2.3708317e+10 | FB10: =FB12+FB20 -> 2.3708317e+10 | FC10: =FC12+FC20 -> 2.3708317e+10 | FD10: =FD12+FD20 -> 2.3708317e+10 | FE10: =FE12+FE20 -> 2.3708317e+10 | ... GA10: =GA12+GA20 -> 0 | GC10: =GC12+GC20 -> 2.3708317e+10 | GD10: =GD12+GD20 -> 2.3708317e+10 | GE10: =GE12+GE20 -> 2.3708317e+10 | GF10: =GF12+GF20 -> 2.3708317e+10 | GG10: =GG12+GG20 -> 2.3708317e+10 | GH10: =GH12+GH20 -> 2.3708317e+10 | GI10: =GI12+GI20 -> 2.3708317e+10 | GJ10: =GJ12+GJ20 -> 2.3708317e+10 | ... HF10: =HF12+HF20 -> 0 | HH10: =HH12+HH20 -> 2.3708317e+10 | HI10: =HI12+HI20 -> 2.3708317e+10 | HJ10: =HJ12+HJ20 -> 2.3708317e+10 | HK10: =HK12+HK20 -> 2.3708317e+10 | HL10: =HL12+HL20 -> 2.3708317e+10 | HM10: =HM12+HM20 -> 2.3708317e+10 | HN10: =HN12+HN20 -> 2.3708317e+10 | HO10: =HO12+HO20 -> 2.3708317e+10 | ... IK10: =IK12+IK20 -> 0 | IM10: =IM12+IM20 -> 2.3708317e+10 | IN10: =IN12+IN20 -> 2.3708317e+10 | IO10: =IO12+IO20 -> 2.3708317e+10 | IP10: =IP12+IP20 -> 2.3708317e+10 | IQ10: =IQ12+IQ20 -> 2.3708317e+10 | IR10: =IR12+IR20 -> 2.3708317e+10 | IS10: =IS12+IS20 -> 2.3708317e+10 | IT10: =IT12+IT20 -> 2.3708317e+10 | ... JP10: =JP12+JP20 -> 0 | JR10: =JR12+JR20 -> 2.3708317e+10 | JS10: =JS12+JS20 -> 2.3708317e+10 | JT10: =JT12+JT20 -> 2.3708317e+10 | JU10: =JU12+JU20 -> 2.3708317e+10 | JV10: =JV12+JV20 -> 2.3708317e+10 | JW10: =JW12+JW20 -> 2.3708317e+10 | JX10: =JX12+JX20 -> 2.3708317e+10 | JY10: =JY12+JY20 -> 2.3708317e+10 | ... KU10: =KU12+KU20 -> 0 | KW10: =KW12+KW20 -> 2.3708317e+10 | KX10: =KX12+KX20 -> 2.3708317e+10 | KY10: =KY12+KY20 -> 2.3708317e+10 | KZ10: =KZ12+KZ20 -> 2.3708317e+10 | LA10: =LA12+LA20 -> 2.3708317e+10 | LB10: =LB12+LB20 -> 2.3708317e+10 | LC10: =LC12+LC20 -> 2.3708317e+10 | LD10: =LD12+LD20 -> 2.3708317e+10 | ... LZ10: =LZ12+LZ20 -> 0 | MB10: =MB12+MB20 -> 2.3708317e+10 | MC10: =MC12+MC20 -> 2.3708317e+10 | MD10: =MD12+MD20 -> 2.3708317e+10 | ME10: =ME12+ME20 -> 2.3708317e+10 | MF10: =MF12+MF20 -> 2.3708317e+10 | MG10: =MG12+MG20 -> 2.3708317e+10 | MH10: =MH12+MH20 -> 2.3708317e+10 | MI10: =MI12+MI20 -> 2.3708317e+10 | ... NE10: =NE12+NE20 -> 0
A12: CAPEX-MAIN | C12: 1.1 | D12: Máy móc thiết bị chính | I12: =SUM(I13:I18) -> 2.46389e+11 | J12: =SUM(J13:J18) -> 2.0532417e+10 | N12: =SUM(N13:N18) -> 2.46389e+11 | O12: =SUM(O13:O18) -> 2.0532417e+10 | S12: =SUM(S13:S18) -> 2.46389e+11 | T12: =SUM(T13:T18) -> 2.0532417e+10 | X12: =SUM(X13:X18) -> 2.46389e+11 | Y12: =SUM(Y13:Y18) -> 2.0532417e+10 | AC12: =SUM(AC13:AC18) -> 2.46389e+11 | AD12: =SUM(AD13:AD18) -> 2.0532417e+10 | AH12: =SUM(AH13:AH18) -> 2.46389e+11 | AI12: =SUM(AI13:AI18) -> 2.0532417e+10 | AM12: =SUM(AM13:AM18) -> 2.46389e+11 | AN12: =SUM(AN13:AN18) -> 2.0532417e+10 | AR12: =SUM(AR13:AR18) -> 2.46389e+11 | AS12: =SUM(AS13:AS18) -> 2.0532417e+10 | AW12: =SUM(AW13:AW18) -> 2.46389e+11 | AX12: =SUM(AX13:AX18) -> 2.0532417e+10 | BB12: =SUM(BB13:BB18) -> 2.46389e+11 | BC12: =SUM(BC13:BC18) -> 2.0532417e+10 | BI12: =SUM(BI13:BI18) -> 2.0532417e+10 | BJ12: =SUM(BJ13:BJ18) -> 2.0532417e+10 | BK12: =SUM(BK13:BK18) -> 2.0532417e+10 | BL12: =SUM(BL13:BL18) -> 2.0532417e+10 | BM12: =SUM(BM13:BM18) -> 2.0532417e+10 | BN12: =SUM(BN13:BN18) -> 2.0532417e+10 | BO12: =SUM(BO13:BO18) -> 2.0532417e+10 | BP12: =SUM(BP13:BP18) -> 2.0532417e+10 | ... CL12: =SUM(CL13:CL18) -> 0 | CN12: =SUM(CN13:CN18) -> 2.0532417e+10 | CO12: =SUM(CO13:CO18) -> 2.0532417e+10 | CP12: =SUM(CP13:CP18) -> 2.0532417e+10 | CQ12: =SUM(CQ13:CQ18) -> 2.0532417e+10 | CR12: =SUM(CR13:CR18) -> 2.0532417e+10 | CS12: =SUM(CS13:CS18) -> 2.0532417e+10 | CT12: =SUM(CT13:CT18) -> 2.0532417e+10 | CU12: =SUM(CU13:CU18) -> 2.0532417e+10 | ... DQ12: =SUM(DQ13:DQ18) -> 0 | DS12: =SUM(DS13:DS18) -> 2.0532417e+10 | DT12: =SUM(DT13:DT18) -> 2.0532417e+10 | DU12: =SUM(DU13:DU18) -> 2.0532417e+10 | DV12: =SUM(DV13:DV18) -> 2.0532417e+10 | DW12: =SUM(DW13:DW18) -> 2.0532417e+10 | DX12: =SUM(DX13:DX18) -> 2.0532417e+10 | DY12: =SUM(DY13:DY18) -> 2.0532417e+10 | DZ12: =SUM(DZ13:DZ18) -> 2.0532417e+10 | ... EV12: =SUM(EV13:EV18) -> 0 | EX12: =SUM(EX13:EX18) -> 2.0532417e+10 | EY12: =SUM(EY13:EY18) -> 2.0532417e+10 | EZ12: =SUM(EZ13:EZ18) -> 2.0532417e+10 | FA12: =SUM(FA13:FA18) -> 2.0532417e+10 | FB12: =SUM(FB13:FB18) -> 2.0532417e+10 | FC12: =SUM(FC13:FC18) -> 2.0532417e+10 | FD12: =SUM(FD13:FD18) -> 2.0532417e+10 | FE12: =SUM(FE13:FE18) -> 2.0532417e+10 | ... GA12: =SUM(GA13:GA18) -> 0 | GC12: =SUM(GC13:GC18) -> 2.0532417e+10 | GD12: =SUM(GD13:GD18) -> 2.0532417e+10 | GE12: =SUM(GE13:GE18) -> 2.0532417e+10 | GF12: =SUM(GF13:GF18) -> 2.0532417e+10 | GG12: =SUM(GG13:GG18) -> 2.0532417e+10 | GH12: =SUM(GH13:GH18) -> 2.0532417e+10 | GI12: =SUM(GI13:GI18) -> 2.0532417e+10 | GJ12: =SUM(GJ13:GJ18) -> 2.0532417e+10 | ... HF12: =SUM(HF13:HF18) -> 0 | HH12: =SUM(HH13:HH18) -> 2.0532417e+10 | HI12: =SUM(HI13:HI18) -> 2.0532417e+10 | HJ12: =SUM(HJ13:HJ18) -> 2.0532417e+10 | HK12: =SUM(HK13:HK18) -> 2.0532417e+10 | HL12: =SUM(HL13:HL18) -> 2.0532417e+10 | HM12: =SUM(HM13:HM18) -> 2.0532417e+10 | HN12: =SUM(HN13:HN18) -> 2.0532417e+10 | HO12: =SUM(HO13:HO18) -> 2.0532417e+10 | ... IK12: =SUM(IK13:IK18) -> 0 | IM12: =SUM(IM13:IM18) -> 2.0532417e+10 | IN12: =SUM(IN13:IN18) -> 2.0532417e+10 | IO12: =SUM(IO13:IO18) -> 2.0532417e+10 | IP12: =SUM(IP13:IP18) -> 2.0532417e+10 | IQ12: =SUM(IQ13:IQ18) -> 2.0532417e+10 | IR12: =SUM(IR13:IR18) -> 2.0532417e+10 | IS12: =SUM(IS13:IS18) -> 2.0532417e+10 | IT12: =SUM(IT13:IT18) -> 2.0532417e+10 | ... JP12: =SUM(JP13:JP18) -> 0 | JR12: =SUM(JR13:JR18) -> 2.0532417e+10 | JS12: =SUM(JS13:JS18) -> 2.0532417e+10 | JT12: =SUM(JT13:JT18) -> 2.0532417e+10 | JU12: =SUM(JU13:JU18) -> 2.0532417e+10 | JV12: =SUM(JV13:JV18) -> 2.0532417e+10 | JW12: =SUM(JW13:JW18) -> 2.0532417e+10 | JX12: =SUM(JX13:JX18) -> 2.0532417e+10 | JY12: =SUM(JY13:JY18) -> 2.0532417e+10 | ... KU12: =SUM(KU13:KU18) -> 0 | KW12: =SUM(KW13:KW18) -> 2.0532417e+10 | KX12: =SUM(KX13:KX18) -> 2.0532417e+10 | KY12: =SUM(KY13:KY18) -> 2.0532417e+10 | KZ12: =SUM(KZ13:KZ18) -> 2.0532417e+10 | LA12: =SUM(LA13:LA18) -> 2.0532417e+10 | LB12: =SUM(LB13:LB18) -> 2.0532417e+10 | LC12: =SUM(LC13:LC18) -> 2.0532417e+10 | LD12: =SUM(LD13:LD18) -> 2.0532417e+10 | ... LZ12: =SUM(LZ13:LZ18) -> 0 | MB12: =SUM(MB13:MB18) -> 2.0532417e+10 | MC12: =SUM(MC13:MC18) -> 2.0532417e+10 | MD12: =SUM(MD13:MD18) -> 2.0532417e+10 | ME12: =SUM(ME13:ME18) -> 2.0532417e+10 | MF12: =SUM(MF13:MF18) -> 2.0532417e+10 | MG12: =SUM(MG13:MG18) -> 2.0532417e+10 | MH12: =SUM(MH13:MH18) -> 2.0532417e+10 | MI12: =SUM(MI13:MI18) -> 2.0532417e+10 | ... NE12: =SUM(NE13:NE18) -> 0
B13: NGR system | C13: 1.1.01 | D13: NGR : LSP 1200 | E13: 1 | G13: 12 | H13: =(123250000000/$D$6)*1.04 -> 128180000000 | I13: =$E13*$H13 -> 128180000000 | J13: =I13/G13 -> 1.0681667e+10 | L13: 12 | M13: =$H13*(1+O$6) -> 128180000000 | N13: =$E13*M13 -> 128180000000 | O13: =N13/L13 -> 1.0681667e+10 | Q13: 12 | R13: =$H13*(1+T$6) -> 128180000000 | S13: =$E13*R13 -> 128180000000 | T13: =S13/Q13 -> 1.0681667e+10 | V13: 12 | W13: =$H13*(1+Y$6) -> 128180000000 | X13: =$E13*W13 -> 128180000000 | Y13: =X13/V13 -> 1.0681667e+10 | AA13: 12 | AB13: =$H13*(1+AD$6) -> 128180000000 | AC13: =$E13*AB13 -> 128180000000 | AD13: =AC13/AA13 -> 1.0681667e+10 | AF13: 12 | AG13: =$H13*(1+AI$6) -> 128180000000 | AH13: =$E13*AG13 -> 128180000000 | AI13: =AH13/AF13 -> 1.0681667e+10 | AK13: 12 | AL13: =$H13*(1+AN$6) -> 128180000000 | AM13: =$E13*AL13 -> 128180000000 | AN13: =AM13/AK13 -> 1.0681667e+10 | AP13: 12 | AQ13: =$H13*(1+AS$6) -> 128180000000 | AR13: =$E13*AQ13 -> 128180000000 | AS13: =AR13/AP13 -> 1.0681667e+10 | AU13: 12 | AV13: =$H13*(1+AX$6) -> 128180000000 | AW13: =$E13*AV13 -> 128180000000 | AX13: =AW13/AU13 -> 1.0681667e+10 | AZ13: 12 | BA13: =$H13*(1+BC$6) -> 128180000000 | BB13: =$E13*BA13 -> 128180000000 | BC13: =BB13/AZ13 -> 1.0681667e+10 | BE13: Áo | BF13: A. Quân | BG13: Gía trị bán lại = giá trị ban đầu - khấu hao * sản lượng sx | BI13: =IF($G13>=BI$8,$J13,0) -> 1.0681667e+10 | BJ13: =IF($G13>=BJ$8,$J13,0) -> 1.0681667e+10 | BK13: =IF($G13>=BK$8,$J13,0) -> 1.0681667e+10 | BL13: =IF($G13>=BL$8,$J13,0) -> 1.0681667e+10 | BM13: =IF($G13>=BM$8,$J13,0) -> 1.0681667e+10 | BN13: =IF($G13>=BN$8,$J13,0) -> 1.0681667e+10 | BO13: =IF($G13>=BO$8,$J13,0) -> 1.0681667e+10 | BP13: =IF($G13>=BP$8,$J13,0) -> 1.0681667e+10 | ... CL13: =IF($G13>=CL$8,$J13,0) -> 0 | CN13: =IF($L13>=CN$8,$O13,0) -> 1.0681667e+10 | CO13: =IF($L13>=CO$8,$O13,0) -> 1.0681667e+10 | CP13: =IF($L13>=CP$8,$O13,0) -> 1.0681667e+10 | CQ13: =IF($L13>=CQ$8,$O13,0) -> 1.0681667e+10 | CR13: =IF($L13>=CR$8,$O13,0) -> 1.0681667e+10 | CS13: =IF($L13>=CS$8,$O13,0) -> 1.0681667e+10 | CT13: =IF($L13>=CT$8,$O13,0) -> 1.0681667e+10 | CU13: =IF($L13>=CU$8,$O13,0) -> 1.0681667e+10 | ... DQ13: =IF($L13>=DQ$8,$O13,0) -> 0 | DS13: =IF($Q13>=DS$8,$T13,0) -> 1.0681667e+10 | DT13: =IF($Q13>=DT$8,$T13,0) -> 1.0681667e+10 | DU13: =IF($Q13>=DU$8,$T13,0) -> 1.0681667e+10 | DV13: =IF($Q13>=DV$8,$T13,0) -> 1.0681667e+10 | DW13: =IF($Q13>=DW$8,$T13,0) -> 1.0681667e+10 | DX13: =IF($Q13>=DX$8,$T13,0) -> 1.0681667e+10 | DY13: =IF($Q13>=DY$8,$T13,0) -> 1.0681667e+10 | DZ13: =IF($Q13>=DZ$8,$T13,0) -> 1.0681667e+10 | ... EV13: =IF($Q13>=EV$8,$T13,0) -> 0 | EX13: =IF($V13>=EX$8,$Y13,0) -> 1.0681667e+10 | EY13: =IF($V13>=EY$8,$Y13,0) -> 1.0681667e+10 | EZ13: =IF($V13>=EZ$8,$Y13,0) -> 1.0681667e+10 | FA13: =IF($V13>=FA$8,$Y13,0) -> 1.0681667e+10 | FB13: =IF($V13>=FB$8,$Y13,0) -> 1.0681667e+10 | FC13: =IF($V13>=FC$8,$Y13,0) -> 1.0681667e+10 | FD13: =IF($V13>=FD$8,$Y13,0) -> 1.0681667e+10 | FE13: =IF($V13>=FE$8,$Y13,0) -> 1.0681667e+10 | ... GA13: =IF($V13>=GA$8,$Y13,0) -> 0 | GC13: =IF($AA13>=GC$8,$AD13,0) -> 1.0681667e+10 | GD13: =IF($AA13>=GD$8,$AD13,0) -> 1.0681667e+10 | GE13: =IF($AA13>=GE$8,$AD13,0) -> 1.0681667e+10 | GF13: =IF($AA13>=GF$8,$AD13,0) -> 1.0681667e+10 | GG13: =IF($AA13>=GG$8,$AD13,0) -> 1.0681667e+10 | GH13: =IF($AA13>=GH$8,$AD13,0) -> 1.0681667e+10 | GI13: =IF($AA13>=GI$8,$AD13,0) -> 1.0681667e+10 | GJ13: =IF($AA13>=GJ$8,$AD13,0) -> 1.0681667e+10 | ... HF13: =IF($AA13>=HF$8,$AD13,0) -> 0 | HH13: =IF($AF13>=HH$8,$AI13,0) -> 1.0681667e+10 | HI13: =IF($AF13>=HI$8,$AI13,0) -> 1.0681667e+10 | HJ13: =IF($AF13>=HJ$8,$AI13,0) -> 1.0681667e+10 | HK13: =IF($AF13>=HK$8,$AI13,0) -> 1.0681667e+10 | HL13: =IF($AF13>=HL$8,$AI13,0) -> 1.0681667e+10 | HM13: =IF($AF13>=HM$8,$AI13,0) -> 1.0681667e+10 | HN13: =IF($AF13>=HN$8,$AI13,0) -> 1.0681667e+10 | HO13: =IF($AF13>=HO$8,$AI13,0) -> 1.0681667e+10 | ... IK13: =IF($AF13>=IK$8,$AI13,0) -> 0 | IM13: =IF($AK13>=IM$8,$AN13,0) -> 1.0681667e+10 | IN13: =IF($AK13>=IN$8,$AN13,0) -> 1.0681667e+10 | IO13: =IF($AK13>=IO$8,$AN13,0) -> 1.0681667e+10 | IP13: =IF($AK13>=IP$8,$AN13,0) -> 1.0681667e+10 | IQ13: =IF($AK13>=IQ$8,$AN13,0) -> 1.0681667e+10 | IR13: =IF($AK13>=IR$8,$AN13,0) -> 1.0681667e+10 | IS13: =IF($AK13>=IS$8,$AN13,0) -> 1.0681667e+10 | IT13: =IF($AK13>=IT$8,$AN13,0) -> 1.0681667e+10 | ... JP13: =IF($AK13>=JP$8,$AN13,0) -> 0 | JR13: =IF($AP13>=JR$8,$AS13,0) -> 1.0681667e+10 | JS13: =IF($AP13>=JS$8,$AS13,0) -> 1.0681667e+10 | JT13: =IF($AP13>=JT$8,$AS13,0) -> 1.0681667e+10 | JU13: =IF($AP13>=JU$8,$AS13,0) -> 1.0681667e+10 | JV13: =IF($AP13>=JV$8,$AS13,0) -> 1.0681667e+10 | JW13: =IF($AP13>=JW$8,$AS13,0) -> 1.0681667e+10 | JX13: =IF($AP13>=JX$8,$AS13,0) -> 1.0681667e+10 | JY13: =IF($AP13>=JY$8,$AS13,0) -> 1.0681667e+10 | ... KU13: =IF($AP13>=KU$8,$AS13,0) -> 0 | KW13: =IF($AU13>=KW$8,$AX13,0) -> 1.0681667e+10 | KX13: =IF($AU13>=KX$8,$AX13,0) -> 1.0681667e+10 | KY13: =IF($AU13>=KY$8,$AX13,0) -> 1.0681667e+10 | KZ13: =IF($AU13>=KZ$8,$AX13,0) -> 1.0681667e+10 | LA13: =IF($AU13>=LA$8,$AX13,0) -> 1.0681667e+10 | LB13: =IF($AU13>=LB$8,$AX13,0) -> 1.0681667e+10 | LC13: =IF($AU13>=LC$8,$AX13,0) -> 1.0681667e+10 | LD13: =IF($AU13>=LD$8,$AX13,0) -> 1.0681667e+10 | ... LZ13: =IF($AU13>=LZ$8,$AX13,0) -> 0 | MB13: =IF($AZ13>=MB$8,$BC13,0) -> 1.0681667e+10 | MC13: =IF($AZ13>=MC$8,$BC13,0) -> 1.0681667e+10 | MD13: =IF($AZ13>=MD$8,$BC13,0) -> 1.0681667e+10 | ME13: =IF($AZ13>=ME$8,$BC13,0) -> 1.0681667e+10 | MF13: =IF($AZ13>=MF$8,$BC13,0) -> 1.0681667e+10 | MG13: =IF($AZ13>=MG$8,$BC13,0) -> 1.0681667e+10 | MH13: =IF($AZ13>=MH$8,$BC13,0) -> 1.0681667e+10 | MI13: =IF($AZ13>=MI$8,$BC13,0) -> 1.0681667e+10 | ... NE13: =IF($AZ13>=NE$8,$BC13,0) -> 0
B14: Husky 128 cavs Injection Machine | C14: 1.1.02 | D14: HyPET400 HPP5e rMtP P120/120 | E14: 1 | G14: 12 | H14: =(80500000000/$D$6*(1-0.196393571148569))*1.04 -> 6.727793e+10 | I14: =$E14*$H14 -> 6.727793e+10 | J14: =I14/G14 -> 5.6064942e+09 | L14: 12 | M14: =$H14*(1+O$6) -> 6.727793e+10 | N14: =$E14*M14 -> 6.727793e+10 | O14: =N14/L14 -> 5.6064942e+09 | Q14: 12 | R14: =$H14*(1+T$6) -> 6.727793e+10 | S14: =$E14*R14 -> 6.727793e+10 | T14: =S14/Q14 -> 5.6064942e+09 | V14: 12 | W14: =$H14*(1+Y$6) -> 6.727793e+10 | X14: =$E14*W14 -> 6.727793e+10 | Y14: =X14/V14 -> 5.6064942e+09 | AA14: 12 | AB14: =$H14*(1+AD$6) -> 6.727793e+10 | AC14: =$E14*AB14 -> 6.727793e+10 | AD14: =AC14/AA14 -> 5.6064942e+09 | AF14: 12 | AG14: =$H14*(1+AI$6) -> 6.727793e+10 | AH14: =$E14*AG14 -> 6.727793e+10 | AI14: =AH14/AF14 -> 5.6064942e+09 | AK14: 12 | AL14: =$H14*(1+AN$6) -> 6.727793e+10 | AM14: =$E14*AL14 -> 6.727793e+10 | AN14: =AM14/AK14 -> 5.6064942e+09 | AP14: 12 | AQ14: =$H14*(1+AS$6) -> 6.727793e+10 | AR14: =$E14*AQ14 -> 6.727793e+10 | AS14: =AR14/AP14 -> 5.6064942e+09 | AU14: 12 | AV14: =$H14*(1+AX$6) -> 6.727793e+10 | AW14: =$E14*AV14 -> 6.727793e+10 | AX14: =AW14/AU14 -> 5.6064942e+09 | AZ14: 12 | BA14: =$H14*(1+BC$6) -> 6.727793e+10 | BB14: =$E14*BA14 -> 6.727793e+10 | BC14: =BB14/AZ14 -> 5.6064942e+09 | BE14: Canada | BF14: A. Quân | BG14: Gía trị bán lại = giá trị ban đầu - khấu hao * sản lượng sx | BI14: =IF($G14>=BI$8,$J14,0) -> 5.6064942e+09 | BJ14: =IF($G14>=BJ$8,$J14,0) -> 5.6064942e+09 | BK14: =IF($G14>=BK$8,$J14,0) -> 5.6064942e+09 | BL14: =IF($G14>=BL$8,$J14,0) -> 5.6064942e+09 | BM14: =IF($G14>=BM$8,$J14,0) -> 5.6064942e+09 | BN14: =IF($G14>=BN$8,$J14,0) -> 5.6064942e+09 | BO14: =IF($G14>=BO$8,$J14,0) -> 5.6064942e+09 | BP14: =IF($G14>=BP$8,$J14,0) -> 5.6064942e+09 | ... CL14: =IF($G14>=CL$8,$J14,0) -> 0 | CN14: =IF($L14>=CN$8,$O14,0) -> 5.6064942e+09 | CO14: =IF($L14>=CO$8,$O14,0) -> 5.6064942e+09 | CP14: =IF($L14>=CP$8,$O14,0) -> 5.6064942e+09 | CQ14: =IF($L14>=CQ$8,$O14,0) -> 5.6064942e+09 | CR14: =IF($L14>=CR$8,$O14,0) -> 5.6064942e+09 | CS14: =IF($L14>=CS$8,$O14,0) -> 5.6064942e+09 | CT14: =IF($L14>=CT$8,$O14,0) -> 5.6064942e+09 | CU14: =IF($L14>=CU$8,$O14,0) -> 5.6064942e+09 | ... DQ14: =IF($L14>=DQ$8,$O14,0) -> 0 | DS14: =IF($Q14>=DS$8,$T14,0) -> 5.6064942e+09 | DT14: =IF($Q14>=DT$8,$T14,0) -> 5.6064942e+09 | DU14: =IF($Q14>=DU$8,$T14,0) -> 5.6064942e+09 | DV14: =IF($Q14>=DV$8,$T14,0) -> 5.6064942e+09 | DW14: =IF($Q14>=DW$8,$T14,0) -> 5.6064942e+09 | DX14: =IF($Q14>=DX$8,$T14,0) -> 5.6064942e+09 | DY14: =IF($Q14>=DY$8,$T14,0) -> 5.6064942e+09 | DZ14: =IF($Q14>=DZ$8,$T14,0) -> 5.6064942e+09 | ... EV14: =IF($Q14>=EV$8,$T14,0) -> 0 | EX14: =IF($V14>=EX$8,$Y14,0) -> 5.6064942e+09 | EY14: =IF($V14>=EY$8,$Y14,0) -> 5.6064942e+09 | EZ14: =IF($V14>=EZ$8,$Y14,0) -> 5.6064942e+09 | FA14: =IF($V14>=FA$8,$Y14,0) -> 5.6064942e+09 | FB14: =IF($V14>=FB$8,$Y14,0) -> 5.6064942e+09 | FC14: =IF($V14>=FC$8,$Y14,0) -> 5.6064942e+09 | FD14: =IF($V14>=FD$8,$Y14,0) -> 5.6064942e+09 | FE14: =IF($V14>=FE$8,$Y14,0) -> 5.6064942e+09 | ... GA14: =IF($V14>=GA$8,$Y14,0) -> 0 | GC14: =IF($AA14>=GC$8,$AD14,0) -> 5.6064942e+09 | GD14: =IF($AA14>=GD$8,$AD14,0) -> 5.6064942e+09 | GE14: =IF($AA14>=GE$8,$AD14,0) -> 5.6064942e+09 | GF14: =IF($AA14>=GF$8,$AD14,0) -> 5.6064942e+09 | GG14: =IF($AA14>=GG$8,$AD14,0) -> 5.6064942e+09 | GH14: =IF($AA14>=GH$8,$AD14,0) -> 5.6064942e+09 | GI14: =IF($AA14>=GI$8,$AD14,0) -> 5.6064942e+09 | GJ14: =IF($AA14>=GJ$8,$AD14,0) -> 5.6064942e+09 | ... HF14: =IF($AA14>=HF$8,$AD14,0) -> 0 | HH14: =IF($AF14>=HH$8,$AI14,0) -> 5.6064942e+09 | HI14: =IF($AF14>=HI$8,$AI14,0) -> 5.6064942e+09 | HJ14: =IF($AF14>=HJ$8,$AI14,0) -> 5.6064942e+09 | HK14: =IF($AF14>=HK$8,$AI14,0) -> 5.6064942e+09 | HL14: =IF($AF14>=HL$8,$AI14,0) -> 5.6064942e+09 | HM14: =IF($AF14>=HM$8,$AI14,0) -> 5.6064942e+09 | HN14: =IF($AF14>=HN$8,$AI14,0) -> 5.6064942e+09 | HO14: =IF($AF14>=HO$8,$AI14,0) -> 5.6064942e+09 | ... IK14: =IF($AF14>=IK$8,$AI14,0) -> 0 | IM14: =IF($AK14>=IM$8,$AN14,0) -> 5.6064942e+09 | IN14: =IF($AK14>=IN$8,$AN14,0) -> 5.6064942e+09 | IO14: =IF($AK14>=IO$8,$AN14,0) -> 5.6064942e+09 | IP14: =IF($AK14>=IP$8,$AN14,0) -> 5.6064942e+09 | IQ14: =IF($AK14>=IQ$8,$AN14,0) -> 5.6064942e+09 | IR14: =IF($AK14>=IR$8,$AN14,0) -> 5.6064942e+09 | IS14: =IF($AK14>=IS$8,$AN14,0) -> 5.6064942e+09 | IT14: =IF($AK14>=IT$8,$AN14,0) -> 5.6064942e+09 | ... JP14: =IF($AK14>=JP$8,$AN14,0) -> 0 | JR14: =IF($AP14>=JR$8,$AS14,0) -> 5.6064942e+09 | JS14: =IF($AP14>=JS$8,$AS14,0) -> 5.6064942e+09 | JT14: =IF($AP14>=JT$8,$AS14,0) -> 5.6064942e+09 | JU14: =IF($AP14>=JU$8,$AS14,0) -> 5.6064942e+09 | JV14: =IF($AP14>=JV$8,$AS14,0) -> 5.6064942e+09 | JW14: =IF($AP14>=JW$8,$AS14,0) -> 5.6064942e+09 | JX14: =IF($AP14>=JX$8,$AS14,0) -> 5.6064942e+09 | JY14: =IF($AP14>=JY$8,$AS14,0) -> 5.6064942e+09 | ... KU14: =IF($AP14>=KU$8,$AS14,0) -> 0 | KW14: =IF($AU14>=KW$8,$AX14,0) -> 5.6064942e+09 | KX14: =IF($AU14>=KX$8,$AX14,0) -> 5.6064942e+09 | KY14: =IF($AU14>=KY$8,$AX14,0) -> 5.6064942e+09 | KZ14: =IF($AU14>=KZ$8,$AX14,0) -> 5.6064942e+09 | LA14: =IF($AU14>=LA$8,$AX14,0) -> 5.6064942e+09 | LB14: =IF($AU14>=LB$8,$AX14,0) -> 5.6064942e+09 | LC14: =IF($AU14>=LC$8,$AX14,0) -> 5.6064942e+09 | LD14: =IF($AU14>=LD$8,$AX14,0) -> 5.6064942e+09 | ... LZ14: =IF($AU14>=LZ$8,$AX14,0) -> 0 | MB14: =IF($AZ14>=MB$8,$BC14,0) -> 5.6064942e+09 | MC14: =IF($AZ14>=MC$8,$BC14,0) -> 5.6064942e+09 | MD14: =IF($AZ14>=MD$8,$BC14,0) -> 5.6064942e+09 | ME14: =IF($AZ14>=ME$8,$BC14,0) -> 5.6064942e+09 | MF14: =IF($AZ14>=MF$8,$BC14,0) -> 5.6064942e+09 | MG14: =IF($AZ14>=MG$8,$BC14,0) -> 5.6064942e+09 | MH14: =IF($AZ14>=MH$8,$BC14,0) -> 5.6064942e+09 | MI14: =IF($AZ14>=MI$8,$BC14,0) -> 5.6064942e+09 | ... NE14: =IF($AZ14>=NE$8,$BC14,0) -> 0
B15: Husky 128 cavs Injection Machine | C15: 1.1.03 | D15: Khuôn 15g PCO 1881 128 cavtiy | E15: 1 | G15: 12 | H15: =(47050000000/$D$6*(1-0.196393571148569))*1.04 -> 3.932207e+10 | I15: =$E15*$H15 -> 3.932207e+10 | J15: =I15/G15 -> 3.2768391e+09 | L15: 12 | M15: =$H15*(1+O$6) -> 3.932207e+10 | N15: =$E15*M15 -> 3.932207e+10 | O15: =N15/L15 -> 3.2768391e+09 | Q15: 12 | R15: =$H15*(1+T$6) -> 3.932207e+10 | S15: =$E15*R15 -> 3.932207e+10 | T15: =S15/Q15 -> 3.2768391e+09 | V15: 12 | W15: =$H15*(1+Y$6) -> 3.932207e+10 | X15: =$E15*W15 -> 3.932207e+10 | Y15: =X15/V15 -> 3.2768391e+09 | AA15: 12 | AB15: =$H15*(1+AD$6) -> 3.932207e+10 | AC15: =$E15*AB15 -> 3.932207e+10 | AD15: =AC15/AA15 -> 3.2768391e+09 | AF15: 12 | AG15: =$H15*(1+AI$6) -> 3.932207e+10 | AH15: =$E15*AG15 -> 3.932207e+10 | AI15: =AH15/AF15 -> 3.2768391e+09 | AK15: 12 | AL15: =$H15*(1+AN$6) -> 3.932207e+10 | AM15: =$E15*AL15 -> 3.932207e+10 | AN15: =AM15/AK15 -> 3.2768391e+09 | AP15: 12 | AQ15: =$H15*(1+AS$6) -> 3.932207e+10 | AR15: =$E15*AQ15 -> 3.932207e+10 | AS15: =AR15/AP15 -> 3.2768391e+09 | AU15: 12 | AV15: =$H15*(1+AX$6) -> 3.932207e+10 | AW15: =$E15*AV15 -> 3.932207e+10 | AX15: =AW15/AU15 -> 3.2768391e+09 | AZ15: 12 | BA15: =$H15*(1+BC$6) -> 3.932207e+10 | BB15: =$E15*BA15 -> 3.932207e+10 | BC15: =BB15/AZ15 -> 3.2768391e+09 | BE15: Canada | BF15: A. Quân | BG15: Gía trị bán lại = giá trị ban đầu - khấu hao * sản lượng sx | BI15: =IF($G15>=BI$8,$J15,0) -> 3.2768391e+09 | BJ15: =IF($G15>=BJ$8,$J15,0) -> 3.2768391e+09 | BK15: =IF($G15>=BK$8,$J15,0) -> 3.2768391e+09 | BL15: =IF($G15>=BL$8,$J15,0) -> 3.2768391e+09 | BM15: =IF($G15>=BM$8,$J15,0) -> 3.2768391e+09 | BN15: =IF($G15>=BN$8,$J15,0) -> 3.2768391e+09 | BO15: =IF($G15>=BO$8,$J15,0) -> 3.2768391e+09 | BP15: =IF($G15>=BP$8,$J15,0) -> 3.2768391e+09 | ... CL15: =IF($G15>=CL$8,$J15,0) -> 0 | CN15: =IF($L15>=CN$8,$O15,0) -> 3.2768391e+09 | CO15: =IF($L15>=CO$8,$O15,0) -> 3.2768391e+09 | CP15: =IF($L15>=CP$8,$O15,0) -> 3.2768391e+09 | CQ15: =IF($L15>=CQ$8,$O15,0) -> 3.2768391e+09 | CR15: =IF($L15>=CR$8,$O15,0) -> 3.2768391e+09 | CS15: =IF($L15>=CS$8,$O15,0) -> 3.2768391e+09 | CT15: =IF($L15>=CT$8,$O15,0) -> 3.2768391e+09 | CU15: =IF($L15>=CU$8,$O15,0) -> 3.2768391e+09 | ... DQ15: =IF($L15>=DQ$8,$O15,0) -> 0 | DS15: =IF($Q15>=DS$8,$T15,0) -> 3.2768391e+09 | DT15: =IF($Q15>=DT$8,$T15,0) -> 3.2768391e+09 | DU15: =IF($Q15>=DU$8,$T15,0) -> 3.2768391e+09 | DV15: =IF($Q15>=DV$8,$T15,0) -> 3.2768391e+09 | DW15: =IF($Q15>=DW$8,$T15,0) -> 3.2768391e+09 | DX15: =IF($Q15>=DX$8,$T15,0) -> 3.2768391e+09 | DY15: =IF($Q15>=DY$8,$T15,0) -> 3.2768391e+09 | DZ15: =IF($Q15>=DZ$8,$T15,0) -> 3.2768391e+09 | ... EV15: =IF($Q15>=EV$8,$T15,0) -> 0 | EX15: =IF($V15>=EX$8,$Y15,0) -> 3.2768391e+09 | EY15: =IF($V15>=EY$8,$Y15,0) -> 3.2768391e+09 | EZ15: =IF($V15>=EZ$8,$Y15,0) -> 3.2768391e+09 | FA15: =IF($V15>=FA$8,$Y15,0) -> 3.2768391e+09 | FB15: =IF($V15>=FB$8,$Y15,0) -> 3.2768391e+09 | FC15: =IF($V15>=FC$8,$Y15,0) -> 3.2768391e+09 | FD15: =IF($V15>=FD$8,$Y15,0) -> 3.2768391e+09 | FE15: =IF($V15>=FE$8,$Y15,0) -> 3.2768391e+09 | ... GA15: =IF($V15>=GA$8,$Y15,0) -> 0 | GC15: =IF($AA15>=GC$8,$AD15,0) -> 3.2768391e+09 | GD15: =IF($AA15>=GD$8,$AD15,0) -> 3.2768391e+09 | GE15: =IF($AA15>=GE$8,$AD15,0) -> 3.2768391e+09 | GF15: =IF($AA15>=GF$8,$AD15,0) -> 3.2768391e+09 | GG15: =IF($AA15>=GG$8,$AD15,0) -> 3.2768391e+09 | GH15: =IF($AA15>=GH$8,$AD15,0) -> 3.2768391e+09 | GI15: =IF($AA15>=GI$8,$AD15,0) -> 3.2768391e+09 | GJ15: =IF($AA15>=GJ$8,$AD15,0) -> 3.2768391e+09 | ... HF15: =IF($AA15>=HF$8,$AD15,0) -> 0 | HH15: =IF($AF15>=HH$8,$AI15,0) -> 3.2768391e+09 | HI15: =IF($AF15>=HI$8,$AI15,0) -> 3.2768391e+09 | HJ15: =IF($AF15>=HJ$8,$AI15,0) -> 3.2768391e+09 | HK15: =IF($AF15>=HK$8,$AI15,0) -> 3.2768391e+09 | HL15: =IF($AF15>=HL$8,$AI15,0) -> 3.2768391e+09 | HM15: =IF($AF15>=HM$8,$AI15,0) -> 3.2768391e+09 | HN15: =IF($AF15>=HN$8,$AI15,0) -> 3.2768391e+09 | HO15: =IF($AF15>=HO$8,$AI15,0) -> 3.2768391e+09 | ... IK15: =IF($AF15>=IK$8,$AI15,0) -> 0 | IM15: =IF($AK15>=IM$8,$AN15,0) -> 3.2768391e+09 | IN15: =IF($AK15>=IN$8,$AN15,0) -> 3.2768391e+09 | IO15: =IF($AK15>=IO$8,$AN15,0) -> 3.2768391e+09 | IP15: =IF($AK15>=IP$8,$AN15,0) -> 3.2768391e+09 | IQ15: =IF($AK15>=IQ$8,$AN15,0) -> 3.2768391e+09 | IR15: =IF($AK15>=IR$8,$AN15,0) -> 3.2768391e+09 | IS15: =IF($AK15>=IS$8,$AN15,0) -> 3.2768391e+09 | IT15: =IF($AK15>=IT$8,$AN15,0) -> 3.2768391e+09 | ... JP15: =IF($AK15>=JP$8,$AN15,0) -> 0 | JR15: =IF($AP15>=JR$8,$AS15,0) -> 3.2768391e+09 | JS15: =IF($AP15>=JS$8,$AS15,0) -> 3.2768391e+09 | JT15: =IF($AP15>=JT$8,$AS15,0) -> 3.2768391e+09 | JU15: =IF($AP15>=JU$8,$AS15,0) -> 3.2768391e+09 | JV15: =IF($AP15>=JV$8,$AS15,0) -> 3.2768391e+09 | JW15: =IF($AP15>=JW$8,$AS15,0) -> 3.2768391e+09 | JX15: =IF($AP15>=JX$8,$AS15,0) -> 3.2768391e+09 | JY15: =IF($AP15>=JY$8,$AS15,0) -> 3.2768391e+09 | ... KU15: =IF($AP15>=KU$8,$AS15,0) -> 0 | KW15: =IF($AU15>=KW$8,$AX15,0) -> 3.2768391e+09 | KX15: =IF($AU15>=KX$8,$AX15,0) -> 3.2768391e+09 | KY15: =IF($AU15>=KY$8,$AX15,0) -> 3.2768391e+09 | KZ15: =IF($AU15>=KZ$8,$AX15,0) -> 3.2768391e+09 | LA15: =IF($AU15>=LA$8,$AX15,0) -> 3.2768391e+09 | LB15: =IF($AU15>=LB$8,$AX15,0) -> 3.2768391e+09 | LC15: =IF($AU15>=LC$8,$AX15,0) -> 3.2768391e+09 | LD15: =IF($AU15>=LD$8,$AX15,0) -> 3.2768391e+09 | ... LZ15: =IF($AU15>=LZ$8,$AX15,0) -> 0 | MB15: =IF($AZ15>=MB$8,$BC15,0) -> 3.2768391e+09 | MC15: =IF($AZ15>=MC$8,$BC15,0) -> 3.2768391e+09 | MD15: =IF($AZ15>=MD$8,$BC15,0) -> 3.2768391e+09 | ME15: =IF($AZ15>=ME$8,$BC15,0) -> 3.2768391e+09 | MF15: =IF($AZ15>=MF$8,$BC15,0) -> 3.2768391e+09 | MG15: =IF($AZ15>=MG$8,$BC15,0) -> 3.2768391e+09 | MH15: =IF($AZ15>=MH$8,$BC15,0) -> 3.2768391e+09 | MI15: =IF($AZ15>=MI$8,$BC15,0) -> 3.2768391e+09 | ... NE15: =IF($AZ15>=NE$8,$BC15,0) -> 0
B16: Installing & delivery cost | C16: 1.1.04 | D16: Chi phí vận chuyển | E16: 1 | G16: 12 | H16: =(2500000000/$D$6)*1.04 -> 2600000000 | I16: =$E16*$H16 -> 2600000000 | J16: =I16/G16 -> 2.1666667e+08 | L16: 12 | M16: =$H16*(1+O$6) -> 2600000000 | N16: =$E16*M16 -> 2600000000 | O16: =N16/L16 -> 2.1666667e+08 | Q16: 12 | R16: =$H16*(1+T$6) -> 2600000000 | S16: =$E16*R16 -> 2600000000 | T16: =S16/Q16 -> 2.1666667e+08 | V16: 12 | W16: =$H16*(1+Y$6) -> 2600000000 | X16: =$E16*W16 -> 2600000000 | Y16: =X16/V16 -> 2.1666667e+08 | AA16: 12 | AB16: =$H16*(1+AD$6) -> 2600000000 | AC16: =$E16*AB16 -> 2600000000 | AD16: =AC16/AA16 -> 2.1666667e+08 | AF16: 12 | AG16: =$H16*(1+AI$6) -> 2600000000 | AH16: =$E16*AG16 -> 2600000000 | AI16: =AH16/AF16 -> 2.1666667e+08 | AK16: 12 | AL16: =$H16*(1+AN$6) -> 2600000000 | AM16: =$E16*AL16 -> 2600000000 | AN16: =AM16/AK16 -> 2.1666667e+08 | AP16: 12 | AQ16: =$H16*(1+AS$6) -> 2600000000 | AR16: =$E16*AQ16 -> 2600000000 | AS16: =AR16/AP16 -> 2.1666667e+08 | AU16: 12 | AV16: =$H16*(1+AX$6) -> 2600000000 | AW16: =$E16*AV16 -> 2600000000 | AX16: =AW16/AU16 -> 2.1666667e+08 | AZ16: 12 | BA16: =$H16*(1+BC$6) -> 2600000000 | BB16: =$E16*BA16 -> 2600000000 | BC16: =BB16/AZ16 -> 2.1666667e+08 | BF16: A. Quân | BG16: Gía trị bán lại = giá trị ban đầu - khấu hao * sản lượng sx | BI16: =IF($G16>=BI$8,$J16,0) -> 2.1666667e+08 | BJ16: =IF($G16>=BJ$8,$J16,0) -> 2.1666667e+08 | BK16: =IF($G16>=BK$8,$J16,0) -> 2.1666667e+08 | BL16: =IF($G16>=BL$8,$J16,0) -> 2.1666667e+08 | BM16: =IF($G16>=BM$8,$J16,0) -> 2.1666667e+08 | BN16: =IF($G16>=BN$8,$J16,0) -> 2.1666667e+08 | BO16: =IF($G16>=BO$8,$J16,0) -> 2.1666667e+08 | BP16: =IF($G16>=BP$8,$J16,0) -> 2.1666667e+08 | ... CL16: =IF($G16>=CL$8,$J16,0) -> 0 | CN16: =IF($L16>=CN$8,$O16,0) -> 2.1666667e+08 | CO16: =IF($L16>=CO$8,$O16,0) -> 2.1666667e+08 | CP16: =IF($L16>=CP$8,$O16,0) -> 2.1666667e+08 | CQ16: =IF($L16>=CQ$8,$O16,0) -> 2.1666667e+08 | CR16: =IF($L16>=CR$8,$O16,0) -> 2.1666667e+08 | CS16: =IF($L16>=CS$8,$O16,0) -> 2.1666667e+08 | CT16: =IF($L16>=CT$8,$O16,0) -> 2.1666667e+08 | CU16: =IF($L16>=CU$8,$O16,0) -> 2.1666667e+08 | ... DQ16: =IF($L16>=DQ$8,$O16,0) -> 0 | DS16: =IF($Q16>=DS$8,$T16,0) -> 2.1666667e+08 | DT16: =IF($Q16>=DT$8,$T16,0) -> 2.1666667e+08 | DU16: =IF($Q16>=DU$8,$T16,0) -> 2.1666667e+08 | DV16: =IF($Q16>=DV$8,$T16,0) -> 2.1666667e+08 | DW16: =IF($Q16>=DW$8,$T16,0) -> 2.1666667e+08 | DX16: =IF($Q16>=DX$8,$T16,0) -> 2.1666667e+08 | DY16: =IF($Q16>=DY$8,$T16,0) -> 2.1666667e+08 | DZ16: =IF($Q16>=DZ$8,$T16,0) -> 2.1666667e+08 | ... EV16: =IF($Q16>=EV$8,$T16,0) -> 0 | EX16: =IF($V16>=EX$8,$Y16,0) -> 2.1666667e+08 | EY16: =IF($V16>=EY$8,$Y16,0) -> 2.1666667e+08 | EZ16: =IF($V16>=EZ$8,$Y16,0) -> 2.1666667e+08 | FA16: =IF($V16>=FA$8,$Y16,0) -> 2.1666667e+08 | FB16: =IF($V16>=FB$8,$Y16,0) -> 2.1666667e+08 | FC16: =IF($V16>=FC$8,$Y16,0) -> 2.1666667e+08 | FD16: =IF($V16>=FD$8,$Y16,0) -> 2.1666667e+08 | FE16: =IF($V16>=FE$8,$Y16,0) -> 2.1666667e+08 | ... GA16: =IF($V16>=GA$8,$Y16,0) -> 0 | GC16: =IF($AA16>=GC$8,$AD16,0) -> 2.1666667e+08 | GD16: =IF($AA16>=GD$8,$AD16,0) -> 2.1666667e+08 | GE16: =IF($AA16>=GE$8,$AD16,0) -> 2.1666667e+08 | GF16: =IF($AA16>=GF$8,$AD16,0) -> 2.1666667e+08 | GG16: =IF($AA16>=GG$8,$AD16,0) -> 2.1666667e+08 | GH16: =IF($AA16>=GH$8,$AD16,0) -> 2.1666667e+08 | GI16: =IF($AA16>=GI$8,$AD16,0) -> 2.1666667e+08 | GJ16: =IF($AA16>=GJ$8,$AD16,0) -> 2.1666667e+08 | ... HF16: =IF($AA16>=HF$8,$AD16,0) -> 0 | HH16: =IF($AF16>=HH$8,$AI16,0) -> 2.1666667e+08 | HI16: =IF($AF16>=HI$8,$AI16,0) -> 2.1666667e+08 | HJ16: =IF($AF16>=HJ$8,$AI16,0) -> 2.1666667e+08 | HK16: =IF($AF16>=HK$8,$AI16,0) -> 2.1666667e+08 | HL16: =IF($AF16>=HL$8,$AI16,0) -> 2.1666667e+08 | HM16: =IF($AF16>=HM$8,$AI16,0) -> 2.1666667e+08 | HN16: =IF($AF16>=HN$8,$AI16,0) -> 2.1666667e+08 | HO16: =IF($AF16>=HO$8,$AI16,0) -> 2.1666667e+08 | ... IK16: =IF($AF16>=IK$8,$AI16,0) -> 0 | IM16: =IF($AK16>=IM$8,$AN16,0) -> 2.1666667e+08 | IN16: =IF($AK16>=IN$8,$AN16,0) -> 2.1666667e+08 | IO16: =IF($AK16>=IO$8,$AN16,0) -> 2.1666667e+08 | IP16: =IF($AK16>=IP$8,$AN16,0) -> 2.1666667e+08 | IQ16: =IF($AK16>=IQ$8,$AN16,0) -> 2.1666667e+08 | IR16: =IF($AK16>=IR$8,$AN16,0) -> 2.1666667e+08 | IS16: =IF($AK16>=IS$8,$AN16,0) -> 2.1666667e+08 | IT16: =IF($AK16>=IT$8,$AN16,0) -> 2.1666667e+08 | ... JP16: =IF($AK16>=JP$8,$AN16,0) -> 0 | JR16: =IF($AP16>=JR$8,$AS16,0) -> 2.1666667e+08 | JS16: =IF($AP16>=JS$8,$AS16,0) -> 2.1666667e+08 | JT16: =IF($AP16>=JT$8,$AS16,0) -> 2.1666667e+08 | JU16: =IF($AP16>=JU$8,$AS16,0) -> 2.1666667e+08 | JV16: =IF($AP16>=JV$8,$AS16,0) -> 2.1666667e+08 | JW16: =IF($AP16>=JW$8,$AS16,0) -> 2.1666667e+08 | JX16: =IF($AP16>=JX$8,$AS16,0) -> 2.1666667e+08 | JY16: =IF($AP16>=JY$8,$AS16,0) -> 2.1666667e+08 | ... KU16: =IF($AP16>=KU$8,$AS16,0) -> 0 | KW16: =IF($AU16>=KW$8,$AX16,0) -> 2.1666667e+08 | KX16: =IF($AU16>=KX$8,$AX16,0) -> 2.1666667e+08 | KY16: =IF($AU16>=KY$8,$AX16,0) -> 2.1666667e+08 | KZ16: =IF($AU16>=KZ$8,$AX16,0) -> 2.1666667e+08 | LA16: =IF($AU16>=LA$8,$AX16,0) -> 2.1666667e+08 | LB16: =IF($AU16>=LB$8,$AX16,0) -> 2.1666667e+08 | LC16: =IF($AU16>=LC$8,$AX16,0) -> 2.1666667e+08 | LD16: =IF($AU16>=LD$8,$AX16,0) -> 2.1666667e+08 | ... LZ16: =IF($AU16>=LZ$8,$AX16,0) -> 0 | MB16: =IF($AZ16>=MB$8,$BC16,0) -> 2.1666667e+08 | MC16: =IF($AZ16>=MC$8,$BC16,0) -> 2.1666667e+08 | MD16: =IF($AZ16>=MD$8,$BC16,0) -> 2.1666667e+08 | ME16: =IF($AZ16>=ME$8,$BC16,0) -> 2.1666667e+08 | MF16: =IF($AZ16>=MF$8,$BC16,0) -> 2.1666667e+08 | MG16: =IF($AZ16>=MG$8,$BC16,0) -> 2.1666667e+08 | MH16: =IF($AZ16>=MH$8,$BC16,0) -> 2.1666667e+08 | MI16: =IF($AZ16>=MI$8,$BC16,0) -> 2.1666667e+08 | ... NE16: =IF($AZ16>=NE$8,$BC16,0) -> 0
B17: Installing & delivery cost | C17: 1.1.05 | D17: Chi phí lắp đặt | E17: 1 | G17: 12 | H17: =(8250000000/$D$6)*1.04 -> 8580000000 | I17: =$E17*$H17 -> 8580000000 | J17: =I17/G17 -> 715000000 | L17: 12 | M17: =$H17*(1+O$6) -> 8580000000 | N17: =$E17*M17 -> 8580000000 | O17: =N17/L17 -> 715000000 | Q17: 12 | R17: =$H17*(1+T$6) -> 8580000000 | S17: =$E17*R17 -> 8580000000 | T17: =S17/Q17 -> 715000000 | V17: 12 | W17: =$H17*(1+Y$6) -> 8580000000 | X17: =$E17*W17 -> 8580000000 | Y17: =X17/V17 -> 715000000 | AA17: 12 | AB17: =$H17*(1+AD$6) -> 8580000000 | AC17: =$E17*AB17 -> 8580000000 | AD17: =AC17/AA17 -> 715000000 | AF17: 12 | AG17: =$H17*(1+AI$6) -> 8580000000 | AH17: =$E17*AG17 -> 8580000000 | AI17: =AH17/AF17 -> 715000000 | AK17: 12 | AL17: =$H17*(1+AN$6) -> 8580000000 | AM17: =$E17*AL17 -> 8580000000 | AN17: =AM17/AK17 -> 715000000 | AP17: 12 | AQ17: =$H17*(1+AS$6) -> 8580000000 | AR17: =$E17*AQ17 -> 8580000000 | AS17: =AR17/AP17 -> 715000000 | AU17: 12 | AV17: =$H17*(1+AX$6) -> 8580000000 | AW17: =$E17*AV17 -> 8580000000 | AX17: =AW17/AU17 -> 715000000 | AZ17: 12 | BA17: =$H17*(1+BC$6) -> 8580000000 | BB17: =$E17*BA17 -> 8580000000 | BC17: =BB17/AZ17 -> 715000000 | BF17: A. Quân | BG17: Gía trị bán lại = giá trị ban đầu - khấu hao * sản lượng sx | BI17: =IF($G17>=BI$8,$J17,0) -> 715000000 | BJ17: =IF($G17>=BJ$8,$J17,0) -> 715000000 | BK17: =IF($G17>=BK$8,$J17,0) -> 715000000 | BL17: =IF($G17>=BL$8,$J17,0) -> 715000000 | BM17: =IF($G17>=BM$8,$J17,0) -> 715000000 | BN17: =IF($G17>=BN$8,$J17,0) -> 715000000 | BO17: =IF($G17>=BO$8,$J17,0) -> 715000000 | BP17: =IF($G17>=BP$8,$J17,0) -> 715000000 | ... CL17: =IF($G17>=CL$8,$J17,0) -> 0 | CN17: =IF($L17>=CN$8,$O17,0) -> 715000000 | CO17: =IF($L17>=CO$8,$O17,0) -> 715000000 | CP17: =IF($L17>=CP$8,$O17,0) -> 715000000 | CQ17: =IF($L17>=CQ$8,$O17,0) -> 715000000 | CR17: =IF($L17>=CR$8,$O17,0) -> 715000000 | CS17: =IF($L17>=CS$8,$O17,0) -> 715000000 | CT17: =IF($L17>=CT$8,$O17,0) -> 715000000 | CU17: =IF($L17>=CU$8,$O17,0) -> 715000000 | ... DQ17: =IF($L17>=DQ$8,$O17,0) -> 0 | DS17: =IF($Q17>=DS$8,$T17,0) -> 715000000 | DT17: =IF($Q17>=DT$8,$T17,0) -> 715000000 | DU17: =IF($Q17>=DU$8,$T17,0) -> 715000000 | DV17: =IF($Q17>=DV$8,$T17,0) -> 715000000 | DW17: =IF($Q17>=DW$8,$T17,0) -> 715000000 | DX17: =IF($Q17>=DX$8,$T17,0) -> 715000000 | DY17: =IF($Q17>=DY$8,$T17,0) -> 715000000 | DZ17: =IF($Q17>=DZ$8,$T17,0) -> 715000000 | ... EV17: =IF($Q17>=EV$8,$T17,0) -> 0 | EX17: =IF($V17>=EX$8,$Y17,0) -> 715000000 | EY17: =IF($V17>=EY$8,$Y17,0) -> 715000000 | EZ17: =IF($V17>=EZ$8,$Y17,0) -> 715000000 | FA17: =IF($V17>=FA$8,$Y17,0) -> 715000000 | FB17: =IF($V17>=FB$8,$Y17,0) -> 715000000 | FC17: =IF($V17>=FC$8,$Y17,0) -> 715000000 | FD17: =IF($V17>=FD$8,$Y17,0) -> 715000000 | FE17: =IF($V17>=FE$8,$Y17,0) -> 715000000 | ... GA17: =IF($V17>=GA$8,$Y17,0) -> 0 | GC17: =IF($AA17>=GC$8,$AD17,0) -> 715000000 | GD17: =IF($AA17>=GD$8,$AD17,0) -> 715000000 | GE17: =IF($AA17>=GE$8,$AD17,0) -> 715000000 | GF17: =IF($AA17>=GF$8,$AD17,0) -> 715000000 | GG17: =IF($AA17>=GG$8,$AD17,0) -> 715000000 | GH17: =IF($AA17>=GH$8,$AD17,0) -> 715000000 | GI17: =IF($AA17>=GI$8,$AD17,0) -> 715000000 | GJ17: =IF($AA17>=GJ$8,$AD17,0) -> 715000000 | ... HF17: =IF($AA17>=HF$8,$AD17,0) -> 0 | HH17: =IF($AF17>=HH$8,$AI17,0) -> 715000000 | HI17: =IF($AF17>=HI$8,$AI17,0) -> 715000000 | HJ17: =IF($AF17>=HJ$8,$AI17,0) -> 715000000 | HK17: =IF($AF17>=HK$8,$AI17,0) -> 715000000 | HL17: =IF($AF17>=HL$8,$AI17,0) -> 715000000 | HM17: =IF($AF17>=HM$8,$AI17,0) -> 715000000 | HN17: =IF($AF17>=HN$8,$AI17,0) -> 715000000 | HO17: =IF($AF17>=HO$8,$AI17,0) -> 715000000 | ... IK17: =IF($AF17>=IK$8,$AI17,0) -> 0 | IM17: =IF($AK17>=IM$8,$AN17,0) -> 715000000 | IN17: =IF($AK17>=IN$8,$AN17,0) -> 715000000 | IO17: =IF($AK17>=IO$8,$AN17,0) -> 715000000 | IP17: =IF($AK17>=IP$8,$AN17,0) -> 715000000 | IQ17: =IF($AK17>=IQ$8,$AN17,0) -> 715000000 | IR17: =IF($AK17>=IR$8,$AN17,0) -> 715000000 | IS17: =IF($AK17>=IS$8,$AN17,0) -> 715000000 | IT17: =IF($AK17>=IT$8,$AN17,0) -> 715000000 | ... JP17: =IF($AK17>=JP$8,$AN17,0) -> 0 | JR17: =IF($AP17>=JR$8,$AS17,0) -> 715000000 | JS17: =IF($AP17>=JS$8,$AS17,0) -> 715000000 | JT17: =IF($AP17>=JT$8,$AS17,0) -> 715000000 | JU17: =IF($AP17>=JU$8,$AS17,0) -> 715000000 | JV17: =IF($AP17>=JV$8,$AS17,0) -> 715000000 | JW17: =IF($AP17>=JW$8,$AS17,0) -> 715000000 | JX17: =IF($AP17>=JX$8,$AS17,0) -> 715000000 | JY17: =IF($AP17>=JY$8,$AS17,0) -> 715000000 | ... KU17: =IF($AP17>=KU$8,$AS17,0) -> 0 | KW17: =IF($AU17>=KW$8,$AX17,0) -> 715000000 | KX17: =IF($AU17>=KX$8,$AX17,0) -> 715000000 | KY17: =IF($AU17>=KY$8,$AX17,0) -> 715000000 | KZ17: =IF($AU17>=KZ$8,$AX17,0) -> 715000000 | LA17: =IF($AU17>=LA$8,$AX17,0) -> 715000000 | LB17: =IF($AU17>=LB$8,$AX17,0) -> 715000000 | LC17: =IF($AU17>=LC$8,$AX17,0) -> 715000000 | LD17: =IF($AU17>=LD$8,$AX17,0) -> 715000000 | ... LZ17: =IF($AU17>=LZ$8,$AX17,0) -> 0 | MB17: =IF($AZ17>=MB$8,$BC17,0) -> 715000000 | MC17: =IF($AZ17>=MC$8,$BC17,0) -> 715000000 | MD17: =IF($AZ17>=MD$8,$BC17,0) -> 715000000 | ME17: =IF($AZ17>=ME$8,$BC17,0) -> 715000000 | MF17: =IF($AZ17>=MF$8,$BC17,0) -> 715000000 | MG17: =IF($AZ17>=MG$8,$BC17,0) -> 715000000 | MH17: =IF($AZ17>=MH$8,$BC17,0) -> 715000000 | MI17: =IF($AZ17>=MI$8,$BC17,0) -> 715000000 | ... NE17: =IF($AZ17>=NE$8,$BC17,0) -> 0
B18: Installing & delivery cost | C18: 1.1.06 | D18: Thuế nhà thầu | E18: 1 | G18: 12 | H18: =(8250000000*5%/$D$6)*1.04 -> 429000000 | I18: =$E18*$H18 -> 429000000 | J18: =I18/G18 -> 35750000 | L18: 12 | M18: =$H18*(1+O$6) -> 429000000 | N18: =$E18*M18 -> 429000000 | O18: =N18/L18 -> 35750000 | Q18: 12 | R18: =$H18*(1+T$6) -> 429000000 | S18: =$E18*R18 -> 429000000 | T18: =S18/Q18 -> 35750000 | V18: 12 | W18: =$H18*(1+Y$6) -> 429000000 | X18: =$E18*W18 -> 429000000 | Y18: =X18/V18 -> 35750000 | AA18: 12 | AB18: =$H18*(1+AD$6) -> 429000000 | AC18: =$E18*AB18 -> 429000000 | AD18: =AC18/AA18 -> 35750000 | AF18: 12 | AG18: =$H18*(1+AI$6) -> 429000000 | AH18: =$E18*AG18 -> 429000000 | AI18: =AH18/AF18 -> 35750000 | AK18: 12 | AL18: =$H18*(1+AN$6) -> 429000000 | AM18: =$E18*AL18 -> 429000000 | AN18: =AM18/AK18 -> 35750000 | AP18: 12 | AQ18: =$H18*(1+AS$6) -> 429000000 | AR18: =$E18*AQ18 -> 429000000 | AS18: =AR18/AP18 -> 35750000 | AU18: 12 | AV18: =$H18*(1+AX$6) -> 429000000 | AW18: =$E18*AV18 -> 429000000 | AX18: =AW18/AU18 -> 35750000 | AZ18: 12 | BA18: =$H18*(1+BC$6) -> 429000000 | BB18: =$E18*BA18 -> 429000000 | BC18: =BB18/AZ18 -> 35750000 | BI18: =IF($G18>=BI$8,$J18,0) -> 35750000 | BJ18: =IF($G18>=BJ$8,$J18,0) -> 35750000 | BK18: =IF($G18>=BK$8,$J18,0) -> 35750000 | BL18: =IF($G18>=BL$8,$J18,0) -> 35750000 | BM18: =IF($G18>=BM$8,$J18,0) -> 35750000 | BN18: =IF($G18>=BN$8,$J18,0) -> 35750000 | BO18: =IF($G18>=BO$8,$J18,0) -> 35750000 | BP18: =IF($G18>=BP$8,$J18,0) -> 35750000 | ... CL18: =IF($G18>=CL$8,$J18,0) -> 0 | CN18: =IF($L18>=CN$8,$O18,0) -> 35750000 | CO18: =IF($L18>=CO$8,$O18,0) -> 35750000 | CP18: =IF($L18>=CP$8,$O18,0) -> 35750000 | CQ18: =IF($L18>=CQ$8,$O18,0) -> 35750000 | CR18: =IF($L18>=CR$8,$O18,0) -> 35750000 | CS18: =IF($L18>=CS$8,$O18,0) -> 35750000 | CT18: =IF($L18>=CT$8,$O18,0) -> 35750000 | CU18: =IF($L18>=CU$8,$O18,0) -> 35750000 | ... DQ18: =IF($L18>=DQ$8,$O18,0) -> 0 | DS18: =IF($Q18>=DS$8,$T18,0) -> 35750000 | DT18: =IF($Q18>=DT$8,$T18,0) -> 35750000 | DU18: =IF($Q18>=DU$8,$T18,0) -> 35750000 | DV18: =IF($Q18>=DV$8,$T18,0) -> 35750000 | DW18: =IF($Q18>=DW$8,$T18,0) -> 35750000 | DX18: =IF($Q18>=DX$8,$T18,0) -> 35750000 | DY18: =IF($Q18>=DY$8,$T18,0) -> 35750000 | DZ18: =IF($Q18>=DZ$8,$T18,0) -> 35750000 | ... EV18: =IF($Q18>=EV$8,$T18,0) -> 0 | EX18: =IF($V18>=EX$8,$Y18,0) -> 35750000 | EY18: =IF($V18>=EY$8,$Y18,0) -> 35750000 | EZ18: =IF($V18>=EZ$8,$Y18,0) -> 35750000 | FA18: =IF($V18>=FA$8,$Y18,0) -> 35750000 | FB18: =IF($V18>=FB$8,$Y18,0) -> 35750000 | FC18: =IF($V18>=FC$8,$Y18,0) -> 35750000 | FD18: =IF($V18>=FD$8,$Y18,0) -> 35750000 | FE18: =IF($V18>=FE$8,$Y18,0) -> 35750000 | ... GA18: =IF($V18>=GA$8,$Y18,0) -> 0 | GC18: =IF($AA18>=GC$8,$AD18,0) -> 35750000 | GD18: =IF($AA18>=GD$8,$AD18,0) -> 35750000 | GE18: =IF($AA18>=GE$8,$AD18,0) -> 35750000 | GF18: =IF($AA18>=GF$8,$AD18,0) -> 35750000 | GG18: =IF($AA18>=GG$8,$AD18,0) -> 35750000 | GH18: =IF($AA18>=GH$8,$AD18,0) -> 35750000 | GI18: =IF($AA18>=GI$8,$AD18,0) -> 35750000 | GJ18: =IF($AA18>=GJ$8,$AD18,0) -> 35750000 | ... HF18: =IF($AA18>=HF$8,$AD18,0) -> 0 | HH18: =IF($AF18>=HH$8,$AI18,0) -> 35750000 | HI18: =IF($AF18>=HI$8,$AI18,0) -> 35750000 | HJ18: =IF($AF18>=HJ$8,$AI18,0) -> 35750000 | HK18: =IF($AF18>=HK$8,$AI18,0) -> 35750000 | HL18: =IF($AF18>=HL$8,$AI18,0) -> 35750000 | HM18: =IF($AF18>=HM$8,$AI18,0) -> 35750000 | HN18: =IF($AF18>=HN$8,$AI18,0) -> 35750000 | HO18: =IF($AF18>=HO$8,$AI18,0) -> 35750000 | ... IK18: =IF($AF18>=IK$8,$AI18,0) -> 0 | IM18: =IF($AK18>=IM$8,$AN18,0) -> 35750000 | IN18: =IF($AK18>=IN$8,$AN18,0) -> 35750000 | IO18: =IF($AK18>=IO$8,$AN18,0) -> 35750000 | IP18: =IF($AK18>=IP$8,$AN18,0) -> 35750000 | IQ18: =IF($AK18>=IQ$8,$AN18,0) -> 35750000 | IR18: =IF($AK18>=IR$8,$AN18,0) -> 35750000 | IS18: =IF($AK18>=IS$8,$AN18,0) -> 35750000 | IT18: =IF($AK18>=IT$8,$AN18,0) -> 35750000 | ... JP18: =IF($AK18>=JP$8,$AN18,0) -> 0 | JR18: =IF($AP18>=JR$8,$AS18,0) -> 35750000 | JS18: =IF($AP18>=JS$8,$AS18,0) -> 35750000 | JT18: =IF($AP18>=JT$8,$AS18,0) -> 35750000 | JU18: =IF($AP18>=JU$8,$AS18,0) -> 35750000 | JV18: =IF($AP18>=JV$8,$AS18,0) -> 35750000 | JW18: =IF($AP18>=JW$8,$AS18,0) -> 35750000 | JX18: =IF($AP18>=JX$8,$AS18,0) -> 35750000 | JY18: =IF($AP18>=JY$8,$AS18,0) -> 35750000 | ... KU18: =IF($AP18>=KU$8,$AS18,0) -> 0 | KW18: =IF($AU18>=KW$8,$AX18,0) -> 35750000 | KX18: =IF($AU18>=KX$8,$AX18,0) -> 35750000 | KY18: =IF($AU18>=KY$8,$AX18,0) -> 35750000 | KZ18: =IF($AU18>=KZ$8,$AX18,0) -> 35750000 | LA18: =IF($AU18>=LA$8,$AX18,0) -> 35750000 | LB18: =IF($AU18>=LB$8,$AX18,0) -> 35750000 | LC18: =IF($AU18>=LC$8,$AX18,0) -> 35750000 | LD18: =IF($AU18>=LD$8,$AX18,0) -> 35750000 | ... LZ18: =IF($AU18>=LZ$8,$AX18,0) -> 0 | MB18: =IF($AZ18>=MB$8,$BC18,0) -> 35750000 | MC18: =IF($AZ18>=MC$8,$BC18,0) -> 35750000 | MD18: =IF($AZ18>=MD$8,$BC18,0) -> 35750000 | ME18: =IF($AZ18>=ME$8,$BC18,0) -> 35750000 | MF18: =IF($AZ18>=MF$8,$BC18,0) -> 35750000 | MG18: =IF($AZ18>=MG$8,$BC18,0) -> 35750000 | MH18: =IF($AZ18>=MH$8,$BC18,0) -> 35750000 | MI18: =IF($AZ18>=MI$8,$BC18,0) -> 35750000 | ... NE18: =IF($AZ18>=NE$8,$BC18,0) -> 0
A20: CAPEX-SUB | C20: 1.2 | D20: Máy móc thiết bị phụ | I20: =SUM(I21:I33) -> 38110800000 | J20: =SUM(J21:J33) -> 3175900000 | N20: =SUM(N21:N33) -> 38110800000 | O20: =SUM(O21:O33) -> 3175900000 | S20: =SUM(S21:S33) -> 38110800000 | T20: =SUM(T21:T33) -> 3175900000 | X20: =SUM(X21:X33) -> 38110800000 | Y20: =SUM(Y21:Y33) -> 3175900000 | AC20: =SUM(AC21:AC33) -> 38110800000 | AD20: =SUM(AD21:AD33) -> 3175900000 | AH20: =SUM(AH21:AH33) -> 38110800000 | AI20: =SUM(AI21:AI33) -> 3175900000 | AM20: =SUM(AM21:AM33) -> 38110800000 | AN20: =SUM(AN21:AN33) -> 3175900000 | AR20: =SUM(AR21:AR33) -> 38110800000 | AS20: =SUM(AS21:AS33) -> 3175900000 | AW20: =SUM(AW21:AW33) -> 38110800000 | AX20: =SUM(AX21:AX33) -> 3175900000 | BB20: =SUM(BB21:BB33) -> 38110800000 | BC20: =SUM(BC21:BC33) -> 3175900000 | BI20: =SUM(BI21:BI33) -> 3175900000 | BJ20: =SUM(BJ21:BJ33) -> 3175900000 | BK20: =SUM(BK21:BK33) -> 3175900000 | BL20: =SUM(BL21:BL33) -> 3175900000 | BM20: =SUM(BM21:BM33) -> 3175900000 | BN20: =SUM(BN21:BN33) -> 3175900000 | BO20: =SUM(BO21:BO33) -> 3175900000 | BP20: =SUM(BP21:BP33) -> 3175900000 | ... CL20: =SUM(CL21:CL33) -> 0 | CN20: =SUM(CN21:CN33) -> 3175900000 | CO20: =SUM(CO21:CO33) -> 3175900000 | CP20: =SUM(CP21:CP33) -> 3175900000 | CQ20: =SUM(CQ21:CQ33) -> 3175900000 | CR20: =SUM(CR21:CR33) -> 3175900000 | CS20: =SUM(CS21:CS33) -> 3175900000 | CT20: =SUM(CT21:CT33) -> 3175900000 | CU20: =SUM(CU21:CU33) -> 3175900000 | ... DQ20: =SUM(DQ21:DQ33) -> 0 | DS20: =SUM(DS21:DS33) -> 3175900000 | DT20: =SUM(DT21:DT33) -> 3175900000 | DU20: =SUM(DU21:DU33) -> 3175900000 | DV20: =SUM(DV21:DV33) -> 3175900000 | DW20: =SUM(DW21:DW33) -> 3175900000 | DX20: =SUM(DX21:DX33) -> 3175900000 | DY20: =SUM(DY21:DY33) -> 3175900000 | DZ20: =SUM(DZ21:DZ33) -> 3175900000 | ... EV20: =SUM(EV21:EV33) -> 0 | EX20: =SUM(EX21:EX33) -> 3175900000 | EY20: =SUM(EY21:EY33) -> 3175900000 | EZ20: =SUM(EZ21:EZ33) -> 3175900000 | FA20: =SUM(FA21:FA33) -> 3175900000 | FB20: =SUM(FB21:FB33) -> 3175900000 | FC20: =SUM(FC21:FC33) -> 3175900000 | FD20: =SUM(FD21:FD33) -> 3175900000 | FE20: =SUM(FE21:FE33) -> 3175900000 | ... GA20: =SUM(GA21:GA33) -> 0 | GC20: =SUM(GC21:GC33) -> 3175900000 | GD20: =SUM(GD21:GD33) -> 3175900000 | GE20: =SUM(GE21:GE33) -> 3175900000 | GF20: =SUM(GF21:GF33) -> 3175900000 | GG20: =SUM(GG21:GG33) -> 3175900000 | GH20: =SUM(GH21:GH33) -> 3175900000 | GI20: =SUM(GI21:GI33) -> 3175900000 | GJ20: =SUM(GJ21:GJ33) -> 3175900000 | ... HF20: =SUM(HF21:HF33) -> 0 | HH20: =SUM(HH21:HH33) -> 3175900000 | HI20: =SUM(HI21:HI33) -> 3175900000 | HJ20: =SUM(HJ21:HJ33) -> 3175900000 | HK20: =SUM(HK21:HK33) -> 3175900000 | HL20: =SUM(HL21:HL33) -> 3175900000 | HM20: =SUM(HM21:HM33) -> 3175900000 | HN20: =SUM(HN21:HN33) -> 3175900000 | HO20: =SUM(HO21:HO33) -> 3175900000 | ... IK20: =SUM(IK21:IK33) -> 0 | IM20: =SUM(IM21:IM33) -> 3175900000 | IN20: =SUM(IN21:IN33) -> 3175900000 | IO20: =SUM(IO21:IO33) -> 3175900000 | IP20: =SUM(IP21:IP33) -> 3175900000 | IQ20: =SUM(IQ21:IQ33) -> 3175900000 | IR20: =SUM(IR21:IR33) -> 3175900000 | IS20: =SUM(IS21:IS33) -> 3175900000 | IT20: =SUM(IT21:IT33) -> 3175900000 | ... JP20: =SUM(JP21:JP33) -> 0 | JR20: =SUM(JR21:JR33) -> 3175900000 | JS20: =SUM(JS21:JS33) -> 3175900000 | JT20: =SUM(JT21:JT33) -> 3175900000 | JU20: =SUM(JU21:JU33) -> 3175900000 | JV20: =SUM(JV21:JV33) -> 3175900000 | JW20: =SUM(JW21:JW33) -> 3175900000 | JX20: =SUM(JX21:JX33) -> 3175900000 | JY20: =SUM(JY21:JY33) -> 3175900000 | ... KU20: =SUM(KU21:KU33) -> 0 | KW20: =SUM(KW21:KW33) -> 3175900000 | KX20: =SUM(KX21:KX33) -> 3175900000 | KY20: =SUM(KY21:KY33) -> 3175900000 | KZ20: =SUM(KZ21:KZ33) -> 3175900000 | LA20: =SUM(LA21:LA33) -> 3175900000 | LB20: =SUM(LB21:LB33) -> 3175900000 | LC20: =SUM(LC21:LC33) -> 3175900000 | LD20: =SUM(LD21:LD33) -> 3175900000 | ... LZ20: =SUM(LZ21:LZ33) -> 0 | MB20: =SUM(MB21:MB33) -> 3175900000 | MC20: =SUM(MC21:MC33) -> 3175900000 | MD20: =SUM(MD21:MD33) -> 3175900000 | ME20: =SUM(ME21:ME33) -> 3175900000 | MF20: =SUM(MF21:MF33) -> 3175900000 | MG20: =SUM(MG21:MG33) -> 3175900000 | MH20: =SUM(MH21:MH33) -> 3175900000 | MI20: =SUM(MI21:MI33) -> 3175900000 | ... NE20: =SUM(NE21:NE33) -> 0
B21: Auxiliary Equipment | C21: 1.2.06 | D21: Hệ thống nước, khí nén | E21: 1 | G21: 12 | H21: =(7500000000/$D$6)*1.04 -> 7800000000 | I21: =$E21*$H21 -> 7800000000 | J21: =I21/G21 -> 650000000 | L21: 12 | M21: =$H21*(1+O$6) -> 7800000000 | N21: =$E21*M21 -> 7800000000 | O21: =N21/L21 -> 650000000 | Q21: 12 | R21: =$H21*(1+T$6) -> 7800000000 | S21: =$E21*R21 -> 7800000000 | T21: =S21/Q21 -> 650000000 | V21: 12 | W21: =$H21*(1+Y$6) -> 7800000000 | X21: =$E21*W21 -> 7800000000 | Y21: =X21/V21 -> 650000000 | AA21: 12 | AB21: =$H21*(1+AD$6) -> 7800000000 | AC21: =$E21*AB21 -> 7800000000 | AD21: =AC21/AA21 -> 650000000 | AF21: 12 | AG21: =$H21*(1+AI$6) -> 7800000000 | AH21: =$E21*AG21 -> 7800000000 | AI21: =AH21/AF21 -> 650000000 | AK21: 12 | AL21: =$H21*(1+AN$6) -> 7800000000 | AM21: =$E21*AL21 -> 7800000000 | AN21: =AM21/AK21 -> 650000000 | AP21: 12 | AQ21: =$H21*(1+AS$6) -> 7800000000 | AR21: =$E21*AQ21 -> 7800000000 | AS21: =AR21/AP21 -> 650000000 | AU21: 12 | AV21: =$H21*(1+AX$6) -> 7800000000 | AW21: =$E21*AV21 -> 7800000000 | AX21: =AW21/AU21 -> 650000000 | AZ21: 12 | BA21: =$H21*(1+BC$6) -> 7800000000 | BB21: =$E21*BA21 -> 7800000000 | BC21: =BB21/AZ21 -> 650000000 | BF21: A. Quân | BG21: Đàm phán | BI21: =IF($G21>=BI$8,$J21,0) -> 650000000 | BJ21: =IF($G21>=BJ$8,$J21,0) -> 650000000 | BK21: =IF($G21>=BK$8,$J21,0) -> 650000000 | BL21: =IF($G21>=BL$8,$J21,0) -> 650000000 | BM21: =IF($G21>=BM$8,$J21,0) -> 650000000 | BN21: =IF($G21>=BN$8,$J21,0) -> 650000000 | BO21: =IF($G21>=BO$8,$J21,0) -> 650000000 | BP21: =IF($G21>=BP$8,$J21,0) -> 650000000 | ... CL21: =IF($G21>=CL$8,$J21,0) -> 0 | CN21: =IF($L21>=CN$8,$O21,0) -> 650000000 | CO21: =IF($L21>=CO$8,$O21,0) -> 650000000 | CP21: =IF($L21>=CP$8,$O21,0) -> 650000000 | CQ21: =IF($L21>=CQ$8,$O21,0) -> 650000000 | CR21: =IF($L21>=CR$8,$O21,0) -> 650000000 | CS21: =IF($L21>=CS$8,$O21,0) -> 650000000 | CT21: =IF($L21>=CT$8,$O21,0) -> 650000000 | CU21: =IF($L21>=CU$8,$O21,0) -> 650000000 | ... DQ21: =IF($L21>=DQ$8,$O21,0) -> 0 | DS21: =IF($Q21>=DS$8,$T21,0) -> 650000000 | DT21: =IF($Q21>=DT$8,$T21,0) -> 650000000 | DU21: =IF($Q21>=DU$8,$T21,0) -> 650000000 | DV21: =IF($Q21>=DV$8,$T21,0) -> 650000000 | DW21: =IF($Q21>=DW$8,$T21,0) -> 650000000 | DX21: =IF($Q21>=DX$8,$T21,0) -> 650000000 | DY21: =IF($Q21>=DY$8,$T21,0) -> 650000000 | DZ21: =IF($Q21>=DZ$8,$T21,0) -> 650000000 | ... EV21: =IF($Q21>=EV$8,$T21,0) -> 0 | EX21: =IF($V21>=EX$8,$Y21,0) -> 650000000 | EY21: =IF($V21>=EY$8,$Y21,0) -> 650000000 | EZ21: =IF($V21>=EZ$8,$Y21,0) -> 650000000 | FA21: =IF($V21>=FA$8,$Y21,0) -> 650000000 | FB21: =IF($V21>=FB$8,$Y21,0) -> 650000000 | FC21: =IF($V21>=FC$8,$Y21,0) -> 650000000 | FD21: =IF($V21>=FD$8,$Y21,0) -> 650000000 | FE21: =IF($V21>=FE$8,$Y21,0) -> 650000000 | ... GA21: =IF($V21>=GA$8,$Y21,0) -> 0 | GC21: =IF($AA21>=GC$8,$AD21,0) -> 650000000 | GD21: =IF($AA21>=GD$8,$AD21,0) -> 650000000 | GE21: =IF($AA21>=GE$8,$AD21,0) -> 650000000 | GF21: =IF($AA21>=GF$8,$AD21,0) -> 650000000 | GG21: =IF($AA21>=GG$8,$AD21,0) -> 650000000 | GH21: =IF($AA21>=GH$8,$AD21,0) -> 650000000 | GI21: =IF($AA21>=GI$8,$AD21,0) -> 650000000 | GJ21: =IF($AA21>=GJ$8,$AD21,0) -> 650000000 | ... HF21: =IF($AA21>=HF$8,$AD21,0) -> 0 | HH21: =IF($AF21>=HH$8,$AI21,0) -> 650000000 | HI21: =IF($AF21>=HI$8,$AI21,0) -> 650000000 | HJ21: =IF($AF21>=HJ$8,$AI21,0) -> 650000000 | HK21: =IF($AF21>=HK$8,$AI21,0) -> 650000000 | HL21: =IF($AF21>=HL$8,$AI21,0) -> 650000000 | HM21: =IF($AF21>=HM$8,$AI21,0) -> 650000000 | HN21: =IF($AF21>=HN$8,$AI21,0) -> 650000000 | HO21: =IF($AF21>=HO$8,$AI21,0) -> 650000000 | ... IK21: =IF($AF21>=IK$8,$AI21,0) -> 0 | IM21: =IF($AK21>=IM$8,$AN21,0) -> 650000000 | IN21: =IF($AK21>=IN$8,$AN21,0) -> 650000000 | IO21: =IF($AK21>=IO$8,$AN21,0) -> 650000000 | IP21: =IF($AK21>=IP$8,$AN21,0) -> 650000000 | IQ21: =IF($AK21>=IQ$8,$AN21,0) -> 650000000 | IR21: =IF($AK21>=IR$8,$AN21,0) -> 650000000 | IS21: =IF($AK21>=IS$8,$AN21,0) -> 650000000 | IT21: =IF($AK21>=IT$8,$AN21,0) -> 650000000 | ... JP21: =IF($AK21>=JP$8,$AN21,0) -> 0 | JR21: =IF($AP21>=JR$8,$AS21,0) -> 650000000 | JS21: =IF($AP21>=JS$8,$AS21,0) -> 650000000 | JT21: =IF($AP21>=JT$8,$AS21,0) -> 650000000 | JU21: =IF($AP21>=JU$8,$AS21,0) -> 650000000 | JV21: =IF($AP21>=JV$8,$AS21,0) -> 650000000 | JW21: =IF($AP21>=JW$8,$AS21,0) -> 650000000 | JX21: =IF($AP21>=JX$8,$AS21,0) -> 650000000 | JY21: =IF($AP21>=JY$8,$AS21,0) -> 650000000 | ... KU21: =IF($AP21>=KU$8,$AS21,0) -> 0 | KW21: =IF($AU21>=KW$8,$AX21,0) -> 650000000 | KX21: =IF($AU21>=KX$8,$AX21,0) -> 650000000 | KY21: =IF($AU21>=KY$8,$AX21,0) -> 650000000 | KZ21: =IF($AU21>=KZ$8,$AX21,0) -> 650000000 | LA21: =IF($AU21>=LA$8,$AX21,0) -> 650000000 | LB21: =IF($AU21>=LB$8,$AX21,0) -> 650000000 | LC21: =IF($AU21>=LC$8,$AX21,0) -> 650000000 | LD21: =IF($AU21>=LD$8,$AX21,0) -> 650000000 | ... LZ21: =IF($AU21>=LZ$8,$AX21,0) -> 0 | MB21: =IF($AZ21>=MB$8,$BC21,0) -> 650000000 | MC21: =IF($AZ21>=MC$8,$BC21,0) -> 650000000 | MD21: =IF($AZ21>=MD$8,$BC21,0) -> 650000000 | ME21: =IF($AZ21>=ME$8,$BC21,0) -> 650000000 | MF21: =IF($AZ21>=MF$8,$BC21,0) -> 650000000 | MG21: =IF($AZ21>=MG$8,$BC21,0) -> 650000000 | MH21: =IF($AZ21>=MH$8,$BC21,0) -> 650000000 | MI21: =IF($AZ21>=MI$8,$BC21,0) -> 650000000 | ... NE21: =IF($AZ21>=NE$8,$BC21,0) -> 0
B22: Auxiliary Equipment | C22: 1.2.07 | D22: Hệ thống điện | E22: 1 | G22: 12 | H22: =(7500000000/$D$6)*1.04 -> 7800000000 | I22: =$E22*$H22 -> 7800000000 | J22: =I22/G22 -> 650000000 | L22: 12 | M22: =$H22*(1+O$6) -> 7800000000 | N22: =$E22*M22 -> 7800000000 | O22: =N22/L22 -> 650000000 | Q22: 12 | R22: =$H22*(1+T$6) -> 7800000000 | S22: =$E22*R22 -> 7800000000 | T22: =S22/Q22 -> 650000000 | V22: 12 | W22: =$H22*(1+Y$6) -> 7800000000 | X22: =$E22*W22 -> 7800000000 | Y22: =X22/V22 -> 650000000 | AA22: 12 | AB22: =$H22*(1+AD$6) -> 7800000000 | AC22: =$E22*AB22 -> 7800000000 | AD22: =AC22/AA22 -> 650000000 | AF22: 12 | AG22: =$H22*(1+AI$6) -> 7800000000 | AH22: =$E22*AG22 -> 7800000000 | AI22: =AH22/AF22 -> 650000000 | AK22: 12 | AL22: =$H22*(1+AN$6) -> 7800000000 | AM22: =$E22*AL22 -> 7800000000 | AN22: =AM22/AK22 -> 650000000 | AP22: 12 | AQ22: =$H22*(1+AS$6) -> 7800000000 | AR22: =$E22*AQ22 -> 7800000000 | AS22: =AR22/AP22 -> 650000000 | AU22: 12 | AV22: =$H22*(1+AX$6) -> 7800000000 | AW22: =$E22*AV22 -> 7800000000 | AX22: =AW22/AU22 -> 650000000 | AZ22: 12 | BA22: =$H22*(1+BC$6) -> 7800000000 | BB22: =$E22*BA22 -> 7800000000 | BC22: =BB22/AZ22 -> 650000000 | BF22: A. Quân | BG22: Đàm phán | BI22: =IF($G22>=BI$8,$J22,0) -> 650000000 | BJ22: =IF($G22>=BJ$8,$J22,0) -> 650000000 | BK22: =IF($G22>=BK$8,$J22,0) -> 650000000 | BL22: =IF($G22>=BL$8,$J22,0) -> 650000000 | BM22: =IF($G22>=BM$8,$J22,0) -> 650000000 | BN22: =IF($G22>=BN$8,$J22,0) -> 650000000 | BO22: =IF($G22>=BO$8,$J22,0) -> 650000000 | BP22: =IF($G22>=BP$8,$J22,0) -> 650000000 | ... CL22: =IF($G22>=CL$8,$J22,0) -> 0 | CN22: =IF($L22>=CN$8,$O22,0) -> 650000000 | CO22: =IF($L22>=CO$8,$O22,0) -> 650000000 | CP22: =IF($L22>=CP$8,$O22,0) -> 650000000 | CQ22: =IF($L22>=CQ$8,$O22,0) -> 650000000 | CR22: =IF($L22>=CR$8,$O22,0) -> 650000000 | CS22: =IF($L22>=CS$8,$O22,0) -> 650000000 | CT22: =IF($L22>=CT$8,$O22,0) -> 650000000 | CU22: =IF($L22>=CU$8,$O22,0) -> 650000000 | ... DQ22: =IF($L22>=DQ$8,$O22,0) -> 0 | DS22: =IF($Q22>=DS$8,$T22,0) -> 650000000 | DT22: =IF($Q22>=DT$8,$T22,0) -> 650000000 | DU22: =IF($Q22>=DU$8,$T22,0) -> 650000000 | DV22: =IF($Q22>=DV$8,$T22,0) -> 650000000 | DW22: =IF($Q22>=DW$8,$T22,0) -> 650000000 | DX22: =IF($Q22>=DX$8,$T22,0) -> 650000000 | DY22: =IF($Q22>=DY$8,$T22,0) -> 650000000 | DZ22: =IF($Q22>=DZ$8,$T22,0) -> 650000000 | ... EV22: =IF($Q22>=EV$8,$T22,0) -> 0 | EX22: =IF($V22>=EX$8,$Y22,0) -> 650000000 | EY22: =IF($V22>=EY$8,$Y22,0) -> 650000000 | EZ22: =IF($V22>=EZ$8,$Y22,0) -> 650000000 | FA22: =IF($V22>=FA$8,$Y22,0) -> 650000000 | FB22: =IF($V22>=FB$8,$Y22,0) -> 650000000 | FC22: =IF($V22>=FC$8,$Y22,0) -> 650000000 | FD22: =IF($V22>=FD$8,$Y22,0) -> 650000000 | FE22: =IF($V22>=FE$8,$Y22,0) -> 650000000 | ... GA22: =IF($V22>=GA$8,$Y22,0) -> 0 | GC22: =IF($AA22>=GC$8,$AD22,0) -> 650000000 | GD22: =IF($AA22>=GD$8,$AD22,0) -> 650000000 | GE22: =IF($AA22>=GE$8,$AD22,0) -> 650000000 | GF22: =IF($AA22>=GF$8,$AD22,0) -> 650000000 | GG22: =IF($AA22>=GG$8,$AD22,0) -> 650000000 | GH22: =IF($AA22>=GH$8,$AD22,0) -> 650000000 | GI22: =IF($AA22>=GI$8,$AD22,0) -> 650000000 | GJ22: =IF($AA22>=GJ$8,$AD22,0) -> 650000000 | ... HF22: =IF($AA22>=HF$8,$AD22,0) -> 0 | HH22: =IF($AF22>=HH$8,$AI22,0) -> 650000000 | HI22: =IF($AF22>=HI$8,$AI22,0) -> 650000000 | HJ22: =IF($AF22>=HJ$8,$AI22,0) -> 650000000 | HK22: =IF($AF22>=HK$8,$AI22,0) -> 650000000 | HL22: =IF($AF22>=HL$8,$AI22,0) -> 650000000 | HM22: =IF($AF22>=HM$8,$AI22,0) -> 650000000 | HN22: =IF($AF22>=HN$8,$AI22,0) -> 650000000 | HO22: =IF($AF22>=HO$8,$AI22,0) -> 650000000 | ... IK22: =IF($AF22>=IK$8,$AI22,0) -> 0 | IM22: =IF($AK22>=IM$8,$AN22,0) -> 650000000 | IN22: =IF($AK22>=IN$8,$AN22,0) -> 650000000 | IO22: =IF($AK22>=IO$8,$AN22,0) -> 650000000 | IP22: =IF($AK22>=IP$8,$AN22,0) -> 650000000 | IQ22: =IF($AK22>=IQ$8,$AN22,0) -> 650000000 | IR22: =IF($AK22>=IR$8,$AN22,0) -> 650000000 | IS22: =IF($AK22>=IS$8,$AN22,0) -> 650000000 | IT22: =IF($AK22>=IT$8,$AN22,0) -> 650000000 | ... JP22: =IF($AK22>=JP$8,$AN22,0) -> 0 | JR22: =IF($AP22>=JR$8,$AS22,0) -> 650000000 | JS22: =IF($AP22>=JS$8,$AS22,0) -> 650000000 | JT22: =IF($AP22>=JT$8,$AS22,0) -> 650000000 | JU22: =IF($AP22>=JU$8,$AS22,0) -> 650000000 | JV22: =IF($AP22>=JV$8,$AS22,0) -> 650000000 | JW22: =IF($AP22>=JW$8,$AS22,0) -> 650000000 | JX22: =IF($AP22>=JX$8,$AS22,0) -> 650000000 | JY22: =IF($AP22>=JY$8,$AS22,0) -> 650000000 | ... KU22: =IF($AP22>=KU$8,$AS22,0) -> 0 | KW22: =IF($AU22>=KW$8,$AX22,0) -> 650000000 | KX22: =IF($AU22>=KX$8,$AX22,0) -> 650000000 | KY22: =IF($AU22>=KY$8,$AX22,0) -> 650000000 | KZ22: =IF($AU22>=KZ$8,$AX22,0) -> 650000000 | LA22: =IF($AU22>=LA$8,$AX22,0) -> 650000000 | LB22: =IF($AU22>=LB$8,$AX22,0) -> 650000000 | LC22: =IF($AU22>=LC$8,$AX22,0) -> 650000000 | LD22: =IF($AU22>=LD$8,$AX22,0) -> 650000000 | ... LZ22: =IF($AU22>=LZ$8,$AX22,0) -> 0 | MB22: =IF($AZ22>=MB$8,$BC22,0) -> 650000000 | MC22: =IF($AZ22>=MC$8,$BC22,0) -> 650000000 | MD22: =IF($AZ22>=MD$8,$BC22,0) -> 650000000 | ME22: =IF($AZ22>=ME$8,$BC22,0) -> 650000000 | MF22: =IF($AZ22>=MF$8,$BC22,0) -> 650000000 | MG22: =IF($AZ22>=MG$8,$BC22,0) -> 650000000 | MH22: =IF($AZ22>=MH$8,$BC22,0) -> 650000000 | MI22: =IF($AZ22>=MI$8,$BC22,0) -> 650000000 | ... NE22: =IF($AZ22>=NE$8,$BC22,0) -> 0
B23: Auxiliary Equipment | C23: 1.2.08 | D23: Pump system | E23: 1 | G23: 12 | H23: =(3750000000/$D$6)*1.04 -> 3900000000 | I23: =$E23*$H23 -> 3900000000 | J23: =I23/G23 -> 325000000 | L23: 12 | M23: =$H23*(1+O$6) -> 3900000000 | N23: =$E23*M23 -> 3900000000 | O23: =N23/L23 -> 325000000 | Q23: 12 | R23: =$H23*(1+T$6) -> 3900000000 | S23: =$E23*R23 -> 3900000000 | T23: =S23/Q23 -> 325000000 | V23: 12 | W23: =$H23*(1+Y$6) -> 3900000000 | X23: =$E23*W23 -> 3900000000 | Y23: =X23/V23 -> 325000000 | AA23: 12 | AB23: =$H23*(1+AD$6) -> 3900000000 | AC23: =$E23*AB23 -> 3900000000 | AD23: =AC23/AA23 -> 325000000 | AF23: 12 | AG23: =$H23*(1+AI$6) -> 3900000000 | AH23: =$E23*AG23 -> 3900000000 | AI23: =AH23/AF23 -> 325000000 | AK23: 12 | AL23: =$H23*(1+AN$6) -> 3900000000 | AM23: =$E23*AL23 -> 3900000000 | AN23: =AM23/AK23 -> 325000000 | AP23: 12 | AQ23: =$H23*(1+AS$6) -> 3900000000 | AR23: =$E23*AQ23 -> 3900000000 | AS23: =AR23/AP23 -> 325000000 | AU23: 12 | AV23: =$H23*(1+AX$6) -> 3900000000 | AW23: =$E23*AV23 -> 3900000000 | AX23: =AW23/AU23 -> 325000000 | AZ23: 12 | BA23: =$H23*(1+BC$6) -> 3900000000 | BB23: =$E23*BA23 -> 3900000000 | BC23: =BB23/AZ23 -> 325000000 | BF23: A. Quân | BG23: Đàm phán | BI23: =IF($G23>=BI$8,$J23,0) -> 325000000 | BJ23: =IF($G23>=BJ$8,$J23,0) -> 325000000 | BK23: =IF($G23>=BK$8,$J23,0) -> 325000000 | BL23: =IF($G23>=BL$8,$J23,0) -> 325000000 | BM23: =IF($G23>=BM$8,$J23,0) -> 325000000 | BN23: =IF($G23>=BN$8,$J23,0) -> 325000000 | BO23: =IF($G23>=BO$8,$J23,0) -> 325000000 | BP23: =IF($G23>=BP$8,$J23,0) -> 325000000 | ... CL23: =IF($G23>=CL$8,$J23,0) -> 0 | CN23: =IF($L23>=CN$8,$O23,0) -> 325000000 | CO23: =IF($L23>=CO$8,$O23,0) -> 325000000 | CP23: =IF($L23>=CP$8,$O23,0) -> 325000000 | CQ23: =IF($L23>=CQ$8,$O23,0) -> 325000000 | CR23: =IF($L23>=CR$8,$O23,0) -> 325000000 | CS23: =IF($L23>=CS$8,$O23,0) -> 325000000 | CT23: =IF($L23>=CT$8,$O23,0) -> 325000000 | CU23: =IF($L23>=CU$8,$O23,0) -> 325000000 | ... DQ23: =IF($L23>=DQ$8,$O23,0) -> 0 | DS23: =IF($Q23>=DS$8,$T23,0) -> 325000000 | DT23: =IF($Q23>=DT$8,$T23,0) -> 325000000 | DU23: =IF($Q23>=DU$8,$T23,0) -> 325000000 | DV23: =IF($Q23>=DV$8,$T23,0) -> 325000000 | DW23: =IF($Q23>=DW$8,$T23,0) -> 325000000 | DX23: =IF($Q23>=DX$8,$T23,0) -> 325000000 | DY23: =IF($Q23>=DY$8,$T23,0) -> 325000000 | DZ23: =IF($Q23>=DZ$8,$T23,0) -> 325000000 | ... EV23: =IF($Q23>=EV$8,$T23,0) -> 0 | EX23: =IF($V23>=EX$8,$Y23,0) -> 325000000 | EY23: =IF($V23>=EY$8,$Y23,0) -> 325000000 | EZ23: =IF($V23>=EZ$8,$Y23,0) -> 325000000 | FA23: =IF($V23>=FA$8,$Y23,0) -> 325000000 | FB23: =IF($V23>=FB$8,$Y23,0) -> 325000000 | FC23: =IF($V23>=FC$8,$Y23,0) -> 325000000 | FD23: =IF($V23>=FD$8,$Y23,0) -> 325000000 | FE23: =IF($V23>=FE$8,$Y23,0) -> 325000000 | ... GA23: =IF($V23>=GA$8,$Y23,0) -> 0 | GC23: =IF($AA23>=GC$8,$AD23,0) -> 325000000 | GD23: =IF($AA23>=GD$8,$AD23,0) -> 325000000 | GE23: =IF($AA23>=GE$8,$AD23,0) -> 325000000 | GF23: =IF($AA23>=GF$8,$AD23,0) -> 325000000 | GG23: =IF($AA23>=GG$8,$AD23,0) -> 325000000 | GH23: =IF($AA23>=GH$8,$AD23,0) -> 325000000 | GI23: =IF($AA23>=GI$8,$AD23,0) -> 325000000 | GJ23: =IF($AA23>=GJ$8,$AD23,0) -> 325000000 | ... HF23: =IF($AA23>=HF$8,$AD23,0) -> 0 | HH23: =IF($AF23>=HH$8,$AI23,0) -> 325000000 | HI23: =IF($AF23>=HI$8,$AI23,0) -> 325000000 | HJ23: =IF($AF23>=HJ$8,$AI23,0) -> 325000000 | HK23: =IF($AF23>=HK$8,$AI23,0) -> 325000000 | HL23: =IF($AF23>=HL$8,$AI23,0) -> 325000000 | HM23: =IF($AF23>=HM$8,$AI23,0) -> 325000000 | HN23: =IF($AF23>=HN$8,$AI23,0) -> 325000000 | HO23: =IF($AF23>=HO$8,$AI23,0) -> 325000000 | ... IK23: =IF($AF23>=IK$8,$AI23,0) -> 0 | IM23: =IF($AK23>=IM$8,$AN23,0) -> 325000000 | IN23: =IF($AK23>=IN$8,$AN23,0) -> 325000000 | IO23: =IF($AK23>=IO$8,$AN23,0) -> 325000000 | IP23: =IF($AK23>=IP$8,$AN23,0) -> 325000000 | IQ23: =IF($AK23>=IQ$8,$AN23,0) -> 325000000 | IR23: =IF($AK23>=IR$8,$AN23,0) -> 325000000 | IS23: =IF($AK23>=IS$8,$AN23,0) -> 325000000 | IT23: =IF($AK23>=IT$8,$AN23,0) -> 325000000 | ... JP23: =IF($AK23>=JP$8,$AN23,0) -> 0 | JR23: =IF($AP23>=JR$8,$AS23,0) -> 325000000 | JS23: =IF($AP23>=JS$8,$AS23,0) -> 325000000 | JT23: =IF($AP23>=JT$8,$AS23,0) -> 325000000 | JU23: =IF($AP23>=JU$8,$AS23,0) -> 325000000 | JV23: =IF($AP23>=JV$8,$AS23,0) -> 325000000 | JW23: =IF($AP23>=JW$8,$AS23,0) -> 325000000 | JX23: =IF($AP23>=JX$8,$AS23,0) -> 325000000 | JY23: =IF($AP23>=JY$8,$AS23,0) -> 325000000 | ... KU23: =IF($AP23>=KU$8,$AS23,0) -> 0 | KW23: =IF($AU23>=KW$8,$AX23,0) -> 325000000 | KX23: =IF($AU23>=KX$8,$AX23,0) -> 325000000 | KY23: =IF($AU23>=KY$8,$AX23,0) -> 325000000 | KZ23: =IF($AU23>=KZ$8,$AX23,0) -> 325000000 | LA23: =IF($AU23>=LA$8,$AX23,0) -> 325000000 | LB23: =IF($AU23>=LB$8,$AX23,0) -> 325000000 | LC23: =IF($AU23>=LC$8,$AX23,0) -> 325000000 | LD23: =IF($AU23>=LD$8,$AX23,0) -> 325000000 | ... LZ23: =IF($AU23>=LZ$8,$AX23,0) -> 0 | MB23: =IF($AZ23>=MB$8,$BC23,0) -> 325000000 | MC23: =IF($AZ23>=MC$8,$BC23,0) -> 325000000 | MD23: =IF($AZ23>=MD$8,$BC23,0) -> 325000000 | ME23: =IF($AZ23>=ME$8,$BC23,0) -> 325000000 | MF23: =IF($AZ23>=MF$8,$BC23,0) -> 325000000 | MG23: =IF($AZ23>=MG$8,$BC23,0) -> 325000000 | MH23: =IF($AZ23>=MH$8,$BC23,0) -> 325000000 | MI23: =IF($AZ23>=MI$8,$BC23,0) -> 325000000 | ... NE23: =IF($AZ23>=NE$8,$BC23,0) -> 0
B24: Auxiliary Equipment | C24: 1.2.09 | D24: Camera online check | E24: 1 | G24: 12 | H24: =(3125000000/$D$6)*1.04 -> 3250000000 | I24: =$E24*$H24 -> 3250000000 | J24: =I24/G24 -> 2.7083333e+08 | L24: 12 | M24: =$H24*(1+O$6) -> 3250000000 | N24: =$E24*M24 -> 3250000000 | O24: =N24/L24 -> 2.7083333e+08 | Q24: 12 | R24: =$H24*(1+T$6) -> 3250000000 | S24: =$E24*R24 -> 3250000000 | T24: =S24/Q24 -> 2.7083333e+08 | V24: 12 | W24: =$H24*(1+Y$6) -> 3250000000 | X24: =$E24*W24 -> 3250000000 | Y24: =X24/V24 -> 2.7083333e+08 | AA24: 12 | AB24: =$H24*(1+AD$6) -> 3250000000 | AC24: =$E24*AB24 -> 3250000000 | AD24: =AC24/AA24 -> 2.7083333e+08 | AF24: 12 | AG24: =$H24*(1+AI$6) -> 3250000000 | AH24: =$E24*AG24 -> 3250000000 | AI24: =AH24/AF24 -> 2.7083333e+08 | AK24: 12 | AL24: =$H24*(1+AN$6) -> 3250000000 | AM24: =$E24*AL24 -> 3250000000 | AN24: =AM24/AK24 -> 2.7083333e+08 | AP24: 12 | AQ24: =$H24*(1+AS$6) -> 3250000000 | AR24: =$E24*AQ24 -> 3250000000 | AS24: =AR24/AP24 -> 2.7083333e+08 | AU24: 12 | AV24: =$H24*(1+AX$6) -> 3250000000 | AW24: =$E24*AV24 -> 3250000000 | AX24: =AW24/AU24 -> 2.7083333e+08 | AZ24: 12 | BA24: =$H24*(1+BC$6) -> 3250000000 | BB24: =$E24*BA24 -> 3250000000 | BC24: =BB24/AZ24 -> 2.7083333e+08 | BF24: A. Quân | BG24: Gía trị bán lại = giá trị ban đầu - khấu hao * sản lượng sx | BI24: =IF($G24>=BI$8,$J24,0) -> 2.7083333e+08 | BJ24: =IF($G24>=BJ$8,$J24,0) -> 2.7083333e+08 | BK24: =IF($G24>=BK$8,$J24,0) -> 2.7083333e+08 | BL24: =IF($G24>=BL$8,$J24,0) -> 2.7083333e+08 | BM24: =IF($G24>=BM$8,$J24,0) -> 2.7083333e+08 | BN24: =IF($G24>=BN$8,$J24,0) -> 2.7083333e+08 | BO24: =IF($G24>=BO$8,$J24,0) -> 2.7083333e+08 | BP24: =IF($G24>=BP$8,$J24,0) -> 2.7083333e+08 | ... CL24: =IF($G24>=CL$8,$J24,0) -> 0 | CN24: =IF($L24>=CN$8,$O24,0) -> 2.7083333e+08 | CO24: =IF($L24>=CO$8,$O24,0) -> 2.7083333e+08 | CP24: =IF($L24>=CP$8,$O24,0) -> 2.7083333e+08 | CQ24: =IF($L24>=CQ$8,$O24,0) -> 2.7083333e+08 | CR24: =IF($L24>=CR$8,$O24,0) -> 2.7083333e+08 | CS24: =IF($L24>=CS$8,$O24,0) -> 2.7083333e+08 | CT24: =IF($L24>=CT$8,$O24,0) -> 2.7083333e+08 | CU24: =IF($L24>=CU$8,$O24,0) -> 2.7083333e+08 | ... DQ24: =IF($L24>=DQ$8,$O24,0) -> 0 | DS24: =IF($Q24>=DS$8,$T24,0) -> 2.7083333e+08 | DT24: =IF($Q24>=DT$8,$T24,0) -> 2.7083333e+08 | DU24: =IF($Q24>=DU$8,$T24,0) -> 2.7083333e+08 | DV24: =IF($Q24>=DV$8,$T24,0) -> 2.7083333e+08 | DW24: =IF($Q24>=DW$8,$T24,0) -> 2.7083333e+08 | DX24: =IF($Q24>=DX$8,$T24,0) -> 2.7083333e+08 | DY24: =IF($Q24>=DY$8,$T24,0) -> 2.7083333e+08 | DZ24: =IF($Q24>=DZ$8,$T24,0) -> 2.7083333e+08 | ... EV24: =IF($Q24>=EV$8,$T24,0) -> 0 | EX24: =IF($V24>=EX$8,$Y24,0) -> 2.7083333e+08 | EY24: =IF($V24>=EY$8,$Y24,0) -> 2.7083333e+08 | EZ24: =IF($V24>=EZ$8,$Y24,0) -> 2.7083333e+08 | FA24: =IF($V24>=FA$8,$Y24,0) -> 2.7083333e+08 | FB24: =IF($V24>=FB$8,$Y24,0) -> 2.7083333e+08 | FC24: =IF($V24>=FC$8,$Y24,0) -> 2.7083333e+08 | FD24: =IF($V24>=FD$8,$Y24,0) -> 2.7083333e+08 | FE24: =IF($V24>=FE$8,$Y24,0) -> 2.7083333e+08 | ... GA24: =IF($V24>=GA$8,$Y24,0) -> 0 | GC24: =IF($AA24>=GC$8,$AD24,0) -> 2.7083333e+08 | GD24: =IF($AA24>=GD$8,$AD24,0) -> 2.7083333e+08 | GE24: =IF($AA24>=GE$8,$AD24,0) -> 2.7083333e+08 | GF24: =IF($AA24>=GF$8,$AD24,0) -> 2.7083333e+08 | GG24: =IF($AA24>=GG$8,$AD24,0) -> 2.7083333e+08 | GH24: =IF($AA24>=GH$8,$AD24,0) -> 2.7083333e+08 | GI24: =IF($AA24>=GI$8,$AD24,0) -> 2.7083333e+08 | GJ24: =IF($AA24>=GJ$8,$AD24,0) -> 2.7083333e+08 | ... HF24: =IF($AA24>=HF$8,$AD24,0) -> 0 | HH24: =IF($AF24>=HH$8,$AI24,0) -> 2.7083333e+08 | HI24: =IF($AF24>=HI$8,$AI24,0) -> 2.7083333e+08 | HJ24: =IF($AF24>=HJ$8,$AI24,0) -> 2.7083333e+08 | HK24: =IF($AF24>=HK$8,$AI24,0) -> 2.7083333e+08 | HL24: =IF($AF24>=HL$8,$AI24,0) -> 2.7083333e+08 | HM24: =IF($AF24>=HM$8,$AI24,0) -> 2.7083333e+08 | HN24: =IF($AF24>=HN$8,$AI24,0) -> 2.7083333e+08 | HO24: =IF($AF24>=HO$8,$AI24,0) -> 2.7083333e+08 | ... IK24: =IF($AF24>=IK$8,$AI24,0) -> 0 | IM24: =IF($AK24>=IM$8,$AN24,0) -> 2.7083333e+08 | IN24: =IF($AK24>=IN$8,$AN24,0) -> 2.7083333e+08 | IO24: =IF($AK24>=IO$8,$AN24,0) -> 2.7083333e+08 | IP24: =IF($AK24>=IP$8,$AN24,0) -> 2.7083333e+08 | IQ24: =IF($AK24>=IQ$8,$AN24,0) -> 2.7083333e+08 | IR24: =IF($AK24>=IR$8,$AN24,0) -> 2.7083333e+08 | IS24: =IF($AK24>=IS$8,$AN24,0) -> 2.7083333e+08 | IT24: =IF($AK24>=IT$8,$AN24,0) -> 2.7083333e+08 | ... JP24: =IF($AK24>=JP$8,$AN24,0) -> 0 | JR24: =IF($AP24>=JR$8,$AS24,0) -> 2.7083333e+08 | JS24: =IF($AP24>=JS$8,$AS24,0) -> 2.7083333e+08 | JT24: =IF($AP24>=JT$8,$AS24,0) -> 2.7083333e+08 | JU24: =IF($AP24>=JU$8,$AS24,0) -> 2.7083333e+08 | JV24: =IF($AP24>=JV$8,$AS24,0) -> 2.7083333e+08 | JW24: =IF($AP24>=JW$8,$AS24,0) -> 2.7083333e+08 | JX24: =IF($AP24>=JX$8,$AS24,0) -> 2.7083333e+08 | JY24: =IF($AP24>=JY$8,$AS24,0) -> 2.7083333e+08 | ... KU24: =IF($AP24>=KU$8,$AS24,0) -> 0 | KW24: =IF($AU24>=KW$8,$AX24,0) -> 2.7083333e+08 | KX24: =IF($AU24>=KX$8,$AX24,0) -> 2.7083333e+08 | KY24: =IF($AU24>=KY$8,$AX24,0) -> 2.7083333e+08 | KZ24: =IF($AU24>=KZ$8,$AX24,0) -> 2.7083333e+08 | LA24: =IF($AU24>=LA$8,$AX24,0) -> 2.7083333e+08 | LB24: =IF($AU24>=LB$8,$AX24,0) -> 2.7083333e+08 | LC24: =IF($AU24>=LC$8,$AX24,0) -> 2.7083333e+08 | LD24: =IF($AU24>=LD$8,$AX24,0) -> 2.7083333e+08 | ... LZ24: =IF($AU24>=LZ$8,$AX24,0) -> 0 | MB24: =IF($AZ24>=MB$8,$BC24,0) -> 2.7083333e+08 | MC24: =IF($AZ24>=MC$8,$BC24,0) -> 2.7083333e+08 | MD24: =IF($AZ24>=MD$8,$BC24,0) -> 2.7083333e+08 | ME24: =IF($AZ24>=ME$8,$BC24,0) -> 2.7083333e+08 | MF24: =IF($AZ24>=MF$8,$BC24,0) -> 2.7083333e+08 | MG24: =IF($AZ24>=MG$8,$BC24,0) -> 2.7083333e+08 | MH24: =IF($AZ24>=MH$8,$BC24,0) -> 2.7083333e+08 | MI24: =IF($AZ24>=MI$8,$BC24,0) -> 2.7083333e+08 | ... NE24: =IF($AZ24>=NE$8,$BC24,0) -> 0
B25: Auxiliary Equipment | C25: 1.2.10 | D25: Chiller | E25: 1 | G25: 12 | H25: =(2500000000/$D$6)*1.04 -> 2600000000 | I25: =$E25*$H25 -> 2600000000 | J25: =I25/G25 -> 2.1666667e+08 | L25: 12 | M25: =$H25*(1+O$6) -> 2600000000 | N25: =$E25*M25 -> 2600000000 | O25: =N25/L25 -> 2.1666667e+08 | Q25: 12 | R25: =$H25*(1+T$6) -> 2600000000 | S25: =$E25*R25 -> 2600000000 | T25: =S25/Q25 -> 2.1666667e+08 | V25: 12 | W25: =$H25*(1+Y$6) -> 2600000000 | X25: =$E25*W25 -> 2600000000 | Y25: =X25/V25 -> 2.1666667e+08 | AA25: 12 | AB25: =$H25*(1+AD$6) -> 2600000000 | AC25: =$E25*AB25 -> 2600000000 | AD25: =AC25/AA25 -> 2.1666667e+08 | AF25: 12 | AG25: =$H25*(1+AI$6) -> 2600000000 | AH25: =$E25*AG25 -> 2600000000 | AI25: =AH25/AF25 -> 2.1666667e+08 | AK25: 12 | AL25: =$H25*(1+AN$6) -> 2600000000 | AM25: =$E25*AL25 -> 2600000000 | AN25: =AM25/AK25 -> 2.1666667e+08 | AP25: 12 | AQ25: =$H25*(1+AS$6) -> 2600000000 | AR25: =$E25*AQ25 -> 2600000000 | AS25: =AR25/AP25 -> 2.1666667e+08 | AU25: 12 | AV25: =$H25*(1+AX$6) -> 2600000000 | AW25: =$E25*AV25 -> 2600000000 | AX25: =AW25/AU25 -> 2.1666667e+08 | AZ25: 12 | BA25: =$H25*(1+BC$6) -> 2600000000 | BB25: =$E25*BA25 -> 2600000000 | BC25: =BB25/AZ25 -> 2.1666667e+08 | BF25: A. Quân | BG25: Đàm phán | BI25: =IF($G25>=BI$8,$J25,0) -> 2.1666667e+08 | BJ25: =IF($G25>=BJ$8,$J25,0) -> 2.1666667e+08 | BK25: =IF($G25>=BK$8,$J25,0) -> 2.1666667e+08 | BL25: =IF($G25>=BL$8,$J25,0) -> 2.1666667e+08 | BM25: =IF($G25>=BM$8,$J25,0) -> 2.1666667e+08 | BN25: =IF($G25>=BN$8,$J25,0) -> 2.1666667e+08 | BO25: =IF($G25>=BO$8,$J25,0) -> 2.1666667e+08 | BP25: =IF($G25>=BP$8,$J25,0) -> 2.1666667e+08 | ... CL25: =IF($G25>=CL$8,$J25,0) -> 0 | CN25: =IF($L25>=CN$8,$O25,0) -> 2.1666667e+08 | CO25: =IF($L25>=CO$8,$O25,0) -> 2.1666667e+08 | CP25: =IF($L25>=CP$8,$O25,0) -> 2.1666667e+08 | CQ25: =IF($L25>=CQ$8,$O25,0) -> 2.1666667e+08 | CR25: =IF($L25>=CR$8,$O25,0) -> 2.1666667e+08 | CS25: =IF($L25>=CS$8,$O25,0) -> 2.1666667e+08 | CT25: =IF($L25>=CT$8,$O25,0) -> 2.1666667e+08 | CU25: =IF($L25>=CU$8,$O25,0) -> 2.1666667e+08 | ... DQ25: =IF($L25>=DQ$8,$O25,0) -> 0 | DS25: =IF($Q25>=DS$8,$T25,0) -> 2.1666667e+08 | DT25: =IF($Q25>=DT$8,$T25,0) -> 2.1666667e+08 | DU25: =IF($Q25>=DU$8,$T25,0) -> 2.1666667e+08 | DV25: =IF($Q25>=DV$8,$T25,0) -> 2.1666667e+08 | DW25: =IF($Q25>=DW$8,$T25,0) -> 2.1666667e+08 | DX25: =IF($Q25>=DX$8,$T25,0) -> 2.1666667e+08 | DY25: =IF($Q25>=DY$8,$T25,0) -> 2.1666667e+08 | DZ25: =IF($Q25>=DZ$8,$T25,0) -> 2.1666667e+08 | ... EV25: =IF($Q25>=EV$8,$T25,0) -> 0 | EX25: =IF($V25>=EX$8,$Y25,0) -> 2.1666667e+08 | EY25: =IF($V25>=EY$8,$Y25,0) -> 2.1666667e+08 | EZ25: =IF($V25>=EZ$8,$Y25,0) -> 2.1666667e+08 | FA25: =IF($V25>=FA$8,$Y25,0) -> 2.1666667e+08 | FB25: =IF($V25>=FB$8,$Y25,0) -> 2.1666667e+08 | FC25: =IF($V25>=FC$8,$Y25,0) -> 2.1666667e+08 | FD25: =IF($V25>=FD$8,$Y25,0) -> 2.1666667e+08 | FE25: =IF($V25>=FE$8,$Y25,0) -> 2.1666667e+08 | ... GA25: =IF($V25>=GA$8,$Y25,0) -> 0 | GC25: =IF($AA25>=GC$8,$AD25,0) -> 2.1666667e+08 | GD25: =IF($AA25>=GD$8,$AD25,0) -> 2.1666667e+08 | GE25: =IF($AA25>=GE$8,$AD25,0) -> 2.1666667e+08 | GF25: =IF($AA25>=GF$8,$AD25,0) -> 2.1666667e+08 | GG25: =IF($AA25>=GG$8,$AD25,0) -> 2.1666667e+08 | GH25: =IF($AA25>=GH$8,$AD25,0) -> 2.1666667e+08 | GI25: =IF($AA25>=GI$8,$AD25,0) -> 2.1666667e+08 | GJ25: =IF($AA25>=GJ$8,$AD25,0) -> 2.1666667e+08 | ... HF25: =IF($AA25>=HF$8,$AD25,0) -> 0 | HH25: =IF($AF25>=HH$8,$AI25,0) -> 2.1666667e+08 | HI25: =IF($AF25>=HI$8,$AI25,0) -> 2.1666667e+08 | HJ25: =IF($AF25>=HJ$8,$AI25,0) -> 2.1666667e+08 | HK25: =IF($AF25>=HK$8,$AI25,0) -> 2.1666667e+08 | HL25: =IF($AF25>=HL$8,$AI25,0) -> 2.1666667e+08 | HM25: =IF($AF25>=HM$8,$AI25,0) -> 2.1666667e+08 | HN25: =IF($AF25>=HN$8,$AI25,0) -> 2.1666667e+08 | HO25: =IF($AF25>=HO$8,$AI25,0) -> 2.1666667e+08 | ... IK25: =IF($AF25>=IK$8,$AI25,0) -> 0 | IM25: =IF($AK25>=IM$8,$AN25,0) -> 2.1666667e+08 | IN25: =IF($AK25>=IN$8,$AN25,0) -> 2.1666667e+08 | IO25: =IF($AK25>=IO$8,$AN25,0) -> 2.1666667e+08 | IP25: =IF($AK25>=IP$8,$AN25,0) -> 2.1666667e+08 | IQ25: =IF($AK25>=IQ$8,$AN25,0) -> 2.1666667e+08 | IR25: =IF($AK25>=IR$8,$AN25,0) -> 2.1666667e+08 | IS25: =IF($AK25>=IS$8,$AN25,0) -> 2.1666667e+08 | IT25: =IF($AK25>=IT$8,$AN25,0) -> 2.1666667e+08 | ... JP25: =IF($AK25>=JP$8,$AN25,0) -> 0 | JR25: =IF($AP25>=JR$8,$AS25,0) -> 2.1666667e+08 | JS25: =IF($AP25>=JS$8,$AS25,0) -> 2.1666667e+08 | JT25: =IF($AP25>=JT$8,$AS25,0) -> 2.1666667e+08 | JU25: =IF($AP25>=JU$8,$AS25,0) -> 2.1666667e+08 | JV25: =IF($AP25>=JV$8,$AS25,0) -> 2.1666667e+08 | JW25: =IF($AP25>=JW$8,$AS25,0) -> 2.1666667e+08 | JX25: =IF($AP25>=JX$8,$AS25,0) -> 2.1666667e+08 | JY25: =IF($AP25>=JY$8,$AS25,0) -> 2.1666667e+08 | ... KU25: =IF($AP25>=KU$8,$AS25,0) -> 0 | KW25: =IF($AU25>=KW$8,$AX25,0) -> 2.1666667e+08 | KX25: =IF($AU25>=KX$8,$AX25,0) -> 2.1666667e+08 | KY25: =IF($AU25>=KY$8,$AX25,0) -> 2.1666667e+08 | KZ25: =IF($AU25>=KZ$8,$AX25,0) -> 2.1666667e+08 | LA25: =IF($AU25>=LA$8,$AX25,0) -> 2.1666667e+08 | LB25: =IF($AU25>=LB$8,$AX25,0) -> 2.1666667e+08 | LC25: =IF($AU25>=LC$8,$AX25,0) -> 2.1666667e+08 | LD25: =IF($AU25>=LD$8,$AX25,0) -> 2.1666667e+08 | ... LZ25: =IF($AU25>=LZ$8,$AX25,0) -> 0 | MB25: =IF($AZ25>=MB$8,$BC25,0) -> 2.1666667e+08 | MC25: =IF($AZ25>=MC$8,$BC25,0) -> 2.1666667e+08 | MD25: =IF($AZ25>=MD$8,$BC25,0) -> 2.1666667e+08 | ME25: =IF($AZ25>=ME$8,$BC25,0) -> 2.1666667e+08 | MF25: =IF($AZ25>=MF$8,$BC25,0) -> 2.1666667e+08 | MG25: =IF($AZ25>=MG$8,$BC25,0) -> 2.1666667e+08 | MH25: =IF($AZ25>=MH$8,$BC25,0) -> 2.1666667e+08 | MI25: =IF($AZ25>=MI$8,$BC25,0) -> 2.1666667e+08 | ... NE25: =IF($AZ25>=NE$8,$BC25,0) -> 0
