Workbook
Name Code_General_Data: 'General Data'!$A$9:$A$120
Name Code_General_Item: 'General Data'!$C$9:$C$120
Name General_Data: 'General Data'!$F$9:$BB$120
Name Month: 'General Data'!$F$4:$BB$4
Name Year: 'General Data'!$F$3:$BB$3

Sheet BÌA
A5: MA TRẬN KHÁCH HÀNG
C11: I. | D11: TỔNG QUAN GIÁ CÔNG THỨC THEO KHÁCH HÀNG
C14: II. | D14: CHI TIẾT GIÁ CÔNG THỨC THEO KHÁCH HÀNG
C17: III. | D17: BIỂU ĐỒ

Sheet Giá công thức
G1: =DATE(G3,G4,1) -> 45292 | H1: =DATE(H3,H4,1) -> 45323 | I1: =DATE(I3,I4,1) -> 45352 | J1: =DATE(J3,J4,1) -> 45383 | K1: =DATE(K3,K4,1) -> 45413 | L1: =DATE(L3,L4,1) -> 45444 | M1: =DATE(M3,M4,1) -> 45474 | N1: =DATE(N3,N4,1) -> 45505 | ... AD1: =DATE(AD3,AD4,1) -> 45992
G2: =EOMONTH(G1,0) -> 45322 | H2: =EOMONTH(H1,0) -> 45351 | I2: =EOMONTH(I1,0) -> 45382 | J2: =EOMONTH(J1,0) -> 45412 | K2: =EOMONTH(K1,0) -> 45443 | L2: =EOMONTH(L1,0) -> 45473 | M2: =EOMONTH(M1,0) -> 45504 | N2: =EOMONTH(N1,0) -> 45535 | ... AD2: =EOMONTH(AD1,0) -> 46022
G3: 2024 | H3: 2024 | I3: 2024 | J3: 2024 | K3: 2024 | L3: 2024 | M3: 2024 | N3: 2024 | O3: 2024 | P3: 2024 | Q3: 2024 | R3: 2024 | S3: 2025 | T3: 2025 | U3: 2025 | V3: 2025 | W3: 2025 | X3: 2025 | Y3: 2025 | Z3: 2025 | AA3: 2025 | AB3: 2025 | AC3: 2025 | AD3: 2025
G4: 1 | H4: 2 | I4: 3 | J4: 4 | K4: 5 | L4: 6 | M4: 7 | N4: 8 | O4: 9 | P4: 10 | Q4: 11 | R4: 12 | S4: 1 | T4: 2 | U4: 3 | V4: 4 | W4: 5 | X4: 6 | Y4: 7 | Z4: 8 | AA4: 9 | AB4: 10 | AC4: 11 | AD4: 12
G5: I. GIÁ CÔNG THỨC THEO KHÁCH HÀNG | S5: I. GIÁ CÔNG THỨC THEO KHÁCH HÀNG | AE5: I. GIÁ CÔNG THỨC THEO KHÁCH HÀNG
D8: STT | E8: KHÁCH HÀNG/SẢN PHẨM | G8: 2024 | S8: 2025 | AE8: 2026
G9: 1 | H9: 2 | I9: 3 | J9: 4 | K9: 5 | L9: 6 | M9: 7 | N9: 8 | O9: 9 | P9: 10 | Q9: 11 | R9: 12 | S9: 1 | T9: 2 | U9: 3 | V9: 4 | W9: 5 | X9: 6 | Y9: 7 | Z9: 8 | AA9: 9 | AB9: 10 | AC9: 11 | AD9: 12 | AE9: 1 | AF9: 2 | AG9: 3 | AH9: 4 | AI9: 5 | AJ9: 6 | AK9: 7 | AL9: 8 | AM9: 9 | AN9: 10 | AO9: 11 | AP9: 12
A11: 200319 | D11: 1 | E11: NIAGARA
A12: 200319 | B12: 110000354 | F12: WSS01G
A13: 200319 | B13: 110000354 | D13: 1.1 | F13: Giá bán - FOB | G13: {=INDEX(Price!$L$11:$AM$182,MATCH(1,(Price!$A$11:$A$182=$A13)*(Price!$B$11:$B$182=$B13)*(Price!$D$11:$D$182="gb"),0),MATCH(1,(Price!$L$3:$AM$3=G$3)*(Price!$L$4:$AM$4=G$4),0))} -> 1200 | H13: {=INDEX(Price!$L$11:$AM$182,MATCH(1,(Price!$A$11:$A$182=$A13)*(Price!$B$11:$B$182=$B13)*(Price!$D$11:$D$182="gb"),0),MATCH(1,(Price!$L$3:$AM$3=H$3)*(Price!$L$4:$AM$4=H$4),0))} -> 1200 | I13: {=INDEX(Price!$L$11:$AM$182,MATCH(1,(Price!$A$11:$A$182=$A13)*(Price!$B$11:$B$182=$B13)*(Price!$D$11:$D$182="gb"),0),MATCH(1,(Price!$L$3:$AM$3=I$3)*(Price!$L$4:$AM$4=I$4),0))} -> 1200 | J13: {=INDEX(Price!$L$11:$AM$182,MATCH(1,(Price!$A$11:$A$182=$A13)*(Price!$B$11:$B$182=$B13)*(Price!$D$11:$D$182="gb"),0),MATCH(1,(Price!$L$3:$AM$3=J$3)*(Price!$L$4:$AM$4=J$4),0))} -> 1200 | K13: {=INDEX(Price!$L$11:$AM$182,MATCH(1,(Price!$A$11:$A$182=$A13)*(Price!$B$11:$B$182=$B13)*(Price!$D$11:$D$182="gb"),0),MATCH(1,(Price!$L$3:$AM$3=K$3)*(Price!$L$4:$AM$4=K$4),0))} -> 1200 | L13: {=INDEX(Price!$L$11:$AM$182,MATCH(1,(Price!$A$11:$A$182=$A13)*(Price!$B$11:$B$182=$B13)*(Price!$D$11:$D$182="gb"),0),MATCH(1,(Price!$L$3:$AM$3=L$3)*(Price!$L$4:$AM$4=L$4),0))} -> 1200.9 | M13: {=INDEX(Price!$L$11:$AM$182,MATCH(1,(Price!$A$11:$A$182=$A13)*(Price!$B$11:$B$182=$B13)*(Price!$D$11:$D$182="gb"),0),MATCH(1,(Price!$L$3:$AM$3=M$3)*(Price!$L$4:$AM$4=M$4),0))} -> 1214.4 | N13: {=INDEX(Price!$L$11:$AM$182,MATCH(1,(Price!$A$11:$A$182=$A13)*(Price!$B$11:$B$182=$B13)*(Price!$D$11:$D$182="gb"),0),MATCH(1,(Price!$L$3:$AM$3=N$3)*(Price!$L$4:$AM$4=N$4),0))} -> 1226.1 | ... AD13: {=INDEX(Price!$L$11:$AM$182,MATCH(1,(Price!$A$11:$A$182=$A13)*(Price!$B$11:$B$182=$B13)*(Price!$D$11:$D$182="gb"),0),MATCH(1,(Price!$L$3:$AM$3=AD$3)*(Price!$L$4:$AM$4=AD$4),0))} -> 1200
A14: 200319 | B14: 110000354 | C14: GB | D14: 1.2 | F14: Giá bán quy đổi EXW | G14: {=INDEX(Price!$L$11:$AM$182,MATCH(1,(Price!$A$11:$A$182=$A14)*(Price!$B$11:$B$182=$B14)*(Price!$D$11:$D$182="exw"),0),MATCH(1,(Price!$L$3:$AM$3=G$3)*(Price!$L$4:$AM$4=G$4),0))} -> 1180 | H14: {=INDEX(Price!$L$11:$AM$182,MATCH(1,(Price!$A$11:$A$182=$A14)*(Price!$B$11:$B$182=$B14)*(Price!$D$11:$D$182="exw"),0),MATCH(1,(Price!$L$3:$AM$3=H$3)*(Price!$L$4:$AM$4=H$4),0))} -> 1180 | I14: {=INDEX(Price!$L$11:$AM$182,MATCH(1,(Price!$A$11:$A$182=$A14)*(Price!$B$11:$B$182=$B14)*(Price!$D$11:$D$182="exw"),0),MATCH(1,(Price!$L$3:$AM$3=I$3)*(Price!$L$4:$AM$4=I$4),0))} -> 1180 | J14: {=INDEX(Price!$L$11:$AM$182,MATCH(1,(Price!$A$11:$A$182=$A14)*(Price!$B$11:$B$182=$B14)*(Price!$D$11:$D$182="exw"),0),MATCH(1,(Price!$L$3:$AM$3=J$3)*(Price!$L$4:$AM$4=J$4),0))} -> 1180 | K14: {=INDEX(Price!$L$11:$AM$182,MATCH(1,(Price!$A$11:$A$182=$A14)*(Price!$B$11:$B$182=$B14)*(Price!$D$11:$D$182="exw"),0),MATCH(1,(Price!$L$3:$AM$3=K$3)*(Price!$L$4:$AM$4=K$4),0))} -> 1180 | L14: {=INDEX(Price!$L$11:$AM$182,MATCH(1,(Price!$A$11:$A$182=$A14)*(Price!$B$11:$B$182=$B14)*(Price!$D$11:$D$182="exw"),0),MATCH(1,(Price!$L$3:$AM$3=L$3)*(Price!$L$4:$AM$4=L$4),0))} -> 1180.9 | M14: {=INDEX(Price!$L$11:$AM$182,MATCH(1,(Price!$A$11:$A$182=$A14)*(Price!$B$11:$B$182=$B14)*(Price!$D$11:$D$182="exw"),0),MATCH(1,(Price!$L$3:$AM$3=M$3)*(Price!$L$4:$AM$4=M$4),0))} -> 1194.4 | N14: {=INDEX(Price!$L$11:$AM$182,MATCH(1,(Price!$A$11:$A$182=$A14)*(Price!$B$11:$B$182=$B14)*(Price!$D$11:$D$182="exw"),0),MATCH(1,(Price!$L$3:$AM$3=N$3)*(Price!$L$4:$AM$4=N$4),0))} -> 1206.1 | ... AD14: {=INDEX(Price!$L$11:$AM$182,MATCH(1,(Price!$A$11:$A$182=$A14)*(Price!$B$11:$B$182=$B14)*(Price!$D$11:$D$182="exw"),0),MATCH(1,(Price!$L$3:$AM$3=AD$3)*(Price!$L$4:$AM$4=AD$4),0))} -> 1180
A15: 200319 | B15: 110000354 | C15: PETVirgin | D15: 1.3 | F15: Giá chính phẩm | G15: {=SUMPRODUCT(General_Data*(Code_General_Data=$C15)*(Year=G$3)*(Month=G$4))} -> 930 | H15: {=SUMPRODUCT(General_Data*(Code_General_Data=$C15)*(Year=H$3)*(Month=H$4))} -> 943.33333 | I15: {=SUMPRODUCT(General_Data*(Code_General_Data=$C15)*(Year=I$3)*(Month=I$4))} -> 940 | J15: {=SUMPRODUCT(General_Data*(Code_General_Data=$C15)*(Year=J$3)*(Month=J$4))} -> 940 | K15: {=SUMPRODUCT(General_Data*(Code_General_Data=$C15)*(Year=K$3)*(Month=K$4))} -> 942 | L15: {=SUMPRODUCT(General_Data*(Code_General_Data=$C15)*(Year=L$3)*(Month=L$4))} -> 950 | M15: {=SUMPRODUCT(General_Data*(Code_General_Data=$C15)*(Year=M$3)*(Month=M$4))} -> 947.5 | N15: {=SUMPRODUCT(General_Data*(Code_General_Data=$C15)*(Year=N$3)*(Month=N$4))} -> 930 | ... AD15: {=SUMPRODUCT(General_Data*(Code_General_Data=$C15)*(Year=AD$3)*(Month=AD$4))} -> 770
A16: 200319 | B16: 110000354 | D16: 1.4 | F16: Chênh lệch giữa R sv Virgin | G16: =IF(G13*G14*G15<>0,G14-G15,0) -> 250 | H16: =IF(H13*H14*H15<>0,H14-H15,0) -> 236.66667 | I16: =IF(I13*I14*I15<>0,I14-I15,0) -> 240 | J16: =IF(J13*J14*J15<>0,J14-J15,0) -> 240 | K16: =IF(K13*K14*K15<>0,K14-K15,0) -> 238 | L16: =IF(L13*L14*L15<>0,L14-L15,0) -> 230.9 | M16: =IF(M13*M14*M15<>0,M14-M15,0) -> 246.9 | N16: =IF(N13*N14*N15<>0,N14-N15,0) -> 276.1 | ... AD16: =IF(AD13*AD14*AD15<>0,AD14-AD15,0) -> 410
A17: 200319 | B17: 110000354 | D17: 1.5 | F17: % +/- | G17: =IFERROR(G16/G15,0) -> 0.2688172 | H17: =IFERROR(H16/H15,0) -> 0.25088339 | I17: =IFERROR(I16/I15,0) -> 0.25531915 | J17: =IFERROR(J16/J15,0) -> 0.25531915 | K17: =IFERROR(K16/K15,0) -> 0.25265393 | L17: =IFERROR(L16/L15,0) -> 0.24305263 | M17: =IFERROR(M16/M15,0) -> 0.26058047 | N17: =IFERROR(N16/N15,0) -> 0.29688172 | ... AD17: =IFERROR(AD16/AD15,0) -> 0.53246753
A18: 200319 | B18: 110000354 | C18: 110000354 | D18: 1.6 | F18: Giá duyệt tháng | G18: {=SUMPRODUCT(General_Data*(Code_General_Data=$C18)*(Year=G$3)*(Month=G$4))} -> 1250 | H18: {=SUMPRODUCT(General_Data*(Code_General_Data=$C18)*(Year=H$3)*(Month=H$4))} -> 1250 | I18: {=SUMPRODUCT(General_Data*(Code_General_Data=$C18)*(Year=I$3)*(Month=I$4))} -> 1250 | J18: {=SUMPRODUCT(General_Data*(Code_General_Data=$C18)*(Year=J$3)*(Month=J$4))} -> 1250 | K18: {=SUMPRODUCT(General_Data*(Code_General_Data=$C18)*(Year=K$3)*(Month=K$4))} -> 1300 | L18: {=SUMPRODUCT(General_Data*(Code_General_Data=$C18)*(Year=L$3)*(Month=L$4))} -> 1300 | M18: {=SUMPRODUCT(General_Data*(Code_General_Data=$C18)*(Year=M$3)*(Month=M$4))} -> 1300 | N18: {=SUMPRODUCT(General_Data*(Code_General_Data=$C18)*(Year=N$3)*(Month=N$4))} -> 1300 | ... AD18: {=SUMPRODUCT(General_Data*(Code_General_Data=$C18)*(Year=AD$3)*(Month=AD$4))} -> 1200
A20: 200332 | D20: 2 | E20: OUTEIRINHO
A21: 200332 | B21: 110000355 | F21: iSS01G
A22: 200332 | B22: 110000355 | D22: 2.1 | F22: Giá bán-FOB | G22: {=INDEX(Price!$L$11:$AM$182,MATCH(1,(Price!$A$11:$A$182=$A22)*(Price!$B$11:$B$182=$B22)*(Price!$D$11:$D$182="gb"),0),MATCH(1,(Price!$L$3:$AM$3=G$3)*(Price!$L$4:$AM$4=G$4),0))} -> 0 | H22: {=INDEX(Price!$L$11:$AM$182,MATCH(1,(Price!$A$11:$A$182=$A22)*(Price!$B$11:$B$182=$B22)*(Price!$D$11:$D$182="gb"),0),MATCH(1,(Price!$L$3:$AM$3=H$3)*(Price!$L$4:$AM$4=H$4),0))} -> 0 | I22: {=INDEX(Price!$L$11:$AM$182,MATCH(1,(Price!$A$11:$A$182=$A22)*(Price!$B$11:$B$182=$B22)*(Price!$D$11:$D$182="gb"),0),MATCH(1,(Price!$L$3:$AM$3=I$3)*(Price!$L$4:$AM$4=I$4),0))} -> 0 | J22: {=INDEX(Price!$L$11:$AM$182,MATCH(1,(Price!$A$11:$A$182=$A22)*(Price!$B$11:$B$182=$B22)*(Price!$D$11:$D$182="gb"),0),MATCH(1,(Price!$L$3:$AM$3=J$3)*(Price!$L$4:$AM$4=J$4),0))} -> 0 | K22: {=INDEX(Price!$L$11:$AM$182,MATCH(1,(Price!$A$11:$A$182=$A22)*(Price!$B$11:$B$182=$B22)*(Price!$D$11:$D$182="gb"),0),MATCH(1,(Price!$L$3:$AM$3=K$3)*(Price!$L$4:$AM$4=K$4),0))} -> 0 | L22: {=INDEX(Price!$L$11:$AM$182,MATCH(1,(Price!$A$11:$A$182=$A22)*(Price!$B$11:$B$182=$B22)*(Price!$D$11:$D$182="gb"),0),MATCH(1,(Price!$L$3:$AM$3=L$3)*(Price!$L$4:$AM$4=L$4),0))} -> 0 | M22: {=INDEX(Price!$L$11:$AM$182,MATCH(1,(Price!$A$11:$A$182=$A22)*(Price!$B$11:$B$182=$B22)*(Price!$D$11:$D$182="gb"),0),MATCH(1,(Price!$L$3:$AM$3=M$3)*(Price!$L$4:$AM$4=M$4),0))} -> 0 | N22: {=INDEX(Price!$L$11:$AM$182,MATCH(1,(Price!$A$11:$A$182=$A22)*(Price!$B$11:$B$182=$B22)*(Price!$D$11:$D$182="gb"),0),MATCH(1,(Price!$L$3:$AM$3=N$3)*(Price!$L$4:$AM$4=N$4),0))} -> 0 | O22: {=INDEX(Price!$L$11:$AM$182,MATCH(1,(Price!$A$11:$A$182=$A22)*(Price!$B$11:$B$182=$B22)*(Price!$D$11:$D$182="gb"),0),MATCH(1,(Price!$L$3:$AM$3=O$3)*(Price!$L$4:$AM$4=O$4),0))} -> 0 | S22: {=INDEX(Price!$L$11:$AM$182,MATCH(1,(Price!$A$11:$A$182=$A22)*(Price!$B$11:$B$182=$B22)*(Price!$D$11:$D$182="gb"),0),MATCH(1,(Price!$L$3:$AM$3=S$3)*(Price!$L$4:$AM$4=S$4),0))} -> 1250 | T22: {=INDEX(Price!$L$11:$AM$182,MATCH(1,(Price!$A$11:$A$182=$A22)*(Price!$B$11:$B$182=$B22)*(Price!$D$11:$D$182="gb"),0),MATCH(1,(Price!$L$3:$AM$3=T$3)*(Price!$L$4:$AM$4=T$4),0))} -> 1250 | U22: {=INDEX(Price!$L$11:$AM$182,MATCH(1,(Price!$A$11:$A$182=$A22)*(Price!$B$11:$B$182=$B22)*(Price!$D$11:$D$182="gb"),0),MATCH(1,(Price!$L$3:$AM$3=U$3)*(Price!$L$4:$AM$4=U$4),0))} -> 1250 | V22: {=INDEX(Price!$L$11:$AM$182,MATCH(1,(Price!$A$11:$A$182=$A22)*(Price!$B$11:$B$182=$B22)*(Price!$D$11:$D$182="gb"),0),MATCH(1,(Price!$L$3:$AM$3=V$3)*(Price!$L$4:$AM$4=V$4),0))} -> 1250 | W22: {=INDEX(Price!$L$11:$AM$182,MATCH(1,(Price!$A$11:$A$182=$A22)*(Price!$B$11:$B$182=$B22)*(Price!$D$11:$D$182="gb"),0),MATCH(1,(Price!$L$3:$AM$3=W$3)*(Price!$L$4:$AM$4=W$4),0))} -> 1250 | X22: {=INDEX(Price!$L$11:$AM$182,MATCH(1,(Price!$A$11:$A$182=$A22)*(Price!$B$11:$B$182=$B22)*(Price!$D$11:$D$182="gb"),0),MATCH(1,(Price!$L$3:$AM$3=X$3)*(Price!$L$4:$AM$4=X$4),0))} -> 1250 | Y22: {=INDEX(Price!$L$11:$AM$182,MATCH(1,(Price!$A$11:$A$182=$A22)*(Price!$B$11:$B$182=$B22)*(Price!$D$11:$D$182="gb"),0),MATCH(1,(Price!$L$3:$AM$3=Y$3)*(Price!$L$4:$AM$4=Y$4),0))} -> 1250 | Z22: {=INDEX(Price!$L$11:$AM$182,MATCH(1,(Price!$A$11:$A$182=$A22)*(Price!$B$11:$B$182=$B22)*(Price!$D$11:$D$182="gb"),0),MATCH(1,(Price!$L$3:$AM$3=Z$3)*(Price!$L$4:$AM$4=Z$4),0))} -> 1250 | ... AD22: {=INDEX(Price!$L$11:$AM$182,MATCH(1,(Price!$A$11:$A$182=$A22)*(Price!$B$11:$B$182=$B22)*(Price!$D$11:$D$182="gb"),0),MATCH(1,(Price!$L$3:$AM$3=AD$3)*(Price!$L$4:$AM$4=AD$4),0))} -> 1250
A23: 200332 | B23: 110000355 | C23: GB | D23: 2.2 | F23: Giá bán quy đổi EXW | G23: {=INDEX(Price!$L$11:$AM$182,MATCH(1,(Price!$A$11:$A$182=$A23)*(Price!$B$11:$B$182=$B23)*(Price!$D$11:$D$182="exw"),0),MATCH(1,(Price!$L$3:$AM$3=G$3)*(Price!$L$4:$AM$4=G$4),0))} -> 0 | H23: {=INDEX(Price!$L$11:$AM$182,MATCH(1,(Price!$A$11:$A$182=$A23)*(Price!$B$11:$B$182=$B23)*(Price!$D$11:$D$182="exw"),0),MATCH(1,(Price!$L$3:$AM$3=H$3)*(Price!$L$4:$AM$4=H$4),0))} -> 0 | I23: {=INDEX(Price!$L$11:$AM$182,MATCH(1,(Price!$A$11:$A$182=$A23)*(Price!$B$11:$B$182=$B23)*(Price!$D$11:$D$182="exw"),0),MATCH(1,(Price!$L$3:$AM$3=I$3)*(Price!$L$4:$AM$4=I$4),0))} -> 0 | J23: {=INDEX(Price!$L$11:$AM$182,MATCH(1,(Price!$A$11:$A$182=$A23)*(Price!$B$11:$B$182=$B23)*(Price!$D$11:$D$182="exw"),0),MATCH(1,(Price!$L$3:$AM$3=J$3)*(Price!$L$4:$AM$4=J$4),0))} -> 0 | K23: {=INDEX(Price!$L$11:$AM$182,MATCH(1,(Price!$A$11:$A$182=$A23)*(Price!$B$11:$B$182=$B23)*(Price!$D$11:$D$182="exw"),0),MATCH(1,(Price!$L$3:$AM$3=K$3)*(Price!$L$4:$AM$4=K$4),0))} -> 0 | L23: {=INDEX(Price!$L$11:$AM$182,MATCH(1,(Price!$A$11:$A$182=$A23)*(Price!$B$11:$B$182=$B23)*(Price!$D$11:$D$182="exw"),0),MATCH(1,(Price!$L$3:$AM$3=L$3)*(Price!$L$4:$AM$4=L$4),0))} -> 0 | M23: {=INDEX(Price!$L$11:$AM$182,MATCH(1,(Price!$A$11:$A$182=$A23)*(Price!$B$11:$B$182=$B23)*(Price!$D$11:$D$182="exw"),0),MATCH(1,(Price!$L$3:$AM$3=M$3)*(Price!$L$4:$AM$4=M$4),0))} -> 0 | N23: {=INDEX(Price!$L$11:$AM$182,MATCH(1,(Price!$A$11:$A$182=$A23)*(Price!$B$11:$B$182=$B23)*(Price!$D$11:$D$182="exw"),0),MATCH(1,(Price!$L$3:$AM$3=N$3)*(Price!$L$4:$AM$4=N$4),0))} -> 0 | O23: {=INDEX(Price!$L$11:$AM$182,MATCH(1,(Price!$A$11:$A$182=$A23)*(Price!$B$11:$B$182=$B23)*(Price!$D$11:$D$182="exw"),0),MATCH(1,(Price!$L$3:$AM$3=O$3)*(Price!$L$4:$AM$4=O$4),0))} -> 0 | S23: {=INDEX(Price!$L$11:$AM$182,MATCH(1,(Price!$A$11:$A$182=$A23)*(Price!$B$11:$B$182=$B23)*(Price!$D$11:$D$182="exw"),0),MATCH(1,(Price!$L$3:$AM$3=S$3)*(Price!$L$4:$AM$4=S$4),0))} -> 1230 | T23: {=INDEX(Price!$L$11:$AM$182,MATCH(1,(Price!$A$11:$A$182=$A23)*(Price!$B$11:$B$182=$B23)*(Price!$D$11:$D$182="exw"),0),MATCH(1,(Price!$L$3:$AM$3=T$3)*(Price!$L$4:$AM$4=T$4),0))} -> 1230 | U23: {=INDEX(Price!$L$11:$AM$182,MATCH(1,(Price!$A$11:$A$182=$A23)*(Price!$B$11:$B$182=$B23)*(Price!$D$11:$D$182="exw"),0),MATCH(1,(Price!$L$3:$AM$3=U$3)*(Price!$L$4:$AM$4=U$4),0))} -> 1230 | V23: {=INDEX(Price!$L$11:$AM$182,MATCH(1,(Price!$A$11:$A$182=$A23)*(Price!$B$11:$B$182=$B23)*(Price!$D$11:$D$182="exw"),0),MATCH(1,(Price!$L$3:$AM$3=V$3)*(Price!$L$4:$AM$4=V$4),0))} -> 1228 | W23: {=INDEX(Price!$L$11:$AM$182,MATCH(1,(Price!$A$11:$A$182=$A23)*(Price!$B$11:$B$182=$B23)*(Price!$D$11:$D$182="exw"),0),MATCH(1,(Price!$L$3:$AM$3=W$3)*(Price!$L$4:$AM$4=W$4),0))} -> 1228 | X23: {=INDEX(Price!$L$11:$AM$182,MATCH(1,(Price!$A$11:$A$182=$A23)*(Price!$B$11:$B$182=$B23)*(Price!$D$11:$D$182="exw"),0),MATCH(1,(Price!$L$3:$AM$3=X$3)*(Price!$L$4:$AM$4=X$4),0))} -> 1228 | Y23: {=INDEX(Price!$L$11:$AM$182,MATCH(1,(Price!$A$11:$A$182=$A23)*(Price!$B$11:$B$182=$B23)*(Price!$D$11:$D$182="exw"),0),MATCH(1,(Price!$L$3:$AM$3=Y$3)*(Price!$L$4:$AM$4=Y$4),0))} -> 1228 | Z23: {=INDEX(Price!$L$11:$AM$182,MATCH(1,(Price!$A$11:$A$182=$A23)*(Price!$B$11:$B$182=$B23)*(Price!$D$11:$D$182="exw"),0),MATCH(1,(Price!$L$3:$AM$3=Z$3)*(Price!$L$4:$AM$4=Z$4),0))} -> 1228 | ... AD23: {=INDEX(Price!$L$11:$AM$182,MATCH(1,(Price!$A$11:$A$182=$A23)*(Price!$B$11:$B$182=$B23)*(Price!$D$11:$D$182="exw"),0),MATCH(1,(Price!$L$3:$AM$3=AD$3)*(Price!$L$4:$AM$4=AD$4),0))} -> 1228
A24: 200332 | B24: 110000355 | C24: PETVirgin | D24: 2.3 | F24: Giá chính phẩm | S24: {=SUMPRODUCT(General_Data*(Code_General_Data=$C24)*(Year=S$3)*(Month=S$4))} -> 828 | T24: {=SUMPRODUCT(General_Data*(Code_General_Data=$C24)*(Year=T$3)*(Month=T$4))} -> 840 | U24: {=SUMPRODUCT(General_Data*(Code_General_Data=$C24)*(Year=U$3)*(Month=U$4))} -> 823 | V24: {=SUMPRODUCT(General_Data*(Code_General_Data=$C24)*(Year=V$3)*(Month=V$4))} -> 765 | W24: {=SUMPRODUCT(General_Data*(Code_General_Data=$C24)*(Year=W$3)*(Month=W$4))} -> 782 | X24: {=SUMPRODUCT(General_Data*(Code_General_Data=$C24)*(Year=X$3)*(Month=X$4))} -> 807.5 | Y24: {=SUMPRODUCT(General_Data*(Code_General_Data=$C24)*(Year=Y$3)*(Month=Y$4))} -> 802 | Z24: {=SUMPRODUCT(General_Data*(Code_General_Data=$C24)*(Year=Z$3)*(Month=Z$4))} -> 795 | ... AD24: {=SUMPRODUCT(General_Data*(Code_General_Data=$C24)*(Year=AD$3)*(Month=AD$4))} -> 770
A25: 200332 | B25: 110000355 | D25: 2.4 | F25: Chênh lệch giữa R sv Virgin | S25: =IF(S22*S23*S24<>0,S23-S24,0) -> 402 | T25: =IF(T22*T23*T24<>0,T23-T24,0) -> 390 | U25: =IF(U22*U23*U24<>0,U23-U24,0) -> 407 | V25: =IF(V22*V23*V24<>0,V23-V24,0) -> 463 | W25: =IF(W22*W23*W24<>0,W23-W24,0) -> 446 | X25: =IF(X22*X23*X24<>0,X23-X24,0) -> 420.5 | Y25: =IF(Y22*Y23*Y24<>0,Y23-Y24,0) -> 426 | Z25: =IF(Z22*Z23*Z24<>0,Z23-Z24,0) -> 433 | ... AD25: =IF(AD22*AD23*AD24<>0,AD23-AD24,0) -> 458
A26: 200332 | B26: 110000355 | D26: 2.5 | F26: % +/- | S26: =IFERROR(S25/S24,0) -> 0.48550725 | T26: =IFERROR(T25/T24,0) -> 0.46428571 | U26: =IFERROR(U25/U24,0) -> 0.4945322 | V26: =IFERROR(V25/V24,0) -> 0.60522876 | W26: =IFERROR(W25/W24,0) -> 0.57033248 | X26: =IFERROR(X25/X24,0) -> 0.52074303 | Y26: =IFERROR(Y25/Y24,0) -> 0.53117207 | Z26: =IFERROR(Z25/Z24,0) -> 0.54465409 | ... AD26: =IFERROR(AD25/AD24,0) -> 0.59480519
A27: 200332 | B27: 110000355 | C27: 110000355 | D27: 2.6 | F27: Giá duyệt tháng | S27: {=SUMPRODUCT(General_Data*(Code_General_Data=$C27)*(Year=S$3)*(Month=S$4))} -> 1260 | T27: {=SUMPRODUCT(General_Data*(Code_General_Data=$C27)*(Year=T$3)*(Month=T$4))} -> 1260 | U27: {=SUMPRODUCT(General_Data*(Code_General_Data=$C27)*(Year=U$3)*(Month=U$4))} -> 1260 | V27: {=SUMPRODUCT(General_Data*(Code_General_Data=$C27)*(Year=V$3)*(Month=V$4))} -> 1280 | W27: {=SUMPRODUCT(General_Data*(Code_General_Data=$C27)*(Year=W$3)*(Month=W$4))} -> 1280 | X27: {=SUMPRODUCT(General_Data*(Code_General_Data=$C27)*(Year=X$3)*(Month=X$4))} -> 1280 | Y27: {=SUMPRODUCT(General_Data*(Code_General_Data=$C27)*(Year=Y$3)*(Month=Y$4))} -> 1280 | Z27: {=SUMPRODUCT(General_Data*(Code_General_Data=$C27)*(Year=Z$3)*(Month=Z$4))} -> 1250 | ... AD27: {=SUMPRODUCT(General_Data*(Code_General_Data=$C27)*(Year=AD$3)*(Month=AD$4))} -> 1230
A29: 105263 | D29: 3 | E29: UNILEVER VIET NAM
A30: 105263 | B30: 110000354 | F30: WSS01G
A31: 105263 | B31: 110000354 | D31: 3.1 | F31: Giá bán - DDP | G31: {=INDEX(Price!$L$11:$AM$182,MATCH(1,(Price!$A$11:$A$182=$A31)*(Price!$B$11:$B$182=$B31)*(Price!$D$11:$D$182="gb"),0),MATCH(1,(Price!$L$3:$AM$3=G$3)*(Price!$L$4:$AM$4=G$4),0))} -> 1320 | H31: {=INDEX(Price!$L$11:$AM$182,MATCH(1,(Price!$A$11:$A$182=$A31)*(Price!$B$11:$B$182=$B31)*(Price!$D$11:$D$182="gb"),0),MATCH(1,(Price!$L$3:$AM$3=H$3)*(Price!$L$4:$AM$4=H$4),0))} -> 1320 | I31: {=INDEX(Price!$L$11:$AM$182,MATCH(1,(Price!$A$11:$A$182=$A31)*(Price!$B$11:$B$182=$B31)*(Price!$D$11:$D$182="gb"),0),MATCH(1,(Price!$L$3:$AM$3=I$3)*(Price!$L$4:$AM$4=I$4),0))} -> 1320 | J31: {=INDEX(Price!$L$11:$AM$182,MATCH(1,(Price!$A$11:$A$182=$A31)*(Price!$B$11:$B$182=$B31)*(Price!$D$11:$D$182="gb"),0),MATCH(1,(Price!$L$3:$AM$3=J$3)*(Price!$L$4:$AM$4=J$4),0))} -> 1320 | K31: {=INDEX(Price!$L$11:$AM$182,MATCH(1,(Price!$A$11:$A$182=$A31)*(Price!$B$11:$B$182=$B31)*(Price!$D$11:$D$182="gb"),0),MATCH(1,(Price!$L$3:$AM$3=K$3)*(Price!$L$4:$AM$4=K$4),0))} -> 1320 | L31: {=INDEX(Price!$L$11:$AM$182,MATCH(1,(Price!$A$11:$A$182=$A31)*(Price!$B$11:$B$182=$B31)*(Price!$D$11:$D$182="gb"),0),MATCH(1,(Price!$L$3:$AM$3=L$3)*(Price!$L$4:$AM$4=L$4),0))} -> 1320 | M31: {=INDEX(Price!$L$11:$AM$182,MATCH(1,(Price!$A$11:$A$182=$A31)*(Price!$B$11:$B$182=$B31)*(Price!$D$11:$D$182="gb"),0),MATCH(1,(Price!$L$3:$AM$3=M$3)*(Price!$L$4:$AM$4=M$4),0))} -> 1320 | N31: {=INDEX(Price!$L$11:$AM$182,MATCH(1,(Price!$A$11:$A$182=$A31)*(Price!$B$11:$B$182=$B31)*(Price!$D$11:$D$182="gb"),0),MATCH(1,(Price!$L$3:$AM$3=N$3)*(Price!$L$4:$AM$4=N$4),0))} -> 1320 | ... AD31: {=INDEX(Price!$L$11:$AM$182,MATCH(1,(Price!$A$11:$A$182=$A31)*(Price!$B$11:$B$182=$B31)*(Price!$D$11:$D$182="gb"),0),MATCH(1,(Price!$L$3:$AM$3=AD$3)*(Price!$L$4:$AM$4=AD$4),0))} -> 1280
A32: 105263 | B32: 110000354 | C32: GB | D32: 3.2 | F32: Giá bán quy đổi EXW | G32: {=INDEX(Price!$L$11:$AM$182,MATCH(1,(Price!$A$11:$A$182=$A32)*(Price!$B$11:$B$182=$B32)*(Price!$D$11:$D$182="exw"),0),MATCH(1,(Price!$L$3:$AM$3=G$3)*(Price!$L$4:$AM$4=G$4),0))} -> 1307.7959 | H32: {=INDEX(Price!$L$11:$AM$182,MATCH(1,(Price!$A$11:$A$182=$A32)*(Price!$B$11:$B$182=$B32)*(Price!$D$11:$D$182="exw"),0),MATCH(1,(Price!$L$3:$AM$3=H$3)*(Price!$L$4:$AM$4=H$4),0))} -> 1307.7959 | I32: {=INDEX(Price!$L$11:$AM$182,MATCH(1,(Price!$A$11:$A$182=$A32)*(Price!$B$11:$B$182=$B32)*(Price!$D$11:$D$182="exw"),0),MATCH(1,(Price!$L$3:$AM$3=I$3)*(Price!$L$4:$AM$4=I$4),0))} -> 1307.7959 | J32: {=INDEX(Price!$L$11:$AM$182,MATCH(1,(Price!$A$11:$A$182=$A32)*(Price!$B$11:$B$182=$B32)*(Price!$D$11:$D$182="exw"),0),MATCH(1,(Price!$L$3:$AM$3=J$3)*(Price!$L$4:$AM$4=J$4),0))} -> 1307.7959 | K32: {=INDEX(Price!$L$11:$AM$182,MATCH(1,(Price!$A$11:$A$182=$A32)*(Price!$B$11:$B$182=$B32)*(Price!$D$11:$D$182="exw"),0),MATCH(1,(Price!$L$3:$AM$3=K$3)*(Price!$L$4:$AM$4=K$4),0))} -> 1307.7959 | L32: {=INDEX(Price!$L$11:$AM$182,MATCH(1,(Price!$A$11:$A$182=$A32)*(Price!$B$11:$B$182=$B32)*(Price!$D$11:$D$182="exw"),0),MATCH(1,(Price!$L$3:$AM$3=L$3)*(Price!$L$4:$AM$4=L$4),0))} -> 1307.7959 | M32: {=INDEX(Price!$L$11:$AM$182,MATCH(1,(Price!$A$11:$A$182=$A32)*(Price!$B$11:$B$182=$B32)*(Price!$D$11:$D$182="exw"),0),MATCH(1,(Price!$L$3:$AM$3=M$3)*(Price!$L$4:$AM$4=M$4),0))} -> 1308.04 | N32: {=INDEX(Price!$L$11:$AM$182,MATCH(1,(Price!$A$11:$A$182=$A32)*(Price!$B$11:$B$182=$B32)*(Price!$D$11:$D$182="exw"),0),MATCH(1,(Price!$L$3:$AM$3=N$3)*(Price!$L$4:$AM$4=N$4),0))} -> 1308.04 | ... AD32: {=INDEX(Price!$L$11:$AM$182,MATCH(1,(Price!$A$11:$A$182=$A32)*(Price!$B$11:$B$182=$B32)*(Price!$D$11:$D$182="exw"),0),MATCH(1,(Price!$L$3:$AM$3=AD$3)*(Price!$L$4:$AM$4=AD$4),0))} -> 1268.04
A33: 105263 | B33: 110000354 | C33: PETVirgin | D33: 3.3 | F33: Giá chính phẩm | G33: {=SUMPRODUCT(General_Data*(Code_General_Data=$C33)*(Year=G$3)*(Month=G$4))} -> 930 | H33: {=SUMPRODUCT(General_Data*(Code_General_Data=$C33)*(Year=H$3)*(Month=H$4))} -> 943.33333 | I33: {=SUMPRODUCT(General_Data*(Code_General_Data=$C33)*(Year=I$3)*(Month=I$4))} -> 940 | J33: {=SUMPRODUCT(General_Data*(Code_General_Data=$C33)*(Year=J$3)*(Month=J$4))} -> 940 | K33: {=SUMPRODUCT(General_Data*(Code_General_Data=$C33)*(Year=K$3)*(Month=K$4))} -> 942 | L33: {=SUMPRODUCT(General_Data*(Code_General_Data=$C33)*(Year=L$3)*(Month=L$4))} -> 950 | M33: {=SUMPRODUCT(General_Data*(Code_General_Data=$C33)*(Year=M$3)*(Month=M$4))} -> 947.5 | N33: {=SUMPRODUCT(General_Data*(Code_General_Data=$C33)*(Year=N$3)*(Month=N$4))} -> 930 | ... AD33: {=SUMPRODUCT(General_Data*(Code_General_Data=$C33)*(Year=AD$3)*(Month=AD$4))} -> 770
A34: 105263 | B34: 110000354 | D34: 3.4 | F34: Chênh lệch giữa R sv Virgin | G34: =IF(G31*G32*G33<>0,G32-G33,0) -> 377.79592 | H34: =IF(H31*H32*H33<>0,H32-H33,0) -> 364.46259 | I34: =IF(I31*I32*I33<>0,I32-I33,0) -> 367.79592 | J34: =IF(J31*J32*J33<>0,J32-J33,0) -> 367.79592 | K34: =IF(K31*K32*K33<>0,K32-K33,0) -> 365.79592 | L34: =IF(L31*L32*L33<>0,L32-L33,0) -> 357.79592 | M34: =IF(M31*M32*M33<>0,M32-M33,0) -> 360.54 | N34: =IF(N31*N32*N33<>0,N32-N33,0) -> 378.04 | ... AD34: =IF(AD31*AD32*AD33<>0,AD32-AD33,0) -> 498.04
A35: 105263 | B35: 110000354 | D35: 3.5 | F35: % +/- | G35: =IFERROR(G34/G33,0) -> 0.40623217 | H35: =IFERROR(H34/H33,0) -> 0.3863561 | I35: =IFERROR(I34/I33,0) -> 0.39127225 | J35: =IFERROR(J34/J33,0) -> 0.39127225 | K35: =IFERROR(K34/K33,0) -> 0.38831838 | L35: =IFERROR(L34/L33,0) -> 0.37662728 | M35: =IFERROR(M34/M33,0) -> 0.38051715 | N35: =IFERROR(N34/N33,0) -> 0.40649462 | ... AD35: =IFERROR(AD34/AD33,0) -> 0.64680519
A36: 105263 | B36: 110000354 | C36: 110000354 | D36: 3.6 | F36: Giá duyệt tháng | G36: {=SUMPRODUCT(General_Data*(Code_General_Data=$C36)*(Year=G$3)*(Month=G$4))} -> 1250 | H36: {=SUMPRODUCT(General_Data*(Code_General_Data=$C36)*(Year=H$3)*(Month=H$4))} -> 1250 | I36: {=SUMPRODUCT(General_Data*(Code_General_Data=$C36)*(Year=I$3)*(Month=I$4))} -> 1250 | J36: {=SUMPRODUCT(General_Data*(Code_General_Data=$C36)*(Year=J$3)*(Month=J$4))} -> 1250 | K36: {=SUMPRODUCT(General_Data*(Code_General_Data=$C36)*(Year=K$3)*(Month=K$4))} -> 1300 | L36: {=SUMPRODUCT(General_Data*(Code_General_Data=$C36)*(Year=L$3)*(Month=L$4))} -> 1300 | M36: {=SUMPRODUCT(General_Data*(Code_General_Data=$C36)*(Year=M$3)*(Month=M$4))} -> 1300 | N36: {=SUMPRODUCT(General_Data*(Code_General_Data=$C36)*(Year=N$3)*(Month=N$4))} -> 1300 | ... AD36: {=SUMPRODUCT(General_Data*(Code_General_Data=$C36)*(Year=AD$3)*(Month=AD$4))} -> 1200
A37: 105263
A38: 105263 | B38: 110000339 | F38: MBF01
A39: 105263 | B39: 110000339 | D39: 3.7 | F39: Giá bán - DDP | G39: {=INDEX(Price!$L$11:$AM$182,MATCH(1,(Price!$A$11:$A$182=$A39)*(Price!$B$11:$B$182=$B39)*(Price!$D$11:$D$182="gb"),0),MATCH(1,(Price!$L$3:$AM$3=G$3)*(Price!$L$4:$AM$4=G$4),0))} -> 1500 | H39: {=INDEX(Price!$L$11:$AM$182,MATCH(1,(Price!$A$11:$A$182=$A39)*(Price!$B$11:$B$182=$B39)*(Price!$D$11:$D$182="gb"),0),MATCH(1,(Price!$L$3:$AM$3=H$3)*(Price!$L$4:$AM$4=H$4),0))} -> 1500 | I39: {=INDEX(Price!$L$11:$AM$182,MATCH(1,(Price!$A$11:$A$182=$A39)*(Price!$B$11:$B$182=$B39)*(Price!$D$11:$D$182="gb"),0),MATCH(1,(Price!$L$3:$AM$3=I$3)*(Price!$L$4:$AM$4=I$4),0))} -> 1500 | J39: {=INDEX(Price!$L$11:$AM$182,MATCH(1,(Price!$A$11:$A$182=$A39)*(Price!$B$11:$B$182=$B39)*(Price!$D$11:$D$182="gb"),0),MATCH(1,(Price!$L$3:$AM$3=J$3)*(Price!$L$4:$AM$4=J$4),0))} -> 1430 | K39: {=INDEX(Price!$L$11:$AM$182,MATCH(1,(Price!$A$11:$A$182=$A39)*(Price!$B$11:$B$182=$B39)*(Price!$D$11:$D$182="gb"),0),MATCH(1,(Price!$L$3:$AM$3=K$3)*(Price!$L$4:$AM$4=K$4),0))} -> 1430 | L39: {=INDEX(Price!$L$11:$AM$182,MATCH(1,(Price!$A$11:$A$182=$A39)*(Price!$B$11:$B$182=$B39)*(Price!$D$11:$D$182="gb"),0),MATCH(1,(Price!$L$3:$AM$3=L$3)*(Price!$L$4:$AM$4=L$4),0))} -> 1430 | M39: {=INDEX(Price!$L$11:$AM$182,MATCH(1,(Price!$A$11:$A$182=$A39)*(Price!$B$11:$B$182=$B39)*(Price!$D$11:$D$182="gb"),0),MATCH(1,(Price!$L$3:$AM$3=M$3)*(Price!$L$4:$AM$4=M$4),0))} -> 1430 | N39: {=INDEX(Price!$L$11:$AM$182,MATCH(1,(Price!$A$11:$A$182=$A39)*(Price!$B$11:$B$182=$B39)*(Price!$D$11:$D$182="gb"),0),MATCH(1,(Price!$L$3:$AM$3=N$3)*(Price!$L$4:$AM$4=N$4),0))} -> 1430 | ... AD39: {=INDEX(Price!$L$11:$AM$182,MATCH(1,(Price!$A$11:$A$182=$A39)*(Price!$B$11:$B$182=$B39)*(Price!$D$11:$D$182="gb"),0),MATCH(1,(Price!$L$3:$AM$3=AD$3)*(Price!$L$4:$AM$4=AD$4),0))} -> 1380
A40: 105263 | B40: 110000339 | C40: GB | D40: 3.8 | F40: Giá bán quy đổi EXW | G40: {=INDEX(Price!$L$11:$AM$182,MATCH(1,(Price!$A$11:$A$182=$A40)*(Price!$B$11:$B$182=$B40)*(Price!$D$11:$D$182="exw"),0),MATCH(1,(Price!$L$3:$AM$3=G$3)*(Price!$L$4:$AM$4=G$4),0))} -> 1487.7959 | H40: {=INDEX(Price!$L$11:$AM$182,MATCH(1,(Price!$A$11:$A$182=$A40)*(Price!$B$11:$B$182=$B40)*(Price!$D$11:$D$182="exw"),0),MATCH(1,(Price!$L$3:$AM$3=H$3)*(Price!$L$4:$AM$4=H$4),0))} -> 1487.7959 | I40: {=INDEX(Price!$L$11:$AM$182,MATCH(1,(Price!$A$11:$A$182=$A40)*(Price!$B$11:$B$182=$B40)*(Price!$D$11:$D$182="exw"),0),MATCH(1,(Price!$L$3:$AM$3=I$3)*(Price!$L$4:$AM$4=I$4),0))} -> 1487.7959 | J40: {=INDEX(Price!$L$11:$AM$182,MATCH(1,(Price!$A$11:$A$182=$A40)*(Price!$B$11:$B$182=$B40)*(Price!$D$11:$D$182="exw"),0),MATCH(1,(Price!$L$3:$AM$3=J$3)*(Price!$L$4:$AM$4=J$4),0))} -> 1417.7959 | K40: {=INDEX(Price!$L$11:$AM$182,MATCH(1,(Price!$A$11:$A$182=$A40)*(Price!$B$11:$B$182=$B40)*(Price!$D$11:$D$182="exw"),0),MATCH(1,(Price!$L$3:$AM$3=K$3)*(Price!$L$4:$AM$4=K$4),0))} -> 1417.7959 | L40: {=INDEX(Price!$L$11:$AM$182,MATCH(1,(Price!$A$11:$A$182=$A40)*(Price!$B$11:$B$182=$B40)*(Price!$D$11:$D$182="exw"),0),MATCH(1,(Price!$L$3:$AM$3=L$3)*(Price!$L$4:$AM$4=L$4),0))} -> 1417.7959 | M40: {=INDEX(Price!$L$11:$AM$182,MATCH(1,(Price!$A$11:$A$182=$A40)*(Price!$B$11:$B$182=$B40)*(Price!$D$11:$D$182="exw"),0),MATCH(1,(Price!$L$3:$AM$3=M$3)*(Price!$L$4:$AM$4=M$4),0))} -> 1418.04 | N40: {=INDEX(Price!$L$11:$AM$182,MATCH(1,(Price!$A$11:$A$182=$A40)*(Price!$B$11:$B$182=$B40)*(Price!$D$11:$D$182="exw"),0),MATCH(1,(Price!$L$3:$AM$3=N$3)*(Price!$L$4:$AM$4=N$4),0))} -> 1418.04 | ... AD40: {=INDEX(Price!$L$11:$AM$182,MATCH(1,(Price!$A$11:$A$182=$A40)*(Price!$B$11:$B$182=$B40)*(Price!$D$11:$D$182="exw"),0),MATCH(1,(Price!$L$3:$AM$3=AD$3)*(Price!$L$4:$AM$4=AD$4),0))} -> 1368.04
A41: 105263 | B41: 110000339 | C41: HDPEVirgin | D41: 3.9 | F41: Giá chính phẩm | G41: {=SUMPRODUCT(General_Data*(Code_General_Data=$C41)*(Year=G$3)*(Month=G$4))} -> 940 | H41: {=SUMPRODUCT(General_Data*(Code_General_Data=$C41)*(Year=H$3)*(Month=H$4))} -> 993.33333 | I41: {=SUMPRODUCT(General_Data*(Code_General_Data=$C41)*(Year=I$3)*(Month=I$4))} -> 985 | J41: {=SUMPRODUCT(General_Data*(Code_General_Data=$C41)*(Year=J$3)*(Month=J$4))} -> 962.5 | K41: {=SUMPRODUCT(General_Data*(Code_General_Data=$C41)*(Year=K$3)*(Month=K$4))} -> 982 | L41: {=SUMPRODUCT(General_Data*(Code_General_Data=$C41)*(Year=L$3)*(Month=L$4))} -> 1000 | M41: {=SUMPRODUCT(General_Data*(Code_General_Data=$C41)*(Year=M$3)*(Month=M$4))} -> 1000 | N41: {=SUMPRODUCT(General_Data*(Code_General_Data=$C41)*(Year=N$3)*(Month=N$4))} -> 984 | ... AD41: {=SUMPRODUCT(General_Data*(Code_General_Data=$C41)*(Year=AD$3)*(Month=AD$4))} -> 805
A42: 105263 | B42: 110000339 | D42: 3.1 | F42: Chênh lệch giữa R sv Virgin | G42: =IF(G39*G40*G41<>0,G40-G41,0) -> 547.79592 | H42: =IF(H39*H40*H41<>0,H40-H41,0) -> 494.46259 | I42: =IF(I39*I40*I41<>0,I40-I41,0) -> 502.79592 | J42: =IF(J39*J40*J41<>0,J40-J41,0) -> 455.29592 | K42: =IF(K39*K40*K41<>0,K40-K41,0) -> 435.79592 | L42: =IF(L39*L40*L41<>0,L40-L41,0) -> 417.79592 | M42: =IF(M39*M40*M41<>0,M40-M41,0) -> 418.04 | N42: =IF(N39*N40*N41<>0,N40-N41,0) -> 434.04 | ... AD42: =IF(AD39*AD40*AD41<>0,AD40-AD41,0) -> 563.04
A43: 105263 | B43: 110000339 | D43: 3.11 | F43: % +/- | G43: =IFERROR(G42/G41,0) -> 0.58276162 | H43: =IFERROR(H42/H41,0) -> 0.49778113 | I43: =IFERROR(I42/I41,0) -> 0.51045271 | J43: =IFERROR(J42/J41,0) -> 0.47303472 | K43: =IFERROR(K42/K41,0) -> 0.44378403 | L43: =IFERROR(L42/L41,0) -> 0.41779592 | M43: =IFERROR(M42/M41,0) -> 0.41804 | N43: =IFERROR(N42/N41,0) -> 0.44109756 | ... AD43: =IFERROR(AD42/AD41,0) -> 0.69942857
A44: 105263 | B44: 110000339 | C44: 110000339 | D44: 3.12 | F44: Giá duyệt tháng | G44: {=SUMPRODUCT(General_Data*(Code_General_Data=$C44)*(Year=G$3)*(Month=G$4))} -> 1350 | H44: {=SUMPRODUCT(General_Data*(Code_General_Data=$C44)*(Year=H$3)*(Month=H$4))} -> 1350 | I44: {=SUMPRODUCT(General_Data*(Code_General_Data=$C44)*(Year=I$3)*(Month=I$4))} -> 1350 | J44: {=SUMPRODUCT(General_Data*(Code_General_Data=$C44)*(Year=J$3)*(Month=J$4))} -> 1350 | K44: {=SUMPRODUCT(General_Data*(Code_General_Data=$C44)*(Year=K$3)*(Month=K$4))} -> 1350 | L44: {=SUMPRODUCT(General_Data*(Code_General_Data=$C44)*(Year=L$3)*(Month=L$4))} -> 1350 | M44: {=SUMPRODUCT(General_Data*(Code_General_Data=$C44)*(Year=M$3)*(Month=M$4))} -> 1350 | N44: {=SUMPRODUCT(General_Data*(Code_General_Data=$C44)*(Year=N$3)*(Month=N$4))} -> 1350 | ... AD44: {=SUMPRODUCT(General_Data*(Code_General_Data=$C44)*(Year=AD$3)*(Month=AD$4))} -> 1200
A45: 105263
A46: 105263 | B46: 110000481 | F46: PCF01
A47: 105263 | B47: 110000481 | D47: 3.13 | F47: Giá bán - DDP | G47: {=INDEX(Price!$L$11:$AM$182,MATCH(1,(Price!$A$11:$A$182=$A47)*(Price!$B$11:$B$182=$B47)*(Price!$D$11:$D$182="gb"),0),MATCH(1,(Price!$L$3:$AM$3=G$3)*(Price!$L$4:$AM$4=G$4),0))} -> 0 | H47: {=INDEX(Price!$L$11:$AM$182,MATCH(1,(Price!$A$11:$A$182=$A47)*(Price!$B$11:$B$182=$B47)*(Price!$D$11:$D$182="gb"),0),MATCH(1,(Price!$L$3:$AM$3=H$3)*(Price!$L$4:$AM$4=H$4),0))} -> 0 | I47: {=INDEX(Price!$L$11:$AM$182,MATCH(1,(Price!$A$11:$A$182=$A47)*(Price!$B$11:$B$182=$B47)*(Price!$D$11:$D$182="gb"),0),MATCH(1,(Price!$L$3:$AM$3=I$3)*(Price!$L$4:$AM$4=I$4),0))} -> 0 | J47: {=INDEX(Price!$L$11:$AM$182,MATCH(1,(Price!$A$11:$A$182=$A47)*(Price!$B$11:$B$182=$B47)*(Price!$D$11:$D$182="gb"),0),MATCH(1,(Price!$L$3:$AM$3=J$3)*(Price!$L$4:$AM$4=J$4),0))} -> 0 | K47: {=INDEX(Price!$L$11:$AM$182,MATCH(1,(Price!$A$11:$A$182=$A47)*(Price!$B$11:$B$182=$B47)*(Price!$D$11:$D$182="gb"),0),MATCH(1,(Price!$L$3:$AM$3=K$3)*(Price!$L$4:$AM$4=K$4),0))} -> 0 | L47: {=INDEX(Price!$L$11:$AM$182,MATCH(1,(Price!$A$11:$A$182=$A47)*(Price!$B$11:$B$182=$B47)*(Price!$D$11:$D$182="gb"),0),MATCH(1,(Price!$L$3:$AM$3=L$3)*(Price!$L$4:$AM$4=L$4),0))} -> 0 | M47: {=INDEX(Price!$L$11:$AM$182,MATCH(1,(Price!$A$11:$A$182=$A47)*(Price!$B$11:$B$182=$B47)*(Price!$D$11:$D$182="gb"),0),MATCH(1,(Price!$L$3:$AM$3=M$3)*(Price!$L$4:$AM$4=M$4),0))} -> 0 | N47: {=INDEX(Price!$L$11:$AM$182,MATCH(1,(Price!$A$11:$A$182=$A47)*(Price!$B$11:$B$182=$B47)*(Price!$D$11:$D$182="gb"),0),MATCH(1,(Price!$L$3:$AM$3=N$3)*(Price!$L$4:$AM$4=N$4),0))} -> 0 | ... AD47: {=INDEX(Price!$L$11:$AM$182,MATCH(1,(Price!$A$11:$A$182=$A47)*(Price!$B$11:$B$182=$B47)*(Price!$D$11:$D$182="gb"),0),MATCH(1,(Price!$L$3:$AM$3=AD$3)*(Price!$L$4:$AM$4=AD$4),0))} -> 1380
A48: 105263 | B48: 110000481 | C48: GB | D48: 3.14 | F48: Giá bán quy đổi EXW | G48: {=INDEX(Price!$L$11:$AM$182,MATCH(1,(Price!$A$11:$A$182=$A48)*(Price!$B$11:$B$182=$B48)*(Price!$D$11:$D$182="exw"),0),MATCH(1,(Price!$L$3:$AM$3=G$3)*(Price!$L$4:$AM$4=G$4),0))} -> 0 | H48: {=INDEX(Price!$L$11:$AM$182,MATCH(1,(Price!$A$11:$A$182=$A48)*(Price!$B$11:$B$182=$B48)*(Price!$D$11:$D$182="exw"),0),MATCH(1,(Price!$L$3:$AM$3=H$3)*(Price!$L$4:$AM$4=H$4),0))} -> 0 | I48: {=INDEX(Price!$L$11:$AM$182,MATCH(1,(Price!$A$11:$A$182=$A48)*(Price!$B$11:$B$182=$B48)*(Price!$D$11:$D$182="exw"),0),MATCH(1,(Price!$L$3:$AM$3=I$3)*(Price!$L$4:$AM$4=I$4),0))} -> 0 | J48: {=INDEX(Price!$L$11:$AM$182,MATCH(1,(Price!$A$11:$A$182=$A48)*(Price!$B$11:$B$182=$B48)*(Price!$D$11:$D$182="exw"),0),MATCH(1,(Price!$L$3:$AM$3=J$3)*(Price!$L$4:$AM$4=J$4),0))} -> 0 | K48: {=INDEX(Price!$L$11:$AM$182,MATCH(1,(Price!$A$11:$A$182=$A48)*(Price!$B$11:$B$182=$B48)*(Price!$D$11:$D$182="exw"),0),MATCH(1,(Price!$L$3:$AM$3=K$3)*(Price!$L$4:$AM$4=K$4),0))} -> 0 | L48: {=INDEX(Price!$L$11:$AM$182,MATCH(1,(Price!$A$11:$A$182=$A48)*(Price!$B$11:$B$182=$B48)*(Price!$D$11:$D$182="exw"),0),MATCH(1,(Price!$L$3:$AM$3=L$3)*(Price!$L$4:$AM$4=L$4),0))} -> 0 | M48: {=INDEX(Price!$L$11:$AM$182,MATCH(1,(Price!$A$11:$A$182=$A48)*(Price!$B$11:$B$182=$B48)*(Price!$D$11:$D$182="exw"),0),MATCH(1,(Price!$L$3:$AM$3=M$3)*(Price!$L$4:$AM$4=M$4),0))} -> 0 | N48: {=INDEX(Price!$L$11:$AM$182,MATCH(1,(Price!$A$11:$A$182=$A48)*(Price!$B$11:$B$182=$B48)*(Price!$D$11:$D$182="exw"),0),MATCH(1,(Price!$L$3:$AM$3=N$3)*(Price!$L$4:$AM$4=N$4),0))} -> 0 | ... AD48: {=INDEX(Price!$L$11:$AM$182,MATCH(1,(Price!$A$11:$A$182=$A48)*(Price!$B$11:$B$182=$B48)*(Price!$D$11:$D$182="exw"),0),MATCH(1,(Price!$L$3:$AM$3=AD$3)*(Price!$L$4:$AM$4=AD$4),0))} -> 1368.04
A49: 105263 | B49: 110000481 | C49: HDPEVirgin | D49: 3.15 | F49: Giá chính phẩm | S49: {=SUMPRODUCT(General_Data*(Code_General_Data=$C49)*(Year=S$3)*(Month=S$4))} -> 940 | T49: {=SUMPRODUCT(General_Data*(Code_General_Data=$C49)*(Year=T$3)*(Month=T$4))} -> 918 | U49: {=SUMPRODUCT(General_Data*(Code_General_Data=$C49)*(Year=U$3)*(Month=U$4))} -> 896 | V49: {=SUMPRODUCT(General_Data*(Code_General_Data=$C49)*(Year=V$3)*(Month=V$4))} -> 891.5 | W49: {=SUMPRODUCT(General_Data*(Code_General_Data=$C49)*(Year=W$3)*(Month=W$4))} -> 864 | X49: {=SUMPRODUCT(General_Data*(Code_General_Data=$C49)*(Year=X$3)*(Month=X$4))} -> 833 | Y49: {=SUMPRODUCT(General_Data*(Code_General_Data=$C49)*(Year=Y$3)*(Month=Y$4))} -> 833 | Z49: {=SUMPRODUCT(General_Data*(Code_General_Data=$C49)*(Year=Z$3)*(Month=Z$4))} -> 815 | ... AD49: {=SUMPRODUCT(General_Data*(Code_General_Data=$C49)*(Year=AD$3)*(Month=AD$4))} -> 805
A50: 105263 | B50: 110000481 | D50: 3.16 | F50: Chênh lệch giữa R sv Virgin | S50: =IF(S47*S48*S49<>0,S48-S49,0) -> 448.04 | T50: =IF(T47*T48*T49<>0,T48-T49,0) -> 470.04 | U50: =IF(U47*U48*U49<>0,U48-U49,0) -> 492.04 | V50: =IF(V47*V48*V49<>0,V48-V49,0) -> 446.54 | W50: =IF(W47*W48*W49<>0,W48-W49,0) -> 474.04 | X50: =IF(X47*X48*X49<>0,X48-X49,0) -> 505.04 | Y50: =IF(Y47*Y48*Y49<>0,Y48-Y49,0) -> 535.04 | Z50: =IF(Z47*Z48*Z49<>0,Z48-Z49,0) -> 553.04 | ... AD50: =IF(AD47*AD48*AD49<>0,AD48-AD49,0) -> 563.04
A51: 105263 | B51: 110000481 | D51: 3.17 | F51: % +/- | S51: =IFERROR(S50/S49,0) -> 0.4766383 | T51: =IFERROR(T50/T49,0) -> 0.51202614 | U51: =IFERROR(U50/U49,0) -> 0.54915179 | V51: =IFERROR(V50/V49,0) -> 0.50088615 | W51: =IFERROR(W50/W49,0) -> 0.54865741 | X51: =IFERROR(X50/X49,0) -> 0.60629052 | Y51: =IFERROR(Y50/Y49,0) -> 0.64230492 | Z51: =IFERROR(Z50/Z49,0) -> 0.67857669 | ... AD51: =IFERROR(AD50/AD49,0) -> 0.69942857
A52: 105263 | B52: 110000481 | C52: 110000481 | D52: 3.18 | F52: Giá duyệt tháng | S52: {=SUMPRODUCT(General_Data*(Code_General_Data=$C52)*(Year=S$3)*(Month=S$4))} -> 1400 | T52: {=SUMPRODUCT(General_Data*(Code_General_Data=$C52)*(Year=T$3)*(Month=T$4))} -> 1400 | U52: {=SUMPRODUCT(General_Data*(Code_General_Data=$C52)*(Year=U$3)*(Month=U$4))} -> 1350 | V52: {=SUMPRODUCT(General_Data*(Code_General_Data=$C52)*(Year=V$3)*(Month=V$4))} -> 1350 | W52: {=SUMPRODUCT(General_Data*(Code_General_Data=$C52)*(Year=W$3)*(Month=W$4))} -> 1350 | X52: {=SUMPRODUCT(General_Data*(Code_General_Data=$C52)*(Year=X$3)*(Month=X$4))} -> 1350 | Y52: {=SUMPRODUCT(General_Data*(Code_General_Data=$C52)*(Year=Y$3)*(Month=Y$4))} -> 1350 | Z52: {=SUMPRODUCT(General_Data*(Code_General_Data=$C52)*(Year=Z$3)*(Month=Z$4))} -> 1330 | ... AD52: {=SUMPRODUCT(General_Data*(Code_General_Data=$C52)*(Year=AD$3)*(Month=AD$4))} -> 1300
A53: 105263
A54: 105263 | B54: RHDPETHOI-MAU | D54: 3.19 | F54: rHDPE thổi màu - khử mùi
A55: 105263 | B55: RHDPETHOI-MAU | D55: 3.2 | F55: Giá bán - DDP | G55: {=INDEX(Price!$L$11:$AM$182,MATCH(1,(Price!$A$11:$A$182=$A55)*(Price!$B$11:$B$182=$B55)*(Price!$D$11:$D$182="gb"),0),MATCH(1,(Price!$L$3:$AM$3=G$3)*(Price!$L$4:$AM$4=G$4),0))} -> 1450 | H55: {=INDEX(Price!$L$11:$AM$182,MATCH(1,(Price!$A$11:$A$182=$A55)*(Price!$B$11:$B$182=$B55)*(Price!$D$11:$D$182="gb"),0),MATCH(1,(Price!$L$3:$AM$3=H$3)*(Price!$L$4:$AM$4=H$4),0))} -> 1450 | I55: {=INDEX(Price!$L$11:$AM$182,MATCH(1,(Price!$A$11:$A$182=$A55)*(Price!$B$11:$B$182=$B55)*(Price!$D$11:$D$182="gb"),0),MATCH(1,(Price!$L$3:$AM$3=I$3)*(Price!$L$4:$AM$4=I$4),0))} -> 1450 | J55: {=INDEX(Price!$L$11:$AM$182,MATCH(1,(Price!$A$11:$A$182=$A55)*(Price!$B$11:$B$182=$B55)*(Price!$D$11:$D$182="gb"),0),MATCH(1,(Price!$L$3:$AM$3=J$3)*(Price!$L$4:$AM$4=J$4),0))} -> 1380 | K55: {=INDEX(Price!$L$11:$AM$182,MATCH(1,(Price!$A$11:$A$182=$A55)*(Price!$B$11:$B$182=$B55)*(Price!$D$11:$D$182="gb"),0),MATCH(1,(Price!$L$3:$AM$3=K$3)*(Price!$L$4:$AM$4=K$4),0))} -> 1380 | L55: {=INDEX(Price!$L$11:$AM$182,MATCH(1,(Price!$A$11:$A$182=$A55)*(Price!$B$11:$B$182=$B55)*(Price!$D$11:$D$182="gb"),0),MATCH(1,(Price!$L$3:$AM$3=L$3)*(Price!$L$4:$AM$4=L$4),0))} -> 1380 | M55: {=INDEX(Price!$L$11:$AM$182,MATCH(1,(Price!$A$11:$A$182=$A55)*(Price!$B$11:$B$182=$B55)*(Price!$D$11:$D$182="gb"),0),MATCH(1,(Price!$L$3:$AM$3=M$3)*(Price!$L$4:$AM$4=M$4),0))} -> 1380 | N55: {=INDEX(Price!$L$11:$AM$182,MATCH(1,(Price!$A$11:$A$182=$A55)*(Price!$B$11:$B$182=$B55)*(Price!$D$11:$D$182="gb"),0),MATCH(1,(Price!$L$3:$AM$3=N$3)*(Price!$L$4:$AM$4=N$4),0))} -> 1380 | ... AD55: {=INDEX(Price!$L$11:$AM$182,MATCH(1,(Price!$A$11:$A$182=$A55)*(Price!$B$11:$B$182=$B55)*(Price!$D$11:$D$182="gb"),0),MATCH(1,(Price!$L$3:$AM$3=AD$3)*(Price!$L$4:$AM$4=AD$4),0))} -> 1330
A56: 105263 | B56: RHDPETHOI-MAU | C56: GB | D56: 3.21 | F56: Giá bán quy đổi EXW | G56: {=INDEX(Price!$L$11:$AM$182,MATCH(1,(Price!$A$11:$A$182=$A56)*(Price!$B$11:$B$182=$B56)*(Price!$D$11:$D$182="exw"),0),MATCH(1,(Price!$L$3:$AM$3=G$3)*(Price!$L$4:$AM$4=G$4),0))} -> 1437.7959 | H56: {=INDEX(Price!$L$11:$AM$182,MATCH(1,(Price!$A$11:$A$182=$A56)*(Price!$B$11:$B$182=$B56)*(Price!$D$11:$D$182="exw"),0),MATCH(1,(Price!$L$3:$AM$3=H$3)*(Price!$L$4:$AM$4=H$4),0))} -> 1437.7959 | I56: {=INDEX(Price!$L$11:$AM$182,MATCH(1,(Price!$A$11:$A$182=$A56)*(Price!$B$11:$B$182=$B56)*(Price!$D$11:$D$182="exw"),0),MATCH(1,(Price!$L$3:$AM$3=I$3)*(Price!$L$4:$AM$4=I$4),0))} -> 1437.7959 | J56: {=INDEX(Price!$L$11:$AM$182,MATCH(1,(Price!$A$11:$A$182=$A56)*(Price!$B$11:$B$182=$B56)*(Price!$D$11:$D$182="exw"),0),MATCH(1,(Price!$L$3:$AM$3=J$3)*(Price!$L$4:$AM$4=J$4),0))} -> 1367.7959 | K56: {=INDEX(Price!$L$11:$AM$182,MATCH(1,(Price!$A$11:$A$182=$A56)*(Price!$B$11:$B$182=$B56)*(Price!$D$11:$D$182="exw"),0),MATCH(1,(Price!$L$3:$AM$3=K$3)*(Price!$L$4:$AM$4=K$4),0))} -> 1367.7959 | L56: {=INDEX(Price!$L$11:$AM$182,MATCH(1,(Price!$A$11:$A$182=$A56)*(Price!$B$11:$B$182=$B56)*(Price!$D$11:$D$182="exw"),0),MATCH(1,(Price!$L$3:$AM$3=L$3)*(Price!$L$4:$AM$4=L$4),0))} -> 1367.7959 | M56: {=INDEX(Price!$L$11:$AM$182,MATCH(1,(Price!$A$11:$A$182=$A56)*(Price!$B$11:$B$182=$B56)*(Price!$D$11:$D$182="exw"),0),MATCH(1,(Price!$L$3:$AM$3=M$3)*(Price!$L$4:$AM$4=M$4),0))} -> 1368.04 | N56: {=INDEX(Price!$L$11:$AM$182,MATCH(1,(Price!$A$11:$A$182=$A56)*(Price!$B$11:$B$182=$B56)*(Price!$D$11:$D$182="exw"),0),MATCH(1,(Price!$L$3:$AM$3=N$3)*(Price!$L$4:$AM$4=N$4),0))} -> 1368.04 | ... AD56: {=INDEX(Price!$L$11:$AM$182,MATCH(1,(Price!$A$11:$A$182=$A56)*(Price!$B$11:$B$182=$B56)*(Price!$D$11:$D$182="exw"),0),MATCH(1,(Price!$L$3:$AM$3=AD$3)*(Price!$L$4:$AM$4=AD$4),0))} -> 1318.04
A57: 105263 | B57: RHDPETHOI-MAU | C57: HDPEVirgin | D57: 3.22 | F57: Giá chính phẩm | G57: {=SUMPRODUCT(General_Data*(Code_General_Data=$C57)*(Year=G$3)*(Month=G$4))} -> 940 | H57: {=SUMPRODUCT(General_Data*(Code_General_Data=$C57)*(Year=H$3)*(Month=H$4))} -> 993.33333 | I57: {=SUMPRODUCT(General_Data*(Code_General_Data=$C57)*(Year=I$3)*(Month=I$4))} -> 985 | J57: {=SUMPRODUCT(General_Data*(Code_General_Data=$C57)*(Year=J$3)*(Month=J$4))} -> 962.5 | K57: {=SUMPRODUCT(General_Data*(Code_General_Data=$C57)*(Year=K$3)*(Month=K$4))} -> 982 | L57: {=SUMPRODUCT(General_Data*(Code_General_Data=$C57)*(Year=L$3)*(Month=L$4))} -> 1000 | M57: {=SUMPRODUCT(General_Data*(Code_General_Data=$C57)*(Year=M$3)*(Month=M$4))} -> 1000 | N57: {=SUMPRODUCT(General_Data*(Code_General_Data=$C57)*(Year=N$3)*(Month=N$4))} -> 984 | ... AD57: {=SUMPRODUCT(General_Data*(Code_General_Data=$C57)*(Year=AD$3)*(Month=AD$4))} -> 805
A58: 105263 | B58: RHDPETHOI-MAU | D58: 3.23 | F58: Chênh lệch giữa R sv Virgin | G58: =IF(G55*G56*G57<>0,G56-G57,0) -> 497.79592 | H58: =IF(H55*H56*H57<>0,H56-H57,0) -> 444.46259 | I58: =IF(I55*I56*I57<>0,I56-I57,0) -> 452.79592 | J58: =IF(J55*J56*J57<>0,J56-J57,0) -> 405.29592 | K58: =IF(K55*K56*K57<>0,K56-K57,0) -> 385.79592 | L58: =IF(L55*L56*L57<>0,L56-L57,0) -> 367.79592 | M58: =IF(M55*M56*M57<>0,M56-M57,0) -> 368.04 | N58: =IF(N55*N56*N57<>0,N56-N57,0) -> 384.04 | ... AD58: =IF(AD55*AD56*AD57<>0,AD56-AD57,0) -> 513.04
A59: 105263 | B59: RHDPETHOI-MAU | D59: 3.24 | F59: % +/- | G59: =IFERROR(G58/G57,0) -> 0.52957013 | H59: =IFERROR(H58/H57,0) -> 0.44744556 | I59: =IFERROR(I58/I57,0) -> 0.45969129 | J59: =IFERROR(J58/J57,0) -> 0.42108667 | K59: =IFERROR(K58/K57,0) -> 0.39286753 | L59: =IFERROR(L58/L57,0) -> 0.36779592 | M59: =IFERROR(M58/M57,0) -> 0.36804 | N59: =IFERROR(N58/N57,0) -> 0.39028455 | ... AD59: =IFERROR(AD58/AD57,0) -> 0.63731677
A60: 105263 | B60: RHDPETHOI-MAU | C60: RHDPETHOI-MAU | D60: 3.25 | F60: Giá duyệt tháng | G60: {=SUMPRODUCT(General_Data*(Code_General_Data=$C60)*(Year=G$3)*(Month=G$4))} -> 1350 | H60: {=SUMPRODUCT(General_Data*(Code_General_Data=$C60)*(Year=H$3)*(Month=H$4))} -> 1350 | I60: {=SUMPRODUCT(General_Data*(Code_General_Data=$C60)*(Year=I$3)*(Month=I$4))} -> 1350 | J60: {=SUMPRODUCT(General_Data*(Code_General_Data=$C60)*(Year=J$3)*(Month=J$4))} -> 1350 | K60: {=SUMPRODUCT(General_Data*(Code_General_Data=$C60)*(Year=K$3)*(Month=K$4))} -> 1350 | L60: {=SUMPRODUCT(General_Data*(Code_General_Data=$C60)*(Year=L$3)*(Month=L$4))} -> 1350 | M60: {=SUMPRODUCT(General_Data*(Code_General_Data=$C60)*(Year=M$3)*(Month=M$4))} -> 1350 | N60: {=SUMPRODUCT(General_Data*(Code_General_Data=$C60)*(Year=N$3)*(Month=N$4))} -> 1350 | ... AD60: {=SUMPRODUCT(General_Data*(Code_General_Data=$C60)*(Year=AD$3)*(Month=AD$4))} -> 1250
A62: 105194 | D62: 4 | E62: SUNTORY VIET NAM
A63: 105194 | B63: 110000332 | F63: iSS1084G
A64: 105194 | B64: 110000332 | D64: 4.1 | F64: Giá bán-DDP | G64: {=INDEX(Price!$L$11:$AM$182,MATCH(1,(Price!$A$11:$A$182=$A64)*(Price!$B$11:$B$182=$B64)*(Price!$D$11:$D$182="gb"),0),MATCH(1,(Price!$L$3:$AM$3=G$3)*(Price!$L$4:$AM$4=G$4),0))} -> 1366.5 | H64: {=INDEX(Price!$L$11:$AM$182,MATCH(1,(Price!$A$11:$A$182=$A64)*(Price!$B$11:$B$182=$B64)*(Price!$D$11:$D$182="gb"),0),MATCH(1,(Price!$L$3:$AM$3=H$3)*(Price!$L$4:$AM$4=H$4),0))} -> 1374 | I64: {=INDEX(Price!$L$11:$AM$182,MATCH(1,(Price!$A$11:$A$182=$A64)*(Price!$B$11:$B$182=$B64)*(Price!$D$11:$D$182="gb"),0),MATCH(1,(Price!$L$3:$AM$3=I$3)*(Price!$L$4:$AM$4=I$4),0))} -> 1386.5 | J64: {=INDEX(Price!$L$11:$AM$182,MATCH(1,(Price!$A$11:$A$182=$A64)*(Price!$B$11:$B$182=$B64)*(Price!$D$11:$D$182="gb"),0),MATCH(1,(Price!$L$3:$AM$3=J$3)*(Price!$L$4:$AM$4=J$4),0))} -> 1389 | K64: {=INDEX(Price!$L$11:$AM$182,MATCH(1,(Price!$A$11:$A$182=$A64)*(Price!$B$11:$B$182=$B64)*(Price!$D$11:$D$182="gb"),0),MATCH(1,(Price!$L$3:$AM$3=K$3)*(Price!$L$4:$AM$4=K$4),0))} -> 1393 | L64: {=INDEX(Price!$L$11:$AM$182,MATCH(1,(Price!$A$11:$A$182=$A64)*(Price!$B$11:$B$182=$B64)*(Price!$D$11:$D$182="gb"),0),MATCH(1,(Price!$L$3:$AM$3=L$3)*(Price!$L$4:$AM$4=L$4),0))} -> 1408 | M64: {=INDEX(Price!$L$11:$AM$182,MATCH(1,(Price!$A$11:$A$182=$A64)*(Price!$B$11:$B$182=$B64)*(Price!$D$11:$D$182="gb"),0),MATCH(1,(Price!$L$3:$AM$3=M$3)*(Price!$L$4:$AM$4=M$4),0))} -> 1424 | N64: {=INDEX(Price!$L$11:$AM$182,MATCH(1,(Price!$A$11:$A$182=$A64)*(Price!$B$11:$B$182=$B64)*(Price!$D$11:$D$182="gb"),0),MATCH(1,(Price!$L$3:$AM$3=N$3)*(Price!$L$4:$AM$4=N$4),0))} -> 1435 | ... AD64: {=INDEX(Price!$L$11:$AM$182,MATCH(1,(Price!$A$11:$A$182=$A64)*(Price!$B$11:$B$182=$B64)*(Price!$D$11:$D$182="gb"),0),MATCH(1,(Price!$L$3:$AM$3=AD$3)*(Price!$L$4:$AM$4=AD$4),0))} -> 1293.1562
A65: 105194 | B65: 110000332 | C65: GB | D65: 4.2 | F65: Giá bán quy đổi EXW | G65: {=INDEX(Price!$L$11:$AM$182,MATCH(1,(Price!$A$11:$A$182=$A65)*(Price!$B$11:$B$182=$B65)*(Price!$D$11:$D$182="exw"),0),MATCH(1,(Price!$L$3:$AM$3=G$3)*(Price!$L$4:$AM$4=G$4),0))} -> 1340 | H65: {=INDEX(Price!$L$11:$AM$182,MATCH(1,(Price!$A$11:$A$182=$A65)*(Price!$B$11:$B$182=$B65)*(Price!$D$11:$D$182="exw"),0),MATCH(1,(Price!$L$3:$AM$3=H$3)*(Price!$L$4:$AM$4=H$4),0))} -> 1347.5 | I65: {=INDEX(Price!$L$11:$AM$182,MATCH(1,(Price!$A$11:$A$182=$A65)*(Price!$B$11:$B$182=$B65)*(Price!$D$11:$D$182="exw"),0),MATCH(1,(Price!$L$3:$AM$3=I$3)*(Price!$L$4:$AM$4=I$4),0))} -> 1360 | J65: {=INDEX(Price!$L$11:$AM$182,MATCH(1,(Price!$A$11:$A$182=$A65)*(Price!$B$11:$B$182=$B65)*(Price!$D$11:$D$182="exw"),0),MATCH(1,(Price!$L$3:$AM$3=J$3)*(Price!$L$4:$AM$4=J$4),0))} -> 1362.5 | K65: {=INDEX(Price!$L$11:$AM$182,MATCH(1,(Price!$A$11:$A$182=$A65)*(Price!$B$11:$B$182=$B65)*(Price!$D$11:$D$182="exw"),0),MATCH(1,(Price!$L$3:$AM$3=K$3)*(Price!$L$4:$AM$4=K$4),0))} -> 1366.5 | L65: {=INDEX(Price!$L$11:$AM$182,MATCH(1,(Price!$A$11:$A$182=$A65)*(Price!$B$11:$B$182=$B65)*(Price!$D$11:$D$182="exw"),0),MATCH(1,(Price!$L$3:$AM$3=L$3)*(Price!$L$4:$AM$4=L$4),0))} -> 1381.5 | M65: {=INDEX(Price!$L$11:$AM$182,MATCH(1,(Price!$A$11:$A$182=$A65)*(Price!$B$11:$B$182=$B65)*(Price!$D$11:$D$182="exw"),0),MATCH(1,(Price!$L$3:$AM$3=M$3)*(Price!$L$4:$AM$4=M$4),0))} -> 1397.5 | N65: {=INDEX(Price!$L$11:$AM$182,MATCH(1,(Price!$A$11:$A$182=$A65)*(Price!$B$11:$B$182=$B65)*(Price!$D$11:$D$182="exw"),0),MATCH(1,(Price!$L$3:$AM$3=N$3)*(Price!$L$4:$AM$4=N$4),0))} -> 1408.5 | ... AD65: {=INDEX(Price!$L$11:$AM$182,MATCH(1,(Price!$A$11:$A$182=$A65)*(Price!$B$11:$B$182=$B65)*(Price!$D$11:$D$182="exw"),0),MATCH(1,(Price!$L$3:$AM$3=AD$3)*(Price!$L$4:$AM$4=AD$4),0))} -> 1266.6562
A66: 105194 | B66: 110000332 | C66: PETVirgin | D66: 4.3 | F66: Giá chính phẩm | G66: {=SUMPRODUCT(General_Data*(Code_General_Data=$C66)*(Year=G$3)*(Month=G$4))} -> 930 | H66: {=SUMPRODUCT(General_Data*(Code_General_Data=$C66)*(Year=H$3)*(Month=H$4))} -> 943.33333 | I66: {=SUMPRODUCT(General_Data*(Code_General_Data=$C66)*(Year=I$3)*(Month=I$4))} -> 940 | J66: {=SUMPRODUCT(General_Data*(Code_General_Data=$C66)*(Year=J$3)*(Month=J$4))} -> 940 | K66: {=SUMPRODUCT(General_Data*(Code_General_Data=$C66)*(Year=K$3)*(Month=K$4))} -> 942 | L66: {=SUMPRODUCT(General_Data*(Code_General_Data=$C66)*(Year=L$3)*(Month=L$4))} -> 950 | M66: {=SUMPRODUCT(General_Data*(Code_General_Data=$C66)*(Year=M$3)*(Month=M$4))} -> 947.5 | N66: {=SUMPRODUCT(General_Data*(Code_General_Data=$C66)*(Year=N$3)*(Month=N$4))} -> 930 | ... AD66: {=SUMPRODUCT(General_Data*(Code_General_Data=$C66)*(Year=AD$3)*(Month=AD$4))} -> 770
A67: 105194 | B67: 110000332 | D67: 4.4 | F67: Chênh lệch giữa R sv Virgin | G67: =IF(G64*G65*G66<>0,G65-G66,0) -> 410 | H67: =IF(H64*H65*H66<>0,H65-H66,0) -> 404.16667 | I67: =IF(I64*I65*I66<>0,I65-I66,0) -> 420 | J67: =IF(J64*J65*J66<>0,J65-J66,0) -> 422.5 | K67: =IF(K64*K65*K66<>0,K65-K66,0) -> 424.5 | L67: =IF(L64*L65*L66<>0,L65-L66,0) -> 431.5 | M67: =IF(M64*M65*M66<>0,M65-M66,0) -> 450 | N67: =IF(N64*N65*N66<>0,N65-N66,0) -> 478.5 | ... AD67: =IF(AD64*AD65*AD66<>0,AD65-AD66,0) -> 496.65625
A68: 105194 | B68: 110000332 | D68: 4.5 | F68: % +/- | G68: =IFERROR(G67/G66,0) -> 0.44086022 | H68: =IFERROR(H67/H66,0) -> 0.42844523 | I68: =IFERROR(I67/I66,0) -> 0.44680851 | J68: =IFERROR(J67/J66,0) -> 0.44946809 | K68: =IFERROR(K67/K66,0) -> 0.45063694 | L68: =IFERROR(L67/L66,0) -> 0.45421053 | M68: =IFERROR(M67/M66,0) -> 0.47493404 | N68: =IFERROR(N67/N66,0) -> 0.51451613 | ... AD68: =IFERROR(AD67/AD66,0) -> 0.64500812
A69: 105194 | B69: 110000332 | C69: 110000332 | D69: 4.6 | F69: Giá duyệt tháng | G69: {=SUMPRODUCT(General_Data*(Code_General_Data=$C69)*(Year=G$3)*(Month=G$4))} -> 1340 | H69: {=SUMPRODUCT(General_Data*(Code_General_Data=$C69)*(Year=H$3)*(Month=H$4))} -> 1340 | I69: {=SUMPRODUCT(General_Data*(Code_General_Data=$C69)*(Year=I$3)*(Month=I$4))} -> 1340 | J69: {=SUMPRODUCT(General_Data*(Code_General_Data=$C69)*(Year=J$3)*(Month=J$4))} -> 1340 | K69: {=SUMPRODUCT(General_Data*(Code_General_Data=$C69)*(Year=K$3)*(Month=K$4))} -> 1390 | L69: {=SUMPRODUCT(General_Data*(Code_General_Data=$C69)*(Year=L$3)*(Month=L$4))} -> 1390 | M69: {=SUMPRODUCT(General_Data*(Code_General_Data=$C69)*(Year=M$3)*(Month=M$4))} -> 1390 | N69: {=SUMPRODUCT(General_Data*(Code_General_Data=$C69)*(Year=N$3)*(Month=N$4))} -> 1390 | ... AD69: {=SUMPRODUCT(General_Data*(Code_General_Data=$C69)*(Year=AD$3)*(Month=AD$4))} -> 1290
A70: 105194 | Z70: =Z69-Z65 -> 16.1
A71: 105194 | B71: 110000355 | F71: iSS01G
A72: 105194 | B72: 110000355 | D72: 4.7 | F72: Giá bán-DDP | G72: {=INDEX(Price!$L$11:$AM$182,MATCH(1,(Price!$A$11:$A$182=$A72)*(Price!$B$11:$B$182=$B72)*(Price!$D$11:$D$182="gb"),0),MATCH(1,(Price!$L$3:$AM$3=G$3)*(Price!$L$4:$AM$4=G$4),0))} -> 1346.5 | H72: {=INDEX(Price!$L$11:$AM$182,MATCH(1,(Price!$A$11:$A$182=$A72)*(Price!$B$11:$B$182=$B72)*(Price!$D$11:$D$182="gb"),0),MATCH(1,(Price!$L$3:$AM$3=H$3)*(Price!$L$4:$AM$4=H$4),0))} -> 1354 | I72: {=INDEX(Price!$L$11:$AM$182,MATCH(1,(Price!$A$11:$A$182=$A72)*(Price!$B$11:$B$182=$B72)*(Price!$D$11:$D$182="gb"),0),MATCH(1,(Price!$L$3:$AM$3=I$3)*(Price!$L$4:$AM$4=I$4),0))} -> 1366.5 | J72: {=INDEX(Price!$L$11:$AM$182,MATCH(1,(Price!$A$11:$A$182=$A72)*(Price!$B$11:$B$182=$B72)*(Price!$D$11:$D$182="gb"),0),MATCH(1,(Price!$L$3:$AM$3=J$3)*(Price!$L$4:$AM$4=J$4),0))} -> 1369 | K72: {=INDEX(Price!$L$11:$AM$182,MATCH(1,(Price!$A$11:$A$182=$A72)*(Price!$B$11:$B$182=$B72)*(Price!$D$11:$D$182="gb"),0),MATCH(1,(Price!$L$3:$AM$3=K$3)*(Price!$L$4:$AM$4=K$4),0))} -> 1373 | L72: {=INDEX(Price!$L$11:$AM$182,MATCH(1,(Price!$A$11:$A$182=$A72)*(Price!$B$11:$B$182=$B72)*(Price!$D$11:$D$182="gb"),0),MATCH(1,(Price!$L$3:$AM$3=L$3)*(Price!$L$4:$AM$4=L$4),0))} -> 1388 | M72: {=INDEX(Price!$L$11:$AM$182,MATCH(1,(Price!$A$11:$A$182=$A72)*(Price!$B$11:$B$182=$B72)*(Price!$D$11:$D$182="gb"),0),MATCH(1,(Price!$L$3:$AM$3=M$3)*(Price!$L$4:$AM$4=M$4),0))} -> 1404 | N72: {=INDEX(Price!$L$11:$AM$182,MATCH(1,(Price!$A$11:$A$182=$A72)*(Price!$B$11:$B$182=$B72)*(Price!$D$11:$D$182="gb"),0),MATCH(1,(Price!$L$3:$AM$3=N$3)*(Price!$L$4:$AM$4=N$4),0))} -> 1415 | ... AD72: {=INDEX(Price!$L$11:$AM$182,MATCH(1,(Price!$A$11:$A$182=$A72)*(Price!$B$11:$B$182=$B72)*(Price!$D$11:$D$182="gb"),0),MATCH(1,(Price!$L$3:$AM$3=AD$3)*(Price!$L$4:$AM$4=AD$4),0))} -> 1293.1562
A73: 105194 | B73: 110000355 | C73: GB | D73: 4.8 | F73: Giá bán quy đổi EXW | G73: {=INDEX(Price!$L$11:$AM$182,MATCH(1,(Price!$A$11:$A$182=$A73)*(Price!$B$11:$B$182=$B73)*(Price!$D$11:$D$182="exw"),0),MATCH(1,(Price!$L$3:$AM$3=G$3)*(Price!$L$4:$AM$4=G$4),0))} -> 1320 | H73: {=INDEX(Price!$L$11:$AM$182,MATCH(1,(Price!$A$11:$A$182=$A73)*(Price!$B$11:$B$182=$B73)*(Price!$D$11:$D$182="exw"),0),MATCH(1,(Price!$L$3:$AM$3=H$3)*(Price!$L$4:$AM$4=H$4),0))} -> 1327.5 | I73: {=INDEX(Price!$L$11:$AM$182,MATCH(1,(Price!$A$11:$A$182=$A73)*(Price!$B$11:$B$182=$B73)*(Price!$D$11:$D$182="exw"),0),MATCH(1,(Price!$L$3:$AM$3=I$3)*(Price!$L$4:$AM$4=I$4),0))} -> 1340 | J73: {=INDEX(Price!$L$11:$AM$182,MATCH(1,(Price!$A$11:$A$182=$A73)*(Price!$B$11:$B$182=$B73)*(Price!$D$11:$D$182="exw"),0),MATCH(1,(Price!$L$3:$AM$3=J$3)*(Price!$L$4:$AM$4=J$4),0))} -> 1342.5 | K73: {=INDEX(Price!$L$11:$AM$182,MATCH(1,(Price!$A$11:$A$182=$A73)*(Price!$B$11:$B$182=$B73)*(Price!$D$11:$D$182="exw"),0),MATCH(1,(Price!$L$3:$AM$3=K$3)*(Price!$L$4:$AM$4=K$4),0))} -> 1346.5 | L73: {=INDEX(Price!$L$11:$AM$182,MATCH(1,(Price!$A$11:$A$182=$A73)*(Price!$B$11:$B$182=$B73)*(Price!$D$11:$D$182="exw"),0),MATCH(1,(Price!$L$3:$AM$3=L$3)*(Price!$L$4:$AM$4=L$4),0))} -> 1361.5 | M73: {=INDEX(Price!$L$11:$AM$182,MATCH(1,(Price!$A$11:$A$182=$A73)*(Price!$B$11:$B$182=$B73)*(Price!$D$11:$D$182="exw"),0),MATCH(1,(Price!$L$3:$AM$3=M$3)*(Price!$L$4:$AM$4=M$4),0))} -> 1377.5 | N73: {=INDEX(Price!$L$11:$AM$182,MATCH(1,(Price!$A$11:$A$182=$A73)*(Price!$B$11:$B$182=$B73)*(Price!$D$11:$D$182="exw"),0),MATCH(1,(Price!$L$3:$AM$3=N$3)*(Price!$L$4:$AM$4=N$4),0))} -> 1388.5 | ... AD73: {=INDEX(Price!$L$11:$AM$182,MATCH(1,(Price!$A$11:$A$182=$A73)*(Price!$B$11:$B$182=$B73)*(Price!$D$11:$D$182="exw"),0),MATCH(1,(Price!$L$3:$AM$3=AD$3)*(Price!$L$4:$AM$4=AD$4),0))} -> 1266.6562
A74: 105194 | B74: 110000355 | C74: PETVirgin | D74: 4.9 | F74: Giá chính phẩm | G74: {=SUMPRODUCT(General_Data*(Code_General_Data=$C74)*(Year=G$3)*(Month=G$4))} -> 930 | H74: {=SUMPRODUCT(General_Data*(Code_General_Data=$C74)*(Year=H$3)*(Month=H$4))} -> 943.33333 | I74: {=SUMPRODUCT(General_Data*(Code_General_Data=$C74)*(Year=I$3)*(Month=I$4))} -> 940 | J74: {=SUMPRODUCT(General_Data*(Code_General_Data=$C74)*(Year=J$3)*(Month=J$4))} -> 940 | K74: {=SUMPRODUCT(General_Data*(Code_General_Data=$C74)*(Year=K$3)*(Month=K$4))} -> 942 | L74: {=SUMPRODUCT(General_Data*(Code_General_Data=$C74)*(Year=L$3)*(Month=L$4))} -> 950 | M74: {=SUMPRODUCT(General_Data*(Code_General_Data=$C74)*(Year=M$3)*(Month=M$4))} -> 947.5 | N74: {=SUMPRODUCT(General_Data*(Code_General_Data=$C74)*(Year=N$3)*(Month=N$4))} -> 930 | ... AD74: {=SUMPRODUCT(General_Data*(Code_General_Data=$C74)*(Year=AD$3)*(Month=AD$4))} -> 770
A75: 105194 | B75: 110000355 | D75: 4.1 | F75: Chênh lệch giữa R sv Virgin | G75: =IF(G72*G73*G74<>0,G73-G74,0) -> 390 | H75: =IF(H72*H73*H74<>0,H73-H74,0) -> 384.16667 | I75: =IF(I72*I73*I74<>0,I73-I74,0) -> 400 | J75: =IF(J72*J73*J74<>0,J73-J74,0) -> 402.5 | K75: =IF(K72*K73*K74<>0,K73-K74,0) -> 404.5 | L75: =IF(L72*L73*L74<>0,L73-L74,0) -> 411.5 | M75: =IF(M72*M73*M74<>0,M73-M74,0) -> 430 | N75: =IF(N72*N73*N74<>0,N73-N74,0) -> 458.5 | ... AD75: =IF(AD72*AD73*AD74<>0,AD73-AD74,0) -> 496.65625
A76: 105194 | B76: 110000355 | D76: 4.11 | F76: % +/- | G76: =IFERROR(G75/G74,0) -> 0.41935484 | H76: =IFERROR(H75/H74,0) -> 0.40724382 | I76: =IFERROR(I75/I74,0) -> 0.42553191 | J76: =IFERROR(J75/J74,0) -> 0.42819149 | K76: =IFERROR(K75/K74,0) -> 0.42940552 | L76: =IFERROR(L75/L74,0) -> 0.43315789 | M76: =IFERROR(M75/M74,0) -> 0.45382586 | N76: =IFERROR(N75/N74,0) -> 0.49301075 | ... AD76: =IFERROR(AD75/AD74,0) -> 0.64500812
A77: 105194 | B77: 110000355 | C77: 110000355 | D77: 4.12 | F77: Giá duyệt tháng | G77: {=SUMPRODUCT(General_Data*(Code_General_Data=$C77)*(Year=G$3)*(Month=G$4))} -> 1280 | H77: {=SUMPRODUCT(General_Data*(Code_General_Data=$C77)*(Year=H$3)*(Month=H$4))} -> 1280 | I77: {=SUMPRODUCT(General_Data*(Code_General_Data=$C77)*(Year=I$3)*(Month=I$4))} -> 1280 | J77: {=SUMPRODUCT(General_Data*(Code_General_Data=$C77)*(Year=J$3)*(Month=J$4))} -> 1280 | K77: {=SUMPRODUCT(General_Data*(Code_General_Data=$C77)*(Year=K$3)*(Month=K$4))} -> 1330 | L77: {=SUMPRODUCT(General_Data*(Code_General_Data=$C77)*(Year=L$3)*(Month=L$4))} -> 1330 | M77: {=SUMPRODUCT(General_Data*(Code_General_Data=$C77)*(Year=M$3)*(Month=M$4))} -> 1330 | N77: {=SUMPRODUCT(General_Data*(Code_General_Data=$C77)*(Year=N$3)*(Month=N$4))} -> 1330 | ... AD77: {=SUMPRODUCT(General_Data*(Code_General_Data=$C77)*(Year=AD$3)*(Month=AD$4))} -> 1230
A79: 104909 | D79: 5 | E79: LAVIE VIET NAM
A80: 104909 | B80: 110000329 | F80: WSS01
A81: 104909 | B81: 110000329 | D81: 5.1 | F81: Giá bán-EXW | G81: {=INDEX(Price!$L$11:$AM$182,MATCH(1,(Price!$A$11:$A$182=$A81)*(Price!$B$11:$B$182=$B81)*(Price!$D$11:$D$182="gb"),0),MATCH(1,(Price!$L$3:$AM$3=G$3)*(Price!$L$4:$AM$4=G$4),0))} -> 1250 | H81: {=INDEX(Price!$L$11:$AM$182,MATCH(1,(Price!$A$11:$A$182=$A81)*(Price!$B$11:$B$182=$B81)*(Price!$D$11:$D$182="gb"),0),MATCH(1,(Price!$L$3:$AM$3=H$3)*(Price!$L$4:$AM$4=H$4),0))} -> 1250 | I81: {=INDEX(Price!$L$11:$AM$182,MATCH(1,(Price!$A$11:$A$182=$A81)*(Price!$B$11:$B$182=$B81)*(Price!$D$11:$D$182="gb"),0),MATCH(1,(Price!$L$3:$AM$3=I$3)*(Price!$L$4:$AM$4=I$4),0))} -> 1250 | J81: {=INDEX(Price!$L$11:$AM$182,MATCH(1,(Price!$A$11:$A$182=$A81)*(Price!$B$11:$B$182=$B81)*(Price!$D$11:$D$182="gb"),0),MATCH(1,(Price!$L$3:$AM$3=J$3)*(Price!$L$4:$AM$4=J$4),0))} -> 1250 | K81: {=INDEX(Price!$L$11:$AM$182,MATCH(1,(Price!$A$11:$A$182=$A81)*(Price!$B$11:$B$182=$B81)*(Price!$D$11:$D$182="gb"),0),MATCH(1,(Price!$L$3:$AM$3=K$3)*(Price!$L$4:$AM$4=K$4),0))} -> 1250 | L81: {=INDEX(Price!$L$11:$AM$182,MATCH(1,(Price!$A$11:$A$182=$A81)*(Price!$B$11:$B$182=$B81)*(Price!$D$11:$D$182="gb"),0),MATCH(1,(Price!$L$3:$AM$3=L$3)*(Price!$L$4:$AM$4=L$4),0))} -> 1250 | M81: {=INDEX(Price!$L$11:$AM$182,MATCH(1,(Price!$A$11:$A$182=$A81)*(Price!$B$11:$B$182=$B81)*(Price!$D$11:$D$182="gb"),0),MATCH(1,(Price!$L$3:$AM$3=M$3)*(Price!$L$4:$AM$4=M$4),0))} -> 1330 | N81: {=INDEX(Price!$L$11:$AM$182,MATCH(1,(Price!$A$11:$A$182=$A81)*(Price!$B$11:$B$182=$B81)*(Price!$D$11:$D$182="gb"),0),MATCH(1,(Price!$L$3:$AM$3=N$3)*(Price!$L$4:$AM$4=N$4),0))} -> 1330 | ... AD81: {=INDEX(Price!$L$11:$AM$182,MATCH(1,(Price!$A$11:$A$182=$A81)*(Price!$B$11:$B$182=$B81)*(Price!$D$11:$D$182="gb"),0),MATCH(1,(Price!$L$3:$AM$3=AD$3)*(Price!$L$4:$AM$4=AD$4),0))} -> 1303.8316
A82: 104909 | B82: 110000329 | C82: GB | D82: 5.2 | F82: Giá bán quy đổi EXW | G82: {=INDEX(Price!$L$11:$AM$182,MATCH(1,(Price!$A$11:$A$182=$A82)*(Price!$B$11:$B$182=$B82)*(Price!$D$11:$D$182="exw"),0),MATCH(1,(Price!$L$3:$AM$3=G$3)*(Price!$L$4:$AM$4=G$4),0))} -> 1250 | H82: {=INDEX(Price!$L$11:$AM$182,MATCH(1,(Price!$A$11:$A$182=$A82)*(Price!$B$11:$B$182=$B82)*(Price!$D$11:$D$182="exw"),0),MATCH(1,(Price!$L$3:$AM$3=H$3)*(Price!$L$4:$AM$4=H$4),0))} -> 1250 | I82: {=INDEX(Price!$L$11:$AM$182,MATCH(1,(Price!$A$11:$A$182=$A82)*(Price!$B$11:$B$182=$B82)*(Price!$D$11:$D$182="exw"),0),MATCH(1,(Price!$L$3:$AM$3=I$3)*(Price!$L$4:$AM$4=I$4),0))} -> 1250 | J82: {=INDEX(Price!$L$11:$AM$182,MATCH(1,(Price!$A$11:$A$182=$A82)*(Price!$B$11:$B$182=$B82)*(Price!$D$11:$D$182="exw"),0),MATCH(1,(Price!$L$3:$AM$3=J$3)*(Price!$L$4:$AM$4=J$4),0))} -> 1250 | K82: {=INDEX(Price!$L$11:$AM$182,MATCH(1,(Price!$A$11:$A$182=$A82)*(Price!$B$11:$B$182=$B82)*(Price!$D$11:$D$182="exw"),0),MATCH(1,(Price!$L$3:$AM$3=K$3)*(Price!$L$4:$AM$4=K$4),0))} -> 1250 | L82: {=INDEX(Price!$L$11:$AM$182,MATCH(1,(Price!$A$11:$A$182=$A82)*(Price!$B$11:$B$182=$B82)*(Price!$D$11:$D$182="exw"),0),MATCH(1,(Price!$L$3:$AM$3=L$3)*(Price!$L$4:$AM$4=L$4),0))} -> 1250 | M82: {=INDEX(Price!$L$11:$AM$182,MATCH(1,(Price!$A$11:$A$182=$A82)*(Price!$B$11:$B$182=$B82)*(Price!$D$11:$D$182="exw"),0),MATCH(1,(Price!$L$3:$AM$3=M$3)*(Price!$L$4:$AM$4=M$4),0))} -> 1330 | N82: {=INDEX(Price!$L$11:$AM$182,MATCH(1,(Price!$A$11:$A$182=$A82)*(Price!$B$11:$B$182=$B82)*(Price!$D$11:$D$182="exw"),0),MATCH(1,(Price!$L$3:$AM$3=N$3)*(Price!$L$4:$AM$4=N$4),0))} -> 1330 | ... AD82: {=INDEX(Price!$L$11:$AM$182,MATCH(1,(Price!$A$11:$A$182=$A82)*(Price!$B$11:$B$182=$B82)*(Price!$D$11:$D$182="exw"),0),MATCH(1,(Price!$L$3:$AM$3=AD$3)*(Price!$L$4:$AM$4=AD$4),0))} -> 1303.8316
A83: 104909 | B83: 110000329 | C83: PETVirgin | D83: 5.3 | F83: Giá chính phẩm | G83: {=SUMPRODUCT(General_Data*(Code_General_Data=$C83)*(Year=G$3)*(Month=G$4))} -> 930 | H83: {=SUMPRODUCT(General_Data*(Code_General_Data=$C83)*(Year=H$3)*(Month=H$4))} -> 943.33333 | I83: {=SUMPRODUCT(General_Data*(Code_General_Data=$C83)*(Year=I$3)*(Month=I$4))} -> 940 | J83: {=SUMPRODUCT(General_Data*(Code_General_Data=$C83)*(Year=J$3)*(Month=J$4))} -> 940 | K83: {=SUMPRODUCT(General_Data*(Code_General_Data=$C83)*(Year=K$3)*(Month=K$4))} -> 942 | L83: {=SUMPRODUCT(General_Data*(Code_General_Data=$C83)*(Year=L$3)*(Month=L$4))} -> 950 | M83: {=SUMPRODUCT(General_Data*(Code_General_Data=$C83)*(Year=M$3)*(Month=M$4))} -> 947.5 | N83: {=SUMPRODUCT(General_Data*(Code_General_Data=$C83)*(Year=N$3)*(Month=N$4))} -> 930 | ... AD83: {=SUMPRODUCT(General_Data*(Code_General_Data=$C83)*(Year=AD$3)*(Month=AD$4))} -> 770
A84: 104909 | B84: 110000329 | D84: 5.4 | F84: Chênh lệch giữa R sv Virgin | G84: =IF(G81*G82*G83<>0,G82-G83,0) -> 320 | H84: =IF(H81*H82*H83<>0,H82-H83,0) -> 306.66667 | I84: =IF(I81*I82*I83<>0,I82-I83,0) -> 310 | J84: =IF(J81*J82*J83<>0,J82-J83,0) -> 310 | K84: =IF(K81*K82*K83<>0,K82-K83,0) -> 308 | L84: =IF(L81*L82*L83<>0,L82-L83,0) -> 300 | M84: =IF(M81*M82*M83<>0,M82-M83,0) -> 382.5 | N84: =IF(N81*N82*N83<>0,N82-N83,0) -> 400 | ... AD84: =IF(AD81*AD82*AD83<>0,AD82-AD83,0) -> 533.83163
A85: 104909 | B85: 110000329 | D85: 5.5 | F85: % +/- | G85: =IFERROR(G84/G83,0) -> 0.34408602 | H85: =IFERROR(H84/H83,0) -> 0.32508834 | I85: =IFERROR(I84/I83,0) -> 0.32978723 | J85: =IFERROR(J84/J83,0) -> 0.32978723 | K85: =IFERROR(K84/K83,0) -> 0.32696391 | L85: =IFERROR(L84/L83,0) -> 0.31578947 | M85: =IFERROR(M84/M83,0) -> 0.40369393 | N85: =IFERROR(N84/N83,0) -> 0.43010753 | ... AD85: =IFERROR(AD84/AD83,0) -> 0.69328783
A86: 104909 | B86: 110000329 | C86: 110000329 | D86: 5.6 | F86: Giá duyệt tháng | G86: {=SUMPRODUCT(General_Data*(Code_General_Data=$C86)*(Year=G$3)*(Month=G$4))} -> 1250 | H86: {=SUMPRODUCT(General_Data*(Code_General_Data=$C86)*(Year=H$3)*(Month=H$4))} -> 1250 | I86: {=SUMPRODUCT(General_Data*(Code_General_Data=$C86)*(Year=I$3)*(Month=I$4))} -> 1250 | J86: {=SUMPRODUCT(General_Data*(Code_General_Data=$C86)*(Year=J$3)*(Month=J$4))} -> 1250 | K86: {=SUMPRODUCT(General_Data*(Code_General_Data=$C86)*(Year=K$3)*(Month=K$4))} -> 1300 | L86: {=SUMPRODUCT(General_Data*(Code_General_Data=$C86)*(Year=L$3)*(Month=L$4))} -> 1300 | M86: {=SUMPRODUCT(General_Data*(Code_General_Data=$C86)*(Year=M$3)*(Month=M$4))} -> 1300 | N86: {=SUMPRODUCT(General_Data*(Code_General_Data=$C86)*(Year=N$3)*(Month=N$4))} -> 1300 | ... AD86: {=SUMPRODUCT(General_Data*(Code_General_Data=$C86)*(Year=AD$3)*(Month=AD$4))} -> 1200
A88: 102990 | D88: 6 | E88: COCA VIET NAM
A89: 102990 | B89: 110000332 | F89: iSS1084G
A90: 102990 | B90: 110000332 | D90: 6.1 | F90: Giá bán-DDP | G90: {=INDEX(Price!$L$11:$AM$182,MATCH(1,(Price!$A$11:$A$182=$A90)*(Price!$B$11:$B$182=$B90)*(Price!$D$11:$D$182="gb"),0),MATCH(1,(Price!$L$3:$AM$3=G$3)*(Price!$L$4:$AM$4=G$4),0))} -> 1325 | H90: {=INDEX(Price!$L$11:$AM$182,MATCH(1,(Price!$A$11:$A$182=$A90)*(Price!$B$11:$B$182=$B90)*(Price!$D$11:$D$182="gb"),0),MATCH(1,(Price!$L$3:$AM$3=H$3)*(Price!$L$4:$AM$4=H$4),0))} -> 1325 | I90: {=INDEX(Price!$L$11:$AM$182,MATCH(1,(Price!$A$11:$A$182=$A90)*(Price!$B$11:$B$182=$B90)*(Price!$D$11:$D$182="gb"),0),MATCH(1,(Price!$L$3:$AM$3=I$3)*(Price!$L$4:$AM$4=I$4),0))} -> 1325 | J90: {=INDEX(Price!$L$11:$AM$182,MATCH(1,(Price!$A$11:$A$182=$A90)*(Price!$B$11:$B$182=$B90)*(Price!$D$11:$D$182="gb"),0),MATCH(1,(Price!$L$3:$AM$3=J$3)*(Price!$L$4:$AM$4=J$4),0))} -> 1325 | K90: {=INDEX(Price!$L$11:$AM$182,MATCH(1,(Price!$A$11:$A$182=$A90)*(Price!$B$11:$B$182=$B90)*(Price!$D$11:$D$182="gb"),0),MATCH(1,(Price!$L$3:$AM$3=K$3)*(Price!$L$4:$AM$4=K$4),0))} -> 1325 | L90: {=INDEX(Price!$L$11:$AM$182,MATCH(1,(Price!$A$11:$A$182=$A90)*(Price!$B$11:$B$182=$B90)*(Price!$D$11:$D$182="gb"),0),MATCH(1,(Price!$L$3:$AM$3=L$3)*(Price!$L$4:$AM$4=L$4),0))} -> 1325 | M90: {=INDEX(Price!$L$11:$AM$182,MATCH(1,(Price!$A$11:$A$182=$A90)*(Price!$B$11:$B$182=$B90)*(Price!$D$11:$D$182="gb"),0),MATCH(1,(Price!$L$3:$AM$3=M$3)*(Price!$L$4:$AM$4=M$4),0))} -> 1325 | N90: {=INDEX(Price!$L$11:$AM$182,MATCH(1,(Price!$A$11:$A$182=$A90)*(Price!$B$11:$B$182=$B90)*(Price!$D$11:$D$182="gb"),0),MATCH(1,(Price!$L$3:$AM$3=N$3)*(Price!$L$4:$AM$4=N$4),0))} -> 1325 | ... AD90: {=INDEX(Price!$L$11:$AM$182,MATCH(1,(Price!$A$11:$A$182=$A90)*(Price!$B$11:$B$182=$B90)*(Price!$D$11:$D$182="gb"),0),MATCH(1,(Price!$L$3:$AM$3=AD$3)*(Price!$L$4:$AM$4=AD$4),0))} -> 1400
A91: 102990 | B91: 110000332 | C91: GB | D91: 6.2 | F91: Giá bán quy đổi EXW | G91: {=INDEX(Price!$L$11:$AM$182,MATCH(1,(Price!$A$11:$A$182=$A91)*(Price!$B$11:$B$182=$B91)*(Price!$D$11:$D$182="exw"),0),MATCH(1,(Price!$L$3:$AM$3=G$3)*(Price!$L$4:$AM$4=G$4),0))} -> 1315 | H91: {=INDEX(Price!$L$11:$AM$182,MATCH(1,(Price!$A$11:$A$182=$A91)*(Price!$B$11:$B$182=$B91)*(Price!$D$11:$D$182="exw"),0),MATCH(1,(Price!$L$3:$AM$3=H$3)*(Price!$L$4:$AM$4=H$4),0))} -> 1315 | I91: {=INDEX(Price!$L$11:$AM$182,MATCH(1,(Price!$A$11:$A$182=$A91)*(Price!$B$11:$B$182=$B91)*(Price!$D$11:$D$182="exw"),0),MATCH(1,(Price!$L$3:$AM$3=I$3)*(Price!$L$4:$AM$4=I$4),0))} -> 1315 | J91: {=INDEX(Price!$L$11:$AM$182,MATCH(1,(Price!$A$11:$A$182=$A91)*(Price!$B$11:$B$182=$B91)*(Price!$D$11:$D$182="exw"),0),MATCH(1,(Price!$L$3:$AM$3=J$3)*(Price!$L$4:$AM$4=J$4),0))} -> 1315 | K91: {=INDEX(Price!$L$11:$AM$182,MATCH(1,(Price!$A$11:$A$182=$A91)*(Price!$B$11:$B$182=$B91)*(Price!$D$11:$D$182="exw"),0),MATCH(1,(Price!$L$3:$AM$3=K$3)*(Price!$L$4:$AM$4=K$4),0))} -> 1315 | L91: {=INDEX(Price!$L$11:$AM$182,MATCH(1,(Price!$A$11:$A$182=$A91)*(Price!$B$11:$B$182=$B91)*(Price!$D$11:$D$182="exw"),0),MATCH(1,(Price!$L$3:$AM$3=L$3)*(Price!$L$4:$AM$4=L$4),0))} -> 1315 | M91: {=INDEX(Price!$L$11:$AM$182,MATCH(1,(Price!$A$11:$A$182=$A91)*(Price!$B$11:$B$182=$B91)*(Price!$D$11:$D$182="exw"),0),MATCH(1,(Price!$L$3:$AM$3=M$3)*(Price!$L$4:$AM$4=M$4),0))} -> 1315 | N91: {=INDEX(Price!$L$11:$AM$182,MATCH(1,(Price!$A$11:$A$182=$A91)*(Price!$B$11:$B$182=$B91)*(Price!$D$11:$D$182="exw"),0),MATCH(1,(Price!$L$3:$AM$3=N$3)*(Price!$L$4:$AM$4=N$4),0))} -> 1315 | ... AD91: {=INDEX(Price!$L$11:$AM$182,MATCH(1,(Price!$A$11:$A$182=$A91)*(Price!$B$11:$B$182=$B91)*(Price!$D$11:$D$182="exw"),0),MATCH(1,(Price!$L$3:$AM$3=AD$3)*(Price!$L$4:$AM$4=AD$4),0))} -> 1348.3
A92: 102990 | B92: 110000332 | C92: PETVirgin | D92: 6.3 | F92: Giá chính phẩm | G92: {=SUMPRODUCT(General_Data*(Code_General_Data=$C92)*(Year=G$3)*(Month=G$4))} -> 930 | H92: {=SUMPRODUCT(General_Data*(Code_General_Data=$C92)*(Year=H$3)*(Month=H$4))} -> 943.33333 | I92: {=SUMPRODUCT(General_Data*(Code_General_Data=$C92)*(Year=I$3)*(Month=I$4))} -> 940 | J92: {=SUMPRODUCT(General_Data*(Code_General_Data=$C92)*(Year=J$3)*(Month=J$4))} -> 940 | K92: {=SUMPRODUCT(General_Data*(Code_General_Data=$C92)*(Year=K$3)*(Month=K$4))} -> 942 | L92: {=SUMPRODUCT(General_Data*(Code_General_Data=$C92)*(Year=L$3)*(Month=L$4))} -> 950 | M92: {=SUMPRODUCT(General_Data*(Code_General_Data=$C92)*(Year=M$3)*(Month=M$4))} -> 947.5 | N92: {=SUMPRODUCT(General_Data*(Code_General_Data=$C92)*(Year=N$3)*(Month=N$4))} -> 930 | ... AD92: {=SUMPRODUCT(General_Data*(Code_General_Data=$C92)*(Year=AD$3)*(Month=AD$4))} -> 770
A93: 102990 | B93: 110000332 | D93: 6.4 | F93: Chênh lệch giữa R sv Virgin | G93: =IF(G90*G91*G92<>0,G91-G92,0) -> 385 | H93: =IF(H90*H91*H92<>0,H91-H92,0) -> 371.66667 | I93: =IF(I90*I91*I92<>0,I91-I92,0) -> 375 | J93: =IF(J90*J91*J92<>0,J91-J92,0) -> 375 | K93: =IF(K90*K91*K92<>0,K91-K92,0) -> 373 | L93: =IF(L90*L91*L92<>0,L91-L92,0) -> 365 | M93: =IF(M90*M91*M92<>0,M91-M92,0) -> 367.5 | N93: =IF(N90*N91*N92<>0,N91-N92,0) -> 385 | ... AD93: =IF(AD90*AD91*AD92<>0,AD91-AD92,0) -> 578.3
A94: 102990 | B94: 110000332 | D94: 6.5 | F94: % +/- | G94: =IFERROR(G93/G92,0) -> 0.41397849 | H94: =IFERROR(H93/H92,0) -> 0.39399293 | I94: =IFERROR(I93/I92,0) -> 0.39893617 | J94: =IFERROR(J93/J92,0) -> 0.39893617 | K94: =IFERROR(K93/K92,0) -> 0.39596603 | L94: =IFERROR(L93/L92,0) -> 0.38421053 | M94: =IFERROR(M93/M92,0) -> 0.3878628 | N94: =IFERROR(N93/N92,0) -> 0.41397849 | ... AD94: =IFERROR(AD93/AD92,0) -> 0.75103896
A95: 102990 | B95: 110000332 | C95: 110000332 | D95: 6.6 | F95: Giá duyệt tháng | G95: {=SUMPRODUCT(General_Data*(Code_General_Data=$C95)*(Year=G$3)*(Month=G$4))} -> 1340 | H95: {=SUMPRODUCT(General_Data*(Code_General_Data=$C95)*(Year=H$3)*(Month=H$4))} -> 1340 | I95: {=SUMPRODUCT(General_Data*(Code_General_Data=$C95)*(Year=I$3)*(Month=I$4))} -> 1340 | J95: {=SUMPRODUCT(General_Data*(Code_General_Data=$C95)*(Year=J$3)*(Month=J$4))} -> 1340 | K95: {=SUMPRODUCT(General_Data*(Code_General_Data=$C95)*(Year=K$3)*(Month=K$4))} -> 1390 | L95: {=SUMPRODUCT(General_Data*(Code_General_Data=$C95)*(Year=L$3)*(Month=L$4))} -> 1390 | M95: {=SUMPRODUCT(General_Data*(Code_General_Data=$C95)*(Year=M$3)*(Month=M$4))} -> 1390 | N95: {=SUMPRODUCT(General_Data*(Code_General_Data=$C95)*(Year=N$3)*(Month=N$4))} -> 1390 | ... AD95: {=SUMPRODUCT(General_Data*(Code_General_Data=$C95)*(Year=AD$3)*(Month=AD$4))} -> 1290
A97: 105217 | D97: 7 | E97: NESTLE VIET NAM
A98: 105217 | B98: 110000329 | F98: WSS01
A99: 105217 | B99: 110000329 | D99: 7.1 | F99: Giá bán-DDP | G99: {=INDEX(Price!$L$11:$AM$182,MATCH(1,(Price!$A$11:$A$182=$A99)*(Price!$B$11:$B$182=$B99)*(Price!$D$11:$D$182="gb"),0),MATCH(1,(Price!$L$3:$AM$3=G$3)*(Price!$L$4:$AM$4=G$4),0))} -> 0 | H99: {=INDEX(Price!$L$11:$AM$182,MATCH(1,(Price!$A$11:$A$182=$A99)*(Price!$B$11:$B$182=$B99)*(Price!$D$11:$D$182="gb"),0),MATCH(1,(Price!$L$3:$AM$3=H$3)*(Price!$L$4:$AM$4=H$4),0))} -> 0 | I99: {=INDEX(Price!$L$11:$AM$182,MATCH(1,(Price!$A$11:$A$182=$A99)*(Price!$B$11:$B$182=$B99)*(Price!$D$11:$D$182="gb"),0),MATCH(1,(Price!$L$3:$AM$3=I$3)*(Price!$L$4:$AM$4=I$4),0))} -> 0 | J99: {=INDEX(Price!$L$11:$AM$182,MATCH(1,(Price!$A$11:$A$182=$A99)*(Price!$B$11:$B$182=$B99)*(Price!$D$11:$D$182="gb"),0),MATCH(1,(Price!$L$3:$AM$3=J$3)*(Price!$L$4:$AM$4=J$4),0))} -> 0 | K99: {=INDEX(Price!$L$11:$AM$182,MATCH(1,(Price!$A$11:$A$182=$A99)*(Price!$B$11:$B$182=$B99)*(Price!$D$11:$D$182="gb"),0),MATCH(1,(Price!$L$3:$AM$3=K$3)*(Price!$L$4:$AM$4=K$4),0))} -> 0 | L99: {=INDEX(Price!$L$11:$AM$182,MATCH(1,(Price!$A$11:$A$182=$A99)*(Price!$B$11:$B$182=$B99)*(Price!$D$11:$D$182="gb"),0),MATCH(1,(Price!$L$3:$AM$3=L$3)*(Price!$L$4:$AM$4=L$4),0))} -> 0 | M99: {=INDEX(Price!$L$11:$AM$182,MATCH(1,(Price!$A$11:$A$182=$A99)*(Price!$B$11:$B$182=$B99)*(Price!$D$11:$D$182="gb"),0),MATCH(1,(Price!$L$3:$AM$3=M$3)*(Price!$L$4:$AM$4=M$4),0))} -> 0 | N99: {=INDEX(Price!$L$11:$AM$182,MATCH(1,(Price!$A$11:$A$182=$A99)*(Price!$B$11:$B$182=$B99)*(Price!$D$11:$D$182="gb"),0),MATCH(1,(Price!$L$3:$AM$3=N$3)*(Price!$L$4:$AM$4=N$4),0))} -> 0 | ... AD99: {=INDEX(Price!$L$11:$AM$182,MATCH(1,(Price!$A$11:$A$182=$A99)*(Price!$B$11:$B$182=$B99)*(Price!$D$11:$D$182="gb"),0),MATCH(1,(Price!$L$3:$AM$3=AD$3)*(Price!$L$4:$AM$4=AD$4),0))} -> 0
A100: 105217 | B100: 110000329 | C100: GB | D100: 7.2 | F100: Giá bán quy đổi EXW | G100: {=INDEX(Price!$L$11:$AM$182,MATCH(1,(Price!$A$11:$A$182=$A100)*(Price!$B$11:$B$182=$B100)*(Price!$D$11:$D$182="exw"),0),MATCH(1,(Price!$L$3:$AM$3=G$3)*(Price!$L$4:$AM$4=G$4),0))} -> 0 | H100: {=INDEX(Price!$L$11:$AM$182,MATCH(1,(Price!$A$11:$A$182=$A100)*(Price!$B$11:$B$182=$B100)*(Price!$D$11:$D$182="exw"),0),MATCH(1,(Price!$L$3:$AM$3=H$3)*(Price!$L$4:$AM$4=H$4),0))} -> 0 | I100: {=INDEX(Price!$L$11:$AM$182,MATCH(1,(Price!$A$11:$A$182=$A100)*(Price!$B$11:$B$182=$B100)*(Price!$D$11:$D$182="exw"),0),MATCH(1,(Price!$L$3:$AM$3=I$3)*(Price!$L$4:$AM$4=I$4),0))} -> 0 | J100: {=INDEX(Price!$L$11:$AM$182,MATCH(1,(Price!$A$11:$A$182=$A100)*(Price!$B$11:$B$182=$B100)*(Price!$D$11:$D$182="exw"),0),MATCH(1,(Price!$L$3:$AM$3=J$3)*(Price!$L$4:$AM$4=J$4),0))} -> 0 | K100: {=INDEX(Price!$L$11:$AM$182,MATCH(1,(Price!$A$11:$A$182=$A100)*(Price!$B$11:$B$182=$B100)*(Price!$D$11:$D$182="exw"),0),MATCH(1,(Price!$L$3:$AM$3=K$3)*(Price!$L$4:$AM$4=K$4),0))} -> 0 | L100: {=INDEX(Price!$L$11:$AM$182,MATCH(1,(Price!$A$11:$A$182=$A100)*(Price!$B$11:$B$182=$B100)*(Price!$D$11:$D$182="exw"),0),MATCH(1,(Price!$L$3:$AM$3=L$3)*(Price!$L$4:$AM$4=L$4),0))} -> 0 | M100: {=INDEX(Price!$L$11:$AM$182,MATCH(1,(Price!$A$11:$A$182=$A100)*(Price!$B$11:$B$182=$B100)*(Price!$D$11:$D$182="exw"),0),MATCH(1,(Price!$L$3:$AM$3=M$3)*(Price!$L$4:$AM$4=M$4),0))} -> 0 | N100: {=INDEX(Price!$L$11:$AM$182,MATCH(1,(Price!$A$11:$A$182=$A100)*(Price!$B$11:$B$182=$B100)*(Price!$D$11:$D$182="exw"),0),MATCH(1,(Price!$L$3:$AM$3=N$3)*(Price!$L$4:$AM$4=N$4),0))} -> 0 | ... AD100: {=INDEX(Price!$L$11:$AM$182,MATCH(1,(Price!$A$11:$A$182=$A100)*(Price!$B$11:$B$182=$B100)*(Price!$D$11:$D$182="exw"),0),MATCH(1,(Price!$L$3:$AM$3=AD$3)*(Price!$L$4:$AM$4=AD$4),0))} -> 0
A101: 105217 | B101: 110000329 | C101: PETVirgin | D101: 7.3 | F101: Giá chính phẩm | P101: {=SUMPRODUCT(General_Data*(Code_General_Data=$C101)*(Year=P$3)*(Month=P$4))} -> 862.5 | Q101: {=SUMPRODUCT(General_Data*(Code_General_Data=$C101)*(Year=Q$3)*(Month=Q$4))} -> 852 | R101: {=SUMPRODUCT(General_Data*(Code_General_Data=$C101)*(Year=R$3)*(Month=R$4))} -> 830 | S101: {=SUMPRODUCT(General_Data*(Code_General_Data=$C101)*(Year=S$3)*(Month=S$4))} -> 828 | T101: {=SUMPRODUCT(General_Data*(Code_General_Data=$C101)*(Year=T$3)*(Month=T$4))} -> 840 | U101: {=SUMPRODUCT(General_Data*(Code_General_Data=$C101)*(Year=U$3)*(Month=U$4))} -> 823 | V101: {=SUMPRODUCT(General_Data*(Code_General_Data=$C101)*(Year=V$3)*(Month=V$4))} -> 765 | W101: {=SUMPRODUCT(General_Data*(Code_General_Data=$C101)*(Year=W$3)*(Month=W$4))} -> 782 | ... AD101: {=SUMPRODUCT(General_Data*(Code_General_Data=$C101)*(Year=AD$3)*(Month=AD$4))} -> 770
A102: 105217 | B102: 110000329 | D102: 7.4 | F102: Chênh lệch giữa R sv Virgin | P102: =IF(P99*P100*P101<>0,P100-P101,0) -> 447.5 | Q102: =IF(Q99*Q100*Q101<>0,Q100-Q101,0) -> 458 | R102: =IF(R99*R100*R101<>0,R100-R101,0) -> 480 | S102: =IF(S99*S100*S101<>0,S100-S101,0) -> 0 | T102: =IF(T99*T100*T101<>0,T100-T101,0) -> 0 | U102: =IF(U99*U100*U101<>0,U100-U101,0) -> 0 | V102: =IF(V99*V100*V101<>0,V100-V101,0) -> 0 | W102: =IF(W99*W100*W101<>0,W100-W101,0) -> 0 | ... AD102: =IF(AD99*AD100*AD101<>0,AD100-AD101,0) -> 0
A103: 105217 | B103: 110000329 | D103: 7.5 | F103: % +/- | P103: =IFERROR(P102/P101,0) -> 0.51884058 | Q103: =IFERROR(Q102/Q101,0) -> 0.53755869 | R103: =IFERROR(R102/R101,0) -> 0.57831325 | S103: =IFERROR(S102/S101,0) -> 0 | T103: =IFERROR(T102/T101,0) -> 0 | U103: =IFERROR(U102/U101,0) -> 0 | V103: =IFERROR(V102/V101,0) -> 0 | W103: =IFERROR(W102/W101,0) -> 0 | ... AD103: =IFERROR(AD102/AD101,0) -> 0
A104: 105217 | B104: 110000329 | C104: 110000329 | D104: 7.6 | F104: Giá duyệt tháng | P104: {=SUMPRODUCT(General_Data*(Code_General_Data=$C104)*(Year=P$3)*(Month=P$4))} -> 1325 | Q104: {=SUMPRODUCT(General_Data*(Code_General_Data=$C104)*(Year=Q$3)*(Month=Q$4))} -> 1325 | R104: {=SUMPRODUCT(General_Data*(Code_General_Data=$C104)*(Year=R$3)*(Month=R$4))} -> 1275 | S104: {=SUMPRODUCT(General_Data*(Code_General_Data=$C104)*(Year=S$3)*(Month=S$4))} -> 1230 | T104: {=SUMPRODUCT(General_Data*(Code_General_Data=$C104)*(Year=T$3)*(Month=T$4))} -> 1230 | U104: {=SUMPRODUCT(General_Data*(Code_General_Data=$C104)*(Year=U$3)*(Month=U$4))} -> 1230 | V104: {=SUMPRODUCT(General_Data*(Code_General_Data=$C104)*(Year=V$3)*(Month=V$4))} -> 1250 | W104: {=SUMPRODUCT(General_Data*(Code_General_Data=$C104)*(Year=W$3)*(Month=W$4))} -> 1250 | ... AD104: {=SUMPRODUCT(General_Data*(Code_General_Data=$C104)*(Year=AD$3)*(Month=AD$4))} -> 1200

Sheet Price
L1: =DATE(L3,L4,1) -> 45200 | M1: =DATE(M3,M4,1) -> 45231 | N1: =DATE(N3,N4,1) -> 45261 | O1: =DATE(O3,O4,1) -> 45292 | P1: =DATE(P3,P4,1) -> 45323 | Q1: =DATE(Q3,Q4,1) -> 45352 | R1: =DATE(R3,R4,1) -> 45383 | S1: =DATE(S3,S4,1) -> 45413 | ... AL1: =DATE(AL3,AL4,1) -> 45992
L2: =EOMONTH(L1,0) -> 45230 | M2: =EOMONTH(M1,0) -> 45260 | N2: =EOMONTH(N1,0) -> 45291 | O2: =EOMONTH(O1,0) -> 45322 | P2: =EOMONTH(P1,0) -> 45351 | Q2: =EOMONTH(Q1,0) -> 45382 | R2: =EOMONTH(R1,0) -> 45412 | S2: =EOMONTH(S1,0) -> 45443 | ... AL2: =EOMONTH(AL1,0) -> 46022
L3: 2023 | M3: 2023 | N3: 2023 | O3: 2024 | P3: 2024 | Q3: 2024 | R3: 2024 | S3: 2024 | T3: 2024 | U3: 2024 | V3: 2024 | W3: 2024 | X3: 2024 | Y3: 2024 | Z3: 2024 | AA3: 2025 | AB3: 2025 | AC3: 2025 | AD3: 2025 | AE3: 2025 | AF3: 2025 | AG3: 2025 | AH3: 2025 | AI3: 2025 | AJ3: 2025 | AK3: 2025 | AL3: 2025
L4: 10 | M4: 11 | N4: 12 | O4: 1 | P4: 2 | Q4: 3 | R4: 4 | S4: 5 | T4: 6 | U4: 7 | V4: 8 | W4: 9 | X4: 10 | Y4: 11 | Z4: 12 | AA4: 1 | AB4: 2 | AC4: 3 | AD4: 4 | AE4: 5 | AF4: 6 | AG4: 7 | AH4: 8 | AI4: 9 | AJ4: 10 | AK4: 11 | AL4: 12
O6: II. CHI TIẾT GIÁ CÔNG THỨC THEO KHÁCH HÀNG | AA6: II. CHI TIẾT GIÁ CÔNG THỨC THEO KHÁCH HÀNG | AM6: II. CHI TIẾT GIÁ CÔNG THỨC THEO KHÁCH HÀNG
F8: STT | G8: KHÁCH HÀNG/NỘI DUNG | L8: 2023 | O8: 2024 | AA8: 2025 | AM8: 2026
A9: Khách | B9: SKU | C9: Code | D9: Link | L9: 10 | M9: 11 | N9: 12 | O9: 1 | P9: 2 | Q9: 3 | R9: 4 | S9: 5 | T9: 6 | U9: 7 | V9: 8 | W9: 9 | X9: 10 | Y9: 11 | Z9: 12 | AA9: 1 | AB9: 2 | AC9: 3 | AD9: 4 | AE9: 5 | AF9: 6 | AG9: 7 | AH9: 8 | AI9: 9 | AJ9: 10 | AK9: 11 | AL9: 12 | AM9: 1 | AN9: 2 | AO9: 3 | AP9: 4 | AQ9: 5 | AR9: 6 | AS9: 7 | AT9: 8 | AU9: 9 | AV9: 10 | AW9: 11 | AX9: 12
A11: 200319 | F11: 1 | G11: NIAGARA
A12: 200319 | B12: 110000354 | D12: GB | F12: 1.1 | H12: GIÁ BÁN WSS01G (FOB) | O12: =MIN(MAX(SUM(O13:O14),O20),O19) -> 1200 | P12: =MIN(MAX(SUM(P13:P14),P20),P19) -> 1200 | Q12: =MIN(MAX(SUM(Q13:Q14),Q20),Q19) -> 1200 | R12: =MIN(MAX(SUM(R13:R14),R20),R19) -> 1200 | S12: =MIN(MAX(SUM(S13:S14),S20),S19) -> 1200 | T12: =MIN(MAX(SUM(T13:T14),T20),T19) -> 1200.9 | U12: =MIN(MAX(SUM(U13:U14),U20),U19) -> 1214.4 | V12: =MIN(MAX(SUM(V13:V14),V20),V19) -> 1226.1 | ... AC12: =MIN(MAX(SUM(AC13:AC14),AC20),AC19) -> 1238.875 | AD12: =MIN(MAX(SUM(AD13:AD14),AD20),AD19)-0.619999999998981 -> 1219.88 | AE12: =MIN(MAX(SUM(AE13:AE14),AE20),AE19) -> 1221 | AF12: =MIN(MAX(SUM(AF13:AF14),AF20),AF19) -> 1224 | AG12: =MIN(MAX(SUM(AG13:AG14),AG20),AG19) -> 1224 | AH12: =MIN(MAX(SUM(AH13:AH14),AH20),AH19) -> 1213.2 | AI12: =MIN(MAX(SUM(AI13:AI14),AI20),AI19) -> 1200 | AJ12: =MIN(MAX(SUM(AJ13:AJ14),AJ20),AJ19) -> 1200 | AK12: =MIN(MAX(SUM(AK13:AK14),AK20),AK19) -> 1200 | AL12: =MIN(MAX(SUM(AL13:AL14),AL20),AL19) -> 1200
A13: 200319 | B13: 110000354 | F13: 1.1.A | H13: [+] | I13: ICIS Bales - SEA trung bình 3 tháng trước | O13: =AVERAGE(L17:N17) -> 1296.0417 | P13: =AVERAGE(M17:O17) -> 1305 | Q13: =AVERAGE(N17:P17) -> 1313.3333 | R13: =AVERAGE(O17:Q17) -> 1320 | S13: =AVERAGE(P17:R17) -> 1326 | T13: =AVERAGE(Q17:S17) -> 1334.3333 | U13: =AVERAGE(R17:T17) -> 1349.3333 | V13: =AVERAGE(S17:U17) -> 1362.3333 | ... AL13: =AVERAGE(AI17:AK17) -> 1253.9167
A14: 200319 | B14: 110000354 | F14: 1.1.B | H14: [+] | I14: Chiết khấu (10%) | O14: =-O13*O18 -> -129.60417 | P14: =-P13*P18 -> -130.5 | Q14: =-Q13*Q18 -> -131.33333 | R14: =-R13*R18 -> -132 | S14: =-S13*S18 -> -132.6 | T14: =-T13*T18 -> -133.43333 | U14: =-U13*U18 -> -134.93333 | V14: =-V13*V18 -> -136.23333 | ... AL14: =-AL13*AL18 -> -125.39167
A15: 200319 | B15: 110000354 | D15: EXW | F15: 1.1.1 | I15: Giá bán quy đổi EXW | O15: =O12-O16 -> 1180 | P15: =P12-P16 -> 1180 | Q15: =Q12-Q16 -> 1180 | R15: =R12-R16 -> 1180 | S15: =S12-S16 -> 1180 | T15: =T12-T16 -> 1180.9 | U15: =U12-U16 -> 1194.4 | V15: =V12-V16 -> 1206.1 | ... AL15: =AL12-AL16 -> 1180
A16: 200319 | B16: 110000354 | I16: Chi phí vận chuyển | O16: 20 | P16: 20 | Q16: 20 | R16: 20 | S16: 20 | T16: 20 | U16: 20 | V16: 20 | W16: 20 | X16: 20 | Y16: 20 | Z16: 20 | AA16: 20 | AB16: 20 | AC16: 20 | AD16: 22 | AE16: 22 | AF16: 22 | AG16: 22 | AH16: 20 | AI16: 20 | AJ16: 20 | AK16: 20 | AL16: 20
A17: 200319 | B17: 110000354 | C17: 04 | J17: ICIS Bales - SEA | L17: {=SUMPRODUCT(General_Data*(Year=L$3)*(Month=L$4)*(Code_General_Data=$C17))} -> 1288.125 | M17: {=SUMPRODUCT(General_Data*(Year=M$3)*(Month=M$4)*(Code_General_Data=$C17))} -> 1300 | N17: {=SUMPRODUCT(General_Data*(Year=N$3)*(Month=N$4)*(Code_General_Data=$C17))} -> 1300 | O17: {=SUMPRODUCT(General_Data*(Year=O$3)*(Month=O$4)*(Code_General_Data=$C17))} -> 1315 | P17: {=SUMPRODUCT(General_Data*(Year=P$3)*(Month=P$4)*(Code_General_Data=$C17))} -> 1325 | Q17: {=SUMPRODUCT(General_Data*(Year=Q$3)*(Month=Q$4)*(Code_General_Data=$C17))} -> 1320 | R17: {=SUMPRODUCT(General_Data*(Year=R$3)*(Month=R$4)*(Code_General_Data=$C17))} -> 1333 | S17: {=SUMPRODUCT(General_Data*(Year=S$3)*(Month=S$4)*(Code_General_Data=$C17))} -> 1350 | ... AL17: {=SUMPRODUCT(General_Data*(Year=AL$3)*(Month=AL$4)*(Code_General_Data=$C17))} -> 0
A18: 200319 | B18: 110000354 | J18: %Chiết khấu | O18: 0.1 | P18: 0.1 | Q18: 0.1 | R18: 0.1 | S18: 0.1 | T18: 0.1 | U18: 0.1 | V18: 0.1 | W18: 0.1 | X18: 0.1 | Y18: 0.1 | Z18: 0.1 | AA18: 0.1 | AB18: 0.1 | AC18: 0.1 | AD18: 0.1 | AE18: 0.1 | AF18: 0.1 | AG18: 0.1 | AH18: 0.1 | AI18: 0.1 | AJ18: 0.1 | AK18: 0.1 | AL18: 0.1
A19: 200319 | B19: 110000354 | F19: 1.1.2 | J19: Giá trần | O19: {=INDEX(Note!$J$3:$J$101,MATCH(1,(Note!$A$3:$A$101=$A19)*(Note!$C$3:$C$101=$B19)*(Note!$E$3:$E$101<=O$1)*(Note!$F$3:$F$101>=O$2),0))} -> 1600 | P19: {=INDEX(Note!$J$3:$J$101,MATCH(1,(Note!$A$3:$A$101=$A19)*(Note!$C$3:$C$101=$B19)*(Note!$E$3:$E$101<=P$1)*(Note!$F$3:$F$101>=P$2),0))} -> 1600 | Q19: {=INDEX(Note!$J$3:$J$101,MATCH(1,(Note!$A$3:$A$101=$A19)*(Note!$C$3:$C$101=$B19)*(Note!$E$3:$E$101<=Q$1)*(Note!$F$3:$F$101>=Q$2),0))} -> 1600 | R19: {=INDEX(Note!$J$3:$J$101,MATCH(1,(Note!$A$3:$A$101=$A19)*(Note!$C$3:$C$101=$B19)*(Note!$E$3:$E$101<=R$1)*(Note!$F$3:$F$101>=R$2),0))} -> 1600 | S19: {=INDEX(Note!$J$3:$J$101,MATCH(1,(Note!$A$3:$A$101=$A19)*(Note!$C$3:$C$101=$B19)*(Note!$E$3:$E$101<=S$1)*(Note!$F$3:$F$101>=S$2),0))} -> 1600 | T19: {=INDEX(Note!$J$3:$J$101,MATCH(1,(Note!$A$3:$A$101=$A19)*(Note!$C$3:$C$101=$B19)*(Note!$E$3:$E$101<=T$1)*(Note!$F$3:$F$101>=T$2),0))} -> 1600 | U19: {=INDEX(Note!$J$3:$J$101,MATCH(1,(Note!$A$3:$A$101=$A19)*(Note!$C$3:$C$101=$B19)*(Note!$E$3:$E$101<=U$1)*(Note!$F$3:$F$101>=U$2),0))} -> 1600 | V19: {=INDEX(Note!$J$3:$J$101,MATCH(1,(Note!$A$3:$A$101=$A19)*(Note!$C$3:$C$101=$B19)*(Note!$E$3:$E$101<=V$1)*(Note!$F$3:$F$101>=V$2),0))} -> 1600 | ... AL19: {=INDEX(Note!$J$3:$J$101,MATCH(1,(Note!$A$3:$A$101=$A19)*(Note!$C$3:$C$101=$B19)*(Note!$E$3:$E$101<=AL$1)*(Note!$F$3:$F$101>=AL$2),0))} -> 1600
A20: 200319 | B20: 110000354 | F20: 1.1.3 | J20: Giá sàn | O20: {=INDEX(Note!$K$3:$K$101,MATCH(1,(Note!$A$3:$A$101=$A20)*(Note!$C$3:$C$101=$B20)*(Note!$E$3:$E$101<=O$1)*(Note!$F$3:$F$101>=O$2),0))} -> 1200 | P20: {=INDEX(Note!$K$3:$K$101,MATCH(1,(Note!$A$3:$A$101=$A20)*(Note!$C$3:$C$101=$B20)*(Note!$E$3:$E$101<=P$1)*(Note!$F$3:$F$101>=P$2),0))} -> 1200 | Q20: {=INDEX(Note!$K$3:$K$101,MATCH(1,(Note!$A$3:$A$101=$A20)*(Note!$C$3:$C$101=$B20)*(Note!$E$3:$E$101<=Q$1)*(Note!$F$3:$F$101>=Q$2),0))} -> 1200 | R20: {=INDEX(Note!$K$3:$K$101,MATCH(1,(Note!$A$3:$A$101=$A20)*(Note!$C$3:$C$101=$B20)*(Note!$E$3:$E$101<=R$1)*(Note!$F$3:$F$101>=R$2),0))} -> 1200 | S20: {=INDEX(Note!$K$3:$K$101,MATCH(1,(Note!$A$3:$A$101=$A20)*(Note!$C$3:$C$101=$B20)*(Note!$E$3:$E$101<=S$1)*(Note!$F$3:$F$101>=S$2),0))} -> 1200 | T20: {=INDEX(Note!$K$3:$K$101,MATCH(1,(Note!$A$3:$A$101=$A20)*(Note!$C$3:$C$101=$B20)*(Note!$E$3:$E$101<=T$1)*(Note!$F$3:$F$101>=T$2),0))} -> 1200 | U20: {=INDEX(Note!$K$3:$K$101,MATCH(1,(Note!$A$3:$A$101=$A20)*(Note!$C$3:$C$101=$B20)*(Note!$E$3:$E$101<=U$1)*(Note!$F$3:$F$101>=U$2),0))} -> 1200 | V20: {=INDEX(Note!$K$3:$K$101,MATCH(1,(Note!$A$3:$A$101=$A20)*(Note!$C$3:$C$101=$B20)*(Note!$E$3:$E$101<=V$1)*(Note!$F$3:$F$101>=V$2),0))} -> 1200 | ... AL20: {=INDEX(Note!$K$3:$K$101,MATCH(1,(Note!$A$3:$A$101=$A20)*(Note!$C$3:$C$101=$B20)*(Note!$E$3:$E$101<=AL$1)*(Note!$F$3:$F$101>=AL$2),0))} -> 1200
A21: 200319 | B21: 110000354 | F21: 1.1.4 | J21: Giá duyệt tháng | O21: {=SUMPRODUCT(General_Data*(Year=O$3)*(Month=O$4)*(Code_General_Data=$B21))} -> 1250 | P21: {=SUMPRODUCT(General_Data*(Year=P$3)*(Month=P$4)*(Code_General_Data=$B21))} -> 1250 | Q21: {=SUMPRODUCT(General_Data*(Year=Q$3)*(Month=Q$4)*(Code_General_Data=$B21))} -> 1250 | R21: {=SUMPRODUCT(General_Data*(Year=R$3)*(Month=R$4)*(Code_General_Data=$B21))} -> 1250 | S21: {=SUMPRODUCT(General_Data*(Year=S$3)*(Month=S$4)*(Code_General_Data=$B21))} -> 1300 | T21: {=SUMPRODUCT(General_Data*(Year=T$3)*(Month=T$4)*(Code_General_Data=$B21))} -> 1300 | U21: {=SUMPRODUCT(General_Data*(Year=U$3)*(Month=U$4)*(Code_General_Data=$B21))} -> 1300 | V21: {=SUMPRODUCT(General_Data*(Year=V$3)*(Month=V$4)*(Code_General_Data=$B21))} -> 1300 | ... AL21: {=SUMPRODUCT(General_Data*(Year=AL$3)*(Month=AL$4)*(Code_General_Data=$B21))} -> 1200
J22: Giá trần - quy đổi EXW | O22: =O19-O16 -> 1580 | P22: =P19-P16 -> 1580 | Q22: =Q19-Q16 -> 1580 | R22: =R19-R16 -> 1580 | S22: =S19-S16 -> 1580 | T22: =T19-T16 -> 1580 | U22: =U19-U16 -> 1580 | V22: =V19-V16 -> 1580 | ... AL22: =AL19-AL16 -> 1580
J23: Giá sàn - quy đổi EXW | O23: =O20-O16 -> 1180 | P23: =P20-P16 -> 1180 | Q23: =Q20-Q16 -> 1180 | R23: =R20-R16 -> 1180 | S23: =S20-S16 -> 1180 | T23: =T20-T16 -> 1180 | U23: =U20-U16 -> 1180 | V23: =V20-V16 -> 1180 | ... AL23: =AL20-AL16 -> 1180
A25: 200332 | F25: 2 | G25: OUTEIRINHO
A26: 200332 | B26: 110000355 | D26: GB | F26: 2.1 | H26: GIÁ BÁN iSS01G (FOB) | AA26: 1250 | AB26: 1250 | AC26: 1250 | AD26: 1250 | AE26: 1250 | AF26: 1250 | AG26: 1250 | AH26: 1250 | AI26: 1250 | AJ26: 1250 | AK26: 1250 | AL26: 1250
A27: 200332 | B27: 110000355 | D27: EXW | F27: 2.1.1 | I27: Giá bán quy đổi EXW | AA27: =AA26-AA28 -> 1230 | AB27: =AB26-AB28 -> 1230 | AC27: =AC26-AC28 -> 1230 | AD27: =AD26-AD28 -> 1228 | AE27: 1228 | AF27: 1228 | AG27: 1228 | AH27: 1228 | AI27: 1228 | AJ27: 1228 | AK27: 1228 | AL27: 1228
A28: 200332 | B28: 110000355 | F28: 2.1.2 | I28: Chi phí vận chuyển | AA28: 20 | AB28: 20 | AC28: 20 | AD28: 22 | AE28: 22 | AF28: 22 | AG28: 22 | AH28: 20 | AI28: 20 | AJ28: 20 | AK28: 20 | AL28: 20
A29: 200332 | B29: 110000355 | F29: 2.1.3 | J29: Giá duyệt tháng | AA29: {=SUMPRODUCT(General_Data*(Year=AA$3)*(Month=AA$4)*(Code_General_Data=$B29))} -> 1260 | AB29: {=SUMPRODUCT(General_Data*(Year=AB$3)*(Month=AB$4)*(Code_General_Data=$B29))} -> 1260 | AC29: {=SUMPRODUCT(General_Data*(Year=AC$3)*(Month=AC$4)*(Code_General_Data=$B29))} -> 1260 | AD29: {=SUMPRODUCT(General_Data*(Year=AD$3)*(Month=AD$4)*(Code_General_Data=$B29))} -> 1280 | AE29: {=SUMPRODUCT(General_Data*(Year=AE$3)*(Month=AE$4)*(Code_General_Data=$B29))} -> 1280 | AF29: {=SUMPRODUCT(General_Data*(Year=AF$3)*(Month=AF$4)*(Code_General_Data=$B29))} -> 1280 | AG29: {=SUMPRODUCT(General_Data*(Year=AG$3)*(Month=AG$4)*(Code_General_Data=$B29))} -> 1280 | AH29: {=SUMPRODUCT(General_Data*(Year=AH$3)*(Month=AH$4)*(Code_General_Data=$B29))} -> 1250 | ... AL29: {=SUMPRODUCT(General_Data*(Year=AL$3)*(Month=AL$4)*(Code_General_Data=$B29))} -> 1230
A31: 105263 | F31: 3 | G31: UNILEVER VIỆT NAM
A32: 105263 | B32: 110000354 | D32: GB | F32: 3.1 | H32: GIÁ BÁN WSS01G (DDP) | O32: =ROUND(SUM(O33:O38),-2)+O39 -> 1320 | P32: =ROUND(SUM(P33:P38),-2)+P39 -> 1320 | Q32: =ROUND(SUM(Q33:Q38),-2)+Q39 -> 1320 | R32: =ROUND(SUM(R33:R38),-2)+R39 -> 1320 | S32: =ROUND(SUM(S33:S38),-2)+S39 -> 1320 | T32: =ROUND(SUM(T33:T38),-2)+T39 -> 1320 | U32: =ROUND(SUM(U33:U38),-2)+U39 -> 1320 | V32: =ROUND(SUM(V33:V38),-2)+V39 -> 1320 | W32: =ROUND(SUM(W33:W38),-2)+W39 -> 1320 | X32: =ROUND(SUM(X33:X38),-1)+X39 -> 1300 | Y32: =ROUND(SUM(Y33:Y38),-1)+Y39 -> 1300 | Z32: =ROUND(SUM(Z33:Z38),-1)+Z39 -> 1300 | AA32: =ROUND(SUM(AA33:AA38),-1)+AA39 -> 1300 | AB32: =ROUND(SUM(AB33:AB38),-1)+AB39 -> 1300 | AC32: =ROUND(SUM(AC33:AC38),-1)+AC39 -> 1300 | AD32: =ROUND(SUM(AD33:AD38),-1)+AD39 -> 1250 | AE32: =ROUND(SUM(AE33:AE38),-1)+AE39 -> 1250 | ... AL32: =ROUND(SUM(AL33:AL38),-1)+AL39 -> 1280
A33: 105263 | B33: 110000354 | F33: 3.1.A | H33: [+] | I33: Bales DTR | O33: =16500/O$40*10^3 -> 673.46939 | P33: =16500/P$40*10^3 -> 673.46939 | Q33: =16500/Q$40*10^3 -> 673.46939 | R33: =16500/R$40*10^3 -> 673.46939 | S33: =16500/S$40*10^3 -> 673.46939 | T33: =16500/T$40*10^3 -> 673.46939 | U33: =16500/U$40*10^3 -> 660 | V33: =16500/V$40*10^3 -> 660 | ... AC33: =16500/AC$40*10^3 -> 660 | AD33: =16800/AD$40*10^3 -> 672 | AE33: =16800/AE$40*10^3 -> 672 | AF33: =16800/AF$40*10^3 -> 672 | AG33: =16800/AG$40*10^3 -> 672 | AH33: =16800/AH$40*10^3 -> 672 | AI33: =16800/AI$40*10^3 -> 672 | AJ33: =16800/AJ$40*10^3 -> 672 | AK33: =16800/AK$40*10^3 -> 672 | AL33: =16800/AL$40*10^3 -> 672
A34: 105263 | B34: 110000354 | F34: 3.1.B | H34: [+] | I34: Hao hụt (30%) | O34: =O33*O41 -> 202.04082 | P34: =P33*P41 -> 202.04082 | Q34: =Q33*Q41 -> 202.04082 | R34: =R33*R41 -> 202.04082 | S34: =S33*S41 -> 202.04082 | T34: =T33*T41 -> 202.04082 | U34: =U33*U41 -> 198 | V34: =V33*V41 -> 198 | ... AL34: =AL33*AL41 -> 201.6
A35: 105263 | B35: 110000354 | F35: 3.1.C | H35: [+] | I35: Conversion cost | O35: =9193.7/O40*10^3 -> 375.25306 | P35: =9193.7/P40*10^3 -> 375.25306 | Q35: =9193.7/Q40*10^3 -> 375.25306 | R35: =9193.7/R40*10^3 -> 375.25306 | S35: =9193.7/S40*10^3 -> 375.25306 | T35: =9193.7/T40*10^3 -> 375.25306 | U35: =9193.7/U40*10^3 -> 367.748 | V35: =9193.7/V40*10^3 -> 367.748 | ... AC35: =9193.7/AC40*10^3 -> 367.748 | AD35: =9377.55821/AD40*10^3 -> 375.10233 | AE35: =9377.55821/AE40*10^3 -> 375.10233 | AF35: =9377.55821/AF40*10^3 -> 375.10233 | AG35: =9377.55821/AG40*10^3 -> 375.10233 | AH35: =9377.55821/AH40*10^3 -> 375.10233 | AI35: =9377.55821/AI40*10^3 -> 375.10233 | AJ35: =9377.55821/AJ40*10^3 -> 375.10233 | AK35: =9377.55821/AK40*10^3 -> 375.10233 | AL35: =9377.55821/AL40*10^3 -> 375.10233
A36: 105263 | B36: 110000354 | F36: 3.1.D | H36: [+] | I36: Chi phí vận chuyển | O36: =299/O40*10^3 -> 12.204082 | P36: =299/P40*10^3 -> 12.204082 | Q36: =299/Q40*10^3 -> 12.204082 | R36: =299/R40*10^3 -> 12.204082 | S36: =299/S40*10^3 -> 12.204082 | T36: =299/T40*10^3 -> 12.204082 | U36: =299/U40*10^3 -> 11.96 | V36: =299/V40*10^3 -> 11.96 | ... AL36: =299/AL40*10^3 -> 11.96
A37: 105263 | B37: 110000354 | F37: 3.1.E | H37: [+] | I37: Lợi nhuận trước thuế (EBT) | O37: =3295/O40*10^3 -> 134.4898 | P37: =3295/P40*10^3 -> 134.4898 | Q37: =3295/Q40*10^3 -> 134.4898 | R37: =3295/R40*10^3 -> 134.4898 | S37: =3295/S40*10^3 -> 134.4898 | T37: =3295/T40*10^3 -> 134.4898 | U37: =3295/U40*10^3 -> 131.8 | V37: =3295/V40*10^3 -> 131.8 | ... AL37: =3295/AL40*10^3 -> 131.8
A38: 105263 | B38: 110000354 | F38: 3.1.F | H38: [+] | I38: Interest (lãi vay) | O38: =8%/12*SUM(O33:O37) -> 9.316381 | P38: =8%/12*SUM(P33:P37) -> 9.316381 | Q38: =8%/12*SUM(Q33:Q37) -> 9.316381 | R38: =8%/12*SUM(R33:R37) -> 9.316381 | S38: =8%/12*SUM(S33:S37) -> 9.316381 | T38: =8%/12*SUM(T33:T37) -> 9.316381 | U38: =8%/12*SUM(U33:U37) -> 9.1300533 | V38: =8%/12*SUM(V33:V37) -> 9.1300533 | ... AL38: =8%/12*SUM(AL33:AL37) -> 9.2830822
A39: 105263 | B39: 110000354 | F39: 3.1.G | H39: [+] | I39: Chiết khấu | O39: -80 | P39: -80 | Q39: -80 | R39: -80 | S39: -80 | T39: -80 | U39: -80 | V39: -80 | W39: -80 | X39: -80 | Y39: -80 | Z39: -80 | AA39: -80 | AB39: -80 | AC39: -80 | AD39: -150 | AE39: -150 | AF39: -150 | AG39: -120 | AH39: -120 | AI39: -120 | AJ39: -120 | AK39: -120 | AL39: -120
A40: 105263 | B40: 110000354 | J40: Exchange rate | O40: 24500 | P40: 24500 | Q40: 24500 | R40: 24500 | S40: 24500 | T40: 24500 | U40: 25000 | V40: 25000 | W40: 25000 | X40: 25000 | Y40: 25000 | Z40: 25000 | AA40: 25000 | AB40: 25000 | AC40: 25000 | AD40: 25000 | AE40: 25000 | AF40: 25000 | AG40: 25000 | AH40: 25000 | AI40: 25000 | AJ40: 25000 | AK40: 25000 | AL40: 25000
A41: 105263 | B41: 110000354 | J41: %Hao hụt | O41: 0.3 | P41: 0.3 | Q41: 0.3 | R41: 0.3 | S41: 0.3 | T41: 0.3 | U41: 0.3 | V41: 0.3 | W41: 0.3 | X41: 0.3 | Y41: 0.3 | Z41: 0.3 | AA41: 0.3 | AB41: 0.3 | AC41: 0.3 | AD41: 0.3 | AE41: 0.3 | AF41: 0.3 | AG41: 0.3 | AH41: 0.3 | AI41: 0.3 | AJ41: 0.3 | AK41: 0.3 | AL41: 0.3
A42: 105263 | B42: 110000354 | D42: EXW | F42: 3.1.1 | I42: Giá bán quy đổi EXW | O42: =O32-O36 -> 1307.7959 | P42: =P32-P36 -> 1307.7959 | Q42: =Q32-Q36 -> 1307.7959 | R42: =R32-R36 -> 1307.7959 | S42: =S32-S36 -> 1307.7959 | T42: =T32-T36 -> 1307.7959 | U42: =U32-U36 -> 1308.04 | V42: =V32-V36 -> 1308.04 | ... AL42: =AL32-AL36 -> 1268.04
A43: 105263 | B43: 110000354 | F43: 3.1.2 | J43: Giá duyệt tháng | O43: {=SUMPRODUCT(General_Data*(Year=O$3)*(Month=O$4)*(Code_General_Data=$B43))} -> 1250 | P43: {=SUMPRODUCT(General_Data*(Year=P$3)*(Month=P$4)*(Code_General_Data=$B43))} -> 1250 | Q43: {=SUMPRODUCT(General_Data*(Year=Q$3)*(Month=Q$4)*(Code_General_Data=$B43))} -> 1250 | R43: {=SUMPRODUCT(General_Data*(Year=R$3)*(Month=R$4)*(Code_General_Data=$B43))} -> 1250 | S43: {=SUMPRODUCT(General_Data*(Year=S$3)*(Month=S$4)*(Code_General_Data=$B43))} -> 1300 | T43: {=SUMPRODUCT(General_Data*(Year=T$3)*(Month=T$4)*(Code_General_Data=$B43))} -> 1300 | U43: {=SUMPRODUCT(General_Data*(Year=U$3)*(Month=U$4)*(Code_General_Data=$B43))} -> 1300 | V43: {=SUMPRODUCT(General_Data*(Year=V$3)*(Month=V$4)*(Code_General_Data=$B43))} -> 1300 | ... AL43: {=SUMPRODUCT(General_Data*(Year=AL$3)*(Month=AL$4)*(Code_General_Data=$B43))} -> 1200
A45: 105263 | B45: 110000339 | D45: GB | F45: 3.2 | H45: GIÁ BÁN MBF01 (DDP) | O45: =ROUND(SUM(O46:O52),-1) -> 1500 | P45: =ROUND(SUM(P46:P52),-1) -> 1500 | Q45: =ROUND(SUM(Q46:Q52),-1) -> 1500 | R45: =ROUND(SUM(R46:R52),-1) -> 1430 | S45: =ROUND(SUM(S46:S52),-1) -> 1430 | T45: =ROUND(SUM(T46:T52),-1) -> 1430 | U45: =ROUND(SUM(U46:U52),-1) -> 1430 | V45: =ROUND(SUM(V46:V52),-1) -> 1430 | ... AL45: =ROUND(SUM(AL46:AL52),-1) -> 1380
A46: 105263 | B46: 110000339 | F46: 3.2.A | H46: [+] | I46: Bales DTR | O46: =22500/O53*10^3 -> 918.36735 | P46: =22500/P53*10^3 -> 918.36735 | Q46: =22500/Q53*10^3 -> 918.36735 | R46: =21000/R53*10^3 -> 857.14286 | S46: =21000/S53*10^3 -> 857.14286 | T46: =21000/T53*10^3 -> 857.14286 | U46: =21000/U53*10^3 -> 840 | V46: =21000/V53*10^3 -> 840 | W46: =21000/W53*10^3 -> 840 | X46: =21000/X53*10^3 -> 840 | Y46: =21000/Y53*10^3 -> 840 | ... AC46: =21000/AC53*10^3 -> 840 | AD46: =(21500*75%+24500*25%)/AD53*10^3 -> 890 | AE46: =(21500*75%+24500*25%)/AE53*10^3 -> 890 | AF46: =(21500*75%+24500*25%)/AF53*10^3 -> 890 | AG46: =21000/AG53*10^3 -> 840 | AH46: =21000/AH53*10^3 -> 840 | AI46: =21000/AI53*10^3 -> 840 | AJ46: =21000/AJ53*10^3 -> 840 | AK46: =21000/AK53*10^3 -> 840 | AL46: =21000/AL53*10^3 -> 840
A47: 105263 | B47: 110000339 | F47: 3.2.B | H47: [+] | I47: Hao hụt (21.27%) | O47: =O46*O54 -> 195.33673 | P47: =P46*P54 -> 195.33673 | Q47: =Q46*Q54 -> 195.33673 | R47: =R46*R54 -> 182.31429 | S47: =S46*S54 -> 182.31429 | T47: =T46*T54 -> 182.31429 | U47: =U46*U54 -> 178.668 | V47: =V46*V54 -> 178.668 | ... AL47: =AL46*AL54 -> 178.668
A48: 105263 | B48: 110000339 | F48: 3.2.C | H48: [+] | I48: Conversion cost | O48: =8720.586/O53*10^3 -> 355.94229 | P48: =8720.586/P53*10^3 -> 355.94229 | Q48: =8720.586/Q53*10^3 -> 355.94229 | R48: =8720.586/R53*10^3 -> 355.94229 | S48: =8720.586/S53*10^3 -> 355.94229 | T48: =8720.586/T53*10^3 -> 355.94229 | U48: =8720.586/U53*10^3 -> 348.82344 | V48: =8720.586/V53*10^3 -> 348.82344 | ... AC48: =8720.586/AC53*10^3 -> 348.82344 | AD48: =9127.69249949/AD53*10^3 -> 365.1077 | AE48: =9127.69249949/AE53*10^3 -> 365.1077 | AF48: =9127.69249949/AF53*10^3 -> 365.1077 | AG48: =8720.586/AG53*10^3 -> 348.82344 | AH48: =8720.586/AH53*10^3 -> 348.82344 | AI48: =8720.586/AI53*10^3 -> 348.82344 | AJ48: =8720.586/AJ53*10^3 -> 348.82344 | AK48: =8720.586/AK53*10^3 -> 348.82344 | AL48: =8720.586/AL53*10^3 -> 348.82344
A49: 105263 | B49: 110000339 | F49: 3.2.D | H49: [+] | I49: Chi phí vận chuyển | O49: =299/O53*10^3 -> 12.204082 | P49: =299/P53*10^3 -> 12.204082 | Q49: =299/Q53*10^3 -> 12.204082 | R49: =299/R53*10^3 -> 12.204082 | S49: =299/S53*10^3 -> 12.204082 | T49: =299/T53*10^3 -> 12.204082 | U49: =299/U53*10^3 -> 11.96 | V49: =299/V53*10^3 -> 11.96 | ... AL49: =299/AL53*10^3 -> 11.96
A50: 105263 | B50: 110000339 | F50: 3.2.E | H50: [+] | I50: Lợi nhuận trước thuế (EBT) | O50: =1248/O53*10^3 -> 50.938776 | P50: =1248/P53*10^3 -> 50.938776 | Q50: =1248/Q53*10^3 -> 50.938776 | R50: =1248/R53*10^3 -> 50.938776 | S50: =1248/S53*10^3 -> 50.938776 | T50: =1248/T53*10^3 -> 50.938776 | U50: =1248/U53*10^3 -> 49.92 | V50: =1248/V53*10^3 -> 49.92 | ... AL50: =1248/AL53*10^3 -> 49.92
A51: 105263 | B51: 110000339 | F51: 3.2.F | H51: [+] | I51: Interest (lãi vay) | O51: =8%*SUM(O46:O50)*2/12 -> 20.43719 | P51: =8%*SUM(P46:P50)*2/12 -> 20.43719 | Q51: =8%*SUM(Q46:Q50)*2/12 -> 20.43719 | R51: =8%*SUM(R46:R50)*2/12 -> 19.44723 | S51: =8%*SUM(S46:S50)*2/12 -> 19.44723 | T51: =8%*SUM(T46:T50)*2/12 -> 19.44723 | U51: =8%*SUM(U46:U50)*2/12 -> 19.058286 | V51: =8%*SUM(V46:V50)*2/12 -> 19.058286 | ... AL51: =8%*SUM(AL46:AL50)*2/12 -> 19.058286
A52: 105263 | B52: 110000339 | F52: 3.2.G | H52: [+] | I52: Chiết khấu | O52: -50 | P52: -50 | Q52: -50 | R52: -50 | S52: -50 | T52: -50 | U52: -20 | V52: -20 | W52: -20 | X52: -20 | Y52: -20 | Z52: -20 | AA52: -50 | AB52: -50 | AC52: -50 | AD52: -180 | AE52: -180 | AF52: -180 | AG52: -70 | AH52: -70 | AI52: -70 | AJ52: -70 | AK52: -70 | AL52: -70
A53: 105263 | B53: 110000339 | J53: Exchange rate | O53: 24500 | P53: 24500 | Q53: 24500 | R53: 24500 | S53: 24500 | T53: 24500 | U53: 25000 | V53: 25000 | W53: 25000 | X53: 25000 | Y53: 25000 | Z53: 25000 | AA53: 25000 | AB53: 25000 | AC53: 25000 | AD53: 25000 | AE53: 25000 | AF53: 25000 | AG53: 25000 | AH53: 25000 | AI53: 25000 | AJ53: 25000 | AK53: 25000 | AL53: 25000
A54: 105263 | B54: 110000339 | J54: %Hao hụt | O54: 0.2127 | P54: 0.2127 | Q54: 0.2127 | R54: 0.2127 | S54: 0.2127 | T54: 0.2127 | U54: 0.2127 | V54: 0.2127 | W54: 0.2127 | X54: 0.2127 | Y54: 0.2127 | Z54: 0.2127 | AA54: 0.2127 | AB54: 0.2127 | AC54: 0.2127 | AD54: 0.2127 | AE54: 0.2127 | AF54: 0.2127 | AG54: 0.2127 | AH54: 0.2127 | AI54: 0.2127 | AJ54: 0.2127 | AK54: 0.2127 | AL54: 0.2127
A55: 105263 | B55: 110000339 | D55: EXW | F55: 3.2.1 | I55: Giá bán quy đổi EXW | O55: =O45-O49 -> 1487.7959 | P55: =P45-P49 -> 1487.7959 | Q55: =Q45-Q49 -> 1487.7959 | R55: =R45-R49 -> 1417.7959 | S55: =S45-S49 -> 1417.7959 | T55: =T45-T49 -> 1417.7959 | U55: =U45-U49 -> 1418.04 | V55: =V45-V49 -> 1418.04 | ... AL55: =AL45-AL49 -> 1368.04
A56: 105263 | B56: 110000339 | F56: 3.2.2 | J56: Giá duyệt tháng | O56: {=SUMPRODUCT(General_Data*(Year=O$3)*(Month=O$4)*(Code_General_Data=$B56))} -> 1350 | P56: {=SUMPRODUCT(General_Data*(Year=P$3)*(Month=P$4)*(Code_General_Data=$B56))} -> 1350 | Q56: {=SUMPRODUCT(General_Data*(Year=Q$3)*(Month=Q$4)*(Code_General_Data=$B56))} -> 1350 | R56: {=SUMPRODUCT(General_Data*(Year=R$3)*(Month=R$4)*(Code_General_Data=$B56))} -> 1350 | S56: {=SUMPRODUCT(General_Data*(Year=S$3)*(Month=S$4)*(Code_General_Data=$B56))} -> 1350 | T56: {=SUMPRODUCT(General_Data*(Year=T$3)*(Month=T$4)*(Code_General_Data=$B56))} -> 1350 | U56: {=SUMPRODUCT(General_Data*(Year=U$3)*(Month=U$4)*(Code_General_Data=$B56))} -> 1350 | V56: {=SUMPRODUCT(General_Data*(Year=V$3)*(Month=V$4)*(Code_General_Data=$B56))} -> 1350 | ... AL56: {=SUMPRODUCT(General_Data*(Year=AL$3)*(Month=AL$4)*(Code_General_Data=$B56))} -> 1200
A58: 105263 | B58: 110000481 | D58: GB | F58: 3.3 | H58: GIÁ BÁN PCF01 (DDP) | AA58: =AA59 -> 1400 | AB58: =AB59 -> 1400 | AC58: =AC59 -> 1400 | AD58: =AD59 -> 1350 | AE58: =AE59 -> 1350 | AF58: =AF59 -> 1350 | AG58: =AG59 -> 1380 | AH58: =AH59 -> 1380 | ... AL58: =AL59 -> 1380
A59: 105263 | B59: 110000481 | F59: 3.3.A | H59: [+] | I59: Giá bán MBF01 | AA59: =AA45 -> 1400 | AB59: =AB45 -> 1400 | AC59: =AC45 -> 1400 | AD59: =AD45 -> 1350 | AE59: =AE45 -> 1350 | AF59: =AF45 -> 1350 | AG59: =AG45 -> 1380 | AH59: =AH45 -> 1380 | ... AL59: =AL45 -> 1380
A60: 105263 | B60: 110000481 | D60: EXW | F60: 3.3.1 | I60: Giá bán quy đổi EXW | AA60: =AA55 -> 1388.04 | AB60: =AB55 -> 1388.04 | AC60: =AC55 -> 1388.04 | AD60: =AD55 -> 1338.04 | AE60: =AE55 -> 1338.04 | AF60: =AF55 -> 1338.04 | AG60: =AG55 -> 1368.04 | AH60: =AH55 -> 1368.04 | ... AL60: =AL55 -> 1368.04
A61: 105263 | B61: 110000481 | F61: 3.3.2 | J61: Giá duyệt tháng | AA61: {=SUMPRODUCT(General_Data*(Year=AA$3)*(Month=AA$4)*(Code_General_Data=$B61))} -> 1400 | AB61: {=SUMPRODUCT(General_Data*(Year=AB$3)*(Month=AB$4)*(Code_General_Data=$B61))} -> 1400 | AC61: {=SUMPRODUCT(General_Data*(Year=AC$3)*(Month=AC$4)*(Code_General_Data=$B61))} -> 1350 | AD61: {=SUMPRODUCT(General_Data*(Year=AD$3)*(Month=AD$4)*(Code_General_Data=$B61))} -> 1350 | AE61: {=SUMPRODUCT(General_Data*(Year=AE$3)*(Month=AE$4)*(Code_General_Data=$B61))} -> 1350 | AF61: {=SUMPRODUCT(General_Data*(Year=AF$3)*(Month=AF$4)*(Code_General_Data=$B61))} -> 1350 | AG61: {=SUMPRODUCT(General_Data*(Year=AG$3)*(Month=AG$4)*(Code_General_Data=$B61))} -> 1350 | AH61: {=SUMPRODUCT(General_Data*(Year=AH$3)*(Month=AH$4)*(Code_General_Data=$B61))} -> 1330 | ... AL61: {=SUMPRODUCT(General_Data*(Year=AL$3)*(Month=AL$4)*(Code_General_Data=$B61))} -> 1300
A63: 105263 | B63: RHDPETHOI-MAU | D63: GB | F63: 3.4 | H63: GIÁ BÁN rHDPE thổi màu-khử mùi (DDP) | O63: =ROUND(SUM(O64:O65),-1) -> 1450 | P63: =ROUND(SUM(P64:P65),-1) -> 1450 | Q63: =ROUND(SUM(Q64:Q65),-1) -> 1450 | R63: =ROUND(SUM(R64:R65),-1) -> 1380 | S63: =ROUND(SUM(S64:S65),-1) -> 1380 | T63: =ROUND(SUM(T64:T65),-1) -> 1380 | U63: =ROUND(SUM(U64:U65),-1) -> 1380 | V63: =ROUND(SUM(V64:V65),-1) -> 1380 | ... AL63: =ROUND(SUM(AL64:AL65),-1) -> 1330
A64: 105263 | B64: RHDPETHOI-MAU | F64: 3.4.A | H64: [+] | I64: Giá PCF01/MBF01 | O64: =O45 -> 1500 | P64: =P45 -> 1500 | Q64: =Q45 -> 1500 | R64: =R45 -> 1430 | S64: =S45 -> 1430 | T64: =T45 -> 1430 | U64: =U45 -> 1430 | V64: =V45 -> 1430 | ... Z64: =Z45 -> 1430 | AA64: =AA58 -> 1400 | AB64: =AB58 -> 1400 | AC64: =AC58 -> 1400 | AD64: =AD58 -> 1350 | AE64: =AE58 -> 1350 | AF64: =AF58 -> 1350 | AG64: =AG58 -> 1380 | AH64: =AH58 -> 1380 | ... AL64: =AL58 -> 1380
A65: 105263 | B65: RHDPETHOI-MAU | F65: 3.4.B | H65: [+] | I65: Chiết khấu | O65: -50 | P65: -50 | Q65: -50 | R65: -50 | S65: -50 | T65: -50 | U65: -50 | V65: -50 | W65: -50 | X65: -50 | Y65: -50 | Z65: -50 | AA65: -50 | AB65: -50 | AC65: -50 | AD65: -50 | AE65: -50 | AF65: -50 | AG65: -50 | AH65: -50 | AI65: -50 | AJ65: -50 | AK65: -50 | AL65: -50
A66: 105263 | B66: RHDPETHOI-MAU | D66: EXW | F66: 3.4.1 | I66: Giá bán quy đổi EXW | O66: =O63-O49 -> 1437.7959 | P66: =P63-P49 -> 1437.7959 | Q66: =Q63-Q49 -> 1437.7959 | R66: =R63-R49 -> 1367.7959 | S66: =S63-S49 -> 1367.7959 | T66: =T63-T49 -> 1367.7959 | U66: =U63-U49 -> 1368.04 | V66: =V63-V49 -> 1368.04 | ... AL66: =AL63-AL49 -> 1318.04
A67: 105263 | B67: RHDPETHOI-MAU | F67: 3.4.2 | J67: Giá duyệt tháng | O67: {=SUMPRODUCT(General_Data*(Year=O$3)*(Month=O$4)*(Code_General_Data=$B67))} -> 1350 | P67: {=SUMPRODUCT(General_Data*(Year=P$3)*(Month=P$4)*(Code_General_Data=$B67))} -> 1350 | Q67: {=SUMPRODUCT(General_Data*(Year=Q$3)*(Month=Q$4)*(Code_General_Data=$B67))} -> 1350 | R67: {=SUMPRODUCT(General_Data*(Year=R$3)*(Month=R$4)*(Code_General_Data=$B67))} -> 1350 | S67: {=SUMPRODUCT(General_Data*(Year=S$3)*(Month=S$4)*(Code_General_Data=$B67))} -> 1350 | T67: {=SUMPRODUCT(General_Data*(Year=T$3)*(Month=T$4)*(Code_General_Data=$B67))} -> 1350 | U67: {=SUMPRODUCT(General_Data*(Year=U$3)*(Month=U$4)*(Code_General_Data=$B67))} -> 1350 | V67: {=SUMPRODUCT(General_Data*(Year=V$3)*(Month=V$4)*(Code_General_Data=$B67))} -> 1350 | ... AL67: {=SUMPRODUCT(General_Data*(Year=AL$3)*(Month=AL$4)*(Code_General_Data=$B67))} -> 1250
A69: 105194 | F69: 4 | G69: SUNTORY VIỆT NAM
A70: 105194 | B70: 110000332 | D70: GB | F70: 4.1 | H70: GIÁ BÁN iSS1084G (DDP) | O70: =SUM(O71:O74) -> 1366.5 | P70: =SUM(P71:P74) -> 1374 | Q70: =SUM(Q71:Q74) -> 1386.5 | R70: =SUM(R71:R74) -> 1389 | S70: =SUM(S71:S74) -> 1393 | T70: =SUM(T71:T74) -> 1408 | U70: =SUM(U71:U74) -> 1424 | V70: =SUM(V71:V74) -> 1435 | ... Z70: =SUM(Z71:Z74) -> 1504 | AA70: =MIN(MAX(SUM(AA71,AA72),AA78),AA77)+AA73+AA74 -> 1402.2188 | AB70: =MIN(MAX(SUM(AB71,AB72),AB78),AB77)+AB73+AB74 -> 1365.8021 | AC70: =MIN(MAX(SUM(AC71,AC72),AC78),AC77)+AC73+AC74 -> 1331.9583 | AD70: =MIN(MAX(SUM(AD71,AD72),AD78),AD77)+AD73+AD74 -> 1332.75 | AE70: =MIN(MAX(SUM(AE71,AE72),AE78),AE77)+AE73+AE74 -> 1337.5 | AF70: =MIN(MAX(SUM(AF71,AF72),AF78),AF77)+AF73+AF74 -> 1337.5 | AG70: =MIN(MAX(SUM(AG71,AG72),AG78),AG77)+AG73+AG74 -> 1337.5 | AH70: =MIN(MAX(SUM(AH71,AH72),AH78),AH77)+AH73+AH74 -> 1320.4 | ... AL70: =MIN(MAX(SUM(AL71,AL72),AL78),AL77)+AL73+AL74 -> 1293.1562
A71: 105194 | B71: 110000332 | F71: 4.1.A | H71: [+] | I71: ICIS Bales - SEA trung bình 2 tháng trước | O71: =(M76+N76)/2 -> 1300 | P71: =(N76+O76)/2 -> 1307.5 | Q71: =(O76+P76)/2 -> 1320 | R71: =(P76+Q76)/2 -> 1322.5 | S71: =(Q76+R76)/2 -> 1326.5 | T71: =(R76+S76)/2 -> 1341.5 | U71: =(S76+T76)/2 -> 1357.5 | V71: =(T76+U76)/2 -> 1368.5 | ... AL71: =(AJ76+AK76)/2 -> 1246.875
A72: 105194 | B72: 110000332 | F72: 4.1.B | H72: [+] | I72: Premium (2025: $20; 2024: $50) | O72: 50 | P72: 50 | Q72: 50 | R72: 50 | S72: 50 | T72: 50 | U72: 50 | V72: 50 | W72: 50 | X72: 50 | Y72: 50 | Z72: 50 | AA72: 20 | AB72: 20 | AC72: 20 | AD72: 20 | AE72: 20 | AF72: 20 | AG72: 20 | AH72: 20 | AI72: 20 | AJ72: 20 | AK72: 20 | AL72: 20
A73: 105194 | B73: 110000332 | F73: 4.1.C | H73: [+] | I73: Rebate (2025: 6000-7000 tấn ~ 5% giá trị) | O73: =-IF('Rebate-Suntory'!$E$14="/tấn",'Rebate-Suntory'!$D$14,IF('Rebate-Suntory'!$E$14="giá trị",'Rebate-Suntory'!$D$14*(O71+O72+O74),0)) -> -10 | P73: =-IF('Rebate-Suntory'!$E$14="/tấn",'Rebate-Suntory'!$D$14,IF('Rebate-Suntory'!$E$14="giá trị",'Rebate-Suntory'!$D$14*(P71+P72+P74),0)) -> -10 | Q73: =-IF('Rebate-Suntory'!$E$14="/tấn",'Rebate-Suntory'!$D$14,IF('Rebate-Suntory'!$E$14="giá trị",'Rebate-Suntory'!$D$14*(Q71+Q72+Q74),0)) -> -10 | R73: =-IF('Rebate-Suntory'!$E$14="/tấn",'Rebate-Suntory'!$D$14,IF('Rebate-Suntory'!$E$14="giá trị",'Rebate-Suntory'!$D$14*(R71+R72+R74),0)) -> -10 | S73: =-IF('Rebate-Suntory'!$E$14="/tấn",'Rebate-Suntory'!$D$14,IF('Rebate-Suntory'!$E$14="giá trị",'Rebate-Suntory'!$D$14*(S71+S72+S74),0)) -> -10 | T73: =-IF('Rebate-Suntory'!$E$14="/tấn",'Rebate-Suntory'!$D$14,IF('Rebate-Suntory'!$E$14="giá trị",'Rebate-Suntory'!$D$14*(T71+T72+T74),0)) -> -10 | U73: =-IF('Rebate-Suntory'!$E$14="/tấn",'Rebate-Suntory'!$D$14,IF('Rebate-Suntory'!$E$14="giá trị",'Rebate-Suntory'!$D$14*(U71+U72+U74),0)) -> -10 | V73: =-IF('Rebate-Suntory'!$E$14="/tấn",'Rebate-Suntory'!$D$14,IF('Rebate-Suntory'!$E$14="giá trị",'Rebate-Suntory'!$D$14*(V71+V72+V74),0)) -> -10 | ... Z73: =-IF('Rebate-Suntory'!$E$14="/tấn",'Rebate-Suntory'!$D$14,IF('Rebate-Suntory'!$E$14="giá trị",'Rebate-Suntory'!$D$14*(Z71+Z72+Z74),0)) -> -10 | AA73: =-IF('Rebate-Suntory'!$J$14="/tấn",'Rebate-Suntory'!$I$14,IF('Rebate-Suntory'!$J$14="giá trị",'Rebate-Suntory'!$I$14*(AA71+AA72),0)) -> -72.40625 | AB73: =-IF('Rebate-Suntory'!$J$14="/tấn",'Rebate-Suntory'!$I$14,IF('Rebate-Suntory'!$J$14="giá trị",'Rebate-Suntory'!$I$14*(AB71+AB72),0)) -> -70.489583 | AC73: =-IF('Rebate-Suntory'!$J$14="/tấn",'Rebate-Suntory'!$I$14,IF('Rebate-Suntory'!$J$14="giá trị",'Rebate-Suntory'!$I$14*(AC71+AC72),0)) -> -68.708333 | AD73: =-IF('Rebate-Suntory'!$J$14="/tấn",'Rebate-Suntory'!$I$14,IF('Rebate-Suntory'!$J$14="giá trị",'Rebate-Suntory'!$I$14*(AD71+AD72),0)) -> -68.75 | AE73: =-IF('Rebate-Suntory'!$J$14="/tấn",'Rebate-Suntory'!$I$14,IF('Rebate-Suntory'!$J$14="giá trị",'Rebate-Suntory'!$I$14*(AE71+AE72),0)) -> -69 | AF73: =-IF('Rebate-Suntory'!$J$14="/tấn",'Rebate-Suntory'!$I$14,IF('Rebate-Suntory'!$J$14="giá trị",'Rebate-Suntory'!$I$14*(AF71+AF72),0)) -> -69 | AG73: =-IF('Rebate-Suntory'!$J$14="/tấn",'Rebate-Suntory'!$I$14,IF('Rebate-Suntory'!$J$14="giá trị",'Rebate-Suntory'!$I$14*(AG71+AG72),0)) -> -69 | AH73: =-IF('Rebate-Suntory'!$J$14="/tấn",'Rebate-Suntory'!$I$14,IF('Rebate-Suntory'!$J$14="giá trị",'Rebate-Suntory'!$I$14*(AH71+AH72),0)) -> -68.1 | ... AL73: =-IF('Rebate-Suntory'!$J$14="/tấn",'Rebate-Suntory'!$I$14,IF('Rebate-Suntory'!$J$14="giá trị",'Rebate-Suntory'!$I$14*(AL71+AL72),0)) -> -63.34375
A74: 105194 | B74: 110000332 | F74: 4.1.D | H74: [+] | I74: CP vận chuyển-Miền Bắc | O74: 26.5 | P74: 26.5 | Q74: 26.5 | R74: 26.5 | S74: 26.5 | T74: 26.5 | U74: 26.5 | V74: 26.5 | W74: 26.5 | X74: 26.5 | Y74: 26.5 | Z74: 26.5 | AA74: 26.5 | AB74: 26.5 | AC74: 26.5 | AD74: 26.5 | AE74: 26.5 | AF74: 26.5 | AG74: 26.5 | AH74: 26.5 | AI74: 26.5 | AJ74: 26.5 | AK74: 26.5 | AL74: 26.5
A75: 105194 | B75: 110000332 | D75: EXW | F75: 4.1.1 | I75: Giá bán quy đổi EXW | O75: =O70-O74 -> 1340 | P75: =P70-P74 -> 1347.5 | Q75: =Q70-Q74 -> 1360 | R75: =R70-R74 -> 1362.5 | S75: =S70-S74 -> 1366.5 | T75: =T70-T74 -> 1381.5 | U75: =U70-U74 -> 1397.5 | V75: =V70-V74 -> 1408.5 | ... AL75: =AL70-AL74 -> 1266.6562
A76: 105194 | B76: 110000332 | C76: 04 | J76: ICIS Bales - SEA | L76: {=SUMPRODUCT(General_Data*(Year=L$3)*(Month=L$4)*(Code_General_Data=$C76))} -> 1288.125 | M76: {=SUMPRODUCT(General_Data*(Year=M$3)*(Month=M$4)*(Code_General_Data=$C76))} -> 1300 | N76: {=SUMPRODUCT(General_Data*(Year=N$3)*(Month=N$4)*(Code_General_Data=$C76))} -> 1300 | O76: {=SUMPRODUCT(General_Data*(Year=O$3)*(Month=O$4)*(Code_General_Data=$C76))} -> 1315 | P76: {=SUMPRODUCT(General_Data*(Year=P$3)*(Month=P$4)*(Code_General_Data=$C76))} -> 1325 | Q76: {=SUMPRODUCT(General_Data*(Year=Q$3)*(Month=Q$4)*(Code_General_Data=$C76))} -> 1320 | R76: {=SUMPRODUCT(General_Data*(Year=R$3)*(Month=R$4)*(Code_General_Data=$C76))} -> 1333 | S76: {=SUMPRODUCT(General_Data*(Year=S$3)*(Month=S$4)*(Code_General_Data=$C76))} -> 1350 | ... AL76: {=SUMPRODUCT(General_Data*(Year=AL$3)*(Month=AL$4)*(Code_General_Data=$C76))} -> 0
A77: 105194 | B77: 110000332 | F77: 4.1.2 | J77: Giá trần | O77: {=INDEX(Note!$J$3:$J$101,MATCH(1,(Note!$A$3:$A$101=$A77)*(Note!$C$3:$C$101=$B77)*(Note!$E$3:$E$101<=O$1)*(Note!$F$3:$F$101>=O$2),0))} -> 0 | P77: {=INDEX(Note!$J$3:$J$101,MATCH(1,(Note!$A$3:$A$101=$A77)*(Note!$C$3:$C$101=$B77)*(Note!$E$3:$E$101<=P$1)*(Note!$F$3:$F$101>=P$2),0))} -> 0 | Q77: {=INDEX(Note!$J$3:$J$101,MATCH(1,(Note!$A$3:$A$101=$A77)*(Note!$C$3:$C$101=$B77)*(Note!$E$3:$E$101<=Q$1)*(Note!$F$3:$F$101>=Q$2),0))} -> 0 | R77: {=INDEX(Note!$J$3:$J$101,MATCH(1,(Note!$A$3:$A$101=$A77)*(Note!$C$3:$C$101=$B77)*(Note!$E$3:$E$101<=R$1)*(Note!$F$3:$F$101>=R$2),0))} -> 0 | S77: {=INDEX(Note!$J$3:$J$101,MATCH(1,(Note!$A$3:$A$101=$A77)*(Note!$C$3:$C$101=$B77)*(Note!$E$3:$E$101<=S$1)*(Note!$F$3:$F$101>=S$2),0))} -> 0 | T77: {=INDEX(Note!$J$3:$J$101,MATCH(1,(Note!$A$3:$A$101=$A77)*(Note!$C$3:$C$101=$B77)*(Note!$E$3:$E$101<=T$1)*(Note!$F$3:$F$101>=T$2),0))} -> 0 | U77: {=INDEX(Note!$J$3:$J$101,MATCH(1,(Note!$A$3:$A$101=$A77)*(Note!$C$3:$C$101=$B77)*(Note!$E$3:$E$101<=U$1)*(Note!$F$3:$F$101>=U$2),0))} -> 0 | V77: {=INDEX(Note!$J$3:$J$101,MATCH(1,(Note!$A$3:$A$101=$A77)*(Note!$C$3:$C$101=$B77)*(Note!$E$3:$E$101<=V$1)*(Note!$F$3:$F$101>=V$2),0))} -> 0 | ... AL77: {=INDEX(Note!$J$3:$J$101,MATCH(1,(Note!$A$3:$A$101=$A77)*(Note!$C$3:$C$101=$B77)*(Note!$E$3:$E$101<=AL$1)*(Note!$F$3:$F$101>=AL$2),0))} -> 1550
A78: 105194 | B78: 110000332 | F78: 4.1.3 | J78: Giá sàn | O78: {=INDEX(Note!$K$3:$K$101,MATCH(1,(Note!$A$3:$A$101=$A78)*(Note!$C$3:$C$101=$B78)*(Note!$E$3:$E$101<=O$1)*(Note!$F$3:$F$101>=O$2),0))} -> 0 | P78: {=INDEX(Note!$K$3:$K$101,MATCH(1,(Note!$A$3:$A$101=$A78)*(Note!$C$3:$C$101=$B78)*(Note!$E$3:$E$101<=P$1)*(Note!$F$3:$F$101>=P$2),0))} -> 0 | Q78: {=INDEX(Note!$K$3:$K$101,MATCH(1,(Note!$A$3:$A$101=$A78)*(Note!$C$3:$C$101=$B78)*(Note!$E$3:$E$101<=Q$1)*(Note!$F$3:$F$101>=Q$2),0))} -> 0 | R78: {=INDEX(Note!$K$3:$K$101,MATCH(1,(Note!$A$3:$A$101=$A78)*(Note!$C$3:$C$101=$B78)*(Note!$E$3:$E$101<=R$1)*(Note!$F$3:$F$101>=R$2),0))} -> 0 | S78: {=INDEX(Note!$K$3:$K$101,MATCH(1,(Note!$A$3:$A$101=$A78)*(Note!$C$3:$C$101=$B78)*(Note!$E$3:$E$101<=S$1)*(Note!$F$3:$F$101>=S$2),0))} -> 0 | T78: {=INDEX(Note!$K$3:$K$101,MATCH(1,(Note!$A$3:$A$101=$A78)*(Note!$C$3:$C$101=$B78)*(Note!$E$3:$E$101<=T$1)*(Note!$F$3:$F$101>=T$2),0))} -> 0 | U78: {=INDEX(Note!$K$3:$K$101,MATCH(1,(Note!$A$3:$A$101=$A78)*(Note!$C$3:$C$101=$B78)*(Note!$E$3:$E$101<=U$1)*(Note!$F$3:$F$101>=U$2),0))} -> 0 | V78: {=INDEX(Note!$K$3:$K$101,MATCH(1,(Note!$A$3:$A$101=$A78)*(Note!$C$3:$C$101=$B78)*(Note!$E$3:$E$101<=V$1)*(Note!$F$3:$F$101>=V$2),0))} -> 0 | ... AL78: {=INDEX(Note!$K$3:$K$101,MATCH(1,(Note!$A$3:$A$101=$A78)*(Note!$C$3:$C$101=$B78)*(Note!$E$3:$E$101<=AL$1)*(Note!$F$3:$F$101>=AL$2),0))} -> 1330
A79: 105194 | B79: 110000332 | F79: 4.1.4 | J79: Giá duyệt tháng | O79: {=SUMPRODUCT(General_Data*(Year=O$3)*(Month=O$4)*(Code_General_Data=$B79))} -> 1340 | P79: {=SUMPRODUCT(General_Data*(Year=P$3)*(Month=P$4)*(Code_General_Data=$B79))} -> 1340 | Q79: {=SUMPRODUCT(General_Data*(Year=Q$3)*(Month=Q$4)*(Code_General_Data=$B79))} -> 1340 | R79: {=SUMPRODUCT(General_Data*(Year=R$3)*(Month=R$4)*(Code_General_Data=$B79))} -> 1340 | S79: {=SUMPRODUCT(General_Data*(Year=S$3)*(Month=S$4)*(Code_General_Data=$B79))} -> 1390 | T79: {=SUMPRODUCT(General_Data*(Year=T$3)*(Month=T$4)*(Code_General_Data=$B79))} -> 1390 | U79: {=SUMPRODUCT(General_Data*(Year=U$3)*(Month=U$4)*(Code_General_Data=$B79))} -> 1390 | V79: {=SUMPRODUCT(General_Data*(Year=V$3)*(Month=V$4)*(Code_General_Data=$B79))} -> 1390 | ... AL79: {=SUMPRODUCT(General_Data*(Year=AL$3)*(Month=AL$4)*(Code_General_Data=$B79))} -> 1290
J80: Giá trần - quy đổi EXW | AA80: =AA77+AA73 -> 1477.5938 | AB80: =AB77+AB73 -> 1479.5104 | AC80: =AC77+AC73 -> 1481.2917 | AD80: =AD77+AD73 -> 1481.25 | AE80: =AE77+AE73 -> 1481 | AF80: =AF77+AF73 -> 1481 | AG80: =AG77+AG73 -> 1481 | AH80: =AH77+AH73 -> 1481.9 | ... AL80: =AL77+AL73 -> 1486.6562
J81: Giá sàn - quy đổi EXW | AA81: =AA78+AA73 -> 1257.5938 | AB81: =AB78+AB73 -> 1259.5104 | AC81: =AC78+AC73 -> 1261.2917 | AD81: =AD78+AD73 -> 1261.25 | AE81: =AE78+AE73 -> 1261 | AF81: =AF78+AF73 -> 1261 | AG81: =AG78+AG73 -> 1261 | AH81: =AH78+AH73 -> 1261.9 | ... AL81: =AL78+AL73 -> 1266.6562
A83: 105194 | B83: 110000355 | D83: GB | F83: 4.2 | H83: GIÁ BÁN iSS01G (DDP) | O83: =SUM(O84:O87) -> 1346.5 | P83: =SUM(P84:P87) -> 1354 | Q83: =SUM(Q84:Q87) -> 1366.5 | R83: =SUM(R84:R87) -> 1369 | S83: =SUM(S84:S87) -> 1373 | T83: =SUM(T84:T87) -> 1388 | U83: =SUM(U84:U87) -> 1404 | V83: =SUM(V84:V87) -> 1415 | ... Z83: =SUM(Z84:Z87) -> 1484 | AA83: =MIN(MAX(SUM(AA84,AA85),AA91),AA90)+AA86+AA87 -> 1402.2188 | AB83: =MIN(MAX(SUM(AB84,AB85),AB91),AB90)+AB86+AB87 -> 1365.8021 | AC83: =MIN(MAX(SUM(AC84,AC85),AC91),AC90)+AC86+AC87 -> 1331.9583 | AD83: =MIN(MAX(SUM(AD84,AD85),AD91),AD90)+AD86+AD87 -> 1332.75 | AE83: =MIN(MAX(SUM(AE84,AE85),AE91),AE90)+AE86+AE87 -> 1337.5 | AF83: =MIN(MAX(SUM(AF84,AF85),AF91),AF90)+AF86+AF87 -> 1337.5 | AG83: =MIN(MAX(SUM(AG84,AG85),AG91),AG90)+AG86+AG87 -> 1337.5 | AH83: =MIN(MAX(SUM(AH84,AH85),AH91),AH90)+AH86+AH87 -> 1320.4 | ... AL83: =MIN(MAX(SUM(AL84,AL85),AL91),AL90)+AL86+AL87 -> 1293.1562
A84: 105194 | B84: 110000355 | F84: 4.2.A | H84: [+] | I84: ICIS Bales - SEA trung bình 2 tháng trước | O84: =(M89+N89)/2 -> 1300 | P84: =(N89+O89)/2 -> 1307.5 | Q84: =(O89+P89)/2 -> 1320 | R84: =(P89+Q89)/2 -> 1322.5 | S84: =(Q89+R89)/2 -> 1326.5 | T84: =(R89+S89)/2 -> 1341.5 | U84: =(S89+T89)/2 -> 1357.5 | V84: =(T89+U89)/2 -> 1368.5 | ... AL84: =(AJ89+AK89)/2 -> 1246.875
A85: 105194 | B85: 110000355 | F85: 4.2.B | H85: [+] | I85: Premium (2025: $20; 2024: $30) | O85: 30 | P85: 30 | Q85: 30 | R85: 30 | S85: 30 | T85: 30 | U85: 30 | V85: 30 | W85: 30 | X85: 30 | Y85: 30 | Z85: 30 | AA85: 20 | AB85: 20 | AC85: 20 | AD85: 20 | AE85: 20 | AF85: 20 | AG85: 20 | AH85: 20 | AI85: 20 | AJ85: 20 | AK85: 20 | AL85: 20
A86: 105194 | B86: 110000355 | F86: 4.2.C | H86: [+] | I86: Rebate (2025: 6000-7000 tấn ~ 5% giá trị) | O86: =-IF('Rebate-Suntory'!$E$14="/tấn",'Rebate-Suntory'!$D$14,IF('Rebate-Suntory'!$E$14="giá trị",'Rebate-Suntory'!$D$14*(O84+O85+O87),0)) -> -10 | P86: =-IF('Rebate-Suntory'!$E$14="/tấn",'Rebate-Suntory'!$D$14,IF('Rebate-Suntory'!$E$14="giá trị",'Rebate-Suntory'!$D$14*(P84+P85+P87),0)) -> -10 | Q86: =-IF('Rebate-Suntory'!$E$14="/tấn",'Rebate-Suntory'!$D$14,IF('Rebate-Suntory'!$E$14="giá trị",'Rebate-Suntory'!$D$14*(Q84+Q85+Q87),0)) -> -10 | R86: =-IF('Rebate-Suntory'!$E$14="/tấn",'Rebate-Suntory'!$D$14,IF('Rebate-Suntory'!$E$14="giá trị",'Rebate-Suntory'!$D$14*(R84+R85+R87),0)) -> -10 | S86: =-IF('Rebate-Suntory'!$E$14="/tấn",'Rebate-Suntory'!$D$14,IF('Rebate-Suntory'!$E$14="giá trị",'Rebate-Suntory'!$D$14*(S84+S85+S87),0)) -> -10 | T86: =-IF('Rebate-Suntory'!$E$14="/tấn",'Rebate-Suntory'!$D$14,IF('Rebate-Suntory'!$E$14="giá trị",'Rebate-Suntory'!$D$14*(T84+T85+T87),0)) -> -10 | U86: =-IF('Rebate-Suntory'!$E$14="/tấn",'Rebate-Suntory'!$D$14,IF('Rebate-Suntory'!$E$14="giá trị",'Rebate-Suntory'!$D$14*(U84+U85+U87),0)) -> -10 | V86: =-IF('Rebate-Suntory'!$E$14="/tấn",'Rebate-Suntory'!$D$14,IF('Rebate-Suntory'!$E$14="giá trị",'Rebate-Suntory'!$D$14*(V84+V85+V87),0)) -> -10 | ... Z86: =-IF('Rebate-Suntory'!$E$14="/tấn",'Rebate-Suntory'!$D$14,IF('Rebate-Suntory'!$E$14="giá trị",'Rebate-Suntory'!$D$14*(Z84+Z85+Z87),0)) -> -10 | AA86: =-IF('Rebate-Suntory'!$J$14="/tấn",'Rebate-Suntory'!$I$14,IF('Rebate-Suntory'!$J$14="giá trị",'Rebate-Suntory'!$I$14*(AA84+AA85),0)) -> -72.40625 | AB86: =-IF('Rebate-Suntory'!$J$14="/tấn",'Rebate-Suntory'!$I$14,IF('Rebate-Suntory'!$J$14="giá trị",'Rebate-Suntory'!$I$14*(AB84+AB85),0)) -> -70.489583 | AC86: =-IF('Rebate-Suntory'!$J$14="/tấn",'Rebate-Suntory'!$I$14,IF('Rebate-Suntory'!$J$14="giá trị",'Rebate-Suntory'!$I$14*(AC84+AC85),0)) -> -68.708333 | AD86: =-IF('Rebate-Suntory'!$J$14="/tấn",'Rebate-Suntory'!$I$14,IF('Rebate-Suntory'!$J$14="giá trị",'Rebate-Suntory'!$I$14*(AD84+AD85),0)) -> -68.75 | AE86: =-IF('Rebate-Suntory'!$J$14="/tấn",'Rebate-Suntory'!$I$14,IF('Rebate-Suntory'!$J$14="giá trị",'Rebate-Suntory'!$I$14*(AE84+AE85),0)) -> -69 | AF86: =-IF('Rebate-Suntory'!$J$14="/tấn",'Rebate-Suntory'!$I$14,IF('Rebate-Suntory'!$J$14="giá trị",'Rebate-Suntory'!$I$14*(AF84+AF85),0)) -> -69 | AG86: =-IF('Rebate-Suntory'!$J$14="/tấn",'Rebate-Suntory'!$I$14,IF('Rebate-Suntory'!$J$14="giá trị",'Rebate-Suntory'!$I$14*(AG84+AG85),0)) -> -69 | AH86: =-IF('Rebate-Suntory'!$J$14="/tấn",'Rebate-Suntory'!$I$14,IF('Rebate-Suntory'!$J$14="giá trị",'Rebate-Suntory'!$I$14*(AH84+AH85),0)) -> -68.1 | ... AL86: =-IF('Rebate-Suntory'!$J$14="/tấn",'Rebate-Suntory'!$I$14,IF('Rebate-Suntory'!$J$14="giá trị",'Rebate-Suntory'!$I$14*(AL84+AL85),0)) -> -63.34375
A87: 105194 | B87: 110000355 | F87: 4.2.D | H87: [+] | I87: CP vận chuyển-Miền Bắc | O87: 26.5 | P87: 26.5 | Q87: 26.5 | R87: 26.5 | S87: 26.5 | T87: 26.5 | U87: 26.5 | V87: 26.5 | W87: 26.5 | X87: 26.5 | Y87: 26.5 | Z87: 26.5 | AA87: 26.5 | AB87: 26.5 | AC87: 26.5 | AD87: 26.5 | AE87: 26.5 | AF87: 26.5 | AG87: 26.5 | AH87: 26.5 | AI87: 26.5 | AJ87: 26.5 | AK87: 26.5 | AL87: 26.5
A88: 105194 | B88: 110000355 | D88: EXW | F88: 4.2.1 | I88: Giá bán quy đổi EXW | O88: =O83-O87 -> 1320 | P88: =P83-P87 -> 1327.5 | Q88: =Q83-Q87 -> 1340 | R88: =R83-R87 -> 1342.5 | S88: =S83-S87 -> 1346.5 | T88: =T83-T87 -> 1361.5 | U88: =U83-U87 -> 1377.5 | V88: =V83-V87 -> 1388.5 | ... AL88: =AL83-AL87 -> 1266.6562
A89: 105194 | B89: 110000355 | C89: 04 | J89: ICIS Bales - SEA | L89: {=SUMPRODUCT(General_Data*(Year=L$3)*(Month=L$4)*(Code_General_Data=$C89))} -> 1288.125 | M89: {=SUMPRODUCT(General_Data*(Year=M$3)*(Month=M$4)*(Code_General_Data=$C89))} -> 1300 | N89: {=SUMPRODUCT(General_Data*(Year=N$3)*(Month=N$4)*(Code_General_Data=$C89))} -> 1300 | O89: {=SUMPRODUCT(General_Data*(Year=O$3)*(Month=O$4)*(Code_General_Data=$C89))} -> 1315 | P89: {=SUMPRODUCT(General_Data*(Year=P$3)*(Month=P$4)*(Code_General_Data=$C89))} -> 1325 | Q89: {=SUMPRODUCT(General_Data*(Year=Q$3)*(Month=Q$4)*(Code_General_Data=$C89))} -> 1320 | R89: {=SUMPRODUCT(General_Data*(Year=R$3)*(Month=R$4)*(Code_General_Data=$C89))} -> 1333 | S89: {=SUMPRODUCT(General_Data*(Year=S$3)*(Month=S$4)*(Code_General_Data=$C89))} -> 1350 | ... AL89: {=SUMPRODUCT(General_Data*(Year=AL$3)*(Month=AL$4)*(Code_General_Data=$C89))} -> 0
A90: 105194 | B90: 110000355 | F90: 4.2.2 | J90: Giá trần | O90: {=INDEX(Note!$J$3:$J$101,MATCH(1,(Note!$A$3:$A$101=$A90)*(Note!$C$3:$C$101=$B90)*(Note!$E$3:$E$101<=O$1)*(Note!$F$3:$F$101>=O$2),0))} -> 0 | P90: {=INDEX(Note!$J$3:$J$101,MATCH(1,(Note!$A$3:$A$101=$A90)*(Note!$C$3:$C$101=$B90)*(Note!$E$3:$E$101<=P$1)*(Note!$F$3:$F$101>=P$2),0))} -> 0 | Q90: {=INDEX(Note!$J$3:$J$101,MATCH(1,(Note!$A$3:$A$101=$A90)*(Note!$C$3:$C$101=$B90)*(Note!$E$3:$E$101<=Q$1)*(Note!$F$3:$F$101>=Q$2),0))} -> 0 | R90: {=INDEX(Note!$J$3:$J$101,MATCH(1,(Note!$A$3:$A$101=$A90)*(Note!$C$3:$C$101=$B90)*(Note!$E$3:$E$101<=R$1)*(Note!$F$3:$F$101>=R$2),0))} -> 0 | S90: {=INDEX(Note!$J$3:$J$101,MATCH(1,(Note!$A$3:$A$101=$A90)*(Note!$C$3:$C$101=$B90)*(Note!$E$3:$E$101<=S$1)*(Note!$F$3:$F$101>=S$2),0))} -> 0 | T90: {=INDEX(Note!$J$3:$J$101,MATCH(1,(Note!$A$3:$A$101=$A90)*(Note!$C$3:$C$101=$B90)*(Note!$E$3:$E$101<=T$1)*(Note!$F$3:$F$101>=T$2),0))} -> 0 | U90: {=INDEX(Note!$J$3:$J$101,MATCH(1,(Note!$A$3:$A$101=$A90)*(Note!$C$3:$C$101=$B90)*(Note!$E$3:$E$101<=U$1)*(Note!$F$3:$F$101>=U$2),0))} -> 0 | V90: {=INDEX(Note!$J$3:$J$101,MATCH(1,(Note!$A$3:$A$101=$A90)*(Note!$C$3:$C$101=$B90)*(Note!$E$3:$E$101<=V$1)*(Note!$F$3:$F$101>=V$2),0))} -> 0 | ... AL90: {=INDEX(Note!$J$3:$J$101,MATCH(1,(Note!$A$3:$A$101=$A90)*(Note!$C$3:$C$101=$B90)*(Note!$E$3:$E$101<=AL$1)*(Note!$F$3:$F$101>=AL$2),0))} -> 1550
A91: 105194 | B91: 110000355 | F91: 4.2.3 | J91: Giá sàn | O91: {=INDEX(Note!$K$3:$K$101,MATCH(1,(Note!$A$3:$A$101=$A91)*(Note!$C$3:$C$101=$B91)*(Note!$E$3:$E$101<=O$1)*(Note!$F$3:$F$101>=O$2),0))} -> 0 | P91: {=INDEX(Note!$K$3:$K$101,MATCH(1,(Note!$A$3:$A$101=$A91)*(Note!$C$3:$C$101=$B91)*(Note!$E$3:$E$101<=P$1)*(Note!$F$3:$F$101>=P$2),0))} -> 0 | Q91: {=INDEX(Note!$K$3:$K$101,MATCH(1,(Note!$A$3:$A$101=$A91)*(Note!$C$3:$C$101=$B91)*(Note!$E$3:$E$101<=Q$1)*(Note!$F$3:$F$101>=Q$2),0))} -> 0 | R91: {=INDEX(Note!$K$3:$K$101,MATCH(1,(Note!$A$3:$A$101=$A91)*(Note!$C$3:$C$101=$B91)*(Note!$E$3:$E$101<=R$1)*(Note!$F$3:$F$101>=R$2),0))} -> 0 | S91: {=INDEX(Note!$K$3:$K$101,MATCH(1,(Note!$A$3:$A$101=$A91)*(Note!$C$3:$C$101=$B91)*(Note!$E$3:$E$101<=S$1)*(Note!$F$3:$F$101>=S$2),0))} -> 0 | T91: {=INDEX(Note!$K$3:$K$101,MATCH(1,(Note!$A$3:$A$101=$A91)*(Note!$C$3:$C$101=$B91)*(Note!$E$3:$E$101<=T$1)*(Note!$F$3:$F$101>=T$2),0))} -> 0 | U91: {=INDEX(Note!$K$3:$K$101,MATCH(1,(Note!$A$3:$A$101=$A91)*(Note!$C$3:$C$101=$B91)*(Note!$E$3:$E$101<=U$1)*(Note!$F$3:$F$101>=U$2),0))} -> 0 | V91: {=INDEX(Note!$K$3:$K$101,MATCH(1,(Note!$A$3:$A$101=$A91)*(Note!$C$3:$C$101=$B91)*(Note!$E$3:$E$101<=V$1)*(Note!$F$3:$F$101>=V$2),0))} -> 0 | ... AL91: {=INDEX(Note!$K$3:$K$101,MATCH(1,(Note!$A$3:$A$101=$A91)*(Note!$C$3:$C$101=$B91)*(Note!$E$3:$E$101<=AL$1)*(Note!$F$3:$F$101>=AL$2),0))} -> 1330
A92: 105194 | B92: 110000355 | F92: 4.2.4 | J92: Giá duyệt tháng | O92: {=SUMPRODUCT(General_Data*(Year=O$3)*(Month=O$4)*(Code_General_Data=$B92))} -> 1280 | P92: {=SUMPRODUCT(General_Data*(Year=P$3)*(Month=P$4)*(Code_General_Data=$B92))} -> 1280 | Q92: {=SUMPRODUCT(General_Data*(Year=Q$3)*(Month=Q$4)*(Code_General_Data=$B92))} -> 1280 | R92: {=SUMPRODUCT(General_Data*(Year=R$3)*(Month=R$4)*(Code_General_Data=$B92))} -> 1280 | S92: {=SUMPRODUCT(General_Data*(Year=S$3)*(Month=S$4)*(Code_General_Data=$B92))} -> 1330 | T92: {=SUMPRODUCT(General_Data*(Year=T$3)*(Month=T$4)*(Code_General_Data=$B92))} -> 1330 | U92: {=SUMPRODUCT(General_Data*(Year=U$3)*(Month=U$4)*(Code_General_Data=$B92))} -> 1330 | V92: {=SUMPRODUCT(General_Data*(Year=V$3)*(Month=V$4)*(Code_General_Data=$B92))} -> 1330 | ... AL92: {=SUMPRODUCT(General_Data*(Year=AL$3)*(Month=AL$4)*(Code_General_Data=$B92))} -> 1230
J93: Giá trần - quy đổi EXW | AA93: =AA90+AA86 -> 1477.5938 | AB93: =AB90+AB86 -> 1479.5104 | AC93: =AC90+AC86 -> 1481.2917 | AD93: =AD90+AD86 -> 1481.25 | AE93: =AE90+AE86 -> 1481 | AF93: =AF90+AF86 -> 1481 | AG93: =AG90+AG86 -> 1481 | AH93: =AH90+AH86 -> 1481.9 | ... AL93: =AL90+AL86 -> 1486.6562
J94: Giá sàn - quy đổi EXW | AA94: =AA91+AA86 -> 1257.5938 | AB94: =AB91+AB86 -> 1259.5104 | AC94: =AC91+AC86 -> 1261.2917 | AD94: =AD91+AD86 -> 1261.25 | AE94: =AE91+AE86 -> 1261 | AF94: =AF91+AF86 -> 1261 | AG94: =AG91+AG86 -> 1261 | AH94: =AH91+AH86 -> 1261.9 | ... AL94: =AL91+AL86 -> 1266.6562
A96: 104909 | F96: 5 | G96: LA VIE VIỆT NAM
A97: 104909 | B97: 110000329 | D97: GB | F97: 5.1 | H97: GIÁ BÁN WSS01 (EXW) | O97: 1250 | P97: 1250 | Q97: 1250 | R97: 1250 | S97: 1250 | T97: 1250 | U97: 1330 | V97: 1330 | W97: 1330 | X97: 1330 | Y97: 1330 | Z97: 1330 | AA97: 1250 | AB97: 1250 | AC97: 1250 | AD97: 1250 | AE97: 1250 | AF97: 1250 | AH97: =34382.04/26.37 -> 1303.8316 | AI97: =34382.04/26.37 -> 1303.8316 | AJ97: =34382.04/26.37 -> 1303.8316 | AK97: =34382.04/26.37 -> 1303.8316 | AL97: =34382.04/26.37 -> 1303.8316
A98: 104909 | B98: 110000329 | D98: EXW | F98: 5.1.1 | I98: Giá bán quy đổi EXW | O98: =O97 -> 1250 | P98: =P97 -> 1250 | Q98: =Q97 -> 1250 | R98: =R97 -> 1250 | S98: =S97 -> 1250 | T98: =T97 -> 1250 | U98: =U97 -> 1330 | V98: =V97 -> 1330 | ... AF98: =AF97 -> 1250 | AH98: =34382.04/26.37 -> 1303.8316 | AI98: =34382.04/26.37 -> 1303.8316 | AJ98: =34382.04/26.37 -> 1303.8316 | AK98: =34382.04/26.37 -> 1303.8316 | AL98: =34382.04/26.37 -> 1303.8316
A99: 104909 | B99: 110000329 | F99: 5.1.2 | J99: Giá duyệt tháng | O99: {=SUMPRODUCT(General_Data*(Year=O$3)*(Month=O$4)*(Code_General_Data=$B99))} -> 1250 | P99: {=SUMPRODUCT(General_Data*(Year=P$3)*(Month=P$4)*(Code_General_Data=$B99))} -> 1250 | Q99: {=SUMPRODUCT(General_Data*(Year=Q$3)*(Month=Q$4)*(Code_General_Data=$B99))} -> 1250 | R99: {=SUMPRODUCT(General_Data*(Year=R$3)*(Month=R$4)*(Code_General_Data=$B99))} -> 1250 | S99: {=SUMPRODUCT(General_Data*(Year=S$3)*(Month=S$4)*(Code_General_Data=$B99))} -> 1300 | T99: {=SUMPRODUCT(General_Data*(Year=T$3)*(Month=T$4)*(Code_General_Data=$B99))} -> 1300 | U99: {=SUMPRODUCT(General_Data*(Year=U$3)*(Month=U$4)*(Code_General_Data=$B99))} -> 1300 | V99: {=SUMPRODUCT(General_Data*(Year=V$3)*(Month=V$4)*(Code_General_Data=$B99))} -> 1300 | ... AL99: {=SUMPRODUCT(General_Data*(Year=AL$3)*(Month=AL$4)*(Code_General_Data=$B99))} -> 1200
A101: 102990 | F101: 6 | G101: COCA VIỆT NAM
A102: 102990 | B102: 110000332 | D102: GB | F102: 6.1 | H102: GIÁ BÁN iSS1084G (DDP) | O102: 1325 | P102: 1325 | Q102: 1325 | R102: 1325 | S102: 1325 | T102: 1325 | U102: 1325 | V102: 1325 | W102: 1325 | X102: 1325 | Y102: 1325 | Z102: 1325 | AA102: 1400 | AB102: 1400 | AC102: 1400 | AD102: 1400 | AE102: 1400 | AF102: 1400 | AG102: 1400 | AH102: 1400 | AI102: 1400 | AJ102: 1400 | AK102: 1400 | AL102: 1400
A103: 102990 | B103: 110000332 | D103: EXW | F103: 6.1.1 | I103: Giá bán quy đổi EXW | O103: =O102-O104-O105 -> 1315 | P103: =P102-P104-P105 -> 1315 | Q103: =Q102-Q104-Q105 -> 1315 | R103: =R102-R104-R105 -> 1315 | S103: =S102-S104-S105 -> 1315 | T103: =T102-T104-T105 -> 1315 | U103: =U102-U104-U105 -> 1315 | V103: =V102-V104-V105 -> 1315 | ... AL103: =AL102-AL104-AL105 -> 1348.3
A104: 102990 | B104: 110000332 | F104: 6.1.2 | I104: Chi phí vận chuyển - Miền Nam | O104: 10 | P104: 10 | Q104: 10 | R104: 10 | S104: 10 | T104: 10 | U104: 10 | V104: 10 | W104: 10 | X104: 10 | Y104: 10 | Z104: 10 | AA104: 10 | AB104: 10 | AC104: 10 | AD104: 10 | AE104: 10 | AF104: 10 | AG104: 10 | AH104: 10 | AI104: 10 | AJ104: 10 | AK104: 10 | AL104: 10
A105: 102990 | B105: 110000332 | F105: 6.1.3 | I105: Rebate (2025: 3% giá EXW) | AA105: =(AA102-AA104)*3% -> 41.7 | AB105: =(AB102-AB104)*3% -> 41.7 | AC105: =(AC102-AC104)*3% -> 41.7 | AD105: =(AD102-AD104)*3% -> 41.7 | AE105: =(AE102-AE104)*3% -> 41.7 | AF105: =(AF102-AF104)*3% -> 41.7 | AG105: =(AG102-AG104)*3% -> 41.7 | AH105: =(AH102-AH104)*3% -> 41.7 | ... AL105: =(AL102-AL104)*3% -> 41.7
A106: 102990 | B106: 110000332 | F106: 6.1.4 | J106: Giá duyệt tháng | O106: {=SUMPRODUCT(General_Data*(Year=O$3)*(Month=O$4)*(Code_General_Data=$B106))} -> 1340 | P106: {=SUMPRODUCT(General_Data*(Year=P$3)*(Month=P$4)*(Code_General_Data=$B106))} -> 1340 | Q106: {=SUMPRODUCT(General_Data*(Year=Q$3)*(Month=Q$4)*(Code_General_Data=$B106))} -> 1340 | R106: {=SUMPRODUCT(General_Data*(Year=R$3)*(Month=R$4)*(Code_General_Data=$B106))} -> 1340 | S106: {=SUMPRODUCT(General_Data*(Year=S$3)*(Month=S$4)*(Code_General_Data=$B106))} -> 1390 | T106: {=SUMPRODUCT(General_Data*(Year=T$3)*(Month=T$4)*(Code_General_Data=$B106))} -> 1390 | U106: {=SUMPRODUCT(General_Data*(Year=U$3)*(Month=U$4)*(Code_General_Data=$B106))} -> 1390 | V106: {=SUMPRODUCT(General_Data*(Year=V$3)*(Month=V$4)*(Code_General_Data=$B106))} -> 1390 | ... AL106: {=SUMPRODUCT(General_Data*(Year=AL$3)*(Month=AL$4)*(Code_General_Data=$B106))} -> 1290
A108: 105217 | F108: 7 | G108: NESTLE VIỆT NAM
A109: 105217 | B109: 110000329 | D109: GB | F109: 7.1 | H109: GIÁ BÁN WSS01 (DDP) | X109: 1320 | Y109: 1320 | Z109: 1320
A110: 105217 | B110: 110000329 | D110: EXW | F110: 7.1.1 | I110: Giá bán quy đổi EXW | X110: =X109-X111 -> 1310 | Y110: =Y109-Y111 -> 1310 | Z110: =Z109-Z111 -> 1310
A111: 105217 | B111: 110000329 | F111: 7.1.2 | I111: Chi phí vận chuyển | X111: 10 | Y111: 10 | Z111: 10
A112: 105217 | B112: 110000329 | F112: 7.1.3 | J112: Giá duyệt tháng | X112: {=SUMPRODUCT(General_Data*(Year=X$3)*(Month=X$4)*(Code_General_Data=$B112))} -> 1325 | Y112: {=SUMPRODUCT(General_Data*(Year=Y$3)*(Month=Y$4)*(Code_General_Data=$B112))} -> 1325 | Z112: {=SUMPRODUCT(General_Data*(Year=Z$3)*(Month=Z$4)*(Code_General_Data=$B112))} -> 1275

Sheet Biểu đồ
C1: III. BIỂU ĐỒ
C36: III. BIỂU ĐỒ
C71: III. BIỂU ĐỒ
C106: III. BIỂU ĐỒ
C141: III. BIỂU ĐỒ

Sheet Vẽ Biểu đồ
E1: 2024 | F1: 2024 | G1: 2024 | H1: 2024 | I1: 2024 | J1: 2024 | K1: 2024 | L1: 2024 | M1: 2024 | N1: 2024 | O1: 2024 | P1: 2024 | Q1: 2025 | R1: 2025 | S1: 2025 | T1: 2025 | U1: 2025 | V1: 2025 | W1: 2025 | X1: 2025 | Y1: 2025 | Z1: 2025 | AA1: 2025 | AB1: 2025 | AC1: 2026 | AD1: 2026 | AE1: 2026 | AF1: 2026 | AG1: 2026 | AH1: 2026 | AI1: 2026 | AJ1: 2026 | AK1: 2026 | AL1: 2026 | AM1: 2026 | AN1: 2026
E2: 1 | F2: 2 | G2: 3 | H2: 4 | I2: 5 | J2: 6 | K2: 7 | L2: 8 | M2: 9 | N2: 10 | O2: 11 | P2: 12 | Q2: 1 | R2: 2 | S2: 3 | T2: 4 | U2: 5 | V2: 6 | W2: 7 | X2: 8 | Y2: 9 | Z2: 10 | AA2: 11 | AB2: 12 | AC2: 1 | AD2: 2 | AE2: 3 | AF2: 4 | AG2: 5 | AH2: 6 | AI2: 7 | AJ2: 8 | AK2: 9 | AL2: 10 | AM2: 11 | AN2: 12
D3: X dòng này làm lable -> | AB3: x
A4: Genearal Data | B4: Price
C5: 110000354 | D5: WSS01G
E6: 2024 | Q6: 2025
E7: 1 | F7: 2 | G7: 3 | H7: 4 | I7: 5 | J7: 6 | K7: 7 | L7: 8 | M7: 9 | N7: 10 | O7: 11 | P7: 12 | Q7: 1 | R7: 2 | S7: 3 | T7: 4 | U7: 5 | V7: 6 | W7: 7 | X7: 8 | Y7: 9 | Z7: 10 | AA7: 11 | AB7: 12 | AC7: 1 | AD7: 2 | AE7: 3 | AF7: 4 | AG7: 5 | AH7: 6 | AI7: 7 | AJ7: 8 | AK7: 9 | AL7: 10 | AM7: 11 | AN7: 12
B8: 200319 | C8: 110000354 | D8: Niagara | E8: {=IF(SUMPRODUCT('Giá công thức'!$G$11:$AD$106*('Giá công thức'!$A$11:$A$106=$B8)*('Giá công thức'!$B$11:$B$106=$C8)*('Giá công thức'!$C$11:$C$106="GB")*('Giá công thức'!$G$3:$AD$3=E$1)*('Giá công thức'!$G$4:$AD$4=E$2))=0,NA(),SUMPRODUCT('Giá công thức'!$G$11:$AD$106*('Giá công thức'!$A$11:$A$106=$B8)*('Giá công thức'!$B$11:$B$106=$C8)*('Giá công thức'!$C$11:$C$106="GB")*('Giá công thức'!$G$3:$AD$3=E$1)*('Giá công thức'!$G$4:$AD$4=E$2)))} -> 1180 | F8: {=IF(SUMPRODUCT('Giá công thức'!$G$11:$AD$106*('Giá công thức'!$A$11:$A$106=$B8)*('Giá công thức'!$B$11:$B$106=$C8)*('Giá công thức'!$C$11:$C$106="GB")*('Giá công thức'!$G$3:$AD$3=F$1)*('Giá công thức'!$G$4:$AD$4=F$2))=0,NA(),SUMPRODUCT('Giá công thức'!$G$11:$AD$106*('Giá công thức'!$A$11:$A$106=$B8)*('Giá công thức'!$B$11:$B$106=$C8)*('Giá công thức'!$C$11:$C$106="GB")*('Giá công thức'!$G$3:$AD$3=F$1)*('Giá công thức'!$G$4:$AD$4=F$2)))} -> 1180 | G8: {=IF(SUMPRODUCT('Giá công thức'!$G$11:$AD$106*('Giá công thức'!$A$11:$A$106=$B8)*('Giá công thức'!$B$11:$B$106=$C8)*('Giá công thức'!$C$11:$C$106="GB")*('Giá công thức'!$G$3:$AD$3=G$1)*('Giá công thức'!$G$4:$AD$4=G$2))=0,NA(),SUMPRODUCT('Giá công thức'!$G$11:$AD$106*('Giá công thức'!$A$11:$A$106=$B8)*('Giá công thức'!$B$11:$B$106=$C8)*('Giá công thức'!$C$11:$C$106="GB")*('Giá công thức'!$G$3:$AD$3=G$1)*('Giá công thức'!$G$4:$AD$4=G$2)))} -> 1180 | H8: {=IF(SUMPRODUCT('Giá công thức'!$G$11:$AD$106*('Giá công thức'!$A$11:$A$106=$B8)*('Giá công thức'!$B$11:$B$106=$C8)*('Giá công thức'!$C$11:$C$106="GB")*('Giá công thức'!$G$3:$AD$3=H$1)*('Giá công thức'!$G$4:$AD$4=H$2))=0,NA(),SUMPRODUCT('Giá công thức'!$G$11:$AD$106*('Giá công thức'!$A$11:$A$106=$B8)*('Giá công thức'!$B$11:$B$106=$C8)*('Giá công thức'!$C$11:$C$106="GB")*('Giá công thức'!$G$3:$AD$3=H$1)*('Giá công thức'!$G$4:$AD$4=H$2)))} -> 1180 | I8: {=IF(SUMPRODUCT('Giá công thức'!$G$11:$AD$106*('Giá công thức'!$A$11:$A$106=$B8)*('Giá công thức'!$B$11:$B$106=$C8)*('Giá công thức'!$C$11:$C$106="GB")*('Giá công thức'!$G$3:$AD$3=I$1)*('Giá công thức'!$G$4:$AD$4=I$2))=0,NA(),SUMPRODUCT('Giá công thức'!$G$11:$AD$106*('Giá công thức'!$A$11:$A$106=$B8)*('Giá công thức'!$B$11:$B$106=$C8)*('Giá công thức'!$C$11:$C$106="GB")*('Giá công thức'!$G$3:$AD$3=I$1)*('Giá công thức'!$G$4:$AD$4=I$2)))} -> 1180 | J8: {=IF(SUMPRODUCT('Giá công thức'!$G$11:$AD$106*('Giá công thức'!$A$11:$A$106=$B8)*('Giá công thức'!$B$11:$B$106=$C8)*('Giá công thức'!$C$11:$C$106="GB")*('Giá công thức'!$G$3:$AD$3=J$1)*('Giá công thức'!$G$4:$AD$4=J$2))=0,NA(),SUMPRODUCT('Giá công thức'!$G$11:$AD$106*('Giá công thức'!$A$11:$A$106=$B8)*('Giá công thức'!$B$11:$B$106=$C8)*('Giá công thức'!$C$11:$C$106="GB")*('Giá công thức'!$G$3:$AD$3=J$1)*('Giá công thức'!$G$4:$AD$4=J$2)))} -> 1180.9 | K8: {=IF(SUMPRODUCT('Giá công thức'!$G$11:$AD$106*('Giá công thức'!$A$11:$A$106=$B8)*('Giá công thức'!$B$11:$B$106=$C8)*('Giá công thức'!$C$11:$C$106="GB")*('Giá công thức'!$G$3:$AD$3=K$1)*('Giá công thức'!$G$4:$AD$4=K$2))=0,NA(),SUMPRODUCT('Giá công thức'!$G$11:$AD$106*('Giá công thức'!$A$11:$A$106=$B8)*('Giá công thức'!$B$11:$B$106=$C8)*('Giá công thức'!$C$11:$C$106="GB")*('Giá công thức'!$G$3:$AD$3=K$1)*('Giá công thức'!$G$4:$AD$4=K$2)))} -> 1194.4 | L8: {=IF(SUMPRODUCT('Giá công thức'!$G$11:$AD$106*('Giá công thức'!$A$11:$A$106=$B8)*('Giá công thức'!$B$11:$B$106=$C8)*('Giá công thức'!$C$11:$C$106="GB")*('Giá công thức'!$G$3:$AD$3=L$1)*('Giá công thức'!$G$4:$AD$4=L$2))=0,NA(),SUMPRODUCT('Giá công thức'!$G$11:$AD$106*('Giá công thức'!$A$11:$A$106=$B8)*('Giá công thức'!$B$11:$B$106=$C8)*('Giá công thức'!$C$11:$C$106="GB")*('Giá công thức'!$G$3:$AD$3=L$1)*('Giá công thức'!$G$4:$AD$4=L$2)))} -> 1206.1 | ... AB8: {=IF(SUMPRODUCT('Giá công thức'!$G$11:$AD$106*('Giá công thức'!$A$11:$A$106=$B8)*('Giá công thức'!$B$11:$B$106=$C8)*('Giá công thức'!$C$11:$C$106="GB")*('Giá công thức'!$G$3:$AD$3=AB$1)*('Giá công thức'!$G$4:$AD$4=AB$2))=0,NA(),SUMPRODUCT('Giá công thức'!$G$11:$AD$106*('Giá công thức'!$A$11:$A$106=$B8)*('Giá công thức'!$B$11:$B$106=$C8)*('Giá công thức'!$C$11:$C$106="GB")*('Giá công thức'!$G$3:$AD$3=AB$1)*('Giá công thức'!$G$4:$AD$4=AB$2)))} -> 1180 | AO8: =INDEX($E8:$AB8,MATCH("X",$E$3:$AB$3,0)) -> 1180
B9: 105263 | C9: 110000354 | D9: Unilever | E9: {=IF(SUMPRODUCT('Giá công thức'!$G$11:$AD$106*('Giá công thức'!$A$11:$A$106=$B9)*('Giá công thức'!$B$11:$B$106=$C9)*('Giá công thức'!$C$11:$C$106="GB")*('Giá công thức'!$G$3:$AD$3=E$1)*('Giá công thức'!$G$4:$AD$4=E$2))=0,NA(),SUMPRODUCT('Giá công thức'!$G$11:$AD$106*('Giá công thức'!$A$11:$A$106=$B9)*('Giá công thức'!$B$11:$B$106=$C9)*('Giá công thức'!$C$11:$C$106="GB")*('Giá công thức'!$G$3:$AD$3=E$1)*('Giá công thức'!$G$4:$AD$4=E$2)))} -> 1307.7959 | F9: {=IF(SUMPRODUCT('Giá công thức'!$G$11:$AD$106*('Giá công thức'!$A$11:$A$106=$B9)*('Giá công thức'!$B$11:$B$106=$C9)*('Giá công thức'!$C$11:$C$106="GB")*('Giá công thức'!$G$3:$AD$3=F$1)*('Giá công thức'!$G$4:$AD$4=F$2))=0,NA(),SUMPRODUCT('Giá công thức'!$G$11:$AD$106*('Giá công thức'!$A$11:$A$106=$B9)*('Giá công thức'!$B$11:$B$106=$C9)*('Giá công thức'!$C$11:$C$106="GB")*('Giá công thức'!$G$3:$AD$3=F$1)*('Giá công thức'!$G$4:$AD$4=F$2)))} -> 1307.7959 | G9: {=IF(SUMPRODUCT('Giá công thức'!$G$11:$AD$106*('Giá công thức'!$A$11:$A$106=$B9)*('Giá công thức'!$B$11:$B$106=$C9)*('Giá công thức'!$C$11:$C$106="GB")*('Giá công thức'!$G$3:$AD$3=G$1)*('Giá công thức'!$G$4:$AD$4=G$2))=0,NA(),SUMPRODUCT('Giá công thức'!$G$11:$AD$106*('Giá công thức'!$A$11:$A$106=$B9)*('Giá công thức'!$B$11:$B$106=$C9)*('Giá công thức'!$C$11:$C$106="GB")*('Giá công thức'!$G$3:$AD$3=G$1)*('Giá công thức'!$G$4:$AD$4=G$2)))} -> 1307.7959 | H9: {=IF(SUMPRODUCT('Giá công thức'!$G$11:$AD$106*('Giá công thức'!$A$11:$A$106=$B9)*('Giá công thức'!$B$11:$B$106=$C9)*('Giá công thức'!$C$11:$C$106="GB")*('Giá công thức'!$G$3:$AD$3=H$1)*('Giá công thức'!$G$4:$AD$4=H$2))=0,NA(),SUMPRODUCT('Giá công thức'!$G$11:$AD$106*('Giá công thức'!$A$11:$A$106=$B9)*('Giá công thức'!$B$11:$B$106=$C9)*('Giá công thức'!$C$11:$C$106="GB")*('Giá công thức'!$G$3:$AD$3=H$1)*('Giá công thức'!$G$4:$AD$4=H$2)))} -> 1307.7959 | I9: {=IF(SUMPRODUCT('Giá công thức'!$G$11:$AD$106*('Giá công thức'!$A$11:$A$106=$B9)*('Giá công thức'!$B$11:$B$106=$C9)*('Giá công thức'!$C$11:$C$106="GB")*('Giá công thức'!$G$3:$AD$3=I$1)*('Giá công thức'!$G$4:$AD$4=I$2))=0,NA(),SUMPRODUCT('Giá công thức'!$G$11:$AD$106*('Giá công thức'!$A$11:$A$106=$B9)*('Giá công thức'!$B$11:$B$106=$C9)*('Giá công thức'!$C$11:$C$106="GB")*('Giá công thức'!$G$3:$AD$3=I$1)*('Giá công thức'!$G$4:$AD$4=I$2)))} -> 1307.7959 | J9: {=IF(SUMPRODUCT('Giá công thức'!$G$11:$AD$106*('Giá công thức'!$A$11:$A$106=$B9)*('Giá công thức'!$B$11:$B$106=$C9)*('Giá công thức'!$C$11:$C$106="GB")*('Giá công thức'!$G$3:$AD$3=J$1)*('Giá công thức'!$G$4:$AD$4=J$2))=0,NA(),SUMPRODUCT('Giá công thức'!$G$11:$AD$106*('Giá công thức'!$A$11:$A$106=$B9)*('Giá công thức'!$B$11:$B$106=$C9)*('Giá công thức'!$C$11:$C$106="GB")*('Giá công thức'!$G$3:$AD$3=J$1)*('Giá công thức'!$G$4:$AD$4=J$2)))} -> 1307.7959 | K9: {=IF(SUMPRODUCT('Giá công thức'!$G$11:$AD$106*('Giá công thức'!$A$11:$A$106=$B9)*('Giá công thức'!$B$11:$B$106=$C9)*('Giá công thức'!$C$11:$C$106="GB")*('Giá công thức'!$G$3:$AD$3=K$1)*('Giá công thức'!$G$4:$AD$4=K$2))=0,NA(),SUMPRODUCT('Giá công thức'!$G$11:$AD$106*('Giá công thức'!$A$11:$A$106=$B9)*('Giá công thức'!$B$11:$B$106=$C9)*('Giá công thức'!$C$11:$C$106="GB")*('Giá công thức'!$G$3:$AD$3=K$1)*('Giá công thức'!$G$4:$AD$4=K$2)))} -> 1308.04 | L9: {=IF(SUMPRODUCT('Giá công thức'!$G$11:$AD$106*('Giá công thức'!$A$11:$A$106=$B9)*('Giá công thức'!$B$11:$B$106=$C9)*('Giá công thức'!$C$11:$C$106="GB")*('Giá công thức'!$G$3:$AD$3=L$1)*('Giá công thức'!$G$4:$AD$4=L$2))=0,NA(),SUMPRODUCT('Giá công thức'!$G$11:$AD$106*('Giá công thức'!$A$11:$A$106=$B9)*('Giá công thức'!$B$11:$B$106=$C9)*('Giá công thức'!$C$11:$C$106="GB")*('Giá công thức'!$G$3:$AD$3=L$1)*('Giá công thức'!$G$4:$AD$4=L$2)))} -> 1308.04 | ... AB9: {=IF(SUMPRODUCT('Giá công thức'!$G$11:$AD$106*('Giá công thức'!$A$11:$A$106=$B9)*('Giá công thức'!$B$11:$B$106=$C9)*('Giá công thức'!$C$11:$C$106="GB")*('Giá công thức'!$G$3:$AD$3=AB$1)*('Giá công thức'!$G$4:$AD$4=AB$2))=0,NA(),SUMPRODUCT('Giá công thức'!$G$11:$AD$106*('Giá công thức'!$A$11:$A$106=$B9)*('Giá công thức'!$B$11:$B$106=$C9)*('Giá công thức'!$C$11:$C$106="GB")*('Giá công thức'!$G$3:$AD$3=AB$1)*('Giá công thức'!$G$4:$AD$4=AB$2)))} -> 1268.04 | AO9: =INDEX($E9:$AB9,MATCH("X",$E$3:$AB$3,0)) -> 1268.04
B10: 104909 | C10: 110000329 | D10: Lavie | E10: {=IF(SUMPRODUCT('Giá công thức'!$G$11:$AD$106*('Giá công thức'!$A$11:$A$106=$B10)*('Giá công thức'!$B$11:$B$106=$C10)*('Giá công thức'!$C$11:$C$106="GB")*('Giá công thức'!$G$3:$AD$3=E$1)*('Giá công thức'!$G$4:$AD$4=E$2))=0,NA(),SUMPRODUCT('Giá công thức'!$G$11:$AD$106*('Giá công thức'!$A$11:$A$106=$B10)*('Giá công thức'!$B$11:$B$106=$C10)*('Giá công thức'!$C$11:$C$106="GB")*('Giá công thức'!$G$3:$AD$3=E$1)*('Giá công thức'!$G$4:$AD$4=E$2)))} -> 1250 | F10: {=IF(SUMPRODUCT('Giá công thức'!$G$11:$AD$106*('Giá công thức'!$A$11:$A$106=$B10)*('Giá công thức'!$B$11:$B$106=$C10)*('Giá công thức'!$C$11:$C$106="GB")*('Giá công thức'!$G$3:$AD$3=F$1)*('Giá công thức'!$G$4:$AD$4=F$2))=0,NA(),SUMPRODUCT('Giá công thức'!$G$11:$AD$106*('Giá công thức'!$A$11:$A$106=$B10)*('Giá công thức'!$B$11:$B$106=$C10)*('Giá công thức'!$C$11:$C$106="GB")*('Giá công thức'!$G$3:$AD$3=F$1)*('Giá công thức'!$G$4:$AD$4=F$2)))} -> 1250 | G10: {=IF(SUMPRODUCT('Giá công thức'!$G$11:$AD$106*('Giá công thức'!$A$11:$A$106=$B10)*('Giá công thức'!$B$11:$B$106=$C10)*('Giá công thức'!$C$11:$C$106="GB")*('Giá công thức'!$G$3:$AD$3=G$1)*('Giá công thức'!$G$4:$AD$4=G$2))=0,NA(),SUMPRODUCT('Giá công thức'!$G$11:$AD$106*('Giá công thức'!$A$11:$A$106=$B10)*('Giá công thức'!$B$11:$B$106=$C10)*('Giá công thức'!$C$11:$C$106="GB")*('Giá công thức'!$G$3:$AD$3=G$1)*('Giá công thức'!$G$4:$AD$4=G$2)))} -> 1250 | H10: {=IF(SUMPRODUCT('Giá công thức'!$G$11:$AD$106*('Giá công thức'!$A$11:$A$106=$B10)*('Giá công thức'!$B$11:$B$106=$C10)*('Giá công thức'!$C$11:$C$106="GB")*('Giá công thức'!$G$3:$AD$3=H$1)*('Giá công thức'!$G$4:$AD$4=H$2))=0,NA(),SUMPRODUCT('Giá công thức'!$G$11:$AD$106*('Giá công thức'!$A$11:$A$106=$B10)*('Giá công thức'!$B$11:$B$106=$C10)*('Giá công thức'!$C$11:$C$106="GB")*('Giá công thức'!$G$3:$AD$3=H$1)*('Giá công thức'!$G$4:$AD$4=H$2)))} -> 1250 | I10: {=IF(SUMPRODUCT('Giá công thức'!$G$11:$AD$106*('Giá công thức'!$A$11:$A$106=$B10)*('Giá công thức'!$B$11:$B$106=$C10)*('Giá công thức'!$C$11:$C$106="GB")*('Giá công thức'!$G$3:$AD$3=I$1)*('Giá công thức'!$G$4:$AD$4=I$2))=0,NA(),SUMPRODUCT('Giá công thức'!$G$11:$AD$106*('Giá công thức'!$A$11:$A$106=$B10)*('Giá công thức'!$B$11:$B$106=$C10)*('Giá công thức'!$C$11:$C$106="GB")*('Giá công thức'!$G$3:$AD$3=I$1)*('Giá công thức'!$G$4:$AD$4=I$2)))} -> 1250 | J10: {=IF(SUMPRODUCT('Giá công thức'!$G$11:$AD$106*('Giá công thức'!$A$11:$A$106=$B10)*('Giá công thức'!$B$11:$B$106=$C10)*('Giá công thức'!$C$11:$C$106="GB")*('Giá công thức'!$G$3:$AD$3=J$1)*('Giá công thức'!$G$4:$AD$4=J$2))=0,NA(),SUMPRODUCT('Giá công thức'!$G$11:$AD$106*('Giá công thức'!$A$11:$A$106=$B10)*('Giá công thức'!$B$11:$B$106=$C10)*('Giá công thức'!$C$11:$C$106="GB")*('Giá công thức'!$G$3:$AD$3=J$1)*('Giá công thức'!$G$4:$AD$4=J$2)))} -> 1250 | K10: {=IF(SUMPRODUCT('Giá công thức'!$G$11:$AD$106*('Giá công thức'!$A$11:$A$106=$B10)*('Giá công thức'!$B$11:$B$106=$C10)*('Giá công thức'!$C$11:$C$106="GB")*('Giá công thức'!$G$3:$AD$3=K$1)*('Giá công thức'!$G$4:$AD$4=K$2))=0,NA(),SUMPRODUCT('Giá công thức'!$G$11:$AD$106*('Giá công thức'!$A$11:$A$106=$B10)*('Giá công thức'!$B$11:$B$106=$C10)*('Giá công thức'!$C$11:$C$106="GB")*('Giá công thức'!$G$3:$AD$3=K$1)*('Giá công thức'!$G$4:$AD$4=K$2)))} -> 1330 | L10: {=IF(SUMPRODUCT('Giá công thức'!$G$11:$AD$106*('Giá công thức'!$A$11:$A$106=$B10)*('Giá công thức'!$B$11:$B$106=$C10)*('Giá công thức'!$C$11:$C$106="GB")*('Giá công thức'!$G$3:$AD$3=L$1)*('Giá công thức'!$G$4:$AD$4=L$2))=0,NA(),SUMPRODUCT('Giá công thức'!$G$11:$AD$106*('Giá công thức'!$A$11:$A$106=$B10)*('Giá công thức'!$B$11:$B$106=$C10)*('Giá công thức'!$C$11:$C$106="GB")*('Giá công thức'!$G$3:$AD$3=L$1)*('Giá công thức'!$G$4:$AD$4=L$2)))} -> 1330 | ... AB10: {=IF(SUMPRODUCT('Giá công thức'!$G$11:$AD$106*('Giá công thức'!$A$11:$A$106=$B10)*('Giá công thức'!$B$11:$B$106=$C10)*('Giá công thức'!$C$11:$C$106="GB")*('Giá công thức'!$G$3:$AD$3=AB$1)*('Giá công thức'!$G$4:$AD$4=AB$2))=0,NA(),SUMPRODUCT('Giá công thức'!$G$11:$AD$106*('Giá công thức'!$A$11:$A$106=$B10)*('Giá công thức'!$B$11:$B$106=$C10)*('Giá công thức'!$C$11:$C$106="GB")*('Giá công thức'!$G$3:$AD$3=AB$1)*('Giá công thức'!$G$4:$AD$4=AB$2)))} -> 1303.8316 | AO10: =INDEX($E10:$AB10,MATCH("X",$E$3:$AB$3,0)) -> 1303.8316
A11: 110000354 | C11: 110000354 | D11: Giá duyệt | E11: {=SUMPRODUCT(General_Data*(Code_General_Data=$A11)*(Year=E$1)*(Month=E$2))} -> 1250 | F11: {=SUMPRODUCT(General_Data*(Code_General_Data=$A11)*(Year=F$1)*(Month=F$2))} -> 1250 | G11: {=SUMPRODUCT(General_Data*(Code_General_Data=$A11)*(Year=G$1)*(Month=G$2))} -> 1250 | H11: {=SUMPRODUCT(General_Data*(Code_General_Data=$A11)*(Year=H$1)*(Month=H$2))} -> 1250 | I11: {=SUMPRODUCT(General_Data*(Code_General_Data=$A11)*(Year=I$1)*(Month=I$2))} -> 1300 | J11: {=SUMPRODUCT(General_Data*(Code_General_Data=$A11)*(Year=J$1)*(Month=J$2))} -> 1300 | K11: {=SUMPRODUCT(General_Data*(Code_General_Data=$A11)*(Year=K$1)*(Month=K$2))} -> 1300 | L11: {=SUMPRODUCT(General_Data*(Code_General_Data=$A11)*(Year=L$1)*(Month=L$2))} -> 1300 | ... AB11: {=SUMPRODUCT(General_Data*(Code_General_Data=$A11)*(Year=AB$1)*(Month=AB$2))} -> 1200 | AO11: =INDEX($E11:$AB11,MATCH("X",$E$3:$AB$3,0)) -> 1200
A12: PETVirgin | D12: Giá chính phẩm | E12: {=SUMPRODUCT(General_Data*(Code_General_Data=$A12)*(Year=E$1)*(Month=E$2))} -> 930 | F12: {=SUMPRODUCT(General_Data*(Code_General_Data=$A12)*(Year=F$1)*(Month=F$2))} -> 943.33333 | G12: {=SUMPRODUCT(General_Data*(Code_General_Data=$A12)*(Year=G$1)*(Month=G$2))} -> 940 | H12: {=SUMPRODUCT(General_Data*(Code_General_Data=$A12)*(Year=H$1)*(Month=H$2))} -> 940 | I12: {=SUMPRODUCT(General_Data*(Code_General_Data=$A12)*(Year=I$1)*(Month=I$2))} -> 942 | J12: {=SUMPRODUCT(General_Data*(Code_General_Data=$A12)*(Year=J$1)*(Month=J$2))} -> 950 | K12: {=SUMPRODUCT(General_Data*(Code_General_Data=$A12)*(Year=K$1)*(Month=K$2))} -> 947.5 | L12: {=SUMPRODUCT(General_Data*(Code_General_Data=$A12)*(Year=L$1)*(Month=L$2))} -> 930 | ... AB12: {=SUMPRODUCT(General_Data*(Code_General_Data=$A12)*(Year=AB$1)*(Month=AB$2))} -> 770 | AO12: =INDEX($E12:$AB12,MATCH("X",$E$3:$AB$3,0)) -> 770
D13: Chênh lệch | E13: =E11-E12 -> 320 | F13: =F11-F12 -> 306.66667 | G13: =G11-G12 -> 310 | H13: =H11-H12 -> 310 | I13: =I11-I12 -> 358 | J13: =J11-J12 -> 350 | K13: =K11-K12 -> 352.5 | L13: =L11-L12 -> 370 | ... AB13: =AB11-AB12 -> 430
D14: %Chênh lệch | E14: =IFERROR(E13/E12,0) -> 0.34408602 | F14: =IFERROR(F13/F12,0) -> 0.32508834 | G14: =IFERROR(G13/G12,0) -> 0.32978723 | H14: =IFERROR(H13/H12,0) -> 0.32978723 | I14: =IFERROR(I13/I12,0) -> 0.38004246 | J14: =IFERROR(J13/J12,0) -> 0.36842105 | K14: =IFERROR(K13/K12,0) -> 0.37203166 | L14: =IFERROR(L13/L12,0) -> 0.39784946 | ... AB14: =IFERROR(AB13/AB12,0) -> 0.55844156 | AO14: =IFERROR(AO13/AO12,0) -> 0
D15: Chênh lệch-Line Drop | E15: =E11 -> 1250 | F15: =F11 -> 1250 | G15: =G11 -> 1250 | H15: =H11 -> 1250 | I15: =I11 -> 1300 | J15: =J11 -> 1300 | K15: =K11 -> 1300 | L15: =L11 -> 1300 | ... AB15: =AB11 -> 1200
D16: Chênh lệch-Label | E16: =E12+E13/2 -> 1090 | F16: =F12+F13/2 -> 1096.6667 | G16: =G12+G13/2 -> 1095 | H16: =H12+H13/2 -> 1095 | I16: =I12+I13/2 -> 1121 | J16: =J12+J13/2 -> 1125 | K16: =K12+K13/2 -> 1123.75 | L16: =L12+L13/2 -> 1115 | ... AB16: =AB12+AB13/2 -> 985
D17: Giá duyệt-Area | E17: =E11 -> 1250 | F17: =F11 -> 1250 | G17: =G11 -> 1250 | H17: =H11 -> 1250 | I17: =I11 -> 1300 | J17: =J11 -> 1300 | K17: =K11 -> 1300 | L17: =L11 -> 1300 | ... AB17: =AB11 -> 1200
D18: Giá chính phẩm-Area | E18: =E12 -> 930 | F18: =F12 -> 943.33333 | G18: =G12 -> 940 | H18: =H12 -> 940 | I18: =I12 -> 942 | J18: =J12 -> 950 | K18: =K12 -> 947.5 | L18: =L12 -> 930 | ... AB18: =AB12 -> 770
D19: Niagara-Label | E19: =IFERROR(E8,0) -> 1180 | F19: =IFERROR(F8,0) -> 1180 | G19: =IFERROR(G8,0) -> 1180 | H19: =IFERROR(H8,0) -> 1180 | I19: =IFERROR(I8,0) -> 1180 | J19: =IFERROR(J8,0) -> 1180.9 | K19: =IFERROR(K8,0) -> 1194.4 | L19: =IFERROR(L8,0) -> 1206.1 | ... AB19: =IFERROR(AB8,0) -> 1180 | AO19: NIAGARA
D20: Unilever-Label | E20: =IFERROR(E9,0) -> 1307.7959 | F20: =IFERROR(F9,0) -> 1307.7959 | G20: =IFERROR(G9,0) -> 1307.7959 | H20: =IFERROR(H9,0) -> 1307.7959 | I20: =IFERROR(I9,0) -> 1307.7959 | J20: =IFERROR(J9,0) -> 1307.7959 | K20: =IFERROR(K9,0) -> 1308.04 | L20: =IFERROR(L9,0) -> 1308.04 | ... AB20: =IFERROR(AB9,0) -> 1268.04 | AO20: UNILERVER
D21: Laive-Label | E21: =IFERROR(E10,0) -> 1250 | F21: =IFERROR(F10,0) -> 1250 | G21: =IFERROR(G10,0) -> 1250 | H21: =IFERROR(H10,0) -> 1250 | I21: =IFERROR(I10,0) -> 1250 | J21: =IFERROR(J10,0) -> 1250 | K21: =IFERROR(K10,0) -> 1330 | L21: =IFERROR(L10,0) -> 1330 | ... AB21: =IFERROR(AB10,0) -> 1303.8316 | AO21: LAVIE
D22: Giá duyệt-Label | E22: =IFERROR(E11,0) -> 1250 | F22: =IFERROR(F11,0) -> 1250 | G22: =IFERROR(G11,0) -> 1250 | H22: =IFERROR(H11,0) -> 1250 | I22: =IFERROR(I11,0) -> 1300 | J22: =IFERROR(J11,0) -> 1300 | K22: =IFERROR(K11,0) -> 1300 | L22: =IFERROR(L11,0) -> 1300 | ... AB22: =IFERROR(AB11,0) -> 1200 | AO22: Giá duyệt
D23: Giá chính phẩm-Label | E23: =IFERROR(E12,0) -> 930 | F23: =IFERROR(F12,0) -> 943.33333 | G23: =IFERROR(G12,0) -> 940 | H23: =IFERROR(H12,0) -> 940 | I23: =IFERROR(I12,0) -> 942 | J23: =IFERROR(J12,0) -> 950 | K23: =IFERROR(K12,0) -> 947.5 | L23: =IFERROR(L12,0) -> 930 | ... AB23: =IFERROR(AB12,0) -> 770 | AO23: Giá chính phẩm
C25: 110000355 | D25: iSS01G
E26: 2024 | Q26: 2025
E27: 1 | F27: 2 | G27: 3 | H27: 4 | I27: 5 | J27: 6 | K27: 7 | L27: 8 | M27: 9 | N27: 10 | O27: 11 | P27: 12 | Q27: 1 | R27: 2 | S27: 3 | T27: 4 | U27: 5 | V27: 6 | W27: 7 | X27: 8 | Y27: 9 | Z27: 10 | AA27: 11 | AB27: 12 | AC27: 1 | AD27: 2 | AE27: 3 | AF27: 4 | AG27: 5 | AH27: 6 | AI27: 7 | AJ27: 8 | AK27: 9 | AL27: 10 | AM27: 11 | AN27: 12
B28: 200332 | C28: 110000355 | D28: OUTEIRINHO | E28: {=IF(SUMPRODUCT('Giá công thức'!$G$11:$AD$106*('Giá công thức'!$A$11:$A$106=$B28)*('Giá công thức'!$B$11:$B$106=$C28)*('Giá công thức'!$C$11:$C$106="GB")*('Giá công thức'!$G$3:$AD$3=E$1)*('Giá công thức'!$G$4:$AD$4=E$2))=0,NA(),SUMPRODUCT('Giá công thức'!$G$11:$AD$106*('Giá công thức'!$A$11:$A$106=$B28)*('Giá công thức'!$B$11:$B$106=$C28)*('Giá công thức'!$C$11:$C$106="GB")*('Giá công thức'!$G$3:$AD$3=E$1)*('Giá công thức'!$G$4:$AD$4=E$2)))} -> #N/A | F28: {=IF(SUMPRODUCT('Giá công thức'!$G$11:$AD$106*('Giá công thức'!$A$11:$A$106=$B28)*('Giá công thức'!$B$11:$B$106=$C28)*('Giá công thức'!$C$11:$C$106="GB")*('Giá công thức'!$G$3:$AD$3=F$1)*('Giá công thức'!$G$4:$AD$4=F$2))=0,NA(),SUMPRODUCT('Giá công thức'!$G$11:$AD$106*('Giá công thức'!$A$11:$A$106=$B28)*('Giá công thức'!$B$11:$B$106=$C28)*('Giá công thức'!$C$11:$C$106="GB")*('Giá công thức'!$G$3:$AD$3=F$1)*('Giá công thức'!$G$4:$AD$4=F$2)))} -> #N/A | G28: {=IF(SUMPRODUCT('Giá công thức'!$G$11:$AD$106*('Giá công thức'!$A$11:$A$106=$B28)*('Giá công thức'!$B$11:$B$106=$C28)*('Giá công thức'!$C$11:$C$106="GB")*('Giá công thức'!$G$3:$AD$3=G$1)*('Giá công thức'!$G$4:$AD$4=G$2))=0,NA(),SUMPRODUCT('Giá công thức'!$G$11:$AD$106*('Giá công thức'!$A$11:$A$106=$B28)*('Giá công thức'!$B$11:$B$106=$C28)*('Giá công thức'!$C$11:$C$106="GB")*('Giá công thức'!$G$3:$AD$3=G$1)*('Giá công thức'!$G$4:$AD$4=G$2)))} -> #N/A | H28: {=IF(SUMPRODUCT('Giá công thức'!$G$11:$AD$106*('Giá công thức'!$A$11:$A$106=$B28)*('Giá công thức'!$B$11:$B$106=$C28)*('Giá công thức'!$C$11:$C$106="GB")*('Giá công thức'!$G$3:$AD$3=H$1)*('Giá công thức'!$G$4:$AD$4=H$2))=0,NA(),SUMPRODUCT('Giá công thức'!$G$11:$AD$106*('Giá công thức'!$A$11:$A$106=$B28)*('Giá công thức'!$B$11:$B$106=$C28)*('Giá công thức'!$C$11:$C$106="GB")*('Giá công thức'!$G$3:$AD$3=H$1)*('Giá công thức'!$G$4:$AD$4=H$2)))} -> #N/A | I28: {=IF(SUMPRODUCT('Giá công thức'!$G$11:$AD$106*('Giá công thức'!$A$11:$A$106=$B28)*('Giá công thức'!$B$11:$B$106=$C28)*('Giá công thức'!$C$11:$C$106="GB")*('Giá công thức'!$G$3:$AD$3=I$1)*('Giá công thức'!$G$4:$AD$4=I$2))=0,NA(),SUMPRODUCT('Giá công thức'!$G$11:$AD$106*('Giá công thức'!$A$11:$A$106=$B28)*('Giá công thức'!$B$11:$B$106=$C28)*('Giá công thức'!$C$11:$C$106="GB")*('Giá công thức'!$G$3:$AD$3=I$1)*('Giá công thức'!$G$4:$AD$4=I$2)))} -> #N/A | J28: {=IF(SUMPRODUCT('Giá công thức'!$G$11:$AD$106*('Giá công thức'!$A$11:$A$106=$B28)*('Giá công thức'!$B$11:$B$106=$C28)*('Giá công thức'!$C$11:$C$106="GB")*('Giá công thức'!$G$3:$AD$3=J$1)*('Giá công thức'!$G$4:$AD$4=J$2))=0,NA(),SUMPRODUCT('Giá công thức'!$G$11:$AD$106*('Giá công thức'!$A$11:$A$106=$B28)*('Giá công thức'!$B$11:$B$106=$C28)*('Giá công thức'!$C$11:$C$106="GB")*('Giá công thức'!$G$3:$AD$3=J$1)*('Giá công thức'!$G$4:$AD$4=J$2)))} -> #N/A | K28: {=IF(SUMPRODUCT('Giá công thức'!$G$11:$AD$106*('Giá công thức'!$A$11:$A$106=$B28)*('Giá công thức'!$B$11:$B$106=$C28)*('Giá công thức'!$C$11:$C$106="GB")*('Giá công thức'!$G$3:$AD$3=K$1)*('Giá công thức'!$G$4:$AD$4=K$2))=0,NA(),SUMPRODUCT('Giá công thức'!$G$11:$AD$106*('Giá công thức'!$A$11:$A$106=$B28)*('Giá công thức'!$B$11:$B$106=$C28)*('Giá công thức'!$C$11:$C$106="GB")*('Giá công thức'!$G$3:$AD$3=K$1)*('Giá công thức'!$G$4:$AD$4=K$2)))} -> #N/A | L28: {=IF(SUMPRODUCT('Giá công thức'!$G$11:$AD$106*('Giá công thức'!$A$11:$A$106=$B28)*('Giá công thức'!$B$11:$B$106=$C28)*('Giá công thức'!$C$11:$C$106="GB")*('Giá công thức'!$G$3:$AD$3=L$1)*('Giá công thức'!$G$4:$AD$4=L$2))=0,NA(),SUMPRODUCT('Giá công thức'!$G$11:$AD$106*('Giá công thức'!$A$11:$A$106=$B28)*('Giá công thức'!$B$11:$B$106=$C28)*('Giá công thức'!$C$11:$C$106="GB")*('Giá công thức'!$G$3:$AD$3=L$1)*('Giá công thức'!$G$4:$AD$4=L$2)))} -> #N/A | ... AB28: {=IF(SUMPRODUCT('Giá công thức'!$G$11:$AD$106*('Giá công thức'!$A$11:$A$106=$B28)*('Giá công thức'!$B$11:$B$106=$C28)*('Giá công thức'!$C$11:$C$106="GB")*('Giá công thức'!$G$3:$AD$3=AB$1)*('Giá công thức'!$G$4:$AD$4=AB$2))=0,NA(),SUMPRODUCT('Giá công thức'!$G$11:$AD$106*('Giá công thức'!$A$11:$A$106=$B28)*('Giá công thức'!$B$11:$B$106=$C28)*('Giá công thức'!$C$11:$C$106="GB")*('Giá công thức'!$G$3:$AD$3=AB$1)*('Giá công thức'!$G$4:$AD$4=AB$2)))} -> 1228 | AO28: =INDEX($E28:$AB28,MATCH("X",$E$3:$AB$3,0)) -> 1228
B29: 105194 | C29: 110000355 | D29: SUNTORY VIET NAM | E29: {=IF(SUMPRODUCT('Giá công thức'!$G$11:$AD$106*('Giá công thức'!$A$11:$A$106=$B29)*('Giá công thức'!$B$11:$B$106=$C29)*('Giá công thức'!$C$11:$C$106="GB")*('Giá công thức'!$G$3:$AD$3=E$1)*('Giá công thức'!$G$4:$AD$4=E$2))=0,NA(),SUMPRODUCT('Giá công thức'!$G$11:$AD$106*('Giá công thức'!$A$11:$A$106=$B29)*('Giá công thức'!$B$11:$B$106=$C29)*('Giá công thức'!$C$11:$C$106="GB")*('Giá công thức'!$G$3:$AD$3=E$1)*('Giá công thức'!$G$4:$AD$4=E$2)))} -> 1320 | F29: {=IF(SUMPRODUCT('Giá công thức'!$G$11:$AD$106*('Giá công thức'!$A$11:$A$106=$B29)*('Giá công thức'!$B$11:$B$106=$C29)*('Giá công thức'!$C$11:$C$106="GB")*('Giá công thức'!$G$3:$AD$3=F$1)*('Giá công thức'!$G$4:$AD$4=F$2))=0,NA(),SUMPRODUCT('Giá công thức'!$G$11:$AD$106*('Giá công thức'!$A$11:$A$106=$B29)*('Giá công thức'!$B$11:$B$106=$C29)*('Giá công thức'!$C$11:$C$106="GB")*('Giá công thức'!$G$3:$AD$3=F$1)*('Giá công thức'!$G$4:$AD$4=F$2)))} -> 1327.5 | G29: {=IF(SUMPRODUCT('Giá công thức'!$G$11:$AD$106*('Giá công thức'!$A$11:$A$106=$B29)*('Giá công thức'!$B$11:$B$106=$C29)*('Giá công thức'!$C$11:$C$106="GB")*('Giá công thức'!$G$3:$AD$3=G$1)*('Giá công thức'!$G$4:$AD$4=G$2))=0,NA(),SUMPRODUCT('Giá công thức'!$G$11:$AD$106*('Giá công thức'!$A$11:$A$106=$B29)*('Giá công thức'!$B$11:$B$106=$C29)*('Giá công thức'!$C$11:$C$106="GB")*('Giá công thức'!$G$3:$AD$3=G$1)*('Giá công thức'!$G$4:$AD$4=G$2)))} -> 1340 | H29: {=IF(SUMPRODUCT('Giá công thức'!$G$11:$AD$106*('Giá công thức'!$A$11:$A$106=$B29)*('Giá công thức'!$B$11:$B$106=$C29)*('Giá công thức'!$C$11:$C$106="GB")*('Giá công thức'!$G$3:$AD$3=H$1)*('Giá công thức'!$G$4:$AD$4=H$2))=0,NA(),SUMPRODUCT('Giá công thức'!$G$11:$AD$106*('Giá công thức'!$A$11:$A$106=$B29)*('Giá công thức'!$B$11:$B$106=$C29)*('Giá công thức'!$C$11:$C$106="GB")*('Giá công thức'!$G$3:$AD$3=H$1)*('Giá công thức'!$G$4:$AD$4=H$2)))} -> 1342.5 | I29: {=IF(SUMPRODUCT('Giá công thức'!$G$11:$AD$106*('Giá công thức'!$A$11:$A$106=$B29)*('Giá công thức'!$B$11:$B$106=$C29)*('Giá công thức'!$C$11:$C$106="GB")*('Giá công thức'!$G$3:$AD$3=I$1)*('Giá công thức'!$G$4:$AD$4=I$2))=0,NA(),SUMPRODUCT('Giá công thức'!$G$11:$AD$106*('Giá công thức'!$A$11:$A$106=$B29)*('Giá công thức'!$B$11:$B$106=$C29)*('Giá công thức'!$C$11:$C$106="GB")*('Giá công thức'!$G$3:$AD$3=I$1)*('Giá công thức'!$G$4:$AD$4=I$2)))} -> 1346.5 | J29: {=IF(SUMPRODUCT('Giá công thức'!$G$11:$AD$106*('Giá công thức'!$A$11:$A$106=$B29)*('Giá công thức'!$B$11:$B$106=$C29)*('Giá công thức'!$C$11:$C$106="GB")*('Giá công thức'!$G$3:$AD$3=J$1)*('Giá công thức'!$G$4:$AD$4=J$2))=0,NA(),SUMPRODUCT('Giá công thức'!$G$11:$AD$106*('Giá công thức'!$A$11:$A$106=$B29)*('Giá công thức'!$B$11:$B$106=$C29)*('Giá công thức'!$C$11:$C$106="GB")*('Giá công thức'!$G$3:$AD$3=J$1)*('Giá công thức'!$G$4:$AD$4=J$2)))} -> 1361.5 | K29: {=IF(SUMPRODUCT('Giá công thức'!$G$11:$AD$106*('Giá công thức'!$A$11:$A$106=$B29)*('Giá công thức'!$B$11:$B$106=$C29)*('Giá công thức'!$C$11:$C$106="GB")*('Giá công thức'!$G$3:$AD$3=K$1)*('Giá công thức'!$G$4:$AD$4=K$2))=0,NA(),SUMPRODUCT('Giá công thức'!$G$11:$AD$106*('Giá công thức'!$A$11:$A$106=$B29)*('Giá công thức'!$B$11:$B$106=$C29)*('Giá công thức'!$C$11:$C$106="GB")*('Giá công thức'!$G$3:$AD$3=K$1)*('Giá công thức'!$G$4:$AD$4=K$2)))} -> 1377.5 | L29: {=IF(SUMPRODUCT('Giá công thức'!$G$11:$AD$106*('Giá công thức'!$A$11:$A$106=$B29)*('Giá công thức'!$B$11:$B$106=$C29)*('Giá công thức'!$C$11:$C$106="GB")*('Giá công thức'!$G$3:$AD$3=L$1)*('Giá công thức'!$G$4:$AD$4=L$2))=0,NA(),SUMPRODUCT('Giá công thức'!$G$11:$AD$106*('Giá công thức'!$A$11:$A$106=$B29)*('Giá công thức'!$B$11:$B$106=$C29)*('Giá công thức'!$C$11:$C$106="GB")*('Giá công thức'!$G$3:$AD$3=L$1)*('Giá công thức'!$G$4:$AD$4=L$2)))} -> 1388.5 | ... AB29: {=IF(SUMPRODUCT('Giá công thức'!$G$11:$AD$106*('Giá công thức'!$A$11:$A$106=$B29)*('Giá công thức'!$B$11:$B$106=$C29)*('Giá công thức'!$C$11:$C$106="GB")*('Giá công thức'!$G$3:$AD$3=AB$1)*('Giá công thức'!$G$4:$AD$4=AB$2))=0,NA(),SUMPRODUCT('Giá công thức'!$G$11:$AD$106*('Giá công thức'!$A$11:$A$106=$B29)*('Giá công thức'!$B$11:$B$106=$C29)*('Giá công thức'!$C$11:$C$106="GB")*('Giá công thức'!$G$3:$AD$3=AB$1)*('Giá công thức'!$G$4:$AD$4=AB$2)))} -> 1266.6562 | AO29: =INDEX($E29:$AB29,MATCH("X",$E$3:$AB$3,0)) -> 1266.6562
A30: 110000355 | C30: 110000355 | D30: Giá duyệt | E30: {=SUMPRODUCT(General_Data*(Code_General_Data=$A30)*(Year=E$1)*(Month=E$2))} -> 1280 | F30: {=SUMPRODUCT(General_Data*(Code_General_Data=$A30)*(Year=F$1)*(Month=F$2))} -> 1280 | G30: {=SUMPRODUCT(General_Data*(Code_General_Data=$A30)*(Year=G$1)*(Month=G$2))} -> 1280 | H30: {=SUMPRODUCT(General_Data*(Code_General_Data=$A30)*(Year=H$1)*(Month=H$2))} -> 1280 | I30: {=SUMPRODUCT(General_Data*(Code_General_Data=$A30)*(Year=I$1)*(Month=I$2))} -> 1330 | J30: {=SUMPRODUCT(General_Data*(Code_General_Data=$A30)*(Year=J$1)*(Month=J$2))} -> 1330 | K30: {=SUMPRODUCT(General_Data*(Code_General_Data=$A30)*(Year=K$1)*(Month=K$2))} -> 1330 | L30: {=SUMPRODUCT(General_Data*(Code_General_Data=$A30)*(Year=L$1)*(Month=L$2))} -> 1330 | ... AB30: {=SUMPRODUCT(General_Data*(Code_General_Data=$A30)*(Year=AB$1)*(Month=AB$2))} -> 1230 | AO30: =INDEX($E30:$AB30,MATCH("X",$E$3:$AB$3,0)) -> 1230
A31: PETVirgin | D31: Giá chính phẩm | E31: {=SUMPRODUCT(General_Data*(Code_General_Data=$A31)*(Year=E$1)*(Month=E$2))} -> 930 | F31: {=SUMPRODUCT(General_Data*(Code_General_Data=$A31)*(Year=F$1)*(Month=F$2))} -> 943.33333 | G31: {=SUMPRODUCT(General_Data*(Code_General_Data=$A31)*(Year=G$1)*(Month=G$2))} -> 940 | H31: {=SUMPRODUCT(General_Data*(Code_General_Data=$A31)*(Year=H$1)*(Month=H$2))} -> 940 | I31: {=SUMPRODUCT(General_Data*(Code_General_Data=$A31)*(Year=I$1)*(Month=I$2))} -> 942 | J31: {=SUMPRODUCT(General_Data*(Code_General_Data=$A31)*(Year=J$1)*(Month=J$2))} -> 950 | K31: {=SUMPRODUCT(General_Data*(Code_General_Data=$A31)*(Year=K$1)*(Month=K$2))} -> 947.5 | L31: {=SUMPRODUCT(General_Data*(Code_General_Data=$A31)*(Year=L$1)*(Month=L$2))} -> 930 | ... AB31: {=SUMPRODUCT(General_Data*(Code_General_Data=$A31)*(Year=AB$1)*(Month=AB$2))} -> 770 | AO31: =INDEX($E31:$AB31,MATCH("X",$E$3:$AB$3,0)) -> 770
D32: Chênh lệch | E32: =E30-E31 -> 350 | F32: =F30-F31 -> 336.66667 | G32: =G30-G31 -> 340 | H32: =H30-H31 -> 340 | I32: =I30-I31 -> 388 | J32: =J30-J31 -> 380 | K32: =K30-K31 -> 382.5 | L32: =L30-L31 -> 400 | ... AB32: =AB30-AB31 -> 460
D33: %Chênh lệch | E33: =IFERROR(E32/E31,0) -> 0.37634409 | F33: =IFERROR(F32/F31,0) -> 0.35689046 | G33: =IFERROR(G32/G31,0) -> 0.36170213 | H33: =IFERROR(H32/H31,0) -> 0.36170213 | I33: =IFERROR(I32/I31,0) -> 0.4118896 | J33: =IFERROR(J32/J31,0) -> 0.4 | K33: =IFERROR(K32/K31,0) -> 0.40369393 | L33: =IFERROR(L32/L31,0) -> 0.43010753 | ... AB33: =IFERROR(AB32/AB31,0) -> 0.5974026
D34: Chênh lệch-Line Drop | E34: =E30 -> 1280 | F34: =F30 -> 1280 | G34: =G30 -> 1280 | H34: =H30 -> 1280 | I34: =I30 -> 1330 | J34: =J30 -> 1330 | K34: =K30 -> 1330 | L34: =L30 -> 1330 | ... AB34: =AB30 -> 1230
D35: Chênh lệch-Label | E35: =E31+E32/2 -> 1105 | F35: =F31+F32/2 -> 1111.6667 | G35: =G31+G32/2 -> 1110 | H35: =H31+H32/2 -> 1110 | I35: =I31+I32/2 -> 1136 | J35: =J31+J32/2 -> 1140 | K35: =K31+K32/2 -> 1138.75 | L35: =L31+L32/2 -> 1130 | ... AB35: =AB31+AB32/2 -> 1000
D36: Giá duyệt-Area | E36: =E30 -> 1280 | F36: =F30 -> 1280 | G36: =G30 -> 1280 | H36: =H30 -> 1280 | I36: =I30 -> 1330 | J36: =J30 -> 1330 | K36: =K30 -> 1330 | L36: =L30 -> 1330 | ... AB36: =AB30 -> 1230
D37: Giá chính phẩm-Area | E37: =E31 -> 930 | F37: =F31 -> 943.33333 | G37: =G31 -> 940 | H37: =H31 -> 940 | I37: =I31 -> 942 | J37: =J31 -> 950 | K37: =K31 -> 947.5 | L37: =L31 -> 930 | ... AB37: =AB31 -> 770
D38: Outeirinho-Label | E38: =IFERROR(E28,0) -> 0 | F38: =IFERROR(F28,0) -> 0 | G38: =IFERROR(G28,0) -> 0 | H38: =IFERROR(H28,0) -> 0 | I38: =IFERROR(I28,0) -> 0 | J38: =IFERROR(J28,0) -> 0 | K38: =IFERROR(K28,0) -> 0 | L38: =IFERROR(L28,0) -> 0 | ... AB38: =IFERROR(AB28,0) -> 1228 | AO38: OUTEIRINHO
D39: Suntory VN-Label | E39: =IFERROR(E29,0) -> 1320 | F39: =IFERROR(F29,0) -> 1327.5 | G39: =IFERROR(G29,0) -> 1340 | H39: =IFERROR(H29,0) -> 1342.5 | I39: =IFERROR(I29,0) -> 1346.5 | J39: =IFERROR(J29,0) -> 1361.5 | K39: =IFERROR(K29,0) -> 1377.5 | L39: =IFERROR(L29,0) -> 1388.5 | ... AB39: =IFERROR(AB29,0) -> 1266.6562 | AO39: SUNTORY VN
D40: Giá duyệt-Label | E40: =IFERROR(E30,0) -> 1280 | F40: =IFERROR(F30,0) -> 1280 | G40: =IFERROR(G30,0) -> 1280 | H40: =IFERROR(H30,0) -> 1280 | I40: =IFERROR(I30,0) -> 1330 | J40: =IFERROR(J30,0) -> 1330 | K40: =IFERROR(K30,0) -> 1330 | L40: =IFERROR(L30,0) -> 1330 | ... AB40: =IFERROR(AB30,0) -> 1230 | AO40: Giá duyệt
D41: Giá chính phẩm-Label | E41: =IFERROR(E31,0) -> 930 | F41: =IFERROR(F31,0) -> 943.33333 | G41: =IFERROR(G31,0) -> 940 | H41: =IFERROR(H31,0) -> 940 | I41: =IFERROR(I31,0) -> 942 | J41: =IFERROR(J31,0) -> 950 | K41: =IFERROR(K31,0) -> 947.5 | L41: =IFERROR(L31,0) -> 930 | ... AB41: =IFERROR(AB31,0) -> 770 | AO41: Giá chính phẩm
C43: 110000332 | D43: iSS1084G
E44: 2024 | Q44: 2025
E45: 1 | F45: 2 | G45: 3 | H45: 4 | I45: 5 | J45: 6 | K45: 7 | L45: 8 | M45: 9 | N45: 10 | O45: 11 | P45: 12 | Q45: 1 | R45: 2 | S45: 3 | T45: 4 | U45: 5 | V45: 6 | W45: 7 | X45: 8 | Y45: 9 | Z45: 10 | AA45: 11 | AB45: 12 | AC45: 1 | AD45: 2 | AE45: 3 | AF45: 4 | AG45: 5 | AH45: 6 | AI45: 7 | AJ45: 8 | AK45: 9 | AL45: 10 | AM45: 11 | AN45: 12
B46: 102990 | C46: 110000332 | D46: COCA VIET NAM | E46: {=IF(SUMPRODUCT('Giá công thức'!$G$11:$AD$106*('Giá công thức'!$A$11:$A$106=$B46)*('Giá công thức'!$B$11:$B$106=$C46)*('Giá công thức'!$C$11:$C$106="GB")*('Giá công thức'!$G$3:$AD$3=E$1)*('Giá công thức'!$G$4:$AD$4=E$2))=0,NA(),SUMPRODUCT('Giá công thức'!$G$11:$AD$106*('Giá công thức'!$A$11:$A$106=$B46)*('Giá công thức'!$B$11:$B$106=$C46)*('Giá công thức'!$C$11:$C$106="GB")*('Giá công thức'!$G$3:$AD$3=E$1)*('Giá công thức'!$G$4:$AD$4=E$2)))} -> 1315 | F46: {=IF(SUMPRODUCT('Giá công thức'!$G$11:$AD$106*('Giá công thức'!$A$11:$A$106=$B46)*('Giá công thức'!$B$11:$B$106=$C46)*('Giá công thức'!$C$11:$C$106="GB")*('Giá công thức'!$G$3:$AD$3=F$1)*('Giá công thức'!$G$4:$AD$4=F$2))=0,NA(),SUMPRODUCT('Giá công thức'!$G$11:$AD$106*('Giá công thức'!$A$11:$A$106=$B46)*('Giá công thức'!$B$11:$B$106=$C46)*('Giá công thức'!$C$11:$C$106="GB")*('Giá công thức'!$G$3:$AD$3=F$1)*('Giá công thức'!$G$4:$AD$4=F$2)))} -> 1315 | G46: {=IF(SUMPRODUCT('Giá công thức'!$G$11:$AD$106*('Giá công thức'!$A$11:$A$106=$B46)*('Giá công thức'!$B$11:$B$106=$C46)*('Giá công thức'!$C$11:$C$106="GB")*('Giá công thức'!$G$3:$AD$3=G$1)*('Giá công thức'!$G$4:$AD$4=G$2))=0,NA(),SUMPRODUCT('Giá công thức'!$G$11:$AD$106*('Giá công thức'!$A$11:$A$106=$B46)*('Giá công thức'!$B$11:$B$106=$C46)*('Giá công thức'!$C$11:$C$106="GB")*('Giá công thức'!$G$3:$AD$3=G$1)*('Giá công thức'!$G$4:$AD$4=G$2)))} -> 1315 | H46: {=IF(SUMPRODUCT('Giá công thức'!$G$11:$AD$106*('Giá công thức'!$A$11:$A$106=$B46)*('Giá công thức'!$B$11:$B$106=$C46)*('Giá công thức'!$C$11:$C$106="GB")*('Giá công thức'!$G$3:$AD$3=H$1)*('Giá công thức'!$G$4:$AD$4=H$2))=0,NA(),SUMPRODUCT('Giá công thức'!$G$11:$AD$106*('Giá công thức'!$A$11:$A$106=$B46)*('Giá công thức'!$B$11:$B$106=$C46)*('Giá công thức'!$C$11:$C$106="GB")*('Giá công thức'!$G$3:$AD$3=H$1)*('Giá công thức'!$G$4:$AD$4=H$2)))} -> 1315 | I46: {=IF(SUMPRODUCT('Giá công thức'!$G$11:$AD$106*('Giá công thức'!$A$11:$A$106=$B46)*('Giá công thức'!$B$11:$B$106=$C46)*('Giá công thức'!$C$11:$C$106="GB")*('Giá công thức'!$G$3:$AD$3=I$1)*('Giá công thức'!$G$4:$AD$4=I$2))=0,NA(),SUMPRODUCT('Giá công thức'!$G$11:$AD$106*('Giá công thức'!$A$11:$A$106=$B46)*('Giá công thức'!$B$11:$B$106=$C46)*('Giá công thức'!$C$11:$C$106="GB")*('Giá công thức'!$G$3:$AD$3=I$1)*('Giá công thức'!$G$4:$AD$4=I$2)))} -> 1315 | J46: {=IF(SUMPRODUCT('Giá công thức'!$G$11:$AD$106*('Giá công thức'!$A$11:$A$106=$B46)*('Giá công thức'!$B$11:$B$106=$C46)*('Giá công thức'!$C$11:$C$106="GB")*('Giá công thức'!$G$3:$AD$3=J$1)*('Giá công thức'!$G$4:$AD$4=J$2))=0,NA(),SUMPRODUCT('Giá công thức'!$G$11:$AD$106*('Giá công thức'!$A$11:$A$106=$B46)*('Giá công thức'!$B$11:$B$106=$C46)*('Giá công thức'!$C$11:$C$106="GB")*('Giá công thức'!$G$3:$AD$3=J$1)*('Giá công thức'!$G$4:$AD$4=J$2)))} -> 1315 | K46: {=IF(SUMPRODUCT('Giá công thức'!$G$11:$AD$106*('Giá công thức'!$A$11:$A$106=$B46)*('Giá công thức'!$B$11:$B$106=$C46)*('Giá công thức'!$C$11:$C$106="GB")*('Giá công thức'!$G$3:$AD$3=K$1)*('Giá công thức'!$G$4:$AD$4=K$2))=0,NA(),SUMPRODUCT('Giá công thức'!$G$11:$AD$106*('Giá công thức'!$A$11:$A$106=$B46)*('Giá công thức'!$B$11:$B$106=$C46)*('Giá công thức'!$C$11:$C$106="GB")*('Giá công thức'!$G$3:$AD$3=K$1)*('Giá công thức'!$G$4:$AD$4=K$2)))} -> 1315 | L46: {=IF(SUMPRODUCT('Giá công thức'!$G$11:$AD$106*('Giá công thức'!$A$11:$A$106=$B46)*('Giá công thức'!$B$11:$B$106=$C46)*('Giá công thức'!$C$11:$C$106="GB")*('Giá công thức'!$G$3:$AD$3=L$1)*('Giá công thức'!$G$4:$AD$4=L$2))=0,NA(),SUMPRODUCT('Giá công thức'!$G$11:$AD$106*('Giá công thức'!$A$11:$A$106=$B46)*('Giá công thức'!$B$11:$B$106=$C46)*('Giá công thức'!$C$11:$C$106="GB")*('Giá công thức'!$G$3:$AD$3=L$1)*('Giá công thức'!$G$4:$AD$4=L$2)))} -> 1315 | ... AB46: {=IF(SUMPRODUCT('Giá công thức'!$G$11:$AD$106*('Giá công thức'!$A$11:$A$106=$B46)*('Giá công thức'!$B$11:$B$106=$C46)*('Giá công thức'!$C$11:$C$106="GB")*('Giá công thức'!$G$3:$AD$3=AB$1)*('Giá công thức'!$G$4:$AD$4=AB$2))=0,NA(),SUMPRODUCT('Giá công thức'!$G$11:$AD$106*('Giá công thức'!$A$11:$A$106=$B46)*('Giá công thức'!$B$11:$B$106=$C46)*('Giá công thức'!$C$11:$C$106="GB")*('Giá công thức'!$G$3:$AD$3=AB$1)*('Giá công thức'!$G$4:$AD$4=AB$2)))} -> 1348.3 | AO46: =INDEX($E46:$AB46,MATCH("X",$E$3:$AB$3,0)) -> 1348.3
B47: 105194 | C47: 110000332 | D47: SUNTORY VIET NAM | E47: {=IF(SUMPRODUCT('Giá công thức'!$G$11:$AD$106*('Giá công thức'!$A$11:$A$106=$B47)*('Giá công thức'!$B$11:$B$106=$C47)*('Giá công thức'!$C$11:$C$106="GB")*('Giá công thức'!$G$3:$AD$3=E$1)*('Giá công thức'!$G$4:$AD$4=E$2))=0,NA(),SUMPRODUCT('Giá công thức'!$G$11:$AD$106*('Giá công thức'!$A$11:$A$106=$B47)*('Giá công thức'!$B$11:$B$106=$C47)*('Giá công thức'!$C$11:$C$106="GB")*('Giá công thức'!$G$3:$AD$3=E$1)*('Giá công thức'!$G$4:$AD$4=E$2)))} -> 1340 | F47: {=IF(SUMPRODUCT('Giá công thức'!$G$11:$AD$106*('Giá công thức'!$A$11:$A$106=$B47)*('Giá công thức'!$B$11:$B$106=$C47)*('Giá công thức'!$C$11:$C$106="GB")*('Giá công thức'!$G$3:$AD$3=F$1)*('Giá công thức'!$G$4:$AD$4=F$2))=0,NA(),SUMPRODUCT('Giá công thức'!$G$11:$AD$106*('Giá công thức'!$A$11:$A$106=$B47)*('Giá công thức'!$B$11:$B$106=$C47)*('Giá công thức'!$C$11:$C$106="GB")*('Giá công thức'!$G$3:$AD$3=F$1)*('Giá công thức'!$G$4:$AD$4=F$2)))} -> 1347.5 | G47: {=IF(SUMPRODUCT('Giá công thức'!$G$11:$AD$106*('Giá công thức'!$A$11:$A$106=$B47)*('Giá công thức'!$B$11:$B$106=$C47)*('Giá công thức'!$C$11:$C$106="GB")*('Giá công thức'!$G$3:$AD$3=G$1)*('Giá công thức'!$G$4:$AD$4=G$2))=0,NA(),SUMPRODUCT('Giá công thức'!$G$11:$AD$106*('Giá công thức'!$A$11:$A$106=$B47)*('Giá công thức'!$B$11:$B$106=$C47)*('Giá công thức'!$C$11:$C$106="GB")*('Giá công thức'!$G$3:$AD$3=G$1)*('Giá công thức'!$G$4:$AD$4=G$2)))} -> 1360 | H47: {=IF(SUMPRODUCT('Giá công thức'!$G$11:$AD$106*('Giá công thức'!$A$11:$A$106=$B47)*('Giá công thức'!$B$11:$B$106=$C47)*('Giá công thức'!$C$11:$C$106="GB")*('Giá công thức'!$G$3:$AD$3=H$1)*('Giá công thức'!$G$4:$AD$4=H$2))=0,NA(),SUMPRODUCT('Giá công thức'!$G$11:$AD$106*('Giá công thức'!$A$11:$A$106=$B47)*('Giá công thức'!$B$11:$B$106=$C47)*('Giá công thức'!$C$11:$C$106="GB")*('Giá công thức'!$G$3:$AD$3=H$1)*('Giá công thức'!$G$4:$AD$4=H$2)))} -> 1362.5 | I47: {=IF(SUMPRODUCT('Giá công thức'!$G$11:$AD$106*('Giá công thức'!$A$11:$A$106=$B47)*('Giá công thức'!$B$11:$B$106=$C47)*('Giá công thức'!$C$11:$C$106="GB")*('Giá công thức'!$G$3:$AD$3=I$1)*('Giá công thức'!$G$4:$AD$4=I$2))=0,NA(),SUMPRODUCT('Giá công thức'!$G$11:$AD$106*('Giá công thức'!$A$11:$A$106=$B47)*('Giá công thức'!$B$11:$B$106=$C47)*('Giá công thức'!$C$11:$C$106="GB")*('Giá công thức'!$G$3:$AD$3=I$1)*('Giá công thức'!$G$4:$AD$4=I$2)))} -> 1366.5 | J47: {=IF(SUMPRODUCT('Giá công thức'!$G$11:$AD$106*('Giá công thức'!$A$11:$A$106=$B47)*('Giá công thức'!$B$11:$B$106=$C47)*('Giá công thức'!$C$11:$C$106="GB")*('Giá công thức'!$G$3:$AD$3=J$1)*('Giá công thức'!$G$4:$AD$4=J$2))=0,NA(),SUMPRODUCT('Giá công thức'!$G$11:$AD$106*('Giá công thức'!$A$11:$A$106=$B47)*('Giá công thức'!$B$11:$B$106=$C47)*('Giá công thức'!$C$11:$C$106="GB")*('Giá công thức'!$G$3:$AD$3=J$1)*('Giá công thức'!$G$4:$AD$4=J$2)))} -> 1381.5 | K47: {=IF(SUMPRODUCT('Giá công thức'!$G$11:$AD$106*('Giá công thức'!$A$11:$A$106=$B47)*('Giá công thức'!$B$11:$B$106=$C47)*('Giá công thức'!$C$11:$C$106="GB")*('Giá công thức'!$G$3:$AD$3=K$1)*('Giá công thức'!$G$4:$AD$4=K$2))=0,NA(),SUMPRODUCT('Giá công thức'!$G$11:$AD$106*('Giá công thức'!$A$11:$A$106=$B47)*('Giá công thức'!$B$11:$B$106=$C47)*('Giá công thức'!$C$11:$C$106="GB")*('Giá công thức'!$G$3:$AD$3=K$1)*('Giá công thức'!$G$4:$AD$4=K$2)))} -> 1397.5 | L47: {=IF(SUMPRODUCT('Giá công thức'!$G$11:$AD$106*('Giá công thức'!$A$11:$A$106=$B47)*('Giá công thức'!$B$11:$B$106=$C47)*('Giá công thức'!$C$11:$C$106="GB")*('Giá công thức'!$G$3:$AD$3=L$1)*('Giá công thức'!$G$4:$AD$4=L$2))=0,NA(),SUMPRODUCT('Giá công thức'!$G$11:$AD$106*('Giá công thức'!$A$11:$A$106=$B47)*('Giá công thức'!$B$11:$B$106=$C47)*('Giá công thức'!$C$11:$C$106="GB")*('Giá công thức'!$G$3:$AD$3=L$1)*('Giá công thức'!$G$4:$AD$4=L$2)))} -> 1408.5 | ... AB47: {=IF(SUMPRODUCT('Giá công thức'!$G$11:$AD$106*('Giá công thức'!$A$11:$A$106=$B47)*('Giá công thức'!$B$11:$B$106=$C47)*('Giá công thức'!$C$11:$C$106="GB")*('Giá công thức'!$G$3:$AD$3=AB$1)*('Giá công thức'!$G$4:$AD$4=AB$2))=0,NA(),SUMPRODUCT('Giá công thức'!$G$11:$AD$106*('Giá công thức'!$A$11:$A$106=$B47)*('Giá công thức'!$B$11:$B$106=$C47)*('Giá công thức'!$C$11:$C$106="GB")*('Giá công thức'!$G$3:$AD$3=AB$1)*('Giá công thức'!$G$4:$AD$4=AB$2)))} -> 1266.6562 | AO47: =INDEX($E47:$AB47,MATCH("X",$E$3:$AB$3,0)) -> 1266.6562
A48: 110000332 | C48: 110000332 | D48: Giá duyệt | E48: {=SUMPRODUCT(General_Data*(Code_General_Data=$A48)*(Year=E$1)*(Month=E$2))} -> 1340 | F48: {=SUMPRODUCT(General_Data*(Code_General_Data=$A48)*(Year=F$1)*(Month=F$2))} -> 1340 | G48: {=SUMPRODUCT(General_Data*(Code_General_Data=$A48)*(Year=G$1)*(Month=G$2))} -> 1340 | H48: {=SUMPRODUCT(General_Data*(Code_General_Data=$A48)*(Year=H$1)*(Month=H$2))} -> 1340 | I48: {=SUMPRODUCT(General_Data*(Code_General_Data=$A48)*(Year=I$1)*(Month=I$2))} -> 1390 | J48: {=SUMPRODUCT(General_Data*(Code_General_Data=$A48)*(Year=J$1)*(Month=J$2))} -> 1390 | K48: {=SUMPRODUCT(General_Data*(Code_General_Data=$A48)*(Year=K$1)*(Month=K$2))} -> 1390 | L48: {=SUMPRODUCT(General_Data*(Code_General_Data=$A48)*(Year=L$1)*(Month=L$2))} -> 1390 | ... AB48: {=SUMPRODUCT(General_Data*(Code_General_Data=$A48)*(Year=AB$1)*(Month=AB$2))} -> 1290 | AO48: =INDEX($E48:$AB48,MATCH("X",$E$3:$AB$3,0)) -> 1290
A49: PETVirgin | D49: Giá chính phẩm | E49: {=SUMPRODUCT(General_Data*(Code_General_Data=$A49)*(Year=E$1)*(Month=E$2))} -> 930 | F49: {=SUMPRODUCT(General_Data*(Code_General_Data=$A49)*(Year=F$1)*(Month=F$2))} -> 943.33333 | G49: {=SUMPRODUCT(General_Data*(Code_General_Data=$A49)*(Year=G$1)*(Month=G$2))} -> 940 | H49: {=SUMPRODUCT(General_Data*(Code_General_Data=$A49)*(Year=H$1)*(Month=H$2))} -> 940 | I49: {=SUMPRODUCT(General_Data*(Code_General_Data=$A49)*(Year=I$1)*(Month=I$2))} -> 942 | J49: {=SUMPRODUCT(General_Data*(Code_General_Data=$A49)*(Year=J$1)*(Month=J$2))} -> 950 | K49: {=SUMPRODUCT(General_Data*(Code_General_Data=$A49)*(Year=K$1)*(Month=K$2))} -> 947.5 | L49: {=SUMPRODUCT(General_Data*(Code_General_Data=$A49)*(Year=L$1)*(Month=L$2))} -> 930 | ... AB49: {=SUMPRODUCT(General_Data*(Code_General_Data=$A49)*(Year=AB$1)*(Month=AB$2))} -> 770 | AO49: =INDEX($E49:$AB49,MATCH("X",$E$3:$AB$3,0)) -> 770
D50: Chênh lệch-Area | E50: =E48-E49 -> 410 | F50: =F48-F49 -> 396.66667 | G50: =G48-G49 -> 400 | H50: =H48-H49 -> 400 | I50: =I48-I49 -> 448 | J50: =J48-J49 -> 440 | K50: =K48-K49 -> 442.5 | L50: =L48-L49 -> 460 | ... AB50: =AB48-AB49 -> 520
D51: %Chênh lệch | E51: =IFERROR(E50/E49,0) -> 0.44086022 | F51: =IFERROR(F50/F49,0) -> 0.4204947 | G51: =IFERROR(G50/G49,0) -> 0.42553191 | H51: =IFERROR(H50/H49,0) -> 0.42553191 | I51: =IFERROR(I50/I49,0) -> 0.47558386 | J51: =IFERROR(J50/J49,0) -> 0.46315789 | K51: =IFERROR(K50/K49,0) -> 0.46701847 | L51: =IFERROR(L50/L49,0) -> 0.49462366 | ... AB51: =IFERROR(AB50/AB49,0) -> 0.67532468
D52: Chênh lệch-Line Drop | E52: =E48 -> 1340 | F52: =F48 -> 1340 | G52: =G48 -> 1340 | H52: =H48 -> 1340 | I52: =I48 -> 1390 | J52: =J48 -> 1390 | K52: =K48 -> 1390 | L52: =L48 -> 1390 | ... AB52: =AB48 -> 1290
D53: Chênh lệch-Label | E53: =E49+E50/2 -> 1135 | F53: =F49+F50/2 -> 1141.6667 | G53: =G49+G50/2 -> 1140 | H53: =H49+H50/2 -> 1140 | I53: =I49+I50/2 -> 1166 | J53: =J49+J50/2 -> 1170 | K53: =K49+K50/2 -> 1168.75 | L53: =L49+L50/2 -> 1160 | ... AB53: =AB49+AB50/2 -> 1030
D54: Giá duyệt-Area | E54: =E48 -> 1340 | F54: =F48 -> 1340 | G54: =G48 -> 1340 | H54: =H48 -> 1340 | I54: =I48 -> 1390 | J54: =J48 -> 1390 | K54: =K48 -> 1390 | L54: =L48 -> 1390 | ... AB54: =AB48 -> 1290
D55: Giá chính phẩm-Area | E55: =E49 -> 930 | F55: =F49 -> 943.33333 | G55: =G49 -> 940 | H55: =H49 -> 940 | I55: =I49 -> 942 | J55: =J49 -> 950 | K55: =K49 -> 947.5 | L55: =L49 -> 930 | ... AB55: =AB49 -> 770
D56: Coca VN-Label | E56: =IFERROR(E46,0) -> 1315 | F56: =IFERROR(F46,0) -> 1315 | G56: =IFERROR(G46,0) -> 1315 | H56: =IFERROR(H46,0) -> 1315 | I56: =IFERROR(I46,0) -> 1315 | J56: =IFERROR(J46,0) -> 1315 | K56: =IFERROR(K46,0) -> 1315 | L56: =IFERROR(L46,0) -> 1315 | ... AB56: =IFERROR(AB46,0) -> 1348.3 | AO56: COCA VN
D57: Suntory VN-Label | E57: =IFERROR(E47,0) -> 1340 | F57: =IFERROR(F47,0) -> 1347.5 | G57: =IFERROR(G47,0) -> 1360 | H57: =IFERROR(H47,0) -> 1362.5 | I57: =IFERROR(I47,0) -> 1366.5 | J57: =IFERROR(J47,0) -> 1381.5 | K57: =IFERROR(K47,0) -> 1397.5 | L57: =IFERROR(L47,0) -> 1408.5 | ... AB57: =IFERROR(AB47,0) -> 1266.6562 | AO57: SUNTORY VN
D58: Giá duyệt-Label | E58: =IFERROR(E48,0) -> 1340 | F58: =IFERROR(F48,0) -> 1340 | G58: =IFERROR(G48,0) -> 1340 | H58: =IFERROR(H48,0) -> 1340 | I58: =IFERROR(I48,0) -> 1390 | J58: =IFERROR(J48,0) -> 1390 | K58: =IFERROR(K48,0) -> 1390 | L58: =IFERROR(L48,0) -> 1390 | ... AB58: =IFERROR(AB48,0) -> 1290 | AO58: Giá duyệt
D59: Giá chính phẩm-Label | E59: =IFERROR(E49,0) -> 930 | F59: =IFERROR(F49,0) -> 943.33333 | G59: =IFERROR(G49,0) -> 940 | H59: =IFERROR(H49,0) -> 940 | I59: =IFERROR(I49,0) -> 942 | J59: =IFERROR(J49,0) -> 950 | K59: =IFERROR(K49,0) -> 947.5 | L59: =IFERROR(L49,0) -> 930 | ... AB59: =IFERROR(AB49,0) -> 770 | AO59: Giá chính phẩm
C61: 110000481 | D61: PCF01
E62: 2024 | Q62: 2025
E63: 1 | F63: 2 | G63: 3 | H63: 4 | I63: 5 | J63: 6 | K63: 7 | L63: 8 | M63: 9 | N63: 10 | O63: 11 | P63: 12 | Q63: 1 | R63: 2 | S63: 3 | T63: 4 | U63: 5 | V63: 6 | W63: 7 | X63: 8 | Y63: 9 | Z63: 10 | AA63: 11 | AB63: 12 | AC63: 1 | AD63: 2 | AE63: 3 | AF63: 4 | AG63: 5 | AH63: 6 | AI63: 7 | AJ63: 8 | AK63: 9 | AL63: 10 | AM63: 11 | AN63: 12
B64: 105263 | C64: 110000481 | D64: Unilever | E64: {=IF(SUMPRODUCT('Giá công thức'!$G$11:$AD$106*('Giá công thức'!$A$11:$A$106=$B64)*('Giá công thức'!$B$11:$B$106=$C64)*('Giá công thức'!$C$11:$C$106="GB")*('Giá công thức'!$G$3:$AD$3=E$1)*('Giá công thức'!$G$4:$AD$4=E$2))=0,NA(),SUMPRODUCT('Giá công thức'!$G$11:$AD$106*('Giá công thức'!$A$11:$A$106=$B64)*('Giá công thức'!$B$11:$B$106=$C64)*('Giá công thức'!$C$11:$C$106="GB")*('Giá công thức'!$G$3:$AD$3=E$1)*('Giá công thức'!$G$4:$AD$4=E$2)))} -> #N/A | F64: {=IF(SUMPRODUCT('Giá công thức'!$G$11:$AD$106*('Giá công thức'!$A$11:$A$106=$B64)*('Giá công thức'!$B$11:$B$106=$C64)*('Giá công thức'!$C$11:$C$106="GB")*('Giá công thức'!$G$3:$AD$3=F$1)*('Giá công thức'!$G$4:$AD$4=F$2))=0,NA(),SUMPRODUCT('Giá công thức'!$G$11:$AD$106*('Giá công thức'!$A$11:$A$106=$B64)*('Giá công thức'!$B$11:$B$106=$C64)*('Giá công thức'!$C$11:$C$106="GB")*('Giá công thức'!$G$3:$AD$3=F$1)*('Giá công thức'!$G$4:$AD$4=F$2)))} -> #N/A | G64: {=IF(SUMPRODUCT('Giá công thức'!$G$11:$AD$106*('Giá công thức'!$A$11:$A$106=$B64)*('Giá công thức'!$B$11:$B$106=$C64)*('Giá công thức'!$C$11:$C$106="GB")*('Giá công thức'!$G$3:$AD$3=G$1)*('Giá công thức'!$G$4:$AD$4=G$2))=0,NA(),SUMPRODUCT('Giá công thức'!$G$11:$AD$106*('Giá công thức'!$A$11:$A$106=$B64)*('Giá công thức'!$B$11:$B$106=$C64)*('Giá công thức'!$C$11:$C$106="GB")*('Giá công thức'!$G$3:$AD$3=G$1)*('Giá công thức'!$G$4:$AD$4=G$2)))} -> #N/A | H64: {=IF(SUMPRODUCT('Giá công thức'!$G$11:$AD$106*('Giá công thức'!$A$11:$A$106=$B64)*('Giá công thức'!$B$11:$B$106=$C64)*('Giá công thức'!$C$11:$C$106="GB")*('Giá công thức'!$G$3:$AD$3=H$1)*('Giá công thức'!$G$4:$AD$4=H$2))=0,NA(),SUMPRODUCT('Giá công thức'!$G$11:$AD$106*('Giá công thức'!$A$11:$A$106=$B64)*('Giá công thức'!$B$11:$B$106=$C64)*('Giá công thức'!$C$11:$C$106="GB")*('Giá công thức'!$G$3:$AD$3=H$1)*('Giá công thức'!$G$4:$AD$4=H$2)))} -> #N/A | I64: {=IF(SUMPRODUCT('Giá công thức'!$G$11:$AD$106*('Giá công thức'!$A$11:$A$106=$B64)*('Giá công thức'!$B$11:$B$106=$C64)*('Giá công thức'!$C$11:$C$106="GB")*('Giá công thức'!$G$3:$AD$3=I$1)*('Giá công thức'!$G$4:$AD$4=I$2))=0,NA(),SUMPRODUCT('Giá công thức'!$G$11:$AD$106*('Giá công thức'!$A$11:$A$106=$B64)*('Giá công thức'!$B$11:$B$106=$C64)*('Giá công thức'!$C$11:$C$106="GB")*('Giá công thức'!$G$3:$AD$3=I$1)*('Giá công thức'!$G$4:$AD$4=I$2)))} -> #N/A | J64: {=IF(SUMPRODUCT('Giá công thức'!$G$11:$AD$106*('Giá công thức'!$A$11:$A$106=$B64)*('Giá công thức'!$B$11:$B$106=$C64)*('Giá công thức'!$C$11:$C$106="GB")*('Giá công thức'!$G$3:$AD$3=J$1)*('Giá công thức'!$G$4:$AD$4=J$2))=0,NA(),SUMPRODUCT('Giá công thức'!$G$11:$AD$106*('Giá công thức'!$A$11:$A$106=$B64)*('Giá công thức'!$B$11:$B$106=$C64)*('Giá công thức'!$C$11:$C$106="GB")*('Giá công thức'!$G$3:$AD$3=J$1)*('Giá công thức'!$G$4:$AD$4=J$2)))} -> #N/A | K64: {=IF(SUMPRODUCT('Giá công thức'!$G$11:$AD$106*('Giá công thức'!$A$11:$A$106=$B64)*('Giá công thức'!$B$11:$B$106=$C64)*('Giá công thức'!$C$11:$C$106="GB")*('Giá công thức'!$G$3:$AD$3=K$1)*('Giá công thức'!$G$4:$AD$4=K$2))=0,NA(),SUMPRODUCT('Giá công thức'!$G$11:$AD$106*('Giá công thức'!$A$11:$A$106=$B64)*('Giá công thức'!$B$11:$B$106=$C64)*('Giá công thức'!$C$11:$C$106="GB")*('Giá công thức'!$G$3:$AD$3=K$1)*('Giá công thức'!$G$4:$AD$4=K$2)))} -> #N/A | L64: {=IF(SUMPRODUCT('Giá công thức'!$G$11:$AD$106*('Giá công thức'!$A$11:$A$106=$B64)*('Giá công thức'!$B$11:$B$106=$C64)*('Giá công thức'!$C$11:$C$106="GB")*('Giá công thức'!$G$3:$AD$3=L$1)*('Giá công thức'!$G$4:$AD$4=L$2))=0,NA(),SUMPRODUCT('Giá công thức'!$G$11:$AD$106*('Giá công thức'!$A$11:$A$106=$B64)*('Giá công thức'!$B$11:$B$106=$C64)*('Giá công thức'!$C$11:$C$106="GB")*('Giá công thức'!$G$3:$AD$3=L$1)*('Giá công thức'!$G$4:$AD$4=L$2)))} -> #N/A | ... AB64: {=IF(SUMPRODUCT('Giá công thức'!$G$11:$AD$106*('Giá công thức'!$A$11:$A$106=$B64)*('Giá công thức'!$B$11:$B$106=$C64)*('Giá công thức'!$C$11:$C$106="GB")*('Giá công thức'!$G$3:$AD$3=AB$1)*('Giá công thức'!$G$4:$AD$4=AB$2))=0,NA(),SUMPRODUCT('Giá công thức'!$G$11:$AD$106*('Giá công thức'!$A$11:$A$106=$B64)*('Giá công thức'!$B$11:$B$106=$C64)*('Giá công thức'!$C$11:$C$106="GB")*('Giá công thức'!$G$3:$AD$3=AB$1)*('Giá công thức'!$G$4:$AD$4=AB$2)))} -> 1368.04 | AO64: =INDEX($E64:$AB64,MATCH("X",$E$3:$AB$3,0)) -> 1368.04
A65: 110000481 | C65: 110000481 | D65: Giá duyệt | E65: {=IF(SUMPRODUCT(General_Data*(Code_General_Data=$A65)*(Year=E$1)*(Month=E$2))=0,NA(),SUMPRODUCT(General_Data*(Code_General_Data=$A65)*(Year=E$1)*(Month=E$2)))} -> #N/A | F65: {=IF(SUMPRODUCT(General_Data*(Code_General_Data=$A65)*(Year=F$1)*(Month=F$2))=0,NA(),SUMPRODUCT(General_Data*(Code_General_Data=$A65)*(Year=F$1)*(Month=F$2)))} -> #N/A | G65: {=IF(SUMPRODUCT(General_Data*(Code_General_Data=$A65)*(Year=G$1)*(Month=G$2))=0,NA(),SUMPRODUCT(General_Data*(Code_General_Data=$A65)*(Year=G$1)*(Month=G$2)))} -> #N/A | H65: {=IF(SUMPRODUCT(General_Data*(Code_General_Data=$A65)*(Year=H$1)*(Month=H$2))=0,NA(),SUMPRODUCT(General_Data*(Code_General_Data=$A65)*(Year=H$1)*(Month=H$2)))} -> #N/A | I65: {=IF(SUMPRODUCT(General_Data*(Code_General_Data=$A65)*(Year=I$1)*(Month=I$2))=0,NA(),SUMPRODUCT(General_Data*(Code_General_Data=$A65)*(Year=I$1)*(Month=I$2)))} -> #N/A | J65: {=IF(SUMPRODUCT(General_Data*(Code_General_Data=$A65)*(Year=J$1)*(Month=J$2))=0,NA(),SUMPRODUCT(General_Data*(Code_General_Data=$A65)*(Year=J$1)*(Month=J$2)))} -> #N/A | K65: {=IF(SUMPRODUCT(General_Data*(Code_General_Data=$A65)*(Year=K$1)*(Month=K$2))=0,NA(),SUMPRODUCT(General_Data*(Code_General_Data=$A65)*(Year=K$1)*(Month=K$2)))} -> #N/A | L65: {=IF(SUMPRODUCT(General_Data*(Code_General_Data=$A65)*(Year=L$1)*(Month=L$2))=0,NA(),SUMPRODUCT(General_Data*(Code_General_Data=$A65)*(Year=L$1)*(Month=L$2)))} -> #N/A | ... AB65: {=IF(SUMPRODUCT(General_Data*(Code_General_Data=$A65)*(Year=AB$1)*(Month=AB$2))=0,NA(),SUMPRODUCT(General_Data*(Code_General_Data=$A65)*(Year=AB$1)*(Month=AB$2)))} -> 1300 | AO65: =INDEX($E65:$AB65,MATCH("X",$E$3:$AB$3,0)) -> 1300
A66: HDPEVirgin | D66: Giá chính phẩm | E66: {=SUMPRODUCT(General_Data*(Code_General_Data=$A66)*(Year=E$1)*(Month=E$2))} -> 940 | F66: {=SUMPRODUCT(General_Data*(Code_General_Data=$A66)*(Year=F$1)*(Month=F$2))} -> 993.33333 | G66: {=SUMPRODUCT(General_Data*(Code_General_Data=$A66)*(Year=G$1)*(Month=G$2))} -> 985 | H66: {=SUMPRODUCT(General_Data*(Code_General_Data=$A66)*(Year=H$1)*(Month=H$2))} -> 962.5 | I66: {=SUMPRODUCT(General_Data*(Code_General_Data=$A66)*(Year=I$1)*(Month=I$2))} -> 982 | J66: {=SUMPRODUCT(General_Data*(Code_General_Data=$A66)*(Year=J$1)*(Month=J$2))} -> 1000 | K66: {=SUMPRODUCT(General_Data*(Code_General_Data=$A66)*(Year=K$1)*(Month=K$2))} -> 1000 | L66: {=SUMPRODUCT(General_Data*(Code_General_Data=$A66)*(Year=L$1)*(Month=L$2))} -> 984 | ... AB66: {=SUMPRODUCT(General_Data*(Code_General_Data=$A66)*(Year=AB$1)*(Month=AB$2))} -> 805 | AO66: =INDEX($E66:$AB66,MATCH("X",$E$3:$AB$3,0)) -> 805
D67: Chênh lệch-Area | E67: =E65-E66 -> #N/A | F67: =F65-F66 -> #N/A | G67: =G65-G66 -> #N/A | H67: =H65-H66 -> #N/A | I67: =I65-I66 -> #N/A | J67: =J65-J66 -> #N/A | K67: =K65-K66 -> #N/A | L67: =L65-L66 -> #N/A | ... AB67: =AB65-AB66 -> 495
D68: %Chênh lệch | E68: =IFERROR(E67/E66,0) -> 0 | F68: =IFERROR(F67/F66,0) -> 0 | G68: =IFERROR(G67/G66,0) -> 0 | H68: =IFERROR(H67/H66,0) -> 0 | I68: =IFERROR(I67/I66,0) -> 0 | J68: =IFERROR(J67/J66,0) -> 0 | K68: =IFERROR(K67/K66,0) -> 0 | L68: =IFERROR(L67/L66,0) -> 0 | ... AB68: =IFERROR(AB67/AB66,0) -> 0.61490683
D69: Chênh lệch-Line Drop | E69: =E65 -> #N/A | F69: =F65 -> #N/A | G69: =G65 -> #N/A | H69: =H65 -> #N/A | I69: =I65 -> #N/A | J69: =J65 -> #N/A | K69: =K65 -> #N/A | L69: =L65 -> #N/A | ... AB69: =AB65 -> 1300
D70: Chênh lệch-Label | E70: =E66+E67/2 -> #N/A | F70: =F66+F67/2 -> #N/A | G70: =G66+G67/2 -> #N/A | H70: =H66+H67/2 -> #N/A | I70: =I66+I67/2 -> #N/A | J70: =J66+J67/2 -> #N/A | K70: =K66+K67/2 -> #N/A | L70: =L66+L67/2 -> #N/A | ... AB70: =AB66+AB67/2 -> 1052.5
D71: Giá duyệt-Area | E71: =E65 -> #N/A | F71: =F65 -> #N/A | G71: =G65 -> #N/A | H71: =H65 -> #N/A | I71: =I65 -> #N/A | J71: =J65 -> #N/A | K71: =K65 -> #N/A | L71: =L65 -> #N/A | ... AB71: =AB65 -> 1300
D72: Giá chính phẩm-Area | E72: =E66 -> 940 | F72: =F66 -> 993.33333 | G72: =G66 -> 985 | H72: =H66 -> 962.5 | I72: =I66 -> 982 | J72: =J66 -> 1000 | K72: =K66 -> 1000 | L72: =L66 -> 984 | ... AB72: =AB66 -> 805
D73: Unilever-Label | E73: =IFERROR(E64,0) -> 0 | F73: =IFERROR(F64,0) -> 0 | G73: =IFERROR(G64,0) -> 0 | H73: =IFERROR(H64,0) -> 0 | I73: =IFERROR(I64,0) -> 0 | J73: =IFERROR(J64,0) -> 0 | K73: =IFERROR(K64,0) -> 0 | L73: =IFERROR(L64,0) -> 0 | ... AB73: =IFERROR(AB64,0) -> 1368.04 | AO73: UNILEVER
D74: Giá duyệt-Label | E74: =IFERROR(E65,0) -> 0 | F74: =IFERROR(F65,0) -> 0 | G74: =IFERROR(G65,0) -> 0 | H74: =IFERROR(H65,0) -> 0 | I74: =IFERROR(I65,0) -> 0 | J74: =IFERROR(J65,0) -> 0 | K74: =IFERROR(K65,0) -> 0 | L74: =IFERROR(L65,0) -> 0 | ... AB74: =IFERROR(AB65,0) -> 1300 | AO74: Giá duyệt
D75: Giá chính phẩm-Label | E75: =IFERROR(E66,0) -> 940 | F75: =IFERROR(F66,0) -> 993.33333 | G75: =IFERROR(G66,0) -> 985 | H75: =IFERROR(H66,0) -> 962.5 | I75: =IFERROR(I66,0) -> 982 | J75: =IFERROR(J66,0) -> 1000 | K75: =IFERROR(K66,0) -> 1000 | L75: =IFERROR(L66,0) -> 984 | ... AB75: =IFERROR(AB66,0) -> 805 | AO75: Giá chính phẩm
C77: 110000339 | D77: MBF01
E78: 2024 | Q78: 2025
E79: 1 | F79: 2 | G79: 3 | H79: 4 | I79: 5 | J79: 6 | K79: 7 | L79: 8 | M79: 9 | N79: 10 | O79: 11 | P79: 12 | Q79: 1 | R79: 2 | S79: 3 | T79: 4 | U79: 5 | V79: 6 | W79: 7 | X79: 8 | Y79: 9 | Z79: 10 | AA79: 11 | AB79: 12 | AC79: 1 | AD79: 2 | AE79: 3 | AF79: 4 | AG79: 5 | AH79: 6 | AI79: 7 | AJ79: 8 | AK79: 9 | AL79: 10 | AM79: 11 | AN79: 12
B80: 105263 | C80: 110000339 | D80: Unilever | E80: {=IF(SUMPRODUCT('Giá công thức'!$G$11:$AD$106*('Giá công thức'!$A$11:$A$106=$B80)*('Giá công thức'!$B$11:$B$106=$C80)*('Giá công thức'!$C$11:$C$106="GB")*('Giá công thức'!$G$3:$AD$3=E$1)*('Giá công thức'!$G$4:$AD$4=E$2))=0,NA(),SUMPRODUCT('Giá công thức'!$G$11:$AD$106*('Giá công thức'!$A$11:$A$106=$B80)*('Giá công thức'!$B$11:$B$106=$C80)*('Giá công thức'!$C$11:$C$106="GB")*('Giá công thức'!$G$3:$AD$3=E$1)*('Giá công thức'!$G$4:$AD$4=E$2)))} -> 1487.7959 | F80: {=IF(SUMPRODUCT('Giá công thức'!$G$11:$AD$106*('Giá công thức'!$A$11:$A$106=$B80)*('Giá công thức'!$B$11:$B$106=$C80)*('Giá công thức'!$C$11:$C$106="GB")*('Giá công thức'!$G$3:$AD$3=F$1)*('Giá công thức'!$G$4:$AD$4=F$2))=0,NA(),SUMPRODUCT('Giá công thức'!$G$11:$AD$106*('Giá công thức'!$A$11:$A$106=$B80)*('Giá công thức'!$B$11:$B$106=$C80)*('Giá công thức'!$C$11:$C$106="GB")*('Giá công thức'!$G$3:$AD$3=F$1)*('Giá công thức'!$G$4:$AD$4=F$2)))} -> 1487.7959 | G80: {=IF(SUMPRODUCT('Giá công thức'!$G$11:$AD$106*('Giá công thức'!$A$11:$A$106=$B80)*('Giá công thức'!$B$11:$B$106=$C80)*('Giá công thức'!$C$11:$C$106="GB")*('Giá công thức'!$G$3:$AD$3=G$1)*('Giá công thức'!$G$4:$AD$4=G$2))=0,NA(),SUMPRODUCT('Giá công thức'!$G$11:$AD$106*('Giá công thức'!$A$11:$A$106=$B80)*('Giá công thức'!$B$11:$B$106=$C80)*('Giá công thức'!$C$11:$C$106="GB")*('Giá công thức'!$G$3:$AD$3=G$1)*('Giá công thức'!$G$4:$AD$4=G$2)))} -> 1487.7959 | H80: {=IF(SUMPRODUCT('Giá công thức'!$G$11:$AD$106*('Giá công thức'!$A$11:$A$106=$B80)*('Giá công thức'!$B$11:$B$106=$C80)*('Giá công thức'!$C$11:$C$106="GB")*('Giá công thức'!$G$3:$AD$3=H$1)*('Giá công thức'!$G$4:$AD$4=H$2))=0,NA(),SUMPRODUCT('Giá công thức'!$G$11:$AD$106*('Giá công thức'!$A$11:$A$106=$B80)*('Giá công thức'!$B$11:$B$106=$C80)*('Giá công thức'!$C$11:$C$106="GB")*('Giá công thức'!$G$3:$AD$3=H$1)*('Giá công thức'!$G$4:$AD$4=H$2)))} -> 1417.7959 | I80: {=IF(SUMPRODUCT('Giá công thức'!$G$11:$AD$106*('Giá công thức'!$A$11:$A$106=$B80)*('Giá công thức'!$B$11:$B$106=$C80)*('Giá công thức'!$C$11:$C$106="GB")*('Giá công thức'!$G$3:$AD$3=I$1)*('Giá công thức'!$G$4:$AD$4=I$2))=0,NA(),SUMPRODUCT('Giá công thức'!$G$11:$AD$106*('Giá công thức'!$A$11:$A$106=$B80)*('Giá công thức'!$B$11:$B$106=$C80)*('Giá công thức'!$C$11:$C$106="GB")*('Giá công thức'!$G$3:$AD$3=I$1)*('Giá công thức'!$G$4:$AD$4=I$2)))} -> 1417.7959 | J80: {=IF(SUMPRODUCT('Giá công thức'!$G$11:$AD$106*('Giá công thức'!$A$11:$A$106=$B80)*('Giá công thức'!$B$11:$B$106=$C80)*('Giá công thức'!$C$11:$C$106="GB")*('Giá công thức'!$G$3:$AD$3=J$1)*('Giá công thức'!$G$4:$AD$4=J$2))=0,NA(),SUMPRODUCT('Giá công thức'!$G$11:$AD$106*('Giá công thức'!$A$11:$A$106=$B80)*('Giá công thức'!$B$11:$B$106=$C80)*('Giá công thức'!$C$11:$C$106="GB")*('Giá công thức'!$G$3:$AD$3=J$1)*('Giá công thức'!$G$4:$AD$4=J$2)))} -> 1417.7959 | K80: {=IF(SUMPRODUCT('Giá công thức'!$G$11:$AD$106*('Giá công thức'!$A$11:$A$106=$B80)*('Giá công thức'!$B$11:$B$106=$C80)*('Giá công thức'!$C$11:$C$106="GB")*('Giá công thức'!$G$3:$AD$3=K$1)*('Giá công thức'!$G$4:$AD$4=K$2))=0,NA(),SUMPRODUCT('Giá công thức'!$G$11:$AD$106*('Giá công thức'!$A$11:$A$106=$B80)*('Giá công thức'!$B$11:$B$106=$C80)*('Giá công thức'!$C$11:$C$106="GB")*('Giá công thức'!$G$3:$AD$3=K$1)*('Giá công thức'!$G$4:$AD$4=K$2)))} -> 1418.04 | L80: {=IF(SUMPRODUCT('Giá công thức'!$G$11:$AD$106*('Giá công thức'!$A$11:$A$106=$B80)*('Giá công thức'!$B$11:$B$106=$C80)*('Giá công thức'!$C$11:$C$106="GB")*('Giá công thức'!$G$3:$AD$3=L$1)*('Giá công thức'!$G$4:$AD$4=L$2))=0,NA(),SUMPRODUCT('Giá công thức'!$G$11:$AD$106*('Giá công thức'!$A$11:$A$106=$B80)*('Giá công thức'!$B$11:$B$106=$C80)*('Giá công thức'!$C$11:$C$106="GB")*('Giá công thức'!$G$3:$AD$3=L$1)*('Giá công thức'!$G$4:$AD$4=L$2)))} -> 1418.04 | ... AB80: {=IF(SUMPRODUCT('Giá công thức'!$G$11:$AD$106*('Giá công thức'!$A$11:$A$106=$B80)*('Giá công thức'!$B$11:$B$106=$C80)*('Giá công thức'!$C$11:$C$106="GB")*('Giá công thức'!$G$3:$AD$3=AB$1)*('Giá công thức'!$G$4:$AD$4=AB$2))=0,NA(),SUMPRODUCT('Giá công thức'!$G$11:$AD$106*('Giá công thức'!$A$11:$A$106=$B80)*('Giá công thức'!$B$11:$B$106=$C80)*('Giá công thức'!$C$11:$C$106="GB")*('Giá công thức'!$G$3:$AD$3=AB$1)*('Giá công thức'!$G$4:$AD$4=AB$2)))} -> 1368.04 | AO80: =INDEX($E80:$AB80,MATCH("X",$E$3:$AB$3,0)) -> 1368.04
A81: 110000339 | C81: 110000339 | D81: Giá duyệt | E81: {=IF(SUMPRODUCT(General_Data*(Code_General_Data=$A81)*(Year=E$1)*(Month=E$2))=0,NA(),SUMPRODUCT(General_Data*(Code_General_Data=$A81)*(Year=E$1)*(Month=E$2)))} -> 1350 | F81: {=IF(SUMPRODUCT(General_Data*(Code_General_Data=$A81)*(Year=F$1)*(Month=F$2))=0,NA(),SUMPRODUCT(General_Data*(Code_General_Data=$A81)*(Year=F$1)*(Month=F$2)))} -> 1350 | G81: {=IF(SUMPRODUCT(General_Data*(Code_General_Data=$A81)*(Year=G$1)*(Month=G$2))=0,NA(),SUMPRODUCT(General_Data*(Code_General_Data=$A81)*(Year=G$1)*(Month=G$2)))} -> 1350 | H81: {=IF(SUMPRODUCT(General_Data*(Code_General_Data=$A81)*(Year=H$1)*(Month=H$2))=0,NA(),SUMPRODUCT(General_Data*(Code_General_Data=$A81)*(Year=H$1)*(Month=H$2)))} -> 1350 | I81: {=IF(SUMPRODUCT(General_Data*(Code_General_Data=$A81)*(Year=I$1)*(Month=I$2))=0,NA(),SUMPRODUCT(General_Data*(Code_General_Data=$A81)*(Year=I$1)*(Month=I$2)))} -> 1350 | J81: {=IF(SUMPRODUCT(General_Data*(Code_General_Data=$A81)*(Year=J$1)*(Month=J$2))=0,NA(),SUMPRODUCT(General_Data*(Code_General_Data=$A81)*(Year=J$1)*(Month=J$2)))} -> 1350 | K81: {=IF(SUMPRODUCT(General_Data*(Code_General_Data=$A81)*(Year=K$1)*(Month=K$2))=0,NA(),SUMPRODUCT(General_Data*(Code_General_Data=$A81)*(Year=K$1)*(Month=K$2)))} -> 1350 | L81: {=IF(SUMPRODUCT(General_Data*(Code_General_Data=$A81)*(Year=L$1)*(Month=L$2))=0,NA(),SUMPRODUCT(General_Data*(Code_General_Data=$A81)*(Year=L$1)*(Month=L$2)))} -> 1350 | ... AB81: {=IF(SUMPRODUCT(General_Data*(Code_General_Data=$A81)*(Year=AB$1)*(Month=AB$2))=0,NA(),SUMPRODUCT(General_Data*(Code_General_Data=$A81)*(Year=AB$1)*(Month=AB$2)))} -> 1200 | AO81: =INDEX($E81:$AB81,MATCH("X",$E$3:$AB$3,0)) -> 1200
A82: HDPEVirgin | D82: Giá chính phẩm | E82: {=SUMPRODUCT(General_Data*(Code_General_Data=$A82)*(Year=E$1)*(Month=E$2))} -> 940 | F82: {=SUMPRODUCT(General_Data*(Code_General_Data=$A82)*(Year=F$1)*(Month=F$2))} -> 993.33333 | G82: {=SUMPRODUCT(General_Data*(Code_General_Data=$A82)*(Year=G$1)*(Month=G$2))} -> 985 | H82: {=SUMPRODUCT(General_Data*(Code_General_Data=$A82)*(Year=H$1)*(Month=H$2))} -> 962.5 | I82: {=SUMPRODUCT(General_Data*(Code_General_Data=$A82)*(Year=I$1)*(Month=I$2))} -> 982 | J82: {=SUMPRODUCT(General_Data*(Code_General_Data=$A82)*(Year=J$1)*(Month=J$2))} -> 1000 | K82: {=SUMPRODUCT(General_Data*(Code_General_Data=$A82)*(Year=K$1)*(Month=K$2))} -> 1000 | L82: {=SUMPRODUCT(General_Data*(Code_General_Data=$A82)*(Year=L$1)*(Month=L$2))} -> 984 | ... AB82: {=SUMPRODUCT(General_Data*(Code_General_Data=$A82)*(Year=AB$1)*(Month=AB$2))} -> 805 | AO82: =INDEX($E82:$AB82,MATCH("X",$E$3:$AB$3,0)) -> 805
D83: Chênh lệch-Area | E83: =E81-E82 -> 410 | F83: =F81-F82 -> 356.66667 | G83: =G81-G82 -> 365 | H83: =H81-H82 -> 387.5 | I83: =I81-I82 -> 368 | J83: =J81-J82 -> 350 | K83: =K81-K82 -> 350 | L83: =L81-L82 -> 366 | ... AB83: =AB81-AB82 -> 395
D84: %Chênh lệch | E84: =IFERROR(E83/E82,0) -> 0.43617021 | F84: =IFERROR(F83/F82,0) -> 0.3590604 | G84: =IFERROR(G83/G82,0) -> 0.37055838 | H84: =IFERROR(H83/H82,0) -> 0.4025974 | I84: =IFERROR(I83/I82,0) -> 0.37474542 | J84: =IFERROR(J83/J82,0) -> 0.35 | K84: =IFERROR(K83/K82,0) -> 0.35 | L84: =IFERROR(L83/L82,0) -> 0.37195122 | ... AB84: =IFERROR(AB83/AB82,0) -> 0.49068323
D85: Chênh lệch-Line Drop | E85: =E81 -> 1350 | F85: =F81 -> 1350 | G85: =G81 -> 1350 | H85: =H81 -> 1350 | I85: =I81 -> 1350 | J85: =J81 -> 1350 | K85: =K81 -> 1350 | L85: =L81 -> 1350 | ... AB85: =AB81 -> 1200
D86: Chênh lệch-Label | E86: =E82+E83/2 -> 1145 | F86: =F82+F83/2 -> 1171.6667 | G86: =G82+G83/2 -> 1167.5 | H86: =H82+H83/2 -> 1156.25 | I86: =I82+I83/2 -> 1166 | J86: =J82+J83/2 -> 1175 | K86: =K82+K83/2 -> 1175 | L86: =L82+L83/2 -> 1167 | ... AB86: =AB82+AB83/2 -> 1002.5
D87: Giá duyệt-Area | E87: =E81 -> 1350 | F87: =F81 -> 1350 | G87: =G81 -> 1350 | H87: =H81 -> 1350 | I87: =I81 -> 1350 | J87: =J81 -> 1350 | K87: =K81 -> 1350 | L87: =L81 -> 1350 | ... AB87: =AB81 -> 1200
D88: Giá chính phẩm-Area | E88: =E82 -> 940 | F88: =F82 -> 993.33333 | G88: =G82 -> 985 | H88: =H82 -> 962.5 | I88: =I82 -> 982 | J88: =J82 -> 1000 | K88: =K82 -> 1000 | L88: =L82 -> 984 | ... AB88: =AB82 -> 805
D89: Unilever-Label | E89: =IFERROR(E80,0) -> 1487.7959 | F89: =IFERROR(F80,0) -> 1487.7959 | G89: =IFERROR(G80,0) -> 1487.7959 | H89: =IFERROR(H80,0) -> 1417.7959 | I89: =IFERROR(I80,0) -> 1417.7959 | J89: =IFERROR(J80,0) -> 1417.7959 | K89: =IFERROR(K80,0) -> 1418.04 | L89: =IFERROR(L80,0) -> 1418.04 | ... AB89: =IFERROR(AB80,0) -> 1368.04 | AO89: UNILEVER
D90: Giá duyệt-Label | E90: =IFERROR(E81,0) -> 1350 | F90: =IFERROR(F81,0) -> 1350 | G90: =IFERROR(G81,0) -> 1350 | H90: =IFERROR(H81,0) -> 1350 | I90: =IFERROR(I81,0) -> 1350 | J90: =IFERROR(J81,0) -> 1350 | K90: =IFERROR(K81,0) -> 1350 | L90: =IFERROR(L81,0) -> 1350 | ... AB90: =IFERROR(AB81,0) -> 1200 | AO90: Giá duyệt
D91: Giá chính phẩm-Label | E91: =IFERROR(E82,0) -> 940 | F91: =IFERROR(F82,0) -> 993.33333 | G91: =IFERROR(G82,0) -> 985 | H91: =IFERROR(H82,0) -> 962.5 | I91: =IFERROR(I82,0) -> 982 | J91: =IFERROR(J82,0) -> 1000 | K91: =IFERROR(K82,0) -> 1000 | L91: =IFERROR(L82,0) -> 984 | ... AB91: =IFERROR(AB82,0) -> 805 | AO91: Giá chính phẩm

Sheet Price_cũ
L1: =DATE(L3,L4,1) -> 45200 | M1: =DATE(M3,M4,1) -> 45231 | N1: =DATE(N3,N4,1) -> 45261 | O1: =DATE(O3,O4,1) -> 45292 | P1: =DATE(P3,P4,1) -> 45323 | Q1: =DATE(Q3,Q4,1) -> 45352 | R1: =DATE(R3,R4,1) -> 45383 | S1: =DATE(S3,S4,1) -> 45413 | ... AL1: =DATE(AL3,AL4,1) -> 45992
L2: =EOMONTH(L1,0) -> 45230 | M2: =EOMONTH(M1,0) -> 45260 | N2: =EOMONTH(N1,0) -> 45291 | O2: =EOMONTH(O1,0) -> 45322 | P2: =EOMONTH(P1,0) -> 45351 | Q2: =EOMONTH(Q1,0) -> 45382 | R2: =EOMONTH(R1,0) -> 45412 | S2: =EOMONTH(S1,0) -> 45443 | ... AL2: =EOMONTH(AL1,0) -> 46022
L3: 2023 | M3: 2023 | N3: 2023 | O3: 2024 | P3: 2024 | Q3: 2024 | R3: 2024 | S3: 2024 | T3: 2024 | U3: 2024 | V3: 2024 | W3: 2024 | X3: 2024 | Y3: 2024 | Z3: 2024 | AA3: 2025 | AB3: 2025 | AC3: 2025 | AD3: 2025 | AE3: 2025 | AF3: 2025 | AG3: 2025 | AH3: 2025 | AI3: 2025 | AJ3: 2025 | AK3: 2025 | AL3: 2025
L4: 10 | M4: 11 | N4: 12 | O4: 1 | P4: 2 | Q4: 3 | R4: 4 | S4: 5 | T4: 6 | U4: 7 | V4: 8 | W4: 9 | X4: 10 | Y4: 11 | Z4: 12 | AA4: 1 | AB4: 2 | AC4: 3 | AD4: 4 | AE4: 5 | AF4: 6 | AG4: 7 | AH4: 8 | AI4: 9 | AJ4: 10 | AK4: 11 | AL4: 12
F6: ĐƠN GIÁ (USD/tấn)
F8: STT | G8: KHÁCH HÀNG/NỘI DUNG | L8: 2023 | O8: 2024 | AA8: 2025
A9: Khách | B9: SKU | C9: Code | D9: Link | L9: 10 | M9: 11 | N9: 12 | O9: 1 | P9: 2 | Q9: 3 | R9: 4 | S9: 5 | T9: 6 | U9: 7 | V9: 8 | W9: 9 | X9: 10 | Y9: 11 | Z9: 12 | AA9: 1 | AB9: 2 | AC9: 3 | AD9: 4 | AE9: 5 | AF9: 6 | AG9: 7 | AH9: 8 | AI9: 9 | AJ9: 10 | AK9: 11 | AL9: 12
A11: 200319 | F11: 1 | G11: NIAGARA
A12: 200319 | B12: 110000354 | D12: GB | F12: 1.1 | H12: GIÁ BÁN WSS01G (FOB) | O12: =MIN(MAX(SUM(O13:O14),O23),O22) -> 1200 | P12: =MIN(MAX(SUM(P13:P14),P23),P22) -> 1200 | Q12: =MIN(MAX(SUM(Q13:Q14),Q23),Q22) -> 1200 | R12: =MIN(MAX(SUM(R13:R14),R23),R22) -> 1200 | S12: =MIN(MAX(SUM(S13:S14),S23),S22) -> 1200 | T12: =MIN(MAX(SUM(T13:T14),T23),T22) -> 1200.9 | U12: =MIN(MAX(SUM(U13:U14),U23),U22) -> 1214.4 | V12: =MIN(MAX(SUM(V13:V14),V23),V22) -> 1226.1 | ... AB12: =MIN(MAX(SUM(AB13:AB14),AB23),AB22) -> 1264.375
A13: 200319 | B13: 110000354 | F13: 1.1.1 | H13: [+] | I13: ICIS Bales - SEA trung bình 3 tháng gần nhất | O13: =AVERAGE(L17:N17) -> 1296.0417 | P13: =AVERAGE(M17:O17) -> 1305 | Q13: =AVERAGE(N17:P17) -> 1313.3333 | R13: =AVERAGE(O17:Q17) -> 1320 | S13: =AVERAGE(P17:R17) -> 1326 | T13: =AVERAGE(Q17:S17) -> 1334.3333 | U13: =AVERAGE(R17:T17) -> 1349.3333 | V13: =AVERAGE(S17:U17) -> 1362.3333 | ... AB13: =AVERAGE(Y17:AA17) -> 1404.8611
A14: 200319 | B14: 110000354 | F14: 1.1.2 | H14: [+] | I14: Chiết khấu 10% | O14: =-O13*O18 -> -129.60417 | P14: =-P13*P18 -> -130.5 | Q14: =-Q13*Q18 -> -131.33333 | R14: =-R13*R18 -> -132 | S14: =-S13*S18 -> -132.6 | T14: =-T13*T18 -> -133.43333 | U14: =-U13*U18 -> -134.93333 | V14: =-V13*V18 -> -136.23333 | ... AB14: =-AB13*AB18 -> -140.48611
A15: 200319 | B15: 110000354 | D15: EXW | F15: 1.1.3 | I15: Giá bán quy đổi EXW | O15: =O12-O16 -> 1180 | P15: =P12-P16 -> 1180 | Q15: =Q12-Q16 -> 1180 | R15: =R12-R16 -> 1180 | S15: =S12-S16 -> 1180 | T15: =T12-T16 -> 1180.9 | U15: =U12-U16 -> 1194.4 | V15: =V12-V16 -> 1206.1 | ... AB15: =AB12-AB16 -> 1244.375
A16: 200319 | B16: 110000354 | F16: 1.1.4 | I16: Chi phí vận chuyển | O16: 20 | P16: 20 | Q16: 20 | R16: 20 | S16: 20 | T16: 20 | U16: 20 | V16: 20 | W16: 20 | X16: 20 | Y16: 20 | Z16: 20 | AA16: 20 | AB16: 20
A17: 200319 | B17: 110000354 | C17: 04 | F17: 1.1.5 | J17: ICIS Bales - SEA | L17: {=SUMPRODUCT(General_Data*(Year=L$3)*(Month=L$4)*(Code_General_Data=$C17))} -> 1288.125 | M17: {=SUMPRODUCT(General_Data*(Year=M$3)*(Month=M$4)*(Code_General_Data=$C17))} -> 1300 | N17: {=SUMPRODUCT(General_Data*(Year=N$3)*(Month=N$4)*(Code_General_Data=$C17))} -> 1300 | O17: {=SUMPRODUCT(General_Data*(Year=O$3)*(Month=O$4)*(Code_General_Data=$C17))} -> 1315 | P17: {=SUMPRODUCT(General_Data*(Year=P$3)*(Month=P$4)*(Code_General_Data=$C17))} -> 1325 | Q17: {=SUMPRODUCT(General_Data*(Year=Q$3)*(Month=Q$4)*(Code_General_Data=$C17))} -> 1320 | R17: {=SUMPRODUCT(General_Data*(Year=R$3)*(Month=R$4)*(Code_General_Data=$C17))} -> 1333 | S17: {=SUMPRODUCT(General_Data*(Year=S$3)*(Month=S$4)*(Code_General_Data=$C17))} -> 1350 | ... AB17: {=SUMPRODUCT(General_Data*(Year=AB$3)*(Month=AB$4)*(Code_General_Data=$C17))} -> 1350
