Workbook
Name Code_General_Data: 'General Data'!$A$9:$A$137
Name Code_General_Item: 'General Data'!$C$9:$C$137
Name General_Data: 'General Data'!$F$9:$BB$137
Name Month: 'General Data'!$F$4:$BB$4
Name Year: 'General Data'!$F$3:$BB$3

Sheet BÌA
A5: MA TRẬN KHÁCH HÀNG
C11: I. | D11: TỔNG QUAN GIÁ CÔNG THỨC THEO KHÁCH HÀNG
C14: II. | D14: CHI TIẾT GIÁ CÔNG THỨC THEO KHÁCH HÀNG
C17: III. | D17: BIỂU ĐỒ

Sheet Giá công thức
G1: =DATE(G3,G4,1) -> 45292 | H1: =DATE(H3,H4,1) -> 45323 | I1: =DATE(I3,I4,1) -> 45352 | J1: =DATE(J3,J4,1) -> 45383 | K1: =DATE(K3,K4,1) -> 45413 | L1: =DATE(L3,L4,1) -> 45444 | M1: =DATE(M3,M4,1) -> 45474 | N1: =DATE(N3,N4,1) -> 45505 | ... AP1: =DATE(AP3,AP4,1) -> 46357
G2: =EOMONTH(G1,0) -> 45322 | H2: =EOMONTH(H1,0) -> 45351 | I2: =EOMONTH(I1,0) -> 45382 | J2: =EOMONTH(J1,0) -> 45412 | K2: =EOMONTH(K1,0) -> 45443 | L2: =EOMONTH(L1,0) -> 45473 | M2: =EOMONTH(M1,0) -> 45504 | N2: =EOMONTH(N1,0) -> 45535 | ... AP2: =EOMONTH(AP1,0) -> 46387
G3: 2024 | H3: 2024 | I3: 2024 | J3: 2024 | K3: 2024 | L3: 2024 | M3: 2024 | N3: 2024 | O3: 2024 | P3: 2024 | Q3: 2024 | R3: 2024 | S3: 2025 | T3: 2025 | U3: 2025 | V3: 2025 | W3: 2025 | X3: 2025 | Y3: 2025 | Z3: 2025 | AA3: 2025 | AB3: 2025 | AC3: 2025 | AD3: 2025 | AE3: 2026 | AF3: 2026 | AG3: 2026 | AH3: 2026 | AI3: 2026 | AJ3: 2026 | AK3: 2026 | AL3: 2026 | AM3: 2026 | AN3: 2026 | AO3: 2026 | AP3: 2026
G4: 1 | H4: 2 | I4: 3 | J4: 4 | K4: 5 | L4: 6 | M4: 7 | N4: 8 | O4: 9 | P4: 10 | Q4: 11 | R4: 12 | S4: 1 | T4: 2 | U4: 3 | V4: 4 | W4: 5 | X4: 6 | Y4: 7 | Z4: 8 | AA4: 9 | AB4: 10 | AC4: 11 | AD4: 12 | AE4: 1 | AF4: 2 | AG4: 3 | AH4: 4 | AI4: 5 | AJ4: 6 | AK4: 7 | AL4: 8 | AM4: 9 | AN4: 10 | AO4: 11 | AP4: 12
G5: I. GIÁ CÔNG THỨC THEO KHÁCH HÀNG | S5: I. GIÁ CÔNG THỨC THEO KHÁCH HÀNG | AE5: I. GIÁ CÔNG THỨC THEO KHÁCH HÀNG
D8: STT | E8: KHÁCH HÀNG/SẢN PHẨM | G8: 2024 | S8: 2025 | AE8: 2026
G9: 1 | H9: 2 | I9: 3 | J9: 4 | K9: 5 | L9: 6 | M9: 7 | N9: 8 | O9: 9 | P9: 10 | Q9: 11 | R9: 12 | S9: 1 | T9: 2 | U9: 3 | V9: 4 | W9: 5 | X9: 6 | Y9: 7 | Z9: 8 | AA9: 9 | AB9: 10 | AC9: 11 | AD9: 12 | AE9: 1 | AF9: 2 | AG9: 3 | AH9: 4 | AI9: 5 | AJ9: 6 | AK9: 7 | AL9: 8 | AM9: 9 | AN9: 10 | AO9: 11 | AP9: 12
A11: 200319 | D11: 1 | E11: NIAGARA
A12: 200319 | B12: 110000354 | F12: WSS01G
A13: 200319 | B13: 110000354 | D13: 1.1 | F13: Giá bán - FOB | G13: {=INDEX(Price!$L$11:$AY$210,MATCH(1,(Price!$A$11:$A$210=$A13)*(Price!$B$11:$B$210=$B13)*(Price!$D$11:$D$210="gb"),0),MATCH(1,(Price!$L$3:$AY$3=G$3)*(Price!$L$4:$AY$4=G$4),0))} -> 1200 | H13: {=INDEX(Price!$L$11:$AY$210,MATCH(1,(Price!$A$11:$A$210=$A13)*(Price!$B$11:$B$210=$B13)*(Price!$D$11:$D$210="gb"),0),MATCH(1,(Price!$L$3:$AY$3=H$3)*(Price!$L$4:$AY$4=H$4),0))} -> 1200 | I13: {=INDEX(Price!$L$11:$AY$210,MATCH(1,(Price!$A$11:$A$210=$A13)*(Price!$B$11:$B$210=$B13)*(Price!$D$11:$D$210="gb"),0),MATCH(1,(Price!$L$3:$AY$3=I$3)*(Price!$L$4:$AY$4=I$4),0))} -> 1200 | J13: {=INDEX(Price!$L$11:$AY$210,MATCH(1,(Price!$A$11:$A$210=$A13)*(Price!$B$11:$B$210=$B13)*(Price!$D$11:$D$210="gb"),0),MATCH(1,(Price!$L$3:$AY$3=J$3)*(Price!$L$4:$AY$4=J$4),0))} -> 1200 | K13: {=INDEX(Price!$L$11:$AY$210,MATCH(1,(Price!$A$11:$A$210=$A13)*(Price!$B$11:$B$210=$B13)*(Price!$D$11:$D$210="gb"),0),MATCH(1,(Price!$L$3:$AY$3=K$3)*(Price!$L$4:$AY$4=K$4),0))} -> 1200 | L13: {=INDEX(Price!$L$11:$AY$210,MATCH(1,(Price!$A$11:$A$210=$A13)*(Price!$B$11:$B$210=$B13)*(Price!$D$11:$D$210="gb"),0),MATCH(1,(Price!$L$3:$AY$3=L$3)*(Price!$L$4:$AY$4=L$4),0))} -> 1200.9 | M13: {=INDEX(Price!$L$11:$AY$210,MATCH(1,(Price!$A$11:$A$210=$A13)*(Price!$B$11:$B$210=$B13)*(Price!$D$11:$D$210="gb"),0),MATCH(1,(Price!$L$3:$AY$3=M$3)*(Price!$L$4:$AY$4=M$4),0))} -> 1214.4 | N13: {=INDEX(Price!$L$11:$AY$210,MATCH(1,(Price!$A$11:$A$210=$A13)*(Price!$B$11:$B$210=$B13)*(Price!$D$11:$D$210="gb"),0),MATCH(1,(Price!$L$3:$AY$3=N$3)*(Price!$L$4:$AY$4=N$4),0))} -> 1226.1 | ... AJ13: {=INDEX(Price!$L$11:$AY$210,MATCH(1,(Price!$A$11:$A$210=$A13)*(Price!$B$11:$B$210=$B13)*(Price!$D$11:$D$210="gb"),0),MATCH(1,(Price!$L$3:$AY$3=AJ$3)*(Price!$L$4:$AY$4=AJ$4),0))} -> 1221
A14: 200319 | B14: 110000354 | C14: GB | D14: 1.2 | F14: Giá bán quy đổi EXW | G14: {=INDEX(Price!$L$11:$AY$210,MATCH(1,(Price!$A$11:$A$210=$A14)*(Price!$B$11:$B$210=$B14)*(Price!$D$11:$D$210="exw"),0),MATCH(1,(Price!$L$3:$AY$3=G$3)*(Price!$L$4:$AY$4=G$4),0))} -> 1162 | H14: {=INDEX(Price!$L$11:$AY$210,MATCH(1,(Price!$A$11:$A$210=$A14)*(Price!$B$11:$B$210=$B14)*(Price!$D$11:$D$210="exw"),0),MATCH(1,(Price!$L$3:$AY$3=H$3)*(Price!$L$4:$AY$4=H$4),0))} -> 1162 | I14: {=INDEX(Price!$L$11:$AY$210,MATCH(1,(Price!$A$11:$A$210=$A14)*(Price!$B$11:$B$210=$B14)*(Price!$D$11:$D$210="exw"),0),MATCH(1,(Price!$L$3:$AY$3=I$3)*(Price!$L$4:$AY$4=I$4),0))} -> 1162 | J14: {=INDEX(Price!$L$11:$AY$210,MATCH(1,(Price!$A$11:$A$210=$A14)*(Price!$B$11:$B$210=$B14)*(Price!$D$11:$D$210="exw"),0),MATCH(1,(Price!$L$3:$AY$3=J$3)*(Price!$L$4:$AY$4=J$4),0))} -> 1162 | K14: {=INDEX(Price!$L$11:$AY$210,MATCH(1,(Price!$A$11:$A$210=$A14)*(Price!$B$11:$B$210=$B14)*(Price!$D$11:$D$210="exw"),0),MATCH(1,(Price!$L$3:$AY$3=K$3)*(Price!$L$4:$AY$4=K$4),0))} -> 1162 | L14: {=INDEX(Price!$L$11:$AY$210,MATCH(1,(Price!$A$11:$A$210=$A14)*(Price!$B$11:$B$210=$B14)*(Price!$D$11:$D$210="exw"),0),MATCH(1,(Price!$L$3:$AY$3=L$3)*(Price!$L$4:$AY$4=L$4),0))} -> 1162.8865 | M14: {=INDEX(Price!$L$11:$AY$210,MATCH(1,(Price!$A$11:$A$210=$A14)*(Price!$B$11:$B$210=$B14)*(Price!$D$11:$D$210="exw"),0),MATCH(1,(Price!$L$3:$AY$3=M$3)*(Price!$L$4:$AY$4=M$4),0))} -> 1176.184 | N14: {=INDEX(Price!$L$11:$AY$210,MATCH(1,(Price!$A$11:$A$210=$A14)*(Price!$B$11:$B$210=$B14)*(Price!$D$11:$D$210="exw"),0),MATCH(1,(Price!$L$3:$AY$3=N$3)*(Price!$L$4:$AY$4=N$4),0))} -> 1187.7085 | ... AJ14: {=INDEX(Price!$L$11:$AY$210,MATCH(1,(Price!$A$11:$A$210=$A14)*(Price!$B$11:$B$210=$B14)*(Price!$D$11:$D$210="exw"),0),MATCH(1,(Price!$L$3:$AY$3=AJ$3)*(Price!$L$4:$AY$4=AJ$4),0))} -> 1182.685
A15: 200319 | B15: 110000354 | C15: PETVirgin | D15: 1.3 | F15: Giá chính phẩm | G15: {=SUMPRODUCT(General_Data*(Code_General_Data=$C15)*(Year=G$3)*(Month=G$4))} -> 930 | H15: {=SUMPRODUCT(General_Data*(Code_General_Data=$C15)*(Year=H$3)*(Month=H$4))} -> 943.33333 | I15: {=SUMPRODUCT(General_Data*(Code_General_Data=$C15)*(Year=I$3)*(Month=I$4))} -> 940 | J15: {=SUMPRODUCT(General_Data*(Code_General_Data=$C15)*(Year=J$3)*(Month=J$4))} -> 940 | K15: {=SUMPRODUCT(General_Data*(Code_General_Data=$C15)*(Year=K$3)*(Month=K$4))} -> 942 | L15: {=SUMPRODUCT(General_Data*(Code_General_Data=$C15)*(Year=L$3)*(Month=L$4))} -> 950 | M15: {=SUMPRODUCT(General_Data*(Code_General_Data=$C15)*(Year=M$3)*(Month=M$4))} -> 947.5 | N15: {=SUMPRODUCT(General_Data*(Code_General_Data=$C15)*(Year=N$3)*(Month=N$4))} -> 930 | ... AJ15: {=SUMPRODUCT(General_Data*(Code_General_Data=$C15)*(Year=AJ$3)*(Month=AJ$4))} -> 1190
A16: 200319 | B16: 110000354 | D16: 1.4 | F16: Chênh lệch giữa R sv Virgin | G16: =IF(G13*G14*G15<>0,G14-G15,0) -> 232 | H16: =IF(H13*H14*H15<>0,H14-H15,0) -> 218.66667 | I16: =IF(I13*I14*I15<>0,I14-I15,0) -> 222 | J16: =IF(J13*J14*J15<>0,J14-J15,0) -> 222 | K16: =IF(K13*K14*K15<>0,K14-K15,0) -> 220 | L16: =IF(L13*L14*L15<>0,L14-L15,0) -> 212.8865 | M16: =IF(M13*M14*M15<>0,M14-M15,0) -> 228.684 | N16: =IF(N13*N14*N15<>0,N14-N15,0) -> 257.7085 | ... AJ16: =IF(AJ13*AJ14*AJ15<>0,AJ14-AJ15,0) -> -7.315
A17: 200319 | B17: 110000354 | D17: 1.5 | F17: % +/- | G17: =IFERROR(G16/G15,0) -> 0.24946237 | H17: =IFERROR(H16/H15,0) -> 0.23180212 | I17: =IFERROR(I16/I15,0) -> 0.23617021 | J17: =IFERROR(J16/J15,0) -> 0.23617021 | K17: =IFERROR(K16/K15,0) -> 0.23354565 | L17: =IFERROR(L16/L15,0) -> 0.22409105 | M17: =IFERROR(M16/M15,0) -> 0.24135515 | N17: =IFERROR(N16/N15,0) -> 0.27710591 | ... AJ17: =IFERROR(AJ16/AJ15,0) -> -0.0061470588
A18: 200319 | B18: 110000354 | C18: 110000354 | D18: 1.6 | F18: Giá duyệt tháng | G18: {=SUMPRODUCT(General_Data*(Code_General_Data=$C18)*(Year=G$3)*(Month=G$4))} -> 1250 | H18: {=SUMPRODUCT(General_Data*(Code_General_Data=$C18)*(Year=H$3)*(Month=H$4))} -> 1250 | I18: {=SUMPRODUCT(General_Data*(Code_General_Data=$C18)*(Year=I$3)*(Month=I$4))} -> 1250 | J18: {=SUMPRODUCT(General_Data*(Code_General_Data=$C18)*(Year=J$3)*(Month=J$4))} -> 1250 | K18: {=SUMPRODUCT(General_Data*(Code_General_Data=$C18)*(Year=K$3)*(Month=K$4))} -> 1300 | L18: {=SUMPRODUCT(General_Data*(Code_General_Data=$C18)*(Year=L$3)*(Month=L$4))} -> 1300 | M18: {=SUMPRODUCT(General_Data*(Code_General_Data=$C18)*(Year=M$3)*(Month=M$4))} -> 1300 | N18: {=SUMPRODUCT(General_Data*(Code_General_Data=$C18)*(Year=N$3)*(Month=N$4))} -> 1300 | ... AJ18: {=SUMPRODUCT(General_Data*(Code_General_Data=$C18)*(Year=AJ$3)*(Month=AJ$4))} -> 1350
A20: 200400 | D20: 2 | E20: SHEPLEY (NIAGARA NON-US)
A21: 200400 | B21: 110000354 | F21: WSS01G
A22: 200400 | B22: 110000354 | D22: 2.1 | F22: Giá bán - FOB | G22: {=INDEX(Price!$L$11:$AY$210,MATCH(1,(Price!$A$11:$A$210=$A22)*(Price!$B$11:$B$210=$B22)*(Price!$D$11:$D$210="gb"),0),MATCH(1,(Price!$L$3:$AY$3=G$3)*(Price!$L$4:$AY$4=G$4),0))} -> 1200 | H22: {=INDEX(Price!$L$11:$AY$210,MATCH(1,(Price!$A$11:$A$210=$A22)*(Price!$B$11:$B$210=$B22)*(Price!$D$11:$D$210="gb"),0),MATCH(1,(Price!$L$3:$AY$3=H$3)*(Price!$L$4:$AY$4=H$4),0))} -> 1200 | I22: {=INDEX(Price!$L$11:$AY$210,MATCH(1,(Price!$A$11:$A$210=$A22)*(Price!$B$11:$B$210=$B22)*(Price!$D$11:$D$210="gb"),0),MATCH(1,(Price!$L$3:$AY$3=I$3)*(Price!$L$4:$AY$4=I$4),0))} -> 1200 | J22: {=INDEX(Price!$L$11:$AY$210,MATCH(1,(Price!$A$11:$A$210=$A22)*(Price!$B$11:$B$210=$B22)*(Price!$D$11:$D$210="gb"),0),MATCH(1,(Price!$L$3:$AY$3=J$3)*(Price!$L$4:$AY$4=J$4),0))} -> 1200 | K22: {=INDEX(Price!$L$11:$AY$210,MATCH(1,(Price!$A$11:$A$210=$A22)*(Price!$B$11:$B$210=$B22)*(Price!$D$11:$D$210="gb"),0),MATCH(1,(Price!$L$3:$AY$3=K$3)*(Price!$L$4:$AY$4=K$4),0))} -> 1200 | L22: {=INDEX(Price!$L$11:$AY$210,MATCH(1,(Price!$A$11:$A$210=$A22)*(Price!$B$11:$B$210=$B22)*(Price!$D$11:$D$210="gb"),0),MATCH(1,(Price!$L$3:$AY$3=L$3)*(Price!$L$4:$AY$4=L$4),0))} -> 1200.9 | M22: {=INDEX(Price!$L$11:$AY$210,MATCH(1,(Price!$A$11:$A$210=$A22)*(Price!$B$11:$B$210=$B22)*(Price!$D$11:$D$210="gb"),0),MATCH(1,(Price!$L$3:$AY$3=M$3)*(Price!$L$4:$AY$4=M$4),0))} -> 1214.4 | N22: {=INDEX(Price!$L$11:$AY$210,MATCH(1,(Price!$A$11:$A$210=$A22)*(Price!$B$11:$B$210=$B22)*(Price!$D$11:$D$210="gb"),0),MATCH(1,(Price!$L$3:$AY$3=N$3)*(Price!$L$4:$AY$4=N$4),0))} -> 1226.1 | ... AJ22: {=INDEX(Price!$L$11:$AY$210,MATCH(1,(Price!$A$11:$A$210=$A22)*(Price!$B$11:$B$210=$B22)*(Price!$D$11:$D$210="gb"),0),MATCH(1,(Price!$L$3:$AY$3=AJ$3)*(Price!$L$4:$AY$4=AJ$4),0))} -> 1150
A23: 200400 | B23: 110000354 | C23: GB | D23: 2.2 | F23: Giá bán quy đổi EXW | G23: {=INDEX(Price!$L$11:$AY$210,MATCH(1,(Price!$A$11:$A$210=$A23)*(Price!$B$11:$B$210=$B23)*(Price!$D$11:$D$210="exw"),0),MATCH(1,(Price!$L$3:$AY$3=G$3)*(Price!$L$4:$AY$4=G$4),0))} -> 1162 | H23: {=INDEX(Price!$L$11:$AY$210,MATCH(1,(Price!$A$11:$A$210=$A23)*(Price!$B$11:$B$210=$B23)*(Price!$D$11:$D$210="exw"),0),MATCH(1,(Price!$L$3:$AY$3=H$3)*(Price!$L$4:$AY$4=H$4),0))} -> 1162 | I23: {=INDEX(Price!$L$11:$AY$210,MATCH(1,(Price!$A$11:$A$210=$A23)*(Price!$B$11:$B$210=$B23)*(Price!$D$11:$D$210="exw"),0),MATCH(1,(Price!$L$3:$AY$3=I$3)*(Price!$L$4:$AY$4=I$4),0))} -> 1162 | J23: {=INDEX(Price!$L$11:$AY$210,MATCH(1,(Price!$A$11:$A$210=$A23)*(Price!$B$11:$B$210=$B23)*(Price!$D$11:$D$210="exw"),0),MATCH(1,(Price!$L$3:$AY$3=J$3)*(Price!$L$4:$AY$4=J$4),0))} -> 1162 | K23: {=INDEX(Price!$L$11:$AY$210,MATCH(1,(Price!$A$11:$A$210=$A23)*(Price!$B$11:$B$210=$B23)*(Price!$D$11:$D$210="exw"),0),MATCH(1,(Price!$L$3:$AY$3=K$3)*(Price!$L$4:$AY$4=K$4),0))} -> 1162 | L23: {=INDEX(Price!$L$11:$AY$210,MATCH(1,(Price!$A$11:$A$210=$A23)*(Price!$B$11:$B$210=$B23)*(Price!$D$11:$D$210="exw"),0),MATCH(1,(Price!$L$3:$AY$3=L$3)*(Price!$L$4:$AY$4=L$4),0))} -> 1162.8865 | M23: {=INDEX(Price!$L$11:$AY$210,MATCH(1,(Price!$A$11:$A$210=$A23)*(Price!$B$11:$B$210=$B23)*(Price!$D$11:$D$210="exw"),0),MATCH(1,(Price!$L$3:$AY$3=M$3)*(Price!$L$4:$AY$4=M$4),0))} -> 1176.184 | N23: {=INDEX(Price!$L$11:$AY$210,MATCH(1,(Price!$A$11:$A$210=$A23)*(Price!$B$11:$B$210=$B23)*(Price!$D$11:$D$210="exw"),0),MATCH(1,(Price!$L$3:$AY$3=N$3)*(Price!$L$4:$AY$4=N$4),0))} -> 1187.7085 | ... AJ23: {=INDEX(Price!$L$11:$AY$210,MATCH(1,(Price!$A$11:$A$210=$A23)*(Price!$B$11:$B$210=$B23)*(Price!$D$11:$D$210="exw"),0),MATCH(1,(Price!$L$3:$AY$3=AJ$3)*(Price!$L$4:$AY$4=AJ$4),0))} -> 1112.75
A24: 200400 | B24: 110000354 | C24: PETVirgin | D24: 2.3 | F24: Giá chính phẩm | G24: {=SUMPRODUCT(General_Data*(Code_General_Data=$C24)*(Year=G$3)*(Month=G$4))} -> 930 | H24: {=SUMPRODUCT(General_Data*(Code_General_Data=$C24)*(Year=H$3)*(Month=H$4))} -> 943.33333 | I24: {=SUMPRODUCT(General_Data*(Code_General_Data=$C24)*(Year=I$3)*(Month=I$4))} -> 940 | J24: {=SUMPRODUCT(General_Data*(Code_General_Data=$C24)*(Year=J$3)*(Month=J$4))} -> 940 | K24: {=SUMPRODUCT(General_Data*(Code_General_Data=$C24)*(Year=K$3)*(Month=K$4))} -> 942 | L24: {=SUMPRODUCT(General_Data*(Code_General_Data=$C24)*(Year=L$3)*(Month=L$4))} -> 950 | M24: {=SUMPRODUCT(General_Data*(Code_General_Data=$C24)*(Year=M$3)*(Month=M$4))} -> 947.5 | N24: {=SUMPRODUCT(General_Data*(Code_General_Data=$C24)*(Year=N$3)*(Month=N$4))} -> 930 | ... AJ24: {=SUMPRODUCT(General_Data*(Code_General_Data=$C24)*(Year=AJ$3)*(Month=AJ$4))} -> 1190
A25: 200400 | B25: 110000354 | D25: 2.4 | F25: Chênh lệch giữa R sv Virgin | G25: =IF(G22*G23*G24<>0,G23-G24,0) -> 232 | H25: =IF(H22*H23*H24<>0,H23-H24,0) -> 218.66667 | I25: =IF(I22*I23*I24<>0,I23-I24,0) -> 222 | J25: =IF(J22*J23*J24<>0,J23-J24,0) -> 222 | K25: =IF(K22*K23*K24<>0,K23-K24,0) -> 220 | L25: =IF(L22*L23*L24<>0,L23-L24,0) -> 212.8865 | M25: =IF(M22*M23*M24<>0,M23-M24,0) -> 228.684 | N25: =IF(N22*N23*N24<>0,N23-N24,0) -> 257.7085 | ... AJ25: =IF(AJ22*AJ23*AJ24<>0,AJ23-AJ24,0) -> -77.25
A26: 200400 | B26: 110000354 | D26: 2.5 | F26: % +/- | G26: =IFERROR(G25/G24,0) -> 0.24946237 | H26: =IFERROR(H25/H24,0) -> 0.23180212 | I26: =IFERROR(I25/I24,0) -> 0.23617021 | J26: =IFERROR(J25/J24,0) -> 0.23617021 | K26: =IFERROR(K25/K24,0) -> 0.23354565 | L26: =IFERROR(L25/L24,0) -> 0.22409105 | M26: =IFERROR(M25/M24,0) -> 0.24135515 | N26: =IFERROR(N25/N24,0) -> 0.27710591 | ... AJ26: =IFERROR(AJ25/AJ24,0) -> -0.064915966
A27: 200400 | B27: 110000354 | C27: 110000354 | D27: 2.6 | F27: Giá duyệt tháng | G27: {=SUMPRODUCT(General_Data*(Code_General_Data=$C27)*(Year=G$3)*(Month=G$4))} -> 1250 | H27: {=SUMPRODUCT(General_Data*(Code_General_Data=$C27)*(Year=H$3)*(Month=H$4))} -> 1250 | I27: {=SUMPRODUCT(General_Data*(Code_General_Data=$C27)*(Year=I$3)*(Month=I$4))} -> 1250 | J27: {=SUMPRODUCT(General_Data*(Code_General_Data=$C27)*(Year=J$3)*(Month=J$4))} -> 1250 | K27: {=SUMPRODUCT(General_Data*(Code_General_Data=$C27)*(Year=K$3)*(Month=K$4))} -> 1300 | L27: {=SUMPRODUCT(General_Data*(Code_General_Data=$C27)*(Year=L$3)*(Month=L$4))} -> 1300 | M27: {=SUMPRODUCT(General_Data*(Code_General_Data=$C27)*(Year=M$3)*(Month=M$4))} -> 1300 | N27: {=SUMPRODUCT(General_Data*(Code_General_Data=$C27)*(Year=N$3)*(Month=N$4))} -> 1300 | ... AJ27: {=SUMPRODUCT(General_Data*(Code_General_Data=$C27)*(Year=AJ$3)*(Month=AJ$4))} -> 1350
A29: 200332 | D29: 3 | E29: OUTEIRINHO
A30: 200332 | B30: 110000355 | F30: iSS01G
A31: 200332 | B31: 110000355 | D31: 3.1 | F31: Giá bán-FOB | G31: {=INDEX(Price!$L$11:$AY$210,MATCH(1,(Price!$A$11:$A$210=$A31)*(Price!$B$11:$B$210=$B31)*(Price!$D$11:$D$210="gb"),0),MATCH(1,(Price!$L$3:$AY$3=G$3)*(Price!$L$4:$AY$4=G$4),0))} -> 0 | H31: {=INDEX(Price!$L$11:$AY$210,MATCH(1,(Price!$A$11:$A$210=$A31)*(Price!$B$11:$B$210=$B31)*(Price!$D$11:$D$210="gb"),0),MATCH(1,(Price!$L$3:$AY$3=H$3)*(Price!$L$4:$AY$4=H$4),0))} -> 0 | I31: {=INDEX(Price!$L$11:$AY$210,MATCH(1,(Price!$A$11:$A$210=$A31)*(Price!$B$11:$B$210=$B31)*(Price!$D$11:$D$210="gb"),0),MATCH(1,(Price!$L$3:$AY$3=I$3)*(Price!$L$4:$AY$4=I$4),0))} -> 0 | J31: {=INDEX(Price!$L$11:$AY$210,MATCH(1,(Price!$A$11:$A$210=$A31)*(Price!$B$11:$B$210=$B31)*(Price!$D$11:$D$210="gb"),0),MATCH(1,(Price!$L$3:$AY$3=J$3)*(Price!$L$4:$AY$4=J$4),0))} -> 0 | K31: {=INDEX(Price!$L$11:$AY$210,MATCH(1,(Price!$A$11:$A$210=$A31)*(Price!$B$11:$B$210=$B31)*(Price!$D$11:$D$210="gb"),0),MATCH(1,(Price!$L$3:$AY$3=K$3)*(Price!$L$4:$AY$4=K$4),0))} -> 0 | L31: {=INDEX(Price!$L$11:$AY$210,MATCH(1,(Price!$A$11:$A$210=$A31)*(Price!$B$11:$B$210=$B31)*(Price!$D$11:$D$210="gb"),0),MATCH(1,(Price!$L$3:$AY$3=L$3)*(Price!$L$4:$AY$4=L$4),0))} -> 0 | M31: {=INDEX(Price!$L$11:$AY$210,MATCH(1,(Price!$A$11:$A$210=$A31)*(Price!$B$11:$B$210=$B31)*(Price!$D$11:$D$210="gb"),0),MATCH(1,(Price!$L$3:$AY$3=M$3)*(Price!$L$4:$AY$4=M$4),0))} -> 0 | N31: {=INDEX(Price!$L$11:$AY$210,MATCH(1,(Price!$A$11:$A$210=$A31)*(Price!$B$11:$B$210=$B31)*(Price!$D$11:$D$210="gb"),0),MATCH(1,(Price!$L$3:$AY$3=N$3)*(Price!$L$4:$AY$4=N$4),0))} -> 0 | O31: {=INDEX(Price!$L$11:$AY$210,MATCH(1,(Price!$A$11:$A$210=$A31)*(Price!$B$11:$B$210=$B31)*(Price!$D$11:$D$210="gb"),0),MATCH(1,(Price!$L$3:$AY$3=O$3)*(Price!$L$4:$AY$4=O$4),0))} -> 0 | S31: {=INDEX(Price!$L$11:$AY$210,MATCH(1,(Price!$A$11:$A$210=$A31)*(Price!$B$11:$B$210=$B31)*(Price!$D$11:$D$210="gb"),0),MATCH(1,(Price!$L$3:$AY$3=S$3)*(Price!$L$4:$AY$4=S$4),0))} -> 1250 | T31: {=INDEX(Price!$L$11:$AY$210,MATCH(1,(Price!$A$11:$A$210=$A31)*(Price!$B$11:$B$210=$B31)*(Price!$D$11:$D$210="gb"),0),MATCH(1,(Price!$L$3:$AY$3=T$3)*(Price!$L$4:$AY$4=T$4),0))} -> 1250 | U31: {=INDEX(Price!$L$11:$AY$210,MATCH(1,(Price!$A$11:$A$210=$A31)*(Price!$B$11:$B$210=$B31)*(Price!$D$11:$D$210="gb"),0),MATCH(1,(Price!$L$3:$AY$3=U$3)*(Price!$L$4:$AY$4=U$4),0))} -> 1250 | V31: {=INDEX(Price!$L$11:$AY$210,MATCH(1,(Price!$A$11:$A$210=$A31)*(Price!$B$11:$B$210=$B31)*(Price!$D$11:$D$210="gb"),0),MATCH(1,(Price!$L$3:$AY$3=V$3)*(Price!$L$4:$AY$4=V$4),0))} -> 1250 | W31: {=INDEX(Price!$L$11:$AY$210,MATCH(1,(Price!$A$11:$A$210=$A31)*(Price!$B$11:$B$210=$B31)*(Price!$D$11:$D$210="gb"),0),MATCH(1,(Price!$L$3:$AY$3=W$3)*(Price!$L$4:$AY$4=W$4),0))} -> 1250 | X31: {=INDEX(Price!$L$11:$AY$210,MATCH(1,(Price!$A$11:$A$210=$A31)*(Price!$B$11:$B$210=$B31)*(Price!$D$11:$D$210="gb"),0),MATCH(1,(Price!$L$3:$AY$3=X$3)*(Price!$L$4:$AY$4=X$4),0))} -> 1250 | Y31: {=INDEX(Price!$L$11:$AY$210,MATCH(1,(Price!$A$11:$A$210=$A31)*(Price!$B$11:$B$210=$B31)*(Price!$D$11:$D$210="gb"),0),MATCH(1,(Price!$L$3:$AY$3=Y$3)*(Price!$L$4:$AY$4=Y$4),0))} -> 1250 | Z31: {=INDEX(Price!$L$11:$AY$210,MATCH(1,(Price!$A$11:$A$210=$A31)*(Price!$B$11:$B$210=$B31)*(Price!$D$11:$D$210="gb"),0),MATCH(1,(Price!$L$3:$AY$3=Z$3)*(Price!$L$4:$AY$4=Z$4),0))} -> 1250 | ... AD31: {=INDEX(Price!$L$11:$AY$210,MATCH(1,(Price!$A$11:$A$210=$A31)*(Price!$B$11:$B$210=$B31)*(Price!$D$11:$D$210="gb"),0),MATCH(1,(Price!$L$3:$AY$3=AD$3)*(Price!$L$4:$AY$4=AD$4),0))} -> 1250
A32: 200332 | B32: 110000355 | C32: GB | D32: 3.2 | F32: Giá bán quy đổi EXW | G32: {=INDEX(Price!$L$11:$AY$210,MATCH(1,(Price!$A$11:$A$210=$A32)*(Price!$B$11:$B$210=$B32)*(Price!$D$11:$D$210="exw"),0),MATCH(1,(Price!$L$3:$AY$3=G$3)*(Price!$L$4:$AY$4=G$4),0))} -> 0 | H32: {=INDEX(Price!$L$11:$AY$210,MATCH(1,(Price!$A$11:$A$210=$A32)*(Price!$B$11:$B$210=$B32)*(Price!$D$11:$D$210="exw"),0),MATCH(1,(Price!$L$3:$AY$3=H$3)*(Price!$L$4:$AY$4=H$4),0))} -> 0 | I32: {=INDEX(Price!$L$11:$AY$210,MATCH(1,(Price!$A$11:$A$210=$A32)*(Price!$B$11:$B$210=$B32)*(Price!$D$11:$D$210="exw"),0),MATCH(1,(Price!$L$3:$AY$3=I$3)*(Price!$L$4:$AY$4=I$4),0))} -> 0 | J32: {=INDEX(Price!$L$11:$AY$210,MATCH(1,(Price!$A$11:$A$210=$A32)*(Price!$B$11:$B$210=$B32)*(Price!$D$11:$D$210="exw"),0),MATCH(1,(Price!$L$3:$AY$3=J$3)*(Price!$L$4:$AY$4=J$4),0))} -> 0 | K32: {=INDEX(Price!$L$11:$AY$210,MATCH(1,(Price!$A$11:$A$210=$A32)*(Price!$B$11:$B$210=$B32)*(Price!$D$11:$D$210="exw"),0),MATCH(1,(Price!$L$3:$AY$3=K$3)*(Price!$L$4:$AY$4=K$4),0))} -> 0 | L32: {=INDEX(Price!$L$11:$AY$210,MATCH(1,(Price!$A$11:$A$210=$A32)*(Price!$B$11:$B$210=$B32)*(Price!$D$11:$D$210="exw"),0),MATCH(1,(Price!$L$3:$AY$3=L$3)*(Price!$L$4:$AY$4=L$4),0))} -> 0 | M32: {=INDEX(Price!$L$11:$AY$210,MATCH(1,(Price!$A$11:$A$210=$A32)*(Price!$B$11:$B$210=$B32)*(Price!$D$11:$D$210="exw"),0),MATCH(1,(Price!$L$3:$AY$3=M$3)*(Price!$L$4:$AY$4=M$4),0))} -> 0 | N32: {=INDEX(Price!$L$11:$AY$210,MATCH(1,(Price!$A$11:$A$210=$A32)*(Price!$B$11:$B$210=$B32)*(Price!$D$11:$D$210="exw"),0),MATCH(1,(Price!$L$3:$AY$3=N$3)*(Price!$L$4:$AY$4=N$4),0))} -> 0 | O32: {=INDEX(Price!$L$11:$AY$210,MATCH(1,(Price!$A$11:$A$210=$A32)*(Price!$B$11:$B$210=$B32)*(Price!$D$11:$D$210="exw"),0),MATCH(1,(Price!$L$3:$AY$3=O$3)*(Price!$L$4:$AY$4=O$4),0))} -> 0 | S32: {=INDEX(Price!$L$11:$AY$210,MATCH(1,(Price!$A$11:$A$210=$A32)*(Price!$B$11:$B$210=$B32)*(Price!$D$11:$D$210="exw"),0),MATCH(1,(Price!$L$3:$AY$3=S$3)*(Price!$L$4:$AY$4=S$4),0))} -> 1230 | T32: {=INDEX(Price!$L$11:$AY$210,MATCH(1,(Price!$A$11:$A$210=$A32)*(Price!$B$11:$B$210=$B32)*(Price!$D$11:$D$210="exw"),0),MATCH(1,(Price!$L$3:$AY$3=T$3)*(Price!$L$4:$AY$4=T$4),0))} -> 1230 | U32: {=INDEX(Price!$L$11:$AY$210,MATCH(1,(Price!$A$11:$A$210=$A32)*(Price!$B$11:$B$210=$B32)*(Price!$D$11:$D$210="exw"),0),MATCH(1,(Price!$L$3:$AY$3=U$3)*(Price!$L$4:$AY$4=U$4),0))} -> 1230 | V32: {=INDEX(Price!$L$11:$AY$210,MATCH(1,(Price!$A$11:$A$210=$A32)*(Price!$B$11:$B$210=$B32)*(Price!$D$11:$D$210="exw"),0),MATCH(1,(Price!$L$3:$AY$3=V$3)*(Price!$L$4:$AY$4=V$4),0))} -> 1228 | W32: {=INDEX(Price!$L$11:$AY$210,MATCH(1,(Price!$A$11:$A$210=$A32)*(Price!$B$11:$B$210=$B32)*(Price!$D$11:$D$210="exw"),0),MATCH(1,(Price!$L$3:$AY$3=W$3)*(Price!$L$4:$AY$4=W$4),0))} -> 1228 | X32: {=INDEX(Price!$L$11:$AY$210,MATCH(1,(Price!$A$11:$A$210=$A32)*(Price!$B$11:$B$210=$B32)*(Price!$D$11:$D$210="exw"),0),MATCH(1,(Price!$L$3:$AY$3=X$3)*(Price!$L$4:$AY$4=X$4),0))} -> 1228 | Y32: {=INDEX(Price!$L$11:$AY$210,MATCH(1,(Price!$A$11:$A$210=$A32)*(Price!$B$11:$B$210=$B32)*(Price!$D$11:$D$210="exw"),0),MATCH(1,(Price!$L$3:$AY$3=Y$3)*(Price!$L$4:$AY$4=Y$4),0))} -> 1228 | Z32: {=INDEX(Price!$L$11:$AY$210,MATCH(1,(Price!$A$11:$A$210=$A32)*(Price!$B$11:$B$210=$B32)*(Price!$D$11:$D$210="exw"),0),MATCH(1,(Price!$L$3:$AY$3=Z$3)*(Price!$L$4:$AY$4=Z$4),0))} -> 1230 | ... AD32: {=INDEX(Price!$L$11:$AY$210,MATCH(1,(Price!$A$11:$A$210=$A32)*(Price!$B$11:$B$210=$B32)*(Price!$D$11:$D$210="exw"),0),MATCH(1,(Price!$L$3:$AY$3=AD$3)*(Price!$L$4:$AY$4=AD$4),0))} -> 1230
A33: 200332 | B33: 110000355 | C33: PETVirgin | D33: 3.3 | F33: Giá chính phẩm | S33: {=SUMPRODUCT(General_Data*(Code_General_Data=$C33)*(Year=S$3)*(Month=S$4))} -> 828 | T33: {=SUMPRODUCT(General_Data*(Code_General_Data=$C33)*(Year=T$3)*(Month=T$4))} -> 840 | U33: {=SUMPRODUCT(General_Data*(Code_General_Data=$C33)*(Year=U$3)*(Month=U$4))} -> 823 | V33: {=SUMPRODUCT(General_Data*(Code_General_Data=$C33)*(Year=V$3)*(Month=V$4))} -> 765 | W33: {=SUMPRODUCT(General_Data*(Code_General_Data=$C33)*(Year=W$3)*(Month=W$4))} -> 782 | X33: {=SUMPRODUCT(General_Data*(Code_General_Data=$C33)*(Year=X$3)*(Month=X$4))} -> 807.5 | Y33: {=SUMPRODUCT(General_Data*(Code_General_Data=$C33)*(Year=Y$3)*(Month=Y$4))} -> 802 | Z33: {=SUMPRODUCT(General_Data*(Code_General_Data=$C33)*(Year=Z$3)*(Month=Z$4))} -> 795 | ... AD33: {=SUMPRODUCT(General_Data*(Code_General_Data=$C33)*(Year=AD$3)*(Month=AD$4))} -> 772.5
A34: 200332 | B34: 110000355 | D34: 3.4 | F34: Chênh lệch giữa R sv Virgin | S34: =IF(S31*S32*S33<>0,S32-S33,0) -> 402 | T34: =IF(T31*T32*T33<>0,T32-T33,0) -> 390 | U34: =IF(U31*U32*U33<>0,U32-U33,0) -> 407 | V34: =IF(V31*V32*V33<>0,V32-V33,0) -> 463 | W34: =IF(W31*W32*W33<>0,W32-W33,0) -> 446 | X34: =IF(X31*X32*X33<>0,X32-X33,0) -> 420.5 | Y34: =IF(Y31*Y32*Y33<>0,Y32-Y33,0) -> 426 | Z34: =IF(Z31*Z32*Z33<>0,Z32-Z33,0) -> 435 | ... AD34: =IF(AD31*AD32*AD33<>0,AD32-AD33,0) -> 457.5
A35: 200332 | B35: 110000355 | D35: 3.5 | F35: % +/- | S35: =IFERROR(S34/S33,0) -> 0.48550725 | T35: =IFERROR(T34/T33,0) -> 0.46428571 | U35: =IFERROR(U34/U33,0) -> 0.4945322 | V35: =IFERROR(V34/V33,0) -> 0.60522876 | W35: =IFERROR(W34/W33,0) -> 0.57033248 | X35: =IFERROR(X34/X33,0) -> 0.52074303 | Y35: =IFERROR(Y34/Y33,0) -> 0.53117207 | Z35: =IFERROR(Z34/Z33,0) -> 0.54716981 | ... AD35: =IFERROR(AD34/AD33,0) -> 0.59223301
A36: 200332 | B36: 110000355 | C36: 110000355 | D36: 3.6 | F36: Giá duyệt tháng | S36: {=SUMPRODUCT(General_Data*(Code_General_Data=$C36)*(Year=S$3)*(Month=S$4))} -> 1260 | T36: {=SUMPRODUCT(General_Data*(Code_General_Data=$C36)*(Year=T$3)*(Month=T$4))} -> 1260 | U36: {=SUMPRODUCT(General_Data*(Code_General_Data=$C36)*(Year=U$3)*(Month=U$4))} -> 1260 | V36: {=SUMPRODUCT(General_Data*(Code_General_Data=$C36)*(Year=V$3)*(Month=V$4))} -> 1280 | W36: {=SUMPRODUCT(General_Data*(Code_General_Data=$C36)*(Year=W$3)*(Month=W$4))} -> 1280 | X36: {=SUMPRODUCT(General_Data*(Code_General_Data=$C36)*(Year=X$3)*(Month=X$4))} -> 1280 | Y36: {=SUMPRODUCT(General_Data*(Code_General_Data=$C36)*(Year=Y$3)*(Month=Y$4))} -> 1280 | Z36: {=SUMPRODUCT(General_Data*(Code_General_Data=$C36)*(Year=Z$3)*(Month=Z$4))} -> 1250 | ... AD36: {=SUMPRODUCT(General_Data*(Code_General_Data=$C36)*(Year=AD$3)*(Month=AD$4))} -> 1230
A38: 105263 | D38: 4 | E38: UNILEVER VIET NAM
A39: 105263 | B39: 110000354 | F39: WSS01G
A40: 105263 | B40: 110000354 | D40: 4.1 | F40: Giá bán - DDP | G40: {=INDEX(Price!$L$11:$AY$210,MATCH(1,(Price!$A$11:$A$210=$A40)*(Price!$B$11:$B$210=$B40)*(Price!$D$11:$D$210="gb"),0),MATCH(1,(Price!$L$3:$AY$3=G$3)*(Price!$L$4:$AY$4=G$4),0))} -> 1320 | H40: {=INDEX(Price!$L$11:$AY$210,MATCH(1,(Price!$A$11:$A$210=$A40)*(Price!$B$11:$B$210=$B40)*(Price!$D$11:$D$210="gb"),0),MATCH(1,(Price!$L$3:$AY$3=H$3)*(Price!$L$4:$AY$4=H$4),0))} -> 1320 | I40: {=INDEX(Price!$L$11:$AY$210,MATCH(1,(Price!$A$11:$A$210=$A40)*(Price!$B$11:$B$210=$B40)*(Price!$D$11:$D$210="gb"),0),MATCH(1,(Price!$L$3:$AY$3=I$3)*(Price!$L$4:$AY$4=I$4),0))} -> 1320 | J40: {=INDEX(Price!$L$11:$AY$210,MATCH(1,(Price!$A$11:$A$210=$A40)*(Price!$B$11:$B$210=$B40)*(Price!$D$11:$D$210="gb"),0),MATCH(1,(Price!$L$3:$AY$3=J$3)*(Price!$L$4:$AY$4=J$4),0))} -> 1320 | K40: {=INDEX(Price!$L$11:$AY$210,MATCH(1,(Price!$A$11:$A$210=$A40)*(Price!$B$11:$B$210=$B40)*(Price!$D$11:$D$210="gb"),0),MATCH(1,(Price!$L$3:$AY$3=K$3)*(Price!$L$4:$AY$4=K$4),0))} -> 1320 | L40: {=INDEX(Price!$L$11:$AY$210,MATCH(1,(Price!$A$11:$A$210=$A40)*(Price!$B$11:$B$210=$B40)*(Price!$D$11:$D$210="gb"),0),MATCH(1,(Price!$L$3:$AY$3=L$3)*(Price!$L$4:$AY$4=L$4),0))} -> 1320 | M40: {=INDEX(Price!$L$11:$AY$210,MATCH(1,(Price!$A$11:$A$210=$A40)*(Price!$B$11:$B$210=$B40)*(Price!$D$11:$D$210="gb"),0),MATCH(1,(Price!$L$3:$AY$3=M$3)*(Price!$L$4:$AY$4=M$4),0))} -> 1320 | N40: {=INDEX(Price!$L$11:$AY$210,MATCH(1,(Price!$A$11:$A$210=$A40)*(Price!$B$11:$B$210=$B40)*(Price!$D$11:$D$210="gb"),0),MATCH(1,(Price!$L$3:$AY$3=N$3)*(Price!$L$4:$AY$4=N$4),0))} -> 1320 | ... AJ40: {=INDEX(Price!$L$11:$AY$210,MATCH(1,(Price!$A$11:$A$210=$A40)*(Price!$B$11:$B$210=$B40)*(Price!$D$11:$D$210="gb"),0),MATCH(1,(Price!$L$3:$AY$3=AJ$3)*(Price!$L$4:$AY$4=AJ$4),0))} -> 1191
A41: 105263 | B41: 110000354 | C41: GB | D41: 4.2 | F41: Giá bán quy đổi EXW | G41: {=INDEX(Price!$L$11:$AY$210,MATCH(1,(Price!$A$11:$A$210=$A41)*(Price!$B$11:$B$210=$B41)*(Price!$D$11:$D$210="exw"),0),MATCH(1,(Price!$L$3:$AY$3=G$3)*(Price!$L$4:$AY$4=G$4),0))} -> 1307.7959 | H41: {=INDEX(Price!$L$11:$AY$210,MATCH(1,(Price!$A$11:$A$210=$A41)*(Price!$B$11:$B$210=$B41)*(Price!$D$11:$D$210="exw"),0),MATCH(1,(Price!$L$3:$AY$3=H$3)*(Price!$L$4:$AY$4=H$4),0))} -> 1307.7959 | I41: {=INDEX(Price!$L$11:$AY$210,MATCH(1,(Price!$A$11:$A$210=$A41)*(Price!$B$11:$B$210=$B41)*(Price!$D$11:$D$210="exw"),0),MATCH(1,(Price!$L$3:$AY$3=I$3)*(Price!$L$4:$AY$4=I$4),0))} -> 1307.7959 | J41: {=INDEX(Price!$L$11:$AY$210,MATCH(1,(Price!$A$11:$A$210=$A41)*(Price!$B$11:$B$210=$B41)*(Price!$D$11:$D$210="exw"),0),MATCH(1,(Price!$L$3:$AY$3=J$3)*(Price!$L$4:$AY$4=J$4),0))} -> 1307.7959 | K41: {=INDEX(Price!$L$11:$AY$210,MATCH(1,(Price!$A$11:$A$210=$A41)*(Price!$B$11:$B$210=$B41)*(Price!$D$11:$D$210="exw"),0),MATCH(1,(Price!$L$3:$AY$3=K$3)*(Price!$L$4:$AY$4=K$4),0))} -> 1307.7959 | L41: {=INDEX(Price!$L$11:$AY$210,MATCH(1,(Price!$A$11:$A$210=$A41)*(Price!$B$11:$B$210=$B41)*(Price!$D$11:$D$210="exw"),0),MATCH(1,(Price!$L$3:$AY$3=L$3)*(Price!$L$4:$AY$4=L$4),0))} -> 1307.7959 | M41: {=INDEX(Price!$L$11:$AY$210,MATCH(1,(Price!$A$11:$A$210=$A41)*(Price!$B$11:$B$210=$B41)*(Price!$D$11:$D$210="exw"),0),MATCH(1,(Price!$L$3:$AY$3=M$3)*(Price!$L$4:$AY$4=M$4),0))} -> 1308.04 | N41: {=INDEX(Price!$L$11:$AY$210,MATCH(1,(Price!$A$11:$A$210=$A41)*(Price!$B$11:$B$210=$B41)*(Price!$D$11:$D$210="exw"),0),MATCH(1,(Price!$L$3:$AY$3=N$3)*(Price!$L$4:$AY$4=N$4),0))} -> 1308.04 | ... AJ41: {=INDEX(Price!$L$11:$AY$210,MATCH(1,(Price!$A$11:$A$210=$A41)*(Price!$B$11:$B$210=$B41)*(Price!$D$11:$D$210="exw"),0),MATCH(1,(Price!$L$3:$AY$3=AJ$3)*(Price!$L$4:$AY$4=AJ$4),0))} -> 1185
A42: 105263 | B42: 110000354 | C42: PETVirgin | D42: 4.3 | F42: Giá chính phẩm | G42: {=SUMPRODUCT(General_Data*(Code_General_Data=$C42)*(Year=G$3)*(Month=G$4))} -> 930 | H42: {=SUMPRODUCT(General_Data*(Code_General_Data=$C42)*(Year=H$3)*(Month=H$4))} -> 943.33333 | I42: {=SUMPRODUCT(General_Data*(Code_General_Data=$C42)*(Year=I$3)*(Month=I$4))} -> 940 | J42: {=SUMPRODUCT(General_Data*(Code_General_Data=$C42)*(Year=J$3)*(Month=J$4))} -> 940 | K42: {=SUMPRODUCT(General_Data*(Code_General_Data=$C42)*(Year=K$3)*(Month=K$4))} -> 942 | L42: {=SUMPRODUCT(General_Data*(Code_General_Data=$C42)*(Year=L$3)*(Month=L$4))} -> 950 | M42: {=SUMPRODUCT(General_Data*(Code_General_Data=$C42)*(Year=M$3)*(Month=M$4))} -> 947.5 | N42: {=SUMPRODUCT(General_Data*(Code_General_Data=$C42)*(Year=N$3)*(Month=N$4))} -> 930 | ... AJ42: {=SUMPRODUCT(General_Data*(Code_General_Data=$C42)*(Year=AJ$3)*(Month=AJ$4))} -> 1190
A43: 105263 | B43: 110000354 | D43: 4.4 | F43: Chênh lệch giữa R sv Virgin | G43: =IF(G40*G41*G42<>0,G41-G42,0) -> 377.79592 | H43: =IF(H40*H41*H42<>0,H41-H42,0) -> 364.46259 | I43: =IF(I40*I41*I42<>0,I41-I42,0) -> 367.79592 | J43: =IF(J40*J41*J42<>0,J41-J42,0) -> 367.79592 | K43: =IF(K40*K41*K42<>0,K41-K42,0) -> 365.79592 | L43: =IF(L40*L41*L42<>0,L41-L42,0) -> 357.79592 | M43: =IF(M40*M41*M42<>0,M41-M42,0) -> 360.54 | N43: =IF(N40*N41*N42<>0,N41-N42,0) -> 378.04 | ... AJ43: =IF(AJ40*AJ41*AJ42<>0,AJ41-AJ42,0) -> -5
A44: 105263 | B44: 110000354 | D44: 4.5 | F44: % +/- | G44: =IFERROR(G43/G42,0) -> 0.40623217 | H44: =IFERROR(H43/H42,0) -> 0.3863561 | I44: =IFERROR(I43/I42,0) -> 0.39127225 | J44: =IFERROR(J43/J42,0) -> 0.39127225 | K44: =IFERROR(K43/K42,0) -> 0.38831838 | L44: =IFERROR(L43/L42,0) -> 0.37662728 | M44: =IFERROR(M43/M42,0) -> 0.38051715 | N44: =IFERROR(N43/N42,0) -> 0.40649462 | ... AJ44: =IFERROR(AJ43/AJ42,0) -> -0.0042016807
A45: 105263 | B45: 110000354 | C45: 110000354 | D45: 4.6 | F45: Giá duyệt tháng | G45: {=SUMPRODUCT(General_Data*(Code_General_Data=$C45)*(Year=G$3)*(Month=G$4))} -> 1250 | H45: {=SUMPRODUCT(General_Data*(Code_General_Data=$C45)*(Year=H$3)*(Month=H$4))} -> 1250 | I45: {=SUMPRODUCT(General_Data*(Code_General_Data=$C45)*(Year=I$3)*(Month=I$4))} -> 1250 | J45: {=SUMPRODUCT(General_Data*(Code_General_Data=$C45)*(Year=J$3)*(Month=J$4))} -> 1250 | K45: {=SUMPRODUCT(General_Data*(Code_General_Data=$C45)*(Year=K$3)*(Month=K$4))} -> 1300 | L45: {=SUMPRODUCT(General_Data*(Code_General_Data=$C45)*(Year=L$3)*(Month=L$4))} -> 1300 | M45: {=SUMPRODUCT(General_Data*(Code_General_Data=$C45)*(Year=M$3)*(Month=M$4))} -> 1300 | N45: {=SUMPRODUCT(General_Data*(Code_General_Data=$C45)*(Year=N$3)*(Month=N$4))} -> 1300 | ... AJ45: {=SUMPRODUCT(General_Data*(Code_General_Data=$C45)*(Year=AJ$3)*(Month=AJ$4))} -> 1350
A46: 105263
A47: 105263 | B47: 110000339 | F47: MBF01
A48: 105263 | B48: 110000339 | D48: 4.7 | F48: Giá bán - DDP | G48: {=INDEX(Price!$L$11:$AY$210,MATCH(1,(Price!$A$11:$A$210=$A48)*(Price!$B$11:$B$210=$B48)*(Price!$D$11:$D$210="gb"),0),MATCH(1,(Price!$L$3:$AY$3=G$3)*(Price!$L$4:$AY$4=G$4),0))} -> 1500 | H48: {=INDEX(Price!$L$11:$AY$210,MATCH(1,(Price!$A$11:$A$210=$A48)*(Price!$B$11:$B$210=$B48)*(Price!$D$11:$D$210="gb"),0),MATCH(1,(Price!$L$3:$AY$3=H$3)*(Price!$L$4:$AY$4=H$4),0))} -> 1500 | I48: {=INDEX(Price!$L$11:$AY$210,MATCH(1,(Price!$A$11:$A$210=$A48)*(Price!$B$11:$B$210=$B48)*(Price!$D$11:$D$210="gb"),0),MATCH(1,(Price!$L$3:$AY$3=I$3)*(Price!$L$4:$AY$4=I$4),0))} -> 1500 | J48: {=INDEX(Price!$L$11:$AY$210,MATCH(1,(Price!$A$11:$A$210=$A48)*(Price!$B$11:$B$210=$B48)*(Price!$D$11:$D$210="gb"),0),MATCH(1,(Price!$L$3:$AY$3=J$3)*(Price!$L$4:$AY$4=J$4),0))} -> 1430 | K48: {=INDEX(Price!$L$11:$AY$210,MATCH(1,(Price!$A$11:$A$210=$A48)*(Price!$B$11:$B$210=$B48)*(Price!$D$11:$D$210="gb"),0),MATCH(1,(Price!$L$3:$AY$3=K$3)*(Price!$L$4:$AY$4=K$4),0))} -> 1430 | L48: {=INDEX(Price!$L$11:$AY$210,MATCH(1,(Price!$A$11:$A$210=$A48)*(Price!$B$11:$B$210=$B48)*(Price!$D$11:$D$210="gb"),0),MATCH(1,(Price!$L$3:$AY$3=L$3)*(Price!$L$4:$AY$4=L$4),0))} -> 1430 | M48: {=INDEX(Price!$L$11:$AY$210,MATCH(1,(Price!$A$11:$A$210=$A48)*(Price!$B$11:$B$210=$B48)*(Price!$D$11:$D$210="gb"),0),MATCH(1,(Price!$L$3:$AY$3=M$3)*(Price!$L$4:$AY$4=M$4),0))} -> 1430 | N48: {=INDEX(Price!$L$11:$AY$210,MATCH(1,(Price!$A$11:$A$210=$A48)*(Price!$B$11:$B$210=$B48)*(Price!$D$11:$D$210="gb"),0),MATCH(1,(Price!$L$3:$AY$3=N$3)*(Price!$L$4:$AY$4=N$4),0))} -> 1430 | ... AJ48: {=INDEX(Price!$L$11:$AY$210,MATCH(1,(Price!$A$11:$A$210=$A48)*(Price!$B$11:$B$210=$B48)*(Price!$D$11:$D$210="gb"),0),MATCH(1,(Price!$L$3:$AY$3=AJ$3)*(Price!$L$4:$AY$4=AJ$4),0))} -> 1272
A49: 105263 | B49: 110000339 | C49: GB | D49: 4.8 | F49: Giá bán quy đổi EXW | G49: {=INDEX(Price!$L$11:$AY$210,MATCH(1,(Price!$A$11:$A$210=$A49)*(Price!$B$11:$B$210=$B49)*(Price!$D$11:$D$210="exw"),0),MATCH(1,(Price!$L$3:$AY$3=G$3)*(Price!$L$4:$AY$4=G$4),0))} -> 1487.7959 | H49: {=INDEX(Price!$L$11:$AY$210,MATCH(1,(Price!$A$11:$A$210=$A49)*(Price!$B$11:$B$210=$B49)*(Price!$D$11:$D$210="exw"),0),MATCH(1,(Price!$L$3:$AY$3=H$3)*(Price!$L$4:$AY$4=H$4),0))} -> 1487.7959 | I49: {=INDEX(Price!$L$11:$AY$210,MATCH(1,(Price!$A$11:$A$210=$A49)*(Price!$B$11:$B$210=$B49)*(Price!$D$11:$D$210="exw"),0),MATCH(1,(Price!$L$3:$AY$3=I$3)*(Price!$L$4:$AY$4=I$4),0))} -> 1487.7959 | J49: {=INDEX(Price!$L$11:$AY$210,MATCH(1,(Price!$A$11:$A$210=$A49)*(Price!$B$11:$B$210=$B49)*(Price!$D$11:$D$210="exw"),0),MATCH(1,(Price!$L$3:$AY$3=J$3)*(Price!$L$4:$AY$4=J$4),0))} -> 1417.7959 | K49: {=INDEX(Price!$L$11:$AY$210,MATCH(1,(Price!$A$11:$A$210=$A49)*(Price!$B$11:$B$210=$B49)*(Price!$D$11:$D$210="exw"),0),MATCH(1,(Price!$L$3:$AY$3=K$3)*(Price!$L$4:$AY$4=K$4),0))} -> 1417.7959 | L49: {=INDEX(Price!$L$11:$AY$210,MATCH(1,(Price!$A$11:$A$210=$A49)*(Price!$B$11:$B$210=$B49)*(Price!$D$11:$D$210="exw"),0),MATCH(1,(Price!$L$3:$AY$3=L$3)*(Price!$L$4:$AY$4=L$4),0))} -> 1417.7959 | M49: {=INDEX(Price!$L$11:$AY$210,MATCH(1,(Price!$A$11:$A$210=$A49)*(Price!$B$11:$B$210=$B49)*(Price!$D$11:$D$210="exw"),0),MATCH(1,(Price!$L$3:$AY$3=M$3)*(Price!$L$4:$AY$4=M$4),0))} -> 1418.04 | N49: {=INDEX(Price!$L$11:$AY$210,MATCH(1,(Price!$A$11:$A$210=$A49)*(Price!$B$11:$B$210=$B49)*(Price!$D$11:$D$210="exw"),0),MATCH(1,(Price!$L$3:$AY$3=N$3)*(Price!$L$4:$AY$4=N$4),0))} -> 1418.04 | ... AJ49: {=INDEX(Price!$L$11:$AY$210,MATCH(1,(Price!$A$11:$A$210=$A49)*(Price!$B$11:$B$210=$B49)*(Price!$D$11:$D$210="exw"),0),MATCH(1,(Price!$L$3:$AY$3=AJ$3)*(Price!$L$4:$AY$4=AJ$4),0))} -> 1266
A50: 105263 | B50: 110000339 | C50: HDPEVirgin | D50: 4.9 | F50: Giá chính phẩm | G50: {=SUMPRODUCT(General_Data*(Code_General_Data=$C50)*(Year=G$3)*(Month=G$4))} -> 940 | H50: {=SUMPRODUCT(General_Data*(Code_General_Data=$C50)*(Year=H$3)*(Month=H$4))} -> 993.33333 | I50: {=SUMPRODUCT(General_Data*(Code_General_Data=$C50)*(Year=I$3)*(Month=I$4))} -> 985 | J50: {=SUMPRODUCT(General_Data*(Code_General_Data=$C50)*(Year=J$3)*(Month=J$4))} -> 962.5 | K50: {=SUMPRODUCT(General_Data*(Code_General_Data=$C50)*(Year=K$3)*(Month=K$4))} -> 982 | L50: {=SUMPRODUCT(General_Data*(Code_General_Data=$C50)*(Year=L$3)*(Month=L$4))} -> 1000 | M50: {=SUMPRODUCT(General_Data*(Code_General_Data=$C50)*(Year=M$3)*(Month=M$4))} -> 1000 | N50: {=SUMPRODUCT(General_Data*(Code_General_Data=$C50)*(Year=N$3)*(Month=N$4))} -> 984 | ... AJ50: {=SUMPRODUCT(General_Data*(Code_General_Data=$C50)*(Year=AJ$3)*(Month=AJ$4))} -> 1470
A51: 105263 | B51: 110000339 | D51: 4.1 | F51: Chênh lệch giữa R sv Virgin | G51: =IF(G48*G49*G50<>0,G49-G50,0) -> 547.79592 | H51: =IF(H48*H49*H50<>0,H49-H50,0) -> 494.46259 | I51: =IF(I48*I49*I50<>0,I49-I50,0) -> 502.79592 | J51: =IF(J48*J49*J50<>0,J49-J50,0) -> 455.29592 | K51: =IF(K48*K49*K50<>0,K49-K50,0) -> 435.79592 | L51: =IF(L48*L49*L50<>0,L49-L50,0) -> 417.79592 | M51: =IF(M48*M49*M50<>0,M49-M50,0) -> 418.04 | N51: =IF(N48*N49*N50<>0,N49-N50,0) -> 434.04 | ... AJ51: =IF(AJ48*AJ49*AJ50<>0,AJ49-AJ50,0) -> -204
A52: 105263 | B52: 110000339 | D52: 4.11 | F52: % +/- | G52: =IFERROR(G51/G50,0) -> 0.58276162 | H52: =IFERROR(H51/H50,0) -> 0.49778113 | I52: =IFERROR(I51/I50,0) -> 0.51045271 | J52: =IFERROR(J51/J50,0) -> 0.47303472 | K52: =IFERROR(K51/K50,0) -> 0.44378403 | L52: =IFERROR(L51/L50,0) -> 0.41779592 | M52: =IFERROR(M51/M50,0) -> 0.41804 | N52: =IFERROR(N51/N50,0) -> 0.44109756 | ... AJ52: =IFERROR(AJ51/AJ50,0) -> -0.13877551
A53: 105263 | B53: 110000339 | C53: 110000339 | D53: 4.12 | F53: Giá duyệt tháng | G53: {=SUMPRODUCT(General_Data*(Code_General_Data=$C53)*(Year=G$3)*(Month=G$4))} -> 1350 | H53: {=SUMPRODUCT(General_Data*(Code_General_Data=$C53)*(Year=H$3)*(Month=H$4))} -> 1350 | I53: {=SUMPRODUCT(General_Data*(Code_General_Data=$C53)*(Year=I$3)*(Month=I$4))} -> 1350 | J53: {=SUMPRODUCT(General_Data*(Code_General_Data=$C53)*(Year=J$3)*(Month=J$4))} -> 1350 | K53: {=SUMPRODUCT(General_Data*(Code_General_Data=$C53)*(Year=K$3)*(Month=K$4))} -> 1350 | L53: {=SUMPRODUCT(General_Data*(Code_General_Data=$C53)*(Year=L$3)*(Month=L$4))} -> 1350 | M53: {=SUMPRODUCT(General_Data*(Code_General_Data=$C53)*(Year=M$3)*(Month=M$4))} -> 1350 | N53: {=SUMPRODUCT(General_Data*(Code_General_Data=$C53)*(Year=N$3)*(Month=N$4))} -> 1350 | ... AJ53: {=SUMPRODUCT(General_Data*(Code_General_Data=$C53)*(Year=AJ$3)*(Month=AJ$4))} -> 1350
A54: 105263
A55: 105263 | B55: 110000481 | F55: PCF01
A56: 105263 | B56: 110000481 | D56: 4.13 | F56: Giá bán - DDP | G56: {=INDEX(Price!$L$11:$AY$210,MATCH(1,(Price!$A$11:$A$210=$A56)*(Price!$B$11:$B$210=$B56)*(Price!$D$11:$D$210="gb"),0),MATCH(1,(Price!$L$3:$AY$3=G$3)*(Price!$L$4:$AY$4=G$4),0))} -> 0 | H56: {=INDEX(Price!$L$11:$AY$210,MATCH(1,(Price!$A$11:$A$210=$A56)*(Price!$B$11:$B$210=$B56)*(Price!$D$11:$D$210="gb"),0),MATCH(1,(Price!$L$3:$AY$3=H$3)*(Price!$L$4:$AY$4=H$4),0))} -> 0 | I56: {=INDEX(Price!$L$11:$AY$210,MATCH(1,(Price!$A$11:$A$210=$A56)*(Price!$B$11:$B$210=$B56)*(Price!$D$11:$D$210="gb"),0),MATCH(1,(Price!$L$3:$AY$3=I$3)*(Price!$L$4:$AY$4=I$4),0))} -> 0 | J56: {=INDEX(Price!$L$11:$AY$210,MATCH(1,(Price!$A$11:$A$210=$A56)*(Price!$B$11:$B$210=$B56)*(Price!$D$11:$D$210="gb"),0),MATCH(1,(Price!$L$3:$AY$3=J$3)*(Price!$L$4:$AY$4=J$4),0))} -> 0 | K56: {=INDEX(Price!$L$11:$AY$210,MATCH(1,(Price!$A$11:$A$210=$A56)*(Price!$B$11:$B$210=$B56)*(Price!$D$11:$D$210="gb"),0),MATCH(1,(Price!$L$3:$AY$3=K$3)*(Price!$L$4:$AY$4=K$4),0))} -> 0 | L56: {=INDEX(Price!$L$11:$AY$210,MATCH(1,(Price!$A$11:$A$210=$A56)*(Price!$B$11:$B$210=$B56)*(Price!$D$11:$D$210="gb"),0),MATCH(1,(Price!$L$3:$AY$3=L$3)*(Price!$L$4:$AY$4=L$4),0))} -> 0 | M56: {=INDEX(Price!$L$11:$AY$210,MATCH(1,(Price!$A$11:$A$210=$A56)*(Price!$B$11:$B$210=$B56)*(Price!$D$11:$D$210="gb"),0),MATCH(1,(Price!$L$3:$AY$3=M$3)*(Price!$L$4:$AY$4=M$4),0))} -> 0 | N56: {=INDEX(Price!$L$11:$AY$210,MATCH(1,(Price!$A$11:$A$210=$A56)*(Price!$B$11:$B$210=$B56)*(Price!$D$11:$D$210="gb"),0),MATCH(1,(Price!$L$3:$AY$3=N$3)*(Price!$L$4:$AY$4=N$4),0))} -> 0 | ... AJ56: {=INDEX(Price!$L$11:$AY$210,MATCH(1,(Price!$A$11:$A$210=$A56)*(Price!$B$11:$B$210=$B56)*(Price!$D$11:$D$210="gb"),0),MATCH(1,(Price!$L$3:$AY$3=AJ$3)*(Price!$L$4:$AY$4=AJ$4),0))} -> 1272
A57: 105263 | B57: 110000481 | C57: GB | D57: 4.14 | F57: Giá bán quy đổi EXW | G57: {=INDEX(Price!$L$11:$AY$210,MATCH(1,(Price!$A$11:$A$210=$A57)*(Price!$B$11:$B$210=$B57)*(Price!$D$11:$D$210="exw"),0),MATCH(1,(Price!$L$3:$AY$3=G$3)*(Price!$L$4:$AY$4=G$4),0))} -> 0 | H57: {=INDEX(Price!$L$11:$AY$210,MATCH(1,(Price!$A$11:$A$210=$A57)*(Price!$B$11:$B$210=$B57)*(Price!$D$11:$D$210="exw"),0),MATCH(1,(Price!$L$3:$AY$3=H$3)*(Price!$L$4:$AY$4=H$4),0))} -> 0 | I57: {=INDEX(Price!$L$11:$AY$210,MATCH(1,(Price!$A$11:$A$210=$A57)*(Price!$B$11:$B$210=$B57)*(Price!$D$11:$D$210="exw"),0),MATCH(1,(Price!$L$3:$AY$3=I$3)*(Price!$L$4:$AY$4=I$4),0))} -> 0 | J57: {=INDEX(Price!$L$11:$AY$210,MATCH(1,(Price!$A$11:$A$210=$A57)*(Price!$B$11:$B$210=$B57)*(Price!$D$11:$D$210="exw"),0),MATCH(1,(Price!$L$3:$AY$3=J$3)*(Price!$L$4:$AY$4=J$4),0))} -> 0 | K57: {=INDEX(Price!$L$11:$AY$210,MATCH(1,(Price!$A$11:$A$210=$A57)*(Price!$B$11:$B$210=$B57)*(Price!$D$11:$D$210="exw"),0),MATCH(1,(Price!$L$3:$AY$3=K$3)*(Price!$L$4:$AY$4=K$4),0))} -> 0 | L57: {=INDEX(Price!$L$11:$AY$210,MATCH(1,(Price!$A$11:$A$210=$A57)*(Price!$B$11:$B$210=$B57)*(Price!$D$11:$D$210="exw"),0),MATCH(1,(Price!$L$3:$AY$3=L$3)*(Price!$L$4:$AY$4=L$4),0))} -> 0 | M57: {=INDEX(Price!$L$11:$AY$210,MATCH(1,(Price!$A$11:$A$210=$A57)*(Price!$B$11:$B$210=$B57)*(Price!$D$11:$D$210="exw"),0),MATCH(1,(Price!$L$3:$AY$3=M$3)*(Price!$L$4:$AY$4=M$4),0))} -> 0 | N57: {=INDEX(Price!$L$11:$AY$210,MATCH(1,(Price!$A$11:$A$210=$A57)*(Price!$B$11:$B$210=$B57)*(Price!$D$11:$D$210="exw"),0),MATCH(1,(Price!$L$3:$AY$3=N$3)*(Price!$L$4:$AY$4=N$4),0))} -> 0 | ... AJ57: {=INDEX(Price!$L$11:$AY$210,MATCH(1,(Price!$A$11:$A$210=$A57)*(Price!$B$11:$B$210=$B57)*(Price!$D$11:$D$210="exw"),0),MATCH(1,(Price!$L$3:$AY$3=AJ$3)*(Price!$L$4:$AY$4=AJ$4),0))} -> 1266
A58: 105263 | B58: 110000481 | C58: HDPEVirgin | D58: 4.15 | F58: Giá chính phẩm | S58: {=SUMPRODUCT(General_Data*(Code_General_Data=$C58)*(Year=S$3)*(Month=S$4))} -> 940 | T58: {=SUMPRODUCT(General_Data*(Code_General_Data=$C58)*(Year=T$3)*(Month=T$4))} -> 918 | U58: {=SUMPRODUCT(General_Data*(Code_General_Data=$C58)*(Year=U$3)*(Month=U$4))} -> 896 | V58: {=SUMPRODUCT(General_Data*(Code_General_Data=$C58)*(Year=V$3)*(Month=V$4))} -> 891.5 | W58: {=SUMPRODUCT(General_Data*(Code_General_Data=$C58)*(Year=W$3)*(Month=W$4))} -> 864 | X58: {=SUMPRODUCT(General_Data*(Code_General_Data=$C58)*(Year=X$3)*(Month=X$4))} -> 833 | Y58: {=SUMPRODUCT(General_Data*(Code_General_Data=$C58)*(Year=Y$3)*(Month=Y$4))} -> 833 | Z58: {=SUMPRODUCT(General_Data*(Code_General_Data=$C58)*(Year=Z$3)*(Month=Z$4))} -> 815 | ... AJ58: {=SUMPRODUCT(General_Data*(Code_General_Data=$C58)*(Year=AJ$3)*(Month=AJ$4))} -> 1470
A59: 105263 | B59: 110000481 | D59: 4.16 | F59: Chênh lệch giữa R sv Virgin | S59: =IF(S56*S57*S58<>0,S57-S58,0) -> 448.04 | T59: =IF(T56*T57*T58<>0,T57-T58,0) -> 470.04 | U59: =IF(U56*U57*U58<>0,U57-U58,0) -> 492.04 | V59: =IF(V56*V57*V58<>0,V57-V58,0) -> 446.54 | W59: =IF(W56*W57*W58<>0,W57-W58,0) -> 474.04 | X59: =IF(X56*X57*X58<>0,X57-X58,0) -> 505.04 | Y59: =IF(Y56*Y57*Y58<>0,Y57-Y58,0) -> 535.04 | Z59: =IF(Z56*Z57*Z58<>0,Z57-Z58,0) -> 553.04 | ... AJ59: =IF(AJ56*AJ57*AJ58<>0,AJ57-AJ58,0) -> -204
A60: 105263 | B60: 110000481 | D60: 4.17 | F60: % +/- | S60: =IFERROR(S59/S58,0) -> 0.4766383 | T60: =IFERROR(T59/T58,0) -> 0.51202614 | U60: =IFERROR(U59/U58,0) -> 0.54915179 | V60: =IFERROR(V59/V58,0) -> 0.50088615 | W60: =IFERROR(W59/W58,0) -> 0.54865741 | X60: =IFERROR(X59/X58,0) -> 0.60629052 | Y60: =IFERROR(Y59/Y58,0) -> 0.64230492 | Z60: =IFERROR(Z59/Z58,0) -> 0.67857669 | ... AJ60: =IFERROR(AJ59/AJ58,0) -> -0.13877551
A61: 105263 | B61: 110000481 | C61: 110000481 | D61: 4.18 | F61: Giá duyệt tháng | S61: {=SUMPRODUCT(General_Data*(Code_General_Data=$C61)*(Year=S$3)*(Month=S$4))} -> 1400 | T61: {=SUMPRODUCT(General_Data*(Code_General_Data=$C61)*(Year=T$3)*(Month=T$4))} -> 1400 | U61: {=SUMPRODUCT(General_Data*(Code_General_Data=$C61)*(Year=U$3)*(Month=U$4))} -> 1350 | V61: {=SUMPRODUCT(General_Data*(Code_General_Data=$C61)*(Year=V$3)*(Month=V$4))} -> 1350 | W61: {=SUMPRODUCT(General_Data*(Code_General_Data=$C61)*(Year=W$3)*(Month=W$4))} -> 1350 | X61: {=SUMPRODUCT(General_Data*(Code_General_Data=$C61)*(Year=X$3)*(Month=X$4))} -> 1350 | Y61: {=SUMPRODUCT(General_Data*(Code_General_Data=$C61)*(Year=Y$3)*(Month=Y$4))} -> 1350 | Z61: {=SUMPRODUCT(General_Data*(Code_General_Data=$C61)*(Year=Z$3)*(Month=Z$4))} -> 1330 | ... AJ61: {=SUMPRODUCT(General_Data*(Code_General_Data=$C61)*(Year=AJ$3)*(Month=AJ$4))} -> 1450
A62: 105263
A63: 105263 | B63: RHDPETHOI-MAU | D63: 4.19 | F63: rHDPE thổi màu - khử mùi
A64: 105263 | B64: RHDPETHOI-MAU | D64: 4.2 | F64: Giá bán - DDP | G64: {=INDEX(Price!$L$11:$AY$210,MATCH(1,(Price!$A$11:$A$210=$A64)*(Price!$B$11:$B$210=$B64)*(Price!$D$11:$D$210="gb"),0),MATCH(1,(Price!$L$3:$AY$3=G$3)*(Price!$L$4:$AY$4=G$4),0))} -> 1450 | H64: {=INDEX(Price!$L$11:$AY$210,MATCH(1,(Price!$A$11:$A$210=$A64)*(Price!$B$11:$B$210=$B64)*(Price!$D$11:$D$210="gb"),0),MATCH(1,(Price!$L$3:$AY$3=H$3)*(Price!$L$4:$AY$4=H$4),0))} -> 1450 | I64: {=INDEX(Price!$L$11:$AY$210,MATCH(1,(Price!$A$11:$A$210=$A64)*(Price!$B$11:$B$210=$B64)*(Price!$D$11:$D$210="gb"),0),MATCH(1,(Price!$L$3:$AY$3=I$3)*(Price!$L$4:$AY$4=I$4),0))} -> 1450 | J64: {=INDEX(Price!$L$11:$AY$210,MATCH(1,(Price!$A$11:$A$210=$A64)*(Price!$B$11:$B$210=$B64)*(Price!$D$11:$D$210="gb"),0),MATCH(1,(Price!$L$3:$AY$3=J$3)*(Price!$L$4:$AY$4=J$4),0))} -> 1380 | K64: {=INDEX(Price!$L$11:$AY$210,MATCH(1,(Price!$A$11:$A$210=$A64)*(Price!$B$11:$B$210=$B64)*(Price!$D$11:$D$210="gb"),0),MATCH(1,(Price!$L$3:$AY$3=K$3)*(Price!$L$4:$AY$4=K$4),0))} -> 1380 | L64: {=INDEX(Price!$L$11:$AY$210,MATCH(1,(Price!$A$11:$A$210=$A64)*(Price!$B$11:$B$210=$B64)*(Price!$D$11:$D$210="gb"),0),MATCH(1,(Price!$L$3:$AY$3=L$3)*(Price!$L$4:$AY$4=L$4),0))} -> 1380 | M64: {=INDEX(Price!$L$11:$AY$210,MATCH(1,(Price!$A$11:$A$210=$A64)*(Price!$B$11:$B$210=$B64)*(Price!$D$11:$D$210="gb"),0),MATCH(1,(Price!$L$3:$AY$3=M$3)*(Price!$L$4:$AY$4=M$4),0))} -> 1380 | N64: {=INDEX(Price!$L$11:$AY$210,MATCH(1,(Price!$A$11:$A$210=$A64)*(Price!$B$11:$B$210=$B64)*(Price!$D$11:$D$210="gb"),0),MATCH(1,(Price!$L$3:$AY$3=N$3)*(Price!$L$4:$AY$4=N$4),0))} -> 1380 | ... AJ64: {=INDEX(Price!$L$11:$AY$210,MATCH(1,(Price!$A$11:$A$210=$A64)*(Price!$B$11:$B$210=$B64)*(Price!$D$11:$D$210="gb"),0),MATCH(1,(Price!$L$3:$AY$3=AJ$3)*(Price!$L$4:$AY$4=AJ$4),0))} -> 0
A65: 105263 | B65: RHDPETHOI-MAU | C65: GB | D65: 4.21 | F65: Giá bán quy đổi EXW | G65: {=INDEX(Price!$L$11:$AY$210,MATCH(1,(Price!$A$11:$A$210=$A65)*(Price!$B$11:$B$210=$B65)*(Price!$D$11:$D$210="exw"),0),MATCH(1,(Price!$L$3:$AY$3=G$3)*(Price!$L$4:$AY$4=G$4),0))} -> 1437.7959 | H65: {=INDEX(Price!$L$11:$AY$210,MATCH(1,(Price!$A$11:$A$210=$A65)*(Price!$B$11:$B$210=$B65)*(Price!$D$11:$D$210="exw"),0),MATCH(1,(Price!$L$3:$AY$3=H$3)*(Price!$L$4:$AY$4=H$4),0))} -> 1437.7959 | I65: {=INDEX(Price!$L$11:$AY$210,MATCH(1,(Price!$A$11:$A$210=$A65)*(Price!$B$11:$B$210=$B65)*(Price!$D$11:$D$210="exw"),0),MATCH(1,(Price!$L$3:$AY$3=I$3)*(Price!$L$4:$AY$4=I$4),0))} -> 1437.7959 | J65: {=INDEX(Price!$L$11:$AY$210,MATCH(1,(Price!$A$11:$A$210=$A65)*(Price!$B$11:$B$210=$B65)*(Price!$D$11:$D$210="exw"),0),MATCH(1,(Price!$L$3:$AY$3=J$3)*(Price!$L$4:$AY$4=J$4),0))} -> 1367.7959 | K65: {=INDEX(Price!$L$11:$AY$210,MATCH(1,(Price!$A$11:$A$210=$A65)*(Price!$B$11:$B$210=$B65)*(Price!$D$11:$D$210="exw"),0),MATCH(1,(Price!$L$3:$AY$3=K$3)*(Price!$L$4:$AY$4=K$4),0))} -> 1367.7959 | L65: {=INDEX(Price!$L$11:$AY$210,MATCH(1,(Price!$A$11:$A$210=$A65)*(Price!$B$11:$B$210=$B65)*(Price!$D$11:$D$210="exw"),0),MATCH(1,(Price!$L$3:$AY$3=L$3)*(Price!$L$4:$AY$4=L$4),0))} -> 1367.7959 | M65: {=INDEX(Price!$L$11:$AY$210,MATCH(1,(Price!$A$11:$A$210=$A65)*(Price!$B$11:$B$210=$B65)*(Price!$D$11:$D$210="exw"),0),MATCH(1,(Price!$L$3:$AY$3=M$3)*(Price!$L$4:$AY$4=M$4),0))} -> 1368.04 | N65: {=INDEX(Price!$L$11:$AY$210,MATCH(1,(Price!$A$11:$A$210=$A65)*(Price!$B$11:$B$210=$B65)*(Price!$D$11:$D$210="exw"),0),MATCH(1,(Price!$L$3:$AY$3=N$3)*(Price!$L$4:$AY$4=N$4),0))} -> 1368.04 | ... AJ65: {=INDEX(Price!$L$11:$AY$210,MATCH(1,(Price!$A$11:$A$210=$A65)*(Price!$B$11:$B$210=$B65)*(Price!$D$11:$D$210="exw"),0),MATCH(1,(Price!$L$3:$AY$3=AJ$3)*(Price!$L$4:$AY$4=AJ$4),0))} -> 0
A66: 105263 | B66: RHDPETHOI-MAU | C66: HDPEVirgin | D66: 4.22 | F66: Giá chính phẩm | G66: {=SUMPRODUCT(General_Data*(Code_General_Data=$C66)*(Year=G$3)*(Month=G$4))} -> 940 | H66: {=SUMPRODUCT(General_Data*(Code_General_Data=$C66)*(Year=H$3)*(Month=H$4))} -> 993.33333 | I66: {=SUMPRODUCT(General_Data*(Code_General_Data=$C66)*(Year=I$3)*(Month=I$4))} -> 985 | J66: {=SUMPRODUCT(General_Data*(Code_General_Data=$C66)*(Year=J$3)*(Month=J$4))} -> 962.5 | K66: {=SUMPRODUCT(General_Data*(Code_General_Data=$C66)*(Year=K$3)*(Month=K$4))} -> 982 | L66: {=SUMPRODUCT(General_Data*(Code_General_Data=$C66)*(Year=L$3)*(Month=L$4))} -> 1000 | M66: {=SUMPRODUCT(General_Data*(Code_General_Data=$C66)*(Year=M$3)*(Month=M$4))} -> 1000 | N66: {=SUMPRODUCT(General_Data*(Code_General_Data=$C66)*(Year=N$3)*(Month=N$4))} -> 984 | ... AJ66: {=SUMPRODUCT(General_Data*(Code_General_Data=$C66)*(Year=AJ$3)*(Month=AJ$4))} -> 1470
A67: 105263 | B67: RHDPETHOI-MAU | D67: 4.23 | F67: Chênh lệch giữa R sv Virgin | G67: =IF(G64*G65*G66<>0,G65-G66,0) -> 497.79592 | H67: =IF(H64*H65*H66<>0,H65-H66,0) -> 444.46259 | I67: =IF(I64*I65*I66<>0,I65-I66,0) -> 452.79592 | J67: =IF(J64*J65*J66<>0,J65-J66,0) -> 405.29592 | K67: =IF(K64*K65*K66<>0,K65-K66,0) -> 385.79592 | L67: =IF(L64*L65*L66<>0,L65-L66,0) -> 367.79592 | M67: =IF(M64*M65*M66<>0,M65-M66,0) -> 368.04 | N67: =IF(N64*N65*N66<>0,N65-N66,0) -> 384.04 | ... AJ67: =IF(AJ64*AJ65*AJ66<>0,AJ65-AJ66,0) -> 0
A68: 105263 | B68: RHDPETHOI-MAU | D68: 4.24 | F68: % +/- | G68: =IFERROR(G67/G66,0) -> 0.52957013 | H68: =IFERROR(H67/H66,0) -> 0.44744556 | I68: =IFERROR(I67/I66,0) -> 0.45969129 | J68: =IFERROR(J67/J66,0) -> 0.42108667 | K68: =IFERROR(K67/K66,0) -> 0.39286753 | L68: =IFERROR(L67/L66,0) -> 0.36779592 | M68: =IFERROR(M67/M66,0) -> 0.36804 | N68: =IFERROR(N67/N66,0) -> 0.39028455 | ... AJ68: =IFERROR(AJ67/AJ66,0) -> 0
A69: 105263 | B69: RHDPETHOI-MAU | C69: RHDPETHOI-MAU | D69: 4.25 | F69: Giá duyệt tháng | G69: {=SUMPRODUCT(General_Data*(Code_General_Data=$C69)*(Year=G$3)*(Month=G$4))} -> 1350 | H69: {=SUMPRODUCT(General_Data*(Code_General_Data=$C69)*(Year=H$3)*(Month=H$4))} -> 1350 | I69: {=SUMPRODUCT(General_Data*(Code_General_Data=$C69)*(Year=I$3)*(Month=I$4))} -> 1350 | J69: {=SUMPRODUCT(General_Data*(Code_General_Data=$C69)*(Year=J$3)*(Month=J$4))} -> 1350 | K69: {=SUMPRODUCT(General_Data*(Code_General_Data=$C69)*(Year=K$3)*(Month=K$4))} -> 1350 | L69: {=SUMPRODUCT(General_Data*(Code_General_Data=$C69)*(Year=L$3)*(Month=L$4))} -> 1350 | M69: {=SUMPRODUCT(General_Data*(Code_General_Data=$C69)*(Year=M$3)*(Month=M$4))} -> 1350 | N69: {=SUMPRODUCT(General_Data*(Code_General_Data=$C69)*(Year=N$3)*(Month=N$4))} -> 1350 | ... AJ69: {=SUMPRODUCT(General_Data*(Code_General_Data=$C69)*(Year=AJ$3)*(Month=AJ$4))} -> 1400
A71: 105194 | D71: 5 | E71: SUNTORY VIET NAM
A72: 105194 | B72: 110000332 | F72: iSS1084G
A73: 105194 | B73: 110000332 | D73: 5.1 | F73: Giá bán-DDP | G73: {=INDEX(Price!$L$11:$AY$210,MATCH(1,(Price!$A$11:$A$210=$A73)*(Price!$B$11:$B$210=$B73)*(Price!$D$11:$D$210="gb"),0),MATCH(1,(Price!$L$3:$AY$3=G$3)*(Price!$L$4:$AY$4=G$4),0))} -> 1366.5 | H73: {=INDEX(Price!$L$11:$AY$210,MATCH(1,(Price!$A$11:$A$210=$A73)*(Price!$B$11:$B$210=$B73)*(Price!$D$11:$D$210="gb"),0),MATCH(1,(Price!$L$3:$AY$3=H$3)*(Price!$L$4:$AY$4=H$4),0))} -> 1374 | I73: {=INDEX(Price!$L$11:$AY$210,MATCH(1,(Price!$A$11:$A$210=$A73)*(Price!$B$11:$B$210=$B73)*(Price!$D$11:$D$210="gb"),0),MATCH(1,(Price!$L$3:$AY$3=I$3)*(Price!$L$4:$AY$4=I$4),0))} -> 1386.5 | J73: {=INDEX(Price!$L$11:$AY$210,MATCH(1,(Price!$A$11:$A$210=$A73)*(Price!$B$11:$B$210=$B73)*(Price!$D$11:$D$210="gb"),0),MATCH(1,(Price!$L$3:$AY$3=J$3)*(Price!$L$4:$AY$4=J$4),0))} -> 1389 | K73: {=INDEX(Price!$L$11:$AY$210,MATCH(1,(Price!$A$11:$A$210=$A73)*(Price!$B$11:$B$210=$B73)*(Price!$D$11:$D$210="gb"),0),MATCH(1,(Price!$L$3:$AY$3=K$3)*(Price!$L$4:$AY$4=K$4),0))} -> 1393 | L73: {=INDEX(Price!$L$11:$AY$210,MATCH(1,(Price!$A$11:$A$210=$A73)*(Price!$B$11:$B$210=$B73)*(Price!$D$11:$D$210="gb"),0),MATCH(1,(Price!$L$3:$AY$3=L$3)*(Price!$L$4:$AY$4=L$4),0))} -> 1408 | M73: {=INDEX(Price!$L$11:$AY$210,MATCH(1,(Price!$A$11:$A$210=$A73)*(Price!$B$11:$B$210=$B73)*(Price!$D$11:$D$210="gb"),0),MATCH(1,(Price!$L$3:$AY$3=M$3)*(Price!$L$4:$AY$4=M$4),0))} -> 1424 | N73: {=INDEX(Price!$L$11:$AY$210,MATCH(1,(Price!$A$11:$A$210=$A73)*(Price!$B$11:$B$210=$B73)*(Price!$D$11:$D$210="gb"),0),MATCH(1,(Price!$L$3:$AY$3=N$3)*(Price!$L$4:$AY$4=N$4),0))} -> 1435 | ... AJ73: {=INDEX(Price!$L$11:$AY$210,MATCH(1,(Price!$A$11:$A$210=$A73)*(Price!$B$11:$B$210=$B73)*(Price!$D$11:$D$210="gb"),0),MATCH(1,(Price!$L$3:$AY$3=AJ$3)*(Price!$L$4:$AY$4=AJ$4),0))} -> 1233
A74: 105194 | B74: 110000332 | C74: GB | D74: 5.2 | F74: Giá bán quy đổi EXW | G74: {=INDEX(Price!$L$11:$AY$210,MATCH(1,(Price!$A$11:$A$210=$A74)*(Price!$B$11:$B$210=$B74)*(Price!$D$11:$D$210="exw"),0),MATCH(1,(Price!$L$3:$AY$3=G$3)*(Price!$L$4:$AY$4=G$4),0))} -> 1340 | H74: {=INDEX(Price!$L$11:$AY$210,MATCH(1,(Price!$A$11:$A$210=$A74)*(Price!$B$11:$B$210=$B74)*(Price!$D$11:$D$210="exw"),0),MATCH(1,(Price!$L$3:$AY$3=H$3)*(Price!$L$4:$AY$4=H$4),0))} -> 1347.5 | I74: {=INDEX(Price!$L$11:$AY$210,MATCH(1,(Price!$A$11:$A$210=$A74)*(Price!$B$11:$B$210=$B74)*(Price!$D$11:$D$210="exw"),0),MATCH(1,(Price!$L$3:$AY$3=I$3)*(Price!$L$4:$AY$4=I$4),0))} -> 1360 | J74: {=INDEX(Price!$L$11:$AY$210,MATCH(1,(Price!$A$11:$A$210=$A74)*(Price!$B$11:$B$210=$B74)*(Price!$D$11:$D$210="exw"),0),MATCH(1,(Price!$L$3:$AY$3=J$3)*(Price!$L$4:$AY$4=J$4),0))} -> 1362.5 | K74: {=INDEX(Price!$L$11:$AY$210,MATCH(1,(Price!$A$11:$A$210=$A74)*(Price!$B$11:$B$210=$B74)*(Price!$D$11:$D$210="exw"),0),MATCH(1,(Price!$L$3:$AY$3=K$3)*(Price!$L$4:$AY$4=K$4),0))} -> 1366.5 | L74: {=INDEX(Price!$L$11:$AY$210,MATCH(1,(Price!$A$11:$A$210=$A74)*(Price!$B$11:$B$210=$B74)*(Price!$D$11:$D$210="exw"),0),MATCH(1,(Price!$L$3:$AY$3=L$3)*(Price!$L$4:$AY$4=L$4),0))} -> 1381.5 | M74: {=INDEX(Price!$L$11:$AY$210,MATCH(1,(Price!$A$11:$A$210=$A74)*(Price!$B$11:$B$210=$B74)*(Price!$D$11:$D$210="exw"),0),MATCH(1,(Price!$L$3:$AY$3=M$3)*(Price!$L$4:$AY$4=M$4),0))} -> 1397.5 | N74: {=INDEX(Price!$L$11:$AY$210,MATCH(1,(Price!$A$11:$A$210=$A74)*(Price!$B$11:$B$210=$B74)*(Price!$D$11:$D$210="exw"),0),MATCH(1,(Price!$L$3:$AY$3=N$3)*(Price!$L$4:$AY$4=N$4),0))} -> 1408.5 | ... AJ74: {=INDEX(Price!$L$11:$AY$210,MATCH(1,(Price!$A$11:$A$210=$A74)*(Price!$B$11:$B$210=$B74)*(Price!$D$11:$D$210="exw"),0),MATCH(1,(Price!$L$3:$AY$3=AJ$3)*(Price!$L$4:$AY$4=AJ$4),0))} -> 1128
A75: 105194 | B75: 110000332 | C75: PETVirgin | D75: 5.3 | F75: Giá chính phẩm | G75: {=SUMPRODUCT(General_Data*(Code_General_Data=$C75)*(Year=G$3)*(Month=G$4))} -> 930 | H75: {=SUMPRODUCT(General_Data*(Code_General_Data=$C75)*(Year=H$3)*(Month=H$4))} -> 943.33333 | I75: {=SUMPRODUCT(General_Data*(Code_General_Data=$C75)*(Year=I$3)*(Month=I$4))} -> 940 | J75: {=SUMPRODUCT(General_Data*(Code_General_Data=$C75)*(Year=J$3)*(Month=J$4))} -> 940 | K75: {=SUMPRODUCT(General_Data*(Code_General_Data=$C75)*(Year=K$3)*(Month=K$4))} -> 942 | L75: {=SUMPRODUCT(General_Data*(Code_General_Data=$C75)*(Year=L$3)*(Month=L$4))} -> 950 | M75: {=SUMPRODUCT(General_Data*(Code_General_Data=$C75)*(Year=M$3)*(Month=M$4))} -> 947.5 | N75: {=SUMPRODUCT(General_Data*(Code_General_Data=$C75)*(Year=N$3)*(Month=N$4))} -> 930 | ... AJ75: {=SUMPRODUCT(General_Data*(Code_General_Data=$C75)*(Year=AJ$3)*(Month=AJ$4))} -> 1190
A76: 105194 | B76: 110000332 | D76: 5.4 | F76: Chênh lệch giữa R sv Virgin | G76: =IF(G73*G74*G75<>0,G74-G75,0) -> 410 | H76: =IF(H73*H74*H75<>0,H74-H75,0) -> 404.16667 | I76: =IF(I73*I74*I75<>0,I74-I75,0) -> 420 | J76: =IF(J73*J74*J75<>0,J74-J75,0) -> 422.5 | K76: =IF(K73*K74*K75<>0,K74-K75,0) -> 424.5 | L76: =IF(L73*L74*L75<>0,L74-L75,0) -> 431.5 | M76: =IF(M73*M74*M75<>0,M74-M75,0) -> 450 | N76: =IF(N73*N74*N75<>0,N74-N75,0) -> 478.5 | ... AJ76: =IF(AJ73*AJ74*AJ75<>0,AJ74-AJ75,0) -> -62
A77: 105194 | B77: 110000332 | D77: 5.5 | F77: % +/- | G77: =IFERROR(G76/G75,0) -> 0.44086022 | H77: =IFERROR(H76/H75,0) -> 0.42844523 | I77: =IFERROR(I76/I75,0) -> 0.44680851 | J77: =IFERROR(J76/J75,0) -> 0.44946809 | K77: =IFERROR(K76/K75,0) -> 0.45063694 | L77: =IFERROR(L76/L75,0) -> 0.45421053 | M77: =IFERROR(M76/M75,0) -> 0.47493404 | N77: =IFERROR(N76/N75,0) -> 0.51451613 | ... AJ77: =IFERROR(AJ76/AJ75,0) -> -0.05210084
A78: 105194 | B78: 110000332 | C78: 110000332 | D78: 5.6 | F78: Giá duyệt tháng | G78: {=SUMPRODUCT(General_Data*(Code_General_Data=$C78)*(Year=G$3)*(Month=G$4))} -> 1340 | H78: {=SUMPRODUCT(General_Data*(Code_General_Data=$C78)*(Year=H$3)*(Month=H$4))} -> 1340 | I78: {=SUMPRODUCT(General_Data*(Code_General_Data=$C78)*(Year=I$3)*(Month=I$4))} -> 1340 | J78: {=SUMPRODUCT(General_Data*(Code_General_Data=$C78)*(Year=J$3)*(Month=J$4))} -> 1340 | K78: {=SUMPRODUCT(General_Data*(Code_General_Data=$C78)*(Year=K$3)*(Month=K$4))} -> 1390 | L78: {=SUMPRODUCT(General_Data*(Code_General_Data=$C78)*(Year=L$3)*(Month=L$4))} -> 1390 | M78: {=SUMPRODUCT(General_Data*(Code_General_Data=$C78)*(Year=M$3)*(Month=M$4))} -> 1390 | N78: {=SUMPRODUCT(General_Data*(Code_General_Data=$C78)*(Year=N$3)*(Month=N$4))} -> 1390 | ... AJ78: {=SUMPRODUCT(General_Data*(Code_General_Data=$C78)*(Year=AJ$3)*(Month=AJ$4))} -> 1440
A79: 105194
A80: 105194 | B80: 110000355 | F80: iSS01G
A81: 105194 | B81: 110000355 | D81: 5.7 | F81: Giá bán-DDP | G81: {=INDEX(Price!$L$11:$AY$210,MATCH(1,(Price!$A$11:$A$210=$A81)*(Price!$B$11:$B$210=$B81)*(Price!$D$11:$D$210="gb"),0),MATCH(1,(Price!$L$3:$AY$3=G$3)*(Price!$L$4:$AY$4=G$4),0))} -> 1346.5 | H81: {=INDEX(Price!$L$11:$AY$210,MATCH(1,(Price!$A$11:$A$210=$A81)*(Price!$B$11:$B$210=$B81)*(Price!$D$11:$D$210="gb"),0),MATCH(1,(Price!$L$3:$AY$3=H$3)*(Price!$L$4:$AY$4=H$4),0))} -> 1354 | I81: {=INDEX(Price!$L$11:$AY$210,MATCH(1,(Price!$A$11:$A$210=$A81)*(Price!$B$11:$B$210=$B81)*(Price!$D$11:$D$210="gb"),0),MATCH(1,(Price!$L$3:$AY$3=I$3)*(Price!$L$4:$AY$4=I$4),0))} -> 1366.5 | J81: {=INDEX(Price!$L$11:$AY$210,MATCH(1,(Price!$A$11:$A$210=$A81)*(Price!$B$11:$B$210=$B81)*(Price!$D$11:$D$210="gb"),0),MATCH(1,(Price!$L$3:$AY$3=J$3)*(Price!$L$4:$AY$4=J$4),0))} -> 1369 | K81: {=INDEX(Price!$L$11:$AY$210,MATCH(1,(Price!$A$11:$A$210=$A81)*(Price!$B$11:$B$210=$B81)*(Price!$D$11:$D$210="gb"),0),MATCH(1,(Price!$L$3:$AY$3=K$3)*(Price!$L$4:$AY$4=K$4),0))} -> 1373 | L81: {=INDEX(Price!$L$11:$AY$210,MATCH(1,(Price!$A$11:$A$210=$A81)*(Price!$B$11:$B$210=$B81)*(Price!$D$11:$D$210="gb"),0),MATCH(1,(Price!$L$3:$AY$3=L$3)*(Price!$L$4:$AY$4=L$4),0))} -> 1388 | M81: {=INDEX(Price!$L$11:$AY$210,MATCH(1,(Price!$A$11:$A$210=$A81)*(Price!$B$11:$B$210=$B81)*(Price!$D$11:$D$210="gb"),0),MATCH(1,(Price!$L$3:$AY$3=M$3)*(Price!$L$4:$AY$4=M$4),0))} -> 1404 | N81: {=INDEX(Price!$L$11:$AY$210,MATCH(1,(Price!$A$11:$A$210=$A81)*(Price!$B$11:$B$210=$B81)*(Price!$D$11:$D$210="gb"),0),MATCH(1,(Price!$L$3:$AY$3=N$3)*(Price!$L$4:$AY$4=N$4),0))} -> 1415 | ... AJ81: {=INDEX(Price!$L$11:$AY$210,MATCH(1,(Price!$A$11:$A$210=$A81)*(Price!$B$11:$B$210=$B81)*(Price!$D$11:$D$210="gb"),0),MATCH(1,(Price!$L$3:$AY$3=AJ$3)*(Price!$L$4:$AY$4=AJ$4),0))} -> 1233
A82: 105194 | B82: 110000355 | C82: GB | D82: 5.8 | F82: Giá bán quy đổi EXW | G82: {=INDEX(Price!$L$11:$AY$210,MATCH(1,(Price!$A$11:$A$210=$A82)*(Price!$B$11:$B$210=$B82)*(Price!$D$11:$D$210="exw"),0),MATCH(1,(Price!$L$3:$AY$3=G$3)*(Price!$L$4:$AY$4=G$4),0))} -> 1320 | H82: {=INDEX(Price!$L$11:$AY$210,MATCH(1,(Price!$A$11:$A$210=$A82)*(Price!$B$11:$B$210=$B82)*(Price!$D$11:$D$210="exw"),0),MATCH(1,(Price!$L$3:$AY$3=H$3)*(Price!$L$4:$AY$4=H$4),0))} -> 1327.5 | I82: {=INDEX(Price!$L$11:$AY$210,MATCH(1,(Price!$A$11:$A$210=$A82)*(Price!$B$11:$B$210=$B82)*(Price!$D$11:$D$210="exw"),0),MATCH(1,(Price!$L$3:$AY$3=I$3)*(Price!$L$4:$AY$4=I$4),0))} -> 1340 | J82: {=INDEX(Price!$L$11:$AY$210,MATCH(1,(Price!$A$11:$A$210=$A82)*(Price!$B$11:$B$210=$B82)*(Price!$D$11:$D$210="exw"),0),MATCH(1,(Price!$L$3:$AY$3=J$3)*(Price!$L$4:$AY$4=J$4),0))} -> 1342.5 | K82: {=INDEX(Price!$L$11:$AY$210,MATCH(1,(Price!$A$11:$A$210=$A82)*(Price!$B$11:$B$210=$B82)*(Price!$D$11:$D$210="exw"),0),MATCH(1,(Price!$L$3:$AY$3=K$3)*(Price!$L$4:$AY$4=K$4),0))} -> 1346.5 | L82: {=INDEX(Price!$L$11:$AY$210,MATCH(1,(Price!$A$11:$A$210=$A82)*(Price!$B$11:$B$210=$B82)*(Price!$D$11:$D$210="exw"),0),MATCH(1,(Price!$L$3:$AY$3=L$3)*(Price!$L$4:$AY$4=L$4),0))} -> 1361.5 | M82: {=INDEX(Price!$L$11:$AY$210,MATCH(1,(Price!$A$11:$A$210=$A82)*(Price!$B$11:$B$210=$B82)*(Price!$D$11:$D$210="exw"),0),MATCH(1,(Price!$L$3:$AY$3=M$3)*(Price!$L$4:$AY$4=M$4),0))} -> 1377.5 | N82: {=INDEX(Price!$L$11:$AY$210,MATCH(1,(Price!$A$11:$A$210=$A82)*(Price!$B$11:$B$210=$B82)*(Price!$D$11:$D$210="exw"),0),MATCH(1,(Price!$L$3:$AY$3=N$3)*(Price!$L$4:$AY$4=N$4),0))} -> 1388.5 | ... AJ82: {=INDEX(Price!$L$11:$AY$210,MATCH(1,(Price!$A$11:$A$210=$A82)*(Price!$B$11:$B$210=$B82)*(Price!$D$11:$D$210="exw"),0),MATCH(1,(Price!$L$3:$AY$3=AJ$3)*(Price!$L$4:$AY$4=AJ$4),0))} -> 1128
A83: 105194 | B83: 110000355 | C83: PETVirgin | D83: 5.9 | F83: Giá chính phẩm | G83: {=SUMPRODUCT(General_Data*(Code_General_Data=$C83)*(Year=G$3)*(Month=G$4))} -> 930 | H83: {=SUMPRODUCT(General_Data*(Code_General_Data=$C83)*(Year=H$3)*(Month=H$4))} -> 943.33333 | I83: {=SUMPRODUCT(General_Data*(Code_General_Data=$C83)*(Year=I$3)*(Month=I$4))} -> 940 | J83: {=SUMPRODUCT(General_Data*(Code_General_Data=$C83)*(Year=J$3)*(Month=J$4))} -> 940 | K83: {=SUMPRODUCT(General_Data*(Code_General_Data=$C83)*(Year=K$3)*(Month=K$4))} -> 942 | L83: {=SUMPRODUCT(General_Data*(Code_General_Data=$C83)*(Year=L$3)*(Month=L$4))} -> 950 | M83: {=SUMPRODUCT(General_Data*(Code_General_Data=$C83)*(Year=M$3)*(Month=M$4))} -> 947.5 | N83: {=SUMPRODUCT(General_Data*(Code_General_Data=$C83)*(Year=N$3)*(Month=N$4))} -> 930 | ... AJ83: {=SUMPRODUCT(General_Data*(Code_General_Data=$C83)*(Year=AJ$3)*(Month=AJ$4))} -> 1190
A84: 105194 | B84: 110000355 | D84: 5.1 | F84: Chênh lệch giữa R sv Virgin | G84: =IF(G81*G82*G83<>0,G82-G83,0) -> 390 | H84: =IF(H81*H82*H83<>0,H82-H83,0) -> 384.16667 | I84: =IF(I81*I82*I83<>0,I82-I83,0) -> 400 | J84: =IF(J81*J82*J83<>0,J82-J83,0) -> 402.5 | K84: =IF(K81*K82*K83<>0,K82-K83,0) -> 404.5 | L84: =IF(L81*L82*L83<>0,L82-L83,0) -> 411.5 | M84: =IF(M81*M82*M83<>0,M82-M83,0) -> 430 | N84: =IF(N81*N82*N83<>0,N82-N83,0) -> 458.5 | ... AJ84: =IF(AJ81*AJ82*AJ83<>0,AJ82-AJ83,0) -> -62
A85: 105194 | B85: 110000355 | D85: 5.11 | F85: % +/- | G85: =IFERROR(G84/G83,0) -> 0.41935484 | H85: =IFERROR(H84/H83,0) -> 0.40724382 | I85: =IFERROR(I84/I83,0) -> 0.42553191 | J85: =IFERROR(J84/J83,0) -> 0.42819149 | K85: =IFERROR(K84/K83,0) -> 0.42940552 | L85: =IFERROR(L84/L83,0) -> 0.43315789 | M85: =IFERROR(M84/M83,0) -> 0.45382586 | N85: =IFERROR(N84/N83,0) -> 0.49301075 | ... AJ85: =IFERROR(AJ84/AJ83,0) -> -0.05210084
A86: 105194 | B86: 110000355 | C86: 110000355 | D86: 5.12 | F86: Giá duyệt tháng | G86: {=SUMPRODUCT(General_Data*(Code_General_Data=$C86)*(Year=G$3)*(Month=G$4))} -> 1280 | H86: {=SUMPRODUCT(General_Data*(Code_General_Data=$C86)*(Year=H$3)*(Month=H$4))} -> 1280 | I86: {=SUMPRODUCT(General_Data*(Code_General_Data=$C86)*(Year=I$3)*(Month=I$4))} -> 1280 | J86: {=SUMPRODUCT(General_Data*(Code_General_Data=$C86)*(Year=J$3)*(Month=J$4))} -> 1280 | K86: {=SUMPRODUCT(General_Data*(Code_General_Data=$C86)*(Year=K$3)*(Month=K$4))} -> 1330 | L86: {=SUMPRODUCT(General_Data*(Code_General_Data=$C86)*(Year=L$3)*(Month=L$4))} -> 1330 | M86: {=SUMPRODUCT(General_Data*(Code_General_Data=$C86)*(Year=M$3)*(Month=M$4))} -> 1330 | N86: {=SUMPRODUCT(General_Data*(Code_General_Data=$C86)*(Year=N$3)*(Month=N$4))} -> 1330 | ... AJ86: {=SUMPRODUCT(General_Data*(Code_General_Data=$C86)*(Year=AJ$3)*(Month=AJ$4))} -> 1380
A88: 104909 | D88: 6 | E88: LAVIE VIET NAM
A89: 104909 | B89: 110000329 | F89: WSS01
A90: 104909 | B90: 110000329 | D90: 6.1 | F90: Giá bán-EXW | G90: {=INDEX(Price!$L$11:$AY$210,MATCH(1,(Price!$A$11:$A$210=$A90)*(Price!$B$11:$B$210=$B90)*(Price!$D$11:$D$210="gb"),0),MATCH(1,(Price!$L$3:$AY$3=G$3)*(Price!$L$4:$AY$4=G$4),0))} -> 1250 | H90: {=INDEX(Price!$L$11:$AY$210,MATCH(1,(Price!$A$11:$A$210=$A90)*(Price!$B$11:$B$210=$B90)*(Price!$D$11:$D$210="gb"),0),MATCH(1,(Price!$L$3:$AY$3=H$3)*(Price!$L$4:$AY$4=H$4),0))} -> 1250 | I90: {=INDEX(Price!$L$11:$AY$210,MATCH(1,(Price!$A$11:$A$210=$A90)*(Price!$B$11:$B$210=$B90)*(Price!$D$11:$D$210="gb"),0),MATCH(1,(Price!$L$3:$AY$3=I$3)*(Price!$L$4:$AY$4=I$4),0))} -> 1250 | J90: {=INDEX(Price!$L$11:$AY$210,MATCH(1,(Price!$A$11:$A$210=$A90)*(Price!$B$11:$B$210=$B90)*(Price!$D$11:$D$210="gb"),0),MATCH(1,(Price!$L$3:$AY$3=J$3)*(Price!$L$4:$AY$4=J$4),0))} -> 1250 | K90: {=INDEX(Price!$L$11:$AY$210,MATCH(1,(Price!$A$11:$A$210=$A90)*(Price!$B$11:$B$210=$B90)*(Price!$D$11:$D$210="gb"),0),MATCH(1,(Price!$L$3:$AY$3=K$3)*(Price!$L$4:$AY$4=K$4),0))} -> 1250 | L90: {=INDEX(Price!$L$11:$AY$210,MATCH(1,(Price!$A$11:$A$210=$A90)*(Price!$B$11:$B$210=$B90)*(Price!$D$11:$D$210="gb"),0),MATCH(1,(Price!$L$3:$AY$3=L$3)*(Price!$L$4:$AY$4=L$4),0))} -> 1250 | M90: {=INDEX(Price!$L$11:$AY$210,MATCH(1,(Price!$A$11:$A$210=$A90)*(Price!$B$11:$B$210=$B90)*(Price!$D$11:$D$210="gb"),0),MATCH(1,(Price!$L$3:$AY$3=M$3)*(Price!$L$4:$AY$4=M$4),0))} -> 1330 | N90: {=INDEX(Price!$L$11:$AY$210,MATCH(1,(Price!$A$11:$A$210=$A90)*(Price!$B$11:$B$210=$B90)*(Price!$D$11:$D$210="gb"),0),MATCH(1,(Price!$L$3:$AY$3=N$3)*(Price!$L$4:$AY$4=N$4),0))} -> 1330 | ... AJ90: {=INDEX(Price!$L$11:$AY$210,MATCH(1,(Price!$A$11:$A$210=$A90)*(Price!$B$11:$B$210=$B90)*(Price!$D$11:$D$210="gb"),0),MATCH(1,(Price!$L$3:$AY$3=AJ$3)*(Price!$L$4:$AY$4=AJ$4),0))} -> 1290
A91: 104909 | B91: 110000329 | C91: GB | D91: 6.2 | F91: Giá bán quy đổi EXW | G91: {=INDEX(Price!$L$11:$AY$210,MATCH(1,(Price!$A$11:$A$210=$A91)*(Price!$B$11:$B$210=$B91)*(Price!$D$11:$D$210="exw"),0),MATCH(1,(Price!$L$3:$AY$3=G$3)*(Price!$L$4:$AY$4=G$4),0))} -> 1250 | H91: {=INDEX(Price!$L$11:$AY$210,MATCH(1,(Price!$A$11:$A$210=$A91)*(Price!$B$11:$B$210=$B91)*(Price!$D$11:$D$210="exw"),0),MATCH(1,(Price!$L$3:$AY$3=H$3)*(Price!$L$4:$AY$4=H$4),0))} -> 1250 | I91: {=INDEX(Price!$L$11:$AY$210,MATCH(1,(Price!$A$11:$A$210=$A91)*(Price!$B$11:$B$210=$B91)*(Price!$D$11:$D$210="exw"),0),MATCH(1,(Price!$L$3:$AY$3=I$3)*(Price!$L$4:$AY$4=I$4),0))} -> 1250 | J91: {=INDEX(Price!$L$11:$AY$210,MATCH(1,(Price!$A$11:$A$210=$A91)*(Price!$B$11:$B$210=$B91)*(Price!$D$11:$D$210="exw"),0),MATCH(1,(Price!$L$3:$AY$3=J$3)*(Price!$L$4:$AY$4=J$4),0))} -> 1250 | K91: {=INDEX(Price!$L$11:$AY$210,MATCH(1,(Price!$A$11:$A$210=$A91)*(Price!$B$11:$B$210=$B91)*(Price!$D$11:$D$210="exw"),0),MATCH(1,(Price!$L$3:$AY$3=K$3)*(Price!$L$4:$AY$4=K$4),0))} -> 1250 | L91: {=INDEX(Price!$L$11:$AY$210,MATCH(1,(Price!$A$11:$A$210=$A91)*(Price!$B$11:$B$210=$B91)*(Price!$D$11:$D$210="exw"),0),MATCH(1,(Price!$L$3:$AY$3=L$3)*(Price!$L$4:$AY$4=L$4),0))} -> 1250 | M91: {=INDEX(Price!$L$11:$AY$210,MATCH(1,(Price!$A$11:$A$210=$A91)*(Price!$B$11:$B$210=$B91)*(Price!$D$11:$D$210="exw"),0),MATCH(1,(Price!$L$3:$AY$3=M$3)*(Price!$L$4:$AY$4=M$4),0))} -> 1330 | N91: {=INDEX(Price!$L$11:$AY$210,MATCH(1,(Price!$A$11:$A$210=$A91)*(Price!$B$11:$B$210=$B91)*(Price!$D$11:$D$210="exw"),0),MATCH(1,(Price!$L$3:$AY$3=N$3)*(Price!$L$4:$AY$4=N$4),0))} -> 1330 | ... AJ91: {=INDEX(Price!$L$11:$AY$210,MATCH(1,(Price!$A$11:$A$210=$A91)*(Price!$B$11:$B$210=$B91)*(Price!$D$11:$D$210="exw"),0),MATCH(1,(Price!$L$3:$AY$3=AJ$3)*(Price!$L$4:$AY$4=AJ$4),0))} -> 1290
A92: 104909 | B92: 110000329 | C92: PETVirgin | D92: 6.3 | F92: Giá chính phẩm | G92: {=SUMPRODUCT(General_Data*(Code_General_Data=$C92)*(Year=G$3)*(Month=G$4))} -> 930 | H92: {=SUMPRODUCT(General_Data*(Code_General_Data=$C92)*(Year=H$3)*(Month=H$4))} -> 943.33333 | I92: {=SUMPRODUCT(General_Data*(Code_General_Data=$C92)*(Year=I$3)*(Month=I$4))} -> 940 | J92: {=SUMPRODUCT(General_Data*(Code_General_Data=$C92)*(Year=J$3)*(Month=J$4))} -> 940 | K92: {=SUMPRODUCT(General_Data*(Code_General_Data=$C92)*(Year=K$3)*(Month=K$4))} -> 942 | L92: {=SUMPRODUCT(General_Data*(Code_General_Data=$C92)*(Year=L$3)*(Month=L$4))} -> 950 | M92: {=SUMPRODUCT(General_Data*(Code_General_Data=$C92)*(Year=M$3)*(Month=M$4))} -> 947.5 | N92: {=SUMPRODUCT(General_Data*(Code_General_Data=$C92)*(Year=N$3)*(Month=N$4))} -> 930 | ... AJ92: {=SUMPRODUCT(General_Data*(Code_General_Data=$C92)*(Year=AJ$3)*(Month=AJ$4))} -> 1190
A93: 104909 | B93: 110000329 | D93: 6.4 | F93: Chênh lệch giữa R sv Virgin | G93: =IF(G90*G91*G92<>0,G91-G92,0) -> 320 | H93: =IF(H90*H91*H92<>0,H91-H92,0) -> 306.66667 | I93: =IF(I90*I91*I92<>0,I91-I92,0) -> 310 | J93: =IF(J90*J91*J92<>0,J91-J92,0) -> 310 | K93: =IF(K90*K91*K92<>0,K91-K92,0) -> 308 | L93: =IF(L90*L91*L92<>0,L91-L92,0) -> 300 | M93: =IF(M90*M91*M92<>0,M91-M92,0) -> 382.5 | N93: =IF(N90*N91*N92<>0,N91-N92,0) -> 400 | ... AJ93: =IF(AJ90*AJ91*AJ92<>0,AJ91-AJ92,0) -> 100
A94: 104909 | B94: 110000329 | D94: 6.5 | F94: % +/- | G94: =IFERROR(G93/G92,0) -> 0.34408602 | H94: =IFERROR(H93/H92,0) -> 0.32508834 | I94: =IFERROR(I93/I92,0) -> 0.32978723 | J94: =IFERROR(J93/J92,0) -> 0.32978723 | K94: =IFERROR(K93/K92,0) -> 0.32696391 | L94: =IFERROR(L93/L92,0) -> 0.31578947 | M94: =IFERROR(M93/M92,0) -> 0.40369393 | N94: =IFERROR(N93/N92,0) -> 0.43010753 | ... AJ94: =IFERROR(AJ93/AJ92,0) -> 0.084033613
A95: 104909 | B95: 110000329 | C95: 110000329 | D95: 6.6 | F95: Giá duyệt tháng | G95: {=SUMPRODUCT(General_Data*(Code_General_Data=$C95)*(Year=G$3)*(Month=G$4))} -> 1250 | H95: {=SUMPRODUCT(General_Data*(Code_General_Data=$C95)*(Year=H$3)*(Month=H$4))} -> 1250 | I95: {=SUMPRODUCT(General_Data*(Code_General_Data=$C95)*(Year=I$3)*(Month=I$4))} -> 1250 | J95: {=SUMPRODUCT(General_Data*(Code_General_Data=$C95)*(Year=J$3)*(Month=J$4))} -> 1250 | K95: {=SUMPRODUCT(General_Data*(Code_General_Data=$C95)*(Year=K$3)*(Month=K$4))} -> 1300 | L95: {=SUMPRODUCT(General_Data*(Code_General_Data=$C95)*(Year=L$3)*(Month=L$4))} -> 1300 | M95: {=SUMPRODUCT(General_Data*(Code_General_Data=$C95)*(Year=M$3)*(Month=M$4))} -> 1300 | N95: {=SUMPRODUCT(General_Data*(Code_General_Data=$C95)*(Year=N$3)*(Month=N$4))} -> 1300 | ... AJ95: {=SUMPRODUCT(General_Data*(Code_General_Data=$C95)*(Year=AJ$3)*(Month=AJ$4))} -> 1350
A97: 102990 | D97: 7 | E97: COCA VIET NAM
A98: 102990 | B98: 110000332 | F98: iSS1084G
A99: 102990 | B99: 110000332 | D99: 7.1 | F99: Giá bán-DDP | G99: {=INDEX(Price!$L$11:$AY$210,MATCH(1,(Price!$A$11:$A$210=$A99)*(Price!$B$11:$B$210=$B99)*(Price!$D$11:$D$210="gb"),0),MATCH(1,(Price!$L$3:$AY$3=G$3)*(Price!$L$4:$AY$4=G$4),0))} -> 1325 | H99: {=INDEX(Price!$L$11:$AY$210,MATCH(1,(Price!$A$11:$A$210=$A99)*(Price!$B$11:$B$210=$B99)*(Price!$D$11:$D$210="gb"),0),MATCH(1,(Price!$L$3:$AY$3=H$3)*(Price!$L$4:$AY$4=H$4),0))} -> 1325 | I99: {=INDEX(Price!$L$11:$AY$210,MATCH(1,(Price!$A$11:$A$210=$A99)*(Price!$B$11:$B$210=$B99)*(Price!$D$11:$D$210="gb"),0),MATCH(1,(Price!$L$3:$AY$3=I$3)*(Price!$L$4:$AY$4=I$4),0))} -> 1325 | J99: {=INDEX(Price!$L$11:$AY$210,MATCH(1,(Price!$A$11:$A$210=$A99)*(Price!$B$11:$B$210=$B99)*(Price!$D$11:$D$210="gb"),0),MATCH(1,(Price!$L$3:$AY$3=J$3)*(Price!$L$4:$AY$4=J$4),0))} -> 1325 | K99: {=INDEX(Price!$L$11:$AY$210,MATCH(1,(Price!$A$11:$A$210=$A99)*(Price!$B$11:$B$210=$B99)*(Price!$D$11:$D$210="gb"),0),MATCH(1,(Price!$L$3:$AY$3=K$3)*(Price!$L$4:$AY$4=K$4),0))} -> 1325 | L99: {=INDEX(Price!$L$11:$AY$210,MATCH(1,(Price!$A$11:$A$210=$A99)*(Price!$B$11:$B$210=$B99)*(Price!$D$11:$D$210="gb"),0),MATCH(1,(Price!$L$3:$AY$3=L$3)*(Price!$L$4:$AY$4=L$4),0))} -> 1325 | M99: {=INDEX(Price!$L$11:$AY$210,MATCH(1,(Price!$A$11:$A$210=$A99)*(Price!$B$11:$B$210=$B99)*(Price!$D$11:$D$210="gb"),0),MATCH(1,(Price!$L$3:$AY$3=M$3)*(Price!$L$4:$AY$4=M$4),0))} -> 1325 | N99: {=INDEX(Price!$L$11:$AY$210,MATCH(1,(Price!$A$11:$A$210=$A99)*(Price!$B$11:$B$210=$B99)*(Price!$D$11:$D$210="gb"),0),MATCH(1,(Price!$L$3:$AY$3=N$3)*(Price!$L$4:$AY$4=N$4),0))} -> 1325 | ... AJ99: {=INDEX(Price!$L$11:$AY$210,MATCH(1,(Price!$A$11:$A$210=$A99)*(Price!$B$11:$B$210=$B99)*(Price!$D$11:$D$210="gb"),0),MATCH(1,(Price!$L$3:$AY$3=AJ$3)*(Price!$L$4:$AY$4=AJ$4),0))} -> 1280
A100: 102990 | B100: 110000332 | C100: GB | D100: 7.2 | F100: Giá bán quy đổi EXW | G100: {=INDEX(Price!$L$11:$AY$210,MATCH(1,(Price!$A$11:$A$210=$A100)*(Price!$B$11:$B$210=$B100)*(Price!$D$11:$D$210="exw"),0),MATCH(1,(Price!$L$3:$AY$3=G$3)*(Price!$L$4:$AY$4=G$4),0))} -> 1315 | H100: {=INDEX(Price!$L$11:$AY$210,MATCH(1,(Price!$A$11:$A$210=$A100)*(Price!$B$11:$B$210=$B100)*(Price!$D$11:$D$210="exw"),0),MATCH(1,(Price!$L$3:$AY$3=H$3)*(Price!$L$4:$AY$4=H$4),0))} -> 1315 | I100: {=INDEX(Price!$L$11:$AY$210,MATCH(1,(Price!$A$11:$A$210=$A100)*(Price!$B$11:$B$210=$B100)*(Price!$D$11:$D$210="exw"),0),MATCH(1,(Price!$L$3:$AY$3=I$3)*(Price!$L$4:$AY$4=I$4),0))} -> 1315 | J100: {=INDEX(Price!$L$11:$AY$210,MATCH(1,(Price!$A$11:$A$210=$A100)*(Price!$B$11:$B$210=$B100)*(Price!$D$11:$D$210="exw"),0),MATCH(1,(Price!$L$3:$AY$3=J$3)*(Price!$L$4:$AY$4=J$4),0))} -> 1315 | K100: {=INDEX(Price!$L$11:$AY$210,MATCH(1,(Price!$A$11:$A$210=$A100)*(Price!$B$11:$B$210=$B100)*(Price!$D$11:$D$210="exw"),0),MATCH(1,(Price!$L$3:$AY$3=K$3)*(Price!$L$4:$AY$4=K$4),0))} -> 1315 | L100: {=INDEX(Price!$L$11:$AY$210,MATCH(1,(Price!$A$11:$A$210=$A100)*(Price!$B$11:$B$210=$B100)*(Price!$D$11:$D$210="exw"),0),MATCH(1,(Price!$L$3:$AY$3=L$3)*(Price!$L$4:$AY$4=L$4),0))} -> 1315 | M100: {=INDEX(Price!$L$11:$AY$210,MATCH(1,(Price!$A$11:$A$210=$A100)*(Price!$B$11:$B$210=$B100)*(Price!$D$11:$D$210="exw"),0),MATCH(1,(Price!$L$3:$AY$3=M$3)*(Price!$L$4:$AY$4=M$4),0))} -> 1315 | N100: {=INDEX(Price!$L$11:$AY$210,MATCH(1,(Price!$A$11:$A$210=$A100)*(Price!$B$11:$B$210=$B100)*(Price!$D$11:$D$210="exw"),0),MATCH(1,(Price!$L$3:$AY$3=N$3)*(Price!$L$4:$AY$4=N$4),0))} -> 1315 | ... AJ100: {=INDEX(Price!$L$11:$AY$210,MATCH(1,(Price!$A$11:$A$210=$A100)*(Price!$B$11:$B$210=$B100)*(Price!$D$11:$D$210="exw"),0),MATCH(1,(Price!$L$3:$AY$3=AJ$3)*(Price!$L$4:$AY$4=AJ$4),0))} -> 1270
A101: 102990 | B101: 110000332 | C101: PETVirgin | D101: 7.3 | F101: Giá chính phẩm | G101: {=SUMPRODUCT(General_Data*(Code_General_Data=$C101)*(Year=G$3)*(Month=G$4))} -> 930 | H101: {=SUMPRODUCT(General_Data*(Code_General_Data=$C101)*(Year=H$3)*(Month=H$4))} -> 943.33333 | I101: {=SUMPRODUCT(General_Data*(Code_General_Data=$C101)*(Year=I$3)*(Month=I$4))} -> 940 | J101: {=SUMPRODUCT(General_Data*(Code_General_Data=$C101)*(Year=J$3)*(Month=J$4))} -> 940 | K101: {=SUMPRODUCT(General_Data*(Code_General_Data=$C101)*(Year=K$3)*(Month=K$4))} -> 942 | L101: {=SUMPRODUCT(General_Data*(Code_General_Data=$C101)*(Year=L$3)*(Month=L$4))} -> 950 | M101: {=SUMPRODUCT(General_Data*(Code_General_Data=$C101)*(Year=M$3)*(Month=M$4))} -> 947.5 | N101: {=SUMPRODUCT(General_Data*(Code_General_Data=$C101)*(Year=N$3)*(Month=N$4))} -> 930 | ... AJ101: {=SUMPRODUCT(General_Data*(Code_General_Data=$C101)*(Year=AJ$3)*(Month=AJ$4))} -> 1190
A102: 102990 | B102: 110000332 | D102: 7.4 | F102: Chênh lệch giữa R sv Virgin | G102: =IF(G99*G100*G101<>0,G100-G101,0) -> 385 | H102: =IF(H99*H100*H101<>0,H100-H101,0) -> 371.66667 | I102: =IF(I99*I100*I101<>0,I100-I101,0) -> 375 | J102: =IF(J99*J100*J101<>0,J100-J101,0) -> 375 | K102: =IF(K99*K100*K101<>0,K100-K101,0) -> 373 | L102: =IF(L99*L100*L101<>0,L100-L101,0) -> 365 | M102: =IF(M99*M100*M101<>0,M100-M101,0) -> 367.5 | N102: =IF(N99*N100*N101<>0,N100-N101,0) -> 385 | ... AJ102: =IF(AJ99*AJ100*AJ101<>0,AJ100-AJ101,0) -> 80
A103: 102990 | B103: 110000332 | D103: 7.5 | F103: % +/- | G103: =IFERROR(G102/G101,0) -> 0.41397849 | H103: =IFERROR(H102/H101,0) -> 0.39399293 | I103: =IFERROR(I102/I101,0) -> 0.39893617 | J103: =IFERROR(J102/J101,0) -> 0.39893617 | K103: =IFERROR(K102/K101,0) -> 0.39596603 | L103: =IFERROR(L102/L101,0) -> 0.38421053 | M103: =IFERROR(M102/M101,0) -> 0.3878628 | N103: =IFERROR(N102/N101,0) -> 0.41397849 | ... AJ103: =IFERROR(AJ102/AJ101,0) -> 0.067226891
A104: 102990 | B104: 110000332 | C104: 110000332 | D104: 7.6 | F104: Giá duyệt tháng | G104: {=SUMPRODUCT(General_Data*(Code_General_Data=$C104)*(Year=G$3)*(Month=G$4))} -> 1340 | H104: {=SUMPRODUCT(General_Data*(Code_General_Data=$C104)*(Year=H$3)*(Month=H$4))} -> 1340 | I104: {=SUMPRODUCT(General_Data*(Code_General_Data=$C104)*(Year=I$3)*(Month=I$4))} -> 1340 | J104: {=SUMPRODUCT(General_Data*(Code_General_Data=$C104)*(Year=J$3)*(Month=J$4))} -> 1340 | K104: {=SUMPRODUCT(General_Data*(Code_General_Data=$C104)*(Year=K$3)*(Month=K$4))} -> 1390 | L104: {=SUMPRODUCT(General_Data*(Code_General_Data=$C104)*(Year=L$3)*(Month=L$4))} -> 1390 | M104: {=SUMPRODUCT(General_Data*(Code_General_Data=$C104)*(Year=M$3)*(Month=M$4))} -> 1390 | N104: {=SUMPRODUCT(General_Data*(Code_General_Data=$C104)*(Year=N$3)*(Month=N$4))} -> 1390 | ... AJ104: {=SUMPRODUCT(General_Data*(Code_General_Data=$C104)*(Year=AJ$3)*(Month=AJ$4))} -> 1440
A106: 105217 | D106: 8 | E106: NESTLE VIET NAM
A107: 105217 | B107: 110000329 | F107: WSS01
A108: 105217 | B108: 110000329 | D108: 8.1 | F108: Giá bán-DDP | G108: {=INDEX(Price!$L$11:$AY$210,MATCH(1,(Price!$A$11:$A$210=$A108)*(Price!$B$11:$B$210=$B108)*(Price!$D$11:$D$210="gb"),0),MATCH(1,(Price!$L$3:$AY$3=G$3)*(Price!$L$4:$AY$4=G$4),0))} -> 0 | H108: {=INDEX(Price!$L$11:$AY$210,MATCH(1,(Price!$A$11:$A$210=$A108)*(Price!$B$11:$B$210=$B108)*(Price!$D$11:$D$210="gb"),0),MATCH(1,(Price!$L$3:$AY$3=H$3)*(Price!$L$4:$AY$4=H$4),0))} -> 0 | I108: {=INDEX(Price!$L$11:$AY$210,MATCH(1,(Price!$A$11:$A$210=$A108)*(Price!$B$11:$B$210=$B108)*(Price!$D$11:$D$210="gb"),0),MATCH(1,(Price!$L$3:$AY$3=I$3)*(Price!$L$4:$AY$4=I$4),0))} -> 0 | J108: {=INDEX(Price!$L$11:$AY$210,MATCH(1,(Price!$A$11:$A$210=$A108)*(Price!$B$11:$B$210=$B108)*(Price!$D$11:$D$210="gb"),0),MATCH(1,(Price!$L$3:$AY$3=J$3)*(Price!$L$4:$AY$4=J$4),0))} -> 0 | K108: {=INDEX(Price!$L$11:$AY$210,MATCH(1,(Price!$A$11:$A$210=$A108)*(Price!$B$11:$B$210=$B108)*(Price!$D$11:$D$210="gb"),0),MATCH(1,(Price!$L$3:$AY$3=K$3)*(Price!$L$4:$AY$4=K$4),0))} -> 0 | L108: {=INDEX(Price!$L$11:$AY$210,MATCH(1,(Price!$A$11:$A$210=$A108)*(Price!$B$11:$B$210=$B108)*(Price!$D$11:$D$210="gb"),0),MATCH(1,(Price!$L$3:$AY$3=L$3)*(Price!$L$4:$AY$4=L$4),0))} -> 0 | M108: {=INDEX(Price!$L$11:$AY$210,MATCH(1,(Price!$A$11:$A$210=$A108)*(Price!$B$11:$B$210=$B108)*(Price!$D$11:$D$210="gb"),0),MATCH(1,(Price!$L$3:$AY$3=M$3)*(Price!$L$4:$AY$4=M$4),0))} -> 0 | N108: {=INDEX(Price!$L$11:$AY$210,MATCH(1,(Price!$A$11:$A$210=$A108)*(Price!$B$11:$B$210=$B108)*(Price!$D$11:$D$210="gb"),0),MATCH(1,(Price!$L$3:$AY$3=N$3)*(Price!$L$4:$AY$4=N$4),0))} -> 0 | ... AD108: {=INDEX(Price!$L$11:$AY$210,MATCH(1,(Price!$A$11:$A$210=$A108)*(Price!$B$11:$B$210=$B108)*(Price!$D$11:$D$210="gb"),0),MATCH(1,(Price!$L$3:$AY$3=AD$3)*(Price!$L$4:$AY$4=AD$4),0))} -> 0
A109: 105217 | B109: 110000329 | C109: GB | D109: 8.2 | F109: Giá bán quy đổi EXW | G109: {=INDEX(Price!$L$11:$AY$210,MATCH(1,(Price!$A$11:$A$210=$A109)*(Price!$B$11:$B$210=$B109)*(Price!$D$11:$D$210="exw"),0),MATCH(1,(Price!$L$3:$AY$3=G$3)*(Price!$L$4:$AY$4=G$4),0))} -> 0 | H109: {=INDEX(Price!$L$11:$AY$210,MATCH(1,(Price!$A$11:$A$210=$A109)*(Price!$B$11:$B$210=$B109)*(Price!$D$11:$D$210="exw"),0),MATCH(1,(Price!$L$3:$AY$3=H$3)*(Price!$L$4:$AY$4=H$4),0))} -> 0 | I109: {=INDEX(Price!$L$11:$AY$210,MATCH(1,(Price!$A$11:$A$210=$A109)*(Price!$B$11:$B$210=$B109)*(Price!$D$11:$D$210="exw"),0),MATCH(1,(Price!$L$3:$AY$3=I$3)*(Price!$L$4:$AY$4=I$4),0))} -> 0 | J109: {=INDEX(Price!$L$11:$AY$210,MATCH(1,(Price!$A$11:$A$210=$A109)*(Price!$B$11:$B$210=$B109)*(Price!$D$11:$D$210="exw"),0),MATCH(1,(Price!$L$3:$AY$3=J$3)*(Price!$L$4:$AY$4=J$4),0))} -> 0 | K109: {=INDEX(Price!$L$11:$AY$210,MATCH(1,(Price!$A$11:$A$210=$A109)*(Price!$B$11:$B$210=$B109)*(Price!$D$11:$D$210="exw"),0),MATCH(1,(Price!$L$3:$AY$3=K$3)*(Price!$L$4:$AY$4=K$4),0))} -> 0 | L109: {=INDEX(Price!$L$11:$AY$210,MATCH(1,(Price!$A$11:$A$210=$A109)*(Price!$B$11:$B$210=$B109)*(Price!$D$11:$D$210="exw"),0),MATCH(1,(Price!$L$3:$AY$3=L$3)*(Price!$L$4:$AY$4=L$4),0))} -> 0 | M109: {=INDEX(Price!$L$11:$AY$210,MATCH(1,(Price!$A$11:$A$210=$A109)*(Price!$B$11:$B$210=$B109)*(Price!$D$11:$D$210="exw"),0),MATCH(1,(Price!$L$3:$AY$3=M$3)*(Price!$L$4:$AY$4=M$4),0))} -> 0 | N109: {=INDEX(Price!$L$11:$AY$210,MATCH(1,(Price!$A$11:$A$210=$A109)*(Price!$B$11:$B$210=$B109)*(Price!$D$11:$D$210="exw"),0),MATCH(1,(Price!$L$3:$AY$3=N$3)*(Price!$L$4:$AY$4=N$4),0))} -> 0 | ... AD109: {=INDEX(Price!$L$11:$AY$210,MATCH(1,(Price!$A$11:$A$210=$A109)*(Price!$B$11:$B$210=$B109)*(Price!$D$11:$D$210="exw"),0),MATCH(1,(Price!$L$3:$AY$3=AD$3)*(Price!$L$4:$AY$4=AD$4),0))} -> 0
A110: 105217 | B110: 110000329 | C110: PETVirgin | D110: 8.3 | F110: Giá chính phẩm | P110: {=SUMPRODUCT(General_Data*(Code_General_Data=$C110)*(Year=P$3)*(Month=P$4))} -> 862.5 | Q110: {=SUMPRODUCT(General_Data*(Code_General_Data=$C110)*(Year=Q$3)*(Month=Q$4))} -> 852 | R110: {=SUMPRODUCT(General_Data*(Code_General_Data=$C110)*(Year=R$3)*(Month=R$4))} -> 830 | S110: {=SUMPRODUCT(General_Data*(Code_General_Data=$C110)*(Year=S$3)*(Month=S$4))} -> 828 | T110: {=SUMPRODUCT(General_Data*(Code_General_Data=$C110)*(Year=T$3)*(Month=T$4))} -> 840 | U110: {=SUMPRODUCT(General_Data*(Code_General_Data=$C110)*(Year=U$3)*(Month=U$4))} -> 823 | V110: {=SUMPRODUCT(General_Data*(Code_General_Data=$C110)*(Year=V$3)*(Month=V$4))} -> 765 | W110: {=SUMPRODUCT(General_Data*(Code_General_Data=$C110)*(Year=W$3)*(Month=W$4))} -> 782 | ... AD110: {=SUMPRODUCT(General_Data*(Code_General_Data=$C110)*(Year=AD$3)*(Month=AD$4))} -> 772.5
...

Sheet Price
L1: =DATE(L3,L4,1) -> 45200 | M1: =DATE(M3,M4,1) -> 45231 | N1: =DATE(N3,N4,1) -> 45261 | O1: =DATE(O3,O4,1) -> 45292 | P1: =DATE(P3,P4,1) -> 45323 | Q1: =DATE(Q3,Q4,1) -> 45352 | R1: =DATE(R3,R4,1) -> 45383 | S1: =DATE(S3,S4,1) -> 45413 | ... AX1: =DATE(AX3,AX4,1) -> 46357
L2: =EOMONTH(L1,0) -> 45230 | M2: =EOMONTH(M1,0) -> 45260 | N2: =EOMONTH(N1,0) -> 45291 | O2: =EOMONTH(O1,0) -> 45322 | P2: =EOMONTH(P1,0) -> 45351 | Q2: =EOMONTH(Q1,0) -> 45382 | R2: =EOMONTH(R1,0) -> 45412 | S2: =EOMONTH(S1,0) -> 45443 | ... AX2: =EOMONTH(AX1,0) -> 46387
L3: 2023 | M3: 2023 | N3: 2023 | O3: 2024 | P3: 2024 | Q3: 2024 | R3: 2024 | S3: 2024 | T3: 2024 | U3: 2024 | V3: 2024 | W3: 2024 | X3: 2024 | Y3: 2024 | Z3: 2024 | AA3: 2025 | AB3: 2025 | AC3: 2025 | AD3: 2025 | AE3: 2025 | AF3: 2025 | AG3: 2025 | AH3: 2025 | AI3: 2025 | AJ3: 2025 | AK3: 2025 | AL3: 2025 | AM3: 2026 | AN3: 2026 | AO3: 2026 | AP3: 2026 | AQ3: 2026 | AR3: 2026 | AS3: 2026 | AT3: 2026 | AU3: 2026 | AV3: 2026 | AW3: 2026 | AX3: 2026
L4: 10 | M4: 11 | N4: 12 | O4: 1 | P4: 2 | Q4: 3 | R4: 4 | S4: 5 | T4: 6 | U4: 7 | V4: 8 | W4: 9 | X4: 10 | Y4: 11 | Z4: 12 | AA4: 1 | AB4: 2 | AC4: 3 | AD4: 4 | AE4: 5 | AF4: 6 | AG4: 7 | AH4: 8 | AI4: 9 | AJ4: 10 | AK4: 11 | AL4: 12 | AM4: 1 | AN4: 2 | AO4: 3 | AP4: 4 | AQ4: 5 | AR4: 6 | AS4: 7 | AT4: 8 | AU4: 9 | AV4: 10 | AW4: 11 | AX4: 12
O6: II. CHI TIẾT GIÁ CÔNG THỨC THEO KHÁCH HÀNG | AA6: II. CHI TIẾT GIÁ CÔNG THỨC THEO KHÁCH HÀNG | AM6: II. CHI TIẾT GIÁ CÔNG THỨC THEO KHÁCH HÀNG
F8: STT | G8: KHÁCH HÀNG/NỘI DUNG | L8: 2023 | O8: 2024 | AA8: 2025 | AM8: 2026
A9: Khách | B9: SKU | C9: Code | D9: Link | L9: 10 | M9: 11 | N9: 12 | O9: 1 | P9: 2 | Q9: 3 | R9: 4 | S9: 5 | T9: 6 | U9: 7 | V9: 8 | W9: 9 | X9: 10 | Y9: 11 | Z9: 12 | AA9: 1 | AB9: 2 | AC9: 3 | AD9: 4 | AE9: 5 | AF9: 6 | AG9: 7 | AH9: 8 | AI9: 9 | AJ9: 10 | AK9: 11 | AL9: 12 | AM9: 1 | AN9: 2 | AO9: 3 | AP9: 4 | AQ9: 5 | AR9: 6 | AS9: 7 | AT9: 8 | AU9: 9 | AV9: 10 | AW9: 11 | AX9: 12
A11: 200319 | F11: 1 | G11: NIAGARA
A12: 200319 | B12: 110000354 | D12: GB | F12: 1.1 | H12: GIÁ BÁN WSS01G (FOB) | O12: =MIN(MAX(SUM(O13:O14),O24),O23) -> 1200 | P12: =MIN(MAX(SUM(P13:P14),P24),P23) -> 1200 | Q12: =MIN(MAX(SUM(Q13:Q14),Q24),Q23) -> 1200 | R12: =MIN(MAX(SUM(R13:R14),R24),R23) -> 1200 | S12: =MIN(MAX(SUM(S13:S14),S24),S23) -> 1200 | T12: =MIN(MAX(SUM(T13:T14),T24),T23) -> 1200.9 | U12: =MIN(MAX(SUM(U13:U14),U24),U23) -> 1214.4 | V12: =MIN(MAX(SUM(V13:V14),V24),V23) -> 1226.1 | ... AC12: =MIN(MAX(SUM(AC13:AC14),AC24),AC23) -> 1238.875 | AD12: =MIN(MAX(SUM(AD13:AD14),AD24),AD23)-0.619999999998981 -> 1219.88 | AE12: =MIN(MAX(SUM(AE13:AE14),AE24),AE23) -> 1221 | AF12: =MIN(MAX(SUM(AF13:AF14),AF24),AF23) -> 1224 | AG12: =MIN(MAX(SUM(AG13:AG14),AG24),AG23) -> 1224 | AH12: =MIN(MAX(SUM(AH13:AH14),AH24),AH23) -> 1213.2 | AI12: =MIN(MAX(SUM(AI13:AI14),AI24),AI23) -> 1200 | AJ12: =MIN(MAX(SUM(AJ13:AJ14),AJ24),AJ23) -> 1200 | AK12: =MIN(MAX(SUM(AK13:AK14),AK24),AK23) -> 1200 | AL12: 1100 | AM12: =MIN(MAX(AM24,SUM(AM13:AM16)),AM23) -> 1080 | AN12: =MIN(MAX(AN24,SUM(AN13:AN16)),AN23) -> 1050 | AO12: =MIN(MAX(AO24,SUM(AO13:AO16)),AO23) -> 1061.25 | AP12: =MIN(MAX(AP24,SUM(AP13:AP16)),AP23) -> 1221 | AQ12: =MIN(MAX(AQ24,SUM(AQ13:AQ16)),AQ23) -> 1221 | AR12: =MIN(MAX(AR24,SUM(AR13:AR16)),AR23) -> 1221
A13: 200319 | B13: 110000354 | F13: 1.1.A | H13: [+] | I13: ICIS Bales - SEA trung bình 3 tháng trước | O13: =AVERAGE(L20:N20) -> 1296.0417 | P13: =AVERAGE(M20:O20) -> 1305 | Q13: =AVERAGE(N20:P20) -> 1313.3333 | R13: =AVERAGE(O20:Q20) -> 1320 | S13: =AVERAGE(P20:R20) -> 1326 | T13: =AVERAGE(Q20:S20) -> 1334.3333 | U13: =AVERAGE(R20:T20) -> 1349.3333 | V13: =AVERAGE(S20:U20) -> 1362.3333 | ... AK13: =AVERAGE(AH20:AJ20) -> 1271
A14: 200319 | B14: 110000354 | F14: 1.1.B | H14: [+] | I14: Chiết khấu (10%) | O14: =-O13*O21 -> -129.60417 | P14: =-P13*P21 -> -130.5 | Q14: =-Q13*Q21 -> -131.33333 | R14: =-R13*R21 -> -132 | S14: =-S13*S21 -> -132.6 | T14: =-T13*T21 -> -133.43333 | U14: =-U13*U21 -> -134.93333 | V14: =-V13*V21 -> -136.23333 | ... AK14: =-AK13*AK21 -> -127.1
F15: 1.1.C | H15: [+] | I15: Giá Báse (Áp dụng 2026) | AM15: 1080 | AN15: =AM12 -> 1080 | AO15: =AN12 -> 1050 | AP15: =AO12*1.1 -> 1167.375 | AQ15: =AP12 -> 1221 | AR15: =AQ12 -> 1221
F16: 1.1.D | H16: [+] | I16: Chênh lệch ICIS 2 tháng trước (Áp dụng 2026) | AN16: =AM20-AL20 -> -43.75 | AO16: =AN20-AM20 -> 11.25 | AP16: =AO20-AN20 -> 74.75 | AQ16: =AP20-AO20 -> 81.5 | AR16: =AQ20-AP20 -> 41.25
A17: 200319 | B17: 110000354 | D17: EXW | F17: 1.1.1 | I17: Giá bán quy đổi EXW | O17: =O12-O18-O19 -> 1162 | P17: =P12-P18-P19 -> 1162 | Q17: =Q12-Q18-Q19 -> 1162 | R17: =R12-R18-R19 -> 1162 | S17: =S12-S18-S19 -> 1162 | T17: =T12-T18-T19 -> 1162.8865 | U17: =U12-U18-U19 -> 1176.184 | V17: =V12-V18-V19 -> 1187.7085 | ... AR17: =AR12-AR18-AR19 -> 1182.685
A18: 200319 | B18: 110000354 | I18: Chi phí vận chuyển | O18: 20 | P18: 20 | Q18: 20 | R18: 20 | S18: 20 | T18: 20 | U18: 20 | V18: 20 | W18: 20 | X18: 20 | Y18: 20 | Z18: 20 | AA18: 20 | AB18: 20 | AC18: 20 | AD18: 22 | AE18: 22 | AF18: 22 | AG18: 22 | AH18: 20 | AI18: 20 | AJ18: 20 | AK18: 20 | AL18: 20 | AM18: 20 | AN18: 20 | AO18: 20 | AP18: 20 | AQ18: 20 | AR18: 20
A19: 200319 | B19: 110000354 | J19: Chi phí hoa hồng | O19: =O12*O22 -> 18 | P19: =P12*P22 -> 18 | Q19: =Q12*Q22 -> 18 | R19: =R12*R22 -> 18 | S19: =S12*S22 -> 18 | T19: =T12*T22 -> 18.0135 | U19: =U12*U22 -> 18.216 | V19: =V12*V22 -> 18.3915 | ... AR19: =AR12*AR22 -> 18.315
A20: 200319 | B20: 110000354 | C20: 04 | J20: ICIS Bales - SEA | L20: {=SUMPRODUCT(General_Data*(Year=L$3)*(Month=L$4)*(Code_General_Data=$C20))} -> 1288.125 | M20: {=SUMPRODUCT(General_Data*(Year=M$3)*(Month=M$4)*(Code_General_Data=$C20))} -> 1300 | N20: {=SUMPRODUCT(General_Data*(Year=N$3)*(Month=N$4)*(Code_General_Data=$C20))} -> 1300 | O20: {=SUMPRODUCT(General_Data*(Year=O$3)*(Month=O$4)*(Code_General_Data=$C20))} -> 1315 | P20: {=SUMPRODUCT(General_Data*(Year=P$3)*(Month=P$4)*(Code_General_Data=$C20))} -> 1325 | Q20: {=SUMPRODUCT(General_Data*(Year=Q$3)*(Month=Q$4)*(Code_General_Data=$C20))} -> 1320 | R20: {=SUMPRODUCT(General_Data*(Year=R$3)*(Month=R$4)*(Code_General_Data=$C20))} -> 1333 | S20: {=SUMPRODUCT(General_Data*(Year=S$3)*(Month=S$4)*(Code_General_Data=$C20))} -> 1350 | ... AR20: {=SUMPRODUCT(General_Data*(Year=AR$3)*(Month=AR$4)*(Code_General_Data=$C20))} -> 0
A21: 200319 | B21: 110000354 | J21: %Chiết khấu | O21: 0.1 | P21: 0.1 | Q21: 0.1 | R21: 0.1 | S21: 0.1 | T21: 0.1 | U21: 0.1 | V21: 0.1 | W21: 0.1 | X21: 0.1 | Y21: 0.1 | Z21: 0.1 | AA21: 0.1 | AB21: 0.1 | AC21: 0.1 | AD21: 0.1 | AE21: 0.1 | AF21: 0.1 | AG21: 0.1 | AH21: 0.1 | AI21: 0.1 | AJ21: 0.1 | AK21: 0.1 | AL21: 0.1 | AM21: N/A | AN21: N/A | AO21: N/A | AP21: N/A | AQ21: N/A | AR21: N/A
A22: 200319 | B22: 110000354 | J22: %Hoa hồng | O22: 0.015 | P22: 0.015 | Q22: 0.015 | R22: 0.015 | S22: 0.015 | T22: 0.015 | U22: 0.015 | V22: 0.015 | W22: 0.015 | X22: 0.015 | Y22: 0.015 | Z22: 0.015 | AA22: 0.015 | AB22: 0.015 | AC22: 0.015 | AD22: 0.015 | AE22: 0.015 | AF22: 0.015 | AG22: 0.015 | AH22: 0.015 | AI22: 0.015 | AJ22: 0.015 | AK22: 0.015 | AL22: 0.015 | AM22: 0.015 | AN22: 0.015 | AO22: 0.015 | AP22: 0.015 | AQ22: 0.015 | AR22: 0.015
A23: 200319 | B23: 110000354 | F23: 1.1.2 | J23: Giá trần | O23: {=INDEX(Note!$J$3:$J$102,MATCH(1,(Note!$A$3:$A$102=$A23)*(Note!$C$3:$C$102=$B23)*(Note!$E$3:$E$102<=O$1)*(Note!$F$3:$F$102>=O$2),0))} -> 1600 | P23: {=INDEX(Note!$J$3:$J$102,MATCH(1,(Note!$A$3:$A$102=$A23)*(Note!$C$3:$C$102=$B23)*(Note!$E$3:$E$102<=P$1)*(Note!$F$3:$F$102>=P$2),0))} -> 1600 | Q23: {=INDEX(Note!$J$3:$J$102,MATCH(1,(Note!$A$3:$A$102=$A23)*(Note!$C$3:$C$102=$B23)*(Note!$E$3:$E$102<=Q$1)*(Note!$F$3:$F$102>=Q$2),0))} -> 1600 | R23: {=INDEX(Note!$J$3:$J$102,MATCH(1,(Note!$A$3:$A$102=$A23)*(Note!$C$3:$C$102=$B23)*(Note!$E$3:$E$102<=R$1)*(Note!$F$3:$F$102>=R$2),0))} -> 1600 | S23: {=INDEX(Note!$J$3:$J$102,MATCH(1,(Note!$A$3:$A$102=$A23)*(Note!$C$3:$C$102=$B23)*(Note!$E$3:$E$102<=S$1)*(Note!$F$3:$F$102>=S$2),0))} -> 1600 | T23: {=INDEX(Note!$J$3:$J$102,MATCH(1,(Note!$A$3:$A$102=$A23)*(Note!$C$3:$C$102=$B23)*(Note!$E$3:$E$102<=T$1)*(Note!$F$3:$F$102>=T$2),0))} -> 1600 | U23: {=INDEX(Note!$J$3:$J$102,MATCH(1,(Note!$A$3:$A$102=$A23)*(Note!$C$3:$C$102=$B23)*(Note!$E$3:$E$102<=U$1)*(Note!$F$3:$F$102>=U$2),0))} -> 1600 | V23: {=INDEX(Note!$J$3:$J$102,MATCH(1,(Note!$A$3:$A$102=$A23)*(Note!$C$3:$C$102=$B23)*(Note!$E$3:$E$102<=V$1)*(Note!$F$3:$F$102>=V$2),0))} -> 1600 | ... AR23: {=INDEX(Note!$J$3:$J$102,MATCH(1,(Note!$A$3:$A$102=$A23)*(Note!$C$3:$C$102=$B23)*(Note!$E$3:$E$102<=AR$1)*(Note!$F$3:$F$102>=AR$2),0))} -> 1221
A24: 200319 | B24: 110000354 | F24: 1.1.3 | J24: Giá sàn | O24: {=INDEX(Note!$K$3:$K$102,MATCH(1,(Note!$A$3:$A$102=$A24)*(Note!$C$3:$C$102=$B24)*(Note!$E$3:$E$102<=O$1)*(Note!$F$3:$F$102>=O$2),0))} -> 1200 | P24: {=INDEX(Note!$K$3:$K$102,MATCH(1,(Note!$A$3:$A$102=$A24)*(Note!$C$3:$C$102=$B24)*(Note!$E$3:$E$102<=P$1)*(Note!$F$3:$F$102>=P$2),0))} -> 1200 | Q24: {=INDEX(Note!$K$3:$K$102,MATCH(1,(Note!$A$3:$A$102=$A24)*(Note!$C$3:$C$102=$B24)*(Note!$E$3:$E$102<=Q$1)*(Note!$F$3:$F$102>=Q$2),0))} -> 1200 | R24: {=INDEX(Note!$K$3:$K$102,MATCH(1,(Note!$A$3:$A$102=$A24)*(Note!$C$3:$C$102=$B24)*(Note!$E$3:$E$102<=R$1)*(Note!$F$3:$F$102>=R$2),0))} -> 1200 | S24: {=INDEX(Note!$K$3:$K$102,MATCH(1,(Note!$A$3:$A$102=$A24)*(Note!$C$3:$C$102=$B24)*(Note!$E$3:$E$102<=S$1)*(Note!$F$3:$F$102>=S$2),0))} -> 1200 | T24: {=INDEX(Note!$K$3:$K$102,MATCH(1,(Note!$A$3:$A$102=$A24)*(Note!$C$3:$C$102=$B24)*(Note!$E$3:$E$102<=T$1)*(Note!$F$3:$F$102>=T$2),0))} -> 1200 | U24: {=INDEX(Note!$K$3:$K$102,MATCH(1,(Note!$A$3:$A$102=$A24)*(Note!$C$3:$C$102=$B24)*(Note!$E$3:$E$102<=U$1)*(Note!$F$3:$F$102>=U$2),0))} -> 1200 | V24: {=INDEX(Note!$K$3:$K$102,MATCH(1,(Note!$A$3:$A$102=$A24)*(Note!$C$3:$C$102=$B24)*(Note!$E$3:$E$102<=V$1)*(Note!$F$3:$F$102>=V$2),0))} -> 1200 | ... AR24: {=INDEX(Note!$K$3:$K$102,MATCH(1,(Note!$A$3:$A$102=$A24)*(Note!$C$3:$C$102=$B24)*(Note!$E$3:$E$102<=AR$1)*(Note!$F$3:$F$102>=AR$2),0))} -> 1155
A25: 200319 | B25: 110000354 | F25: 1.1.4 | J25: Giá duyệt tháng | O25: {=SUMPRODUCT(General_Data*(Year=O$3)*(Month=O$4)*(Code_General_Data=$B25))} -> 1250 | P25: {=SUMPRODUCT(General_Data*(Year=P$3)*(Month=P$4)*(Code_General_Data=$B25))} -> 1250 | Q25: {=SUMPRODUCT(General_Data*(Year=Q$3)*(Month=Q$4)*(Code_General_Data=$B25))} -> 1250 | R25: {=SUMPRODUCT(General_Data*(Year=R$3)*(Month=R$4)*(Code_General_Data=$B25))} -> 1250 | S25: {=SUMPRODUCT(General_Data*(Year=S$3)*(Month=S$4)*(Code_General_Data=$B25))} -> 1300 | T25: {=SUMPRODUCT(General_Data*(Year=T$3)*(Month=T$4)*(Code_General_Data=$B25))} -> 1300 | U25: {=SUMPRODUCT(General_Data*(Year=U$3)*(Month=U$4)*(Code_General_Data=$B25))} -> 1300 | V25: {=SUMPRODUCT(General_Data*(Year=V$3)*(Month=V$4)*(Code_General_Data=$B25))} -> 1300 | ... AR25: {=SUMPRODUCT(General_Data*(Year=AR$3)*(Month=AR$4)*(Code_General_Data=$B25))} -> 1350
J26: Giá trần - quy đổi EXW | O26: =O23-O18-O19 -> 1562 | P26: =P23-P18-P19 -> 1562 | Q26: =Q23-Q18-Q19 -> 1562 | R26: =R23-R18-R19 -> 1562 | S26: =S23-S18-S19 -> 1562 | T26: =T23-T18-T19 -> 1561.9865 | U26: =U23-U18-U19 -> 1561.784 | V26: =V23-V18-V19 -> 1561.6085 | ... AK26: =AK23-AK18-AK19 -> 1562 | AM26: =AM23-AM18-AM19 -> 1073.8 | AN26: =AN23-AN18-AN19 -> 1074.25 | AO26: =AO23-AO18-AO19 -> 1074.0812 | AP26: =AP23-AP18-AP19 -> 1182.685 | AQ26: =AQ23-AQ18-AQ19 -> 1182.685 | AR26: =AR23-AR18-AR19 -> 1182.685
J27: Giá sàn - quy đổi EXW | O27: =O24-O18-O19 -> 1162 | P27: =P24-P18-P19 -> 1162 | Q27: =Q24-Q18-Q19 -> 1162 | R27: =R24-R18-R19 -> 1162 | S27: =S24-S18-S19 -> 1162 | T27: =T24-T18-T19 -> 1161.9865 | U27: =U24-U18-U19 -> 1161.784 | V27: =V24-V18-V19 -> 1161.6085 | ... AK27: =AK24-AK18-AK19 -> 1162 | AM27: =AM24-AM18-AM19 -> 1013.8 | AN27: =AN24-AN18-AN19 -> 1014.25 | AO27: =AO24-AO18-AO19 -> 1014.0812 | AP27: =AP24-AP18-AP19 -> 1116.685 | AQ27: =AQ24-AQ18-AQ19 -> 1116.685 | AR27: =AR24-AR18-AR19 -> 1116.685
A29: 200400 | F29: 2 | G29: SHEPLEY (NIAGARA NON-US)
A30: 200400 | B30: 110000354 | D30: GB | F30: 2.1 | H30: GIÁ BÁN WSS01G (FOB) | O30: =MIN(MAX(SUM(O31:O32),O42),O41) -> 1200 | P30: =MIN(MAX(SUM(P31:P32),P42),P41) -> 1200 | Q30: =MIN(MAX(SUM(Q31:Q32),Q42),Q41) -> 1200 | R30: =MIN(MAX(SUM(R31:R32),R42),R41) -> 1200 | S30: =MIN(MAX(SUM(S31:S32),S42),S41) -> 1200 | T30: =MIN(MAX(SUM(T31:T32),T42),T41) -> 1200.9 | U30: =MIN(MAX(SUM(U31:U32),U42),U41) -> 1214.4 | V30: =MIN(MAX(SUM(V31:V32),V42),V41) -> 1226.1 | ... AC30: =MIN(MAX(SUM(AC31:AC32),AC42),AC41) -> 1238.875 | AD30: =MIN(MAX(SUM(AD31:AD32),AD42),AD41)-0.619999999998981 -> 1219.88 | AE30: =MIN(MAX(SUM(AE31:AE32),AE42),AE41) -> 1221 | AF30: =MIN(MAX(SUM(AF31:AF32),AF42),AF41) -> 1224 | AG30: =MIN(MAX(SUM(AG31:AG32),AG42),AG41) -> 1224 | AH30: =MIN(MAX(SUM(AH31:AH32),AH42),AH41) -> 1213.2 | AI30: =MIN(MAX(SUM(AI31:AI32),AI42),AI41) -> 1200 | AJ30: =MIN(MAX(SUM(AJ31:AJ32),AJ42),AJ41) -> 1200 | AK30: =MIN(MAX(SUM(AK31:AK32),AK42),AK41) -> 1200 | AL30: 1100 | AM30: =MIN(MAX(AM42,SUM(AM31:AM34)),AM41) -> 1120 | AN30: =MIN(MAX(AN42,SUM(AN31:AN34)),AN41) -> 1090 | AO30: =MIN(MAX(AO42,SUM(AO31:AO34)),AO41) -> 1101.25 | AP30: =MIN(MAX(AP42,SUM(AP31:AP34)),AP41) -> 1150 | AQ30: =MIN(MAX(AQ42,SUM(AQ31:AQ34)),AQ41) -> 1150 | AR30: =MIN(MAX(AR42,SUM(AR31:AR34)),AR41) -> 1150
A31: 200400 | B31: 110000354 | F31: 2.1.A | H31: [+] | I31: ICIS Bales - SEA trung bình 3 tháng trước | O31: 1296.0417 | P31: 1305 | Q31: 1313.3333 | R31: 1320 | S31: 1326 | T31: 1334.3333 | U31: 1349.3333 | V31: 1362.3333 | W31: 1380.6667 | X31: 1401.5 | Y31: 1424.1667 | Z31: 1434.1667 | AA31: 1432.0833 | AB31: 1404.8611 | AC31: 1376.5278 | AD31: 1356.1111 | AE31: 1356.6667 | AF31: 1360 | AG31: 1360 | AH31: 1348 | AI31: 1326.3333 | AJ31: 1295.6667 | AK31: 1271
A32: 200400 | B32: 110000354 | F32: 2.1.B | H32: [+] | I32: Chiết khấu (10%) | O32: -129.60417 | P32: -130.5 | Q32: -131.33333 | R32: -132 | S32: -132.6 | T32: -133.43333 | U32: -134.93333 | V32: -136.23333 | W32: -138.06667 | X32: -140.15 | Y32: -142.41667 | Z32: -143.41667 | AA32: -143.20833 | AB32: -140.48611 | AC32: -137.65278 | AD32: -135.61111 | AE32: -135.66667 | AF32: -136 | AG32: -136 | AH32: -134.8 | AI32: -132.63333 | AJ32: -129.56667 | AK32: -127.1
A33: 200400 | F33: 2.1.C | H33: [+] | I33: Giá Báse (Áp dụng 2026) | AM33: 1120 | AN33: =AM30 -> 1120 | AO33: =AN30 -> 1090 | AP33: =AO30 -> 1101.25 | AQ33: =AP30 -> 1150 | AR33: =AQ30 -> 1150
A34: 200400 | F34: 2.1.D | H34: [+] | I34: Chênh lệch ICIS 2 tháng trước (Áp dụng 2026) | AN34: =AM38-AL38 -> -43.75 | AO34: =AN38-AM38 -> 11.25 | AP34: =AO38-AN38 -> 74.75 | AQ34: =AP38-AO38 -> 81.5 | AR34: =AQ38-AP38 -> 41.25
A35: 200400 | B35: 110000354 | D35: EXW | F35: 2.1.1 | I35: Giá bán quy đổi EXW | O35: =O30-O36-O37 -> 1162 | P35: =P30-P36-P37 -> 1162 | Q35: =Q30-Q36-Q37 -> 1162 | R35: =R30-R36-R37 -> 1162 | S35: =S30-S36-S37 -> 1162 | T35: =T30-T36-T37 -> 1162.8865 | U35: =U30-U36-U37 -> 1176.184 | V35: =V30-V36-V37 -> 1187.7085 | ... AR35: =AR30-AR36-AR37 -> 1112.75
A36: 200400 | B36: 110000354 | I36: Chi phí vận chuyển | O36: 20 | P36: 20 | Q36: 20 | R36: 20 | S36: 20 | T36: 20 | U36: 20 | V36: 20 | W36: 20 | X36: 20 | Y36: 20 | Z36: 20 | AA36: 20 | AB36: 20 | AC36: 20 | AD36: 22 | AE36: 22 | AF36: 22 | AG36: 22 | AH36: 20 | AI36: 20 | AJ36: 20 | AK36: 20 | AL36: 20 | AM36: 20 | AN36: 20 | AO36: 20 | AP36: 20 | AQ36: 20 | AR36: 20
A37: 200400 | B37: 110000354 | J37: Chi phí hoa hồng | O37: =O30*O40 -> 18 | P37: =P30*P40 -> 18 | Q37: =Q30*Q40 -> 18 | R37: =R30*R40 -> 18 | S37: =S30*S40 -> 18 | T37: =T30*T40 -> 18.0135 | U37: =U30*U40 -> 18.216 | V37: =V30*V40 -> 18.3915 | ... AR37: =AR30*AR40 -> 17.25
A38: 200400 | B38: 110000354 | C38: 04 | J38: ICIS Bales - SEA | L38: 1288.125 | M38: 1300 | N38: 1300 | O38: 1315 | P38: 1325 | Q38: 1320 | R38: 1333 | S38: 1350 | T38: 1365 | U38: 1372 | V38: 1405 | W38: 1427.5 | X38: 1440 | Y38: 1435 | Z38: 1421.25 | AA38: 1358.3333 | AB38: 1350 | AC38: 1360 | AD38: 1360 | AE38: 1360 | AF38: 1360 | AG38: 1324 | AH38: 1295 | AI38: 1268 | AJ38: 1250 | AK38: 1243.75 | AL38: 1193.75 | AM38: {=SUMPRODUCT(General_Data*(Year=AM$3)*(Month=AM$4)*(Code_General_Data=$C38))} -> 1150 | AN38: {=SUMPRODUCT(General_Data*(Year=AN$3)*(Month=AN$4)*(Code_General_Data=$C38))} -> 1161.25 | AO38: {=SUMPRODUCT(General_Data*(Year=AO$3)*(Month=AO$4)*(Code_General_Data=$C38))} -> 1236 | AP38: {=SUMPRODUCT(General_Data*(Year=AP$3)*(Month=AP$4)*(Code_General_Data=$C38))} -> 1317.5 | AQ38: {=SUMPRODUCT(General_Data*(Year=AQ$3)*(Month=AQ$4)*(Code_General_Data=$C38))} -> 1358.75 | AR38: {=SUMPRODUCT(General_Data*(Year=AR$3)*(Month=AR$4)*(Code_General_Data=$C38))} -> 0
A39: 200400 | B39: 110000354 | J39: %Chiết khấu | O39: 0.1 | P39: 0.1 | Q39: 0.1 | R39: 0.1 | S39: 0.1 | T39: 0.1 | U39: 0.1 | V39: 0.1 | W39: 0.1 | X39: 0.1 | Y39: 0.1 | Z39: 0.1 | AA39: 0.1 | AB39: 0.1 | AC39: 0.1 | AD39: 0.1 | AE39: 0.1 | AF39: 0.1 | AG39: 0.1 | AH39: 0.1 | AI39: 0.1 | AJ39: 0.1 | AK39: 0.1 | AL39: 0.1 | AM39: N/A | AN39: N/A | AO39: N/A | AP39: N/A | AQ39: N/A | AR39: N/A
A40: 200319 | B40: 110000354 | J40: %Hoa hồng | O40: 0.015 | P40: 0.015 | Q40: 0.015 | R40: 0.015 | S40: 0.015 | T40: 0.015 | U40: 0.015 | V40: 0.015 | W40: 0.015 | X40: 0.015 | Y40: 0.015 | Z40: 0.015 | AA40: 0.015 | AB40: 0.015 | AC40: 0.015 | AD40: 0.015 | AE40: 0.015 | AF40: 0.015 | AG40: 0.015 | AH40: 0.015 | AI40: 0.015 | AJ40: 0.015 | AK40: 0.015 | AL40: 0.015 | AM40: 0.015 | AN40: 0.015 | AO40: 0.015 | AP40: 0.015 | AQ40: 0.015 | AR40: 0.015
A41: 200400 | B41: 110000354 | F41: 2.1.2 | J41: Giá trần | O41: 1600 | P41: 1600 | Q41: 1600 | R41: 1600 | S41: 1600 | T41: 1600 | U41: 1600 | V41: 1600 | W41: 1600 | X41: 1600 | Y41: 1600 | Z41: 1600 | AA41: 1600 | AB41: 1600 | AC41: 1600 | AD41: 1600 | AE41: 1600 | AF41: 1600 | AG41: 1600 | AH41: 1600 | AI41: 1600 | AJ41: 1600 | AK41: 1600 | AM41: {=INDEX(Note!$J$3:$J$102,MATCH(1,(Note!$A$3:$A$102=$A41)*(Note!$C$3:$C$102=$B41)*(Note!$E$3:$E$102<=AM$1)*(Note!$F$3:$F$102>=AM$2),0))} -> 1150 | AN41: {=INDEX(Note!$J$3:$J$102,MATCH(1,(Note!$A$3:$A$102=$A41)*(Note!$C$3:$C$102=$B41)*(Note!$E$3:$E$102<=AN$1)*(Note!$F$3:$F$102>=AN$2),0))} -> 1150 | AO41: {=INDEX(Note!$J$3:$J$102,MATCH(1,(Note!$A$3:$A$102=$A41)*(Note!$C$3:$C$102=$B41)*(Note!$E$3:$E$102<=AO$1)*(Note!$F$3:$F$102>=AO$2),0))} -> 1150 | AP41: {=INDEX(Note!$J$3:$J$102,MATCH(1,(Note!$A$3:$A$102=$A41)*(Note!$C$3:$C$102=$B41)*(Note!$E$3:$E$102<=AP$1)*(Note!$F$3:$F$102>=AP$2),0))} -> 1150 | AQ41: {=INDEX(Note!$J$3:$J$102,MATCH(1,(Note!$A$3:$A$102=$A41)*(Note!$C$3:$C$102=$B41)*(Note!$E$3:$E$102<=AQ$1)*(Note!$F$3:$F$102>=AQ$2),0))} -> 1150 | AR41: {=INDEX(Note!$J$3:$J$102,MATCH(1,(Note!$A$3:$A$102=$A41)*(Note!$C$3:$C$102=$B41)*(Note!$E$3:$E$102<=AR$1)*(Note!$F$3:$F$102>=AR$2),0))} -> 1150
A42: 200400 | B42: 110000354 | F42: 2.1.3 | J42: Giá sàn | O42: 1200 | P42: 1200 | Q42: 1200 | R42: 1200 | S42: 1200 | T42: 1200 | U42: 1200 | V42: 1200 | W42: 1200 | X42: 1200 | Y42: 1200 | Z42: 1200 | AA42: 1200 | AB42: 1200 | AC42: 1200 | AD42: 1200 | AE42: 1200 | AF42: 1200 | AG42: 1200 | AH42: 1200 | AI42: 1200 | AJ42: 1200 | AK42: 1200 | AM42: {=INDEX(Note!$K$3:$K$102,MATCH(1,(Note!$A$3:$A$102=$A42)*(Note!$C$3:$C$102=$B42)*(Note!$E$3:$E$102<=AM$1)*(Note!$F$3:$F$102>=AM$2),0))} -> 1090 | AN42: {=INDEX(Note!$K$3:$K$102,MATCH(1,(Note!$A$3:$A$102=$A42)*(Note!$C$3:$C$102=$B42)*(Note!$E$3:$E$102<=AN$1)*(Note!$F$3:$F$102>=AN$2),0))} -> 1090 | AO42: {=INDEX(Note!$K$3:$K$102,MATCH(1,(Note!$A$3:$A$102=$A42)*(Note!$C$3:$C$102=$B42)*(Note!$E$3:$E$102<=AO$1)*(Note!$F$3:$F$102>=AO$2),0))} -> 1090 | AP42: {=INDEX(Note!$K$3:$K$102,MATCH(1,(Note!$A$3:$A$102=$A42)*(Note!$C$3:$C$102=$B42)*(Note!$E$3:$E$102<=AP$1)*(Note!$F$3:$F$102>=AP$2),0))} -> 1090 | AQ42: {=INDEX(Note!$K$3:$K$102,MATCH(1,(Note!$A$3:$A$102=$A42)*(Note!$C$3:$C$102=$B42)*(Note!$E$3:$E$102<=AQ$1)*(Note!$F$3:$F$102>=AQ$2),0))} -> 1090 | AR42: {=INDEX(Note!$K$3:$K$102,MATCH(1,(Note!$A$3:$A$102=$A42)*(Note!$C$3:$C$102=$B42)*(Note!$E$3:$E$102<=AR$1)*(Note!$F$3:$F$102>=AR$2),0))} -> 1090
A43: 200400 | B43: 110000354 | F43: 2.1.4 | J43: Giá duyệt tháng | O43: 1250 | P43: 1250 | Q43: 1250 | R43: 1250 | S43: 1300 | T43: 1300 | U43: 1300 | V43: 1300 | W43: 1310 | X43: 1325 | Y43: 1325 | Z43: 1275 | AA43: 1230 | AB43: 1230 | AC43: 1230 | AD43: 1250 | AE43: 1250 | AF43: 1250 | AG43: 1250 | AH43: 1220 | AI43: 1220 | AJ43: 1210 | AK43: 1200 | AL43: 1200 | AM43: {=SUMPRODUCT(General_Data*(Year=AM$3)*(Month=AM$4)*(Code_General_Data=$B43))} -> 1160 | AN43: {=SUMPRODUCT(General_Data*(Year=AN$3)*(Month=AN$4)*(Code_General_Data=$B43))} -> 1160 | AO43: {=SUMPRODUCT(General_Data*(Year=AO$3)*(Month=AO$4)*(Code_General_Data=$B43))} -> 1160 | AP43: {=SUMPRODUCT(General_Data*(Year=AP$3)*(Month=AP$4)*(Code_General_Data=$B43))} -> 1280 | AQ43: {=SUMPRODUCT(General_Data*(Year=AQ$3)*(Month=AQ$4)*(Code_General_Data=$B43))} -> 1380 | AR43: {=SUMPRODUCT(General_Data*(Year=AR$3)*(Month=AR$4)*(Code_General_Data=$B43))} -> 1350
J44: Giá trần - quy đổi EXW | O44: =O41-O36-O37 -> 1562 | P44: =P41-P36-P37 -> 1562 | Q44: =Q41-Q36-Q37 -> 1562 | R44: =R41-R36-R37 -> 1562 | S44: =S41-S36-S37 -> 1562 | T44: =T41-T36-T37 -> 1561.9865 | U44: =U41-U36-U37 -> 1561.784 | V44: =V41-V36-V37 -> 1561.6085 | ... AK44: =AK41-AK36-AK37 -> 1562 | AM44: =AM41-AM36-AM37 -> 1113.2 | AN44: =AN41-AN36-AN37 -> 1113.65 | AO44: =AO41-AO36-AO37 -> 1113.4813 | AP44: =AP41-AP36-AP37 -> 1112.75 | AQ44: =AQ41-AQ36-AQ37 -> 1112.75 | AR44: =AR41-AR36-AR37 -> 1112.75
J45: Giá sàn - quy đổi EXW | O45: =O42-O36-O37 -> 1162 | P45: =P42-P36-P37 -> 1162 | Q45: =Q42-Q36-Q37 -> 1162 | R45: =R42-R36-R37 -> 1162 | S45: =S42-S36-S37 -> 1162 | T45: =T42-T36-T37 -> 1161.9865 | U45: =U42-U36-U37 -> 1161.784 | V45: =V42-V36-V37 -> 1161.6085 | ... AK45: =AK42-AK36-AK37 -> 1162 | AM45: =AM42-AM36-AM37 -> 1053.2 | AN45: =AN42-AN36-AN37 -> 1053.65 | AO45: =AO42-AO36-AO37 -> 1053.4813 | AP45: =AP42-AP36-AP37 -> 1052.75 | AQ45: =AQ42-AQ36-AQ37 -> 1052.75 | AR45: =AR42-AR36-AR37 -> 1052.75
A47: 200332 | F47: 3 | G47: OUTEIRINHO
A48: 200332 | B48: 110000355 | D48: GB | F48: 3.1 | H48: GIÁ BÁN iSS01G (FOB) | AA48: 1250 | AB48: 1250 | AC48: 1250 | AD48: 1250 | AE48: 1250 | AF48: 1250 | AG48: 1250 | AH48: 1250 | AI48: 1250 | AJ48: 1250 | AK48: 1250 | AL48: 1250
A49: 200332 | B49: 110000355 | D49: EXW | F49: 3.1.1 | I49: Giá bán quy đổi EXW | AA49: =AA48-AA50 -> 1230 | AB49: =AB48-AB50 -> 1230 | AC49: =AC48-AC50 -> 1230 | AD49: =AD48-AD50 -> 1228 | AE49: =AE48-AE50 -> 1228 | AF49: =AF48-AF50 -> 1228 | AG49: =AG48-AG50 -> 1228 | AH49: =AH48-AH50 -> 1230 | ... AL49: =AL48-AL50 -> 1230
A50: 200332 | B50: 110000355 | F50: 3.1.2 | I50: Chi phí vận chuyển | AA50: 20 | AB50: 20 | AC50: 20 | AD50: 22 | AE50: 22 | AF50: 22 | AG50: 22 | AH50: 20 | AI50: 20 | AJ50: 20 | AK50: 20 | AL50: 20
A51: 200332 | B51: 110000355 | F51: 3.1.3 | J51: Giá duyệt tháng | AA51: {=SUMPRODUCT(General_Data*(Year=AA$3)*(Month=AA$4)*(Code_General_Data=$B51))} -> 1260 | AB51: {=SUMPRODUCT(General_Data*(Year=AB$3)*(Month=AB$4)*(Code_General_Data=$B51))} -> 1260 | AC51: {=SUMPRODUCT(General_Data*(Year=AC$3)*(Month=AC$4)*(Code_General_Data=$B51))} -> 1260 | AD51: {=SUMPRODUCT(General_Data*(Year=AD$3)*(Month=AD$4)*(Code_General_Data=$B51))} -> 1280 | AE51: {=SUMPRODUCT(General_Data*(Year=AE$3)*(Month=AE$4)*(Code_General_Data=$B51))} -> 1280 | AF51: {=SUMPRODUCT(General_Data*(Year=AF$3)*(Month=AF$4)*(Code_General_Data=$B51))} -> 1280 | AG51: {=SUMPRODUCT(General_Data*(Year=AG$3)*(Month=AG$4)*(Code_General_Data=$B51))} -> 1280 | AH51: {=SUMPRODUCT(General_Data*(Year=AH$3)*(Month=AH$4)*(Code_General_Data=$B51))} -> 1250 | ... AL51: {=SUMPRODUCT(General_Data*(Year=AL$3)*(Month=AL$4)*(Code_General_Data=$B51))} -> 1230
A53: 105263 | F53: 4 | G53: UNILEVER VIỆT NAM
A54: 105263 | B54: 110000354 | D54: GB | F54: 4.1 | H54: GIÁ BÁN WSS01G (DDP) | O54: =ROUND(SUM(O55:O60),-2)+O61 -> 1320 | P54: =ROUND(SUM(P55:P60),-2)+P61 -> 1320 | Q54: =ROUND(SUM(Q55:Q60),-2)+Q61 -> 1320 | R54: =ROUND(SUM(R55:R60),-2)+R61 -> 1320 | S54: =ROUND(SUM(S55:S60),-2)+S61 -> 1320 | T54: =ROUND(SUM(T55:T60),-2)+T61 -> 1320 | U54: =ROUND(SUM(U55:U60),-2)+U61 -> 1320 | V54: =ROUND(SUM(V55:V60),-2)+V61 -> 1320 | W54: =ROUND(SUM(W55:W60),-2)+W61 -> 1320 | X54: =ROUND(SUM(X55:X60),-1)+X61 -> 1300 | Y54: =ROUND(SUM(Y55:Y60),-1)+Y61 -> 1300 | Z54: =ROUND(SUM(Z55:Z60),-1)+Z61 -> 1300 | AA54: =ROUND(SUM(AA55:AA60),-1)+AA61 -> 1300 | AB54: =ROUND(SUM(AB55:AB60),-1)+AB61 -> 1300 | AC54: =ROUND(SUM(AC55:AC60),-1)+AC61 -> 1300 | AD54: =ROUND(SUM(AD55:AD60),-1)+AD61 -> 1250 | AE54: =ROUND(SUM(AE55:AE60),-1)+AE61 -> 1250 | ... AL54: =ROUND(SUM(AL55:AL60),-1)+AL61 -> 1280 | AM54: 1250 | AN54: 1250 | AO54: 1250 | AP54: 1191 | AQ54: =AP54 -> 1191 | AR54: =AQ54 -> 1191 | AS54: =AR54 -> 1191 | AT54: =AS54 -> 1191 | AU54: =AT54 -> 1191 | AV54: =AU54 -> 1191 | AW54: =AV54 -> 1191 | AX54: =AW54 -> 1191
A55: 105263 | B55: 110000354 | F55: 4.1.A | H55: [+] | I55: Bales DTR | O55: =16500/O$62*10^3 -> 673.46939 | P55: =16500/P$62*10^3 -> 673.46939 | Q55: =16500/Q$62*10^3 -> 673.46939 | R55: =16500/R$62*10^3 -> 673.46939 | S55: =16500/S$62*10^3 -> 673.46939 | T55: =16500/T$62*10^3 -> 673.46939 | U55: =16500/U$62*10^3 -> 660 | V55: =16500/V$62*10^3 -> 660 | ... AC55: =16500/AC$62*10^3 -> 660 | AD55: =16800/AD$62*10^3 -> 672 | AE55: =16800/AE$62*10^3 -> 672 | AF55: =16800/AF$62*10^3 -> 672 | AG55: =16800/AG$62*10^3 -> 672 | AH55: =16800/AH$62*10^3 -> 672 | AI55: =16800/AI$62*10^3 -> 672 | AJ55: =16800/AJ$62*10^3 -> 672 | AK55: =16800/AK$62*10^3 -> 672 | AL55: =16800/AL$62*10^3 -> 672
A56: 105263 | B56: 110000354 | F56: 4.1.B | H56: [+] | I56: Hao hụt (30%) | O56: =O55*O63 -> 202.04082 | P56: =P55*P63 -> 202.04082 | Q56: =Q55*Q63 -> 202.04082 | R56: =R55*R63 -> 202.04082 | S56: =S55*S63 -> 202.04082 | T56: =T55*T63 -> 202.04082 | U56: =U55*U63 -> 198 | V56: =V55*V63 -> 198 | ... AL56: =AL55*AL63 -> 201.6
A57: 105263 | B57: 110000354 | F57: 4.1.C | H57: [+] | I57: Conversion cost | O57: =9193.7/O62*10^3 -> 375.25306 | P57: =9193.7/P62*10^3 -> 375.25306 | Q57: =9193.7/Q62*10^3 -> 375.25306 | R57: =9193.7/R62*10^3 -> 375.25306 | S57: =9193.7/S62*10^3 -> 375.25306 | T57: =9193.7/T62*10^3 -> 375.25306 | U57: =9193.7/U62*10^3 -> 367.748 | V57: =9193.7/V62*10^3 -> 367.748 | ... AC57: =9193.7/AC62*10^3 -> 367.748 | AD57: =9377.55821/AD62*10^3 -> 375.10233 | AE57: =9377.55821/AE62*10^3 -> 375.10233 | AF57: =9377.55821/AF62*10^3 -> 375.10233 | AG57: =9377.55821/AG62*10^3 -> 375.10233 | AH57: =9377.55821/AH62*10^3 -> 375.10233 | AI57: =9377.55821/AI62*10^3 -> 375.10233 | AJ57: =9377.55821/AJ62*10^3 -> 375.10233 | AK57: =9377.55821/AK62*10^3 -> 375.10233 | AL57: =9377.55821/AL62*10^3 -> 375.10233
A58: 105263 | B58: 110000354 | F58: 4.1.D | H58: [+] | I58: Chi phí vận chuyển | O58: =299/O62*10^3 -> 12.204082 | P58: =299/P62*10^3 -> 12.204082 | Q58: =299/Q62*10^3 -> 12.204082 | R58: =299/R62*10^3 -> 12.204082 | S58: =299/S62*10^3 -> 12.204082 | T58: =299/T62*10^3 -> 12.204082 | U58: =299/U62*10^3 -> 11.96 | V58: =299/V62*10^3 -> 11.96 | ... AL58: =299/AL62*10^3 -> 11.96
A59: 105263 | B59: 110000354 | F59: 4.1.E | H59: [+] | I59: Lợi nhuận trước thuế (EBT) | O59: =3295/O62*10^3 -> 134.4898 | P59: =3295/P62*10^3 -> 134.4898 | Q59: =3295/Q62*10^3 -> 134.4898 | R59: =3295/R62*10^3 -> 134.4898 | S59: =3295/S62*10^3 -> 134.4898 | T59: =3295/T62*10^3 -> 134.4898 | U59: =3295/U62*10^3 -> 131.8 | V59: =3295/V62*10^3 -> 131.8 | ... AL59: =3295/AL62*10^3 -> 131.8
A60: 105263 | B60: 110000354 | F60: 4.1.F | H60: [+] | I60: Interest (lãi vay) | O60: =8%/12*SUM(O55:O59) -> 9.316381 | P60: =8%/12*SUM(P55:P59) -> 9.316381 | Q60: =8%/12*SUM(Q55:Q59) -> 9.316381 | R60: =8%/12*SUM(R55:R59) -> 9.316381 | S60: =8%/12*SUM(S55:S59) -> 9.316381 | T60: =8%/12*SUM(T55:T59) -> 9.316381 | U60: =8%/12*SUM(U55:U59) -> 9.1300533 | V60: =8%/12*SUM(V55:V59) -> 9.1300533 | ... AL60: =8%/12*SUM(AL55:AL59) -> 9.2830822
A61: 105263 | B61: 110000354 | F61: 4.1.G | H61: [+] | I61: Chiết khấu | O61: -80 | P61: -80 | Q61: -80 | R61: -80 | S61: -80 | T61: -80 | U61: -80 | V61: -80 | W61: -80 | X61: -80 | Y61: -80 | Z61: -80 | AA61: -80 | AB61: -80 | AC61: -80 | AD61: -150 | AE61: -150 | AF61: -150 | AG61: -120 | AH61: -120 | AI61: -120 | AJ61: -120 | AK61: -120 | AL61: -120
A62: 105263 | B62: 110000354 | J62: Exchange rate | O62: 24500 | P62: 24500 | Q62: 24500 | R62: 24500 | S62: 24500 | T62: 24500 | U62: 25000 | V62: 25000 | W62: 25000 | X62: 25000 | Y62: 25000 | Z62: 25000 | AA62: 25000 | AB62: 25000 | AC62: 25000 | AD62: 25000 | AE62: 25000 | AF62: 25000 | AG62: 25000 | AH62: 25000 | AI62: 25000 | AJ62: 25000 | AK62: 25000 | AL62: 25000
A63: 105263 | B63: 110000354 | J63: %Hao hụt | O63: 0.3 | P63: 0.3 | Q63: 0.3 | R63: 0.3 | S63: 0.3 | T63: 0.3 | U63: 0.3 | V63: 0.3 | W63: 0.3 | X63: 0.3 | Y63: 0.3 | Z63: 0.3 | AA63: 0.3 | AB63: 0.3 | AC63: 0.3 | AD63: 0.3 | AE63: 0.3 | AF63: 0.3 | AG63: 0.3 | AH63: 0.3 | AI63: 0.3 | AJ63: 0.3 | AK63: 0.3 | AL63: 0.3
A64: 105263 | B64: 110000354 | D64: EXW | F64: 4.1.1 | I64: Giá bán quy đổi EXW | O64: =O54-O58 -> 1307.7959 | P64: =P54-P58 -> 1307.7959 | Q64: =Q54-Q58 -> 1307.7959 | R64: =R54-R58 -> 1307.7959 | S64: =S54-S58 -> 1307.7959 | T64: =T54-T58 -> 1307.7959 | U64: =U54-U58 -> 1308.04 | V64: =V54-V58 -> 1308.04 | ... AL64: =AL54-AL58 -> 1268.04 | AM64: =AM54-AM65 -> 1245 | AN64: =AN54-AN65 -> 1245 | AO64: =AO54-AO65 -> 1245 | AP64: =AP54-AP65 -> 1185 | AQ64: =AQ54-AQ65 -> 1185 | AR64: =AR54-AR65 -> 1185 | AS64: =AS54-AS65 -> 1185 | AT64: =AT54-AT65 -> 1185 | ... AX64: =AX54-AX65 -> 1185
F65: 4.1.2 | I65: Chi phí vận chuyển | AM65: 5 | AN65: 5 | AO65: 5 | AP65: 6 | AQ65: 6 | AR65: 6 | AS65: 6 | AT65: 6 | AU65: 6 | AV65: 6 | AW65: 6 | AX65: 6
A66: 105263 | B66: 110000354 | F66: 4.1.3 | J66: Giá duyệt tháng | O66: {=SUMPRODUCT(General_Data*(Year=O$3)*(Month=O$4)*(Code_General_Data=$B66))} -> 1250 | P66: {=SUMPRODUCT(General_Data*(Year=P$3)*(Month=P$4)*(Code_General_Data=$B66))} -> 1250 | Q66: {=SUMPRODUCT(General_Data*(Year=Q$3)*(Month=Q$4)*(Code_General_Data=$B66))} -> 1250 | R66: {=SUMPRODUCT(General_Data*(Year=R$3)*(Month=R$4)*(Code_General_Data=$B66))} -> 1250 | S66: {=SUMPRODUCT(General_Data*(Year=S$3)*(Month=S$4)*(Code_General_Data=$B66))} -> 1300 | T66: {=SUMPRODUCT(General_Data*(Year=T$3)*(Month=T$4)*(Code_General_Data=$B66))} -> 1300 | U66: {=SUMPRODUCT(General_Data*(Year=U$3)*(Month=U$4)*(Code_General_Data=$B66))} -> 1300 | V66: {=SUMPRODUCT(General_Data*(Year=V$3)*(Month=V$4)*(Code_General_Data=$B66))} -> 1300 | ... AR66: {=SUMPRODUCT(General_Data*(Year=AR$3)*(Month=AR$4)*(Code_General_Data=$B66))} -> 1350
A68: 105263 | B68: 110000339 | D68: GB | F68: 4.2 | H68: GIÁ BÁN MBF01 (DDP) | O68: =ROUND(SUM(O69:O75),-1) -> 1500 | P68: =ROUND(SUM(P69:P75),-1) -> 1500 | Q68: =ROUND(SUM(Q69:Q75),-1) -> 1500 | R68: =ROUND(SUM(R69:R75),-1) -> 1430 | S68: =ROUND(SUM(S69:S75),-1) -> 1430 | T68: =ROUND(SUM(T69:T75),-1) -> 1430 | U68: =ROUND(SUM(U69:U75),-1) -> 1430 | V68: =ROUND(SUM(V69:V75),-1) -> 1430 | ... AL68: =ROUND(SUM(AL69:AL75),-1) -> 1380 | AM68: 1330 | AN68: 1330 | AO68: 1330 | AP68: 1272 | AQ68: 1272 | AR68: 1272 | AS68: 1272 | AT68: 1272 | AU68: 1272 | AV68: 1272 | AW68: 1272 | AX68: 1272
A69: 105263 | B69: 110000339 | F69: 4.2.A | H69: [+] | I69: Bales DTR | O69: =22500/O76*10^3 -> 918.36735 | P69: =22500/P76*10^3 -> 918.36735 | Q69: =22500/Q76*10^3 -> 918.36735 | R69: =21000/R76*10^3 -> 857.14286 | S69: =21000/S76*10^3 -> 857.14286 | T69: =21000/T76*10^3 -> 857.14286 | U69: =21000/U76*10^3 -> 840 | V69: =21000/V76*10^3 -> 840 | W69: =21000/W76*10^3 -> 840 | X69: =21000/X76*10^3 -> 840 | Y69: =21000/Y76*10^3 -> 840 | ... AC69: =21000/AC76*10^3 -> 840 | AD69: =(21500*75%+24500*25%)/AD76*10^3 -> 890 | AE69: =(21500*75%+24500*25%)/AE76*10^3 -> 890 | AF69: =(21500*75%+24500*25%)/AF76*10^3 -> 890 | AG69: =21000/AG76*10^3 -> 840 | AH69: =21000/AH76*10^3 -> 840 | AI69: =21000/AI76*10^3 -> 840 | AJ69: =21000/AJ76*10^3 -> 840 | AK69: =21000/AK76*10^3 -> 840 | AL69: =21000/AL76*10^3 -> 840
A70: 105263 | B70: 110000339 | F70: 4.2.B | H70: [+] | I70: Hao hụt (21.27%) | O70: =O69*O77 -> 195.33673 | P70: =P69*P77 -> 195.33673 | Q70: =Q69*Q77 -> 195.33673 | R70: =R69*R77 -> 182.31429 | S70: =S69*S77 -> 182.31429 | T70: =T69*T77 -> 182.31429 | U70: =U69*U77 -> 178.668 | V70: =V69*V77 -> 178.668 | ... AL70: =AL69*AL77 -> 178.668
A71: 105263 | B71: 110000339 | F71: 4.2.C | H71: [+] | I71: Conversion cost | O71: =8720.586/O76*10^3 -> 355.94229 | P71: =8720.586/P76*10^3 -> 355.94229 | Q71: =8720.586/Q76*10^3 -> 355.94229 | R71: =8720.586/R76*10^3 -> 355.94229 | S71: =8720.586/S76*10^3 -> 355.94229 | T71: =8720.586/T76*10^3 -> 355.94229 | U71: =8720.586/U76*10^3 -> 348.82344 | V71: =8720.586/V76*10^3 -> 348.82344 | ... AC71: =8720.586/AC76*10^3 -> 348.82344 | AD71: =9127.69249949/AD76*10^3 -> 365.1077 | AE71: =9127.69249949/AE76*10^3 -> 365.1077 | AF71: =9127.69249949/AF76*10^3 -> 365.1077 | AG71: =8720.586/AG76*10^3 -> 348.82344 | AH71: =8720.586/AH76*10^3 -> 348.82344 | AI71: =8720.586/AI76*10^3 -> 348.82344 | AJ71: =8720.586/AJ76*10^3 -> 348.82344 | AK71: =8720.586/AK76*10^3 -> 348.82344 | AL71: =8720.586/AL76*10^3 -> 348.82344
A72: 105263 | B72: 110000339 | F72: 4.2.D | H72: [+] | I72: Chi phí vận chuyển | O72: =299/O76*10^3 -> 12.204082 | P72: =299/P76*10^3 -> 12.204082 | Q72: =299/Q76*10^3 -> 12.204082 | R72: =299/R76*10^3 -> 12.204082 | S72: =299/S76*10^3 -> 12.204082 | T72: =299/T76*10^3 -> 12.204082 | U72: =299/U76*10^3 -> 11.96 | V72: =299/V76*10^3 -> 11.96 | ... AL72: =299/AL76*10^3 -> 11.96
A73: 105263 | B73: 110000339 | F73: 4.2.E | H73: [+] | I73: Lợi nhuận trước thuế (EBT) | O73: =1248/O76*10^3 -> 50.938776 | P73: =1248/P76*10^3 -> 50.938776 | Q73: =1248/Q76*10^3 -> 50.938776 | R73: =1248/R76*10^3 -> 50.938776 | S73: =1248/S76*10^3 -> 50.938776 | T73: =1248/T76*10^3 -> 50.938776 | U73: =1248/U76*10^3 -> 49.92 | V73: =1248/V76*10^3 -> 49.92 | ... AL73: =1248/AL76*10^3 -> 49.92
A74: 105263 | B74: 110000339 | F74: 4.2.F | H74: [+] | I74: Interest (lãi vay) | O74: =8%*SUM(O69:O73)*2/12 -> 20.43719 | P74: =8%*SUM(P69:P73)*2/12 -> 20.43719 | Q74: =8%*SUM(Q69:Q73)*2/12 -> 20.43719 | R74: =8%*SUM(R69:R73)*2/12 -> 19.44723 | S74: =8%*SUM(S69:S73)*2/12 -> 19.44723 | T74: =8%*SUM(T69:T73)*2/12 -> 19.44723 | U74: =8%*SUM(U69:U73)*2/12 -> 19.058286 | V74: =8%*SUM(V69:V73)*2/12 -> 19.058286 | ... AL74: =8%*SUM(AL69:AL73)*2/12 -> 19.058286
A75: 105263 | B75: 110000339 | F75: 4.2.G | H75: [+] | I75: Chiết khấu | O75: -50 | P75: -50 | Q75: -50 | R75: -50 | S75: -50 | T75: -50 | U75: -20 | V75: -20 | W75: -20 | X75: -20 | Y75: -20 | Z75: -20 | AA75: -50 | AB75: -50 | AC75: -50 | AD75: -180 | AE75: -180 | AF75: -180 | AG75: -70 | AH75: -70 | AI75: -70 | AJ75: -70 | AK75: -70 | AL75: -70
A76: 105263 | B76: 110000339 | J76: Exchange rate | O76: 24500 | P76: 24500 | Q76: 24500 | R76: 24500 | S76: 24500 | T76: 24500 | U76: 25000 | V76: 25000 | W76: 25000 | X76: 25000 | Y76: 25000 | Z76: 25000 | AA76: 25000 | AB76: 25000 | AC76: 25000 | AD76: 25000 | AE76: 25000 | AF76: 25000 | AG76: 25000 | AH76: 25000 | AI76: 25000 | AJ76: 25000 | AK76: 25000 | AL76: 25000
A77: 105263 | B77: 110000339 | J77: %Hao hụt | O77: 0.2127 | P77: 0.2127 | Q77: 0.2127 | R77: 0.2127 | S77: 0.2127 | T77: 0.2127 | U77: 0.2127 | V77: 0.2127 | W77: 0.2127 | X77: 0.2127 | Y77: 0.2127 | Z77: 0.2127 | AA77: 0.2127 | AB77: 0.2127 | AC77: 0.2127 | AD77: 0.2127 | AE77: 0.2127 | AF77: 0.2127 | AG77: 0.2127 | AH77: 0.2127 | AI77: 0.2127 | AJ77: 0.2127 | AK77: 0.2127 | AL77: 0.2127
A78: 105263 | B78: 110000339 | D78: EXW | F78: 4.2.1 | I78: Giá bán quy đổi EXW | O78: =O68-O72 -> 1487.7959 | P78: =P68-P72 -> 1487.7959 | Q78: =Q68-Q72 -> 1487.7959 | R78: =R68-R72 -> 1417.7959 | S78: =S68-S72 -> 1417.7959 | T78: =T68-T72 -> 1417.7959 | U78: =U68-U72 -> 1418.04 | V78: =V68-V72 -> 1418.04 | ... AL78: =AL68-AL72 -> 1368.04 | AM78: =AM68-AM79 -> 1325 | AN78: =AN68-AN79 -> 1325 | AO78: =AO68-AO79 -> 1325 | AP78: =AP68-AP79 -> 1266 | AQ78: =AQ68-AQ79 -> 1266 | AR78: =AR68-AR79 -> 1266 | AS78: =AS68-AS79 -> 1266 | AT78: =AT68-AT79 -> 1266 | ... AX78: =AX68-AX79 -> 1266
F79: 4.2.2 | I79: Chi phí vận chuyển (Miền Nam) | AM79: 5 | AN79: 5 | AO79: 5 | AP79: 6 | AQ79: 6 | AR79: 6 | AS79: 6 | AT79: 6 | AU79: 6 | AV79: 6 | AW79: 6 | AX79: 6
A80: 105263 | B80: 110000339 | F80: 4.2.3 | J80: Giá duyệt tháng | O80: {=SUMPRODUCT(General_Data*(Year=O$3)*(Month=O$4)*(Code_General_Data=$B80))} -> 1350 | P80: {=SUMPRODUCT(General_Data*(Year=P$3)*(Month=P$4)*(Code_General_Data=$B80))} -> 1350 | Q80: {=SUMPRODUCT(General_Data*(Year=Q$3)*(Month=Q$4)*(Code_General_Data=$B80))} -> 1350 | R80: {=SUMPRODUCT(General_Data*(Year=R$3)*(Month=R$4)*(Code_General_Data=$B80))} -> 1350 | S80: {=SUMPRODUCT(General_Data*(Year=S$3)*(Month=S$4)*(Code_General_Data=$B80))} -> 1350 | T80: {=SUMPRODUCT(General_Data*(Year=T$3)*(Month=T$4)*(Code_General_Data=$B80))} -> 1350 | U80: {=SUMPRODUCT(General_Data*(Year=U$3)*(Month=U$4)*(Code_General_Data=$B80))} -> 1350 | V80: {=SUMPRODUCT(General_Data*(Year=V$3)*(Month=V$4)*(Code_General_Data=$B80))} -> 1350 | ... AR80: {=SUMPRODUCT(General_Data*(Year=AR$3)*(Month=AR$4)*(Code_General_Data=$B80))} -> 1350
A82: 105263 | B82: 110000481 | D82: GB | F82: 4.3 | H82: GIÁ BÁN PCF01 (DDP) | AA82: =AA83 -> 1400 | AB82: =AB83 -> 1400 | AC82: =AC83 -> 1400 | AD82: =AD83 -> 1350 | AE82: =AE83 -> 1350 | AF82: =AF83 -> 1350 | AG82: =AG83 -> 1380 | AH82: =AH83 -> 1380 | ... AX82: =AX83 -> 1272
A83: 105263 | B83: 110000481 | F83: 4.3.A | H83: [+] | I83: Giá bán MBF01 | AA83: =AA68 -> 1400 | AB83: =AB68 -> 1400 | AC83: =AC68 -> 1400 | AD83: =AD68 -> 1350 | AE83: =AE68 -> 1350 | AF83: =AF68 -> 1350 | AG83: =AG68 -> 1380 | AH83: =AH68 -> 1380 | ... AX83: =AX68 -> 1272
A84: 105263 | B84: 110000481 | D84: EXW | F84: 4.3.1 | I84: Giá bán quy đổi EXW | AA84: =AA78 -> 1388.04 | AB84: =AB78 -> 1388.04 | AC84: =AC78 -> 1388.04 | AD84: =AD78 -> 1338.04 | AE84: =AE78 -> 1338.04 | AF84: =AF78 -> 1338.04 | AG84: =AG78 -> 1368.04 | AH84: =AH78 -> 1368.04 | ... AX84: =AX78 -> 1266
A85: 105263 | B85: 110000481 | F85: 4.3.2 | J85: Giá duyệt tháng | AA85: {=SUMPRODUCT(General_Data*(Year=AA$3)*(Month=AA$4)*(Code_General_Data=$B85))} -> 1400 | AB85: {=SUMPRODUCT(General_Data*(Year=AB$3)*(Month=AB$4)*(Code_General_Data=$B85))} -> 1400 | AC85: {=SUMPRODUCT(General_Data*(Year=AC$3)*(Month=AC$4)*(Code_General_Data=$B85))} -> 1350 | AD85: {=SUMPRODUCT(General_Data*(Year=AD$3)*(Month=AD$4)*(Code_General_Data=$B85))} -> 1350 | AE85: {=SUMPRODUCT(General_Data*(Year=AE$3)*(Month=AE$4)*(Code_General_Data=$B85))} -> 1350 | AF85: {=SUMPRODUCT(General_Data*(Year=AF$3)*(Month=AF$4)*(Code_General_Data=$B85))} -> 1350 | AG85: {=SUMPRODUCT(General_Data*(Year=AG$3)*(Month=AG$4)*(Code_General_Data=$B85))} -> 1350 | AH85: {=SUMPRODUCT(General_Data*(Year=AH$3)*(Month=AH$4)*(Code_General_Data=$B85))} -> 1330 | ... AR85: {=SUMPRODUCT(General_Data*(Year=AR$3)*(Month=AR$4)*(Code_General_Data=$B85))} -> 1450
A87: 105263 | B87: RHDPETHOI-MAU | D87: GB | F87: 4.4 | H87: GIÁ BÁN rHDPE thổi màu-khử mùi (DDP) | O87: =ROUND(SUM(O88:O89),-1) -> 1450 | P87: =ROUND(SUM(P88:P89),-1) -> 1450 | Q87: =ROUND(SUM(Q88:Q89),-1) -> 1450 | R87: =ROUND(SUM(R88:R89),-1) -> 1380 | S87: =ROUND(SUM(S88:S89),-1) -> 1380 | T87: =ROUND(SUM(T88:T89),-1) -> 1380 | U87: =ROUND(SUM(U88:U89),-1) -> 1380 | V87: =ROUND(SUM(V88:V89),-1) -> 1380 | ... AL87: =ROUND(SUM(AL88:AL89),-1) -> 1330 | AM87: =SUM(AM88:AM89) -> 1280 | AN87: =SUM(AN88:AN89) -> 1280 | AO87: =SUM(AO88:AO89) -> 1280
A88: 105263 | B88: RHDPETHOI-MAU | F88: 4.4.A | H88: [+] | I88: Giá PCF01/MBF01 | O88: =O68 -> 1500 | P88: =P68 -> 1500 | Q88: =Q68 -> 1500 | R88: =R68 -> 1430 | S88: =S68 -> 1430 | T88: =T68 -> 1430 | U88: =U68 -> 1430 | V88: =V68 -> 1430 | ... Z88: =Z68 -> 1430 | AA88: =AA82 -> 1400 | AB88: =AB82 -> 1400 | AC88: =AC82 -> 1400 | AD88: =AD82 -> 1350 | AE88: =AE82 -> 1350 | AF88: =AF82 -> 1350 | AG88: =AG82 -> 1380 | AH88: =AH82 -> 1380 | ... AO88: =AO82 -> 1330
A89: 105263 | B89: RHDPETHOI-MAU | F89: 4.4.B | H89: [+] | I89: Chiết khấu | O89: -50 | P89: -50 | Q89: -50 | R89: -50 | S89: -50 | T89: -50 | U89: -50 | V89: -50 | W89: -50 | X89: -50 | Y89: -50 | Z89: -50 | AA89: -50 | AB89: -50 | AC89: -50 | AD89: -50 | AE89: -50 | AF89: -50 | AG89: -50 | AH89: -50 | AI89: -50 | AJ89: -50 | AK89: -50 | AL89: -50 | AM89: -50 | AN89: -50 | AO89: -50
A90: 105263 | B90: RHDPETHOI-MAU | D90: EXW | F90: 4.4.1 | I90: Giá bán quy đổi EXW | O90: =O87-O72 -> 1437.7959 | P90: =P87-P72 -> 1437.7959 | Q90: =Q87-Q72 -> 1437.7959 | R90: =R87-R72 -> 1367.7959 | S90: =S87-S72 -> 1367.7959 | T90: =T87-T72 -> 1367.7959 | U90: =U87-U72 -> 1368.04 | V90: =V87-V72 -> 1368.04 | ... AL90: =AL87-AL72 -> 1318.04 | AM90: =AM87-AM79 -> 1275 | AN90: =AN87-AN79 -> 1275 | AO90: =AO87-AO79 -> 1275
A91: 105263 | B91: RHDPETHOI-MAU | F91: 4.4.2 | J91: Giá duyệt tháng | O91: {=SUMPRODUCT(General_Data*(Year=O$3)*(Month=O$4)*(Code_General_Data=$B91))} -> 1350 | P91: {=SUMPRODUCT(General_Data*(Year=P$3)*(Month=P$4)*(Code_General_Data=$B91))} -> 1350 | Q91: {=SUMPRODUCT(General_Data*(Year=Q$3)*(Month=Q$4)*(Code_General_Data=$B91))} -> 1350 | R91: {=SUMPRODUCT(General_Data*(Year=R$3)*(Month=R$4)*(Code_General_Data=$B91))} -> 1350 | S91: {=SUMPRODUCT(General_Data*(Year=S$3)*(Month=S$4)*(Code_General_Data=$B91))} -> 1350 | T91: {=SUMPRODUCT(General_Data*(Year=T$3)*(Month=T$4)*(Code_General_Data=$B91))} -> 1350 | U91: {=SUMPRODUCT(General_Data*(Year=U$3)*(Month=U$4)*(Code_General_Data=$B91))} -> 1350 | V91: {=SUMPRODUCT(General_Data*(Year=V$3)*(Month=V$4)*(Code_General_Data=$B91))} -> 1350 | ... AO91: {=SUMPRODUCT(General_Data*(Year=AO$3)*(Month=AO$4)*(Code_General_Data=$B91))} -> 1250
A93: 105194 | F93: 5 | G93: SUNTORY VIỆT NAM
A94: 105194 | B94: 110000332 | D94: GB | F94: 5.1 | H94: GIÁ BÁN iSS1084G (DDP) | O94: =SUM(O95:O98) -> 1366.5 | P94: =SUM(P95:P98) -> 1374 | Q94: =SUM(Q95:Q98) -> 1386.5 | R94: =SUM(R95:R98) -> 1389 | S94: =SUM(S95:S98) -> 1393 | T94: =SUM(T95:T98) -> 1408 | U94: =SUM(U95:U98) -> 1424 | V94: =SUM(V95:V98) -> 1435 | ... Z94: =SUM(Z95:Z98) -> 1504 | AA94: =MIN(MAX(SUM(AA95,AA96),AA104),AA103)+AA97+AA98 -> 1452.9031 | AB94: =MIN(MAX(SUM(AB95,AB96),AB104),AB103)+AB97+AB98 -> 1415.1448 | AC94: =MIN(MAX(SUM(AC95,AC96),AC104),AC103)+AC97+AC98 -> 1380.0542 | AD94: =MIN(MAX(SUM(AD95,AD96),AD104),AD103)+AD97+AD98 -> 1380.875 | AE94: =MIN(MAX(SUM(AE95,AE96),AE104),AE103)+AE97+AE98 -> 1385.8 | AF94: =MIN(MAX(SUM(AF95,AF96),AF104),AF103)+AF97+AF98 -> 1385.8 | AG94: =MIN(MAX(SUM(AG95,AG96),AG104),AG103)+AG97+AG98 -> 1385.8 | AH94: =MIN(MAX(SUM(AH95,AH96),AH104),AH103)+AH97+AH98 -> 1368.07 | ... AL94: =MIN(MAX(SUM(AL95,AL96),AL104),AL103)+AL97+AL98 -> 1337.4969 | AM94: 1225 | AN94: 1225 | AO94: 1225 | AP94: =1225+8 -> 1233 | AQ94: =1225+8 -> 1233 | AR94: =1225+8 -> 1233 | AS94: =1225+8 -> 1233 | AT94: =1225+8 -> 1233 | AU94: =1225+8 -> 1233 | AV94: =1225+8 -> 1233 | AW94: =1225+8 -> 1233 | AX94: =1225+8 -> 1233
A95: 105194 | B95: 110000332 | F95: 5.1.A | H95: [+] | I95: ICIS Bales - SEA trung bình 2 tháng trước | O95: =(M102+N102)/2 -> 1300 | P95: =(N102+O102)/2 -> 1307.5 | Q95: =(O102+P102)/2 -> 1320 | R95: =(P102+Q102)/2 -> 1322.5 | S95: =(Q102+R102)/2 -> 1326.5 | T95: =(R102+S102)/2 -> 1341.5 | U95: =(S102+T102)/2 -> 1357.5 | V95: =(T102+U102)/2 -> 1368.5 | ... AL95: =(AJ102+AK102)/2 -> 1246.875
A96: 105194 | B96: 110000332 | F96: 5.1.B | H96: [+] | I96: Premium (2025: $20; 2024: $50) | O96: 50 | P96: 50 | Q96: 50 | R96: 50 | S96: 50 | T96: 50 | U96: 50 | V96: 50 | W96: 50 | X96: 50 | Y96: 50 | Z96: 50 | AA96: 20 | AB96: 20 | AC96: 20 | AD96: 20 | AE96: 20 | AF96: 20 | AG96: 20 | AH96: 20 | AI96: 20 | AJ96: 20 | AK96: 20 | AL96: 20
A97: 105194 | B97: 110000332 | F97: 5.1.C | H97: [+] | I97: Rebate (2025: 5000-6000 tấn ~ 1.5% giá trị) | O97: =-IF('Rebate-Suntory'!$E$14="/tấn",'Rebate-Suntory'!$D$14,IF('Rebate-Suntory'!$E$14="giá trị",'Rebate-Suntory'!$D$14*(O95+O96+O98),0)) -> -10 | P97: =-IF('Rebate-Suntory'!$E$14="/tấn",'Rebate-Suntory'!$D$14,IF('Rebate-Suntory'!$E$14="giá trị",'Rebate-Suntory'!$D$14*(P95+P96+P98),0)) -> -10 | Q97: =-IF('Rebate-Suntory'!$E$14="/tấn",'Rebate-Suntory'!$D$14,IF('Rebate-Suntory'!$E$14="giá trị",'Rebate-Suntory'!$D$14*(Q95+Q96+Q98),0)) -> -10 | R97: =-IF('Rebate-Suntory'!$E$14="/tấn",'Rebate-Suntory'!$D$14,IF('Rebate-Suntory'!$E$14="giá trị",'Rebate-Suntory'!$D$14*(R95+R96+R98),0)) -> -10 | S97: =-IF('Rebate-Suntory'!$E$14="/tấn",'Rebate-Suntory'!$D$14,IF('Rebate-Suntory'!$E$14="giá trị",'Rebate-Suntory'!$D$14*(S95+S96+S98),0)) -> -10 | T97: =-IF('Rebate-Suntory'!$E$14="/tấn",'Rebate-Suntory'!$D$14,IF('Rebate-Suntory'!$E$14="giá trị",'Rebate-Suntory'!$D$14*(T95+T96+T98),0)) -> -10 | U97: =-IF('Rebate-Suntory'!$E$14="/tấn",'Rebate-Suntory'!$D$14,IF('Rebate-Suntory'!$E$14="giá trị",'Rebate-Suntory'!$D$14*(U95+U96+U98),0)) -> -10 | V97: =-IF('Rebate-Suntory'!$E$14="/tấn",'Rebate-Suntory'!$D$14,IF('Rebate-Suntory'!$E$14="giá trị",'Rebate-Suntory'!$D$14*(V95+V96+V98),0)) -> -10 | ... Z97: =-IF('Rebate-Suntory'!$E$14="/tấn",'Rebate-Suntory'!$D$14,IF('Rebate-Suntory'!$E$14="giá trị",'Rebate-Suntory'!$D$14*(Z95+Z96+Z98),0)) -> -10 | AA97: =-IF('Rebate-Suntory'!$J$14="/tấn",'Rebate-Suntory'!$I$14,IF('Rebate-Suntory'!$J$14="giá trị",'Rebate-Suntory'!$I$14*(AA95+AA96),0)) -> -21.721875 | AB97: =-IF('Rebate-Suntory'!$J$14="/tấn",'Rebate-Suntory'!$I$14,IF('Rebate-Suntory'!$J$14="giá trị",'Rebate-Suntory'!$I$14*(AB95+AB96),0)) -> -21.146875 | AC97: =-IF('Rebate-Suntory'!$J$14="/tấn",'Rebate-Suntory'!$I$14,IF('Rebate-Suntory'!$J$14="giá trị",'Rebate-Suntory'!$I$14*(AC95+AC96),0)) -> -20.6125 | AD97: =-IF('Rebate-Suntory'!$J$14="/tấn",'Rebate-Suntory'!$I$14,IF('Rebate-Suntory'!$J$14="giá trị",'Rebate-Suntory'!$I$14*(AD95+AD96),0)) -> -20.625 | AE97: =-IF('Rebate-Suntory'!$J$14="/tấn",'Rebate-Suntory'!$I$14,IF('Rebate-Suntory'!$J$14="giá trị",'Rebate-Suntory'!$I$14*(AE95+AE96),0)) -> -20.7 | AF97: =-IF('Rebate-Suntory'!$J$14="/tấn",'Rebate-Suntory'!$I$14,IF('Rebate-Suntory'!$J$14="giá trị",'Rebate-Suntory'!$I$14*(AF95+AF96),0)) -> -20.7 | AG97: =-IF('Rebate-Suntory'!$J$14="/tấn",'Rebate-Suntory'!$I$14,IF('Rebate-Suntory'!$J$14="giá trị",'Rebate-Suntory'!$I$14*(AG95+AG96),0)) -> -20.7 | AH97: =-IF('Rebate-Suntory'!$J$14="/tấn",'Rebate-Suntory'!$I$14,IF('Rebate-Suntory'!$J$14="giá trị",'Rebate-Suntory'!$I$14*(AH95+AH96),0)) -> -20.43 | ... AL97: =-IF('Rebate-Suntory'!$J$14="/tấn",'Rebate-Suntory'!$I$14,IF('Rebate-Suntory'!$J$14="giá trị",'Rebate-Suntory'!$I$14*(AL95+AL96),0)) -> -19.003125
A98: 105194 | B98: 110000332 | F98: 5.1.D | H98: [+] | I98: CP vận chuyển-Miền Bắc | O98: 26.5 | P98: 26.5 | Q98: 26.5 | R98: 26.5 | S98: 26.5 | T98: 26.5 | U98: 26.5 | V98: 26.5 | W98: 26.5 | X98: 26.5 | Y98: 26.5 | Z98: 26.5 | AA98: 26.5 | AB98: 26.5 | AC98: 26.5 | AD98: 26.5 | AE98: 26.5 | AF98: 26.5 | AG98: 26.5 | AH98: 26.5 | AI98: 26.5 | AJ98: 26.5 | AK98: 26.5 | AL98: 26.5
A99: 105194 | B99: 110000332 | D99: EXW | F99: 5.1.1 | I99: Giá bán quy đổi EXW | O99: =O94-O98 -> 1340 | P99: =P94-P98 -> 1347.5 | Q99: =Q94-Q98 -> 1360 | R99: =R94-R98 -> 1362.5 | S99: =S94-S98 -> 1366.5 | T99: =T94-T98 -> 1381.5 | U99: =U94-U98 -> 1397.5 | V99: =V94-V98 -> 1408.5 | ... AL99: =AL94-AL98 -> 1310.9969 | AM99: =AM94-AM100-AM101 -> 1128 | AN99: =AN94-AN100-AN101 -> 1128 | AO99: =AO94-AO100-AO101 -> 1128 | AP99: =AP94-AP100-AP101 -> 1128 | AQ99: =AQ94-AQ100-AQ101 -> 1128 | AR99: =AR94-AR100-AR101 -> 1128 | AS99: =AS94-AS100-AS101 -> 1128 | AT99: =AT94-AT100-AT101 -> 1128 | ... AX99: =AX94-AX100-AX101 -> 1128
I100: Chi phí vận chuyển-Miền Bắc | AM100: 25 | AN100: 25 | AO100: 25 | AP100: 33 | AQ100: 33 | AR100: 33 | AS100: 33 | AT100: 33 | AU100: 33 | AV100: 33 | AW100: 33 | AX100: 33
I101: Rebate (2026: 5000-6000 tấn ~ 6% giá trị) | AM101: =IF('Rebate-Suntory'!$O$14="/tấn",'Rebate-Suntory'!$N$14,IF('Rebate-Suntory'!$O$14="giá trị",'Rebate-Suntory'!$N$14*(AM94-AM100),0)) -> 72 | AN101: =IF('Rebate-Suntory'!$O$14="/tấn",'Rebate-Suntory'!$N$14,IF('Rebate-Suntory'!$O$14="giá trị",'Rebate-Suntory'!$N$14*(AN94-AN100),0)) -> 72 | AO101: =IF('Rebate-Suntory'!$O$14="/tấn",'Rebate-Suntory'!$N$14,IF('Rebate-Suntory'!$O$14="giá trị",'Rebate-Suntory'!$N$14*(AO94-AO100),0)) -> 72 | AP101: =IF('Rebate-Suntory'!$O$14="/tấn",'Rebate-Suntory'!$N$14,IF('Rebate-Suntory'!$O$14="giá trị",'Rebate-Suntory'!$N$14*(AP94-AP100),0)) -> 72 | AQ101: =IF('Rebate-Suntory'!$O$14="/tấn",'Rebate-Suntory'!$N$14,IF('Rebate-Suntory'!$O$14="giá trị",'Rebate-Suntory'!$N$14*(AQ94-AQ100),0)) -> 72 | AR101: =IF('Rebate-Suntory'!$O$14="/tấn",'Rebate-Suntory'!$N$14,IF('Rebate-Suntory'!$O$14="giá trị",'Rebate-Suntory'!$N$14*(AR94-AR100),0)) -> 72 | AS101: =IF('Rebate-Suntory'!$O$14="/tấn",'Rebate-Suntory'!$N$14,IF('Rebate-Suntory'!$O$14="giá trị",'Rebate-Suntory'!$N$14*(AS94-AS100),0)) -> 72 | AT101: =IF('Rebate-Suntory'!$O$14="/tấn",'Rebate-Suntory'!$N$14,IF('Rebate-Suntory'!$O$14="giá trị",'Rebate-Suntory'!$N$14*(AT94-AT100),0)) -> 72 | ... AX101: =IF('Rebate-Suntory'!$O$14="/tấn",'Rebate-Suntory'!$N$14,IF('Rebate-Suntory'!$O$14="giá trị",'Rebate-Suntory'!$N$14*(AX94-AX100),0)) -> 72
A102: 105194 | B102: 110000332 | C102: 04 | J102: ICIS Bales - SEA | L102: {=SUMPRODUCT(General_Data*(Year=L$3)*(Month=L$4)*(Code_General_Data=$C102))} -> 1288.125 | M102: {=SUMPRODUCT(General_Data*(Year=M$3)*(Month=M$4)*(Code_General_Data=$C102))} -> 1300 | N102: {=SUMPRODUCT(General_Data*(Year=N$3)*(Month=N$4)*(Code_General_Data=$C102))} -> 1300 | O102: {=SUMPRODUCT(General_Data*(Year=O$3)*(Month=O$4)*(Code_General_Data=$C102))} -> 1315 | P102: {=SUMPRODUCT(General_Data*(Year=P$3)*(Month=P$4)*(Code_General_Data=$C102))} -> 1325 | Q102: {=SUMPRODUCT(General_Data*(Year=Q$3)*(Month=Q$4)*(Code_General_Data=$C102))} -> 1320 | R102: {=SUMPRODUCT(General_Data*(Year=R$3)*(Month=R$4)*(Code_General_Data=$C102))} -> 1333 | S102: {=SUMPRODUCT(General_Data*(Year=S$3)*(Month=S$4)*(Code_General_Data=$C102))} -> 1350 | ... AL102: {=SUMPRODUCT(General_Data*(Year=AL$3)*(Month=AL$4)*(Code_General_Data=$C102))} -> 1193.75
A103: 105194 | B103: 110000332 | F103: 5.1.2 | J103: Giá trần | O103: {=INDEX(Note!$J$3:$J$102,MATCH(1,(Note!$A$3:$A$102=$A103)*(Note!$C$3:$C$102=$B103)*(Note!$E$3:$E$102<=O$1)*(Note!$F$3:$F$102>=O$2),0))} -> 0 | P103: {=INDEX(Note!$J$3:$J$102,MATCH(1,(Note!$A$3:$A$102=$A103)*(Note!$C$3:$C$102=$B103)*(Note!$E$3:$E$102<=P$1)*(Note!$F$3:$F$102>=P$2),0))} -> 0 | Q103: {=INDEX(Note!$J$3:$J$102,MATCH(1,(Note!$A$3:$A$102=$A103)*(Note!$C$3:$C$102=$B103)*(Note!$E$3:$E$102<=Q$1)*(Note!$F$3:$F$102>=Q$2),0))} -> 0 | R103: {=INDEX(Note!$J$3:$J$102,MATCH(1,(Note!$A$3:$A$102=$A103)*(Note!$C$3:$C$102=$B103)*(Note!$E$3:$E$102<=R$1)*(Note!$F$3:$F$102>=R$2),0))} -> 0 | S103: {=INDEX(Note!$J$3:$J$102,MATCH(1,(Note!$A$3:$A$102=$A103)*(Note!$C$3:$C$102=$B103)*(Note!$E$3:$E$102<=S$1)*(Note!$F$3:$F$102>=S$2),0))} -> 0 | T103: {=INDEX(Note!$J$3:$J$102,MATCH(1,(Note!$A$3:$A$102=$A103)*(Note!$C$3:$C$102=$B103)*(Note!$E$3:$E$102<=T$1)*(Note!$F$3:$F$102>=T$2),0))} -> 0 | U103: {=INDEX(Note!$J$3:$J$102,MATCH(1,(Note!$A$3:$A$102=$A103)*(Note!$C$3:$C$102=$B103)*(Note!$E$3:$E$102<=U$1)*(Note!$F$3:$F$102>=U$2),0))} -> 0 | V103: {=INDEX(Note!$J$3:$J$102,MATCH(1,(Note!$A$3:$A$102=$A103)*(Note!$C$3:$C$102=$B103)*(Note!$E$3:$E$102<=V$1)*(Note!$F$3:$F$102>=V$2),0))} -> 0 | ... AL103: {=INDEX(Note!$J$3:$J$102,MATCH(1,(Note!$A$3:$A$102=$A103)*(Note!$C$3:$C$102=$B103)*(Note!$E$3:$E$102<=AL$1)*(Note!$F$3:$F$102>=AL$2),0))} -> 1550
A104: 105194 | B104: 110000332 | F104: 5.1.3 | J104: Giá sàn | O104: {=INDEX(Note!$K$3:$K$102,MATCH(1,(Note!$A$3:$A$102=$A104)*(Note!$C$3:$C$102=$B104)*(Note!$E$3:$E$102<=O$1)*(Note!$F$3:$F$102>=O$2),0))} -> 0 | P104: {=INDEX(Note!$K$3:$K$102,MATCH(1,(Note!$A$3:$A$102=$A104)*(Note!$C$3:$C$102=$B104)*(Note!$E$3:$E$102<=P$1)*(Note!$F$3:$F$102>=P$2),0))} -> 0 | Q104: {=INDEX(Note!$K$3:$K$102,MATCH(1,(Note!$A$3:$A$102=$A104)*(Note!$C$3:$C$102=$B104)*(Note!$E$3:$E$102<=Q$1)*(Note!$F$3:$F$102>=Q$2),0))} -> 0 | R104: {=INDEX(Note!$K$3:$K$102,MATCH(1,(Note!$A$3:$A$102=$A104)*(Note!$C$3:$C$102=$B104)*(Note!$E$3:$E$102<=R$1)*(Note!$F$3:$F$102>=R$2),0))} -> 0 | S104: {=INDEX(Note!$K$3:$K$102,MATCH(1,(Note!$A$3:$A$102=$A104)*(Note!$C$3:$C$102=$B104)*(Note!$E$3:$E$102<=S$1)*(Note!$F$3:$F$102>=S$2),0))} -> 0 | T104: {=INDEX(Note!$K$3:$K$102,MATCH(1,(Note!$A$3:$A$102=$A104)*(Note!$C$3:$C$102=$B104)*(Note!$E$3:$E$102<=T$1)*(Note!$F$3:$F$102>=T$2),0))} -> 0 | U104: {=INDEX(Note!$K$3:$K$102,MATCH(1,(Note!$A$3:$A$102=$A104)*(Note!$C$3:$C$102=$B104)*(Note!$E$3:$E$102<=U$1)*(Note!$F$3:$F$102>=U$2),0))} -> 0 | V104: {=INDEX(Note!$K$3:$K$102,MATCH(1,(Note!$A$3:$A$102=$A104)*(Note!$C$3:$C$102=$B104)*(Note!$E$3:$E$102<=V$1)*(Note!$F$3:$F$102>=V$2),0))} -> 0 | ... AL104: {=INDEX(Note!$K$3:$K$102,MATCH(1,(Note!$A$3:$A$102=$A104)*(Note!$C$3:$C$102=$B104)*(Note!$E$3:$E$102<=AL$1)*(Note!$F$3:$F$102>=AL$2),0))} -> 1330
A105: 105194 | B105: 110000332 | F105: 5.1.4 | J105: Giá duyệt tháng | O105: {=SUMPRODUCT(General_Data*(Year=O$3)*(Month=O$4)*(Code_General_Data=$B105))} -> 1340 | P105: {=SUMPRODUCT(General_Data*(Year=P$3)*(Month=P$4)*(Code_General_Data=$B105))} -> 1340 | Q105: {=SUMPRODUCT(General_Data*(Year=Q$3)*(Month=Q$4)*(Code_General_Data=$B105))} -> 1340 | R105: {=SUMPRODUCT(General_Data*(Year=R$3)*(Month=R$4)*(Code_General_Data=$B105))} -> 1340 | S105: {=SUMPRODUCT(General_Data*(Year=S$3)*(Month=S$4)*(Code_General_Data=$B105))} -> 1390 | T105: {=SUMPRODUCT(General_Data*(Year=T$3)*(Month=T$4)*(Code_General_Data=$B105))} -> 1390 | U105: {=SUMPRODUCT(General_Data*(Year=U$3)*(Month=U$4)*(Code_General_Data=$B105))} -> 1390 | V105: {=SUMPRODUCT(General_Data*(Year=V$3)*(Month=V$4)*(Code_General_Data=$B105))} -> 1390 | ... AR105: {=SUMPRODUCT(General_Data*(Year=AR$3)*(Month=AR$4)*(Code_General_Data=$B105))} -> 1440
J106: Giá trần - quy đổi EXW | AA106: =AA103+AA97 -> 1528.2781 | AB106: =AB103+AB97 -> 1528.8531 | AC106: =AC103+AC97 -> 1529.3875 | AD106: =AD103+AD97 -> 1529.375 | AE106: =AE103+AE97 -> 1529.3 | AF106: =AF103+AF97 -> 1529.3 | AG106: =AG103+AG97 -> 1529.3 | AH106: =AH103+AH97 -> 1529.57 | ... AL106: =AL103+AL97 -> 1530.9969
J107: Giá sàn - quy đổi EXW | AA107: =AA104+AA97 -> 1308.2781 | AB107: =AB104+AB97 -> 1308.8531 | AC107: =AC104+AC97 -> 1309.3875 | AD107: =AD104+AD97 -> 1309.375 | AE107: =AE104+AE97 -> 1309.3 | AF107: =AF104+AF97 -> 1309.3 | AG107: =AG104+AG97 -> 1309.3 | AH107: =AH104+AH97 -> 1309.57 | ... AL107: =AL104+AL97 -> 1310.9969
A109: 105194 | B109: 110000355 | D109: GB | F109: 5.2 | H109: GIÁ BÁN iSS01G (DDP) | O109: =SUM(O110:O113) -> 1346.5 | P109: =SUM(P110:P113) -> 1354 | Q109: =SUM(Q110:Q113) -> 1366.5 | R109: =SUM(R110:R113) -> 1369 | S109: =SUM(S110:S113) -> 1373 | T109: =SUM(T110:T113) -> 1388 | U109: =SUM(U110:U113) -> 1404 | V109: =SUM(V110:V113) -> 1415 | ... Z109: =SUM(Z110:Z113) -> 1484 | AA109: =MIN(MAX(SUM(AA110,AA111),AA119),AA118)+AA112+AA113 -> 1452.9031 | AB109: =MIN(MAX(SUM(AB110,AB111),AB119),AB118)+AB112+AB113 -> 1415.1448 | AC109: =MIN(MAX(SUM(AC110,AC111),AC119),AC118)+AC112+AC113 -> 1380.0542 | AD109: =MIN(MAX(SUM(AD110,AD111),AD119),AD118)+AD112+AD113 -> 1380.875 | AE109: =MIN(MAX(SUM(AE110,AE111),AE119),AE118)+AE112+AE113 -> 1385.8 | AF109: =MIN(MAX(SUM(AF110,AF111),AF119),AF118)+AF112+AF113 -> 1385.8 | AG109: =MIN(MAX(SUM(AG110,AG111),AG119),AG118)+AG112+AG113 -> 1385.8 | AH109: =MIN(MAX(SUM(AH110,AH111),AH119),AH118)+AH112+AH113 -> 1368.07 | ... AL109: =MIN(MAX(SUM(AL110,AL111),AL119),AL118)+AL112+AL113 -> 1337.4969 | AM109: 1225 | AN109: 1225 | AO109: 1225 | AP109: =1225+8 -> 1233 | AQ109: 1233 | AR109: 1233 | AS109: 1233 | AT109: 1233 | AU109: 1233 | AV109: 1233 | AW109: 1233 | AX109: 1233
A110: 105194 | B110: 110000355 | F110: 5.2.A | H110: [+] | I110: ICIS Bales - SEA trung bình 2 tháng trước | O110: =(M117+N117)/2 -> 1300 | P110: =(N117+O117)/2 -> 1307.5 | Q110: =(O117+P117)/2 -> 1320 | R110: =(P117+Q117)/2 -> 1322.5 | S110: =(Q117+R117)/2 -> 1326.5 | T110: =(R117+S117)/2 -> 1341.5 | U110: =(S117+T117)/2 -> 1357.5 | V110: =(T117+U117)/2 -> 1368.5 | ... AL110: =(AJ117+AK117)/2 -> 1246.875
A111: 105194 | B111: 110000355 | F111: 5.2.B | H111: [+] | I111: Premium (2025: $20; 2024: $30) | O111: 30 | P111: 30 | Q111: 30 | R111: 30 | S111: 30 | T111: 30 | U111: 30 | V111: 30 | W111: 30 | X111: 30 | Y111: 30 | Z111: 30 | AA111: 20 | AB111: 20 | AC111: 20 | AD111: 20 | AE111: 20 | AF111: 20 | AG111: 20 | AH111: 20 | AI111: 20 | AJ111: 20 | AK111: 20 | AL111: 20
...

Sheet Biểu đồ
C1: III. BIỂU ĐỒ
C36: III. BIỂU ĐỒ
C71: III. BIỂU ĐỒ
C106: III. BIỂU ĐỒ
C141: III. BIỂU ĐỒ

Sheet Vẽ Biểu đồ
E1: 2024 | F1: 2024 | G1: 2024 | H1: 2024 | I1: 2024 | J1: 2024 | K1: 2024 | L1: 2024 | M1: 2024 | N1: 2024 | O1: 2024 | P1: 2024 | Q1: 2025 | R1: 2025 | S1: 2025 | T1: 2025 | U1: 2025 | V1: 2025 | W1: 2025 | X1: 2025 | Y1: 2025 | Z1: 2025 | AA1: 2025 | AB1: 2025 | AC1: 2026 | AD1: 2026 | AE1: 2026 | AF1: 2026 | AG1: 2026 | AH1: 2026 | AI1: 2026 | AJ1: 2026 | AK1: 2026 | AL1: 2026 | AM1: 2026 | AN1: 2026
E2: 1 | F2: 2 | G2: 3 | H2: 4 | I2: 5 | J2: 6 | K2: 7 | L2: 8 | M2: 9 | N2: 10 | O2: 11 | P2: 12 | Q2: 1 | R2: 2 | S2: 3 | T2: 4 | U2: 5 | V2: 6 | W2: 7 | X2: 8 | Y2: 9 | Z2: 10 | AA2: 11 | AB2: 12 | AC2: 1 | AD2: 2 | AE2: 3 | AF2: 4 | AG2: 5 | AH2: 6 | AI2: 7 | AJ2: 8 | AK2: 9 | AL2: 10 | AM2: 11 | AN2: 12
D3: X dòng này làm lable -> | AH3: x
A4: Genearal Data | B4: Price
C5: 110000354 | D5: WSS01G
E6: 2024 | Q6: 2025 | AC6: 2026
E7: 1 | F7: 2 | G7: 3 | H7: 4 | I7: 5 | J7: 6 | K7: 7 | L7: 8 | M7: 9 | N7: 10 | O7: 11 | P7: 12 | Q7: 1 | R7: 2 | S7: 3 | T7: 4 | U7: 5 | V7: 6 | W7: 7 | X7: 8 | Y7: 9 | Z7: 10 | AA7: 11 | AB7: 12 | AC7: 1 | AD7: 2 | AE7: 3 | AF7: 4 | AG7: 5 | AH7: 6 | AI7: 7 | AJ7: 8 | AK7: 9 | AL7: 10 | AM7: 11 | AN7: 12
B8: 200319 | C8: 110000354 | D8: Niagara | E8: {=IF(SUMPRODUCT('Giá công thức'!$G$11:$AQ$115*('Giá công thức'!$A$11:$A$115=$B8)*('Giá công thức'!$B$11:$B$115=$C8)*('Giá công thức'!$C$11:$C$115="GB")*('Giá công thức'!$G$3:$AQ$3=E$1)*('Giá công thức'!$G$4:$AQ$4=E$2))=0,NA(),SUMPRODUCT('Giá công thức'!$G$11:$AQ$115*('Giá công thức'!$A$11:$A$115=$B8)*('Giá công thức'!$B$11:$B$115=$C8)*('Giá công thức'!$C$11:$C$115="GB")*('Giá công thức'!$G$3:$AQ$3=E$1)*('Giá công thức'!$G$4:$AQ$4=E$2)))} -> 1162 | F8: {=IF(SUMPRODUCT('Giá công thức'!$G$11:$AQ$115*('Giá công thức'!$A$11:$A$115=$B8)*('Giá công thức'!$B$11:$B$115=$C8)*('Giá công thức'!$C$11:$C$115="GB")*('Giá công thức'!$G$3:$AQ$3=F$1)*('Giá công thức'!$G$4:$AQ$4=F$2))=0,NA(),SUMPRODUCT('Giá công thức'!$G$11:$AQ$115*('Giá công thức'!$A$11:$A$115=$B8)*('Giá công thức'!$B$11:$B$115=$C8)*('Giá công thức'!$C$11:$C$115="GB")*('Giá công thức'!$G$3:$AQ$3=F$1)*('Giá công thức'!$G$4:$AQ$4=F$2)))} -> 1162 | G8: {=IF(SUMPRODUCT('Giá công thức'!$G$11:$AQ$115*('Giá công thức'!$A$11:$A$115=$B8)*('Giá công thức'!$B$11:$B$115=$C8)*('Giá công thức'!$C$11:$C$115="GB")*('Giá công thức'!$G$3:$AQ$3=G$1)*('Giá công thức'!$G$4:$AQ$4=G$2))=0,NA(),SUMPRODUCT('Giá công thức'!$G$11:$AQ$115*('Giá công thức'!$A$11:$A$115=$B8)*('Giá công thức'!$B$11:$B$115=$C8)*('Giá công thức'!$C$11:$C$115="GB")*('Giá công thức'!$G$3:$AQ$3=G$1)*('Giá công thức'!$G$4:$AQ$4=G$2)))} -> 1162 | H8: {=IF(SUMPRODUCT('Giá công thức'!$G$11:$AQ$115*('Giá công thức'!$A$11:$A$115=$B8)*('Giá công thức'!$B$11:$B$115=$C8)*('Giá công thức'!$C$11:$C$115="GB")*('Giá công thức'!$G$3:$AQ$3=H$1)*('Giá công thức'!$G$4:$AQ$4=H$2))=0,NA(),SUMPRODUCT('Giá công thức'!$G$11:$AQ$115*('Giá công thức'!$A$11:$A$115=$B8)*('Giá công thức'!$B$11:$B$115=$C8)*('Giá công thức'!$C$11:$C$115="GB")*('Giá công thức'!$G$3:$AQ$3=H$1)*('Giá công thức'!$G$4:$AQ$4=H$2)))} -> 1162 | I8: {=IF(SUMPRODUCT('Giá công thức'!$G$11:$AQ$115*('Giá công thức'!$A$11:$A$115=$B8)*('Giá công thức'!$B$11:$B$115=$C8)*('Giá công thức'!$C$11:$C$115="GB")*('Giá công thức'!$G$3:$AQ$3=I$1)*('Giá công thức'!$G$4:$AQ$4=I$2))=0,NA(),SUMPRODUCT('Giá công thức'!$G$11:$AQ$115*('Giá công thức'!$A$11:$A$115=$B8)*('Giá công thức'!$B$11:$B$115=$C8)*('Giá công thức'!$C$11:$C$115="GB")*('Giá công thức'!$G$3:$AQ$3=I$1)*('Giá công thức'!$G$4:$AQ$4=I$2)))} -> 1162 | J8: {=IF(SUMPRODUCT('Giá công thức'!$G$11:$AQ$115*('Giá công thức'!$A$11:$A$115=$B8)*('Giá công thức'!$B$11:$B$115=$C8)*('Giá công thức'!$C$11:$C$115="GB")*('Giá công thức'!$G$3:$AQ$3=J$1)*('Giá công thức'!$G$4:$AQ$4=J$2))=0,NA(),SUMPRODUCT('Giá công thức'!$G$11:$AQ$115*('Giá công thức'!$A$11:$A$115=$B8)*('Giá công thức'!$B$11:$B$115=$C8)*('Giá công thức'!$C$11:$C$115="GB")*('Giá công thức'!$G$3:$AQ$3=J$1)*('Giá công thức'!$G$4:$AQ$4=J$2)))} -> 1162.8865 | K8: {=IF(SUMPRODUCT('Giá công thức'!$G$11:$AQ$115*('Giá công thức'!$A$11:$A$115=$B8)*('Giá công thức'!$B$11:$B$115=$C8)*('Giá công thức'!$C$11:$C$115="GB")*('Giá công thức'!$G$3:$AQ$3=K$1)*('Giá công thức'!$G$4:$AQ$4=K$2))=0,NA(),SUMPRODUCT('Giá công thức'!$G$11:$AQ$115*('Giá công thức'!$A$11:$A$115=$B8)*('Giá công thức'!$B$11:$B$115=$C8)*('Giá công thức'!$C$11:$C$115="GB")*('Giá công thức'!$G$3:$AQ$3=K$1)*('Giá công thức'!$G$4:$AQ$4=K$2)))} -> 1176.184 | L8: {=IF(SUMPRODUCT('Giá công thức'!$G$11:$AQ$115*('Giá công thức'!$A$11:$A$115=$B8)*('Giá công thức'!$B$11:$B$115=$C8)*('Giá công thức'!$C$11:$C$115="GB")*('Giá công thức'!$G$3:$AQ$3=L$1)*('Giá công thức'!$G$4:$AQ$4=L$2))=0,NA(),SUMPRODUCT('Giá công thức'!$G$11:$AQ$115*('Giá công thức'!$A$11:$A$115=$B8)*('Giá công thức'!$B$11:$B$115=$C8)*('Giá công thức'!$C$11:$C$115="GB")*('Giá công thức'!$G$3:$AQ$3=L$1)*('Giá công thức'!$G$4:$AQ$4=L$2)))} -> 1187.7085 | ... AH8: {=IF(SUMPRODUCT('Giá công thức'!$G$11:$AQ$115*('Giá công thức'!$A$11:$A$115=$B8)*('Giá công thức'!$B$11:$B$115=$C8)*('Giá công thức'!$C$11:$C$115="GB")*('Giá công thức'!$G$3:$AQ$3=AH$1)*('Giá công thức'!$G$4:$AQ$4=AH$2))=0,NA(),SUMPRODUCT('Giá công thức'!$G$11:$AQ$115*('Giá công thức'!$A$11:$A$115=$B8)*('Giá công thức'!$B$11:$B$115=$C8)*('Giá công thức'!$C$11:$C$115="GB")*('Giá công thức'!$G$3:$AQ$3=AH$1)*('Giá công thức'!$G$4:$AQ$4=AH$2)))} -> 1182.685 | AO8: =INDEX($E8:$AN8,MATCH("X",$E$3:$AN$3,0)) -> 1182.685
B9: 200400 | C9: 110000354 | D9: SHEPLEY (NIAGARA NON-US) | AB9: {=IF(SUMPRODUCT('Giá công thức'!$G$11:$AQ$115*('Giá công thức'!$A$11:$A$115=$B9)*('Giá công thức'!$B$11:$B$115=$C9)*('Giá công thức'!$C$11:$C$115="GB")*('Giá công thức'!$G$3:$AQ$3=AB$1)*('Giá công thức'!$G$4:$AQ$4=AB$2))=0,NA(),SUMPRODUCT('Giá công thức'!$G$11:$AQ$115*('Giá công thức'!$A$11:$A$115=$B9)*('Giá công thức'!$B$11:$B$115=$C9)*('Giá công thức'!$C$11:$C$115="GB")*('Giá công thức'!$G$3:$AQ$3=AB$1)*('Giá công thức'!$G$4:$AQ$4=AB$2)))} -> 1063.5 | AC9: {=IF(SUMPRODUCT('Giá công thức'!$G$11:$AQ$115*('Giá công thức'!$A$11:$A$115=$B9)*('Giá công thức'!$B$11:$B$115=$C9)*('Giá công thức'!$C$11:$C$115="GB")*('Giá công thức'!$G$3:$AQ$3=AC$1)*('Giá công thức'!$G$4:$AQ$4=AC$2))=0,NA(),SUMPRODUCT('Giá công thức'!$G$11:$AQ$115*('Giá công thức'!$A$11:$A$115=$B9)*('Giá công thức'!$B$11:$B$115=$C9)*('Giá công thức'!$C$11:$C$115="GB")*('Giá công thức'!$G$3:$AQ$3=AC$1)*('Giá công thức'!$G$4:$AQ$4=AC$2)))} -> 1083.2 | AD9: {=IF(SUMPRODUCT('Giá công thức'!$G$11:$AQ$115*('Giá công thức'!$A$11:$A$115=$B9)*('Giá công thức'!$B$11:$B$115=$C9)*('Giá công thức'!$C$11:$C$115="GB")*('Giá công thức'!$G$3:$AQ$3=AD$1)*('Giá công thức'!$G$4:$AQ$4=AD$2))=0,NA(),SUMPRODUCT('Giá công thức'!$G$11:$AQ$115*('Giá công thức'!$A$11:$A$115=$B9)*('Giá công thức'!$B$11:$B$115=$C9)*('Giá công thức'!$C$11:$C$115="GB")*('Giá công thức'!$G$3:$AQ$3=AD$1)*('Giá công thức'!$G$4:$AQ$4=AD$2)))} -> 1053.65 | AE9: {=IF(SUMPRODUCT('Giá công thức'!$G$11:$AQ$115*('Giá công thức'!$A$11:$A$115=$B9)*('Giá công thức'!$B$11:$B$115=$C9)*('Giá công thức'!$C$11:$C$115="GB")*('Giá công thức'!$G$3:$AQ$3=AE$1)*('Giá công thức'!$G$4:$AQ$4=AE$2))=0,NA(),SUMPRODUCT('Giá công thức'!$G$11:$AQ$115*('Giá công thức'!$A$11:$A$115=$B9)*('Giá công thức'!$B$11:$B$115=$C9)*('Giá công thức'!$C$11:$C$115="GB")*('Giá công thức'!$G$3:$AQ$3=AE$1)*('Giá công thức'!$G$4:$AQ$4=AE$2)))} -> 1064.7313 | AF9: {=IF(SUMPRODUCT('Giá công thức'!$G$11:$AQ$115*('Giá công thức'!$A$11:$A$115=$B9)*('Giá công thức'!$B$11:$B$115=$C9)*('Giá công thức'!$C$11:$C$115="GB")*('Giá công thức'!$G$3:$AQ$3=AF$1)*('Giá công thức'!$G$4:$AQ$4=AF$2))=0,NA(),SUMPRODUCT('Giá công thức'!$G$11:$AQ$115*('Giá công thức'!$A$11:$A$115=$B9)*('Giá công thức'!$B$11:$B$115=$C9)*('Giá công thức'!$C$11:$C$115="GB")*('Giá công thức'!$G$3:$AQ$3=AF$1)*('Giá công thức'!$G$4:$AQ$4=AF$2)))} -> 1112.75 | AG9: {=IF(SUMPRODUCT('Giá công thức'!$G$11:$AQ$115*('Giá công thức'!$A$11:$A$115=$B9)*('Giá công thức'!$B$11:$B$115=$C9)*('Giá công thức'!$C$11:$C$115="GB")*('Giá công thức'!$G$3:$AQ$3=AG$1)*('Giá công thức'!$G$4:$AQ$4=AG$2))=0,NA(),SUMPRODUCT('Giá công thức'!$G$11:$AQ$115*('Giá công thức'!$A$11:$A$115=$B9)*('Giá công thức'!$B$11:$B$115=$C9)*('Giá công thức'!$C$11:$C$115="GB")*('Giá công thức'!$G$3:$AQ$3=AG$1)*('Giá công thức'!$G$4:$AQ$4=AG$2)))} -> 1112.75 | AH9: {=IF(SUMPRODUCT('Giá công thức'!$G$11:$AQ$115*('Giá công thức'!$A$11:$A$115=$B9)*('Giá công thức'!$B$11:$B$115=$C9)*('Giá công thức'!$C$11:$C$115="GB")*('Giá công thức'!$G$3:$AQ$3=AH$1)*('Giá công thức'!$G$4:$AQ$4=AH$2))=0,NA(),SUMPRODUCT('Giá công thức'!$G$11:$AQ$115*('Giá công thức'!$A$11:$A$115=$B9)*('Giá công thức'!$B$11:$B$115=$C9)*('Giá công thức'!$C$11:$C$115="GB")*('Giá công thức'!$G$3:$AQ$3=AH$1)*('Giá công thức'!$G$4:$AQ$4=AH$2)))} -> 1112.75 | AO9: =INDEX($E9:$AN9,MATCH("X",$E$3:$AN$3,0)) -> 1112.75
B10: 105263 | C10: 110000354 | D10: Unilever | E10: {=IF(SUMPRODUCT('Giá công thức'!$G$11:$AQ$115*('Giá công thức'!$A$11:$A$115=$B10)*('Giá công thức'!$B$11:$B$115=$C10)*('Giá công thức'!$C$11:$C$115="GB")*('Giá công thức'!$G$3:$AQ$3=E$1)*('Giá công thức'!$G$4:$AQ$4=E$2))=0,NA(),SUMPRODUCT('Giá công thức'!$G$11:$AQ$115*('Giá công thức'!$A$11:$A$115=$B10)*('Giá công thức'!$B$11:$B$115=$C10)*('Giá công thức'!$C$11:$C$115="GB")*('Giá công thức'!$G$3:$AQ$3=E$1)*('Giá công thức'!$G$4:$AQ$4=E$2)))} -> 1307.7959 | F10: {=IF(SUMPRODUCT('Giá công thức'!$G$11:$AQ$115*('Giá công thức'!$A$11:$A$115=$B10)*('Giá công thức'!$B$11:$B$115=$C10)*('Giá công thức'!$C$11:$C$115="GB")*('Giá công thức'!$G$3:$AQ$3=F$1)*('Giá công thức'!$G$4:$AQ$4=F$2))=0,NA(),SUMPRODUCT('Giá công thức'!$G$11:$AQ$115*('Giá công thức'!$A$11:$A$115=$B10)*('Giá công thức'!$B$11:$B$115=$C10)*('Giá công thức'!$C$11:$C$115="GB")*('Giá công thức'!$G$3:$AQ$3=F$1)*('Giá công thức'!$G$4:$AQ$4=F$2)))} -> 1307.7959 | G10: {=IF(SUMPRODUCT('Giá công thức'!$G$11:$AQ$115*('Giá công thức'!$A$11:$A$115=$B10)*('Giá công thức'!$B$11:$B$115=$C10)*('Giá công thức'!$C$11:$C$115="GB")*('Giá công thức'!$G$3:$AQ$3=G$1)*('Giá công thức'!$G$4:$AQ$4=G$2))=0,NA(),SUMPRODUCT('Giá công thức'!$G$11:$AQ$115*('Giá công thức'!$A$11:$A$115=$B10)*('Giá công thức'!$B$11:$B$115=$C10)*('Giá công thức'!$C$11:$C$115="GB")*('Giá công thức'!$G$3:$AQ$3=G$1)*('Giá công thức'!$G$4:$AQ$4=G$2)))} -> 1307.7959 | H10: {=IF(SUMPRODUCT('Giá công thức'!$G$11:$AQ$115*('Giá công thức'!$A$11:$A$115=$B10)*('Giá công thức'!$B$11:$B$115=$C10)*('Giá công thức'!$C$11:$C$115="GB")*('Giá công thức'!$G$3:$AQ$3=H$1)*('Giá công thức'!$G$4:$AQ$4=H$2))=0,NA(),SUMPRODUCT('Giá công thức'!$G$11:$AQ$115*('Giá công thức'!$A$11:$A$115=$B10)*('Giá công thức'!$B$11:$B$115=$C10)*('Giá công thức'!$C$11:$C$115="GB")*('Giá công thức'!$G$3:$AQ$3=H$1)*('Giá công thức'!$G$4:$AQ$4=H$2)))} -> 1307.7959 | I10: {=IF(SUMPRODUCT('Giá công thức'!$G$11:$AQ$115*('Giá công thức'!$A$11:$A$115=$B10)*('Giá công thức'!$B$11:$B$115=$C10)*('Giá công thức'!$C$11:$C$115="GB")*('Giá công thức'!$G$3:$AQ$3=I$1)*('Giá công thức'!$G$4:$AQ$4=I$2))=0,NA(),SUMPRODUCT('Giá công thức'!$G$11:$AQ$115*('Giá công thức'!$A$11:$A$115=$B10)*('Giá công thức'!$B$11:$B$115=$C10)*('Giá công thức'!$C$11:$C$115="GB")*('Giá công thức'!$G$3:$AQ$3=I$1)*('Giá công thức'!$G$4:$AQ$4=I$2)))} -> 1307.7959 | J10: {=IF(SUMPRODUCT('Giá công thức'!$G$11:$AQ$115*('Giá công thức'!$A$11:$A$115=$B10)*('Giá công thức'!$B$11:$B$115=$C10)*('Giá công thức'!$C$11:$C$115="GB")*('Giá công thức'!$G$3:$AQ$3=J$1)*('Giá công thức'!$G$4:$AQ$4=J$2))=0,NA(),SUMPRODUCT('Giá công thức'!$G$11:$AQ$115*('Giá công thức'!$A$11:$A$115=$B10)*('Giá công thức'!$B$11:$B$115=$C10)*('Giá công thức'!$C$11:$C$115="GB")*('Giá công thức'!$G$3:$AQ$3=J$1)*('Giá công thức'!$G$4:$AQ$4=J$2)))} -> 1307.7959 | K10: {=IF(SUMPRODUCT('Giá công thức'!$G$11:$AQ$115*('Giá công thức'!$A$11:$A$115=$B10)*('Giá công thức'!$B$11:$B$115=$C10)*('Giá công thức'!$C$11:$C$115="GB")*('Giá công thức'!$G$3:$AQ$3=K$1)*('Giá công thức'!$G$4:$AQ$4=K$2))=0,NA(),SUMPRODUCT('Giá công thức'!$G$11:$AQ$115*('Giá công thức'!$A$11:$A$115=$B10)*('Giá công thức'!$B$11:$B$115=$C10)*('Giá công thức'!$C$11:$C$115="GB")*('Giá công thức'!$G$3:$AQ$3=K$1)*('Giá công thức'!$G$4:$AQ$4=K$2)))} -> 1308.04 | L10: {=IF(SUMPRODUCT('Giá công thức'!$G$11:$AQ$115*('Giá công thức'!$A$11:$A$115=$B10)*('Giá công thức'!$B$11:$B$115=$C10)*('Giá công thức'!$C$11:$C$115="GB")*('Giá công thức'!$G$3:$AQ$3=L$1)*('Giá công thức'!$G$4:$AQ$4=L$2))=0,NA(),SUMPRODUCT('Giá công thức'!$G$11:$AQ$115*('Giá công thức'!$A$11:$A$115=$B10)*('Giá công thức'!$B$11:$B$115=$C10)*('Giá công thức'!$C$11:$C$115="GB")*('Giá công thức'!$G$3:$AQ$3=L$1)*('Giá công thức'!$G$4:$AQ$4=L$2)))} -> 1308.04 | ... AH10: {=IF(SUMPRODUCT('Giá công thức'!$G$11:$AQ$115*('Giá công thức'!$A$11:$A$115=$B10)*('Giá công thức'!$B$11:$B$115=$C10)*('Giá công thức'!$C$11:$C$115="GB")*('Giá công thức'!$G$3:$AQ$3=AH$1)*('Giá công thức'!$G$4:$AQ$4=AH$2))=0,NA(),SUMPRODUCT('Giá công thức'!$G$11:$AQ$115*('Giá công thức'!$A$11:$A$115=$B10)*('Giá công thức'!$B$11:$B$115=$C10)*('Giá công thức'!$C$11:$C$115="GB")*('Giá công thức'!$G$3:$AQ$3=AH$1)*('Giá công thức'!$G$4:$AQ$4=AH$2)))} -> 1185 | AO10: =INDEX($E10:$AN10,MATCH("X",$E$3:$AN$3,0)) -> 1185
B11: 104909 | C11: 110000329 | D11: Lavie | E11: {=IF(SUMPRODUCT('Giá công thức'!$G$11:$AQ$115*('Giá công thức'!$A$11:$A$115=$B11)*('Giá công thức'!$B$11:$B$115=$C11)*('Giá công thức'!$C$11:$C$115="GB")*('Giá công thức'!$G$3:$AQ$3=E$1)*('Giá công thức'!$G$4:$AQ$4=E$2))=0,NA(),SUMPRODUCT('Giá công thức'!$G$11:$AQ$115*('Giá công thức'!$A$11:$A$115=$B11)*('Giá công thức'!$B$11:$B$115=$C11)*('Giá công thức'!$C$11:$C$115="GB")*('Giá công thức'!$G$3:$AQ$3=E$1)*('Giá công thức'!$G$4:$AQ$4=E$2)))} -> 1250 | F11: {=IF(SUMPRODUCT('Giá công thức'!$G$11:$AQ$115*('Giá công thức'!$A$11:$A$115=$B11)*('Giá công thức'!$B$11:$B$115=$C11)*('Giá công thức'!$C$11:$C$115="GB")*('Giá công thức'!$G$3:$AQ$3=F$1)*('Giá công thức'!$G$4:$AQ$4=F$2))=0,NA(),SUMPRODUCT('Giá công thức'!$G$11:$AQ$115*('Giá công thức'!$A$11:$A$115=$B11)*('Giá công thức'!$B$11:$B$115=$C11)*('Giá công thức'!$C$11:$C$115="GB")*('Giá công thức'!$G$3:$AQ$3=F$1)*('Giá công thức'!$G$4:$AQ$4=F$2)))} -> 1250 | G11: {=IF(SUMPRODUCT('Giá công thức'!$G$11:$AQ$115*('Giá công thức'!$A$11:$A$115=$B11)*('Giá công thức'!$B$11:$B$115=$C11)*('Giá công thức'!$C$11:$C$115="GB")*('Giá công thức'!$G$3:$AQ$3=G$1)*('Giá công thức'!$G$4:$AQ$4=G$2))=0,NA(),SUMPRODUCT('Giá công thức'!$G$11:$AQ$115*('Giá công thức'!$A$11:$A$115=$B11)*('Giá công thức'!$B$11:$B$115=$C11)*('Giá công thức'!$C$11:$C$115="GB")*('Giá công thức'!$G$3:$AQ$3=G$1)*('Giá công thức'!$G$4:$AQ$4=G$2)))} -> 1250 | H11: {=IF(SUMPRODUCT('Giá công thức'!$G$11:$AQ$115*('Giá công thức'!$A$11:$A$115=$B11)*('Giá công thức'!$B$11:$B$115=$C11)*('Giá công thức'!$C$11:$C$115="GB")*('Giá công thức'!$G$3:$AQ$3=H$1)*('Giá công thức'!$G$4:$AQ$4=H$2))=0,NA(),SUMPRODUCT('Giá công thức'!$G$11:$AQ$115*('Giá công thức'!$A$11:$A$115=$B11)*('Giá công thức'!$B$11:$B$115=$C11)*('Giá công thức'!$C$11:$C$115="GB")*('Giá công thức'!$G$3:$AQ$3=H$1)*('Giá công thức'!$G$4:$AQ$4=H$2)))} -> 1250 | I11: {=IF(SUMPRODUCT('Giá công thức'!$G$11:$AQ$115*('Giá công thức'!$A$11:$A$115=$B11)*('Giá công thức'!$B$11:$B$115=$C11)*('Giá công thức'!$C$11:$C$115="GB")*('Giá công thức'!$G$3:$AQ$3=I$1)*('Giá công thức'!$G$4:$AQ$4=I$2))=0,NA(),SUMPRODUCT('Giá công thức'!$G$11:$AQ$115*('Giá công thức'!$A$11:$A$115=$B11)*('Giá công thức'!$B$11:$B$115=$C11)*('Giá công thức'!$C$11:$C$115="GB")*('Giá công thức'!$G$3:$AQ$3=I$1)*('Giá công thức'!$G$4:$AQ$4=I$2)))} -> 1250 | J11: {=IF(SUMPRODUCT('Giá công thức'!$G$11:$AQ$115*('Giá công thức'!$A$11:$A$115=$B11)*('Giá công thức'!$B$11:$B$115=$C11)*('Giá công thức'!$C$11:$C$115="GB")*('Giá công thức'!$G$3:$AQ$3=J$1)*('Giá công thức'!$G$4:$AQ$4=J$2))=0,NA(),SUMPRODUCT('Giá công thức'!$G$11:$AQ$115*('Giá công thức'!$A$11:$A$115=$B11)*('Giá công thức'!$B$11:$B$115=$C11)*('Giá công thức'!$C$11:$C$115="GB")*('Giá công thức'!$G$3:$AQ$3=J$1)*('Giá công thức'!$G$4:$AQ$4=J$2)))} -> 1250 | K11: {=IF(SUMPRODUCT('Giá công thức'!$G$11:$AQ$115*('Giá công thức'!$A$11:$A$115=$B11)*('Giá công thức'!$B$11:$B$115=$C11)*('Giá công thức'!$C$11:$C$115="GB")*('Giá công thức'!$G$3:$AQ$3=K$1)*('Giá công thức'!$G$4:$AQ$4=K$2))=0,NA(),SUMPRODUCT('Giá công thức'!$G$11:$AQ$115*('Giá công thức'!$A$11:$A$115=$B11)*('Giá công thức'!$B$11:$B$115=$C11)*('Giá công thức'!$C$11:$C$115="GB")*('Giá công thức'!$G$3:$AQ$3=K$1)*('Giá công thức'!$G$4:$AQ$4=K$2)))} -> 1330 | L11: {=IF(SUMPRODUCT('Giá công thức'!$G$11:$AQ$115*('Giá công thức'!$A$11:$A$115=$B11)*('Giá công thức'!$B$11:$B$115=$C11)*('Giá công thức'!$C$11:$C$115="GB")*('Giá công thức'!$G$3:$AQ$3=L$1)*('Giá công thức'!$G$4:$AQ$4=L$2))=0,NA(),SUMPRODUCT('Giá công thức'!$G$11:$AQ$115*('Giá công thức'!$A$11:$A$115=$B11)*('Giá công thức'!$B$11:$B$115=$C11)*('Giá công thức'!$C$11:$C$115="GB")*('Giá công thức'!$G$3:$AQ$3=L$1)*('Giá công thức'!$G$4:$AQ$4=L$2)))} -> 1330 | ... AH11: {=IF(SUMPRODUCT('Giá công thức'!$G$11:$AQ$115*('Giá công thức'!$A$11:$A$115=$B11)*('Giá công thức'!$B$11:$B$115=$C11)*('Giá công thức'!$C$11:$C$115="GB")*('Giá công thức'!$G$3:$AQ$3=AH$1)*('Giá công thức'!$G$4:$AQ$4=AH$2))=0,NA(),SUMPRODUCT('Giá công thức'!$G$11:$AQ$115*('Giá công thức'!$A$11:$A$115=$B11)*('Giá công thức'!$B$11:$B$115=$C11)*('Giá công thức'!$C$11:$C$115="GB")*('Giá công thức'!$G$3:$AQ$3=AH$1)*('Giá công thức'!$G$4:$AQ$4=AH$2)))} -> 1290 | AO11: =INDEX($E11:$AN11,MATCH("X",$E$3:$AN$3,0)) -> 1290
A12: 110000354 | C12: 110000354 | D12: Giá duyệt | E12: {=SUMPRODUCT(General_Data*(Code_General_Data=$A12)*(Year=E$1)*(Month=E$2))} -> 1250 | F12: {=SUMPRODUCT(General_Data*(Code_General_Data=$A12)*(Year=F$1)*(Month=F$2))} -> 1250 | G12: {=SUMPRODUCT(General_Data*(Code_General_Data=$A12)*(Year=G$1)*(Month=G$2))} -> 1250 | H12: {=SUMPRODUCT(General_Data*(Code_General_Data=$A12)*(Year=H$1)*(Month=H$2))} -> 1250 | I12: {=SUMPRODUCT(General_Data*(Code_General_Data=$A12)*(Year=I$1)*(Month=I$2))} -> 1300 | J12: {=SUMPRODUCT(General_Data*(Code_General_Data=$A12)*(Year=J$1)*(Month=J$2))} -> 1300 | K12: {=SUMPRODUCT(General_Data*(Code_General_Data=$A12)*(Year=K$1)*(Month=K$2))} -> 1300 | L12: {=SUMPRODUCT(General_Data*(Code_General_Data=$A12)*(Year=L$1)*(Month=L$2))} -> 1300 | ... AH12: {=SUMPRODUCT(General_Data*(Code_General_Data=$A12)*(Year=AH$1)*(Month=AH$2))} -> 1350 | AO12: =INDEX($E12:$AN12,MATCH("X",$E$3:$AN$3,0)) -> 1350
A13: PETVirgin | D13: Giá chính phẩm | E13: {=SUMPRODUCT(General_Data*(Code_General_Data=$A13)*(Year=E$1)*(Month=E$2))} -> 930 | F13: {=SUMPRODUCT(General_Data*(Code_General_Data=$A13)*(Year=F$1)*(Month=F$2))} -> 943.33333 | G13: {=SUMPRODUCT(General_Data*(Code_General_Data=$A13)*(Year=G$1)*(Month=G$2))} -> 940 | H13: {=SUMPRODUCT(General_Data*(Code_General_Data=$A13)*(Year=H$1)*(Month=H$2))} -> 940 | I13: {=SUMPRODUCT(General_Data*(Code_General_Data=$A13)*(Year=I$1)*(Month=I$2))} -> 942 | J13: {=SUMPRODUCT(General_Data*(Code_General_Data=$A13)*(Year=J$1)*(Month=J$2))} -> 950 | K13: {=SUMPRODUCT(General_Data*(Code_General_Data=$A13)*(Year=K$1)*(Month=K$2))} -> 947.5 | L13: {=SUMPRODUCT(General_Data*(Code_General_Data=$A13)*(Year=L$1)*(Month=L$2))} -> 930 | ... AH13: {=SUMPRODUCT(General_Data*(Code_General_Data=$A13)*(Year=AH$1)*(Month=AH$2))} -> 1190 | AO13: =INDEX($E13:$AN13,MATCH("X",$E$3:$AN$3,0)) -> 1190
D14: Chênh lệch | E14: =E12-E13 -> 320 | F14: =F12-F13 -> 306.66667 | G14: =G12-G13 -> 310 | H14: =H12-H13 -> 310 | I14: =I12-I13 -> 358 | J14: =J12-J13 -> 350 | K14: =K12-K13 -> 352.5 | L14: =L12-L13 -> 370 | ... AH14: =AH12-AH13 -> 160
D15: %Chênh lệch | E15: =IFERROR(E14/E13,0) -> 0.34408602 | F15: =IFERROR(F14/F13,0) -> 0.32508834 | G15: =IFERROR(G14/G13,0) -> 0.32978723 | H15: =IFERROR(H14/H13,0) -> 0.32978723 | I15: =IFERROR(I14/I13,0) -> 0.38004246 | J15: =IFERROR(J14/J13,0) -> 0.36842105 | K15: =IFERROR(K14/K13,0) -> 0.37203166 | L15: =IFERROR(L14/L13,0) -> 0.39784946 | ... AH15: =IFERROR(AH14/AH13,0) -> 0.13445378 | AO15: =IFERROR(AO14/AO13,0) -> 0
A16: 110000354-GVXK-USD | C16: 110000329 | D16: Giá vốn (bao gồm CPBH,CPQLDN,lãi vay phân bổ) | E16: {=SUMPRODUCT(General_Data*(Code_General_Data=$A16)*(Year=E$1)*(Month=E$2))} -> 938.00333 | F16: {=SUMPRODUCT(General_Data*(Code_General_Data=$A16)*(Year=F$1)*(Month=F$2))} -> 982.91021 | G16: {=SUMPRODUCT(General_Data*(Code_General_Data=$A16)*(Year=G$1)*(Month=G$2))} -> 970.37667 | H16: {=SUMPRODUCT(General_Data*(Code_General_Data=$A16)*(Year=H$1)*(Month=H$2))} -> 957.76248 | I16: {=SUMPRODUCT(General_Data*(Code_General_Data=$A16)*(Year=I$1)*(Month=I$2))} -> 996.74618 | J16: {=SUMPRODUCT(General_Data*(Code_General_Data=$A16)*(Year=J$1)*(Month=J$2))} -> 973.77248 | K16: {=SUMPRODUCT(General_Data*(Code_General_Data=$A16)*(Year=K$1)*(Month=K$2))} -> 969.69531 | L16: {=SUMPRODUCT(General_Data*(Code_General_Data=$A16)*(Year=L$1)*(Month=L$2))} -> 1006.8708 | ... AH16: {=SUMPRODUCT(General_Data*(Code_General_Data=$A16)*(Year=AH$1)*(Month=AH$2))} -> 944.59825 | AO16: =INDEX($E16:$AN16,MATCH("X",$E$3:$AN$3,0)) -> 944.59825
D17: Chênh lệch-Line Drop | E17: =E12 -> 1250 | F17: =F12 -> 1250 | G17: =G12 -> 1250 | H17: =H12 -> 1250 | I17: =I12 -> 1300 | J17: =J12 -> 1300 | K17: =K12 -> 1300 | L17: =L12 -> 1300 | ... AH17: =AH12 -> 1350
D18: Chênh lệch-Label | E18: =E13+E14/2 -> 1090 | F18: =F13+F14/2 -> 1096.6667 | G18: =G13+G14/2 -> 1095 | H18: =H13+H14/2 -> 1095 | I18: =I13+I14/2 -> 1121 | J18: =J13+J14/2 -> 1125 | K18: =K13+K14/2 -> 1123.75 | L18: =L13+L14/2 -> 1115 | ... AH18: =AH13+AH14/2 -> 1270
D19: Giá duyệt-Area | E19: =E12 -> 1250 | F19: =F12 -> 1250 | G19: =G12 -> 1250 | H19: =H12 -> 1250 | I19: =I12 -> 1300 | J19: =J12 -> 1300 | K19: =K12 -> 1300 | L19: =L12 -> 1300 | ... AH19: =AH12 -> 1350
D20: Giá chính phẩm-Area | E20: =E13 -> 930 | F20: =F13 -> 943.33333 | G20: =G13 -> 940 | H20: =H13 -> 940 | I20: =I13 -> 942 | J20: =J13 -> 950 | K20: =K13 -> 947.5 | L20: =L13 -> 930 | ... AH20: =AH13 -> 1190
D21: Niagara-Label | E21: =IFERROR(E8,0) -> 1162 | F21: =IF(AND(IFERROR(F8,0)=IFERROR(E8,0),IFERROR(E8,0)=IFERROR(G8,0)),0,IFERROR(F8,0)) -> 0 | G21: =IF(AND(IFERROR(G8,0)=IFERROR(F8,0),IFERROR(F8,0)=IFERROR(H8,0)),0,IFERROR(G8,0)) -> 0 | H21: =IF(AND(IFERROR(H8,0)=IFERROR(G8,0),IFERROR(G8,0)=IFERROR(I8,0)),0,IFERROR(H8,0)) -> 0 | I21: =IF(AND(IFERROR(I8,0)=IFERROR(H8,0),IFERROR(H8,0)=IFERROR(J8,0)),0,IFERROR(I8,0)) -> 1162 | J21: =IF(AND(IFERROR(J8,0)=IFERROR(I8,0),IFERROR(I8,0)=IFERROR(K8,0)),0,IFERROR(J8,0)) -> 1162.8865 | K21: =IF(AND(IFERROR(K8,0)=IFERROR(J8,0),IFERROR(J8,0)=IFERROR(L8,0)),0,IFERROR(K8,0)) -> 1176.184 | L21: =IF(AND(IFERROR(L8,0)=IFERROR(K8,0),IFERROR(K8,0)=IFERROR(M8,0)),0,IFERROR(L8,0)) -> 1187.7085 | M21: =IF(AND(IFERROR(M8,0)=IFERROR(L8,0),IFERROR(L8,0)=IFERROR(N8,0)),0,IFERROR(M8,0)) -> 1203.961 | ... AE21: =IF(AND(IFERROR(AE8,0)=IFERROR(AD8,0),IFERROR(AD8,0)=IFERROR(AF8,0)),0,IFERROR(AE8,0)) -> 1025.3312 | AF21: =IF(AF$3="X",IFERROR(AF8,0),IF(AND(IFERROR(AF8,0)=IFERROR(AE8,0),IFERROR(AE8,0)=IFERROR(AG8,0)),0,IFERROR(AF8,0))) -> 1182.685 | AG21: =IF(AG$3="X",IFERROR(AG8,0),IF(AND(IFERROR(AG8,0)=IFERROR(AF8,0),IFERROR(AF8,0)=IFERROR(AH8,0)),0,IFERROR(AG8,0))) -> 0 | AH21: =IF(AH$3="X",IFERROR(AH8,0),IF(AND(IFERROR(AH8,0)=IFERROR(AG8,0),IFERROR(AG8,0)=IFERROR(AI8,0)),0,IFERROR(AH8,0))) -> 1182.685 | AO21: NIAGARA
D22: Shepley-Label | AB22: =IFERROR(AB9,0) -> 1063.5 | AC22: =IF(IFERROR(AC9,0)=AB9,0,AC9) -> 1083.2 | AD22: =IF(IFERROR(AD9,0)=AC9,0,AD9) -> 1053.65 | AE22: =IF(IFERROR(AE9,0)=AD9,0,AE9) -> 1064.7313 | AF22: =IF(AF$3="X",IFERROR(AF9,0),IF(AND(IFERROR(AF9,0)=IFERROR(AE9,0),IFERROR(AE9,0)=IFERROR(AG9,0)),0,IFERROR(AF9,0))) -> 1112.75 | AG22: =IF(AG$3="X",IFERROR(AG9,0),IF(AND(IFERROR(AG9,0)=IFERROR(AF9,0),IFERROR(AF9,0)=IFERROR(AH9,0)),0,IFERROR(AG9,0))) -> 0 | AH22: =IF(AH$3="X",IFERROR(AH9,0),IF(AND(IFERROR(AH9,0)=IFERROR(AG9,0),IFERROR(AG9,0)=IFERROR(AI9,0)),0,IFERROR(AH9,0))) -> 1112.75 | AO22: SHEPLEY
D23: Unilever-Label | E23: =IFERROR(E10,0) -> 1307.7959 | F23: =IF(AND(IFERROR(F10,0)=IFERROR(E10,0),IFERROR(E10,0)=IFERROR(G10,0)),0,IFERROR(F10,0)) -> 0 | G23: =IF(AND(IFERROR(G10,0)=IFERROR(F10,0),IFERROR(F10,0)=IFERROR(H10,0)),0,IFERROR(G10,0)) -> 0 | H23: =IF(AND(IFERROR(H10,0)=IFERROR(G10,0),IFERROR(G10,0)=IFERROR(I10,0)),0,IFERROR(H10,0)) -> 0 | I23: =IF(AND(IFERROR(I10,0)=IFERROR(H10,0),IFERROR(H10,0)=IFERROR(J10,0)),0,IFERROR(I10,0)) -> 0 | J23: =IF(AND(IFERROR(J10,0)=IFERROR(I10,0),IFERROR(I10,0)=IFERROR(K10,0)),0,IFERROR(J10,0)) -> 1307.7959 | K23: =IF(AND(IFERROR(K10,0)=IFERROR(J10,0),IFERROR(J10,0)=IFERROR(L10,0)),0,IFERROR(K10,0)) -> 1308.04 | L23: =IF(AND(IFERROR(L10,0)=IFERROR(K10,0),IFERROR(K10,0)=IFERROR(M10,0)),0,IFERROR(L10,0)) -> 0 | M23: =IF(AND(IFERROR(M10,0)=IFERROR(L10,0),IFERROR(L10,0)=IFERROR(N10,0)),0,IFERROR(M10,0)) -> 1308.04 | ... AE23: =IF(AND(IFERROR(AE10,0)=IFERROR(AD10,0),IFERROR(AD10,0)=IFERROR(AF10,0)),0,IFERROR(AE10,0)) -> 1245 | AF23: =IF(AF$3="X",IFERROR(AF10,0),IF(AND(IFERROR(AF10,0)=IFERROR(AE10,0),IFERROR(AE10,0)=IFERROR(AG10,0)),0,IFERROR(AF10,0))) -> 1185 | AG23: =IF(AG$3="X",IFERROR(AG10,0),IF(AND(IFERROR(AG10,0)=IFERROR(AF10,0),IFERROR(AF10,0)=IFERROR(AH10,0)),0,IFERROR(AG10,0))) -> 0 | AH23: =IF(AH$3="X",IFERROR(AH10,0),IF(AND(IFERROR(AH10,0)=IFERROR(AG10,0),IFERROR(AG10,0)=IFERROR(AI10,0)),0,IFERROR(AH10,0))) -> 1185 | AO23: UNILERVER
D24: Laive-Label | E24: =IFERROR(E11,0) -> 1250 | F24: =IF(AND(IFERROR(F11,0)=IFERROR(E11,0),IFERROR(E11,0)=IFERROR(G11,0)),0,IFERROR(F11,0)) -> 0 | G24: =IF(AND(IFERROR(G11,0)=IFERROR(F11,0),IFERROR(F11,0)=IFERROR(H11,0)),0,IFERROR(G11,0)) -> 0 | H24: =IF(AND(IFERROR(H11,0)=IFERROR(G11,0),IFERROR(G11,0)=IFERROR(I11,0)),0,IFERROR(H11,0)) -> 0 | I24: =IF(AND(IFERROR(I11,0)=IFERROR(H11,0),IFERROR(H11,0)=IFERROR(J11,0)),0,IFERROR(I11,0)) -> 0 | J24: =IF(AND(IFERROR(J11,0)=IFERROR(I11,0),IFERROR(I11,0)=IFERROR(K11,0)),0,IFERROR(J11,0)) -> 1250 | K24: =IF(AND(IFERROR(K11,0)=IFERROR(J11,0),IFERROR(J11,0)=IFERROR(L11,0)),0,IFERROR(K11,0)) -> 1330 | L24: =IF(AND(IFERROR(L11,0)=IFERROR(K11,0),IFERROR(K11,0)=IFERROR(M11,0)),0,IFERROR(L11,0)) -> 0 | M24: =IF(AND(IFERROR(M11,0)=IFERROR(L11,0),IFERROR(L11,0)=IFERROR(N11,0)),0,IFERROR(M11,0)) -> 0 | ... AE24: =IF(AND(IFERROR(AE11,0)=IFERROR(AD11,0),IFERROR(AD11,0)=IFERROR(AF11,0)),0,IFERROR(AE11,0)) -> 0 | AF24: =IF(AF$3="X",IFERROR(AF11,0),IF(AND(IFERROR(AF11,0)=IFERROR(AE11,0),IFERROR(AE11,0)=IFERROR(AG11,0)),0,IFERROR(AF11,0))) -> 0 | AG24: =IF(AG$3="X",IFERROR(AG11,0),IF(AND(IFERROR(AG11,0)=IFERROR(AF11,0),IFERROR(AF11,0)=IFERROR(AH11,0)),0,IFERROR(AG11,0))) -> 0 | AH24: =IF(AH$3="X",IFERROR(AH11,0),IF(AND(IFERROR(AH11,0)=IFERROR(AG11,0),IFERROR(AG11,0)=IFERROR(AI11,0)),0,IFERROR(AH11,0))) -> 1290 | AO24: LAVIE
D25: Giá duyệt-Label | E25: =IFERROR(E12,0) -> 1250 | F25: =IF(AND(IFERROR(F12,0)=IFERROR(E12,0),IFERROR(E12,0)=IFERROR(G12,0)),0,IFERROR(F12,0)) -> 0 | G25: =IF(AND(IFERROR(G12,0)=IFERROR(F12,0),IFERROR(F12,0)=IFERROR(H12,0)),0,IFERROR(G12,0)) -> 0 | H25: =IF(AND(IFERROR(H12,0)=IFERROR(G12,0),IFERROR(G12,0)=IFERROR(I12,0)),0,IFERROR(H12,0)) -> 1250 | I25: =IF(AND(IFERROR(I12,0)=IFERROR(H12,0),IFERROR(H12,0)=IFERROR(J12,0)),0,IFERROR(I12,0)) -> 1300 | J25: =IF(AND(IFERROR(J12,0)=IFERROR(I12,0),IFERROR(I12,0)=IFERROR(K12,0)),0,IFERROR(J12,0)) -> 0 | K25: =IF(AND(IFERROR(K12,0)=IFERROR(J12,0),IFERROR(J12,0)=IFERROR(L12,0)),0,IFERROR(K12,0)) -> 0 | L25: =IF(AND(IFERROR(L12,0)=IFERROR(K12,0),IFERROR(K12,0)=IFERROR(M12,0)),0,IFERROR(L12,0)) -> 1300 | M25: =IF(AND(IFERROR(M12,0)=IFERROR(L12,0),IFERROR(L12,0)=IFERROR(N12,0)),0,IFERROR(M12,0)) -> 1310 | ... AE25: =IF(AND(IFERROR(AE12,0)=IFERROR(AD12,0),IFERROR(AD12,0)=IFERROR(AF12,0)),0,IFERROR(AE12,0)) -> 1160 | AF25: =IF(AF$3="X",IFERROR(AF12,0),IF(AND(IFERROR(AF12,0)=IFERROR(AE12,0),IFERROR(AE12,0)=IFERROR(AG12,0)),0,IFERROR(AF12,0))) -> 1280 | AG25: =IF(AG$3="X",IFERROR(AG12,0),IF(AND(IFERROR(AG12,0)=IFERROR(AF12,0),IFERROR(AF12,0)=IFERROR(AH12,0)),0,IFERROR(AG12,0))) -> 1380 | AH25: =IF(AH$3="X",IFERROR(AH12,0),IF(AND(IFERROR(AH12,0)=IFERROR(AG12,0),IFERROR(AG12,0)=IFERROR(AI12,0)),0,IFERROR(AH12,0))) -> 1350 | AO25: Giá duyệt
D26: Giá chính phẩm-Label | E26: =IFERROR(E13,0) -> 930 | F26: =IF(AND(IFERROR(F13,0)=IFERROR(E13,0),IFERROR(E13,0)=IFERROR(G13,0)),0,IFERROR(F13,0)) -> 943.33333 | G26: =IF(AND(IFERROR(G13,0)=IFERROR(F13,0),IFERROR(F13,0)=IFERROR(H13,0)),0,IFERROR(G13,0)) -> 940 | H26: =IF(AND(IFERROR(H13,0)=IFERROR(G13,0),IFERROR(G13,0)=IFERROR(I13,0)),0,IFERROR(H13,0)) -> 940 | I26: =IF(AND(IFERROR(I13,0)=IFERROR(H13,0),IFERROR(H13,0)=IFERROR(J13,0)),0,IFERROR(I13,0)) -> 942 | J26: =IF(AND(IFERROR(J13,0)=IFERROR(I13,0),IFERROR(I13,0)=IFERROR(K13,0)),0,IFERROR(J13,0)) -> 950 | K26: =IF(AND(IFERROR(K13,0)=IFERROR(J13,0),IFERROR(J13,0)=IFERROR(L13,0)),0,IFERROR(K13,0)) -> 947.5 | L26: =IF(AND(IFERROR(L13,0)=IFERROR(K13,0),IFERROR(K13,0)=IFERROR(M13,0)),0,IFERROR(L13,0)) -> 930 | M26: =IF(AND(IFERROR(M13,0)=IFERROR(L13,0),IFERROR(L13,0)=IFERROR(N13,0)),0,IFERROR(M13,0)) -> 880 | ... AE26: =IF(AND(IFERROR(AE13,0)=IFERROR(AD13,0),IFERROR(AD13,0)=IFERROR(AF13,0)),0,IFERROR(AE13,0)) -> 1109 | AF26: =IF(AF$3="X",IFERROR(AF13,0),IF(AND(IFERROR(AF13,0)=IFERROR(AE13,0),IFERROR(AE13,0)=IFERROR(AG13,0)),0,IFERROR(AF13,0))) -> 1194 | AG26: =IF(AG$3="X",IFERROR(AG13,0),IF(AND(IFERROR(AG13,0)=IFERROR(AF13,0),IFERROR(AF13,0)=IFERROR(AH13,0)),0,IFERROR(AG13,0))) -> 1216 | AH26: =IF(AH$3="X",IFERROR(AH13,0),IF(AND(IFERROR(AH13,0)=IFERROR(AG13,0),IFERROR(AG13,0)=IFERROR(AI13,0)),0,IFERROR(AH13,0))) -> 1190 | AO26: Giá chính phẩm
D27: Giá vốn (bao gồm CPBH,CPQLDN,lãi vay phân bổ)-Label | E27: =IFERROR(E16,0) -> 938.00333 | F27: =IF(AND(IFERROR(F16,0)=IFERROR(E16,0),IFERROR(E16,0)=IFERROR(G16,0)),0,IFERROR(F16,0)) -> 982.91021 | G27: =IF(AND(IFERROR(G16,0)=IFERROR(F16,0),IFERROR(F16,0)=IFERROR(H16,0)),0,IFERROR(G16,0)) -> 970.37667 | H27: =IF(AND(IFERROR(H16,0)=IFERROR(G16,0),IFERROR(G16,0)=IFERROR(I16,0)),0,IFERROR(H16,0)) -> 957.76248 | I27: =IF(AND(IFERROR(I16,0)=IFERROR(H16,0),IFERROR(H16,0)=IFERROR(J16,0)),0,IFERROR(I16,0)) -> 996.74618 | J27: =IF(AND(IFERROR(J16,0)=IFERROR(I16,0),IFERROR(I16,0)=IFERROR(K16,0)),0,IFERROR(J16,0)) -> 973.77248 | K27: =IF(AND(IFERROR(K16,0)=IFERROR(J16,0),IFERROR(J16,0)=IFERROR(L16,0)),0,IFERROR(K16,0)) -> 969.69531 | L27: =IF(AND(IFERROR(L16,0)=IFERROR(K16,0),IFERROR(K16,0)=IFERROR(M16,0)),0,IFERROR(L16,0)) -> 1006.8708 | M27: =IF(AND(IFERROR(M16,0)=IFERROR(L16,0),IFERROR(L16,0)=IFERROR(N16,0)),0,IFERROR(M16,0)) -> 1018.6405 | ... AH27: =IF(AND(IFERROR(AH16,0)=IFERROR(AG16,0),IFERROR(AG16,0)=IFERROR(AI16,0)),0,IFERROR(AH16,0)) -> 944.59825 | AO27: Giá vốn (*)
F28: =IF(AND(IFERROR(F16,0)/IFERROR(E16,0)<1.001,IFERROR(G16,0)/IFERROR(F16,0)<1.001),0,IFERROR(F16,0)) -> 982.91021
C29: 110000355 | D29: iSS01G
E30: 2024 | Q30: 2025 | AC30: 2026
E31: 1 | F31: 2 | G31: 3 | H31: 4 | I31: 5 | J31: 6 | K31: 7 | L31: 8 | M31: 9 | N31: 10 | O31: 11 | P31: 12 | Q31: 1 | R31: 2 | S31: 3 | T31: 4 | U31: 5 | V31: 6 | W31: 7 | X31: 8 | Y31: 9 | Z31: 10 | AA31: 11 | AB31: 12 | AC31: 1 | AD31: 2 | AE31: 3 | AF31: 4 | AG31: 5 | AH31: 6 | AI31: 7 | AJ31: 8 | AK31: 9 | AL31: 10 | AM31: 11 | AN31: 12
B32: 200332 | C32: 110000355 | D32: OUTEIRINHO | E32: {=IF(SUMPRODUCT('Giá công thức'!$G$11:$AQ$115*('Giá công thức'!$A$11:$A$115=$B32)*('Giá công thức'!$B$11:$B$115=$C32)*('Giá công thức'!$C$11:$C$115="GB")*('Giá công thức'!$G$3:$AQ$3=E$1)*('Giá công thức'!$G$4:$AQ$4=E$2))=0,NA(),SUMPRODUCT('Giá công thức'!$G$11:$AQ$115*('Giá công thức'!$A$11:$A$115=$B32)*('Giá công thức'!$B$11:$B$115=$C32)*('Giá công thức'!$C$11:$C$115="GB")*('Giá công thức'!$G$3:$AQ$3=E$1)*('Giá công thức'!$G$4:$AQ$4=E$2)))} -> #N/A | F32: {=IF(SUMPRODUCT('Giá công thức'!$G$11:$AQ$115*('Giá công thức'!$A$11:$A$115=$B32)*('Giá công thức'!$B$11:$B$115=$C32)*('Giá công thức'!$C$11:$C$115="GB")*('Giá công thức'!$G$3:$AQ$3=F$1)*('Giá công thức'!$G$4:$AQ$4=F$2))=0,NA(),SUMPRODUCT('Giá công thức'!$G$11:$AQ$115*('Giá công thức'!$A$11:$A$115=$B32)*('Giá công thức'!$B$11:$B$115=$C32)*('Giá công thức'!$C$11:$C$115="GB")*('Giá công thức'!$G$3:$AQ$3=F$1)*('Giá công thức'!$G$4:$AQ$4=F$2)))} -> #N/A | G32: {=IF(SUMPRODUCT('Giá công thức'!$G$11:$AQ$115*('Giá công thức'!$A$11:$A$115=$B32)*('Giá công thức'!$B$11:$B$115=$C32)*('Giá công thức'!$C$11:$C$115="GB")*('Giá công thức'!$G$3:$AQ$3=G$1)*('Giá công thức'!$G$4:$AQ$4=G$2))=0,NA(),SUMPRODUCT('Giá công thức'!$G$11:$AQ$115*('Giá công thức'!$A$11:$A$115=$B32)*('Giá công thức'!$B$11:$B$115=$C32)*('Giá công thức'!$C$11:$C$115="GB")*('Giá công thức'!$G$3:$AQ$3=G$1)*('Giá công thức'!$G$4:$AQ$4=G$2)))} -> #N/A | H32: {=IF(SUMPRODUCT('Giá công thức'!$G$11:$AQ$115*('Giá công thức'!$A$11:$A$115=$B32)*('Giá công thức'!$B$11:$B$115=$C32)*('Giá công thức'!$C$11:$C$115="GB")*('Giá công thức'!$G$3:$AQ$3=H$1)*('Giá công thức'!$G$4:$AQ$4=H$2))=0,NA(),SUMPRODUCT('Giá công thức'!$G$11:$AQ$115*('Giá công thức'!$A$11:$A$115=$B32)*('Giá công thức'!$B$11:$B$115=$C32)*('Giá công thức'!$C$11:$C$115="GB")*('Giá công thức'!$G$3:$AQ$3=H$1)*('Giá công thức'!$G$4:$AQ$4=H$2)))} -> #N/A | I32: {=IF(SUMPRODUCT('Giá công thức'!$G$11:$AQ$115*('Giá công thức'!$A$11:$A$115=$B32)*('Giá công thức'!$B$11:$B$115=$C32)*('Giá công thức'!$C$11:$C$115="GB")*('Giá công thức'!$G$3:$AQ$3=I$1)*('Giá công thức'!$G$4:$AQ$4=I$2))=0,NA(),SUMPRODUCT('Giá công thức'!$G$11:$AQ$115*('Giá công thức'!$A$11:$A$115=$B32)*('Giá công thức'!$B$11:$B$115=$C32)*('Giá công thức'!$C$11:$C$115="GB")*('Giá công thức'!$G$3:$AQ$3=I$1)*('Giá công thức'!$G$4:$AQ$4=I$2)))} -> #N/A | J32: {=IF(SUMPRODUCT('Giá công thức'!$G$11:$AQ$115*('Giá công thức'!$A$11:$A$115=$B32)*('Giá công thức'!$B$11:$B$115=$C32)*('Giá công thức'!$C$11:$C$115="GB")*('Giá công thức'!$G$3:$AQ$3=J$1)*('Giá công thức'!$G$4:$AQ$4=J$2))=0,NA(),SUMPRODUCT('Giá công thức'!$G$11:$AQ$115*('Giá công thức'!$A$11:$A$115=$B32)*('Giá công thức'!$B$11:$B$115=$C32)*('Giá công thức'!$C$11:$C$115="GB")*('Giá công thức'!$G$3:$AQ$3=J$1)*('Giá công thức'!$G$4:$AQ$4=J$2)))} -> #N/A | K32: {=IF(SUMPRODUCT('Giá công thức'!$G$11:$AQ$115*('Giá công thức'!$A$11:$A$115=$B32)*('Giá công thức'!$B$11:$B$115=$C32)*('Giá công thức'!$C$11:$C$115="GB")*('Giá công thức'!$G$3:$AQ$3=K$1)*('Giá công thức'!$G$4:$AQ$4=K$2))=0,NA(),SUMPRODUCT('Giá công thức'!$G$11:$AQ$115*('Giá công thức'!$A$11:$A$115=$B32)*('Giá công thức'!$B$11:$B$115=$C32)*('Giá công thức'!$C$11:$C$115="GB")*('Giá công thức'!$G$3:$AQ$3=K$1)*('Giá công thức'!$G$4:$AQ$4=K$2)))} -> #N/A | L32: {=IF(SUMPRODUCT('Giá công thức'!$G$11:$AQ$115*('Giá công thức'!$A$11:$A$115=$B32)*('Giá công thức'!$B$11:$B$115=$C32)*('Giá công thức'!$C$11:$C$115="GB")*('Giá công thức'!$G$3:$AQ$3=L$1)*('Giá công thức'!$G$4:$AQ$4=L$2))=0,NA(),SUMPRODUCT('Giá công thức'!$G$11:$AQ$115*('Giá công thức'!$A$11:$A$115=$B32)*('Giá công thức'!$B$11:$B$115=$C32)*('Giá công thức'!$C$11:$C$115="GB")*('Giá công thức'!$G$3:$AQ$3=L$1)*('Giá công thức'!$G$4:$AQ$4=L$2)))} -> #N/A | ... AH32: {=IF(SUMPRODUCT('Giá công thức'!$G$11:$AQ$115*('Giá công thức'!$A$11:$A$115=$B32)*('Giá công thức'!$B$11:$B$115=$C32)*('Giá công thức'!$C$11:$C$115="GB")*('Giá công thức'!$G$3:$AQ$3=AH$1)*('Giá công thức'!$G$4:$AQ$4=AH$2))=0,NA(),SUMPRODUCT('Giá công thức'!$G$11:$AQ$115*('Giá công thức'!$A$11:$A$115=$B32)*('Giá công thức'!$B$11:$B$115=$C32)*('Giá công thức'!$C$11:$C$115="GB")*('Giá công thức'!$G$3:$AQ$3=AH$1)*('Giá công thức'!$G$4:$AQ$4=AH$2)))} -> #N/A | AO32: 1230
B33: 105194 | C33: 110000355 | D33: SUNTORY VIET NAM | E33: {=IF(SUMPRODUCT('Giá công thức'!$G$11:$AQ$115*('Giá công thức'!$A$11:$A$115=$B33)*('Giá công thức'!$B$11:$B$115=$C33)*('Giá công thức'!$C$11:$C$115="GB")*('Giá công thức'!$G$3:$AQ$3=E$1)*('Giá công thức'!$G$4:$AQ$4=E$2))=0,NA(),SUMPRODUCT('Giá công thức'!$G$11:$AQ$115*('Giá công thức'!$A$11:$A$115=$B33)*('Giá công thức'!$B$11:$B$115=$C33)*('Giá công thức'!$C$11:$C$115="GB")*('Giá công thức'!$G$3:$AQ$3=E$1)*('Giá công thức'!$G$4:$AQ$4=E$2)))} -> 1320 | F33: {=IF(SUMPRODUCT('Giá công thức'!$G$11:$AQ$115*('Giá công thức'!$A$11:$A$115=$B33)*('Giá công thức'!$B$11:$B$115=$C33)*('Giá công thức'!$C$11:$C$115="GB")*('Giá công thức'!$G$3:$AQ$3=F$1)*('Giá công thức'!$G$4:$AQ$4=F$2))=0,NA(),SUMPRODUCT('Giá công thức'!$G$11:$AQ$115*('Giá công thức'!$A$11:$A$115=$B33)*('Giá công thức'!$B$11:$B$115=$C33)*('Giá công thức'!$C$11:$C$115="GB")*('Giá công thức'!$G$3:$AQ$3=F$1)*('Giá công thức'!$G$4:$AQ$4=F$2)))} -> 1327.5 | G33: {=IF(SUMPRODUCT('Giá công thức'!$G$11:$AQ$115*('Giá công thức'!$A$11:$A$115=$B33)*('Giá công thức'!$B$11:$B$115=$C33)*('Giá công thức'!$C$11:$C$115="GB")*('Giá công thức'!$G$3:$AQ$3=G$1)*('Giá công thức'!$G$4:$AQ$4=G$2))=0,NA(),SUMPRODUCT('Giá công thức'!$G$11:$AQ$115*('Giá công thức'!$A$11:$A$115=$B33)*('Giá công thức'!$B$11:$B$115=$C33)*('Giá công thức'!$C$11:$C$115="GB")*('Giá công thức'!$G$3:$AQ$3=G$1)*('Giá công thức'!$G$4:$AQ$4=G$2)))} -> 1340 | H33: {=IF(SUMPRODUCT('Giá công thức'!$G$11:$AQ$115*('Giá công thức'!$A$11:$A$115=$B33)*('Giá công thức'!$B$11:$B$115=$C33)*('Giá công thức'!$C$11:$C$115="GB")*('Giá công thức'!$G$3:$AQ$3=H$1)*('Giá công thức'!$G$4:$AQ$4=H$2))=0,NA(),SUMPRODUCT('Giá công thức'!$G$11:$AQ$115*('Giá công thức'!$A$11:$A$115=$B33)*('Giá công thức'!$B$11:$B$115=$C33)*('Giá công thức'!$C$11:$C$115="GB")*('Giá công thức'!$G$3:$AQ$3=H$1)*('Giá công thức'!$G$4:$AQ$4=H$2)))} -> 1342.5 | I33: {=IF(SUMPRODUCT('Giá công thức'!$G$11:$AQ$115*('Giá công thức'!$A$11:$A$115=$B33)*('Giá công thức'!$B$11:$B$115=$C33)*('Giá công thức'!$C$11:$C$115="GB")*('Giá công thức'!$G$3:$AQ$3=I$1)*('Giá công thức'!$G$4:$AQ$4=I$2))=0,NA(),SUMPRODUCT('Giá công thức'!$G$11:$AQ$115*('Giá công thức'!$A$11:$A$115=$B33)*('Giá công thức'!$B$11:$B$115=$C33)*('Giá công thức'!$C$11:$C$115="GB")*('Giá công thức'!$G$3:$AQ$3=I$1)*('Giá công thức'!$G$4:$AQ$4=I$2)))} -> 1346.5 | J33: {=IF(SUMPRODUCT('Giá công thức'!$G$11:$AQ$115*('Giá công thức'!$A$11:$A$115=$B33)*('Giá công thức'!$B$11:$B$115=$C33)*('Giá công thức'!$C$11:$C$115="GB")*('Giá công thức'!$G$3:$AQ$3=J$1)*('Giá công thức'!$G$4:$AQ$4=J$2))=0,NA(),SUMPRODUCT('Giá công thức'!$G$11:$AQ$115*('Giá công thức'!$A$11:$A$115=$B33)*('Giá công thức'!$B$11:$B$115=$C33)*('Giá công thức'!$C$11:$C$115="GB")*('Giá công thức'!$G$3:$AQ$3=J$1)*('Giá công thức'!$G$4:$AQ$4=J$2)))} -> 1361.5 | K33: {=IF(SUMPRODUCT('Giá công thức'!$G$11:$AQ$115*('Giá công thức'!$A$11:$A$115=$B33)*('Giá công thức'!$B$11:$B$115=$C33)*('Giá công thức'!$C$11:$C$115="GB")*('Giá công thức'!$G$3:$AQ$3=K$1)*('Giá công thức'!$G$4:$AQ$4=K$2))=0,NA(),SUMPRODUCT('Giá công thức'!$G$11:$AQ$115*('Giá công thức'!$A$11:$A$115=$B33)*('Giá công thức'!$B$11:$B$115=$C33)*('Giá công thức'!$C$11:$C$115="GB")*('Giá công thức'!$G$3:$AQ$3=K$1)*('Giá công thức'!$G$4:$AQ$4=K$2)))} -> 1377.5 | L33: {=IF(SUMPRODUCT('Giá công thức'!$G$11:$AQ$115*('Giá công thức'!$A$11:$A$115=$B33)*('Giá công thức'!$B$11:$B$115=$C33)*('Giá công thức'!$C$11:$C$115="GB")*('Giá công thức'!$G$3:$AQ$3=L$1)*('Giá công thức'!$G$4:$AQ$4=L$2))=0,NA(),SUMPRODUCT('Giá công thức'!$G$11:$AQ$115*('Giá công thức'!$A$11:$A$115=$B33)*('Giá công thức'!$B$11:$B$115=$C33)*('Giá công thức'!$C$11:$C$115="GB")*('Giá công thức'!$G$3:$AQ$3=L$1)*('Giá công thức'!$G$4:$AQ$4=L$2)))} -> 1388.5 | ... AH33: {=IF(SUMPRODUCT('Giá công thức'!$G$11:$AQ$115*('Giá công thức'!$A$11:$A$115=$B33)*('Giá công thức'!$B$11:$B$115=$C33)*('Giá công thức'!$C$11:$C$115="GB")*('Giá công thức'!$G$3:$AQ$3=AH$1)*('Giá công thức'!$G$4:$AQ$4=AH$2))=0,NA(),SUMPRODUCT('Giá công thức'!$G$11:$AQ$115*('Giá công thức'!$A$11:$A$115=$B33)*('Giá công thức'!$B$11:$B$115=$C33)*('Giá công thức'!$C$11:$C$115="GB")*('Giá công thức'!$G$3:$AQ$3=AH$1)*('Giá công thức'!$G$4:$AQ$4=AH$2)))} -> 1128 | AO33: =INDEX($E33:$AN33,MATCH("X",$E$3:$AN$3,0)) -> 1128
A34: 110000355 | C34: 110000355 | D34: Giá duyệt | E34: {=SUMPRODUCT(General_Data*(Code_General_Data=$A34)*(Year=E$1)*(Month=E$2))} -> 1280 | F34: {=SUMPRODUCT(General_Data*(Code_General_Data=$A34)*(Year=F$1)*(Month=F$2))} -> 1280 | G34: {=SUMPRODUCT(General_Data*(Code_General_Data=$A34)*(Year=G$1)*(Month=G$2))} -> 1280 | H34: {=SUMPRODUCT(General_Data*(Code_General_Data=$A34)*(Year=H$1)*(Month=H$2))} -> 1280 | I34: {=SUMPRODUCT(General_Data*(Code_General_Data=$A34)*(Year=I$1)*(Month=I$2))} -> 1330 | J34: {=SUMPRODUCT(General_Data*(Code_General_Data=$A34)*(Year=J$1)*(Month=J$2))} -> 1330 | K34: {=SUMPRODUCT(General_Data*(Code_General_Data=$A34)*(Year=K$1)*(Month=K$2))} -> 1330 | L34: {=SUMPRODUCT(General_Data*(Code_General_Data=$A34)*(Year=L$1)*(Month=L$2))} -> 1330 | ... AH34: {=SUMPRODUCT(General_Data*(Code_General_Data=$A34)*(Year=AH$1)*(Month=AH$2))} -> 1380 | AO34: =INDEX($E34:$AN34,MATCH("X",$E$3:$AN$3,0)) -> 1380
A35: PETVirgin | D35: Giá chính phẩm | E35: {=SUMPRODUCT(General_Data*(Code_General_Data=$A35)*(Year=E$1)*(Month=E$2))} -> 930 | F35: {=SUMPRODUCT(General_Data*(Code_General_Data=$A35)*(Year=F$1)*(Month=F$2))} -> 943.33333 | G35: {=SUMPRODUCT(General_Data*(Code_General_Data=$A35)*(Year=G$1)*(Month=G$2))} -> 940 | H35: {=SUMPRODUCT(General_Data*(Code_General_Data=$A35)*(Year=H$1)*(Month=H$2))} -> 940 | I35: {=SUMPRODUCT(General_Data*(Code_General_Data=$A35)*(Year=I$1)*(Month=I$2))} -> 942 | J35: {=SUMPRODUCT(General_Data*(Code_General_Data=$A35)*(Year=J$1)*(Month=J$2))} -> 950 | K35: {=SUMPRODUCT(General_Data*(Code_General_Data=$A35)*(Year=K$1)*(Month=K$2))} -> 947.5 | L35: {=SUMPRODUCT(General_Data*(Code_General_Data=$A35)*(Year=L$1)*(Month=L$2))} -> 930 | ... AH35: {=SUMPRODUCT(General_Data*(Code_General_Data=$A35)*(Year=AH$1)*(Month=AH$2))} -> 1190 | AO35: =INDEX($E35:$AN35,MATCH("X",$E$3:$AN$3,0)) -> 1190
D36: Chênh lệch | E36: =E34-E35 -> 350 | F36: =F34-F35 -> 336.66667 | G36: =G34-G35 -> 340 | H36: =H34-H35 -> 340 | I36: =I34-I35 -> 388 | J36: =J34-J35 -> 380 | K36: =K34-K35 -> 382.5 | L36: =L34-L35 -> 400 | ... AH36: =AH34-AH35 -> 190
D37: %Chênh lệch | E37: =IFERROR(E36/E35,0) -> 0.37634409 | F37: =IFERROR(F36/F35,0) -> 0.35689046 | G37: =IFERROR(G36/G35,0) -> 0.36170213 | H37: =IFERROR(H36/H35,0) -> 0.36170213 | I37: =IFERROR(I36/I35,0) -> 0.4118896 | J37: =IFERROR(J36/J35,0) -> 0.4 | K37: =IFERROR(K36/K35,0) -> 0.40369393 | L37: =IFERROR(L36/L35,0) -> 0.43010753 | ... AH37: =IFERROR(AH36/AH35,0) -> 0.15966387
A38: 110000355-GVXK-USD | C38: 110000355 | D38: Giá vốn (bao gồm CPBH,CPQLDN,lãi vay phân bổ) | E38: {=SUMPRODUCT(General_Data*(Code_General_Data=$A38)*(Year=E$1)*(Month=E$2))} -> 886.70564 | F38: {=SUMPRODUCT(General_Data*(Code_General_Data=$A38)*(Year=F$1)*(Month=F$2))} -> 885.79972 | G38: {=SUMPRODUCT(General_Data*(Code_General_Data=$A38)*(Year=G$1)*(Month=G$2))} -> 915.00612 | H38: {=SUMPRODUCT(General_Data*(Code_General_Data=$A38)*(Year=H$1)*(Month=H$2))} -> 901.26282 | I38: {=SUMPRODUCT(General_Data*(Code_General_Data=$A38)*(Year=I$1)*(Month=I$2))} -> 965.18474 | J38: {=SUMPRODUCT(General_Data*(Code_General_Data=$A38)*(Year=J$1)*(Month=J$2))} -> 923.78268 | K38: {=SUMPRODUCT(General_Data*(Code_General_Data=$A38)*(Year=K$1)*(Month=K$2))} -> 936.21245 | L38: {=SUMPRODUCT(General_Data*(Code_General_Data=$A38)*(Year=L$1)*(Month=L$2))} -> 967.70903 | ... AH38: {=SUMPRODUCT(General_Data*(Code_General_Data=$A38)*(Year=AH$1)*(Month=AH$2))} -> 1005.2866 | AO38: =INDEX($E38:$AN38,MATCH("X",$E$3:$AN$3,0)) -> 1005.2866
D39: Chênh lệch-Line Drop | E39: =E34 -> 1280 | F39: =F34 -> 1280 | G39: =G34 -> 1280 | H39: =H34 -> 1280 | I39: =I34 -> 1330 | J39: =J34 -> 1330 | K39: =K34 -> 1330 | L39: =L34 -> 1330 | ... AH39: =AH34 -> 1380
D40: Chênh lệch-Label | E40: =E35+E36/2 -> 1105 | F40: =F35+F36/2 -> 1111.6667 | G40: =G35+G36/2 -> 1110 | H40: =H35+H36/2 -> 1110 | I40: =I35+I36/2 -> 1136 | J40: =J35+J36/2 -> 1140 | K40: =K35+K36/2 -> 1138.75 | L40: =L35+L36/2 -> 1130 | ... AH40: =AH35+AH36/2 -> 1285
D41: Giá duyệt-Area | E41: =E34 -> 1280 | F41: =F34 -> 1280 | G41: =G34 -> 1280 | H41: =H34 -> 1280 | I41: =I34 -> 1330 | J41: =J34 -> 1330 | K41: =K34 -> 1330 | L41: =L34 -> 1330 | ... AH41: =AH34 -> 1380
D42: Giá chính phẩm-Area | E42: =E35 -> 930 | F42: =F35 -> 943.33333 | G42: =G35 -> 940 | H42: =H35 -> 940 | I42: =I35 -> 942 | J42: =J35 -> 950 | K42: =K35 -> 947.5 | L42: =L35 -> 930 | ... AH42: =AH35 -> 1190
D43: Outeirinho-Label | E43: =IFERROR(E32,0) -> 0 | F43: =IF(AND(IFERROR(F32,0)=IFERROR(E32,0),IFERROR(E32,0)=IFERROR(G32,0)),0,IFERROR(F32,0)) -> 0 | G43: =IF(AND(IFERROR(G32,0)=IFERROR(F32,0),IFERROR(F32,0)=IFERROR(H32,0)),0,IFERROR(G32,0)) -> 0 | H43: =IF(AND(IFERROR(H32,0)=IFERROR(G32,0),IFERROR(G32,0)=IFERROR(I32,0)),0,IFERROR(H32,0)) -> 0 | I43: =IF(AND(IFERROR(I32,0)=IFERROR(H32,0),IFERROR(H32,0)=IFERROR(J32,0)),0,IFERROR(I32,0)) -> 0 | J43: =IF(AND(IFERROR(J32,0)=IFERROR(I32,0),IFERROR(I32,0)=IFERROR(K32,0)),0,IFERROR(J32,0)) -> 0 | K43: =IF(AND(IFERROR(K32,0)=IFERROR(J32,0),IFERROR(J32,0)=IFERROR(L32,0)),0,IFERROR(K32,0)) -> 0 | L43: =IF(AND(IFERROR(L32,0)=IFERROR(K32,0),IFERROR(K32,0)=IFERROR(M32,0)),0,IFERROR(L32,0)) -> 0 | M43: =IF(AND(IFERROR(M32,0)=IFERROR(L32,0),IFERROR(L32,0)=IFERROR(N32,0)),0,IFERROR(M32,0)) -> 0 | ... AH43: =IF(AND(IFERROR(AH32,0)=IFERROR(AG32,0),IFERROR(AG32,0)=IFERROR(AI32,0)),0,IFERROR(AH32,0)) -> 0 | AO43: OUTEIRINHO
D44: Suntory VN-Label | E44: =IFERROR(E33,0) -> 1320 | F44: =IF(AND(IFERROR(F33,0)=IFERROR(E33,0),IFERROR(E33,0)=IFERROR(G33,0)),0,IFERROR(F33,0)) -> 1327.5 | G44: =IF(AND(IFERROR(G33,0)=IFERROR(F33,0),IFERROR(F33,0)=IFERROR(H33,0)),0,IFERROR(G33,0)) -> 1340 | H44: =IF(AND(IFERROR(H33,0)=IFERROR(G33,0),IFERROR(G33,0)=IFERROR(I33,0)),0,IFERROR(H33,0)) -> 1342.5 | I44: =IF(AND(IFERROR(I33,0)=IFERROR(H33,0),IFERROR(H33,0)=IFERROR(J33,0)),0,IFERROR(I33,0)) -> 1346.5 | J44: =IF(AND(IFERROR(J33,0)=IFERROR(I33,0),IFERROR(I33,0)=IFERROR(K33,0)),0,IFERROR(J33,0)) -> 1361.5 | K44: =IF(AND(IFERROR(K33,0)=IFERROR(J33,0),IFERROR(J33,0)=IFERROR(L33,0)),0,IFERROR(K33,0)) -> 1377.5 | L44: =IF(AND(IFERROR(L33,0)=IFERROR(K33,0),IFERROR(K33,0)=IFERROR(M33,0)),0,IFERROR(L33,0)) -> 1388.5 | M44: =IF(AND(IFERROR(M33,0)=IFERROR(L33,0),IFERROR(L33,0)=IFERROR(N33,0)),0,IFERROR(M33,0)) -> 1408.5 | ... AH44: =IF(AND(IFERROR(AH33,0)=IFERROR(AG33,0),IFERROR(AG33,0)=IFERROR(AI33,0)),0,IFERROR(AH33,0)) -> 1128 | AO44: SUNTORY VN
D45: Giá duyệt-Label | E45: =IFERROR(E34,0) -> 1280 | F45: =IF(AND(IFERROR(F34,0)=IFERROR(E34,0),IFERROR(E34,0)=IFERROR(G34,0)),0,IFERROR(F34,0)) -> 0 | G45: =IF(AND(IFERROR(G34,0)=IFERROR(F34,0),IFERROR(F34,0)=IFERROR(H34,0)),0,IFERROR(G34,0)) -> 0 | H45: =IF(AND(IFERROR(H34,0)=IFERROR(G34,0),IFERROR(G34,0)=IFERROR(I34,0)),0,IFERROR(H34,0)) -> 1280 | I45: =IF(AND(IFERROR(I34,0)=IFERROR(H34,0),IFERROR(H34,0)=IFERROR(J34,0)),0,IFERROR(I34,0)) -> 1330 | J45: =IF(AND(IFERROR(J34,0)=IFERROR(I34,0),IFERROR(I34,0)=IFERROR(K34,0)),0,IFERROR(J34,0)) -> 0 | K45: =IF(AND(IFERROR(K34,0)=IFERROR(J34,0),IFERROR(J34,0)=IFERROR(L34,0)),0,IFERROR(K34,0)) -> 0 | L45: =IF(AND(IFERROR(L34,0)=IFERROR(K34,0),IFERROR(K34,0)=IFERROR(M34,0)),0,IFERROR(L34,0)) -> 1330 | M45: =IF(AND(IFERROR(M34,0)=IFERROR(L34,0),IFERROR(L34,0)=IFERROR(N34,0)),0,IFERROR(M34,0)) -> 1340 | ... AH45: =IF(AND(IFERROR(AH34,0)=IFERROR(AG34,0),IFERROR(AG34,0)=IFERROR(AI34,0)),0,IFERROR(AH34,0)) -> 1380 | AO45: Giá duyệt
D46: Giá chính phẩm-Label | E46: =IFERROR(E35,0) -> 930 | F46: =IF(AND(IFERROR(F35,0)=IFERROR(E35,0),IFERROR(E35,0)=IFERROR(G35,0)),0,IFERROR(F35,0)) -> 943.33333 | G46: =IF(AND(IFERROR(G35,0)=IFERROR(F35,0),IFERROR(F35,0)=IFERROR(H35,0)),0,IFERROR(G35,0)) -> 940 | H46: =IF(AND(IFERROR(H35,0)=IFERROR(G35,0),IFERROR(G35,0)=IFERROR(I35,0)),0,IFERROR(H35,0)) -> 940 | I46: =IF(AND(IFERROR(I35,0)=IFERROR(H35,0),IFERROR(H35,0)=IFERROR(J35,0)),0,IFERROR(I35,0)) -> 942 | J46: =IF(AND(IFERROR(J35,0)=IFERROR(I35,0),IFERROR(I35,0)=IFERROR(K35,0)),0,IFERROR(J35,0)) -> 950 | K46: =IF(AND(IFERROR(K35,0)=IFERROR(J35,0),IFERROR(J35,0)=IFERROR(L35,0)),0,IFERROR(K35,0)) -> 947.5 | L46: =IF(AND(IFERROR(L35,0)=IFERROR(K35,0),IFERROR(K35,0)=IFERROR(M35,0)),0,IFERROR(L35,0)) -> 930 | M46: =IF(AND(IFERROR(M35,0)=IFERROR(L35,0),IFERROR(L35,0)=IFERROR(N35,0)),0,IFERROR(M35,0)) -> 880 | ... AH46: =IF(AND(IFERROR(AH35,0)=IFERROR(AG35,0),IFERROR(AG35,0)=IFERROR(AI35,0)),0,IFERROR(AH35,0)) -> 1190 | AO46: Giá chính phẩm
D47: Giá vốn (bao gồm CPBH,CPQLDN,lãi vay phân bổ)-Label | E47: =IFERROR(E38,0) -> 886.70564 | F47: =IF(AND(IFERROR(F38,0)=IFERROR(E38,0),IFERROR(E38,0)=IFERROR(G38,0)),0,IFERROR(F38,0)) -> 885.79972 | G47: =IF(AND(IFERROR(G38,0)=IFERROR(F38,0),IFERROR(F38,0)=IFERROR(H38,0)),0,IFERROR(G38,0)) -> 915.00612 | H47: =IF(AND(IFERROR(H38,0)=IFERROR(G38,0),IFERROR(G38,0)=IFERROR(I38,0)),0,IFERROR(H38,0)) -> 901.26282 | I47: =IF(AND(IFERROR(I38,0)=IFERROR(H38,0),IFERROR(H38,0)=IFERROR(J38,0)),0,IFERROR(I38,0)) -> 965.18474 | J47: =IF(AND(IFERROR(J38,0)=IFERROR(I38,0),IFERROR(I38,0)=IFERROR(K38,0)),0,IFERROR(J38,0)) -> 923.78268 | K47: =IF(AND(IFERROR(K38,0)=IFERROR(J38,0),IFERROR(J38,0)=IFERROR(L38,0)),0,IFERROR(K38,0)) -> 936.21245 | L47: =IF(AND(IFERROR(L38,0)=IFERROR(K38,0),IFERROR(K38,0)=IFERROR(M38,0)),0,IFERROR(L38,0)) -> 967.70903 | M47: =IF(AND(IFERROR(M38,0)=IFERROR(L38,0),IFERROR(L38,0)=IFERROR(N38,0)),0,IFERROR(M38,0)) -> 991.40086 | ... AH47: =IF(AND(IFERROR(AH38,0)=IFERROR(AG38,0),IFERROR(AG38,0)=IFERROR(AI38,0)),0,IFERROR(AH38,0)) -> 1005.2866 | AO47: Giá vốn (*)
C49: 110000332 | D49: iSS01084G
E50: 2024 | Q50: 2025 | AC50: 2026
E51: 1 | F51: 2 | G51: 3 | H51: 4 | I51: 5 | J51: 6 | K51: 7 | L51: 8 | M51: 9 | N51: 10 | O51: 11 | P51: 12 | Q51: 1 | R51: 2 | S51: 3 | T51: 4 | U51: 5 | V51: 6 | W51: 7 | X51: 8 | Y51: 9 | Z51: 10 | AA51: 11 | AB51: 12 | AC51: 1 | AD51: 2 | AE51: 3 | AF51: 4 | AG51: 5 | AH51: 6 | AI51: 7 | AJ51: 8 | AK51: 9 | AL51: 10 | AM51: 11 | AN51: 12
B52: 102990 | C52: 110000332 | D52: COCA VIET NAM | E52: {=IF(SUMPRODUCT('Giá công thức'!$G$11:$AQ$115*('Giá công thức'!$A$11:$A$115=$B52)*('Giá công thức'!$B$11:$B$115=$C52)*('Giá công thức'!$C$11:$C$115="GB")*('Giá công thức'!$G$3:$AQ$3=E$1)*('Giá công thức'!$G$4:$AQ$4=E$2))=0,NA(),SUMPRODUCT('Giá công thức'!$G$11:$AQ$115*('Giá công thức'!$A$11:$A$115=$B52)*('Giá công thức'!$B$11:$B$115=$C52)*('Giá công thức'!$C$11:$C$115="GB")*('Giá công thức'!$G$3:$AQ$3=E$1)*('Giá công thức'!$G$4:$AQ$4=E$2)))} -> 1315 | F52: {=IF(SUMPRODUCT('Giá công thức'!$G$11:$AQ$115*('Giá công thức'!$A$11:$A$115=$B52)*('Giá công thức'!$B$11:$B$115=$C52)*('Giá công thức'!$C$11:$C$115="GB")*('Giá công thức'!$G$3:$AQ$3=F$1)*('Giá công thức'!$G$4:$AQ$4=F$2))=0,NA(),SUMPRODUCT('Giá công thức'!$G$11:$AQ$115*('Giá công thức'!$A$11:$A$115=$B52)*('Giá công thức'!$B$11:$B$115=$C52)*('Giá công thức'!$C$11:$C$115="GB")*('Giá công thức'!$G$3:$AQ$3=F$1)*('Giá công thức'!$G$4:$AQ$4=F$2)))} -> 1315 | G52: {=IF(SUMPRODUCT('Giá công thức'!$G$11:$AQ$115*('Giá công thức'!$A$11:$A$115=$B52)*('Giá công thức'!$B$11:$B$115=$C52)*('Giá công thức'!$C$11:$C$115="GB")*('Giá công thức'!$G$3:$AQ$3=G$1)*('Giá công thức'!$G$4:$AQ$4=G$2))=0,NA(),SUMPRODUCT('Giá công thức'!$G$11:$AQ$115*('Giá công thức'!$A$11:$A$115=$B52)*('Giá công thức'!$B$11:$B$115=$C52)*('Giá công thức'!$C$11:$C$115="GB")*('Giá công thức'!$G$3:$AQ$3=G$1)*('Giá công thức'!$G$4:$AQ$4=G$2)))} -> 1315 | H52: {=IF(SUMPRODUCT('Giá công thức'!$G$11:$AQ$115*('Giá công thức'!$A$11:$A$115=$B52)*('Giá công thức'!$B$11:$B$115=$C52)*('Giá công thức'!$C$11:$C$115="GB")*('Giá công thức'!$G$3:$AQ$3=H$1)*('Giá công thức'!$G$4:$AQ$4=H$2))=0,NA(),SUMPRODUCT('Giá công thức'!$G$11:$AQ$115*('Giá công thức'!$A$11:$A$115=$B52)*('Giá công thức'!$B$11:$B$115=$C52)*('Giá công thức'!$C$11:$C$115="GB")*('Giá công thức'!$G$3:$AQ$3=H$1)*('Giá công thức'!$G$4:$AQ$4=H$2)))} -> 1315 | I52: {=IF(SUMPRODUCT('Giá công thức'!$G$11:$AQ$115*('Giá công thức'!$A$11:$A$115=$B52)*('Giá công thức'!$B$11:$B$115=$C52)*('Giá công thức'!$C$11:$C$115="GB")*('Giá công thức'!$G$3:$AQ$3=I$1)*('Giá công thức'!$G$4:$AQ$4=I$2))=0,NA(),SUMPRODUCT('Giá công thức'!$G$11:$AQ$115*('Giá công thức'!$A$11:$A$115=$B52)*('Giá công thức'!$B$11:$B$115=$C52)*('Giá công thức'!$C$11:$C$115="GB")*('Giá công thức'!$G$3:$AQ$3=I$1)*('Giá công thức'!$G$4:$AQ$4=I$2)))} -> 1315 | J52: {=IF(SUMPRODUCT('Giá công thức'!$G$11:$AQ$115*('Giá công thức'!$A$11:$A$115=$B52)*('Giá công thức'!$B$11:$B$115=$C52)*('Giá công thức'!$C$11:$C$115="GB")*('Giá công thức'!$G$3:$AQ$3=J$1)*('Giá công thức'!$G$4:$AQ$4=J$2))=0,NA(),SUMPRODUCT('Giá công thức'!$G$11:$AQ$115*('Giá công thức'!$A$11:$A$115=$B52)*('Giá công thức'!$B$11:$B$115=$C52)*('Giá công thức'!$C$11:$C$115="GB")*('Giá công thức'!$G$3:$AQ$3=J$1)*('Giá công thức'!$G$4:$AQ$4=J$2)))} -> 1315 | K52: {=IF(SUMPRODUCT('Giá công thức'!$G$11:$AQ$115*('Giá công thức'!$A$11:$A$115=$B52)*('Giá công thức'!$B$11:$B$115=$C52)*('Giá công thức'!$C$11:$C$115="GB")*('Giá công thức'!$G$3:$AQ$3=K$1)*('Giá công thức'!$G$4:$AQ$4=K$2))=0,NA(),SUMPRODUCT('Giá công thức'!$G$11:$AQ$115*('Giá công thức'!$A$11:$A$115=$B52)*('Giá công thức'!$B$11:$B$115=$C52)*('Giá công thức'!$C$11:$C$115="GB")*('Giá công thức'!$G$3:$AQ$3=K$1)*('Giá công thức'!$G$4:$AQ$4=K$2)))} -> 1315 | L52: {=IF(SUMPRODUCT('Giá công thức'!$G$11:$AQ$115*('Giá công thức'!$A$11:$A$115=$B52)*('Giá công thức'!$B$11:$B$115=$C52)*('Giá công thức'!$C$11:$C$115="GB")*('Giá công thức'!$G$3:$AQ$3=L$1)*('Giá công thức'!$G$4:$AQ$4=L$2))=0,NA(),SUMPRODUCT('Giá công thức'!$G$11:$AQ$115*('Giá công thức'!$A$11:$A$115=$B52)*('Giá công thức'!$B$11:$B$115=$C52)*('Giá công thức'!$C$11:$C$115="GB")*('Giá công thức'!$G$3:$AQ$3=L$1)*('Giá công thức'!$G$4:$AQ$4=L$2)))} -> 1315 | ... AH52: {=IF(SUMPRODUCT('Giá công thức'!$G$11:$AQ$115*('Giá công thức'!$A$11:$A$115=$B52)*('Giá công thức'!$B$11:$B$115=$C52)*('Giá công thức'!$C$11:$C$115="GB")*('Giá công thức'!$G$3:$AQ$3=AH$1)*('Giá công thức'!$G$4:$AQ$4=AH$2))=0,NA(),SUMPRODUCT('Giá công thức'!$G$11:$AQ$115*('Giá công thức'!$A$11:$A$115=$B52)*('Giá công thức'!$B$11:$B$115=$C52)*('Giá công thức'!$C$11:$C$115="GB")*('Giá công thức'!$G$3:$AQ$3=AH$1)*('Giá công thức'!$G$4:$AQ$4=AH$2)))} -> 1270 | AO52: =INDEX($E52:$AN52,MATCH("X",$E$3:$AN$3,0)) -> 1270
B53: 105194 | C53: 110000332 | D53: SUNTORY VIET NAM | E53: {=IF(SUMPRODUCT('Giá công thức'!$G$11:$AQ$115*('Giá công thức'!$A$11:$A$115=$B53)*('Giá công thức'!$B$11:$B$115=$C53)*('Giá công thức'!$C$11:$C$115="GB")*('Giá công thức'!$G$3:$AQ$3=E$1)*('Giá công thức'!$G$4:$AQ$4=E$2))=0,NA(),SUMPRODUCT('Giá công thức'!$G$11:$AQ$115*('Giá công thức'!$A$11:$A$115=$B53)*('Giá công thức'!$B$11:$B$115=$C53)*('Giá công thức'!$C$11:$C$115="GB")*('Giá công thức'!$G$3:$AQ$3=E$1)*('Giá công thức'!$G$4:$AQ$4=E$2)))} -> 1340 | F53: {=IF(SUMPRODUCT('Giá công thức'!$G$11:$AQ$115*('Giá công thức'!$A$11:$A$115=$B53)*('Giá công thức'!$B$11:$B$115=$C53)*('Giá công thức'!$C$11:$C$115="GB")*('Giá công thức'!$G$3:$AQ$3=F$1)*('Giá công thức'!$G$4:$AQ$4=F$2))=0,NA(),SUMPRODUCT('Giá công thức'!$G$11:$AQ$115*('Giá công thức'!$A$11:$A$115=$B53)*('Giá công thức'!$B$11:$B$115=$C53)*('Giá công thức'!$C$11:$C$115="GB")*('Giá công thức'!$G$3:$AQ$3=F$1)*('Giá công thức'!$G$4:$AQ$4=F$2)))} -> 1347.5 | G53: {=IF(SUMPRODUCT('Giá công thức'!$G$11:$AQ$115*('Giá công thức'!$A$11:$A$115=$B53)*('Giá công thức'!$B$11:$B$115=$C53)*('Giá công thức'!$C$11:$C$115="GB")*('Giá công thức'!$G$3:$AQ$3=G$1)*('Giá công thức'!$G$4:$AQ$4=G$2))=0,NA(),SUMPRODUCT('Giá công thức'!$G$11:$AQ$115*('Giá công thức'!$A$11:$A$115=$B53)*('Giá công thức'!$B$11:$B$115=$C53)*('Giá công thức'!$C$11:$C$115="GB")*('Giá công thức'!$G$3:$AQ$3=G$1)*('Giá công thức'!$G$4:$AQ$4=G$2)))} -> 1360 | H53: {=IF(SUMPRODUCT('Giá công thức'!$G$11:$AQ$115*('Giá công thức'!$A$11:$A$115=$B53)*('Giá công thức'!$B$11:$B$115=$C53)*('Giá công thức'!$C$11:$C$115="GB")*('Giá công thức'!$G$3:$AQ$3=H$1)*('Giá công thức'!$G$4:$AQ$4=H$2))=0,NA(),SUMPRODUCT('Giá công thức'!$G$11:$AQ$115*('Giá công thức'!$A$11:$A$115=$B53)*('Giá công thức'!$B$11:$B$115=$C53)*('Giá công thức'!$C$11:$C$115="GB")*('Giá công thức'!$G$3:$AQ$3=H$1)*('Giá công thức'!$G$4:$AQ$4=H$2)))} -> 1362.5 | I53: {=IF(SUMPRODUCT('Giá công thức'!$G$11:$AQ$115*('Giá công thức'!$A$11:$A$115=$B53)*('Giá công thức'!$B$11:$B$115=$C53)*('Giá công thức'!$C$11:$C$115="GB")*('Giá công thức'!$G$3:$AQ$3=I$1)*('Giá công thức'!$G$4:$AQ$4=I$2))=0,NA(),SUMPRODUCT('Giá công thức'!$G$11:$AQ$115*('Giá công thức'!$A$11:$A$115=$B53)*('Giá công thức'!$B$11:$B$115=$C53)*('Giá công thức'!$C$11:$C$115="GB")*('Giá công thức'!$G$3:$AQ$3=I$1)*('Giá công thức'!$G$4:$AQ$4=I$2)))} -> 1366.5 | J53: {=IF(SUMPRODUCT('Giá công thức'!$G$11:$AQ$115*('Giá công thức'!$A$11:$A$115=$B53)*('Giá công thức'!$B$11:$B$115=$C53)*('Giá công thức'!$C$11:$C$115="GB")*('Giá công thức'!$G$3:$AQ$3=J$1)*('Giá công thức'!$G$4:$AQ$4=J$2))=0,NA(),SUMPRODUCT('Giá công thức'!$G$11:$AQ$115*('Giá công thức'!$A$11:$A$115=$B53)*('Giá công thức'!$B$11:$B$115=$C53)*('Giá công thức'!$C$11:$C$115="GB")*('Giá công thức'!$G$3:$AQ$3=J$1)*('Giá công thức'!$G$4:$AQ$4=J$2)))} -> 1381.5 | K53: {=IF(SUMPRODUCT('Giá công thức'!$G$11:$AQ$115*('Giá công thức'!$A$11:$A$115=$B53)*('Giá công thức'!$B$11:$B$115=$C53)*('Giá công thức'!$C$11:$C$115="GB")*('Giá công thức'!$G$3:$AQ$3=K$1)*('Giá công thức'!$G$4:$AQ$4=K$2))=0,NA(),SUMPRODUCT('Giá công thức'!$G$11:$AQ$115*('Giá công thức'!$A$11:$A$115=$B53)*('Giá công thức'!$B$11:$B$115=$C53)*('Giá công thức'!$C$11:$C$115="GB")*('Giá công thức'!$G$3:$AQ$3=K$1)*('Giá công thức'!$G$4:$AQ$4=K$2)))} -> 1397.5 | L53: {=IF(SUMPRODUCT('Giá công thức'!$G$11:$AQ$115*('Giá công thức'!$A$11:$A$115=$B53)*('Giá công thức'!$B$11:$B$115=$C53)*('Giá công thức'!$C$11:$C$115="GB")*('Giá công thức'!$G$3:$AQ$3=L$1)*('Giá công thức'!$G$4:$AQ$4=L$2))=0,NA(),SUMPRODUCT('Giá công thức'!$G$11:$AQ$115*('Giá công thức'!$A$11:$A$115=$B53)*('Giá công thức'!$B$11:$B$115=$C53)*('Giá công thức'!$C$11:$C$115="GB")*('Giá công thức'!$G$3:$AQ$3=L$1)*('Giá công thức'!$G$4:$AQ$4=L$2)))} -> 1408.5 | ... AH53: {=IF(SUMPRODUCT('Giá công thức'!$G$11:$AQ$115*('Giá công thức'!$A$11:$A$115=$B53)*('Giá công thức'!$B$11:$B$115=$C53)*('Giá công thức'!$C$11:$C$115="GB")*('Giá công thức'!$G$3:$AQ$3=AH$1)*('Giá công thức'!$G$4:$AQ$4=AH$2))=0,NA(),SUMPRODUCT('Giá công thức'!$G$11:$AQ$115*('Giá công thức'!$A$11:$A$115=$B53)*('Giá công thức'!$B$11:$B$115=$C53)*('Giá công thức'!$C$11:$C$115="GB")*('Giá công thức'!$G$3:$AQ$3=AH$1)*('Giá công thức'!$G$4:$AQ$4=AH$2)))} -> 1128 | AO53: =INDEX($E53:$AN53,MATCH("X",$E$3:$AN$3,0)) -> 1128
A54: 110000332 | C54: 110000332 | D54: Giá duyệt | E54: {=SUMPRODUCT(General_Data*(Code_General_Data=$A54)*(Year=E$1)*(Month=E$2))} -> 1340 | F54: {=SUMPRODUCT(General_Data*(Code_General_Data=$A54)*(Year=F$1)*(Month=F$2))} -> 1340 | G54: {=SUMPRODUCT(General_Data*(Code_General_Data=$A54)*(Year=G$1)*(Month=G$2))} -> 1340 | H54: {=SUMPRODUCT(General_Data*(Code_General_Data=$A54)*(Year=H$1)*(Month=H$2))} -> 1340 | I54: {=SUMPRODUCT(General_Data*(Code_General_Data=$A54)*(Year=I$1)*(Month=I$2))} -> 1390 | J54: {=SUMPRODUCT(General_Data*(Code_General_Data=$A54)*(Year=J$1)*(Month=J$2))} -> 1390 | K54: {=SUMPRODUCT(General_Data*(Code_General_Data=$A54)*(Year=K$1)*(Month=K$2))} -> 1390 | L54: {=SUMPRODUCT(General_Data*(Code_General_Data=$A54)*(Year=L$1)*(Month=L$2))} -> 1390 | ... AH54: {=SUMPRODUCT(General_Data*(Code_General_Data=$A54)*(Year=AH$1)*(Month=AH$2))} -> 1440 | AO54: =INDEX($E54:$AN54,MATCH("X",$E$3:$AN$3,0)) -> 1440
A55: PETVirgin | D55: Giá chính phẩm | E55: {=SUMPRODUCT(General_Data*(Code_General_Data=$A55)*(Year=E$1)*(Month=E$2))} -> 930 | F55: {=SUMPRODUCT(General_Data*(Code_General_Data=$A55)*(Year=F$1)*(Month=F$2))} -> 943.33333 | G55: {=SUMPRODUCT(General_Data*(Code_General_Data=$A55)*(Year=G$1)*(Month=G$2))} -> 940 | H55: {=SUMPRODUCT(General_Data*(Code_General_Data=$A55)*(Year=H$1)*(Month=H$2))} -> 940 | I55: {=SUMPRODUCT(General_Data*(Code_General_Data=$A55)*(Year=I$1)*(Month=I$2))} -> 942 | J55: {=SUMPRODUCT(General_Data*(Code_General_Data=$A55)*(Year=J$1)*(Month=J$2))} -> 950 | K55: {=SUMPRODUCT(General_Data*(Code_General_Data=$A55)*(Year=K$1)*(Month=K$2))} -> 947.5 | L55: {=SUMPRODUCT(General_Data*(Code_General_Data=$A55)*(Year=L$1)*(Month=L$2))} -> 930 | ... AH55: {=SUMPRODUCT(General_Data*(Code_General_Data=$A55)*(Year=AH$1)*(Month=AH$2))} -> 1190 | AO55: =INDEX($E55:$AN55,MATCH("X",$E$3:$AN$3,0)) -> 1190
D56: Chênh lệch-Area | E56: =E54-E55 -> 410 | F56: =F54-F55 -> 396.66667 | G56: =G54-G55 -> 400 | H56: =H54-H55 -> 400 | I56: =I54-I55 -> 448 | J56: =J54-J55 -> 440 | K56: =K54-K55 -> 442.5 | L56: =L54-L55 -> 460 | ... AH56: =AH54-AH55 -> 250
D57: %Chênh lệch | E57: =IFERROR(E56/E55,0) -> 0.44086022 | F57: =IFERROR(F56/F55,0) -> 0.4204947 | G57: =IFERROR(G56/G55,0) -> 0.42553191 | H57: =IFERROR(H56/H55,0) -> 0.42553191 | I57: =IFERROR(I56/I55,0) -> 0.47558386 | J57: =IFERROR(J56/J55,0) -> 0.46315789 | K57: =IFERROR(K56/K55,0) -> 0.46701847 | L57: =IFERROR(L56/L55,0) -> 0.49462366 | ... AH57: =IFERROR(AH56/AH55,0) -> 0.21008403
A58: 110000332-GVXK-USD | C58: 110000332 | D58: Giá vốn (bao gồm CPBH,CPQLDN,lãi vay phân bổ) | E58: {=SUMPRODUCT(General_Data*(Code_General_Data=$A58)*(Year=E$1)*(Month=E$2))} -> 880.33849 | F58: {=SUMPRODUCT(General_Data*(Code_General_Data=$A58)*(Year=F$1)*(Month=F$2))} -> 947.3118 | G58: {=SUMPRODUCT(General_Data*(Code_General_Data=$A58)*(Year=G$1)*(Month=G$2))} -> 966.27318 | H58: {=SUMPRODUCT(General_Data*(Code_General_Data=$A58)*(Year=H$1)*(Month=H$2))} -> 980.77936 | I58: {=SUMPRODUCT(General_Data*(Code_General_Data=$A58)*(Year=I$1)*(Month=I$2))} -> 967.8225 | J58: {=SUMPRODUCT(General_Data*(Code_General_Data=$A58)*(Year=J$1)*(Month=J$2))} -> 1011.9357 | K58: {=SUMPRODUCT(General_Data*(Code_General_Data=$A58)*(Year=K$1)*(Month=K$2))} -> 1089.0598 | L58: {=SUMPRODUCT(General_Data*(Code_General_Data=$A58)*(Year=L$1)*(Month=L$2))} -> 1264.8474 | ... AH58: {=SUMPRODUCT(General_Data*(Code_General_Data=$A58)*(Year=AH$1)*(Month=AH$2))} -> 1136.4181 | AO58: =INDEX($E58:$AN58,MATCH("X",$E$3:$AN$3,0)) -> 1136.4181
D59: Chênh lệch-Line Drop | E59: =E54 -> 1340 | F59: =F54 -> 1340 | G59: =G54 -> 1340 | H59: =H54 -> 1340 | I59: =I54 -> 1390 | J59: =J54 -> 1390 | K59: =K54 -> 1390 | L59: =L54 -> 1390 | ... AH59: =AH54 -> 1440
D60: Chênh lệch-Label | E60: =E55+E56/2 -> 1135 | F60: =F55+F56/2 -> 1141.6667 | G60: =G55+G56/2 -> 1140 | H60: =H55+H56/2 -> 1140 | I60: =I55+I56/2 -> 1166 | J60: =J55+J56/2 -> 1170 | K60: =K55+K56/2 -> 1168.75 | L60: =L55+L56/2 -> 1160 | ... AH60: =AH55+AH56/2 -> 1315
D61: Giá duyệt-Area | E61: =E54 -> 1340 | F61: =F54 -> 1340 | G61: =G54 -> 1340 | H61: =H54 -> 1340 | I61: =I54 -> 1390 | J61: =J54 -> 1390 | K61: =K54 -> 1390 | L61: =L54 -> 1390 | ... AH61: =AH54 -> 1440
D62: Giá chính phẩm-Area | E62: =E55 -> 930 | F62: =F55 -> 943.33333 | G62: =G55 -> 940 | H62: =H55 -> 940 | I62: =I55 -> 942 | J62: =J55 -> 950 | K62: =K55 -> 947.5 | L62: =L55 -> 930 | ... AH62: =AH55 -> 1190
