Workbook
Name \0: #REF!
Name \a: #REF!
Name \b: #REF!
Name \c: #REF!
Name \C_: #REF!
Name \e: #REF!
Name \f: #REF!
Name \k: #REF!
Name \m: #REF!
Name \o: #REF!
Name \p: #REF!
Name \q: #N/A
Name \r: #REF!
Name \s: #REF!
Name \t: #REF!
Name \x: #REF!
Name \z: #REF!
Name _???: #REF!
Name _????????: #REF!
Name _????????????: #REF!
Name _?????????????: #N/A
Name _?_??????: #REF!
Name _?1_HP_A: #REF!
Name _?1_HP_B: #REF!
Name _?2_HP_A: #REF!
Name _?2_HP_B: #REF!
Name _?3_HP_A: #REF!
Name _?3_HP_B: #REF!
Name _?5_HP: #REF!
Name __???: #N/A
Name __????????????: #REF!
Name __?????????????: #REF!
Name ______TAX2: #REF!
Name _____06: #REF!
Name _____CWF1: #REF!
Name _____CWF2: #REF!
Name _____DAT1: #REF!
Name _____DAT10: #REF!
Name _____DAT2: #REF!
Name _____DAT3: #REF!
Name _____DAT4: #REF!
Name _____DAT5: #REF!
Name _____DAT6: #REF!
Name _____DAT7: #REF!
Name _____DAT8: #REF!
Name _____DAT9: #REF!
Name _____UWF1: #REF!
Name _____UWF2: #REF!
Name ____06: #REF!
Name ____CWF1: #REF!
Name ____CWF2: #REF!
Name ____DAT1: #REF!
Name ____DAT10: #REF!
Name ____DAT2: #REF!
Name ____DAT3: #REF!
Name ____DAT4: #REF!
Name ____DAT5: #REF!
Name ____DAT6: #REF!
Name ____DAT7: #REF!
Name ____DAT8: #REF!

Sheet Performance
E1: PERFORMANCE | F1: =IF(K1="EN","PERFORMANCE","KẾT QUẢ KINH DOANH") -> KẾT QUẢ KINH DOANH | G1: 2024 | H1: 2025 | I1: 2026 | K1: VN | O1: 2024 | P1: 2025 | Q1: 2026
E2: =F2 -> DTR | F2: DTR | G2: 12 | H2: 5 | I2: 5 | J2: =IF(K1="EN","Unit:","Đvt:") -> Đvt: | K2: Triệu VND | O2: =G2 -> 12 | P2: =H2 -> 5 | Q2: =I2 -> 5 | X2: =H2 -> 5 | Y2: =I2 -> 5
E3: PROFIT & LOSS | F3: =IF($K$1="EN",E3,"KẾT QUẢ KINH DOANH") -> KẾT QUẢ KINH DOANH | G3: =IF(J1="EN",IF(G2=12,"FY "&G1,"YTD "&G1),IF(G2=12,"Năm "&G1,"LK "&G1)) -> Năm 2024 | H3: =IF(K1="EN",IF(H2=12,"FY "&H1,"YTD "&H1),IF(H2=12,"Năm "&H1,"LK "&H1)) -> LK 2025 | I3: =IF(K1="EN",IF(I2=12,"FY "&I1,"YTD "&I1),IF(I2=12,"Năm "&I1,"LK "&I1)) -> LK 2026 | J3: =IF($K$1="EN","Change from last year","So với năm trước") -> So với năm trước | M3: =IF(K1="EN",N3,"BẢNG CÂN ĐỐI KẾ TOÁN") -> BẢNG CÂN ĐỐI KẾ TOÁN | N3: BALANCE SHEET | O3: =IF(K1="EN"," "&O2&"/"&RIGHT(O1,4),O2&"/"&RIGHT(O1,4)) -> 12/2024 | P3: =IF(K1="EN"," "&P2&"/"&RIGHT(P1,4),P2&"/"&RIGHT(P1,4)) -> 5/2025 | Q3: =IF(K1="EN"," "&Q2&"/" &RIGHT(Q1,4),Q2&"/"&RIGHT(Q1,4)) -> 5/2026 | R3: =J3 -> So với năm trước | V3: =IF(K1="EN","Key Financial Indicators","CHỈ SỐ TÀI CHÍNH") -> CHỈ SỐ TÀI CHÍNH | W3: =G3 -> Năm 2024 | X3: =H3 -> LK 2025 | Y3: =I3 -> LK 2026 | Z3: =IF(K1="EN","Ref.","Tham chiếu") -> Tham chiếu
E4: Production volume | F4: =IF($K$1="EN",E4,"Sản lượng sản xuất (Tấn)") -> Sản lượng sản xuất (Tấn) | G4: =IFERROR(SUMIFS(Data!Q:Q,Data!B:B,Performance!$E$2,Data!D:D,Performance!E4),"") -> 21515.497 | H4: =IFERROR(SUMIFS(Data!AD:AD,Data!B:B,Performance!$E$2,Data!D:D,Performance!E4),"") -> 18536.137 | I4: =IFERROR(SUMIFS(Data!AR:AR,Data!B:B,Performance!$E$2,Data!D:D,Performance!E4),"") -> 16555.638 | J4: =IFERROR(I4-H4,"") -> -1980.4994 | K4: =IFERROR(J4/H4,"") -> -0.10684532 | M4: =IF(K1="en",N4,"Tài sản ngắn hạn") -> Tài sản ngắn hạn | N4: Current Assets | O4: =IF($K$2="USD",SUMIFS(Data!Q:Q,Data!B:B,Performance!$F$2,Data!D:D,Performance!N4)*10^6,SUMIFS(Data!Q:Q,Data!B:B,Performance!$F$2,Data!D:D,Performance!N4)) -> 928155716736 | P4: =IF($K$2="USD",SUMIFS(Data!AD:AD,Data!B:B,Performance!$E$2,Data!D:D,Performance!N4)*10^6,SUMIFS(Data!AD:AD,Data!B:B,Performance!$E$2,Data!D:D,Performance!N4)) -> 981599372849 | Q4: =IF($K$2="USD",SUMIFS(Data!AR:AR,Data!B:B,Performance!$F$2,Data!D:D,Performance!N4)*10^6,SUMIFS(Data!AR:AR,Data!B:B,Performance!$F$2,Data!D:D,Performance!N4)) -> 886588369025 | R4: =Q4-P4 -> -95011003824 | S4: =IFERROR(R4/P4,"") -> -0.096792038 | U4: 1 | V4: =IF(K1="EN","SG&A / Net sales","CP bán hàng & quản lý / Doanh thu") -> CP bán hàng & quản lý / Doanh thu | W4: =IFERROR((G24-G29)/G6,0) -> 0.068520423 | X4: =IFERROR((H24-H29)/H6,0) -> 0.068898903 | Y4: =IFERROR((I24-I29)/I6,0) -> 0.080839702 | Z4: 0.1 | AC4: =P3 -> 5/2025 | AD4: =Q3 -> 5/2026
E5: Sales volume | F5: =IF($K$1="EN",E5,"Sản lượng bán")& IF(F2="DTPM"," (molds)"," (Tấn)") -> Sản lượng bán (Tấn) | G5: =SUMIFS(Data!Q:Q,Data!B:B,Performance!$E$2,Data!D:D,Performance!E5) -> 15468.961 | H5: =SUMIFS(Data!AD:AD,Data!B:B,Performance!$E$2,Data!D:D,Performance!E5) -> 23446.449 | I5: =SUMIFS(Data!AR:AR,Data!B:B,Performance!$E$2,Data!D:D,Performance!E5) -> 25012.587 | J5: =I5-H5 -> 1566.1384 | K5: =IFERROR(J5/H5,"") -> 0.066796402 | M5: =IF($K$1="EN",N5,"Tiền") -> Tiền | N5: Cash | O5: =IF($K$2="USD",SUMIFS(Data!Q:Q,Data!B:B,Performance!$F$2,Data!D:D,Performance!N5)*10^6,SUMIFS(Data!Q:Q,Data!B:B,Performance!$F$2,Data!D:D,Performance!N5)) -> 16007340290 | P5: =IF($K$2="USD",SUMIFS(Data!AD:AD,Data!B:B,Performance!$E$2,Data!D:D,Performance!N5)*10^6,SUMIFS(Data!AD:AD,Data!B:B,Performance!$E$2,Data!D:D,Performance!N5)) -> 21868727527 | Q5: =IF($K$2="USD",SUMIFS(Data!AR:AR,Data!B:B,Performance!$F$2,Data!D:D,Performance!N5)*10^6,SUMIFS(Data!AR:AR,Data!B:B,Performance!$F$2,Data!D:D,Performance!N5)) -> 41014004605 | R5: =Q5-P5 -> 19145277078 | S5: =IFERROR(R5/P5,"") -> 0.8754637 | U5: 2 | V5: =IF(K1="EN","Gross profit margin","Tỷ suất lợi nhuận gộp") -> Tỷ suất lợi nhuận gộp | W5: =IFERROR(G23/G6,0) -> 0.06734304 | X5: =IFERROR(H23/H6,0) -> 0.15103121 | Y5: =IFERROR(I23/I6,0) -> 0.090643578 | Z5: 0.25 | AB5: Tổng nợ | AC5: =P14+P17 -> 383542692015 | AD5: =Q14+Q17 -> 374252871584 | AE5: =AD5-AC5 -> -9289820431
E6: NET SALES | F6: =IF($K$1="EN",E6,"Doanh thu thuần") -> Doanh thu thuần | G6: =IF($K$2="USD",SUMIFS(Data!Q:Q,Data!B:B,Performance!$E$2,Data!D:D,Performance!E6)*10^6,SUMIFS(Data!Q:Q,Data!B:B,Performance!$E$2,Data!D:D,Performance!E6)) -> 456864963103 | H6: =IF($K$2="USD",SUMIFS(Data!AD:AD,Data!B:B,Performance!$E$2,Data!D:D,Performance!E6)*10^6,SUMIFS(Data!AD:AD,Data!B:B,Performance!$E$2,Data!D:D,Performance!E6)) -> 730212096848 | I6: =IF($K$2="USD",SUMIFS(Data!AR:AR,Data!B:B,Performance!$E$2,Data!D:D,Performance!E6)*10^6,SUMIFS(Data!AR:AR,Data!B:B,Performance!$E$2,Data!D:D,Performance!E6)) -> 714793828678 | J6: =I6-H6 -> -15418268170 | K6: =IFERROR(I6/H6-1,0) -> -0.021114781 | M6: =IF($K$1="EN",N6,"Đầu tư tài chính ngắn hạn") -> Đầu tư tài chính ngắn hạn | N6: Financial investment | O6: =IF($K$2="USD",SUMIFS(Data!Q:Q,Data!B:B,Performance!$F$2,Data!D:D,Performance!N6)*10^6,SUMIFS(Data!Q:Q,Data!B:B,Performance!$F$2,Data!D:D,Performance!N6)) -> 2010000000 | P6: =IF($K$2="USD",SUMIFS(Data!AD:AD,Data!B:B,Performance!$E$2,Data!D:D,Performance!N6)*10^6,SUMIFS(Data!AD:AD,Data!B:B,Performance!$E$2,Data!D:D,Performance!N6)) -> 22840000000 | Q6: =IF($K$2="USD",SUMIFS(Data!AR:AR,Data!B:B,Performance!$F$2,Data!D:D,Performance!N6)*10^6,SUMIFS(Data!AR:AR,Data!B:B,Performance!$F$2,Data!D:D,Performance!N6)) -> 34340000000 | R6: =Q6-P6 -> 11500000000 | S6: =IFERROR(R6/P6,"") -> 0.50350263 | U6: 3 | V6: =IF(K1="EN","EBITDA margin","Tỷ suất EBITDA") -> Tỷ suất EBITDA | W6: =IFERROR(G35/G6,0) -> 0.023923692 | X6: =IFERROR(H35/H6,0) -> 0.10211502 | Y6: =IFERROR(I35/I6,0) -> 0.01843225 | Z6: 0.2 | AB6: Vốn điều lệ | AC6: =P19-P20 -> 650000000000 | AD6: =Q19-Q20 -> 650000000000
E7: Export | F7: Xuất khẩu | G7: =IF(J2="USD",SUMIFS(Data!Q:Q,Data!B:B,Performance!$E$2,Data!D:D,Performance!E7)*10^6,SUMIFS(Data!Q:Q,Data!B:B,Performance!$E$2,Data!D:D,Performance!E7)) -> 410615873525 | H7: =IF(K2="USD",SUMIFS(Data!AD:AD,Data!B:B,Performance!$E$2,Data!D:D,Performance!E7)*10^6,SUMIFS(Data!AD:AD,Data!B:B,Performance!$E$2,Data!D:D,Performance!E7)) -> 518069151644 | I7: =IF(K2="USD",SUMIFS(Data!AR:AR,Data!B:B,Performance!$E$2,Data!D:D,Performance!E7)*10^6,SUMIFS(Data!AR:AR,Data!B:B,Performance!$E$2,Data!D:D,Performance!E7)) -> 364524912433 | J7: =I7-H7 -> -153544239211 | K7: =IFERROR(J7/H7,"") -> -0.29637788 | M7: =IF($K$1="EN",N7,"Các khoản phải thu") -> Các khoản phải thu | N7: Account receivables | O7: =IF($K$2="USD",SUMIFS(Data!Q:Q,Data!B:B,Performance!$F$2,Data!D:D,Performance!N7)*10^6,SUMIFS(Data!Q:Q,Data!B:B,Performance!$F$2,Data!D:D,Performance!N7)) -> 304477407097 | P7: =IF($K$2="USD",SUMIFS(Data!AD:AD,Data!B:B,Performance!$E$2,Data!D:D,Performance!N7)*10^6,SUMIFS(Data!AD:AD,Data!B:B,Performance!$E$2,Data!D:D,Performance!N7)) -> 355551041672 | Q7: =IF($K$2="USD",SUMIFS(Data!AR:AR,Data!B:B,Performance!$F$2,Data!D:D,Performance!N7)*10^6,SUMIFS(Data!AR:AR,Data!B:B,Performance!$F$2,Data!D:D,Performance!N7)) -> 417392857129 | R7: =Q7-P7 -> 61841815457 | S7: =IFERROR(R7/P7,"") -> 0.17393231 | U7: 4 | V7: =IF(K1="EN","Net profit margin (ROS)","Tỷ suất lợi nhuận sau thuế (ROS)") -> Tỷ suất lợi nhuận sau thuế (ROS) | W7: =IFERROR(G38/G6,0) -> -0.017472065 | X7: =IFERROR(H38/H6,0) -> 0.058445093 | Y7: =IFERROR(I38/I6,0) -> -0.0039828288 | Z7: 0.1 | AB7: Lợi nhuận luỹ kế | AC7: =P20 -> 247436969996 | AD7: =Q20 -> 227649509332 | AE7: =AD7-AC7 -> -19787460664
E8: Domestic | F8: Nội địa | G8: =IF(J2="USD",SUMIFS(Data!Q:Q,Data!B:B,Performance!$E$2,Data!D:D,Performance!E8)*10^6,SUMIFS(Data!Q:Q,Data!B:B,Performance!$E$2,Data!D:D,Performance!E8)) -> 161696678485 | H8: =IF(K2="USD",SUMIFS(Data!AD:AD,Data!B:B,Performance!$E$2,Data!D:D,Performance!E8)*10^6,SUMIFS(Data!AD:AD,Data!B:B,Performance!$E$2,Data!D:D,Performance!E8)) -> 211963572602 | I8: =IF(K2="USD",SUMIFS(Data!AR:AR,Data!B:B,Performance!$E$2,Data!D:D,Performance!E8)*10^6,SUMIFS(Data!AR:AR,Data!B:B,Performance!$E$2,Data!D:D,Performance!E8)) -> 346764544100 | J8: =I8-H8 -> 134800971498 | K8: =IFERROR(J8/H8,"") -> 0.63596291 | M8: =IF($K$1="EN",N8,"Hàng tồn kho") -> Hàng tồn kho | N8: Inventory | O8: =IF($K$2="USD",SUMIFS(Data!Q:Q,Data!B:B,Performance!$F$2,Data!D:D,Performance!N8)*10^6,SUMIFS(Data!Q:Q,Data!B:B,Performance!$F$2,Data!D:D,Performance!N8)) -> 541180364701 | P8: =IF($K$2="USD",SUMIFS(Data!AD:AD,Data!B:B,Performance!$E$2,Data!D:D,Performance!N8)*10^6,SUMIFS(Data!AD:AD,Data!B:B,Performance!$E$2,Data!D:D,Performance!N8)) -> 526499028418 | Q8: =IF($K$2="USD",SUMIFS(Data!AR:AR,Data!B:B,Performance!$F$2,Data!D:D,Performance!N8)*10^6,SUMIFS(Data!AR:AR,Data!B:B,Performance!$F$2,Data!D:D,Performance!N8)) -> 361880765551 | R8: =Q8-P8 -> -164618262867 | S8: =IFERROR(R8/P8,"") -> -0.31266584 | U8: 5 | V8: =IF(K1="EN","Net contribution margin","Tỷ suất lãi biến phí") -> Tỷ suất lãi biến phí | W8: =IFERROR((G6-G11-G12-G13-G29-G21-G27-G28-G22)/G6,0) -> 0.35666237 | X8: =IFERROR((H6-H11-H12-H13-H29-H21-H27-H28-H22)/H6,0) -> 0.29301473 | Y8: =IFERROR((I6-I11-I12-I13-I29-I21-I28-I27-I22)/I6,0) -> 0.23303561 | Z8: 0.4 | AB8: Tổng nguồn vốn | AC8: =SUM(AC5:AC7) -> 1280979662011 | AD8: =SUM(AD5:AD7) -> 1251902380916
E9: Others | F9: Khác | G9: =IF(J2="USD",SUMIFS(Data!Q:Q,Data!B:B,Performance!$E$2,Data!D:D,Performance!E9)*10^6,SUMIFS(Data!Q:Q,Data!B:B,Performance!$E$2,Data!D:D,Performance!E9)) -> 0 | H9: =IF(K2="USD",SUMIFS(Data!AD:AD,Data!B:B,Performance!$E$2,Data!D:D,Performance!E9)*10^6,SUMIFS(Data!AD:AD,Data!B:B,Performance!$E$2,Data!D:D,Performance!E9)) -> 179372602 | I9: =IF(K2="USD",SUMIFS(Data!AR:AR,Data!B:B,Performance!$E$2,Data!D:D,Performance!E9)*10^6,SUMIFS(Data!AR:AR,Data!B:B,Performance!$E$2,Data!D:D,Performance!E9)) -> 3504372145 | J9: =I9-H9 -> 3324999543 | K9: =IFERROR(J9/H9,0) -> 18.536831 | M9: =IF($K$1="EN",N9,"Tài sản dài hạn") -> Tài sản dài hạn | N9: Long-term assets | O9: =IF($K$2="USD",SUMIFS(Data!Q:Q,Data!B:B,Performance!$F$2,Data!D:D,Performance!N9)*10^6,SUMIFS(Data!Q:Q,Data!B:B,Performance!$F$2,Data!D:D,Performance!N9)) -> 269907328559 | P9: =IF($K$2="USD",SUMIFS(Data!AD:AD,Data!B:B,Performance!$E$2,Data!D:D,Performance!N9)*10^6,SUMIFS(Data!AD:AD,Data!B:B,Performance!$E$2,Data!D:D,Performance!N9)) -> 299380289162 | Q9: =IF($K$2="USD",SUMIFS(Data!AR:AR,Data!B:B,Performance!$F$2,Data!D:D,Performance!N9)*10^6,SUMIFS(Data!AR:AR,Data!B:B,Performance!$F$2,Data!D:D,Performance!N9)) -> 365314011891 | R9: =Q9-P9 -> 65933722729 | S9: =IFERROR(R9/P9,"") -> 0.22023401 | U9: 6 | V9: =IF(K1="EN","D/E","Nợ / Vốn chủ sở hữu") -> Nợ / Vốn chủ sở hữu | W9: =(O14+O17-O6)/O19 -> 0.50776939 | X9: =(P14+P17)/P19 -> 0.42737563 | Y9: =(Q14+Q17)/Q19 -> 0.42642634 | Z9: 1
E10: Cost of Goods Sold (COGS) | F10: =IF($K$1="EN",E10,"Giá vốn hàng bán") -> Giá vốn hàng bán | G10: =IF(J2="USD",SUMIFS(Data!Q:Q,Data!B:B,Performance!$E$2,Data!D:D,Performance!E10)*10^6,SUMIFS(Data!Q:Q,Data!B:B,Performance!$E$2,Data!D:D,Performance!E10)) -> 426098287597 | H10: =IF(K2="USD",SUMIFS(Data!AD:AD,Data!B:B,Performance!$E$2,Data!D:D,Performance!E10)*10^6,SUMIFS(Data!AD:AD,Data!B:B,Performance!$E$2,Data!D:D,Performance!E10)) -> 619927281523 | I10: =IF(K2="USD",SUMIFS(Data!AR:AR,Data!B:B,Performance!$E$2,Data!D:D,Performance!E10)*10^6,SUMIFS(Data!AR:AR,Data!B:B,Performance!$E$2,Data!D:D,Performance!E10)) -> 650002358474 | J10: =I10-H10 -> 30075076951 | K10: =IFERROR(J10/H10,0) -> 0.048513879 | M10: =IF($K$1="EN",N10,"Tài sản cố định") -> Tài sản cố định | N10: Fixed Assets | O10: =IF($K$2="USD",SUMIFS(Data!Q:Q,Data!B:B,Performance!$F$2,Data!D:D,Performance!N10)*10^6,SUMIFS(Data!Q:Q,Data!B:B,Performance!$F$2,Data!D:D,Performance!N10)) -> 224673388970 | P10: =IF($K$2="USD",SUMIFS(Data!AD:AD,Data!B:B,Performance!$E$2,Data!D:D,Performance!N10)*10^6,SUMIFS(Data!AD:AD,Data!B:B,Performance!$E$2,Data!D:D,Performance!N10)) -> 237349552865 | Q10: =IF($K$2="USD",SUMIFS(Data!AR:AR,Data!B:B,Performance!$F$2,Data!D:D,Performance!N10)*10^6,SUMIFS(Data!AR:AR,Data!B:B,Performance!$F$2,Data!D:D,Performance!N10)) -> 268070715296 | R10: =Q10-P10 -> 30721162431 | S10: =IFERROR(R10/P10,"") -> 0.12943425 | U10: 7 | V10: =IF(K1="EN","Debt / EBITDA","Nợ vay / EBITDA") -> Nợ vay / EBITDA | W10: =(O15+O18)/G35 -> 23.250062 | X10: 0.58194405 | Y10: 7.9845739 | Z10: 4 | AB10: Nợ phải thu | AC10: =P7 -> 355551041672 | AD10: =Q7 -> 417392857129 | AE10: =AD10-AC10 -> 61841815457 | AF10: =SUM(AE10:AE12) -> -36842724681
D11: VC | E11: Material cost | F11: =IF($K$1="EN",E11,"Chi phí nguyên vật liệu") -> Chi phí nguyên vật liệu | G11: =IF(J2="USD",SUMIFS(Data!Q:Q,Data!B:B,Performance!$E$2,Data!D:D,Performance!E11)*10^6,SUMIFS(Data!Q:Q,Data!B:B,Performance!$E$2,Data!D:D,Performance!E11)) -> 2.8650612e+11 | H11: =IF(K2="USD",SUMIFS(Data!AD:AD,Data!B:B,Performance!$E$2,Data!D:D,Performance!E11)*10^6,SUMIFS(Data!AD:AD,Data!B:B,Performance!$E$2,Data!D:D,Performance!E11)) -> 4.5534206e+11 | I11: =IF(K2="USD",SUMIFS(Data!AR:AR,Data!B:B,Performance!$E$2,Data!D:D,Performance!E11)*10^6,SUMIFS(Data!AR:AR,Data!B:B,Performance!$E$2,Data!D:D,Performance!E11)) -> 4.6521435e+11 | J11: =I11-H11 -> 9.8722882e+09 | K11: =IFERROR(J11/H11,"") -> 0.021681037 | M11: =IF($K$1="EN",N11,"Nguyên giá") -> Nguyên giá | N11: Cost | O11: =IF($K$2="USD",SUMIFS(Data!Q:Q,Data!B:B,Performance!$F$2,Data!D:D,Performance!N11)*10^6,SUMIFS(Data!Q:Q,Data!B:B,Performance!$F$2,Data!D:D,Performance!N11)) -> 299394448651 | P11: =IF($K$2="USD",SUMIFS(Data!AD:AD,Data!B:B,Performance!$E$2,Data!D:D,Performance!N11)*10^6,SUMIFS(Data!AD:AD,Data!B:B,Performance!$E$2,Data!D:D,Performance!N11)) -> 338856847837 | Q11: =IF($K$2="USD",SUMIFS(Data!AR:AR,Data!B:B,Performance!$F$2,Data!D:D,Performance!N11)*10^6,SUMIFS(Data!AR:AR,Data!B:B,Performance!$F$2,Data!D:D,Performance!N11)) -> 409700584982 | R11: =Q11-P11 -> 70843737145 | S11: =IFERROR(R11/P11,"") -> 0.20906686 | U11: 8 | V11: =IF(K1="EN","Current liquidity","Khả năng thanh toán hiện hành") -> Khả năng thanh toán hiện hành | W11: =O4/O14 -> 2.8161069 | X11: =P4/P14 -> 3.4377216 | Y11: =Q4/Q14 -> 4.0424487 | Z11: 1.5 | AB11: Hàng tồn kho | AC11: =P8 -> 526499028418 | AD11: =Q8 -> 361880765551 | AE11: =AD11-AC11 -> -164618262867
B12: Production cost | D12: VC | E12: Electricity | F12: =IF($K$1="EN",E12,"Chi phí điện") -> Chi phí điện | G12: =IF(J2="USD",SUMIFS(Data!Q:Q,Data!B:B,Performance!$E$2,Data!D:D,Performance!E12)*10^6,SUMIFS(Data!Q:Q,Data!B:B,Performance!$E$2,Data!D:D,Performance!E12)) -> 26054054069 | H12: =IF(K2="USD",SUMIFS(Data!AD:AD,Data!B:B,Performance!$E$2,Data!D:D,Performance!E12)*10^6,SUMIFS(Data!AD:AD,Data!B:B,Performance!$E$2,Data!D:D,Performance!E12)) -> 26358956271 | I12: =IF(K2="USD",SUMIFS(Data!AR:AR,Data!B:B,Performance!$E$2,Data!D:D,Performance!E12)*10^6,SUMIFS(Data!AR:AR,Data!B:B,Performance!$E$2,Data!D:D,Performance!E12)) -> 23524568050 | J12: =I12-H12 -> -2834388221 | K12: =IFERROR(J12/H12,"") -> -0.10753037 | M12: =IF($K$1="EN",N12,"Hao mòn lũy kế") -> Hao mòn lũy kế | N12: Accumulated depreciation | O12: =IF($K$2="USD",SUMIFS(Data!Q:Q,Data!B:B,Performance!$F$2,Data!D:D,Performance!N12)*10^6,SUMIFS(Data!Q:Q,Data!B:B,Performance!$F$2,Data!D:D,Performance!N12)) -> -74721059681 | P12: =IF($K$2="USD",SUMIFS(Data!AD:AD,Data!B:B,Performance!$E$2,Data!D:D,Performance!N12)*10^6,SUMIFS(Data!AD:AD,Data!B:B,Performance!$E$2,Data!D:D,Performance!N12)) -> -101507294972 | Q12: =IF($K$2="USD",SUMIFS(Data!AR:AR,Data!B:B,Performance!$F$2,Data!D:D,Performance!N12)*10^6,SUMIFS(Data!AR:AR,Data!B:B,Performance!$F$2,Data!D:D,Performance!N12)) -> -141629869686 | R12: =Q12-P12 -> -40122574714 | S12: =IFERROR(R12/P12,"") -> 0.39526789 | U12: 9 | V12: =IF(K1="EN","Quick liquidity","Khả năng thanh toán nhanh") -> Khả năng thanh toán nhanh | W12: =(O4-O8)/O14 -> 1.1741176 | X12: =(P4-P8)/P14 -> 1.5938359 | Y12: =(Q4-Q8)/Q14 -> 2.3924333 | Z12: 1 | AB12: Tài sản cố định | AC12: =P9 -> 299380289162 | AD12: =Q9 -> 365314011891 | AE12: =AD12-AC12 -> 65933722729
B13: Production cost | D13: VC | E13: Overtime | F13: =IF($K$1="EN",E13,"Lương ngoài giờ") -> Lương ngoài giờ | G13: =IF(J2="USD",SUMIFS(Data!Q:Q,Data!B:B,Performance!$E$2,Data!D:D,Performance!E13)*10^6,SUMIFS(Data!Q:Q,Data!B:B,Performance!$E$2,Data!D:D,Performance!E13)) -> 4297992394 | H13: =IF(K2="USD",SUMIFS(Data!AD:AD,Data!B:B,Performance!$E$2,Data!D:D,Performance!E13)*10^6,SUMIFS(Data!AD:AD,Data!B:B,Performance!$E$2,Data!D:D,Performance!E13)) -> 1932148253 | I13: =IF(K2="USD",SUMIFS(Data!AR:AR,Data!B:B,Performance!$E$2,Data!D:D,Performance!E13)*10^6,SUMIFS(Data!AR:AR,Data!B:B,Performance!$E$2,Data!D:D,Performance!E13)) -> 1809482234 | J13: =I13-H13 -> -122666019 | K13: =IFERROR(J13/H13,"") -> -0.063486857 | M13: =IF($K$1="EN",N13,"Tổng tài sản") -> Tổng tài sản | N13: Total Assets | O13: =O4+O9 -> 1198063045295 | P13: =P4+P9 -> 1280979662011 | Q13: =Q4+Q9 -> 1251902380916 | R13: =Q13-P13 -> -29077281095 | S13: =IFERROR(R13/P13,"") -> -0.022699253 | U13: 10 | V13: =IF(K1="EN","DWC (days)","Ngày vốn lưu động (ngày)") -> Ngày vốn lưu động (ngày) | W13: =IFERROR((O7+O8-O16)*30*G2/G6,0) -> 589.67503 | X13: =IFERROR((P7+P8-P16)*30*H2/H6,0) -> 173.63858 | Y13: =IFERROR((Q7+Q8-Q16)*30*I2/I6,0) -> 149.74002 | Z13: 90 | AB13: Tiền | AC13: =IF(F2="MIDA",P5,P5+P6) -> 44708727527 | AD13: =IF(F2="MIDA",Q5,Q5+Q6) -> 75354004605 | AE13: =AD13-AC13 -> 30645277078
B14: Production cost | C14: FOH | D14: FC | E14: Direct labor | F14: =IF($K$1="EN",E14,"Lương nhân công trực tiếp") -> Lương nhân công trực tiếp | G14: =IF(J2="USD",SUMIFS(Data!Q:Q,Data!B:B,Performance!$E$2,Data!D:D,Performance!E14)*10^6,SUMIFS(Data!Q:Q,Data!B:B,Performance!$E$2,Data!D:D,Performance!E14)) -> 6496977417 | H14: =IF(K2="USD",SUMIFS(Data!AD:AD,Data!B:B,Performance!$E$2,Data!D:D,Performance!E14)*10^6,SUMIFS(Data!AD:AD,Data!B:B,Performance!$E$2,Data!D:D,Performance!E14)) -> 10924942546 | I14: =IF(K2="USD",SUMIFS(Data!AR:AR,Data!B:B,Performance!$E$2,Data!D:D,Performance!E14)*10^6,SUMIFS(Data!AR:AR,Data!B:B,Performance!$E$2,Data!D:D,Performance!E14)) -> 11177167097 | J14: =I14-H14 -> 252224551 | K14: =IFERROR(J14/H14,"") -> 0.023087037 | M14: =IF($K$1="EN",N14,"Nợ ngắn hạn") -> Nợ ngắn hạn | N14: Short-term Liabilities | O14: =IF($K$2="USD",SUMIFS(Data!Q:Q,Data!B:B,Performance!$F$2,Data!D:D,Performance!N14)*10^6,SUMIFS(Data!Q:Q,Data!B:B,Performance!$F$2,Data!D:D,Performance!N14)) -> 329588242794 | P14: =IF($K$2="USD",SUMIFS(Data!AD:AD,Data!B:B,Performance!$E$2,Data!D:D,Performance!N14)*10^6,SUMIFS(Data!AD:AD,Data!B:B,Performance!$E$2,Data!D:D,Performance!N14)) -> 285537774573 | Q14: =IF($K$2="USD",SUMIFS(Data!AR:AR,Data!B:B,Performance!$F$2,Data!D:D,Performance!N14)*10^6,SUMIFS(Data!AR:AR,Data!B:B,Performance!$F$2,Data!D:D,Performance!N14)) -> 219319635169 | R14: =Q14-P14 -> -66218139404 | S14: =IFERROR(R14/P14,"") -> -0.23190676 | U14: 11 | V14: =IF(K1="EN","ROE","Lợi nhuận / Vốn chủ sở hữu (ROE)") -> Lợi nhuận / Vốn chủ sở hữu (ROE) | W14: =O20/O19 -> 0.18059646 | X14: 0.11114706 | Y14: -0.02089847 | Z14: 0.2 | AB14: Khấu hao | AC14: =P12 -> -101507294972 | AD14: =Q12 -> -141629869686 | AE14: =-(AD14-AC14)/10^3 -> 40122575
B15: Production cost | C15: FOH | D15: FC | E15: Indirect labor | F15: =IF($K$1="EN",E15,"Lương nhân công gián tiếp") -> Lương nhân công gián tiếp | G15: =IF(J2="USD",SUMIFS(Data!Q:Q,Data!B:B,Performance!$E$2,Data!D:D,Performance!E15)*10^6,SUMIFS(Data!Q:Q,Data!B:B,Performance!$E$2,Data!D:D,Performance!E15)) -> 14365408991 | H15: =IF(K2="USD",SUMIFS(Data!AD:AD,Data!B:B,Performance!$E$2,Data!D:D,Performance!E15)*10^6,SUMIFS(Data!AD:AD,Data!B:B,Performance!$E$2,Data!D:D,Performance!E15)) -> 19333674244 | I15: =IF(K2="USD",SUMIFS(Data!AR:AR,Data!B:B,Performance!$E$2,Data!D:D,Performance!E15)*10^6,SUMIFS(Data!AR:AR,Data!B:B,Performance!$E$2,Data!D:D,Performance!E15)) -> 20071879576 | J15: =I15-H15 -> 738205332 | K15: =IFERROR(J15/H15,"") -> 0.038182361 | M15: =IF($K$1="EN",N15,"Vay ngắn hạn") -> Vay ngắn hạn | N15: Short-term borrowings | O15: =IF($K$2="USD",SUMIFS(Data!Q:Q,Data!B:B,Performance!$F$2,Data!D:D,Performance!N15)*10^6,SUMIFS(Data!Q:Q,Data!B:B,Performance!$F$2,Data!D:D,Performance!N15)) -> 178905916168 | P15: =IF($K$2="USD",SUMIFS(Data!AD:AD,Data!B:B,Performance!$E$2,Data!D:D,Performance!N15)*10^6,SUMIFS(Data!AD:AD,Data!B:B,Performance!$E$2,Data!D:D,Performance!N15)) -> 200666324688 | Q15: =IF($K$2="USD",SUMIFS(Data!AR:AR,Data!B:B,Performance!$F$2,Data!D:D,Performance!N15)*10^6,SUMIFS(Data!AR:AR,Data!B:B,Performance!$F$2,Data!D:D,Performance!N15)) -> 116595603825 | R15: =Q15-P15 -> -84070720863 | S15: =IFERROR(R15/P15,"") -> -0.41895779 | U15: 12 | V15: =IF(K1="EN","ROA","Lợi nhuận / Tài sản (ROA)") -> Lợi nhuận / Tài sản (ROA) | W15: =O20/O13 -> 0.11957629 | X15: 0.076189954 | Y15: -0.014554774 | Z15: 0.15
B16: Production cost | C16: FOH | D16: FC | E16: Employee welfare (FOH) | F16: =IF($K$1="EN",E16,"Phúc lợi nhân viên") -> Phúc lợi nhân viên | G16: =IF(J2="USD",SUMIFS(Data!Q:Q,Data!B:B,Performance!$E$2,Data!D:D,Performance!E16)*10^6,SUMIFS(Data!Q:Q,Data!B:B,Performance!$E$2,Data!D:D,Performance!E16)) -> 4887723770 | H16: =IF(K2="USD",SUMIFS(Data!AD:AD,Data!B:B,Performance!$E$2,Data!D:D,Performance!E16)*10^6,SUMIFS(Data!AD:AD,Data!B:B,Performance!$E$2,Data!D:D,Performance!E16)) -> 6473941109 | I16: =IF(K2="USD",SUMIFS(Data!AR:AR,Data!B:B,Performance!$E$2,Data!D:D,Performance!E16)*10^6,SUMIFS(Data!AR:AR,Data!B:B,Performance!$E$2,Data!D:D,Performance!E16)) -> 6450663123 | J16: =I16-H16 -> -23277986 | K16: =IFERROR(J16/H16,"") -> -0.0035956438 | M16: =IF($K$1="EN",N16,"Các khoản phải trả") -> Các khoản phải trả | N16: Account payables | O16: =IF($K$2="USD",SUMIFS(Data!Q:Q,Data!B:B,Performance!$F$2,Data!D:D,Performance!N16)*10^6,SUMIFS(Data!Q:Q,Data!B:B,Performance!$F$2,Data!D:D,Performance!N16)) -> 97319270425 | P16: =IF($K$2="USD",SUMIFS(Data!AD:AD,Data!B:B,Performance!$E$2,Data!D:D,Performance!N16)*10^6,SUMIFS(Data!AD:AD,Data!B:B,Performance!$E$2,Data!D:D,Performance!N16)) -> 36763462032 | Q16: =IF($K$2="USD",SUMIFS(Data!AR:AR,Data!B:B,Performance!$F$2,Data!D:D,Performance!N16)*10^6,SUMIFS(Data!AR:AR,Data!B:B,Performance!$F$2,Data!D:D,Performance!N16)) -> 65718659314 | R16: =Q16-P16 -> 28955197282 | S16: =IFERROR(R16/P16,"") -> 0.78760801 | U16: Net Cash flow | V16: =IF(K1="EN","CASH FLOW","DÒNG TIỀN") -> DÒNG TIỀN | W16: =W3 -> Năm 2024 | X16: =X3 -> LK 2025 | Y16: =Y3 -> LK 2026
B17: Production cost | C17: FOH | D17: FC | E17: Repairs and maintanance | F17: =IF($K$1="EN",E17,"Sửa chữa, bảo trì") -> Sửa chữa, bảo trì | G17: =IF(J2="USD",SUMIFS(Data!Q:Q,Data!B:B,Performance!$E$2,Data!D:D,Performance!E17)*10^6,SUMIFS(Data!Q:Q,Data!B:B,Performance!$E$2,Data!D:D,Performance!E17)) -> 2592205996 | H17: =IF(K2="USD",SUMIFS(Data!AD:AD,Data!B:B,Performance!$E$2,Data!D:D,Performance!E17)*10^6,SUMIFS(Data!AD:AD,Data!B:B,Performance!$E$2,Data!D:D,Performance!E17)) -> 3558171258 | I17: =IF(K2="USD",SUMIFS(Data!AR:AR,Data!B:B,Performance!$E$2,Data!D:D,Performance!E17)*10^6,SUMIFS(Data!AR:AR,Data!B:B,Performance!$E$2,Data!D:D,Performance!E17)) -> 3158106760 | J17: =I17-H17 -> -400064498 | K17: =IFERROR(J17/H17,"") -> -0.11243543 | M17: =IF($K$1="EN",N17,"Nợ dài hạn") -> Nợ dài hạn | N17: Long-term liabilities | O17: =IF($K$2="USD",SUMIFS(Data!Q:Q,Data!B:B,Performance!$F$2,Data!D:D,Performance!N17)*10^6,SUMIFS(Data!Q:Q,Data!B:B,Performance!$F$2,Data!D:D,Performance!N17)) -> 75214867678 | P17: =IF($K$2="USD",SUMIFS(Data!AD:AD,Data!B:B,Performance!$E$2,Data!D:D,Performance!N17)*10^6,SUMIFS(Data!AD:AD,Data!B:B,Performance!$E$2,Data!D:D,Performance!N17)) -> 98004917442 | Q17: =IF($K$2="USD",SUMIFS(Data!AR:AR,Data!B:B,Performance!$F$2,Data!D:D,Performance!N17)*10^6,SUMIFS(Data!AR:AR,Data!B:B,Performance!$F$2,Data!D:D,Performance!N17)) -> 154933236415 | R17: =Q17-P17 -> 56928318973 | S17: =IFERROR(R17/P17,"") -> 0.58087207 | U17: Net cash flow from operating activities | V17: =IF(K1="EN","Cash flow from operation","Dòng tiền hoạt động kinh doanh") -> Dòng tiền hoạt động kinh doanh | W17: =Data!AC18 -> -22475023560 | X17: =IF($K$2="USD",SUMIFS(Data!$AD:$AD,Data!$B:$B,Performance!$E$2,Data!$D:$D,Performance!$U17)*10^6,SUMIFS(Data!$AD:$AD,Data!$B:$B,Performance!$E$2,Data!$D:$D,Performance!$U17)) -> 55101774784 | Y17: =IF($K$2="USD",SUMIFS(Data!$AR:$AR,Data!$B:$B,Performance!$E$2,Data!$D:$D,Performance!$U17)*10^6,SUMIFS(Data!$AR:$AR,Data!$B:$B,Performance!$E$2,Data!$D:$D,Performance!$U17)) -> 135903187315 | Z17: =Y17-X17 -> 80801412531
B18: Production cost | C18: FOH | D18: FC | E18: Factory expenses | F18: =IF($K$1="EN",E18,"Chi phí chung phân xưởng") -> Chi phí chung phân xưởng | G18: =IF(J2="USD",SUMIFS(Data!Q:Q,Data!B:B,Performance!$E$2,Data!D:D,Performance!E18)*10^6,SUMIFS(Data!Q:Q,Data!B:B,Performance!$E$2,Data!D:D,Performance!E18)) -> 35211653392 | H18: =IF(K2="USD",SUMIFS(Data!AD:AD,Data!B:B,Performance!$E$2,Data!D:D,Performance!E18)*10^6,SUMIFS(Data!AD:AD,Data!B:B,Performance!$E$2,Data!D:D,Performance!E18)) -> 36726436636 | I18: =IF(K2="USD",SUMIFS(Data!AR:AR,Data!B:B,Performance!$E$2,Data!D:D,Performance!E18)*10^6,SUMIFS(Data!AR:AR,Data!B:B,Performance!$E$2,Data!D:D,Performance!E18)) -> 41164807588 | J18: =I18-H18 -> 4438370952 | K18: =IFERROR(J18/H18,"") -> 0.12084948 | M18: =IF($K$1="EN",N15,"Vay dài hạn") -> Vay dài hạn | N18: Long-term borrowings | O18: =IF($K$2="USD",SUMIFS(Data!Q:Q,Data!B:B,Performance!$F$2,Data!D:D,Performance!N18)*10^6,SUMIFS(Data!Q:Q,Data!B:B,Performance!$F$2,Data!D:D,Performance!N18)) -> 75214867678 | P18: =IF($K$2="USD",SUMIFS(Data!AD:AD,Data!B:B,Performance!$E$2,Data!D:D,Performance!N18)*10^6,SUMIFS(Data!AD:AD,Data!B:B,Performance!$E$2,Data!D:D,Performance!N18)) -> 98004917442 | Q18: =IF($K$2="USD",SUMIFS(Data!AR:AR,Data!B:B,Performance!$F$2,Data!D:D,Performance!N18)*10^6,SUMIFS(Data!AR:AR,Data!B:B,Performance!$F$2,Data!D:D,Performance!N18)) -> 154933236415 | R18: =Q18-P18 -> 56928318973 | S18: =IFERROR(R18/P18,"") -> 0.58087207 | U18: Net cash flow from investment activities | V18: =IF(K1="EN","Cash flow from investment","Dòng tiền hoạt động đầu tư") -> Dòng tiền hoạt động đầu tư | W18: =Data!AC21 -> 15615882426 | X18: =IF($K$2="USD",SUMIFS(Data!$AD:$AD,Data!$B:$B,Performance!$E$2,Data!$D:$D,Performance!$U18)*10^6,SUMIFS(Data!$AD:$AD,Data!$B:$B,Performance!$E$2,Data!$D:$D,Performance!$U18)) -> -100725871241 | Y18: =IF($K$2="USD",SUMIFS(Data!$AR:$AR,Data!$B:$B,Performance!$E$2,Data!$D:$D,Performance!$U18)*10^6,SUMIFS(Data!$AR:$AR,Data!$B:$B,Performance!$E$2,Data!$D:$D,Performance!$U18)) -> -92531166165
D19: FC | E19: Depreciation (FOH) | F19: =IF($K$1="EN",E19,"Khấu hao (sản xuất)") -> Khấu hao (sản xuất) | G19: =IF(J2="USD",SUMIFS(Data!Q:Q,Data!B:B,Performance!$E$2,Data!D:D,Performance!E19)*10^6,SUMIFS(Data!Q:Q,Data!B:B,Performance!$E$2,Data!D:D,Performance!E19)) -> 20052559894 | H19: =IF(K2="USD",SUMIFS(Data!AD:AD,Data!B:B,Performance!$E$2,Data!D:D,Performance!E19)*10^6,SUMIFS(Data!AD:AD,Data!B:B,Performance!$E$2,Data!D:D,Performance!E19)) -> 31961594702 | I19: =IF(K2="USD",SUMIFS(Data!AR:AR,Data!B:B,Performance!$E$2,Data!D:D,Performance!E19)*10^6,SUMIFS(Data!AR:AR,Data!B:B,Performance!$E$2,Data!D:D,Performance!E19)) -> 28122702259 | J19: =I19-H19 -> -3838892443 | K19: =IFERROR(J19/H19,"") -> -0.12010954 | M19: =IF($K$1="EN",N19,"Vốn chủ sở hữu") -> Vốn chủ sở hữu | N19: Equity | O19: =IF($K$2="USD",SUMIFS(Data!Q:Q,Data!B:B,Performance!$F$2,Data!D:D,Performance!N19)*10^6,SUMIFS(Data!Q:Q,Data!B:B,Performance!$F$2,Data!D:D,Performance!N19)) -> 793259934823 | P19: =IF($K$2="USD",SUMIFS(Data!AD:AD,Data!B:B,Performance!$E$2,Data!D:D,Performance!N19)*10^6,SUMIFS(Data!AD:AD,Data!B:B,Performance!$E$2,Data!D:D,Performance!N19)) -> 897436969996 | Q19: =IF($K$2="USD",SUMIFS(Data!AR:AR,Data!B:B,Performance!$F$2,Data!D:D,Performance!N19)*10^6,SUMIFS(Data!AR:AR,Data!B:B,Performance!$F$2,Data!D:D,Performance!N19)) -> 877649509332 | R19: =Q19-P19 -> -19787460664 | S19: =IFERROR(R19/P19,"") -> -0.022048858 | U19: Net cash flow from financial activities | V19: =IF(K1="EN","Cash flow from finance","Dòng tiền hoạt động tài chính") -> Dòng tiền hoạt động tài chính | X19: =IF($K$2="USD",SUMIFS(Data!$AD:$AD,Data!$B:$B,Performance!$E$2,Data!$D:$D,Performance!$U19)*10^6,SUMIFS(Data!$AD:$AD,Data!$B:$B,Performance!$E$2,Data!$D:$D,Performance!$U19)) -> 23143016200 | Y19: =IF($K$2="USD",SUMIFS(Data!$AR:$AR,Data!$B:$B,Performance!$E$2,Data!$D:$D,Performance!$U19)*10^6,SUMIFS(Data!$AR:$AR,Data!$B:$B,Performance!$E$2,Data!$D:$D,Performance!$U19)) -> -41079393352
D20: FC | E20: Other COGs | F20: =IF($K$1="EN",E20,"Giá vốn Khác") -> Giá vốn Khác | G20: =IF(J2="USD",SUMIFS(Data!Q:Q,Data!B:B,Performance!$E$2,Data!D:D,Performance!E20)*10^6,SUMIFS(Data!Q:Q,Data!B:B,Performance!$E$2,Data!D:D,Performance!E20)) -> 60188636051 | H20: =IF(K2="USD",SUMIFS(Data!AD:AD,Data!B:B,Performance!$E$2,Data!D:D,Performance!E20)*10^6,SUMIFS(Data!AD:AD,Data!B:B,Performance!$E$2,Data!D:D,Performance!E20)) -> 1.223123e+10 | I20: =IF(K2="USD",SUMIFS(Data!AR:AR,Data!B:B,Performance!$E$2,Data!D:D,Performance!E20)*10^6,SUMIFS(Data!AR:AR,Data!B:B,Performance!$E$2,Data!D:D,Performance!E20)) -> 9.7017706e+09 | J20: =I20-H20 -> -2.529459e+09 | K20: =IFERROR(J20/H20,"") -> -0.20680333 | M20: =IF($K$1="EN",N20,"Lợi nhuận chưa phân phối") -> Lợi nhuận chưa phân phối | N20: Retained earnings | O20: =IF($K$2="USD",SUMIFS(Data!Q:Q,Data!B:B,Performance!$F$2,Data!D:D,Performance!N20)*10^6,SUMIFS(Data!Q:Q,Data!B:B,Performance!$F$2,Data!D:D,Performance!N20)) -> 143259934823 | P20: =IF($K$2="USD",SUMIFS(Data!AD:AD,Data!B:B,Performance!$E$2,Data!D:D,Performance!N20)*10^6,SUMIFS(Data!AD:AD,Data!B:B,Performance!$E$2,Data!D:D,Performance!N20)) -> 247436969996 | Q20: =IF($K$2="USD",SUMIFS(Data!AR:AR,Data!B:B,Performance!$F$2,Data!D:D,Performance!N20)*10^6,SUMIFS(Data!AR:AR,Data!B:B,Performance!$F$2,Data!D:D,Performance!N20)) -> 227649509332 | R20: =Q20-P20 -> -19787460664 | S20: =IFERROR(R20/P20,"") -> -0.079969702 | V20: =IF(K1="EN","Productivity KPI","KPI năng suất") -> KPI năng suất | W20: =W3 -> Năm 2024 | X20: =X3 -> LK 2025 | Y20: =Y3 -> LK 2026
D21: VC | E21: Processing cost | F21: =IF($K$1="EN",E21,"Phí gia công") -> Phí gia công | G21: =IF(J2="USD",SUMIFS(Data!Q:Q,Data!B:B,Performance!$E$2,Data!D:D,Performance!E21)*10^6,SUMIFS(Data!Q:Q,Data!B:B,Performance!$E$2,Data!D:D,Performance!E21)) -> 5461823200 | H21: =IF(K2="USD",SUMIFS(Data!AD:AD,Data!B:B,Performance!$E$2,Data!D:D,Performance!E21)*10^6,SUMIFS(Data!AD:AD,Data!B:B,Performance!$E$2,Data!D:D,Performance!E21)) -> 4762024734 | I21: =IF(K2="USD",SUMIFS(Data!AR:AR,Data!B:B,Performance!$E$2,Data!D:D,Performance!E21)*10^6,SUMIFS(Data!AR:AR,Data!B:B,Performance!$E$2,Data!D:D,Performance!E21)) -> 387853873 | J21: =I21-H21 -> -4374170861 | K21: =IFERROR(J21/H21,"") -> -0.91855274 | M21: =IF($K$1="EN",N21,"Tổng nguồn vốn") -> Tổng nguồn vốn | N21: Total Resources | O21: =O14+O17+O19 -> 1198063045295 | P21: =P14+P17+P19 -> 1280979662011 | Q21: =Q14+Q17+Q19 -> 1251902380916 | R21: =Q21-P21 -> -29077281095 | S21: =IFERROR(R21/P21,"") -> -0.022699253 | V21: Doanh thu / người (Triệu/người) | W21: =IFERROR(G6/IFERROR(SUMIFS(Data!Q:Q,Data!B:B,Performance!$E$2,Data!D:D,"Total Headcount"),0)/10^6,0) -> 970.73559 | X21: =IFERROR(H6/IFERROR(SUMIFS(Data!AD:AD,Data!B:B,Performance!$E$2,Data!D:D,"Total Headcount"),0)/10^6,0) -> 1198.559 | Y21: =IFERROR(I6/IFERROR(SUMIFS(Data!AR:AR,Data!B:B,Performance!$E$2,Data!D:D,"Total Headcount"),0)/10^6,0) -> 1146.2534 | Z21: =Y21-X21 -> -52.305567
E22: COGs in inventory | F22: =IF($K$1="EN",E22,"Giá vốn trong thành phẩm & bán TP") -> Giá vốn trong thành phẩm & bán TP | G22: =IF(J2="USD",SUMIFS(Data!Q:Q,Data!B:B,Performance!$E$2,Data!D:D,Performance!E22)*10^6,SUMIFS(Data!Q:Q,Data!B:B,Performance!$E$2,Data!D:D,Performance!E22)) -> -4.0016867e+10 | H22: =IF(K2="USD",SUMIFS(Data!AD:AD,Data!B:B,Performance!$E$2,Data!D:D,Performance!E22)*10^6,SUMIFS(Data!AD:AD,Data!B:B,Performance!$E$2,Data!D:D,Performance!E22)) -> 1.0322101e+10 | I22: =IF(K2="USD",SUMIFS(Data!AR:AR,Data!B:B,Performance!$E$2,Data!D:D,Performance!E22)*10^6,SUMIFS(Data!AR:AR,Data!B:B,Performance!$E$2,Data!D:D,Performance!E22)) -> 3.9219008e+10 | J22: =I22-H22 -> 2.8896907e+10 | K22: =IFERROR(J22/H22,"") -> 2.799518 | M22: =IF($K$1="EN","Man-day (8 hrs)","Giờ công (8 giờ)") -> Giờ công (8 giờ) | N22: Man-day (8 hrs) | O22: =SUMIFS(Data!Q:Q,Data!B:B,Performance!$E$2,Data!D:D,Performance!N22) -> 41220.643 | P22: =SUMIFS(Data!AD:AD,Data!B:B,Performance!$E$2,Data!D:D,Performance!N22) -> 44236.176 | Q22: =SUMIFS(Data!AR:AR,Data!B:B,Performance!$E$2,Data!D:D,Performance!N22) -> 40735.577 | R22: =Q22-P22 -> -3500.5988 | S22: =IFERROR(R22/P22,"") -> -0.079134298 | V22: Chi phí nhân sự / Doanh thu (%) | W22: =IFERROR((G13+G14+G15+G16+G25+G26)/G6,0) -> 0.10752671 | X22: =IFERROR((H13+H14+H15+H16+H25+H26)/H6,0) -> 0.089225434 | Y22: =IFERROR((I13+I14+I15+I16+I25+I26)/I6,0) -> 0.10001718 | Z22: =Y22-X22 -> 0.010791742
E23: Gross Profit | F23: =IF($K$1="EN",E23,"Lợi nhuận gộp") -> Lợi nhuận gộp | G23: =G6-G10 -> 30766675506 | H23: =H6-H10 -> 110284815325 | I23: =I6-I10 -> 64791470204 | J23: =I23-H23 -> -45493345121 | K23: =IFERROR(J23/H23,0) -> -0.41250779 | M23: =IF($K$1="EN",N23,"Số lượng nhân sự sản xuất") -> Số lượng nhân sự sản xuất | N23: Production headcount (avg) | O23: =IFERROR(SUMIFS(Data!Q:Q,Data!B:B,Performance!$E$2,Data!D:D,Performance!N23),0) -> 259.2379 | P23: =IFERROR(SUMIFS(Data!AD:AD,Data!B:B,Performance!$E$2,Data!D:D,Performance!N23),0) -> 340.0417 | Q23: =IFERROR(SUMIFS(Data!AR:AR,Data!B:B,Performance!$E$2,Data!D:D,Performance!N23),0) -> 341.39146 | R23: =Q23-P23 -> 1.3497628 | S23: =IFERROR(R23/P23,"") -> 0.0039694038
E24: SG&A (MKT&ADM) expenses | F24: =IF($K$1="EN",E24,"Chi phí bán hàng & quản lý") -> Chi phí bán hàng & quản lý | G24: =IF(J2="USD",SUMIFS(Data!Q:Q,Data!B:B,Performance!$E$2,Data!D:D,Performance!E24)*10^6,SUMIFS(Data!Q:Q,Data!B:B,Performance!$E$2,Data!D:D,Performance!E24)) -> 39586252838 | H24: =IF(K2="USD",SUMIFS(Data!AD:AD,Data!B:B,Performance!$E$2,Data!D:D,Performance!E24)*10^6,SUMIFS(Data!AD:AD,Data!B:B,Performance!$E$2,Data!D:D,Performance!E24)) -> 61264901433 | I24: =IF(K2="USD",SUMIFS(Data!AR:AR,Data!B:B,Performance!$E$2,Data!D:D,Performance!E24)*10^6,SUMIFS(Data!AR:AR,Data!B:B,Performance!$E$2,Data!D:D,Performance!E24)) -> 64760343520 | J24: =I24-H24 -> 3495442087 | K24: =J24/H24 -> 0.057054562 | M24: =IF($K$1="EN",N24,"PHÂN TÍCH LỢI NHUẬN") -> PHÂN TÍCH LỢI NHUẬN | N24: PROFIT ANALYSIS | O24: =G3 -> Năm 2024 | P24: =H3 -> LK 2025 | Q24: =I3 -> LK 2026 | R24: =R3 -> So với năm trước
B25: MKT & ADM (SG&A) | D25: FC | E25: Salary | F25: =IF($K$1="EN",E25,"Lương quản lý") -> Lương quản lý | G25: =IF(J2="USD",SUMIFS(Data!Q:Q,Data!B:B,Performance!$E$2,Data!D:D,Performance!E25)*10^6,SUMIFS(Data!Q:Q,Data!B:B,Performance!$E$2,Data!D:D,Performance!E25)) -> 15564591994 | H25: =IF(K2="USD",SUMIFS(Data!AD:AD,Data!B:B,Performance!$E$2,Data!D:D,Performance!E25)*10^6,SUMIFS(Data!AD:AD,Data!B:B,Performance!$E$2,Data!D:D,Performance!E25)) -> 21108428439 | I25: =IF(K2="USD",SUMIFS(Data!AR:AR,Data!B:B,Performance!$E$2,Data!D:D,Performance!E25)*10^6,SUMIFS(Data!AR:AR,Data!B:B,Performance!$E$2,Data!D:D,Performance!E25)) -> 25157743581 | J25: =I25-H25 -> 4049315142 | K25: =IFERROR(J25/H25,"") -> 0.19183404 | M25: =F5 -> Sản lượng bán (Tấn) | N25: Sales volume (Ton) | O25: =G5 -> 15468.961 | P25: =H5 -> 23446.449 | Q25: =I5 -> 25012.587 | R25: =Q25-P25 -> 1566.1384 | S25: =IFERROR(R25/P25,"") -> 0.066796402 | AB25: Volume | AC25: Fixed cost | AD25: =IF(K1="EN","Total cost","Tổng chi phí") -> Tổng chi phí | AE25: =IF(K1="EN","Revenue","Doanh thu") -> Doanh thu
B26: MKT & ADM (SG&A) | D26: FC | E26: Employee welfare | F26: =IF($K$1="EN",E26,"Phúc lợi nhân viên quản lý") -> Phúc lợi nhân viên quản lý | G26: =IF(J2="USD",SUMIFS(Data!Q:Q,Data!B:B,Performance!$E$2,Data!D:D,Performance!E26)*10^6,SUMIFS(Data!Q:Q,Data!B:B,Performance!$E$2,Data!D:D,Performance!E26)) -> 3512492392 | H26: =IF(K2="USD",SUMIFS(Data!AD:AD,Data!B:B,Performance!$E$2,Data!D:D,Performance!E26)*10^6,SUMIFS(Data!AD:AD,Data!B:B,Performance!$E$2,Data!D:D,Performance!E26)) -> 5380356731 | I26: =IF(K2="USD",SUMIFS(Data!AR:AR,Data!B:B,Performance!$E$2,Data!D:D,Performance!E26)*10^6,SUMIFS(Data!AR:AR,Data!B:B,Performance!$E$2,Data!D:D,Performance!E26)) -> 6824724413 | J26: =I26-H26 -> 1444367682 | K26: =IFERROR(J26/H26,"") -> 0.26845203 | M26: =IF($K$1="EN","Variable Cost/" & IF(F2="DTPM","mold(m VND/mold)","Ton(m VND/Ton)"),"Biến phí / " & IF(F2="DTPM","Cái (triệu đồng/cái) ","Tấn (Triệu đồng /tấn)")) -> Biến phí / Tấn (Triệu đồng /tấn) | N26: Variable cost/ton (m VND/ton) | O26: =IFERROR(IF(E2="DTPM",(G11+G12+G13+G21+G27+G28+G29)/G5,(G11+G12+G13+G21)/G4+(G27+G28+G29)/G5),0) -> 15731707 | P26: =IFERROR(IF(F2="DTPM",(H11+H12+H13+H21+H27+H28+H29)/H5,(H11+H12+H13+H21)/H4+(H27+H28+H29)/H5),0) -> 27096015 | Q26: =IFERROR(IF(F2="DTPM",(I11+I12+I13+I21+I27+I28+I29)/I4,(I11+I12+I13+I21+I27+I28+I29)/I5),0) -> 20349850 | R26: =Q26-P26 -> -6746164.8 | S26: =IFERROR(R26/P26,"") -> -0.24897258 | AB26: 0 | AC26: =$Q$33/$I$2 -> 3.293197e+10 | AD26: =AC26+AB26*($Q$26+$I$22/$I$5) -> 3.293197e+10 | AE26: =AB26*($I$6/$I$5) -> 0
B27: Direct Selling | D27: VC | E27: Commission expenses | F27: =IF($K$1="EN",E27,"Hoa hồng bán hàng") -> Hoa hồng bán hàng | G27: =IF(J2="USD",SUMIFS(Data!Q:Q,Data!B:B,Performance!$E$2,Data!D:D,Performance!E27)*10^6,SUMIFS(Data!Q:Q,Data!B:B,Performance!$E$2,Data!D:D,Performance!E27)) -> 2775360992 | H27: =IF(K2="USD",SUMIFS(Data!AD:AD,Data!B:B,Performance!$E$2,Data!D:D,Performance!E27)*10^6,SUMIFS(Data!AD:AD,Data!B:B,Performance!$E$2,Data!D:D,Performance!E27)) -> 4947114404 | I27: =IF(K2="USD",SUMIFS(Data!AR:AR,Data!B:B,Performance!$E$2,Data!D:D,Performance!E27)*10^6,SUMIFS(Data!AR:AR,Data!B:B,Performance!$E$2,Data!D:D,Performance!E27)) -> 8553891209 | J27: =I27-H27 -> 3606776805 | K27: =IFERROR(J27/H27,"") -> 0.72906679 | M27: =IF($K$1="EN","Material cost /" & IF(F2="DTPM"," mold"," Ton"),"Chi phí nguyên vật liệu / " & IF(F2="DTPM","Cái","Tấn")) -> Chi phí nguyên vật liệu / Tấn | N27: Material cost per Ton | O27: =IFERROR(IF(E2="DTPM",G11/G4,G11/G4),0) -> 13316268 | P27: =IFERROR(IF(F2="DTPM",H11/H5,H11/H4),0) -> 24565100 | Q27: =IFERROR(I11/I5,0) -> 18599210 | R27: =Q27-P27 -> -5965890.5 | S27: =IFERROR(R27/P27,"") -> -0.24286042 | AB27: =I5/I2 -> 5002.5174 | AC27: =$Q$33/$I$2 -> 3.293197e+10 | AD27: =AC27+AB27*($Q$26+$I$22/$I$5) -> 1.4257625e+11 | AE27: =AB27*($I$6/$I$5) -> 1.4295877e+11
B28: Direct Selling | D28: VC | E28: Domestic Freight | F28: =IF($K$1="EN",E28,"Chi phí vận chuyển trong nước") -> Chi phí vận chuyển trong nước | G28: =IF(J2="USD",SUMIFS(Data!Q:Q,Data!B:B,Performance!$E$2,Data!D:D,Performance!E28)*10^6,SUMIFS(Data!Q:Q,Data!B:B,Performance!$E$2,Data!D:D,Performance!E28)) -> 558268174 | H28: =IF(K2="USD",SUMIFS(Data!AD:AD,Data!B:B,Performance!$E$2,Data!D:D,Performance!E28)*10^6,SUMIFS(Data!AD:AD,Data!B:B,Performance!$E$2,Data!D:D,Performance!E28)) -> 1630704741 | I28: =IF(K2="USD",SUMIFS(Data!AR:AR,Data!B:B,Performance!$E$2,Data!D:D,Performance!E28)*10^6,SUMIFS(Data!AR:AR,Data!B:B,Performance!$E$2,Data!D:D,Performance!E28)) -> 2535633671 | J28: =I28-H28 -> 904928930 | K28: =IFERROR(J28/H28,"") -> 0.55493119 | M28: =IF($K$1="EN","Electricity cost / " & IF(F2="DTPM","mold","Ton"),"Chi phí điện / " & IF(F2="DTPM","Cái","Tấn")) -> Chi phí điện / Tấn | N28: Electricity cost per Ton | O28: =IFERROR(IF(E2="DTPM",G12/G4,G12/G4),0) -> 1210943.6 | P28: =IFERROR(IF(F2="DTPM",H12/H4,H12/H4),0) -> 1422030.7 | Q28: =IFERROR(I12/I4,0) -> 1420940 | R28: =Q28-P28 -> -1090.6959 | S28: =IFERROR(R28/P28,"") -> -0.00076699882 | AB28: =AB27*(1+12%) -> 5602.8195 | AC28: =$Q$33/$I$2 -> 3.293197e+10 | AD28: =AC28+AB28*($Q$26+$I$22/$I$5) -> 1.5573357e+11 | AE28: =AB28*($I$6/$I$5) -> 1.6011382e+11
B29: Direct Selling | D29: VC | E29: Export Freight | F29: =IF($K$1="EN",E29,"Cước xuất khẩu") -> Cước xuất khẩu | G29: =IF(J2="USD",SUMIFS(Data!Q:Q,Data!B:B,Performance!$E$2,Data!D:D,Performance!E29)*10^6,SUMIFS(Data!Q:Q,Data!B:B,Performance!$E$2,Data!D:D,Performance!E29)) -> 8281672437 | H29: =IF(K2="USD",SUMIFS(Data!AD:AD,Data!B:B,Performance!$E$2,Data!D:D,Performance!E29)*10^6,SUMIFS(Data!AD:AD,Data!B:B,Performance!$E$2,Data!D:D,Performance!E29)) -> 10954088709 | I29: =IF(K2="USD",SUMIFS(Data!AR:AR,Data!B:B,Performance!$E$2,Data!D:D,Performance!E29)*10^6,SUMIFS(Data!AR:AR,Data!B:B,Performance!$E$2,Data!D:D,Performance!E29)) -> 6976623658 | J29: =I29-H29 -> -3977465051 | K29: =IFERROR(J29/H29,"") -> -0.36310324 | M29: =IF($K$1="EN","Overtime cost / " & IF(F2="DTPM","mold","Ton"),"Lương ngoài giờ / " & IF(F2="DTPM","Cái","Tấn")) -> Lương ngoài giờ / Tấn | N29: Overtime per Ton | O29: =IFERROR(IF(E2="DTPM",G13/G4,G13/G4),0) -> 199762.64 | P29: =IFERROR(IF(F2="DTPM",H13/H4,H13/H4),0) -> 104236.83 | Q29: =IFERROR(I13/I4,0) -> 109297.04 | R29: =Q29-P29 -> 5060.2083 | S29: =IFERROR(R29/P29,"") -> 0.048545299 | AB29: =AB28*(1+12%) -> 6275.1578 | AC29: =$Q$33/$I$2 -> 3.293197e+10 | AD29: =AC29+AB29*($Q$26+$I$22/$I$5) -> 1.7046976e+11 | AE29: =AB29*($I$6/$I$5) -> 1.7932748e+11
B30: MKT & ADM (SG&A) | D30: FC | E30: Depreciation | F30: =IF($K$1="EN",E30,"Khấu hao (quản lý)") -> Khấu hao (quản lý) | G30: =IF(J2="USD",SUMIFS(Data!Q:Q,Data!B:B,Performance!$E$2,Data!D:D,Performance!E30)*10^6,SUMIFS(Data!Q:Q,Data!B:B,Performance!$E$2,Data!D:D,Performance!E30)) -> 930972362 | H30: =IF(K2="USD",SUMIFS(Data!AD:AD,Data!B:B,Performance!$E$2,Data!D:D,Performance!E30)*10^6,SUMIFS(Data!AD:AD,Data!B:B,Performance!$E$2,Data!D:D,Performance!E30)) -> 2274537180 | I30: =IF(K2="USD",SUMIFS(Data!AR:AR,Data!B:B,Performance!$E$2,Data!D:D,Performance!E30)*10^6,SUMIFS(Data!AR:AR,Data!B:B,Performance!$E$2,Data!D:D,Performance!E30)) -> 424659097 | J30: =I30-H30 -> -1849878083 | K30: =IFERROR(J30/H30,"") -> -0.81329868 | M30: =IF(K1="EN","Processing cost / " & IF(F2="DTPM","mold","Ton"),"Phí gia công /" & IF(F2="DTPM"," Cái"," Tấn")) -> Phí gia công / Tấn | N30: Processing cost per Ton | O30: =IFERROR(IF(E2="DTPM",G21/G4,G21/G4),0) -> 253855.31 | P30: =IFERROR(IF(F2="DTPM",H21/H4,H21/H4),0) -> 256904.92 | Q30: =IFERROR(I21/I4,0) -> 23427.299 | R30: =Q30-P30 -> -233477.62 | S30: =IFERROR(R30/P30,"") -> -0.90880946 | AB30: =AB29*(1+12%) -> 7028.1768 | AC30: =$Q$33/$I$2 -> 3.293197e+10 | AD30: =AC30+AB30*($Q$26+$I$22/$I$5) -> 1.8697429e+11 | AE30: =AB30*($I$6/$I$5) -> 2.0084677e+11
B31: MKT & ADM (SG&A) | D31: FC | E31: Controllable expenses | F31: =IF($K$1="EN",E31,"Chi phí còn lại khác") -> Chi phí còn lại khác | G31: =IF(J2="USD",SUMIFS(Data!Q:Q,Data!B:B,Performance!$E$2,Data!D:D,Performance!E31)*10^6,SUMIFS(Data!Q:Q,Data!B:B,Performance!$E$2,Data!D:D,Performance!E31)) -> 7962894487 | H31: =IF(K2="USD",SUMIFS(Data!AD:AD,Data!B:B,Performance!$E$2,Data!D:D,Performance!E31)*10^6,SUMIFS(Data!AD:AD,Data!B:B,Performance!$E$2,Data!D:D,Performance!E31)) -> 14969671229 | I31: =IF(K2="USD",SUMIFS(Data!AR:AR,Data!B:B,Performance!$E$2,Data!D:D,Performance!E31)*10^6,SUMIFS(Data!AR:AR,Data!B:B,Performance!$E$2,Data!D:D,Performance!E31)) -> 14287067891 | J31: =I31-H31 -> -682603338 | K31: =IFERROR(J31/H31,"") -> -0.045599087 | M31: =IF(K1="EN","Direct selling / " & IF(F2="DTPM","mold","Ton"),"CP bán hàng trực tiếp /" & IF(F2="DTPM"," Cái"," Tấn")) -> CP bán hàng trực tiếp / Tấn | N31: Direct selling | O31: =IFERROR(SUM(G27:G29)/G5/10^6,0) -> 0.75087794 | P31: =IFERROR(SUM(H27:H29)/H5/10^6,0) -> 0.74774258 | Q31: =IFERROR(SUM(I27:I29)/I5/10^6,0) -> 0.72228229 | R31: =Q31-P31 -> -0.025460288 | S31: =IFERROR(R31/P31,"") -> -0.034049537 | AB31: =AB30*(1+12%) -> 7871.558 | AC31: =$Q$33/$I$2 -> 3.293197e+10 | AD31: =AC31+AB31*($Q$26+$I$22/$I$5) -> 2.0545937e+11 | AE31: =AB31*($I$6/$I$5) -> 2.2494839e+11
D32: FC | E32: Financial Expense | F32: =IF($K$1="EN",E32,"Chi phí tài chính") -> Chi phí tài chính | G32: =IF(J2="USD",SUMIFS(Data!Q:Q,Data!B:B,Performance!$E$2,Data!D:D,Performance!E32)*10^6,SUMIFS(Data!Q:Q,Data!B:B,Performance!$E$2,Data!D:D,Performance!E32)) -> 4652566598 | H32: =IF(K2="USD",SUMIFS(Data!AD:AD,Data!B:B,Performance!$E$2,Data!D:D,Performance!E32)*10^6,SUMIFS(Data!AD:AD,Data!B:B,Performance!$E$2,Data!D:D,Performance!E32)) -> 6090227204 | I32: =IF(K2="USD",SUMIFS(Data!AR:AR,Data!B:B,Performance!$E$2,Data!D:D,Performance!E32)*10^6,SUMIFS(Data!AR:AR,Data!B:B,Performance!$E$2,Data!D:D,Performance!E32)) -> 7820326383 | J32: =I32-H32 -> 1730099179 | K32: =IFERROR(J32/H32,0) -> 0.28407794 | M32: =IF(K1="EN","Others / " & IF(F2="DTPM","mold","Ton"),"CP khác /" & IF(F2="DTPM"," Cái"," Tấn")) -> CP khác / Tấn | O32: =IFERROR(G20/G5,0) -> 3890929.5 | P32: =IFERROR(H20/H5,0) -> 521666.62 | Q32: =IFERROR(I20/I5,0) -> 387875.54 | R32: =Q32-P32 -> -133791.08 | S32: =IFERROR(R32/P32,"") -> -0.25646855 | AB32: =AB31*(1+12%) -> 8816.1449 | AC32: =$Q$33/$I$2 -> 3.293197e+10 | AD32: =AC32+AB32*($Q$26+$I$22/$I$5) -> 2.2616266e+11 | AE32: =AB32*($I$6/$I$5) -> 2.5194219e+11
E33: Interest expense | F33: =IF($K$1="EN",E33,"Chi phí lãi vay") -> Chi phí lãi vay | G33: =IF(J2="USD",SUMIFS(Data!Q:Q,Data!B:B,Performance!$E$2,Data!D:D,Performance!E33)*10^6,SUMIFS(Data!Q:Q,Data!B:B,Performance!$E$2,Data!D:D,Performance!E33)) -> 3491705382 | H33: =IF(K2="USD",SUMIFS(Data!AD:AD,Data!B:B,Performance!$E$2,Data!D:D,Performance!E33)*10^6,SUMIFS(Data!AD:AD,Data!B:B,Performance!$E$2,Data!D:D,Performance!E33)) -> 4792152527 | I33: =IF(K2="USD",SUMIFS(Data!AR:AR,Data!B:B,Performance!$E$2,Data!D:D,Performance!E33)*10^6,SUMIFS(Data!AR:AR,Data!B:B,Performance!$E$2,Data!D:D,Performance!E33)) -> 5257034313 | J33: =I33-H33 -> 464881786 | K33: =IFERROR(J33/H33,"") -> 0.097008971 | M33: =IF($K$1="EN",N33,"Định phí") -> Định phí | N33: Fixed cost | O33: =SUM(G14:G18)+G26+G25+G31+G32+G30+G19 -> 116230047293 | P33: =SUM(H14:H18)+H26+H25+H31+H32+H30+H19 -> 158801981278 | Q33: =SUM(I14:I18)+I26+I25+I31+I32+I30+I19 -> 164659847768 | R33: =Q33-P33 -> 5857866490 | S33: =IFERROR(R33/P33,0) -> 0.036887868 | V33: =IF(K1="EN","Break even","SL hòa vốn") -> SL hòa vốn | X33: =I6/I2 -> 1.4295877e+11 | AB33: =AB32*(1+12%) -> 9874.0823 | AC33: =$Q$33/$I$2 -> 3.293197e+10 | AD33: =AC33+AB33*($Q$26+$I$22/$I$5) -> 2.4935034e+11 | AE33: =AB33*($I$6/$I$5) -> 2.8217525e+11
E34: Other Income | F34: =IF($K$1="EN",E34,"Thu nhập khác") -> Thu nhập khác | G34: =IF(J2="USD",SUMIFS(Data!Q:Q,Data!B:B,Performance!$E$2,Data!D:D,Performance!E34)*10^6,SUMIFS(Data!Q:Q,Data!B:B,Performance!$E$2,Data!D:D,Performance!E34)) -> 5489769545 | H34: =IF(K2="USD",SUMIFS(Data!AD:AD,Data!B:B,Performance!$E$2,Data!D:D,Performance!E34)*10^6,SUMIFS(Data!AD:AD,Data!B:B,Performance!$E$2,Data!D:D,Performance!E34)) -> 7236244341 | I34: =IF(K2="USD",SUMIFS(Data!AR:AR,Data!B:B,Performance!$E$2,Data!D:D,Performance!E34)*10^6,SUMIFS(Data!AR:AR,Data!B:B,Performance!$E$2,Data!D:D,Performance!E34)) -> 4743395864 | J34: =I34-H34 -> -2492848477 | K34: =IFERROR(J34/H34,"") -> -0.34449479 | M34: =IF(K1="EN","Operating Expense (OpEx)","Chi phí hoạt động") -> Chi phí hoạt động | O34: =O33-O36-O37 -> 90593948439 | P34: =P33-P36-P37 -> 118475622192 | Q34: =Q33-Q36-Q37 -> 128292160029 | R34: =Q34-P34 -> 9816537837 | S34: =IFERROR(R34/P34,0) -> 0.082857027 | V34: =H38 -> 42677314129 | AB34: =AB33*(1+12%) -> 11058.972 | AC34: =$Q$33/$I$2 -> 3.293197e+10 | AD34: =AC34+AB34*($Q$26+$I$22/$I$5) -> 2.7532055e+11 | AE34: =AB34*($I$6/$I$5) -> 3.1603629e+11
E35: EBITDA | F35: =IF($K$1="EN",E35,"EBITDA") -> EBITDA | G35: =IF(J2="USD",SUMIFS(Data!Q:Q,Data!B:B,Performance!$E$2,Data!D:D,Performance!E35)*10^6,SUMIFS(Data!Q:Q,Data!B:B,Performance!$E$2,Data!D:D,Performance!E35)) -> 10929896878 | H35: =IF(K2="USD",SUMIFS(Data!AD:AD,Data!B:B,Performance!$E$2,Data!D:D,Performance!E35)*10^6,SUMIFS(Data!AD:AD,Data!B:B,Performance!$E$2,Data!D:D,Performance!E35)) -> 74565621227 | I35: =IF(K2="USD",SUMIFS(Data!AR:AR,Data!B:B,Performance!$E$2,Data!D:D,Performance!E35)*10^6,SUMIFS(Data!AR:AR,Data!B:B,Performance!$E$2,Data!D:D,Performance!E35)) -> 13175258499 | J35: =I35-H35 -> -61390362728 | K35: =IFERROR(J35/H35,"") -> -0.82330653 | M35: Trong đó: chi phí nhân sự | O35: =G14+G15+G16+G25+G26 -> 44827194564 | P35: =H14+H15+H16+H25+H26 -> 63221343069 | Q35: =I14+I15+I16+I25+I26 -> 69682177790 | R35: =Q35-P35 -> 6460834721 | S35: =R35/P35 -> 0.10219389 | AB35: =AB34*(1+12%) -> 12386.049 | AC35: =$Q$33/$I$2 -> 3.293197e+10 | AD35: =AC35+AB35*($Q$26+$I$22/$I$5) -> 3.0440717e+11 | AE35: =AB35*($I$6/$I$5) -> 3.5396064e+11
E36: Profit before tax | F36: =IF($K$1="EN",E36,"Lợi nhuận trước thuế") -> Lợi nhuận trước thuế | G36: =IF(J2="USD",SUMIFS(Data!Q:Q,Data!B:B,Performance!$E$2,Data!D:D,Performance!E36)*10^6,SUMIFS(Data!Q:Q,Data!B:B,Performance!$E$2,Data!D:D,Performance!E36)) -> -7982374385 | H36: =IF(K2="USD",SUMIFS(Data!AD:AD,Data!B:B,Performance!$E$2,Data!D:D,Performance!E36)*10^6,SUMIFS(Data!AD:AD,Data!B:B,Performance!$E$2,Data!D:D,Performance!E36)) -> 50165931029 | I36: =IF(K2="USD",SUMIFS(Data!AR:AR,Data!B:B,Performance!$E$2,Data!D:D,Performance!E36)*10^6,SUMIFS(Data!AR:AR,Data!B:B,Performance!$E$2,Data!D:D,Performance!E36)) -> -3045803835 | J36: =I36-H36 -> -53211734864 | K36: =IFERROR(J36/H36,"") -> -1.0607146 | M36: =IF(K1="EN","Depreciation","Khấu hao") -> Khấu hao | O36: =G19+G30 -> 20983532256 | P36: =H19+H30 -> 34236131882 | Q36: =I19+I30 -> 28547361356 | R36: =Q36-P36 -> -5688770526 | S36: =IFERROR(R36/P36,0) -> -0.16616277 | AB36: =IF(K1="EN","Actual volume","SL thực tế") -> SL thực tế | AC36: =I5/I2 -> 5002.5174
E37: CIT | F37: =IF($K$1="EN",E37,"Thuế TNDN") -> Thuế TNDN | G37: =IF(J2="USD",SUMIFS(Data!Q:Q,Data!B:B,Performance!$E$2,Data!D:D,Performance!E37)*10^6,SUMIFS(Data!Q:Q,Data!B:B,Performance!$E$2,Data!D:D,Performance!E37)) -> 0 | H37: =IF(K2="USD",SUMIFS(Data!AD:AD,Data!B:B,Performance!$E$2,Data!D:D,Performance!E37)*10^6,SUMIFS(Data!AD:AD,Data!B:B,Performance!$E$2,Data!D:D,Performance!E37)) -> 7488616900 | I37: =IF(K2="USD",SUMIFS(Data!AR:AR,Data!B:B,Performance!$E$2,Data!D:D,Performance!E37)*10^6,SUMIFS(Data!AR:AR,Data!B:B,Performance!$E$2,Data!D:D,Performance!E37)) -> -198902366 | J37: =I37-H37 -> -7687519266 | K37: =IFERROR(J37/H37,"") -> -1.0265606 | M37: =IF(K1="EN","Financial expense","Chi phí tài chính") -> Chi phí tài chính | O37: =G32 -> 4652566598 | P37: =H32 -> 6090227204 | Q37: =I32 -> 7820326383 | R37: =Q37-P37 -> 1730099179 | S37: =IFERROR(R37/P37,0) -> 0.28407794
E38: NET PROFIT | F38: =IF($K$1="EN",E38,"Lợi nhuận sau thuế") -> Lợi nhuận sau thuế | G38: =IF(J2="USD",SUMIFS(Data!Q:Q,Data!B:B,Performance!$E$2,Data!D:D,Performance!E38)*10^6,SUMIFS(Data!Q:Q,Data!B:B,Performance!$E$2,Data!D:D,Performance!E38)) -> -7982374385 | H38: =IF(K2="USD",SUMIFS(Data!AD:AD,Data!B:B,Performance!$E$2,Data!D:D,Performance!E38)*10^6,SUMIFS(Data!AD:AD,Data!B:B,Performance!$E$2,Data!D:D,Performance!E38)) -> 42677314129 | I38: =IF(K2="USD",SUMIFS(Data!AR:AR,Data!B:B,Performance!$E$2,Data!D:D,Performance!E38)*10^6,SUMIFS(Data!AR:AR,Data!B:B,Performance!$E$2,Data!D:D,Performance!E38)) -> -2846901469 | J38: =I38-H38 -> -45524215598 | K38: =J38/H38 -> -1.0667076 | L38: =M40 -> Phân tích lợi nhuận sau thuế | M38: =IF(K1="EN","Breakeven Volume/month","Sản lượng hòa vốn/tháng ") -> Sản lượng hòa vốn/tháng | P38: =IFERROR(P33/X8/(H6/H5)/H2,0) -> 3480.3627 | Q38: =IFERROR((Q33)/Y8/(I6/I5)/I2,0) -> 4945.0789 | R38: =Q38-P38 -> 1464.7162 | S38: =IFERROR(R38/P38,"") -> 0.42085158
L39: =IF(K1="EN","Volume","Sản lượng") -> Sản lượng | M39: =IF(K1="EN","Breakeven Sales (m VND)/month","Doanh thu hòa vốn (Triệu)/tháng ") -> Doanh thu hòa vốn (Triệu)/tháng | P39: =IFERROR(P38*(H6/H5),0) -> 1.0839181e+11 | Q39: =IFERROR(Q38*(I6/I5),0) -> 1.4131732e+11 | R39: =Q39-P39 -> 3.2925516e+10 | S39: =IFERROR(R39/P39,"") -> 0.30376387 | U39: =SUM(U40:U49) -> -1.0667076
L40: =IF(K1="EN","Selling price","Giá bán") -> Giá bán | M40: =IF(K1="EN","Net profit analysis by Factors","Phân tích lợi nhuận sau thuế") -> Phân tích lợi nhuận sau thuế | O40: =O24 -> Năm 2024 | P40: =P24 -> LK 2025 | Q40: =Q24 -> LK 2026 | R40: =IF(K1="EN","Change","Thay đổi") -> Thay đổi | S40: =IF(K1="EN","Impact","Ảnh hưởng") -> Ảnh hưởng | U40: =S41*10^6/$H$38 -> 0.31574034 | AB40: =IF(K1="EN","Net profit 2025","LNST 2025") -> LNST 2025 | AD40: =H38/10^6 -> 42677.314 | AE40: 1
L41: =IF(K1="EN","Direct selling","CP bán hàng") -> CP bán hàng | M41: =IF(K1="EN","1. Sales volume "& IF(F2="DTPM"," (molds)"," (Ton)"),"1.Sản lượng bán "&IF(F2="DTPM","(Khuôn)","(Tấn)")) -> 1.Sản lượng bán (Tấn) | N41: Sales volume | O41: =O25 -> 15468.961 | P41: =P25 -> 23446.449 | Q41: =Q25 -> 25012.587 | R41: =Q41-P41 -> 1566.1384 | S41: =IFERROR(R41*((H6-H11-H12-H13-H29-H20-H22-H21-H27-H28)/H5/10^6),0) -> 13474.95 | U41: =S42*10^6/$H$38 -> -1.504167 | AB41: =IF(K1="EN","Sales volume","Sản lượng bán") -> Sản lượng bán | AD41: =S41 -> 13474.95 | AE41: =U40 -> 0.31574034
L42: =IF(K1="EN","VCOGs","Biến phí hàng bán") -> Biến phí hàng bán | M42: =IF(K1="EN","2. Selling price " & IF(I5=0,"(m VND","(m VND/Ton)"),"2.Đơn giá bán " & IF(I5=0,"(Triệu)","(Triệu/Tấn)")) -> 2.Đơn giá bán (Triệu/Tấn) | N42: Selling price | O42: =IFERROR(G6/G5/10^6,G6/10^6) -> 29.534302 | P42: =IFERROR(H6/H5/10^6,H6/10^6) -> 31.143825 | Q42: =IFERROR(I6/I5/10^6,I6/10^6) -> 28.577365 | R42: =Q42-P42 -> -2.5664602 | S42: =IF(R42*Q41=0,R42,R42*Q41) -> -64193.809 | U42: =S43*10^6/$H$38 -> 0.014921925 | AB42: =IF(K1="EN","Selling price","Giá bán") -> Giá bán | AD42: =S42 -> -64193.809 | AE42: =U41 -> -1.504167
L43: =IF(K1="EN","FOH","CP Sản xuất") -> CP Sản xuất | M43: =IF(K1="EN","3. Direct selling " & IF(F2="DTPM","(m VND/mold)","(m VND/Ton)"),"3.CP bán hàng trực tiếp " & IF(F2="DTPM","(Triệu/Cái)","(Triệu/Tấn)")) -> 3.CP bán hàng trực tiếp (Triệu/Tấn) | N43: Direct selling | O43: =IFERROR(SUM(G27:G29)/G5/10^6,SUM(G27:G29)/10^6) -> 0.75087794 | P43: =IFERROR(SUM(H27:H29)/H5/10^6,SUM(H27:H29)/10^6) -> 0.74774258 | Q43: =IFERROR(SUM(I27:I29)/I5/10^6,SUM(I27:I29)/10^6) -> 0.72228229 | R43: =Q43-P43 -> -0.025460288 | S43: =IF(-R43*Q41=0,-R43,-R43*Q41) -> 636.82768 | U43: =S44*10^6/$H$38 -> 0.12233693 | AB43: =IF(K1="EN","Direct selling","Vận chuyển") -> Vận chuyển | AD43: =S43 -> 636.82768 | AE43: =U42 -> 0.014921925
L44: =IF(K1="EN","MKT & ADM","CP bán hàng&quản lý") -> CP bán hàng&quản lý | M44: =IF(K1="EN","4. VCOGS "&IF(F2="DTPM","(m VND/mold)","(m VND/Ton)"),"4.Biến phí hàng bán "&IF(F2="DTPM","(Triệu/Cái)","(Triệu/Tấn)")) -> 4.Biến phí hàng bán (Triệu/Tấn) | N44: VCOGS | O44: =IF(O25=0,(SUM(G11:G13)+SUM(G20:G22))/10^6,(SUM(G11:G13)+SUM(G20:G22))/O25/10^6) -> 22.140579 | P44: =IF(P25=0,(SUM(H11:H13)+SUM(H20:H22))/10^6,(SUM(H11:H13)+SUM(H20:H22))/P25/10^6) -> 21.79215 | Q44: =IF(Q25=0,(SUM(I11:I13)+SUM(I20:I22))/10^6,(SUM(I11:I13)+SUM(I20:I22))/Q25/10^6) -> 21.583414 | R44: =Q44-P44 -> -0.20873537 | S44: =IF(-R44*Q41=0,-R44,-R44*Q41) -> 5221.0116 | U44: =S45*10^6/$H$38 -> -0.11728616 | AB44: =IF(K1="EN","VCOGS","Giá vốn") -> Giá vốn | AD44: =S44 -> 5221.0116 | AE44: =U43 -> 0.12233693
L45: =IF(K1="EN","Depreciation","Khấu hao") -> Khấu hao | M45: =IF(K1="EN","5. FOH (m VND)","5.Chi phí sản xuất ((Triệu)") -> 5.Chi phí sản xuất ((Triệu) | N45: FOH | O45: =SUM(G14:G18) -> 63553969566 | P45: =SUM(H14:H18) -> 77017165793 | Q45: =SUM(I14:I18) -> 82022624144 | R45: =Q45-P45 -> 5005458351 | S45: =-R45/10^6 -> -5005.4584 | U45: =S46*10^6/$H$38 -> -0.11273154 | AB45: =IF(K1="EN","FOH","CP Sản xuất") -> CP Sản xuất | AD45: =S45 -> -5005.4584 | AE45: =U44 -> -0.11728616
L46: =IF(K1="EN","Interest","Lãi vay") -> Lãi vay | M46: =IF(K1="EN","6. MKT & ADM (m VND)","6.CP bán hàng & quản lý (Triệu)") -> 6.CP bán hàng & quản lý (Triệu) | N46: MKT & ADM | O46: =G25+G26+G31 -> 27039978873 | P46: =H25+H26+H31 -> 41458456399 | Q46: =I25+I26+I31 -> 46269535885 | R46: =Q46-P46 -> 4811079486 | S46: =-R46/10^6 -> -4811.0795 | U46: =S47*10^6/$H$38 -> 0.13329729 | AB46: =IF(K1="EN","MKT & ADM","CP BH & Quản lý") -> CP BH & Quản lý | AD46: =S46 -> -4811.0795 | AE46: =U45 -> -0.11273154
L47: =IF(K1="EN","CIT","Thuế TNDN") -> Thuế TNDN | M47: =IF(K1="EN","7. Depreciation (m VND)","7.Khấu hao (Triệu)") -> 7.Khấu hao (Triệu) | N47: Depreciation | O47: =G19+G30 -> 20983532256 | P47: =H19+H30 -> 34236131882 | Q47: =I19+I30 -> 28547361356 | R47: =Q47-P47 -> -5688770526 | S47: =-R47/10^6 -> 5688.7705 | U47: =S48*10^6/$H$38 -> -0.010892949 | AB47: =IF(K1="EN","Depreciation","Khấu hao") -> Khấu hao | AD47: =S47 -> 5688.7705 | AE47: =U46 -> 0.13329729
L48: =IF(K1="EN","Others","Thu nhập khác") -> Thu nhập khác | M48: =IF(K1="EN","8. Interest (m VND)","8.Lãi vay (Triệu)") -> 8.Lãi vay (Triệu) | N48: Interest | O48: =G33 -> 3491705382 | P48: =H33 -> 4792152527 | Q48: =I33 -> 5257034313 | R48: =Q48-P48 -> 464881786 | S48: =-R48/10^6 -> -464.88179 | U48: =S49*10^6/$H$38 -> 0.18013128 | AB48: =IF(K1="EN","Interest","Lãi vay") -> Lãi vay | AD48: =S48 -> -464.88179 | AE48: =U47 -> -0.010892949
M49: =IF(K1="EN","9. CIT (m VND)","9.Thuế TNDN (Triệu)") -> 9.Thuế TNDN (Triệu) | N49: CIT | O49: =G37 -> 0 | P49: =H37 -> 7488616900 | Q49: =I37 -> -198902366 | R49: =Q49-P49 -> -7687519266 | S49: =-R49/10^6 -> 7687.5193 | U49: =S50*10^6/$H$38 -> -0.088057694 | AB49: =IF(K1="EN","CIT","Thuế") -> Thuế | AD49: =S49 -> 7687.5193 | AE49: =U48 -> 0.18013128
L50: =M51 -> Lợi nhuận sau thuế(2026) | M50: =IF(K1="EN","10. Others (m VND)","10.Khác (Triệu)") -> 10.Khác (Triệu) | N50: Others | O50: =G34-(G32-G33) -> 4328908329 | P50: =H34-(H32-H33) -> 5938169664 | Q50: =I34-(I32-I33) -> 2180103794 | R50: =Q50-P50 -> -3758065870 | S50: =R50/10^6 -> -3758.0659 | U50: =S51*10^6/$H$38 -> 0 | AB50: =IF(K1="EN","Others","Khác") -> Khác | AD50: =S50 -> -3758.0659 | AE50: =U49 -> -0.088057694
M51: =F38&"("&I1&")" -> Lợi nhuận sau thuế(2026) | N51: Total | AB51: =IF(K1="EN","Net profit 2026","LNST 2026") -> LNST 2026 | AD51: =SUM(AD40:AD50) -> -2846.9015 | AE51: =SUM(AE40:AE50) -> -0.066707606

Sheet Data
D1: Check
E2: 1 | F2: 2 | G2: 3 | H2: 4 | I2: 5 | J2: 6 | K2: 7 | L2: 8 | M2: 9 | N2: 10 | O2: 11 | P2: 12 | Q2: 2024 | R2: 1 | S2: 2 | T2: 3 | U2: 4 | V2: 5 | W2: 6 | X2: 7 | Y2: 8 | Z2: 9 | AA2: 10 | AB2: 11 | AC2: 12 | AD2: 2025
A3: =Performance!$K$1 -> VN | B3: =Performance!K2 -> Triệu VND | D3: =IF(B3="USD","nghìn USD","Triệu đồng") -> Triệu đồng
B4: =Performance!F2 -> DTR | D4: Operating Expense | R4: 1 | S4: 2 | T4: 3 | U4: 4 | V4: 5 | W4: 6 | X4: 7 | Y4: 8 | Z4: 9 | AA4: 10 | AB4: 11 | AC4: 12 | AD4: =IF('FS matrix'!A1="EN","YTD","Lũy kế") -> Lũy kế
B5: =Performance!H1 -> 2025 | D5: =IF(A3="EN","Last year","Năm trước") -> Năm trước | R5: =IF($B$3="USD",SUMIFS(E$28:E$359,$B$28:$B$359,$B$4,$D$28:$D$359,$D$4),SUMIFS(E$28:E$359,$B$28:$B$359,$B$4,$D$28:$D$359,$D$4)/10^6) -> 15301.449 | S5: =IF($B$3="USD",SUMIFS(F$28:F$359,$B$28:$B$359,$B$4,$D$28:$D$359,$D$4),SUMIFS(F$28:F$359,$B$28:$B$359,$B$4,$D$28:$D$359,$D$4)/10^6) -> 13873.741 | T5: =IF($B$3="USD",SUMIFS(G$28:G$359,$B$28:$B$359,$B$4,$D$28:$D$359,$D$4),SUMIFS(G$28:G$359,$B$28:$B$359,$B$4,$D$28:$D$359,$D$4)/10^6) -> 20712.853 | U5: =IF($B$3="USD",SUMIFS(H$28:H$359,$B$28:$B$359,$B$4,$D$28:$D$359,$D$4),SUMIFS(H$28:H$359,$B$28:$B$359,$B$4,$D$28:$D$359,$D$4)/10^6) -> 19330.107 | V5: =IF($B$3="USD",SUMIFS(I$28:I$359,$B$28:$B$359,$B$4,$D$28:$D$359,$D$4),SUMIFS(I$28:I$359,$B$28:$B$359,$B$4,$D$28:$D$359,$D$4)/10^6) -> 21375.798 | W5: =IF($B$3="USD",SUMIFS(J$28:J$359,$B$28:$B$359,$B$4,$D$28:$D$359,$D$4),SUMIFS(J$28:J$359,$B$28:$B$359,$B$4,$D$28:$D$359,$D$4)/10^6) -> 20743.137 | X5: =IF($B$3="USD",SUMIFS(K$28:K$359,$B$28:$B$359,$B$4,$D$28:$D$359,$D$4),SUMIFS(K$28:K$359,$B$28:$B$359,$B$4,$D$28:$D$359,$D$4)/10^6) -> 19696.085 | Y5: =IF($B$3="USD",SUMIFS(L$28:L$359,$B$28:$B$359,$B$4,$D$28:$D$359,$D$4),SUMIFS(L$28:L$359,$B$28:$B$359,$B$4,$D$28:$D$359,$D$4)/10^6) -> 21459.303 | ... AC5: =IF($B$3="USD",SUMIFS(P$28:P$359,$B$28:$B$359,$B$4,$D$28:$D$359,$D$4),SUMIFS(P$28:P$359,$B$28:$B$359,$B$4,$D$28:$D$359,$D$4)/10^6) -> 25170.049 | AD5: =SUM(OFFSET(R5:AC5,0,0,1,Performance!H2)) -> 90593.948
B6: =Performance!I1 -> 2026 | D6: =IF(A3="EN","Current year","Năm nay") -> Năm nay | R6: =IF($B$3="USD",SUMIFS(R$28:R$359,$B$28:$B$359,$B$4,$D$28:$D$359,$D$4),SUMIFS(R$28:R$359,$B$28:$B$359,$B$4,$D$28:$D$359,$D$4)/10^6) -> 23429.032 | S6: =IF($B$3="USD",SUMIFS(S$28:S$359,$B$28:$B$359,$B$4,$D$28:$D$359,$D$4),SUMIFS(S$28:S$359,$B$28:$B$359,$B$4,$D$28:$D$359,$D$4)/10^6) -> 22438.833 | T6: =IF($B$3="USD",SUMIFS(T$28:T$359,$B$28:$B$359,$B$4,$D$28:$D$359,$D$4),SUMIFS(T$28:T$359,$B$28:$B$359,$B$4,$D$28:$D$359,$D$4)/10^6) -> 24091.469 | U6: =IF($B$3="USD",SUMIFS(U$28:U$359,$B$28:$B$359,$B$4,$D$28:$D$359,$D$4),SUMIFS(U$28:U$359,$B$28:$B$359,$B$4,$D$28:$D$359,$D$4)/10^6) -> 24143.191 | V6: =IF($B$3="USD",SUMIFS(V$28:V$359,$B$28:$B$359,$B$4,$D$28:$D$359,$D$4),SUMIFS(V$28:V$359,$B$28:$B$359,$B$4,$D$28:$D$359,$D$4)/10^6) -> 24373.097 | W6: =IF($B$3="USD",SUMIFS(W$28:W$359,$B$28:$B$359,$B$4,$D$28:$D$359,$D$4),SUMIFS(W$28:W$359,$B$28:$B$359,$B$4,$D$28:$D$359,$D$4)/10^6) -> 24531.919 | X6: =IF($B$3="USD",SUMIFS(X$28:X$359,$B$28:$B$359,$B$4,$D$28:$D$359,$D$4),SUMIFS(X$28:X$359,$B$28:$B$359,$B$4,$D$28:$D$359,$D$4)/10^6) -> 25277.268 | Y6: =IF($B$3="USD",SUMIFS(Y$28:Y$359,$B$28:$B$359,$B$4,$D$28:$D$359,$D$4),SUMIFS(Y$28:Y$359,$B$28:$B$359,$B$4,$D$28:$D$359,$D$4)/10^6) -> 25871.126 | ... AC6: =IF($B$3="USD",SUMIFS(AC$28:AC$359,$B$28:$B$359,$B$4,$D$28:$D$359,$D$4),SUMIFS(AC$28:AC$359,$B$28:$B$359,$B$4,$D$28:$D$359,$D$4)/10^6) -> 33123.812 | AD6: =SUM(OFFSET(R6:AC6,0,0,1,Performance!I2)) -> 118475.62
D7: Sales volume
B8: 2024 | D8: =D5 -> Năm trước | R8: =SUMIFS(E$28:E$359,$B$28:$B$359,$B$4,$D$28:$D$359,$D$7) -> 3553.2 | S8: =SUMIFS(F$28:F$359,$B$28:$B$359,$B$4,$D$28:$D$359,$D$7) -> 2285.051 | T8: =SUMIFS(G$28:G$359,$B$28:$B$359,$B$4,$D$28:$D$359,$D$7) -> 2972.068 | U8: =SUMIFS(H$28:H$359,$B$28:$B$359,$B$4,$D$28:$D$359,$D$7) -> 3202.752 | V8: =SUMIFS(I$28:I$359,$B$28:$B$359,$B$4,$D$28:$D$359,$D$7) -> 3455.89 | W8: =SUMIFS(J$28:J$359,$B$28:$B$359,$B$4,$D$28:$D$359,$D$7) -> 2432.325 | X8: =SUMIFS(K$28:K$359,$B$28:$B$359,$B$4,$D$28:$D$359,$D$7) -> 1986.853 | Y8: =SUMIFS(L$28:L$359,$B$28:$B$359,$B$4,$D$28:$D$359,$D$7) -> 5184.5942 | ... AC8: =SUMIFS(P$28:P$359,$B$28:$B$359,$B$4,$D$28:$D$359,$D$7) -> 3375.148 | AD8: =SUM(OFFSET(R8:AC8,0,0,1,Performance!H2)) -> 15468.961
B9: 2025 | D9: =D6 -> Năm nay | R9: =SUMIFS(R$28:R$359,$B$28:$B$359,$B$4,$D$28:$D$359,$D$7) -> 3612.7513 | S9: =SUMIFS(S$28:S$359,$B$28:$B$359,$B$4,$D$28:$D$359,$D$7) -> 6002.038 | T9: =SUMIFS(T$28:T$359,$B$28:$B$359,$B$4,$D$28:$D$359,$D$7) -> 4985.538 | U9: =SUMIFS(U$28:U$359,$B$28:$B$359,$B$4,$D$28:$D$359,$D$7) -> 4060.361 | V9: =SUMIFS(V$28:V$359,$B$28:$B$359,$B$4,$D$28:$D$359,$D$7) -> 4785.7603 | W9: =SUMIFS(W$28:W$359,$B$28:$B$359,$B$4,$D$28:$D$359,$D$7) -> 3895.695 | X9: =SUMIFS(X$28:X$359,$B$28:$B$359,$B$4,$D$28:$D$359,$D$7) -> 4652.4191 | Y9: =SUMIFS(Y$28:Y$359,$B$28:$B$359,$B$4,$D$28:$D$359,$D$7) -> 5655.27 | ... AC9: =SUMIFS(AC$28:AC$359,$B$28:$B$359,$B$4,$D$28:$D$359,$D$7) -> 3185.679 | AD9: =SUM(OFFSET(R9:AC9,0,0,1,Performance!H2)) -> 23446.449
B10: =IF(A3="EN","Net sales (B VND)","Doanh thu thuần (Tỷ)") -> Doanh thu thuần (Tỷ) | D10: Net sales
B11: =B5 -> 2025 | D11: =IF(A3="EN","Last year","Năm trước") -> Năm trước | R11: =SUMIFS(E$28:E$359,$B$28:$B$359,$B$4,$D$28:$D$359,$D$10) -> 95961616736 | S11: =SUMIFS(F$28:F$359,$B$28:$B$359,$B$4,$D$28:$D$359,$D$10) -> 68939746996 | T11: =SUMIFS(G$28:G$359,$B$28:$B$359,$B$4,$D$28:$D$359,$D$10) -> 92109508133 | U11: =SUMIFS(H$28:H$359,$B$28:$B$359,$B$4,$D$28:$D$359,$D$10) -> 97489092894 | V11: =SUMIFS(I$28:I$359,$B$28:$B$359,$B$4,$D$28:$D$359,$D$10) -> 102364998344 | W11: =SUMIFS(J$28:J$359,$B$28:$B$359,$B$4,$D$28:$D$359,$D$10) -> 68093170109 | X11: =SUMIFS(K$28:K$359,$B$28:$B$359,$B$4,$D$28:$D$359,$D$10) -> 56451269692 | Y11: =SUMIFS(L$28:L$359,$B$28:$B$359,$B$4,$D$28:$D$359,$D$10) -> 154027868172 | ... AC11: =SUMIFS(P$28:P$359,$B$28:$B$359,$B$4,$D$28:$D$359,$D$10) -> 106210088680 | AD11: =SUM(OFFSET(R11:AC11,0,0,1,Performance!$H$2)) -> 456864963103
B12: =B6 -> 2026 | D12: =IF(A3="EN","Current year","Năm nay") -> Năm nay | R12: =SUMIFS(R$28:R$359,$B$28:$B$359,$B$4,$D$28:$D$359,$D$10) -> 114462510402 | S12: =SUMIFS(S$28:S$359,$B$28:$B$359,$B$4,$D$28:$D$359,$D$10) -> 187999461059 | T12: =SUMIFS(T$28:T$359,$B$28:$B$359,$B$4,$D$28:$D$359,$D$10) -> 150253332680 | U12: =SUMIFS(U$28:U$359,$B$28:$B$359,$B$4,$D$28:$D$359,$D$10) -> 125429649855 | V12: =SUMIFS(V$28:V$359,$B$28:$B$359,$B$4,$D$28:$D$359,$D$10) -> 152067142852 | W12: =SUMIFS(W$28:W$359,$B$28:$B$359,$B$4,$D$28:$D$359,$D$10) -> 119134672797 | X12: =SUMIFS(X$28:X$359,$B$28:$B$359,$B$4,$D$28:$D$359,$D$10) -> 137991406898 | Y12: =SUMIFS(Y$28:Y$359,$B$28:$B$359,$B$4,$D$28:$D$359,$D$10) -> 168442653383 | ... AC12: =SUMIFS(AC$28:AC$359,$B$28:$B$359,$B$4,$D$28:$D$359,$D$10) -> 99758121581 | AD12: =SUM(OFFSET(R12:AC12,0,0,1,Performance!$I$2)) -> 730212096848
D13: EBITDA
B14: =B11 -> 2025 | D14: =D13&"_"&D5 -> EBITDA_Năm trước | R14: =SUMIFS(E$28:E$359,$B$28:$B$359,$B$4,$D$28:$D$359,$D$13) -> 5384680897 | S14: =SUMIFS(F$28:F$359,$B$28:$B$359,$B$4,$D$28:$D$359,$D$13) -> -1703380519 | T14: =SUMIFS(G$28:G$359,$B$28:$B$359,$B$4,$D$28:$D$359,$D$13) -> 626985252 | U14: =SUMIFS(H$28:H$359,$B$28:$B$359,$B$4,$D$28:$D$359,$D$13) -> 6561979281 | V14: =SUMIFS(I$28:I$359,$B$28:$B$359,$B$4,$D$28:$D$359,$D$13) -> 59631967 | W14: =SUMIFS(J$28:J$359,$B$28:$B$359,$B$4,$D$28:$D$359,$D$13) -> -5859951964 | X14: =SUMIFS(K$28:K$359,$B$28:$B$359,$B$4,$D$28:$D$359,$D$13) -> -9089366006 | Y14: =SUMIFS(L$28:L$359,$B$28:$B$359,$B$4,$D$28:$D$359,$D$13) -> -4047933145 | ... AC14: =SUMIFS(P$28:P$359,$B$28:$B$359,$B$4,$D$28:$D$359,$D$13) -> 110198971178 | AD14: =SUM(OFFSET(R14:AC14,0,0,1,Performance!H2)) -> 10929896878
B15: =B12 -> 2026 | D15: =D13&"_"&D6 -> EBITDA_Năm nay | R15: =SUMIFS(R$28:R$359,$B$28:$B$359,$B$4,$D$28:$D$359,$D$13) -> 10679249682 | S15: =SUMIFS(S$28:S$359,$B$28:$B$359,$B$4,$D$28:$D$359,$D$13) -> 25146574404 | T15: =SUMIFS(T$28:T$359,$B$28:$B$359,$B$4,$D$28:$D$359,$D$13) -> 13027482010 | U15: =SUMIFS(U$28:U$359,$B$28:$B$359,$B$4,$D$28:$D$359,$D$13) -> 9221866353 | V15: =SUMIFS(V$28:V$359,$B$28:$B$359,$B$4,$D$28:$D$359,$D$13) -> 16490448778 | W15: =SUMIFS(W$28:W$359,$B$28:$B$359,$B$4,$D$28:$D$359,$D$13) -> 6798133756 | X15: =SUMIFS(X$28:X$359,$B$28:$B$359,$B$4,$D$28:$D$359,$D$13) -> 3536012394 | Y15: =SUMIFS(Y$28:Y$359,$B$28:$B$359,$B$4,$D$28:$D$359,$D$13) -> 5693975403 | ... AC15: =SUMIFS(AC$28:AC$359,$B$28:$B$359,$B$4,$D$28:$D$359,$D$13) -> 11690093189 | AD15: =SUM(OFFSET(R15:AC15,0,0,1,Performance!H2)) -> 74565621227
D17: Net cash flow from operating activities
B18: =B14 -> 2025 | D18: =D11 -> Năm trước | R18: =SUMIFS(R$29:R$359,$B$29:$B$359,$B$4,$D$29:$D$359,$D$17) -> 77939030716 | S18: =SUMIFS(S$29:S$359,$B$29:$B$359,$B$4,$D$29:$D$359,$D$17) -> 52466748566 | T18: =SUMIFS(T$29:T$359,$B$29:$B$359,$B$4,$D$29:$D$359,$D$17) -> -20916557445 | U18: =SUMIFS(U$29:U$359,$B$29:$B$359,$B$4,$D$29:$D$359,$D$17) -> -32579374222 | V18: =SUMIFS(V$29:V$359,$B$29:$B$359,$B$4,$D$29:$D$359,$D$17) -> -21808072831 | W18: =SUMIFS(W$29:W$359,$B$29:$B$359,$B$4,$D$29:$D$359,$D$17) -> -2281933617 | X18: =SUMIFS(X$29:X$359,$B$29:$B$359,$B$4,$D$29:$D$359,$D$17) -> -27735233437 | Y18: =SUMIFS(Y$29:Y$359,$B$29:$B$359,$B$4,$D$29:$D$359,$D$17) -> -40414033126 | ... AC18: =SUMIFS(AC$29:AC$359,$B$29:$B$359,$B$4,$D$29:$D$359,$D$17) -> -22475023560 | AD18: =SUM(OFFSET(R18:AC18,0,0,1,Performance!$H$2)) -> 55101774784
B19: =B15 -> 2026 | D19: =D12 -> Năm nay | R19: =SUMIFS(AF$29:AF$359,$B$29:$B$359,$B$4,$D$29:$D$359,$D$17) -> 52850277689 | S19: =SUMIFS(AG$29:AG$359,$B$29:$B$359,$B$4,$D$29:$D$359,$D$17) -> 1381288086 | T19: =SUMIFS(AH$29:AH$359,$B$29:$B$359,$B$4,$D$29:$D$359,$D$17) -> 52119683826 | U19: =SUMIFS(AI$29:AI$359,$B$29:$B$359,$B$4,$D$29:$D$359,$D$17) -> 82694562008 | V19: =SUMIFS(AJ$29:AJ$359,$B$29:$B$359,$B$4,$D$29:$D$359,$D$17) -> -53142624294 | W19: =SUMIFS(AK$29:AK$359,$B$29:$B$359,$B$4,$D$29:$D$359,$D$17) -> 0 | X19: =SUMIFS(AL$29:AL$359,$B$29:$B$359,$B$4,$D$29:$D$359,$D$17) -> 0 | Y19: =SUMIFS(AM$29:AM$359,$B$29:$B$359,$B$4,$D$29:$D$359,$D$17) -> 0 | ... AC19: =SUMIFS(AQ$29:AQ$359,$B$29:$B$359,$B$4,$D$29:$D$359,$D$17) -> 0 | AD19: =SUM(OFFSET(R19:AC19,0,0,1,Performance!$I$2)) -> 135903187315
D20: Net cash flow from investment activities
B21: =B18 -> 2025 | D21: =D18 -> Năm trước | R21: =SUMIFS(R$29:R$359,$B$29:$B$359,$B$4,$D$29:$D$359,$D$20) -> -9422603254 | S21: =SUMIFS(S$29:S$359,$B$29:$B$359,$B$4,$D$29:$D$359,$D$20) -> -1409744554 | T21: =SUMIFS(T$29:T$359,$B$29:$B$359,$B$4,$D$29:$D$359,$D$20) -> -42949753759 | U21: =SUMIFS(U$29:U$359,$B$29:$B$359,$B$4,$D$29:$D$359,$D$20) -> -27896985790 | V21: =SUMIFS(V$29:V$359,$B$29:$B$359,$B$4,$D$29:$D$359,$D$20) -> -19046783884 | W21: =SUMIFS(W$29:W$359,$B$29:$B$359,$B$4,$D$29:$D$359,$D$20) -> -4600165478 | X21: =SUMIFS(X$29:X$359,$B$29:$B$359,$B$4,$D$29:$D$359,$D$20) -> 14056363160 | Y21: =SUMIFS(Y$29:Y$359,$B$29:$B$359,$B$4,$D$29:$D$359,$D$20) -> -3771779405 | ... AC21: =SUMIFS(AC$29:AC$359,$B$29:$B$359,$B$4,$D$29:$D$359,$D$20) -> 15615882426 | AD21: =SUM(OFFSET(R21:AC21,0,0,1,Performance!$H$2)) -> -100725871241
B22: =B19 -> 2026 | D22: =D19 -> Năm nay | R22: =SUMIFS(AF$29:AF$359,$B$29:$B$359,$B$4,$D$29:$D$359,$D$20) -> -1524383164 | S22: =SUMIFS(AG$29:AG$359,$B$29:$B$359,$B$4,$D$29:$D$359,$D$20) -> -34677649362 | T22: =SUMIFS(AH$29:AH$359,$B$29:$B$359,$B$4,$D$29:$D$359,$D$20) -> -21851806644 | U22: =SUMIFS(AI$29:AI$359,$B$29:$B$359,$B$4,$D$29:$D$359,$D$20) -> -36965946130 | V22: =SUMIFS(AJ$29:AJ$359,$B$29:$B$359,$B$4,$D$29:$D$359,$D$20) -> 2488619135 | W22: =SUMIFS(AK$29:AK$359,$B$29:$B$359,$B$4,$D$29:$D$359,$D$20) -> 0 | X22: =SUMIFS(AL$29:AL$359,$B$29:$B$359,$B$4,$D$29:$D$359,$D$20) -> 0 | Y22: =SUMIFS(AM$29:AM$359,$B$29:$B$359,$B$4,$D$29:$D$359,$D$20) -> 0 | ... AC22: =SUMIFS(AQ$29:AQ$359,$B$29:$B$359,$B$4,$D$29:$D$359,$D$20) -> 0 | AD22: =SUM(OFFSET(R22:AC22,0,0,1,Performance!$I$2)) -> -92531166165
D23: Net cash flow from financial activities
B24: =B21 -> 2025 | D24: =D21 -> Năm trước | R24: =SUMIFS(R$29:R$359,$B$29:$B$359,$B$4,$D$29:$D$359,$D$23) -> -32192329733 | S24: =SUMIFS(S$29:S$359,$B$29:$B$359,$B$4,$D$29:$D$359,$D$23) -> -95561562751 | T24: =SUMIFS(T$29:T$359,$B$29:$B$359,$B$4,$D$29:$D$359,$D$23) -> 53554413425 | U24: =SUMIFS(U$29:U$359,$B$29:$B$359,$B$4,$D$29:$D$359,$D$23) -> 73852915769 | V24: =SUMIFS(V$29:V$359,$B$29:$B$359,$B$4,$D$29:$D$359,$D$23) -> 23489579490 | W24: =SUMIFS(W$29:W$359,$B$29:$B$359,$B$4,$D$29:$D$359,$D$23) -> 16839228535 | X24: =SUMIFS(X$29:X$359,$B$29:$B$359,$B$4,$D$29:$D$359,$D$23) -> 11111720339 | Y24: =SUMIFS(Y$29:Y$359,$B$29:$B$359,$B$4,$D$29:$D$359,$D$23) -> 42673563192 | ... AC24: =SUMIFS(AC$29:AC$359,$B$29:$B$359,$B$4,$D$29:$D$359,$D$23) -> -11723844029 | AD24: =SUM(OFFSET(R24:AC24,0,0,1,Performance!$I$2)) -> 23143016200
B25: =B22 -> 2026 | D25: =D22 -> Năm nay | R25: =SUMIFS(AF$29:AF$359,$B$29:$B$359,$B$4,$D$29:$D$359,$D$23) -> -46316594032 | S25: =SUMIFS(AG$29:AG$359,$B$29:$B$359,$B$4,$D$29:$D$359,$D$23) -> 36955208932 | T25: =SUMIFS(AH$29:AH$359,$B$29:$B$359,$B$4,$D$29:$D$359,$D$23) -> -43409395667 | U25: =SUMIFS(AI$29:AI$359,$B$29:$B$359,$B$4,$D$29:$D$359,$D$23) -> -32222541860 | V25: =SUMIFS(AJ$29:AJ$359,$B$29:$B$359,$B$4,$D$29:$D$359,$D$23) -> 43913929275 | W25: =SUMIFS(AK$29:AK$359,$B$29:$B$359,$B$4,$D$29:$D$359,$D$23) -> 0 | X25: =SUMIFS(AL$29:AL$359,$B$29:$B$359,$B$4,$D$29:$D$359,$D$23) -> 0 | Y25: =SUMIFS(AM$29:AM$359,$B$29:$B$359,$B$4,$D$29:$D$359,$D$23) -> 0 | ... AC25: =SUMIFS(AQ$29:AQ$359,$B$29:$B$359,$B$4,$D$29:$D$359,$D$23) -> 0 | AD25: =SUM(OFFSET(R25:AC25,0,0,1,Performance!$I$2)) -> -41079393352
Q26: =Performance!H2 -> 5 | AD26: =Performance!H2 -> 5 | AR26: =Performance!I2 -> 5
AF27: =SUM(#REF!,#REF!)/10^9 -> #REF! | AG27: =SUM(#REF!,#REF!)/10^9 -> #REF! | AH27: =SUM(#REF!,#REF!)/10^9 -> #REF! | AI27: =SUM(#REF!,#REF!)/10^9 -> #REF!
A28: Code | B28: Company | D28: Items | E28: 1 | F28: 2 | G28: 3 | H28: 4 | I28: 5 | J28: 6 | K28: 7 | L28: 8 | M28: 9 | N28: 10 | O28: 11 | P28: 12 | Q28: 2024 | R28: 1 | S28: 2 | T28: 3 | U28: 4 | V28: 5 | W28: 6 | X28: 7 | Y28: 8 | Z28: 9 | AA28: 10 | AB28: 11 | AC28: 12 | AD28: 2025 | AE28: Current month | AF28: 1 | AG28: 2 | AH28: 3 | AI28: 4 | AJ28: 5 | AK28: 6 | AL28: 7 | AM28: 8 | AN28: 9 | AO28: 10 | AP28: 11 | AQ28: 12 | AR28: 2026 | AS28: Current month | AT28: 1 | AU28: 2 | AV28: 3 | AW28: 4 | AX28: 5 | AY28: 6 | AZ28: 7 | BA28: 8 | BB28: 9 | BC28: 10 | BD28: 11 | BE28: 12
B29: Nhóm Tái Chế | D29: Net sales | E29: =E39+#REF!+#REF!+#REF! -> #REF! | F29: =F39+#REF!+#REF!+#REF! -> #REF! | G29: =G39+#REF!+#REF!+#REF! -> #REF! | H29: =H39+#REF!+#REF!+#REF! -> #REF! | I29: =I39+#REF!+#REF!+#REF! -> #REF! | J29: =J39+#REF!+#REF!+#REF! -> #REF! | K29: =K39+#REF!+#REF!+#REF! -> #REF! | L29: =L39+#REF!+#REF!+#REF! -> #REF! | ... AD29: =AD39+#REF!+#REF!+#REF! -> #REF!
B30: Nhóm Tái Chế | D30: Net profit | E30: =E71+#REF!+#REF!+#REF! -> #REF! | F30: =F71+#REF!+#REF!+#REF! -> #REF! | G30: =G71+#REF!+#REF!+#REF! -> #REF! | H30: =H71+#REF!+#REF!+#REF! -> #REF! | I30: =I71+#REF!+#REF!+#REF! -> #REF! | J30: =J71+#REF!+#REF!+#REF! -> #REF! | K30: =K71+#REF!+#REF!+#REF! -> #REF! | L30: =L71+#REF!+#REF!+#REF! -> #REF! | ... AD30: =AD71+#REF!+#REF!+#REF! -> #REF!
B31: Nhóm Tái Chế | D31: EBITDA | E31: =E68+#REF!+#REF!+#REF! -> #REF! | F31: =F68+#REF!+#REF!+#REF! -> #REF! | G31: =G68+#REF!+#REF!+#REF! -> #REF! | H31: =H68+#REF!+#REF!+#REF! -> #REF! | I31: =I68+#REF!+#REF!+#REF! -> #REF! | J31: =J68+#REF!+#REF!+#REF! -> #REF! | K31: =K68+#REF!+#REF!+#REF! -> #REF! | L31: =L68+#REF!+#REF!+#REF! -> #REF! | ... AD31: =AD68+#REF!+#REF!+#REF! -> #REF!
B34: DTR | D34: Production headcount (avg) | E34: =DTR!C200 -> 248.32407 | F34: =DTR!D200 -> 228.94231 | G34: =DTR!E200 -> 262.77 | H34: =DTR!F200 -> 275.26852 | I34: =DTR!G200 -> 280.88462 | J34: =DTR!H200 -> 291.61538 | K34: =DTR!I200 -> 294.125 | L34: =DTR!J200 -> 289.92308 | ... P34: =DTR!N200 -> 360.65385 | Q34: =AVERAGE(OFFSET(E34:P34,0,0,1,$AD$26)) -> 259.2379 | R34: =DTR!O200 -> 333.7037 | S34: =DTR!P200 -> 337.96154 | T34: =DTR!Q200 -> 344.22917 | U34: =DTR!R200 -> 347.57407 | V34: =DTR!S200 -> 336.74 | W34: =DTR!T200 -> 351.75481 | X34: =DTR!U200 -> 406.15385 | Y34: =DTR!V200 -> 409.73077 | ... AC34: =DTR!Z200 -> 340.42788 | AD34: =AVERAGE(OFFSET(R34:AC34,0,0,1,$AD$26)) -> 340.0417 | AE34: =IF($AD$26=1,R34,SUM(OFFSET(R34:AC34,0,0,1,$AD$26))-SUM(OFFSET(R34:AC34,0,0,1,$AD$26-1))) -> 336.74 | AF34: =DTR!AA$200 -> 326.32 | AG34: =DTR!AB$200 -> 348.40909 | AH34: =DTR!AC$200 -> 335.09635 | AI34: =DTR!AD$200 -> 342.35185 | AJ34: =DTR!AE$200 -> 354.78 | AK34: =DTR!AF$200 -> 369 | AL34: =DTR!AG$200 -> 369 | AM34: =DTR!AH$200 -> 369 | ... AQ34: =DTR!AL$200 -> 370 | AR34: =AVERAGE(OFFSET(AF34:AQ34,0,0,1,$AR$26)) -> 341.39146 | AS34: =IF($AR$26=1,AF34,SUM(OFFSET(AF34:AQ34,0,0,1,$AR$26))-SUM(OFFSET(AF34:AQ34,0,0,1,$AR$26-1))) -> 354.78
B35: DTR | D35: Man-day (8 hrs) | E35: =DTR!C201 -> 8313.125 | F35: =DTR!D201 -> 5751.2563 | G35: =DTR!E201 -> 8410.5487 | H35: =DTR!F201 -> 9674.7638 | I35: =DTR!G201 -> 9070.9487 | J35: =DTR!H201 -> 9978.34 | K35: =DTR!I201 -> 9880.3888 | L35: =DTR!J201 -> 8027.2775 | ... P35: =DTR!N201 -> 9981.595 | Q35: =SUM(OFFSET(E35:P35,0,0,1,$AD$26)) -> 41220.643 | R35: =DTR!O201 -> 8888.6763 | S35: =DTR!P201 -> 7373.15 | T35: =DTR!Q201 -> 8885.245 | U35: =DTR!R201 -> 9712.6712 | V35: =DTR!S201 -> 9376.4338 | W35: =DTR!T201 -> 10781.005 | X35: =DTR!U201 -> 11002.837 | Y35: =DTR!V201 -> 10746.68 | ... AC35: =DTR!Z201 -> 9400.6362 | AD35: =SUM(OFFSET(R35:AC35,0,0,1,$AD$26)) -> 44236.176 | AE35: =IF($AD$26=1,R35,SUM(OFFSET(R35:AC35,0,0,1,$AD$26))-SUM(OFFSET(R35:AC35,0,0,1,$AD$26-1))) -> 9376.4338 | AF35: =DTR!AA$201 -> 8272.0988 | AG35: =DTR!AB$201 -> 6904.42 | AH35: =DTR!AC$201 -> 8481.5962 | AI35: =DTR!AD$201 -> 10303.626 | AJ35: =DTR!AE$201 -> 6773.8363 | AK35: =DTR!AF$201 -> 9225 | AL35: =DTR!AG$201 -> 9225 | AM35: =DTR!AH$201 -> 9225 | ... AQ35: =DTR!AL$201 -> 9250 | AR35: =SUM(OFFSET(AF35:AQ35,0,0,1,$AR$26)) -> 40735.577 | AS35: =IF($AR$26=1,AF35,SUM(OFFSET(AF35:AQ35,0,0,1,$AR$26))-SUM(OFFSET(AF35:AQ35,0,0,1,$AR$26-1))) -> 6773.8363
A36: P01 | B36: DTR | D36: Production volume | E36: =DTR!C202 -> 4748.313 | F36: =DTR!D202 -> 2926.502 | G36: =DTR!E202 -> 4896.438 | H36: =DTR!F202 -> 4526.369 | I36: =DTR!G202 -> 4417.875 | J36: =DTR!H202 -> 3495.0745 | K36: =DTR!I202 -> 1866.424 | L36: =DTR!J202 -> 2192.5825 | ... P36: =DTR!N202 -> 3318.6421 | Q36: =SUM(OFFSET(E36:P36,0,0,1,$AD$26)) -> 21515.497 | R36: =DTR!O202 -> 1839.731 | S36: =DTR!P202 -> 2957.266 | T36: =DTR!Q202 -> 4821.92 | U36: =DTR!R202 -> 4088.249 | V36: =DTR!S202 -> 4828.971 | W36: =DTR!T202 -> 4232.453 | X36: =DTR!U202 -> 4561.641 | Y36: =DTR!V202 -> 4570.5645 | ... AC36: =DTR!Z202 -> 3552.8618 | AD36: =SUM(OFFSET(R36:AC36,0,0,1,$AD$26)) -> 18536.137 | AE36: =IF($AD$26=1,R36,SUM(OFFSET(R36:AC36,0,0,1,$AD$26))-SUM(OFFSET(R36:AC36,0,0,1,$AD$26-1))) -> 4828.971 | AF36: =DTR!AA$202 -> 2868.5693 | AG36: =DTR!AB$202 -> 1811.1 | AH36: =DTR!AC$202 -> 4279.489 | AI36: =DTR!AD$202 -> 4003.7973 | AJ36: =DTR!AE$202 -> 3592.682 | AK36: =DTR!AF$202 -> 4284.8144 | AL36: =DTR!AG$202 -> 4264.7784 | AM36: =DTR!AH$202 -> 4161.4732 | ... AQ36: =DTR!AL$202 -> 4380.6502 | AR36: =SUM(OFFSET(AF36:AQ36,0,0,1,$AR$26)) -> 16555.638 | AS36: =IF($AR$26=1,AF36,SUM(OFFSET(AF36:AQ36,0,0,1,$AR$26))-SUM(OFFSET(AF36:AQ36,0,0,1,$AR$26-1))) -> 3592.682
B37: DTR | D37: Total Headcount | E37: =DTR!C199 -> 449.32407 | F37: =DTR!D199 -> 426.94231 | G37: =DTR!E199 -> 469.77 | H37: =DTR!F199 -> 495.26852 | I37: =DTR!G199 -> 511.88462 | J37: =DTR!H199 -> 520.61538 | K37: =DTR!I199 -> 525.125 | L37: =DTR!J199 -> 518.92308 | ... P37: =DTR!N199 -> 615.65385 | Q37: =AVERAGE(OFFSET(E37:P37,0,0,1,$AD$26)) -> 470.6379 | R37: =DTR!O199 -> 593.7037 | S37: =DTR!P199 -> 594.96154 | T37: =DTR!Q199 -> 615.22917 | U37: =DTR!R199 -> 624.57407 | V37: =DTR!S199 -> 617.74 | W37: =DTR!T199 -> 637.75481 | X37: =DTR!U199 -> 691.15385 | Y37: =DTR!V199 -> 697.73077 | ... AC37: =DTR!Z199 -> 634.42788 | AD37: =AVERAGE(OFFSET(R37:AC37,0,0,1,$AD$26)) -> 609.2417 | AE37: =IF($AD$26=1,R37,SUM(OFFSET(R37:AC37,0,0,1,$AD$26))-SUM(OFFSET(R37:AC37,0,0,1,$AD$26-1))) -> 617.74 | AF37: =DTR!AA$199 -> 616.32 | AG37: =DTR!AB$199 -> 628.40909 | AH37: =DTR!AC$199 -> 616.09635 | AI37: =DTR!AD$199 -> 619.35185 | AJ37: =DTR!AE$199 -> 637.78 | AK37: =DTR!AF$199 -> 674 | AL37: =DTR!AG$199 -> 674 | AM37: =DTR!AH$199 -> 674 | ... AQ37: =DTR!AL$199 -> 675 | AR37: =AVERAGE(OFFSET(AF37:AQ37,0,0,1,$AR$26)) -> 623.59146 | AS37: =IF($AR$26=1,AF37,SUM(OFFSET(AF37:AQ37,0,0,1,$AR$26))-SUM(OFFSET(AF37:AQ37,0,0,1,$AR$26-1))) -> 637.78
A38: P02 | B38: DTR | D38: Sales volume | E38: =DTR!C134 -> 3553.2 | F38: =DTR!D134 -> 2285.051 | G38: =DTR!E134 -> 2972.068 | H38: =DTR!F134 -> 3202.752 | I38: =DTR!G134 -> 3455.89 | J38: =DTR!H134 -> 2432.325 | K38: =DTR!I134 -> 1986.853 | L38: =DTR!J134 -> 5184.5942 | ... P38: =DTR!N134 -> 3375.148 | Q38: =SUM(OFFSET(E38:P38,0,0,1,$AD$26)) -> 15468.961 | R38: =DTR!O134 -> 3612.7513 | S38: =DTR!P134 -> 6002.038 | T38: =DTR!Q134 -> 4985.538 | U38: =DTR!R134 -> 4060.361 | V38: =DTR!S134 -> 4785.7603 | W38: =DTR!T134 -> 3895.695 | X38: =DTR!U134 -> 4652.4191 | Y38: =DTR!V134 -> 5655.27 | ... AC38: =DTR!Z134 -> 3185.679 | AD38: =SUM(OFFSET(R38:AC38,0,0,1,$AD$26)) -> 23446.449 | AE38: =IF($AD$26=1,R38,SUM(OFFSET(R38:AC38,0,0,1,$AD$26))-SUM(OFFSET(R38:AC38,0,0,1,$AD$26-1))) -> 4785.7603 | AF38: =DTR!AA$134 -> 4409.992 | AG38: =DTR!AB$134 -> 3267.6 | AH38: =DTR!AC$134 -> 6445.446 | AI38: =DTR!AD$134 -> 5748.625 | AJ38: =DTR!AE$134 -> 5140.924 | AK38: =DTR!AF$134 -> 0 | AL38: =DTR!AG$134 -> 0 | AM38: =DTR!AH$134 -> 0 | ... AQ38: =DTR!AL$134 -> 0 | AR38: =SUM(OFFSET(AF38:AQ38,0,0,1,$AR$26)) -> 25012.587 | AS38: =IF($AR$26=1,AF38,SUM(OFFSET(AF38:AQ38,0,0,1,$AR$26))-SUM(OFFSET(AF38:AQ38,0,0,1,$AR$26-1))) -> 5140.924
A39: P03 | B39: DTR | D39: Net sales | E39: =DTR!C137 -> 95961616736 | F39: =DTR!D137 -> 68939746996 | G39: =DTR!E137 -> 92109508133 | H39: =DTR!F137 -> 97489092894 | I39: =DTR!G137 -> 102364998344 | J39: =DTR!H137 -> 68093170109 | K39: =DTR!I137 -> 56451269692 | L39: =DTR!J137 -> 154027868172 | ... P39: =DTR!N137 -> 106210088680 | Q39: =SUM(OFFSET(E39:P39,0,0,1,$AD$26)) -> 456864963103 | R39: =DTR!O137 -> 114462510402 | S39: =DTR!P137 -> 187999461059 | T39: =DTR!Q137 -> 150253332680 | U39: =DTR!R137 -> 125429649855 | V39: =DTR!S137 -> 152067142852 | W39: =DTR!T137 -> 119134672797 | X39: =DTR!U137 -> 137991406898 | Y39: =DTR!V137 -> 168442653383 | ... AC39: =DTR!Z137 -> 99758121581 | AD39: =SUM(OFFSET(R39:AC39,0,0,1,$AD$26)) -> 730212096848 | AE39: =IF($AD$26=1,R39,SUM(OFFSET(R39:AC39,0,0,1,$AD$26))-SUM(OFFSET(R39:AC39,0,0,1,$AD$26-1))) -> 152067142852 | AF39: =DTR!AA$137 -> 126099036923 | AG39: =DTR!AB$137 -> 96566805360 | AH39: =DTR!AC$137 -> 173305822529 | AI39: =DTR!AD$137 -> 159056854829 | AJ39: =DTR!AE$137 -> 159765309037 | AK39: =DTR!AF$137 -> 0 | AL39: =DTR!AG$137 -> 0 | AM39: =DTR!AH$137 -> 0 | ... AQ39: =DTR!AL$137 -> 0 | AR39: =SUM(OFFSET(AF39:AQ39,0,0,1,$AR$26)) -> 714793828678 | AS39: =IF($AR$26=1,AF39,SUM(OFFSET(AF39:AQ39,0,0,1,$AR$26))-SUM(OFFSET(AF39:AQ39,0,0,1,$AR$26-1))) -> 159765309037 | BH39: =(AD39-Q39)/Q39 -> 0.59831056
A40: P04 | B40: DTR | D40: Export | E40: =DTR!C208 -> 82123174705 | F40: =DTR!D208 -> 82123174705 | G40: =DTR!E208 -> 82123174705 | H40: =DTR!F208 -> 82123174705 | I40: =DTR!G208 -> 82123174705 | J40: =DTR!H208 -> 82123174705 | K40: =DTR!I208 -> 82123174705 | L40: =DTR!J208 -> 82123174705 | ... P40: =DTR!N208 -> 82123174705 | Q40: =SUM(OFFSET(E40:P40,0,0,1,$AD$26)) -> 410615873525 | R40: =DTR!O208 -> 82123174705 | S40: =DTR!P208 -> 127754884829 | T40: =DTR!Q208 -> 103667980875 | U40: =DTR!R208 -> 89699052245 | V40: =DTR!S208 -> 114824058990 | W40: =DTR!T208 -> 70054412500 | X40: =DTR!U208 -> 88123126474 | Y40: =DTR!V208 -> 94069028914 | ... AC40: =DTR!Z208 -> 30893476900 | AD40: =SUM(OFFSET(R40:AC40,0,0,1,$AD$26)) -> 518069151644 | AE40: =IF($AD$26=1,R40,SUM(OFFSET(R40:AC40,0,0,1,$AD$26))-SUM(OFFSET(R40:AC40,0,0,1,$AD$26-1))) -> 114824058990 | AF40: =DTR!AA$208 -> 70701288516 | AG40: =DTR!AB$208 -> 58540341826 | AH40: =DTR!AC$208 -> 80759624796 | AI40: =DTR!AD$208 -> 67176948835 | AJ40: =DTR!AE$208 -> 87346708460 | AK40: =DTR!AF$208 -> 8.4694024e+10 | AL40: =DTR!AG$208 -> 8.1755189e+10 | AM40: =DTR!AH$208 -> 7.4361265e+10 | ... AQ40: =DTR!AL$208 -> 8.2308032e+10 | AR40: =SUM(OFFSET(AF40:AQ40,0,0,1,$AR$26)) -> 364524912433 | AS40: =IF($AR$26=1,AF40,SUM(OFFSET(AF40:AQ40,0,0,1,$AR$26))-SUM(OFFSET(AF40:AQ40,0,0,1,$AR$26-1))) -> 87346708460
A41: P05 | B41: DTR | D41: Domestic | E41: =DTR!C209 -> 32339335697 | F41: =DTR!D209 -> 32339335697 | G41: =DTR!E209 -> 32339335697 | H41: =DTR!F209 -> 32339335697 | I41: =DTR!G209 -> 32339335697 | J41: =DTR!H209 -> 32339335697 | K41: =DTR!I209 -> 32339335697 | L41: =DTR!J209 -> 32339335697 | ... P41: =DTR!N209 -> 32339335697 | Q41: =SUM(OFFSET(E41:P41,0,0,1,$AD$26)) -> 161696678485 | R41: =DTR!O209 -> 32339335697 | S41: =DTR!P209 -> 60244576230 | T41: =DTR!Q209 -> 46405979203 | U41: =DTR!R209 -> 35730597610 | V41: =DTR!S209 -> 37243083862 | W41: =DTR!T209 -> 49080260297 | X41: =DTR!U209 -> 49868280424 | Y41: =DTR!V209 -> 74191430822 | ... AC41: =DTR!Z209 -> 62246318181 | AD41: =SUM(OFFSET(R41:AC41,0,0,1,$AD$26)) -> 211963572602 | AE41: =IF($AD$26=1,R41,SUM(OFFSET(R41:AC41,0,0,1,$AD$26))-SUM(OFFSET(R41:AC41,0,0,1,$AD$26-1))) -> 37243083862 | AF41: =DTR!AA$209 -> 55230863407 | AG41: =DTR!AB$209 -> 37446516644 | AH41: =DTR!AC$209 -> 9.1465683e+10 | AI41: =DTR!AD$209 -> 91879905994 | AJ41: =DTR!AE$209 -> 70741575322 | AK41: =DTR!AF$209 -> 5.8821049e+10 | AL41: =DTR!AG$209 -> 6.085225e+10 | AM41: =DTR!AH$209 -> 6.4042688e+10 | ... AQ41: =DTR!AL$209 -> 6.2271077e+10 | AR41: =SUM(OFFSET(AF41:AQ41,0,0,1,$AR$26)) -> 346764544100 | AS41: =IF($AR$26=1,AF41,SUM(OFFSET(AF41:AQ41,0,0,1,$AR$26))-SUM(OFFSET(AF41:AQ41,0,0,1,$AR$26-1))) -> 70741575322
A42: P06 | B42: DTR | D42: Others | E42: =DTR!C210 -> 0 | F42: =DTR!D210 -> 0 | G42: =DTR!E210 -> 0 | H42: =DTR!F210 -> 0 | I42: =DTR!G210 -> 0 | J42: =DTR!H210 -> 0 | K42: =DTR!I210 -> 0 | L42: =DTR!J210 -> 0 | ... P42: =DTR!N210 -> 0 | Q42: =SUM(OFFSET(E42:P42,0,0,1,$AD$26)) -> 0 | R42: =DTR!O210 -> 0 | S42: =DTR!P210 -> 0 | T42: =DTR!Q210 -> 179372602 | U42: =DTR!R210 -> 0 | V42: =DTR!S210 -> 0 | W42: =DTR!T210 -> 0 | X42: =DTR!U210 -> 0 | Y42: =DTR!V210 -> 182193647 | ... AC42: =DTR!Z210 -> 8295287500 | AD42: =SUM(OFFSET(R42:AC42,0,0,1,$AD$26)) -> 179372602 | AE42: =IF($AD$26=1,R42,SUM(OFFSET(R42:AC42,0,0,1,$AD$26))-SUM(OFFSET(R42:AC42,0,0,1,$AD$26-1))) -> 0 | AF42: =DTR!AA$210 -> 166885000 | AG42: =DTR!AB$210 -> 579946890 | AH42: =DTR!AC$210 -> 1080515000 | AI42: =DTR!AD$210 -> 0 | AJ42: =DTR!AE$210 -> 1677025255 | AK42: =DTR!AF$210 -> 0 | AL42: =DTR!AG$210 -> 4925058000 | AM42: =DTR!AH$210 -> 4925058000 | ... AQ42: =DTR!AL$210 -> 5243797200 | AR42: =SUM(OFFSET(AF42:AQ42,0,0,1,$AR$26)) -> 3504372145 | AS42: =IF($AR$26=1,AF42,SUM(OFFSET(AF42:AQ42,0,0,1,$AR$26))-SUM(OFFSET(AF42:AQ42,0,0,1,$AR$26-1))) -> 1677025255
A43: P07 | B43: DTR | D43: Cost of goods sold (COGs) | E43: =DTR!C138 -> 85841765176 | F43: =DTR!D138 -> 68748321616 | G43: =DTR!E138 -> 86824377307 | H43: =DTR!F138 -> 85475594862 | I43: =DTR!G138 -> 99208228636 | J43: =DTR!H138 -> 69795611979 | K43: =DTR!I138 -> 61217801757 | L43: =DTR!J138 -> 147970813832 | ... P43: =DTR!N138 -> -22758768790 | Q43: =SUM(OFFSET(E43:P43,0,0,1,$AD$26)) -> 426098287597 | R43: =DTR!O138 -> 96299447936 | S43: =DTR!P138 -> 154570631505 | T43: =DTR!Q138 -> 129509315823 | U43: =DTR!R138 -> 109641808151 | V43: =DTR!S138 -> 129906078108 | W43: =DTR!T138 -> 105463649620 | X43: =DTR!U138 -> 128673842020 | Y43: =DTR!V138 -> 155101842643 | ... AC43: =DTR!Z138 -> 70308328665 | AD43: =SUM(OFFSET(R43:AC43,0,0,1,$AD$26)) -> 619927281523 | AE43: =IF($AD$26=1,R43,SUM(OFFSET(R43:AC43,0,0,1,$AD$26))-SUM(OFFSET(R43:AC43,0,0,1,$AD$26-1))) -> 129906078108 | AF43: =DTR!AA$138 -> 115080112871 | AG43: =DTR!AB$138 -> 90411470461 | AH43: =DTR!AC$138 -> 165844739865 | AI43: =DTR!AD$138 -> 141086003219 | AJ43: =DTR!AE$138 -> 137580032058 | AK43: =DTR!AF$138 -> 0 | AL43: =DTR!AG$138 -> 0 | AM43: =DTR!AH$138 -> 0 | ... AQ43: =DTR!AL$138 -> 0 | AR43: =SUM(OFFSET(AF43:AQ43,0,0,1,$AR$26)) -> 650002358474 | AS43: =IF($AR$26=1,AF43,SUM(OFFSET(AF43:AQ43,0,0,1,$AR$26))-SUM(OFFSET(AF43:AQ43,0,0,1,$AR$26-1))) -> 137580032058
A44: P08 | B44: DTR | C44: Biến phí sản xuất | D44: Material cost | E44: =DTR!C212 -> 5.932969e+10 | F44: =DTR!D212 -> 44670723974 | G44: =DTR!E212 -> 5.5370087e+10 | H44: =DTR!F212 -> 5.8899112e+10 | I44: =DTR!G212 -> 6.8236506e+10 | J44: =DTR!H212 -> 4.6389174e+10 | K44: =DTR!I212 -> 4.0923611e+10 | L44: =DTR!J212 -> 1.0323661e+11 | ... P44: =DTR!N212 -> 5.810373e+10 | Q44: =SUM(OFFSET(E44:P44,0,0,1,$AD$26)) -> 2.8650612e+11 | R44: =DTR!O212 -> 6.8221516e+10 | S44: =DTR!P212 -> 1.1352751e+11 | T44: =DTR!Q212 -> 9.6004842e+10 | U44: =DTR!R212 -> 7.9931588e+10 | V44: =DTR!S212 -> 9.765661e+10 | W44: =DTR!T212 -> 7.8658432e+10 | X44: =DTR!U212 -> 9.5890721e+10 | Y44: =DTR!V212 -> 1.1427074e+11 | ... AC44: =DTR!Z212 -> 5.7953398e+10 | AD44: =SUM(OFFSET(R44:AC44,0,0,1,$AD$26)) -> 4.5534206e+11 | AE44: =IF($AD$26=1,R44,SUM(OFFSET(R44:AC44,0,0,1,$AD$26))-SUM(OFFSET(R44:AC44,0,0,1,$AD$26-1))) -> 9.765661e+10 | AF44: =DTR!AA$212 -> 8.2659834e+10 | AG44: =DTR!AB$212 -> 6.0512615e+10 | AH44: =DTR!AC$212 -> 1.1954014e+11 | AI44: =DTR!AD$212 -> 1.0182565e+11 | AJ44: =DTR!AE$212 -> 1.0067611e+11 | AK44: =DTR!AF$212 -> 8.5107632e+10 | AL44: =DTR!AG$212 -> 8.4284703e+10 | AM44: =DTR!AH$212 -> 8.2266894e+10 | ... AQ44: =DTR!AL$212 -> 8.6852311e+10 | AR44: =SUM(OFFSET(AF44:AQ44,0,0,1,$AR$26)) -> 4.6521435e+11 | AS44: =IF($AR$26=1,AF44,SUM(OFFSET(AF44:AQ44,0,0,1,$AR$26))-SUM(OFFSET(AF44:AQ44,0,0,1,$AR$26-1))) -> 1.0067611e+11
A45: P09 | B45: DTR | C45: Biến phí sản xuất | D45: Electricity | E45: =DTR!C213 -> 5457667459 | F45: =DTR!D213 -> 4115002140 | G45: =DTR!E213 -> 5069779794 | H45: =DTR!F213 -> 5488644404 | I45: =DTR!G213 -> 5922960272 | J45: =DTR!H213 -> 4771803237 | K45: =DTR!I213 -> 2990887219 | L45: =DTR!J213 -> 3465068093 | ... P45: =DTR!N213 -> 4848607138 | Q45: =SUM(OFFSET(E45:P45,0,0,1,$AD$26)) -> 26054054069 | R45: =DTR!O213 -> 3115586041 | S45: =DTR!P213 -> 4131446442 | T45: =DTR!Q213 -> 6471627635 | U45: =DTR!R213 -> 6106208552 | V45: =DTR!S213 -> 6534087601 | W45: =DTR!T213 -> 6331091846 | X45: =DTR!U213 -> 7033711933 | Y45: =DTR!V213 -> 7206770412 | ... AC45: =DTR!Z213 -> 4839388132 | AD45: =SUM(OFFSET(R45:AC45,0,0,1,$AD$26)) -> 26358956271 | AE45: =IF($AD$26=1,R45,SUM(OFFSET(R45:AC45,0,0,1,$AD$26))-SUM(OFFSET(R45:AC45,0,0,1,$AD$26-1))) -> 6534087601 | AF45: =DTR!AA$213 -> 4027863724 | AG45: =DTR!AB$213 -> 2451956924 | AH45: =DTR!AC$213 -> 5626303966 | AI45: =DTR!AD$213 -> 5649277552 | AJ45: =DTR!AE$213 -> 5769165884 | AK45: =DTR!AF$213 -> 5.1472403e+09 | AL45: =DTR!AG$213 -> 5.2826893e+09 | AM45: =DTR!AH$213 -> 5.3496326e+09 | ... AQ45: =DTR!AL$213 -> 5.4884684e+09 | AR45: =SUM(OFFSET(AF45:AQ45,0,0,1,$AR$26)) -> 23524568050 | AS45: =IF($AR$26=1,AF45,SUM(OFFSET(AF45:AQ45,0,0,1,$AR$26))-SUM(OFFSET(AF45:AQ45,0,0,1,$AR$26-1))) -> 5769165884
A46: P10 | B46: DTR | C46: Chi phí nhân sự | D46: Overtime | E46: =DTR!C214 -> 673524358 | F46: =DTR!D214 -> 445330075 | G46: =DTR!E214 -> 646654899 | H46: =DTR!F214 -> 1789160297 | I46: =DTR!G214 -> 743322765 | J46: =DTR!H214 -> 710659695 | K46: =DTR!I214 -> 562555746 | L46: =DTR!J214 -> 273359738 | ... P46: =DTR!N214 -> 352714337 | Q46: =SUM(OFFSET(E46:P46,0,0,1,$AD$26)) -> 4297992394 | R46: =DTR!O214 -> 326525959 | S46: =DTR!P214 -> 301395737 | T46: =DTR!Q214 -> 353064382 | U46: =DTR!R214 -> 367893640 | V46: =DTR!S214 -> 583268535 | W46: =DTR!T214 -> 409683221 | X46: =DTR!U214 -> 382580514 | Y46: =DTR!V214 -> 409675223 | ... AC46: =DTR!Z214 -> 371608824 | AD46: =SUM(OFFSET(R46:AC46,0,0,1,$AD$26)) -> 1932148253 | AE46: =IF($AD$26=1,R46,SUM(OFFSET(R46:AC46,0,0,1,$AD$26))-SUM(OFFSET(R46:AC46,0,0,1,$AD$26-1))) -> 583268535 | AF46: =DTR!AA$214 -> 368816619 | AG46: =DTR!AB$214 -> 248754636 | AH46: =DTR!AC$214 -> 337308264 | AI46: =DTR!AD$214 -> 499755909 | AJ46: =DTR!AE$214 -> 354846806 | AK46: =DTR!AF$214 -> 550521969 | AL46: =DTR!AG$214 -> 530132244 | AM46: =DTR!AH$214 -> 530132244 | ... AQ46: =DTR!AL$214 -> 530132244 | AR46: =SUM(OFFSET(AF46:AQ46,0,0,1,$AR$26)) -> 1809482234 | AS46: =IF($AR$26=1,AF46,SUM(OFFSET(AF46:AQ46,0,0,1,$AR$26))-SUM(OFFSET(AF46:AQ46,0,0,1,$AR$26-1))) -> 354846806
A47: P11 | B47: DTR | C47: Chi phí nhân sự | D47: Direct labor | E47: =DTR!C215 -> 1708507014 | F47: =DTR!D215 -> 1230497207 | G47: =DTR!E215 -> 1379015197 | H47: =DTR!F215 -> 521248356 | I47: =DTR!G215 -> 1657709643 | J47: =DTR!H215 -> 1580786853 | K47: =DTR!I215 -> 1552872520 | L47: =DTR!J215 -> 1840092100 | ... P47: =DTR!N215 -> 2664027703 | Q47: =SUM(OFFSET(E47:P47,0,0,1,$AD$26)) -> 6496977417 | R47: =DTR!O215 -> 2102841120 | S47: =DTR!P215 -> 2139570280 | T47: =DTR!Q215 -> 2143336877 | U47: =DTR!R215 -> 2211173874 | V47: =DTR!S215 -> 2328020395 | W47: =DTR!T215 -> 2570077869 | X47: =DTR!U215 -> 3450671363 | Y47: =DTR!V215 -> 2893137111 | ... AC47: =DTR!Z215 -> 2339162817 | AD47: =SUM(OFFSET(R47:AC47,0,0,1,$AD$26)) -> 10924942546 | AE47: =IF($AD$26=1,R47,SUM(OFFSET(R47:AC47,0,0,1,$AD$26))-SUM(OFFSET(R47:AC47,0,0,1,$AD$26-1))) -> 2328020395 | AF47: =DTR!AA$215 -> 2314962109 | AG47: =DTR!AB$215 -> 1839461214 | AH47: =DTR!AC$215 -> 2152019625 | AI47: =DTR!AD$215 -> 2463187426 | AJ47: =DTR!AE$215 -> 2407536723 | AK47: =DTR!AF$215 -> 3.3248653e+09 | AL47: =DTR!AG$215 -> 3258165255 | AM47: =DTR!AH$215 -> 3258165255 | ... AQ47: =DTR!AL$215 -> 3258165255 | AR47: =SUM(OFFSET(AF47:AQ47,0,0,1,$AR$26)) -> 11177167097 | AS47: =IF($AR$26=1,AF47,SUM(OFFSET(AF47:AQ47,0,0,1,$AR$26))-SUM(OFFSET(AF47:AQ47,0,0,1,$AR$26-1))) -> 2407536723
A48: P12 | B48: DTR | C48: Chi phí nhân sự | D48: Indirect labor | E48: =DTR!C216 -> 2782213759 | F48: =DTR!D216 -> 2629007193 | G48: =DTR!E216 -> 2770751785 | H48: =DTR!F216 -> 3041632252 | I48: =DTR!G216 -> 3141804002 | J48: =DTR!H216 -> 3245971482 | K48: =DTR!I216 -> 3110331141 | L48: =DTR!J216 -> 3202665604 | ... P48: =DTR!N216 -> 3622850142 | Q48: =SUM(OFFSET(E48:P48,0,0,1,$AD$26)) -> 14365408991 | R48: =DTR!O216 -> 3867069957 | S48: =DTR!P216 -> 3594333014 | T48: =DTR!Q216 -> 3676490698 | U48: =DTR!R216 -> 4144437406 | V48: =DTR!S216 -> 4051343169 | W48: =DTR!T216 -> 4168433618 | X48: =DTR!U216 -> 4155409281 | Y48: =DTR!V216 -> 4177314711 | ... AC48: =DTR!Z216 -> 3914832620 | AD48: =SUM(OFFSET(R48:AC48,0,0,1,$AD$26)) -> 19333674244 | AE48: =IF($AD$26=1,R48,SUM(OFFSET(R48:AC48,0,0,1,$AD$26))-SUM(OFFSET(R48:AC48,0,0,1,$AD$26-1))) -> 4051343169 | AF48: =DTR!AA$216 -> 4079461212 | AG48: =DTR!AB$216 -> 3772730095 | AH48: =DTR!AC$216 -> 3815553479 | AI48: =DTR!AD$216 -> 4321000559 | AJ48: =DTR!AE$216 -> 4083134231 | AK48: =DTR!AF$216 -> 5024152177 | AL48: =DTR!AG$216 -> 4874545466 | AM48: =DTR!AH$216 -> 4879100238 | ... AQ48: =DTR!AL$216 -> 4.9147002e+09 | AR48: =SUM(OFFSET(AF48:AQ48,0,0,1,$AR$26)) -> 20071879576 | AS48: =IF($AR$26=1,AF48,SUM(OFFSET(AF48:AQ48,0,0,1,$AR$26))-SUM(OFFSET(AF48:AQ48,0,0,1,$AR$26-1))) -> 4083134231
A49: P13 | B49: DTR | C49: Chi phí nhân sự | D49: Employee welfare (FOH) | E49: =DTR!C217 -> 911307115 | F49: =DTR!D217 -> 1033542982 | G49: =DTR!E217 -> 848336770 | H49: =DTR!F217 -> 1031003534 | I49: =DTR!G217 -> 1063533369 | J49: =DTR!H217 -> 973190576 | K49: =DTR!I217 -> 1014630936 | L49: =DTR!J217 -> 959100838 | ... P49: =DTR!N217 -> 1148303858 | Q49: =SUM(OFFSET(E49:P49,0,0,1,$AD$26)) -> 4887723770 | R49: =DTR!O217 -> 1410836444 | S49: =DTR!P217 -> 1399090851 | T49: =DTR!Q217 -> 1131053888 | U49: =DTR!R217 -> 1267920577 | V49: =DTR!S217 -> 1265039349 | W49: =DTR!T217 -> 1227820821 | X49: =DTR!U217 -> 1280940063 | Y49: =DTR!V217 -> 1361210881 | ... AC49: =DTR!Z217 -> 1304400970 | AD49: =SUM(OFFSET(R49:AC49,0,0,1,$AD$26)) -> 6473941109 | AE49: =IF($AD$26=1,R49,SUM(OFFSET(R49:AC49,0,0,1,$AD$26))-SUM(OFFSET(R49:AC49,0,0,1,$AD$26-1))) -> 1265039349 | AF49: =DTR!AA$217 -> 1426956545 | AG49: =DTR!AB$217 -> 1161357165 | AH49: =DTR!AC$217 -> 1239376171 | AI49: =DTR!AD$217 -> 1265702203 | AJ49: =DTR!AE$217 -> 1357271039 | AK49: =DTR!AF$217 -> 9.9155907e+08 | AL49: =DTR!AG$217 -> 9.6435026e+08 | AM49: =DTR!AH$217 -> 9.4195225e+08 | ... AQ49: =DTR!AL$217 -> 9.8362835e+08 | AR49: =SUM(OFFSET(AF49:AQ49,0,0,1,$AR$26)) -> 6450663123 | AS49: =IF($AR$26=1,AF49,SUM(OFFSET(AF49:AQ49,0,0,1,$AR$26))-SUM(OFFSET(AF49:AQ49,0,0,1,$AR$26-1))) -> 1357271039
A50: P14 | B50: DTR | C50: Định phí hoạt động | D50: Repairs and maintanance | E50: =DTR!C218 -> 460529842 | F50: =DTR!D218 -> 434571553 | G50: =DTR!E218 -> 544088110 | H50: =DTR!F218 -> 510521295 | I50: =DTR!G218 -> 642495196 | J50: =DTR!H218 -> 690234002 | K50: =DTR!I218 -> 410469104 | L50: =DTR!J218 -> 569152145 | ... P50: =DTR!N218 -> 939137701 | Q50: =SUM(OFFSET(E50:P50,0,0,1,$AD$26)) -> 2592205996 | R50: =DTR!O218 -> 734659695 | S50: =DTR!P218 -> 631468372 | T50: =DTR!Q218 -> 695561422 | U50: =DTR!R218 -> 743147515 | V50: =DTR!S218 -> 753334254 | W50: =DTR!T218 -> 977482432 | X50: =DTR!U218 -> 1028204484 | Y50: =DTR!V218 -> 944206342 | ... AC50: =DTR!Z218 -> 759303904 | AD50: =SUM(OFFSET(R50:AC50,0,0,1,$AD$26)) -> 3558171258 | AE50: =IF($AD$26=1,R50,SUM(OFFSET(R50:AC50,0,0,1,$AD$26))-SUM(OFFSET(R50:AC50,0,0,1,$AD$26-1))) -> 753334254 | AF50: =DTR!AA$218 -> 675532018 | AG50: =DTR!AB$218 -> 427508026 | AH50: =DTR!AC$218 -> 594679880 | AI50: =DTR!AD$218 -> 684234657 | AJ50: =DTR!AE$218 -> 776152179 | AK50: =DTR!AF$218 -> 1.3427655e+09 | AL50: =DTR!AG$218 -> 1.1694359e+09 | AM50: =DTR!AH$218 -> 1.1717805e+09 | ... AQ50: =DTR!AL$218 -> 1.2729463e+09 | AR50: =SUM(OFFSET(AF50:AQ50,0,0,1,$AR$26)) -> 3158106760 | AS50: =IF($AR$26=1,AF50,SUM(OFFSET(AF50:AQ50,0,0,1,$AR$26))-SUM(OFFSET(AF50:AQ50,0,0,1,$AR$26-1))) -> 776152179
A51: P15 | B51: DTR | C51: Định phí hoạt động | D51: Factory expenses | E51: =DTR!C219 -> 3894354715 | F51: =DTR!D219 -> 3652447665 | G51: =DTR!E219 -> 10039240901 | H51: =DTR!F219 -> 8812805553 | I51: =DTR!G219 -> 8812804558 | J51: =DTR!H219 -> 8371551826 | K51: =DTR!I219 -> 7720780123 | L51: =DTR!J219 -> 8071776355 | ... P51: =DTR!N219 -> 4107851153 | Q51: =SUM(OFFSET(E51:P51,0,0,1,$AD$26)) -> 35211653392 | R51: =DTR!O219 -> 6967902702 | S51: =DTR!P219 -> 7268983233 | T51: =DTR!Q219 -> 7432302750 | U51: =DTR!R219 -> 7711233616 | V51: =DTR!S219 -> 7346014335 | W51: =DTR!T219 -> 7576020330 | X51: =DTR!U219 -> 7255934279 | Y51: =DTR!V219 -> 7718888264 | ... AC51: =DTR!Z219 -> 7190954710 | AD51: =SUM(OFFSET(R51:AC51,0,0,1,$AD$26)) -> 36726436636 | AE51: =IF($AD$26=1,R51,SUM(OFFSET(R51:AC51,0,0,1,$AD$26))-SUM(OFFSET(R51:AC51,0,0,1,$AD$26-1))) -> 7346014335 | AF51: =DTR!AA$219 -> 8152127945 | AG51: =DTR!AB$219 -> 7520098945 | AH51: =DTR!AC$219 -> 8458447921 | AI51: =DTR!AD$219 -> 8501500743 | AJ51: =DTR!AE$219 -> 8532632034 | AK51: =DTR!AF$219 -> 7.7973088e+09 | AL51: =DTR!AG$219 -> 7.747614e+09 | AM51: =DTR!AH$219 -> 7.5371939e+09 | ... AQ51: =DTR!AL$219 -> 7.5478654e+09 | AR51: =SUM(OFFSET(AF51:AQ51,0,0,1,$AR$26)) -> 41164807588 | AS51: =IF($AR$26=1,AF51,SUM(OFFSET(AF51:AQ51,0,0,1,$AR$26))-SUM(OFFSET(AF51:AQ51,0,0,1,$AR$26-1))) -> 8532632034
A52: P16 | B52: DTR | C52: Chi phí khấu hao | D52: Depreciation (FOH) | E52: =DTR!C220 -> 5568667717 | F52: =DTR!D220 -> 5573546970 | G52: =DTR!E220 -> 2870749336 | H52: =DTR!F220 -> 2993181073 | I52: =DTR!G220 -> 3046414798 | J52: =DTR!H220 -> 3049589322 | K52: =DTR!I220 -> 3083645781 | L52: =DTR!J220 -> 3104579094 | ... P52: =DTR!N220 -> 3553075383 | Q52: =SUM(OFFSET(E52:P52,0,0,1,$AD$26)) -> 20052559894 | R52: =DTR!O220 -> 6282890506 | S52: =DTR!P220 -> 6284434951 | T52: =DTR!Q220 -> 6478465588 | U52: =DTR!R220 -> 6364572301 | V52: =DTR!S220 -> 6551231356 | W52: =DTR!T220 -> 7301286882 | X52: =DTR!U220 -> 8036503847 | Y52: =DTR!V220 -> 8029010438 | ... AC52: =DTR!Z220 -> 8348386906 | AD52: =SUM(OFFSET(R52:AC52,0,0,1,$AD$26)) -> 31961594702 | AE52: =IF($AD$26=1,R52,SUM(OFFSET(R52:AC52,0,0,1,$AD$26))-SUM(OFFSET(R52:AC52,0,0,1,$AD$26-1))) -> 6551231356 | AF52: =DTR!AA$220 -> 5561606002 | AG52: =DTR!AB$220 -> 5530647021 | AH52: =DTR!AC$220 -> 5553408317 | AI52: =DTR!AD$220 -> 5712976010 | AJ52: =DTR!AE$220 -> 5764064909 | AK52: =DTR!AF$220 -> 5.8830874e+09 | AL52: =DTR!AG$220 -> 5.8830874e+09 | AM52: =DTR!AH$220 -> 5.8830874e+09 | ... AQ52: =DTR!AL$220 -> 5.8953624e+09 | AR52: =SUM(OFFSET(AF52:AQ52,0,0,1,$AR$26)) -> 28122702259 | AS52: =IF($AR$26=1,AF52,SUM(OFFSET(AF52:AQ52,0,0,1,$AR$26))-SUM(OFFSET(AF52:AQ52,0,0,1,$AR$26-1))) -> 5764064909
A53: P17 | B53: DTR | D53: Other COGs | E53: =DTR!C222 -> 11008792358 | F53: =DTR!D222 -> 14091966230 | G53: =DTR!E222 -> 14967977208 | H53: =DTR!F222 -> 9793313487 | I53: =DTR!G222 -> 10326586768 | J53: =DTR!H222 -> 10046707984 | K53: =DTR!I222 -> 10237671622 | L53: =DTR!J222 -> 1.1454537e+10 | ... P53: =DTR!N222 -> -1.0075016e+11 | Q53: =SUM(OFFSET(E53:P53,0,0,1,$AD$26)) -> 60188636051 | R53: =DTR!O222 -> 1.1993138e+09 | S53: =DTR!P222 -> 3951106221 | T53: =DTR!Q222 -> 2477786130 | U53: =DTR!R222 -> 2672108313 | V53: =DTR!S222 -> 1930915150 | W53: =DTR!T222 -> -1.171662e+09 | X53: =DTR!U222 -> -632408976 | Y53: =DTR!V222 -> 2.4508384e+09 | ... AC53: =DTR!Z222 -> -1.4106509e+10 | AD53: =SUM(OFFSET(R53:AC53,0,0,1,$AD$26)) -> 1.223123e+10 | AE53: =IF($AD$26=1,R53,SUM(OFFSET(R53:AC53,0,0,1,$AD$26))-SUM(OFFSET(R53:AC53,0,0,1,$AD$26-1))) -> 1930915150 | AF53: =DTR!AA$222 -> 2.2690792e+09 | AG53: =DTR!AB$222 -> 1.3453055e+09 | AH53: =DTR!AC$222 -> 2.5572562e+09 | AI53: =DTR!AD$222 -> 4.5845299e+08 | AJ53: =DTR!AE$222 -> 3.0716767e+09 | AK53: =DTR!AF$222 -> 4.5798605e+08 | AL53: =DTR!AG$222 -> 4.5775838e+08 | AM53: =DTR!AH$222 -> 4.4636681e+08 | ... AQ53: =DTR!AL$222 -> 4.6631719e+08 | AR53: =SUM(OFFSET(AF53:AQ53,0,0,1,$AR$26)) -> 9.7017706e+09 | AS53: =IF($AR$26=1,AF53,SUM(OFFSET(AF53:AQ53,0,0,1,$AR$26))-SUM(OFFSET(AF53:AQ53,0,0,1,$AR$26-1))) -> 3.0716767e+09
A54: P18 | B54: DTR | C54: Biến phí sản xuất | D54: Processing cost | E54: =DTR!C221 -> 2408877200 | F54: =DTR!D221 -> 321736000 | G54: =DTR!E221 -> 407200000 | H54: =DTR!F221 -> 1027400000 | I54: =DTR!G221 -> 1296610000 | J54: =DTR!H221 -> 932027000 | K54: =DTR!I221 -> 1461251000 | L54: =DTR!J221 -> 1743703999 | ... P54: =DTR!N221 -> 1496105366 | Q54: =SUM(OFFSET(E54:P54,0,0,1,$AD$26)) -> 5461823200 | R54: =DTR!O221 -> 380467548 | S54: =DTR!P221 -> 1845315600 | T54: =DTR!Q221 -> 1342787586 | U54: =DTR!R221 -> 843454000 | V54: =DTR!S221 -> 350000000 | W54: =DTR!T221 -> 510000000 | X54: =DTR!U221 -> 200000000 | Y54: =DTR!V221 -> 898330000 | ... AC54: =DTR!Z221 -> 930000000 | AD54: =SUM(OFFSET(R54:AC54,0,0,1,$AD$26)) -> 4762024734 | AE54: =IF($AD$26=1,R54,SUM(OFFSET(R54:AC54,0,0,1,$AD$26))-SUM(OFFSET(R54:AC54,0,0,1,$AD$26-1))) -> 350000000 | AF54: =DTR!AA$221 -> 0 | AG54: =DTR!AB$221 -> 0 | AH54: =DTR!AC$221 -> 44274073 | AI54: =DTR!AD$221 -> 176148628 | AJ54: =DTR!AE$221 -> 167431172 | AK54: =DTR!AF$221 -> 0 | AL54: =DTR!AG$221 -> 0 | AM54: =DTR!AH$221 -> 0 | ... AQ54: =DTR!AL$221 -> 0 | AR54: =SUM(OFFSET(AF54:AQ54,0,0,1,$AR$26)) -> 387853873 | AS54: =IF($AR$26=1,AF54,SUM(OFFSET(AF54:AQ54,0,0,1,$AR$26))-SUM(OFFSET(AF54:AQ54,0,0,1,$AR$26-1))) -> 167431172
A55: P19 | B55: DTR | D55: COGs in inventory | E55: =DTR!C223 -> -8.362366e+09 | F55: =DTR!D223 -> -9450050373 | G55: =DTR!E223 -> -8.0895041e+09 | H55: =DTR!F223 -> -8.4324273e+09 | I55: =DTR!G223 -> -5.6825189e+09 | J55: =DTR!H223 -> -10966084437 | K55: =DTR!I223 -> -1.1850904e+10 | L55: =DTR!J223 -> 10050172869 | ... P55: =DTR!N223 -> -2.8450087e+09 | Q55: =SUM(OFFSET(E55:P55,0,0,1,$AD$26)) -> -4.0016867e+10 | R55: =DTR!O223 -> 1.6898378e+09 | S55: =DTR!P223 -> 9.4959809e+09 | T55: =DTR!Q223 -> 1.3019973e+09 | U55: =DTR!R223 -> -2.7219297e+09 | V55: =DTR!S223 -> 5.5621436e+08 | W55: =DTR!T223 -> -3.0950172e+09 | X55: =DTR!U223 -> 5.9157376e+08 | Y55: =DTR!V223 -> 4.7417162e+09 | ... AC55: =DTR!Z223 -> -3.5365997e+09 | AD55: =SUM(OFFSET(R55:AC55,0,0,1,$AD$26)) -> 1.0322101e+10 | AE55: =IF($AD$26=1,R55,SUM(OFFSET(R55:AC55,0,0,1,$AD$26))-SUM(OFFSET(R55:AC55,0,0,1,$AD$26-1))) -> 5.5621436e+08 | AF55: =DTR!AA$223 -> 3.5438733e+09 | AG55: =DTR!AB$223 -> 5.6010355e+09 | AH55: =DTR!AC$223 -> 1.5925976e+10 | AI55: =DTR!AD$223 -> 9.5281123e+09 | AJ55: =DTR!AE$223 -> 4.6200101e+09 | AK55: =DTR!AF$223 -> 1.1002302e+10 | AL55: =DTR!AG$223 -> 1.1069536e+10 | AM55: =DTR!AH$223 -> 1.0797342e+10 | ... AQ55: =DTR!AL$223 -> 1.0821711e+10 | AR55: =SUM(OFFSET(AF55:AQ55,0,0,1,$AR$26)) -> 3.9219008e+10 | AS55: =IF($AR$26=1,AF55,SUM(OFFSET(AF55:AQ55,0,0,1,$AR$26))-SUM(OFFSET(AF55:AQ55,0,0,1,$AR$26-1))) -> 4.6200101e+09
A56: P20 | B56: DTR | D56: Gross Profit | E56: =DTR!C139 -> 10119851560 | F56: =DTR!D139 -> 191425380 | G56: =DTR!E139 -> 5285130826 | H56: =DTR!F139 -> 12013498032 | I56: =DTR!G139 -> 3156769708 | J56: =DTR!H139 -> -1702441870 | K56: =DTR!I139 -> -4766532065 | L56: =DTR!J139 -> 6057054340 | ... P56: =DTR!N139 -> 128968857470 | Q56: =SUM(OFFSET(E56:P56,0,0,1,$AD$26)) -> 30766675506 | R56: =DTR!O139 -> 18163062466 | S56: =DTR!P139 -> 33428829554 | T56: =DTR!Q139 -> 20744016857 | U56: =DTR!R139 -> 15787841704 | V56: =DTR!S139 -> 22161064744 | W56: =DTR!T139 -> 13671023177 | X56: =DTR!U139 -> 9317564878 | Y56: =DTR!V139 -> 13340810740 | ... AC56: =DTR!Z139 -> 29449792916 | AD56: =SUM(OFFSET(R56:AC56,0,0,1,$AD$26)) -> 110284815325 | AE56: =IF($AD$26=1,R56,SUM(OFFSET(R56:AC56,0,0,1,$AD$26))-SUM(OFFSET(R56:AC56,0,0,1,$AD$26-1))) -> 22161064744 | AF56: =DTR!AA$139 -> 11018924052 | AG56: =DTR!AB$139 -> 6155334899 | AH56: =DTR!AC$139 -> 7461082664 | AI56: =DTR!AD$139 -> 17970851610 | AJ56: =DTR!AE$139 -> 22185276979 | AK56: =DTR!AF$139 -> 0 | AL56: =DTR!AG$139 -> 0 | AM56: =DTR!AH$139 -> 0 | ... AQ56: =DTR!AL$139 -> 0 | AR56: =SUM(OFFSET(AF56:AQ56,0,0,1,$AR$26)) -> 64791470204 | AS56: =IF($AR$26=1,AF56,SUM(OFFSET(AF56:AQ56,0,0,1,$AR$26))-SUM(OFFSET(AF56:AQ56,0,0,1,$AR$26-1))) -> 22185276979
A57: P21 | B57: DTR | D57: SG&A (MKT&ADM) expenses | E57: =SUM(DTR!C144:C145) -> 8087596830 | F57: =SUM(DTR!D144:D145) -> 5867437075 | G57: =SUM(DTR!E144:E145) -> 8553853349 | H57: =SUM(DTR!F144:F145) -> 9717948043 | I57: =SUM(DTR!G144:G145) -> 7359417541 | J57: =SUM(DTR!H144:H145) -> 7878264395 | K57: =SUM(DTR!I144:I145) -> 7540006644 | L57: =SUM(DTR!J144:J145) -> 14270625142 | ... P57: =SUM(DTR!N144:N145) -> 16100235918 | Q57: =SUM(OFFSET(E57:P57,0,0,1,$AD$26)) -> 39586252838 | R57: =SUM(DTR!O144:O145) -> 11645293419 | S57: =SUM(DTR!P144:P145) -> 13327216998 | T57: =SUM(DTR!Q144:Q145) -> 12424129710 | U57: =SUM(DTR!R144:R145) -> 11233030058 | V57: =SUM(DTR!S144:S145) -> 12635231248 | W57: =SUM(DTR!T144:T145) -> 12518377756 | X57: =SUM(DTR!U144:U145) -> 11066425605 | Y57: =SUM(DTR!V144:V145) -> 12880688905 | ... AC57: =SUM(DTR!Z144:Z145) -> 20099119553 | AD57: =SUM(OFFSET(R57:AC57,0,0,1,$AD$26)) -> 61264901433 | AE57: =IF($AD$26=1,R57,SUM(OFFSET(R57:AC57,0,0,1,$AD$26))-SUM(OFFSET(R57:AC57,0,0,1,$AD$26-1))) -> 12635231248 | AF57: =SUM(DTR!AA$144:AA$145) -> 12125928642 | AG57: =SUM(DTR!AB$144:AB$145) -> 11162039668 | AH57: =SUM(DTR!AC$144:AC$145) -> 13575506377 | AI57: =SUM(DTR!AD$144:AD$145) -> 13970261268 | AJ57: =SUM(DTR!AE$144:AE$145) -> 13926607565 | AK57: =SUM(DTR!AF$144:AF$145) -> 0 | AL57: =SUM(DTR!AG$144:AG$145) -> 0 | AM57: =SUM(DTR!AH$144:AH$145) -> 0 | ... AQ57: =SUM(DTR!AL$144:AL$145) -> 0 | AR57: =SUM(OFFSET(AF57:AQ57,0,0,1,$AR$26)) -> 64760343520 | AS57: =IF($AR$26=1,AF57,SUM(OFFSET(AF57:AQ57,0,0,1,$AR$26))-SUM(OFFSET(AF57:AQ57,0,0,1,$AR$26-1))) -> 13926607565
A58: P22 | B58: DTR | C58: Chi phí nhân sự | D58: Salary | E58: =DTR!C236+DTR!C245 -> 3051657559 | F58: =DTR!D236+DTR!D245 -> 2803049266 | G58: =DTR!E236+DTR!E245 -> 3196348082 | H58: =DTR!F236+DTR!F245 -> 3325101040 | I58: =DTR!G236+DTR!G245 -> 3188436047 | J58: =DTR!H236+DTR!H245 -> 3172300108 | K58: =DTR!I236+DTR!I245 -> 3284593032 | L58: =DTR!J236+DTR!J245 -> 3274228001 | ... P58: =DTR!N236+DTR!N245 -> 4027620555 | Q58: =SUM(OFFSET(E58:P58,0,0,1,$AD$26)) -> 15564591994 | R58: =DTR!O236+DTR!O245 -> 4047329643 | S58: =DTR!P236+DTR!P245 -> 4084237593 | T58: =DTR!Q236+DTR!Q245 -> 4017063162 | U58: =DTR!R236+DTR!R245 -> 4463411607 | V58: =DTR!S236+DTR!S245 -> 4496386434 | W58: =DTR!T236+DTR!T245 -> 4693377748 | X58: =DTR!U236+DTR!U245 -> 4366364011 | Y58: =DTR!V236+DTR!V245 -> 4898958153 | ... AC58: =DTR!Z236+DTR!Z245 -> 7123521172 | AD58: =SUM(OFFSET(R58:AC58,0,0,1,$AD$26)) -> 21108428439 | AE58: =IF($AD$26=1,R58,SUM(OFFSET(R58:AC58,0,0,1,$AD$26))-SUM(OFFSET(R58:AC58,0,0,1,$AD$26-1))) -> 4496386434 | AF58: =DTR!AA$236+DTR!AA$245 -> 4970697671 | AG58: =DTR!AB$236+DTR!AB$245 -> 4694850341 | AH58: =DTR!AC$236+DTR!AC$245 -> 5059466631 | AI58: =DTR!AD$236+DTR!AD$245 -> 5463430612 | AJ58: =DTR!AE$236+DTR!AE$245 -> 4969298326 | AK58: =DTR!AF$236+DTR!AF$245 -> 4.7035453e+09 | AL58: =DTR!AG$236+DTR!AG$245 -> 4580904075 | AM58: =DTR!AH$236+DTR!AH$245 -> 4611154203 | ... AQ58: =DTR!AL$236+DTR!AL$245 -> 4703654203 | AR58: =SUM(OFFSET(AF58:AQ58,0,0,1,$AR$26)) -> 25157743581 | AS58: =IF($AR$26=1,AF58,SUM(OFFSET(AF58:AQ58,0,0,1,$AR$26))-SUM(OFFSET(AF58:AQ58,0,0,1,$AR$26-1))) -> 4969298326
A59: P23 | B59: DTR | C59: Chi phí nhân sự | D59: Employee welfare | E59: =DTR!C237+DTR!C246 -> 705680925 | F59: =DTR!D237+DTR!D246 -> 647258409 | G59: =DTR!E237+DTR!E246 -> 702219275 | H59: =DTR!F237+DTR!F246 -> 676557262 | I59: =DTR!G237+DTR!G246 -> 780776521 | J59: =DTR!H237+DTR!H246 -> 749978781 | K59: =DTR!I237+DTR!I246 -> 930683132 | L59: =DTR!J237+DTR!J246 -> 713495994 | ... P59: =DTR!N237+DTR!N246 -> 1273554022 | Q59: =SUM(OFFSET(E59:P59,0,0,1,$AD$26)) -> 3512492392 | R59: =DTR!O237+DTR!O246 -> 816227226 | S59: =DTR!P237+DTR!P246 -> 952365785 | T59: =DTR!Q237+DTR!Q246 -> 1168343229 | U59: =DTR!R237+DTR!R246 -> 1308752860 | V59: =DTR!S237+DTR!S246 -> 1134667631 | W59: =DTR!T237+DTR!T246 -> 1135273961 | X59: =DTR!U237+DTR!U246 -> 1122021125 | Y59: =DTR!V237+DTR!V246 -> 1243258635 | ... AC59: =DTR!Z237+DTR!Z246 -> 4450487060 | AD59: =SUM(OFFSET(R59:AC59,0,0,1,$AD$26)) -> 5380356731 | AE59: =IF($AD$26=1,R59,SUM(OFFSET(R59:AC59,0,0,1,$AD$26))-SUM(OFFSET(R59:AC59,0,0,1,$AD$26-1))) -> 1134667631 | AF59: =DTR!AA$237+DTR!AA$246 -> 1260382388 | AG59: =DTR!AB$237+DTR!AB$246 -> 1177587929 | AH59: =DTR!AC$237+DTR!AC$246 -> 1312365712 | AI59: =DTR!AD$237+DTR!AD$246 -> 1579566875 | AJ59: =DTR!AE$237+DTR!AE$246 -> 1494821509 | AK59: =DTR!AF$237+DTR!AF$246 -> 2.3049046e+09 | AL59: =DTR!AG$237+DTR!AG$246 -> 3.0910823e+09 | AM59: =DTR!AH$237+DTR!AH$246 -> 3.2345222e+09 | ... AQ59: =DTR!AL$237+DTR!AL$246 -> 5.174564e+09 | AR59: =SUM(OFFSET(AF59:AQ59,0,0,1,$AR$26)) -> 6824724413 | AS59: =IF($AR$26=1,AF59,SUM(OFFSET(AF59:AQ59,0,0,1,$AR$26))-SUM(OFFSET(AF59:AQ59,0,0,1,$AR$26-1))) -> 1494821509
A60: P24 | B60: DTR | C60: Biến phí bán hàng | D60: Commission expenses | E60: =DTR!C238 -> 339423744 | F60: =DTR!D238 -> 271418400 | G60: =DTR!E238 -> 484682880 | H60: =DTR!F238 -> 947585288 | I60: =DTR!G238 -> 732250680 | J60: =DTR!H238 -> 1259908312 | K60: =DTR!I238 -> 706508840 | L60: =DTR!J238 -> 1228570570 | ... P60: =DTR!N238 -> 1203477272 | Q60: =SUM(OFFSET(E60:P60,0,0,1,$AD$26)) -> 2775360992 | R60: =DTR!O238 -> 1156648724 | S60: =DTR!P238 -> 1395989840 | T60: =DTR!Q238 -> 718938840 | U60: =DTR!R238 -> 873725670 | V60: =DTR!S238 -> 801811330 | W60: =DTR!T238 -> 2343197427 | X60: =DTR!U238 -> 962161347 | Y60: =DTR!V238 -> 1102469718 | ... AC60: =DTR!Z238 -> 914940436 | AD60: =SUM(OFFSET(R60:AC60,0,0,1,$AD$26)) -> 4947114404 | AE60: =IF($AD$26=1,R60,SUM(OFFSET(R60:AC60,0,0,1,$AD$26))-SUM(OFFSET(R60:AC60,0,0,1,$AD$26-1))) -> 801811330 | AF60: =DTR!AA$238 -> 1284224102 | AG60: =DTR!AB$238 -> 828225273 | AH60: =DTR!AC$238 -> 2221270799 | AI60: =DTR!AD$238 -> 2175577325 | AJ60: =DTR!AE$238 -> 2044593710 | AK60: =DTR!AF$238 -> 552369180 | AL60: =DTR!AG$238 -> 581519180 | AM60: =DTR!AH$238 -> 552369180 | ... AQ60: =DTR!AL$238 -> 556042080 | AR60: =SUM(OFFSET(AF60:AQ60,0,0,1,$AR$26)) -> 8553891209 | AS60: =IF($AR$26=1,AF60,SUM(OFFSET(AF60:AQ60,0,0,1,$AR$26))-SUM(OFFSET(AF60:AQ60,0,0,1,$AR$26-1))) -> 2044593710
A61: P25 | B61: DTR | C61: Biến phí bán hàng | D61: Domestic Freight | E61: =DTR!C239 -> 176869000 | F61: =DTR!D239 -> 98405100 | G61: =DTR!E239 -> 109040000 | H61: =DTR!F239 -> 105874074 | I61: =DTR!G239 -> 68080000 | J61: =DTR!H239 -> 196593648 | K61: =DTR!I239 -> 93037900 | L61: =DTR!J239 -> 632197036 | ... P61: =DTR!N239 -> 478477333 | Q61: =SUM(OFFSET(E61:P61,0,0,1,$AD$26)) -> 558268174 | R61: =DTR!O239 -> 249728148 | S61: =DTR!P239 -> 500505186 | T61: =DTR!Q239 -> 292398814 | U61: =DTR!R239 -> 318375557 | V61: =DTR!S239 -> 269697036 | W61: =DTR!T239 -> 488977036 | X61: =DTR!U239 -> 351793707 | Y61: =DTR!V239 -> 1015741347 | ... AC61: =DTR!Z239 -> 543177912 | AD61: =SUM(OFFSET(R61:AC61,0,0,1,$AD$26)) -> 1630704741 | AE61: =IF($AD$26=1,R61,SUM(OFFSET(R61:AC61,0,0,1,$AD$26))-SUM(OFFSET(R61:AC61,0,0,1,$AD$26-1))) -> 269697036 | AF61: =DTR!AA$239 -> 345080148 | AG61: =DTR!AB$239 -> 240106741 | AH61: =DTR!AC$239 -> 556120832 | AI61: =DTR!AD$239 -> 814097700 | AJ61: =DTR!AE$239 -> 580228250 | AK61: =DTR!AF$239 -> 2.3017816e+08 | AL61: =DTR!AG$239 -> 1.8177816e+08 | AM61: =DTR!AH$239 -> 2.3017816e+08 | ... AQ61: =DTR!AL$239 -> 1.8507816e+08 | AR61: =SUM(OFFSET(AF61:AQ61,0,0,1,$AR$26)) -> 2535633671 | AS61: =IF($AR$26=1,AF61,SUM(OFFSET(AF61:AQ61,0,0,1,$AR$26))-SUM(OFFSET(AF61:AQ61,0,0,1,$AR$26-1))) -> 580228250
A62: P26 | B62: DTR | C62: Biến phí bán hàng | D62: Export Freight | E62: =DTR!C240 -> 1862640439 | F62: =DTR!D240 -> 439812589 | G62: =DTR!E240 -> 2669034839 | H62: =DTR!F240 -> 3032304136 | I62: =DTR!G240 -> 277880434 | J62: =DTR!H240 -> 318063920 | K62: =DTR!I240 -> 626032613 | L62: =DTR!J240 -> 5216793028 | ... P62: =DTR!N240 -> 1317844326 | Q62: =SUM(OFFSET(E62:P62,0,0,1,$AD$26)) -> 8281672437 | R62: =DTR!O240 -> 1442696903 | S62: =DTR!P240 -> 3574837862 | T62: =DTR!Q240 -> 1969857757 | U62: =DTR!R240 -> 1503984454 | V62: =DTR!S240 -> 2462711733 | W62: =DTR!T240 -> 1186353811 | X62: =DTR!U240 -> 1311037332 | Y62: =DTR!V240 -> 1643007682 | ... AC62: =DTR!Z240 -> 692122387 | AD62: =SUM(OFFSET(R62:AC62,0,0,1,$AD$26)) -> 10954088709 | AE62: =IF($AD$26=1,R62,SUM(OFFSET(R62:AC62,0,0,1,$AD$26))-SUM(OFFSET(R62:AC62,0,0,1,$AD$26-1))) -> 2462711733 | AF62: =DTR!AA$240 -> 1092685189 | AG62: =DTR!AB$240 -> 1193026840 | AH62: =DTR!AC$240 -> 1805602205 | AI62: =DTR!AD$240 -> 1237377546 | AJ62: =DTR!AE$240 -> 1647931878 | AK62: =DTR!AF$240 -> 2.9465591e+09 | AL62: =DTR!AG$240 -> 2.5568115e+09 | AM62: =DTR!AH$240 -> 2.3480445e+09 | ... AQ62: =DTR!AL$240 -> 2.8695645e+09 | AR62: =SUM(OFFSET(AF62:AQ62,0,0,1,$AR$26)) -> 6976623658 | AS62: =IF($AR$26=1,AF62,SUM(OFFSET(AF62:AQ62,0,0,1,$AR$26))-SUM(OFFSET(AF62:AQ62,0,0,1,$AR$26-1))) -> 1647931878
A63: P27 | B63: DTR | C63: Chi phí khấu hao | D63: Depreciation | E63: =DTR!C241+DTR!C247 -> 164126749 | F63: =DTR!D241+DTR!D247 -> 164126749 | G63: =DTR!E241+DTR!E247 -> 159675084 | H63: =DTR!F241+DTR!F247 -> 219288813 | I63: =DTR!G241+DTR!G247 -> 223754967 | J63: =DTR!H241+DTR!H247 -> 222296188 | K63: =DTR!I241+DTR!I247 -> 227426380 | L63: =DTR!J241+DTR!J247 -> 376548206 | ... P63: =DTR!N241+DTR!N247 -> 412558117 | Q63: =SUM(OFFSET(E63:P63,0,0,1,$AD$26)) -> 930972362 | R63: =DTR!O241+DTR!O247 -> 450497304 | S63: =DTR!P241+DTR!P247 -> 450497305 | T63: =DTR!Q241+DTR!Q247 -> 430210696 | U63: =DTR!R241+DTR!R247 -> 471665936 | V63: =DTR!S241+DTR!S247 -> 471665939 | W63: =DTR!T241+DTR!T247 -> 487765401 | X63: =DTR!U241+DTR!U247 -> 335324866 | Y63: =DTR!V241+DTR!V247 -> 343101730 | ... AC63: =DTR!Z241+DTR!Z247 -> 333721862 | AD63: =SUM(OFFSET(R63:AC63,0,0,1,$AD$26)) -> 2274537180 | AE63: =IF($AD$26=1,R63,SUM(OFFSET(R63:AC63,0,0,1,$AD$26))-SUM(OFFSET(R63:AC63,0,0,1,$AD$26-1))) -> 471665939 | AF63: =DTR!AA$241+DTR!AA$247 -> 89029510 | AG63: =DTR!AB$241+DTR!AB$247 -> 89028134 | AH63: =DTR!AC$241+DTR!AC$247 -> 81369908 | AI63: =DTR!AD$241+DTR!AD$247 -> 81652230 | AJ63: =DTR!AE$241+DTR!AE$247 -> 83579315 | AK63: =DTR!AF$241+DTR!AF$247 -> 84982320 | AL63: =DTR!AG$241+DTR!AG$247 -> 84982320 | AM63: =DTR!AH$241+DTR!AH$247 -> 84982320 | ... AQ63: =DTR!AL$241+DTR!AL$247 -> 97801753 | AR63: =SUM(OFFSET(AF63:AQ63,0,0,1,$AR$26)) -> 424659097 | AS63: =IF($AR$26=1,AF63,SUM(OFFSET(AF63:AQ63,0,0,1,$AR$26))-SUM(OFFSET(AF63:AQ63,0,0,1,$AR$26-1))) -> 83579315
A64: P28 | B64: DTR | C64: Định phí hoạt động | D64: Controllable expenses | E64: =DTR!C242+DTR!C248 -> 1787198414 | F64: =DTR!D242+DTR!D248 -> 1443366562 | G64: =DTR!E242+DTR!E248 -> 1232853189 | H64: =DTR!F242+DTR!F248 -> 1411237430 | I64: =DTR!G242+DTR!G248 -> 2088238892 | J64: =DTR!H242+DTR!H248 -> 1959123438 | K64: =DTR!I242+DTR!I248 -> 1671724747 | L64: =DTR!J242+DTR!J248 -> 2828792307 | ... P64: =DTR!N242+DTR!N248 -> 7386704293 | Q64: =SUM(OFFSET(E64:P64,0,0,1,$AD$26)) -> 7962894487 | R64: =DTR!O242+DTR!O248 -> 3482165471 | S64: =DTR!P242+DTR!P248 -> 2368783427 | T64: =DTR!Q242+DTR!Q248 -> 3827317212 | U64: =DTR!R242+DTR!R248 -> 2293113974 | V64: =DTR!S242+DTR!S248 -> 2998291145 | W64: =DTR!T242+DTR!T248 -> 2183432372 | X64: =DTR!U242+DTR!U248 -> 2617723217 | Y64: =DTR!V242+DTR!V248 -> 2634151640 | ... AC64: =DTR!Z242+DTR!Z248 -> 6041148724 | AD64: =SUM(OFFSET(R64:AC64,0,0,1,$AD$26)) -> 14969671229 | AE64: =IF($AD$26=1,R64,SUM(OFFSET(R64:AC64,0,0,1,$AD$26))-SUM(OFFSET(R64:AC64,0,0,1,$AD$26-1))) -> 2998291145 | AF64: =DTR!AA$242+DTR!AA$248 -> 3083829634 | AG64: =DTR!AB$242+DTR!AB$248 -> 2939214410 | AH64: =DTR!AC$242+DTR!AC$248 -> 2539310290 | AI64: =DTR!AD$242+DTR!AD$248 -> 2618558980 | AJ64: =DTR!AE$242+DTR!AE$248 -> 3106154577 | AK64: =DTR!AF$242+DTR!AF$248 -> 2.2696419e+09 | AL64: =DTR!AG$242+DTR!AG$248 -> 1.9153313e+09 | AM64: =DTR!AH$242+DTR!AH$248 -> 2.0089703e+09 | ... AQ64: =DTR!AL$242+DTR!AL$248 -> 2.1085589e+09 | AR64: =SUM(OFFSET(AF64:AQ64,0,0,1,$AR$26)) -> 14287067891 | AS64: =IF($AR$26=1,AF64,SUM(OFFSET(AF64:AQ64,0,0,1,$AR$26))-SUM(OFFSET(AF64:AQ64,0,0,1,$AR$26-1))) -> 3106154577
A65: P29 | B65: DTR | D65: Financial Expense | E65: =DTR!C142 -> 801399604 | F65: =DTR!D142 -> 695500231 | G65: =DTR!E142 -> 663502461 | H65: =DTR!F142 -> 1555671370 | I65: =DTR!G142 -> 936492932 | J65: =DTR!H142 -> 1103852896 | K65: =DTR!I142 -> 1608708972 | L65: =DTR!J142 -> 1489581015 | ... P65: =DTR!N142 -> 993026233 | Q65: =SUM(OFFSET(E65:P65,0,0,1,$AD$26)) -> 4652566598 | R65: =DTR!O142 -> 1529745602 | S65: =DTR!P142 -> 1349010483 | T65: =DTR!Q142 -> 902730488 | U65: =DTR!R142 -> 1450570894 | V65: =DTR!S142 -> 858169737 | W65: =DTR!T142 -> 1483876982 | X65: =DTR!U142 -> 1315247967 | Y65: =DTR!V142 -> 1366041150 | ... AC65: =DTR!Z142 -> 2479436989 | AD65: =SUM(OFFSET(R65:AC65,0,0,1,$AD$26)) -> 6090227204 | AE65: =IF($AD$26=1,R65,SUM(OFFSET(R65:AC65,0,0,1,$AD$26))-SUM(OFFSET(R65:AC65,0,0,1,$AD$26-1))) -> 858169737 | AF65: =DTR!AA$142 -> 1532817392 | AG65: =DTR!AB$142 -> 1569283837 | AH65: =DTR!AC$142 -> 1510605035 | AI65: =DTR!AD$142 -> 1998884061 | AJ65: =DTR!AE$142 -> 1208736058 | AK65: =DTR!AF$142 -> 0 | AL65: =DTR!AG$142 -> 0 | AM65: =DTR!AH$142 -> 0 | ... AQ65: =DTR!AL$142 -> 0 | AR65: =SUM(OFFSET(AF65:AQ65,0,0,1,$AR$26)) -> 7820326383 | AS65: =IF($AR$26=1,AF65,SUM(OFFSET(AF65:AQ65,0,0,1,$AR$26))-SUM(OFFSET(AF65:AQ65,0,0,1,$AR$26-1))) -> 1208736058
A66: P30 | B66: DTR | C66: Chi phí lãi vay | D66: Interest expense | E66: =DTR!C143 -> 460461775 | F66: =DTR!D143 -> 563909516 | G66: =DTR!E143 -> 587315920 | H66: =DTR!F143 -> 905708142 | I66: =DTR!G143 -> 974310029 | J66: =DTR!H143 -> 1115056080 | K66: =DTR!I143 -> 1160823006 | L66: =DTR!J143 -> 939585045 | ... P66: =DTR!N143 -> 1032562923 | Q66: =SUM(OFFSET(E66:P66,0,0,1,$AD$26)) -> 3491705382 | R66: =DTR!O143 -> 1114824276 | S66: =DTR!P143 -> 928379281 | T66: =DTR!Q143 -> 673966789 | U66: =DTR!R143 -> 888393452 | V66: =DTR!S143 -> 1186588729 | W66: =DTR!T143 -> 1448899822 | X66: =DTR!U143 -> 1242023326 | Y66: =DTR!V143 -> 1303560910 | ... AC66: =DTR!Z143 -> 1256103396 | AD66: =SUM(OFFSET(R66:AC66,0,0,1,$AD$26)) -> 4792152527 | AE66: =IF($AD$26=1,R66,SUM(OFFSET(R66:AC66,0,0,1,$AD$26))-SUM(OFFSET(R66:AC66,0,0,1,$AD$26-1))) -> 1186588729 | AF66: =DTR!AA$143 -> 1240115065 | AG66: =DTR!AB$143 -> 1156279418 | AH66: =DTR!AC$143 -> 959718564 | AI66: =DTR!AD$143 -> 1062084475 | AJ66: =DTR!AE$143 -> 838836791 | AK66: =DTR!AF$143 -> 0 | AL66: =DTR!AG$143 -> 0 | AM66: =DTR!AH$143 -> 0 | ... AQ66: =DTR!AL$143 -> 0 | AR66: =SUM(OFFSET(AF66:AQ66,0,0,1,$AR$26)) -> 5257034313 | AS66: =IF($AR$26=1,AF66,SUM(OFFSET(AF66:AQ66,0,0,1,$AR$26))-SUM(OFFSET(AF66:AQ66,0,0,1,$AR$26-1))) -> 838836791
A67: P31 | B67: DTR | D67: Other Income | E67: =DTR!C141+DTR!C149 -> 694884487 | F67: =DTR!D141+DTR!D149 -> 1100863129 | G67: =DTR!E141+DTR!E149 -> 972915383 | H67: =DTR!F141+DTR!F149 -> 1735368121 | I67: =DTR!G141+DTR!G149 -> 985738425 | J67: =DTR!H141+DTR!H149 -> 469111094 | K67: =DTR!I141+DTR!I149 -> 390562188 | L67: =DTR!J141+DTR!J149 -> 1420203832 | ... P67: =DTR!N141+DTR!N149 -> -6471647725 | Q67: =SUM(OFFSET(E67:P67,0,0,1,$AD$26)) -> 5489769545 | R67: =DTR!O141+DTR!O149 -> 773247793 | S67: =DTR!P141+DTR!P149 -> 1660894436 | T67: =DTR!Q141+DTR!Q149 -> 933724587 | U67: =DTR!R141+DTR!R149 -> 1324036221 | V67: =DTR!S141+DTR!S149 -> 2544341304 | W67: =DTR!T141+DTR!T149 -> 1592997157 | X67: =DTR!U141+DTR!U149 -> 1272640211 | Y67: =DTR!V141+DTR!V149 -> 1203338648 | ... AC67: =DTR!Z141+DTR!Z149 -> -879564924 | AD67: =SUM(OFFSET(R67:AC67,0,0,1,$AD$26)) -> 7236244341 | AE67: =IF($AD$26=1,R67,SUM(OFFSET(R67:AC67,0,0,1,$AD$26))-SUM(OFFSET(R67:AC67,0,0,1,$AD$26-1))) -> 2544341304 | AF67: =DTR!AA$141+DTR!AA$149 -> 946361246 | AG67: =DTR!AB$141+DTR!AB$149 -> 156774868 | AH67: =DTR!AC$141+DTR!AC$149 -> 806561257 | AI67: =DTR!AD$141+DTR!AD$149 -> 1702047931 | AJ67: =DTR!AE$141+DTR!AE$149 -> 1131650562 | AK67: =DTR!AF$141+DTR!AF$149 -> 0 | AL67: =DTR!AG$141+DTR!AG$149 -> 0 | AM67: =DTR!AH$141+DTR!AH$149 -> 0 | ... AQ67: =DTR!AL$141+DTR!AL$149 -> 0 | AR67: =SUM(OFFSET(AF67:AQ67,0,0,1,$AR$26)) -> 4743395864 | AS67: =IF($AR$26=1,AF67,SUM(OFFSET(AF67:AQ67,0,0,1,$AR$26))-SUM(OFFSET(AF67:AQ67,0,0,1,$AR$26-1))) -> 1131650562
A68: P32 | B68: DTR | D68: EBITDA | E68: =DTR!C229 -> 5384680897 | F68: =DTR!D229 -> -1703380519 | G68: =DTR!E229 -> 626985252 | H68: =DTR!F229 -> 6561979281 | I68: =DTR!G229 -> 59631967 | J68: =DTR!H229 -> -5859951964 | K68: =DTR!I229 -> -9089366006 | L68: =DTR!J229 -> -4047933145 | ... P68: =DTR!N229 -> 110198971178 | Q68: =SUM(OFFSET(E68:P68,0,0,1,$AD$26)) -> 10929896878 | R68: =DTR!O229 -> 10679249682 | S68: =DTR!P229 -> 25146574404 | T68: =DTR!Q229 -> 13027482010 | U68: =DTR!R229 -> 9221866353 | V68: =DTR!S229 -> 16490448778 | W68: =DTR!T229 -> 6798133756 | X68: =DTR!U229 -> 3536012394 | Y68: =DTR!V229 -> 5693975403 | ... AC68: =DTR!Z229 -> 11690093189 | AD68: =SUM(OFFSET(R68:AC68,0,0,1,$AD$26)) -> 74565621227 | AE68: =IF($AD$26=1,R68,SUM(OFFSET(R68:AC68,0,0,1,$AD$26))-SUM(OFFSET(R68:AC68,0,0,1,$AD$26-1))) -> 16490448778 | AF68: =DTR!AA$229 -> 1680623174 | AG68: =DTR!AB$229 -> -3159925832 | AH68: =DTR!AC$229 -> -3740637369 | AI68: =DTR!AD$229 -> 7043800260 | AJ68: =DTR!AE$229 -> 11351398266 | AK68: =DTR!AF$229 -> 0 | AL68: =DTR!AG$229 -> 0 | AM68: =DTR!AH$229 -> 0 | ... AQ68: =DTR!AL$229 -> 0 | AR68: =SUM(OFFSET(AF68:AQ68,0,0,1,$AR$26)) -> 13175258499 | AS68: =IF($AR$26=1,AF68,SUM(OFFSET(AF68:AQ68,0,0,1,$AR$26))-SUM(OFFSET(AF68:AQ68,0,0,1,$AR$26-1))) -> 11351398266
A69: P33 | B69: DTR | D69: Profit before tax | E69: =DTR!C227 -> 1925739613 | F69: =DTR!D227 -> -5270648797 | G69: =DTR!E227 -> -2959309601 | H69: =DTR!F227 -> 2475246740 | I69: =DTR!G227 -> -4153402340 | J69: =DTR!H227 -> -10215448067 | K69: =DTR!I227 -> -13524685493 | L69: =DTR!J227 -> -8282947985 | ... P69: =DTR!N227 -> 105403947594 | Q69: =SUM(OFFSET(E69:P69,0,0,1,$AD$26)) -> -7982374385 | R69: =DTR!O227 -> 5761271238 | S69: =DTR!P227 -> 20413496509 | T69: =DTR!Q227 -> 8350881246 | U69: =DTR!R227 -> 4428276973 | V69: =DTR!S227 -> 11212005063 | W69: =DTR!T227 -> 1261765596 | X69: =DTR!U227 -> -1791468483 | Y69: =DTR!V227 -> 297419333 | ... AC69: =DTR!Z227 -> 5991671450 | AD69: =SUM(OFFSET(R69:AC69,0,0,1,$AD$26)) -> 50165931029 | AE69: =IF($AD$26=1,R69,SUM(OFFSET(R69:AC69,0,0,1,$AD$26))-SUM(OFFSET(R69:AC69,0,0,1,$AD$26-1))) -> 11212005063 | AF69: =DTR!AA$227 -> -1693460736 | AG69: =DTR!AB$227 -> -6419213738 | AH69: =DTR!AC$227 -> -6818467491 | AI69: =DTR!AD$227 -> 3703754212 | AJ69: =DTR!AE$227 -> 8181583918 | AK69: =DTR!AF$227 -> 0 | AL69: =DTR!AG$227 -> 0 | AM69: =DTR!AH$227 -> 0 | ... AQ69: =DTR!AL$227 -> 0 | AR69: =SUM(OFFSET(AF69:AQ69,0,0,1,$AR$26)) -> -3045803835 | AS69: =IF($AR$26=1,AF69,SUM(OFFSET(AF69:AQ69,0,0,1,$AR$26))-SUM(OFFSET(AF69:AQ69,0,0,1,$AR$26-1))) -> 8181583918
A70: P34 | B70: DTR | D70: CIT | E70: =DTR!C151+DTR!C152 -> 0 | F70: =DTR!D151+DTR!D152 -> 0 | G70: =DTR!E151+DTR!E152 -> 0 | H70: =DTR!F151+DTR!F152 -> 0 | I70: =DTR!G151+DTR!G152 -> 0 | J70: =DTR!H151+DTR!H152 -> 0 | K70: =DTR!I151+DTR!I152 -> 0 | L70: =DTR!J151+DTR!J152 -> 0 | ... P70: =DTR!N151+DTR!N152 -> 13334207765 | Q70: =SUM(OFFSET(E70:P70,0,0,1,$AD$26)) -> 0 | R70: =DTR!O151+DTR!O152 -> 864190686 | S70: =DTR!P151+DTR!P152 -> 3012699780 | T70: =DTR!Q151+DTR!Q152 -> 1252632187 | U70: =DTR!R151+DTR!R152 -> 677293488 | V70: =DTR!S151+DTR!S152 -> 1681800759 | W70: =DTR!T151+DTR!T152 -> 189264839 | X70: =DTR!U151+DTR!U152 -> -2830986340 | Y70: =DTR!V151+DTR!V152 -> 204199602 | ... AC70: =DTR!Z151+DTR!Z152 -> 3330158442 | AD70: =SUM(OFFSET(R70:AC70,0,0,1,$AD$26)) -> 7488616900 | AE70: =IF($AD$26=1,R70,SUM(OFFSET(R70:AC70,0,0,1,$AD$26))-SUM(OFFSET(R70:AC70,0,0,1,$AD$26-1))) -> 1681800759 | AF70: =DTR!AA$151+DTR!AA$152 -> 0 | AG70: =DTR!AB$151+DTR!AB$152 -> 0 | AH70: =DTR!AC$151+DTR!AC$152 -> -153060867 | AI70: =DTR!AD$151+DTR!AD$152 -> 0 | AJ70: =DTR!AE$151+DTR!AE$152 -> -45841499 | AK70: =DTR!AF$151+DTR!AF$152 -> 0 | AL70: =DTR!AG$151+DTR!AG$152 -> 0 | AM70: =DTR!AH$151+DTR!AH$152 -> 0 | ... AQ70: =DTR!AL$151+DTR!AL$152 -> 0 | AR70: =SUM(OFFSET(AF70:AQ70,0,0,1,$AR$26)) -> -198902366 | AS70: =IF($AR$26=1,AF70,SUM(OFFSET(AF70:AQ70,0,0,1,$AR$26))-SUM(OFFSET(AF70:AQ70,0,0,1,$AR$26-1))) -> -45841499
A71: P35 | B71: DTR | D71: Net profit | E71: =DTR!C233 -> 1925739613 | F71: =DTR!D233 -> -5270648797 | G71: =DTR!E233 -> -2959309601 | H71: =DTR!F233 -> 2475246740 | I71: =DTR!G233 -> -4153402340 | J71: =DTR!H233 -> -10215448067 | K71: =DTR!I233 -> -13524685493 | L71: =DTR!J233 -> -8282947985 | ... P71: =DTR!N233 -> 92069739829 | Q71: =SUM(OFFSET(E71:P71,0,0,1,$AD$26)) -> -7982374385 | R71: =DTR!O233 -> 4897080552 | S71: =DTR!P233 -> 17400796729 | T71: =DTR!Q233 -> 7098249059 | U71: =DTR!R233 -> 3750983485 | V71: =DTR!S233 -> 9530204304 | W71: =DTR!T233 -> 1072500757 | X71: =DTR!U233 -> 1039517857 | Y71: =DTR!V233 -> 93219731 | ... AC71: =DTR!Z233 -> 2661513008 | AD71: =SUM(OFFSET(R71:AC71,0,0,1,$AD$26)) -> 42677314129 | AE71: =IF($AD$26=1,R71,SUM(OFFSET(R71:AC71,0,0,1,$AD$26))-SUM(OFFSET(R71:AC71,0,0,1,$AD$26-1))) -> 9530204304 | AF71: =DTR!AA$233 -> -1693460736 | AG71: =DTR!AB$233 -> -6419213738 | AH71: =DTR!AC$233 -> -6665406624 | AI71: =DTR!AD$233 -> 3703754212 | AJ71: =DTR!AE$233 -> 8227425417 | AK71: =DTR!AF$233 -> 0 | AL71: =DTR!AG$233 -> 0 | AM71: =DTR!AH$233 -> 0 | ... AQ71: =DTR!AL$233 -> 0 | AR71: =SUM(OFFSET(AF71:AQ71,0,0,1,$AR$26)) -> -2846901469 | AS71: =IF($AR$26=1,AF71,SUM(OFFSET(AF71:AQ71,0,0,1,$AR$26))-SUM(OFFSET(AF71:AQ71,0,0,1,$AR$26-1))) -> 8227425417
A72: B01 | B72: DTR | D72: Current Assets | E72: =DTR!C6 -> 782481934423 | F72: =DTR!D6 -> 768590764263 | G72: =DTR!E6 -> 815465869041 | H72: =DTR!F6 -> 877414026420 | I72: =DTR!G6 -> 928155716736 | J72: =DTR!H6 -> 956563222023 | K72: =DTR!I6 -> 906133879099 | L72: =DTR!J6 -> 849218290026 | ... P72: =DTR!N6 -> 969587265880 | Q72: =IF($AD$26=1,E72,SUM(OFFSET(E72:P72,0,0,1,$AD$26))-SUM(OFFSET(E72:P72,0,0,1,$AD$26-1))) -> 928155716736 | R72: =DTR!O6 -> 894788032291 | S72: =DTR!P6 -> 814157821775 | T72: =DTR!Q6 -> 866303373135 | U72: =DTR!R6 -> 929599762285 | V72: =DTR!S6 -> 981599372849 | W72: =DTR!T6 -> 1010794698754 | X72: =DTR!U6 -> 999811801439 | Y72: =DTR!V6 -> 1060333071975 | ... AC72: =DTR!Z6 -> 945217150933 | AD72: =IF($AD$26=1,R72,SUM(OFFSET(R72:AC72,0,0,1,$AD$26))-SUM(OFFSET(R72:AC72,0,0,1,$AD$26-1))) -> 981599372849 | AE72: =IF($AD$26=1,R72,SUM(OFFSET(R72:AC72,0,0,1,$AD$26))-SUM(OFFSET(R72:AC72,0,0,1,$AD$26-1))) -> 981599372849 | AF72: =DTR!AA$6 -> 894150692345 | AG72: =DTR!AB$6 -> 895502322076 | AH72: =DTR!AC$6 -> 848468475952 | AI72: =DTR!AD$6 -> 807952336254 | AJ72: =DTR!AE$6 -> 886588369025 | AK72: =DTR!AF$6 -> 0 | AL72: =DTR!AG$6 -> 0 | AM72: =DTR!AH$6 -> 0 | ... AQ72: =DTR!AL$6 -> 0 | AR72: =IF($AR$26=1,AF72,SUM(OFFSET(AF72:AQ72,0,0,1,$AR$26))-SUM(OFFSET(AF72:AQ72,0,0,1,$AR$26-1))) -> 886588369025 | AS72: =IF($AR$26=1,AF72,SUM(OFFSET(AF72:AQ72,0,0,1,$AR$26))-SUM(OFFSET(AF72:AQ72,0,0,1,$AR$26-1))) -> 886588369025
A73: B02 | B73: DTR | D73: Cash | E73: =DTR!C7 -> 31037848308 | F73: =DTR!D7 -> 22669663716 | G73: =DTR!E7 -> 6664945115 | H73: =DTR!F7 -> 15574807889 | I73: =DTR!G7 -> 16007340290 | J73: =DTR!H7 -> 3678057757 | K73: =DTR!I7 -> 36916493026 | L73: =DTR!J7 -> 16748498285 | ... P73: =DTR!N7 -> 39805017284 | Q73: =IF($AD$26=1,E73,SUM(OFFSET(E73:P73,0,0,1,$AD$26))-SUM(OFFSET(E73:P73,0,0,1,$AD$26-1))) -> 16007340290 | R73: =DTR!O7 -> 76486895109 | S73: =DTR!P7 -> 33258200889 | T73: =DTR!Q7 -> 23555271373 | U73: =DTR!R7 -> 37590058839 | V73: =DTR!S7 -> 21868727527 | W73: =DTR!T7 -> 32470900772 | X73: =DTR!U7 -> 30661632458 | Y73: =DTR!V7 -> 29770776625 | ... AC73: =DTR!Z7 -> 36834893155 | AD73: =IF($AD$26=1,R73,SUM(OFFSET(R73:AC73,0,0,1,$AD$26))-SUM(OFFSET(R73:AC73,0,0,1,$AD$26-1))) -> 21868727527 | AE73: =IF($AD$26=1,R73,SUM(OFFSET(R73:AC73,0,0,1,$AD$26))-SUM(OFFSET(R73:AC73,0,0,1,$AD$26-1))) -> 21868727527 | AF73: =DTR!AA$7 -> 42126572011 | AG73: =DTR!AB$7 -> 45981412915 | AH73: =DTR!AC$7 -> 33613094972 | AI73: =DTR!AD$7 -> 47135211556 | AJ73: =DTR!AE$7 -> 41014004605 | AK73: =DTR!AF$7 -> 0 | AL73: =DTR!AG$7 -> 0 | AM73: =DTR!AH$7 -> 0 | ... AQ73: =DTR!AL$7 -> 0 | AR73: =IF($AR$26=1,AF73,SUM(OFFSET(AF73:AQ73,0,0,1,$AR$26))-SUM(OFFSET(AF73:AQ73,0,0,1,$AR$26-1))) -> 41014004605 | AS73: =IF($AR$26=1,AF73,SUM(OFFSET(AF73:AQ73,0,0,1,$AR$26))-SUM(OFFSET(AF73:AQ73,0,0,1,$AR$26-1))) -> 41014004605
A74: B03 | B74: DTR | D74: Financial Investment | E74: =DTR!C10 -> 2010000000 | F74: =DTR!D10 -> 2010000000 | G74: =DTR!E10 -> 2010000000 | H74: =DTR!F10 -> 2010000000 | I74: =DTR!G10 -> 2010000000 | J74: =DTR!H10 -> 2010000000 | K74: =DTR!I10 -> 2010000000 | L74: =DTR!J10 -> 2010000000 | ... P74: =DTR!N10 -> 2840000000 | Q74: =IF($AD$26=1,E74,SUM(OFFSET(E74:P74,0,0,1,$AD$26))-SUM(OFFSET(E74:P74,0,0,1,$AD$26-1))) -> 2010000000 | R74: =DTR!O10 -> 0 | S74: =DTR!P10 -> 0 | T74: =DTR!Q10 -> 22840000000 | U74: =DTR!R10 -> 22840000000 | V74: =DTR!S10 -> 22840000000 | W74: =DTR!T10 -> 22840000000 | X74: =DTR!U10 -> 22840000000 | Y74: =DTR!V10 -> 22840000000 | ... AC74: =DTR!Z10 -> 32840000000 | AD74: =IF($AD$26=1,R74,SUM(OFFSET(R74:AC74,0,0,1,$AD$26))-SUM(OFFSET(R74:AC74,0,0,1,$AD$26-1))) -> 22840000000 | AE74: =IF($AD$26=1,R74,SUM(OFFSET(R74:AC74,0,0,1,$AD$26))-SUM(OFFSET(R74:AC74,0,0,1,$AD$26-1))) -> 22840000000 | AF74: =DTR!AA$10 -> 32840000000 | AG74: =DTR!AB$10 -> 32840000000 | AH74: =DTR!AC$10 -> 32840000000 | AI74: =DTR!AD$10 -> 34340000000 | AJ74: =DTR!AE$10 -> 34340000000 | AK74: =DTR!AF$10 -> 0 | AL74: =DTR!AG$10 -> 0 | AM74: =DTR!AH$10 -> 0 | ... AQ74: =DTR!AL$10 -> 0 | AR74: =IF($AR$26=1,AF74,SUM(OFFSET(AF74:AQ74,0,0,1,$AR$26))-SUM(OFFSET(AF74:AQ74,0,0,1,$AR$26-1))) -> 34340000000 | AS74: =IF($AR$26=1,AF74,SUM(OFFSET(AF74:AQ74,0,0,1,$AR$26))-SUM(OFFSET(AF74:AQ74,0,0,1,$AR$26-1))) -> 34340000000
A75: B04 | B75: DTR | D75: Account receivables | E75: =DTR!C17 -> 294283662527 | F75: =DTR!D17 -> 277719968888 | G75: =DTR!E17 -> 297405577345 | H75: =DTR!F17 -> 303674749988 | I75: =DTR!G17 -> 304477407097 | J75: =DTR!H17 -> 308711681498 | K75: =DTR!I17 -> 200469936704 | L75: =DTR!J17 -> 222854636431 | ... P75: =DTR!N17 -> 292036709951 | Q75: =IF($AD$26=1,E75,SUM(OFFSET(E75:P75,0,0,1,$AD$26))-SUM(OFFSET(E75:P75,0,0,1,$AD$26-1))) -> 304477407097 | R75: =DTR!O17 -> 220033096514 | S75: =DTR!P17 -> 264758570553 | T75: =DTR!Q17 -> 314044742217 | U75: =DTR!R17 -> 300175012111 | V75: =DTR!S17 -> 355551041672 | W75: =DTR!T17 -> 347420810569 | X75: =DTR!U17 -> 326074813439 | Y75: =DTR!V17 -> 416521420158 | ... AC75: =DTR!Z17 -> 293560124180 | AD75: =IF($AD$26=1,R75,SUM(OFFSET(R75:AC75,0,0,1,$AD$26))-SUM(OFFSET(R75:AC75,0,0,1,$AD$26-1))) -> 355551041672 | AE75: =IF($AD$26=1,R75,SUM(OFFSET(R75:AC75,0,0,1,$AD$26))-SUM(OFFSET(R75:AC75,0,0,1,$AD$26-1))) -> 355551041672 | AF75: =DTR!AA$17 -> 263624916145 | AG75: =DTR!AB$17 -> 289980302579 | AH75: =DTR!AC$17 -> 331342767193 | AI75: =DTR!AD$17 -> 329741435832 | AJ75: =DTR!AE$17 -> 417392857129 | AK75: =DTR!AF$17 -> 0 | AL75: =DTR!AG$17 -> 0 | AM75: =DTR!AH$17 -> 0 | ... AQ75: =DTR!AL$17 -> 0 | AR75: =IF($AR$26=1,AF75,SUM(OFFSET(AF75:AQ75,0,0,1,$AR$26))-SUM(OFFSET(AF75:AQ75,0,0,1,$AR$26-1))) -> 417392857129 | AS75: =IF($AR$26=1,AF75,SUM(OFFSET(AF75:AQ75,0,0,1,$AR$26))-SUM(OFFSET(AF75:AQ75,0,0,1,$AR$26-1))) -> 417392857129
A76: B04.1 | B76: DTR | D76: Account receivables from customers | E76: =DTR!C18 -> 122887480695 | F76: =DTR!D18 -> 127016253433 | G76: =DTR!E18 -> 139011604932 | H76: =DTR!F18 -> 152040845787 | I76: =DTR!G18 -> 161172642369 | J76: =DTR!H18 -> 159378679498 | K76: =DTR!I18 -> 97722288447 | L76: =DTR!J18 -> 120989360950 | ... P76: =DTR!N18 -> 152669364944 | Q76: =IF($AD$26=1,E76,SUM(OFFSET(E76:P76,0,0,1,$AD$26))-SUM(OFFSET(E76:P76,0,0,1,$AD$26-1))) -> 161172642369 | R76: =DTR!O18 -> 108322209217 | S76: =DTR!P18 -> 161139219719 | T76: =DTR!Q18 -> 202956915270 | U76: =DTR!R18 -> 159438788675 | V76: =DTR!S18 -> 170977391735 | W76: =DTR!T18 -> 157629418587 | X76: =DTR!U18 -> 156235244643 | Y76: =DTR!V18 -> 193809016663 | ... AC76: =DTR!Z18 -> 154342206132 | AD76: =IF($AD$26=1,R76,SUM(OFFSET(R76:AC76,0,0,1,$AD$26))-SUM(OFFSET(R76:AC76,0,0,1,$AD$26-1))) -> 170977391735 | AE76: =IF($AD$26=1,R76,SUM(OFFSET(R76:AC76,0,0,1,$AD$26))-SUM(OFFSET(R76:AC76,0,0,1,$AD$26-1))) -> 170977391735 | AF76: =DTR!AA$18 -> 132649296167 | AG76: =DTR!AB$18 -> 140446291758 | AH76: =DTR!AC$18 -> 153248625708 | AI76: =DTR!AD$18 -> 178191270169 | AJ76: =DTR!AE$18 -> 178005616424 | AK76: =DTR!AF$18 -> 0 | AL76: =DTR!AG$18 -> 0 | AM76: =DTR!AH$18 -> 0 | ... AQ76: =DTR!AL$18 -> 0 | AR76: =IF($AR$26=1,AF76,SUM(OFFSET(AF76:AQ76,0,0,1,$AR$26))-SUM(OFFSET(AF76:AQ76,0,0,1,$AR$26-1))) -> 178005616424 | AS76: =IF($AR$26=1,AF76,SUM(OFFSET(AF76:AQ76,0,0,1,$AR$26))-SUM(OFFSET(AF76:AQ76,0,0,1,$AR$26-1))) -> 178005616424
A77: B05 | B77: DTR | D77: Inventory | E77: =DTR!C25 -> 406821244018 | F77: =DTR!D25 -> 413788449441 | G77: =DTR!E25 -> 455747162045 | H77: =DTR!F25 -> 496057122616 | I77: =DTR!G25 -> 541180364701 | J77: =DTR!H25 -> 600190018005 | K77: =DTR!I25 -> 619776297407 | L77: =DTR!J25 -> 559053982584 | ... P77: =DTR!N25 -> 605821152798 | Q77: =IF($AD$26=1,E77,SUM(OFFSET(E77:P77,0,0,1,$AD$26))-SUM(OFFSET(E77:P77,0,0,1,$AD$26-1))) -> 541180364701 | R77: =DTR!O25 -> 566809475589 | S77: =DTR!P25 -> 483821147048 | T77: =DTR!Q25 -> 468355569440 | U77: =DTR!R25 -> 522665513478 | V77: =DTR!S25 -> 526499028418 | W77: =DTR!T25 -> 543591846704 | X77: =DTR!U25 -> 548599437580 | Y77: =DTR!V25 -> 548273459394 | ... AC77: =DTR!Z25 -> 562435021579 | AD77: =IF($AD$26=1,R77,SUM(OFFSET(R77:AC77,0,0,1,$AD$26))-SUM(OFFSET(R77:AC77,0,0,1,$AD$26-1))) -> 526499028418 | AE77: =IF($AD$26=1,R77,SUM(OFFSET(R77:AC77,0,0,1,$AD$26))-SUM(OFFSET(R77:AC77,0,0,1,$AD$26-1))) -> 526499028418 | AF77: =DTR!AA$25 -> 534105826237 | AG77: =DTR!AB$25 -> 502545827363 | AH77: =DTR!AC$25 -> 425450972162 | AI77: =DTR!AD$25 -> 370413533224 | AJ77: =DTR!AE$25 -> 361880765551 | AK77: =DTR!AF$25 -> 0 | AL77: =DTR!AG$25 -> 0 | AM77: =DTR!AH$25 -> 0 | ... AQ77: =DTR!AL$25 -> 0 | AR77: =IF($AR$26=1,AF77,SUM(OFFSET(AF77:AQ77,0,0,1,$AR$26))-SUM(OFFSET(AF77:AQ77,0,0,1,$AR$26-1))) -> 361880765551 | AS77: =IF($AR$26=1,AF77,SUM(OFFSET(AF77:AQ77,0,0,1,$AR$26))-SUM(OFFSET(AF77:AQ77,0,0,1,$AR$26-1))) -> 361880765551
A78: B06 | B78: DTR | D78: Long-term Assets | E78: =DTR!C38 -> 274624562032 | F78: =DTR!D38 -> 272308792463 | G78: =DTR!E38 -> 271203283116 | H78: =DTR!F38 -> 270904814396 | I78: =DTR!G38 -> 269907328559 | J78: =DTR!H38 -> 270747087858 | K78: =DTR!I38 -> 268779207254 | L78: =DTR!J38 -> 274334422235 | ... P78: =DTR!N38 -> 285939000851 | Q78: =IF($AD$26=1,E78,SUM(OFFSET(E78:P78,0,0,1,$AD$26))-SUM(OFFSET(E78:P78,0,0,1,$AD$26-1))) -> 269907328559 | R78: =DTR!O38 -> 289379194755 | S78: =DTR!P38 -> 285515570351 | T78: =DTR!Q38 -> 287407502163 | U78: =DTR!R38 -> 294777015341 | V78: =DTR!S38 -> 299380289162 | W78: =DTR!T38 -> 300166972168 | X78: =DTR!U38 -> 296753996838 | Y78: =DTR!V38 -> 296192973827 | ... AC78: =DTR!Z38 -> 320800563599 | AD78: =IF($AD$26=1,R78,SUM(OFFSET(R78:AC78,0,0,1,$AD$26))-SUM(OFFSET(R78:AC78,0,0,1,$AD$26-1))) -> 299380289162 | AE78: =IF($AD$26=1,R78,SUM(OFFSET(R78:AC78,0,0,1,$AD$26))-SUM(OFFSET(R78:AC78,0,0,1,$AD$26-1))) -> 299380289162 | AF78: =DTR!AA$38 -> 317415705891 | AG78: =DTR!AB$38 -> 337499929442 | AH78: =DTR!AC$38 -> 343594894451 | AI78: =DTR!AD$38 -> 365048803536 | AJ78: =DTR!AE$38 -> 365314011891 | AK78: =DTR!AF$38 -> 0 | AL78: =DTR!AG$38 -> 0 | AM78: =DTR!AH$38 -> 0 | ... AQ78: =DTR!AL$38 -> 0 | AR78: =IF($AR$26=1,AF78,SUM(OFFSET(AF78:AQ78,0,0,1,$AR$26))-SUM(OFFSET(AF78:AQ78,0,0,1,$AR$26-1))) -> 365314011891 | AS78: =IF($AR$26=1,AF78,SUM(OFFSET(AF78:AQ78,0,0,1,$AR$26))-SUM(OFFSET(AF78:AQ78,0,0,1,$AR$26-1))) -> 365314011891
A79: B07 | B79: DTR | D79: Fixed Assets | E79: =DTR!C46 -> 198013903445 | F79: =DTR!D46 -> 195010544683 | G79: =DTR!E46 -> 225730823955 | H79: =DTR!F46 -> 226001461052 | I79: =DTR!G46 -> 224673388970 | J79: =DTR!H46 -> 221428232280 | K79: =DTR!I46 -> 219409735799 | L79: =DTR!J46 -> 226228538916 | ... P79: =DTR!N46 -> 236902591180 | Q79: =IF($AD$26=1,E79,SUM(OFFSET(E79:P79,0,0,1,$AD$26))-SUM(OFFSET(E79:P79,0,0,1,$AD$26-1))) -> 224673388970 | R79: =DTR!O46 -> 233135637012 | S79: =DTR!P46 -> 239769028633 | T79: =DTR!Q46 -> 244837616747 | U79: =DTR!R46 -> 241369190811 | V79: =DTR!S46 -> 237349552865 | W79: =DTR!T46 -> 233717444711 | X79: =DTR!U46 -> 229848858132 | Y79: =DTR!V46 -> 248058151289 | ... AC79: =DTR!Z46 -> 243859258508 | AD79: =IF($AD$26=1,R79,SUM(OFFSET(R79:AC79,0,0,1,$AD$26))-SUM(OFFSET(R79:AC79,0,0,1,$AD$26-1))) -> 237349552865 | AE79: =IF($AD$26=1,R79,SUM(OFFSET(R79:AC79,0,0,1,$AD$26))-SUM(OFFSET(R79:AC79,0,0,1,$AD$26-1))) -> 237349552865 | AF79: =DTR!AA$46 -> 243650467528 | AG79: =DTR!AB$46 -> 244965950858 | AH79: =DTR!AC$46 -> 265786488609 | AI79: =DTR!AD$46 -> 270226692853 | AJ79: =DTR!AE$46 -> 268070715296 | AK79: =DTR!AF$46 -> 0 | AL79: =DTR!AG$46 -> 0 | AM79: =DTR!AH$46 -> 0 | ... AQ79: =DTR!AL$46 -> 0 | AR79: =IF($AR$26=1,AF79,SUM(OFFSET(AF79:AQ79,0,0,1,$AR$26))-SUM(OFFSET(AF79:AQ79,0,0,1,$AR$26-1))) -> 268070715296 | AS79: =IF($AR$26=1,AF79,SUM(OFFSET(AF79:AQ79,0,0,1,$AR$26))-SUM(OFFSET(AF79:AQ79,0,0,1,$AR$26-1))) -> 268070715296
A80: B08 | B80: DTR | D80: Cost | E80: =DTR!C48+DTR!C51+DTR!C54 -> 260312876754 | F80: =DTR!D48+DTR!D51+DTR!D54 -> 260312876754 | G80: =DTR!E48+DTR!E51+DTR!E54 -> 294032134959 | H80: =DTR!F48+DTR!F51+DTR!F54 -> 297483796455 | I80: =DTR!G48+DTR!G51+DTR!G54 -> 299394448651 | J80: =DTR!H48+DTR!H51+DTR!H54 -> 299389731984 | K80: =DTR!I48+DTR!I51+DTR!I54 -> 300645731984 | L80: =DTR!J48+DTR!J51+DTR!J54 -> 310582237964 | ... P80: =DTR!N48+DTR!N51+DTR!N54 -> 319211223481 | Q80: =IF($AD$26=1,E80,SUM(OFFSET(E80:P80,0,0,1,$AD$26))-SUM(OFFSET(E80:P80,0,0,1,$AD$26-1))) -> 299394448651 | R80: =DTR!O48+DTR!O51+DTR!O54 -> 319247423481 | S80: =DTR!P48+DTR!P51+DTR!P54 -> 329685513716 | T80: =DTR!Q48+DTR!Q51+DTR!Q54 -> 338756735805 | U80: =DTR!R48+DTR!R51+DTR!R54 -> 338784630797 | V80: =DTR!S48+DTR!S51+DTR!S54 -> 338856847837 | W80: =DTR!T48+DTR!T51+DTR!T54 -> 339312208021 | X80: =DTR!U48+DTR!U51+DTR!U54 -> 339289078993 | Y80: =DTR!V48+DTR!V51+DTR!V54 -> 361191367310 | ... AC80: =DTR!Z48+DTR!Z51+DTR!Z54 -> 374525100173 | AD80: =IF($AD$26=1,R80,SUM(OFFSET(R80:AC80,0,0,1,$AD$26))-SUM(OFFSET(R80:AC80,0,0,1,$AD$26-1))) -> 338856847837 | AE80: =IF($AD$26=1,R80,SUM(OFFSET(R80:AC80,0,0,1,$AD$26))-SUM(OFFSET(R80:AC80,0,0,1,$AD$26-1))) -> 338856847837 | AF80: =DTR!AA$48+DTR!AA$51+DTR!AA$54 -> 376450278038 | AG80: =DTR!AB$48+DTR!AB$51+DTR!AB$54 -> 379868769856 | AH80: =DTR!AC$48+DTR!AC$51+DTR!AC$54 -> 402807419165 | AI80: =DTR!AD$48+DTR!AD$51+DTR!AD$54 -> 409525584982 | AJ80: =DTR!AE$48+DTR!AE$51+DTR!AE$54 -> 409700584982 | AK80: =DTR!AF$48+DTR!AF$51+DTR!AF$54 -> 0 | AL80: =DTR!AG$48+DTR!AG$51+DTR!AG$54 -> 0 | AM80: =DTR!AH$48+DTR!AH$51+DTR!AH$54 -> 0 | ... AQ80: =DTR!AL$48+DTR!AL$51+DTR!AL$54 -> 0 | AR80: =IF($AR$26=1,AF80,SUM(OFFSET(AF80:AQ80,0,0,1,$AR$26))-SUM(OFFSET(AF80:AQ80,0,0,1,$AR$26-1))) -> 409700584982 | AS80: =IF($AR$26=1,AF80,SUM(OFFSET(AF80:AQ80,0,0,1,$AR$26))-SUM(OFFSET(AF80:AQ80,0,0,1,$AR$26-1))) -> 409700584982
A81: B09 | B81: DTR | D81: Accumulated depreciation | E81: =DTR!C49+DTR!C52+DTR!C55 -> -62298973309 | F81: =DTR!D49+DTR!D52+DTR!D55 -> -65302332071 | G81: =DTR!E49+DTR!E52+DTR!E55 -> -68301311004 | H81: =DTR!F49+DTR!F52+DTR!F55 -> -71482335403 | I81: =DTR!G49+DTR!G52+DTR!G55 -> -74721059681 | J81: =DTR!H49+DTR!H52+DTR!H55 -> -77961499704 | K81: =DTR!I49+DTR!I52+DTR!I55 -> -81235996185 | L81: =DTR!J49+DTR!J52+DTR!J55 -> -84353699048 | ... P81: =DTR!N49+DTR!N52+DTR!N55 -> -82308632301 | Q81: =IF($AD$26=1,E81,SUM(OFFSET(E81:P81,0,0,1,$AD$26))-SUM(OFFSET(E81:P81,0,0,1,$AD$26-1))) -> -74721059681 | R81: =DTR!O49+DTR!O52+DTR!O55 -> -86111786469 | S81: =DTR!P49+DTR!P52+DTR!P55 -> -89916485083 | T81: =DTR!Q49+DTR!Q52+DTR!Q55 -> -93919119058 | U81: =DTR!R49+DTR!R52+DTR!R55 -> -97415439986 | V81: =DTR!S49+DTR!S52+DTR!S55 -> -101507294972 | W81: =DTR!T49+DTR!T52+DTR!T55 -> -105594763310 | X81: =DTR!U49+DTR!U52+DTR!U55 -> -109440220861 | Y81: =DTR!V49+DTR!V52+DTR!V55 -> -113133216021 | ... AC81: =DTR!Z49+DTR!Z52+DTR!Z55 -> -130665841665 | AD81: =IF($AD$26=1,R81,SUM(OFFSET(R81:AC81,0,0,1,$AD$26))-SUM(OFFSET(R81:AC81,0,0,1,$AD$26-1))) -> -101507294972 | AE81: =IF($AD$26=1,R81,SUM(OFFSET(R81:AC81,0,0,1,$AD$26))-SUM(OFFSET(R81:AC81,0,0,1,$AD$26-1))) -> -101507294972 | AF81: =DTR!AA$49+DTR!AA$52+DTR!AA$55 -> -132799810510 | AG81: =DTR!AB$49+DTR!AB$52+DTR!AB$55 -> -134902818998 | AH81: =DTR!AC$49+DTR!AC$52+DTR!AC$55 -> -137020930556 | AI81: =DTR!AD$49+DTR!AD$52+DTR!AD$55 -> -139298892129 | AJ81: =DTR!AE$49+DTR!AE$52+DTR!AE$55 -> -141629869686 | AK81: =DTR!AF$49+DTR!AF$52+DTR!AF$55 -> 0 | AL81: =DTR!AG$49+DTR!AG$52+DTR!AG$55 -> 0 | AM81: =DTR!AH$49+DTR!AH$52+DTR!AH$55 -> 0 | ... AQ81: =DTR!AL$49+DTR!AL$52+DTR!AL$55 -> 0 | AR81: =IF($AR$26=1,AF81,SUM(OFFSET(AF81:AQ81,0,0,1,$AR$26))-SUM(OFFSET(AF81:AQ81,0,0,1,$AR$26-1))) -> -141629869686 | AS81: =IF($AR$26=1,AF81,SUM(OFFSET(AF81:AQ81,0,0,1,$AR$26))-SUM(OFFSET(AF81:AQ81,0,0,1,$AR$26-1))) -> -141629869686
A82: B10 | B82: DTR | D82: Total Assets | E82: =DTR!C83 -> 1057106496455 | F82: =DTR!D83 -> 1040899556726 | G82: =DTR!E83 -> 1086669152157 | H82: =DTR!F83 -> 1148318840816 | I82: =DTR!G83 -> 1198063045295 | J82: =DTR!H83 -> 1227310309881 | K82: =DTR!I83 -> 1174913086353 | L82: =DTR!J83 -> 1123552712261 | ... P82: =DTR!N83 -> 1255526266731 | Q82: =IF($AD$26=1,E82,SUM(OFFSET(E82:P82,0,0,1,$AD$26))-SUM(OFFSET(E82:P82,0,0,1,$AD$26-1))) -> 1198063045295 | R82: =DTR!O83 -> 1184167227046 | S82: =DTR!P83 -> 1099673392126 | T82: =DTR!Q83 -> 1153710875298 | U82: =DTR!R83 -> 1224376777626 | V82: =DTR!S83 -> 1280979662011 | W82: =DTR!T83 -> 1310961670922 | X82: =DTR!U83 -> 1296565798277 | Y82: =DTR!V83 -> 1356526045802 | ... AC82: =DTR!Z83 -> 1266017714532 | AD82: =IF($AD$26=1,R82,SUM(OFFSET(R82:AC82,0,0,1,$AD$26))-SUM(OFFSET(R82:AC82,0,0,1,$AD$26-1))) -> 1280979662011 | AE82: =IF($AD$26=1,R82,SUM(OFFSET(R82:AC82,0,0,1,$AD$26))-SUM(OFFSET(R82:AC82,0,0,1,$AD$26-1))) -> 1280979662011 | AF82: =DTR!AA$83 -> 1211566398236 | AG82: =DTR!AB$83 -> 1233002251518 | AH82: =DTR!AC$83 -> 1192063370403 | AI82: =DTR!AD$83 -> 1173001139790 | AJ82: =DTR!AE$83 -> 1251902380916 | AK82: =DTR!AF$83 -> 0 | AL82: =DTR!AG$83 -> 0 | AM82: =DTR!AH$83 -> 0 | ... AQ82: =DTR!AL$83 -> 0 | AR82: =IF($AR$26=1,AF82,SUM(OFFSET(AF82:AQ82,0,0,1,$AR$26))-SUM(OFFSET(AF82:AQ82,0,0,1,$AR$26-1))) -> 1251902380916 | AS82: =IF($AR$26=1,AF82,SUM(OFFSET(AF82:AQ82,0,0,1,$AR$26))-SUM(OFFSET(AF82:AQ82,0,0,1,$AR$26-1))) -> 1251902380916
A83: B11 | B83: DTR | D83: Short-term Liabilities | E83: =DTR!C85 -> 176322036564 | F83: =DTR!D85 -> 165479805632 | G83: =DTR!E85 -> 214267710664 | H83: =DTR!F85 -> 273737345975 | I83: =DTR!G85 -> 329588242794 | J83: =DTR!H85 -> 367721787447 | K83: =DTR!I85 -> 328736442804 | L83: =DTR!J85 -> 286316076697 | ... P83: =DTR!N85 -> 316029265342 | Q83: =IF($AD$26=1,E83,SUM(OFFSET(E83:P83,0,0,1,$AD$26))-SUM(OFFSET(E83:P83,0,0,1,$AD$26-1))) -> 329588242794 | R83: =DTR!O85 -> 216100148681 | S83: =DTR!P85 -> 118453354810 | T83: =DTR!Q85 -> 166229366701 | U83: =DTR!R85 -> 234217256714 | V83: =DTR!S85 -> 285537774573 | W83: =DTR!T85 -> 335330408775 | X83: =DTR!U85 -> 320967989443 | Y83: =DTR!V85 -> 382420327015 | ... AC83: =DTR!Z85 -> 335139049377 | AD83: =IF($AD$26=1,R83,SUM(OFFSET(R83:AC83,0,0,1,$AD$26))-SUM(OFFSET(R83:AC83,0,0,1,$AD$26-1))) -> 285537774573 | AE83: =IF($AD$26=1,R83,SUM(OFFSET(R83:AC83,0,0,1,$AD$26))-SUM(OFFSET(R83:AC83,0,0,1,$AD$26-1))) -> 285537774573 | AF83: =DTR!AA$85 -> 283290606756 | AG83: =DTR!AB$85 -> 289218173776 | AH83: =DTR!AC$85 -> 246244699285 | AI83: =DTR!AD$85 -> 223478714460 | AJ83: =DTR!AE$85 -> 219319635169 | AK83: =DTR!AF$85 -> 0 | AL83: =DTR!AG$85 -> 0 | AM83: =DTR!AH$85 -> 0 | ... AQ83: =DTR!AL$85 -> 0 | AR83: =IF($AR$26=1,AF83,SUM(OFFSET(AF83:AQ83,0,0,1,$AR$26))-SUM(OFFSET(AF83:AQ83,0,0,1,$AR$26-1))) -> 219319635169 | AS83: =IF($AR$26=1,AF83,SUM(OFFSET(AF83:AQ83,0,0,1,$AR$26))-SUM(OFFSET(AF83:AQ83,0,0,1,$AR$26-1))) -> 219319635169
A84: B12 | B84: DTR | D84: Short-term borrowings | E84: =DTR!C96 -> 62822745245 | F84: =DTR!D96 -> 57847834995 | G84: =DTR!E96 -> 101832582537 | H84: =DTR!F96 -> 144977288403 | I84: =DTR!G96 -> 178905916168 | J84: =DTR!H96 -> 190748518955 | K84: =DTR!I96 -> 168894814805 | L84: =DTR!J96 -> 126048766562 | ... P84: =DTR!N96 -> 192629821718 | Q84: =IF($AD$26=1,E84,SUM(OFFSET(E84:P84,0,0,1,$AD$26))-SUM(OFFSET(E84:P84,0,0,1,$AD$26-1))) -> 178905916168 | R84: =DTR!O96 -> 134925554251 | S84: =DTR!P96 -> 43611829278 | T84: =DTR!Q96 -> 98003020481 | U84: =DTR!R96 -> 172928907420 | V84: =DTR!S96 -> 200666324688 | W84: =DTR!T96 -> 238388679271 | X84: =DTR!U96 -> 250573370780 | Y84: =DTR!V96 -> 294832243750 | ... AC84: =DTR!Z96 -> 262225979238 | AD84: =IF($AD$26=1,R84,SUM(OFFSET(R84:AC84,0,0,1,$AD$26))-SUM(OFFSET(R84:AC84,0,0,1,$AD$26-1))) -> 200666324688 | AE84: =IF($AD$26=1,R84,SUM(OFFSET(R84:AC84,0,0,1,$AD$26))-SUM(OFFSET(R84:AC84,0,0,1,$AD$26-1))) -> 200666324688 | AF84: =DTR!AA$96 -> 216818798145 | AG84: =DTR!AB$96 -> 231846507077 | AH84: =DTR!AC$96 -> 179737111410 | AI84: =DTR!AD$96 -> 147514569550 | AJ84: =DTR!AE$96 -> 116595603825 | AK84: =DTR!AF$96 -> 0 | AL84: =DTR!AG$96 -> 0 | AM84: =DTR!AH$96 -> 0 | ... AQ84: =DTR!AL$96 -> 0 | AR84: =IF($AR$26=1,AF84,SUM(OFFSET(AF84:AQ84,0,0,1,$AR$26))-SUM(OFFSET(AF84:AQ84,0,0,1,$AR$26-1))) -> 116595603825 | AS84: =IF($AR$26=1,AF84,SUM(OFFSET(AF84:AQ84,0,0,1,$AR$26))-SUM(OFFSET(AF84:AQ84,0,0,1,$AR$26-1))) -> 116595603825
A85: B13 | B85: DTR | D85: Account payables | E85: =DTR!C86+DTR!C87 -> 58385303044 | F85: =DTR!D86+DTR!D87 -> 57459904781 | G85: =DTR!E86+DTR!E87 -> 71125757622 | H85: =DTR!F86+DTR!F87 -> 76995321500 | I85: =DTR!G86+DTR!G87 -> 97319270425 | J85: =DTR!H86+DTR!H87 -> 152128046303 | K85: =DTR!I86+DTR!I87 -> 125254808223 | L85: =DTR!J86+DTR!J87 -> 119990052531 | ... P85: =DTR!N86+DTR!N87 -> 80400812109 | Q85: =IF($AD$26=1,E85,SUM(OFFSET(E85:P85,0,0,1,$AD$26))-SUM(OFFSET(E85:P85,0,0,1,$AD$26-1))) -> 97319270425 | R85: =DTR!O86+DTR!O87 -> 51068412769 | S85: =DTR!P86+DTR!P87 -> 34792825965 | T85: =DTR!Q86+DTR!Q87 -> 51709965211 | U85: =DTR!R86+DTR!R87 -> 40094252832 | V85: =DTR!S86+DTR!S87 -> 36763462032 | W85: =DTR!T86+DTR!T87 -> 65161360489 | X85: =DTR!U86+DTR!U87 -> 27637762536 | Y85: =DTR!V86+DTR!V87 -> 35981686303 | ... AC85: =DTR!Z86+DTR!Z87 -> 33272165919 | AD85: =IF($AD$26=1,R85,SUM(OFFSET(R85:AC85,0,0,1,$AD$26))-SUM(OFFSET(R85:AC85,0,0,1,$AD$26-1))) -> 36763462032 | AE85: =IF($AD$26=1,R85,SUM(OFFSET(R85:AC85,0,0,1,$AD$26))-SUM(OFFSET(R85:AC85,0,0,1,$AD$26-1))) -> 36763462032 | AF85: =DTR!AA$86+DTR!AA$87 -> 24934823841 | AG85: =DTR!AB$86+DTR!AB$87 -> 22553232387 | AH85: =DTR!AC$86+DTR!AC$87 -> 35120916435 | AI85: =DTR!AD$86+DTR!AD$87 -> 38673545309 | AJ85: =DTR!AE$86+DTR!AE$87 -> 65718659314 | AK85: =DTR!AF$86+DTR!AF$87 -> 0 | AL85: =DTR!AG$86+DTR!AG$87 -> 0 | AM85: =DTR!AH$86+DTR!AH$87 -> 0 | ... AQ85: =DTR!AL$86+DTR!AL$87 -> 0 | AR85: =IF($AR$26=1,AF85,SUM(OFFSET(AF85:AQ85,0,0,1,$AR$26))-SUM(OFFSET(AF85:AQ85,0,0,1,$AR$26-1))) -> 65718659314 | AS85: =IF($AR$26=1,AF85,SUM(OFFSET(AF85:AQ85,0,0,1,$AR$26))-SUM(OFFSET(AF85:AQ85,0,0,1,$AR$26-1))) -> 65718659314
A86: B13.1 | B86: DTR | D86: Account payables to suppliers | E86: =DTR!C86 -> 54353400004 | F86: =DTR!D86 -> 57459904781 | G86: =DTR!E86 -> 71666676062 | H86: =DTR!F86 -> 72717166254 | I86: =DTR!G86 -> 82570066775 | J86: =DTR!H86 -> 116097944870 | K86: =DTR!I86 -> 90497312556 | L86: =DTR!J86 -> 104998329522 | ... P86: =DTR!N86 -> 38854336196 | Q86: =IF($AD$26=1,E86,SUM(OFFSET(E86:P86,0,0,1,$AD$26))-SUM(OFFSET(E86:P86,0,0,1,$AD$26-1))) -> 82570066775 | R86: =DTR!O86 -> 17080396612 | S86: =DTR!P86 -> 15854922544 | T86: =DTR!Q86 -> 36651877076 | U86: =DTR!R86 -> 36646554722 | V86: =DTR!S86 -> 36688096679 | W86: =DTR!T86 -> 50235234736 | X86: =DTR!U86 -> 4297727379 | Y86: =DTR!V86 -> 15019964770 | ... AC86: =DTR!Z86 -> 15762773405 | AD86: =IF($AD$26=1,R86,SUM(OFFSET(R86:AC86,0,0,1,$AD$26))-SUM(OFFSET(R86:AC86,0,0,1,$AD$26-1))) -> 36688096679 | AE86: =IF($AD$26=1,R86,SUM(OFFSET(R86:AC86,0,0,1,$AD$26))-SUM(OFFSET(R86:AC86,0,0,1,$AD$26-1))) -> 36688096679 | AF86: =DTR!AA$86 -> 12939623311 | AG86: =DTR!AB$86 -> 16340093986 | AH86: =DTR!AC$86 -> 28822406885 | AI86: =DTR!AD$86 -> 28647773855 | AJ86: =DTR!AE$86 -> 51638550700 | AK86: =DTR!AF$86 -> 0 | AL86: =DTR!AG$86 -> 0 | AM86: =DTR!AH$86 -> 0 | ... AQ86: =DTR!AL$86 -> 0 | AR86: =IF($AR$26=1,AF86,SUM(OFFSET(AF86:AQ86,0,0,1,$AR$26))-SUM(OFFSET(AF86:AQ86,0,0,1,$AR$26-1))) -> 51638550700 | AS86: =IF($AR$26=1,AF86,SUM(OFFSET(AF86:AQ86,0,0,1,$AR$26))-SUM(OFFSET(AF86:AQ86,0,0,1,$AR$26-1))) -> 51638550700
A87: B14 | B87: DTR | D87: Long-term liabilities | E87: =DTR!C101 -> 77616411070 | F87: =DTR!D101 -> 77522351070 | G87: =DTR!E101 -> 77463351070 | H87: =DTR!F101 -> 77168157678 | I87: =DTR!G101 -> 75214867678 | J87: =DTR!H101 -> 76544035678 | K87: =DTR!I101 -> 76656842286 | L87: =DTR!J101 -> 75999782286 | ... P87: =DTR!N101 -> 84737345522 | Q87: =IF($AD$26=1,E87,SUM(OFFSET(E87:P87,0,0,1,$AD$26))-SUM(OFFSET(E87:P87,0,0,1,$AD$26-1))) -> 75214867678 | R87: =DTR!O101 -> 108410341946 | S87: =DTR!P101 -> 104162504168 | T87: =DTR!Q101 -> 103325726390 | U87: =DTR!R101 -> 102252755220 | V87: =DTR!S101 -> 98004917442 | W87: =DTR!T101 -> 77121791394 | X87: =DTR!U101 -> 76048820224 | Y87: =DTR!V101 -> 74463510446 | ... AC87: =DTR!Z101 -> 50382254354 | AD87: =IF($AD$26=1,R87,SUM(OFFSET(R87:AC87,0,0,1,$AD$26))-SUM(OFFSET(R87:AC87,0,0,1,$AD$26-1))) -> 98004917442 | AE87: =IF($AD$26=1,R87,SUM(OFFSET(R87:AC87,0,0,1,$AD$26))-SUM(OFFSET(R87:AC87,0,0,1,$AD$26-1))) -> 98004917442 | AF87: =DTR!AA$101 -> 49472841415 | AG87: =DTR!AB$101 -> 71400341415 | AH87: =DTR!AC$101 -> 80100341415 | AI87: =DTR!AD$101 -> 80100341415 | AJ87: =DTR!AE$101 -> 154933236415 | AK87: =DTR!AF$101 -> 0 | AL87: =DTR!AG$101 -> 0 | AM87: =DTR!AH$101 -> 0 | ... AQ87: =DTR!AL$101 -> 0 | AR87: =IF($AR$26=1,AF87,SUM(OFFSET(AF87:AQ87,0,0,1,$AR$26))-SUM(OFFSET(AF87:AQ87,0,0,1,$AR$26-1))) -> 154933236415 | AS87: =IF($AR$26=1,AF87,SUM(OFFSET(AF87:AQ87,0,0,1,$AR$26))-SUM(OFFSET(AF87:AQ87,0,0,1,$AR$26-1))) -> 154933236415
A88: B15 | B88: DTR | D88: Long-term borrowings | E88: =DTR!C110 -> 77616411070 | F88: =DTR!D110 -> 77522351070 | G88: =DTR!E110 -> 77463351070 | H88: =DTR!F110 -> 77168157678 | I88: =DTR!G110 -> 75214867678 | J88: =DTR!H110 -> 76544035678 | K88: =DTR!I110 -> 76656842286 | L88: =DTR!J110 -> 75999782286 | ... P88: =DTR!N110 -> 82898404212 | Q88: =IF($AD$26=1,E88,SUM(OFFSET(E88:P88,0,0,1,$AD$26))-SUM(OFFSET(E88:P88,0,0,1,$AD$26-1))) -> 75214867678 | R88: =DTR!O110 -> 108410341946 | S88: =DTR!P110 -> 104162504168 | T88: =DTR!Q110 -> 103325726390 | U88: =DTR!R110 -> 102252755220 | V88: =DTR!S110 -> 98004917442 | W88: =DTR!T110 -> 77121791394 | X88: =DTR!U110 -> 76048820224 | Y88: =DTR!V110 -> 74463510446 | ... AC88: =DTR!Z110 -> 50382254354 | AD88: =IF($AD$26=1,R88,SUM(OFFSET(R88:AC88,0,0,1,$AD$26))-SUM(OFFSET(R88:AC88,0,0,1,$AD$26-1))) -> 98004917442 | AE88: =IF($AD$26=1,R88,SUM(OFFSET(R88:AC88,0,0,1,$AD$26))-SUM(OFFSET(R88:AC88,0,0,1,$AD$26-1))) -> 98004917442 | AF88: =DTR!AA$110 -> 49472841415 | AG88: =DTR!AB$110 -> 71400341415 | AH88: =DTR!AC$110 -> 80100341415 | AI88: =DTR!AD$110 -> 80100341415 | AJ88: =DTR!AE$110 -> 154933236415 | AK88: =DTR!AF$110 -> 0 | AL88: =DTR!AG$110 -> 0 | AM88: =DTR!AH$110 -> 0 | ... AQ88: =DTR!AL$110 -> 0 | AR88: =IF($AR$26=1,AF88,SUM(OFFSET(AF88:AQ88,0,0,1,$AR$26))-SUM(OFFSET(AF88:AQ88,0,0,1,$AR$26-1))) -> 154933236415 | AS88: =IF($AR$26=1,AF88,SUM(OFFSET(AF88:AQ88,0,0,1,$AR$26))-SUM(OFFSET(AF88:AQ88,0,0,1,$AR$26-1))) -> 154933236415
A89: B16 | B89: DTR | D89: Equity | E89: =DTR!C116 -> 803168048821 | F89: =DTR!D116 -> 797897400024 | G89: =DTR!E116 -> 794938090423 | H89: =DTR!F116 -> 797413337163 | I89: =DTR!G116 -> 793259934823 | J89: =DTR!H116 -> 783044486756 | K89: =DTR!I116 -> 769519801263 | L89: =DTR!J116 -> 761236853278 | ... P89: =DTR!N116 -> 854759655867 | Q89: =IF($AD$26=1,E89,SUM(OFFSET(E89:P89,0,0,1,$AD$26))-SUM(OFFSET(E89:P89,0,0,1,$AD$26-1))) -> 793259934823 | R89: =DTR!O116 -> 859656736419 | S89: =DTR!P116 -> 877057533148 | T89: =DTR!Q116 -> 884155782207 | U89: =DTR!R116 -> 887906765692 | V89: =DTR!S116 -> 897436969996 | W89: =DTR!T116 -> 898509470753 | X89: =DTR!U116 -> 899548988610 | Y89: =DTR!V116 -> 899642208341 | ... AC89: =DTR!Z116 -> 880496410801 | AD89: =IF($AD$26=1,R89,SUM(OFFSET(R89:AC89,0,0,1,$AD$26))-SUM(OFFSET(R89:AC89,0,0,1,$AD$26-1))) -> 897436969996 | AE89: =IF($AD$26=1,R89,SUM(OFFSET(R89:AC89,0,0,1,$AD$26))-SUM(OFFSET(R89:AC89,0,0,1,$AD$26-1))) -> 897436969996 | AF89: =DTR!AA$116 -> 878802950065 | AG89: =DTR!AB$116 -> 872383736327 | AH89: =DTR!AC$116 -> 865718329703 | AI89: =DTR!AD$116 -> 869422083915 | AJ89: =DTR!AE$116 -> 877649509332 | AK89: =DTR!AF$116 -> 0 | AL89: =DTR!AG$116 -> 0 | AM89: =DTR!AH$116 -> 0 | ... AQ89: =DTR!AL$116 -> 0 | AR89: =IF($AR$26=1,AF89,SUM(OFFSET(AF89:AQ89,0,0,1,$AR$26))-SUM(OFFSET(AF89:AQ89,0,0,1,$AR$26-1))) -> 877649509332 | AS89: =IF($AR$26=1,AF89,SUM(OFFSET(AF89:AQ89,0,0,1,$AR$26))-SUM(OFFSET(AF89:AQ89,0,0,1,$AR$26-1))) -> 877649509332
A90: B17 | B90: DTR | D90: Share capital | E90: =DTR!C117 -> 650000000000 | F90: =DTR!D117 -> 650000000000 | G90: =DTR!E117 -> 650000000000 | H90: =DTR!F117 -> 650000000000 | I90: =DTR!G117 -> 650000000000 | J90: =DTR!H117 -> 650000000000 | K90: =DTR!I117 -> 650000000000 | L90: =DTR!J117 -> 650000000000 | ... P90: =DTR!N117 -> 650000000000 | Q90: =IF($AD$26=1,E90,SUM(OFFSET(E90:P90,0,0,1,$AD$26))-SUM(OFFSET(E90:P90,0,0,1,$AD$26-1))) -> 650000000000 | R90: =DTR!O117 -> 650000000000 | S90: =DTR!P117 -> 650000000000 | T90: =DTR!Q117 -> 650000000000 | U90: =DTR!R117 -> 650000000000 | V90: =DTR!S117 -> 650000000000 | W90: =DTR!T117 -> 650000000000 | X90: =DTR!U117 -> 650000000000 | Y90: =DTR!V117 -> 650000000000 | ... AC90: =DTR!Z117 -> 650000000000 | AD90: =IF($AD$26=1,R90,SUM(OFFSET(R90:AC90,0,0,1,$AD$26))-SUM(OFFSET(R90:AC90,0,0,1,$AD$26-1))) -> 650000000000 | AE90: =IF($AD$26=1,R90,SUM(OFFSET(R90:AC90,0,0,1,$AD$26))-SUM(OFFSET(R90:AC90,0,0,1,$AD$26-1))) -> 650000000000 | AF90: =DTR!AA$117 -> 650000000000 | AG90: =DTR!AB$117 -> 650000000000 | AH90: =DTR!AC$117 -> 650000000000 | AI90: =DTR!AD$117 -> 650000000000 | AJ90: =DTR!AE$117 -> 650000000000 | AK90: =DTR!AF$117 -> 0 | AL90: =DTR!AG$117 -> 0 | AM90: =DTR!AH$117 -> 0 | ... AQ90: =DTR!AL$117 -> 0 | AR90: =IF($AR$26=1,AF90,SUM(OFFSET(AF90:AQ90,0,0,1,$AR$26))-SUM(OFFSET(AF90:AQ90,0,0,1,$AR$26-1))) -> 650000000000 | AS90: =IF($AR$26=1,AF90,SUM(OFFSET(AF90:AQ90,0,0,1,$AR$26))-SUM(OFFSET(AF90:AQ90,0,0,1,$AR$26-1))) -> 650000000000
A91: B18 | B91: DTR | D91: Retained earnings | E91: =DTR!C128 -> 153168048821 | F91: =DTR!D128 -> 147897400024 | G91: =DTR!E128 -> 144938090423 | H91: =DTR!F128 -> 147413337163 | I91: =DTR!G128 -> 143259934823 | J91: =DTR!H128 -> 133044486756 | K91: =DTR!I128 -> 119519801263 | L91: =DTR!J128 -> 111236853278 | ... P91: =DTR!N128 -> 204759655867 | Q91: =IF($AD$26=1,E91,SUM(OFFSET(E91:P91,0,0,1,$AD$26))-SUM(OFFSET(E91:P91,0,0,1,$AD$26-1))) -> 143259934823 | R91: =DTR!O128 -> 209656736419 | S91: =DTR!P128 -> 227057533148 | T91: =DTR!Q128 -> 234155782207 | U91: =DTR!R128 -> 237906765692 | V91: =DTR!S128 -> 247436969996 | W91: =DTR!T128 -> 248509470753 | X91: =DTR!U128 -> 249548988610 | Y91: =DTR!V128 -> 249642208341 | ... AC91: =DTR!Z128 -> 230496410801 | AD91: =IF($AD$26=1,R91,SUM(OFFSET(R91:AC91,0,0,1,$AD$26))-SUM(OFFSET(R91:AC91,0,0,1,$AD$26-1))) -> 247436969996 | AE91: =IF($AD$26=1,R91,SUM(OFFSET(R91:AC91,0,0,1,$AD$26))-SUM(OFFSET(R91:AC91,0,0,1,$AD$26-1))) -> 247436969996 | AF91: =DTR!AA$128 -> 228802950065 | AG91: =DTR!AB$128 -> 222383736327 | AH91: =DTR!AC$128 -> 215718329703 | AI91: =DTR!AD$128 -> 219422083915 | AJ91: =DTR!AE$128 -> 227649509332 | AK91: =DTR!AF$128 -> 0 | AL91: =DTR!AG$128 -> 0 | AM91: =DTR!AH$128 -> 0 | ... AQ91: =DTR!AL$128 -> 0 | AR91: =IF($AR$26=1,AF91,SUM(OFFSET(AF91:AQ91,0,0,1,$AR$26))-SUM(OFFSET(AF91:AQ91,0,0,1,$AR$26-1))) -> 227649509332 | AS91: =IF($AR$26=1,AF91,SUM(OFFSET(AF91:AQ91,0,0,1,$AR$26))-SUM(OFFSET(AF91:AQ91,0,0,1,$AR$26-1))) -> 227649509332
A92: B19 | B92: DTR | D92: Total Resources | E92: =DTR!C131 -> 1057106496455 | F92: =DTR!D131 -> 1040899556726 | G92: =DTR!E131 -> 1086669152157 | H92: =DTR!F131 -> 1148318840816 | I92: =DTR!G131 -> 1198063045295 | J92: =DTR!H131 -> 1227310309881 | K92: =DTR!I131 -> 1174913086353 | L92: =DTR!J131 -> 1123552712261 | ... P92: =DTR!N131 -> 1255526266731 | Q92: =IF($AD$26=1,E92,SUM(OFFSET(E92:P92,0,0,1,$AD$26))-SUM(OFFSET(E92:P92,0,0,1,$AD$26-1))) -> 1198063045295 | R92: =DTR!O131 -> 1184167227046 | S92: =DTR!P131 -> 1099673392126 | T92: =DTR!Q131 -> 1153710875298 | U92: =DTR!R131 -> 1224376777626 | V92: =DTR!S131 -> 1280979662011 | W92: =DTR!T131 -> 1310961670922 | X92: =DTR!U131 -> 1296565798277 | Y92: =DTR!V131 -> 1356526045802 | ... AC92: =DTR!Z131 -> 1266017714532 | AD92: =IF($AD$26=1,R92,SUM(OFFSET(R92:AC92,0,0,1,$AD$26))-SUM(OFFSET(R92:AC92,0,0,1,$AD$26-1))) -> 1280979662011 | AE92: =IF($AD$26=1,R92,SUM(OFFSET(R92:AC92,0,0,1,$AD$26))-SUM(OFFSET(R92:AC92,0,0,1,$AD$26-1))) -> 1280979662011 | AF92: =DTR!AA$131 -> 1211566398236 | AG92: =DTR!AB$131 -> 1233002251518 | AH92: =DTR!AC$131 -> 1192063370403 | AI92: =DTR!AD$131 -> 1173001139790 | AJ92: =DTR!AE$131 -> 1251902380916 | AK92: =DTR!AF$131 -> 0 | AL92: =DTR!AG$131 -> 0 | AM92: =DTR!AH$131 -> 0 | ... AQ92: =DTR!AL$131 -> 0 | AR92: =IF($AR$26=1,AF92,SUM(OFFSET(AF92:AQ92,0,0,1,$AR$26))-SUM(OFFSET(AF92:AQ92,0,0,1,$AR$26-1))) -> 1251902380916 | AS92: =IF($AR$26=1,AF92,SUM(OFFSET(AF92:AQ92,0,0,1,$AR$26))-SUM(OFFSET(AF92:AQ92,0,0,1,$AR$26-1))) -> 1251902380916
B93: DTR | D93: Operating Expense | E93: =SUM(E47:E51)+SUM(E58:E59)+E64 -> 15301449343 | F93: =SUM(F47:F51)+SUM(F58:F59)+F64 -> 13873740837 | G93: =SUM(G47:G51)+SUM(G58:G59)+G64 -> 20712853309 | H93: =SUM(H47:H51)+SUM(H58:H59)+H64 -> 19330106722 | I93: =SUM(I47:I51)+SUM(I58:I59)+I64 -> 21375798228 | J93: =SUM(J47:J51)+SUM(J58:J59)+J64 -> 20743137066 | K93: =SUM(K47:K51)+SUM(K58:K59)+K64 -> 19696084735 | L93: =SUM(L47:L51)+SUM(L58:L59)+L64 -> 21459303344 | ... P93: =SUM(P47:P51)+SUM(P58:P59)+P64 -> 25170049427 | Q93: =SUM(OFFSET(E93:P93,0,0,1,$AD$26)) -> 90593948439 | R93: =SUM(R47:R51)+SUM(R58:R59)+R64 -> 23429032258 | S93: =SUM(S47:S51)+SUM(S58:S59)+S64 -> 22438832555 | T93: =SUM(T47:T51)+SUM(T58:T59)+T64 -> 24091469238 | U93: =SUM(U47:U51)+SUM(U58:U59)+U64 -> 24143191429 | V93: =SUM(V47:V51)+SUM(V58:V59)+V64 -> 24373096712 | W93: =SUM(W47:W51)+SUM(W58:W59)+W64 -> 24531919151 | X93: =SUM(X47:X51)+SUM(X58:X59)+X64 -> 25277267823 | Y93: =SUM(Y47:Y51)+SUM(Y58:Y59)+Y64 -> 25871125737 | ... AC93: =SUM(AC47:AC51)+SUM(AC58:AC59)+AC64 -> 33123811977 | AD93: =SUM(OFFSET(R93:AC93,0,0,1,$AD$26)) -> 118475622192 | AE93: =IF($AD$26=1,R93,SUM(OFFSET(R93:AC93,0,0,1,$AD$26))-SUM(OFFSET(R93:AC93,0,0,1,$AD$26-1))) -> 24373096712 | AF93: =SUM(AF47:AF51)+SUM(AF58:AF59)+AF64 -> 25963949522 | AG93: =SUM(AG47:AG51)+SUM(AG58:AG59)+AG64 -> 23532808125 | AH93: =SUM(AH47:AH51)+SUM(AH58:AH59)+AH64 -> 25171219709 | AI93: =SUM(AI47:AI51)+SUM(AI58:AI59)+AI64 -> 26897182055 | AJ93: =SUM(AJ47:AJ51)+SUM(AJ58:AJ59)+AJ64 -> 26727000618 | AK93: =SUM(AK47:AK51)+SUM(AK58:AK59)+AK64 -> 2.7758743e+10 | AL93: =SUM(AL47:AL51)+SUM(AL58:AL59)+AL64 -> 2.7601429e+10 | AM93: =SUM(AM47:AM51)+SUM(AM58:AM59)+AM64 -> 2.7642839e+10 | ... AQ93: =SUM(AQ47:AQ51)+SUM(AQ58:AQ59)+AQ64 -> 2.9964083e+10 | AR93: =SUM(OFFSET(AF93:AQ93,0,0,1,$AR$26)) -> 128292160029 | AS93: =IF($AR$26=1,AF93,SUM(OFFSET(AF93:AQ93,0,0,1,$AR$26))-SUM(OFFSET(AF93:AQ93,0,0,1,$AR$26-1))) -> 26727000618
B94: DTR | D94: Number of Share | E94: =DTR!C117/10000 -> 65000000 | F94: =DTR!D117/10000 -> 65000000 | G94: =DTR!E117/10000 -> 65000000 | H94: =DTR!F117/10000 -> 65000000 | I94: =DTR!G117/10000 -> 65000000 | J94: =DTR!H117/10000 -> 65000000 | K94: =DTR!I117/10000 -> 65000000 | L94: =DTR!J117/10000 -> 65000000 | ... P94: =DTR!N117/10000 -> 65000000 | Q94: =IF($AD$26=1,E94,SUM(OFFSET(E94:P94,0,0,1,$AD$26))-SUM(OFFSET(E94:P94,0,0,1,$AD$26-1))) -> 65000000 | R94: =DTR!O117/10000 -> 65000000 | S94: =DTR!P117/10000 -> 65000000 | T94: =DTR!Q117/10000 -> 65000000 | U94: =DTR!R117/10000 -> 65000000 | V94: =DTR!S117/10000 -> 65000000 | W94: =DTR!T117/10000 -> 65000000 | X94: =DTR!U117/10000 -> 65000000 | Y94: =DTR!V117/10000 -> 65000000 | ... AC94: =DTR!Z117/10000 -> 65000000 | AD94: =IF($AD$26=1,R94,SUM(OFFSET(R94:AC94,0,0,1,$AD$26))-SUM(OFFSET(R94:AC94,0,0,1,$AD$26-1))) -> 65000000 | AE94: =IF($AD$26=1,R94,SUM(OFFSET(R94:AC94,0,0,1,$AD$26))-SUM(OFFSET(R94:AC94,0,0,1,$AD$26-1))) -> 65000000 | AF94: =DTR!AA$117/10000 -> 65000000 | AG94: =DTR!AB$117/10000 -> 65000000 | AH94: =DTR!AC$117/10000 -> 65000000 | AI94: =DTR!AD$117/10000 -> 65000000 | AJ94: =DTR!AE$117/10000 -> 65000000 | AK94: =DTR!AF$117/10000 -> 0 | AL94: =DTR!AG$117/10000 -> 0 | AM94: =DTR!AH$117/10000 -> 0 | ... AQ94: =DTR!AL$117/10000 -> 0 | AR94: =IF($AR$26=1,AF94,SUM(OFFSET(AF94:AQ94,0,0,1,$AR$26))-SUM(OFFSET(AF94:AQ94,0,0,1,$AR$26-1))) -> 65000000 | AS94: =IF($AR$26=1,AF94,SUM(OFFSET(AF94:AQ94,0,0,1,$AR$26))-SUM(OFFSET(AF94:AQ94,0,0,1,$AR$26-1))) -> 65000000
A95: C01 | B95: DTR | D95: Profit before taxes | E95: =DTR!C157 -> -729878180 | F95: =DTR!D157 -> -5270648797 | G95: =DTR!E157 -> -2959309601 | H95: =DTR!F157 -> 2475246740 | I95: =DTR!G157 -> -4153402340 | J95: =DTR!H157 -> -10215448067 | K95: =DTR!I157 -> -13524685493 | L95: =DTR!J157 -> -8282947985 | ... P95: =DTR!N157 -> 105403947594 | Q95: =SUM(OFFSET(E95:P95,0,0,1,$AD$26)) -> -10637992178 | R95: =DTR!O157 -> 5761271238 | S95: =DTR!P157 -> 20413496509 | T95: =DTR!Q157 -> 8350881246 | U95: =DTR!R157 -> 4428276973 | V95: =DTR!S157 -> 11212005063 | W95: =DTR!T157 -> 1261765596 | X95: =DTR!U157 -> -1791468483 | Y95: =DTR!V157 -> 297419333 | ... AC95: =DTR!Z157 -> 5991671450 | AD95: =SUM(OFFSET(R95:AC95,0,0,1,$AD$26)) -> 50165931029 | AE95: =IF($AD$26=1,R95,SUM(OFFSET(R95:AC95,0,0,1,$AD$26))-SUM(OFFSET(R95:AC95,0,0,1,$AD$26-1))) -> 11212005063 | AF95: =DTR!AA$157 -> -1693460736 | AG95: =DTR!AB$157 -> -6419213738 | AH95: =DTR!AC$157 -> -6818467491 | AI95: =DTR!AD$157 -> 3703754212 | AJ95: =DTR!AE$157 -> 8181583918 | AK95: =DTR!AF$157 -> 0 | AL95: =DTR!AG$157 -> 0 | AM95: =DTR!AH$157 -> 0 | ... AQ95: =DTR!AL$157 -> 0 | AR95: =SUM(OFFSET(AF95:AQ95,0,0,1,$AR$26)) -> -3045803835 | AS95: =IF($AR$26=1,AF95,SUM(OFFSET(AF95:AQ95,0,0,1,$AR$26))-SUM(OFFSET(AF95:AQ95,0,0,1,$AR$26-1))) -> 8181583918
A96: C02 | B96: DTR | D96: Depreciation & Amortization | E96: =DTR!C159 -> 2998479509 | F96: =DTR!D159 -> 3003358762 | G96: =DTR!E159 -> 2998978933 | H96: =DTR!F159 -> 3181024399 | I96: =DTR!G159 -> 3238724278 | J96: =DTR!H159 -> 3240440023 | K96: =DTR!I159 -> 3274496481 | L96: =DTR!J159 -> 3295429795 | ... P96: =DTR!N159 -> 3762460661 | Q96: =SUM(OFFSET(E96:P96,0,0,1,$AD$26)) -> 15420565881 | R96: =DTR!O159 -> 3803154168 | S96: =DTR!P159 -> 3804698614 | T96: =DTR!Q159 -> 4002633975 | U96: =DTR!R159 -> 3905195928 | V96: =DTR!S159 -> 4091854986 | W96: =DTR!T159 -> 4087468338 | X96: =DTR!U159 -> 4085457551 | Y96: =DTR!V159 -> 4092995160 | ... AC96: =DTR!Z159 -> 4442318343 | AD96: =SUM(OFFSET(R96:AC96,0,0,1,$AD$26)) -> 19607537671 | AE96: =IF($AD$26=1,R96,SUM(OFFSET(R96:AC96,0,0,1,$AD$26))-SUM(OFFSET(R96:AC96,0,0,1,$AD$26-1))) -> 4091854986 | AF96: =DTR!AA$159 -> 2133968845 | AG96: =DTR!AB$159 -> 2103008488 | AH96: =DTR!AC$159 -> 2118111558 | AI96: =DTR!AD$159 -> 2277961573 | AJ96: =DTR!AE$159 -> 2330977557 | AK96: =DTR!AF$159 -> 0 | AL96: =DTR!AG$159 -> 0 | AM96: =DTR!AH$159 -> 0 | ... AQ96: =DTR!AL$159 -> 0 | AR96: =AF96 -> 2133968845 | AS96: =IF($AR$26=1,AF96,SUM(OFFSET(AF96:AQ96,0,0,1,$AR$26))-SUM(OFFSET(AF96:AQ96,0,0,1,$AR$26-1))) -> 2330977557
A97: C03 | B97: DTR | D97: Adjustment for | E97: =SUM(DTR!C160:C164) -> 367476086 | F97: =SUM(DTR!D160:D164) -> 136535641 | G97: =SUM(DTR!E160:E164) -> 76229245 | H97: =SUM(DTR!F160:F164) -> 597587201 | I97: =SUM(DTR!G160:G164) -> 142834002 | J97: =SUM(DTR!H160:H164) -> 845006037 | K97: =SUM(DTR!I160:I164) -> 979573206 | L97: =SUM(DTR!J160:J164) -> 674609648 | ... P97: =SUM(DTR!N160:N164) -> -1593107972 | Q97: =SUM(OFFSET(E97:P97,0,0,1,$AD$26)) -> 1320662175 | R97: =SUM(DTR!O160:O164) -> -16621815 | S97: =SUM(DTR!P160:P164) -> -1250528260 | T97: =SUM(DTR!Q160:Q164) -> 64316884 | U97: =SUM(DTR!R160:R164) -> 228499749 | V97: =SUM(DTR!S160:S164) -> -458006811 | W97: =SUM(DTR!T160:T164) -> 802866683 | X97: =SUM(DTR!U160:U164) -> 483271069 | Y97: =SUM(DTR!V160:V164) -> 681254223 | ... AC97: =SUM(DTR!Z160:Z164) -> 665670545 | AD97: =SUM(OFFSET(R97:AC97,0,0,1,$AD$26)) -> -1432340253 | AE97: =IF($AD$26=1,R97,SUM(OFFSET(R97:AC97,0,0,1,$AD$26))-SUM(OFFSET(R97:AC97,0,0,1,$AD$26-1))) -> -458006811 | AF97: =SUM(DTR!AA$160:AA$164) -> 956028091 | AG97: =SUM(DTR!AB$160:AB$164) -> 959170047 | AH97: =SUM(DTR!AC$160:AC$164) -> -1814690175 | AI97: =SUM(DTR!AD$160:AD$164) -> 242600584 | AJ97: =SUM(DTR!AE$160:AE$164) -> 146904400 | AK97: =SUM(DTR!AF$160:AF$164) -> 0 | AL97: =SUM(DTR!AG$160:AG$164) -> 0 | AM97: =SUM(DTR!AH$160:AH$164) -> 0 | ... AQ97: =SUM(DTR!AL$160:AL$164) -> 0 | AR97: =SUM(OFFSET(AF97:AQ97,0,0,1,$AR$26)) -> 490012947 | AS97: =IF($AR$26=1,AF97,SUM(OFFSET(AF97:AQ97,0,0,1,$AR$26))-SUM(OFFSET(AF97:AQ97,0,0,1,$AR$26-1))) -> 146904400
A98: C04 | B98: DTR | D98: Profit from Business activities | E98: =DTR!C165 -> 2636077415 | F98: =DTR!D165 -> -2130754394 | G98: =DTR!E165 -> 115898577 | H98: =DTR!F165 -> 6253858340 | I98: =DTR!G165 -> -771844060 | J98: =DTR!H165 -> -6130002007 | K98: =DTR!I165 -> -9270615806 | L98: =DTR!J165 -> -4312908542 | ... P98: =DTR!N165 -> 107573300283 | Q98: =SUM(OFFSET(E98:P98,0,0,1,$AD$26)) -> 6103235878 | R98: =DTR!O165 -> 9547803591 | S98: =DTR!P165 -> 22967666863 | T98: =DTR!Q165 -> 12417832105 | U98: =DTR!R165 -> 8561972650 | V98: =DTR!S165 -> 14845853238 | W98: =DTR!T165 -> 6152100617 | X98: =DTR!U165 -> 2777260137 | Y98: =DTR!V165 -> 5071668716 | ... AC98: =DTR!Z165 -> 11099660338 | AD98: =SUM(OFFSET(R98:AC98,0,0,1,$AD$26)) -> 68341128447 | AE98: =IF($AD$26=1,R98,SUM(OFFSET(R98:AC98,0,0,1,$AD$26))-SUM(OFFSET(R98:AC98,0,0,1,$AD$26-1))) -> 14845853238 | AF98: =DTR!AA$165 -> 1396536200 | AG98: =DTR!AB$165 -> -3357035203 | AH98: =DTR!AC$165 -> -6515046108 | AI98: =DTR!AD$165 -> 6224316369 | AJ98: =DTR!AE$165 -> 10659465875 | AK98: =DTR!AF$165 -> 0 | AL98: =DTR!AG$165 -> 0 | AM98: =DTR!AH$165 -> 0 | ... AQ98: =DTR!AL$165 -> 0 | AR98: =SUM(OFFSET(AF98:AQ98,0,0,1,$AR$26)) -> 8408237133 | AS98: =IF($AR$26=1,AF98,SUM(OFFSET(AF98:AQ98,0,0,1,$AR$26))-SUM(OFFSET(AF98:AQ98,0,0,1,$AR$26-1))) -> 10659465875
A99: C05 | B99: DTR | D99: Increase/decrease in account receivables | E99: =DTR!C166 -> -5652437642 | F99: =DTR!D166 -> 12718033317 | G99: =DTR!E166 -> -27842598162 | H99: =DTR!F166 -> -18112988822 | I99: =DTR!G166 -> -13542246944 | J99: =DTR!H166 -> -22167334330 | K99: =DTR!I166 -> 85173759375 | L99: =DTR!J166 -> -23854718494 | ... P99: =DTR!N166 -> 48930483720 | Q99: =SUM(OFFSET(E99:P99,0,0,1,$AD$26)) -> -52432238253 | R99: =DTR!O166 -> 48855114582 | S99: =DTR!P166 -> -44766736418 | T99: =DTR!Q166 -> -37871215662 | U99: =DTR!R166 -> 28625577432 | V99: =DTR!S166 -> -55448925268 | W99: =DTR!T166 -> 720428098 | X99: =DTR!U166 -> 256498082 | Y99: =DTR!V166 -> -61126022727 | ... AC99: =DTR!Z166 -> -17408925524 | AD99: =SUM(OFFSET(R99:AC99,0,0,1,$AD$26)) -> -60606185334 | AE99: =IF($AD$26=1,R99,SUM(OFFSET(R99:AC99,0,0,1,$AD$26))-SUM(OFFSET(R99:AC99,0,0,1,$AD$26-1))) -> -55448925268 | AF99: =DTR!AA$166 -> 27691290746 | AG99: =DTR!AB$166 -> -17620075226 | AH99: =DTR!AC$166 -> -26617409794 | AI99: =DTR!AD$166 -> 13431110240 | AJ99: =DTR!AE$166 -> -97423755750 | AK99: =DTR!AF$166 -> 0 | AL99: =DTR!AG$166 -> 0 | AM99: =DTR!AH$166 -> 0 | ... AQ99: =DTR!AL$166 -> 0 | AR99: =SUM(OFFSET(AF99:AQ99,0,0,1,$AR$26)) -> -100538839784 | AS99: =IF($AR$26=1,AF99,SUM(OFFSET(AF99:AQ99,0,0,1,$AR$26))-SUM(OFFSET(AF99:AQ99,0,0,1,$AR$26-1))) -> -97423755750
A100: C06 | B100: DTR | D100: Increase/decrease in inventory | E100: =DTR!C167 -> -62048923911 | F100: =DTR!D167 -> -6967205423 | G100: =DTR!E167 -> -41958712604 | H100: =DTR!F167 -> -40309960571 | I100: =DTR!G167 -> -45123242085 | J100: =DTR!H167 -> -25153534354 | K100: =DTR!I167 -> -23609068040 | L100: =DTR!J167 -> 40963897237 | ... P100: =DTR!N167 -> -17812326753 | Q100: =SUM(OFFSET(E100:P100,0,0,1,$AD$26)) -> -196408044594 | R100: =DTR!O167 -> 39011677209 | S100: =DTR!P167 -> 82988328541 | T100: =DTR!Q167 -> 15465577608 | U100: =DTR!R167 -> -54309944038 | V100: =DTR!S167 -> -3833514940 | W100: =DTR!T167 -> -17092818286 | X100: =DTR!U167 -> -5007590876 | Y100: =DTR!V167 -> 325978186 | ... AC100: =DTR!Z167 -> -11864351833 | AD100: =SUM(OFFSET(R100:AC100,0,0,1,$AD$26)) -> 79322124380 | AE100: =IF($AD$26=1,R100,SUM(OFFSET(R100:AC100,0,0,1,$AD$26))-SUM(OFFSET(R100:AC100,0,0,1,$AD$26-1))) -> -3833514940 | AF100: =DTR!AA$167 -> 28329195342 | AG100: =DTR!AB$167 -> 31559998874 | AH100: =DTR!AC$167 -> 77094855201 | AI100: =DTR!AD$167 -> 55037438938 | AJ100: =DTR!AE$167 -> 8532767673 | AK100: =DTR!AF$167 -> 0 | AL100: =DTR!AG$167 -> 0 | AM100: =DTR!AH$167 -> 0 | ... AQ100: =DTR!AL$167 -> 0 | AR100: =SUM(OFFSET(AF100:AQ100,0,0,1,$AR$26)) -> 200554256028 | AS100: =IF($AR$26=1,AF100,SUM(OFFSET(AF100:AQ100,0,0,1,$AR$26))-SUM(OFFSET(AF100:AQ100,0,0,1,$AR$26-1))) -> 8532767673
A101: C07 | B101: DTR | D101: Increase/decrease in account payables | E101: =DTR!C168 -> 4207075109 | F101: =DTR!D168 -> 3916411982 | G101: =DTR!E168 -> 13622200989 | H101: =DTR!F168 -> 17907838314 | I101: =DTR!G168 -> 29819590224 | J101: =DTR!H168 -> 29796216577 | K101: =DTR!I168 -> 17066288696 | L101: =DTR!J168 -> 12068637446 | ... P101: =DTR!N168 -> -141135934090 | Q101: =SUM(OFFSET(E101:P101,0,0,1,$AD$26)) -> 69473116618 | R101: =DTR!O168 -> -18846487637 | S101: =DTR!P168 -> -3242891008 | T101: =DTR!Q168 -> -10856648380 | U101: =DTR!R168 -> -15817906933 | V101: =DTR!S168 -> 21901299832 | W101: =DTR!T168 -> 14884971711 | X101: =DTR!U168 -> -23926762811 | Y101: =DTR!V168 -> 16989265000 | ... AC101: =DTR!Z168 -> -3419997293 | AD101: =SUM(OFFSET(R101:AC101,0,0,1,$AD$26)) -> -26862634126 | AE101: =IF($AD$26=1,R101,SUM(OFFSET(R101:AC101,0,0,1,$AD$26))-SUM(OFFSET(R101:AC101,0,0,1,$AD$26-1))) -> 21901299832 | AF101: =DTR!AA$168 -> -5147235213 | AG101: =DTR!AB$168 -> -9100141912 | AH101: =DTR!AC$168 -> 9288982043 | AI101: =DTR!AD$168 -> 9456557035 | AJ101: =DTR!AE$168 -> 26805727933 | AK101: =DTR!AF$168 -> 0 | AL101: =DTR!AG$168 -> 0 | AM101: =DTR!AH$168 -> 0 | ... AQ101: =DTR!AL$168 -> 0 | AR101: =SUM(OFFSET(AF101:AQ101,0,0,1,$AR$26)) -> 31303889886 | AS101: =IF($AR$26=1,AF101,SUM(OFFSET(AF101:AQ101,0,0,1,$AR$26))-SUM(OFFSET(AF101:AQ101,0,0,1,$AR$26-1))) -> 26805727933
A102: C08 | B102: DTR | D102: Interest paid | E102: =DTR!C171 -> -422755791 | F102: =DTR!D171 -> -563909516 | G102: =DTR!E171 -> -567924561 | H102: =DTR!F171 -> -840791009 | I102: =DTR!G171 -> -961855770 | J102: =DTR!H171 -> -1030712173 | K102: =DTR!I171 -> -1160823006 | L102: =DTR!J171 -> -939585045 | ... P102: =DTR!N171 -> -1032562923 | Q102: =SUM(OFFSET(E102:P102,0,0,1,$AD$26)) -> -3357236647 | R102: =DTR!O171 -> -739360517 | S102: =DTR!P171 -> -1303843040 | T102: =DTR!Q171 -> -673966789 | U102: =DTR!R171 -> -888393452 | V102: =DTR!S171 -> -1186588729 | W102: =DTR!T171 -> -1448899822 | X102: =DTR!U171 -> -1242023326 | Y102: =DTR!V171 -> -1303560910 | ... AC102: =DTR!Z171 -> -1256103396 | AD102: =SUM(OFFSET(R102:AC102,0,0,1,$AD$26)) -> -4792152527 | AE102: =IF($AD$26=1,R102,SUM(OFFSET(R102:AC102,0,0,1,$AD$26))-SUM(OFFSET(R102:AC102,0,0,1,$AD$26-1))) -> -1186588729 | AF102: =DTR!AA$171 -> -1240115065 | AG102: =DTR!AB$171 -> -1156279418 | AH102: =DTR!AC$171 -> -959718564 | AI102: =DTR!AD$171 -> -1062084475 | AJ102: =DTR!AE$171 -> -838836791 | AK102: =DTR!AF$171 -> 0 | AL102: =DTR!AG$171 -> 0 | AM102: =DTR!AH$171 -> 0 | ... AQ102: =DTR!AL$171 -> 0 | AR102: =SUM(OFFSET(AF102:AQ102,0,0,1,$AR$26)) -> -5257034313 | AS102: =IF($AR$26=1,AF102,SUM(OFFSET(AF102:AQ102,0,0,1,$AR$26))-SUM(OFFSET(AF102:AQ102,0,0,1,$AR$26-1))) -> -838836791
A103: C09 | B103: DTR | D103: Increase/decrease others | E103: =SUM(DTR!C169:C170,DTR!C172:C174) -> 33513063058 | F103: =SUM(DTR!D169:D170,DTR!D172:D174) -> -6372627736 | G103: =SUM(DTR!E169:E170,DTR!E172:E174) -> -2626029698 | H103: =SUM(DTR!F169:F170,DTR!F172:F174) -> 2912013073 | I103: =SUM(DTR!G169:G170,DTR!G172:G174) -> 0 | J103: =SUM(DTR!H169:H170,DTR!H172:H174) -> -168183405 | K103: =SUM(DTR!I169:I170,DTR!I172:I174) -> -12018343230 | L103: =SUM(DTR!J169:J170,DTR!J172:J174) -> 0 | ... P103: =SUM(DTR!N169:N170,DTR!N172:N174) -> 1000976009 | Q103: =SUM(OFFSET(E103:P103,0,0,1,$AD$26)) -> 27426418697 | R103: =SUM(DTR!O169:O170,DTR!O172:O174) -> 110283488 | S103: =SUM(DTR!P169:P170,DTR!P172:P174) -> -4175776372 | T103: =SUM(DTR!Q169:Q170,DTR!Q172:Q174) -> 601863673 | U103: =SUM(DTR!R169:R170,DTR!R172:R174) -> 1249320119 | V103: =SUM(DTR!S169:S170,DTR!S172:S174) -> 1913803036 | W103: =SUM(DTR!T169:T170,DTR!T172:T174) -> -5497715935 | X103: =SUM(DTR!U169:U170,DTR!U172:U174) -> -592614643 | Y103: =SUM(DTR!V169:V170,DTR!V172:V174) -> -371361391 | ... AC103: =SUM(DTR!Z169:Z170,DTR!Z172:Z174) -> 374694148 | AD103: =SUM(OFFSET(R103:AC103,0,0,1,$AD$26)) -> -300506056 | AE103: =IF($AD$26=1,R103,SUM(OFFSET(R103:AC103,0,0,1,$AD$26))-SUM(OFFSET(R103:AC103,0,0,1,$AD$26-1))) -> 1913803036 | AF103: =SUM(DTR!AA$169:AA$170,DTR!AA$172:AA$174) -> 1820605679 | AG103: =SUM(DTR!AB$169:AB$170,DTR!AB$172:AB$174) -> 1054820971 | AH103: =SUM(DTR!AC$169:AC$170,DTR!AC$172:AC$174) -> -171978952 | AI103: =SUM(DTR!AD$169:AD$170,DTR!AD$172:AD$174) -> -392776099 | AJ103: =SUM(DTR!AE$169:AE$170,DTR!AE$172:AE$174) -> -877993234 | AK103: =SUM(DTR!AF$169:AF$170,DTR!AF$172:AF$174) -> 0 | AL103: =SUM(DTR!AG$169:AG$170,DTR!AG$172:AG$174) -> 0 | AM103: =SUM(DTR!AH$169:AH$170,DTR!AH$172:AH$174) -> 0 | ... AQ103: =SUM(DTR!AL$169:AL$170,DTR!AL$172:AL$174) -> 0 | AR103: =SUM(OFFSET(AF103:AQ103,0,0,1,$AR$26)) -> 1432678365 | AS103: =IF($AR$26=1,AF103,SUM(OFFSET(AF103:AQ103,0,0,1,$AR$26))-SUM(OFFSET(AF103:AQ103,0,0,1,$AR$26-1))) -> -877993234
...

Sheet FS matrix
A1: VN | B1: FINANCIAL STATEMENT | C1: =IF(A1="EN",B1,"BÁO CÁO TÀI CHÍNH") -> BÁO CÁO TÀI CHÍNH | I1: Excel | K1: Effect | L1: Effect | R1: Effect | S1: Excel | T1: Effect | V1: Tháng | W1: =_xlfn.XLOOKUP(Y1,Performance!H1:I1,Performance!H2:I2) -> 5 | X1: =IF(A1="EN","Year","Năm") -> Năm | Y1: 2026 | AA1: =IF(A1="EN","Unit: m VND","Đvt : Triệu đồng") -> Đvt : Triệu đồng
B2: PROFIT & LOSS | C2: =IF($A$1="EN",B2,"KẾT QUẢ KINH DOANH") -> KẾT QUẢ KINH DOANH | D2: DTR
A3: P01 | B3: Production volume | C3: =IF($A$1="EN",B3,"Sản lượng sản xuất") -> Sản lượng sản xuất | D3: {=IF($V$1="Tháng", _xlfn.SWITCH(TRUE(), $Y$1=2025,SUMIFS(Data!$AE:$AE,Data!$B:$B,'FS matrix'!D$2,Data!$D:$D,'FS matrix'!$B3), $Y$1=2026,SUMIFS(Data!$AS:$AS,Data!$B:$B,'FS matrix'!D$2,Data!$D:$D,'FS matrix'!$B3)), _xlfn.SWITCH(TRUE(), $Y$1=2025,SUMIFS(Data!$AD:$AD,Data!$B:$B,'FS matrix'!D$2,Data!$D:$D,'FS matrix'!$B3), $Y$1=2026,SUMIFS(Data!$AR:$AR,Data!$B:$B,'FS matrix'!D$2,Data!$D:$D,'FS matrix'!$B3)))} -> 3592.682
A4: P02 | B4: Sales volume | C4: =IF($A$1="EN",B4,"Sản lượng bán") -> Sản lượng bán | D4: {=IF($V$1="Tháng", _xlfn.SWITCH(TRUE(), $Y$1=2025,SUMIFS(Data!$AE:$AE,Data!$B:$B,'FS matrix'!D$2,Data!$D:$D,'FS matrix'!$B4), $Y$1=2026,SUMIFS(Data!$AS:$AS,Data!$B:$B,'FS matrix'!D$2,Data!$D:$D,'FS matrix'!$B4)), _xlfn.SWITCH(TRUE(), $Y$1=2025,SUMIFS(Data!$AD:$AD,Data!$B:$B,'FS matrix'!D$2,Data!$D:$D,'FS matrix'!$B4), $Y$1=2026,SUMIFS(Data!$AR:$AR,Data!$B:$B,'FS matrix'!D$2,Data!$D:$D,'FS matrix'!$B4)))} -> 5140.924
A5: P03 | B5: NET SALES | C5: =IF($A$1="EN",B5,"Doanh thu thuần") -> Doanh thu thuần | D5: {=IF($V$1="Tháng", _xlfn.SWITCH(TRUE(), $Y$1=2025,SUMIFS(Data!$AE:$AE,Data!$B:$B,'FS matrix'!D$2,Data!$D:$D,'FS matrix'!$B5), $Y$1=2026,SUMIFS(Data!$AS:$AS,Data!$B:$B,'FS matrix'!D$2,Data!$D:$D,'FS matrix'!$B5)), _xlfn.SWITCH(TRUE(), $Y$1=2025,SUMIFS(Data!$AD:$AD,Data!$B:$B,'FS matrix'!D$2,Data!$D:$D,'FS matrix'!$B5), $Y$1=2026,SUMIFS(Data!$AR:$AR,Data!$B:$B,'FS matrix'!D$2,Data!$D:$D,'FS matrix'!$B5)))} -> 159765309037
A6: P04 | B6: Export | C6: =IF($A$1="EN",B6,"Xuất khẩu") -> Xuất khẩu | D6: {=IF($V$1="Tháng", _xlfn.SWITCH(TRUE(), $Y$1=2025,SUMIFS(Data!$AE:$AE,Data!$B:$B,'FS matrix'!D$2,Data!$D:$D,'FS matrix'!$B6), $Y$1=2026,SUMIFS(Data!$AS:$AS,Data!$B:$B,'FS matrix'!D$2,Data!$D:$D,'FS matrix'!$B6)), _xlfn.SWITCH(TRUE(), $Y$1=2025,SUMIFS(Data!$AD:$AD,Data!$B:$B,'FS matrix'!D$2,Data!$D:$D,'FS matrix'!$B6), $Y$1=2026,SUMIFS(Data!$AR:$AR,Data!$B:$B,'FS matrix'!D$2,Data!$D:$D,'FS matrix'!$B6)))} -> 87346708460
A7: P05 | B7: Domestic | C7: =IF($A$1="EN",B7,"Trong nước") -> Trong nước | D7: {=IF($V$1="Tháng", _xlfn.SWITCH(TRUE(), $Y$1=2025,SUMIFS(Data!$AE:$AE,Data!$B:$B,'FS matrix'!D$2,Data!$D:$D,'FS matrix'!$B7), $Y$1=2026,SUMIFS(Data!$AS:$AS,Data!$B:$B,'FS matrix'!D$2,Data!$D:$D,'FS matrix'!$B7)), _xlfn.SWITCH(TRUE(), $Y$1=2025,SUMIFS(Data!$AD:$AD,Data!$B:$B,'FS matrix'!D$2,Data!$D:$D,'FS matrix'!$B7), $Y$1=2026,SUMIFS(Data!$AR:$AR,Data!$B:$B,'FS matrix'!D$2,Data!$D:$D,'FS matrix'!$B7)))} -> 70741575322
A8: P06 | B8: Others | C8: =IF($A$1="EN",B8,"Khác") -> Khác | D8: {=IF($V$1="Tháng", _xlfn.SWITCH(TRUE(), $Y$1=2025,SUMIFS(Data!$AE:$AE,Data!$B:$B,'FS matrix'!D$2,Data!$D:$D,'FS matrix'!$B8), $Y$1=2026,SUMIFS(Data!$AS:$AS,Data!$B:$B,'FS matrix'!D$2,Data!$D:$D,'FS matrix'!$B8)), _xlfn.SWITCH(TRUE(), $Y$1=2025,SUMIFS(Data!$AD:$AD,Data!$B:$B,'FS matrix'!D$2,Data!$D:$D,'FS matrix'!$B8), $Y$1=2026,SUMIFS(Data!$AR:$AR,Data!$B:$B,'FS matrix'!D$2,Data!$D:$D,'FS matrix'!$B8)))} -> 1677025255
A9: P07 | B9: Cost of Goods Sold (COGS) | C9: =IF($A$1="EN",B9,"Giá vốn hàng bán") -> Giá vốn hàng bán | D9: {=IF($V$1="Tháng", _xlfn.SWITCH(TRUE(), $Y$1=2025,SUMIFS(Data!$AE:$AE,Data!$B:$B,'FS matrix'!D$2,Data!$D:$D,'FS matrix'!$B9), $Y$1=2026,SUMIFS(Data!$AS:$AS,Data!$B:$B,'FS matrix'!D$2,Data!$D:$D,'FS matrix'!$B9)), _xlfn.SWITCH(TRUE(), $Y$1=2025,SUMIFS(Data!$AD:$AD,Data!$B:$B,'FS matrix'!D$2,Data!$D:$D,'FS matrix'!$B9), $Y$1=2026,SUMIFS(Data!$AR:$AR,Data!$B:$B,'FS matrix'!D$2,Data!$D:$D,'FS matrix'!$B9)))} -> 137580032058
A10: P08 | B10: Material cost | C10: =IF($A$1="EN",B10,"Chi phí nguyên vật liệu") -> Chi phí nguyên vật liệu | D10: {=IF($V$1="Tháng", _xlfn.SWITCH(TRUE(), $Y$1=2025,SUMIFS(Data!$AE:$AE,Data!$B:$B,'FS matrix'!D$2,Data!$D:$D,'FS matrix'!$B10), $Y$1=2026,SUMIFS(Data!$AS:$AS,Data!$B:$B,'FS matrix'!D$2,Data!$D:$D,'FS matrix'!$B10)), _xlfn.SWITCH(TRUE(), $Y$1=2025,SUMIFS(Data!$AD:$AD,Data!$B:$B,'FS matrix'!D$2,Data!$D:$D,'FS matrix'!$B10), $Y$1=2026,SUMIFS(Data!$AR:$AR,Data!$B:$B,'FS matrix'!D$2,Data!$D:$D,'FS matrix'!$B10)))} -> 1.0067611e+11
A11: P09 | B11: Electricity | C11: =IF($A$1="EN",B11,"Chi phí điện") -> Chi phí điện | D11: {=IF($V$1="Tháng", _xlfn.SWITCH(TRUE(), $Y$1=2025,SUMIFS(Data!$AE:$AE,Data!$B:$B,'FS matrix'!D$2,Data!$D:$D,'FS matrix'!$B11), $Y$1=2026,SUMIFS(Data!$AS:$AS,Data!$B:$B,'FS matrix'!D$2,Data!$D:$D,'FS matrix'!$B11)), _xlfn.SWITCH(TRUE(), $Y$1=2025,SUMIFS(Data!$AD:$AD,Data!$B:$B,'FS matrix'!D$2,Data!$D:$D,'FS matrix'!$B11), $Y$1=2026,SUMIFS(Data!$AR:$AR,Data!$B:$B,'FS matrix'!D$2,Data!$D:$D,'FS matrix'!$B11)))} -> 5769165884
A12: P10 | B12: Overtime | C12: =IF($A$1="EN",B12,"Lương ngoài giờ") -> Lương ngoài giờ | D12: {=IF($V$1="Tháng", _xlfn.SWITCH(TRUE(), $Y$1=2025,SUMIFS(Data!$AE:$AE,Data!$B:$B,'FS matrix'!D$2,Data!$D:$D,'FS matrix'!$B12), $Y$1=2026,SUMIFS(Data!$AS:$AS,Data!$B:$B,'FS matrix'!D$2,Data!$D:$D,'FS matrix'!$B12)), _xlfn.SWITCH(TRUE(), $Y$1=2025,SUMIFS(Data!$AD:$AD,Data!$B:$B,'FS matrix'!D$2,Data!$D:$D,'FS matrix'!$B12), $Y$1=2026,SUMIFS(Data!$AR:$AR,Data!$B:$B,'FS matrix'!D$2,Data!$D:$D,'FS matrix'!$B12)))} -> 354846806
A13: P11 | B13: Direct labor | C13: =IF($A$1="EN",B13,"Lương nhân công trực tiếp") -> Lương nhân công trực tiếp | D13: {=IF($V$1="Tháng", _xlfn.SWITCH(TRUE(), $Y$1=2025,SUMIFS(Data!$AE:$AE,Data!$B:$B,'FS matrix'!D$2,Data!$D:$D,'FS matrix'!$B13), $Y$1=2026,SUMIFS(Data!$AS:$AS,Data!$B:$B,'FS matrix'!D$2,Data!$D:$D,'FS matrix'!$B13)), _xlfn.SWITCH(TRUE(), $Y$1=2025,SUMIFS(Data!$AD:$AD,Data!$B:$B,'FS matrix'!D$2,Data!$D:$D,'FS matrix'!$B13), $Y$1=2026,SUMIFS(Data!$AR:$AR,Data!$B:$B,'FS matrix'!D$2,Data!$D:$D,'FS matrix'!$B13)))} -> 2407536723
A14: P12 | B14: Indirect labor | C14: =IF($A$1="EN",B14,"Lương nhân công gián tiếp") -> Lương nhân công gián tiếp | D14: {=IF($V$1="Tháng", _xlfn.SWITCH(TRUE(), $Y$1=2025,SUMIFS(Data!$AE:$AE,Data!$B:$B,'FS matrix'!D$2,Data!$D:$D,'FS matrix'!$B14), $Y$1=2026,SUMIFS(Data!$AS:$AS,Data!$B:$B,'FS matrix'!D$2,Data!$D:$D,'FS matrix'!$B14)), _xlfn.SWITCH(TRUE(), $Y$1=2025,SUMIFS(Data!$AD:$AD,Data!$B:$B,'FS matrix'!D$2,Data!$D:$D,'FS matrix'!$B14), $Y$1=2026,SUMIFS(Data!$AR:$AR,Data!$B:$B,'FS matrix'!D$2,Data!$D:$D,'FS matrix'!$B14)))} -> 4083134231
A15: P13 | B15: Employee welfare (FOH) | C15: =IF($A$1="EN",B15,"Phúc lợi nhân viên") -> Phúc lợi nhân viên | D15: {=IF($V$1="Tháng", _xlfn.SWITCH(TRUE(), $Y$1=2025,SUMIFS(Data!$AE:$AE,Data!$B:$B,'FS matrix'!D$2,Data!$D:$D,'FS matrix'!$B15), $Y$1=2026,SUMIFS(Data!$AS:$AS,Data!$B:$B,'FS matrix'!D$2,Data!$D:$D,'FS matrix'!$B15)), _xlfn.SWITCH(TRUE(), $Y$1=2025,SUMIFS(Data!$AD:$AD,Data!$B:$B,'FS matrix'!D$2,Data!$D:$D,'FS matrix'!$B15), $Y$1=2026,SUMIFS(Data!$AR:$AR,Data!$B:$B,'FS matrix'!D$2,Data!$D:$D,'FS matrix'!$B15)))} -> 1357271039 | E15: Net Cash flow
A16: P14 | B16: Repairs and maintanance | C16: =IF($A$1="EN",B16,"Sửa chữa, bảo trì") -> Sửa chữa, bảo trì | D16: {=IF($V$1="Tháng", _xlfn.SWITCH(TRUE(), $Y$1=2025,SUMIFS(Data!$AE:$AE,Data!$B:$B,'FS matrix'!D$2,Data!$D:$D,'FS matrix'!$B16), $Y$1=2026,SUMIFS(Data!$AS:$AS,Data!$B:$B,'FS matrix'!D$2,Data!$D:$D,'FS matrix'!$B16)), _xlfn.SWITCH(TRUE(), $Y$1=2025,SUMIFS(Data!$AD:$AD,Data!$B:$B,'FS matrix'!D$2,Data!$D:$D,'FS matrix'!$B16), $Y$1=2026,SUMIFS(Data!$AR:$AR,Data!$B:$B,'FS matrix'!D$2,Data!$D:$D,'FS matrix'!$B16)))} -> 776152179
A17: P15 | B17: Factory expenses | C17: =IF($A$1="EN",B17,"Chi phí chung phân xưởng") -> Chi phí chung phân xưởng | D17: {=IF($V$1="Tháng", _xlfn.SWITCH(TRUE(), $Y$1=2025,SUMIFS(Data!$AE:$AE,Data!$B:$B,'FS matrix'!D$2,Data!$D:$D,'FS matrix'!$B17), $Y$1=2026,SUMIFS(Data!$AS:$AS,Data!$B:$B,'FS matrix'!D$2,Data!$D:$D,'FS matrix'!$B17)), _xlfn.SWITCH(TRUE(), $Y$1=2025,SUMIFS(Data!$AD:$AD,Data!$B:$B,'FS matrix'!D$2,Data!$D:$D,'FS matrix'!$B17), $Y$1=2026,SUMIFS(Data!$AR:$AR,Data!$B:$B,'FS matrix'!D$2,Data!$D:$D,'FS matrix'!$B17)))} -> 8532632034
A18: P16 | B18: Depreciation (FOH) | C18: =IF($A$1="EN",B18,"Khấu hao") -> Khấu hao | D18: {=IF($V$1="Tháng", _xlfn.SWITCH(TRUE(), $Y$1=2025,SUMIFS(Data!$AE:$AE,Data!$B:$B,'FS matrix'!D$2,Data!$D:$D,'FS matrix'!$B18), $Y$1=2026,SUMIFS(Data!$AS:$AS,Data!$B:$B,'FS matrix'!D$2,Data!$D:$D,'FS matrix'!$B18)), _xlfn.SWITCH(TRUE(), $Y$1=2025,SUMIFS(Data!$AD:$AD,Data!$B:$B,'FS matrix'!D$2,Data!$D:$D,'FS matrix'!$B18), $Y$1=2026,SUMIFS(Data!$AR:$AR,Data!$B:$B,'FS matrix'!D$2,Data!$D:$D,'FS matrix'!$B18)))} -> 5764064909
A19: P17 | B19: Other COGs | C19: =IF($A$1="EN",B19,"Giá vốn Khác") -> Giá vốn Khác | D19: {=IF($V$1="Tháng", _xlfn.SWITCH(TRUE(), $Y$1=2025,SUMIFS(Data!$AE:$AE,Data!$B:$B,'FS matrix'!D$2,Data!$D:$D,'FS matrix'!$B19), $Y$1=2026,SUMIFS(Data!$AS:$AS,Data!$B:$B,'FS matrix'!D$2,Data!$D:$D,'FS matrix'!$B19)), _xlfn.SWITCH(TRUE(), $Y$1=2025,SUMIFS(Data!$AD:$AD,Data!$B:$B,'FS matrix'!D$2,Data!$D:$D,'FS matrix'!$B19), $Y$1=2026,SUMIFS(Data!$AR:$AR,Data!$B:$B,'FS matrix'!D$2,Data!$D:$D,'FS matrix'!$B19)))} -> 3.0716767e+09
A20: P18 | B20: Processing cost | C20: =IF($A$1="EN",B20,"Phí gia công") -> Phí gia công | D20: {=IF($V$1="Tháng", _xlfn.SWITCH(TRUE(), $Y$1=2025,SUMIFS(Data!$AE:$AE,Data!$B:$B,'FS matrix'!D$2,Data!$D:$D,'FS matrix'!$B20), $Y$1=2026,SUMIFS(Data!$AS:$AS,Data!$B:$B,'FS matrix'!D$2,Data!$D:$D,'FS matrix'!$B20)), _xlfn.SWITCH(TRUE(), $Y$1=2025,SUMIFS(Data!$AD:$AD,Data!$B:$B,'FS matrix'!D$2,Data!$D:$D,'FS matrix'!$B20), $Y$1=2026,SUMIFS(Data!$AR:$AR,Data!$B:$B,'FS matrix'!D$2,Data!$D:$D,'FS matrix'!$B20)))} -> 167431172
A21: P19 | B21: COGs in inventory (semi FG) | C21: =IF($A$1="EN",B21,"Giá vốn trong bán thành phẩm") -> Giá vốn trong bán thành phẩm | D21: {=IF($V$1="Tháng", _xlfn.SWITCH(TRUE(), $Y$1=2025,SUMIFS(Data!$AE:$AE,Data!$B:$B,'FS matrix'!D$2,Data!$D:$D,'FS matrix'!$B21), $Y$1=2026,SUMIFS(Data!$AS:$AS,Data!$B:$B,'FS matrix'!D$2,Data!$D:$D,'FS matrix'!$B21)), _xlfn.SWITCH(TRUE(), $Y$1=2025,SUMIFS(Data!$AD:$AD,Data!$B:$B,'FS matrix'!D$2,Data!$D:$D,'FS matrix'!$B21), $Y$1=2026,SUMIFS(Data!$AR:$AR,Data!$B:$B,'FS matrix'!D$2,Data!$D:$D,'FS matrix'!$B21)))} -> 0
A22: P20 | B22: Gross Profit | C22: =IF($A$1="EN",B22,"Lợi nhuận gộp") -> Lợi nhuận gộp | D22: {=IF($V$1="Tháng", _xlfn.SWITCH(TRUE(), $Y$1=2025,SUMIFS(Data!$AE:$AE,Data!$B:$B,'FS matrix'!D$2,Data!$D:$D,'FS matrix'!$B22), $Y$1=2026,SUMIFS(Data!$AS:$AS,Data!$B:$B,'FS matrix'!D$2,Data!$D:$D,'FS matrix'!$B22)), _xlfn.SWITCH(TRUE(), $Y$1=2025,SUMIFS(Data!$AD:$AD,Data!$B:$B,'FS matrix'!D$2,Data!$D:$D,'FS matrix'!$B22), $Y$1=2026,SUMIFS(Data!$AR:$AR,Data!$B:$B,'FS matrix'!D$2,Data!$D:$D,'FS matrix'!$B22)))} -> 22185276979
A23: P21 | B23: SG&A (MKT&ADM) expenses | C23: =IF($A$1="EN",B23,"Chi phí bán hàng & quản lý") -> Chi phí bán hàng & quản lý | D23: {=IF($V$1="Tháng", _xlfn.SWITCH(TRUE(), $Y$1=2025,SUMIFS(Data!$AE:$AE,Data!$B:$B,'FS matrix'!D$2,Data!$D:$D,'FS matrix'!$B23), $Y$1=2026,SUMIFS(Data!$AS:$AS,Data!$B:$B,'FS matrix'!D$2,Data!$D:$D,'FS matrix'!$B23)), _xlfn.SWITCH(TRUE(), $Y$1=2025,SUMIFS(Data!$AD:$AD,Data!$B:$B,'FS matrix'!D$2,Data!$D:$D,'FS matrix'!$B23), $Y$1=2026,SUMIFS(Data!$AR:$AR,Data!$B:$B,'FS matrix'!D$2,Data!$D:$D,'FS matrix'!$B23)))} -> 13926607565
A24: P22 | B24: Salary | C24: =IF($A$1="EN",B24,"Lương nhân viên") -> Lương nhân viên | D24: {=IF($V$1="Tháng", _xlfn.SWITCH(TRUE(), $Y$1=2025,SUMIFS(Data!$AE:$AE,Data!$B:$B,'FS matrix'!D$2,Data!$D:$D,'FS matrix'!$B24), $Y$1=2026,SUMIFS(Data!$AS:$AS,Data!$B:$B,'FS matrix'!D$2,Data!$D:$D,'FS matrix'!$B24)), _xlfn.SWITCH(TRUE(), $Y$1=2025,SUMIFS(Data!$AD:$AD,Data!$B:$B,'FS matrix'!D$2,Data!$D:$D,'FS matrix'!$B24), $Y$1=2026,SUMIFS(Data!$AR:$AR,Data!$B:$B,'FS matrix'!D$2,Data!$D:$D,'FS matrix'!$B24)))} -> 4969298326
A25: P23 | B25: Employee welfare | C25: =IF($A$1="EN",B25,"Phúc lợi nhân viên") -> Phúc lợi nhân viên | D25: {=IF($V$1="Tháng", _xlfn.SWITCH(TRUE(), $Y$1=2025,SUMIFS(Data!$AE:$AE,Data!$B:$B,'FS matrix'!D$2,Data!$D:$D,'FS matrix'!$B25), $Y$1=2026,SUMIFS(Data!$AS:$AS,Data!$B:$B,'FS matrix'!D$2,Data!$D:$D,'FS matrix'!$B25)), _xlfn.SWITCH(TRUE(), $Y$1=2025,SUMIFS(Data!$AD:$AD,Data!$B:$B,'FS matrix'!D$2,Data!$D:$D,'FS matrix'!$B25), $Y$1=2026,SUMIFS(Data!$AR:$AR,Data!$B:$B,'FS matrix'!D$2,Data!$D:$D,'FS matrix'!$B25)))} -> 1494821509
A26: P26 | B26: Export Freight | C26: =IF($A$1="EN",B26,"Chi phí xuất khẩu") -> Chi phí xuất khẩu | D26: {=IF($V$1="Tháng", _xlfn.SWITCH(TRUE(), $Y$1=2025,SUMIFS(Data!$AE:$AE,Data!$B:$B,'FS matrix'!D$2,Data!$D:$D,'FS matrix'!$B26), $Y$1=2026,SUMIFS(Data!$AS:$AS,Data!$B:$B,'FS matrix'!D$2,Data!$D:$D,'FS matrix'!$B26)), _xlfn.SWITCH(TRUE(), $Y$1=2025,SUMIFS(Data!$AD:$AD,Data!$B:$B,'FS matrix'!D$2,Data!$D:$D,'FS matrix'!$B26), $Y$1=2026,SUMIFS(Data!$AR:$AR,Data!$B:$B,'FS matrix'!D$2,Data!$D:$D,'FS matrix'!$B26)))} -> 1647931878
A27: P27 | B27: Depreciation | C27: =IF($A$1="EN",B27,"Chi phí khấu hao") -> Chi phí khấu hao | D27: {=IF($V$1="Tháng", _xlfn.SWITCH(TRUE(), $Y$1=2025,SUMIFS(Data!$AE:$AE,Data!$B:$B,'FS matrix'!D$2,Data!$D:$D,'FS matrix'!$B27), $Y$1=2026,SUMIFS(Data!$AS:$AS,Data!$B:$B,'FS matrix'!D$2,Data!$D:$D,'FS matrix'!$B27)), _xlfn.SWITCH(TRUE(), $Y$1=2025,SUMIFS(Data!$AD:$AD,Data!$B:$B,'FS matrix'!D$2,Data!$D:$D,'FS matrix'!$B27), $Y$1=2026,SUMIFS(Data!$AR:$AR,Data!$B:$B,'FS matrix'!D$2,Data!$D:$D,'FS matrix'!$B27)))} -> 83579315
A28: P28 | B28: Controllable expenses | C28: =IF($A$1="EN",B28,"Chi phí cần kiểm soát") -> Chi phí cần kiểm soát | D28: {=IF($V$1="Tháng", _xlfn.SWITCH(TRUE(), $Y$1=2025,SUMIFS(Data!$AE:$AE,Data!$B:$B,'FS matrix'!D$2,Data!$D:$D,'FS matrix'!$B28), $Y$1=2026,SUMIFS(Data!$AS:$AS,Data!$B:$B,'FS matrix'!D$2,Data!$D:$D,'FS matrix'!$B28)), _xlfn.SWITCH(TRUE(), $Y$1=2025,SUMIFS(Data!$AD:$AD,Data!$B:$B,'FS matrix'!D$2,Data!$D:$D,'FS matrix'!$B28), $Y$1=2026,SUMIFS(Data!$AR:$AR,Data!$B:$B,'FS matrix'!D$2,Data!$D:$D,'FS matrix'!$B28)))} -> 3106154577
A29: P29 | B29: Financial Expense | C29: =IF($A$1="EN",B29,"Chi phí tài chính") -> Chi phí tài chính | D29: {=IF($V$1="Tháng", _xlfn.SWITCH(TRUE(), $Y$1=2025,SUMIFS(Data!$AE:$AE,Data!$B:$B,'FS matrix'!D$2,Data!$D:$D,'FS matrix'!$B29), $Y$1=2026,SUMIFS(Data!$AS:$AS,Data!$B:$B,'FS matrix'!D$2,Data!$D:$D,'FS matrix'!$B29)), _xlfn.SWITCH(TRUE(), $Y$1=2025,SUMIFS(Data!$AD:$AD,Data!$B:$B,'FS matrix'!D$2,Data!$D:$D,'FS matrix'!$B29), $Y$1=2026,SUMIFS(Data!$AR:$AR,Data!$B:$B,'FS matrix'!D$2,Data!$D:$D,'FS matrix'!$B29)))} -> 1208736058
A30: P30 | B30: Interest expense | C30: =IF($A$1="EN",B30,"Trong đó: Chi phí lãi vay") -> Trong đó: Chi phí lãi vay | D30: {=IF($V$1="Tháng", _xlfn.SWITCH(TRUE(), $Y$1=2025,SUMIFS(Data!$AE:$AE,Data!$B:$B,'FS matrix'!D$2,Data!$D:$D,'FS matrix'!$B30), $Y$1=2026,SUMIFS(Data!$AS:$AS,Data!$B:$B,'FS matrix'!D$2,Data!$D:$D,'FS matrix'!$B30)), _xlfn.SWITCH(TRUE(), $Y$1=2025,SUMIFS(Data!$AD:$AD,Data!$B:$B,'FS matrix'!D$2,Data!$D:$D,'FS matrix'!$B30), $Y$1=2026,SUMIFS(Data!$AR:$AR,Data!$B:$B,'FS matrix'!D$2,Data!$D:$D,'FS matrix'!$B30)))} -> 838836791
A31: P31 | B31: Other Income | C31: =IF($A$1="EN",B31,"Thu nhập khác") -> Thu nhập khác | D31: {=IF($V$1="Tháng", _xlfn.SWITCH(TRUE(), $Y$1=2025,SUMIFS(Data!$AE:$AE,Data!$B:$B,'FS matrix'!D$2,Data!$D:$D,'FS matrix'!$B31), $Y$1=2026,SUMIFS(Data!$AS:$AS,Data!$B:$B,'FS matrix'!D$2,Data!$D:$D,'FS matrix'!$B31)), _xlfn.SWITCH(TRUE(), $Y$1=2025,SUMIFS(Data!$AD:$AD,Data!$B:$B,'FS matrix'!D$2,Data!$D:$D,'FS matrix'!$B31), $Y$1=2026,SUMIFS(Data!$AR:$AR,Data!$B:$B,'FS matrix'!D$2,Data!$D:$D,'FS matrix'!$B31)))} -> 1131650562
A32: P32 | B32: EBITDA | C32: =IF($A$1="EN",B32,"EBITDA") -> EBITDA | D32: {=IF($V$1="Tháng", _xlfn.SWITCH(TRUE(), $Y$1=2025,SUMIFS(Data!$AE:$AE,Data!$B:$B,'FS matrix'!D$2,Data!$D:$D,'FS matrix'!$B32), $Y$1=2026,SUMIFS(Data!$AS:$AS,Data!$B:$B,'FS matrix'!D$2,Data!$D:$D,'FS matrix'!$B32)), _xlfn.SWITCH(TRUE(), $Y$1=2025,SUMIFS(Data!$AD:$AD,Data!$B:$B,'FS matrix'!D$2,Data!$D:$D,'FS matrix'!$B32), $Y$1=2026,SUMIFS(Data!$AR:$AR,Data!$B:$B,'FS matrix'!D$2,Data!$D:$D,'FS matrix'!$B32)))} -> 11351398266
A33: P33 | B33: Profit before tax | C33: =IF($A$1="EN",B33,"Lợi nhuận trước thuế") -> Lợi nhuận trước thuế | D33: {=IF($V$1="Tháng", _xlfn.SWITCH(TRUE(), $Y$1=2025,SUMIFS(Data!$AE:$AE,Data!$B:$B,'FS matrix'!D$2,Data!$D:$D,'FS matrix'!$B33), $Y$1=2026,SUMIFS(Data!$AS:$AS,Data!$B:$B,'FS matrix'!D$2,Data!$D:$D,'FS matrix'!$B33)), _xlfn.SWITCH(TRUE(), $Y$1=2025,SUMIFS(Data!$AD:$AD,Data!$B:$B,'FS matrix'!D$2,Data!$D:$D,'FS matrix'!$B33), $Y$1=2026,SUMIFS(Data!$AR:$AR,Data!$B:$B,'FS matrix'!D$2,Data!$D:$D,'FS matrix'!$B33)))} -> 8181583918
A34: P34 | B34: CIT | C34: =IF($A$1="EN",B34,"Thuế TNDN") -> Thuế TNDN | D34: {=IF($V$1="Tháng", _xlfn.SWITCH(TRUE(), $Y$1=2025,SUMIFS(Data!$AE:$AE,Data!$B:$B,'FS matrix'!D$2,Data!$D:$D,'FS matrix'!$B34), $Y$1=2026,SUMIFS(Data!$AS:$AS,Data!$B:$B,'FS matrix'!D$2,Data!$D:$D,'FS matrix'!$B34)), _xlfn.SWITCH(TRUE(), $Y$1=2025,SUMIFS(Data!$AD:$AD,Data!$B:$B,'FS matrix'!D$2,Data!$D:$D,'FS matrix'!$B34), $Y$1=2026,SUMIFS(Data!$AR:$AR,Data!$B:$B,'FS matrix'!D$2,Data!$D:$D,'FS matrix'!$B34)))} -> -45841499
A35: P35 | B35: Net profit | C35: =IF($A$1="EN","NET PROFIT","Lợi nhuận sau thuế") -> Lợi nhuận sau thuế | D35: {=IF($V$1="Tháng", _xlfn.SWITCH(TRUE(), $Y$1=2025,SUMIFS(Data!$AE:$AE,Data!$B:$B,'FS matrix'!D$2,Data!$D:$D,'FS matrix'!$B35), $Y$1=2026,SUMIFS(Data!$AS:$AS,Data!$B:$B,'FS matrix'!D$2,Data!$D:$D,'FS matrix'!$B35)), _xlfn.SWITCH(TRUE(), $Y$1=2025,SUMIFS(Data!$AD:$AD,Data!$B:$B,'FS matrix'!D$2,Data!$D:$D,'FS matrix'!$B35), $Y$1=2026,SUMIFS(Data!$AR:$AR,Data!$B:$B,'FS matrix'!D$2,Data!$D:$D,'FS matrix'!$B35)))} -> 8227425417
B37: BALANCE SHEET | C37: =IF(A1="EN",B37,"BẢNG CÂN ĐỐI KẾ TOÁN") -> BẢNG CÂN ĐỐI KẾ TOÁN | D37: =D2 -> DTR
A38: B01 | B38: Current Assets | C38: =IF(A1="en",B38,"Tài sản ngắn hạn") -> Tài sản ngắn hạn | D38: {=_xlfn.SWITCH(TRUE(), $Y$1=2025,SUMIFS(Data!$AD:$AD,Data!$B:$B,'FS matrix'!D$37,Data!$A:$A,'FS matrix'!$A38), $Y$1=2026,SUMIFS(Data!$AR:$AR,Data!$B:$B,'FS matrix'!D$37,Data!$A:$A,'FS matrix'!$A38))} -> 886588369025
A39: B02 | B39: Cash | C39: =IF($A$1="EN",B39,"Tiền") -> Tiền | D39: {=_xlfn.SWITCH(TRUE(), $Y$1=2025,SUMIFS(Data!$AD:$AD,Data!$B:$B,'FS matrix'!D$37,Data!$A:$A,'FS matrix'!$A39), $Y$1=2026,SUMIFS(Data!$AR:$AR,Data!$B:$B,'FS matrix'!D$37,Data!$A:$A,'FS matrix'!$A39))} -> 41014004605
A40: B03 | B40: Financial investment | C40: =IF($A$1="EN",B40,"Đầu tư tài chính ngắn hạn") -> Đầu tư tài chính ngắn hạn | D40: {=_xlfn.SWITCH(TRUE(), $Y$1=2025,SUMIFS(Data!$AD:$AD,Data!$B:$B,'FS matrix'!D$37,Data!$A:$A,'FS matrix'!$A40), $Y$1=2026,SUMIFS(Data!$AR:$AR,Data!$B:$B,'FS matrix'!D$37,Data!$A:$A,'FS matrix'!$A40))} -> 34340000000
A41: B04 | B41: Account receivables | C41: =IF($A$1="EN",B41,"Các khoản phải thu") -> Các khoản phải thu | D41: {=_xlfn.SWITCH(TRUE(), $Y$1=2025,SUMIFS(Data!$AD:$AD,Data!$B:$B,'FS matrix'!D$37,Data!$A:$A,'FS matrix'!$A41), $Y$1=2026,SUMIFS(Data!$AR:$AR,Data!$B:$B,'FS matrix'!D$37,Data!$A:$A,'FS matrix'!$A41))} -> 417392857129
A42: B04.1 | B42: Account receivables from customers | C42: =IF($A$1="EN",B42,"Trong đó: Phải thu khách hàng") -> Trong đó: Phải thu khách hàng | D42: {=_xlfn.SWITCH(TRUE(), $Y$1=2025,SUMIFS(Data!$AD:$AD,Data!$B:$B,'FS matrix'!D$37,Data!$A:$A,'FS matrix'!$A42), $Y$1=2026,SUMIFS(Data!$AR:$AR,Data!$B:$B,'FS matrix'!D$37,Data!$A:$A,'FS matrix'!$A42))} -> 178005616424
A43: B05 | B43: Inventory | C43: =IF($A$1="EN",B43,"Hàng tồn kho") -> Hàng tồn kho | D43: {=_xlfn.SWITCH(TRUE(), $Y$1=2025,SUMIFS(Data!$AD:$AD,Data!$B:$B,'FS matrix'!D$37,Data!$A:$A,'FS matrix'!$A43), $Y$1=2026,SUMIFS(Data!$AR:$AR,Data!$B:$B,'FS matrix'!D$37,Data!$A:$A,'FS matrix'!$A43))} -> 361880765551
A44: B06 | B44: Long-term assets | C44: =IF($A$1="EN",B44,"Tài sản dài hạn") -> Tài sản dài hạn | D44: {=_xlfn.SWITCH(TRUE(), $Y$1=2025,SUMIFS(Data!$AD:$AD,Data!$B:$B,'FS matrix'!D$37,Data!$A:$A,'FS matrix'!$A44), $Y$1=2026,SUMIFS(Data!$AR:$AR,Data!$B:$B,'FS matrix'!D$37,Data!$A:$A,'FS matrix'!$A44))} -> 365314011891
A45: B07 | B45: Fixed Assets | C45: =IF($A$1="EN",B45,"Tài sản cố định") -> Tài sản cố định | D45: {=_xlfn.SWITCH(TRUE(), $Y$1=2025,SUMIFS(Data!$AD:$AD,Data!$B:$B,'FS matrix'!D$37,Data!$A:$A,'FS matrix'!$A45), $Y$1=2026,SUMIFS(Data!$AR:$AR,Data!$B:$B,'FS matrix'!D$37,Data!$A:$A,'FS matrix'!$A45))} -> 268070715296
A46: B08 | B46: Cost | C46: =IF($A$1="EN",B46,"Nguyên giá") -> Nguyên giá | D46: {=_xlfn.SWITCH(TRUE(), $Y$1=2025,SUMIFS(Data!$AD:$AD,Data!$B:$B,'FS matrix'!D$37,Data!$A:$A,'FS matrix'!$A46), $Y$1=2026,SUMIFS(Data!$AR:$AR,Data!$B:$B,'FS matrix'!D$37,Data!$A:$A,'FS matrix'!$A46))} -> 409700584982
A47: B09 | B47: Accumulated depreciation | C47: =IF($A$1="EN",B47,"Hao mòn lũy kế") -> Hao mòn lũy kế | D47: {=_xlfn.SWITCH(TRUE(), $Y$1=2025,SUMIFS(Data!$AD:$AD,Data!$B:$B,'FS matrix'!D$37,Data!$A:$A,'FS matrix'!$A47), $Y$1=2026,SUMIFS(Data!$AR:$AR,Data!$B:$B,'FS matrix'!D$37,Data!$A:$A,'FS matrix'!$A47))} -> -141629869686
A48: B10 | B48: Total Assets | C48: =IF($A$1="EN",B48,"Tổng Tài sản") -> Tổng Tài sản | D48: =D38+D44 -> 1251902380916
A49: B11 | B49: Short-term Liabilities | C49: =IF($A$1="EN",B49,"Nợ ngắn hạn") -> Nợ ngắn hạn | D49: {=_xlfn.SWITCH(TRUE(), $Y$1=2025,SUMIFS(Data!$AD:$AD,Data!$B:$B,'FS matrix'!D$37,Data!$A:$A,'FS matrix'!$A49), $Y$1=2026,SUMIFS(Data!$AR:$AR,Data!$B:$B,'FS matrix'!D$37,Data!$A:$A,'FS matrix'!$A49))} -> 219319635169
A50: B12 | B50: Short-term borrowings | C50: =IF($A$1="EN",B50,"Vay ngắn hạn") -> Vay ngắn hạn | D50: {=_xlfn.SWITCH(TRUE(), $Y$1=2025,SUMIFS(Data!$AD:$AD,Data!$B:$B,'FS matrix'!D$37,Data!$A:$A,'FS matrix'!$A50), $Y$1=2026,SUMIFS(Data!$AR:$AR,Data!$B:$B,'FS matrix'!D$37,Data!$A:$A,'FS matrix'!$A50))} -> 116595603825
A51: B13 | B51: Account payables | C51: =IF($A$1="EN",B51,"Các khoản phải trả") -> Các khoản phải trả | D51: {=_xlfn.SWITCH(TRUE(), $Y$1=2025,SUMIFS(Data!$AD:$AD,Data!$B:$B,'FS matrix'!D$37,Data!$A:$A,'FS matrix'!$A51), $Y$1=2026,SUMIFS(Data!$AR:$AR,Data!$B:$B,'FS matrix'!D$37,Data!$A:$A,'FS matrix'!$A51))} -> 65718659314
A52: B13.1 | B52: Account payables to suppliers | C52: =IF($A$1="EN",B52,"Trong đó: Phải trả nhà cung cấp") -> Trong đó: Phải trả nhà cung cấp | D52: {=_xlfn.SWITCH(TRUE(), $Y$1=2025,SUMIFS(Data!$AD:$AD,Data!$B:$B,'FS matrix'!D$37,Data!$A:$A,'FS matrix'!$A52), $Y$1=2026,SUMIFS(Data!$AR:$AR,Data!$B:$B,'FS matrix'!D$37,Data!$A:$A,'FS matrix'!$A52))} -> 51638550700
A53: B14 | B53: Long-term liabilities | C53: =IF($A$1="EN",B53,"Nợ dài hạn") -> Nợ dài hạn | D53: {=_xlfn.SWITCH(TRUE(), $Y$1=2025,SUMIFS(Data!$AD:$AD,Data!$B:$B,'FS matrix'!D$37,Data!$A:$A,'FS matrix'!$A53), $Y$1=2026,SUMIFS(Data!$AR:$AR,Data!$B:$B,'FS matrix'!D$37,Data!$A:$A,'FS matrix'!$A53))} -> 154933236415
A54: B15 | B54: Long-term borrowings | C54: Vay dài hạn | D54: {=_xlfn.SWITCH(TRUE(), $Y$1=2025,SUMIFS(Data!$AD:$AD,Data!$B:$B,'FS matrix'!D$37,Data!$A:$A,'FS matrix'!$A54), $Y$1=2026,SUMIFS(Data!$AR:$AR,Data!$B:$B,'FS matrix'!D$37,Data!$A:$A,'FS matrix'!$A54))} -> 154933236415
A55: B16 | B55: Equity | C55: =IF($A$1="EN",B55,"Vốn chủ sở hữu") -> Vốn chủ sở hữu | D55: {=_xlfn.SWITCH(TRUE(), $Y$1=2025,SUMIFS(Data!$AD:$AD,Data!$B:$B,'FS matrix'!D$37,Data!$A:$A,'FS matrix'!$A55), $Y$1=2026,SUMIFS(Data!$AR:$AR,Data!$B:$B,'FS matrix'!D$37,Data!$A:$A,'FS matrix'!$A55))} -> 877649509332
A56: B18 | B56: Retained earnings | C56: =IF($A$1="EN",B56,"Lợi nhuận chưa phân phối") -> Lợi nhuận chưa phân phối | D56: {=_xlfn.SWITCH(TRUE(), $Y$1=2025,SUMIFS(Data!$AD:$AD,Data!$B:$B,'FS matrix'!D$37,Data!$A:$A,'FS matrix'!$A56), $Y$1=2026,SUMIFS(Data!$AR:$AR,Data!$B:$B,'FS matrix'!D$37,Data!$A:$A,'FS matrix'!$A56))} -> 227649509332
A57: B19 | B57: Total Resources | C57: =IF($A$1="EN",B57,"Tổng Nguồn vốn") -> Tổng Nguồn vốn | D57: =D49+D53+D55 -> 1251902380916
C58: Vốn điều lệ | D58: =D55-D56 -> 650000000000
C59: % Vốn điều lệ / Doanh thu | D59: =IFERROR((D55-D56)/D5,"") -> 4.0684677
B60: CASH FLOW | C60: LƯU CHUYỂN TIỀN TỆ | D60: =D37 -> DTR
A61: C01 | B61: Profit before taxes | C61: Lợi nhuận trước thuế | D61: {=IF($V$1="Tháng", _xlfn.SWITCH(TRUE(), $Y$1=2025,SUMIFS(Data!$AE:$AE,Data!$B:$B,'FS matrix'!D$60,Data!$A:$A,'FS matrix'!$A61), $Y$1=2026,SUMIFS(Data!$AS:$AS,Data!$B:$B,'FS matrix'!D$60,Data!$A:$A,'FS matrix'!$A61)), _xlfn.SWITCH(TRUE(), $Y$1=2025,SUMIFS(Data!$AD:$AD,Data!$B:$B,'FS matrix'!D$60,Data!$A:$A,'FS matrix'!$A61), $Y$1=2026,SUMIFS(Data!$AR:$AR,Data!$B:$B,'FS matrix'!D$60,Data!$A:$A,'FS matrix'!$A61)))} -> 8181583918
