Workbook

Sheet QTSX

Sheet CĐSX
A2: STT | B2: Công đoạn SX
A3: 1 | B3: Thu mua
A4: 2 | B4: Vận chuyển NL về NM
A5: 3 | B5: Nhập hàng và tồn kho NL
A6: 5 | B6: Xuất NL, phá kiện
A7: 6 | B7: Phân loại chai trước tách nhãn
A8: 7 | B8: Tách nhãn
A9: 8 | B9: Phân loại chai sau tách nhãn
A10: 9 | B10: Ép kiện
A11: 10 | B11: Băm vảy
A12: 12 | B12: Rửa vảy
A13: 13 | B13: Tồn kho TP
A14: 14 | B14: Xuất bán, vận chyển

Sheet CAP.Chính
A1: ĐẦU TƯ CAPEX - MÁY CHÍNH
A2: A | B2: CHUYỀN PHÂN LOẠI CHAI
A3: STT | B3: Hạng mục đầu tư | C3: Nhà cung cấp | D3: Công suất/ 1 công đoạn | E3: Đơn giá ( chưa bao gồm VAT) | F3: H.S 40% | H3: H.S 60% | J3: H.S 80% | L3: H.S 100% | N3: Ghi chú
F4: Số lượng | G4: Tổng giá trị (VND) | H4: Số lượng | I4: Tổng giá trị (VND) | J4: Số lượng | K4: Tổng giá trị (VND) | L4: Số lượng | M4: Tổng giá trị (VND)
A5: I | B5: MÁY MÓC THIẾT BỊ CHÍNH | G5: =G6+G9+G12+G15+G25+G32+G39 -> 16230006000 | I5: =I6+I9+I12+I15+I25+I32+I39 -> 16230006000 | K5: =K6+K9+K12+K15+K25+K32+K39 -> 16230006000 | M5: =M6+M9+M12+M15+M25+M32+M39 -> 16230006000
A6: 1 | B6: Cấp liệu | D6: 3 tấn/h | G6: =G7+G8 -> 160000000 | I6: =I7+I8 -> 160000000 | K6: =K7+K8 -> 160000000 | M6: =M7+M8 -> 160000000
B7: Sàn thao tác chai đầu vào | C7: Plenma/HTL | E7: 80000000 | F7: 1 | G7: =$E7*F7 -> 80000000 | H7: 1 | I7: =$E7*H7 -> 80000000 | J7: 1 | K7: =$E7*J7 -> 80000000 | L7: 1 | M7: =$E7*L7 -> 80000000
B8: Băng tải phân loại bì tạp | C8: Plenma/HTL | E8: 80000000 | F8: 1 | G8: =$E8*F8 -> 80000000 | H8: 1 | I8: =$E8*H8 -> 80000000 | J8: 1 | K8: =$E8*J8 -> 80000000 | L8: 1 | M8: =$E8*L8 -> 80000000
A9: 2 | B9: Phá kiện | D9: 2 tấn/h | G9: =G10 -> 445000000 | I9: =I10 -> 445000000 | K9: =K10 -> 445000000 | M9: =M10 -> 445000000
B10: Máy phá kiện | C10: Plenma/HTL | E10: 445000000 | F10: 1 | G10: =$E10*F10 -> 445000000 | H10: 1 | I10: =$E10*H10 -> 445000000 | J10: 1 | K10: =$E10*J10 -> 445000000 | L10: 1 | M10: =$E10*L10 -> 445000000 | N10: GĐ 1 không có
B11: Băng tải máy phá kiện | C11: Plenma/HTL | E11: 120000000 | F11: 1 | G11: =$E11*F11 -> 120000000 | H11: 1 | I11: =$E11*H11 -> 120000000 | J11: 1 | K11: =$E11*J11 -> 120000000 | L11: 1 | M11: =$E11*L11 -> 120000000 | N11: GĐ 1 không có
A12: 3 | B12: Sàn tách tạp chất | D12: 3 tấn/h | G12: =G13+G14 -> 590000000 | I12: =I13+I14 -> 590000000 | K12: =K13+K14 -> 590000000 | M12: =M13+M14 -> 590000000
B13: Băng tải nam châm tách kim loại tự động | C13: Plenma/HTL | E13: 120000000 | F13: 2 | G13: =$E13*F13 -> 240000000 | H13: 2 | I13: =$E13*H13 -> 240000000 | J13: 2 | K13: =$E13*J13 -> 240000000 | L13: 2 | M13: =$E13*L13 -> 240000000
B14: Máy sàn cát đá tromel | C14: HTL | E14: 350000000 | F14: 1 | G14: =$E14*F14 -> 350000000 | H14: 1 | I14: =$E14*H14 -> 350000000 | J14: 1 | K14: =$E14*J14 -> 350000000 | L14: 1 | M14: =$E14*L14 -> 350000000
A15: 4 | B15: Lựa phân loại chai | D15: 3 tấn/h | G15: =SUM(G16:G24) -> 5575000000 | I15: =SUM(I16:I24) -> 5575000000 | K15: =SUM(K16:K24) -> 5575000000 | M15: =SUM(M16:M24) -> 5575000000
B16: Máy sort chai tự động 3 tấn/giờ | C16: Databeyond | E16: 950000000 | F16: 2 | G16: =$E16*F16 -> 1900000000 | H16: 2 | I16: =$E16*H16 -> 1900000000 | J16: 2 | K16: =$E16*J16 -> 1900000000 | L16: 2 | M16: =$E16*L16 -> 1900000000
B17: Lập trình và vận hành máy sort chai | C17: Databeyond | E17: 180000000 | F17: 1 | G17: =$E17*F17 -> 180000000 | H17: 1 | I17: =$E17*H17 -> 180000000 | J17: 1 | K17: =$E17*J17 -> 180000000 | L17: 1 | M17: =$E17*L17 -> 180000000
B18: Băng tải cấp chai máy sort | C18: Plenma/HTL | E18: 295000000 | F18: 1 | G18: =$E18*F18 -> 295000000 | H18: 1 | I18: =$E18*H18 -> 295000000 | J18: 1 | K18: =$E18*J18 -> 295000000 | L18: 1 | M18: =$E18*L18 -> 295000000
B19: Khung sàn thao tác máy sort | C19: Plenma/HTL | E19: 350000000 | F19: 1 | G19: =$E19*F19 -> 350000000 | H19: 1 | I19: =$E19*H19 -> 350000000 | J19: 1 | K19: =$E19*J19 -> 350000000 | L19: 1 | M19: =$E19*L19 -> 350000000
B20: Quạt thổi chai | C20: Plenma/HTL | E20: 240000000 | F20: 5 | G20: =$E20*F20 -> 1200000000 | H20: 5 | I20: =$E20*H20 -> 1200000000 | J20: 5 | K20: =$E20*J20 -> 1200000000 | L20: 5 | M20: =$E20*L20 -> 1200000000
B21: Lồng chứa chai B1 | C21: Plenma/HTL | E21: 600000000 | F21: 1 | G21: =$E21*F21 -> 600000000 | H21: 1 | I21: =$E21*H21 -> 600000000 | J21: 1 | K21: =$E21*J21 -> 600000000 | L21: 1 | M21: =$E21*L21 -> 600000000
B22: Lồng chứa chai B6 | C22: Plenma/HTL | E22: 400000000 | F22: 1 | G22: =$E22*F22 -> 400000000 | H22: 1 | I22: =$E22*H22 -> 400000000 | J22: 1 | K22: =$E22*J22 -> 400000000 | L22: 1 | M22: =$E22*L22 -> 400000000
B23: Lồng chứa chai B2.2 | C23: Plenma/HTL | E23: 350000000 | F23: 1 | G23: =$E23*F23 -> 350000000 | H23: 1 | I23: =$E23*H23 -> 350000000 | J23: 1 | K23: =$E23*J23 -> 350000000 | L23: 1 | M23: =$E23*L23 -> 350000000
B24: Lồng chứa chai B4, B5 | C24: Plenma/HTL | E24: 150000000 | F24: 2 | G24: =$E24*F24 -> 300000000 | H24: 2 | I24: =$E24*H24 -> 300000000 | J24: 2 | K24: =$E24*J24 -> 300000000 | L24: 2 | M24: =$E24*L24 -> 300000000
A25: 5 | B25: Tách nhãn | D25: 1 tấn/h | G25: =SUM(G26:G31) -> 3230000000 | I25: =SUM(I26:I31) -> 3230000000 | K25: =SUM(K26:K31) -> 3230000000 | M25: =SUM(M26:M31) -> 3230000000
B26: Máy tách nhãn | C26: Plenma/HTL | E26: 660000000 | F26: 3 | G26: =$E26*F26 -> 1980000000 | H26: 3 | I26: =$E26*H26 -> 1980000000 | J26: 3 | K26: =$E26*J26 -> 1980000000 | L26: 3 | M26: =$E26*L26 -> 1980000000 | N26: GĐ 1 = 2 Cái
B27: Cylon máy tách nhãn | C27: Plenma/HTL | E27: 50000000 | F27: 2 | G27: =$E27*F27 -> 100000000 | H27: 2 | I27: =$E27*H27 -> 100000000 | J27: 2 | K27: =$E27*J27 -> 100000000 | L27: 2 | M27: =$E27*L27 -> 100000000 | N27: GĐ 1 = 1 Cái
B28: Phòng cách âm cho máy tách nhãn | C28: Lê Quốc | E28: 100000000 | F28: 2 | G28: =$E28*F28 -> 200000000 | H28: 2 | I28: =$E28*H28 -> 200000000 | J28: 2 | K28: =$E28*J28 -> 200000000 | L28: 2 | M28: =$E28*L28 -> 200000000 | N28: GĐ 1 = 1 Cái
B29: Băng tải cấp chai từ lồng chứa | C29: Plenma/HTL | E29: 160000000 | F29: 3 | G29: =$E29*F29 -> 480000000 | H29: 3 | I29: =$E29*H29 -> 480000000 | J29: 3 | K29: =$E29*J29 -> 480000000 | L29: 3 | M29: =$E29*L29 -> 480000000
B30: Băng tải cấp chai máy tách nhãn | C30: Plenma/HTL | E30: 175000000 | F30: 2 | G30: =$E30*F30 -> 350000000 | H30: 2 | I30: =$E30*H30 -> 350000000 | J30: 2 | K30: =$E30*J30 -> 350000000 | L30: 2 | M30: =$E30*L30 -> 350000000 | N30: GĐ 1 = 1 Cái
B31: Băng tải quay đầu | C31: Plenma/HTL | E31: 120000000 | F31: 1 | G31: =$E31*F31 -> 120000000 | H31: 1 | I31: =$E31*H31 -> 120000000 | J31: 1 | K31: =$E31*J31 -> 120000000 | L31: 1 | M31: =$E31*L31 -> 120000000
A32: 6 | B32: Lựa phân loại chai sau tách nhãn | D32: 3 tấn/h | G32: =SUM(G33:G38) -> 3850000000 | I32: =SUM(I33:I38) -> 3850000000 | K32: =SUM(K33:K38) -> 3850000000 | M32: =SUM(M33:M38) -> 3850000000
B33: Máy sort chai tự động 3 tấn/giờ | C33: Databeyond | E33: 950000000 | F33: 3 | G33: =$E33*F33 -> 2850000000 | H33: 3 | I33: =$E33*H33 -> 2850000000 | J33: 3 | K33: =$E33*J33 -> 2850000000 | L33: 3 | M33: =$E33*L33 -> 2850000000 | N33: GĐ 1 = 2 Cái
B34: Khung sàn máy sort chai sau tách nhãn | C34: Plenma/HTL | E34: 100000000 | F34: 2 | G34: =$E34*F34 -> 200000000 | H34: 2 | I34: =$E34*H34 -> 200000000 | J34: 2 | K34: =$E34*J34 -> 200000000 | L34: 2 | M34: =$E34*L34 -> 200000000 | N34: GĐ 1 = 1 Cái
B35: Băng tải cầp chai máy sort | C35: Plenma/HTL | E35: 120000000 | F35: 2 | G35: =$E35*F35 -> 240000000 | H35: 2 | I35: =$E35*H35 -> 240000000 | J35: 2 | K35: =$E35*J35 -> 240000000 | L35: 2 | M35: =$E35*L35 -> 240000000 | N35: GĐ 1 = 1 Cái
B36: Băng tải đứng cấp chai máy line 2 máy sort | C36: Plenma/HTL | E36: 150000000 | F36: 2 | G36: =$E36*F36 -> 300000000 | H36: 2 | I36: =$E36*H36 -> 300000000 | J36: 2 | K36: =$E36*J36 -> 300000000 | L36: 2 | M36: =$E36*L36 -> 300000000 | N36: GĐ 1 = 1 Cái
B37: Băng tải con lăn | C37: Plenma/HTL | E37: 50000000 | F37: 2 | G37: =$E37*F37 -> 100000000 | H37: 2 | I37: =$E37*H37 -> 100000000 | J37: 2 | K37: =$E37*J37 -> 100000000 | L37: 2 | M37: =$E37*L37 -> 100000000 | N37: GĐ 1 = 1 Cái
B38: Băng tải phân loại chai tách nhãn | C38: Plenma/HTL | E38: 80000000 | F38: 2 | G38: =$E38*F38 -> 160000000 | H38: 2 | I38: =$E38*H38 -> 160000000 | J38: 2 | K38: =$E38*J38 -> 160000000 | L38: 2 | M38: =$E38*L38 -> 160000000 | N38: GĐ 1 = 1 Cái
A39: 7 | B39: Ép kiện | D39: 1.5 tấn/h | G39: =SUM(G40:G42) -> 2380006000 | I39: =SUM(I40:I42) -> 2380006000 | K39: =SUM(K40:K42) -> 2380006000 | M39: =SUM(M40:M42) -> 2380006000
B40: Máy ép kiện ngang | C40: HTL | E40: 1015003000 | F40: 2 | G40: =$E40*F40 -> 2030006000 | H40: 2 | I40: =$E40*H40 -> 2030006000 | J40: 2 | K40: =$E40*J40 -> 2030006000 | L40: 2 | M40: =$E40*L40 -> 2030006000 | N40: GĐ 1 = 1 Cái
B41: Băng tải cấp chai máy ép kiện | C41: Plenma/HTL | E41: 175000000 | F41: 2 | G41: =$E41*F41 -> 350000000 | H41: 2 | I41: =$E41*H41 -> 350000000 | J41: 2 | K41: =$E41*J41 -> 350000000 | L41: 2 | M41: =$E41*L41 -> 350000000 | N41: GĐ 1 = 1 Cái
B42: Lồng chứa chai máy ép kiện | C42: Plenma/HTL | E42: 500000000 | G42: =$E42*F42 -> 0 | I42: =$E42*H42 -> 0 | K42: =$E42*J42 -> 0 | M42: =$E42*L42 -> 0
A43: II | B43: HỆ THỐNG ĐIỆN, HƠI | G43: =SUM(G44:G50) -> 4035000000 | I43: =SUM(I44:I50) -> 4035000000 | K43: =SUM(K44:K50) -> 4035000000 | M43: =SUM(M44:M50) -> 4035000000
B44: Cải tạo hệ thống điện (trạm điện và hệ thống điện đến máy) | C44: Khang Thành | E44: 1120000000 | F44: 1 | G44: =$E44*F44 -> 1120000000 | H44: 1 | I44: =$E44*H44 -> 1120000000 | J44: 1 | K44: =$E44*J44 -> 1120000000 | L44: 1 | M44: =$E44*L44 -> 1120000000
B45: Lắp đặt đường hơi khí nén cho hệ thống máy sort chai | C45: Khang Thành | E45: 250000000 | F45: 1 | G45: =$E45*F45 -> 250000000 | H45: 1 | I45: =$E45*H45 -> 250000000 | J45: 1 | K45: =$E45*J45 -> 250000000 | L45: 1 | M45: =$E45*L45 -> 250000000 | N45: GĐ 2 cộng thêm 50 triệu
B46: Hệ thống máy nén khí | C46: Phục Hưng | E46: 761000000 | F46: 1 | G46: =$E46*F46 -> 761000000 | H46: 1 | I46: =$E46*H46 -> 761000000 | J46: 1 | K46: =$E46*J46 -> 761000000 | L46: 1 | M46: =$E46*L46 -> 761000000
B47: Chi phí đi điện nguồn (điện nguồn chuyền máy + tủ điện nguồn) | C47: Thịnh Phát | E47: 800000000 | F47: 1 | G47: =$E47*F47 -> 800000000 | H47: 1 | I47: =$E47*H47 -> 800000000 | J47: 1 | K47: =$E47*J47 -> 800000000 | L47: 1 | M47: =$E47*L47 -> 800000000 | N47: GĐ 2 cộng thêm 300 triệu
B48: Chi phí khác | E48: 300000000 | F48: 1 | G48: =$E48*F48 -> 300000000 | H48: 1 | I48: =$E48*H48 -> 300000000 | J48: 1 | K48: =$E48*J48 -> 300000000 | L48: 1 | M48: =$E48*L48 -> 300000000 | N48: GĐ 2 cộng thêm 100 triệu
B49: Tủ điện điều khiển | C49: Plenma/HTL | E49: 222000000 | F49: 2 | G49: =$E49*F49 -> 444000000 | H49: 2 | I49: =$E49*H49 -> 444000000 | J49: 2 | K49: =$E49*J49 -> 444000000 | L49: 2 | M49: =$E49*L49 -> 444000000 | N49: GĐ 1 = 1 Cái
B50: Chi phí lắp đặt | C50: Plenma/HTL | E50: 360000000 | F50: 1 | G50: =$E50*F50 -> 360000000 | H50: 1 | I50: =$E50*H50 -> 360000000 | J50: 1 | K50: =$E50*J50 -> 360000000 | L50: 1 | M50: =$E50*L50 -> 360000000 | N50: GĐ 2 cộng thêm 100 triệu
B51: TỔNG CỘNG | G51: =G5+G43 -> 20265006000 | I51: =I5+I43 -> 20265006000 | K51: =K5+K43 -> 20265006000 | M51: =M5+M43 -> 20265006000
A53: B | B53: CHUYỀN BĂM CHAI PET
A54: STT | B54: Hạng mục đầu tư | C54: Nhà cung cấp | D54: Công suất/1 công đoạn | E54: Đơn giá ( chưa bao gồm VAT) | F54: H.S 40% | H54: H.S 60% | J54: H.S 80% | L54: H.S 100%
F55: Số lượng | G55: Tổng giá trị (VND) | H55: Số lượng | I55: Tổng giá trị (VND) | J55: Số lượng | K55: Tổng giá trị (VND) | L55: Số lượng | M55: Tổng giá trị (VND)
A56: I | B56: MÁY MÓC THIẾT BỊ CHUYỀN BĂM | G56: =I56/2 -> 0 | I56: =SUM(I57:I61) -> 0 | K56: =I56*1.5 -> 0 | M56: =SUM(M57:M61) -> 0
A62: II | B62: HỆ THỐNG XỬ LÝ NƯỚC THẢI | G62: =I62/2 -> 0 | I62: =I63 -> 0 | K62: =I62*1.5 -> 0 | M62: =M63 -> 0
B64: TỔNG CỘNG | G64: =G56+G62 -> 0 | I64: =I56+I62 -> 0 | K64: =K56+K62 -> 0 | M64: =M56+M62 -> 0

Sheet CAP.Phụ
B1: TRẠM HCM
B2: ĐÁNH GIÁ HIỆU QUẢ ĐẦU TƯ
B3: KẾ HOẠCH ĐẦU TƯ VÀ KHẤU HAO
A5: ĐẦU TƯ CAPEX - THIẾT BỊ PHỤ
A6: A | B6: CHUYỀN PHÂN LOẠI CHAI
A7: STT | B7: Hạng mục đầu tư | C7: Nhà cung cấp | D7: Công suất | E7: Đơn giá ( chưa bao gồm VAT) | F7: H.S 40% | H7: H.S 60% | J7: H.S 80% | L7: H.S 100% | N7: Ghi chú
F8: Số lượng | G8: Tổng giá trị (VND) | H8: Số lượng | I8: Tổng giá trị (VND) | J8: Số lượng | K8: Tổng giá trị (VND) | L8: Số lượng | M8: Tổng giá trị (VND)
A9: I | B9: THIẾT BỊ PHỤC VỤ SẢN XUẤT | G9: =SUM(G10:G13) -> 1724000000 | I9: =SUM(I10:I13) -> 1724000000 | K9: =SUM(K10:K13) -> 1724000000 | M9: =SUM(M10:M13) -> 1724000000
A10: 1 | B10: Xe nâng 2,5 tấn | C10: BYD | D10: 2.5 Tấn | E10: 500000000 | F10: 2 | G10: =$E10*F10 -> 1000000000 | H10: 2 | I10: =$E10*H10 -> 1000000000 | J10: 2 | K10: =$E10*J10 -> 1000000000 | L10: 2 | M10: =$E10*L10 -> 1000000000
A11: 2 | B11: Xe nâng tay 1,5 tấn | C11: BYD | D11: 1.5 Tấn | E11: 87000000 | F11: 2 | G11: =$E11*F11 -> 174000000 | H11: 2 | I11: =$E11*H11 -> 174000000 | J11: 2 | K11: =$E11*J11 -> 174000000 | L11: 2 | M11: =$E11*L11 -> 174000000 | N11: GĐ 1 = 1 Cái
A12: 3 | B12: Trạm cân 40 tấn | C12: MK-Cell | D12: 40 Tấn | E12: 450000000 | F12: 1 | G12: =$E12*F12 -> 450000000 | H12: 1 | I12: =$E12*H12 -> 450000000 | J12: 1 | K12: =$E12*J12 -> 450000000 | L12: 1 | M12: =$E12*L12 -> 450000000
A13: 4 | B13: Nhà chứa máy nén khí | C13: Thành Công | E13: 100000000 | F13: 1 | G13: =$E13*F13 -> 100000000 | H13: 1 | I13: =$E13*H13 -> 100000000 | J13: 1 | K13: =$E13*J13 -> 100000000 | L13: 1 | M13: =$E13*L13 -> 100000000
A14: II | B14: THIẾT BỊ PHỤC VỤ QUẢN LÝ | G14: =SUM(G15:G17) -> 201000000 | I14: =SUM(I15:I17) -> 201000000 | K14: =SUM(K15:K17) -> 201000000 | M14: =SUM(M15:M17) -> 201000000
A15: 1 | B15: Hồ sơ pháp lý ban đầu | E15: 20000000 | F15: 5 | G15: =$E15*F15 -> 100000000 | H15: 5 | I15: =$E15*H15 -> 100000000 | J15: 5 | K15: =$E15*J15 -> 100000000 | L15: 5 | M15: =$E15*L15 -> 100000000
A16: 2 | B16: Chi phí văn phòng, cải tạo cơ sở hạ tầng | E16: 100000000 | F16: 1 | G16: =$E16*F16 -> 100000000 | H16: 1 | I16: =$E16*H16 -> 100000000 | J16: 1 | K16: =$E16*J16 -> 100000000 | L16: 1 | M16: =$E16*L16 -> 100000000
A17: 3 | B17: Chi phí cho công tác huấn luyện & đào tạo | E17: 1000000 | F17: 1 | G17: =$E17*F17 -> 1000000 | H17: 1 | I17: =$E17*H17 -> 1000000 | J17: 1 | K17: =$E17*J17 -> 1000000 | L17: 1 | M17: =$E17*L17 -> 1000000
B18: TỔNG | G18: =G9+G14 -> 1925000000 | I18: =I9+I14 -> 1925000000 | K18: =K9+K14 -> 1925000000 | M18: =M9+M14 -> 1925000000
A20: B | B20: CHUYỀN BĂM CHAI PET
A21: STT | B21: Hạng mục đầu tư | C21: Nhà cung cấp | D21: Công suất | E21: Đơn giá ( chưa bao gồm VAT) | F21: H.S 40% | H21: H.S 60% | J21: H.S 80% | L21: H.S 100%
F22: Số lượng | G22: Tổng giá trị (VND) | H22: Số lượng | I22: Tổng giá trị (VND) | J22: Số lượng | K22: Tổng giá trị (VND) | L22: Số lượng | M22: Tổng giá trị (VND)
A23: I | B23: THIẾT BỊ PHỤC VỤ SẢN XUẤT | G23: =G24 -> 0 | I23: =I24 -> 0 | K23: =K24 -> 0 | M23: =M24 -> 0
A24: 1
B25: TỔNG | G25: =G23 -> 0 | I25: =I23 -> 0 | K25: =K23 -> 0 | M25: =M23 -> 0

Sheet C.Suất
B2: KẾ HOẠCH CÔNG SUẤT THEO CÔNG ĐOẠN VÀ ĐỊNH BIÊN LAO ĐỘNG TRỰC TIẾP
B3: 1/ CHUYỀN PHÂN LOẠI CHAI GĐ 1: | D3: Lưu ý: xác định rõ công suất của từng máy ở mỗi công đoạn để xác định bottle neck (nếu có) và tối ưu đầu tư!
B4: STT | C4: Công sản xuất: | D4: 1 - Cấp liệu | E4: 2 - Phá kiện | F4: 3 - Sàn tách tạp chất | G4: 4 - Lựa phân loại chai | H4: 5 - Tách nhãn 1 | I4: 6 - Lựa phân loại chai sau tách nhãn 1 | J4: 7 - Ép kiện 1 | K4: 8 - Tách nhãn 2 | L4: 9 - Lựa phân loại chai sau tách nhãn 2 | M4: 10 - Ép kiện 2 | N4: 11- Nhập/xuất kho | O4: Công suất thành phẩm cả chuyền
B5: 1 | C5: Tên máy móc thiết bị: | D5: Băng tải cấp liệu | F5: Lồng quay tách tạp chất | G5: Chuyền phân loại (5 loại) | H5: Máy tách nhãn 1 | I5: Chuyền phân loại | J5: Máy ép kiện + xe nâng tay | N5: Xe nâng | O5: Giả định hao hụt 10%
B6: 2 | C6: Công suất THIẾT KẾ: (Kg NVL đầu vào / giờ) | D6: 3000 | F6: 3000 | G6: 3000 | H6: 1000 | I6: 3000 | J6: 1500 | N6: =J6 -> 1500 | O6: =MIN(D6:N6) -> 1000
B7: 3 | C7: Công suất ĐỊNH MỨC: (Kg NVL đầu vào / giờ) | D7: 3000 | F7: 3000 | G7: 3000 | H7: 800 | I7: =H7*90% -> 720 | J7: =I7 -> 720 | N7: =J7 -> 720 | O7: =MIN(D7:N7) -> 720
B8: 4 | C8: Định mức công nhân sản xuất: (Số NV / Ca8) | D8: 2 | F8: 0 | G8: 1 | H8: 1 | I8: 1 | J8: 1 | N8: 0 | O8: =SUM(D8:N8) -> 6
C9: Diễn giải: | D9: 1 NV khuân hàng, 1NV cắt đổ bao | G9: NV lựa chai B4 và tạp bì | H9: NV kéo và thay các bao: nhãn, tạp bì trả, chai còn nhãn | I9: - 1 NV phân loại chai còn nhãn + nắp | J9: - 1 NV ép kiện, ép: thành phẩm, phế liệu, phó sản. | N9: - 1 NV ép kiện kiêm nhiệm
C10: Định mức kỹ thuật vận hành: (Số NV / Ca8) | F10: 1 kỹ thuật toàn chuyền | O10: 1
B12: 2/ CHUYỀN PHÂN LOẠI CHAI GĐ 2:
B13: STT | C13: Công sản xuất: | D13: 1 - Cấp liệu | E13: 2 - Phá kiện | F13: 3 - Sàn tách tạp chất | G13: 4 - Lựa phân loại chai | H13: 5 - Tách nhãn 1 | I13: 6 - Lựa phân loại chai sau tách nhãn 1 | J13: 7 - Ép kiện 1 | K13: 8 - Tách nhãn 2 | L13: 9 - Lựa phân loại chai sau tách nhãn 2 | M13: 10 - Ép kiện 2 | N13: 11- Nhập/xuất kho | O13: Công suất thành phẩm cả chuyền
B14: 1 | C14: Tên máy móc thiết bị: | D14: Băng tải cấp liệu | E14: Máy phá kiện (thủ công hay tự động) + băng tải phụ trợ | F14: Lồng quay tách tạp chất | G14: Chuyền phân loại (5 loại) | H14: Máy tách nhãn 1 | I14: Chuyền phân loại 1 | J14: Máy ép kiện 1 + xe nâng tay | K14: Máy tách nhãn 2 | L14: Chuyền phân loại 2 | M14: Máy ép kiện 2 | N14: Xe nâng | O14: Giả định hao hụt 10%
B15: 2 | C15: Công suất THIẾT KẾ: (Kg NVL đầu vào / giờ) | D15: 3000 | E15: 2000 | F15: 3000 | G15: 3000 | H15: 1000 | I15: 3000 | J15: 1500 | K15: 1000 | L15: 3000 | M15: 1500 | N15: =J15 -> 1500 | O15: =1500 -> 1500
B16: 3 | C16: Công suất ĐỊNH MỨC: (Kg NVL đầu vào / giờ) | D16: 3000 | E16: 2000 | F16: 3000 | G16: 3000 | H16: 800 | I16: =H16*0.9 -> 720 | J16: =I16 -> 720 | K16: 800 | L16: =K16*0.9 -> 720 | M16: =L16 -> 720 | N16: =J16 -> 720 | O16: =J16 -> 720
B17: 4 | C17: Định mức nhân công: (Số NV / Ca8) | D17: 2 | F17: 0 | G17: 1 | H17: 1 | I17: 1 | J17: 1 | K17: 0 | L17: 1 | M17: 1 | N17: 0 | O17: =SUM(D17:N17) -> 8
C18: Diễn giải: | D18: Luân chuyển 2 NV line 1: 1NV lái xe nâng, 1NV cắt dây | G18: NV lựa chai B4 và tạp bì | H18: NV kéo và thay các bao: nhãn, tạp bì trả, chai còn nhãn (2 line) | I18: - 1 NV phân loại chai còn nhãn + nắp | J18: - 1 NV ép kiện, ép: thành phẩm, phế liệu, phó sản. | K18: NV kéo và thay các bao: kiêm nhiệm | L18: - 1 NV phân loại chai còn nhãn + nắp | M18: - 1 NV ép kiện kiêm nhiệm | N18: - 1 NV ép kiện kiêm nhiệm
C19: Định mức kỹ thuật vận hành: (Số NV / Ca8) | F19: 1 kỹ thuật toàn chuyền | O19: 1

Sheet Đ.Biên
B1: ĐỊNH BIÊN NHÂN SỰ
B2: I - ĐỊNH BIÊN PHÂN LOẠI CHAI | K2: ĐVT: Người
B3: STT | C3: Phòng ban | D3: Tài khoản | E3: H.S 40% | F3: H.S 60% | G3: H.S 80% | H3: H.S 100% | I3: Lương cơ bản/ tháng | J3: Số Ca SX | K3: Ghi chú
C4: Số Ca sản xuất | E4: =G.Định!F18 -> 1 | F4: =G.Định!H18 -> 2 | G4: =G.Định!J18 -> 2.5 | H4: =G.Định!L18 -> 3
B5: 1 | C5: Ban giám đốc | D5: 642 | E5: =SUM(E6:E7) -> 1 | F5: =SUM(F6:F7) -> 1 | G5: =SUM(G6:G7) -> 1 | H5: =SUM(H6:H7) -> 1
C6: Giám đốc Trạm | E6: 1 | F6: 1 | G6: 1 | H6: 1 | I6: 70000000 | J6: 1 | K6: Kiêm người ĐDPL
C7: Người đại diện pháp luật | J7: 1
B8: 2 | C8: Phòng Hành chánh nhân sự | D8: 642 | E8: =SUM(E9:E12) -> 3 | F8: =SUM(F9:F12) -> 3 | G8: =SUM(G9:G12) -> 3 | H8: =SUM(H9:H12) -> 3
C9: Trưởng phòng nhân sự | E9: 1 | F9: 1 | G9: 1 | H9: 1 | I9: 28000000 | J9: 1
C10: Nhân viên hành chính | E10: 1 | F10: 1 | G10: 1 | H10: 1 | I10: 12000000 | J10: 1
C11: Nhân viên nhân sự | I11: 12000000 | J11: 1
C12: Nhân viên tạp vụ | E12: 1 | F12: 1 | G12: 1 | H12: 1 | I12: 8000000 | J12: 1
B13: 3 | C13: Phòng Kế toán | D13: 642 | E13: =SUM(E14:E16) -> 3 | F13: =SUM(F14:F16) -> 3 | G13: =SUM(G14:G16) -> 3 | H13: =SUM(H14:H16) -> 3
C14: Kế toán trưởng | E14: 1 | F14: 1 | G14: 1 | H14: 1 | I14: 28000000 | J14: 1
C15: Kế toán tổng hợp | E15: 1 | F15: 1 | G15: 1 | H15: 1 | I15: 18000000 | J15: 1
C16: Kế toán viên | E16: 1 | F16: 1 | G16: 1 | H16: 1 | I16: 12000000 | J16: 1
B17: 4 | C17: Phòng Cung ứng | D17: 642 | E17: =E18 -> 0 | F17: =F18 -> 1 | G17: =G18 -> 1 | H17: =H18 -> 1
C18: Nhân viên mua hàng/ nhận hàng | F18: 1 | G18: 1 | H18: 1 | I18: 12000000 | J18: 1
B19: 5 | C19: Phòng Mua hàng (Bao gồm NVL + Vật tư) | D19: 642 | E19: =E20 -> 1 | F19: =F20 -> 1 | G19: =G20 -> 1 | H19: =H20 -> 1
C20: Nhân viên mua hàng (ngoại trừ mua chai) | E20: 1 | F20: 1 | G20: 1 | H20: 1 | I20: 12000000 | J20: 1
B21: 6 | C21: Phòng Quản Trị Hệ Thống | D21: 642 | E21: =E22 -> 0 | F21: =F22 -> 1 | G21: =G22 -> 1 | H21: =H22 -> 1
C22: Nhân viên QTHT (ISO, 3Q,…) | F22: 1 | G22: 1 | H22: 1 | I22: 12000000 | J22: 1
B23: 7 | C23: Phòng 5S & an toàn | D23: 642 | E23: =E24 -> 0 | F23: =F24 -> 1 | G23: =G24 -> 1 | H23: =H24 -> 1
C24: Nhân viên 5S & an toàn | F24: 1 | G24: 1 | H24: 1 | I24: 12000000 | J24: 1
B25: 8 | C25: Phòng Kho vận (NVL+TP) | D25: 627 | E25: =SUM(E26:E27) -> 2 | F25: =SUM(F26:F27) -> 3 | G25: =SUM(G26:G27) -> 5 | H25: =SUM(H26:H27) -> 5
C26: Thủ kho (phiếu nhập, xuất, quản lý kho) | F26: 1 | G26: 1 | H26: 1 | I26: 12000000 | J26: 1
C27: Nhân viên xuống/lên hàng (1 nhập NVL, 1 xuất TP) | E27: 2 | F27: 2 | G27: 4 | H27: 4 | I27: 10000000 | J27: 1
B28: 9 | C28: Phòng Kiểm soát chất lượng | D28: 627 | E28: =SUM(E29:E30) -> 1 | F28: =SUM(F29:F30) -> 2 | G28: =SUM(G29:G30) -> 3 | H28: =SUM(H29:H30) -> 3
C29: Kiểm soát chất lượng NVL nhập - 1 ca hành chánh | E29: 1 | F29: 1 | G29: 1 | H29: 1 | I29: 12000000 | J29: 1
C30: Kiểm soát chất lượng thành phẩm (1 ca) | F30: 1 | G30: 2 | H30: 2 | I30: 12000000 | J30: 1 | K30: Theo Ca
B31: 10 | C31: Phòng Kỹ thuật | D31: 627 | E31: =SUM(E32:E33) -> 2 | F31: =SUM(F32:F33) -> 3 | G31: =SUM(G32:G33) -> 5 | H31: =SUM(H32:H33) -> 5
C32: Tổ trưởng kỹ thuật | E32: 1 | F32: 1 | G32: 1 | H32: 1 | I32: 12000000 | J32: 1
C33: Nhân viên bảo trì (1 điện, 1 cơ) (1 ca) | E33: 1 | F33: =E33*2 -> 2 | G33: 4 | H33: 4 | I33: 10000000 | J33: 1 | K33: Theo Ca
B34: 11 | C34: Phòng Sản xuất | E34: =E35+E39 -> 12 | F34: =F35+F39 -> 20 | G34: =G35+G39 -> 25 | H34: =H35+H39 -> 29
B35: 11.1 | C35: Bộ phận quản lý sản xuất | D35: 627 | E35: =SUM(E36:E38) -> 3 | F35: =SUM(F36:F38) -> 4 | G35: =SUM(G36:G38) -> 4 | H35: =SUM(H36:H38) -> 4
C36: Quản lý sản xuất | E36: 1 | F36: 1 | G36: 1 | H36: 1 | I36: 40000000 | J36: 1
C37: Tổ trưởng sản xuất (1 ca) | E37: 1 | F37: =E37*2 -> 2 | G37: 2 | H37: 2 | I37: 12000000 | J37: 1 | K37: Theo Ca
C38: Kế hoạch sản xuất | E38: 1 | F38: 1 | G38: 1 | H38: 1 | I38: 10000000 | J38: 1
B39: 11.2 | C39: Công nhân trực tiếp sản xuất | D39: 622 | E39: =E40+E41 -> 9 | F39: =F40+F41 -> 16 | G39: =G40+G41 -> 21 | H39: =H40+H41 -> 25
C40: Nhân viên phân loại (1ca) | E40: 7 | F40: =E40*2 -> 14 | G40: 17 | H40: =E40*3 -> 21 | I40: 8000000 | J40: 1 | K40: Theo Ca
C41: Nhân viên lái xe nâng (1 ca) | E41: 2 | F41: 2 | G41: 4 | H41: 4 | I41: 8000000 | J41: 1 | K41: Theo Ca
C42: TỔNG NHÂN SỰ PHÂN LOẠI CHAI | E42: =E5+E8+E13+E17+E19+E25+E28+E21+E23+E31+E34 -> 25 | F42: =F5+F8+F13+F17+F19+F25+F28+F21+F23+F31+F34 -> 39 | G42: =G5+G8+G13+G17+G19+G25+G28+G21+G23+G31+G34 -> 49 | H42: =H5+H8+H13+H17+H19+H25+H28+H21+H23+H31+H34 -> 53
B44: II - ĐỊNH BIÊN CHUYỀN BĂM VẢY
B45: STT | C45: Phòng ban | D45: Tài khoản | E45: H.S 40% | F45: H.S 60% | G45: H.S 80% | H45: H.S 100% | I45: Lương cơ bản/ tháng | J45: Số Ca SX | K45: Ghi chú
B46: 1 | C46: Kiểm soát chất lượng | D46: 627 | E46: =E47 -> 0 | F46: =F47 -> 0 | G46: =G47 -> 0 | H46: =H47 -> 0
C47: Kiểm soát chất lượng vảy - 1 ca hành chánh
B48: 2 | C48: Kỹ thuật | D48: 627 | E48: 0 | F48: =SUM(F49:F50) -> 0 | G48: 0 | H48: =SUM(H49:H50) -> 0
C49: Nhân viên bảo trì (điện, cơ) (1 ca)
C50: Nhân viên xử lý nước thải, bùn thải - 1 ca
B51: 3 | C51: Kho vận | D51: 627 | E51: =E52 -> 0 | F51: =F52 -> 0 | G51: =G52 -> 0 | H51: =H52 -> 0
C52: Nhân viên kho vảy
B53: 4 | C53: Sản xuất | D53: 622 | E53: =E54 -> 0 | F53: =F54 -> 0 | G53: =G54 -> 0 | H53: =H54 -> 0
C54: Nhân viên chuyền băm vảy (1 chuyền x 1ca)
C55: TỔNG NHÂN SỰ BĂM VẢY | E55: 0 | F55: =F46+F48+F51+F53 -> 0 | G55: 0 | H55: =H46+H48+H51+H53 -> 0
B57: III (I+II) | C57: TỔNG NHÂN SỰ (CẢ CTY) | E57: =E42+E55 -> 25 | F57: =F42+F55 -> 39 | G57: =G42+G55 -> 49 | H57: =H42+H55 -> 53
C58: Trong đó:
B59: 1 | C59: Nhân viên sản xuất trực tiếp: | D59: 622 | E59: =SUMIF($D$5:$D$55,$D59,E$5:E$55) -> 9 | F59: =SUMIF($D$5:$D$55,$D59,F$5:F$55) -> 16 | G59: =SUMIF($D$5:$D$55,$D59,G$5:G$55) -> 21 | H59: =SUMIF($D$5:$D$55,$D59,H$5:H$55) -> 25
B60: 2 | C60: Nhân viên sản xuất gián tiếp: | D60: 627 | E60: =SUMIF($D$5:$D$55,$D60,E$5:E$55) -> 8 | F60: =SUMIF($D$5:$D$55,$D60,F$5:F$55) -> 12 | G60: =SUMIF($D$5:$D$55,$D60,G$5:G$55) -> 17 | H60: =SUMIF($D$5:$D$55,$D60,H$5:H$55) -> 17
B61: 3 | C61: Nhân viên quản lý | D61: 642 | E61: =SUMIF($D$5:$D$55,$D61,E$5:E$55) -> 8 | F61: =SUMIF($D$5:$D$55,$D61,F$5:F$55) -> 11 | G61: =SUMIF($D$5:$D$55,$D61,G$5:G$55) -> 11 | H61: =SUMIF($D$5:$D$55,$D61,H$5:H$55) -> 11

Sheet DMSX
A3: ĐỊNH MỨC BIẾN PHÍ SẢN XUẤT | I3: ĐVT: Đồng
A4: STT | B4: Khoản mục phí | C4: ĐVT | D4: Số lượng tiêu hao | E4: Đơn giá | F4: Tổng chi phí | G4: Định mức thành phẩm (kg) | H4: Chi phí đồng/ kg sản phẩm | I4: Ghi chú
A5: I | B5: ĐỊNH MỨC PHÂN LOẠI CHAI
A6: 1 | B6: Chi phí điện sản xuất | C6: Kw/h | D6: ='DMSX C.tiết'!C9 -> 130.8 | E6: 2100 | F6: =D6*E6 -> 274680 | G6: 2700 | H6: =F6/G6 -> 101.73333 | I6: Công suất 1 chuyền/h = 2.700 kg
A7: 2 | B7: Chi phí dây đai | C7: Cuộn/kiện chai | D7: 0.35 | E7: 51000 | F7: =D7*E7 -> 17850 | G7: 230 | H7: =F7/G7 -> 77.608696 | I7: 1 kiện chai = 230 kg
A8: 3 | B8: Chi phí dao tách nhãn | C8: Bộ | D8: 1 | E8: 165000000 | F8: =D8*E8 -> 165000000 | G8: 1500000 | H8: =F8/G8 -> 110 | I8: 1 bộ băm được 1,5 tấn
A9: 4 | B9: Vật tư khác phục vụ sản xuất
A10: 5 | B10: Chi phí xăng, dầu xe nâng | C10: Lít/h | D10: 2.7 | E10: 15000 | F10: =D10*E10 -> 40500 | G10: =2700/2 -> 1350 | H10: =F10/G10 -> 30 | I10: CĐ băm sử dụng 2 xe nâng
A11: 6 | B11: Chi phí xử lý rác thải CN (nhãn) | C11: Đồng/kg nhãn | D11: 1 | E11: 300 | F11: =D11*E11 -> 300 | G11: =D11/5% -> 20 | H11: =F11/G11 -> 15 | I11: Thuê xử lý nhãn chai, tỷ lệ hao huạt nhãn 5%
A12: 7 | B12: Chi phí sửa chữa, bảo trì MMTB sản xuất | C12: % giá trị MMTB
A13: 8 | B13: Chi phí sửa chữa, bảo trì xe nâng | C13: Đồng/tháng/chiếc | D13: 2 | E13: 3000000 | F13: =D13*E13 -> 6000000 | G13: =G6*16*26 -> 1123200 | H13: =F13/G13 -> 5.3418803 | I13: Sửa chữa xe nâng
A14: II | B14: CÔNG ĐOẠN BĂM VẢY
A15: 1 | B15: Chi phí điện sản xuất | C15: Kw/h | D15: ='DMSX C.tiết'!C19 -> 197.16 | E15: 2200 | F15: =D15*E15 -> 433752 | G15: 1650 | H15: =F15/G15 -> 262.88 | I15: Công suất băm/h = 1.650 kg; Máy chính: 255kwh/giờ - Máy phụ: 90kwh/giờ
A16: 2 | B16: Chi phí hóa chất (rửa vảy)
A17: 3 | B17: Chi phí dao băm vảy | C17: Bộ | D17: 1 | E17: =ROUND('DMSX C.tiết'!H28,-6) -> 72000000 | F17: =D17*E17 -> 72000000 | G17: =ROUND('DMSX C.tiết'!H28/'DMSX C.tiết'!I28,-5) -> 700000 | H17: =F17/G17 -> 102.85714 | I17: 1 bộ băm được 700 tấn
A18: 4 | B18: Chi phí bao jumbo đựng vảy | C18: Bao | D18: 1 | E18: 71000 | F18: =D18*E18 -> 71000 | G18: 450 | H18: =F18/G18 -> 157.77778 | I18: 1 bao jumbo vảy = 450 kg
A19: 5 | B19: Vật tư khác phục vụ sản xuất
A20: 6 | B20: Chi phí nước sản xuất (băm, rửa vảy) | C20: m3/h | D20: 3 | E20: 11500 | F20: =D20*E20 -> 34500 | G20: 1650 | H20: =F20/G20 -> 20.909091
A21: 7 | B21: Chi phí xăng, dầu xe nâng | C21: Lít/h | D21: 2.7 | E21: 15000 | F21: =D21*E21 -> 40500 | G21: 1650 | H21: =F21/G21 -> 24.545455 | I21: CĐ băm sử dụng 1 xe nâng
A22: 8 | B22: Chi phí xử lý nước thải | C22: m3/h | D22: =D20 -> 3 | E22: 50000 | F22: =D22*E22 -> 150000 | G22: 1650 | H22: =F22/G22 -> 90.909091 | I22: Hóa chất XLNT
A23: 9 | B23: Chi phí xử lý bùn thải | C23: đồng/kg bùn thải | D23: =G15*3% -> 49.5 | E23: 1200 | F23: =D23*E23 -> 59400 | G23: 1650 | H23: =F23/G23 -> 36 | I23: Hao hụt bùn đất 3%
A24: 10 | B24: Chi phí sửa chữa, bảo trì MMTB sản xuất | C24: % giá trị MMTB
A25: 11 | B25: Chi phí sửa chữa, bảo trì xe nâng | C25: đồng/tháng/chiếc | D25: 1 | E25: 3000000 | F25: =D25*E25 -> 3000000 | G25: =1650*16*26 -> 686400 | H25: =F25/G25 -> 4.3706294 | I25: Sửa chữa xe nâng
A26: III | B26: ĐỊNH MỨC VẬN CHUYỂN
A27: 1 | B27: Chi phí vận chuyển chai | C27: Chuyến | D27: 1 | E27: =1500000 -> 1500000 | F27: =D27*E27 -> 1500000 | G27: 8000 | H27: =F27/G27 -> 187.5 | I27: Xe trọng tải 10 tấn, chở được 8 tấn chai
A28: 2 | B28: Chi phí vận chuyển vảy | C28: Km

Sheet DMSX C.tiết
B1: ĐỊNH MỨC SX CHI TIẾT
B2: 1 - Định mức điện Chuyền AI (1 chuyền)
B3: Tên MMTB sử dụng điện | C3: Số điện sử dụng kwh/ giờ | D3: Số điện sử dụng kwh/ 1 kg TP
B4: Hệ thống máy Sort + TB phụ | C4: 85 | D4: =C4/$E$24 -> 1.4166667e-05
B5: 2 Chuyền phân loại chai | C5: 31 | D5: =C5/$E$24 -> 5.1666667e-06
B6: Tách nhãn BRT | C6: 57 | D6: =C6/$E$24 -> 9.5e-06
B7: Máy nén khí phân loại 80% | C7: =90*50% -> 45 | D7: =C7/$E$24 -> 7.5e-06
B8: Định mức thiết kế HT AI | C8: =SUM(C4:C7) -> 218 | D8: =C8/$E$24 -> 3.6333333e-05
B9: Thực tế tiêu hao 62% | C9: =C8*60% -> 130.8 | D9: =C9/$E$24 -> 2.18e-05
B11: 2 - Định mức điện chuyền băm vảy
B12: Tên MMTB sử dụng điện | C12: Số điện sử dụng kwh/ giờ
B13: Máy phá kiện | C13: 25
B14: Hệ thống băm thô | C14: 255
B15: Hệ thống rửa lạnh
B16: Thiết bị phụ trợ: Bơm nước, HT li tâm | C16: 20
B17: Máy nén khí phân loại 20% | C17: =90*20% -> 18
B18: Định mức thiết kế | C18: =SUM(C13:C17) -> 318
B19: Thực tế tiêu hao 62% | C19: =C18*62% -> 197.16
B21: 3 - Định mức dao băm vảy
B22: Nội dung | C22: Đơn vị tính | D22: Số lượng | E22: Đơn giá | F22: Sản lượng SX / 1 lưỡi dao (Tấn/1 lưỡi dao) | G22: Sản lượng SX / 1 bộ dao (kg/1 bộ dao) | H22: Tổng CP | I22: Đồng/kg
B23: Dao băm động - chiều dài 60cm | C23: Cái | D23: 14 | E23: 2400000 | F23: 46 | G23: =D23*F23 -> 644 | H23: =D23*E23 -> 33600000 | I23: =(D23*E23)/G23/1000 -> 52.173913
B24: Dao băm tĩnh - chiều dài 120cm | C24: Cái | D24: 6 | E24: 6000000 | F24: 324 | G24: =D24*F24 -> 1944 | H24: =D24*E24 -> 36000000 | I24: =(D24*E24)/G24/1000 -> 18.518519
B25: Bu long M20x110 | C25: Con | D25: 28 | E25: 23000 | G25: =2*G23 -> 1288 | H25: =D25*E25 -> 644000 | I25: =(D25*E25)/G25/1000 -> 0.5
B26: Bu long M20x70 | C26: Con | D26: 28 | E26: 25000 | G26: 1288 | H26: =D26*E26 -> 700000 | I26: =(D26*E26)/G26/1000 -> 0.54347826
B27: Đá mài dao | C27: Viên | D27: 3 | E27: 464000 | G27: =(D23*D27)+(D24*3) -> 60 | H27: =D27*E27 -> 1392000 | I27: =(D27*E27)/G27/1000 -> 23.2
B28: Tổng cộng | H28: =SUM(H23:H27) -> 72336000 | I28: =SUM(I23:I27)*110% -> 104.4295

Sheet DMQL
B1: ĐỊNH MỨC CHI PHÍ QUẢN LÝ (ĐVT: đồng) | O1: ĐVT: Triệu đồng
B2: STT | C2: Mục phí cấp 1 | D2: Mục phí cấp 2 | E2: Mục phí cấp 3 | F2: Link công thức | G2: H.S 40% | I2: H.S 60% | K2: H.S 80% | M2: H.S 100% | O2: Ghi chú
G3: 1 Tháng | H3: Cả Năm | I3: 1 Tháng | J3: Cả Năm | K3: 1 Tháng | L3: Cả Năm | M3: 1 Tháng | N3: Cả Năm
B4: 1 | C4: Chi phí điện, nước quản lý | D4: Chi phí điện quản lý | E4: Chi phí điện quản lý | F4: Chi phí điện quản lý | G4: 2000000 | I4: 2000000 | K4: 2000000 | M4: 2000000
D5: Chi phí nước sinh hoạt | E5: Chi phí nước sinh hoạt | F5: Chi phí nước sinh hoạt | G5: 3000000 | I5: 3000000 | K5: 3000000 | M5: 3000000
B6: =IF(C6=0,"",MAX($B$4:B5)+1) -> 2 | C6: Chi phí in ấn, vật tư, VPP | D6: Chi phí in ấn, vật tư, VPP | E6: Chi phí thuê máy photo, máy in | F6: Chi phí in ấn, vật tư, VPP | G6: 2000000 | I6: 2000000 | K6: 2000000 | M6: 2000000
B7: =IF(C7=0,"",MAX($B$4:B6)+1) | E7: Chi phí VPP | F7: Chi phí in ấn, vật tư, VPP | G7: 2000000 | I7: 2000000 | K7: 2000000 | M7: 2000000
B8: =IF(C8=0,"",MAX($B$4:B7)+1) | E8: Chi phí mực in, mực photo | F8: Chi phí in ấn, vật tư, VPP | G8: 200000 | I8: 200000 | K8: 200000 | M8: 200000
B9: =IF(C9=0,"",MAX($B$4:B8)+1) | E9: Chi phí công chứng, sao y, thuế khác | F9: Chi phí in ấn, vật tư, VPP | G9: 300000 | I9: 300000 | K9: 300000 | M9: 300000
B10: =IF(C10=0,"",MAX($B$4:B9)+1) | E10: Chi phí vật dụng quản lý khác | F10: Chi phí in ấn, vật tư, VPP
B11: =IF(C11=0,"",MAX($B$4:B10)+1) -> 3 | C11: Thuế, phí, lệ phí, bồi thường, nộp phạt, khếu nại khách hàng | D11: Thuế, phí, lệ phí | E11: Thuế môn bài | F11: Thuế, phí, lệ phí | H11: 3000000 | J11: 3000000 | L11: 3000000 | N11: 3000000 | O11: Vốn >10 tỷ = 3 triệu
E12: Thuế, phí, lệ phí khác | F12: Thuế, phí, lệ phí
B13: =IF(C13=0,"",MAX($B$4:B11)+1) -> 4 | C13: Chi phí bảo hiểm tài sản | D13: Chi phí bảo hiểm tài sản | E13: Chi phí bảo hiểm tài sản | F13: Chi phí bảo hiểm tài sản | H13: ='K.Hao, L.v'!C12*0.2% -> 44380012 | J13: ='K.Hao, L.v'!D12*0.2% -> 44380012 | L13: ='K.Hao, L.v'!E12*0.2% -> 44380012 | N13: ='K.Hao, L.v'!F12*0.2% -> 44380012 | O13: Cháy nổ bắt buộc (0.2% giá trị TS)
B14: =IF(C14=0,"",MAX($B$4:B13)+1) -> 5 | C14: Chi phí ủng hộ, hỗ trợ, tài trợ | D14: Chi phí ủng hộ, hỗ trợ, tài trợ | E14: Chi phí ủng hộ, hỗ trợ, tài trợ | F14: Chi phí ủng hộ, hỗ trợ, tài trợ | G14: 2000000 | I14: 2000000 | K14: 2000000 | M14: 2000000
B15: 6 | C15: Chi phí internet, điện thoại, bưu phẩm | D15: Chi phí internet, điện thoại, bưu phẩm | E15: Chi phí internet | F15: Chi phí internet, điện thoại, bưu phẩm | G15: 1000000 | I15: 1000000 | K15: 1000000 | M15: 1000000
E16: Chi phí điện thoại bàn | F16: Chi phí internet, điện thoại, bưu phẩm | G16: 200000 | I16: 200000 | K16: 200000 | M16: 200000
E17: Chi phí bưu phẩm | F17: Chi phí internet, điện thoại, bưu phẩm | G17: 300000 | I17: 300000 | K17: 300000 | M17: 300000
B18: 7 | C18: Chi phí tiếp khách | D18: Chi phí tiếp khách | E18: Chi phí tiếp khách | F18: Chi phí tiếp khách | G18: =3000000 -> 3000000 | I18: =3000000 -> 3000000 | K18: =3000000 -> 3000000 | M18: =3000000 -> 3000000
B19: =IF(C19=0,"",MAX($B$4:B18)+1) | E19: Chi phí quà tặng khách | F19: Chi phí tiếp khách | H19: 10000000 | J19: 10000000 | L19: 10000000 | N19: 10000000 | O19: Quà tặng lễ tết
B20: =IF(C20=0,"",MAX($B$4:B19)+1) | E20: Chi phí bồi dưỡng | F20: Chi phí tiếp khách
B21: 8 | C21: Chi phí công tác | D21: Chi phí công tác | E21: Vé máy bay, xe | F21: Chi phí công tác | G21: 1000000 | I21: 1000000 | K21: 1000000 | M21: 1000000
E22: Khách sạn | F22: Chi phí công tác | G22: 500000 | I22: 500000 | K22: 500000 | M22: 500000
B23: 9 | C23: Chi phí hành chánh văn phòng | D23: Chi phí hành chánh văn phòng | E23: Chi phí nước uống | F23: Chi phí nước uống | G23: 5000000 | I23: 5000000 | K23: 5000000 | M23: 5000000
B24: =IF(C24=0,"",MAX($B$4:B23)+1) | E24: Chi phí cà phê, bánh phòng họp | F24: Chi phí khác
B25: =IF(C25=0,"",MAX($B$4:B24)+1) | E25: Chi phí trang trí văn phòng | F25: Chi phí khác | H25: 5000000 | J25: 5000000 | L25: 5000000 | N25: 5000000 | O25: Trang trí lễ tết
B26: =IF(C26=0,"",MAX($B$4:B25)+1) | E26: Chi phí 5S, an toàn lao động, PCCC | F26: Chi phí 5S, an toàn lao động, PCCC | G26: 1000000 | I26: 1000000 | K26: 1000000 | M26: 1000000
B27: =IF(C27=0,"",MAX($B$4:B26)+1) | E27: Chi phí rác thải sinh hoạt, rác y tế | F27: Chi phí khác | G27: 500000 | I27: 500000 | K27: 500000 | M27: 500000
B28: =IF(C28=0,"",MAX($B$4:B27)+1) | E28: Chi phí kiểm soát côn trùng | F28: Chi phí khác
B29: =IF(C29=0,"",MAX($B$4:B28)+1) | E29: Chi phí vật tư quản lý | F29: Chi phí khác
B30: =IF(C30=0,"",MAX($B$4:B29)+1) | E30: Chi phí hành chánh văn phòng khác | F30: Chi phí khác
B31: =IF(C31=0,"",MAX($B$4:B30)+1) -> 10 | C31: Phúc lợi nhân viên | D31: Chi phí y tế, khám sức khỏe, bảo hiểm sức khỏe | E31: Chi phí y tế, khám sức khỏe, bảo hiểm sức khỏe | F31: Chi phí y tế, khám sức khỏe, bảo hiểm sức khỏe | H31: =Đ.Biên!$E$57*1000000 -> 25000000 | J31: =Đ.Biên!$F$57*1000000 -> 39000000 | L31: =Đ.Biên!$G$57*1000000 -> 49000000 | N31: =Đ.Biên!$H$57*1000000 -> 53000000 | O31: 1 triệu/đồng/người
B32: =IF(C32=0,"",MAX($B$4:B31)+1) | D32: Chi phí suất ăn, tiền ăn giữa ca | E32: Chi phí suất ăn, tiền ăn giữa ca | F32: Chi phí suất ăn, tiền ăn giữa ca | H32: =Đ.Biên!$E$57*30000*26 -> 19500000 | J32: =Đ.Biên!$F$57*30000*26 -> 30420000 | L32: =Đ.Biên!$G$57*30000*26 -> 38220000 | N32: =Đ.Biên!$H$57*30000*26 -> 41340000 | O32: 30.000 đồng/người
B33: =IF(C33=0,"",MAX($B$4:B32)+1) | D33: Chi phí đồng phục, đồ bảo hộ lao động | E33: Chi phí đồng phục | F33: Chi phí đồng phục, đồ bảo hộ lao động | H33: =Đ.Biên!$E$57*800000 -> 20000000 | J33: =Đ.Biên!$F$57*800000 -> 31200000 | L33: =Đ.Biên!$G$57*800000 -> 39200000 | N33: =Đ.Biên!$H$57*800000 -> 42400000 | O33: 800.000 đồng/người
B34: =IF(C34=0,"",MAX($B$4:B33)+1) | E34: Chi phí đồ bảo hộ lao động | F34: Chi phí đồng phục, đồ bảo hộ lao động | G34: 1500000 | I34: 1500000 | K34: 1500000 | M34: 1500000
B35: =IF(C35=0,"",MAX($B$4:B34)+1) | D35: Chi phí tiệc tất niên, tổng kết | E35: Chi phí tiệc tất niên, tổng kết | F35: Chi phí tiệc tất niên, tổng kết | H35: =Đ.Biên!$E$57*1000000 -> 25000000 | J35: =Đ.Biên!$F$57*1000000 -> 39000000 | L35: =Đ.Biên!$G$57*1000000 -> 49000000 | N35: =Đ.Biên!$H$57*1000000 -> 53000000 | O35: 1 triệu/đồng/người (gồm chi phí chung)
B36: =IF(C36=0,"",MAX($B$4:B35)+1) | D36: Chi phí teambuilding | E36: Chi phí teambuilding | F36: Chi phí teambuilding | H36: =Đ.Biên!$E$57*4000000 -> 100000000 | J36: =Đ.Biên!$F$57*4000000 -> 156000000 | L36: =Đ.Biên!$G$57*4000000 -> 196000000 | N36: =Đ.Biên!$H$57*4000000 -> 212000000 | O36: 4 triệu/đồng/người (gồm chi phí chung)
B37: =IF(C37=0,"",MAX($B$4:B36)+1) | D37: Chi phí thuê xe đưa rước nhân viên | E37: Chi phí thuê xe đưa rước nhân viên | F37: Chi phí thuê xe đưa rước nhân viên
B38: =IF(C38=0,"",MAX($B$4:B37)+1) | D38: Chi phí tuyển dụng | E38: Chi phí tuyển dụng | F38: Chi phí tuyển dụng, đào tạo
B39: =IF(C39=0,"",MAX($B$4:B38)+1) | D39: Chi phí đào tạo | E39: Chi phí đào tạo | F39: Chi phí tuyển dụng, đào tạo | G39: 2000000 | I39: 2000000 | K39: 2000000 | M39: 2000000
B40: =IF(C40=0,"",MAX($B$4:B39)+1) | D40: Chi phí phúc lợi nhân viên khác | E40: Chi phí phụ cấp điện thoại di động | F40: Chi phí khác | G40: 500000 | I40: 500000 | K40: 500000 | M40: 500000
B41: =IF(C41=0,"",MAX($B$4:B40)+1) | E41: Chi phí gởi xe du lịch, xe gắn máy | F41: Chi phí khác
B42: =IF(C42=0,"",MAX($B$4:B41)+1) | E42: Chi phí hiếu hỷ, phúc lợi khác | F42: Chi phí hiếu hỷ, phúc lợi khác | G42: 1000000 | I42: 1000000 | K42: 1000000 | M42: 1000000
B43: =IF(C43=0,"",MAX($B$4:B42)+1) | E43: Chi phí phúc lợi nhân viên khác | F43: Chi phí khác
B44: 11 | C44: Chi phí ngân hàng | D44: Chi phí ngân hàng | E44: Chi phí ngân hàng | F44: Chi phí ngân hàng | G44: 500000 | I44: 500000 | K44: 500000 | M44: 500000
B45: 12 | C45: Chi phí khác | D45: Chi phí khác | E45: Chi phí khác | F45: Chi phí khác | G45: 3000000 | I45: 3000000 | K45: 3000000 | M45: 3000000
B46: 13 | C46: Chi phí công cụ dụng cụ phục vụ quản lý | D46: Chi phí công cụ dụng cụ phục vụ quản lý | E46: Chi phí công cụ dụng cụ phục vụ quản lý | F46: Chi phí công cụ dụng cụ phục vụ quản lý | G46: 1000000 | I46: 1000000 | K46: 1000000 | M46: 1000000
B47: 14 | C47: Chi phí dịch vụ bảo vệ | D47: Chi phí dịch vụ bảo vệ | E47: Chi phí dịch vụ bảo vệ | F47: Chi phí dịch vụ bảo vệ | G47: 36000000 | I47: 36000000 | K47: 36000000 | M47: 36000000 | O47: 2 người (24/24)
B48: 15 | C48: Chi phí bản quyền (licences) | D48: Chi phí bản quyền (licences) | E48: Licences SAP | F48: Chi phí bản quyền (licences) | G48: =100*26500*8 -> 21200000 | I48: =100*26500*8 -> 21200000 | K48: =100*26500*8 -> 21200000 | M48: =100*26500*8 -> 21200000 | O48: 2.6 triệu/ users/tháng
E49: Licences VMS | F49: Chi phí bản quyền (licences) | G49: =(1525200+1377600)*1 -> 2902800 | I49: =(1525200+1377600)*1 -> 2902800 | K49: =(1525200+1377600)*1 -> 2902800 | M49: =(1525200+1377600)*1 -> 2902800 | O49: 2.6 triệu/ users/tháng
E50: Các phần mềm khác (365, econtract,…) | F50: Chi phí bản quyền (licences) | G50: =3000000*8 -> 24000000 | I50: =3000000*8 -> 24000000 | K50: =3000000*8 -> 24000000 | M50: =3000000*8 -> 24000000

Sheet G.Định
C2: CÁC GIẢ ĐỊNH
C3: Mồ hình sản xuất
C4: Phân loại chai / băm vảy | D4: Phân loại chai | E4: Băm vảy
C5: Chọn: → | D5: x
C7: Công suất thiết kế chuyền | N7: Công suất
C8: Quy mô đầu tư | D8: ĐVT | E8: H.S 40% | F8: H.S 60% | G8: H.S 80% | H8: H.S 100% | N8: 1giờ | O8: 1500 | P8: tấn
C9: Sản lượng NVL đầu vào (Chai B0) | D9: Tấn/Tháng | E9: 1000000 | F9: 1000000 | G9: 1000000 | H9: 1000000 | N9: 1 ca | O9: 8 | P9: giờ
N10: 1 tháng | O10: 30 | P10: ngày
C11: Hiệu suất mong muốn | N11: Công suất 1 ca/1 tháng | O11: =O8*O9*O10 -> 360000 | P11: Tấn
C12: Chỉ tiêu | E12: Các mức hiệu suất máy mong muốn
C13: Hiệu suất_40% | D13: Chọn: → | F13: x
C14: Hiệu suất_60% | H14: x
C15: Hiệu suất_80% | J15: x
C16: Hiệu suất_100% | L16: x
C17: Hiệu suất mong muốn | D17: % | E17: 0.3 | F17: 0.4 | G17: 0.5 | H17: 0.6 | I17: 0.7 | J17: 0.8 | K17: 0.9 | L17: 1
C18: Số Ca sản xuất | D18: Ca | F18: 1 | H18: 2 | J18: 2.5 | L18: 3
C20: 1 - Diện tích xưởng, giá thuê
C21: Chuyền | D21: ĐVT | E21: H.S 40% | F21: H.S 60% | G21: H.S 80% | H21: H.S 100% | I21: Giá thuê (USD) | N21: Tỷ giá USD (đồng)
H22: Chọn: → | J22: x | Q22: x
C23: Phân loại chai | D23: m2 | E23: 3500 | F23: 3500 | G23: 3500 | H23: 3500
C24: Băm vảy | D24: m2
C25: Tổng diện tích | E25: =E23+E24 -> 3500 | F25: =F23+F24 -> 3500 | G25: =G23+G24 -> 3500 | H25: =H23+H24 -> 3500 | I25: =J25-0.5 -> 4 | J25: =K25-0.5 -> 4.5 | K25: 5 | L25: =K25+0.5 -> 5.5 | M25: =L25+0.5 -> 6 | N25: =O25-300 -> 25400 | O25: =P25-300 -> 25700 | P25: 26000 | Q25: =P25+300 -> 26300 | R25: =Q25+300 -> 26600 | S25: =R25+300 -> 26900
C27: 2 - Giá mua chai B0, tỷ lệ mua, % hao hụt
C28: Loại chai nguyên liệu | D28: Giá mua | M28: Tỷ lệ mua chai | Q28: Tỷ lệ hao hụt
C29: Chọn: → | G29: x | O29: x | R29: x
C30: Chai B0 - Xá tròn | D30: =E30-500 -> 8500 | E30: =F30-500 -> 9000 | F30: =G30-500 -> 9500 | G30: 10000 | H30: =G30+500 -> 10500 | I30: =H30+500 -> 11000 | J30: =I30+500 -> 11500 | K30: =J30+500 -> 12000 | L30: =K30+500 -> 12500 | M30: 0.3 | N30: 0.5 | O30: 0.8 | P30: 1 | Q30: =R30-1% -> 0.06 | R30: 0.07 | S30: =R30+1% -> 0.08
C31: Chai B0 - Ép kiện | D31: =E31-500 -> 8500 | E31: =F31-500 -> 9000 | F31: =G31-500 -> 9500 | G31: 10000 | H31: =G31+500 -> 10500 | I31: =H31+500 -> 11000 | J31: =I31+500 -> 11500 | K31: =J31+500 -> 12000 | L31: =K31+500 -> 12500 | M31: 0.7 | N31: 0.5 | O31: 0.2 | P31: 0 | Q31: =R31-1% -> 0.09 | R31: 0.1 | S31: =R31+1% -> 0.11
C32: Chai B1.4 (xô tuyển -> ép kiện) | D32: =E32-500 -> 10500 | E32: =F32-500 -> 11000 | F32: =G32-500 -> 11500 | G32: 12000 | H32: =G32+500 -> 12500 | I32: =H32+500 -> 13000 | J32: =I32+500 -> 13500 | K32: =J32+500 -> 14000 | L32: =K32+500 -> 14500 | M32: 0 | N32: 0 | O32: 0 | P32: 0 | Q32: =R32-1% -> 0.04 | R32: 0.05 | S32: =R32+1% -> 0.06
C33: Tổng: | M33: =SUM(M30:M32) -> 1 | N33: =SUM(N30:N32) -> 1 | O33: =SUM(O30:O32) -> 1 | P33: =SUM(P30:P32) -> 1
C35: 3 - Giá bán chai thành phẩm, vảy (đồng/kg)
C36: Chai thành phẩm | G36: Vảy thành phẩm | K36: → GAP
C37: Loại chai | D37: Giá chai | G37: Loai vảy | H37: Giá vảy
C38: Chọn: → | E38: x | G38: Chọn: → | I38: x
C39: Chai B1 | D39: =E39-500 -> 14500 | E39: ='[1]DG M-B'!$D$7 -> 15000 | F39: =E39+500 -> 15500 | G39: Vảy B1 | H39: =I39-500 -> 16500 | I39: 17000 | J39: =I39+500 -> 17500 | K39: =HLOOKUP("x",$H$38:$J$45,ROWS($H$38:$H39),0)-HLOOKUP("x",$D$38:$F$45,ROWS($H$38:$H39),0) -> 2000
C40: Chai B2.2 | D40: =E40-500 -> 13000 | E40: ='[1]DG M-B'!$D$9 -> 13500 | F40: =E40+500 -> 14000 | G40: Vảy B2.2 | H40: =I40-500 -> 15000 | I40: 15500 | J40: =I40+500 -> 16000 | K40: =HLOOKUP("x",$H$38:$J$45,ROWS($H$38:$H40),0)-HLOOKUP("x",$D$38:$F$45,ROWS($H$38:$H40),0) -> 2000
C41: Chai B4 | D41: =E41-500 -> 11500 | E41: 12000 | F41: =E41+500 -> 12500 | G41: Vảy B4 | H41: =I41-500 -> 14000 | I41: 14500 | J41: =I41+500 -> 15000 | K41: =HLOOKUP("x",$H$38:$J$45,ROWS($H$38:$H41),0)-HLOOKUP("x",$D$38:$F$45,ROWS($H$38:$H41),0) -> 2500
C42: Chai B5 | D42: =E42-500 -> 11500 | E42: 12000 | F42: =E42+500 -> 12500 | G42: Vảy B5 | H42: =I42-500 -> 14000 | I42: 14500 | J42: =I42+500 -> 15000 | K42: =HLOOKUP("x",$H$38:$J$45,ROWS($H$38:$H42),0)-HLOOKUP("x",$D$38:$F$45,ROWS($H$38:$H42),0) -> 2500
C43: Chai B6.2 | D43: =E43-500 -> 13000 | E43: ='[1]DG M-B'!$D$9 -> 13500 | F43: =E43+500 -> 14000 | G43: Vảy B6.2 | H43: =I43-500 -> 16000 | I43: 16500 | J43: =I43+500 -> 17000 | K43: =HLOOKUP("x",$H$38:$J$45,ROWS($H$38:$H43),0)-HLOOKUP("x",$D$38:$F$45,ROWS($H$38:$H43),0) -> 3000
C44: Cổ Chai | D44: =E44-500 -> 7500 | E44: 8000 | F44: =E44+500 -> 8500 | G44: Vảy Cổ Chai | H44: =I44-500 -> 9500 | I44: 10000 | J44: =I44+500 -> 10500 | K44: =HLOOKUP("x",$H$38:$J$45,ROWS($H$38:$H44),0)-HLOOKUP("x",$D$38:$F$45,ROWS($H$38:$H44),0) -> 2000
C45: Nắp chai | D45: =E45-500 -> 7500 | E45: 8000 | F45: =E45+500 -> 8500 | G45: Vảy Nắp chai | H45: =I45-500 -> 9500 | I45: 10000 | J45: =I45+500 -> 10500 | K45: =HLOOKUP("x",$H$38:$J$45,ROWS($H$38:$H45),0)-HLOOKUP("x",$D$38:$F$45,ROWS($H$38:$H45),0) -> 2000
E46: TT | I46: TT
C47: 4 - Tỷ lệ % chai thành phẩm sau phân loại và tỷ lệ % chai đưa vô băm vảy
C48: Loại chai | D48: Tỷ lệ sau phân loại (B0 tròn) | G48: Tỷ lệ sau phân loại (B0 ép kiện) | J48: Tỷ lệ sau phân loại (Tuyển xô) | M48: Tỷ lệ đưa vô băm | P48: Tỷ lệ hao hụt băm vảy
C49: Chọn: → | E49: x | H49: x | K49: x | M49: x | Q49: x
C50: Chai PET B1 | D50: =100%-SUM(D51:D57) -> 0.655 | E50: =100%-SUM(E51:E57) -> 0.56 | F50: =100%-SUM(F51:F57) -> 0.59 | G50: =100%-SUM(G51:G57) -> 0.625 | H50: =100%-SUM(H51:H57) -> 0.495 | I50: =100%-SUM(I51:I57) -> 0.555 | J50: =100%-SUM(J51:J57) -> 0.805 | K50: =100%-SUM(K51:K57) -> 0.735 | L50: =100%-SUM(L51:L57) -> 0.745 | M50: =IF(ISNA(HLOOKUP("x",$D$5,1,0)),100%,0) -> 0 | N50: =IF(ISNA(HLOOKUP("x",$D$5,1,0)),100%,0) -> 0 | O50: =IF(ISNA(HLOOKUP("x",$D$5,1,0)),100%,0) -> 0 | P50: =Q50-1% -> 0.05 | Q50: 0.06 | R50: =Q50+1% -> 0.07
C51: Chai PET B2.2 | D51: =E51-1% -> 0.06 | E51: 0.07 | F51: =E51+1% -> 0.08 | G51: =H51-1% -> 0.08 | H51: 0.09 | I51: =H51+1% -> 0.1 | J51: =K51-1% -> -0.01 | L51: =K51+1% -> 0.01 | M51: =IF(ISNA(HLOOKUP("x",$D$5,1,0)),100%,0) -> 0 | N51: =IF(ISNA(HLOOKUP("x",$D$5,1,0)),100%,0) -> 0 | O51: =IF(ISNA(HLOOKUP("x",$D$5,1,0)),100%,0) -> 0 | P51: =Q51-1% -> 0.06 | Q51: 0.07 | R51: =Q51+1% -> 0.08
C52: Chai PET B4 | D52: =E52-0.5% -> 0.005 | E52: 0.01 | F52: =E52+0.5% -> 0.015 | G52: =H52-0.5% -> 0.005 | H52: 0.01 | I52: =H52+0.5% -> 0.015 | J52: =K52-0.5% -> -0.005 | L52: =K52+0.5% -> 0.005 | N52: =IF(ISNA(HLOOKUP("x",$D$5,1,0)),100%,0) -> 0 | O52: =IF(ISNA(HLOOKUP("x",$D$5,1,0)),100%,0) -> 0 | P52: =Q52-1% -> 0.06 | Q52: 0.07 | R52: =Q52+1% -> 0.08
C53: Chai PET B5 | D53: 0.005 | E53: 0.005 | F53: =E53+0.5% -> 0.01 | G53: 0.005 | H53: 0.01 | I53: =H53+0.5% -> 0.015 | J53: 0.005 | L53: =K53+0.5% -> 0.005 | N53: =IF(ISNA(HLOOKUP("x",$D$5,1,0)),100%,0) -> 0 | O53: =IF(ISNA(HLOOKUP("x",$D$5,1,0)),100%,0) -> 0 | P53: =Q53-1% -> 0.06 | Q53: 0.07 | R53: =Q53+1% -> 0.08
C54: Chai PET B6.2 | D54: =E54-1% -> 0.26 | E54: 0.27 | F54: =E54+2% -> 0.29 | G54: =H54-1% -> 0.27 | H54: 0.28 | I54: =H54+2% -> 0.3 | J54: =K54-1% -> 0.19 | K54: 0.2 | L54: =K54+2% -> 0.22 | M54: =IF(ISNA(HLOOKUP("x",$D$5,1,0)),100%,0) -> 0 | N54: =IF(ISNA(HLOOKUP("x",$D$5,1,0)),100%,0) -> 0 | O54: =IF(ISNA(HLOOKUP("x",$D$5,1,0)),100%,0) -> 0 | P54: =Q54-1% -> 0.07 | Q54: 0.08 | R54: =Q54+1% -> 0.09
C55: Cổ Chai PET | D55: 0.005 | E55: 0.005 | F55: 0.005 | G55: 0.005 | H55: 0.005 | I55: 0.005 | J55: 0.005 | K55: 0.005 | L55: 0.005 | O55: =IF(ISNA(HLOOKUP("x",$D$5,1,0)),100%,0) -> 0 | P55: =Q55-1% -> 0 | Q55: 0.01 | R55: =Q55+1% -> 0.02
C56: Nắp HD ép các màu | D56: 0.01 | E56: 0.01 | F56: 0.01 | G56: 0.01 | H56: 0.01 | I56: 0.01 | J56: 0.01 | K56: 0.01 | L56: 0.01 | O56: =IF(ISNA(HLOOKUP("x",$D$5,1,0)),100%,0) -> 0 | P56: =Q56-1% -> 0 | Q56: 0.01 | R56: =Q56+1% -> 0.02
C57: Hao hụt | D57: =IF(D$49="x",HLOOKUP("x",$Q$29:$S$32,2,0),0) -> 0 | E57: =IF(E$49="x",HLOOKUP("x",$Q$29:$S$32,2,0),0) -> 0.07 | F57: =IF(F$49="x",HLOOKUP("x",$Q$29:$S$32,2,0),0) -> 0 | G57: =IF(G$49="x",HLOOKUP("x",$Q$29:$S$32,2,0),0) -> 0 | H57: =IF(H$49="x",HLOOKUP("x",$Q$29:$S$32,3,0),0) -> 0.1 | I57: =IF(I$49="x",HLOOKUP("x",$Q$29:$S$32,2,0),0) -> 0 | J57: =IF(J$49="x",HLOOKUP("x",$Q$29:$S$32,2,0),0) -> 0 | K57: =IF(K$49="x",HLOOKUP("x",$Q$29:$S$32,4,0),0) -> 0.05 | L57: =IF(L$49="x",HLOOKUP("x",$Q$29:$S$32,2,0),0) -> 0
C58: Tổng | D58: =SUM(D50:D57) -> 1 | E58: =SUM(E50:E57) -> 1 | F58: =SUM(F50:F57) -> 1 | G58: =SUM(G50:G57) -> 1 | H58: =SUM(H50:H57) -> 1 | I58: =SUM(I50:I57) -> 1 | J58: =SUM(J50:J57) -> 1 | K58: =SUM(K50:K57) -> 1 | L58: =SUM(L50:L57) -> 1
C60: % chi phí theo lương/ lương chính
C61: Các khoản mục phí | D61: Tỷ lệ
C62: Chi phí lương T13, Phép năm | D62: =1/12 -> 0.083333333
C63: Chi phí lương ngoài giờ | D63: 0.03
C64: Chi phí lương Ca đêm
C65: Chi phí phụ cấp theo bảng lương | D65: 0.05
C66: Chi phí khen thưởng theo bảng lương
C67: Chi phí bảo hiểm theo lương (BHXH, BHYT, KPCĐ, BHTN) | D67: 0.12
C68: Chi phí thuế TNCN
C69: Tổng | D69: =SUM(D62:D68) -> 0.28333333
C71: Tỷ lệ % PB Chi phí phúc lợi NV và Chi phí QL
C72: Chuyền | D72: Tỷ lệ
C73: Phân loại chai | D73: 0.9
C74: Băm vảy | D74: 0.1
C76: 5 - Cơ cấu vay
C77: Chỉ tiêu | D77: Tỷ lệ
C78: Vay trung dài hạn | D78: 0.7
C79: Vốn tự có | D79: 0.3
C80: Thời hạn vay | D80: 8
C81: Lãi suất/năm (thời hạn 8 năm) | D81: 0.07
C83: 6 - Chi phí vốn bình quân (WACC)
C84: Chỉ tiêu | D84: Cơ cấu | E84: Chi phí vốn
C85: Vốn vay | D85: =D78 -> 0.7 | E85: =D81 -> 0.07
C86: Vốn tự có | D86: =D79 -> 0.3 | E86: 0.12 | F86: (Bằng lãi suất cho vay dài hạn)
C87: Suất chiết khấu tính NPV | D87: =SUMPRODUCT(D85:D86,E85:E86) -> 0.085
C89: 7 - Thời gian khấu hao (năm)
C90: Hạng mục đầu tư | D90: Số năm
C91: MMTB chính | D91: 12
C92: MMTB phụ | D92: 8
C93: Hệ thống XLNT | D93: 20

Sheet B.đồ
B2: Đầu tư, công suất
B3: Loại chai | C3: Tổng | D3: 1.MMTB chính | E3: 2.Điện, hơi | F3: 3.Thiết bị SX | G3: 4.Thiết bị QL
B4: Công suất thiết kế | C4: =G.Định!E9 -> 1000000 | D4: =G.Định!F9 -> 1000000 | E4: =G.Định!F9 -> 1000000 | F4: =G.Định!G9 -> 1000000 | G4: =G.Định!H9 -> 1000000
B5: Chuyền phân loại chai | C5: =SUM(D5:G5) -> 22190006000 | D5: ='CAP.Chính'!G5 -> 16230006000 | E5: ='CAP.Chính'!G43 -> 4035000000 | F5: ='CAP.Phụ'!G9 -> 1724000000 | G5: ='CAP.Phụ'!G14 -> 201000000
B6: Chuyền băm vảy
B7: Tổng đầu tư | C7: =SUM(C5:C6) -> 22190006000 | D7: =SUM(D5:D6) -> 16230006000 | E7: =SUM(E5:E6) -> 4035000000 | F7: =SUM(F5:F6) -> 1724000000 | G7: =SUM(G5:G6) -> 201000000
B11: Sản lượng, hiệu suất
B12: Loại chai | C12: H.S 40% | D12: H.S 60% | E12: H.S 80% | F12: H.S 100%
B13: SL mua B0 | C13: =S.Lượng!C7 -> 400000 | D13: =S.Lượng!D7 -> 600000 | E13: =S.Lượng!E7 -> 800000 | F13: =S.Lượng!F7 -> 1000000
B14: SL bán Chai | C14: =S.Lượng!C40 -> 369600 | D14: =S.Lượng!D40 -> 554400 | E14: =S.Lượng!E40 -> 739200 | F14: =S.Lượng!F40 -> 924000
B15: SL bán Vảy | C15: =S.Lượng!C29 -> 0 | D15: =S.Lượng!D29 -> 0 | E15: =S.Lượng!E29 -> 0 | F15: =S.Lượng!F29 -> 0
B16: Công suất Chai | C16: =G.Định!E9 -> 1000000 | D16: =G.Định!F9 -> 1000000 | E16: =G.Định!G9 -> 1000000 | F16: =G.Định!H9 -> 1000000
B17: Công suất Vay | C17: =C16 -> 1000000 | D17: =D16 -> 1000000 | E17: =E16 -> 1000000 | F17: =F16 -> 1000000
B18: Hiệu suất Chai | C18: =C13/C16 -> 0.4 | D18: =D13/D16 -> 0.6 | E18: =E13/E16 -> 0.8 | F18: =F13/F16 -> 1
B19: Hiệu suất Vảy | C19: =S.Lượng!C54/B.đồ!C17 -> 0 | D19: =S.Lượng!D54/B.đồ!D17 -> 0 | E19: =S.Lượng!E54/B.đồ!E17 -> 0 | F19: =S.Lượng!F54/B.đồ!F17 -> 0
B22: Doanh thu, lợi nhuận
B23: Loại chai | C23: H.S 40% | D23: H.S 60% | E23: H.S 80% | F23: H.S 100%
B24: Doanh thu | C24: =KQKD!H5 -> 63302400000 | D24: =KQKD!I5 -> 94953600000 | E24: =KQKD!J5 -> 126604800000 | F24: =KQKD!K5 -> 158256000000
B25: Lãi biến phí | C25: =KQKD!H28 -> 1.2982154e+10 | D25: =KQKD!I28 -> 1.9473231e+10 | E25: =KQKD!J28 -> 2.5964308e+10 | F25: =KQKD!K28 -> 3.2455385e+10
B26: % lãi biến phí | C26: =KQKD!H29 -> 0.20508155 | D26: =KQKD!I29 -> 0.20508155 | E26: =KQKD!J29 -> 0.20508155 | F26: =KQKD!K29 -> 0.20508155
B27: LN sau thuế | C27: =KQKD!H103 -> -2.9060747e+09 | D27: =KQKD!I103 -> 1.1007649e+09 | E27: =KQKD!J103 -> 4.9621272e+09 | F27: =KQKD!K103 -> 9.6840719e+09
B28: % LN sau thuế | C28: =KQKD!H104 -> -0.045907813 | D28: =KQKD!I104 -> 0.011592661 | E28: =KQKD!J104 -> 0.039193832 | F28: =KQKD!K104 -> 0.061192447
B29: EBITDA | C29: =KQKD!H105 -> -9.7669923e+08 | D29: =KQKD!I105 -> 3.0301404e+09 | E29: =KQKD!J105 -> 6.8915027e+09 | F29: =KQKD!K105 -> 1.1613447e+10
B30: % EBITDA | C30: =KQKD!H106 -> -0.015429103 | D30: =KQKD!I106 -> 0.031911801 | E30: =KQKD!J106 -> 0.054433187 | F30: =KQKD!K106 -> 0.073383931
B36: Chỉ tiêu | C36: H.S 40% | D36: H.S 60% | E36: H.S 80% | F36: H.S 100%
B37: BIẾN PHÍ | C37: =KQKD!H7 -> 5.0320246e+10 | D37: =KQKD!I7 -> 7.5480369e+10 | E37: =KQKD!J7 -> 1.0064049e+11 | F37: =KQKD!K7 -> 1.2580061e+11
B38: % biến phí | C38: =C37/C41 -> 0.76002726 | D38: =D37/D41 -> 0.80660685 | E38: =E37/E41 -> 0.83586962 | F38: =F37/F41 -> 0.86075834
B39: ĐỊNH PHÍ | C39: =KQKD!H31 -> 1.5888229e+10 | D39: =KQKD!I31 -> 1.8097275e+10 | E39: =KQKD!J31 -> 1.9761649e+10 | F39: =KQKD!K31 -> 2.0350295e+10
B40: % định phí | C40: =C39/C41 -> 0.23997274 | D40: =D39/D41 -> 0.19339315 | E40: =E39/E41 -> 0.16413038 | F40: =F39/F41 -> 0.13924166
B41: TỔNG CHI PHÍ | C41: =C37+C39 -> 6.6208475e+10 | D41: =D37+D39 -> 9.3577644e+10 | E41: =E37+E39 -> 1.2040214e+11 | F41: =F37+F39 -> 1.4615091e+11
B42: % tổng chi phí/ DT | C42: =C41/C24 -> 1.0459078 | D42: =D41/D24 -> 0.98550917 | E42: =E41/E24 -> 0.95100771 | F42: =F41/F24 -> 0.92350944
B44: BIẾN PHÍ | C44: H.S 40% | D44: H.S 60% | E44: H.S 80% | F44: H.S 100%
B45: Biến phí bán hàng | C45: =KQKD!H10 -> 831600000 | D45: =KQKD!I10 -> 1247400000 | E45: =KQKD!J10 -> 1663200000 | F45: =KQKD!K10 -> 2079000000
B46: % biến phí bán hàng | C46: =C45/C49 -> 0.016526151 | D46: =D45/D49 -> 0.016526151 | E46: =E45/E49 -> 0.016526151 | F46: =F45/F49 -> 0.016526151
B47: Biến phí sản xuất | C47: =KQKD!H13 -> 4.9488646e+10 | D47: =KQKD!I13 -> 7.4232969e+10 | E47: =KQKD!J13 -> 9.8977292e+10 | F47: =KQKD!K13 -> 1.2372161e+11
B48: % định phí SX | C48: =C47/C49 -> 0.98347385 | D48: =D47/D49 -> 0.98347385 | E48: =E47/E49 -> 0.98347385 | F48: =F47/F49 -> 0.98347385
B49: Tổng Biến phí | C49: =C37 -> 5.0320246e+10 | D49: =D37 -> 7.5480369e+10 | E49: =E37 -> 1.0064049e+11 | F49: =F37 -> 1.2580061e+11
B51: ĐỊNH PHÍ | C51: H.S 40% | D51: H.S 60% | E51: H.S 80% | F51: H.S 100%
B52: Định phí sản xuất | C52: =KQKD!H34 -> 5.4423794e+09 | D52: =KQKD!I34 -> 5.5262255e+09 | E52: =KQKD!J34 -> 5.6100717e+09 | F52: =KQKD!K34 -> 5.7059178e+09
B53: % định phí sản xuất | C53: =C52/C$62 -> 0.3425416 | D53: =D52/D$62 -> 0.3053623 | E53: =E52/E$62 -> 0.28388682 | F53: =F52/F$62 -> 0.28038502
B54: Định phí quản lý | C54: =KQKD!H47 -> 1419613612 | D54: =KQKD!I47 -> 1419613612 | E54: =KQKD!J47 -> 1419613612 | F54: =KQKD!K47 -> 1419613612
B55: % định phí quản lý | C55: =C54/C$62 -> 0.089350023 | D55: =D54/D$62 -> 0.078443501 | E55: =E54/E$62 -> 0.071836799 | F55: =F54/F$62 -> 0.069758871
B56: Chi phí nhân sự | C56: =KQKD!H66 -> 6009550000 | D56: =KQKD!I66 -> 8134750000 | E56: =KQKD!J66 -> 9715278000 | F56: =KQKD!K66 -> 10208078000
B57: % định phí nhân sự | C57: =C56/C$62 -> 0.37823914 | D57: =D56/D$62 -> 0.44950138 | E57: =E56/E$62 -> 0.49162284 | F57: =F56/F$62 -> 0.50161818
B58: Chi phí tài chính | C58: =KQKD!H92 -> 1.0873103e+09 | D58: =KQKD!I92 -> 1.0873103e+09 | E58: =KQKD!J92 -> 1.0873103e+09 | F58: =KQKD!K92 -> 1.0873103e+09
B59: % định phí tài chính | C59: =C58/C$62 -> 0.06843496 | D59: =D58/D$62 -> 0.060081438 | E59: =E58/E$62 -> 0.055021233 | F59: =F58/F$62 -> 0.053429706
B60: Chi phí khấu hao | C60: =KQKD!H95 -> 1.9293755e+09 | D60: =KQKD!I95 -> 1.9293755e+09 | E60: =KQKD!J95 -> 1.9293755e+09 | F60: =KQKD!K95 -> 1.9293755e+09
B61: % định phí khấu hao | C61: =C60/C$62 -> 0.12143427 | D61: =D60/D$62 -> 0.10661138 | E61: =E60/E$62 -> 0.097632313 | F61: =F60/F$62 -> 0.094808231
B62: Tổng Định phí | C62: =C39 -> 1.5888229e+10 | D62: =D39 -> 1.8097275e+10 | E62: =E39 -> 1.9761649e+10 | F62: =F39 -> 2.0350295e+10
B65: Giá mua, bán, GAP:
C66: H.S 40% | D66: H.S 60% | E66: H.S 80% | F66: H.S 100%
B67: Giá bán | C67: =KQKD!D6/1000 -> 14272.727 | D67: =KQKD!E6/1000 -> 14272.727 | E67: =KQKD!F6/1000 -> 14272.727 | F67: =KQKD!G6/1000 -> 14272.727
B68: Giá mua B0 | C68: =(S.Lượng!C4*HLOOKUP("x",G.Định!$D$29:$L$32,2,0)+S.Lượng!C5*HLOOKUP("x",G.Định!$D$29:$L$32,3,0)+S.Lượng!C6*HLOOKUP("x",G.Định!$D$29:$L$32,4,0))/S.Lượng!C7 -> 10000 | D68: =(S.Lượng!D4*HLOOKUP("x",G.Định!$D$29:$L$32,2,0)+S.Lượng!D5*HLOOKUP("x",G.Định!$D$29:$L$32,3,0)+S.Lượng!D6*HLOOKUP("x",G.Định!$D$29:$L$32,4,0))/S.Lượng!D7 -> 10000 | E68: =(S.Lượng!E4*HLOOKUP("x",G.Định!$D$29:$L$32,2,0)+S.Lượng!E5*HLOOKUP("x",G.Định!$D$29:$L$32,3,0)+S.Lượng!E6*HLOOKUP("x",G.Định!$D$29:$L$32,4,0))/S.Lượng!E7 -> 10000 | F68: =(S.Lượng!F4*HLOOKUP("x",G.Định!$D$29:$L$32,2,0)+S.Lượng!F5*HLOOKUP("x",G.Định!$D$29:$L$32,3,0)+S.Lượng!F6*HLOOKUP("x",G.Định!$D$29:$L$32,4,0))/S.Lượng!F7 -> 10000
B69: % giá mua/ giá bán | C69: =C68/C$67 -> 0.70063694 | D69: =D68/D$67 -> 0.70063694 | E69: =E68/E$67 -> 0.70063694 | F69: =F68/F$67 -> 0.70063694
B70: GAP | C70: =C67-C68 -> 4272.7273 | D70: =D67-D68 -> 4272.7273 | E70: =E67-E68 -> 4272.7273 | F70: =F67-F68 -> 4272.7273
B71: % GAP | C71: =C70/C67 -> 0.29936306 | D71: =D70/D67 -> 0.29936306 | E71: =E70/E67 -> 0.29936306 | F71: =F70/F67 -> 0.29936306
B72: Hao hụt | C72: ='CP 1kg'!Y10-C68 -> 822.51082 | D72: ='CP 1kg'!Z10-D68 -> 822.51082 | E72: ='CP 1kg'!AA10-E68 -> 822.51082 | F72: ='CP 1kg'!AB10-F68 -> 822.51082
B73: % hao hụt/ giá bán | C73: =C72/C$67 -> 0.057628147 | D73: =D72/D$67 -> 0.057628147 | E73: =E72/E$67 -> 0.057628147 | F73: =F72/F$67 -> 0.057628147
B74: Biến phí (SX+VC) | C74: ='CP 1kg'!Y9-'CP 1kg'!Y10+'CP 1kg'!Y7 -> 523.14348 | D74: ='CP 1kg'!Z9-'CP 1kg'!Z10+'CP 1kg'!Z7 -> 523.14348 | E74: ='CP 1kg'!AA9-'CP 1kg'!AA10+'CP 1kg'!AA7 -> 523.14348 | F74: ='CP 1kg'!AB9-'CP 1kg'!AB10+'CP 1kg'!AB7 -> 523.14348
B75: % biến phí/ giá bán | C75: =C74/C$67 -> 0.036653364 | D75: =D74/D$67 -> 0.036653364 | E75: =E74/E$67 -> 0.036653364 | F75: =F74/F$67 -> 0.036653364
B76: Định phí | C76: ='CP 1kg'!Y21 -> 3582.3027 | D76: ='CP 1kg'!Z21 -> 2720.2494 | E76: ='CP 1kg'!AA21 -> 2227.8194 | F76: ='CP 1kg'!AB21 -> 1835.3441
B77: % định phí/ giá bán | C77: =C76/C$67 -> 0.25098936 | D77: =D76/D$67 -> 0.19059072 | E77: =E76/E$67 -> 0.15608926 | F77: =F76/F$67 -> 0.12859099
B78: Thuế TNDN (đồng/kg) | C78: =IF((C67-C68-C72-C74-C76)>0,(C67-C68-C72-C74-C76)*20%,0) -> 0 | D78: =IF((D67-D68-D72-D74-D76)>0,(D67-D68-D72-D74-D76)*20%,0) -> 41.364723 | E78: =IF((E67-E68-E72-E74-E76)>0,(E67-E68-E72-E74-E76)*20%,0) -> 139.85072 | F78: =IF((F67-F68-F72-F74-F76)>0,(F67-F68-F72-F74-F76)*20%,0) -> 218.34578
B79: Lãi/ lỗ | C79: =(C67-C68-C72-C74-C76)-C78 -> -655.22969 | D79: =(D67-D68-D72-D74-D76)-D78 -> 165.45889 | E79: =(E67-E68-E72-E74-E76)-E78 -> 559.40287 | F79: =(F67-F68-F72-F74-F76)-F78 -> 873.38311
B80: % LN sau thuế/ giá bán | C80: =C79/C67 -> -0.045907813 | D80: =D79/D67 -> 0.011592661 | E80: =E79/E67 -> 0.039193832 | F80: =F79/F67 -> 0.061192447
B81: SL bán (tấn/năm) | C81: =KQKD!H4 -> 4435200 | D81: =KQKD!I4 -> 6652800 | E81: =KQKD!J4 -> 8870400 | F81: =KQKD!K4 -> 11088000
B82: LN sau thuế /năm | C82: =C79*C81 -> -2.9060747e+09 | D82: =D79*D81 -> 1.1007649e+09 | E82: =E79*E81 -> 4.9621272e+09 | F82: =F79*F81 -> 9.6840719e+09
B83: Kiểm tra | C83: =C82-KQKD!H103 -> 0 | D83: =D82-KQKD!I103 -> -9.059906e-06 | E83: =E82-KQKD!J103 -> 0 | F83: =F82-KQKD!K103 -> 0
C86: Đồng/kg
B87: Giá bán | C87: =C67 -> 14272.727
B88: Giá mua B0 | C88: =C68 -> 10000
B89: GAP | C89: =C87-C88 -> 4272.7273
B90: GAP + Giá mua | C90: =C89+C88 -> 14272.727
B100: Hiệu quả đầu tư
B101: Chỉ số | C101: H.S 40% | D101: H.S 60% | E101: H.S 80% | F101: H.S 100%
B102: NPV (tỷ đồng) | C102: =HV!C32 -> -2.2966054e+10 | D102: =HV!D32 -> 1.1981478e+10 | E102: =HV!E32 -> 4.5660161e+10 | F102: =HV!F32 -> 8.6844817e+10
B103: IRR | C103: =HV!C33 -> -0.18098752 | D103: =HV!D33 -> 0.15300925 | E103: =HV!E33 -> 0.3261148 | F103: =HV!F33 -> 0.53434391
B104: Thời gian hoàn vốn (năm)_1 | C104: =HV!C34 -> #N/A | D104: =HV!D34 -> 9.422813 | E104: =HV!E34 -> 3.8089478 | F104: =HV!F34 -> 2.1618268
B105: Thời gian hoàn vốn (năm) | C105: =C102*1.1+C104 -> #N/A | D105: =D102*1.1+D104 -> 1.3179626e+10 | E105: =E102*1.1+E104 -> 5.0226177e+10 | F105: =F102*1.1+F104 -> 9.5529299e+10

Sheet KQKD
A1: KẾT QUẢ KINH DOANH | K1: ĐVT: triệu đồng
A2: STT | B2: CHỈ TIÊU | D2: BÌNH QUÂN 1 THÁNG | H2: CẢ NĂM
D3: H.S 40% | E3: H.S 60% | F3: H.S 80% | G3: H.S 100% | H3: H.S 40% | I3: H.S 60% | J3: H.S 80% | K3: H.S 100%
A4: 1 | B4: SẢN LƯỢNG BÁN (Tấn) | D4: =S.Lượng!C42 -> 369600 | E4: =S.Lượng!D42 -> 554400 | F4: =S.Lượng!E42 -> 739200 | G4: =S.Lượng!F42 -> 924000 | H4: =D4*12 -> 4435200 | I4: =E4*12 -> 6652800 | J4: =F4*12 -> 8870400 | K4: =G4*12 -> 11088000
A5: 2 | B5: DOANH THU THUẦN | D5: =D.Thu!C24 -> 5275200000 | E5: =D.Thu!D24 -> 7912800000 | F5: =D.Thu!E24 -> 10550400000 | G5: =D.Thu!F24 -> 13188000000 | H5: =D5*12 -> 63302400000 | I5: =E5*12 -> 94953600000 | J5: =F5*12 -> 126604800000 | K5: =G5*12 -> 158256000000
C6: Giá bán / Tấn (Triệu đồng/Tấn) | D6: =D5/D4*1000 -> 14272727 | E6: =E5/E4*1000 -> 14272727 | F6: =F5/F4*1000 -> 14272727 | G6: =G5/G4*1000 -> 14272727 | H6: =H5/H4*1000 -> 14272727 | I6: =I5/I4*1000 -> 14272727 | J6: =J5/J4*1000 -> 14272727 | K6: =K5/K4*1000 -> 14272727
A7: 3 | B7: BIẾN PHÍ | D7: =D10+D13 -> 4.1933538e+09 | E7: =E10+E13 -> 6.2900307e+09 | F7: =F10+F13 -> 8.3867077e+09 | G7: =G10+G13 -> 1.0483385e+10 | H7: =H10+H13 -> 5.0320246e+10 | I7: =I10+I13 -> 7.5480369e+10 | J7: =J10+J13 -> 1.0064049e+11 | K7: =K10+K13 -> 1.2580061e+11
C8: Biến phí / Doanh thu (%) | D8: =IFERROR(D7/D$5,0) -> 0.79491845 | E8: =IFERROR(E7/E$5,0) -> 0.79491845 | F8: =IFERROR(F7/F$5,0) -> 0.79491845 | G8: =IFERROR(G7/G$5,0) -> 0.79491845 | H8: =IFERROR(H7/H$5,0) -> 0.79491845 | I8: =IFERROR(I7/I$5,0) -> 0.79491845 | J8: =IFERROR(J7/J$5,0) -> 0.79491845 | K8: =IFERROR(K7/K$5,0) -> 0.79491845
C9: Biến phí / Tấn (Triệu đồng/Tấn) | D9: =IFERROR(D7/D$4,0)*1000 -> 11345654 | E9: =IFERROR(E7/E$4,0)*1000 -> 11345654 | F9: =IFERROR(F7/F$4,0)*1000 -> 11345654 | G9: =IFERROR(G7/G$4,0)*1000 -> 11345654 | H9: =IFERROR(H7/H$4,0)*1000 -> 11345654 | I9: =IFERROR(I7/I$4,0)*1000 -> 11345654 | J9: =IFERROR(J7/J$4,0)*1000 -> 11345654 | K9: =IFERROR(K7/K$4,0)*1000 -> 11345654
A10: 3.1 | B10: Biến phí bán hàng | D10: =CPBH!C5 -> 69300000 | E10: =CPBH!D5 -> 103950000 | F10: =CPBH!E5 -> 138600000 | G10: =CPBH!F5 -> 173250000 | H10: =D10*12 -> 831600000 | I10: =E10*12 -> 1247400000 | J10: =F10*12 -> 1663200000 | K10: =G10*12 -> 2079000000
C11: Biến phí / Doanh thu (%) | D11: =IFERROR(D10/D$5,0) -> 0.013136943 | E11: =IFERROR(E10/E$5,0) -> 0.013136943 | F11: =IFERROR(F10/F$5,0) -> 0.013136943 | G11: =IFERROR(G10/G$5,0) -> 0.013136943 | H11: =IFERROR(H10/H$5,0) -> 0.013136943 | I11: =IFERROR(I10/I$5,0) -> 0.013136943 | J11: =IFERROR(J10/J$5,0) -> 0.013136943 | K11: =IFERROR(K10/K$5,0) -> 0.013136943
C12: Biến phí / Tấn (Triệu đồng/Tấn) | D12: =IFERROR(D10/D$4,0)*1000 -> 187500 | E12: =IFERROR(E10/E$4,0)*1000 -> 187500 | F12: =IFERROR(F10/F$4,0)*1000 -> 187500 | G12: =IFERROR(G10/G$4,0)*1000 -> 187500 | H12: =IFERROR(H10/H$4,0)*1000 -> 187500 | I12: =IFERROR(I10/I$4,0)*1000 -> 187500 | J12: =IFERROR(J10/J$4,0)*1000 -> 187500 | K12: =IFERROR(K10/K$4,0)*1000 -> 187500
A13: 3.2 | B13: Biến phí sản xuất | D13: =D16+SUM(D18:D27) -> 4.1240538e+09 | E13: =E16+SUM(E18:E27) -> 6.1860807e+09 | F13: =F16+SUM(F18:F27) -> 8.2481077e+09 | G13: =G16+SUM(G18:G27) -> 1.0310135e+10 | H13: =H16+SUM(H18:H27) -> 4.9488646e+10 | I13: =I16+SUM(I18:I27) -> 7.4232969e+10 | J13: =J16+SUM(J18:J27) -> 9.8977292e+10 | K13: =K16+SUM(K18:K27) -> 1.2372161e+11
C14: Biến phí sản xuất/ Doanh thu (%) | D14: =IFERROR(D13/D$5,0) -> 0.78178151 | E14: =IFERROR(E13/E$5,0) -> 0.78178151 | F14: =IFERROR(F13/F$5,0) -> 0.78178151 | G14: =IFERROR(G13/G$5,0) -> 0.78178151 | H14: =IFERROR(H13/H$5,0) -> 0.78178151 | I14: =IFERROR(I13/I$5,0) -> 0.78178151 | J14: =IFERROR(J13/J$5,0) -> 0.78178151 | K14: =IFERROR(K13/K$5,0) -> 0.78178151
C15: Biến phí sản xuất/ Tấn (Triệu đồng/Tấn) | D15: =IFERROR(D13/D$4,0)*1000 -> 11158154 | E15: =IFERROR(E13/E$4,0)*1000 -> 11158154 | F15: =IFERROR(F13/F$4,0)*1000 -> 11158154 | G15: =IFERROR(G13/G$4,0)*1000 -> 11158154 | H15: =IFERROR(H13/H$4,0)*1000 -> 11158154 | I15: =IFERROR(I13/I$4,0)*1000 -> 11158154 | J15: =IFERROR(J13/J$4,0)*1000 -> 11158154 | K15: =IFERROR(K13/K$4,0)*1000 -> 11158154
A16: -1 | C16: Chi phí nguyên liệu (chai B0) | D16: =VLOOKUP($C16,'CPSX-Chai'!$B:$F,COLUMNS('CPSX-Chai'!$B$4:C$4),0) -> 4000000000 | E16: =VLOOKUP($C16,'CPSX-Chai'!$B:$F,COLUMNS('CPSX-Chai'!$B$4:D$4),0) -> 6000000000 | F16: =VLOOKUP($C16,'CPSX-Chai'!$B:$F,COLUMNS('CPSX-Chai'!$B$4:E$4),0) -> 8000000000 | G16: =VLOOKUP($C16,'CPSX-Chai'!$B:$F,COLUMNS('CPSX-Chai'!$B$4:F$4),0) -> 10000000000 | H16: =D16*12 -> 48000000000 | I16: =E16*12 -> 72000000000 | J16: =F16*12 -> 96000000000 | K16: =G16*12 -> 120000000000
C17: Lãi nguyên liệu / Doanh thu (%) | D17: =IFERROR(D16/D$5,0) -> 0.75826509 | E17: =IFERROR(E16/E$5,0) -> 0.75826509 | F17: =IFERROR(F16/F$5,0) -> 0.75826509 | G17: =IFERROR(G16/G$5,0) -> 0.75826509 | H17: =IFERROR(H16/H$5,0) -> 0.75826509 | I17: =IFERROR(I16/I$5,0) -> 0.75826509 | J17: =IFERROR(J16/J$5,0) -> 0.75826509 | K17: =IFERROR(K16/K$5,0) -> 0.75826509
A18: -2 | C18: Chi phí bao jumbo | D18: =VLOOKUP($C18,'CPSX-Chai'!$B:$F,COLUMNS('CPSX-Chai'!$B$4:C$4),0)+VLOOKUP($C18,'CPSX-Vảy'!$B:$F,COLUMNS('CPSX-Vảy'!$B$4:C$4),0) -> 946666.67 | E18: =VLOOKUP($C18,'CPSX-Chai'!$B:$F,COLUMNS('CPSX-Chai'!$B$4:D$4),0)+VLOOKUP($C18,'CPSX-Vảy'!$B:$F,COLUMNS('CPSX-Vảy'!$B$4:D$4),0) -> 1420000 | F18: =VLOOKUP($C18,'CPSX-Chai'!$B:$F,COLUMNS('CPSX-Chai'!$B$4:E$4),0)+VLOOKUP($C18,'CPSX-Vảy'!$B:$F,COLUMNS('CPSX-Vảy'!$B$4:E$4),0) -> 1893333.3 | G18: =VLOOKUP($C18,'CPSX-Chai'!$B:$F,COLUMNS('CPSX-Chai'!$B$4:F$4),0)+VLOOKUP($C18,'CPSX-Vảy'!$B:$F,COLUMNS('CPSX-Vảy'!$B$4:F$4),0) -> 2366666.7 | H18: =D18*12 -> 11360000 | I18: =E18*12 -> 17040000 | J18: =F18*12 -> 22720000 | K18: =G18*12 -> 28400000
A19: -3 | C19: Chi phí dây đai | D19: =VLOOKUP($C19,'CPSX-Chai'!$B:$F,COLUMNS('CPSX-Chai'!$B$4:C$4),0)+VLOOKUP($C19,'CPSX-Vảy'!$B:$F,COLUMNS('CPSX-Vảy'!$B$4:C$4),0) -> 28218522 | E19: =VLOOKUP($C19,'CPSX-Chai'!$B:$F,COLUMNS('CPSX-Chai'!$B$4:D$4),0)+VLOOKUP($C19,'CPSX-Vảy'!$B:$F,COLUMNS('CPSX-Vảy'!$B$4:D$4),0) -> 42327783 | F19: =VLOOKUP($C19,'CPSX-Chai'!$B:$F,COLUMNS('CPSX-Chai'!$B$4:E$4),0)+VLOOKUP($C19,'CPSX-Vảy'!$B:$F,COLUMNS('CPSX-Vảy'!$B$4:E$4),0) -> 56437043 | G19: =VLOOKUP($C19,'CPSX-Chai'!$B:$F,COLUMNS('CPSX-Chai'!$B$4:F$4),0)+VLOOKUP($C19,'CPSX-Vảy'!$B:$F,COLUMNS('CPSX-Vảy'!$B$4:F$4),0) -> 70546304 | H19: =D19*12 -> 3.3862226e+08 | I19: =E19*12 -> 5.0793339e+08 | J19: =F19*12 -> 6.7724452e+08 | K19: =G19*12 -> 8.4655565e+08
A20: -4 | C20: Chi phí điện sản xuất | D20: =VLOOKUP($C20,'CPSX-Chai'!$B:$F,COLUMNS('CPSX-Chai'!$B$4:C$4),0)+VLOOKUP($C20,'CPSX-Vảy'!$B:$F,COLUMNS('CPSX-Vảy'!$B$4:C$4),0) -> 37600640 | E20: =VLOOKUP($C20,'CPSX-Chai'!$B:$F,COLUMNS('CPSX-Chai'!$B$4:D$4),0)+VLOOKUP($C20,'CPSX-Vảy'!$B:$F,COLUMNS('CPSX-Vảy'!$B$4:D$4),0) -> 56400960 | F20: =VLOOKUP($C20,'CPSX-Chai'!$B:$F,COLUMNS('CPSX-Chai'!$B$4:E$4),0)+VLOOKUP($C20,'CPSX-Vảy'!$B:$F,COLUMNS('CPSX-Vảy'!$B$4:E$4),0) -> 75201280 | G20: =VLOOKUP($C20,'CPSX-Chai'!$B:$F,COLUMNS('CPSX-Chai'!$B$4:F$4),0)+VLOOKUP($C20,'CPSX-Vảy'!$B:$F,COLUMNS('CPSX-Vảy'!$B$4:F$4),0) -> 94001600 | H20: =D20*12 -> 4.5120768e+08 | I20: =E20*12 -> 6.7681152e+08 | J20: =F20*12 -> 9.0241536e+08 | K20: =G20*12 -> 1.1280192e+09
A21: -5 | C21: Chi phí nước sản xuất | D21: =VLOOKUP($C21,'CPSX-Chai'!$B:$F,COLUMNS('CPSX-Chai'!$B$4:C$4),0)+VLOOKUP($C21,'CPSX-Vảy'!$B:$F,COLUMNS('CPSX-Vảy'!$B$4:C$4),0) -> 0 | E21: =VLOOKUP($C21,'CPSX-Chai'!$B:$F,COLUMNS('CPSX-Chai'!$B$4:D$4),0)+VLOOKUP($C21,'CPSX-Vảy'!$B:$F,COLUMNS('CPSX-Vảy'!$B$4:D$4),0) -> 0 | F21: =VLOOKUP($C21,'CPSX-Chai'!$B:$F,COLUMNS('CPSX-Chai'!$B$4:E$4),0)+VLOOKUP($C21,'CPSX-Vảy'!$B:$F,COLUMNS('CPSX-Vảy'!$B$4:E$4),0) -> 0 | G21: =VLOOKUP($C21,'CPSX-Chai'!$B:$F,COLUMNS('CPSX-Chai'!$B$4:F$4),0)+VLOOKUP($C21,'CPSX-Vảy'!$B:$F,COLUMNS('CPSX-Vảy'!$B$4:F$4),0) -> 0 | H21: =D21*12 -> 0 | I21: =E21*12 -> 0 | J21: =F21*12 -> 0 | K21: =G21*12 -> 0
A22: -6 | C22: Chi phí xăng, dầu xe nâng | D22: =VLOOKUP($C22,'CPSX-Chai'!$B:$F,COLUMNS('CPSX-Chai'!$B$4:C$4),0)+VLOOKUP($C22,'CPSX-Vảy'!$B:$F,COLUMNS('CPSX-Vảy'!$B$4:C$4),0) -> 11088000 | E22: =VLOOKUP($C22,'CPSX-Chai'!$B:$F,COLUMNS('CPSX-Chai'!$B$4:D$4),0)+VLOOKUP($C22,'CPSX-Vảy'!$B:$F,COLUMNS('CPSX-Vảy'!$B$4:D$4),0) -> 16632000 | F22: =VLOOKUP($C22,'CPSX-Chai'!$B:$F,COLUMNS('CPSX-Chai'!$B$4:E$4),0)+VLOOKUP($C22,'CPSX-Vảy'!$B:$F,COLUMNS('CPSX-Vảy'!$B$4:E$4),0) -> 22176000 | G22: =VLOOKUP($C22,'CPSX-Chai'!$B:$F,COLUMNS('CPSX-Chai'!$B$4:F$4),0)+VLOOKUP($C22,'CPSX-Vảy'!$B:$F,COLUMNS('CPSX-Vảy'!$B$4:F$4),0) -> 27720000 | H22: =D22*12 -> 133056000 | I22: =E22*12 -> 199584000 | J22: =F22*12 -> 266112000 | K22: =G22*12 -> 332640000
A23: -7 | C23: Chi phí xử lý nước thải | D23: =VLOOKUP($C23,'CPSX-Chai'!$B:$F,COLUMNS('CPSX-Chai'!$B$4:C$4),0)+VLOOKUP($C23,'CPSX-Vảy'!$B:$F,COLUMNS('CPSX-Vảy'!$B$4:C$4),0) -> 0 | E23: =VLOOKUP($C23,'CPSX-Chai'!$B:$F,COLUMNS('CPSX-Chai'!$B$4:D$4),0)+VLOOKUP($C23,'CPSX-Vảy'!$B:$F,COLUMNS('CPSX-Vảy'!$B$4:D$4),0) -> 0 | F23: =VLOOKUP($C23,'CPSX-Chai'!$B:$F,COLUMNS('CPSX-Chai'!$B$4:E$4),0)+VLOOKUP($C23,'CPSX-Vảy'!$B:$F,COLUMNS('CPSX-Vảy'!$B$4:E$4),0) -> 0 | G23: =VLOOKUP($C23,'CPSX-Chai'!$B:$F,COLUMNS('CPSX-Chai'!$B$4:F$4),0)+VLOOKUP($C23,'CPSX-Vảy'!$B:$F,COLUMNS('CPSX-Vảy'!$B$4:F$4),0) -> 0 | H23: =D23*12 -> 0 | I23: =E23*12 -> 0 | J23: =F23*12 -> 0 | K23: =G23*12 -> 0
A24: -8 | C24: Chi phí xử lý bùn thải | D24: =VLOOKUP($C24,'CPSX-Chai'!$B:$F,COLUMNS('CPSX-Chai'!$B$4:C$4),0)+VLOOKUP($C24,'CPSX-Vảy'!$B:$F,COLUMNS('CPSX-Vảy'!$B$4:C$4),0) -> 0 | E24: =VLOOKUP($C24,'CPSX-Chai'!$B:$F,COLUMNS('CPSX-Chai'!$B$4:D$4),0)+VLOOKUP($C24,'CPSX-Vảy'!$B:$F,COLUMNS('CPSX-Vảy'!$B$4:D$4),0) -> 0 | F24: =VLOOKUP($C24,'CPSX-Chai'!$B:$F,COLUMNS('CPSX-Chai'!$B$4:E$4),0)+VLOOKUP($C24,'CPSX-Vảy'!$B:$F,COLUMNS('CPSX-Vảy'!$B$4:E$4),0) -> 0 | G24: =VLOOKUP($C24,'CPSX-Chai'!$B:$F,COLUMNS('CPSX-Chai'!$B$4:F$4),0)+VLOOKUP($C24,'CPSX-Vảy'!$B:$F,COLUMNS('CPSX-Vảy'!$B$4:F$4),0) -> 0 | H24: =D24*12 -> 0 | I24: =E24*12 -> 0 | J24: =F24*12 -> 0 | K24: =G24*12 -> 0
A25: -9 | C25: Chi phí xử lý rác thải CN | D25: =VLOOKUP($C25,'CPSX-Chai'!$B:$F,COLUMNS('CPSX-Chai'!$B$4:C$4),0)+VLOOKUP($C25,'CPSX-Vảy'!$B:$F,COLUMNS('CPSX-Vảy'!$B$4:C$4),0) -> 5544000 | E25: =VLOOKUP($C25,'CPSX-Chai'!$B:$F,COLUMNS('CPSX-Chai'!$B$4:D$4),0)+VLOOKUP($C25,'CPSX-Vảy'!$B:$F,COLUMNS('CPSX-Vảy'!$B$4:D$4),0) -> 8316000 | F25: =VLOOKUP($C25,'CPSX-Chai'!$B:$F,COLUMNS('CPSX-Chai'!$B$4:E$4),0)+VLOOKUP($C25,'CPSX-Vảy'!$B:$F,COLUMNS('CPSX-Vảy'!$B$4:E$4),0) -> 11088000 | G25: =VLOOKUP($C25,'CPSX-Chai'!$B:$F,COLUMNS('CPSX-Chai'!$B$4:F$4),0)+VLOOKUP($C25,'CPSX-Vảy'!$B:$F,COLUMNS('CPSX-Vảy'!$B$4:F$4),0) -> 13860000 | H25: =D25*12 -> 66528000 | I25: =E25*12 -> 99792000 | J25: =F25*12 -> 133056000 | K25: =G25*12 -> 166320000
A26: -10 | C26: Chi phí dao tách nhãn, băm vảy | D26: =VLOOKUP($C26,'CPSX-Chai'!$B:$F,COLUMNS('CPSX-Chai'!$B$4:C$4),0)+VLOOKUP($C26,'CPSX-Vảy'!$B:$F,COLUMNS('CPSX-Vảy'!$B$4:C$4),0) -> 40656000 | E26: =VLOOKUP($C26,'CPSX-Chai'!$B:$F,COLUMNS('CPSX-Chai'!$B$4:D$4),0)+VLOOKUP($C26,'CPSX-Vảy'!$B:$F,COLUMNS('CPSX-Vảy'!$B$4:D$4),0) -> 60984000 | F26: =VLOOKUP($C26,'CPSX-Chai'!$B:$F,COLUMNS('CPSX-Chai'!$B$4:E$4),0)+VLOOKUP($C26,'CPSX-Vảy'!$B:$F,COLUMNS('CPSX-Vảy'!$B$4:E$4),0) -> 81312000 | G26: =VLOOKUP($C26,'CPSX-Chai'!$B:$F,COLUMNS('CPSX-Chai'!$B$4:F$4),0)+VLOOKUP($C26,'CPSX-Vảy'!$B:$F,COLUMNS('CPSX-Vảy'!$B$4:F$4),0) -> 101640000 | H26: =D26*12 -> 487872000 | I26: =E26*12 -> 731808000 | J26: =F26*12 -> 975744000 | K26: =G26*12 -> 1219680000
A27: -11 | C27: Chi phí vật tư kỹ thuật phục vụ sản xuất khác | D27: =VLOOKUP($C27,'CPSX-Chai'!$B:$F,COLUMNS('CPSX-Chai'!$B$4:C$4),0)+VLOOKUP($C27,'CPSX-Vảy'!$B:$F,COLUMNS('CPSX-Vảy'!$B$4:C$4),0) -> 0 | E27: =VLOOKUP($C27,'CPSX-Chai'!$B:$F,COLUMNS('CPSX-Chai'!$B$4:D$4),0)+VLOOKUP($C27,'CPSX-Vảy'!$B:$F,COLUMNS('CPSX-Vảy'!$B$4:D$4),0) -> 0 | F27: =VLOOKUP($C27,'CPSX-Chai'!$B:$F,COLUMNS('CPSX-Chai'!$B$4:E$4),0)+VLOOKUP($C27,'CPSX-Vảy'!$B:$F,COLUMNS('CPSX-Vảy'!$B$4:E$4),0) -> 0 | G27: =VLOOKUP($C27,'CPSX-Chai'!$B:$F,COLUMNS('CPSX-Chai'!$B$4:F$4),0)+VLOOKUP($C27,'CPSX-Vảy'!$B:$F,COLUMNS('CPSX-Vảy'!$B$4:F$4),0) -> 0 | H27: =D27*12 -> 0 | I27: =E27*12 -> 0 | J27: =F27*12 -> 0 | K27: =G27*12 -> 0
A28: 4 | B28: LÃI BIẾN PHÍ | D28: =D5-D7 -> 1.0818462e+09 | E28: =E5-E7 -> 1.6227693e+09 | F28: =F5-F7 -> 2.1636923e+09 | G28: =G5-G7 -> 2.7046154e+09 | H28: =H5-H7 -> 1.2982154e+10 | I28: =I5-I7 -> 1.9473231e+10 | J28: =J5-J7 -> 2.5964308e+10 | K28: =K5-K7 -> 3.2455385e+10
C29: Tỷ lệ Lãi biến phí (%) | D29: =IFERROR(D28/D$5,0) -> 0.20508155 | E29: =IFERROR(E28/E$5,0) -> 0.20508155 | F29: =IFERROR(F28/F$5,0) -> 0.20508155 | G29: =IFERROR(G28/G$5,0) -> 0.20508155 | H29: =IFERROR(H28/H$5,0) -> 0.20508155 | I29: =IFERROR(I28/I$5,0) -> 0.20508155 | J29: =IFERROR(J28/J$5,0) -> 0.20508155 | K29: =IFERROR(K28/K$5,0) -> 0.20508155
C30: Lãi biến phí / Tấn (Triệu đồng/Tấn) | D30: =IFERROR(D28/D$4,0)*1000 -> 2927073 | E30: =IFERROR(E28/E$4,0)*1000 -> 2927073 | F30: =IFERROR(F28/F$4,0)*1000 -> 2927073 | G30: =IFERROR(G28/G$4,0)*1000 -> 2927073 | H30: =IFERROR(H28/H$4,0)*1000 -> 2927073 | I30: =IFERROR(I28/I$4,0)*1000 -> 2927073 | J30: =IFERROR(J28/J$4,0)*1000 -> 2927073 | K30: =IFERROR(K28/K$4,0)*1000 -> 2927073
A31: 5 | B31: ĐỊNH PHÍ | D31: =D34+D47+D66+D92+D95 -> 1.3240191e+09 | E31: =E34+E47+E66+E92+E95 -> 1.5081062e+09 | F31: =F34+F47+F66+F92+F95 -> 1.6468041e+09 | G31: =G34+G47+G66+G92+G95 -> 1.6958579e+09 | H31: =H34+H47+H66+H92+H95 -> 1.5888229e+10 | I31: =I34+I47+I66+I92+I95 -> 1.8097275e+10 | J31: =J34+J47+J66+J92+J95 -> 1.9761649e+10 | K31: =K34+K47+K66+K92+K95 -> 2.0350295e+10
C32: Định phí / Doanh thu (%) | D32: =IFERROR(D31/D$5,0) -> 0.25098936 | E32: =IFERROR(E31/E$5,0) -> 0.19059072 | F32: =IFERROR(F31/F$5,0) -> 0.15608926 | G32: =IFERROR(G31/G$5,0) -> 0.12859099 | H32: =IFERROR(H31/H$5,0) -> 0.25098936 | I32: =IFERROR(I31/I$5,0) -> 0.19059072 | J32: =IFERROR(J31/J$5,0) -> 0.15608926 | K32: =IFERROR(K31/K$5,0) -> 0.12859099
C33: Định phí / Tấn (Triệu đồng/Tấn) | D33: =IFERROR(D31/D$4,0)*1000 -> 3582302.7 | E33: =IFERROR(E31/E$4,0)*1000 -> 2720249.4 | F33: =IFERROR(F31/F$4,0)*1000 -> 2227819.4 | G33: =IFERROR(G31/G$4,0)*1000 -> 1835344.1 | H33: =IFERROR(H31/H$4,0)*1000 -> 3582302.7 | I33: =IFERROR(I31/I$4,0)*1000 -> 2720249.4 | J33: =IFERROR(J31/J$4,0)*1000 -> 2227819.4 | K33: =IFERROR(K31/K$4,0)*1000 -> 1835344.1
A34: 5.1 | B34: Định phí sản xuất | D34: =SUM(D36:D46) -> 4.5353161e+08 | E34: =SUM(E36:E46) -> 4.6051879e+08 | F34: =SUM(F36:F46) -> 4.6750597e+08 | G34: =SUM(G36:G46) -> 4.7549315e+08 | H34: =SUM(H36:H46) -> 5.4423794e+09 | I34: =SUM(I36:I46) -> 5.5262255e+09 | J34: =SUM(J36:J46) -> 5.6100717e+09 | K34: =SUM(K36:K46) -> 5.7059178e+09
C35: Định phí sản xuất / Doanh thu (%) | D35: =IFERROR(D34/D$5,0) -> 0.085974298 | E35: =IFERROR(E34/E$5,0) -> 0.058199221 | F35: =IFERROR(F34/F$5,0) -> 0.044311682 | G35: =IFERROR(G34/G$5,0) -> 0.036054986 | H35: =IFERROR(H34/H$5,0) -> 0.085974298 | I35: =IFERROR(I34/I$5,0) -> 0.058199221 | J35: =IFERROR(J34/J$5,0) -> 0.044311682 | K35: =IFERROR(K34/K$5,0) -> 0.036054986
A36: -1 | C36: Chi phí sửa chữa, bảo trì máy móc thiết bị sản xuất | D36: =VLOOKUP($C36,'CPSX-Chai'!$B:$F,COLUMNS('CPSX-Chai'!$B$4:C$4),0)+VLOOKUP($C36,'CPSX-Vảy'!$B:$F,COLUMNS('CPSX-Vảy'!$B$4:C$4),0) -> 22190006 | E36: =VLOOKUP($C36,'CPSX-Chai'!$B:$F,COLUMNS('CPSX-Chai'!$B$4:D$4),0)+VLOOKUP($C36,'CPSX-Vảy'!$B:$F,COLUMNS('CPSX-Vảy'!$B$4:D$4),0) -> 22190006 | F36: =VLOOKUP($C36,'CPSX-Chai'!$B:$F,COLUMNS('CPSX-Chai'!$B$4:E$4),0)+VLOOKUP($C36,'CPSX-Vảy'!$B:$F,COLUMNS('CPSX-Vảy'!$B$4:E$4),0) -> 22190006 | G36: =VLOOKUP($C36,'CPSX-Chai'!$B:$F,COLUMNS('CPSX-Chai'!$B$4:F$4),0)+VLOOKUP($C36,'CPSX-Vảy'!$B:$F,COLUMNS('CPSX-Vảy'!$B$4:F$4),0) -> 22190006 | H36: =D36*12 -> 266280072 | I36: =E36*12 -> 266280072 | J36: =F36*12 -> 266280072 | K36: =G36*12 -> 266280072
A37: -2 | C37: Chi phí sửa chữa, bảo trì phương tiện vận tải | D37: =VLOOKUP($C37,'CPSX-Chai'!$B:$F,COLUMNS('CPSX-Chai'!$B$4:C$4),0)+VLOOKUP($C37,'CPSX-Vảy'!$B:$F,COLUMNS('CPSX-Vảy'!$B$4:C$4),0) -> 1974359 | E37: =VLOOKUP($C37,'CPSX-Chai'!$B:$F,COLUMNS('CPSX-Chai'!$B$4:D$4),0)+VLOOKUP($C37,'CPSX-Vảy'!$B:$F,COLUMNS('CPSX-Vảy'!$B$4:D$4),0) -> 2961538.5 | F37: =VLOOKUP($C37,'CPSX-Chai'!$B:$F,COLUMNS('CPSX-Chai'!$B$4:E$4),0)+VLOOKUP($C37,'CPSX-Vảy'!$B:$F,COLUMNS('CPSX-Vảy'!$B$4:E$4),0) -> 3948717.9 | G37: =VLOOKUP($C37,'CPSX-Chai'!$B:$F,COLUMNS('CPSX-Chai'!$B$4:F$4),0)+VLOOKUP($C37,'CPSX-Vảy'!$B:$F,COLUMNS('CPSX-Vảy'!$B$4:F$4),0) -> 4935897.4 | H37: =D37*12 -> 23692308 | I37: =E37*12 -> 35538462 | J37: =F37*12 -> 47384615 | K37: =G37*12 -> 59230769
A38: -3 | C38: Chi phí sửa chữa, bảo trì công trình xây dựng (nhà xưởng, ... ) | D38: =VLOOKUP($C38,'CPSX-Chai'!$B:$F,COLUMNS('CPSX-Chai'!$B$4:C$4),0)+VLOOKUP($C38,'CPSX-Vảy'!$B:$F,COLUMNS('CPSX-Vảy'!$B$4:C$4),0) -> 4142250 | E38: =VLOOKUP($C38,'CPSX-Chai'!$B:$F,COLUMNS('CPSX-Chai'!$B$4:D$4),0)+VLOOKUP($C38,'CPSX-Vảy'!$B:$F,COLUMNS('CPSX-Vảy'!$B$4:D$4),0) -> 4142250 | F38: =VLOOKUP($C38,'CPSX-Chai'!$B:$F,COLUMNS('CPSX-Chai'!$B$4:E$4),0)+VLOOKUP($C38,'CPSX-Vảy'!$B:$F,COLUMNS('CPSX-Vảy'!$B$4:E$4),0) -> 4142250 | G38: =VLOOKUP($C38,'CPSX-Chai'!$B:$F,COLUMNS('CPSX-Chai'!$B$4:F$4),0)+VLOOKUP($C38,'CPSX-Vảy'!$B:$F,COLUMNS('CPSX-Vảy'!$B$4:F$4),0) -> 4142250 | H38: =D38*12 -> 49707000 | I38: =E38*12 -> 49707000 | J38: =F38*12 -> 49707000 | K38: =G38*12 -> 49707000
A39: -4 | C39: Chi phí đăng kiểm xe cơ giới | D39: =VLOOKUP($C39,'CPSX-Chai'!$B:$F,COLUMNS('CPSX-Chai'!$B$4:C$4),0)+VLOOKUP($C39,'CPSX-Vảy'!$B:$F,COLUMNS('CPSX-Vảy'!$B$4:C$4),0) -> 0 | E39: =VLOOKUP($C39,'CPSX-Chai'!$B:$F,COLUMNS('CPSX-Chai'!$B$4:D$4),0)+VLOOKUP($C39,'CPSX-Vảy'!$B:$F,COLUMNS('CPSX-Vảy'!$B$4:D$4),0) -> 0 | F39: =VLOOKUP($C39,'CPSX-Chai'!$B:$F,COLUMNS('CPSX-Chai'!$B$4:E$4),0)+VLOOKUP($C39,'CPSX-Vảy'!$B:$F,COLUMNS('CPSX-Vảy'!$B$4:E$4),0) -> 0 | G39: =VLOOKUP($C39,'CPSX-Chai'!$B:$F,COLUMNS('CPSX-Chai'!$B$4:F$4),0)+VLOOKUP($C39,'CPSX-Vảy'!$B:$F,COLUMNS('CPSX-Vảy'!$B$4:F$4),0) -> 0 | H39: =D39*12 -> 0 | I39: =E39*12 -> 0 | J39: =F39*12 -> 0 | K39: =G39*12 -> 0
A40: -5 | C40: Chi phí kiểm định, hiệu chuẩn máy móc thiết bị | D40: =VLOOKUP($C40,'CPSX-Chai'!$B:$F,COLUMNS('CPSX-Chai'!$B$4:C$4),0)+VLOOKUP($C40,'CPSX-Vảy'!$B:$F,COLUMNS('CPSX-Vảy'!$B$4:C$4),0) -> 3000000 | E40: =VLOOKUP($C40,'CPSX-Chai'!$B:$F,COLUMNS('CPSX-Chai'!$B$4:D$4),0)+VLOOKUP($C40,'CPSX-Vảy'!$B:$F,COLUMNS('CPSX-Vảy'!$B$4:D$4),0) -> 5000000 | F40: =VLOOKUP($C40,'CPSX-Chai'!$B:$F,COLUMNS('CPSX-Chai'!$B$4:E$4),0)+VLOOKUP($C40,'CPSX-Vảy'!$B:$F,COLUMNS('CPSX-Vảy'!$B$4:E$4),0) -> 7000000 | G40: =VLOOKUP($C40,'CPSX-Chai'!$B:$F,COLUMNS('CPSX-Chai'!$B$4:F$4),0)+VLOOKUP($C40,'CPSX-Vảy'!$B:$F,COLUMNS('CPSX-Vảy'!$B$4:F$4),0) -> 10000000 | H40: =D40*12 -> 36000000 | I40: =E40*12 -> 60000000 | J40: =F40*12 -> 84000000 | K40: =G40*12 -> 120000000
A41: -6 | C41: Chi phí công cụ dụng cụ phục vụ sản xuất | D41: =VLOOKUP($C41,'CPSX-Chai'!$B:$F,COLUMNS('CPSX-Chai'!$B$4:C$4),0)+VLOOKUP($C41,'CPSX-Vảy'!$B:$F,COLUMNS('CPSX-Vảy'!$B$4:C$4),0) -> 5000000 | E41: =VLOOKUP($C41,'CPSX-Chai'!$B:$F,COLUMNS('CPSX-Chai'!$B$4:D$4),0)+VLOOKUP($C41,'CPSX-Vảy'!$B:$F,COLUMNS('CPSX-Vảy'!$B$4:D$4),0) -> 7000000 | F41: =VLOOKUP($C41,'CPSX-Chai'!$B:$F,COLUMNS('CPSX-Chai'!$B$4:E$4),0)+VLOOKUP($C41,'CPSX-Vảy'!$B:$F,COLUMNS('CPSX-Vảy'!$B$4:E$4),0) -> 8000000 | G41: =VLOOKUP($C41,'CPSX-Chai'!$B:$F,COLUMNS('CPSX-Chai'!$B$4:F$4),0)+VLOOKUP($C41,'CPSX-Vảy'!$B:$F,COLUMNS('CPSX-Vảy'!$B$4:F$4),0) -> 10000000 | H41: =D41*12 -> 60000000 | I41: =E41*12 -> 84000000 | J41: =F41*12 -> 96000000 | K41: =G41*12 -> 120000000
A42: -7 | C42: Chi phí thuê xưởng | D42: =VLOOKUP($C42,'CPSX-Chai'!$B:$F,COLUMNS('CPSX-Chai'!$B$4:C$4),0)+VLOOKUP($C42,'CPSX-Vảy'!$B:$F,COLUMNS('CPSX-Vảy'!$B$4:C$4),0) -> 414225000 | E42: =VLOOKUP($C42,'CPSX-Chai'!$B:$F,COLUMNS('CPSX-Chai'!$B$4:D$4),0)+VLOOKUP($C42,'CPSX-Vảy'!$B:$F,COLUMNS('CPSX-Vảy'!$B$4:D$4),0) -> 414225000 | F42: =VLOOKUP($C42,'CPSX-Chai'!$B:$F,COLUMNS('CPSX-Chai'!$B$4:E$4),0)+VLOOKUP($C42,'CPSX-Vảy'!$B:$F,COLUMNS('CPSX-Vảy'!$B$4:E$4),0) -> 414225000 | G42: =VLOOKUP($C42,'CPSX-Chai'!$B:$F,COLUMNS('CPSX-Chai'!$B$4:F$4),0)+VLOOKUP($C42,'CPSX-Vảy'!$B:$F,COLUMNS('CPSX-Vảy'!$B$4:F$4),0) -> 414225000 | H42: =D42*12 -> 4970700000 | I42: =E42*12 -> 4970700000 | J42: =F42*12 -> 4970700000 | K42: =G42*12 -> 4970700000
A43: -8 | C43: Chi phí thuê kho, bãi | D43: =VLOOKUP($C43,'CPSX-Chai'!$B:$F,COLUMNS('CPSX-Chai'!$B$4:C$4),0)+VLOOKUP($C43,'CPSX-Vảy'!$B:$F,COLUMNS('CPSX-Vảy'!$B$4:C$4),0) -> 0 | E43: =VLOOKUP($C43,'CPSX-Chai'!$B:$F,COLUMNS('CPSX-Chai'!$B$4:D$4),0)+VLOOKUP($C43,'CPSX-Vảy'!$B:$F,COLUMNS('CPSX-Vảy'!$B$4:D$4),0) -> 0 | F43: =VLOOKUP($C43,'CPSX-Chai'!$B:$F,COLUMNS('CPSX-Chai'!$B$4:E$4),0)+VLOOKUP($C43,'CPSX-Vảy'!$B:$F,COLUMNS('CPSX-Vảy'!$B$4:E$4),0) -> 0 | G43: =VLOOKUP($C43,'CPSX-Chai'!$B:$F,COLUMNS('CPSX-Chai'!$B$4:F$4),0)+VLOOKUP($C43,'CPSX-Vảy'!$B:$F,COLUMNS('CPSX-Vảy'!$B$4:F$4),0) -> 0 | H43: =D43*12 -> 0 | I43: =E43*12 -> 0 | J43: =F43*12 -> 0 | K43: =G43*12 -> 0
A44: -9 | C44: Chi phí thuê máy móc thiết bị | D44: =VLOOKUP($C44,'CPSX-Chai'!$B:$F,COLUMNS('CPSX-Chai'!$B$4:C$4),0)+VLOOKUP($C44,'CPSX-Vảy'!$B:$F,COLUMNS('CPSX-Vảy'!$B$4:C$4),0) -> 0 | E44: =VLOOKUP($C44,'CPSX-Chai'!$B:$F,COLUMNS('CPSX-Chai'!$B$4:D$4),0)+VLOOKUP($C44,'CPSX-Vảy'!$B:$F,COLUMNS('CPSX-Vảy'!$B$4:D$4),0) -> 0 | F44: =VLOOKUP($C44,'CPSX-Chai'!$B:$F,COLUMNS('CPSX-Chai'!$B$4:E$4),0)+VLOOKUP($C44,'CPSX-Vảy'!$B:$F,COLUMNS('CPSX-Vảy'!$B$4:E$4),0) -> 0 | G44: =VLOOKUP($C44,'CPSX-Chai'!$B:$F,COLUMNS('CPSX-Chai'!$B$4:F$4),0)+VLOOKUP($C44,'CPSX-Vảy'!$B:$F,COLUMNS('CPSX-Vảy'!$B$4:F$4),0) -> 0 | H44: =D44*12 -> 0 | I44: =E44*12 -> 0 | J44: =F44*12 -> 0 | K44: =G44*12 -> 0
A45: -10 | C45: Chi phí thuê phương tiện vận tải | D45: =VLOOKUP($C45,'CPSX-Chai'!$B:$F,COLUMNS('CPSX-Chai'!$B$4:C$4),0)+VLOOKUP($C45,'CPSX-Vảy'!$B:$F,COLUMNS('CPSX-Vảy'!$B$4:C$4),0) -> 0 | E45: =VLOOKUP($C45,'CPSX-Chai'!$B:$F,COLUMNS('CPSX-Chai'!$B$4:D$4),0)+VLOOKUP($C45,'CPSX-Vảy'!$B:$F,COLUMNS('CPSX-Vảy'!$B$4:D$4),0) -> 0 | F45: =VLOOKUP($C45,'CPSX-Chai'!$B:$F,COLUMNS('CPSX-Chai'!$B$4:E$4),0)+VLOOKUP($C45,'CPSX-Vảy'!$B:$F,COLUMNS('CPSX-Vảy'!$B$4:E$4),0) -> 0 | G45: =VLOOKUP($C45,'CPSX-Chai'!$B:$F,COLUMNS('CPSX-Chai'!$B$4:F$4),0)+VLOOKUP($C45,'CPSX-Vảy'!$B:$F,COLUMNS('CPSX-Vảy'!$B$4:F$4),0) -> 0 | H45: =D45*12 -> 0 | I45: =E45*12 -> 0 | J45: =F45*12 -> 0 | K45: =G45*12 -> 0
A46: -11 | C46: Chi phí sản xuất khác | D46: =VLOOKUP($C46,'CPSX-Chai'!$B:$F,COLUMNS('CPSX-Chai'!$B$4:C$4),0)+VLOOKUP($C46,'CPSX-Vảy'!$B:$F,COLUMNS('CPSX-Vảy'!$B$4:C$4),0) -> 3000000 | E46: =VLOOKUP($C46,'CPSX-Chai'!$B:$F,COLUMNS('CPSX-Chai'!$B$4:D$4),0)+VLOOKUP($C46,'CPSX-Vảy'!$B:$F,COLUMNS('CPSX-Vảy'!$B$4:D$4),0) -> 5000000 | F46: =VLOOKUP($C46,'CPSX-Chai'!$B:$F,COLUMNS('CPSX-Chai'!$B$4:E$4),0)+VLOOKUP($C46,'CPSX-Vảy'!$B:$F,COLUMNS('CPSX-Vảy'!$B$4:E$4),0) -> 8000000 | G46: =VLOOKUP($C46,'CPSX-Chai'!$B:$F,COLUMNS('CPSX-Chai'!$B$4:F$4),0)+VLOOKUP($C46,'CPSX-Vảy'!$B:$F,COLUMNS('CPSX-Vảy'!$B$4:F$4),0) -> 10000000 | H46: =D46*12 -> 36000000 | I46: =E46*12 -> 60000000 | J46: =F46*12 -> 96000000 | K46: =G46*12 -> 120000000
A47: 5.2 | B47: Định phí quản lý | D47: =SUM(D49:D65) -> 1.1830113e+08 | E47: =SUM(E49:E65) -> 1.1830113e+08 | F47: =SUM(F49:F65) -> 1.1830113e+08 | G47: =SUM(G49:G65) -> 1.1830113e+08 | H47: =SUM(H49:H65) -> 1419613612 | I47: =SUM(I49:I65) -> 1419613612 | J47: =SUM(J49:J65) -> 1419613612 | K47: =SUM(K49:K65) -> 1419613612
C48: Định phí quản lý / Doanh thu (%) | D48: =IFERROR(D47/D$5,0) -> 0.022425905 | E48: =IFERROR(E47/E$5,0) -> 0.014950603 | F48: =IFERROR(F47/F$5,0) -> 0.011212953 | G48: =IFERROR(G47/G$5,0) -> 0.008970362 | H48: =IFERROR(H47/H$5,0) -> 0.022425905 | I48: =IFERROR(I47/I$5,0) -> 0.014950603 | J48: =IFERROR(J47/J$5,0) -> 0.011212953 | K48: =IFERROR(K47/K$5,0) -> 0.008970362
A49: -1 | C49: Chi phí điện quản lý | D49: =VLOOKUP($C49,CPQL!$B:$F,COLUMNS(CPQL!$B$3:C$3),0) -> 2000000 | E49: =VLOOKUP($C49,CPQL!$B:$F,COLUMNS(CPQL!$B$3:D$3),0) -> 2000000 | F49: =VLOOKUP($C49,CPQL!$B:$F,COLUMNS(CPQL!$B$3:E$3),0) -> 2000000 | G49: =VLOOKUP($C49,CPQL!$B:$F,COLUMNS(CPQL!$B$3:F$3),0) -> 2000000 | H49: =D49*12 -> 24000000 | I49: =E49*12 -> 24000000 | J49: =F49*12 -> 24000000 | K49: =G49*12 -> 24000000
A50: -2 | C50: Chi phí nước sinh hoạt | D50: =VLOOKUP($C50,CPQL!$B:$F,COLUMNS(CPQL!$B$3:C$3),0) -> 3000000 | E50: =VLOOKUP($C50,CPQL!$B:$F,COLUMNS(CPQL!$B$3:D$3),0) -> 3000000 | F50: =VLOOKUP($C50,CPQL!$B:$F,COLUMNS(CPQL!$B$3:E$3),0) -> 3000000 | G50: =VLOOKUP($C50,CPQL!$B:$F,COLUMNS(CPQL!$B$3:F$3),0) -> 3000000 | H50: =D50*12 -> 36000000 | I50: =E50*12 -> 36000000 | J50: =F50*12 -> 36000000 | K50: =G50*12 -> 36000000
A51: -3 | C51: Chi phí dịch vụ bảo vệ | D51: =VLOOKUP($C51,CPQL!$B:$F,COLUMNS(CPQL!$B$3:C$3),0) -> 36000000 | E51: =VLOOKUP($C51,CPQL!$B:$F,COLUMNS(CPQL!$B$3:D$3),0) -> 36000000 | F51: =VLOOKUP($C51,CPQL!$B:$F,COLUMNS(CPQL!$B$3:E$3),0) -> 36000000 | G51: =VLOOKUP($C51,CPQL!$B:$F,COLUMNS(CPQL!$B$3:F$3),0) -> 36000000 | H51: =D51*12 -> 432000000 | I51: =E51*12 -> 432000000 | J51: =F51*12 -> 432000000 | K51: =G51*12 -> 432000000
A52: -4 | C52: Chi phí bảo hiểm tài sản | D52: =VLOOKUP($C52,CPQL!$B:$F,COLUMNS(CPQL!$B$3:C$3),0) -> 3698334.3 | E52: =VLOOKUP($C52,CPQL!$B:$F,COLUMNS(CPQL!$B$3:D$3),0) -> 3698334.3 | F52: =VLOOKUP($C52,CPQL!$B:$F,COLUMNS(CPQL!$B$3:E$3),0) -> 3698334.3 | G52: =VLOOKUP($C52,CPQL!$B:$F,COLUMNS(CPQL!$B$3:F$3),0) -> 3698334.3 | H52: =D52*12 -> 44380012 | I52: =E52*12 -> 44380012 | J52: =F52*12 -> 44380012 | K52: =G52*12 -> 44380012
A53: -5 | C53: Chi phí xây dựng phần mềm | D53: =VLOOKUP($C53,CPQL!$B:$F,COLUMNS(CPQL!$B$3:C$3),0) -> 0 | E53: =VLOOKUP($C53,CPQL!$B:$F,COLUMNS(CPQL!$B$3:D$3),0) -> 0 | F53: =VLOOKUP($C53,CPQL!$B:$F,COLUMNS(CPQL!$B$3:E$3),0) -> 0 | G53: =VLOOKUP($C53,CPQL!$B:$F,COLUMNS(CPQL!$B$3:F$3),0) -> 0 | H53: =D53*12 -> 0 | I53: =E53*12 -> 0 | J53: =F53*12 -> 0 | K53: =G53*12 -> 0
A54: -6 | C54: Chi phí bản quyền (licences) | D54: =VLOOKUP($C54,CPQL!$B:$F,COLUMNS(CPQL!$B$3:C$3),0) -> 48102800 | E54: =VLOOKUP($C54,CPQL!$B:$F,COLUMNS(CPQL!$B$3:D$3),0) -> 48102800 | F54: =VLOOKUP($C54,CPQL!$B:$F,COLUMNS(CPQL!$B$3:E$3),0) -> 48102800 | G54: =VLOOKUP($C54,CPQL!$B:$F,COLUMNS(CPQL!$B$3:F$3),0) -> 48102800 | H54: =D54*12 -> 577233600 | I54: =E54*12 -> 577233600 | J54: =F54*12 -> 577233600 | K54: =G54*12 -> 577233600
A55: -7 | C55: Chi phí ủng hộ, hỗ trợ, tài trợ | D55: =VLOOKUP($C55,CPQL!$B:$F,COLUMNS(CPQL!$B$3:C$3),0) -> 2000000 | E55: =VLOOKUP($C55,CPQL!$B:$F,COLUMNS(CPQL!$B$3:D$3),0) -> 2000000 | F55: =VLOOKUP($C55,CPQL!$B:$F,COLUMNS(CPQL!$B$3:E$3),0) -> 2000000 | G55: =VLOOKUP($C55,CPQL!$B:$F,COLUMNS(CPQL!$B$3:F$3),0) -> 2000000 | H55: =D55*12 -> 24000000 | I55: =E55*12 -> 24000000 | J55: =F55*12 -> 24000000 | K55: =G55*12 -> 24000000
A56: -8 | C56: Chi phí công tác | D56: =VLOOKUP($C56,CPQL!$B:$F,COLUMNS(CPQL!$B$3:C$3),0) -> 1500000 | E56: =VLOOKUP($C56,CPQL!$B:$F,COLUMNS(CPQL!$B$3:D$3),0) -> 1500000 | F56: =VLOOKUP($C56,CPQL!$B:$F,COLUMNS(CPQL!$B$3:E$3),0) -> 1500000 | G56: =VLOOKUP($C56,CPQL!$B:$F,COLUMNS(CPQL!$B$3:F$3),0) -> 1500000 | H56: =D56*12 -> 18000000 | I56: =E56*12 -> 18000000 | J56: =F56*12 -> 18000000 | K56: =G56*12 -> 18000000
A57: -9 | C57: Chi phí tiếp khách | D57: =VLOOKUP($C57,CPQL!$B:$F,COLUMNS(CPQL!$B$3:C$3),0) -> 3833333.3 | E57: =VLOOKUP($C57,CPQL!$B:$F,COLUMNS(CPQL!$B$3:D$3),0) -> 3833333.3 | F57: =VLOOKUP($C57,CPQL!$B:$F,COLUMNS(CPQL!$B$3:E$3),0) -> 3833333.3 | G57: =VLOOKUP($C57,CPQL!$B:$F,COLUMNS(CPQL!$B$3:F$3),0) -> 3833333.3 | H57: =D57*12 -> 46000000 | I57: =E57*12 -> 46000000 | J57: =F57*12 -> 46000000 | K57: =G57*12 -> 46000000
A58: -10 | C58: Chi phí in ấn, vật tư, VPP | D58: =VLOOKUP($C58,CPQL!$B:$F,COLUMNS(CPQL!$B$3:C$3),0) -> 4500000 | E58: =VLOOKUP($C58,CPQL!$B:$F,COLUMNS(CPQL!$B$3:D$3),0) -> 4500000 | F58: =VLOOKUP($C58,CPQL!$B:$F,COLUMNS(CPQL!$B$3:E$3),0) -> 4500000 | G58: =VLOOKUP($C58,CPQL!$B:$F,COLUMNS(CPQL!$B$3:F$3),0) -> 4500000 | H58: =D58*12 -> 54000000 | I58: =E58*12 -> 54000000 | J58: =F58*12 -> 54000000 | K58: =G58*12 -> 54000000
A59: -11 | C59: Chi phí internet, điện thoại, bưu phẩm | D59: =VLOOKUP($C59,CPQL!$B:$F,COLUMNS(CPQL!$B$3:C$3),0) -> 1500000 | E59: =VLOOKUP($C59,CPQL!$B:$F,COLUMNS(CPQL!$B$3:D$3),0) -> 1500000 | F59: =VLOOKUP($C59,CPQL!$B:$F,COLUMNS(CPQL!$B$3:E$3),0) -> 1500000 | G59: =VLOOKUP($C59,CPQL!$B:$F,COLUMNS(CPQL!$B$3:F$3),0) -> 1500000 | H59: =D59*12 -> 18000000 | I59: =E59*12 -> 18000000 | J59: =F59*12 -> 18000000 | K59: =G59*12 -> 18000000
A60: -12 | C60: Chi phí nước uống | D60: =VLOOKUP($C60,CPQL!$B:$F,COLUMNS(CPQL!$B$3:C$3),0) -> 5000000 | E60: =VLOOKUP($C60,CPQL!$B:$F,COLUMNS(CPQL!$B$3:D$3),0) -> 5000000 | F60: =VLOOKUP($C60,CPQL!$B:$F,COLUMNS(CPQL!$B$3:E$3),0) -> 5000000 | G60: =VLOOKUP($C60,CPQL!$B:$F,COLUMNS(CPQL!$B$3:F$3),0) -> 5000000 | H60: =D60*12 -> 60000000 | I60: =E60*12 -> 60000000 | J60: =F60*12 -> 60000000 | K60: =G60*12 -> 60000000
... A65: -17 | C65: Chi phí khác | D65: =VLOOKUP($C65,CPQL!$B:$F,COLUMNS(CPQL!$B$3:C$3),0) -> 4416666.7 | E65: =VLOOKUP($C65,CPQL!$B:$F,COLUMNS(CPQL!$B$3:D$3),0) -> 4416666.7 | F65: =VLOOKUP($C65,CPQL!$B:$F,COLUMNS(CPQL!$B$3:E$3),0) -> 4416666.7 | G65: =VLOOKUP($C65,CPQL!$B:$F,COLUMNS(CPQL!$B$3:F$3),0) -> 4416666.7 | H65: =D65*12 -> 53000000 | I65: =E65*12 -> 53000000 | J65: =F65*12 -> 53000000 | K65: =G65*12 -> 53000000
A66: 5.3 | B66: Chi phí nhân sự | D66: =D68+D81 -> 5.0079583e+08 | E66: =E68+E81 -> 6.7789583e+08 | F66: =F68+F81 -> 809606500 | G66: =G68+G81 -> 8.5067317e+08 | H66: =H68+H81 -> 6009550000 | I66: =I68+I81 -> 8134750000 | J66: =J68+J81 -> 9715278000 | K66: =K68+K81 -> 10208078000
C67: (%) Chi phí nhân sự / Doanh thu | D67: =IFERROR(D66/D$5,0) -> 0.094933999 | E67: =IFERROR(E66/E$5,0) -> 0.085670791 | F67: =IFERROR(F66/F$5,0) -> 0.076737043 | G67: =IFERROR(G66/G$5,0) -> 0.064503576 | H67: =IFERROR(H66/H$5,0) -> 0.094933999 | I67: =IFERROR(I66/I$5,0) -> 0.085670791 | J67: =IFERROR(J66/J$5,0) -> 0.076737043 | K67: =IFERROR(K66/K$5,0) -> 0.064503576
A68: 5.3.1 | B68: Chi phí lương | D68: =SUM(D70:D80) -> 4.8253333e+08 | E68: =SUM(E70:E80) -> 6.5963333e+08 | F68: =SUM(F70:F80) -> 777700000 | G68: =SUM(G70:G80) -> 8.1876667e+08 | H68: =SUM(H70:H80) -> 5790400000 | I68: =SUM(I70:I80) -> 7915600000 | J68: =SUM(J70:J80) -> 9332400000 | K68: =SUM(K70:K80) -> 9825200000
C69: (%) Chi phí lương / Doanh thu | D69: =IFERROR(D68/D$5,0) -> 0.091472045 | E69: =IFERROR(E68/E$5,0) -> 0.083362821 | F69: =IFERROR(F68/F$5,0) -> 0.073712845 | G69: =IFERROR(G68/G$5,0) -> 0.062084218 | H69: =IFERROR(H68/H$5,0) -> 0.091472045 | I69: =IFERROR(I68/I$5,0) -> 0.083362821 | J69: =IFERROR(J68/J$5,0) -> 0.073712845 | K69: =IFERROR(K68/K$5,0) -> 0.062084218
A70: -1 | C70: Chi phí lương chính - Trực tiếp | D70: =SUMIF('CP.NS'!$B:$B,KQKD!$C70,'CP.NS'!C:C) -> 72000000 | E70: =SUMIF('CP.NS'!$B:$B,KQKD!$C70,'CP.NS'!D:D) -> 128000000 | F70: =SUMIF('CP.NS'!$B:$B,KQKD!$C70,'CP.NS'!E:E) -> 168000000 | G70: =SUMIF('CP.NS'!$B:$B,KQKD!$C70,'CP.NS'!F:F) -> 200000000 | H70: =D70*12 -> 864000000 | I70: =E70*12 -> 1536000000 | J70: =F70*12 -> 2016000000 | K70: =G70*12 -> 2400000000
A71: -2 | C71: Chi phí lương chính - Gián tiếp | D71: =SUMIF('CP.NS'!$B:$B,KQKD!$C71,'CP.NS'!C:C) -> 304000000 | E71: =SUMIF('CP.NS'!$B:$B,KQKD!$C71,'CP.NS'!D:D) -> 386000000 | F71: =SUMIF('CP.NS'!$B:$B,KQKD!$C71,'CP.NS'!E:E) -> 438000000 | G71: =SUMIF('CP.NS'!$B:$B,KQKD!$C71,'CP.NS'!F:F) -> 438000000 | H71: =D71*12 -> 3648000000 | I71: =E71*12 -> 4632000000 | J71: =F71*12 -> 5256000000 | K71: =G71*12 -> 5256000000
A72: -3 | C72: Chi phí lương T13, Phép năm - Trực tiếp | D72: =SUMIF('CP.NS'!$B:$B,KQKD!$C72,'CP.NS'!C:C) -> 6000000 | E72: =SUMIF('CP.NS'!$B:$B,KQKD!$C72,'CP.NS'!D:D) -> 10666667 | F72: =SUMIF('CP.NS'!$B:$B,KQKD!$C72,'CP.NS'!E:E) -> 14000000 | G72: =SUMIF('CP.NS'!$B:$B,KQKD!$C72,'CP.NS'!F:F) -> 16666667 | H72: =D72*12 -> 72000000 | I72: =E72*12 -> 128000000 | J72: =F72*12 -> 168000000 | K72: =G72*12 -> 200000000
A73: -4 | C73: Chi phí lương T13, Phép năm - Gián tiếp | D73: =SUMIF('CP.NS'!$B:$B,KQKD!$C73,'CP.NS'!C:C) -> 25333333 | E73: =SUMIF('CP.NS'!$B:$B,KQKD!$C73,'CP.NS'!D:D) -> 32166667 | F73: =SUMIF('CP.NS'!$B:$B,KQKD!$C73,'CP.NS'!E:E) -> 36500000 | G73: =SUMIF('CP.NS'!$B:$B,KQKD!$C73,'CP.NS'!F:F) -> 36500000 | H73: =D73*12 -> 304000000 | I73: =E73*12 -> 386000000 | J73: =F73*12 -> 438000000 | K73: =G73*12 -> 438000000
A74: -5 | C74: Chi phí lương ngoài giờ - Trực tiếp | D74: =SUMIF('CP.NS'!$B:$B,KQKD!$C74,'CP.NS'!C:C) -> 2160000 | E74: =SUMIF('CP.NS'!$B:$B,KQKD!$C74,'CP.NS'!D:D) -> 3840000 | F74: =SUMIF('CP.NS'!$B:$B,KQKD!$C74,'CP.NS'!E:E) -> 5040000 | G74: =SUMIF('CP.NS'!$B:$B,KQKD!$C74,'CP.NS'!F:F) -> 6000000 | H74: =D74*12 -> 25920000 | I74: =E74*12 -> 46080000 | J74: =F74*12 -> 60480000 | K74: =G74*12 -> 72000000
A75: -6 | C75: Chi phí lương ngoài giờ - Gián tiếp | D75: =SUMIF('CP.NS'!$B:$B,KQKD!$C75,'CP.NS'!C:C) -> 9120000 | E75: =SUMIF('CP.NS'!$B:$B,KQKD!$C75,'CP.NS'!D:D) -> 11580000 | F75: =SUMIF('CP.NS'!$B:$B,KQKD!$C75,'CP.NS'!E:E) -> 13140000 | G75: =SUMIF('CP.NS'!$B:$B,KQKD!$C75,'CP.NS'!F:F) -> 13140000 | H75: =D75*12 -> 109440000 | I75: =E75*12 -> 138960000 | J75: =F75*12 -> 157680000 | K75: =G75*12 -> 157680000
A76: -7 | C76: Chi phí lương Ca đêm | D76: =SUMIF('CP.NS'!$B:$B,KQKD!$C76,'CP.NS'!C:C) -> 0 | E76: =SUMIF('CP.NS'!$B:$B,KQKD!$C76,'CP.NS'!D:D) -> 0 | F76: =SUMIF('CP.NS'!$B:$B,KQKD!$C76,'CP.NS'!E:E) -> 0 | G76: =SUMIF('CP.NS'!$B:$B,KQKD!$C76,'CP.NS'!F:F) -> 0 | H76: =D76*12 -> 0 | I76: =E76*12 -> 0 | J76: =F76*12 -> 0 | K76: =G76*12 -> 0
A77: -8 | C77: Chi phí phụ cấp theo bảng lương | D77: =SUMIF('CP.NS'!$B:$B,KQKD!$C77,'CP.NS'!C:C) -> 18800000 | E77: =SUMIF('CP.NS'!$B:$B,KQKD!$C77,'CP.NS'!D:D) -> 25700000 | F77: =SUMIF('CP.NS'!$B:$B,KQKD!$C77,'CP.NS'!E:E) -> 30300000 | G77: =SUMIF('CP.NS'!$B:$B,KQKD!$C77,'CP.NS'!F:F) -> 31900000 | H77: =D77*12 -> 225600000 | I77: =E77*12 -> 308400000 | J77: =F77*12 -> 363600000 | K77: =G77*12 -> 382800000
A78: -9 | C78: Chi phí khen thưởng theo bảng lương | D78: =SUMIF('CP.NS'!$B:$B,KQKD!$C78,'CP.NS'!C:C) -> 0 | E78: =SUMIF('CP.NS'!$B:$B,KQKD!$C78,'CP.NS'!D:D) -> 0 | F78: =SUMIF('CP.NS'!$B:$B,KQKD!$C78,'CP.NS'!E:E) -> 0 | G78: =SUMIF('CP.NS'!$B:$B,KQKD!$C78,'CP.NS'!F:F) -> 0 | H78: =D78*12 -> 0 | I78: =E78*12 -> 0 | J78: =F78*12 -> 0 | K78: =G78*12 -> 0
A79: -10 | C79: Chi phí bảo hiểm theo lương (BHXH, BHYT, KPCĐ, BHTN) | D79: =SUMIF('CP.NS'!$B:$B,KQKD!$C79,'CP.NS'!C:C) -> 45120000 | E79: =SUMIF('CP.NS'!$B:$B,KQKD!$C79,'CP.NS'!D:D) -> 61680000 | F79: =SUMIF('CP.NS'!$B:$B,KQKD!$C79,'CP.NS'!E:E) -> 72720000 | G79: =SUMIF('CP.NS'!$B:$B,KQKD!$C79,'CP.NS'!F:F) -> 76560000 | H79: =D79*12 -> 541440000 | I79: =E79*12 -> 740160000 | J79: =F79*12 -> 872640000 | K79: =G79*12 -> 918720000
A80: -11 | C80: Chi phí thuế TNCN | D80: =SUMIF('CP.NS'!$B:$B,KQKD!$C80,'CP.NS'!C:C) -> 0 | E80: =SUMIF('CP.NS'!$B:$B,KQKD!$C80,'CP.NS'!D:D) -> 0 | F80: =SUMIF('CP.NS'!$B:$B,KQKD!$C80,'CP.NS'!E:E) -> 0 | G80: =SUMIF('CP.NS'!$B:$B,KQKD!$C80,'CP.NS'!F:F) -> 0 | H80: =D80*12 -> 0 | I80: =E80*12 -> 0 | J80: =F80*12 -> 0 | K80: =G80*12 -> 0
A81: 5.3.2 | B81: Chi phí phúc lợi | D81: =SUM(D83:D91) -> 18262500 | E81: =SUM(E83:E91) -> 18262500 | F81: =SUM(F83:F91) -> 31906500 | G81: =SUM(G83:G91) -> 31906500 | H81: =SUM(H83:H91) -> 219150000 | I81: =SUM(I83:I91) -> 219150000 | J81: =SUM(J83:J91) -> 382878000 | K81: =SUM(K83:K91) -> 382878000
C82: (%) Chi phí phúc lợi / Doanh thu | D82: =IFERROR(D81/D$5,0) -> 0.003461954 | E82: =IFERROR(E81/E$5,0) -> 0.0023079694 | F82: =IFERROR(F81/F$5,0) -> 0.0030241981 | G82: =IFERROR(G81/G$5,0) -> 0.0024193585 | H82: =IFERROR(H81/H$5,0) -> 0.003461954 | I82: =IFERROR(I81/I$5,0) -> 0.0023079694 | J82: =IFERROR(J81/J$5,0) -> 0.0030241981 | K82: =IFERROR(K81/K$5,0) -> 0.0024193585
A83: -1 | C83: Chi phí y tế, khám sức khỏe, bảo hiểm sức khỏe | D83: =SUMIF('CP.NS'!$B:$B,KQKD!$C83,'CP.NS'!C:C) -> 1875000 | E83: =SUMIF('CP.NS'!$B:$B,KQKD!$C83,'CP.NS'!D:D) -> 1875000 | F83: =SUMIF('CP.NS'!$B:$B,KQKD!$C83,'CP.NS'!E:E) -> 3675000 | G83: =SUMIF('CP.NS'!$B:$B,KQKD!$C83,'CP.NS'!F:F) -> 3675000 | H83: =D83*12 -> 22500000 | I83: =E83*12 -> 22500000 | J83: =F83*12 -> 44100000 | K83: =G83*12 -> 44100000
A84: -2 | C84: Chi phí khen thưởng ngoài lương | D84: =SUMIF('CP.NS'!$B:$B,KQKD!$C84,'CP.NS'!C:C) -> 0 | E84: =SUMIF('CP.NS'!$B:$B,KQKD!$C84,'CP.NS'!D:D) -> 0 | F84: =SUMIF('CP.NS'!$B:$B,KQKD!$C84,'CP.NS'!E:E) -> 0 | G84: =SUMIF('CP.NS'!$B:$B,KQKD!$C84,'CP.NS'!F:F) -> 0 | H84: =D84*12 -> 0 | I84: =E84*12 -> 0 | J84: =F84*12 -> 0 | K84: =G84*12 -> 0
A85: -3 | C85: Chi phí suất ăn, tiền ăn giữa ca | D85: =SUMIF('CP.NS'!$B:$B,KQKD!$C85,'CP.NS'!C:C) -> 1462500 | E85: =SUMIF('CP.NS'!$B:$B,KQKD!$C85,'CP.NS'!D:D) -> 1462500 | F85: =SUMIF('CP.NS'!$B:$B,KQKD!$C85,'CP.NS'!E:E) -> 2866500 | G85: =SUMIF('CP.NS'!$B:$B,KQKD!$C85,'CP.NS'!F:F) -> 2866500 | H85: =D85*12 -> 17550000 | I85: =E85*12 -> 17550000 | J85: =F85*12 -> 34398000 | K85: =G85*12 -> 34398000
A86: -4 | C86: Chi phí đồng phục, đồ bảo hộ lao động | D86: =SUMIF('CP.NS'!$B:$B,KQKD!$C86,'CP.NS'!C:C) -> 2850000 | E86: =SUMIF('CP.NS'!$B:$B,KQKD!$C86,'CP.NS'!D:D) -> 2850000 | F86: =SUMIF('CP.NS'!$B:$B,KQKD!$C86,'CP.NS'!E:E) -> 4290000 | G86: =SUMIF('CP.NS'!$B:$B,KQKD!$C86,'CP.NS'!F:F) -> 4290000 | H86: =D86*12 -> 34200000 | I86: =E86*12 -> 34200000 | J86: =F86*12 -> 51480000 | K86: =G86*12 -> 51480000
A87: -5 | C87: Chi phí tiệc tất niên, tổng kết | D87: =SUMIF('CP.NS'!$B:$B,KQKD!$C87,'CP.NS'!C:C) -> 1875000 | E87: =SUMIF('CP.NS'!$B:$B,KQKD!$C87,'CP.NS'!D:D) -> 1875000 | F87: =SUMIF('CP.NS'!$B:$B,KQKD!$C87,'CP.NS'!E:E) -> 3675000 | G87: =SUMIF('CP.NS'!$B:$B,KQKD!$C87,'CP.NS'!F:F) -> 3675000 | H87: =D87*12 -> 22500000 | I87: =E87*12 -> 22500000 | J87: =F87*12 -> 44100000 | K87: =G87*12 -> 44100000
A88: -6 | C88: Chi phí teambuilding | D88: =SUMIF('CP.NS'!$B:$B,KQKD!$C88,'CP.NS'!C:C) -> 7500000 | E88: =SUMIF('CP.NS'!$B:$B,KQKD!$C88,'CP.NS'!D:D) -> 7500000 | F88: =SUMIF('CP.NS'!$B:$B,KQKD!$C88,'CP.NS'!E:E) -> 14700000 | G88: =SUMIF('CP.NS'!$B:$B,KQKD!$C88,'CP.NS'!F:F) -> 14700000 | H88: =D88*12 -> 90000000 | I88: =E88*12 -> 90000000 | J88: =F88*12 -> 176400000 | K88: =G88*12 -> 176400000
A89: -7 | C89: Chi phí thuê xe đưa rước nhân viên | D89: =SUMIF('CP.NS'!$B:$B,KQKD!$C89,'CP.NS'!C:C) -> 0 | E89: =SUMIF('CP.NS'!$B:$B,KQKD!$C89,'CP.NS'!D:D) -> 0 | F89: =SUMIF('CP.NS'!$B:$B,KQKD!$C89,'CP.NS'!E:E) -> 0 | G89: =SUMIF('CP.NS'!$B:$B,KQKD!$C89,'CP.NS'!F:F) -> 0 | H89: =D89*12 -> 0 | I89: =E89*12 -> 0 | J89: =F89*12 -> 0 | K89: =G89*12 -> 0
A90: -8 | C90: Chi phí tuyển dụng, đào tạo | D90: =SUMIF('CP.NS'!$B:$B,KQKD!$C90,'CP.NS'!C:C) -> 1800000 | E90: =SUMIF('CP.NS'!$B:$B,KQKD!$C90,'CP.NS'!D:D) -> 1800000 | F90: =SUMIF('CP.NS'!$B:$B,KQKD!$C90,'CP.NS'!E:E) -> 1800000 | G90: =SUMIF('CP.NS'!$B:$B,KQKD!$C90,'CP.NS'!F:F) -> 1800000 | H90: =D90*12 -> 21600000 | I90: =E90*12 -> 21600000 | J90: =F90*12 -> 21600000 | K90: =G90*12 -> 21600000
A91: -9 | C91: Chi phí hiếu hỷ, phúc lợi khác | D91: =SUMIF('CP.NS'!$B:$B,KQKD!$C91,'CP.NS'!C:C) -> 900000 | E91: =SUMIF('CP.NS'!$B:$B,KQKD!$C91,'CP.NS'!D:D) -> 900000 | F91: =SUMIF('CP.NS'!$B:$B,KQKD!$C91,'CP.NS'!E:E) -> 900000 | G91: =SUMIF('CP.NS'!$B:$B,KQKD!$C91,'CP.NS'!F:F) -> 900000 | H91: =D91*12 -> 10800000 | I91: =E91*12 -> 10800000 | J91: =F91*12 -> 10800000 | K91: =G91*12 -> 10800000
A92: 5.4 | B92: Chi phí tài chính | D92: ='K.Hao, L.v'!C36 -> 90609191 | E92: ='K.Hao, L.v'!D36 -> 90609191 | F92: ='K.Hao, L.v'!E36 -> 90609191 | G92: ='K.Hao, L.v'!F36 -> 90609191 | H92: =D92*12 -> 1.0873103e+09 | I92: =E92*12 -> 1.0873103e+09 | J92: =F92*12 -> 1.0873103e+09 | K92: =G92*12 -> 1.0873103e+09
C93: (%) Doanh thu tài chính / Doanh thu | D93: =IFERROR(D92/D$5,0) -> 0.017176447 | E93: =IFERROR(E92/E$5,0) -> 0.011450964 | F93: =IFERROR(F92/F$5,0) -> 0.0085882233 | G93: =IFERROR(G92/G$5,0) -> 0.0068705786 | H93: =IFERROR(H92/H$5,0) -> 0.017176447 | I93: =IFERROR(I92/I$5,0) -> 0.011450964 | J93: =IFERROR(J92/J$5,0) -> 0.0085882233 | K93: =IFERROR(K92/K$5,0) -> 0.0068705786
C94: Chi phí lãi vay
A95: 5.5 | B95: Chi phí khấu hao | D95: ='K.Hao, L.v'!C24 -> 1.6078129e+08 | E95: ='K.Hao, L.v'!D24 -> 1.6078129e+08 | F95: ='K.Hao, L.v'!E24 -> 1.6078129e+08 | G95: ='K.Hao, L.v'!F24 -> 1.6078129e+08 | H95: =D95*12 -> 1.9293755e+09 | I95: =E95*12 -> 1.9293755e+09 | J95: =F95*12 -> 1.9293755e+09 | K95: =G95*12 -> 1.9293755e+09
C96: Tổng Chi phí Khấu hao / Doanh thu (%) | D96: =IFERROR(D95/D$5,0) -> 0.03047871 | E96: =IFERROR(E95/E$5,0) -> 0.02031914 | F96: =IFERROR(F95/F$5,0) -> 0.015239355 | G96: =IFERROR(G95/G$5,0) -> 0.012191484 | H96: =IFERROR(H95/H$5,0) -> 0.03047871 | I96: =IFERROR(I95/I$5,0) -> 0.02031914 | J96: =IFERROR(J95/J$5,0) -> 0.015239355 | K96: =IFERROR(K95/K$5,0) -> 0.012191484
A97: 6 | B97: TỔNG GIÁ VỐN (BIẾN PHÍ + ĐỊNH PHÍ) | D97: =D7+D31 -> 5.5173729e+09 | E97: =E7+E31 -> 7.798137e+09 | F97: =F7+F31 -> 1.0033512e+10 | G97: =G7+G31 -> 1.2179243e+10 | H97: =H7+H31 -> 6.6208475e+10 | I97: =I7+I31 -> 9.3577644e+10 | J97: =J7+J31 -> 1.2040214e+11 | K97: =K7+K31 -> 1.4615091e+11
C98: Giá vốn / Doanh thu (%) | D98: =IFERROR(D97/D$5,0) -> 1.0459078 | E98: =IFERROR(E97/E$5,0) -> 0.98550917 | F98: =IFERROR(F97/F$5,0) -> 0.95100771 | G98: =IFERROR(G97/G$5,0) -> 0.92350944 | H98: =IFERROR(H97/H$5,0) -> 1.0459078 | I98: =IFERROR(I97/I$5,0) -> 0.98550917 | J98: =IFERROR(J97/J$5,0) -> 0.95100771 | K98: =IFERROR(K97/K$5,0) -> 0.92350944
C99: Giá vốn / Tấn (Triệu đồng/Tấn) | D99: =IFERROR(D97/D$4,0)*1000 -> 14927957 | E99: =IFERROR(E97/E$4,0)*1000 -> 14065904 | F99: =IFERROR(F97/F$4,0)*1000 -> 13573474 | G99: =IFERROR(G97/G$4,0)*1000 -> 13180998 | H99: =IFERROR(H97/H$4,0)*1000 -> 14927957 | I99: =IFERROR(I97/I$4,0)*1000 -> 14065904 | J99: =IFERROR(J97/J$4,0)*1000 -> 13573474 | K99: =IFERROR(K97/K$4,0)*1000 -> 13180998
A100: 7 | B100: LỢI NHUẬN TRƯỚC THUẾ | D100: =D28-D31 -> -2.4217289e+08 | E100: =E28-E31 -> 1.1466301e+08 | F100: =F28-F31 -> 5.1688825e+08 | G100: =G28-G31 -> 1.0087575e+09 | H100: =H28-H31 -> -2.9060747e+09 | I100: =I28-I31 -> 1.3759561e+09 | J100: =J28-J31 -> 6.202659e+09 | K100: =K28-K31 -> 1.210509e+10
C101: Tỷ lệ Lợi nhuận trước thuế (%) | D101: =IFERROR(D100/D$5,0) -> -0.045907813 | E101: =IFERROR(E100/E$5,0) -> 0.014490827 | F101: =IFERROR(F100/F$5,0) -> 0.04899229 | G101: =IFERROR(G100/G$5,0) -> 0.076490559 | H101: =IFERROR(H100/H$5,0) -> -0.045907813 | I101: =IFERROR(I100/I$5,0) -> 0.014490827 | J101: =IFERROR(J100/J$5,0) -> 0.04899229 | K101: =IFERROR(K100/K$5,0) -> 0.076490559
B102: Thuế TNDN | D102: =IF(D100>0,D100*20%,0) -> 0 | E102: =IF(E100>0,E100*20%,0) -> 22932602 | F102: =IF(F100>0,F100*20%,0) -> 1.0337765e+08 | G102: =IF(G100>0,G100*20%,0) -> 2.017515e+08 | H102: =IF(H100>0,H100*20%,0) -> 0 | I102: =IF(I100>0,I100*20%,0) -> 2.7519123e+08 | J102: =IF(J100>0,J100*20%,0) -> 1.2405318e+09 | K102: =IF(K100>0,K100*20%,0) -> 2.421018e+09
A103: 8 | B103: LỢI NHUẬN SAU THUẾ | D103: =D100-D102 -> -2.4217289e+08 | E103: =E100-E102 -> 91730410 | F103: =F100-F102 -> 4.135106e+08 | G103: =G100-G102 -> 8.0700599e+08 | H103: =H100-H102 -> -2.9060747e+09 | I103: =I100-I102 -> 1.1007649e+09 | J103: =J100-J102 -> 4.9621272e+09 | K103: =K100-K102 -> 9.6840719e+09
C104: Tỷ lệ LNST (%) | D104: =IFERROR(D103/D$5,0) -> -0.045907813 | E104: =IFERROR(E103/E$5,0) -> 0.011592661 | F104: =IFERROR(F103/F$5,0) -> 0.039193832 | G104: =IFERROR(G103/G$5,0) -> 0.061192447 | H104: =IFERROR(H103/H$5,0) -> -0.045907813 | I104: =IFERROR(I103/I$5,0) -> 0.011592661 | J104: =IFERROR(J103/J$5,0) -> 0.039193832 | K104: =IFERROR(K103/K$5,0) -> 0.061192447
...

Sheet HV
B1: ĐÁNH GIÁ HIỆU QUẢ ĐẦU TƯ
B2: 1 - Sản lượng HÒA VỐN
B3: Chỉ tiêu | C3: ĐVT | D3: Bình quân 1 tháng | H3: Cả năm
D4: H.S 40% | E4: H.S 60% | F4: H.S 80% | G4: H.S 100% | H4: H.S 40% | I4: H.S 60% | J4: H.S 80% | K4: H.S 100%
B5: SL NVL kế hoạch | C5: Tấn | D5: =S.Lượng!C7 -> 400000 | E5: =S.Lượng!D7 -> 600000 | F5: =S.Lượng!E7 -> 800000 | G5: =S.Lượng!F7 -> 1000000 | H5: =D5*12 -> 4800000 | I5: =E5*12 -> 7200000 | J5: =F5*12 -> 9600000 | K5: =G5*12 -> 12000000
B6: SL NVL HÒA VỐN | C6: Tấn | D6: =D8*(1+(S.Lượng!C7-S.Lượng!C18)/S.Lượng!C7) -> 486713.02 | E6: =E8*(1+(S.Lượng!D7-S.Lượng!D18)/S.Lượng!D7) -> 562814.05 | F6: =F8*(1+(S.Lượng!E7-S.Lượng!E18)/S.Lượng!E7) -> 643371.58 | G6: =G8*(1+(S.Lượng!F7-S.Lượng!F18)/S.Lượng!F7) -> 697566.4 | H6: =D6*12 -> 5840556.2 | I6: =E6*12 -> 6753768.6 | J6: =F6*12 -> 7720458.9 | K6: =G6*12 -> 8370796.8
B7: SL Thành phẩm kế hoạch | C7: Tấn | D7: =KQKD!D4 -> 369600 | E7: =KQKD!E4 -> 554400 | F7: =KQKD!F4 -> 739200 | G7: =KQKD!G4 -> 924000 | H7: =D7*12 -> 4435200 | I7: =E7*12 -> 6652800 | J7: =F7*12 -> 8870400 | K7: =G7*12 -> 11088000
B8: SL Thành phẩm HÒA VỐN | C8: Tấn | D8: =(KQKD!D31+KQKD!D102)/(KQKD!D6-KQKD!D9)*1000 -> 452335.52 | E8: =(KQKD!E31+KQKD!E102)/(KQKD!E6-KQKD!E9)*1000 -> 523061.39 | F8: =(KQKD!F31+KQKD!F102)/(KQKD!F6-KQKD!F9)*1000 -> 597928.97 | G8: =(KQKD!G31+KQKD!G102)/(KQKD!G6-KQKD!G9)*1000 -> 648295.91 | H8: =D8*12 -> 5428026.2 | I8: =E8*12 -> 6276736.6 | J8: =F8*12 -> 7175147.7 | K8: =G8*12 -> 7779550.9
B9: Doanh thu HÒA VỐN | C9: Triệu đồng | D9: =D8*KQKD!D6/1000 -> 6.4560615e+09 | E9: =E8*KQKD!E6/1000 -> 7.4655125e+09 | F9: =F8*KQKD!F6/1000 -> 8.5340772e+09 | G9: =G8*KQKD!G6/1000 -> 9.2529507e+09 | H9: =D9*12 -> 7.7472738e+10 | I9: =E9*12 -> 8.958615e+10 | J9: =F9*12 -> 1.0240893e+11 | K9: =G9*12 -> 1.1103541e+11
B11: 2 - Dòng tiền | K11: ĐVT: Triệu đồng
B12: Chỉ tiêu | C12: Năm 0 | D12: Năm 1 | E12: Năm 2 | F12: Năm 3 | G12: Năm 4 | H12: Năm 5 | I12: Năm 6 | J12: Năm 7 | K12: Năm 8
B13: 500T | C13: (Đầu tư)
B14: 1 - Lợi nhuận sau thuế | D14: =D39 -> -2.9060747e+09 | E14: =E39 -> -2.7701609e+09 | F14: =F39 -> -2.6342472e+09 | G14: =G39 -> -2.4983334e+09 | H14: =H39 -> -2.3624196e+09 | I14: =I39 -> -2.2265058e+09 | J14: =J39 -> -2.090592e+09 | K14: =K39 -> -1.9546782e+09
B15: 2 - Khấu hao | D15: =D40 -> 1.9293755e+09 | E15: =E40 -> 1.9293755e+09 | F15: =F40 -> 1.9293755e+09 | G15: =G40 -> 1.9293755e+09 | H15: =H40 -> 1.9293755e+09 | I15: =I40 -> 1.9293755e+09 | J15: =J40 -> 1.9293755e+09 | K15: =K40 -> 1.9293755e+09
B16: 3 - Dòng tiền (chưa chiết khấu) | C16: =-C38 -> -22190006000 | D16: =D41 -> -9.7669923e+08 | E16: =E41 -> -8.4078544e+08 | F16: =F41 -> -7.0487165e+08 | G16: =G41 -> -5.6895787e+08 | H16: =H41 -> -4.3304408e+08 | I16: =I41 -> -2.9713029e+08 | J16: =J41 -> -1.6121651e+08 | K16: =K41 -> -25302719
B17: 1.000T
B18: 1 - Lợi nhuận sau thuế | D18: =D50 -> 1.1007649e+09 | E18: =E50 -> 1.2366787e+09 | F18: =F50 -> 1.3725925e+09 | G18: =G50 -> 1.5085063e+09 | H18: =H50 -> 1.6444201e+09 | I18: =I50 -> 1.7803339e+09 | J18: =J50 -> 1.9162476e+09 | K18: =K50 -> 2.0521614e+09
B19: 2 - Khấu hao | D19: =D51 -> 1.9293755e+09 | E19: =E51 -> 1.9293755e+09 | F19: =F51 -> 1.9293755e+09 | G19: =G51 -> 1.9293755e+09 | H19: =H51 -> 1.9293755e+09 | I19: =I51 -> 1.9293755e+09 | J19: =J51 -> 1.9293755e+09 | K19: =K51 -> 1.9293755e+09
B20: 3 - Dòng tiền (chưa chiết khấu) | C20: =-C49 -> -22190006000 | D20: =D52 -> 3.0301404e+09 | E20: =E52 -> 3.1660542e+09 | F20: =F52 -> 3.301968e+09 | G20: =G52 -> 3.4378818e+09 | H20: =H52 -> 3.5737956e+09 | I20: =I52 -> 3.7097094e+09 | J20: =J52 -> 3.8456231e+09 | K20: =K52 -> 3.9815369e+09
B21: 1.500T
B22: 1 - Lợi nhuận sau thuế | D22: =D61 -> 4.9621272e+09 | E22: =E61 -> 5.098041e+09 | F22: =F61 -> 5.2339548e+09 | G22: =G61 -> 5.3698686e+09 | H22: =H61 -> 5.5057824e+09 | I22: =I61 -> 5.6416962e+09 | J22: =J61 -> 5.7776099e+09 | K22: =K61 -> 5.9135237e+09
B23: 2 - Khấu hao | D23: =D62 -> 1.9293755e+09 | E23: =E62 -> 1.9293755e+09 | F23: =F62 -> 1.9293755e+09 | G23: =G62 -> 1.9293755e+09 | H23: =H62 -> 1.9293755e+09 | I23: =I62 -> 1.9293755e+09 | J23: =J62 -> 1.9293755e+09 | K23: =K62 -> 1.9293755e+09
B24: 3 - Dòng tiền (chưa chiết khấu) | C24: =-C60 -> -22190006000 | D24: =D63 -> 6.8915027e+09 | E24: =E63 -> 7.0274165e+09 | F24: =F63 -> 7.1633303e+09 | G24: =G63 -> 7.2992441e+09 | H24: =H63 -> 7.4351579e+09 | I24: =I63 -> 7.5710717e+09 | J24: =J63 -> 7.7069854e+09 | K24: =K63 -> 7.8428992e+09
B25: 2.000T
B26: 1 - Lợi nhuận sau thuế | D26: =D72 -> 9.6840719e+09 | E26: =E72 -> 9.8199857e+09 | F26: =F72 -> 9.9558995e+09 | G26: =G72 -> 1.0091813e+10 | H26: =H72 -> 1.0227727e+10 | I26: =I72 -> 1.0363641e+10 | J26: =J72 -> 1.0499555e+10 | K26: =K72 -> 1.0635468e+10
B27: 2 - Khấu hao | D27: =D73 -> 1.9293755e+09 | E27: =E73 -> 1.9293755e+09 | F27: =F73 -> 1.9293755e+09 | G27: =G73 -> 1.9293755e+09 | H27: =H73 -> 1.9293755e+09 | I27: =I73 -> 1.9293755e+09 | J27: =J73 -> 1.9293755e+09 | K27: =K73 -> 1.9293755e+09
B28: 3 - Dòng tiền (chưa chiết khấu) | C28: =-C71 -> -22190006000 | D28: =D74 -> 1.1613447e+10 | E28: =E74 -> 1.1749361e+10 | F28: =F74 -> 1.1885275e+10 | G28: =G74 -> 1.2021189e+10 | H28: =H74 -> 1.2157103e+10 | I28: =I74 -> 1.2293016e+10 | J28: =J74 -> 1.242893e+10 | K28: =K74 -> 1.2564844e+10
B30: 3 - NPV, IRR, thời gian hoàn vốn
B31: Chỉ tiêu | C31: H.S 40% | D31: H.S 60% | E31: H.S 80% | F31: H.S 100%
B32: NPV (Triệu đồng) | C32: =C44 -> -2.2966054e+10 | D32: =C55 -> 1.1981478e+10 | E32: =C66 -> 4.5660161e+10 | F32: =C77 -> 8.6844817e+10
B33: IRR | C33: =C45 -> -0.18098752 | D33: =C56 -> 0.15300925 | E33: =C67 -> 0.3261148 | F33: =C78 -> 0.53434391
B34: Thời gian hoàn vốn (năm) | C34: =C46 -> #N/A | D34: =C57 -> 9.422813 | E34: =C68 -> 3.8089478 | F34: =C79 -> 2.1618268
B36: Chi tiết tính toán:
B37: 500T | C37: Năm 0 | D37: Năm 1 | E37: Năm 2 | F37: Năm 3 | G37: Năm 4 | H37: Năm 5 | I37: Năm 6 | J37: Năm 7 | K37: Năm 8 | L37: Năm 9 | M37: Năm 10 | N37: Năm 11 | O37: Năm 12 | P37: Năm 13 | Q37: Năm 14 | R37: Năm 15 | S37: Năm 16 | T37: Năm 17 | U37: Năm 18 | V37: Năm 19 | W37: Năm 20
B38: Đầu tư | C38: ='K.Hao, L.v'!C12 -> 22190006000
B39: Dòng tiền thuần từ HĐKD | D39: =KQKD!$H$103 -> -2.9060747e+09 | E39: =KQKD!$H$103+KQKD!$H$92-($C$38*G.Định!$D$78-($C$38*G.Định!$D$78/G.Định!$D$80*COLUMNS($E$38:E$38)))*G.Định!$D$81 -> -2.7701609e+09 | F39: =KQKD!$H$103+KQKD!$H$92-($C$38*G.Định!$D$78-($C$38*G.Định!$D$78/G.Định!$D$80*COLUMNS($E$38:F$38)))*G.Định!$D$81 -> -2.6342472e+09 | G39: =KQKD!$H$103+KQKD!$H$92-($C$38*G.Định!$D$78-($C$38*G.Định!$D$78/G.Định!$D$80*COLUMNS($E$38:G$38)))*G.Định!$D$81 -> -2.4983334e+09 | H39: =KQKD!$H$103+KQKD!$H$92-($C$38*G.Định!$D$78-($C$38*G.Định!$D$78/G.Định!$D$80*COLUMNS($E$38:H$38)))*G.Định!$D$81 -> -2.3624196e+09 | I39: =KQKD!$H$103+KQKD!$H$92-($C$38*G.Định!$D$78-($C$38*G.Định!$D$78/G.Định!$D$80*COLUMNS($E$38:I$38)))*G.Định!$D$81 -> -2.2265058e+09 | J39: =KQKD!$H$103+KQKD!$H$92-($C$38*G.Định!$D$78-($C$38*G.Định!$D$78/G.Định!$D$80*COLUMNS($E$38:J$38)))*G.Định!$D$81 -> -2.090592e+09 | K39: =KQKD!$H$103+KQKD!$H$92-($C$38*G.Định!$D$78-($C$38*G.Định!$D$78/G.Định!$D$80*COLUMNS($E$38:K$38)))*G.Định!$D$81 -> -1.9546782e+09 | L39: =KQKD!$H$103+KQKD!$H$92 -> -1.8187644e+09 | M39: =KQKD!$H$103+KQKD!$H$92 -> -1.8187644e+09 | N39: =KQKD!$H$103+KQKD!$H$92 -> -1.8187644e+09 | O39: =KQKD!$H$103+KQKD!$H$92 -> -1.8187644e+09 | P39: =KQKD!$H$103+KQKD!$H$92 -> -1.8187644e+09 | Q39: =KQKD!$H$103+KQKD!$H$92 -> -1.8187644e+09 | R39: =KQKD!$H$103+KQKD!$H$92 -> -1.8187644e+09 | S39: =KQKD!$H$103+KQKD!$H$92 -> -1.8187644e+09 | ... W39: =KQKD!$H$103+KQKD!$H$92 -> -1.8187644e+09
B40: Khấu hao | D40: =KQKD!$H$95 -> 1.9293755e+09 | E40: =KQKD!$H$95 -> 1.9293755e+09 | F40: =KQKD!$H$95 -> 1.9293755e+09 | G40: =KQKD!$H$95 -> 1.9293755e+09 | H40: =KQKD!$H$95 -> 1.9293755e+09 | I40: =KQKD!$H$95 -> 1.9293755e+09 | J40: =KQKD!$H$95 -> 1.9293755e+09 | K40: =KQKD!$H$95 -> 1.9293755e+09 | ... W40: =KQKD!$H$95 -> 1.9293755e+09
B41: Tổng dòng tiền | C41: =-C38 -> -22190006000 | D41: =D39+D40 -> -9.7669923e+08 | E41: =E39+E40 -> -8.4078544e+08 | F41: =F39+F40 -> -7.0487165e+08 | G41: =G39+G40 -> -5.6895787e+08 | H41: =H39+H40 -> -4.3304408e+08 | I41: =I39+I40 -> -2.9713029e+08 | J41: =J39+J40 -> -1.6121651e+08 | K41: =K39+K40 -> -25302719 | ... W41: =W39+W40 -> 1.1061107e+08
B42: Tổng dòng tiền chiết khấu | C42: =C41 -> -22190006000 | D42: =D41/(1+G.Định!$D$87)^COLUMNS($D$41:D$41) -> -9.0018362e+08 | E42: =E41/(1+G.Định!$D$87)^COLUMNS($D$41:E$41) -> -7.1420964e+08 | F42: =F41/(1+G.Định!$D$87)^COLUMNS($D$41:F$41) -> -5.5184973e+08 | G42: =G41/(1+G.Định!$D$87)^COLUMNS($D$41:G$41) -> -4.1054537e+08 | H42: =H41/(1+G.Định!$D$87)^COLUMNS($D$41:H$41) -> -2.8799398e+08 | I42: =I41/(1+G.Định!$D$87)^COLUMNS($D$41:I$41) -> -1.8212455e+08 | J42: =J41/(1+G.Định!$D$87)^COLUMNS($D$41:J$41) -> -91075452 | K42: =K41/(1+G.Định!$D$87)^COLUMNS($D$41:K$41) -> -13174353 | ... W42: =W41/(1+G.Định!$D$87)^COLUMNS($D$41:W$41) -> 21637338
B43: Tổng dòng tiền chiết khấu lũy kế | C43: =C42 -> -22190006000 | D43: =C43+D42 -> -2.309019e+10 | E43: =D43+E42 -> -2.3804399e+10 | F43: =E43+F42 -> -2.4356249e+10 | G43: =F43+G42 -> -2.4766794e+10 | H43: =G43+H42 -> -2.5054788e+10 | I43: =H43+I42 -> -2.5236913e+10 | J43: =I43+J42 -> -2.5327988e+10 | K43: =J43+K42 -> -2.5341163e+10 | ... W43: =V43+W42 -> -2.4918169e+10
B44: NPV | C44: =NPV(G.Định!$D$87,HV!C41:W41) -> -2.2966054e+10
B45: IRR | C45: =IRR(C41:W41) -> -0.18098752
B46: Thời gian hoàn vốn (năm) | C46: {=COUNTIF(D43:W43,"<0")-_xlfn.MAXIFS(D43:W43,D43:W43,"<0")/INDEX(D42:W42,MATCH(TRUE,INDEX(D43:W43>0,),0))} -> #N/A
B48: 1.000T | C48: Năm 0 | D48: Năm 1 | E48: Năm 2 | F48: Năm 3 | G48: Năm 4 | H48: Năm 5 | I48: Năm 6 | J48: Năm 7 | K48: Năm 8 | L48: Năm 9 | M48: Năm 10 | N48: Năm 11 | O48: Năm 12 | P48: Năm 13 | Q48: Năm 14 | R48: Năm 15 | S48: Năm 16 | T48: Năm 17 | U48: Năm 18 | V48: Năm 19 | W48: Năm 20
B49: Đầu tư | C49: ='K.Hao, L.v'!D12 -> 22190006000
B50: Dòng tiền thuần từ HĐKD | D50: =KQKD!$I$103 -> 1.1007649e+09 | E50: =KQKD!$I$103+KQKD!$I$92-($C$49*G.Định!$D$78-($C$49*G.Định!$D$78/G.Định!$D$80*COLUMNS($E$38:E$38)))*G.Định!$D$81 -> 1.2366787e+09 | F50: =KQKD!$I$103+KQKD!$I$92-($C$49*G.Định!$D$78-($C$49*G.Định!$D$78/G.Định!$D$80*COLUMNS($E$38:F$38)))*G.Định!$D$81 -> 1.3725925e+09 | G50: =KQKD!$I$103+KQKD!$I$92-($C$49*G.Định!$D$78-($C$49*G.Định!$D$78/G.Định!$D$80*COLUMNS($E$38:G$38)))*G.Định!$D$81 -> 1.5085063e+09 | H50: =KQKD!$I$103+KQKD!$I$92-($C$49*G.Định!$D$78-($C$49*G.Định!$D$78/G.Định!$D$80*COLUMNS($E$38:H$38)))*G.Định!$D$81 -> 1.6444201e+09 | I50: =KQKD!$I$103+KQKD!$I$92-($C$49*G.Định!$D$78-($C$49*G.Định!$D$78/G.Định!$D$80*COLUMNS($E$38:I$38)))*G.Định!$D$81 -> 1.7803339e+09 | J50: =KQKD!$I$103+KQKD!$I$92-($C$49*G.Định!$D$78-($C$49*G.Định!$D$78/G.Định!$D$80*COLUMNS($E$38:J$38)))*G.Định!$D$81 -> 1.9162476e+09 | K50: =KQKD!$I$103+KQKD!$I$92-($C$49*G.Định!$D$78-($C$49*G.Định!$D$78/G.Định!$D$80*COLUMNS($E$38:K$38)))*G.Định!$D$81 -> 2.0521614e+09 | L50: =KQKD!$I$103+KQKD!$I$92 -> 2.1880752e+09 | M50: =KQKD!$I$103+KQKD!$I$92 -> 2.1880752e+09 | N50: =KQKD!$I$103+KQKD!$I$92 -> 2.1880752e+09 | O50: =KQKD!$I$103+KQKD!$I$92 -> 2.1880752e+09 | P50: =KQKD!$I$103+KQKD!$I$92 -> 2.1880752e+09 | Q50: =KQKD!$I$103+KQKD!$I$92 -> 2.1880752e+09 | R50: =KQKD!$I$103+KQKD!$I$92 -> 2.1880752e+09 | S50: =KQKD!$I$103+KQKD!$I$92 -> 2.1880752e+09 | ... W50: =KQKD!$I$103+KQKD!$I$92 -> 2.1880752e+09
B51: Khấu hao | D51: =KQKD!$I$95 -> 1.9293755e+09 | E51: =KQKD!$I$95 -> 1.9293755e+09 | F51: =KQKD!$I$95 -> 1.9293755e+09 | G51: =KQKD!$I$95 -> 1.9293755e+09 | H51: =KQKD!$I$95 -> 1.9293755e+09 | I51: =KQKD!$I$95 -> 1.9293755e+09 | J51: =KQKD!$I$95 -> 1.9293755e+09 | K51: =KQKD!$I$95 -> 1.9293755e+09 | ... W51: =KQKD!$I$95 -> 1.9293755e+09
B52: Tổng dòng tiền | C52: =-C49 -> -22190006000 | D52: =D50+D51 -> 3.0301404e+09 | E52: =E50+E51 -> 3.1660542e+09 | F52: =F50+F51 -> 3.301968e+09 | G52: =G50+G51 -> 3.4378818e+09 | H52: =H50+H51 -> 3.5737956e+09 | I52: =I50+I51 -> 3.7097094e+09 | J52: =J50+J51 -> 3.8456231e+09 | K52: =K50+K51 -> 3.9815369e+09 | ... W52: =W50+W51 -> 4.1174507e+09
B53: Tổng dòng tiền chiết khấu | C53: =C52 -> -22190006000 | D53: =D52/(1+G.Định!$D$87)^COLUMNS($D$41:D$41) -> 2.7927561e+09 | E53: =E52/(1+G.Định!$D$87)^COLUMNS($D$41:E$41) -> 2.6894215e+09 | F53: =F52/(1+G.Định!$D$87)^COLUMNS($D$41:F$41) -> 2.5851375e+09 | G53: =G52/(1+G.Định!$D$87)^COLUMNS($D$41:G$41) -> 2.4806871e+09 | H53: =H52/(1+G.Định!$D$87)^COLUMNS($D$41:H$41) -> 2.3767364e+09 | I53: =I52/(1+G.Định!$D$87)^COLUMNS($D$41:I$41) -> 2.2738481e+09 | J53: =J52/(1+G.Định!$D$87)^COLUMNS($D$41:J$41) -> 2.1724938e+09 | K53: =K52/(1+G.Định!$D$87)^COLUMNS($D$41:K$41) -> 2.0730646e+09 | ... W53: =W52/(1+G.Định!$D$87)^COLUMNS($D$41:W$41) -> 8.0544084e+08
B54: Tổng dòng tiền chiết khấu lũy kế | C54: =C53 -> -22190006000 | D54: =C54+D53 -> -1.939725e+10 | E54: =D54+E53 -> -1.6707828e+10 | F54: =E54+F53 -> -1.4122691e+10 | G54: =F54+G53 -> -1.1642004e+10 | H54: =G54+H53 -> -9.2652674e+09 | I54: =H54+I53 -> -6.9914193e+09 | J54: =I54+J53 -> -4.8189254e+09 | K54: =J54+K53 -> -2.7458608e+09 | ... W54: =V54+W53 -> 1.2999903e+10
B55: NPV | C55: =NPV(G.Định!$D$87,HV!C52:W52) -> 1.1981478e+10
B56: IRR | C56: =IRR(C52:W52) -> 0.15300925
B57: Thời gian hoàn vốn (năm) | C57: {=COUNTIF(D54:W54,"<0")-_xlfn.MAXIFS(D54:W54,D54:W54,"<0")/INDEX(D53:W53,MATCH(TRUE,INDEX(D54:W54>0,),0))} -> 9.422813
B59: 1.500T | C59: Năm 0 | D59: Năm 1 | E59: Năm 2 | F59: Năm 3 | G59: Năm 4 | H59: Năm 5 | I59: Năm 6 | J59: Năm 7 | K59: Năm 8 | L59: Năm 9 | M59: Năm 10 | N59: Năm 11 | O59: Năm 12 | P59: Năm 13 | Q59: Năm 14 | R59: Năm 15 | S59: Năm 16 | T59: Năm 17 | U59: Năm 18 | V59: Năm 19 | W59: Năm 20
B60: Đầu tư | C60: ='K.Hao, L.v'!E12 -> 22190006000
B61: Dòng tiền thuần từ HĐKD | D61: =KQKD!$J$103 -> 4.9621272e+09 | E61: =KQKD!$J$103+KQKD!$J$92-($C$60*G.Định!$D$78-($C$60*G.Định!$D$78/G.Định!$D$80*COLUMNS($E$38:E$38)))*G.Định!$D$81 -> 5.098041e+09 | F61: =KQKD!$J$103+KQKD!$J$92-($C$60*G.Định!$D$78-($C$60*G.Định!$D$78/G.Định!$D$80*COLUMNS($E$38:F$38)))*G.Định!$D$81 -> 5.2339548e+09 | G61: =KQKD!$J$103+KQKD!$J$92-($C$60*G.Định!$D$78-($C$60*G.Định!$D$78/G.Định!$D$80*COLUMNS($E$38:G$38)))*G.Định!$D$81 -> 5.3698686e+09 | H61: =KQKD!$J$103+KQKD!$J$92-($C$60*G.Định!$D$78-($C$60*G.Định!$D$78/G.Định!$D$80*COLUMNS($E$38:H$38)))*G.Định!$D$81 -> 5.5057824e+09 | I61: =KQKD!$J$103+KQKD!$J$92-($C$60*G.Định!$D$78-($C$60*G.Định!$D$78/G.Định!$D$80*COLUMNS($E$38:I$38)))*G.Định!$D$81 -> 5.6416962e+09 | J61: =KQKD!$J$103+KQKD!$J$92-($C$60*G.Định!$D$78-($C$60*G.Định!$D$78/G.Định!$D$80*COLUMNS($E$38:J$38)))*G.Định!$D$81 -> 5.7776099e+09 | K61: =KQKD!$J$103+KQKD!$J$92-($C$60*G.Định!$D$78-($C$60*G.Định!$D$78/G.Định!$D$80*COLUMNS($E$38:K$38)))*G.Định!$D$81 -> 5.9135237e+09 | L61: =KQKD!$J$103+KQKD!$J$92 -> 6.0494375e+09 | M61: =KQKD!$J$103+KQKD!$J$92 -> 6.0494375e+09 | N61: =KQKD!$J$103+KQKD!$J$92 -> 6.0494375e+09 | O61: =KQKD!$J$103+KQKD!$J$92 -> 6.0494375e+09 | P61: =KQKD!$J$103+KQKD!$J$92 -> 6.0494375e+09 | Q61: =KQKD!$J$103+KQKD!$J$92 -> 6.0494375e+09 | R61: =KQKD!$J$103+KQKD!$J$92 -> 6.0494375e+09 | S61: =KQKD!$J$103+KQKD!$J$92 -> 6.0494375e+09 | ... W61: =KQKD!$J$103+KQKD!$J$92 -> 6.0494375e+09
B62: Khấu hao | D62: =KQKD!$J$95 -> 1.9293755e+09 | E62: =KQKD!$J$95 -> 1.9293755e+09 | F62: =KQKD!$J$95 -> 1.9293755e+09 | G62: =KQKD!$J$95 -> 1.9293755e+09 | H62: =KQKD!$J$95 -> 1.9293755e+09 | I62: =KQKD!$J$95 -> 1.9293755e+09 | J62: =KQKD!$J$95 -> 1.9293755e+09 | K62: =KQKD!$J$95 -> 1.9293755e+09 | ... W62: =KQKD!$J$95 -> 1.9293755e+09
B63: Tổng dòng tiền | C63: =-C60 -> -22190006000 | D63: =D61+D62 -> 6.8915027e+09 | E63: =E61+E62 -> 7.0274165e+09 | F63: =F61+F62 -> 7.1633303e+09 | G63: =G61+G62 -> 7.2992441e+09 | H63: =H61+H62 -> 7.4351579e+09 | I63: =I61+I62 -> 7.5710717e+09 | J63: =J61+J62 -> 7.7069854e+09 | K63: =K61+K62 -> 7.8428992e+09 | ... W63: =W61+W62 -> 7.978813e+09
B64: Tổng dòng tiền chiết khấu | C64: =C63 -> -22190006000 | D64: =D63/(1+G.Định!$D$87)^COLUMNS($D$41:D$41) -> 6.3516154e+09 | E64: =E63/(1+G.Định!$D$87)^COLUMNS($D$41:E$41) -> 5.9694761e+09 | F64: =F63/(1+G.Định!$D$87)^COLUMNS($D$41:F$41) -> 5.6082293e+09 | G64: =G63/(1+G.Định!$D$87)^COLUMNS($D$41:G$41) -> 5.2669468e+09 | H64: =H63/(1+G.Định!$D$87)^COLUMNS($D$41:H$41) -> 4.9447177e+09 | I64: =I63/(1+G.Định!$D$87)^COLUMNS($D$41:I$41) -> 4.6406512e+09 | J64: =J63/(1+G.Định!$D$87)^COLUMNS($D$41:J$41) -> 4.3538792e+09 | K64: =K63/(1+G.Định!$D$87)^COLUMNS($D$41:K$41) -> 4.083558e+09 | ... W64: =W63/(1+G.Định!$D$87)^COLUMNS($D$41:W$41) -> 1.5607866e+09
B65: Tổng dòng tiền chiết khấu lũy kế | C65: =C64 -> -22190006000 | D65: =C65+D64 -> -1.5838391e+10 | E65: =D65+E64 -> -9.8689145e+09 | F65: =E65+F64 -> -4.2606852e+09 | G65: =F65+G64 -> 1.0062616e+09 | H65: =G65+H64 -> 5.9509793e+09 | I65: =H65+I64 -> 1.0591631e+10 | J65: =I65+J64 -> 1.494551e+10 | K65: =J65+K64 -> 1.9029068e+10 | ... W65: =V65+W64 -> 4.9541275e+10
B66: NPV | C66: =NPV(G.Định!$D$87,HV!C63:W63) -> 4.5660161e+10
B67: IRR | C67: =IRR(C63:W63) -> 0.3261148
B68: Thời gian hoàn vốn (năm) | C68: {=COUNTIF(D65:W65,"<0")-_xlfn.MAXIFS(D65:W65,D65:W65,"<0")/INDEX(D64:W64,MATCH(TRUE,INDEX(D65:W65>0,),0))} -> 3.8089478
B70: 2.000T | C70: Năm 0 | D70: Năm 1 | E70: Năm 2 | F70: Năm 3 | G70: Năm 4 | H70: Năm 5 | I70: Năm 6 | J70: Năm 7 | K70: Năm 8 | L70: Năm 9 | M70: Năm 10 | N70: Năm 11 | O70: Năm 12 | P70: Năm 13 | Q70: Năm 14 | R70: Năm 15 | S70: Năm 16 | T70: Năm 17 | U70: Năm 18 | V70: Năm 19 | W70: Năm 20
B71: Đầu tư | C71: ='K.Hao, L.v'!F12 -> 22190006000
B72: Dòng tiền thuần từ HĐKD | D72: =KQKD!$K$103 -> 9.6840719e+09 | E72: =KQKD!$K$103+KQKD!$K$92-($C$71*G.Định!$D$78-($C$71*G.Định!$D$78/G.Định!$D$80*COLUMNS($E$38:E$38)))*G.Định!$D$81 -> 9.8199857e+09 | F72: =KQKD!$K$103+KQKD!$K$92-($C$71*G.Định!$D$78-($C$71*G.Định!$D$78/G.Định!$D$80*COLUMNS($E$38:F$38)))*G.Định!$D$81 -> 9.9558995e+09 | G72: =KQKD!$K$103+KQKD!$K$92-($C$71*G.Định!$D$78-($C$71*G.Định!$D$78/G.Định!$D$80*COLUMNS($E$38:G$38)))*G.Định!$D$81 -> 1.0091813e+10 | H72: =KQKD!$K$103+KQKD!$K$92-($C$71*G.Định!$D$78-($C$71*G.Định!$D$78/G.Định!$D$80*COLUMNS($E$38:H$38)))*G.Định!$D$81 -> 1.0227727e+10 | I72: =KQKD!$K$103+KQKD!$K$92-($C$71*G.Định!$D$78-($C$71*G.Định!$D$78/G.Định!$D$80*COLUMNS($E$38:I$38)))*G.Định!$D$81 -> 1.0363641e+10 | J72: =KQKD!$K$103+KQKD!$K$92-($C$71*G.Định!$D$78-($C$71*G.Định!$D$78/G.Định!$D$80*COLUMNS($E$38:J$38)))*G.Định!$D$81 -> 1.0499555e+10 | K72: =KQKD!$K$103+KQKD!$K$92-($C$71*G.Định!$D$78-($C$71*G.Định!$D$78/G.Định!$D$80*COLUMNS($E$38:K$38)))*G.Định!$D$81 -> 1.0635468e+10 | L72: =KQKD!$K$103+KQKD!$K$92 -> 1.0771382e+10 | M72: =KQKD!$K$103+KQKD!$K$92 -> 1.0771382e+10 | N72: =KQKD!$K$103+KQKD!$K$92 -> 1.0771382e+10 | O72: =KQKD!$K$103+KQKD!$K$92 -> 1.0771382e+10 | P72: =KQKD!$K$103+KQKD!$K$92 -> 1.0771382e+10 | Q72: =KQKD!$K$103+KQKD!$K$92 -> 1.0771382e+10 | R72: =KQKD!$K$103+KQKD!$K$92 -> 1.0771382e+10 | S72: =KQKD!$K$103+KQKD!$K$92 -> 1.0771382e+10 | ... W72: =KQKD!$K$103+KQKD!$K$92 -> 1.0771382e+10
B73: Khấu hao | D73: =KQKD!$K$95 -> 1.9293755e+09 | E73: =KQKD!$K$95 -> 1.9293755e+09 | F73: =KQKD!$K$95 -> 1.9293755e+09 | G73: =KQKD!$K$95 -> 1.9293755e+09 | H73: =KQKD!$K$95 -> 1.9293755e+09 | I73: =KQKD!$K$95 -> 1.9293755e+09 | J73: =KQKD!$K$95 -> 1.9293755e+09 | K73: =KQKD!$K$95 -> 1.9293755e+09 | ... W73: =KQKD!$K$95 -> 1.9293755e+09
B74: Tổng dòng tiền | C74: =-C71 -> -22190006000 | D74: =D72+D73 -> 1.1613447e+10 | E74: =E72+E73 -> 1.1749361e+10 | F74: =F72+F73 -> 1.1885275e+10 | G74: =G72+G73 -> 1.2021189e+10 | H74: =H72+H73 -> 1.2157103e+10 | I74: =I72+I73 -> 1.2293016e+10 | J74: =J72+J73 -> 1.242893e+10 | K74: =K72+K73 -> 1.2564844e+10 | ... W74: =W72+W73 -> 1.2700758e+10
B75: Tổng dòng tiền chiết khấu | C75: =C74 -> -22190006000 | D75: =D74/(1+G.Định!$D$87)^COLUMNS($D$41:D$41) -> 1.0703638e+10 | E75: =E74/(1+G.Định!$D$87)^COLUMNS($D$41:E$41) -> 9.980557e+09 | F75: =F74/(1+G.Định!$D$87)^COLUMNS($D$41:F$41) -> 9.305078e+09 | G75: =G74/(1+G.Định!$D$87)^COLUMNS($D$41:G$41) -> 8.6741807e+09 | H75: =H74/(1+G.Định!$D$87)^COLUMNS($D$41:H$41) -> 8.0850254e+09 | I75: =I74/(1+G.Định!$D$87)^COLUMNS($D$41:I$41) -> 7.534944e+09 | J75: =J74/(1+G.Định!$D$87)^COLUMNS($D$41:J$41) -> 7.0214301e+09 | K75: =K74/(1+G.Định!$D$87)^COLUMNS($D$41:K$41) -> 6.5421303e+09 | ... W75: =W74/(1+G.Định!$D$87)^COLUMNS($D$41:W$41) -> 2.4844764e+09
B76: Tổng dòng tiền chiết khấu lũy kế | C76: =C75 -> -22190006000 | D76: =C76+D75 -> -1.1486368e+10 | E76: =D76+E75 -> -1.5058108e+09 | F76: =E76+F75 -> 7.7992672e+09 | G76: =F76+G75 -> 1.6473448e+10 | H76: =G76+H75 -> 2.4558473e+10 | I76: =H76+I75 -> 3.2093417e+10 | J76: =I76+J75 -> 3.9114847e+10 | K76: =J76+K75 -> 4.5656978e+10 | ... W76: =V76+W75 -> 9.4226627e+10
B77: NPV | C77: =NPV(G.Định!$D$87,HV!C74:W74) -> 8.6844817e+10
B78: IRR | C78: =IRR(C74:W74) -> 0.53434391
B79: Thời gian hoàn vốn (năm) | C79: {=COUNTIF(D76:W76,"<0")-_xlfn.MAXIFS(D76:W76,D76:W76,"<0")/INDEX(D75:W75,MATCH(TRUE,INDEX(D76:W76>0,),0))} -> 2.1618268

Sheet CP 1kg
B2: STT | C2: CHỈ TIÊU | E2: TỔNG CHI PHÍ/ 1 THÁNG (Triệu đồng) | Q2: CHI PHÍ / 1 Kg (Đồng)
E3: Phân loại chai | I3: Băm vảy | M3: TỔNG | Q3: Phân loại chai | U3: Băm vảy | Y3: TỔNG | AC3: Tỷ trọng
C4: QUY MÔ ĐẦU TƯ (Tấn) | E4: H.S 40% | F4: H.S 60% | G4: H.S 80% | H4: H.S 100% | I4: H.S 40% | J4: H.S 60% | K4: H.S 80% | L4: H.S 100% | M4: H.S 40% | N4: H.S 60% | O4: H.S 80% | P4: H.S 100% | Q4: H.S 40% | R4: H.S 60% | S4: H.S 80% | T4: H.S 100% | U4: H.S 40% | V4: H.S 60% | W4: H.S 80% | X4: H.S 100% | Y4: H.S 40% | Z4: H.S 60% | AA4: H.S 80% | AB4: H.S 100%
C5: SẢN LƯỢNG SẢN XUẤT (Tấn) | E5: =S.Lượng!C18 -> 369600 | F5: =S.Lượng!D18 -> 554400 | G5: =S.Lượng!E18 -> 739200 | H5: =S.Lượng!F18 -> 924000 | I5: =S.Lượng!C29 -> 0 | J5: =S.Lượng!D29 -> 0 | K5: =S.Lượng!E29 -> 0 | L5: =S.Lượng!F29 -> 0 | M5: =KQKD!D4 -> 369600 | N5: =KQKD!E4 -> 554400 | O5: =KQKD!F4 -> 739200 | P5: =KQKD!G4 -> 924000
B6: I | C6: BIẾN PHÍ | E6: =E7+E9 -> 4.1933538e+09 | F6: =F7+F9 -> 6.2900307e+09 | G6: =G7+G9 -> 8.3867077e+09 | H6: =H7+H9 -> 1.0483385e+10 | I6: =I7+I9 -> 0 | J6: =J7+J9 -> 0 | K6: =K7+K9 -> 0 | L6: =L7+L9 -> 0 | M6: =E6+I6 -> 4.1933538e+09 | N6: =F6+J6 -> 6.2900307e+09 | O6: =G6+K6 -> 8.3867077e+09 | P6: =H6+L6 -> 1.0483385e+10 | Q6: =E6/E$5 -> 11345.654 | R6: =F6/F$5 -> 11345.654 | S6: =G6/G$5 -> 11345.654 | T6: =H6/H$5 -> 11345.654 | U6: =IFERROR(I6/I$5,0) -> 0 | V6: =IFERROR(J6/J$5,0) -> 0 | W6: =IFERROR(K6/K$5,0) -> 0 | X6: =IFERROR(L6/L$5,0) -> 0 | Y6: =M6/M$5 -> 11345.654 | Z6: =N6/N$5 -> 11345.654 | AA6: =O6/O$5 -> 11345.654 | AB6: =P6/P$5 -> 11345.654 | AC6: =AB6/$AB$74 -> 0.86075834
B7: 1.1 | C7: Biến phí bán hàng | E7: =E8 -> 69300000 | F7: =F8 -> 103950000 | G7: =G8 -> 138600000 | H7: =H8 -> 173250000 | I7: =I8 -> 0 | J7: =J8 -> 0 | K7: =K8 -> 0 | L7: =L8 -> 0 | M7: =E7+I7 -> 69300000 | N7: =F7+J7 -> 103950000 | O7: =G7+K7 -> 138600000 | P7: =H7+L7 -> 173250000 | Q7: =E7/E$5 -> 187.5 | R7: =F7/F$5 -> 187.5 | S7: =G7/G$5 -> 187.5 | T7: =H7/H$5 -> 187.5 | U7: =IFERROR(I7/I$5,0) -> 0 | V7: =IFERROR(J7/J$5,0) -> 0 | W7: =IFERROR(K7/K$5,0) -> 0 | X7: =IFERROR(L7/L$5,0) -> 0 | Y7: =M7/M$5 -> 187.5 | Z7: =N7/N$5 -> 187.5 | AA7: =O7/O$5 -> 187.5 | AB7: =P7/P$5 -> 187.5 | AC7: =AB7/$AB$74 -> 0.014225023
D8: Chi phí vận chuyển | E8: =CPBH!C3 -> 69300000 | F8: =CPBH!D3 -> 103950000 | G8: =CPBH!E3 -> 138600000 | H8: =CPBH!F3 -> 173250000 | I8: =CPBH!C4 -> 0 | J8: =CPBH!D4 -> 0 | K8: =CPBH!E4 -> 0 | L8: =CPBH!F4 -> 0 | M8: =E8+I8 -> 69300000 | N8: =F8+J8 -> 103950000 | O8: =G8+K8 -> 138600000 | P8: =H8+L8 -> 173250000 | Q8: =E8/E$5 -> 187.5 | R8: =F8/F$5 -> 187.5 | S8: =G8/G$5 -> 187.5 | T8: =H8/H$5 -> 187.5 | U8: =IFERROR(I8/I$5,0) -> 0 | V8: =IFERROR(J8/J$5,0) -> 0 | W8: =IFERROR(K8/K$5,0) -> 0 | X8: =IFERROR(L8/L$5,0) -> 0 | Y8: =M8/M$5 -> 187.5 | Z8: =N8/N$5 -> 187.5 | AA8: =O8/O$5 -> 187.5 | AB8: =P8/P$5 -> 187.5 | AC8: =AB8/$AB$74 -> 0.014225023
B9: 1.2 | C9: Biến phí sản xuất | E9: =SUM(E10:E20) -> 4.1240538e+09 | F9: =SUM(F10:F20) -> 6.1860807e+09 | G9: =SUM(G10:G20) -> 8.2481077e+09 | H9: =SUM(H10:H20) -> 1.0310135e+10 | I9: =SUM(I10:I20) -> 0 | J9: =SUM(J10:J20) -> 0 | K9: =SUM(K10:K20) -> 0 | L9: =SUM(L10:L20) -> 0 | M9: =E9+I9 -> 4.1240538e+09 | N9: =F9+J9 -> 6.1860807e+09 | O9: =G9+K9 -> 8.2481077e+09 | P9: =H9+L9 -> 1.0310135e+10 | Q9: =E9/E$5 -> 11158.154 | R9: =F9/F$5 -> 11158.154 | S9: =G9/G$5 -> 11158.154 | T9: =H9/H$5 -> 11158.154 | U9: =IFERROR(I9/I$5,0) -> 0 | V9: =IFERROR(J9/J$5,0) -> 0 | W9: =IFERROR(K9/K$5,0) -> 0 | X9: =IFERROR(L9/L$5,0) -> 0 | Y9: =M9/M$5 -> 11158.154 | Z9: =N9/N$5 -> 11158.154 | AA9: =O9/O$5 -> 11158.154 | AB9: =P9/P$5 -> 11158.154 | AC9: =AB9/$AB$74 -> 0.84653332
B10: -1 | D10: Chi phí nguyên liệu (chai B0) | E10: ='CPSX-Chai'!C4 -> 4000000000 | F10: ='CPSX-Chai'!D4 -> 6000000000 | G10: ='CPSX-Chai'!E4 -> 8000000000 | H10: ='CPSX-Chai'!F4 -> 10000000000 | I10: ='CPSX-Vảy'!C4 -> 0 | J10: ='CPSX-Vảy'!D4 -> 0 | K10: ='CPSX-Vảy'!E4 -> 0 | L10: ='CPSX-Vảy'!F4 -> 0 | M10: =E10+I10 -> 4000000000 | N10: =F10+J10 -> 6000000000 | O10: =G10+K10 -> 8000000000 | P10: =H10+L10 -> 10000000000 | Q10: =E10/E$5 -> 10822.511 | R10: =F10/F$5 -> 10822.511 | S10: =G10/G$5 -> 10822.511 | T10: =H10/H$5 -> 10822.511 | U10: =IFERROR(I10/I$5,0) -> 0 | V10: =IFERROR(J10/J$5,0) -> 0 | W10: =IFERROR(K10/K$5,0) -> 0 | X10: =IFERROR(L10/L$5,0) -> 0 | Y10: =M10/M$5 -> 10822.511 | Z10: =N10/N$5 -> 10822.511 | AA10: =O10/O$5 -> 10822.511 | AB10: =P10/P$5 -> 10822.511 | AC10: =AB10/$AB$74 -> 0.82106913
B11: -2 | D11: Chi phí bao jumbo | E11: ='CPSX-Chai'!C5 -> 946666.67 | F11: ='CPSX-Chai'!D5 -> 1420000 | G11: ='CPSX-Chai'!E5 -> 1893333.3 | H11: ='CPSX-Chai'!F5 -> 2366666.7 | I11: ='CPSX-Vảy'!C5 -> 0 | J11: ='CPSX-Vảy'!D5 -> 0 | K11: ='CPSX-Vảy'!E5 -> 0 | L11: ='CPSX-Vảy'!F5 -> 0 | M11: =E11+I11 -> 946666.67 | N11: =F11+J11 -> 1420000 | O11: =G11+K11 -> 1893333.3 | P11: =H11+L11 -> 2366666.7 | Q11: =E11/E$5 -> 2.5613276 | R11: =F11/F$5 -> 2.5613276 | S11: =G11/G$5 -> 2.5613276 | T11: =H11/H$5 -> 2.5613276 | U11: =IFERROR(I11/I$5,0) -> 0 | V11: =IFERROR(J11/J$5,0) -> 0 | W11: =IFERROR(K11/K$5,0) -> 0 | X11: =IFERROR(L11/L$5,0) -> 0 | Y11: =M11/M$5 -> 2.5613276 | Z11: =N11/N$5 -> 2.5613276 | AA11: =O11/O$5 -> 2.5613276 | AB11: =P11/P$5 -> 2.5613276 | AC11: =AB11/$AB$74 -> 0.00019431969
B12: -3 | D12: Chi phí dây đai | E12: ='CPSX-Chai'!C6 -> 28218522 | F12: ='CPSX-Chai'!D6 -> 42327783 | G12: ='CPSX-Chai'!E6 -> 56437043 | H12: ='CPSX-Chai'!F6 -> 70546304 | I12: ='CPSX-Vảy'!C6 -> 0 | J12: ='CPSX-Vảy'!D6 -> 0 | K12: ='CPSX-Vảy'!E6 -> 0 | L12: ='CPSX-Vảy'!F6 -> 0 | M12: =E12+I12 -> 28218522 | N12: =F12+J12 -> 42327783 | O12: =G12+K12 -> 56437043 | P12: =H12+L12 -> 70546304 | Q12: =E12/E$5 -> 76.348814 | R12: =F12/F$5 -> 76.348814 | S12: =G12/G$5 -> 76.348814 | T12: =H12/H$5 -> 76.348814 | U12: =IFERROR(I12/I$5,0) -> 0 | V12: =IFERROR(J12/J$5,0) -> 0 | W12: =IFERROR(K12/K$5,0) -> 0 | X12: =IFERROR(L12/L$5,0) -> 0 | Y12: =M12/M$5 -> 76.348814 | Z12: =N12/N$5 -> 76.348814 | AA12: =O12/O$5 -> 76.348814 | AB12: =P12/P$5 -> 76.348814 | AC12: =AB12/$AB$74 -> 0.0057923392
B13: -4 | D13: Chi phí điện sản xuất | E13: ='CPSX-Chai'!C7 -> 37600640 | F13: ='CPSX-Chai'!D7 -> 56400960 | G13: ='CPSX-Chai'!E7 -> 75201280 | H13: ='CPSX-Chai'!F7 -> 94001600 | I13: ='CPSX-Vảy'!C7 -> 0 | J13: ='CPSX-Vảy'!D7 -> 0 | K13: ='CPSX-Vảy'!E7 -> 0 | L13: ='CPSX-Vảy'!F7 -> 0 | M13: =E13+I13 -> 37600640 | N13: =F13+J13 -> 56400960 | O13: =G13+K13 -> 75201280 | P13: =H13+L13 -> 94001600 | Q13: =E13/E$5 -> 101.73333 | R13: =F13/F$5 -> 101.73333 | S13: =G13/G$5 -> 101.73333 | T13: =H13/H$5 -> 101.73333 | U13: =IFERROR(I13/I$5,0) -> 0 | V13: =IFERROR(J13/J$5,0) -> 0 | W13: =IFERROR(K13/K$5,0) -> 0 | X13: =IFERROR(L13/L$5,0) -> 0 | Y13: =M13/M$5 -> 101.73333 | Z13: =N13/N$5 -> 101.73333 | AA13: =O13/O$5 -> 101.73333 | AB13: =P13/P$5 -> 101.73333 | AC13: =AB13/$AB$74 -> 0.0077181812
B14: -5 | D14: Chi phí nước sản xuất | E14: ='CPSX-Chai'!C8 -> 0 | F14: ='CPSX-Chai'!D8 -> 0 | G14: ='CPSX-Chai'!E8 -> 0 | H14: ='CPSX-Chai'!F8 -> 0 | I14: ='CPSX-Vảy'!C8 -> 0 | J14: ='CPSX-Vảy'!D8 -> 0 | K14: ='CPSX-Vảy'!E8 -> 0 | L14: ='CPSX-Vảy'!F8 -> 0 | M14: =E14+I14 -> 0 | N14: =F14+J14 -> 0 | O14: =G14+K14 -> 0 | P14: =H14+L14 -> 0 | Q14: =E14/E$5 -> 0 | R14: =F14/F$5 -> 0 | S14: =G14/G$5 -> 0 | T14: =H14/H$5 -> 0 | U14: =IFERROR(I14/I$5,0) -> 0 | V14: =IFERROR(J14/J$5,0) -> 0 | W14: =IFERROR(K14/K$5,0) -> 0 | X14: =IFERROR(L14/L$5,0) -> 0 | Y14: =M14/M$5 -> 0 | Z14: =N14/N$5 -> 0 | AA14: =O14/O$5 -> 0 | AB14: =P14/P$5 -> 0 | AC14: =AB14/$AB$74 -> 0
B15: -6 | D15: Chi phí xăng, dầu xe nâng | E15: ='CPSX-Chai'!C9 -> 11088000 | F15: ='CPSX-Chai'!D9 -> 16632000 | G15: ='CPSX-Chai'!E9 -> 22176000 | H15: ='CPSX-Chai'!F9 -> 27720000 | I15: ='CPSX-Vảy'!C9 -> 0 | J15: ='CPSX-Vảy'!D9 -> 0 | K15: ='CPSX-Vảy'!E9 -> 0 | L15: ='CPSX-Vảy'!F9 -> 0 | M15: =E15+I15 -> 11088000 | N15: =F15+J15 -> 16632000 | O15: =G15+K15 -> 22176000 | P15: =H15+L15 -> 27720000 | Q15: =E15/E$5 -> 30 | R15: =F15/F$5 -> 30 | S15: =G15/G$5 -> 30 | T15: =H15/H$5 -> 30 | U15: =IFERROR(I15/I$5,0) -> 0 | V15: =IFERROR(J15/J$5,0) -> 0 | W15: =IFERROR(K15/K$5,0) -> 0 | X15: =IFERROR(L15/L$5,0) -> 0 | Y15: =M15/M$5 -> 30 | Z15: =N15/N$5 -> 30 | AA15: =O15/O$5 -> 30 | AB15: =P15/P$5 -> 30 | AC15: =AB15/$AB$74 -> 0.0022760036
B16: -7 | D16: Chi phí xử lý nước thải | E16: ='CPSX-Chai'!C10 -> 0 | F16: ='CPSX-Chai'!D10 -> 0 | G16: ='CPSX-Chai'!E10 -> 0 | H16: ='CPSX-Chai'!F10 -> 0 | I16: ='CPSX-Vảy'!C10 -> 0 | J16: ='CPSX-Vảy'!D10 -> 0 | K16: ='CPSX-Vảy'!E10 -> 0 | L16: ='CPSX-Vảy'!F10 -> 0 | M16: =E16+I16 -> 0 | N16: =F16+J16 -> 0 | O16: =G16+K16 -> 0 | P16: =H16+L16 -> 0 | Q16: =E16/E$5 -> 0 | R16: =F16/F$5 -> 0 | S16: =G16/G$5 -> 0 | T16: =H16/H$5 -> 0 | U16: =IFERROR(I16/I$5,0) -> 0 | V16: =IFERROR(J16/J$5,0) -> 0 | W16: =IFERROR(K16/K$5,0) -> 0 | X16: =IFERROR(L16/L$5,0) -> 0 | Y16: =M16/M$5 -> 0 | Z16: =N16/N$5 -> 0 | AA16: =O16/O$5 -> 0 | AB16: =P16/P$5 -> 0 | AC16: =AB16/$AB$74 -> 0
B17: -8 | D17: Chi phí xử lý bùn thải | E17: ='CPSX-Chai'!C11 -> 0 | F17: ='CPSX-Chai'!D11 -> 0 | G17: ='CPSX-Chai'!E11 -> 0 | H17: ='CPSX-Chai'!F11 -> 0 | I17: ='CPSX-Vảy'!C11 -> 0 | J17: ='CPSX-Vảy'!D11 -> 0 | K17: ='CPSX-Vảy'!E11 -> 0 | L17: ='CPSX-Vảy'!F11 -> 0 | M17: =E17+I17 -> 0 | N17: =F17+J17 -> 0 | O17: =G17+K17 -> 0 | P17: =H17+L17 -> 0 | Q17: =E17/E$5 -> 0 | R17: =F17/F$5 -> 0 | S17: =G17/G$5 -> 0 | T17: =H17/H$5 -> 0 | U17: =IFERROR(I17/I$5,0) -> 0 | V17: =IFERROR(J17/J$5,0) -> 0 | W17: =IFERROR(K17/K$5,0) -> 0 | X17: =IFERROR(L17/L$5,0) -> 0 | Y17: =M17/M$5 -> 0 | Z17: =N17/N$5 -> 0 | AA17: =O17/O$5 -> 0 | AB17: =P17/P$5 -> 0 | AC17: =AB17/$AB$74 -> 0
B18: -9 | D18: Chi phí xử lý rác thải CN | E18: ='CPSX-Chai'!C12 -> 5544000 | F18: ='CPSX-Chai'!D12 -> 8316000 | G18: ='CPSX-Chai'!E12 -> 11088000 | H18: ='CPSX-Chai'!F12 -> 13860000 | I18: ='CPSX-Vảy'!C12 -> 0 | J18: ='CPSX-Vảy'!D12 -> 0 | K18: ='CPSX-Vảy'!E12 -> 0 | L18: ='CPSX-Vảy'!F12 -> 0 | M18: =E18+I18 -> 5544000 | N18: =F18+J18 -> 8316000 | O18: =G18+K18 -> 11088000 | P18: =H18+L18 -> 13860000 | Q18: =E18/E$5 -> 15 | R18: =F18/F$5 -> 15 | S18: =G18/G$5 -> 15 | T18: =H18/H$5 -> 15 | U18: =IFERROR(I18/I$5,0) -> 0 | V18: =IFERROR(J18/J$5,0) -> 0 | W18: =IFERROR(K18/K$5,0) -> 0 | X18: =IFERROR(L18/L$5,0) -> 0 | Y18: =M18/M$5 -> 15 | Z18: =N18/N$5 -> 15 | AA18: =O18/O$5 -> 15 | AB18: =P18/P$5 -> 15 | AC18: =AB18/$AB$74 -> 0.0011380018
B19: -10 | D19: Chi phí dao tách nhãn, băm vảy | E19: ='CPSX-Chai'!C13 -> 40656000 | F19: ='CPSX-Chai'!D13 -> 60984000 | G19: ='CPSX-Chai'!E13 -> 81312000 | H19: ='CPSX-Chai'!F13 -> 101640000 | I19: ='CPSX-Vảy'!C13 -> 0 | J19: ='CPSX-Vảy'!D13 -> 0 | K19: ='CPSX-Vảy'!E13 -> 0 | L19: ='CPSX-Vảy'!F13 -> 0 | M19: =E19+I19 -> 40656000 | N19: =F19+J19 -> 60984000 | O19: =G19+K19 -> 81312000 | P19: =H19+L19 -> 101640000 | Q19: =E19/E$5 -> 110 | R19: =F19/F$5 -> 110 | S19: =G19/G$5 -> 110 | T19: =H19/H$5 -> 110 | U19: =IFERROR(I19/I$5,0) -> 0 | V19: =IFERROR(J19/J$5,0) -> 0 | W19: =IFERROR(K19/K$5,0) -> 0 | X19: =IFERROR(L19/L$5,0) -> 0 | Y19: =M19/M$5 -> 110 | Z19: =N19/N$5 -> 110 | AA19: =O19/O$5 -> 110 | AB19: =P19/P$5 -> 110 | AC19: =AB19/$AB$74 -> 0.0083453466
B20: -11 | D20: Chi phí vật tư kỹ thuật phục vụ sản xuất khác | E20: ='CPSX-Chai'!C14 -> 0 | F20: ='CPSX-Chai'!D14 -> 0 | G20: ='CPSX-Chai'!E14 -> 0 | H20: ='CPSX-Chai'!F14 -> 0 | I20: ='CPSX-Vảy'!C14 -> 0 | J20: ='CPSX-Vảy'!D14 -> 0 | K20: ='CPSX-Vảy'!E14 -> 0 | L20: ='CPSX-Vảy'!F14 -> 0 | M20: =E20+I20 -> 0 | N20: =F20+J20 -> 0 | O20: =G20+K20 -> 0 | P20: =H20+L20 -> 0 | Q20: =E20/E$5 -> 0 | R20: =F20/F$5 -> 0 | S20: =G20/G$5 -> 0 | T20: =H20/H$5 -> 0 | U20: =IFERROR(I20/I$5,0) -> 0 | V20: =IFERROR(J20/J$5,0) -> 0 | W20: =IFERROR(K20/K$5,0) -> 0 | X20: =IFERROR(L20/L$5,0) -> 0 | Y20: =M20/M$5 -> 0 | Z20: =N20/N$5 -> 0 | AA20: =O20/O$5 -> 0 | AB20: =P20/P$5 -> 0 | AC20: =AB20/$AB$74 -> 0
B21: II | C21: ĐỊNH PHÍ | E21: =E22+E34+E52+E72+E73 -> 1.3240191e+09 | F21: =F22+F34+F52+F72+F73 -> 1.5081062e+09 | G21: =G22+G34+G52+G72+G73 -> 1.6468041e+09 | H21: =H22+H34+H52+H72+H73 -> 1.6958579e+09 | I21: =I22+I34+I52+I72+I73 -> 0 | J21: =J22+J34+J52+J72+J73 -> 0 | K21: =K22+K34+K52+K72+K73 -> 0 | L21: =L22+L34+L52+L72+L73 -> 0 | M21: =E21+I21 -> 1.3240191e+09 | N21: =F21+J21 -> 1.5081062e+09 | O21: =G21+K21 -> 1.6468041e+09 | P21: =H21+L21 -> 1.6958579e+09 | Q21: =E21/E$5 -> 3582.3027 | R21: =F21/F$5 -> 2720.2494 | S21: =G21/G$5 -> 2227.8194 | T21: =H21/H$5 -> 1835.3441 | U21: =IFERROR(I21/I$5,0) -> 0 | V21: =IFERROR(J21/J$5,0) -> 0 | W21: =IFERROR(K21/K$5,0) -> 0 | X21: =IFERROR(L21/L$5,0) -> 0 | Y21: =M21/M$5 -> 3582.3027 | Z21: =N21/N$5 -> 2720.2494 | AA21: =O21/O$5 -> 2227.8194 | AB21: =P21/P$5 -> 1835.3441 | AC21: =AB21/$AB$74 -> 0.13924166
B22: 2.1 | C22: Định phí sản xuất | E22: =SUM(E23:E33) -> 4.5353161e+08 | F22: =SUM(F23:F33) -> 4.6051879e+08 | G22: =SUM(G23:G33) -> 4.6750597e+08 | H22: =SUM(H23:H33) -> 4.7549315e+08 | I22: =SUM(I23:I33) -> 0 | J22: =SUM(J23:J33) -> 0 | K22: =SUM(K23:K33) -> 0 | L22: =SUM(L23:L33) -> 0 | M22: =E22+I22 -> 4.5353161e+08 | N22: =F22+J22 -> 4.6051879e+08 | O22: =G22+K22 -> 4.6750597e+08 | P22: =H22+L22 -> 4.7549315e+08 | Q22: =E22/E$5 -> 1227.0877 | R22: =F22/F$5 -> 830.66161 | S22: =G22/G$5 -> 632.44856 | T22: =H22/H$5 -> 514.60298 | U22: =IFERROR(I22/I$5,0) -> 0 | V22: =IFERROR(J22/J$5,0) -> 0 | W22: =IFERROR(K22/K$5,0) -> 0 | X22: =IFERROR(L22/L$5,0) -> 0 | Y22: =M22/M$5 -> 1227.0877 | Z22: =N22/N$5 -> 830.66161 | AA22: =O22/O$5 -> 632.44856 | AB22: =P22/P$5 -> 514.60298 | AC22: =AB22/$AB$74 -> 0.039041275
B23: -1 | D23: Chi phí sửa chữa, bảo trì máy móc thiết bị sản xuất | E23: ='CPSX-Chai'!C16 -> 22190006 | F23: ='CPSX-Chai'!D16 -> 22190006 | G23: ='CPSX-Chai'!E16 -> 22190006 | H23: ='CPSX-Chai'!F16 -> 22190006 | I23: ='CPSX-Vảy'!C16 -> 0 | J23: ='CPSX-Vảy'!D16 -> 0 | K23: ='CPSX-Vảy'!E16 -> 0 | L23: ='CPSX-Vảy'!F16 -> 0 | M23: =E23+I23 -> 22190006 | N23: =F23+J23 -> 22190006 | O23: =G23+K23 -> 22190006 | P23: =H23+L23 -> 22190006 | Q23: =E23/E$5 -> 60.037895 | R23: =F23/F$5 -> 40.025263 | S23: =G23/G$5 -> 30.018948 | T23: =H23/H$5 -> 24.015158 | U23: =IFERROR(I23/I$5,0) -> 0 | V23: =IFERROR(J23/J$5,0) -> 0 | W23: =IFERROR(K23/K$5,0) -> 0 | X23: =IFERROR(L23/L$5,0) -> 0 | Y23: =M23/M$5 -> 60.037895 | Z23: =N23/N$5 -> 40.025263 | AA23: =O23/O$5 -> 30.018948 | AB23: =P23/P$5 -> 24.015158 | AC23: =AB23/$AB$74 -> 0.0018219529
B24: -2 | D24: Chi phí sửa chữa, bảo trì phương tiện vận tải | E24: ='CPSX-Chai'!C17 -> 1974359 | F24: ='CPSX-Chai'!D17 -> 2961538.5 | G24: ='CPSX-Chai'!E17 -> 3948717.9 | H24: ='CPSX-Chai'!F17 -> 4935897.4 | I24: ='CPSX-Vảy'!C17 -> 0 | J24: ='CPSX-Vảy'!D17 -> 0 | K24: ='CPSX-Vảy'!E17 -> 0 | L24: ='CPSX-Vảy'!F17 -> 0 | M24: =E24+I24 -> 1974359 | N24: =F24+J24 -> 2961538.5 | O24: =G24+K24 -> 3948717.9 | P24: =H24+L24 -> 4935897.4 | Q24: =E24/E$5 -> 5.3418803 | R24: =F24/F$5 -> 5.3418803 | S24: =G24/G$5 -> 5.3418803 | T24: =H24/H$5 -> 5.3418803 | U24: =IFERROR(I24/I$5,0) -> 0 | V24: =IFERROR(J24/J$5,0) -> 0 | W24: =IFERROR(K24/K$5,0) -> 0 | X24: =IFERROR(L24/L$5,0) -> 0 | Y24: =M24/M$5 -> 5.3418803 | Z24: =N24/N$5 -> 5.3418803 | AA24: =O24/O$5 -> 5.3418803 | AB24: =P24/P$5 -> 5.3418803 | AC24: =AB24/$AB$74 -> 0.0004052713
B25: -3 | D25: Chi phí sửa chữa, bảo trì công trình xây dựng (nhà xưởng, ... ) | E25: ='CPSX-Chai'!C18 -> 4142250 | F25: ='CPSX-Chai'!D18 -> 4142250 | G25: ='CPSX-Chai'!E18 -> 4142250 | H25: ='CPSX-Chai'!F18 -> 4142250 | I25: ='CPSX-Vảy'!C18 -> 0 | J25: ='CPSX-Vảy'!D18 -> 0 | K25: ='CPSX-Vảy'!E18 -> 0 | L25: ='CPSX-Vảy'!F18 -> 0 | M25: =E25+I25 -> 4142250 | N25: =F25+J25 -> 4142250 | O25: =G25+K25 -> 4142250 | P25: =H25+L25 -> 4142250 | Q25: =E25/E$5 -> 11.207386 | R25: =F25/F$5 -> 7.4715909 | S25: =G25/G$5 -> 5.6036932 | T25: =H25/H$5 -> 4.4829545 | U25: =IFERROR(I25/I$5,0) -> 0 | V25: =IFERROR(J25/J$5,0) -> 0 | W25: =IFERROR(K25/K$5,0) -> 0 | X25: =IFERROR(L25/L$5,0) -> 0 | Y25: =M25/M$5 -> 11.207386 | Z25: =N25/N$5 -> 7.4715909 | AA25: =O25/O$5 -> 5.6036932 | AB25: =P25/P$5 -> 4.4829545 | AC25: =AB25/$AB$74 -> 0.00034010736
B26: -4 | D26: Chi phí đăng kiểm xe cơ giới | E26: ='CPSX-Chai'!C19 -> 0 | F26: ='CPSX-Chai'!D19 -> 0 | G26: ='CPSX-Chai'!E19 -> 0 | H26: ='CPSX-Chai'!F19 -> 0 | I26: ='CPSX-Vảy'!C19 -> 0 | J26: ='CPSX-Vảy'!D19 -> 0 | K26: ='CPSX-Vảy'!E19 -> 0 | L26: ='CPSX-Vảy'!F19 -> 0 | M26: =E26+I26 -> 0 | N26: =F26+J26 -> 0 | O26: =G26+K26 -> 0 | P26: =H26+L26 -> 0 | Q26: =E26/E$5 -> 0 | R26: =F26/F$5 -> 0 | S26: =G26/G$5 -> 0 | T26: =H26/H$5 -> 0 | U26: =IFERROR(I26/I$5,0) -> 0 | V26: =IFERROR(J26/J$5,0) -> 0 | W26: =IFERROR(K26/K$5,0) -> 0 | X26: =IFERROR(L26/L$5,0) -> 0 | Y26: =M26/M$5 -> 0 | Z26: =N26/N$5 -> 0 | AA26: =O26/O$5 -> 0 | AB26: =P26/P$5 -> 0 | AC26: =AB26/$AB$74 -> 0
B27: -5 | D27: Chi phí kiểm định, hiệu chuẩn máy móc thiết bị | E27: ='CPSX-Chai'!C20 -> 3000000 | F27: ='CPSX-Chai'!D20 -> 5000000 | G27: ='CPSX-Chai'!E20 -> 7000000 | H27: ='CPSX-Chai'!F20 -> 10000000 | I27: ='CPSX-Vảy'!C20 -> 0 | J27: ='CPSX-Vảy'!D20 -> 0 | K27: ='CPSX-Vảy'!E20 -> 0 | L27: ='CPSX-Vảy'!F20 -> 0 | M27: =E27+I27 -> 3000000 | N27: =F27+J27 -> 5000000 | O27: =G27+K27 -> 7000000 | P27: =H27+L27 -> 10000000 | Q27: =E27/E$5 -> 8.1168831 | R27: =F27/F$5 -> 9.018759 | S27: =G27/G$5 -> 9.469697 | T27: =H27/H$5 -> 10.822511 | U27: =IFERROR(I27/I$5,0) -> 0 | V27: =IFERROR(J27/J$5,0) -> 0 | W27: =IFERROR(K27/K$5,0) -> 0 | X27: =IFERROR(L27/L$5,0) -> 0 | Y27: =M27/M$5 -> 8.1168831 | Z27: =N27/N$5 -> 9.018759 | AA27: =O27/O$5 -> 9.469697 | AB27: =P27/P$5 -> 10.822511 | AC27: =AB27/$AB$74 -> 0.00082106913
B28: -6 | D28: Chi phí công cụ dụng cụ phục vụ sản xuất | E28: ='CPSX-Chai'!C21 -> 5000000 | F28: ='CPSX-Chai'!D21 -> 7000000 | G28: ='CPSX-Chai'!E21 -> 8000000 | H28: ='CPSX-Chai'!F21 -> 10000000 | I28: ='CPSX-Vảy'!C21 -> 0 | J28: ='CPSX-Vảy'!D21 -> 0 | K28: ='CPSX-Vảy'!E21 -> 0 | L28: ='CPSX-Vảy'!F21 -> 0 | M28: =E28+I28 -> 5000000 | N28: =F28+J28 -> 7000000 | O28: =G28+K28 -> 8000000 | P28: =H28+L28 -> 10000000 | Q28: =E28/E$5 -> 13.528139 | R28: =F28/F$5 -> 12.626263 | S28: =G28/G$5 -> 10.822511 | T28: =H28/H$5 -> 10.822511 | U28: =IFERROR(I28/I$5,0) -> 0 | V28: =IFERROR(J28/J$5,0) -> 0 | W28: =IFERROR(K28/K$5,0) -> 0 | X28: =IFERROR(L28/L$5,0) -> 0 | Y28: =M28/M$5 -> 13.528139 | Z28: =N28/N$5 -> 12.626263 | AA28: =O28/O$5 -> 10.822511 | AB28: =P28/P$5 -> 10.822511 | AC28: =AB28/$AB$74 -> 0.00082106913
B29: -7 | D29: Chi phí thuê xưởng | E29: ='CPSX-Chai'!C22 -> 414225000 | F29: ='CPSX-Chai'!D22 -> 414225000 | G29: ='CPSX-Chai'!E22 -> 414225000 | H29: ='CPSX-Chai'!F22 -> 414225000 | I29: ='CPSX-Vảy'!C22 -> 0 | J29: ='CPSX-Vảy'!D22 -> 0 | K29: ='CPSX-Vảy'!E22 -> 0 | L29: ='CPSX-Vảy'!F22 -> 0 | M29: =E29+I29 -> 414225000 | N29: =F29+J29 -> 414225000 | O29: =G29+K29 -> 414225000 | P29: =H29+L29 -> 414225000 | Q29: =E29/E$5 -> 1120.7386 | R29: =F29/F$5 -> 747.15909 | S29: =G29/G$5 -> 560.36932 | T29: =H29/H$5 -> 448.29545 | U29: =IFERROR(I29/I$5,0) -> 0 | V29: =IFERROR(J29/J$5,0) -> 0 | W29: =IFERROR(K29/K$5,0) -> 0 | X29: =IFERROR(L29/L$5,0) -> 0 | Y29: =M29/M$5 -> 1120.7386 | Z29: =N29/N$5 -> 747.15909 | AA29: =O29/O$5 -> 560.36932 | AB29: =P29/P$5 -> 448.29545 | AC29: =AB29/$AB$74 -> 0.034010736
B30: -8 | D30: Chi phí thuê kho, bãi | E30: ='CPSX-Chai'!C23 -> 0 | F30: ='CPSX-Chai'!D23 -> 0 | G30: ='CPSX-Chai'!E23 -> 0 | H30: ='CPSX-Chai'!F23 -> 0 | I30: ='CPSX-Vảy'!C23 -> 0 | J30: ='CPSX-Vảy'!D23 -> 0 | K30: ='CPSX-Vảy'!E23 -> 0 | L30: ='CPSX-Vảy'!F23 -> 0 | M30: =E30+I30 -> 0 | N30: =F30+J30 -> 0 | O30: =G30+K30 -> 0 | P30: =H30+L30 -> 0 | Q30: =E30/E$5 -> 0 | R30: =F30/F$5 -> 0 | S30: =G30/G$5 -> 0 | T30: =H30/H$5 -> 0 | U30: =IFERROR(I30/I$5,0) -> 0 | V30: =IFERROR(J30/J$5,0) -> 0 | W30: =IFERROR(K30/K$5,0) -> 0 | X30: =IFERROR(L30/L$5,0) -> 0 | Y30: =M30/M$5 -> 0 | Z30: =N30/N$5 -> 0 | AA30: =O30/O$5 -> 0 | AB30: =P30/P$5 -> 0 | AC30: =AB30/$AB$74 -> 0
B31: -9 | D31: Chi phí thuê máy móc thiết bị | E31: ='CPSX-Chai'!C24 -> 0 | F31: ='CPSX-Chai'!D24 -> 0 | G31: ='CPSX-Chai'!E24 -> 0 | H31: ='CPSX-Chai'!F24 -> 0 | I31: ='CPSX-Vảy'!C24 -> 0 | J31: ='CPSX-Vảy'!D24 -> 0 | K31: ='CPSX-Vảy'!E24 -> 0 | L31: ='CPSX-Vảy'!F24 -> 0 | M31: =E31+I31 -> 0 | N31: =F31+J31 -> 0 | O31: =G31+K31 -> 0 | P31: =H31+L31 -> 0 | Q31: =E31/E$5 -> 0 | R31: =F31/F$5 -> 0 | S31: =G31/G$5 -> 0 | T31: =H31/H$5 -> 0 | U31: =IFERROR(I31/I$5,0) -> 0 | V31: =IFERROR(J31/J$5,0) -> 0 | W31: =IFERROR(K31/K$5,0) -> 0 | X31: =IFERROR(L31/L$5,0) -> 0 | Y31: =M31/M$5 -> 0 | Z31: =N31/N$5 -> 0 | AA31: =O31/O$5 -> 0 | AB31: =P31/P$5 -> 0 | AC31: =AB31/$AB$74 -> 0
B32: -10 | D32: Chi phí thuê phương tiện vận tải | E32: ='CPSX-Chai'!C25 -> 0 | F32: ='CPSX-Chai'!D25 -> 0 | G32: ='CPSX-Chai'!E25 -> 0 | H32: ='CPSX-Chai'!F25 -> 0 | I32: ='CPSX-Vảy'!C25 -> 0 | J32: ='CPSX-Vảy'!D25 -> 0 | K32: ='CPSX-Vảy'!E25 -> 0 | L32: ='CPSX-Vảy'!F25 -> 0 | M32: =E32+I32 -> 0 | N32: =F32+J32 -> 0 | O32: =G32+K32 -> 0 | P32: =H32+L32 -> 0 | Q32: =E32/E$5 -> 0 | R32: =F32/F$5 -> 0 | S32: =G32/G$5 -> 0 | T32: =H32/H$5 -> 0 | U32: =IFERROR(I32/I$5,0) -> 0 | V32: =IFERROR(J32/J$5,0) -> 0 | W32: =IFERROR(K32/K$5,0) -> 0 | X32: =IFERROR(L32/L$5,0) -> 0 | Y32: =M32/M$5 -> 0 | Z32: =N32/N$5 -> 0 | AA32: =O32/O$5 -> 0 | AB32: =P32/P$5 -> 0 | AC32: =AB32/$AB$74 -> 0
B33: -11 | D33: Chi phí sản xuất khác | E33: ='CPSX-Chai'!C26 -> 3000000 | F33: ='CPSX-Chai'!D26 -> 5000000 | G33: ='CPSX-Chai'!E26 -> 8000000 | H33: ='CPSX-Chai'!F26 -> 10000000 | I33: ='CPSX-Vảy'!C26 -> 0 | J33: ='CPSX-Vảy'!D26 -> 0 | K33: ='CPSX-Vảy'!E26 -> 0 | L33: ='CPSX-Vảy'!F26 -> 0 | M33: =E33+I33 -> 3000000 | N33: =F33+J33 -> 5000000 | O33: =G33+K33 -> 8000000 | P33: =H33+L33 -> 10000000 | Q33: =E33/E$5 -> 8.1168831 | R33: =F33/F$5 -> 9.018759 | S33: =G33/G$5 -> 10.822511 | T33: =H33/H$5 -> 10.822511 | U33: =IFERROR(I33/I$5,0) -> 0 | V33: =IFERROR(J33/J$5,0) -> 0 | W33: =IFERROR(K33/K$5,0) -> 0 | X33: =IFERROR(L33/L$5,0) -> 0 | Y33: =M33/M$5 -> 8.1168831 | Z33: =N33/N$5 -> 9.018759 | AA33: =O33/O$5 -> 10.822511 | AB33: =P33/P$5 -> 10.822511 | AC33: =AB33/$AB$74 -> 0.00082106913
B34: 2.2 | C34: Định phí quản lý | E34: =SUM(E35:E51) -> 1.1830113e+08 | F34: =SUM(F35:F51) -> 1.1830113e+08 | G34: =SUM(G35:G51) -> 1.1830113e+08 | H34: =SUM(H35:H51) -> 1.1830113e+08 | I34: =SUM(I35:I51) -> 0 | J34: =SUM(J35:J51) -> 0 | K34: =SUM(K35:K51) -> 0 | L34: =SUM(L35:L51) -> 0 | M34: =E34+I34 -> 1.1830113e+08 | N34: =F34+J34 -> 1.1830113e+08 | O34: =G34+K34 -> 1.1830113e+08 | P34: =H34+L34 -> 1.1830113e+08 | Q34: =E34/E$5 -> 320.07883 | R34: =F34/F$5 -> 213.38588 | S34: =G34/G$5 -> 160.03941 | T34: =H34/H$5 -> 128.03153 | U34: =IFERROR(I34/I$5,0) -> 0 | V34: =IFERROR(J34/J$5,0) -> 0 | W34: =IFERROR(K34/K$5,0) -> 0 | X34: =IFERROR(L34/L$5,0) -> 0 | Y34: =M34/M$5 -> 320.07883 | Z34: =N34/N$5 -> 213.38588 | AA34: =O34/O$5 -> 160.03941 | AB34: =P34/P$5 -> 128.03153 | AC34: =AB34/$AB$74 -> 0.0097133409
B35: -1 | D35: Chi phí điện quản lý | E35: =CPQL!C3 -> 2000000 | F35: =CPQL!D3 -> 2000000 | G35: =CPQL!E3 -> 2000000 | H35: =CPQL!F3 -> 2000000 | M35: =E35+I35 -> 2000000 | N35: =F35+J35 -> 2000000 | O35: =G35+K35 -> 2000000 | P35: =H35+L35 -> 2000000 | Q35: =E35/E$5 -> 5.4112554 | R35: =F35/F$5 -> 3.6075036 | S35: =G35/G$5 -> 2.7056277 | T35: =H35/H$5 -> 2.1645022 | U35: =IFERROR(I35/I$5,0) -> 0 | V35: =IFERROR(J35/J$5,0) -> 0 | W35: =IFERROR(K35/K$5,0) -> 0 | X35: =IFERROR(L35/L$5,0) -> 0 | Y35: =M35/M$5 -> 5.4112554 | Z35: =N35/N$5 -> 3.6075036 | AA35: =O35/O$5 -> 2.7056277 | AB35: =P35/P$5 -> 2.1645022 | AC35: =AB35/$AB$74 -> 0.00016421383
B36: -2 | D36: Chi phí nước sinh hoạt | E36: =CPQL!C4 -> 3000000 | F36: =CPQL!D4 -> 3000000 | G36: =CPQL!E4 -> 3000000 | H36: =CPQL!F4 -> 3000000 | M36: =E36+I36 -> 3000000 | N36: =F36+J36 -> 3000000 | O36: =G36+K36 -> 3000000 | P36: =H36+L36 -> 3000000 | Q36: =E36/E$5 -> 8.1168831 | R36: =F36/F$5 -> 5.4112554 | S36: =G36/G$5 -> 4.0584416 | T36: =H36/H$5 -> 3.2467532 | U36: =IFERROR(I36/I$5,0) -> 0 | V36: =IFERROR(J36/J$5,0) -> 0 | W36: =IFERROR(K36/K$5,0) -> 0 | X36: =IFERROR(L36/L$5,0) -> 0 | Y36: =M36/M$5 -> 8.1168831 | Z36: =N36/N$5 -> 5.4112554 | AA36: =O36/O$5 -> 4.0584416 | AB36: =P36/P$5 -> 3.2467532 | AC36: =AB36/$AB$74 -> 0.00024632074
B37: -3 | D37: Chi phí dịch vụ bảo vệ | E37: =CPQL!C5 -> 36000000 | F37: =CPQL!D5 -> 36000000 | G37: =CPQL!E5 -> 36000000 | H37: =CPQL!F5 -> 36000000 | M37: =E37+I37 -> 36000000 | N37: =F37+J37 -> 36000000 | O37: =G37+K37 -> 36000000 | P37: =H37+L37 -> 36000000 | Q37: =E37/E$5 -> 97.402597 | R37: =F37/F$5 -> 64.935065 | S37: =G37/G$5 -> 48.701299 | T37: =H37/H$5 -> 38.961039 | U37: =IFERROR(I37/I$5,0) -> 0 | V37: =IFERROR(J37/J$5,0) -> 0 | W37: =IFERROR(K37/K$5,0) -> 0 | X37: =IFERROR(L37/L$5,0) -> 0 | Y37: =M37/M$5 -> 97.402597 | Z37: =N37/N$5 -> 64.935065 | AA37: =O37/O$5 -> 48.701299 | AB37: =P37/P$5 -> 38.961039 | AC37: =AB37/$AB$74 -> 0.0029558489
B38: -4 | D38: Chi phí bảo hiểm tài sản | E38: =CPQL!C6 -> 3698334.3 | F38: =CPQL!D6 -> 3698334.3 | G38: =CPQL!E6 -> 3698334.3 | H38: =CPQL!F6 -> 3698334.3 | M38: =E38+I38 -> 3698334.3 | N38: =F38+J38 -> 3698334.3 | O38: =G38+K38 -> 3698334.3 | P38: =H38+L38 -> 3698334.3 | Q38: =E38/E$5 -> 10.006316 | R38: =F38/F$5 -> 6.6708772 | S38: =G38/G$5 -> 5.0031579 | T38: =H38/H$5 -> 4.0025263 | U38: =IFERROR(I38/I$5,0) -> 0 | V38: =IFERROR(J38/J$5,0) -> 0 | W38: =IFERROR(K38/K$5,0) -> 0 | X38: =IFERROR(L38/L$5,0) -> 0 | Y38: =M38/M$5 -> 10.006316 | Z38: =N38/N$5 -> 6.6708772 | AA38: =O38/O$5 -> 5.0031579 | AB38: =P38/P$5 -> 4.0025263 | AC38: =AB38/$AB$74 -> 0.00030365881
B39: -5 | D39: Chi phí xây dựng phần mềm | E39: =CPQL!C7 -> 0 | F39: =CPQL!D7 -> 0 | G39: =CPQL!E7 -> 0 | H39: =CPQL!F7 -> 0 | M39: =E39+I39 -> 0 | N39: =F39+J39 -> 0 | O39: =G39+K39 -> 0 | P39: =H39+L39 -> 0 | Q39: =E39/E$5 -> 0 | R39: =F39/F$5 -> 0 | S39: =G39/G$5 -> 0 | T39: =H39/H$5 -> 0 | U39: =IFERROR(I39/I$5,0) -> 0 | V39: =IFERROR(J39/J$5,0) -> 0 | W39: =IFERROR(K39/K$5,0) -> 0 | X39: =IFERROR(L39/L$5,0) -> 0 | Y39: =M39/M$5 -> 0 | Z39: =N39/N$5 -> 0 | AA39: =O39/O$5 -> 0 | AB39: =P39/P$5 -> 0 | AC39: =AB39/$AB$74 -> 0
B40: -6 | D40: Chi phí bản quyền (licences) | E40: =CPQL!C8 -> 48102800 | F40: =CPQL!D8 -> 48102800 | G40: =CPQL!E8 -> 48102800 | H40: =CPQL!F8 -> 48102800 | M40: =E40+I40 -> 48102800 | N40: =F40+J40 -> 48102800 | O40: =G40+K40 -> 48102800 | P40: =H40+L40 -> 48102800 | Q40: =E40/E$5 -> 130.14827 | R40: =F40/F$5 -> 86.765512 | S40: =G40/G$5 -> 65.074134 | T40: =H40/H$5 -> 52.059307 | U40: =IFERROR(I40/I$5,0) -> 0 | V40: =IFERROR(J40/J$5,0) -> 0 | W40: =IFERROR(K40/K$5,0) -> 0 | X40: =IFERROR(L40/L$5,0) -> 0 | Y40: =M40/M$5 -> 130.14827 | Z40: =N40/N$5 -> 86.765512 | AA40: =O40/O$5 -> 65.074134 | AB40: =P40/P$5 -> 52.059307 | AC40: =AB40/$AB$74 -> 0.0039495724
B41: -7 | D41: Chi phí ủng hộ, hỗ trợ, tài trợ | E41: =CPQL!C9 -> 2000000 | F41: =CPQL!D9 -> 2000000 | G41: =CPQL!E9 -> 2000000 | H41: =CPQL!F9 -> 2000000 | M41: =E41+I41 -> 2000000 | N41: =F41+J41 -> 2000000 | O41: =G41+K41 -> 2000000 | P41: =H41+L41 -> 2000000 | Q41: =E41/E$5 -> 5.4112554 | R41: =F41/F$5 -> 3.6075036 | S41: =G41/G$5 -> 2.7056277 | T41: =H41/H$5 -> 2.1645022 | U41: =IFERROR(I41/I$5,0) -> 0 | V41: =IFERROR(J41/J$5,0) -> 0 | W41: =IFERROR(K41/K$5,0) -> 0 | X41: =IFERROR(L41/L$5,0) -> 0 | Y41: =M41/M$5 -> 5.4112554 | Z41: =N41/N$5 -> 3.6075036 | AA41: =O41/O$5 -> 2.7056277 | AB41: =P41/P$5 -> 2.1645022 | AC41: =AB41/$AB$74 -> 0.00016421383
B42: -8 | D42: Chi phí công tác | E42: =CPQL!C10 -> 1500000 | F42: =CPQL!D10 -> 1500000 | G42: =CPQL!E10 -> 1500000 | H42: =CPQL!F10 -> 1500000 | M42: =E42+I42 -> 1500000 | N42: =F42+J42 -> 1500000 | O42: =G42+K42 -> 1500000 | P42: =H42+L42 -> 1500000 | Q42: =E42/E$5 -> 4.0584416 | R42: =F42/F$5 -> 2.7056277 | S42: =G42/G$5 -> 2.0292208 | T42: =H42/H$5 -> 1.6233766 | U42: =IFERROR(I42/I$5,0) -> 0 | V42: =IFERROR(J42/J$5,0) -> 0 | W42: =IFERROR(K42/K$5,0) -> 0 | X42: =IFERROR(L42/L$5,0) -> 0 | Y42: =M42/M$5 -> 4.0584416 | Z42: =N42/N$5 -> 2.7056277 | AA42: =O42/O$5 -> 2.0292208 | AB42: =P42/P$5 -> 1.6233766 | AC42: =AB42/$AB$74 -> 0.00012316037
B43: -9 | D43: Chi phí tiếp khách | E43: =CPQL!C11 -> 3833333.3 | F43: =CPQL!D11 -> 3833333.3 | G43: =CPQL!E11 -> 3833333.3 | H43: =CPQL!F11 -> 3833333.3 | M43: =E43+I43 -> 3833333.3 | N43: =F43+J43 -> 3833333.3 | O43: =G43+K43 -> 3833333.3 | P43: =H43+L43 -> 3833333.3 | Q43: =E43/E$5 -> 10.371573 | R43: =F43/F$5 -> 6.9143819 | S43: =G43/G$5 -> 5.1857864 | T43: =H43/H$5 -> 4.1486291 | U43: =IFERROR(I43/I$5,0) -> 0 | V43: =IFERROR(J43/J$5,0) -> 0 | W43: =IFERROR(K43/K$5,0) -> 0 | X43: =IFERROR(L43/L$5,0) -> 0 | Y43: =M43/M$5 -> 10.371573 | Z43: =N43/N$5 -> 6.9143819 | AA43: =O43/O$5 -> 5.1857864 | AB43: =P43/P$5 -> 4.1486291 | AC43: =AB43/$AB$74 -> 0.00031474316
B44: -10 | D44: Chi phí in ấn, vật tư, VPP | E44: =CPQL!C12 -> 4500000 | F44: =CPQL!D12 -> 4500000 | G44: =CPQL!E12 -> 4500000 | H44: =CPQL!F12 -> 4500000 | M44: =E44+I44 -> 4500000 | N44: =F44+J44 -> 4500000 | O44: =G44+K44 -> 4500000 | P44: =H44+L44 -> 4500000 | Q44: =E44/E$5 -> 12.175325 | R44: =F44/F$5 -> 8.1168831 | S44: =G44/G$5 -> 6.0876623 | T44: =H44/H$5 -> 4.8701299 | U44: =IFERROR(I44/I$5,0) -> 0 | V44: =IFERROR(J44/J$5,0) -> 0 | W44: =IFERROR(K44/K$5,0) -> 0 | X44: =IFERROR(L44/L$5,0) -> 0 | Y44: =M44/M$5 -> 12.175325 | Z44: =N44/N$5 -> 8.1168831 | AA44: =O44/O$5 -> 6.0876623 | AB44: =P44/P$5 -> 4.8701299 | AC44: =AB44/$AB$74 -> 0.00036948111
B45: -11 | D45: Chi phí internet, điện thoại, bưu phẩm | E45: =CPQL!C13 -> 1500000 | F45: =CPQL!D13 -> 1500000 | G45: =CPQL!E13 -> 1500000 | H45: =CPQL!F13 -> 1500000 | M45: =E45+I45 -> 1500000 | N45: =F45+J45 -> 1500000 | O45: =G45+K45 -> 1500000 | P45: =H45+L45 -> 1500000 | Q45: =E45/E$5 -> 4.0584416 | R45: =F45/F$5 -> 2.7056277 | S45: =G45/G$5 -> 2.0292208 | T45: =H45/H$5 -> 1.6233766 | U45: =IFERROR(I45/I$5,0) -> 0 | V45: =IFERROR(J45/J$5,0) -> 0 | W45: =IFERROR(K45/K$5,0) -> 0 | X45: =IFERROR(L45/L$5,0) -> 0 | Y45: =M45/M$5 -> 4.0584416 | Z45: =N45/N$5 -> 2.7056277 | AA45: =O45/O$5 -> 2.0292208 | AB45: =P45/P$5 -> 1.6233766 | AC45: =AB45/$AB$74 -> 0.00012316037
B46: -12 | D46: Chi phí nước uống | E46: =CPQL!C14 -> 5000000 | F46: =CPQL!D14 -> 5000000 | G46: =CPQL!E14 -> 5000000 | H46: =CPQL!F14 -> 5000000 | M46: =E46+I46 -> 5000000 | N46: =F46+J46 -> 5000000 | O46: =G46+K46 -> 5000000 | P46: =H46+L46 -> 5000000 | Q46: =E46/E$5 -> 13.528139 | R46: =F46/F$5 -> 9.018759 | S46: =G46/G$5 -> 6.7640693 | T46: =H46/H$5 -> 5.4112554 | U46: =IFERROR(I46/I$5,0) -> 0 | V46: =IFERROR(J46/J$5,0) -> 0 | W46: =IFERROR(K46/K$5,0) -> 0 | X46: =IFERROR(L46/L$5,0) -> 0 | Y46: =M46/M$5 -> 13.528139 | Z46: =N46/N$5 -> 9.018759 | AA46: =O46/O$5 -> 6.7640693 | AB46: =P46/P$5 -> 5.4112554 | AC46: =AB46/$AB$74 -> 0.00041053456
... B51: -17 | D51: Chi phí khác | E51: =CPQL!C19 -> 4416666.7 | F51: =CPQL!D19 -> 4416666.7 | G51: =CPQL!E19 -> 4416666.7 | H51: =CPQL!F19 -> 4416666.7 | M51: =E51+I51 -> 4416666.7 | N51: =F51+J51 -> 4416666.7 | O51: =G51+K51 -> 4416666.7 | P51: =H51+L51 -> 4416666.7 | Q51: =E51/E$5 -> 11.949856 | R51: =F51/F$5 -> 7.9665705 | S51: =G51/G$5 -> 5.9749278 | T51: =H51/H$5 -> 4.7799423 | U51: =IFERROR(I51/I$5,0) -> 0 | V51: =IFERROR(J51/J$5,0) -> 0 | W51: =IFERROR(K51/K$5,0) -> 0 | X51: =IFERROR(L51/L$5,0) -> 0 | Y51: =M51/M$5 -> 11.949856 | Z51: =N51/N$5 -> 7.9665705 | AA51: =O51/O$5 -> 5.9749278 | AB51: =P51/P$5 -> 4.7799423 | AC51: =AB51/$AB$74 -> 0.00036263886
B52: 2.3 | C52: Chi phí nhân sự | E52: =E53+E62 -> 5.0079583e+08 | F52: =F53+F62 -> 6.7789583e+08 | G52: =G53+G62 -> 809606500 | H52: =H53+H62 -> 8.5067317e+08 | I52: =I53+I62 -> 0 | J52: =J53+J62 -> 0 | K52: =K53+K62 -> 0 | L52: =L53+L62 -> 0 | M52: =E52+I52 -> 5.0079583e+08 | N52: =F52+J52 -> 6.7789583e+08 | O52: =G52+K52 -> 809606500 | P52: =H52+L52 -> 8.5067317e+08 | Q52: =E52/E$5 -> 1354.9671 | R52: =F52/F$5 -> 1222.7558 | S52: =G52/G$5 -> 1095.2469 | T52: =H52/H$5 -> 920.64196 | U52: =IFERROR(I52/I$5,0) -> 0 | V52: =IFERROR(J52/J$5,0) -> 0 | W52: =IFERROR(K52/K$5,0) -> 0 | X52: =IFERROR(L52/L$5,0) -> 0 | Y52: =M52/M$5 -> 1354.9671 | Z52: =N52/N$5 -> 1222.7558 | AA52: =O52/O$5 -> 1095.2469 | AB52: =P52/P$5 -> 920.64196 | AC52: =AB52/$AB$74 -> 0.069846147
B53: 2.3.1 | C53: Chi phí lương | E53: =SUM(E54:E61) -> 4.8253333e+08 | F53: =SUM(F54:F61) -> 6.5963333e+08 | G53: =SUM(G54:G61) -> 777700000 | H53: =SUM(H54:H61) -> 8.1876667e+08 | I53: =SUM(I54:I61) -> 0 | J53: =SUM(J54:J61) -> 0 | K53: =SUM(K54:K61) -> 0 | L53: =SUM(L54:L61) -> 0 | M53: =E53+I53 -> 4.8253333e+08 | N53: =F53+J53 -> 6.5963333e+08 | O53: =G53+K53 -> 777700000 | P53: =H53+L53 -> 8.1876667e+08 | Q53: =E53/E$5 -> 1305.5556 | R53: =F53/F$5 -> 1189.8148 | S53: =G53/G$5 -> 1052.0833 | T53: =H53/H$5 -> 886.11111 | U53: =IFERROR(I53/I$5,0) -> 0 | V53: =IFERROR(J53/J$5,0) -> 0 | W53: =IFERROR(K53/K$5,0) -> 0 | X53: =IFERROR(L53/L$5,0) -> 0 | Y53: =M53/M$5 -> 1305.5556 | Z53: =N53/N$5 -> 1189.8148 | AA53: =O53/O$5 -> 1052.0833 | AB53: =P53/P$5 -> 886.11111 | AC53: =AB53/$AB$74 -> 0.067226403
B54: -1 | D54: Chi phí lương chính | E54: ='CP.NS'!C6+'CP.NS'!C15+'CP.NS'!C43 -> 376000000 | F54: ='CP.NS'!D6+'CP.NS'!D15+'CP.NS'!D43 -> 514000000 | G54: ='CP.NS'!E6+'CP.NS'!E15+'CP.NS'!E43 -> 606000000 | H54: ='CP.NS'!F6+'CP.NS'!F15+'CP.NS'!F43 -> 638000000 | I54: ='CP.NS'!C25+'CP.NS'!C34 -> 0 | J54: ='CP.NS'!D25+'CP.NS'!D34 -> 0 | K54: ='CP.NS'!E25+'CP.NS'!E34 -> 0 | L54: ='CP.NS'!F25+'CP.NS'!F34 -> 0 | M54: =E54+I54 -> 376000000 | N54: =F54+J54 -> 514000000 | O54: =G54+K54 -> 606000000 | P54: =H54+L54 -> 638000000 | Q54: =E54/E$5 -> 1017.316 | R54: =F54/F$5 -> 927.12843 | S54: =G54/G$5 -> 819.80519 | T54: =H54/H$5 -> 690.47619 | U54: =IFERROR(I54/I$5,0) -> 0 | V54: =IFERROR(J54/J$5,0) -> 0 | W54: =IFERROR(K54/K$5,0) -> 0 | X54: =IFERROR(L54/L$5,0) -> 0 | Y54: =M54/M$5 -> 1017.316 | Z54: =N54/N$5 -> 927.12843 | AA54: =O54/O$5 -> 819.80519 | AB54: =P54/P$5 -> 690.47619 | AC54: =AB54/$AB$74 -> 0.05238421
B55: -2 | D55: Chi phí lương T13, Phép năm | E55: ='CP.NS'!C7+'CP.NS'!C16+'CP.NS'!C44 -> 31333333 | F55: ='CP.NS'!D7+'CP.NS'!D16+'CP.NS'!D44 -> 42833333 | G55: ='CP.NS'!E7+'CP.NS'!E16+'CP.NS'!E44 -> 50500000 | H55: ='CP.NS'!F7+'CP.NS'!F16+'CP.NS'!F44 -> 53166667 | I55: ='CP.NS'!C26+'CP.NS'!C35 -> 0 | J55: ='CP.NS'!D26+'CP.NS'!D35 -> 0 | K55: ='CP.NS'!E26+'CP.NS'!E35 -> 0 | L55: ='CP.NS'!F26+'CP.NS'!F35 -> 0 | M55: =E55+I55 -> 31333333 | N55: =F55+J55 -> 42833333 | O55: =G55+K55 -> 50500000 | P55: =H55+L55 -> 53166667 | Q55: =E55/E$5 -> 84.776335 | R55: =F55/F$5 -> 77.260702 | S55: =G55/G$5 -> 68.3171 | T55: =H55/H$5 -> 57.539683 | U55: =IFERROR(I55/I$5,0) -> 0 | V55: =IFERROR(J55/J$5,0) -> 0 | W55: =IFERROR(K55/K$5,0) -> 0 | X55: =IFERROR(L55/L$5,0) -> 0 | Y55: =M55/M$5 -> 84.776335 | Z55: =N55/N$5 -> 77.260702 | AA55: =O55/O$5 -> 68.3171 | AB55: =P55/P$5 -> 57.539683 | AC55: =AB55/$AB$74 -> 0.0043653509
B56: -3 | D56: Chi phí lương ngoài giờ | E56: ='CP.NS'!C8+'CP.NS'!C17+'CP.NS'!C45 -> 11280000 | F56: ='CP.NS'!D8+'CP.NS'!D17+'CP.NS'!D45 -> 15420000 | G56: ='CP.NS'!E8+'CP.NS'!E17+'CP.NS'!E45 -> 18180000 | H56: ='CP.NS'!F8+'CP.NS'!F17+'CP.NS'!F45 -> 19140000 | I56: ='CP.NS'!C27+'CP.NS'!C36 -> 0 | J56: ='CP.NS'!D27+'CP.NS'!D36 -> 0 | K56: ='CP.NS'!E27+'CP.NS'!E36 -> 0 | L56: ='CP.NS'!F27+'CP.NS'!F36 -> 0 | M56: =E56+I56 -> 11280000 | N56: =F56+J56 -> 15420000 | O56: =G56+K56 -> 18180000 | P56: =H56+L56 -> 19140000 | Q56: =E56/E$5 -> 30.519481 | R56: =F56/F$5 -> 27.813853 | S56: =G56/G$5 -> 24.594156 | T56: =H56/H$5 -> 20.714286 | U56: =IFERROR(I56/I$5,0) -> 0 | V56: =IFERROR(J56/J$5,0) -> 0 | W56: =IFERROR(K56/K$5,0) -> 0 | X56: =IFERROR(L56/L$5,0) -> 0 | Y56: =M56/M$5 -> 30.519481 | Z56: =N56/N$5 -> 27.813853 | AA56: =O56/O$5 -> 24.594156 | AB56: =P56/P$5 -> 20.714286 | AC56: =AB56/$AB$74 -> 0.0015715263
B57: -4 | D57: Chi phí lương Ca đêm | E57: ='CP.NS'!C9+'CP.NS'!C18+'CP.NS'!C46 -> 0 | F57: ='CP.NS'!D9+'CP.NS'!D18+'CP.NS'!D46 -> 0 | G57: ='CP.NS'!E9+'CP.NS'!E18+'CP.NS'!E46 -> 0 | H57: ='CP.NS'!F9+'CP.NS'!F18+'CP.NS'!F46 -> 0 | I57: ='CP.NS'!C28+'CP.NS'!C37 -> 0 | J57: ='CP.NS'!D28+'CP.NS'!D37 -> 0 | K57: ='CP.NS'!E28+'CP.NS'!E37 -> 0 | L57: ='CP.NS'!F28+'CP.NS'!F37 -> 0 | M57: =E57+I57 -> 0 | N57: =F57+J57 -> 0 | O57: =G57+K57 -> 0 | P57: =H57+L57 -> 0 | Q57: =E57/E$5 -> 0 | R57: =F57/F$5 -> 0 | S57: =G57/G$5 -> 0 | T57: =H57/H$5 -> 0 | U57: =IFERROR(I57/I$5,0) -> 0 | V57: =IFERROR(J57/J$5,0) -> 0 | W57: =IFERROR(K57/K$5,0) -> 0 | X57: =IFERROR(L57/L$5,0) -> 0 | Y57: =M57/M$5 -> 0 | Z57: =N57/N$5 -> 0 | AA57: =O57/O$5 -> 0 | AB57: =P57/P$5 -> 0 | AC57: =AB57/$AB$74 -> 0
B58: -5 | D58: Chi phí phụ cấp theo bảng lương | E58: ='CP.NS'!C10+'CP.NS'!C19+'CP.NS'!C47 -> 18800000 | F58: ='CP.NS'!D10+'CP.NS'!D19+'CP.NS'!D47 -> 25700000 | G58: ='CP.NS'!E10+'CP.NS'!E19+'CP.NS'!E47 -> 30300000 | H58: ='CP.NS'!F10+'CP.NS'!F19+'CP.NS'!F47 -> 31900000 | I58: ='CP.NS'!C29+'CP.NS'!C38 -> 0 | J58: ='CP.NS'!D29+'CP.NS'!D38 -> 0 | K58: ='CP.NS'!E29+'CP.NS'!E38 -> 0 | L58: ='CP.NS'!F29+'CP.NS'!F38 -> 0 | M58: =E58+I58 -> 18800000 | N58: =F58+J58 -> 25700000 | O58: =G58+K58 -> 30300000 | P58: =H58+L58 -> 31900000 | Q58: =E58/E$5 -> 50.865801 | R58: =F58/F$5 -> 46.356421 | S58: =G58/G$5 -> 40.99026 | T58: =H58/H$5 -> 34.52381 | U58: =IFERROR(I58/I$5,0) -> 0 | V58: =IFERROR(J58/J$5,0) -> 0 | W58: =IFERROR(K58/K$5,0) -> 0 | X58: =IFERROR(L58/L$5,0) -> 0 | Y58: =M58/M$5 -> 50.865801 | Z58: =N58/N$5 -> 46.356421 | AA58: =O58/O$5 -> 40.99026 | AB58: =P58/P$5 -> 34.52381 | AC58: =AB58/$AB$74 -> 0.0026192105
B59: -6 | D59: Chi phí khen thưởng theo bảng lương | E59: ='CP.NS'!C11+'CP.NS'!C20+'CP.NS'!C48 -> 0 | F59: ='CP.NS'!D11+'CP.NS'!D20+'CP.NS'!D48 -> 0 | G59: ='CP.NS'!E11+'CP.NS'!E20+'CP.NS'!E48 -> 0 | H59: ='CP.NS'!F11+'CP.NS'!F20+'CP.NS'!F48 -> 0 | I59: ='CP.NS'!C30+'CP.NS'!C39 -> 0 | J59: ='CP.NS'!D30+'CP.NS'!D39 -> 0 | K59: ='CP.NS'!E30+'CP.NS'!E39 -> 0 | L59: ='CP.NS'!F30+'CP.NS'!F39 -> 0 | M59: =E59+I59 -> 0 | N59: =F59+J59 -> 0 | O59: =G59+K59 -> 0 | P59: =H59+L59 -> 0 | Q59: =E59/E$5 -> 0 | R59: =F59/F$5 -> 0 | S59: =G59/G$5 -> 0 | T59: =H59/H$5 -> 0 | U59: =IFERROR(I59/I$5,0) -> 0 | V59: =IFERROR(J59/J$5,0) -> 0 | W59: =IFERROR(K59/K$5,0) -> 0 | X59: =IFERROR(L59/L$5,0) -> 0 | Y59: =M59/M$5 -> 0 | Z59: =N59/N$5 -> 0 | AA59: =O59/O$5 -> 0 | AB59: =P59/P$5 -> 0 | AC59: =AB59/$AB$74 -> 0
B60: -7 | D60: Chi phí bảo hiểm theo lương (BHXH, BHYT, KPCĐ, BHTN) | E60: ='CP.NS'!C12+'CP.NS'!C21+'CP.NS'!C49 -> 45120000 | F60: ='CP.NS'!D12+'CP.NS'!D21+'CP.NS'!D49 -> 61680000 | G60: ='CP.NS'!E12+'CP.NS'!E21+'CP.NS'!E49 -> 72720000 | H60: ='CP.NS'!F12+'CP.NS'!F21+'CP.NS'!F49 -> 76560000 | I60: ='CP.NS'!C31+'CP.NS'!C40 -> 0 | J60: ='CP.NS'!D31+'CP.NS'!D40 -> 0 | K60: ='CP.NS'!E31+'CP.NS'!E40 -> 0 | L60: ='CP.NS'!F31+'CP.NS'!F40 -> 0 | M60: =E60+I60 -> 45120000 | N60: =F60+J60 -> 61680000 | O60: =G60+K60 -> 72720000 | P60: =H60+L60 -> 76560000 | Q60: =E60/E$5 -> 122.07792 | R60: =F60/F$5 -> 111.25541 | S60: =G60/G$5 -> 98.376623 | T60: =H60/H$5 -> 82.857143 | U60: =IFERROR(I60/I$5,0) -> 0 | V60: =IFERROR(J60/J$5,0) -> 0 | W60: =IFERROR(K60/K$5,0) -> 0 | X60: =IFERROR(L60/L$5,0) -> 0 | Y60: =M60/M$5 -> 122.07792 | Z60: =N60/N$5 -> 111.25541 | AA60: =O60/O$5 -> 98.376623 | AB60: =P60/P$5 -> 82.857143 | AC60: =AB60/$AB$74 -> 0.0062861052
B61: -8 | D61: Chi phí thuế TNCN | E61: ='CP.NS'!C13+'CP.NS'!C22+'CP.NS'!C50 -> 0 | F61: ='CP.NS'!D13+'CP.NS'!D22+'CP.NS'!D50 -> 0 | G61: ='CP.NS'!E13+'CP.NS'!E22+'CP.NS'!E50 -> 0 | H61: ='CP.NS'!F13+'CP.NS'!F22+'CP.NS'!F50 -> 0 | I61: ='CP.NS'!C32+'CP.NS'!C41 -> 0 | J61: ='CP.NS'!D32+'CP.NS'!D41 -> 0 | K61: ='CP.NS'!E32+'CP.NS'!E41 -> 0 | L61: ='CP.NS'!F32+'CP.NS'!F41 -> 0 | M61: =E61+I61 -> 0 | N61: =F61+J61 -> 0 | O61: =G61+K61 -> 0 | P61: =H61+L61 -> 0 | Q61: =E61/E$5 -> 0 | R61: =F61/F$5 -> 0 | S61: =G61/G$5 -> 0 | T61: =H61/H$5 -> 0 | U61: =IFERROR(I61/I$5,0) -> 0 | V61: =IFERROR(J61/J$5,0) -> 0 | W61: =IFERROR(K61/K$5,0) -> 0 | X61: =IFERROR(L61/L$5,0) -> 0 | Y61: =M61/M$5 -> 0 | Z61: =N61/N$5 -> 0 | AA61: =O61/O$5 -> 0 | AB61: =P61/P$5 -> 0 | AC61: =AB61/$AB$74 -> 0
B62: 2.3.2 | C62: Chi phí phúc lợi | E62: =SUM(E63:E71) -> 18262500 | F62: =SUM(F63:F71) -> 18262500 | G62: =SUM(G63:G71) -> 31906500 | H62: =SUM(H63:H71) -> 31906500 | I62: =SUM(I63:I71) -> 0 | J62: =SUM(J63:J71) -> 0 | K62: =SUM(K63:K71) -> 0 | L62: =SUM(L63:L71) -> 0 | M62: =E62+I62 -> 18262500 | N62: =F62+J62 -> 18262500 | O62: =G62+K62 -> 31906500 | P62: =H62+L62 -> 31906500 | Q62: =E62/E$5 -> 49.411526 | R62: =F62/F$5 -> 32.941017 | S62: =G62/G$5 -> 43.163555 | T62: =H62/H$5 -> 34.530844 | U62: =IFERROR(I62/I$5,0) -> 0 | V62: =IFERROR(J62/J$5,0) -> 0 | W62: =IFERROR(K62/K$5,0) -> 0 | X62: =IFERROR(L62/L$5,0) -> 0 | Y62: =M62/M$5 -> 49.411526 | Z62: =N62/N$5 -> 32.941017 | AA62: =O62/O$5 -> 43.163555 | AB62: =P62/P$5 -> 34.530844 | AC62: =AB62/$AB$74 -> 0.0026197442
B63: -1 | D63: Chi phí y tế, khám sức khỏe, bảo hiểm sức khỏe | E63: =IF(G.Định!$E$5="x",'CP.NS'!C52*G.Định!$D$73,'CP.NS'!C52) -> 1875000 | F63: =IF(G.Định!$E$5="x",'CP.NS'!D52*G.Định!$D$73,'CP.NS'!D52) -> 1875000 | G63: =IF(G.Định!$E$5="x",'CP.NS'!E52*G.Định!$D$73,'CP.NS'!E52) -> 3675000 | H63: =IF(G.Định!$E$5="x",'CP.NS'!F52*G.Định!$D$73,'CP.NS'!F52) -> 3675000 | I63: =IF(G.Định!$E$5="x",'CP.NS'!C52*G.Định!$D$74,0) -> 0 | J63: =IF(G.Định!$E$5="x",'CP.NS'!D52*G.Định!$D$74,0) -> 0 | K63: =IF(G.Định!$E$5="x",'CP.NS'!E52*G.Định!$D$74,0) -> 0 | L63: =IF(G.Định!$E$5="x",'CP.NS'!F52*G.Định!$D$74,0) -> 0 | M63: =E63+I63 -> 1875000 | N63: =F63+J63 -> 1875000 | O63: =G63+K63 -> 3675000 | P63: =H63+L63 -> 3675000 | Q63: =E63/E$5 -> 5.0730519 | R63: =F63/F$5 -> 3.3820346 | S63: =G63/G$5 -> 4.9715909 | T63: =H63/H$5 -> 3.9772727 | U63: =IFERROR(I63/I$5,0) -> 0 | V63: =IFERROR(J63/J$5,0) -> 0 | W63: =IFERROR(K63/K$5,0) -> 0 | X63: =IFERROR(L63/L$5,0) -> 0 | Y63: =M63/M$5 -> 5.0730519 | Z63: =N63/N$5 -> 3.3820346 | AA63: =O63/O$5 -> 4.9715909 | AB63: =P63/P$5 -> 3.9772727 | AC63: =AB63/$AB$74 -> 0.0003017429
B64: -2 | D64: Chi phí khen thưởng ngoài lương | E64: =IF(G.Định!$E$5="x",'CP.NS'!C53*G.Định!$D$73,'CP.NS'!C53) -> 0 | F64: =IF(G.Định!$E$5="x",'CP.NS'!D53*G.Định!$D$73,'CP.NS'!D53) -> 0 | G64: =IF(G.Định!$E$5="x",'CP.NS'!E53*G.Định!$D$73,'CP.NS'!E53) -> 0 | H64: =IF(G.Định!$E$5="x",'CP.NS'!F53*G.Định!$D$73,'CP.NS'!F53) -> 0 | I64: =IF(G.Định!$E$5="x",'CP.NS'!C53*G.Định!$D$74,0) -> 0 | J64: =IF(G.Định!$E$5="x",'CP.NS'!D53*G.Định!$D$74,0) -> 0 | K64: =IF(G.Định!$E$5="x",'CP.NS'!E53*G.Định!$D$74,0) -> 0 | L64: =IF(G.Định!$E$5="x",'CP.NS'!F53*G.Định!$D$74,0) -> 0 | M64: =E64+I64 -> 0 | N64: =F64+J64 -> 0 | O64: =G64+K64 -> 0 | P64: =H64+L64 -> 0 | Q64: =E64/E$5 -> 0 | R64: =F64/F$5 -> 0 | S64: =G64/G$5 -> 0 | T64: =H64/H$5 -> 0 | U64: =IFERROR(I64/I$5,0) -> 0 | V64: =IFERROR(J64/J$5,0) -> 0 | W64: =IFERROR(K64/K$5,0) -> 0 | X64: =IFERROR(L64/L$5,0) -> 0 | Y64: =M64/M$5 -> 0 | Z64: =N64/N$5 -> 0 | AA64: =O64/O$5 -> 0 | AB64: =P64/P$5 -> 0 | AC64: =AB64/$AB$74 -> 0
B65: -3 | D65: Chi phí suất ăn, tiền ăn giữa ca | E65: =IF(G.Định!$E$5="x",'CP.NS'!C54*G.Định!$D$73,'CP.NS'!C54) -> 1462500 | F65: =IF(G.Định!$E$5="x",'CP.NS'!D54*G.Định!$D$73,'CP.NS'!D54) -> 1462500 | G65: =IF(G.Định!$E$5="x",'CP.NS'!E54*G.Định!$D$73,'CP.NS'!E54) -> 2866500 | H65: =IF(G.Định!$E$5="x",'CP.NS'!F54*G.Định!$D$73,'CP.NS'!F54) -> 2866500 | I65: =IF(G.Định!$E$5="x",'CP.NS'!C54*G.Định!$D$74,0) -> 0 | J65: =IF(G.Định!$E$5="x",'CP.NS'!D54*G.Định!$D$74,0) -> 0 | K65: =IF(G.Định!$E$5="x",'CP.NS'!E54*G.Định!$D$74,0) -> 0 | L65: =IF(G.Định!$E$5="x",'CP.NS'!F54*G.Định!$D$74,0) -> 0 | M65: =E65+I65 -> 1462500 | N65: =F65+J65 -> 1462500 | O65: =G65+K65 -> 2866500 | P65: =H65+L65 -> 2866500 | Q65: =E65/E$5 -> 3.9569805 | R65: =F65/F$5 -> 2.637987 | S65: =G65/G$5 -> 3.8778409 | T65: =H65/H$5 -> 3.1022727 | U65: =IFERROR(I65/I$5,0) -> 0 | V65: =IFERROR(J65/J$5,0) -> 0 | W65: =IFERROR(K65/K$5,0) -> 0 | X65: =IFERROR(L65/L$5,0) -> 0 | Y65: =M65/M$5 -> 3.9569805 | Z65: =N65/N$5 -> 2.637987 | AA65: =O65/O$5 -> 3.8778409 | AB65: =P65/P$5 -> 3.1022727 | AC65: =AB65/$AB$74 -> 0.00023535946
B66: -4 | D66: Chi phí đồng phục, đồ bảo hộ lao động | E66: =IF(G.Định!$E$5="x",'CP.NS'!C55*G.Định!$D$73,'CP.NS'!C55) -> 2850000 | F66: =IF(G.Định!$E$5="x",'CP.NS'!D55*G.Định!$D$73,'CP.NS'!D55) -> 2850000 | G66: =IF(G.Định!$E$5="x",'CP.NS'!E55*G.Định!$D$73,'CP.NS'!E55) -> 4290000 | H66: =IF(G.Định!$E$5="x",'CP.NS'!F55*G.Định!$D$73,'CP.NS'!F55) -> 4290000 | I66: =IF(G.Định!$E$5="x",'CP.NS'!C55*G.Định!$D$74,0) -> 0 | J66: =IF(G.Định!$E$5="x",'CP.NS'!D55*G.Định!$D$74,0) -> 0 | K66: =IF(G.Định!$E$5="x",'CP.NS'!E55*G.Định!$D$74,0) -> 0 | L66: =IF(G.Định!$E$5="x",'CP.NS'!F55*G.Định!$D$74,0) -> 0 | M66: =E66+I66 -> 2850000 | N66: =F66+J66 -> 2850000 | O66: =G66+K66 -> 4290000 | P66: =H66+L66 -> 4290000 | Q66: =E66/E$5 -> 7.711039 | R66: =F66/F$5 -> 5.1406926 | S66: =G66/G$5 -> 5.8035714 | T66: =H66/H$5 -> 4.6428571 | U66: =IFERROR(I66/I$5,0) -> 0 | V66: =IFERROR(J66/J$5,0) -> 0 | W66: =IFERROR(K66/K$5,0) -> 0 | X66: =IFERROR(L66/L$5,0) -> 0 | Y66: =M66/M$5 -> 7.711039 | Z66: =N66/N$5 -> 5.1406926 | AA66: =O66/O$5 -> 5.8035714 | AB66: =P66/P$5 -> 4.6428571 | AC66: =AB66/$AB$74 -> 0.00035223865
B67: -5 | D67: Chi phí tiệc tất niên, tổng kết | E67: =IF(G.Định!$E$5="x",'CP.NS'!C56*G.Định!$D$73,'CP.NS'!C56) -> 1875000 | F67: =IF(G.Định!$E$5="x",'CP.NS'!D56*G.Định!$D$73,'CP.NS'!D56) -> 1875000 | G67: =IF(G.Định!$E$5="x",'CP.NS'!E56*G.Định!$D$73,'CP.NS'!E56) -> 3675000 | H67: =IF(G.Định!$E$5="x",'CP.NS'!F56*G.Định!$D$73,'CP.NS'!F56) -> 3675000 | I67: =IF(G.Định!$E$5="x",'CP.NS'!C56*G.Định!$D$74,0) -> 0 | J67: =IF(G.Định!$E$5="x",'CP.NS'!D56*G.Định!$D$74,0) -> 0 | K67: =IF(G.Định!$E$5="x",'CP.NS'!E56*G.Định!$D$74,0) -> 0 | L67: =IF(G.Định!$E$5="x",'CP.NS'!F56*G.Định!$D$74,0) -> 0 | M67: =E67+I67 -> 1875000 | N67: =F67+J67 -> 1875000 | O67: =G67+K67 -> 3675000 | P67: =H67+L67 -> 3675000 | Q67: =E67/E$5 -> 5.0730519 | R67: =F67/F$5 -> 3.3820346 | S67: =G67/G$5 -> 4.9715909 | T67: =H67/H$5 -> 3.9772727 | U67: =IFERROR(I67/I$5,0) -> 0 | V67: =IFERROR(J67/J$5,0) -> 0 | W67: =IFERROR(K67/K$5,0) -> 0 | X67: =IFERROR(L67/L$5,0) -> 0 | Y67: =M67/M$5 -> 5.0730519 | Z67: =N67/N$5 -> 3.3820346 | AA67: =O67/O$5 -> 4.9715909 | AB67: =P67/P$5 -> 3.9772727 | AC67: =AB67/$AB$74 -> 0.0003017429
B68: -6 | D68: Chi phí teambuilding | E68: =IF(G.Định!$E$5="x",'CP.NS'!C57*G.Định!$D$73,'CP.NS'!C57) -> 7500000 | F68: =IF(G.Định!$E$5="x",'CP.NS'!D57*G.Định!$D$73,'CP.NS'!D57) -> 7500000 | G68: =IF(G.Định!$E$5="x",'CP.NS'!E57*G.Định!$D$73,'CP.NS'!E57) -> 14700000 | H68: =IF(G.Định!$E$5="x",'CP.NS'!F57*G.Định!$D$73,'CP.NS'!F57) -> 14700000 | I68: =IF(G.Định!$E$5="x",'CP.NS'!C57*G.Định!$D$74,0) -> 0 | J68: =IF(G.Định!$E$5="x",'CP.NS'!D57*G.Định!$D$74,0) -> 0 | K68: =IF(G.Định!$E$5="x",'CP.NS'!E57*G.Định!$D$74,0) -> 0 | L68: =IF(G.Định!$E$5="x",'CP.NS'!F57*G.Định!$D$74,0) -> 0 | M68: =E68+I68 -> 7500000 | N68: =F68+J68 -> 7500000 | O68: =G68+K68 -> 14700000 | P68: =H68+L68 -> 14700000 | Q68: =E68/E$5 -> 20.292208 | R68: =F68/F$5 -> 13.528139 | S68: =G68/G$5 -> 19.886364 | T68: =H68/H$5 -> 15.909091 | U68: =IFERROR(I68/I$5,0) -> 0 | V68: =IFERROR(J68/J$5,0) -> 0 | W68: =IFERROR(K68/K$5,0) -> 0 | X68: =IFERROR(L68/L$5,0) -> 0 | Y68: =M68/M$5 -> 20.292208 | Z68: =N68/N$5 -> 13.528139 | AA68: =O68/O$5 -> 19.886364 | AB68: =P68/P$5 -> 15.909091 | AC68: =AB68/$AB$74 -> 0.0012069716
B69: -7 | D69: Chi phí thuê xe đưa rước nhân viên | E69: =IF(G.Định!$E$5="x",'CP.NS'!C58*G.Định!$D$73,'CP.NS'!C58) -> 0 | F69: =IF(G.Định!$E$5="x",'CP.NS'!D58*G.Định!$D$73,'CP.NS'!D58) -> 0 | G69: =IF(G.Định!$E$5="x",'CP.NS'!E58*G.Định!$D$73,'CP.NS'!E58) -> 0 | H69: =IF(G.Định!$E$5="x",'CP.NS'!F58*G.Định!$D$73,'CP.NS'!F58) -> 0 | I69: =IF(G.Định!$E$5="x",'CP.NS'!C58*G.Định!$D$74,0) -> 0 | J69: =IF(G.Định!$E$5="x",'CP.NS'!D58*G.Định!$D$74,0) -> 0 | K69: =IF(G.Định!$E$5="x",'CP.NS'!E58*G.Định!$D$74,0) -> 0 | L69: =IF(G.Định!$E$5="x",'CP.NS'!F58*G.Định!$D$74,0) -> 0 | M69: =E69+I69 -> 0 | N69: =F69+J69 -> 0 | O69: =G69+K69 -> 0 | P69: =H69+L69 -> 0 | Q69: =E69/E$5 -> 0 | R69: =F69/F$5 -> 0 | S69: =G69/G$5 -> 0 | T69: =H69/H$5 -> 0 | U69: =IFERROR(I69/I$5,0) -> 0 | V69: =IFERROR(J69/J$5,0) -> 0 | W69: =IFERROR(K69/K$5,0) -> 0 | X69: =IFERROR(L69/L$5,0) -> 0 | Y69: =M69/M$5 -> 0 | Z69: =N69/N$5 -> 0 | AA69: =O69/O$5 -> 0 | AB69: =P69/P$5 -> 0 | AC69: =AB69/$AB$74 -> 0
B70: -8 | D70: Chi phí tuyển dụng, đào tạo | E70: =IF(G.Định!$E$5="x",'CP.NS'!C59*G.Định!$D$73,'CP.NS'!C59) -> 1800000 | F70: =IF(G.Định!$E$5="x",'CP.NS'!D59*G.Định!$D$73,'CP.NS'!D59) -> 1800000 | G70: =IF(G.Định!$E$5="x",'CP.NS'!E59*G.Định!$D$73,'CP.NS'!E59) -> 1800000 | H70: =IF(G.Định!$E$5="x",'CP.NS'!F59*G.Định!$D$73,'CP.NS'!F59) -> 1800000 | I70: =IF(G.Định!$E$5="x",'CP.NS'!C59*G.Định!$D$74,0) -> 0 | J70: =IF(G.Định!$E$5="x",'CP.NS'!D59*G.Định!$D$74,0) -> 0 | K70: =IF(G.Định!$E$5="x",'CP.NS'!E59*G.Định!$D$74,0) -> 0 | L70: =IF(G.Định!$E$5="x",'CP.NS'!F59*G.Định!$D$74,0) -> 0 | M70: =E70+I70 -> 1800000 | N70: =F70+J70 -> 1800000 | O70: =G70+K70 -> 1800000 | P70: =H70+L70 -> 1800000 | Q70: =E70/E$5 -> 4.8701299 | R70: =F70/F$5 -> 3.2467532 | S70: =G70/G$5 -> 2.4350649 | T70: =H70/H$5 -> 1.9480519 | U70: =IFERROR(I70/I$5,0) -> 0 | V70: =IFERROR(J70/J$5,0) -> 0 | W70: =IFERROR(K70/K$5,0) -> 0 | X70: =IFERROR(L70/L$5,0) -> 0 | Y70: =M70/M$5 -> 4.8701299 | Z70: =N70/N$5 -> 3.2467532 | AA70: =O70/O$5 -> 2.4350649 | AB70: =P70/P$5 -> 1.9480519 | AC70: =AB70/$AB$74 -> 0.00014779244
B71: -9 | D71: Chi phí hiếu hỷ, phúc lợi khác | E71: =IF(G.Định!$E$5="x",'CP.NS'!C60*G.Định!$D$73,'CP.NS'!C60) -> 900000 | F71: =IF(G.Định!$E$5="x",'CP.NS'!D60*G.Định!$D$73,'CP.NS'!D60) -> 900000 | G71: =IF(G.Định!$E$5="x",'CP.NS'!E60*G.Định!$D$73,'CP.NS'!E60) -> 900000 | H71: =IF(G.Định!$E$5="x",'CP.NS'!F60*G.Định!$D$73,'CP.NS'!F60) -> 900000 | I71: =IF(G.Định!$E$5="x",'CP.NS'!C60*G.Định!$D$74,0) -> 0 | J71: =IF(G.Định!$E$5="x",'CP.NS'!D60*G.Định!$D$74,0) -> 0 | K71: =IF(G.Định!$E$5="x",'CP.NS'!E60*G.Định!$D$74,0) -> 0 | L71: =IF(G.Định!$E$5="x",'CP.NS'!F60*G.Định!$D$74,0) -> 0 | M71: =E71+I71 -> 900000 | N71: =F71+J71 -> 900000 | O71: =G71+K71 -> 900000 | P71: =H71+L71 -> 900000 | Q71: =E71/E$5 -> 2.4350649 | R71: =F71/F$5 -> 1.6233766 | S71: =G71/G$5 -> 1.2175325 | T71: =H71/H$5 -> 0.97402597 | U71: =IFERROR(I71/I$5,0) -> 0 | V71: =IFERROR(J71/J$5,0) -> 0 | W71: =IFERROR(K71/K$5,0) -> 0 | X71: =IFERROR(L71/L$5,0) -> 0 | Y71: =M71/M$5 -> 2.4350649 | Z71: =N71/N$5 -> 1.6233766 | AA71: =O71/O$5 -> 1.2175325 | AB71: =P71/P$5 -> 0.97402597 | AC71: =AB71/$AB$74 -> 7.3896221e-05
B72: 2.4 | C72: Chi phí tài chính (lãi vay) | E72: ='K.Hao, L.v'!C28 -> 90609191 | F72: ='K.Hao, L.v'!D28 -> 90609191 | G72: ='K.Hao, L.v'!E28 -> 90609191 | H72: ='K.Hao, L.v'!F28 -> 90609191 | I72: ='K.Hao, L.v'!C32 -> 0 | J72: ='K.Hao, L.v'!D32 -> 0 | K72: ='K.Hao, L.v'!E32 -> 0 | L72: ='K.Hao, L.v'!F32 -> 0 | M72: =E72+I72 -> 90609191 | N72: =F72+J72 -> 90609191 | O72: =G72+K72 -> 90609191 | P72: =H72+L72 -> 90609191 | Q72: =E72/E$5 -> 245.15474 | R72: =F72/F$5 -> 163.43649 | S72: =G72/G$5 -> 122.57737 | T72: =H72/H$5 -> 98.061895 | U72: =IFERROR(I72/I$5,0) -> 0 | V72: =IFERROR(J72/J$5,0) -> 0 | W72: =IFERROR(K72/K$5,0) -> 0 | X72: =IFERROR(L72/L$5,0) -> 0 | Y72: =M72/M$5 -> 245.15474 | Z72: =N72/N$5 -> 163.43649 | AA72: =O72/O$5 -> 122.57737 | AB72: =P72/P$5 -> 98.061895 | AC72: =AB72/$AB$74 -> 0.0074396409
B73: 2.5 | C73: Chi phí khấu hao | E73: ='K.Hao, L.v'!C16 -> 1.6078129e+08 | F73: ='K.Hao, L.v'!D16 -> 1.6078129e+08 | G73: ='K.Hao, L.v'!E16 -> 1.6078129e+08 | H73: ='K.Hao, L.v'!F16 -> 1.6078129e+08 | I73: ='K.Hao, L.v'!C20 -> 0 | J73: ='K.Hao, L.v'!D20 -> 0 | K73: ='K.Hao, L.v'!E20 -> 0 | L73: ='K.Hao, L.v'!F20 -> 0 | M73: =E73+I73 -> 1.6078129e+08 | N73: =F73+J73 -> 1.6078129e+08 | O73: =G73+K73 -> 1.6078129e+08 | P73: =H73+L73 -> 1.6078129e+08 | Q73: =E73/E$5 -> 435.01432 | R73: =F73/F$5 -> 290.00954 | S73: =G73/G$5 -> 217.50716 | T73: =H73/H$5 -> 174.00573 | U73: =IFERROR(I73/I$5,0) -> 0 | V73: =IFERROR(J73/J$5,0) -> 0 | W73: =IFERROR(K73/K$5,0) -> 0 | X73: =IFERROR(L73/L$5,0) -> 0 | Y73: =M73/M$5 -> 435.01432 | Z73: =N73/N$5 -> 290.00954 | AA73: =O73/O$5 -> 217.50716 | AB73: =P73/P$5 -> 174.00573 | AC73: =AB73/$AB$74 -> 0.013201255
B74: III (I+II) | C74: TỔNG GIÁ THÀNH (BIẾN PHÍ + ĐỊNH PHÍ) | E74: =E6+E21 -> 5.5173729e+09 | F74: =F6+F21 -> 7.798137e+09 | G74: =G6+G21 -> 1.0033512e+10 | H74: =H6+H21 -> 1.2179243e+10 | I74: =I6+I21 -> 0 | J74: =J6+J21 -> 0 | K74: =K6+K21 -> 0 | L74: =L6+L21 -> 0 | M74: =E74+I74 -> 5.5173729e+09 | N74: =F74+J74 -> 7.798137e+09 | O74: =G74+K74 -> 1.0033512e+10 | P74: =H74+L74 -> 1.2179243e+10 | Q74: =E74/E$5 -> 14927.957 | R74: =F74/F$5 -> 14065.904 | S74: =G74/G$5 -> 13573.474 | T74: =H74/H$5 -> 13180.998 | U74: =IFERROR(I74/I$5,0) -> 0 | V74: =IFERROR(J74/J$5,0) -> 0 | W74: =IFERROR(K74/K$5,0) -> 0 | X74: =IFERROR(L74/L$5,0) -> 0 | Y74: =M74/M$5 -> 14927.957 | Z74: =N74/N$5 -> 14065.904 | AA74: =O74/O$5 -> 13573.474 | AB74: =P74/P$5 -> 13180.998 | AC74: =AB74/$AB$74 -> 1
C75: Trong đó giá thành KHÔNG gồm NL chai B0 | E75: =E74-E10 -> 1.5173729e+09 | F75: =F74-F10 -> 1.798137e+09 | G75: =G74-G10 -> 2.0335117e+09 | H75: =H74-H10 -> 2.1792425e+09 | I75: =I74-I10 -> 0 | J75: =J74-J10 -> 0 | K75: =K74-K10 -> 0 | L75: =L74-L10 -> 0 | M75: =E75+I75 -> 1.5173729e+09 | N75: =F75+J75 -> 1.798137e+09 | O75: =G75+K75 -> 2.0335117e+09 | P75: =H75+L75 -> 2.1792425e+09 | Q75: =E75/E$5 -> 4105.4461 | R75: =F75/F$5 -> 3243.3928 | S75: =G75/G$5 -> 2750.9629 | T75: =H75/H$5 -> 2358.4876 | U75: =IFERROR(I75/I$5,0) -> 0 | V75: =IFERROR(J75/J$5,0) -> 0 | W75: =IFERROR(K75/K$5,0) -> 0 | X75: =IFERROR(L75/L$5,0) -> 0 | Y75: =M75/M$5 -> 4105.4461 | Z75: =N75/N$5 -> 3243.3928 | AA75: =O75/O$5 -> 2750.9629 | AB75: =P75/P$5 -> 2358.4876 | AC75: =AB75/$AB$74 -> 0.17893087
L76: Check: | M76: =KQKD!D97-M74 -> 0 | N76: =KQKD!E97-N74 -> 0 | O76: =KQKD!F97-O74 -> 0 | P76: =KQKD!G97-P74 -> 0

Sheet Chỉ số TC
B1: CÁC CHỈ SỐ TÀI CHÍNH
B2: STT | C2: Các chỉ tiêu | D2: Đvt | E2: H.S 40% | F2: H.S 60% | G2: H.S 80% | H2: H.S 100%
B3: 1 | C3: Sản lượng
C4: Sản lượng mua (B0) | D4: Tấn | E4: =S.Lượng!C7*12 -> 4800000 | F4: =S.Lượng!D7*12 -> 7200000 | G4: =S.Lượng!E7*12 -> 9600000 | H4: =S.Lượng!F7*12 -> 12000000
C5: Giá mua / Tấn | D5: Triệu đồng/Tấn | E5: =B.đồ!C68*1000 -> 10000000 | F5: =B.đồ!D68*1000 -> 10000000 | G5: =B.đồ!E68*1000 -> 10000000 | H5: =B.đồ!F68*1000 -> 10000000
C6: Sản lượng bán | D6: Tấn | E6: =KQKD!H4 -> 4435200 | F6: =KQKD!I4 -> 6652800 | G6: =KQKD!J4 -> 8870400 | H6: =KQKD!K4 -> 11088000
C7: Giá bán/ Tấn | D7: Triệu đồng/Tấn | E7: =KQKD!H6 -> 14272727 | F7: =KQKD!I6 -> 14272727 | G7: =KQKD!J6 -> 14272727 | H7: =KQKD!K6 -> 14272727
B8: 2 | C8: Doanh thu thuần | D8: Triệu đồng | E8: =KQKD!H5 -> 63302400000 | F8: =KQKD!I5 -> 94953600000 | G8: =KQKD!J5 -> 126604800000 | H8: =KQKD!K5 -> 158256000000
B9: 3 | C9: Lãi biến phí (gồm NVL+biến phí SX+vận chuyển) | D9: Triệu đồng | E9: =KQKD!H28 -> 1.2982154e+10 | F9: =KQKD!I28 -> 1.9473231e+10 | G9: =KQKD!J28 -> 2.5964308e+10 | H9: =KQKD!K28 -> 3.2455385e+10
C10: Lãi biến phí / Tấn | D10: Triệu đồng/Tấn | E10: =E9/E$6 -> 2927.073 | F10: =F9/F$6 -> 2927.073 | G10: =G9/G$6 -> 2927.073 | H10: =H9/H$6 -> 2927.073
C11: Lãi biến phí / Doanh thu (%) | D11: % | E11: =E9/E$8 -> 0.20508155 | F11: =F9/F$8 -> 0.20508155 | G11: =G9/G$8 -> 0.20508155 | H11: =H9/H$8 -> 0.20508155
B12: 4 | C12: Đầu tư | D12: Triệu đồng | E12: ='K.Hao, L.v'!C12 -> 22190006000 | F12: ='K.Hao, L.v'!D12 -> 22190006000 | G12: ='K.Hao, L.v'!E12 -> 22190006000 | H12: ='K.Hao, L.v'!F12 -> 22190006000
C13: NPV | D13: Triệu đồng | E13: =HV!C32 -> -2.2966054e+10 | F13: =HV!D32 -> 1.1981478e+10 | G13: =HV!E32 -> 4.5660161e+10 | H13: =HV!F32 -> 8.6844817e+10
C14: IRR | D14: % | E14: =HV!C33 -> -0.18098752 | F14: =HV!D33 -> 0.15300925 | G14: =HV!E33 -> 0.3261148 | H14: =HV!F33 -> 0.53434391
C15: Thời gian hoàn vốn | D15: Năm | E15: =HV!C34 -> #N/A | F15: =HV!D34 -> 9.422813 | G15: =HV!E34 -> 3.8089478 | H15: =HV!F34 -> 2.1618268
B16: 5 | C16: Chi phí hoạt động (không gồm CP nhân sự) | D16: Triệu đồng | E16: =KQKD!H47+KQKD!H92 -> 2506923906 | F16: =KQKD!I47+KQKD!I92 -> 2506923906 | G16: =KQKD!J47+KQKD!J92 -> 2506923906 | H16: =KQKD!K47+KQKD!K92 -> 2506923906
C17: % Chi phí hoạt động / Doanh thu | E17: =E16/E$8 -> 0.039602352 | F17: =F16/F$8 -> 0.026401568 | G17: =G16/G$8 -> 0.019801176 | H17: =H16/H$8 -> 0.015840941
B18: 6 | C18: Chi phí nhân sự | D18: Triệu đồng | E18: =KQKD!H66 -> 6009550000 | F18: =KQKD!I66 -> 8134750000 | G18: =KQKD!J66 -> 9715278000 | H18: =KQKD!K66 -> 10208078000
C19: Chi phí nhân sự / Doanh thu (%) | E19: =E18/E$8 -> 0.094933999 | F19: =F18/F$8 -> 0.085670791 | G19: =G18/G$8 -> 0.076737043 | H19: =H18/H$8 -> 0.064503576
C20: Doanh thu bình quân đầu người | D20: Triệu đồng/Người | E20: =E8/Đ.Biên!E57 -> 2532096000 | F20: =F8/Đ.Biên!F57 -> 2.4347077e+09 | G20: =G8/Đ.Biên!G57 -> 2.5837714e+09 | H20: =H8/Đ.Biên!H57 -> 2.9859623e+09
C21: Sản lượng bán bình quân đầu người | D21: Tấn/Người | E21: =E6/Đ.Biên!E57 -> 177408 | F21: =F6/Đ.Biên!F57 -> 170584.62 | G21: =G6/Đ.Biên!G57 -> 181028.57 | H21: =H6/Đ.Biên!H57 -> 209207.55
B22: 7 | C22: Chi phí sản xuất (gồm biến phí, không gồm NL) | D22: Triệu đồng | E22: =KQKD!H34+KQKD!H13-KQKD!H16 -> 6.9310253e+09 | F22: =KQKD!I34+KQKD!I13-KQKD!I16 -> 7.7591944e+09 | G22: =KQKD!J34+KQKD!J13-KQKD!J16 -> 8.5873636e+09 | H22: =KQKD!K34+KQKD!K13-KQKD!K16 -> 9.4275327e+09
C23: Chi phí sản xuất / Tấn | D23: Triệu đồng/Tấn | E23: =E22/E6*1000 -> 1562731.2 | F23: =F22/F6*1000 -> 1166305.1 | G23: =G22/G6*1000 -> 968092.03 | H23: =H22/H6*1000 -> 850246.46
C24: Chi phí sản xuất / Doanh thu (%) | E24: =E22/E8 -> 0.10949072 | F24: =F22/F8 -> 0.081715643 | G24: =G22/G8 -> 0.067828104 | H24: =H22/H8 -> 0.059571408
B25: 8 | C25: EBITDA | D25: Triệu đồng | E25: =KQKD!H105 -> -9.7669923e+08 | F25: =KQKD!I105 -> 3.0301404e+09 | G25: =KQKD!J105 -> 6.8915027e+09 | H25: =KQKD!K105 -> 1.1613447e+10
C26: % EBITDA / Doanh thu | E26: =E25/E$8 -> -0.015429103 | F26: =F25/F$8 -> 0.031911801 | G26: =G25/G$8 -> 0.054433187 | H26: =H25/H$8 -> 0.073383931
B27: 9 | C27: Chi phí khấu hao | D27: Triệu đồng | E27: =KQKD!H95 -> 1.9293755e+09 | F27: =KQKD!I95 -> 1.9293755e+09 | G27: =KQKD!J95 -> 1.9293755e+09 | H27: =KQKD!K95 -> 1.9293755e+09
C28: % Chi phí khấu hao / Doanh thu | E28: =E27/E$8 -> 0.03047871 | F28: =F27/F$8 -> 0.02031914 | G28: =G27/G$8 -> 0.015239355 | H28: =H27/H$8 -> 0.012191484
B29: 10 | C29: Lợi nhuận sau thuế | D29: Triệu đồng | E29: =KQKD!H103 -> -2.9060747e+09 | F29: =KQKD!I103 -> 1.1007649e+09 | G29: =KQKD!J103 -> 4.9621272e+09 | H29: =KQKD!K103 -> 9.6840719e+09
C30: % Lợi nhuận sau thuế / Doanh thu | E30: =E29/E$8 -> -0.045907813 | F30: =F29/F$8 -> 0.011592661 | G30: =G29/G$8 -> 0.039193832 | H30: =H29/H$8 -> 0.061192447

Sheet QL rủi ro
B1: QUẢN LÝ RỦI RO
B2: RỦI RO | C2: 1. CÔNG NGHỆ | D2: 2. CUNG ỨNG NGUYÊN LIỆU | E2: 3. THỊ TRƯỜNG ĐẦU RA | F2: 4. VẬN HÀNH | G2: 5. TUÂN THỦ
B3: Nhận diện rủi ro | C3: 1. Công nghệ MMTB phân loại không phù hợp: | D3: 1. Thiếu nguồn chai đầu vào, cạnh tranh với đối thủ | E3: 1. Giá hạt nhựa chính phẩm (vPET) giảm | F3: 1. Hiệu suất máy thấp | G3: 1. Không đáp ứng tiêu chuẩn môi trường
C4: - Máy NK không phù hợp với đặc thù nguyên liệu đầu vào ở VN | D4: 2. Giá đầu vào biến động mạnh | E4: 2. Chính sách EPR thay đổi | F4: 2. Tỷ lệ hao hụt cao | G4: 2. Không đáp ứng tiêu chuẩn PCCC
C5: - Máy (AI) không nhận diện tốt các loại chai | D5: 3. Phụ thuộc vào thương lái, sản lượng không ổn định | E5: 3. Cạnh tranh với đối thủ về giá bán hạt nhựa rPET | F5: 3. Chất lượng chai sau phân loại không đạt chuẩn | G5: 3. Các rủi ro về thuế, hóa đơn
C6: - Công suất các công đoạn không đồng bộ | F6: 4. Chi phí vận hành cao
F7: 5. KQKD bị lỗ
B8: Giải pháp kiểm soát | C8: 1. Đánh giá kỹ và chọn công nghệ/NCC phù hợp | D8: 1. Chọn địa điểm gần nguồn nguyên liệu | E8: 1. Tối ưu chi phí sản xuất để tăng cạnh tranh thông qua các giải pháp: | F8: 1. Xây dựng hệ thống KPIs để kiểm soát: | G8: 1. Xin giấy phép môi trường
D9: 2. Phát triển hệ thống NCC đồng hành, NCC chiến lược (cấp 1) | E9: - Tiêu chuẩn hóa MMTB | F9: - % Hiệu suất máy | G9: 2. Đầu tư hệ thống XLNT
D10: 3. Xây dựng hệ thống NCC vệ tinh cấp 2, cấp 3,.. | E10: - Tinh gọn định biên | F10: - Năng suất lao động (Tấn/giờ; Tấn/người) | G10: 3. Đầu tư hệ thống PCCC, mua bảo hiểm cháy nổ (nếu NX thuê phải đảm bảo có GP PCCC)
D11: 4. Đa dạng nguồn nguyên liệu (nhập khẩu) | E11: - Mua vật tư SX tập trung các Trạm | F11: - % Hao hụt | G11: 4. Chọn địa điểm cách biệt khu dân cư
E12: - Kiểm soát định mức chi phí | F12: - % Thành phần chai sau phân loại | G12: 5. Hỗ trợ NCC thủ tục đăng ký thuế, hóa đơn
E13: - Bố trí Ca sản xuất hợp lý | F13: - Chi phí vận hành/tấn
B15: Ghi chú: | D15: Rủi ro cao
D16: Rủi ro trung bình

Sheet S.Lượng
B1: SẢN LƯỢNG
B2: 1 - Sản lượng mua CHAI B0 | F2: ĐVT: Tấn
B3: Loại chai | C3: H.S 40% | D3: H.S 60% | E3: H.S 80% | F3: H.S 100%
B4: Chai B0 - Xá tròn | C4: =C$7*HLOOKUP("x",G.Định!$M$29:$P$33,ROWS(G.Định!$M$29:$M30),0) -> 320000 | D4: =D$7*HLOOKUP("x",G.Định!$M$29:$P$33,ROWS(G.Định!$M$29:$M30),0) -> 480000 | E4: =E$7*HLOOKUP("x",G.Định!$M$29:$P$33,ROWS(G.Định!$M$29:$M30),0) -> 640000 | F4: =F$7*HLOOKUP("x",G.Định!$M$29:$P$33,ROWS(G.Định!$M$29:$M30),0) -> 800000
B5: Chai B0 - Ép kiện | C5: =C$7*HLOOKUP("x",G.Định!$M$29:$P$33,ROWS(G.Định!$M$29:$M31),0) -> 80000 | D5: =D$7*HLOOKUP("x",G.Định!$M$29:$P$33,ROWS(G.Định!$M$29:$M31),0) -> 120000 | E5: =E$7*HLOOKUP("x",G.Định!$M$29:$P$33,ROWS(G.Định!$M$29:$M31),0) -> 160000 | F5: =F$7*HLOOKUP("x",G.Định!$M$29:$P$33,ROWS(G.Định!$M$29:$M31),0) -> 200000
B6: Chai B1.4 (xô tuyển -> ép kiện) | C6: =C$7*HLOOKUP("x",G.Định!$M$29:$P$33,ROWS(G.Định!$M$29:$M32),0) -> 0 | D6: =D$7*HLOOKUP("x",G.Định!$M$29:$P$33,ROWS(G.Định!$M$29:$M32),0) -> 0 | E6: =E$7*HLOOKUP("x",G.Định!$M$29:$P$33,ROWS(G.Định!$M$29:$M32),0) -> 0 | F6: =F$7*HLOOKUP("x",G.Định!$M$29:$P$33,ROWS(G.Định!$M$29:$M32),0) -> 0
B7: Tổng | C7: =HLOOKUP(C$3,G.Định!$E$8:$H$9,2,0)*HLOOKUP("x",G.Định!$E$13:$L$17,5,0) -> 400000 | D7: =HLOOKUP(D$3,G.Định!$E$8:$H$9,2,0)*HLOOKUP("x",G.Định!$E$14:$L$17,4,0) -> 600000 | E7: =HLOOKUP(E$3,G.Định!$E$8:$H$9,2,0)*HLOOKUP("x",G.Định!E15:L17,3,0) -> 800000 | F7: =HLOOKUP(F$3,G.Định!$E$8:$H$9,2,0)*HLOOKUP("x",G.Định!E16:L17,2,0) -> 1000000
B9: 2 - Sản lượng thành phẩm CHAI sau phân loại
B10: Loại chai | C10: H.S 40% | D10: H.S 60% | E10: H.S 80% | F10: H.S 100%
B11: Chai PET B1 | C11: =C$4*HLOOKUP("x",G.Định!$D$49:$F$57,ROWS(G.Định!$D$49:$D50),0)+C$5*HLOOKUP("x",G.Định!$G$49:$I$57,ROWS(G.Định!$G$49:$G50),0)+C$6*HLOOKUP("x",G.Định!$J$49:$L$57,ROWS(G.Định!$J$49:$J50),0) -> 218800 | D11: =D$4*HLOOKUP("x",G.Định!$D$49:$F$57,ROWS(G.Định!$D$49:$D50),0)+D$5*HLOOKUP("x",G.Định!$G$49:$I$57,ROWS(G.Định!$G$49:$G50),0)+D$6*HLOOKUP("x",G.Định!$J$49:$L$57,ROWS(G.Định!$J$49:$J50),0) -> 328200 | E11: =E$4*HLOOKUP("x",G.Định!$D$49:$F$57,ROWS(G.Định!$D$49:$D50),0)+E$5*HLOOKUP("x",G.Định!$G$49:$I$57,ROWS(G.Định!$G$49:$G50),0)+E$6*HLOOKUP("x",G.Định!$J$49:$L$57,ROWS(G.Định!$J$49:$J50),0) -> 437600 | F11: =F$4*HLOOKUP("x",G.Định!$D$49:$F$57,ROWS(G.Định!$D$49:$D50),0)+F$5*HLOOKUP("x",G.Định!$G$49:$I$57,ROWS(G.Định!$G$49:$G50),0)+F$6*HLOOKUP("x",G.Định!$J$49:$L$57,ROWS(G.Định!$J$49:$J50),0) -> 547000
B12: Chai PET B2.2 | C12: =C$4*HLOOKUP("x",G.Định!$D$49:$F$57,ROWS(G.Định!$D$49:$D51),0)+C$5*HLOOKUP("x",G.Định!$G$49:$I$57,ROWS(G.Định!$G$49:$G51),0)+C$6*HLOOKUP("x",G.Định!$J$49:$L$57,ROWS(G.Định!$J$49:$J51),0) -> 29600 | D12: =D$4*HLOOKUP("x",G.Định!$D$49:$F$57,ROWS(G.Định!$D$49:$D51),0)+D$5*HLOOKUP("x",G.Định!$G$49:$I$57,ROWS(G.Định!$G$49:$G51),0)+D$6*HLOOKUP("x",G.Định!$J$49:$L$57,ROWS(G.Định!$J$49:$J51),0) -> 44400 | E12: =E$4*HLOOKUP("x",G.Định!$D$49:$F$57,ROWS(G.Định!$D$49:$D51),0)+E$5*HLOOKUP("x",G.Định!$G$49:$I$57,ROWS(G.Định!$G$49:$G51),0)+E$6*HLOOKUP("x",G.Định!$J$49:$L$57,ROWS(G.Định!$J$49:$J51),0) -> 59200 | F12: =F$4*HLOOKUP("x",G.Định!$D$49:$F$57,ROWS(G.Định!$D$49:$D51),0)+F$5*HLOOKUP("x",G.Định!$G$49:$I$57,ROWS(G.Định!$G$49:$G51),0)+F$6*HLOOKUP("x",G.Định!$J$49:$L$57,ROWS(G.Định!$J$49:$J51),0) -> 74000
B13: Chai PET B4 | C13: =C$4*HLOOKUP("x",G.Định!$D$49:$F$57,ROWS(G.Định!$D$49:$D52),0)+C$5*HLOOKUP("x",G.Định!$G$49:$I$57,ROWS(G.Định!$G$49:$G52),0)+C$6*HLOOKUP("x",G.Định!$J$49:$L$57,ROWS(G.Định!$J$49:$J52),0) -> 4000 | D13: =D$4*HLOOKUP("x",G.Định!$D$49:$F$57,ROWS(G.Định!$D$49:$D52),0)+D$5*HLOOKUP("x",G.Định!$G$49:$I$57,ROWS(G.Định!$G$49:$G52),0)+D$6*HLOOKUP("x",G.Định!$J$49:$L$57,ROWS(G.Định!$J$49:$J52),0) -> 6000 | E13: =E$4*HLOOKUP("x",G.Định!$D$49:$F$57,ROWS(G.Định!$D$49:$D52),0)+E$5*HLOOKUP("x",G.Định!$G$49:$I$57,ROWS(G.Định!$G$49:$G52),0)+E$6*HLOOKUP("x",G.Định!$J$49:$L$57,ROWS(G.Định!$J$49:$J52),0) -> 8000 | F13: =F$4*HLOOKUP("x",G.Định!$D$49:$F$57,ROWS(G.Định!$D$49:$D52),0)+F$5*HLOOKUP("x",G.Định!$G$49:$I$57,ROWS(G.Định!$G$49:$G52),0)+F$6*HLOOKUP("x",G.Định!$J$49:$L$57,ROWS(G.Định!$J$49:$J52),0) -> 10000
B14: Chai PET B5 | C14: =C$4*HLOOKUP("x",G.Định!$D$49:$F$57,ROWS(G.Định!$D$49:$D53),0)+C$5*HLOOKUP("x",G.Định!$G$49:$I$57,ROWS(G.Định!$G$49:$G53),0)+C$6*HLOOKUP("x",G.Định!$J$49:$L$57,ROWS(G.Định!$J$49:$J53),0) -> 2400 | D14: =D$4*HLOOKUP("x",G.Định!$D$49:$F$57,ROWS(G.Định!$D$49:$D53),0)+D$5*HLOOKUP("x",G.Định!$G$49:$I$57,ROWS(G.Định!$G$49:$G53),0)+D$6*HLOOKUP("x",G.Định!$J$49:$L$57,ROWS(G.Định!$J$49:$J53),0) -> 3600 | E14: =E$4*HLOOKUP("x",G.Định!$D$49:$F$57,ROWS(G.Định!$D$49:$D53),0)+E$5*HLOOKUP("x",G.Định!$G$49:$I$57,ROWS(G.Định!$G$49:$G53),0)+E$6*HLOOKUP("x",G.Định!$J$49:$L$57,ROWS(G.Định!$J$49:$J53),0) -> 4800 | F14: =F$4*HLOOKUP("x",G.Định!$D$49:$F$57,ROWS(G.Định!$D$49:$D53),0)+F$5*HLOOKUP("x",G.Định!$G$49:$I$57,ROWS(G.Định!$G$49:$G53),0)+F$6*HLOOKUP("x",G.Định!$J$49:$L$57,ROWS(G.Định!$J$49:$J53),0) -> 6000
B15: Chai PET B6.2 | C15: =C$4*HLOOKUP("x",G.Định!$D$49:$F$57,ROWS(G.Định!$D$49:$D54),0)+C$5*HLOOKUP("x",G.Định!$G$49:$I$57,ROWS(G.Định!$G$49:$G54),0)+C$6*HLOOKUP("x",G.Định!$J$49:$L$57,ROWS(G.Định!$J$49:$J54),0) -> 108800 | D15: =D$4*HLOOKUP("x",G.Định!$D$49:$F$57,ROWS(G.Định!$D$49:$D54),0)+D$5*HLOOKUP("x",G.Định!$G$49:$I$57,ROWS(G.Định!$G$49:$G54),0)+D$6*HLOOKUP("x",G.Định!$J$49:$L$57,ROWS(G.Định!$J$49:$J54),0) -> 163200 | E15: =E$4*HLOOKUP("x",G.Định!$D$49:$F$57,ROWS(G.Định!$D$49:$D54),0)+E$5*HLOOKUP("x",G.Định!$G$49:$I$57,ROWS(G.Định!$G$49:$G54),0)+E$6*HLOOKUP("x",G.Định!$J$49:$L$57,ROWS(G.Định!$J$49:$J54),0) -> 217600 | F15: =F$4*HLOOKUP("x",G.Định!$D$49:$F$57,ROWS(G.Định!$D$49:$D54),0)+F$5*HLOOKUP("x",G.Định!$G$49:$I$57,ROWS(G.Định!$G$49:$G54),0)+F$6*HLOOKUP("x",G.Định!$J$49:$L$57,ROWS(G.Định!$J$49:$J54),0) -> 272000
B16: Cổ Chai PET | C16: =C$4*HLOOKUP("x",G.Định!$D$49:$F$57,ROWS(G.Định!$D$49:$D55),0)+C$5*HLOOKUP("x",G.Định!$G$49:$I$57,ROWS(G.Định!$G$49:$G55),0)+C$6*HLOOKUP("x",G.Định!$J$49:$L$57,ROWS(G.Định!$J$49:$J55),0) -> 2000 | D16: =D$4*HLOOKUP("x",G.Định!$D$49:$F$57,ROWS(G.Định!$D$49:$D55),0)+D$5*HLOOKUP("x",G.Định!$G$49:$I$57,ROWS(G.Định!$G$49:$G55),0)+D$6*HLOOKUP("x",G.Định!$J$49:$L$57,ROWS(G.Định!$J$49:$J55),0) -> 3000 | E16: =E$4*HLOOKUP("x",G.Định!$D$49:$F$57,ROWS(G.Định!$D$49:$D55),0)+E$5*HLOOKUP("x",G.Định!$G$49:$I$57,ROWS(G.Định!$G$49:$G55),0)+E$6*HLOOKUP("x",G.Định!$J$49:$L$57,ROWS(G.Định!$J$49:$J55),0) -> 4000 | F16: =F$4*HLOOKUP("x",G.Định!$D$49:$F$57,ROWS(G.Định!$D$49:$D55),0)+F$5*HLOOKUP("x",G.Định!$G$49:$I$57,ROWS(G.Định!$G$49:$G55),0)+F$6*HLOOKUP("x",G.Định!$J$49:$L$57,ROWS(G.Định!$J$49:$J55),0) -> 5000
B17: Nắp HD ép các màu | C17: =C$4*HLOOKUP("x",G.Định!$D$49:$F$57,ROWS(G.Định!$D$49:$D56),0)+C$5*HLOOKUP("x",G.Định!$G$49:$I$57,ROWS(G.Định!$G$49:$G56),0)+C$6*HLOOKUP("x",G.Định!$J$49:$L$57,ROWS(G.Định!$J$49:$J56),0) -> 4000 | D17: =D$4*HLOOKUP("x",G.Định!$D$49:$F$57,ROWS(G.Định!$D$49:$D56),0)+D$5*HLOOKUP("x",G.Định!$G$49:$I$57,ROWS(G.Định!$G$49:$G56),0)+D$6*HLOOKUP("x",G.Định!$J$49:$L$57,ROWS(G.Định!$J$49:$J56),0) -> 6000 | E17: =E$4*HLOOKUP("x",G.Định!$D$49:$F$57,ROWS(G.Định!$D$49:$D56),0)+E$5*HLOOKUP("x",G.Định!$G$49:$I$57,ROWS(G.Định!$G$49:$G56),0)+E$6*HLOOKUP("x",G.Định!$J$49:$L$57,ROWS(G.Định!$J$49:$J56),0) -> 8000 | F17: =F$4*HLOOKUP("x",G.Định!$D$49:$F$57,ROWS(G.Định!$D$49:$D56),0)+F$5*HLOOKUP("x",G.Định!$G$49:$I$57,ROWS(G.Định!$G$49:$G56),0)+F$6*HLOOKUP("x",G.Định!$J$49:$L$57,ROWS(G.Định!$J$49:$J56),0) -> 10000
B18: Tổng | C18: =SUM(C11:C17) -> 369600 | D18: =SUM(D11:D17) -> 554400 | E18: =SUM(E11:E17) -> 739200 | F18: =SUM(F11:F17) -> 924000
B20: 3 - Sản lượng thành phẩm VẢY
B21: Loại vảy | C21: H.S 40% | D21: H.S 60% | E21: H.S 80% | F21: H.S 100%
B22: Chai PET B1 | C22: =C11*HLOOKUP("x",G.Định!$M$49:$O$56,ROWS(G.Định!$M$49:$M50),0)*(1-HLOOKUP("x",G.Định!$P$49:$R$56,ROWS(G.Định!$P$49:$P50),0)) -> 0 | D22: =D11*HLOOKUP("x",G.Định!$M$49:$O$56,ROWS(G.Định!$M$49:$M50),0)*(1-HLOOKUP("x",G.Định!$P$49:$R$56,ROWS(G.Định!$P$49:$P50),0)) -> 0 | E22: =E11*HLOOKUP("x",G.Định!$M$49:$O$56,ROWS(G.Định!$M$49:$M50),0)*(1-HLOOKUP("x",G.Định!$P$49:$R$56,ROWS(G.Định!$P$49:$P50),0)) -> 0 | F22: =F11*HLOOKUP("x",G.Định!$M$49:$O$56,ROWS(G.Định!$M$49:$M50),0)*(1-HLOOKUP("x",G.Định!$P$49:$R$56,ROWS(G.Định!$P$49:$P50),0)) -> 0
B23: Chai PET B2.2 | C23: =C12*HLOOKUP("x",G.Định!$M$49:$O$56,ROWS(G.Định!$M$49:$M51),0)*(1-HLOOKUP("x",G.Định!$P$49:$R$56,ROWS(G.Định!$P$49:$P51),0)) -> 0 | D23: =D12*HLOOKUP("x",G.Định!$M$49:$O$56,ROWS(G.Định!$M$49:$M51),0)*(1-HLOOKUP("x",G.Định!$P$49:$R$56,ROWS(G.Định!$P$49:$P51),0)) -> 0 | E23: =E12*HLOOKUP("x",G.Định!$M$49:$O$56,ROWS(G.Định!$M$49:$M51),0)*(1-HLOOKUP("x",G.Định!$P$49:$R$56,ROWS(G.Định!$P$49:$P51),0)) -> 0 | F23: =F12*HLOOKUP("x",G.Định!$M$49:$O$56,ROWS(G.Định!$M$49:$M51),0)*(1-HLOOKUP("x",G.Định!$P$49:$R$56,ROWS(G.Định!$P$49:$P51),0)) -> 0
B24: Chai PET B4 | C24: =C13*HLOOKUP("x",G.Định!$M$49:$O$56,ROWS(G.Định!$M$49:$M52),0)*(1-HLOOKUP("x",G.Định!$P$49:$R$56,ROWS(G.Định!$P$49:$P52),0)) -> 0 | D24: =D13*HLOOKUP("x",G.Định!$M$49:$O$56,ROWS(G.Định!$M$49:$M52),0)*(1-HLOOKUP("x",G.Định!$P$49:$R$56,ROWS(G.Định!$P$49:$P52),0)) -> 0 | E24: =E13*HLOOKUP("x",G.Định!$M$49:$O$56,ROWS(G.Định!$M$49:$M52),0)*(1-HLOOKUP("x",G.Định!$P$49:$R$56,ROWS(G.Định!$P$49:$P52),0)) -> 0 | F24: =F13*HLOOKUP("x",G.Định!$M$49:$O$56,ROWS(G.Định!$M$49:$M52),0)*(1-HLOOKUP("x",G.Định!$P$49:$R$56,ROWS(G.Định!$P$49:$P52),0)) -> 0
B25: Chai PET B5 | C25: =C14*HLOOKUP("x",G.Định!$M$49:$O$56,ROWS(G.Định!$M$49:$M53),0)*(1-HLOOKUP("x",G.Định!$P$49:$R$56,ROWS(G.Định!$P$49:$P53),0)) -> 0 | D25: =D14*HLOOKUP("x",G.Định!$M$49:$O$56,ROWS(G.Định!$M$49:$M53),0)*(1-HLOOKUP("x",G.Định!$P$49:$R$56,ROWS(G.Định!$P$49:$P53),0)) -> 0 | E25: =E14*HLOOKUP("x",G.Định!$M$49:$O$56,ROWS(G.Định!$M$49:$M53),0)*(1-HLOOKUP("x",G.Định!$P$49:$R$56,ROWS(G.Định!$P$49:$P53),0)) -> 0 | F25: =F14*HLOOKUP("x",G.Định!$M$49:$O$56,ROWS(G.Định!$M$49:$M53),0)*(1-HLOOKUP("x",G.Định!$P$49:$R$56,ROWS(G.Định!$P$49:$P53),0)) -> 0
B26: Chai PET B6.2 | C26: =C15*HLOOKUP("x",G.Định!$M$49:$O$56,ROWS(G.Định!$M$49:$M54),0)*(1-HLOOKUP("x",G.Định!$P$49:$R$56,ROWS(G.Định!$P$49:$P54),0)) -> 0 | D26: =D15*HLOOKUP("x",G.Định!$M$49:$O$56,ROWS(G.Định!$M$49:$M54),0)*(1-HLOOKUP("x",G.Định!$P$49:$R$56,ROWS(G.Định!$P$49:$P54),0)) -> 0 | E26: =E15*HLOOKUP("x",G.Định!$M$49:$O$56,ROWS(G.Định!$M$49:$M54),0)*(1-HLOOKUP("x",G.Định!$P$49:$R$56,ROWS(G.Định!$P$49:$P54),0)) -> 0 | F26: =F15*HLOOKUP("x",G.Định!$M$49:$O$56,ROWS(G.Định!$M$49:$M54),0)*(1-HLOOKUP("x",G.Định!$P$49:$R$56,ROWS(G.Định!$P$49:$P54),0)) -> 0
B27: Cổ Chai PET | C27: =C16*HLOOKUP("x",G.Định!$M$49:$O$56,ROWS(G.Định!$M$49:$M55),0)*(1-HLOOKUP("x",G.Định!$P$49:$R$56,ROWS(G.Định!$P$49:$P55),0)) -> 0 | D27: =D16*HLOOKUP("x",G.Định!$M$49:$O$56,ROWS(G.Định!$M$49:$M55),0)*(1-HLOOKUP("x",G.Định!$P$49:$R$56,ROWS(G.Định!$P$49:$P55),0)) -> 0 | E27: =E16*HLOOKUP("x",G.Định!$M$49:$O$56,ROWS(G.Định!$M$49:$M55),0)*(1-HLOOKUP("x",G.Định!$P$49:$R$56,ROWS(G.Định!$P$49:$P55),0)) -> 0 | F27: =F16*HLOOKUP("x",G.Định!$M$49:$O$56,ROWS(G.Định!$M$49:$M55),0)*(1-HLOOKUP("x",G.Định!$P$49:$R$56,ROWS(G.Định!$P$49:$P55),0)) -> 0
B28: Nắp HD ép các màu | C28: =C17*HLOOKUP("x",G.Định!$M$49:$O$56,ROWS(G.Định!$M$49:$M56),0)*(1-HLOOKUP("x",G.Định!$P$49:$R$56,ROWS(G.Định!$P$49:$P56),0)) -> 0 | D28: =D17*HLOOKUP("x",G.Định!$M$49:$O$56,ROWS(G.Định!$M$49:$M56),0)*(1-HLOOKUP("x",G.Định!$P$49:$R$56,ROWS(G.Định!$P$49:$P56),0)) -> 0 | E28: =E17*HLOOKUP("x",G.Định!$M$49:$O$56,ROWS(G.Định!$M$49:$M56),0)*(1-HLOOKUP("x",G.Định!$P$49:$R$56,ROWS(G.Định!$P$49:$P56),0)) -> 0 | F28: =F17*HLOOKUP("x",G.Định!$M$49:$O$56,ROWS(G.Định!$M$49:$M56),0)*(1-HLOOKUP("x",G.Định!$P$49:$R$56,ROWS(G.Định!$P$49:$P56),0)) -> 0
B29: Tổng | C29: =SUM(C22:C28) -> 0 | D29: =SUM(D22:D28) -> 0 | E29: =SUM(E22:E28) -> 0 | F29: =SUM(F22:F28) -> 0
B31: 4 - Sản lượng CHAI bán cho DTR
B32: Loại chai | C32: H.S 40% | D32: H.S 60% | E32: H.S 80% | F32: H.S 100%
B33: Chai PET B1 | C33: =C11-C11*HLOOKUP("x",G.Định!$M$49:$O$56,ROWS(G.Định!$M$49:$M50),0) -> 218800 | D33: =D11-D11*HLOOKUP("x",G.Định!$M$49:$O$56,ROWS(G.Định!$M$49:$M50),0) -> 328200 | E33: =E11-E11*HLOOKUP("x",G.Định!$M$49:$O$56,ROWS(G.Định!$M$49:$M50),0) -> 437600 | F33: =F11-F11*HLOOKUP("x",G.Định!$M$49:$O$56,ROWS(G.Định!$M$49:$M50),0) -> 547000
B34: Chai PET B2.2 | C34: =C12-C12*HLOOKUP("x",G.Định!$M$49:$O$56,ROWS(G.Định!$M$49:$M51),0) -> 29600 | D34: =D12-D12*HLOOKUP("x",G.Định!$M$49:$O$56,ROWS(G.Định!$M$49:$M51),0) -> 44400 | E34: =E12-E12*HLOOKUP("x",G.Định!$M$49:$O$56,ROWS(G.Định!$M$49:$M51),0) -> 59200 | F34: =F12-F12*HLOOKUP("x",G.Định!$M$49:$O$56,ROWS(G.Định!$M$49:$M51),0) -> 74000
B35: Chai PET B4 | C35: =C13-C13*HLOOKUP("x",G.Định!$M$49:$O$56,ROWS(G.Định!$M$49:$M52),0) -> 4000 | D35: =D13-D13*HLOOKUP("x",G.Định!$M$49:$O$56,ROWS(G.Định!$M$49:$M52),0) -> 6000 | E35: =E13-E13*HLOOKUP("x",G.Định!$M$49:$O$56,ROWS(G.Định!$M$49:$M52),0) -> 8000 | F35: =F13-F13*HLOOKUP("x",G.Định!$M$49:$O$56,ROWS(G.Định!$M$49:$M52),0) -> 10000
B36: Chai PET B5 | C36: =C14-C14*HLOOKUP("x",G.Định!$M$49:$O$56,ROWS(G.Định!$M$49:$M53),0) -> 2400 | D36: =D14-D14*HLOOKUP("x",G.Định!$M$49:$O$56,ROWS(G.Định!$M$49:$M53),0) -> 3600 | E36: =E14-E14*HLOOKUP("x",G.Định!$M$49:$O$56,ROWS(G.Định!$M$49:$M53),0) -> 4800 | F36: =F14-F14*HLOOKUP("x",G.Định!$M$49:$O$56,ROWS(G.Định!$M$49:$M53),0) -> 6000
B37: Chai PET B6.2 | C37: =C15-C15*HLOOKUP("x",G.Định!$M$49:$O$56,ROWS(G.Định!$M$49:$M54),0) -> 108800 | D37: =D15-D15*HLOOKUP("x",G.Định!$M$49:$O$56,ROWS(G.Định!$M$49:$M54),0) -> 163200 | E37: =E15-E15*HLOOKUP("x",G.Định!$M$49:$O$56,ROWS(G.Định!$M$49:$M54),0) -> 217600 | F37: =F15-F15*HLOOKUP("x",G.Định!$M$49:$O$56,ROWS(G.Định!$M$49:$M54),0) -> 272000
B38: Cổ Chai PET | C38: =C16-C16*HLOOKUP("x",G.Định!$M$49:$O$56,ROWS(G.Định!$M$49:$M55),0) -> 2000 | D38: =D16-D16*HLOOKUP("x",G.Định!$M$49:$O$56,ROWS(G.Định!$M$49:$M55),0) -> 3000 | E38: =E16-E16*HLOOKUP("x",G.Định!$M$49:$O$56,ROWS(G.Định!$M$49:$M55),0) -> 4000 | F38: =F16-F16*HLOOKUP("x",G.Định!$M$49:$O$56,ROWS(G.Định!$M$49:$M55),0) -> 5000
B39: Nắp HD ép các màu | C39: =C17-C17*HLOOKUP("x",G.Định!$M$49:$O$56,ROWS(G.Định!$M$49:$M56),0) -> 4000 | D39: =D17-D17*HLOOKUP("x",G.Định!$M$49:$O$56,ROWS(G.Định!$M$49:$M56),0) -> 6000 | E39: =E17-E17*HLOOKUP("x",G.Định!$M$49:$O$56,ROWS(G.Định!$M$49:$M56),0) -> 8000 | F39: =F17-F17*HLOOKUP("x",G.Định!$M$49:$O$56,ROWS(G.Định!$M$49:$M56),0) -> 10000
B40: Tổng | C40: =SUM(C33:C39) -> 369600 | D40: =SUM(D33:D39) -> 554400 | E40: =SUM(E33:E39) -> 739200 | F40: =SUM(F33:F39) -> 924000
B42: Tổng sản lượng BÁN (Chai + Vảy) | C42: =C29+C40 -> 369600 | D42: =D29+D40 -> 554400 | E42: =E29+E40 -> 739200 | F42: =F29+F40 -> 924000
B45: Sản lượng chai đưa vô băm
B46: Loại vảy | C46: 500T | D46: 1.000T | E46: 1.500T | F46: 2.000T
B47: Chai PET B1 | C47: =C11*HLOOKUP("x",G.Định!$M$49:$O$56,ROWS(G.Định!$M$49:$M50),0) -> 0 | D47: =D11*HLOOKUP("x",G.Định!$M$49:$O$56,ROWS(G.Định!$M$49:$M50),0) -> 0 | E47: =E11*HLOOKUP("x",G.Định!$M$49:$O$56,ROWS(G.Định!$M$49:$M50),0) -> 0 | F47: =F11*HLOOKUP("x",G.Định!$M$49:$O$56,ROWS(G.Định!$M$49:$M50),0) -> 0
