Workbook
Name \0: #REF!
Name \0: #REF!
Name \A: #REF!
Name \A: #REF!
Name \B: #REF!
Name \B: #REF!
Name \c: #REF!
Name \D: #REF!
Name \E: #REF!
Name \F: #REF!
Name \g: #REF!
Name \H: #REF!
Name \L: #REF!
Name \P: #REF!
Name \S: #REF!
Name \T: #REF!
Name \V: #REF!
Name _: #REF!
Name __2PrintPi: #REF!
Name _1_0PrintPi: #REF!
Name _1DealsMAVCPMJVExt: #REF!
Name _1tradebloc: #REF!
Name _2: #REF!
Name _2AFGearingRatios: #REF!
Name _2PrintPi: #REF!
Name _2RAWAssetFinancing: #REF!
Name _2RAWEquityProviders: #REF!
Name _2RAWSellers: #REF!
Name _483_1M: #REF!
Name _BIG6: #REF!
Name _DAT1: #REF!
Name _DAT10: #REF!
Name _DAT11: #REF!
Name _DAT12: #REF!
Name _DAT13: #REF!
Name _DAT14: #REF!
Name _DAT2: #REF!
Name _DAT3: #REF!
Name _DAT4: #REF!
Name _DAT5: #REF!
Name _DAT6: #REF!
Name _DAT7: #REF!
Name _DAT8: #REF!
Name _DAT9: #REF!
Name _DLX1.USE: #REF!
Name _DLX2.USE7: #REF!
Name _newscore: #REF!
Name _PLT40: #REF!
Name _Regression_Int: 1
Name A: #REF!
Name AAE: #REF!
Name AAH: #REF!
Name AAP: #REF!
Name ABE: #REF!
Name ABH: #REF!
Name ABP: #REF!
Name AE: #REF!
Name AFKAIRCURRENT: #REF!
Name AH: #REF!
Name AIRCOVMTHLYD: #REF!

Sheet SC CONSIDERATION
E1: • Mã: 39076100 áp dụng cho hạt rPET có chỉ số độ nhớt từ 78ml/g trở lên | F1: 39076100
E2: • Mã: 39076910 áp dụng cho hạt rPET có chỉ số độ nhớt dưới 78ml/g | F2: 39076910
E4: GNI per Capita by Country 2024 (worldpopulationreview.com)
A5: GNIPC.pdf (worldbank.org) | E5: GNI per Capita by Country 2024
A6: Country | B6: GNI per capita ($) | E6: Country | F6: GNI per capita, Atlas | G6: GNI per capita, PPP | H6: GNI, Atlas | I6: TO CONSIDER | J6: EXPORT OF RPET | K6: IMPORT OF RPET | L6: EXPORT SURPLUS | M6: PIC
A7: Liechtenstein | B7: 116600 | C7: 2009 | E7: China | F7: 11880 | G7: 19160 | H7: $16.79 Mn | J7: =SUMIFS('Export Data'!$B$13:$B$176,'Export Data'!$A$13:$A$176,'SC CONSIDERATION'!E7) -> 10750920 | K7: =SUMIFS('Imports Data'!$B$13:$B$234,'Imports Data'!$A$13:$A$234,'SC CONSIDERATION'!E7) -> 6969491 | L7: =J7-K7 -> 3781429
A8: Norway | B8: 102460 | C8: 2023 | E8: United States of America | F8: 70930 | G8: 70480 | H8: $23.54 Mn | J8: =SUMIFS('Export Data'!$B$13:$B$176,'Export Data'!$A$13:$A$176,'SC CONSIDERATION'!E8) -> 5633830 | K8: =SUMIFS('Imports Data'!$B$13:$B$234,'Imports Data'!$A$13:$A$234,'SC CONSIDERATION'!E8) -> 4483176 | L8: =J8-K8 -> 1150654
A9: San Marino | B9: 47120 | C9: 2021 | E9: Korea, Republic of | F9: 35110 | G9: 47770 | H9: $1.82 Mn | J9: =SUMIFS('Export Data'!$B$13:$B$176,'Export Data'!$A$13:$A$176,'SC CONSIDERATION'!E9) -> 5306241 | K9: =SUMIFS('Imports Data'!$B$13:$B$234,'Imports Data'!$A$13:$A$234,'SC CONSIDERATION'!E9) -> 1254778 | L9: =J9-K9 -> 4051463
A10: Austria | B10: 55070 | C10: 2023 | E10: Germany | F10: 51660 | G10: 59630 | H10: $4.30 Mn | J10: =SUMIFS('Export Data'!$B$13:$B$176,'Export Data'!$A$13:$A$176,'SC CONSIDERATION'!E10) -> 4885272 | K10: =SUMIFS('Imports Data'!$B$13:$B$234,'Imports Data'!$A$13:$A$234,'SC CONSIDERATION'!E10) -> 4248847 | L10: =J10-K10 -> 636425
A11: French Polynesia (France) | B11: 18560 | C11: 2000 | E11: Netherlands | F11: 55200 | G11: 63370 | H11: 967837.42 | J11: =SUMIFS('Export Data'!$B$13:$B$176,'Export Data'!$A$13:$A$176,'SC CONSIDERATION'!E11) -> 4148736 | K11: =SUMIFS('Imports Data'!$B$13:$B$234,'Imports Data'!$A$13:$A$234,'SC CONSIDERATION'!E11) -> 1198553 | L11: =J11-K11 -> 2950183
A12: Costa Rica | B12: 13850 | C12: 2023 | E12: Belgium | F12: 50490 | G12: 59430 | H12: 585375.4 | J12: =SUMIFS('Export Data'!$B$13:$B$176,'Export Data'!$A$13:$A$176,'SC CONSIDERATION'!E12) -> 3402459 | K12: =SUMIFS('Imports Data'!$B$13:$B$234,'Imports Data'!$A$13:$A$234,'SC CONSIDERATION'!E12) -> 2097351 | L12: =J12-K12 -> 1305108
A13: United Arab Emirates | B13: 53290 | C13: 2023 | E13: Italy | F13: 35990 | G13: 46450 | H13: $2.13 Mn | J13: =SUMIFS('Export Data'!$B$13:$B$176,'Export Data'!$A$13:$A$176,'SC CONSIDERATION'!E13) -> 2433530 | K13: =SUMIFS('Imports Data'!$B$13:$B$234,'Imports Data'!$A$13:$A$234,'SC CONSIDERATION'!E13) -> 2897825 | L13: =J13-K13 -> -464295
A14: Israel | B14: 55020 | C14: 2023 | E14: Thailand | F14: 7090 | G14: 18120 | H14: 507856.67 | J14: =SUMIFS('Export Data'!$B$13:$B$176,'Export Data'!$A$13:$A$176,'SC CONSIDERATION'!E14) -> 2365823 | K14: =SUMIFS('Imports Data'!$B$13:$B$234,'Imports Data'!$A$13:$A$234,'SC CONSIDERATION'!E14) -> 1075708 | L14: =J14-K14 -> 1290115 | M14: TÂN
A15: Singapore | B15: 70590 | C15: 2023 | E15: Japan | F15: 42650 | G15: 44570 | H15: $5.36 Mn | J15: =SUMIFS('Export Data'!$B$13:$B$176,'Export Data'!$A$13:$A$176,'SC CONSIDERATION'!E15) -> 2335669 | K15: =SUMIFS('Imports Data'!$B$13:$B$234,'Imports Data'!$A$13:$A$234,'SC CONSIDERATION'!E15) -> 2289039 | L15: =J15-K15 -> 46630
A16: Macau (China) | B16: 43940 | C16: 2022 | E16: Spain | F16: 29690 | G16: 40910 | H16: $1.41 Mn | J16: =SUMIFS('Export Data'!$B$13:$B$176,'Export Data'!$A$13:$A$176,'SC CONSIDERATION'!E16) -> 1851425 | K16: =SUMIFS('Imports Data'!$B$13:$B$234,'Imports Data'!$A$13:$A$234,'SC CONSIDERATION'!E16) -> 1438278 | L16: =J16-K16 -> 413147
A17: Turkmenistan | B17: 7080 | C17: 2019 | E17: Singapore | F17: 64010 | G17: 102450 | H17: 349100.86 | J17: =SUMIFS('Export Data'!$B$13:$B$176,'Export Data'!$A$13:$A$176,'SC CONSIDERATION'!E17) -> 1344380 | K17: =SUMIFS('Imports Data'!$B$13:$B$234,'Imports Data'!$A$13:$A$234,'SC CONSIDERATION'!E17) -> 573907 | L17: =J17-K17 -> 770473
A18: Bahrain | B18: 28280 | C18: 2023 | E18: Malaysia | F18: 10710 | G18: 28150 | H18: 359707.78 | J18: =SUMIFS('Export Data'!$B$13:$B$176,'Export Data'!$A$13:$A$176,'SC CONSIDERATION'!E18) -> 1155784 | K18: =SUMIFS('Imports Data'!$B$13:$B$234,'Imports Data'!$A$13:$A$234,'SC CONSIDERATION'!E18) -> 951759 | L18: =J18-K18 -> 204025
A19: Spain | B19: 32180 | C19: 2023 | E19: Saudi Arabia | F19: 21540 | G19: 46130 | H19: 755462.63 | J19: =SUMIFS('Export Data'!$B$13:$B$176,'Export Data'!$A$13:$A$176,'SC CONSIDERATION'!E19) -> 990414 | K19: =SUMIFS('Imports Data'!$B$13:$B$234,'Imports Data'!$A$13:$A$234,'SC CONSIDERATION'!E19) -> 290614 | L19: =J19-K19 -> 699800
A20: Canada | B20: 53930 | C20: 2023 | E20: France | F20: 44160 | G20: 51660 | H20: $2.99 Mn | J20: =SUMIFS('Export Data'!$B$13:$B$176,'Export Data'!$A$13:$A$176,'SC CONSIDERATION'!E20) -> 949718 | K20: =SUMIFS('Imports Data'!$B$13:$B$234,'Imports Data'!$A$13:$A$234,'SC CONSIDERATION'!E20) -> 2054554 | L20: =J20-K20 -> -1104836
A21: Sweden | B21: 61650 | C21: 2023 | E21: Viet Nam | F21: 3590 | G21: 11080 | H21: 350209.13 | I21: Vietnam | J21: =SUMIFS('Export Data'!$B$13:$B$176,'Export Data'!$A$13:$A$176,'SC CONSIDERATION'!E21) -> 920122 | K21: =SUMIFS('Imports Data'!$B$13:$B$234,'Imports Data'!$A$13:$A$234,'SC CONSIDERATION'!E21) -> 1953058 | L21: =J21-K21 -> -1032936
A22: Germany | B22: 53970 | C22: 2023 | E22: United Kingdom | F22: 44480 | G22: 49420 | H22: $2.99 Mn | J22: =SUMIFS('Export Data'!$B$13:$B$176,'Export Data'!$A$13:$A$176,'SC CONSIDERATION'!E22) -> 731627 | K22: =SUMIFS('Imports Data'!$B$13:$B$234,'Imports Data'!$A$13:$A$234,'SC CONSIDERATION'!E22) -> 1525023 | L22: =J22-K22 -> -793396
A23: Bermuda (UK) | B23: 134640 | C23: 2022 | E23: India | F23: 2150 | G23: 7130 | H23: $3.02 Mn | J23: =SUMIFS('Export Data'!$B$13:$B$176,'Export Data'!$A$13:$A$176,'SC CONSIDERATION'!E23) -> 726681 | K23: =SUMIFS('Imports Data'!$B$13:$B$234,'Imports Data'!$A$13:$A$234,'SC CONSIDERATION'!E23) -> 2491784 | L23: =J23-K23 -> -1765103 | M23: TÂN
A24: Denmark | B24: 73360 | C24: 2023 | E24: Mexico | F24: 9590 | G24: 19740 | H24: $1.21 Mn | J24: =SUMIFS('Export Data'!$B$13:$B$176,'Export Data'!$A$13:$A$176,'SC CONSIDERATION'!E24) -> 695311 | K24: =SUMIFS('Imports Data'!$B$13:$B$234,'Imports Data'!$A$13:$A$234,'SC CONSIDERATION'!E24) -> 2659901 | L24: =J24-K24 -> -1964590 | M24: TÂN
A25: South Korea | B25: 35490 | C25: 2023 | E25: Poland | F25: 16850 | G25: 36060 | H25: 636064.2 | J25: =SUMIFS('Export Data'!$B$13:$B$176,'Export Data'!$A$13:$A$176,'SC CONSIDERATION'!E25) -> 638928 | K25: =SUMIFS('Imports Data'!$B$13:$B$234,'Imports Data'!$A$13:$A$234,'SC CONSIDERATION'!E25) -> 1168470 | L25: =J25-K25 -> -529542
A26: Bosnia and Herzegovina | B26: 8160 | C26: 2023 | E26: Switzerland | F26: 90600 | G26: 75810 | H26: 788512.43 | J26: =SUMIFS('Export Data'!$B$13:$B$176,'Export Data'!$A$13:$A$176,'SC CONSIDERATION'!E26) -> 634341 | K26: =SUMIFS('Imports Data'!$B$13:$B$234,'Imports Data'!$A$13:$A$234,'SC CONSIDERATION'!E26) -> 601372 | L26: =J26-K26 -> 32969
A27: Micronesia | B27: 4150 | C27: 2023 | E27: Lithuania | F27: 21740 | G27: 41170 | H27: 60884.17 | J27: =SUMIFS('Export Data'!$B$13:$B$176,'Export Data'!$A$13:$A$176,'SC CONSIDERATION'!E27) -> 617698 | K27: =SUMIFS('Imports Data'!$B$13:$B$234,'Imports Data'!$A$13:$A$234,'SC CONSIDERATION'!E27) -> 172147 | L27: =J27-K27 -> 445551
A28: Brunei | B28: 34970 | C28: 2023 | E28: Canada | F28: 48310 | G28: 51690 | H28: $1.85 Mn | J28: =SUMIFS('Export Data'!$B$13:$B$176,'Export Data'!$A$13:$A$176,'SC CONSIDERATION'!E28) -> 533376 | K28: =SUMIFS('Imports Data'!$B$13:$B$234,'Imports Data'!$A$13:$A$234,'SC CONSIDERATION'!E28) -> 1137298 | L28: =J28-K28 -> -603922
A29: Belarus | B29: 7780 | C29: 2023 | E29: Hong Kong, China | F29: 54460 | G29: 70600 | H29: 403721.37 | J29: =SUMIFS('Export Data'!$B$13:$B$176,'Export Data'!$A$13:$A$176,'SC CONSIDERATION'!E29) -> 458319 | K29: =SUMIFS('Imports Data'!$B$13:$B$234,'Imports Data'!$A$13:$A$234,'SC CONSIDERATION'!E29) -> 423883 | L29: =J29-K29 -> 34436
A30: Cayman Islands (UK) | B30: 68790 | C30: 2022 | E30: Egypt | F30: 3350 | G30: 12320 | H30: 365799.86 | I30: Y | J30: =SUMIFS('Export Data'!$B$13:$B$176,'Export Data'!$A$13:$A$176,'SC CONSIDERATION'!E30) -> 453422 | K30: =SUMIFS('Imports Data'!$B$13:$B$234,'Imports Data'!$A$13:$A$234,'SC CONSIDERATION'!E30) -> 327095 | L30: =J30-K30 -> 126327 | M30: MAI
A31: Dominica | B31: 8920 | C31: 2023 | E31: Austria | F31: 52760 | G31: 58370 | H31: 472474.25 | J31: =SUMIFS('Export Data'!$B$13:$B$176,'Export Data'!$A$13:$A$176,'SC CONSIDERATION'!E31) -> 392195 | K31: =SUMIFS('Imports Data'!$B$13:$B$234,'Imports Data'!$A$13:$A$234,'SC CONSIDERATION'!E31) -> 688473 | L31: =J31-K31 -> -296278
A32: Turkey | B32: 11650 | C32: 2023 | E32: Czech Republic | F32: 24430 | G32: 43360 | H32: 256631.3 | J32: =SUMIFS('Export Data'!$B$13:$B$176,'Export Data'!$A$13:$A$176,'SC CONSIDERATION'!E32) -> 357483 | K32: =SUMIFS('Imports Data'!$B$13:$B$234,'Imports Data'!$A$13:$A$234,'SC CONSIDERATION'!E32) -> 946256 | L32: =J32-K32 -> -588773
A33: Switzerland | B33: 95160 | C33: 2023 | E33: Indonesia | F33: 4180 | G33: 12680 | H33: $1.14 Mn | J33: =SUMIFS('Export Data'!$B$13:$B$176,'Export Data'!$A$13:$A$176,'SC CONSIDERATION'!E33) -> 286712 | K33: =SUMIFS('Imports Data'!$B$13:$B$234,'Imports Data'!$A$13:$A$234,'SC CONSIDERATION'!E33) -> 1024301 | L33: =J33-K33 -> -737589 | M33: TÂN
A34: Guatemala | B34: 5580 | C34: 2023 | E34: Oman | F34: 17950 | G34: 35120 | H34: 81164.63 | J34: =SUMIFS('Export Data'!$B$13:$B$176,'Export Data'!$A$13:$A$176,'SC CONSIDERATION'!E34) -> 222355 | K34: =SUMIFS('Imports Data'!$B$13:$B$234,'Imports Data'!$A$13:$A$234,'SC CONSIDERATION'!E34) -> 49962 | L34: =J34-K34 -> 172393
A35: Saint Vincent and the Grenadines | B35: 10070 | C35: 2023 | E35: Hungary | F35: 17740 | G35: 35640 | H35: 172210.65 | J35: =SUMIFS('Export Data'!$B$13:$B$176,'Export Data'!$A$13:$A$176,'SC CONSIDERATION'!E35) -> 196105 | K35: =SUMIFS('Imports Data'!$B$13:$B$234,'Imports Data'!$A$13:$A$234,'SC CONSIDERATION'!E35) -> 576155 | L35: =J35-K35 -> -380050
A36: United States | B36: 80300 | C36: 2023 | E36: Brazil | F36: 7740 | G36: 15600 | H36: $1.66 Mn | J36: =SUMIFS('Export Data'!$B$13:$B$176,'Export Data'!$A$13:$A$176,'SC CONSIDERATION'!E36) -> 194663 | K36: =SUMIFS('Imports Data'!$B$13:$B$234,'Imports Data'!$A$13:$A$234,'SC CONSIDERATION'!E36) -> 876307 | L36: =J36-K36 -> -681644 | M36: MAI
A37: Curaçao (Netherlands) | B37: 20590 | C37: 2022 | E37: Romania | F37: 14160 | G37: 35260 | H37: 270676.86 | J37: =SUMIFS('Export Data'!$B$13:$B$176,'Export Data'!$A$13:$A$176,'SC CONSIDERATION'!E37) -> 190123 | K37: =SUMIFS('Imports Data'!$B$13:$B$234,'Imports Data'!$A$13:$A$234,'SC CONSIDERATION'!E37) -> 574385 | L37: =J37-K37 -> -384262
A38: Luxembourg | B38: 88370 | C38: 2023 | E38: Pakistan | F38: 1470 | G38: 5680 | H38: 340808.73 | J38: =SUMIFS('Export Data'!$B$13:$B$176,'Export Data'!$A$13:$A$176,'SC CONSIDERATION'!E38) -> 177961 | K38: =SUMIFS('Imports Data'!$B$13:$B$234,'Imports Data'!$A$13:$A$234,'SC CONSIDERATION'!E38) -> 157518 | L38: =J38-K38 -> 20443
A39: Mexico | B39: 12100 | C39: 2023 | E39: Sweden | F39: 59540 | G39: 61090 | H39: 620153.67 | J39: =SUMIFS('Export Data'!$B$13:$B$176,'Export Data'!$A$13:$A$176,'SC CONSIDERATION'!E39) -> 174226 | K39: =SUMIFS('Imports Data'!$B$13:$B$234,'Imports Data'!$A$13:$A$234,'SC CONSIDERATION'!E39) -> 409895 | L39: =J39-K39 -> -235669
A40: South Africa | B40: 6750 | C40: 2023 | E40: Slovakia | F40: 20640 | G40: 32450 | H40: 112424.24 | J40: =SUMIFS('Export Data'!$B$13:$B$176,'Export Data'!$A$13:$A$176,'SC CONSIDERATION'!E40) -> 132375 | K40: =SUMIFS('Imports Data'!$B$13:$B$234,'Imports Data'!$A$13:$A$234,'SC CONSIDERATION'!E40) -> 410472 | L40: =J40-K40 -> -278097
A41: Serbia | B41: 10030 | C41: 2023 | E41: United Arab Emirates | F41: 41770 | G41: 71280 | H41: 387961.14 | J41: =SUMIFS('Export Data'!$B$13:$B$176,'Export Data'!$A$13:$A$176,'SC CONSIDERATION'!E41) -> 129249 | K41: =SUMIFS('Imports Data'!$B$13:$B$234,'Imports Data'!$A$13:$A$234,'SC CONSIDERATION'!E41) -> 668314 | L41: =J41-K41 -> -539065
A42: Kazakhstan | B42: 10940 | C42: 2023 | E42: Portugal | F42: 23890 | G42: 35390 | H42: 246714.17 | J42: =SUMIFS('Export Data'!$B$13:$B$176,'Export Data'!$A$13:$A$176,'SC CONSIDERATION'!E42) -> 117078 | K42: =SUMIFS('Imports Data'!$B$13:$B$234,'Imports Data'!$A$13:$A$234,'SC CONSIDERATION'!E42) -> 642930 | L42: =J42-K42 -> -525852
A43: Lebanon | B43: 3740 | C43: 2023 | E43: Slovenia | F43: 28280 | G43: 43040 | H43: 59607.79 | J43: =SUMIFS('Export Data'!$B$13:$B$176,'Export Data'!$A$13:$A$176,'SC CONSIDERATION'!E43) -> 108984 | K43: =SUMIFS('Imports Data'!$B$13:$B$234,'Imports Data'!$A$13:$A$234,'SC CONSIDERATION'!E43) -> 205662 | L43: =J43-K43 -> -96678
A44: Solomon Islands | B44: 2270 | C44: 2023 | E44: Luxembourg | F44: 88190 | G44: 83230 | H44: 56449.08 | J44: =SUMIFS('Export Data'!$B$13:$B$176,'Export Data'!$A$13:$A$176,'SC CONSIDERATION'!E44) -> 90364 | K44: =SUMIFS('Imports Data'!$B$13:$B$234,'Imports Data'!$A$13:$A$234,'SC CONSIDERATION'!E44) -> 191620 | L44: =J44-K44 -> -101256
A45: Azerbaijan | B45: 6680 | C45: 2023 | E45: Finland | F45: 53510 | G45: 55940 | H45: 296473.03 | J45: =SUMIFS('Export Data'!$B$13:$B$176,'Export Data'!$A$13:$A$176,'SC CONSIDERATION'!E45) -> 90127 | K45: =SUMIFS('Imports Data'!$B$13:$B$234,'Imports Data'!$A$13:$A$234,'SC CONSIDERATION'!E45) -> 148304 | L45: =J45-K45 -> -58177
A46: Finland | B46: 53390 | C46: 2023 | E46: South Africa | F46: 6530 | G46: 14340 | H46: 387775.52 | J46: =SUMIFS('Export Data'!$B$13:$B$176,'Export Data'!$A$13:$A$176,'SC CONSIDERATION'!E46) -> 89377 | K46: =SUMIFS('Imports Data'!$B$13:$B$234,'Imports Data'!$A$13:$A$234,'SC CONSIDERATION'!E46) -> 202650 | L46: =J46-K46 -> -113273
A47: Maldives | B47: 11030 | C47: 2023 | E47: Greece | F47: 20000 | G47: 31480 | H47: 212806.98 | J47: =SUMIFS('Export Data'!$B$13:$B$176,'Export Data'!$A$13:$A$176,'SC CONSIDERATION'!E47) -> 81396 | K47: =SUMIFS('Imports Data'!$B$13:$B$234,'Imports Data'!$A$13:$A$234,'SC CONSIDERATION'!E47) -> 187693 | L47: =J47-K47 -> -106297
A48: United Kingdom | B48: 47800 | C48: 2023 | E48: Colombia | F48: 6190 | G48: 16540 | H48: 318932.01 | J48: =SUMIFS('Export Data'!$B$13:$B$176,'Export Data'!$A$13:$A$176,'SC CONSIDERATION'!E48) -> 80889 | K48: =SUMIFS('Imports Data'!$B$13:$B$234,'Imports Data'!$A$13:$A$234,'SC CONSIDERATION'!E48) -> 318811 | L48: =J48-K48 -> -237922 | M48: MAI
A49: Dominican Republic | B49: 9700 | C49: 2023 | E49: Israel | F49: 49290 | G49: 44060 | H49: 461515 | J49: =SUMIFS('Export Data'!$B$13:$B$176,'Export Data'!$A$13:$A$176,'SC CONSIDERATION'!E49) -> 78318 | K49: =SUMIFS('Imports Data'!$B$13:$B$234,'Imports Data'!$A$13:$A$234,'SC CONSIDERATION'!E49) -> 259272 | L49: =J49-K49 -> -180954
A50: Isle of Man (UK) | B50: 76300 | C50: 2021 | E50: Russian Federation | F50: 11610 | G50: 32070 | H50: $1.69 Mn | J50: =SUMIFS('Export Data'!$B$13:$B$176,'Export Data'!$A$13:$A$176,'SC CONSIDERATION'!E50) -> 69539 | K50: =SUMIFS('Imports Data'!$B$13:$B$234,'Imports Data'!$A$13:$A$234,'SC CONSIDERATION'!E50) -> 1000099 | L50: =J50-K50 -> -930560
A51: Morocco | B51: 3700 | C51: 2023 | E51: Latvia | F51: 19790 | G51: 33760 | H51: 37294.66 | J51: =SUMIFS('Export Data'!$B$13:$B$176,'Export Data'!$A$13:$A$176,'SC CONSIDERATION'!E51) -> 54572 | K51: =SUMIFS('Imports Data'!$B$13:$B$234,'Imports Data'!$A$13:$A$234,'SC CONSIDERATION'!E51) -> 47074 | L51: =J51-K51 -> 7498
A52: Peru | B52: 6990 | C52: 2023 | E52: Denmark | F52: 68300 | G52: 66720 | H52: 400036.92 | J52: =SUMIFS('Export Data'!$B$13:$B$176,'Export Data'!$A$13:$A$176,'SC CONSIDERATION'!E52) -> 52641 | K52: =SUMIFS('Imports Data'!$B$13:$B$234,'Imports Data'!$A$13:$A$234,'SC CONSIDERATION'!E52) -> 273932 | L52: =J52-K52 -> -221291
A53: Ivory Coast | B53: 2670 | C53: 2023 | E53: Djibouti | F53: 3080 | G53: 5300 | H53: 3406.96 | I53: Y | J53: =SUMIFS('Export Data'!$B$13:$B$176,'Export Data'!$A$13:$A$176,'SC CONSIDERATION'!E53) -> 52529 | K53: =SUMIFS('Imports Data'!$B$13:$B$234,'Imports Data'!$A$13:$A$234,'SC CONSIDERATION'!E53) -> 34684 | L53: =J53-K53 -> 17845
A54: Ukraine | B54: 5070 | C54: 2023 | E54: Croatia | F54: 17630 | G54: 34620 | H54: 68724.22 | J54: =SUMIFS('Export Data'!$B$13:$B$176,'Export Data'!$A$13:$A$176,'SC CONSIDERATION'!E54) -> 43937 | K54: =SUMIFS('Imports Data'!$B$13:$B$234,'Imports Data'!$A$13:$A$234,'SC CONSIDERATION'!E54) -> 75145 | L54: =J54-K54 -> -31208
A55: Iraq | B55: 5600 | C55: 2023 | E55: Ireland | F55: 76110 | G55: 79370 | H55: 383083.78 | J55: =SUMIFS('Export Data'!$B$13:$B$176,'Export Data'!$A$13:$A$176,'SC CONSIDERATION'!E55) -> 43642 | K55: =SUMIFS('Imports Data'!$B$13:$B$234,'Imports Data'!$A$13:$A$234,'SC CONSIDERATION'!E55) -> 209663 | L55: =J55-K55 -> -166021
A56: Djibouti | B56: 3450 | C56: 2023 | E56: Estonia | F56: 26460 | G56: 41520 | H56: 35218.92 | J56: =SUMIFS('Export Data'!$B$13:$B$176,'Export Data'!$A$13:$A$176,'SC CONSIDERATION'!E56) -> 43105 | K56: =SUMIFS('Imports Data'!$B$13:$B$234,'Imports Data'!$A$13:$A$234,'SC CONSIDERATION'!E56) -> 55633 | L56: =J56-K56 -> -12528
A57: Tuvalu | B57: 7550 | C57: 2023 | E57: Bulgaria | F57: 11200 | G57: 27200 | H57: 77004.62 | J57: =SUMIFS('Export Data'!$B$13:$B$176,'Export Data'!$A$13:$A$176,'SC CONSIDERATION'!E57) -> 42666 | K57: =SUMIFS('Imports Data'!$B$13:$B$234,'Imports Data'!$A$13:$A$234,'SC CONSIDERATION'!E57) -> 219782 | L57: =J57-K57 -> -177116
A58: Lithuania | B58: 24820 | C58: 2023 | E58: Australia | F58: 57170 | G58: 55660 | H58: $1.47 Mn | J58: =SUMIFS('Export Data'!$B$13:$B$176,'Export Data'!$A$13:$A$176,'SC CONSIDERATION'!E58) -> 32824 | K58: =SUMIFS('Imports Data'!$B$13:$B$234,'Imports Data'!$A$13:$A$234,'SC CONSIDERATION'!E58) -> 311319 | L58: =J58-K58 -> -278495
A59: Russia | B59: 14250 | C59: 2023 | E59: Tunisia | F59: 3540 | G59: 10910 | H59: 43393.75 | I59: Y | J59: =SUMIFS('Export Data'!$B$13:$B$176,'Export Data'!$A$13:$A$176,'SC CONSIDERATION'!E59) -> 31704 | K59: =SUMIFS('Imports Data'!$B$13:$B$234,'Imports Data'!$A$13:$A$234,'SC CONSIDERATION'!E59) -> 174456 | L59: =J59-K59 -> -142752
A60: Iceland | B60: 79840 | C60: 2023 | E60: Bangladesh | F60: 2570 | G60: 6840 | H60: 435530.77 | J60: =SUMIFS('Export Data'!$B$13:$B$176,'Export Data'!$A$13:$A$176,'SC CONSIDERATION'!E60) -> 31699 | K60: =SUMIFS('Imports Data'!$B$13:$B$234,'Imports Data'!$A$13:$A$234,'SC CONSIDERATION'!E60) -> 262792 | L60: =J60-K60 -> -231093
A61: Ecuador | B61: 6510 | C61: 2023 | E61: Norway | F61: 83880 | G61: 82840 | H61: 453625.12 | J61: =SUMIFS('Export Data'!$B$13:$B$176,'Export Data'!$A$13:$A$176,'SC CONSIDERATION'!E61) -> 31684 | K61: =SUMIFS('Imports Data'!$B$13:$B$234,'Imports Data'!$A$13:$A$234,'SC CONSIDERATION'!E61) -> 79835 | L61: =J61-K61 -> -48151
A62: Hungary | B62: 19820 | C62: 2023 | E62: Ecuador | F62: 5960 | G62: 11540 | H62: 106042.09 | J62: =SUMIFS('Export Data'!$B$13:$B$176,'Export Data'!$A$13:$A$176,'SC CONSIDERATION'!E62) -> 31567 | K62: =SUMIFS('Imports Data'!$B$13:$B$234,'Imports Data'!$A$13:$A$234,'SC CONSIDERATION'!E62) -> 130927 | L62: =J62-K62 -> -99360
A63: China | B63: 13400 | C63: 2023 | E63: Dominican Republic | F63: 8100 | G63: 19440 | H63: 90005.66 | J63: =SUMIFS('Export Data'!$B$13:$B$176,'Export Data'!$A$13:$A$176,'SC CONSIDERATION'!E63) -> 29534 | K63: =SUMIFS('Imports Data'!$B$13:$B$234,'Imports Data'!$A$13:$A$234,'SC CONSIDERATION'!E63) -> 124727 | L63: =J63-K63 -> -95193
A64: Saudi Arabia | B64: 28690 | C64: 2023 | E64: Peru | F64: 6460 | G64: 12780 | H64: 217752.46 | J64: =SUMIFS('Export Data'!$B$13:$B$176,'Export Data'!$A$13:$A$176,'SC CONSIDERATION'!E64) -> 29147 | K64: =SUMIFS('Imports Data'!$B$13:$B$234,'Imports Data'!$A$13:$A$234,'SC CONSIDERATION'!E64) -> 258526 | L64: =J64-K64 -> -229379
A65: Botswana | B65: 7620 | C65: 2023 | E65: Serbia | F65: 8460 | G65: 20670 | H65: 57797.66 | J65: =SUMIFS('Export Data'!$B$13:$B$176,'Export Data'!$A$13:$A$176,'SC CONSIDERATION'!E65) -> 28882 | K65: =SUMIFS('Imports Data'!$B$13:$B$234,'Imports Data'!$A$13:$A$234,'SC CONSIDERATION'!E65) -> 159085 | L65: =J65-K65 -> -130203
A66: Barbados | B66: 21280 | C66: 2023 | E66: Kazakhstan | F66: 8880 | G66: 25160 | H66: 168692.85 | J66: =SUMIFS('Export Data'!$B$13:$B$176,'Export Data'!$A$13:$A$176,'SC CONSIDERATION'!E66) -> 24367 | K66: =SUMIFS('Imports Data'!$B$13:$B$234,'Imports Data'!$A$13:$A$234,'SC CONSIDERATION'!E66) -> 187856 | L66: =J66-K66 -> -163489
A67: Saint Lucia | B67: 12400 | C67: 2023 | E67: Honduras | F67: 2490 | G67: 5620 | H67: 25542.22 | J67: =SUMIFS('Export Data'!$B$13:$B$176,'Export Data'!$A$13:$A$176,'SC CONSIDERATION'!E67) -> 23415 | K67: =SUMIFS('Imports Data'!$B$13:$B$234,'Imports Data'!$A$13:$A$234,'SC CONSIDERATION'!E67) -> 33418 | L67: =J67-K67 -> -10003
A68: Qatar | B68: 70070 | C68: 2022 | E68: Philippines | F68: 3550 | G68: 9210 | H68: 404238.06 | I68: Y | J68: =SUMIFS('Export Data'!$B$13:$B$176,'Export Data'!$A$13:$A$176,'SC CONSIDERATION'!E68) -> 19705 | K68: =SUMIFS('Imports Data'!$B$13:$B$234,'Imports Data'!$A$13:$A$234,'SC CONSIDERATION'!E68) -> 544210 | L68: =J68-K68 -> -524505 | M68: MAI
A69: Greenland (Denmark) | B69: 34800 | C69: 2007 | E69: Morocco | F69: 3620 | G69: 8730 | H69: 136408.11 | I69: Y | J69: =SUMIFS('Export Data'!$B$13:$B$176,'Export Data'!$A$13:$A$176,'SC CONSIDERATION'!E69) -> 17102 | K69: =SUMIFS('Imports Data'!$B$13:$B$234,'Imports Data'!$A$13:$A$234,'SC CONSIDERATION'!E69) -> 326745 | L69: =J69-K69 -> -309643
A70: Netherlands | B70: 60670 | C70: 2023 | E70: Iran, Islamic Republic of | F70: 3530 | G70: 16540 | H70: 310227.88 | I70: Y | J70: =SUMIFS('Export Data'!$B$13:$B$176,'Export Data'!$A$13:$A$176,'SC CONSIDERATION'!E70) -> 13686 | K70: =SUMIFS('Imports Data'!$B$13:$B$234,'Imports Data'!$A$13:$A$234,'SC CONSIDERATION'!E70) -> 72988 | L70: =J70-K70 -> -59302
A71: Ireland | B71: 80390 | C71: 2023 | E71: Nigeria | F71: 2080 | G71: 5200 | H71: 444027.94 | J71: =SUMIFS('Export Data'!$B$13:$B$176,'Export Data'!$A$13:$A$176,'SC CONSIDERATION'!E71) -> 12151 | K71: =SUMIFS('Imports Data'!$B$13:$B$234,'Imports Data'!$A$13:$A$234,'SC CONSIDERATION'!E71) -> 172300 | L71: =J71-K71 -> -160149
A72: Andorra | B72: 50080 | C72: 2022 | E72: Kenya | F72: 2080 | G72: 5130 | H72: 110400.89 | J72: =SUMIFS('Export Data'!$B$13:$B$176,'Export Data'!$A$13:$A$176,'SC CONSIDERATION'!E72) -> 11624 | K72: =SUMIFS('Imports Data'!$B$13:$B$234,'Imports Data'!$A$13:$A$234,'SC CONSIDERATION'!E72) -> 98021 | L72: =J72-K72 -> -86397
A73: Poland | B73: 19730 | C73: 2023 | E73: Guatemala | F73: 4940 | G73: 9590 | H73: 84534.76 | J73: =SUMIFS('Export Data'!$B$13:$B$176,'Export Data'!$A$13:$A$176,'SC CONSIDERATION'!E73) -> 10514 | K73: =SUMIFS('Imports Data'!$B$13:$B$234,'Imports Data'!$A$13:$A$234,'SC CONSIDERATION'!E73) -> 101364 | L73: =J73-K73 -> -90850
A74: World | B74: 13212 | C74: 2023 | E74: Jordan | F74: 4170 | G74: 10080 | H74: 46535.04 | J74: =SUMIFS('Export Data'!$B$13:$B$176,'Export Data'!$A$13:$A$176,'SC CONSIDERATION'!E74) -> 9562 | K74: =SUMIFS('Imports Data'!$B$13:$B$234,'Imports Data'!$A$13:$A$234,'SC CONSIDERATION'!E74) -> 80027 | L74: =J74-K74 -> -70465
A75: Libya | B75: 7570 | C75: 2023 | E75: Paraguay | F75: 5740 | G75: 14600 | H75: 38513.12 | J75: =SUMIFS('Export Data'!$B$13:$B$176,'Export Data'!$A$13:$A$176,'SC CONSIDERATION'!E75) -> 9146 | K75: =SUMIFS('Imports Data'!$B$13:$B$234,'Imports Data'!$A$13:$A$234,'SC CONSIDERATION'!E75) -> 61653 | L75: =J75-K75 -> -52507
A76: Grenada | B76: 9800 | C76: 2023 | E76: Belarus | F76: 6940 | G76: 20860 | H76: 64824.2 | J76: =SUMIFS('Export Data'!$B$13:$B$176,'Export Data'!$A$13:$A$176,'SC CONSIDERATION'!E76) -> 8873 | K76: =SUMIFS('Imports Data'!$B$13:$B$234,'Imports Data'!$A$13:$A$234,'SC CONSIDERATION'!E76) -> 56203 | L76: =J76-K76 -> -47330
A77: Croatia | B77: 20670 | C77: 2023 | E77: Chile | F77: 14780 | G77: 27020 | H77: 288125.21 | J77: =SUMIFS('Export Data'!$B$13:$B$176,'Export Data'!$A$13:$A$176,'SC CONSIDERATION'!E77) -> 8475 | K77: =SUMIFS('Imports Data'!$B$13:$B$234,'Imports Data'!$A$13:$A$234,'SC CONSIDERATION'!E77) -> 195813 | L77: =J77-K77 -> -187338
A78: New Zealand | B78: 48610 | C78: 2023 | E78: Myanmar | F78: 1170 | G78: 4310 | H78: 62771.31 | J78: =SUMIFS('Export Data'!$B$13:$B$176,'Export Data'!$A$13:$A$176,'SC CONSIDERATION'!E78) -> 6994 | K78: =SUMIFS('Imports Data'!$B$13:$B$234,'Imports Data'!$A$13:$A$234,'SC CONSIDERATION'!E78) -> 96092 | L78: =J78-K78 -> -89098
A79: Italy | B79: 38200 | C79: 2023 | E79: Algeria | F79: 3660 | G79: 11860 | H79: 161494.85 | I79: Y | J79: =SUMIFS('Export Data'!$B$13:$B$176,'Export Data'!$A$13:$A$176,'SC CONSIDERATION'!E79) -> 6984 | K79: =SUMIFS('Imports Data'!$B$13:$B$234,'Imports Data'!$A$13:$A$234,'SC CONSIDERATION'!E79) -> 328178 | L79: =J79-K79 -> -321194
A80: Moldova | B80: 6110 | C80: 2023 | E80: Costa Rica | F80: 12310 | G80: 21810 | H80: 63469.56 | J80: =SUMIFS('Export Data'!$B$13:$B$176,'Export Data'!$A$13:$A$176,'SC CONSIDERATION'!E80) -> 6944 | K80: =SUMIFS('Imports Data'!$B$13:$B$234,'Imports Data'!$A$13:$A$234,'SC CONSIDERATION'!E80) -> 75411 | L80: =J80-K80 -> -68467
A81: Estonia | B81: 27240 | C81: 2023 | E81: Nepal | F81: 1220 | G81: 4230 | H81: 36590.88 | J81: =SUMIFS('Export Data'!$B$13:$B$176,'Export Data'!$A$13:$A$176,'SC CONSIDERATION'!E81) -> 6814 | K81: =SUMIFS('Imports Data'!$B$13:$B$234,'Imports Data'!$A$13:$A$234,'SC CONSIDERATION'!E81) -> 37729 | L81: =J81-K81 -> -30915
A82: Belgium | B82: 54530 | C82: 2023 | E82: Tanzania, United Republic of | F82: 1100 | G82: 2830 | H82: 67787.89 | J82: =SUMIFS('Export Data'!$B$13:$B$176,'Export Data'!$A$13:$A$176,'SC CONSIDERATION'!E82) -> 6755 | K82: =SUMIFS('Imports Data'!$B$13:$B$234,'Imports Data'!$A$13:$A$234,'SC CONSIDERATION'!E82) -> 152657 | L82: =J82-K82 -> -145902
A83: Algeria | B83: 4960 | C83: 2023 | E83: Mongolia | F83: 3730 | G83: 10950 | H83: 12474.52 | I83: Y | J83: =SUMIFS('Export Data'!$B$13:$B$176,'Export Data'!$A$13:$A$176,'SC CONSIDERATION'!E83) -> 4642 | K83: =SUMIFS('Imports Data'!$B$13:$B$234,'Imports Data'!$A$13:$A$234,'SC CONSIDERATION'!E83) -> 19615 | L83: =J83-K83 -> -14973
A84: New Caledonia (France) | B84: 37370 | C84: 2021 | E84: Argentina | F84: 9960 | G84: 23170 | H84: 456139.42 | J84: =SUMIFS('Export Data'!$B$13:$B$176,'Export Data'!$A$13:$A$176,'SC CONSIDERATION'!E84) -> 4164 | K84: =SUMIFS('Imports Data'!$B$13:$B$234,'Imports Data'!$A$13:$A$234,'SC CONSIDERATION'!E84) -> 263036 | L84: =J84-K84 -> -258872
A85: Uganda | B85: 980 | C85: 2023 | E85: Turks and Caicos Islands | F85: 21410 | G85: 20550 | H85: 965.71 | J85: =SUMIFS('Export Data'!$B$13:$B$176,'Export Data'!$A$13:$A$176,'SC CONSIDERATION'!E85) -> 3917 | K85: =SUMIFS('Imports Data'!$B$13:$B$234,'Imports Data'!$A$13:$A$234,'SC CONSIDERATION'!E85) -> 84 | L85: =J85-K85 -> 3833
A86: Belize | B86: 7190 | C86: 2023 | E86: El Salvador | F86: 4260 | G86: 9420 | H86: 26911 | J86: =SUMIFS('Export Data'!$B$13:$B$176,'Export Data'!$A$13:$A$176,'SC CONSIDERATION'!E86) -> 3637 | K86: =SUMIFS('Imports Data'!$B$13:$B$234,'Imports Data'!$A$13:$A$234,'SC CONSIDERATION'!E86) -> 179229 | L86: =J86-K86 -> -175592
A87: Mongolia | B87: 4950 | C87: 2023 | E87: Uruguay | F87: 16080 | G87: 22950 | H87: 55109.23 | J87: =SUMIFS('Export Data'!$B$13:$B$176,'Export Data'!$A$13:$A$176,'SC CONSIDERATION'!E87) -> 3178 | K87: =SUMIFS('Imports Data'!$B$13:$B$234,'Imports Data'!$A$13:$A$234,'SC CONSIDERATION'!E87) -> 133237 | L87: =J87-K87 -> -130059
A88: Marshall Islands | B88: 7570 | C88: 2023 | E88: Kyrgyzstan | F88: 1180 | G88: 4860 | H88: 7893.97 | J88: =SUMIFS('Export Data'!$B$13:$B$176,'Export Data'!$A$13:$A$176,'SC CONSIDERATION'!E88) -> 3122 | K88: =SUMIFS('Imports Data'!$B$13:$B$234,'Imports Data'!$A$13:$A$234,'SC CONSIDERATION'!E88) -> 48755 | L88: =J88-K88 -> -45633
A89: Jordan | B89: 4460 | C89: 2023 | E89: Albania | F89: 6110 | G89: 15490 | H89: 17183.97 | J89: =SUMIFS('Export Data'!$B$13:$B$176,'Export Data'!$A$13:$A$176,'SC CONSIDERATION'!E89) -> 2957 | K89: =SUMIFS('Imports Data'!$B$13:$B$234,'Imports Data'!$A$13:$A$234,'SC CONSIDERATION'!E89) -> 19521 | L89: =J89-K89 -> -16564
A90: Kosovo | B90: 5980 | C90: 2023 | E90: Lebanon | F90: 5110 | G90: 13700 | H90: 28593.82 | J90: =SUMIFS('Export Data'!$B$13:$B$176,'Export Data'!$A$13:$A$176,'SC CONSIDERATION'!E90) -> 2704 | K90: =SUMIFS('Imports Data'!$B$13:$B$234,'Imports Data'!$A$13:$A$234,'SC CONSIDERATION'!E90) -> 56503 | L90: =J90-K90 -> -53799
A91: Malta | B91: 34240 | C91: 2023 | E91: Ukraine | F91: 4120 | G91: 13860 | H91: 170654.88 | J91: =SUMIFS('Export Data'!$B$13:$B$176,'Export Data'!$A$13:$A$176,'SC CONSIDERATION'!E91) -> 2678 | K91: =SUMIFS('Imports Data'!$B$13:$B$234,'Imports Data'!$A$13:$A$234,'SC CONSIDERATION'!E91) -> 256704 | L91: =J91-K91 -> -254026
A92: Bahamas | B92: 31990 | C92: 2023 | E92: Uzbekistan | F92: 1960 | G92: 8520 | H92: 68578.9 | J92: =SUMIFS('Export Data'!$B$13:$B$176,'Export Data'!$A$13:$A$176,'SC CONSIDERATION'!E92) -> 2628 | K92: =SUMIFS('Imports Data'!$B$13:$B$234,'Imports Data'!$A$13:$A$234,'SC CONSIDERATION'!E92) -> 180199 | L92: =J92-K92 -> -177571
A93: Jamaica | B93: 6150 | C93: 2023 | E93: New Zealand | F93: 45230 | G93: 45440 | H93: 231716.72 | J93: =SUMIFS('Export Data'!$B$13:$B$176,'Export Data'!$A$13:$A$176,'SC CONSIDERATION'!E93) -> 2529 | K93: =SUMIFS('Imports Data'!$B$13:$B$234,'Imports Data'!$A$13:$A$234,'SC CONSIDERATION'!E93) -> 78620 | L93: =J93-K93 -> -76091
A94: Slovenia | B94: 30620 | C94: 2023 | E94: Ghana | F94: 2280 | G94: 5820 | H94: 74910.56 | J94: =SUMIFS('Export Data'!$B$13:$B$176,'Export Data'!$A$13:$A$176,'SC CONSIDERATION'!E94) -> 2249 | K94: =SUMIFS('Imports Data'!$B$13:$B$234,'Imports Data'!$A$13:$A$234,'SC CONSIDERATION'!E94) -> 114091 | L94: =J94-K94 -> -111842
A95: North Macedonia | B95: 7660 | C95: 2023 | E95: Nicaragua | F95: 1950 | G95: 5800 | H95: 13360.12 | J95: =SUMIFS('Export Data'!$B$13:$B$176,'Export Data'!$A$13:$A$176,'SC CONSIDERATION'!E95) -> 2216 | K95: =SUMIFS('Imports Data'!$B$13:$B$234,'Imports Data'!$A$13:$A$234,'SC CONSIDERATION'!E95) -> 4706 | L95: =J95-K95 -> -2490
A96: Palau | B96: 14250 | C96: 2023 | E96: Bolivia, Plurinational State of | F96: 3290 | G96: 8620 | H96: 39785.73 | I96: Y | J96: =SUMIFS('Export Data'!$B$13:$B$176,'Export Data'!$A$13:$A$176,'SC CONSIDERATION'!E96) -> 2007 | K96: =SUMIFS('Imports Data'!$B$13:$B$234,'Imports Data'!$A$13:$A$234,'SC CONSIDERATION'!E96) -> 44657 | L96: =J96-K96 -> -42650
A97: Mauritius | B97: 11530 | C97: 2023 | E97: Azerbaijan | F97: 4900 | G97: 15520 | H97: 49671.56 | J97: =SUMIFS('Export Data'!$B$13:$B$176,'Export Data'!$A$13:$A$176,'SC CONSIDERATION'!E97) -> 1568 | K97: =SUMIFS('Imports Data'!$B$13:$B$234,'Imports Data'!$A$13:$A$234,'SC CONSIDERATION'!E97) -> 47212 | L97: =J97-K97 -> -45644
A98: Suriname | B98: 5360 | C98: 2023 | E98: Panama | F98: 13920 | G98: 29720 | H98: 60572.52 | J98: =SUMIFS('Export Data'!$B$13:$B$176,'Export Data'!$A$13:$A$176,'SC CONSIDERATION'!E98) -> 1373 | K98: =SUMIFS('Imports Data'!$B$13:$B$234,'Imports Data'!$A$13:$A$234,'SC CONSIDERATION'!E98) -> 11570 | L98: =J98-K98 -> -10197
A99: Cyprus | B99: 30990 | C99: 2023 | E99: Mozambique | F99: 480 | G99: 1320 | H99: 15350.29 | J99: =SUMIFS('Export Data'!$B$13:$B$176,'Export Data'!$A$13:$A$176,'SC CONSIDERATION'!E99) -> 1190 | K99: =SUMIFS('Imports Data'!$B$13:$B$234,'Imports Data'!$A$13:$A$234,'SC CONSIDERATION'!E99) -> 13200 | L99: =J99-K99 -> -12010
A100: Bhutan | B100: 3590 | C100: 2022 | E100: Bahrain | F100: 22950 | G100: 46900 | H100: 33908.34 | J100: =SUMIFS('Export Data'!$B$13:$B$176,'Export Data'!$A$13:$A$176,'SC CONSIDERATION'!E100) -> 1153 | K100: =SUMIFS('Imports Data'!$B$13:$B$234,'Imports Data'!$A$13:$A$234,'SC CONSIDERATION'!E100) -> 56232 | L100: =J100-K100 -> -55079
A101: Kuwait | B101: 46140 | C101: 2023 | E101: Uganda | F101: 760 | G101: 2140 | H101: 34827.85 | J101: =SUMIFS('Export Data'!$B$13:$B$176,'Export Data'!$A$13:$A$176,'SC CONSIDERATION'!E101) -> 1134 | K101: =SUMIFS('Imports Data'!$B$13:$B$234,'Imports Data'!$A$13:$A$234,'SC CONSIDERATION'!E101) -> 142538 | L101: =J101-K101 -> -141404
...

Sheet EX-1A SV Summary
B1: rPET from Vietnam Duy Tan Group to US
B2: Circumvention & Scope Inquiries: Vietnam
B3: Vietnam Part - Surrogate Values from Egypt
B5: SV Worksheet
B7: CODE | C7: Full Name | D7: HPS | E7: Source | F7: Time Period | G7: Source Value | H7: Source Unit of Measure | I7: Reported Unit of Measure | J7: Converter | K7: Inflator | L7: Surrogate Value (Currency per Reported Unit of Measure) | M7: Exrate (USD/Currency) | N7: Surrogate Value (USD per Reported Unit of Measure)
B8: 150000003 | C8: Chai PET B1 | D8: 39159010 | E8: UNComtrade | F8: IP | G8: ='EX-2.1 Chai & vảy'!$D$69 -> 0.55177264 | H8: USD/KG | I8: KG | J8: 1 | K8: ='EX-3 CPI'!$D$38 -> 1 | L8: =G8/J8*K8 -> 0.55177264 | M8: 1 | N8: =L8*M8 -> 0.55177264
B9: 150000113 | C9: Chai PET B1 Không Phân Loại | D9: 39159010 | E9: UNComtrade | F9: IP | G9: ='EX-2.1 Chai & vảy'!$D$69 -> 0.55177264 | H9: USD/KG | I9: KG | J9: 1 | K9: ='EX-3 CPI'!$D$38 -> 1 | L9: =G9/J9*K9 -> 0.55177264 | M9: 1 | N9: =L9*M9 -> 0.55177264
B10: 150000004 | C10: Chai PET-B2.1 | D10: 39159010 | E10: UNComtrade | F10: IP | G10: ='EX-2.1 Chai & vảy'!$D$69 -> 0.55177264 | H10: USD/KG | I10: KG | J10: 1 | K10: ='EX-3 CPI'!$D$38 -> 1 | L10: =G10/J10*K10 -> 0.55177264 | M10: 1 | N10: =L10*M10 -> 0.55177264
B11: 150000050 | C11: Chai PET-B2.2 | D11: 39159010 | E11: UNComtrade | F11: IP | G11: ='EX-2.1 Chai & vảy'!$D$69 -> 0.55177264 | H11: USD/KG | I11: KG | J11: 1 | K11: ='EX-3 CPI'!$D$38 -> 1 | L11: =G11/J11*K11 -> 0.55177264 | M11: 1 | N11: =L11*M11 -> 0.55177264
B12: 150000005 | C12: Chai PET-B3 | D12: 39159010 | E12: UNComtrade | F12: IP | G12: ='EX-2.1 Chai & vảy'!$D$69 -> 0.55177264 | H12: USD/KG | I12: KG | J12: 1 | K12: ='EX-3 CPI'!$D$38 -> 1 | L12: =G12/J12*K12 -> 0.55177264 | M12: 1 | N12: =L12*M12 -> 0.55177264
B13: 150000014 | C13: Chai PET B4 | D13: 39159010 | E13: UNComtrade | F13: IP | G13: ='EX-2.1 Chai & vảy'!$D$69 -> 0.55177264 | H13: USD/KG | I13: KG | J13: 1 | K13: ='EX-3 CPI'!$D$38 -> 1 | L13: =G13/J13*K13 -> 0.55177264 | M13: 1 | N13: =L13*M13 -> 0.55177264
B14: 150000015 | C14: Chai PET B5 | D14: 39159010 | E14: UNComtrade | F14: IP | G14: ='EX-2.1 Chai & vảy'!$D$69 -> 0.55177264 | H14: USD/KG | I14: KG | J14: 1 | K14: ='EX-3 CPI'!$D$38 -> 1 | L14: =G14/J14*K14 -> 0.55177264 | M14: 1 | N14: =L14*M14 -> 0.55177264
B15: 150000016 | C15: Chai PET B6.1 | D15: 39159010 | E15: UNComtrade | F15: IP | G15: ='EX-2.1 Chai & vảy'!$D$69 -> 0.55177264 | H15: USD/KG | I15: KG | J15: 1 | K15: ='EX-3 CPI'!$D$38 -> 1 | L15: =G15/J15*K15 -> 0.55177264 | M15: 1 | N15: =L15*M15 -> 0.55177264
B16: 150000114 | C16: Chai PET B6.2 | D16: 39159010 | E16: UNComtrade | F16: IP | G16: ='EX-2.1 Chai & vảy'!$D$69 -> 0.55177264 | H16: USD/KG | I16: KG | J16: 1 | K16: ='EX-3 CPI'!$D$38 -> 1 | L16: =G16/J16*K16 -> 0.55177264 | M16: 1 | N16: =L16*M16 -> 0.55177264
B17: 150000010 | C17: Chai PET B7.1 | D17: 39159010 | E17: UNComtrade | F17: IP | G17: ='EX-2.1 Chai & vảy'!$D$69 -> 0.55177264 | H17: USD/KG | I17: KG | J17: 1 | K17: ='EX-3 CPI'!$D$38 -> 1 | L17: =G17/J17*K17 -> 0.55177264 | M17: 1 | N17: =L17*M17 -> 0.55177264
B18: 150000051 | C18: Vảy PET B1_A5.1 | D18: 39159010 | E18: UNComtrade | F18: IP | G18: ='EX-2.1 Chai & vảy'!$D$69 -> 0.55177264 | H18: USD/KG | I18: KG | J18: 1 | K18: ='EX-3 CPI'!$D$38 -> 1 | L18: =G18/J18*K18 -> 0.55177264 | M18: 1 | N18: =L18*M18 -> 0.55177264
B19: 150000052 | C19: Vảy PET B1_A5.2 | D19: 39159010 | E19: UNComtrade | F19: IP | G19: ='EX-2.1 Chai & vảy'!$D$69 -> 0.55177264 | H19: USD/KG | I19: KG | J19: 1 | K19: ='EX-3 CPI'!$D$38 -> 1 | L19: =G19/J19*K19 -> 0.55177264 | M19: 1 | N19: =L19*M19 -> 0.55177264
B20: 150000053 | C20: Vảy PET B1_A6 | D20: 39159010 | E20: UNComtrade | F20: IP | G20: ='EX-2.1 Chai & vảy'!$D$69 -> 0.55177264 | H20: USD/KG | I20: KG | J20: 1 | K20: ='EX-3 CPI'!$D$38 -> 1 | L20: =G20/J20*K20 -> 0.55177264 | M20: 1 | N20: =L20*M20 -> 0.55177264
B21: 700000196 | C21: Phụ gia 409 | D21: 32061990 | E21: UNComtrade | F21: IP | G21: ='EX-2.3 Phụ gia 409'!$G$6 -> 4.8268556 | H21: USD/KG | I21: KG | J21: 1 | K21: ='EX-3 CPI'!$D$38 -> 1 | L21: =G21/J21*K21 -> 4.8268556 | M21: 1 | N21: =L21*M21 -> 4.8268556
B22: 700000169 | C22: Phụ gia 0090 | D22: 32049000 | E22: UNComtrade | F22: 2023 | G22: ='EX-2.4 Phụ gia khác'!$D$6 -> 0.059997551 | H22: USD/KG | I22: KG | J22: 1 | K22: =VLOOKUP(F22,'EX-3 CPI'!$B$33:$D$38,3,0) -> 1.2017885 | L22: =G22/J22*K22 -> 0.07210437 | M22: 1 | N22: =L22*M22 -> 0.07210437
B23: 120003033 | C23: Phụ gia CC10379752ZF | D23: 32049000 | E23: UNComtrade | F23: 2023 | G23: ='EX-2.4 Phụ gia khác'!$D$6 -> 0.059997551 | H23: USD/KG | I23: KG | J23: 1 | K23: =VLOOKUP(F23,'EX-3 CPI'!$B$33:$D$38,3,0) -> 1.2017885 | L23: =G23/J23*K23 -> 0.07210437 | M23: 1 | N23: =L23*M23 -> 0.07210437
B24: 120002994 | C24: Phụ gia 00185 | D24: 32049000 | E24: UNComtrade | F24: 2023 | G24: ='EX-2.4 Phụ gia khác'!$D$6 -> 0.059997551 | H24: USD/KG | I24: KG | J24: 1 | K24: =VLOOKUP(F24,'EX-3 CPI'!$B$33:$D$38,3,0) -> 1.2017885 | L24: =G24/J24*K24 -> 0.07210437 | M24: 1 | N24: =L24*M24 -> 0.07210437
B25: 120003028 | C25: Phụ gia RHC-2 | D25: 3206199 | E25: UNComtrade | F25: 2023 | G25: ='EX-2.5 Phụ gia RHC'!D7 -> 4.8241431 | H25: USD/KG | I25: KG | J25: 1 | K25: =VLOOKUP(F25,'EX-3 CPI'!$B$33:$D$38,3,0) -> 1.2017885 | L25: =G25/J25*K25 -> 5.7975999 | M25: 1 | N25: =L25*M25 -> 5.7975999
B26: 150000078 | C26: Vảy PET B3_A5.1 | D26: 39159010 | E26: UNComtrade | F26: IP | G26: ='EX-2.1 Chai & vảy'!$D$69 -> 0.55177264 | H26: USD/KG | I26: KG | J26: 1 | K26: ='EX-3 CPI'!$D$38 -> 1 | L26: =G26/J26*K26 -> 0.55177264 | M26: 1 | N26: =L26*M26 -> 0.55177264
B27: 150000018 | C27: Vảy PET B3_A6 | D27: 39159010 | E27: UNComtrade | F27: IP | G27: ='EX-2.1 Chai & vảy'!$D$69 -> 0.55177264 | H27: USD/KG | I27: KG | J27: 1 | K27: ='EX-3 CPI'!$D$38 -> 1 | L27: =G27/J27*K27 -> 0.55177264 | M27: 1 | N27: =L27*M27 -> 0.55177264
B28: 150000061 | C28: Vảy PET B6.2_A6 | D28: 39159010 | E28: UNComtrade | F28: IP | G28: ='EX-2.1 Chai & vảy'!$D$69 -> 0.55177264 | H28: USD/KG | I28: KG | J28: 1 | K28: ='EX-3 CPI'!$D$38 -> 1 | L28: =G28/J28*K28 -> 0.55177264 | M28: 1 | N28: =L28*M28 -> 0.55177264
B29: 120003031 | C29: Hạt TiO2 White MTP | D29: 32061990 | E29: UNComtrade | F29: IP | G29: ='EX-2.3 Phụ gia 409'!$G$6 -> 4.8268556 | H29: USD/KG | I29: KG | J29: 1 | K29: ='EX-3 CPI'!$D$38 -> 1 | L29: =G29/J29*K29 -> 4.8268556 | M29: 1 | N29: =L29*M29 -> 4.8268556
B30: 120003027 | C30: Lỏng TiO2 Gumi White 2 | D30: 32061990 | E30: UNComtrade | F30: IP | G30: ='EX-2.3 Phụ gia 409'!$G$6 -> 4.8268556 | H30: USD/KG | I30: KG | J30: 1 | K30: ='EX-3 CPI'!$D$38 -> 1 | L30: =G30/J30*K30 -> 4.8268556 | M30: 1 | N30: =L30*M30 -> 4.8268556
B31: 700000185 | C31: Phá bọt Antifoam CS04 | D31: 38249970 | E31: UNComtrade | F31: IP | G31: ='EX-2.6 Phá bọt'!D6 -> 4.7189261 | H31: USD/KG | I31: KG | J31: 1 | K31: ='EX-3 CPI'!$D$38 -> 1 | L31: =G31/J31*K31 -> 4.7189261 | M31: 1 | N31: =L31*M31 -> 4.7189261
B32: 120002594 | C32: Thủy tinh lỏng Na2SiO3.9H2O | D32: 28391990 | E32: UNComtrade | F32: IP | G32: ='EX-2.7- Thủy tinh lỏng'!D6 -> 0.58017401 | H32: USD/KG | I32: KG | J32: 1 | K32: ='EX-3 CPI'!$D$38 -> 1 | L32: =G32/J32*K32 -> 0.58017401 | M32: 1 | N32: =L32*M32 -> 0.58017401
B33: 700000180 | C33: Sodium Hydroxide (32%) NaOH (rắn) | D33: 28151100 | E33: UNComtrade | F33: IP | G33: ='EX-2.8 Sodium 281511'!$D$6 -> 0.87114878 | H33: USD/KG | I33: KG | J33: 1 | K33: ='EX-3 CPI'!$D$38 -> 1 | L33: =G33/J33*K33 -> 0.87114878 | M33: 1 | N33: =L33*M33 -> 0.87114878
B34: 700000180 | C34: Sodium Hydroxide (32%) NaOH (lỏng) | D34: 28151200 | E34: UNComtrade | F34: IP | G34: ='EX-2.9 Sodium 281512'!D6 -> 0.45179295 | H34: USD/KG | I34: KG | J34: 1 | K34: ='EX-3 CPI'!$D$38 -> 1 | L34: =G34/J34*K34 -> 0.45179295 | M34: 1 | N34: =L34*M34 -> 0.45179295
B35: 140005072 | C35: Bao Jumbo 950x950x1300mm Đai Trắng rPET | D35: 39232990 | E35: UNComtrade | F35: IP | G35: ='EX-2.11 Bao bì'!$D$6 -> 6.3871807 | H35: USD/KG | I35: KG | J35: 1 | K35: ='EX-3 CPI'!$D$38 -> 1 | L35: =G35/J35*K35 -> 6.3871807 | M35: 1 | N35: =L35*M35 -> 6.3871807
B36: 140006135 | C36: Bao PE 2000x2700x5z | D36: 39232990 | E36: UNComtrade | F36: IP | G36: ='EX-2.11 Bao bì'!$D$6 -> 6.3871807 | H36: USD/KG | I36: KG | J36: 1 | K36: ='EX-3 CPI'!$D$38 -> 1 | L36: =G36/J36*K36 -> 6.3871807 | M36: 1 | N36: =L36*M36 -> 6.3871807
B37: 140006103 | C37: Bao PE lót ngoài 2000x2700x7z | D37: 39232990 | E37: UNComtrade | F37: IP | G37: ='EX-2.11 Bao bì'!$D$6 -> 6.3871807 | H37: USD/KG | I37: KG | J37: 1 | K37: ='EX-3 CPI'!$D$38 -> 1 | L37: =G37/J37*K37 -> 6.3871807 | M37: 1 | N37: =L37*M37 -> 6.3871807
B38: 140006125 | C38: Bao Jumbo 950x950x1300mm Đai Xanh Xơ Sợi | D38: 39232990 | E38: UNComtrade | F38: IP | G38: ='EX-2.11 Bao bì'!$D$6 -> 6.3871807 | H38: USD/KG | I38: KG | J38: 1 | K38: ='EX-3 CPI'!$D$38 -> 1 | L38: =G38/J38*K38 -> 6.3871807 | M38: 1 | N38: =L38*M38 -> 6.3871807
B39: 140006123 | C39: Bao jumbo 950x950x1300mm_Không logo | D39: 39232990 | E39: UNComtrade | F39: IP | G39: ='EX-2.11 Bao bì'!$D$6 -> 6.3871807 | H39: USD/KG | I39: KG | J39: 1 | K39: ='EX-3 CPI'!$D$38 -> 1 | L39: =G39/J39*K39 -> 6.3871807 | M39: 1 | N39: =L39*M39 -> 6.3871807
B40: 140006107 | C40: Pallet gỗ 1 mặt 1100x1000x100mm | D40: 44152000 | E40: UNComtrade | F40: IP | G40: ='EX-2.10 Pallet gỗ'!D6 -> 12.096353 | H40: USD/KG | I40: KG | J40: 1 | K40: ='EX-3 CPI'!$D$38 -> 1 | L40: =G40/J40*K40 -> 12.096353 | M40: 1 | N40: =L40*M40 -> 12.096353
B42: DIRLAB | C42: Direct Labor | D42: n/a | F42: 2022 | G42: ='EX-5A LABOR'!$I$20 -> 0.93853993 | H42: USD/Hour | I42: Hour | J42: 1 | K42: =VLOOKUP(F42,'EX-3 CPI'!$B$33:$D$38,3,0) -> 1.6090119 | L42: =G42/J42*K42 -> 1.5101219 | M42: 1 | N42: =L42*M42 -> 1.5101219
B43: INDLAB | C43: Indirect Labor | D43: n/a | F43: 2022 | G43: ='EX-5A LABOR'!$I$20 -> 0.93853993 | H43: USD/Hour | I43: Hour | J43: 1 | K43: =VLOOKUP(F43,'EX-3 CPI'!$B$33:$D$38,3,0) -> 1.6090119 | L43: =G43/J43*K43 -> 1.5101219 | M43: 1 | N43: =L43*M43 -> 1.5101219
B44: ELEC | C44: Electricity | D44: n/a | F44: 2023 | G44: ='EX-6A ELEC'!B11 -> 0.024 | H44: USD/KwH | I44: KwH | J44: 1 | K44: =VLOOKUP(F44,'EX-3 CPI'!$B$33:$D$38,3,0) -> 1.2017885 | L44: =G44/J44*K44 -> 0.028842925 | M44: 1 | N44: =L44*M44 -> 0.028842925
B45: WATER | C45: Water | D45: n/a | F45: IP | G45: =Water!C7 -> 0.11
B46: OH | C46: Overhead | D46: n/a | E46: Various Finan Ratios | F46: IP | G46: ='EX-10A FINRATIO'!B9 -> 0.054786403
B47: SGA | C47: SG&A | D47: n/a | E47: Various Finan Ratios | F47: IP | G47: ='EX-10A FINRATIO'!C9 -> 0.2473953
B48: Profit | C48: Profit | D48: n/a | E48: Various Finan Ratios | F48: IP | G48: ='EX-10A FINRATIO'!D9 -> 0.015189977
B50: Transportation | C50: Marine Insurance
B51: Transportation | C51: Inland Freight Trucking Expense - Import | E51: Doing Business in Egypt, Arab Rep. - World Bank Group | F51: 2020 | G51: =Movement!C7/Movement!C9 -> 8.9285714e-05 | H51: USD/kg/km | J51: 1 | K51: =VLOOKUP(F51,'EX-3 CPI'!$B$33:$D$38,3,0) -> 1.9281471 | L51: =G51/J51*K51 -> 0.000172156 | M51: 1 | N51: =L51*M51 -> 0.000172156
B52: Transportation | C52: Inland Freight Trucking Expense - Export | E52: Doing Business in Egypt, Arab Rep. - World Bank Group | F52: 2020 | G52: =Movement!C8/Movement!C9 -> 8.0357143e-05 | H52: USD/kg/km | J52: 1 | K52: =VLOOKUP(F52,'EX-3 CPI'!$B$33:$D$38,3,0) -> 1.9281471 | L52: =G52/J52*K52 -> 0.0001549404 | M52: 1 | N52: =L52*M52 -> 0.0001549404
B53: Transportation | C53: Domestic Brokerage & Handling - Import | E53: Doing Business in Egypt, Arab Rep. - World Bank Group | F53: 2020 | G53: =Movement!C4/Movement!C9 -> 0.036933333 | H53: USD/kg | J53: 1 | K53: =VLOOKUP(F53,'EX-3 CPI'!$B$33:$D$38,3,0) -> 1.9281471 | L53: =G53/J53*K53 -> 0.071212901 | M53: 1 | N53: =L53*M53 -> 0.071212901
B54: Transportation | C54: Domestic Brokerage & Handling - Export | E54: Doing Business in Egypt, Arab Rep. - World Bank Group | F54: 2020 | G54: =Movement!C5/Movement!C9 -> 0.0172 | H54: USD/kg | J54: 1 | K54: =VLOOKUP(F54,'EX-3 CPI'!$B$33:$D$38,3,0) -> 1.9281471 | L54: =G54/J54*K54 -> 0.033164131 | M54: 1 | N54: =L54*M54 -> 0.033164131

Sheet Movement
B1: Doing Business in Egypt, Arab Rep. - World Bank Group
B3: IP
B4: Domestic Brokerage & Handling - Import | C4: 554
B5: Domestic Brokerage & Handling - Export | C5: 258
B7: Inland Freight Trucking Expense - Import | C7: =D7/E7 -> 1.3392857 | D7: 300 | E7: 224
B8: Inland Freight Trucking Expense - Export | C8: =D8/E7 -> 1.2053571 | D8: 270
B9: Quantity | C9: 15000

Sheet Water
B2: Egypt - Bottled water - price, January 2024 | GlobalProductPrices.com
B3: First price hike on water bills for Egyptian households in nearly a decade - Economy - Business - Ahram Online
B5: Egypt - Bottled water - price, January 2024
B6: EGP | C6: 5.35
B7: USD | C7: 0.11
B8: EUR | C8: 0.101

Sheet NME list
B2: EXCLUDE NME COUNTRIES
B3: Republic of Armenia (see 57 FR 23380) Review Request Submitted by the Government of Armenia on 12/21/2023
B4: Republic of Azerbaijan (see 57 FR 23380)
B5: Republic of Belarus (see 57 FR 23380)
B6: People’s Republic of China (see 82 FR 50858)
B7: Georgia (see 57 FR 23380)
B8: Kyrgyz Republic (see 57 FR 23380)
B9: Republic of Moldova (see 57 FR 23380)
B10: Russian Federation (see 87 FR 69002)
B11: Republic of Tajikistan (see 57 FR 23380)
B12: Turkmenistan (see 57 FR 23380)
B13: Republic of Uzbekistan (see 57 FR 23380)
B14: Socialist Republic of Vietnam (see 68 FR 37116)

Sheet Export Data
A1: List of exporters for the selected product in 2023
A2: Product : 3907 Polyacetals, other polyethers and epoxide resins, in primary forms; polycarbonates, alkyd resins, ...
A4: Sources: ITC calculations based on UN COMTRADE and ITC statistics.
A5: The world aggregation represents the sum of reporting and non reporting countries
A6: The data in orange represents mirror figures based on partner data.
A7: The quantities shown in dark green are estimated by ITC. For further information, please refer to the ITC explanatory note.
A8: The quantities shown in light green are estimated by UNSD. For further information, please refer to the UNSD explanatory note.
A11: Exporters | B11: Select your indicators
B12: Value exported in 2023 (USD thousand) | C12: Trade balance in 2023 (USD thousand) | D12: Quantity exported in 2023 | E12: Quantity Unit | F12: Unit value (USD/unit) | G12: Annual growth in value between 2019-2023 (%) | H12: Annual growth in quantity between 2019-2023 (%) | I12: Annual growth in value between 2022-2023 (%) | J12: Share in world exports (%) | K12: Average distance of importing countries (km) | L12: Concentration of importing countries
A13: World | B13: 62971259 | C13: -1390078 | D13: 0 | E13: No quantity | G13: 7 | H13: 3 | I13: -20 | J13: 100 | K13: 4181 | L13: 0.04
A14: China | B14: 10750920 | C14: 3781429 | D14: 8553332 | E14: Tons | F14: 1257 | G14: 20 | H14: 18 | I14: -9 | J14: 17.1 | K14: 6925 | L14: 0.03
A15: United States of America | B15: 5633830 | C15: 1150654 | D15: 1666353 | E15: Tons | F15: 3381 | G15: 3 | H15: -4 | I15: -17 | J15: 8.9 | K15: 5795 | L15: 0.17
A16: Korea, Republic of | B16: 5306241 | C16: 4051463 | D16: 2653321 | E16: Tons | F16: 2000 | G16: 6 | H16: 0 | I16: -22 | J16: 8.4 | K16: 5987 | L16: 0.09
A17: Germany | B17: 4885272 | C17: 636425 | D17: 1454792 | E17: Tons | F17: 3358 | G17: 4 | H17: -5 | I17: -21 | J17: 7.8 | K17: 1955 | L17: 0.05
A18: Netherlands | B18: 4148736 | C18: 2950183 | D18: 1702960 | E18: Tons | F18: 2436 | G18: 4 | H18: -5 | I18: -27 | J18: 6.6 | K18: 1665 | L18: 0.09
A19: Taipei, Chinese | B19: 3703519 | C19: 2864429 | D19: 2167075 | E19: Tons | F19: 1709 | G19: 3 | H19: -1 | I19: -31 | J19: 5.9 | K19: 4749 | L19: 0.17
A20: Belgium | B20: 3402459 | C20: 1305108 | D20: 1346318 | E20: Tons | F20: 2527 | G20: 11 | H20: 1 | I20: -18 | J20: 5.4 | K20: 1513 | L20: 0.11
A21: Italy | B21: 2433530 | C21: -464295 | D21: 689765 | E21: Tons | F21: 3528 | G21: 10 | H21: 1 | I21: -11 | J21: 3.9 | K21: 2579 | L21: 0.07
A22: Thailand | B22: 2365823 | C22: 1290115 | D22: 1385727 | E22: Tons | F22: 1707 | G22: 6 | H22: 1 | I22: -16 | J22: 3.8 | K22: 4339 | L22: 0.11
A23: Japan | B23: 2335669 | C23: 46630 | D23: 576440 | E23: Tons | F23: 4052 | G23: -1 | H23: -2 | I23: -18 | J23: 3.7 | K23: 4082 | L23: 0.18
A24: Spain | B24: 1851425 | C24: 413147 | D24: 0 | E24: No quantity | G24: 3 | I24: -23 | J24: 2.9 | K24: 2162 | L24: 0.09
A25: Singapore | B25: 1344380 | C25: 770473 | D25: 588010 | E25: Tons | F25: 2286 | G25: 0 | H25: -2 | I25: -16 | J25: 2.1 | K25: 3817 | L25: 0.1
A26: Türkiye | B26: 1171798 | C26: -402327 | D26: 715815 | E26: Tons | F26: 1637 | G26: 25 | H26: 18 | I26: -15 | J26: 1.9 | K26: 2396 | L26: 0.06
A27: Malaysia | B27: 1155784 | C27: 204025 | D27: 764477 | E27: Tons | F27: 1512 | G27: 3 | H27: -2 | I27: -17 | J27: 1.8 | K27: 5655 | L27: 0.1
A28: Saudi Arabia | B28: 990414 | C28: 699800 | D28: 0 | E28: No quantity | G28: -4 | H28: -2 | I28: -40 | J28: 1.6 | K28: 5330 | L28: 0.13
A29: France | B29: 949718 | C29: -1104836 | D29: 352503 | E29: Tons | F29: 2694 | G29: 5 | H29: -2 | I29: -15 | J29: 1.5 | K29: 1582 | L29: 0.09
A30: Viet Nam | B30: 920122 | C30: -1032936 | D30: 761238 | E30: Tons | F30: 1209 | G30: 24 | H30: 13 | I30: -15 | J30: 1.5 | K30: 7994 | L30: 0.08
A31: United Kingdom | B31: 731627 | C31: -793396 | D31: 83941 | E31: Tons | F31: 8716 | G31: 3 | H31: -7 | I31: -16 | J31: 1.2 | K31: 3898 | L31: 0.12
A32: India | B32: 726681 | C32: -1765103 | D32: 570472 | E32: Tons | F32: 1274 | G32: -7 | H32: -14 | I32: -42 | J32: 1.2 | K32: 5928 | L32: 0.03
A33: Mexico | B33: 695311 | C33: -1964590 | D33: 0 | E33: No quantity | G33: 9 | I33: -31 | J33: 1.1 | K33: 2054 | L33: 0.71
A34: Poland | B34: 638928 | C34: -529542 | D34: 0 | E34: No quantity | G34: 19 | I34: -11 | J34: 1 | K34: 1005 | L34: 0.17
A35: Switzerland | B35: 634341 | C35: 32969 | D35: 100134 | E35: Tons | F35: 6335 | G35: 5 | H35: -2 | I35: -4 | J35: 1 | K35: 2538 | L35: 0.17
A36: Lithuania | B36: 617698 | C36: 445551 | D36: 485172 | E36: Tons | F36: 1273 | G36: 5 | H36: -3 | I36: -33 | J36: 1 | K36: 1224 | L36: 0.1
A37: Canada | B37: 533376 | C37: -603922 | D37: 182228 | E37: Tons | F37: 2927 | G37: 9 | H37: 0 | I37: -9 | J37: 0.8 | K37: 1834 | L37: 0.85
A38: Hong Kong, China | B38: 458319 | C38: 34436 | D38: 125286 | E38: Tons | F38: 3658 | G38: -19 | H38: -23 | I38: -36 | J38: 0.7 | K38: 1204 | L38: 0.79
A39: Egypt | B39: 453422 | C39: 126327 | D39: 345576 | E39: Tons | F39: 1312 | G39: 16 | H39: 6 | I39: -30 | J39: 0.7 | K39: 2877 | L39: 0.15
A40: Austria | B40: 392195 | C40: -296278 | D40: 94440 | E40: Tons | F40: 4153 | G40: 7 | H40: 1 | I40: -5 | J40: 0.6 | K40: 1549 | L40: 0.14
A41: Czech Republic | B41: 357483 | C41: -588773 | D41: 110298 | E41: Tons | F41: 3241 | G41: 8 | H41: -4 | I41: -27 | J41: 0.6 | K41: 777 | L41: 0.13
A42: Indonesia | B42: 286712 | C42: -737589 | D42: 300476 | E42: Tons | F42: 954 | G42: -5 | H42: -8 | I42: -2 | J42: 0.5 | K42: 6346 | L42: 0.1
A43: Oman | B43: 222355 | C43: 172393 | D43: 0 | E43: No quantity | G43: 13 | H43: 6 | I43: -64 | J43: 0.4 | K43: 7473 | L43: 0.13
A44: Hungary | B44: 196105 | C44: -380050 | D44: 0 | E44: No quantity | G44: 7 | I44: -16 | J44: 0.3 | K44: 620 | L44: 0.15
A45: Brazil | B45: 194663 | C45: -681644 | D45: 97189 | E45: Tons | F45: 2003 | G45: 3 | H45: -9 | I45: -55 | J45: 0.3 | K45: 4064 | L45: 0.17
A46: Romania | B46: 190123 | C46: -384262 | D46: 102405 | E46: Tons | F46: 1857 | G46: 6 | H46: 0 | I46: -28 | J46: 0.3 | K46: 1177 | L46: 0.1
A47: Pakistan | B47: 177961 | C47: 20443 | D47: 179590 | E47: Tons | F47: 991 | G47: -9 | H47: -13 | I47: 44 | J47: 0.3 | K47: 8462 | L47: 0.19
A48: Sweden | B48: 174226 | C48: -235669 | D48: 53597 | E48: Tons | F48: 3251 | G48: 5 | H48: -3 | I48: -17 | J48: 0.3 | K48: 1215 | L48: 0.11
A49: Slovakia | B49: 132375 | C49: -278097 | D49: 52114 | E49: Tons | F49: 2540 | G49: 6 | H49: 1 | I49: -10 | J49: 0.2 | K49: 398 | L49: 0.19
A50: United Arab Emirates | B50: 129249 | C50: -539065 | D50: 0 | E50: No quantity | G50: 11 | H50: 14 | I50: -36 | J50: 0.2 | K50: 4472 | L50: 0.06
A51: Portugal | B51: 117078 | C51: -525852 | D51: 50363 | E51: Tons | F51: 2325 | G51: 11 | H51: 3 | I51: 6 | J51: 0.2 | K51: 2748 | L51: 0.17
A52: Slovenia | B52: 108984 | C52: -96678 | D52: 42434 | E52: Tons | F52: 2568 | G52: 5 | H52: -4 | I52: -25 | J52: 0.2 | K52: 823 | L52: 0.15
A53: Luxembourg | B53: 90364 | C53: -101256 | D53: 25475 | E53: Tons | F53: 3547 | G53: 10 | H53: 1 | I53: -29 | J53: 0.1 | K53: 226 | L53: 0.81
A54: Finland | B54: 90127 | C54: -58177 | D54: 30462 | E54: Tons | F54: 2959 | G54: 0 | H54: -5 | I54: -20 | J54: 0.1 | K54: 1208 | L54: 0.24
A55: South Africa | B55: 89377 | C55: -113273 | D55: 62887 | E55: Tons | F55: 1421 | G55: -4 | H55: -11 | I55: 11 | J55: 0.1 | K55: 7158 | L55: 0.15
A56: Greece | B56: 81396 | C56: -106297 | D56: 0 | E56: No quantity | G56: 13 | I56: -29 | J56: 0.1 | K56: 1471 | L56: 0.14
A57: Colombia | B57: 80889 | C57: -237922 | D57: 49818 | E57: Tons | F57: 1624 | G57: 22 | H57: 19 | I57: -14 | J57: 0.1 | K57: 3151 | L57: 0.15
A58: Israel | B58: 78318 | C58: -180954 | D58: 18659 | E58: Tons | F58: 4197 | G58: 7 | H58: 0 | I58: -26 | J58: 0.1 | K58: 6764 | L58: 0.14
A59: Russian Federation | B59: 69539 | C59: -930560 | D59: 34638 | E59: Tons | F59: 2008 | G59: -8 | H59: -10 | I59: -47 | J59: 0.1 | K59: 2264 | L59: 0.32
A60: Latvia | B60: 54572 | C60: 7498 | D60: 39945 | E60: Tons | F60: 1366 | G60: 11 | H60: 1 | I60: -39 | J60: 0.1 | K60: 1160 | L60: 0.14
A61: Denmark | B61: 52641 | C61: -221291 | D61: 13655 | E61: Tons | F61: 3855 | G61: 2 | H61: -6 | I61: -15 | J61: 0.1 | K61: 1449 | L61: 0.07
A62: Djibouti | B62: 52529 | C62: 17845 | D62: 40377061 | E62: Tons | F62: 1.3 | I62: 30 | J62: 0.1 | K62: 533 | L62: 0.99
A63: Croatia | B63: 43937 | C63: -31208 | D63: 28898 | E63: Tons | F63: 1520 | G63: 20 | H63: 13 | I63: -6 | J63: 0.1 | K63: 628 | L63: 0.1
A64: Ireland | B64: 43642 | C64: -166021 | D64: 0 | E64: No quantity | G64: 4 | I64: -29 | J64: 0.1 | K64: 2201 | L64: 0.4
A65: Estonia | B65: 43105 | C65: -12528 | D65: 12637 | E65: Tons | F65: 3411 | G65: 6 | H65: -8 | I65: -4 | J65: 0.1 | K65: 890 | L65: 0.2
A66: Bulgaria | B66: 42666 | C66: -177116 | D66: 0 | E66: No quantity | G66: 24 | I66: 6 | J66: 0.1 | K66: 691 | L66: 0.27
A67: Australia | B67: 32824 | C67: -278495 | D67: 16606 | E67: Tons | F67: 1977 | G67: 2 | H67: 1 | I67: -8 | J67: 0.1 | K67: 6345 | L67: 0.23
A68: Tunisia | B68: 31704 | C68: -142752 | D68: 20269 | E68: Tons | F68: 1564 | G68: -2 | H68: -10 | I68: -1 | J68: 0.1 | K68: 1980 | L68: 0.16
A69: Bangladesh | B69: 31699 | C69: -231093 | D69: 39148 | E69: Tons | F69: 810 | G69: 28 | H69: 11 | I69: 8 | J69: 0.1 | K69: 3429 | L69: 0.32
A70: Norway | B70: 31684 | C70: -48151 | D70: 13402 | E70: Tons | F70: 2364 | G70: 36 | H70: 62 | I70: -1 | J70: 0.1 | K70: 1637 | L70: 0.22
A71: Ecuador | B71: 31567 | C71: -99360 | D71: 35192 | E71: Tons | F71: 897 | G71: 17 | H71: 6 | I71: -44 | J71: 0.1 | K71: 3407 | L71: 0.32
A72: Dominican Republic | B72: 29534 | C72: -95193 | D72: 12297 | E72: Tons | F72: 2402 | G72: 24 | H72: 9 | I72: -3 | J72: 0 | K72: 2220 | L72: 0.18
A73: Peru | B73: 29147 | C73: -229379 | D73: 29022 | E73: Tons | F73: 1004 | G73: 11 | H73: 3 | I73: -6 | J73: 0 | K73: 4050 | L73: 0.24
A74: Serbia | B74: 28882 | C74: -130203 | D74: 14032 | E74: Tons | F74: 2058 | G74: 15 | H74: 4 | I74: -19 | J74: 0 | K74: 1159 | L74: 0.14
A75: Kazakhstan | B75: 24367 | C75: -163489 | D75: 14770 | E75: Tons | F75: 1650 | G75: 67 | H75: -28 | I75: 24 | J75: 0 | K75: 1433 | L75: 0.6
A76: Honduras | B76: 23415 | C76: -10003 | D76: 16521 | E76: Tons | F76: 1417 | G76: 203 | H76: 169 | J76: 0 | K76: 1405 | L76: 0.38
A77: Philippines | B77: 19705 | C77: -524505 | D77: 13491 | E77: Tons | F77: 1461 | G77: 10 | H77: 16 | I77: 4 | J77: 0 | K77: 2805 | L77: 0.2
A78: Morocco | B78: 17102 | C78: -309643 | D78: 11778 | E78: Tons | F78: 1452 | G78: -3 | H78: -10 | I78: -54 | J78: 0 | K78: 3643 | L78: 0.17
A79: Moldova, Republic of | B79: 14442 | C79: -5995 | D79: 11363 | E79: Tons | F79: 1271 | G79: 101 | H79: 74 | I79: 231 | J79: 0 | K79: 421 | L79: 0.84
A80: Iran, Islamic Republic of | B80: 13686 | C80: -59302 | D80: 0 | E80: No quantity | G80: 32 | H80: 6 | I80: 0 | J80: 0 | K80: 1976 | L80: 0.35
A81: Nigeria | B81: 12151 | C81: -160149 | D81: 135010 | E81: Tons | F81: 90 | G81: 78 | H81: 112 | I81: 151 | J81: 0 | K81: 5279 | L81: 0.2
A82: Kenya | B82: 11624 | C82: -86397 | D82: 11674 | E82: Tons | F82: 996 | G82: 21 | H82: 17 | I82: 35 | J82: 0 | K82: 3573 | L82: 0.21
A83: Guatemala | B83: 10514 | C83: -90850 | D83: 6314 | E83: Tons | F83: 1665 | G83: 15 | H83: 5 | I83: -21 | J83: 0 | K83: 952 | L83: 0.24
A84: Jordan | B84: 9562 | C84: -70465 | D84: 5191 | E84: Tons | F84: 1842 | G84: 14 | H84: 4 | I84: -13 | J84: 0 | K84: 764 | L84: 0.25
A85: Paraguay | B85: 9146 | C85: -52507 | D85: 9911 | E85: Tons | F85: 923 | G85: 10 | H85: 1 | I85: 28 | J85: 0 | K85: 1054 | L85: 0.5
A86: Belarus | B86: 8873 | C86: -47330 | D86: 7685 | E86: Tons | F86: 1155 | G86: -25 | H86: 13 | I86: 0 | J86: 0 | K86: 2614 | L86: 0.23
A87: Chile | B87: 8475 | C87: -187338 | D87: 4452 | E87: Tons | F87: 1904 | G87: 10 | H87: 9 | I87: -34 | J87: 0 | K87: 3537 | L87: 0.16
A88: Myanmar | B88: 6994 | C88: -89098 | D88: 12224 | E88: Tons | F88: 572 | G88: 33 | H88: 38 | I88: 33 | J88: 0 | K88: 6419 | L88: 0.31
A89: Algeria | B89: 6984 | C89: -321194 | D89: 13482 | E89: Tons | F89: 518 | G89: 159 | I89: -53 | J89: 0 | K89: 1375 | L89: 0.24
A90: Costa Rica | B90: 6944 | C90: -68467 | D90: 1638 | E90: Tons | F90: 4239 | G90: 30 | H90: 18 | I90: 17 | J90: 0 | K90: 9301 | L90: 0.32
A91: Nepal | B91: 6814 | C91: -30915 | D91: 7711 | E91: Tons | F91: 884 | G91: 424 | I91: 21866 | J91: 0 | K91: 871 | L91: 1
A92: Tanzania, United Republic of | B92: 6755 | C92: -145902 | D92: 12215 | E92: Tons | F92: 553 | G92: 28 | H92: 17 | I92: -11 | J92: 0 | K92: 5902 | L92: 0.1
A93: Yemen | B93: 4885 | C93: -33718 | D93: 10247 | E93: Tons | F93: 477 | G93: -6 | H93: 43 | I93: 57 | J93: 0 | K93: 7264 | L93: 0.96
A94: Mongolia | B94: 4642 | C94: -14973 | D94: 6972 | E94: Tons | F94: 666 | G94: 353 | H94: 192 | I94: 186 | J94: 0 | K94: 1667 | L94: 0.96
A95: Argentina | B95: 4164 | C95: -258872 | D95: 1838 | E95: Tons | F95: 2266 | G95: -36 | H95: -41 | I95: -29 | J95: 0 | K95: 1214 | L95: 0.28
A96: Turks and Caicos Islands | B96: 3917 | C96: 3833 | D96: 2684 | E96: Tons | F96: 1459 | G96: 322 | H96: 126 | I96: 24 | J96: 0 | K96: 11794 | L96: 0.93
A97: El Salvador | B97: 3637 | C97: -175592 | D97: 2552 | E97: Tons | F97: 1425 | G97: -4 | H97: -9 | I97: -53 | J97: 0 | K97: 2916 | L97: 0.33
A98: Free Zones | B98: 3348 | C98: -463 | D98: 801 | E98: Tons | F98: 4180 | G98: 10 | H98: 5 | I98: -23 | J98: 0 | L98: 0.45
A99: Uruguay | B99: 3178 | C99: -130059 | D99: 3614 | E99: Tons | F99: 879 | G99: 13 | H99: 8 | I99: 53 | J99: 0 | K99: 2658 | L99: 0.61
A100: Kyrgyzstan | B100: 3122 | C100: -45633 | D100: 2630 | E100: Tons | F100: 1187 | G100: 111 | H100: 75 | I100: -40 | J100: 0 | K100: 734 | L100: 0.77
A101: Albania | B101: 2957 | C101: -16564 | D101: 3109 | E101: Tons | F101: 951 | G101: 46 | I101: -29 | J101: 0 | K101: 506 | L101: 0.5
A102: Lebanon | B102: 2704 | C102: -53799 | D102: 3036 | E102: Tons | F102: 891 | G102: 21 | I102: -23 | J102: 0 | K102: 2212 | L102: 0.23
A103: Ukraine | B103: 2678 | C103: -254026 | D103: 2093 | E103: Tons | F103: 1280 | G103: -31 | H103: -37 | I103: -83 | J103: 0 | K103: 1050 | L103: 0.17
...

Sheet Imports Data
A1: List of importers for the selected product in 2023
A2: Product : 3907 Polyacetals, other polyethers and epoxide resins, in primary forms; polycarbonates, alkyd resins, ...
A4: Sources: ITC calculations based on UN COMTRADE and ITC statistics.
A5: The world aggregation represents the sum of reporting and non reporting countries
A6: The data in orange represents mirror figures based on partner data.
A7: The quantities shown in dark green are estimated by ITC. For further information, please refer to the ITC explanatory note.
A8: The quantities shown in light green are estimated by UNSD. For further information, please refer to the UNSD explanatory note.
A11: Importers | B11: Select your indicators
B12: Value imported in 2023 (USD thousand) | C12: Trade balance in 2023 (USD thousand) | D12: Quantity imported in 2023 | E12: Quantity Unit | F12: Unit value (USD/unit) | G12: Annual growth in value between 2019-2023 (%) | H12: Annual growth in quantity between 2019-2023 (%) | I12: Annual growth in value between 2022-2023 (%) | J12: Share in world imports (%) | K12: Average distance of supplying countries (km) | L12: Concentration of supplying countries | M12: Average tariff (estimated) applied by the country (%)
A13: World | B13: 64361337 | C13: -1390078 | D13: 0 | E13: No quantity | G13: 6 | H13: 1 | I13: -22 | J13: 100 | K13: 4357 | L13: 0.07
A14: China | B14: 6969491 | C14: 3781429 | D14: 2904246 | E14: Tons | F14: 2400 | G14: -4 | H14: -8 | I14: -29 | J14: 10.8 | K14: 4171 | L14: 0.12 | M14: 7.9
A15: United States of America | B15: 4483176 | C15: 1150654 | D15: 2061898 | E15: Tons | F15: 2174 | G15: 16 | H15: 10 | I15: -32 | J15: 7 | K15: 8341 | L15: 0.1 | M15: 2.6
A16: Germany | B16: 4248847 | C16: 636425 | D16: 1498786 | E16: Tons | F16: 2835 | G16: 6 | H16: -1 | I16: -21 | J16: 6.6 | K16: 2047 | L16: 0.09 | M16: 2.1
A17: Italy | B17: 2897825 | C17: -464295 | D17: 1410475 | E17: Tons | F17: 2055 | G17: 10 | H17: 2 | I17: -21 | J17: 4.5 | K17: 2609 | L17: 0.1 | M17: 2.1
A18: Mexico | B18: 2659901 | C18: -1964590 | D18: 0 | E18: No quantity | G18: 10 | I18: -9 | J18: 4.1 | K18: 5377 | L18: 0.41 | M18: 3.8
A19: India | B19: 2491784 | C19: -1765103 | D19: 1407387 | E19: Tons | F19: 1771 | G19: 13 | H19: 5 | I19: -4 | J19: 3.9 | K19: 4712 | L19: 0.14 | M19: 6
A20: Japan | B20: 2289039 | C20: 46630 | D20: 1343808 | E20: Tons | F20: 1703 | G20: 3 | H20: -2 | I20: -18 | J20: 3.6 | K20: 3798 | L20: 0.16 | M20: 0.7
A21: Belgium | B21: 2097351 | C21: 1305108 | D21: 858651 | E21: Tons | F21: 2443 | G21: 14 | H21: 5 | I21: -25 | J21: 3.3 | K21: 3349 | L21: 0.1 | M21: 2.1
A22: France | B22: 2054554 | C22: -1104836 | D22: 870361 | E22: Tons | F22: 2361 | G22: 6 | H22: -3 | I22: -17 | J22: 3.2 | K22: 1768 | L22: 0.12 | M22: 2.1
A23: Viet Nam | B23: 1953058 | C23: -1032936 | D23: 1222438 | E23: Tons | F23: 1598 | G23: 5 | H23: 2 | I23: -16 | J23: 3 | K23: 2508 | L23: 0.23 | M23: 1.9
A24: Türkiye | B24: 1574125 | C24: -402327 | D24: 780423 | E24: Tons | F24: 2017 | G24: 11 | H24: 3 | I24: -28 | J24: 2.4 | K24: 5034 | L24: 0.14 | M24: 3.2
A25: United Kingdom | B25: 1525023 | C25: -793396 | D25: 599861 | E25: Tons | F25: 2542 | G25: 9 | H25: 3 | I25: -19 | J25: 2.4 | K25: 2531 | L25: 0.09 | M25: 1.4
A26: Spain | B26: 1438278 | C26: 413147 | D26: 0 | E26: No quantity | G26: 11 | I26: -18 | J26: 2.2 | K26: 3187 | L26: 0.09 | M26: 2.1
A27: Korea, Republic of | B27: 1254778 | C27: 4051463 | D27: 577362 | E27: Tons | F27: 2173 | G27: 6 | H27: 3 | I27: -11 | J27: 1.9 | K27: 3495 | L27: 0.25 | M27: 3.6
A28: Netherlands | B28: 1198553 | C28: 2950183 | D28: 453508 | E28: Tons | F28: 2643 | G28: 1 | H28: -5 | I28: -26 | J28: 1.9 | K28: 3270 | L28: 0.14 | M28: 2.1
A29: Poland | B29: 1168470 | C29: -529542 | D29: 526403 | E29: Tons | F29: 2220 | G29: 10 | H29: 6 | I29: -18 | J29: 1.8 | K29: 2392 | L29: 0.08 | M29: 2.1
A30: Canada | B30: 1137298 | C30: -603922 | D30: 429663 | E30: Tons | F30: 2647 | G30: 8 | H30: 2 | I30: -16 | J30: 1.8 | K30: 3428 | L30: 0.54 | M30: 0.3
A31: Thailand | B31: 1075708 | C31: 1290115 | D31: 403630 | E31: Tons | F31: 2665 | G31: 5 | H31: -1 | I31: -14 | J31: 1.7 | K31: 4089 | L31: 0.17 | M31: 2.4
A32: Indonesia | B32: 1024301 | C32: -737589 | D32: 659303 | E32: Tons | F32: 1554 | G32: 6 | H32: 3 | I32: -22 | J32: 1.6 | K32: 4865 | L32: 0.18 | M32: 3.5
A33: Russian Federation | B33: 1000099 | C33: -930560 | D33: 610129 | E33: Tons | F33: 1639 | G33: 12 | H33: 11 | I33: -11 | J33: 1.6 | K33: 4026 | L33: 0.38 | M33: 3.2
A34: Malaysia | B34: 951759 | C34: 204025 | D34: 486053 | E34: Tons | F34: 1958 | G34: 4 | H34: 1 | I34: -24 | J34: 1.5 | K34: 3952 | L34: 0.15 | M34: 3.6
A35: Czech Republic | B35: 946256 | C35: -588773 | D35: 355663 | E35: Tons | F35: 2661 | G35: 6 | I35: -11 | J35: 1.5 | K35: 1403 | L35: 0.16 | M35: 2.1
A36: Brazil | B36: 876307 | C36: -681644 | D36: 434690 | E36: Tons | F36: 2016 | G36: 11 | H36: 5 | I36: -21 | J36: 1.4 | K36: 12481 | L36: 0.16 | M36: 11.1
A37: Taipei, Chinese | B37: 839090 | C37: 2864429 | D37: 305202 | E37: Tons | F37: 2749 | G37: 0 | H37: -1 | I37: -29 | J37: 1.3 | K37: 3676 | L37: 0.17 | M37: 2.6
A38: Austria | B38: 688473 | C38: -296278 | D38: 239552 | E38: Tons | F38: 2874 | G38: 6 | H38: -4 | I38: -21 | J38: 1.1 | K38: 1154 | L38: 0.26 | M38: 2.1
A39: United Arab Emirates | B39: 668314 | C39: -539065 | D39: 0 | E39: No quantity | G39: 21 | H39: 28 | I39: -16 | J39: 1 | K39: 5545 | L39: 0.36 | M39: 4.5
A40: Portugal | B40: 642930 | C40: -525852 | D40: 0 | E40: No quantity | G40: 13 | I40: -16 | J40: 1 | K40: 2444 | L40: 0.22 | M40: 2.1
A41: Switzerland | B41: 601372 | C41: 32969 | D41: 177815 | E41: Tons | F41: 3382 | G41: 7 | H41: 0 | I41: -16 | J41: 0.9 | K41: 2972 | L41: 0.12 | M41: 0.1
A42: Hungary | B42: 576155 | C42: -380050 | D42: 0 | E42: No quantity | G42: 6 | I42: -21 | J42: 0.9 | K42: 2712 | L42: 0.09 | M42: 2.1
A43: Romania | B43: 574385 | C43: -384262 | D43: 0 | E43: No quantity | G43: 9 | I43: -10 | J43: 0.9 | K43: 1704 | L43: 0.1 | M43: 2.1
A44: Singapore | B44: 573907 | C44: 770473 | D44: 217080 | E44: Tons | F44: 2644 | G44: -4 | H44: -7 | I44: -28 | J44: 0.9 | K44: 7596 | L44: 0.13 | M44: 0
A45: Philippines | B45: 544210 | C45: -524505 | D45: 299505 | E45: Tons | F45: 1817 | G45: 10 | H45: 6 | I45: -23 | J45: 0.8 | K45: 2845 | L45: 0.23 | M45: 3.3
A46: Hong Kong, China | B46: 423883 | C46: 34436 | D46: 121846 | E46: Tons | F46: 3479 | G46: -19 | H46: -22 | I46: -39 | J46: 0.7 | K46: 3857 | L46: 0.15 | M46: 0
A47: Slovakia | B47: 410472 | C47: -278097 | D47: 141276 | E47: Tons | F47: 2905 | G47: 11 | I47: -3 | J47: 0.6 | K47: 1304 | L47: 0.16 | M47: 2.1
A48: Sweden | B48: 409895 | C48: -235669 | D48: 144454 | E48: Tons | F48: 2838 | G48: 7 | H48: -1 | I48: -20 | J48: 0.6 | K48: 1189 | L48: 0.14 | M48: 2.1
A49: Algeria | B49: 328178 | C49: -321194 | D49: 274869 | E49: Tons | F49: 1194 | G49: 9 | H49: 7 | I49: -26 | J49: 0.5 | K49: 6473 | L49: 0.33 | M49: 4.1
A50: Egypt | B50: 327095 | C50: 126327 | D50: 147723 | E50: Tons | F50: 2214 | G50: -2 | H50: -16 | I50: -35 | J50: 0.5 | K50: 5293 | L50: 0.18 | M50: 1.3
A51: Morocco | B51: 326745 | C51: -309643 | D51: 173151 | E51: Tons | F51: 1887 | G51: 14 | H51: 7 | I51: -17 | J51: 0.5 | K51: 5029 | L51: 0.09 | M51: 4
A52: Colombia | B52: 318811 | C52: -237922 | D52: 216600 | E52: Tons | F52: 1472 | G52: 10 | H52: 5 | I52: -44 | J52: 0.5 | K52: 11438 | L52: 0.29 | M52: 2.7
A53: Australia | B53: 311319 | C53: -278495 | D53: 183188 | E53: Tons | F53: 1699 | G53: 5 | H53: 0 | I53: -20 | J53: 0.5 | K53: 8995 | L53: 0.14 | M53: 3.1
A54: Saudi Arabia | B54: 290614 | C54: 699800 | D54: 190647 | E54: Tons | F54: 1524 | G54: 8 | H54: 7 | I54: -16 | J54: 0.5 | K54: 6215 | L54: 0.2 | M54: 5.1
A55: Denmark | B55: 273932 | C55: -221291 | D55: 91173 | E55: Tons | F55: 3005 | G55: 8 | H55: -2 | I55: -15 | J55: 0.4 | K55: 1980 | L55: 0.15 | M55: 2.1
A56: Argentina | B56: 263036 | C56: -258872 | D56: 116035 | E56: Tons | F56: 2267 | G56: 19 | H56: 10 | I56: -18 | J56: 0.4 | K56: 9026 | L56: 0.19 | M56: 10.2
A57: Bangladesh | B57: 262792 | C57: -231093 | D57: 242243 | E57: Tons | F57: 1085 | G57: 6 | H57: 7 | I57: -28 | J57: 0.4 | K57: 2677 | L57: 0.29 | M57: 5.2
A58: Israel | B58: 259272 | C58: -180954 | D58: 108846 | E58: Tons | F58: 2382 | G58: 3 | H58: -6 | I58: -37 | J58: 0.4 | K58: 5839 | L58: 0.15 | M58: 0
A59: Peru | B59: 258526 | C59: -229379 | D59: 197260 | E59: Tons | F59: 1311 | G59: 6 | H59: 2 | I59: -42 | J59: 0.4 | K59: 14767 | L59: 0.57 | M59: 0.1
... A67: Kazakhstan | B67: 187856 | C67: -163489 | D67: 113884 | E67: Tons | F67: 1650 | G67: 14 | H67: 2 | I67: -12 | J67: 0.3 | K67: 3847 | L67: 0.37 | M67: 3.2
A68: Greece | B68: 187693 | C68: -106297 | D68: 0 | E68: No quantity | G68: 14 | I68: -6 | J68: 0.3 | K68: 2634 | L68: 0.1 | M68: 2.1
A69: Uzbekistan | B69: 180199 | C69: -177571 | D69: 147253 | E69: Tons | F69: 1224 | G69: 20 | H69: 17 | I69: 0 | J69: 0.3 | K69: 4096 | L69: 0.51 | M69: 0
A70: El Salvador | B70: 179229 | C70: -175592 | D70: 132641 | E70: Tons | F70: 1351 | G70: 18 | H70: 12 | I70: -32 | J70: 0.3 | K70: 10380 | L70: 0.31 | M70: 0.2
A71: Tunisia | B71: 174456 | C71: -142752 | D71: 109138 | E71: Tons | F71: 1598 | G71: 12 | H71: 9 | I71: -18 | J71: 0.3 | K71: 4601 | L71: 0.15 | M71: 0.9
A72: Nigeria | B72: 172300 | C72: -160149 | D72: 138606 | E72: Tons | F72: 1243 | G72: -5 | H72: -9 | I72: -55 | J72: 0.3 | K72: 10550 | L72: 0.49 | M72: 4.7
A73: Lithuania | B73: 172147 | C73: 445551 | D73: 0 | E73: No quantity | G73: 15 | I73: -35 | J73: 0.3 | K73: 2301 | L73: 0.07 | M73: 2.1
A74: Iraq | B74: 166747 | C74: -166681 | D74: 154561 | E74: Tons | F74: 1079 | G74: 25 | H74: 40 | I74: -21 | J74: 0.3 | K74: 4450 | L74: 0.41 | M74: ...
A75: Serbia | B75: 159085 | C75: -130203 | D75: 90614 | E75: Tons | F75: 1756 | G75: 6 | H75: -2 | I75: -26 | J75: 0.2 | K75: 3995 | L75: 0.21 | M75: 0.9
A76: Pakistan | B76: 157518 | C76: 20443 | D76: 114557 | E76: Tons | F76: 1375 | G76: 5 | H76: 6 | I76: -31 | J76: 0.2 | K76: 4379 | L76: 0.48 | M76: 11.7
A77: Tanzania, United Republic of | B77: 152657 | C77: -145902 | D77: 130431 | E77: Tons | F77: 1170 | G77: 21 | H77: 14 | I77: -33 | J77: 0.2 | K77: 8803 | L77: 0.68 | M77: 1.4
A78: Ethiopia | B78: 148374 | C78: -148171 | D78: 317764 | E78: Tons | F78: 467 | G78: 5 | H78: 31 | I78: -5 | J78: 0.2 | K78: 7099 | L78: 0.44 | M78: 6
A79: Finland | B79: 148304 | C79: -58177 | D79: 38706 | E79: Tons | F79: 3832 | G79: 5 | H79: -4 | I79: -15 | J79: 0.2 | K79: 1955 | L79: 0.14 | M79: 2.1
A80: Uganda | B80: 142538 | C80: -141404 | D80: 120308 | E80: Tons | F80: 1185 | G80: 17 | H80: 14 | I80: -10 | J80: 0.2 | K80: 8395 | L80: 0.63 | M80: 1.4
A81: Uruguay | B81: 133237 | C81: -130059 | D81: 104749 | E81: Tons | F81: 1272 | G81: 8 | H81: 3 | I81: -21 | J81: 0.2 | K81: 16945 | L81: 0.69 | M81: 10.4
A82: Ecuador | B82: 130927 | C82: -99360 | D82: 93615 | E82: Tons | F82: 1399 | G82: 13 | H82: 9 | I82: -27 | J82: 0.2 | K82: 12940 | L82: 0.48 | M82: 0
A83: Dominican Republic | B83: 124727 | C83: -95193 | D83: 74056 | E83: Tons | F83: 1684 | G83: 16 | H83: 8 | I83: -6 | J83: 0.2 | K83: 8836 | L83: 0.25 | M83: 1
A84: Ghana | B84: 114091 | C84: -111842 | D84: 99255 | E84: Tons | F84: 1149 | G84: 3 | H84: 0 | I84: -15 | J84: 0.2 | K84: 11477 | L84: 0.73 | M84: 4.3
A85: Guatemala | B85: 101364 | C85: -90850 | D85: 71930 | E85: Tons | F85: 1409 | G85: 10 | H85: 4 | I85: -32 | J85: 0.2 | K85: 9324 | L85: 0.33 | M85: 0.2
A86: Kenya | B86: 98021 | C86: -86397 | D86: 76480 | E86: Tons | F86: 1282 | G86: 2 | H86: -1 | I86: -16 | J86: 0.2 | K86: 7819 | L86: 0.48 | M86: 1.4
A87: Myanmar | B87: 96092 | C87: -89098 | D87: 88537 | E87: Tons | F87: 1085 | G87: 13 | I87: 24 | J87: 0.1 | K87: 2554 | L87: 0.46 | M87: 1.4
A88: Jordan | B88: 80027 | C88: -70465 | D88: 49733 | E88: Tons | F88: 1609 | G88: 12 | H88: 3 | I88: -10 | J88: 0.1 | K88: 3719 | L88: 0.22 | M88: 0
A89: Norway | B89: 79835 | C89: -48151 | D89: 20941 | E89: Tons | F89: 3812 | G89: 5 | H89: -3 | I89: -24 | J89: 0.1 | K89: 1957 | L89: 0.11 | M89: 0
A90: New Zealand | B90: 78620 | C90: -76091 | D90: 39278 | E90: Tons | F90: 2002 | G90: 5 | H90: -1 | I90: -28 | J90: 0.1 | K90: 8224 | L90: 0.17 | M90: 1.5
A91: Costa Rica | B91: 75411 | C91: -68467 | D91: 30042 | E91: Tons | F91: 2510 | G91: 15 | H91: 4 | I91: -7 | J91: 0.1 | K91: 7344 | L91: 0.25 | M91: 0.2
A92: Croatia | B92: 75145 | C92: -31208 | D92: 38685 | E92: Tons | F92: 1942 | G92: 15 | H92: 9 | I92: -8 | J92: 0.1 | K92: 1687 | L92: 0.12 | M92: 2.1
A93: Iran, Islamic Republic of | B93: 72988 | C93: -59302 | D93: 41767 | E93: Tons | F93: 1748 | G93: -19 | H93: -23 | I93: -16 | J93: 0.1 | K93: 4689 | L93: 0.45 | M93: 7.2
A94: Côte d'Ivoire | B94: 67676 | C94: -67357 | D94: 58087 | E94: Tons | F94: 1165 | G94: 12 | H94: 9 | I94: -6 | J94: 0.1 | K94: 10898 | L94: 0.62 | M94: 4.4
A95: Cambodia | B95: 63135 | C95: -62440 | D95: 60563 | E95: Tons | F95: 1042 | G95: 10 | H95: 9 | I95: -14 | J95: 0.1 | K95: 2420 | L95: 0.35 | M95: 0
A96: Paraguay | B96: 61653 | C96: -52507 | D96: 46132 | E96: Tons | F96: 1336 | G96: -4 | H96: -10 | I96: -40 | J96: 0.1 | K96: 7552 | L96: 0.25 | M96: 5
A97: Zimbabwe | B97: 59197 | C97: -58776 | D97: 0 | E97: No quantity | G97: 20 | I97: -3 | J97: 0.1 | K97: 6237 | L97: 0.28 | M97: 4.5
A98: Bosnia and Herzegovina | B98: 57717 | C98: -57175 | D98: 28511 | E98: Tons | F98: 2024 | G98: 10 | H98: 4 | I98: -13 | J98: 0.1 | K98: 2689 | L98: 0.14 | M98: 1.2
A99: Lebanon | B99: 56503 | C99: -53799 | D99: 41925 | E99: Tons | F99: 1348 | G99: 1 | H99: -4 | I99: 0 | J99: 0.1 | K99: 4111 | L99: 0.25 | M99: 0
A100: Bahrain | B100: 56232 | C100: -55079 | D100: 27022 | E100: Tons | F100: 2081 | G100: -2 | H100: -16 | I100: -40 | J100: 0.1 | K100: 4724 | L100: 0.36 | M100: 4.5
A101: Belarus | B101: 56203 | C101: -47330 | D101: 22943 | E101: Tons | F101: 2450 | G101: 6 | H101: -1 | I101: 1 | J101: 0.1 | K101: 2221 | L101: 0.14 | M101: 3.2
A102: Estonia | B102: 55633 | C102: -12528 | D102: 0 | E102: No quantity | G102: 0 | I102: -31 | J102: 0.1 | K102: 1500 | L102: 0.13 | M102: 2.1
A103: Venezuela, Bolivarian Republic of | B103: 54683 | C103: -52515 | D103: 0 | E103: No quantity | G103: 50 | H103: 45 | I103: -14 | J103: 0.1 | K103: 10122 | L103: 0.37 | M103: 11.4
A104: Sri Lanka | B104: 52932 | C104: -52816 | D104: 0 | E104: No quantity | G104: -2 | I104: -28 | J104: 0.1 | K104: 4226 | L104: 0.17 | M104: 0
A105: Oman | B105: 49962 | C105: 172393 | D105: 34912 | E105: Tons | F105: 1431 | G105: 28 | H105: 25 | I105: -15 | J105: 0.1 | K105: 5207 | L105: 0.15 | M105: 4.5
A106: Kyrgyzstan | B106: 48755 | C106: -45633 | D106: 35895 | E106: Tons | F106: 1358 | G106: 30 | H106: 20 | I106: 6 | J106: 0.1 | K106: 2953 | L106: 0.52 | M106: 3.2
A107: Libya, State of | B107: 47898 | C107: -47825 | D107: 36502 | E107: Tons | F107: 1312 | G107: 21 | H107: 16 | I107: -16 | J107: 0.1 | K107: 5301 | L107: 0.29 | M107: 4.6
A108: Azerbaijan | B108: 47212 | C108: -45644 | D108: 29969 | E108: Tons | F108: 1575 | G108: 14 | H108: 9 | I108: 14 | J108: 0.1 | K108: 3302 | L108: 0.4 | M108: 0.6
A109: Latvia | B109: 47074 | C109: 7498 | D109: 43874 | E109: Tons | F109: 1073 | G109: 9 | H109: 2 | I109: -47 | J109: 0.1 | K109: 1436 | L109: 0.09 | M109: 2.1
A110: Angola | B110: 44935 | C110: -44919 | D110: 38722 | E110: Tons | F110: 1160 | G110: 21 | H110: 25 | I110: -22 | J110: 0.1 | K110: 10208 | L110: 0.48 | M110: 0
...

Sheet Costing flow
B2: LƯU ĐỒ TÍNH GIÁ THÀNH
AA4: FOP
AA9: OVH COST
B32: 1001603000 | C32: Khối SX - Xưởng 1 | D32: Khối gián tiếp
B33: 1001604000 | C33: Khối SX - Xưởng 2 | D33: Khối gián tiếp | G33: 1001602000 | H33: Xưởng sản xuất PET
B34: 1001605000 | C34: Khối SX - Xưởng 4 | D34: Khối gián tiếp | G34: 1001606000 | H34: Xưởng sản xuất HDPE
B35: 1001601500 | C35: Nghiên Cứu & Phát Triển | D35: Khối gián tiếp
B36: 1001607000 | C36: Kho | D36: Khối gián tiếp
B37: 1001601200 | C37: Khối SX - Kế hoạch | D37: Khối gián tiếp
B38: 1001601300 | C38: Kỹ thuật | D38: Khối gián tiếp
B39: 1001601400 | C39: Kiểm soát chất lượng | D39: Khối gián tiếp
B42: 1001608000 | C42: Xưởng sản xuất PP

Sheet EX-1B Data source
A1: Aluminum Wire and Cable from the People’s Republic of China (A-570-095, C-570-096)
A2: Circumvention & Scope Inquiries: Vietnam
A3: Vietnam Part - Surrogate Values from Indonesia
A5: Data source
A7: Exhibit | B7: Description | C7: Data source
A8: 1 | B8: Surrogate Value Summary Sheet
A9: 2 | B9: Trademap - Indonesia Import Data | C9: https://www.trademap.org/Index.aspx
A10: 3 | B10: Indonesia Exchange Rate | C10: https://access.trade.gov/resources/exchange/index.html
A11: 4 | B11: Consumer Price Index-Indonesia | C11: https://data.imf.org/regular.aspx?key=61545849
A12: 5A | B12: Labor Calculation | C12: https://rshiny.ilo.org/dataexplorer54/?lang=en&id=IDN_A
A13: 5B | B13: ILOSTAT Data
A14: 6A | B14: Electricity Rate Summary | C14: https://web.pln.co.id/pelanggan/tarif-tenaga-listrik/tariff-adjustment
A15: 6B | B15: PLN Tariff Rates
A16: 9A | B16: Freight Rate Summary | C16: https://archive.doingbusiness.org/content/dam/doingBusiness/country/i/indonesia/IDN.pdf
A17: 9B | B17: Doing Business Indonesia
A18: 10A | B18: Financial Ratio Summary
A19: 10B1 | B19: Financial Ratio Calculations - KMI | C19: https://kmi.id/index.php/investor/financial-statement
A20: 10B2 | B20: KMI Financial Statement
A21: 10C1 | B21: Financial Ratio Calculations - VOKSEL | C21: https://www.voksel.co.id/en/financial_report
A22: 10C2 | B22: VOKSEL Financial Statement

Sheet EX-2.1 Chai & vảy
B1: List of supplying markets for a product imported by Egypt | E1: ='EX-1A SV Summary'!D8 -> 39159010
B2: Product: Plastics n.e.c. in heading no. 3915; waste, parings and scrap
B3: Link: | C3: UN Comtrade
B5: EXCLUDE | C5: World
C6: China
C7: Hong Kong, China
C8: Taipei, Chinese
C9: Russian Federation
A11: 1/ | B11: Quantity | S11: PERIOD OF INVESTIGATION | T11: Y
B12: Unit : ton | S12: flowDesc | T12: Import
S13: reporterDesc | T13: Egypt
C14: 2023 | I14: 2024 | O14: Grand Total | P14: Mark | Q14: Note
B15: partnerDesc/ month | C15: 7 | D15: 8 | E15: 9 | F15: 10 | G15: 11 | H15: 12 | I15: 1 | J15: 2 | K15: 3 | L15: 4 | M15: 5 | N15: 6 | S15: Sum of qty | T15: refYear | U15: refMonth
B16: World | C16: 1798598.4 | D16: 1150297.3 | E16: 1594909.6 | F16: 1886942.6 | G16: 2965111.9 | H16: 401290.57 | I16: 2857655.9 | J16: 2209983 | K16: 3903209.6 | L16: 3086149.9 | M16: 776351.35 | N16: 899867.08 | O16: 23530367 | P16: Exclude | T16: 2023 | Z16: 2024 | AF16: Grand Total
B17: Spain | D17: 112718.34 | E17: 186577.67 | F17: 741812.51 | G17: 2003614.7 | H17: 116959.41 | I17: 1554447.4 | J17: 1309526.1 | K17: 1709751.1 | L17: 1305342.8 | M17: 55817.316 | N17: 85018.433 | O17: 9181585.7 | P17: Include | Q17: Qty | S17: partnerDesc | T17: 7 | U17: 8 | V17: 9 | W17: 10 | X17: 11 | Y17: 12 | Z17: 1 | AA17: 2 | AB17: 3 | AC17: 4 | AD17: 5 | AE17: 6
B18: Yemen | C18: 1213316.3 | E18: 790886.02 | F18: 377588.07 | I18: 1083004.5 | K18: 1541964.3 | L18: 972510.51 | N18: 808887.86 | O18: 6788157.6 | P18: Include | Q18: Qty | S18: World | T18: 1798598.4 | U18: 1150297.3 | V18: 1594909.6 | W18: 1886942.6 | X18: 2965111.9 | Y18: 401290.57 | Z18: 2857655.9 | AA18: 2209983 | AB18: 3903209.6 | AC18: 3086149.9 | AD18: 776351.35 | AE18: 899867.08 | AF18: 23530367
B19: Türkiye | D19: 252442.15 | E19: 162114.02 | F19: 194420.92 | G19: 283785.42 | H19: 191233.02 | J19: 271848.64 | K19: 248505.58 | L19: 297114.45 | M19: 187705.03 | O19: 2089169.2 | P19: Include | Q19: Qty | S19: Spain | U19: 112718.34 | V19: 186577.67 | W19: 741812.51 | X19: 2003614.7 | Y19: 116959.41 | Z19: 1554447.4 | AA19: 1309526.1 | AB19: 1709751.1 | AC19: 1305342.8 | AD19: 55817.316 | AE19: 85018.433 | AF19: 9181585.7
B20: Senegal | D20: 555376.43 | G20: 174744.25 | J20: 434372.61 | M20: 461061.17 | O20: 1625554.5 | P20: Include | Q20: Qty | S20: Yemen | T20: 1213316.3 | V20: 790886.02 | W20: 377588.07 | Z20: 1083004.5 | AB20: 1541964.3 | AC20: 972510.51 | AE20: 808887.86 | AF20: 6788157.6
B21: United Arab Emirates | E21: 198360.69 | F21: 16039.217 | G21: 463874.95 | H21: 9991.435 | K21: 117126.13 | O21: 805392.42 | P21: Include | Q21: Qty | S21: Türkiye | U21: 252442.15 | V21: 162114.02 | W21: 194420.92 | X21: 283785.42 | Y21: 191233.02 | AA21: 271848.64 | AB21: 248505.58 | AC21: 297114.45 | AD21: 187705.03 | AF21: 2089169.2
B22: Italy | C22: 410741.67 | F22: 16060.965 | J22: 154701.26 | K22: 55098.784 | M22: 58671.56 | N22: 5960.789 | O22: 701235.03 | P22: Include | Q22: Qty | S22: Senegal | U22: 555376.43 | X22: 174744.25 | AA22: 434372.61 | AD22: 461061.17 | AF22: 1625554.5
B23: United Kingdom | E23: 120527.34 | F23: 286475.9 | I23: 105431.31 | M23: 13096.269 | O23: 525530.82 | P23: Include | Q23: Qty | S23: United Arab Emirates | V23: 198360.69 | W23: 16039.217 | X23: 463874.95 | Y23: 9991.435 | AB23: 117126.13 | AF23: 805392.42
B24: Netherlands | C24: 91298.79 | F24: 231700.51 | L24: 201119.93 | O24: 524119.23 | P24: Include | Q24: Qty | S24: Italy | T24: 410741.67 | W24: 16060.965 | AA24: 154701.26 | AB24: 55098.784 | AD24: 58671.56 | AE24: 5960.789 | AF24: 701235.03
B25: Germany | G25: 38390.017 | H25: 22186.675 | I25: 73351.927 | K25: 206114.12 | O25: 340042.74 | P25: Include | Q25: Qty | S25: United Kingdom | V25: 120527.34 | W25: 286475.9 | Z25: 105431.31 | AD25: 13096.269 | AF25: 525530.82
B26: Lebanon | L26: 285950.78 | O26: 285950.78 | P26: Include | Q26: Qty | S26: Netherlands | T26: 91298.79 | W26: 231700.51 | AC26: 201119.93 | AF26: 524119.23
B27: China | C27: 27166.987 | E27: 136443.89 | H27: 60920.02 | O27: 224530.89 | P27: Exclude | S27: Germany | X27: 38390.017 | Y27: 22186.675 | Z27: 73351.927 | AB27: 206114.12 | AF27: 340042.74
B28: Nigeria | D28: 138642.02 | O28: 138642.02 | P28: Include | Q28: Qty | S28: Lebanon | AC28: 285950.78 | AF28: 285950.78
B29: United Rep. of Tanzania | D29: 91118.38 | O29: 91118.38 | P29: Include | Q29: Qty | S29: China | T29: 27166.987 | V29: 136443.89 | Y29: 60920.02 | AF29: 224530.89
B30: Greece | C30: 56074.632 | F30: 22844.554 | O30: 78919.186 | P30: Include | Q30: Qty | S30: Nigeria | U30: 138642.02 | AF30: 138642.02
B31: Other Europe, nes | I31: 41420.707 | O31: 41420.707 | P31: Include | Q31: Qty | S31: United Rep. of Tanzania | U31: 91118.38 | AF31: 91118.38
B32: France | J32: 39534.404 | O32: 39534.404 | P32: Include | Q32: Qty | S32: Greece | T32: 56074.632 | W32: 22844.554 | AF32: 78919.186
B33: Portugal | K33: 24649.646 | O33: 24649.646 | P33: Include | Q33: Qty | S33: Other Europe, nes | Z33: 41420.707 | AF33: 41420.707
B34: Belgium | L34: 24111.398 | O34: 24111.398 | P34: Include | Q34: Qty | S34: France | AA34: 39534.404 | AF34: 39534.404
B35: USA | G35: 702.49 | O35: 702.49 | P35: Include | Q35: Qty | S35: Portugal | AB35: 24649.646 | AF35: 24649.646
B36: Grand Total | C36: 3597196.8 | D36: 2300594.6 | E36: 3189819.2 | F36: 3773885.3 | G36: 5930223.7 | H36: 802581.13 | I36: 5715311.7 | J36: 4419965.9 | K36: 7806419.3 | L36: 6172299.8 | M36: 1552702.7 | N36: 1799734.2 | O36: 47060734 | S36: Belgium | AC36: 24111.398 | AF36: 24111.398
S37: USA | X37: 702.49 | AF37: 702.49
S38: Grand Total | T38: 3597196.8 | U38: 2300594.6 | V38: 3189819.2 | W38: 3773885.3 | X38: 5930223.7 | Y38: 802581.13 | Z38: 5715311.7 | AA38: 4419965.9 | AB38: 7806419.3 | AC38: 6172299.8 | AD38: 1552702.7 | AE38: 1799734.2 | AF38: 47060734
A39: 2/ | B39: Value
B40: Unit : US Dollar thousand | S40: PERIOD OF INVESTIGATION | T40: Y
S41: flowDesc | T41: Import
C42: 2023 | I42: 2024 | O42: Grand Total | P42: Mark | Q42: Note | S42: reporterDesc | T42: Egypt
B43: partnerDesc/ month | C43: 7 | D43: 8 | E43: 9 | F43: 10 | G43: 11 | H43: 12 | I43: 1 | J43: 2 | K43: 3 | L43: 4 | M43: 5 | N43: 6
B44: World | C44: 992417.39 | D44: 634702.58 | E44: 880027.49 | F44: 1041163.3 | G44: 1636067.6 | H44: 221421.15 | I44: 1576776.3 | J44: 1219408.1 | K44: 2153684.3 | L44: 1702853.1 | M44: 428369.43 | N44: 496522.03 | O44: 12983413 | P44: =VLOOKUP(B44,$B$16:$P$35,15,0) -> Exclude | S44: Sum of primaryValue | T44: refYear | U44: refMonth
B45: Spain | D45: 62194.895 | E45: 102948.45 | F45: 409311.84 | G45: 1105539.8 | H45: 64535.004 | I45: 857701.54 | J45: 722560.64 | K45: 943393.84 | L45: 720252.44 | M45: 30798.468 | N45: 46910.845 | O45: 5066147.8 | P45: =VLOOKUP(B45,$B$16:$P$35,15,0) -> Include | Q45: Val | T45: 2023 | Z45: 2024 | AF45: Grand Total
B46: Yemen | C46: 669474.75 | E46: 436389.27 | F46: 208342.76 | I46: 597572.25 | K46: 850813.72 | L46: 536604.69 | N46: 446322.18 | O46: 3745519.6 | P46: =VLOOKUP(B46,$B$16:$P$35,15,0) -> Include | Q46: Val | S46: partnerDesc | T46: 7 | U46: 8 | V46: 9 | W46: 10 | X46: 11 | Y46: 12 | Z46: 1 | AA46: 2 | AB46: 3 | AC46: 4 | AD46: 5 | AE46: 6
B47: Türkiye | D47: 139290.67 | E47: 89450.078 | F47: 107276.14 | G47: 156585.03 | H47: 105517.15 | J47: 149998.64 | K47: 137118.58 | L47: 163939.62 | M47: 103570.5 | O47: 1152746.4 | P47: =VLOOKUP(B47,$B$16:$P$35,15,0) -> Include | Q47: Val | S47: World | T47: 992417.39 | U47: 634702.58 | V47: 880027.49 | W47: 1041163.3 | X47: 1636067.6 | Y47: 221421.15 | Z47: 1576776.3 | AA47: 1219408.1 | AB47: 2153684.3 | AC47: 1702853.1 | AD47: 428369.43 | AE47: 496522.03 | AF47: 12983413
B48: Senegal | D48: 306441.52 | G48: 96419.094 | J48: 239674.92 | M48: 254400.94 | O48: 896936.47 | P48: =VLOOKUP(B48,$B$16:$P$35,15,0) -> Include | Q48: Val | S48: Spain | U48: 62194.895 | V48: 102948.45 | W48: 409311.84 | X48: 1105539.8 | Y48: 64535.004 | Z48: 857701.54 | AA48: 722560.64 | AB48: 943393.84 | AC48: 720252.44 | AD48: 30798.468 | AE48: 46910.845 | AF48: 5066147.8
B49: United Arab Emirates | E49: 109450 | F49: 8850.001 | G49: 255953.5 | H49: 5513.001 | K49: 64626.994 | O49: 444393.5 | P49: =VLOOKUP(B49,$B$16:$P$35,15,0) -> Include | Q49: Val | S49: Yemen | T49: 669474.75 | V49: 436389.27 | W49: 208342.76 | Z49: 597572.25 | AB49: 850813.72 | AC49: 536604.69 | AE49: 446322.18 | AF49: 3745519.6
B50: Italy | C50: 226636.02 | F50: 8862.001 | J50: 85359.922 | K50: 30402.001 | M50: 32373.361 | N50: 3289 | O50: 386922.3 | P50: =VLOOKUP(B50,$B$16:$P$35,15,0) -> Include | Q50: Val | S50: Türkiye | U50: 139290.67 | V50: 89450.078 | W50: 107276.14 | X50: 156585.03 | Y50: 105517.15 | AA50: 149998.64 | AB50: 137118.58 | AC50: 163939.62 | AD50: 103570.5 | AF50: 1152746.4
B51: United Kingdom | E51: 66503.688 | F51: 158069.56 | I51: 58174.113 | M51: 7226.163 | O51: 289973.53 | P51: =VLOOKUP(B51,$B$16:$P$35,15,0) -> Include | Q51: Val | S51: Senegal | U51: 306441.52 | X51: 96419.094 | AA51: 239674.92 | AD51: 254400.94 | AF51: 896936.47
B52: Netherlands | C52: 50376.174 | F52: 127846 | L52: 110972.48 | O52: 289194.65 | P52: =VLOOKUP(B52,$B$16:$P$35,15,0) -> Include | Q52: Val | S52: United Arab Emirates | V52: 109450 | W52: 8850.001 | X52: 255953.5 | Y52: 5513.001 | AB52: 64626.994 | AF52: 444393.5
B53: Germany | G53: 21182.561 | H53: 12242 | I53: 40473.586 | K53: 113728.13 | O53: 187626.28 | P53: =VLOOKUP(B53,$B$16:$P$35,15,0) -> Include | Q53: Val | S53: Italy | T53: 226636.02 | W53: 8862.001 | AA53: 85359.922 | AB53: 30402.001 | AD53: 32373.361 | AE53: 3289 | AF53: 386922.3
B54: Lebanon | L54: 157779.81 | O54: 157779.81 | P54: =VLOOKUP(B54,$B$16:$P$35,15,0) -> Include | Q54: Val | S54: United Kingdom | V54: 66503.688 | W54: 158069.56 | Z54: 58174.113 | AD54: 7226.163 | AF54: 289973.53
B55: China | C55: 14990 | E55: 75286.004 | H55: 33614 | O55: 123890 | P55: =VLOOKUP(B55,$B$16:$P$35,15,0) -> Exclude | S55: Netherlands | T55: 50376.174 | W55: 127846 | AC55: 110972.48 | AF55: 289194.65
B56: Nigeria | D56: 76498.875 | O56: 76498.875 | P56: =VLOOKUP(B56,$B$16:$P$35,15,0) -> Include | Q56: Val | S56: Germany | X56: 21182.561 | Y56: 12242 | Z56: 40473.586 | AB56: 113728.13 | AF56: 187626.28
B57: United Rep. of Tanzania | D57: 50276.629 | O57: 50276.629 | P57: =VLOOKUP(B57,$B$16:$P$35,15,0) -> Include | Q57: Val | S57: Lebanon | AC57: 157779.81 | AF57: 157779.81
B58: Greece | C58: 30940.447 | F58: 12605 | O58: 43545.447 | P58: =VLOOKUP(B58,$B$16:$P$35,15,0) -> Include | Q58: Val | S58: China | T58: 14990 | V58: 75286.004 | Y58: 33614 | AF58: 123890
B59: Other Europe, nes | I59: 22854.813 | O59: 22854.813 | P59: =VLOOKUP(B59,$B$16:$P$35,15,0) -> Include | Q59: Val | S59: Nigeria | U59: 76498.875 | AF59: 76498.875
B60: France | J60: 21814.002 | O60: 21814.002 | P60: =VLOOKUP(B60,$B$16:$P$35,15,0) -> Include | Q60: Val | S60: United Rep. of Tanzania | U60: 50276.629 | AF60: 50276.629
B61: Portugal | K61: 13601 | O61: 13601 | P61: =VLOOKUP(B61,$B$16:$P$35,15,0) -> Include | Q61: Val | S61: Greece | T61: 30940.447 | W61: 12605 | AF61: 43545.447
B62: Belgium | L62: 13304.01 | O62: 13304.01 | P62: =VLOOKUP(B62,$B$16:$P$35,15,0) -> Include | Q62: Val | S62: Other Europe, nes | Z62: 22854.813 | AF62: 22854.813
B63: USA | G63: 387.615 | O63: 387.615 | P63: =VLOOKUP(B63,$B$16:$P$35,15,0) -> Include | Q63: Val | S63: France | AA63: 21814.002 | AF63: 21814.002
B64: Grand Total | C64: 1984834.8 | D64: 1269405.2 | E64: 1760055 | F64: 2082326.6 | G64: 3272135.2 | H64: 442842.31 | I64: 3153552.6 | J64: 2438816.3 | K64: 4307368.5 | L64: 3405706.1 | M64: 856738.86 | N64: 993044.06 | O64: 25966825 | S64: Portugal | AB64: 13601 | AF64: 13601
S65: Belgium | AC65: 13304.01 | AF65: 13304.01
S66: USA | X66: 387.615 | AF66: 387.615
S67: Grand Total | T67: 1984834.8 | U67: 1269405.2 | V67: 1760055 | W67: 2082326.6 | X67: 3272135.2 | Y67: 442842.31 | Z67: 3153552.6 | AA67: 2438816.3 | AB67: 4307368.5 | AC67: 3405706.1 | AD67: 856738.86 | AE67: 993044.06 | AF67: 25966825
B68: Total quantity imported (Kg) | C68: Total value imported (USD) | D68: Unit price (USD/Kg)
B69: =SUMIFS(O:O,P:P,"Include",Q:Q,"QTY")*1000 -> 2.3305836e+10 | C69: =SUMIFS(O:O,P:P,"Include",Q:Q,"VAL")*1000 -> 1.2859523e+10 | D69: =C69/B69 -> 0.55177264
B74: MASTER DATA | L74: IMPORT/ EXPORT | O74: COUNTRY | AG74: QUANTITY | AS74: VALUE
A75: PERIOD OF INVESTIGATION | B75: typeCode | C75: freqCode | D75: refPeriodId | E75: refYear | F75: refMonth | G75: period | H75: reporterCode | I75: reporterISO | J75: reporterDesc | K75: flowCode | L75: flowDesc | M75: partnerCode | N75: partnerISO | O75: partnerDesc | P75: partner2Code | Q75: partner2ISO | R75: partner2Desc | S75: classificationCode | T75: classificationSearchCode | U75: isOriginalClassification | V75: cmdCode | W75: cmdDesc | X75: aggrLevel | Y75: isLeaf | Z75: customsCode | AA75: customsDesc | AB75: mosCode | AC75: motCode | AD75: motDesc | AE75: qtyUnitCode | AF75: qtyUnitAbbr | AG75: qty | AH75: isQtyEstimated | AI75: altQtyUnitCode | AJ75: altQtyUnitAbbr | AK75: altQty | AL75: isAltQtyEstimated | AM75: netWgt | AN75: isNetWgtEstimated | AO75: grossWgt | AP75: isGrossWgtEstimated | AQ75: cifvalue | AR75: fobvalue | AS75: primaryValue | AT75: legacyEstimationFlag | AU75: isReported | AV75: isAggregate
A76: Y | B76: C | C76: M | D76: 20240101 | E76: 2024 | F76: 1 | G76: 202401 | H76: 818 | I76: EGY | J76: Egypt | K76: M | L76: Import | M76: 0 | N76: W00 | O76: World | P76: 0 | Q76: W00 | R76: World | S76: H6 | T76: HS | U76: TRUE | V76: 391590 | W76: Plastics n.e.c. in heading no. 3915; waste, parings and scrap | X76: 6 | Y76: TRUE | Z76: C00 | AA76: TOTAL CPC | AB76: 0 | AC76: 0 | AD76: TOTAL MOT | AE76: 8 | AF76: kg | AG76: 2857655.9 | AH76: TRUE | AI76: -1 | AJ76: N/A | AK76: 0 | AL76: FALSE | AM76: 2857655.9 | AN76: TRUE | AO76: 0 | AP76: FALSE | AQ76: 1576776.3 | AS76: 1576776.3 | AT76: 6 | AU76: FALSE | AV76: TRUE
A77: Y | B77: C | C77: M | D77: 20240101 | E77: 2024 | F77: 1 | G77: 202401 | H77: 818 | I77: EGY | J77: Egypt | K77: M | L77: Import | M77: 276 | N77: DEU | O77: Germany | P77: 0 | Q77: W00 | R77: World | S77: H6 | T77: HS | U77: TRUE | V77: 391590 | W77: Plastics n.e.c. in heading no. 3915; waste, parings and scrap | X77: 6 | Y77: TRUE | Z77: C00 | AA77: TOTAL CPC | AB77: 0 | AC77: 0 | AD77: TOTAL MOT | AE77: 8 | AF77: kg | AG77: 73351.927 | AH77: TRUE | AI77: -1 | AJ77: N/A | AK77: 0 | AL77: FALSE | AM77: 73351.927 | AN77: TRUE | AO77: 0 | AP77: FALSE | AQ77: 40473.586 | AS77: 40473.586 | AT77: 6 | AU77: TRUE | AV77: FALSE
A78: Y | B78: C | C78: M | D78: 20240101 | E78: 2024 | F78: 1 | G78: 202401 | H78: 818 | I78: EGY | J78: Egypt | K78: M | L78: Import | M78: 568 | N78: E19 | O78: Other Europe, nes | P78: 0 | Q78: W00 | R78: World | S78: H6 | T78: HS | U78: TRUE | V78: 391590 | W78: Plastics n.e.c. in heading no. 3915; waste, parings and scrap | X78: 6 | Y78: TRUE | Z78: C00 | AA78: TOTAL CPC | AB78: 0 | AC78: 0 | AD78: TOTAL MOT | AE78: 8 | AF78: kg | AG78: 41420.707 | AH78: TRUE | AI78: -1 | AJ78: N/A | AK78: 0 | AL78: FALSE | AM78: 41420.707 | AN78: TRUE | AO78: 0 | AP78: FALSE | AQ78: 22854.813 | AS78: 22854.813 | AT78: 6 | AU78: TRUE | AV78: FALSE
A79: Y | B79: C | C79: M | D79: 20240101 | E79: 2024 | F79: 1 | G79: 202401 | H79: 818 | I79: EGY | J79: Egypt | K79: M | L79: Import | M79: 724 | N79: ESP | O79: Spain | P79: 0 | Q79: W00 | R79: World | S79: H6 | T79: HS | U79: TRUE | V79: 391590 | W79: Plastics n.e.c. in heading no. 3915; waste, parings and scrap | X79: 6 | Y79: TRUE | Z79: C00 | AA79: TOTAL CPC | AB79: 0 | AC79: 0 | AD79: TOTAL MOT | AE79: 8 | AF79: kg | AG79: 1554447.4 | AH79: TRUE | AI79: -1 | AJ79: N/A | AK79: 0 | AL79: FALSE | AM79: 1554447.4 | AN79: TRUE | AO79: 0 | AP79: FALSE | AQ79: 857701.54 | AS79: 857701.54 | AT79: 6 | AU79: TRUE | AV79: FALSE
A80: Y | B80: C | C80: M | D80: 20240101 | E80: 2024 | F80: 1 | G80: 202401 | H80: 818 | I80: EGY | J80: Egypt | K80: M | L80: Import | M80: 826 | N80: GBR | O80: United Kingdom | P80: 0 | Q80: W00 | R80: World | S80: H6 | T80: HS | U80: TRUE | V80: 391590 | W80: Plastics n.e.c. in heading no. 3915; waste, parings and scrap | X80: 6 | Y80: TRUE | Z80: C00 | AA80: TOTAL CPC | AB80: 0 | AC80: 0 | AD80: TOTAL MOT | AE80: 8 | AF80: kg | AG80: 105431.31 | AH80: TRUE | AI80: -1 | AJ80: N/A | AK80: 0 | AL80: FALSE | AM80: 105431.31 | AN80: TRUE | AO80: 0 | AP80: FALSE | AQ80: 58174.113 | AS80: 58174.113 | AT80: 6 | AU80: TRUE | AV80: FALSE
A81: Y | B81: C | C81: M | D81: 20240101 | E81: 2024 | F81: 1 | G81: 202401 | H81: 818 | I81: EGY | J81: Egypt | K81: M | L81: Import | M81: 887 | N81: YEM | O81: Yemen | P81: 0 | Q81: W00 | R81: World | S81: H6 | T81: HS | U81: TRUE | V81: 391590 | W81: Plastics n.e.c. in heading no. 3915; waste, parings and scrap | X81: 6 | Y81: TRUE | Z81: C00 | AA81: TOTAL CPC | AB81: 0 | AC81: 0 | AD81: TOTAL MOT | AE81: 8 | AF81: kg | AG81: 1083004.5 | AH81: TRUE | AI81: -1 | AJ81: N/A | AK81: 0 | AL81: FALSE | AM81: 1083004.5 | AN81: TRUE | AO81: 0 | AP81: FALSE | AQ81: 597572.25 | AS81: 597572.25 | AT81: 6 | AU81: TRUE | AV81: FALSE
A82: Y | B82: C | C82: M | D82: 20240201 | E82: 2024 | F82: 2 | G82: 202402 | H82: 818 | I82: EGY | J82: Egypt | K82: M | L82: Import | M82: 0 | N82: W00 | O82: World | P82: 0 | Q82: W00 | R82: World | S82: H6 | T82: HS | U82: TRUE | V82: 391590 | W82: Plastics n.e.c. in heading no. 3915; waste, parings and scrap | X82: 6 | Y82: TRUE | Z82: C00 | AA82: TOTAL CPC | AB82: 0 | AC82: 0 | AD82: TOTAL MOT | AE82: 8 | AF82: kg | AG82: 2209983 | AH82: TRUE | AI82: -1 | AJ82: N/A | AK82: 0 | AL82: FALSE | AM82: 2209983 | AN82: TRUE | AO82: 0 | AP82: FALSE | AQ82: 1219408.1 | AS82: 1219408.1 | AT82: 6 | AU82: FALSE | AV82: TRUE
A83: Y | B83: C | C83: M | D83: 20240201 | E83: 2024 | F83: 2 | G83: 202402 | H83: 818 | I83: EGY | J83: Egypt | K83: M | L83: Import | M83: 251 | N83: FRA | O83: France | P83: 0 | Q83: W00 | R83: World | S83: H6 | T83: HS | U83: TRUE | V83: 391590 | W83: Plastics n.e.c. in heading no. 3915; waste, parings and scrap | X83: 6 | Y83: TRUE | Z83: C00 | AA83: TOTAL CPC | AB83: 0 | AC83: 0 | AD83: TOTAL MOT | AE83: 8 | AF83: kg | AG83: 39534.404 | AH83: TRUE | AI83: -1 | AJ83: N/A | AK83: 0 | AL83: FALSE | AM83: 39534.404 | AN83: TRUE | AO83: 0 | AP83: FALSE | AQ83: 21814.002 | AS83: 21814.002 | AT83: 6 | AU83: TRUE | AV83: FALSE
A84: Y | B84: C | C84: M | D84: 20240201 | E84: 2024 | F84: 2 | G84: 202402 | H84: 818 | I84: EGY | J84: Egypt | K84: M | L84: Import | M84: 380 | N84: ITA | O84: Italy | P84: 0 | Q84: W00 | R84: World | S84: H6 | T84: HS | U84: TRUE | V84: 391590 | W84: Plastics n.e.c. in heading no. 3915; waste, parings and scrap | X84: 6 | Y84: TRUE | Z84: C00 | AA84: TOTAL CPC | AB84: 0 | AC84: 0 | AD84: TOTAL MOT | AE84: 8 | AF84: kg | AG84: 154701.26 | AH84: TRUE | AI84: -1 | AJ84: N/A | AK84: 0 | AL84: FALSE | AM84: 154701.26 | AN84: TRUE | AO84: 0 | AP84: FALSE | AQ84: 85359.922 | AS84: 85359.922 | AT84: 6 | AU84: TRUE | AV84: FALSE
A85: Y | B85: C | C85: M | D85: 20240201 | E85: 2024 | F85: 2 | G85: 202402 | H85: 818 | I85: EGY | J85: Egypt | K85: M | L85: Import | M85: 686 | N85: SEN | O85: Senegal | P85: 0 | Q85: W00 | R85: World | S85: H6 | T85: HS | U85: TRUE | V85: 391590 | W85: Plastics n.e.c. in heading no. 3915; waste, parings and scrap | X85: 6 | Y85: TRUE | Z85: C00 | AA85: TOTAL CPC | AB85: 0 | AC85: 0 | AD85: TOTAL MOT | AE85: 8 | AF85: kg | AG85: 434372.61 | AH85: TRUE | AI85: -1 | AJ85: N/A | AK85: 0 | AL85: FALSE | AM85: 434372.61 | AN85: TRUE | AO85: 0 | AP85: FALSE | AQ85: 239674.92 | AS85: 239674.92 | AT85: 6 | AU85: TRUE | AV85: FALSE
A86: Y | B86: C | C86: M | D86: 20240201 | E86: 2024 | F86: 2 | G86: 202402 | H86: 818 | I86: EGY | J86: Egypt | K86: M | L86: Import | M86: 724 | N86: ESP | O86: Spain | P86: 0 | Q86: W00 | R86: World | S86: H6 | T86: HS | U86: TRUE | V86: 391590 | W86: Plastics n.e.c. in heading no. 3915; waste, parings and scrap | X86: 6 | Y86: TRUE | Z86: C00 | AA86: TOTAL CPC | AB86: 0 | AC86: 0 | AD86: TOTAL MOT | AE86: 8 | AF86: kg | AG86: 1309526.1 | AH86: TRUE | AI86: -1 | AJ86: N/A | AK86: 0 | AL86: FALSE | AM86: 1309526.1 | AN86: TRUE | AO86: 0 | AP86: FALSE | AQ86: 722560.64 | AS86: 722560.64 | AT86: 6 | AU86: TRUE | AV86: FALSE
A87: Y | B87: C | C87: M | D87: 20240201 | E87: 2024 | F87: 2 | G87: 202402 | H87: 818 | I87: EGY | J87: Egypt | K87: M | L87: Import | M87: 792 | N87: TUR | O87: Türkiye | P87: 0 | Q87: W00 | R87: World | S87: H6 | T87: HS | U87: TRUE | V87: 391590 | W87: Plastics n.e.c. in heading no. 3915; waste, parings and scrap | X87: 6 | Y87: TRUE | Z87: C00 | AA87: TOTAL CPC | AB87: 0 | AC87: 0 | AD87: TOTAL MOT | AE87: 8 | AF87: kg | AG87: 271848.64 | AH87: TRUE | AI87: -1 | AJ87: N/A | AK87: 0 | AL87: FALSE | AM87: 271848.64 | AN87: TRUE | AO87: 0 | AP87: FALSE | AQ87: 149998.64 | AS87: 149998.64 | AT87: 6 | AU87: TRUE | AV87: FALSE
... A112: Y | B112: C | C112: M | D112: 20240601 | E112: 2024 | F112: 6 | G112: 202406 | H112: 818 | I112: EGY | J112: Egypt | K112: M | L112: Import | M112: 887 | N112: YEM | O112: Yemen | P112: 0 | Q112: W00 | R112: World | S112: H6 | T112: HS | U112: TRUE | V112: 391590 | W112: Plastics n.e.c. in heading no. 3915; waste, parings and scrap | X112: 6 | Y112: TRUE | Z112: C00 | AA112: TOTAL CPC | AB112: 0 | AC112: 0 | AD112: TOTAL MOT | AE112: 8 | AF112: kg | AG112: 808887.86 | AH112: TRUE | AI112: -1 | AJ112: N/A | AK112: 0 | AL112: FALSE | AM112: 808887.86 | AN112: TRUE | AO112: 0 | AP112: FALSE | AQ112: 446322.18 | AS112: 446322.18 | AT112: 6 | AU112: TRUE | AV112: FALSE
A113: Y | B113: C | C113: M | D113: 20240601 | E113: 2024 | F113: 6 | G113: 202406 | H113: 818 | I113: EGY | J113: Egypt | K113: X | L113: Export | M113: 0 | N113: W00 | O113: World | P113: 0 | Q113: W00 | R113: World | S113: H6 | T113: HS | U113: TRUE | V113: 391590 | W113: Plastics n.e.c. in heading no. 3915; waste, parings and scrap | X113: 6 | Y113: TRUE | Z113: C00 | AA113: TOTAL CPC | AB113: 0 | AC113: 0 | AD113: TOTAL MOT | AE113: -1 | AF113: N/A | AG113: 0 | AH113: FALSE | AI113: -1 | AJ113: N/A | AK113: 0 | AL113: FALSE | AN113: FALSE | AO113: 0 | AP113: FALSE | AR113: 20564.75 | AS113: 20564.75 | AT113: 0 | AU113: FALSE | AV113: TRUE
A114: Y | B114: C | C114: M | D114: 20240601 | E114: 2024 | F114: 6 | G114: 202406 | H114: 818 | I114: EGY | J114: Egypt | K114: X | L114: Export | M114: 380 | N114: ITA | O114: Italy | P114: 0 | Q114: W00 | R114: World | S114: H6 | T114: HS | U114: TRUE | V114: 391590 | W114: Plastics n.e.c. in heading no. 3915; waste, parings and scrap | X114: 6 | Y114: TRUE | Z114: C00 | AA114: TOTAL CPC | AB114: 0 | AC114: 0 | AD114: TOTAL MOT | AE114: -1 | AF114: N/A | AG114: 0 | AH114: FALSE | AI114: -1 | AJ114: N/A | AK114: 0 | AL114: FALSE | AN114: FALSE | AO114: 0 | AP114: FALSE | AR114: 20564.75 | AS114: 20564.75 | AT114: 0 | AU114: TRUE | AV114: FALSE
B115: C | C115: M | D115: 20230101 | E115: 2023 | F115: 1 | G115: 202301 | H115: 818 | I115: EGY | J115: Egypt | K115: M | L115: Import | M115: 0 | N115: W00 | O115: World | P115: 0 | Q115: W00 | R115: World | S115: H6 | T115: HS | U115: TRUE | V115: 391590 | W115: Plastics n.e.c. in heading no. 3915; waste, parings and scrap | X115: 6 | Y115: TRUE | Z115: C00 | AA115: TOTAL CPC | AB115: 0 | AC115: 0 | AD115: TOTAL MOT | AE115: 8 | AF115: kg | AG115: 4611465.3 | AH115: TRUE | AI115: -1 | AJ115: N/A | AK115: 0 | AL115: FALSE | AM115: 4611465.3 | AN115: TRUE | AO115: 0 | AP115: FALSE | AQ115: 2544480.4 | AS115: 2544480.4 | AT115: 6 | AU115: FALSE | AV115: TRUE
B116: C | C116: M | D116: 20230101 | E116: 2023 | F116: 1 | G116: 202301 | H116: 818 | I116: EGY | J116: Egypt | K116: M | L116: Import | M116: 100 | N116: BGR | O116: Bulgaria | P116: 0 | Q116: W00 | R116: World | S116: H6 | T116: HS | U116: TRUE | V116: 391590 | W116: Plastics n.e.c. in heading no. 3915; waste, parings and scrap | X116: 6 | Y116: TRUE | Z116: C00 | AA116: TOTAL CPC | AB116: 0 | AC116: 0 | AD116: TOTAL MOT | AE116: 8 | AF116: kg | AG116: 63395.925 | AH116: TRUE | AI116: -1 | AJ116: N/A | AK116: 0 | AL116: FALSE | AM116: 63395.925 | AN116: TRUE | AO116: 0 | AP116: FALSE | AQ116: 34980.137 | AS116: 34980.137 | AT116: 6 | AU116: TRUE | AV116: FALSE
B117: C | C117: M | D117: 20230101 | E117: 2023 | F117: 1 | G117: 202301 | H117: 818 | I117: EGY | J117: Egypt | K117: M | L117: Import | M117: 380 | N117: ITA | O117: Italy | P117: 0 | Q117: W00 | R117: World | S117: H6 | T117: HS | U117: TRUE | V117: 391590 | W117: Plastics n.e.c. in heading no. 3915; waste, parings and scrap | X117: 6 | Y117: TRUE | Z117: C00 | AA117: TOTAL CPC | AB117: 0 | AC117: 0 | AD117: TOTAL MOT | AE117: 8 | AF117: kg | AG117: 158985.92 | AH117: TRUE | AI117: -1 | AJ117: N/A | AK117: 0 | AL117: FALSE | AM117: 158985.92 | AN117: TRUE | AO117: 0 | AP117: FALSE | AQ117: 87724.078 | AS117: 87724.078 | AT117: 6 | AU117: TRUE | AV117: FALSE
B118: C | C118: M | D118: 20230101 | E118: 2023 | F118: 1 | G118: 202301 | H118: 818 | I118: EGY | J118: Egypt | K118: M | L118: Import | M118: 566 | N118: NGA | O118: Nigeria | P118: 0 | Q118: W00 | R118: World | S118: H6 | T118: HS | U118: TRUE | V118: 391590 | W118: Plastics n.e.c. in heading no. 3915; waste, parings and scrap | X118: 6 | Y118: TRUE | Z118: C00 | AA118: TOTAL CPC | AB118: 0 | AC118: 0 | AD118: TOTAL MOT | AE118: 8 | AF118: kg | AG118: 562531.82 | AH118: TRUE | AI118: -1 | AJ118: N/A | AK118: 0 | AL118: FALSE | AM118: 562531.82 | AN118: TRUE | AO118: 0 | AP118: FALSE | AQ118: 310389.66 | AS118: 310389.66 | AT118: 6 | AU118: TRUE | AV118: FALSE
B119: C | C119: M | D119: 20230101 | E119: 2023 | F119: 1 | G119: 202301 | H119: 818 | I119: EGY | J119: Egypt | K119: M | L119: Import | M119: 724 | N119: ESP | O119: Spain | P119: 0 | Q119: W00 | R119: World | S119: H6 | T119: HS | U119: TRUE | V119: 391590 | W119: Plastics n.e.c. in heading no. 3915; waste, parings and scrap | X119: 6 | Y119: TRUE | Z119: C00 | AA119: TOTAL CPC | AB119: 0 | AC119: 0 | AD119: TOTAL MOT | AE119: 8 | AF119: kg | AG119: 1095865.4 | AH119: TRUE | AI119: -1 | AJ119: N/A | AK119: 0 | AL119: FALSE | AM119: 1095865.4 | AN119: TRUE | AO119: 0 | AP119: FALSE | AQ119: 604668.55 | AS119: 604668.55 | AT119: 6 | AU119: TRUE | AV119: FALSE
B120: C | C120: M | D120: 20230101 | E120: 2023 | F120: 1 | G120: 202301 | H120: 818 | I120: EGY | J120: Egypt | K120: M | L120: Import | M120: 729 | N120: SDN | O120: Sudan | P120: 0 | Q120: W00 | R120: World | S120: H6 | T120: HS | U120: TRUE | V120: 391590 | W120: Plastics n.e.c. in heading no. 3915; waste, parings and scrap | X120: 6 | Y120: TRUE | Z120: C00 | AA120: TOTAL CPC | AB120: 0 | AC120: 0 | AD120: TOTAL MOT | AE120: 8 | AF120: kg | AG120: 246083.98 | AH120: TRUE | AI120: -1 | AJ120: N/A | AK120: 0 | AL120: FALSE | AM120: 246083.98 | AN120: TRUE | AO120: 0 | AP120: FALSE | AQ120: 135782.41 | AS120: 135782.41 | AT120: 6 | AU120: TRUE | AV120: FALSE
B121: C | C121: M | D121: 20230101 | E121: 2023 | F121: 1 | G121: 202301 | H121: 818 | I121: EGY | J121: Egypt | K121: M | L121: Import | M121: 784 | N121: ARE | O121: United Arab Emirates | P121: 0 | Q121: W00 | R121: World | S121: H6 | T121: HS | U121: TRUE | V121: 391590 | W121: Plastics n.e.c. in heading no. 3915; waste, parings and scrap | X121: 6 | Y121: TRUE | Z121: C00 | AA121: TOTAL CPC | AB121: 0 | AC121: 0 | AD121: TOTAL MOT | AE121: 8 | AF121: kg | AG121: 569487.34 | AH121: TRUE | AI121: -1 | AJ121: N/A | AK121: 0 | AL121: FALSE | AM121: 569487.34 | AN121: TRUE | AO121: 0 | AP121: FALSE | AQ121: 314227.53 | AS121: 314227.53 | AT121: 6 | AU121: TRUE | AV121: FALSE
B122: C | C122: M | D122: 20230101 | E122: 2023 | F122: 1 | G122: 202301 | H122: 818 | I122: EGY | J122: Egypt | K122: M | L122: Import | M122: 792 | N122: TUR | O122: Türkiye | P122: 0 | Q122: W00 | R122: World | S122: H6 | T122: HS | U122: TRUE | V122: 391590 | W122: Plastics n.e.c. in heading no. 3915; waste, parings and scrap | X122: 6 | Y122: TRUE | Z122: C00 | AA122: TOTAL CPC | AB122: 0 | AC122: 0 | AD122: TOTAL MOT | AE122: 8 | AF122: kg | AG122: 281347.2 | AH122: TRUE | AI122: -1 | AJ122: N/A | AK122: 0 | AL122: FALSE | AM122: 281347.2 | AN122: TRUE | AO122: 0 | AP122: FALSE | AQ122: 155239.69 | AS122: 155239.69 | AT122: 6 | AU122: TRUE | AV122: FALSE
B123: C | C123: M | D123: 20230101 | E123: 2023 | F123: 1 | G123: 202301 | H123: 818 | I123: EGY | J123: Egypt | K123: M | L123: Import | M123: 834 | N123: TZA | O123: United Rep. of Tanzania | P123: 0 | Q123: W00 | R123: World | S123: H6 | T123: HS | U123: TRUE | V123: 391590 | W123: Plastics n.e.c. in heading no. 3915; waste, parings and scrap | X123: 6 | Y123: TRUE | Z123: C00 | AA123: TOTAL CPC | AB123: 0 | AC123: 0 | AD123: TOTAL MOT | AE123: 8 | AF123: kg | AG123: 212849.43 | AH123: TRUE | AI123: -1 | AJ123: N/A | AK123: 0 | AL123: FALSE | AM123: 212849.43 | AN123: TRUE | AO123: 0 | AP123: FALSE | AQ123: 117444.49 | AS123: 117444.49 | AT123: 6 | AU123: TRUE | AV123: FALSE
B124: C | C124: M | D124: 20230101 | E124: 2023 | F124: 1 | G124: 202301 | H124: 818 | I124: EGY | J124: Egypt | K124: M | L124: Import | M124: 887 | N124: YEM | O124: Yemen | P124: 0 | Q124: W00 | R124: World | S124: H6 | T124: HS | U124: TRUE | V124: 391590 | W124: Plastics n.e.c. in heading no. 3915; waste, parings and scrap | X124: 6 | Y124: TRUE | Z124: C00 | AA124: TOTAL CPC | AB124: 0 | AC124: 0 | AD124: TOTAL MOT | AE124: 8 | AF124: kg | AG124: 1420918.3 | AH124: TRUE | AI124: -1 | AJ124: N/A | AK124: 0 | AL124: FALSE | AM124: 1420918.3 | AN124: TRUE | AO124: 0 | AP124: FALSE | AQ124: 784023.82 | AS124: 784023.82 | AT124: 6 | AU124: TRUE | AV124: FALSE
B125: C | C125: M | D125: 20230201 | E125: 2023 | F125: 2 | G125: 202302 | H125: 818 | I125: EGY | J125: Egypt | K125: M | L125: Import | M125: 0 | N125: W00 | O125: World | P125: 0 | Q125: W00 | R125: World | S125: H6 | T125: HS | U125: TRUE | V125: 391590 | W125: Plastics n.e.c. in heading no. 3915; waste, parings and scrap | X125: 6 | Y125: TRUE | Z125: C00 | AA125: TOTAL CPC | AB125: 0 | AC125: 0 | AD125: TOTAL MOT | AE125: 8 | AF125: kg | AG125: 2988664 | AH125: TRUE | AI125: -1 | AJ125: N/A | AK125: 0 | AL125: FALSE | AM125: 2988664 | AN125: TRUE | AO125: 0 | AP125: FALSE | AQ125: 1649063 | AS125: 1649063 | AT125: 6 | AU125: FALSE | AV125: TRUE
B126: C | C126: M | D126: 20230201 | E126: 2023 | F126: 2 | G126: 202302 | H126: 818 | I126: EGY | J126: Egypt | K126: M | L126: Import | M126: 156 | N126: CHN | O126: China | P126: 0 | Q126: W00 | R126: World | S126: H6 | T126: HS | U126: TRUE | V126: 391590 | W126: Plastics n.e.c. in heading no. 3915; waste, parings and scrap | X126: 6 | Y126: TRUE | Z126: C00 | AA126: TOTAL CPC | AB126: 0 | AC126: 0 | AD126: TOTAL MOT | AE126: 8 | AF126: kg | AG126: 196637.15 | AH126: TRUE | AI126: -1 | AJ126: N/A | AK126: 0 | AL126: FALSE | AM126: 196637.15 | AN126: TRUE | AO126: 0 | AP126: FALSE | AQ126: 108499 | AS126: 108499 | AT126: 6 | AU126: TRUE | AV126: FALSE
... B156: C | C156: M | D156: 20230601 | E156: 2023 | F156: 6 | G156: 202306 | H156: 818 | I156: EGY | J156: Egypt | K156: M | L156: Import | M156: 842 | N156: USA | O156: USA | P156: 0 | Q156: W00 | R156: World | S156: H6 | T156: HS | U156: TRUE | V156: 391590 | W156: Plastics n.e.c. in heading no. 3915; waste, parings and scrap | X156: 6 | Y156: TRUE | Z156: C00 | AA156: TOTAL CPC | AB156: 0 | AC156: 0 | AD156: TOTAL MOT | AE156: 8 | AF156: kg | AG156: 44258.59 | AH156: TRUE | AI156: -1 | AJ156: N/A | AK156: 0 | AL156: FALSE | AM156: 44258.59 | AN156: TRUE | AO156: 0 | AP156: FALSE | AQ156: 24420.679 | AS156: 24420.679 | AT156: 6 | AU156: TRUE | AV156: FALSE
A157: Y | B157: C | C157: M | D157: 20230701 | E157: 2023 | F157: 7 | G157: 202307 | H157: 818 | I157: EGY | J157: Egypt | K157: M | L157: Import | M157: 0 | N157: W00 | O157: World | P157: 0 | Q157: W00 | R157: World | S157: H6 | T157: HS | U157: TRUE | V157: 391590 | W157: Plastics n.e.c. in heading no. 3915; waste, parings and scrap | X157: 6 | Y157: TRUE | Z157: C00 | AA157: TOTAL CPC | AB157: 0 | AC157: 0 | AD157: TOTAL MOT | AE157: 8 | AF157: kg | AG157: 1798598.4 | AH157: TRUE | AI157: -1 | AJ157: N/A | AK157: 0 | AL157: FALSE | AM157: 1798598.4 | AN157: TRUE | AO157: 0 | AP157: FALSE | AQ157: 992417.39 | AS157: 992417.39 | AT157: 6 | AU157: FALSE | AV157: TRUE
A158: Y | B158: C | C158: M | D158: 20230701 | E158: 2023 | F158: 7 | G158: 202307 | H158: 818 | I158: EGY | J158: Egypt | K158: M | L158: Import | M158: 156 | N158: CHN | O158: China | P158: 0 | Q158: W00 | R158: World | S158: H6 | T158: HS | U158: TRUE | V158: 391590 | W158: Plastics n.e.c. in heading no. 3915; waste, parings and scrap | X158: 6 | Y158: TRUE | Z158: C00 | AA158: TOTAL CPC | AB158: 0 | AC158: 0 | AD158: TOTAL MOT | AE158: 8 | AF158: kg | AG158: 27166.987 | AH158: TRUE | AI158: -1 | AJ158: N/A | AK158: 0 | AL158: FALSE | AM158: 27166.987 | AN158: TRUE | AO158: 0 | AP158: FALSE | AQ158: 14990 | AS158: 14990 | AT158: 6 | AU158: TRUE | AV158: FALSE
A159: Y | B159: C | C159: M | D159: 20230701 | E159: 2023 | F159: 7 | G159: 202307 | H159: 818 | I159: EGY | J159: Egypt | K159: M | L159: Import | M159: 300 | N159: GRC | O159: Greece | P159: 0 | Q159: W00 | R159: World | S159: H6 | T159: HS | U159: TRUE | V159: 391590 | W159: Plastics n.e.c. in heading no. 3915; waste, parings and scrap | X159: 6 | Y159: TRUE | Z159: C00 | AA159: TOTAL CPC | AB159: 0 | AC159: 0 | AD159: TOTAL MOT | AE159: 8 | AF159: kg | AG159: 56074.632 | AH159: TRUE | AI159: -1 | AJ159: N/A | AK159: 0 | AL159: FALSE | AM159: 56074.632 | AN159: TRUE | AO159: 0 | AP159: FALSE | AQ159: 30940.447 | AS159: 30940.447 | AT159: 6 | AU159: TRUE | AV159: FALSE
...

Sheet EX-2.4 Phụ gia khác
A1: List of supplying markets for a product imported by Egypt | C1: ='EX-1A SV Summary'!D22 -> 32049000
A2: Product: 320490 Synthetic organic products of a kind used as luminophores, whether or not chemically defined
A3: Sources: ITC calculations based on UN COMTRADE statistics.
A5: Total quantity imported (ton) | B5: Total quantity imported (Kg) | C5: Total value imported (USD) | D5: Unit price (USD/Kg)
A6: =SUMIFS(M:M,N:N,"Include",O:O,"QTY") -> 8167 | B6: =A6*1000 -> 8167000 | C6: =SUMIFS(M:M,N:N,"Include",O:O,"Val")*1000 -> 490000 | D6: =C6/B6 -> 0.059997551
A9: Unit : US Dollar thousand
A10: Exporters | B10: Imported value in 2012 | C10: Imported value in 2013 | D10: Imported value in 2014 | E10: Imported value in 2015 | F10: Imported value in 2016 | G10: Imported value in 2017 | H10: Imported value in 2018 | I10: Imported value in 2019 | J10: Imported value in 2020 | K10: Imported value in 2021 | L10: Imported value in 2022 | M10: Imported value in 2023 | N10: Mark | O10: Note
A11: World | B11: 1194 | C11: 601 | D11: 1168 | E11: 657 | F11: 865 | G11: 617 | H11: 1214 | I11: 850 | J11: 525 | K11: 1117 | L11: 489 | M11: 604 | N11: =VLOOKUP(A11,'EX-2.3 Phụ gia 409'!$B$48:$P$72,15,0) -> Exclude
A12: India | B12: 150 | C12: 233 | D12: 391 | E12: 0 | F12: 22 | G12: 116 | H12: 22 | I12: 203 | J12: 110 | K12: 149 | L12: 40 | M12: 171 | N12: =VLOOKUP(A12,'EX-2.3 Phụ gia 409'!$B$48:$P$72,15,0) -> Include | O12: Val
A13: China | B13: 359 | C13: 94 | D13: 417 | E13: 155 | F13: 223 | G13: 28 | H13: 229 | I13: 85 | J13: 277 | K13: 384 | L13: 95 | M13: 102 | N13: =VLOOKUP(A13,'EX-2.3 Phụ gia 409'!$B$48:$P$72,15,0) -> Exclude
A14: Saudi Arabia | B14: 49 | C14: 35 | D14: 34 | E14: 0 | F14: 2 | G14: 1 | H14: 52 | I14: 0 | J14: 0 | L14: 210 | M14: 84 | N14: =VLOOKUP(A14,'EX-2.3 Phụ gia 409'!$B$48:$P$72,15,0) -> Include | O14: Val
A15: Germany | B15: 229 | C15: 40 | D15: 82 | E15: 285 | F15: 57 | G15: 69 | H15: 46 | I15: 0 | J15: 43 | K15: 3 | L15: 38 | M15: 73 | N15: =VLOOKUP(A15,'EX-2.3 Phụ gia 409'!$B$48:$P$72,15,0) -> Include | O15: Val
A16: France | B16: 9 | C16: 5 | D16: 3 | E16: 0 | F16: 0 | G16: 19 | H16: 21 | I16: 6 | J16: 0 | K16: 24 | L16: 13 | M16: 71 | N16: =VLOOKUP(A16,'EX-2.3 Phụ gia 409'!$B$48:$P$72,15,0) -> Include | O16: Val
A17: Türkiye | B17: 60 | C17: 13 | D17: 13 | E17: 59 | F17: 76 | G17: 56 | H17: 7 | I17: 6 | J17: 26 | K17: 44 | L17: 25 | M17: 32 | N17: =VLOOKUP(A17,'EX-2.3 Phụ gia 409'!$B$48:$P$72,15,0) -> Include | O17: Val
A18: Italy | B18: 26 | C18: 71 | D18: 10 | E18: 93 | F18: 76 | G18: 10 | H18: 49 | I18: 2 | J18: 1 | K18: 34 | L18: 45 | M18: 31 | N18: =VLOOKUP(A18,'EX-2.3 Phụ gia 409'!$B$48:$P$72,15,0) -> Include | O18: Val
A19: Libya, State of | B19: 0 | C19: 0 | D19: 0 | E19: 0 | F19: 0 | G19: 0 | H19: 0 | I19: 0 | J19: 0 | M19: 21 | N19: Include | O19: Val
A20: Russian Federation | B20: 0 | C20: 0 | D20: 0 | E20: 0 | F20: 0 | G20: 0 | H20: 0 | I20: 0 | J20: 0 | M20: 8 | N20: =VLOOKUP(A20,'EX-2.3 Phụ gia 409'!$B$48:$P$72,15,0) -> Exclude
A21: Sri Lanka | B21: 0 | C21: 0 | D21: 0 | E21: 0 | F21: 0 | G21: 0 | H21: 0 | I21: 0 | J21: 0 | M21: 4 | N21: Include | O21: Val
A22: Taipei, Chinese | B22: 0 | C22: 0 | D22: 64 | E22: 0 | F22: 116 | G22: 0 | H22: 0 | I22: 0 | J22: 0 | M22: 3 | N22: Exclude
A23: United States of America | B23: 138 | C23: 7 | D23: 0 | E23: 36 | F23: 0 | G23: 0 | H23: 31 | I23: 12 | J23: 22 | L23: 19 | M23: 3 | N23: Include | O23: Val
A26: List of supplying markets for a product imported by Egypt
A27: Product: 3204 Synthetic organic colouring matter, whether or not chemically defined; preparations based on ...
A28: Sources: ITC calculations based on UN COMTRADE statistics.
A30: Exporters | B30: 2012 | C30: 2013 | D30: 2014 | E30: 2015 | F30: 2016 | G30: 2017 | H30: 2018 | I30: 2019 | J30: 2020 | K30: 2021 | L30: 2022 | M30: 2023 | N30: Mark | O30: Note
B31: Imported quantity, Tons | C31: Imported quantity, Tons | D31: Imported quantity, Tons | E31: Imported quantity, Tons | F31: Imported quantity, Tons | G31: Imported quantity, Tons | H31: Imported quantity, Tons | I31: Imported quantity, Tons | J31: Imported quantity, Tons | K31: Imported quantity, Tons | L31: Imported quantity, Tons | M31: Imported quantity, Tons
A32: World | B32: No Quantity | C32: 26678 | D32: 28978 | E32: No Quantity | F32: No Quantity | G32: No Quantity | H32: No Quantity | I32: No Quantity | J32: No Quantity | K32: 13639 | L32: No Quantity | M32: No Quantity
A33: India | B33: No Quantity | C33: 5348 | D33: 7911 | E33: 3621 | F33: 3365 | G33: 3289 | H33: 3830 | I33: 3889 | J33: 3447 | K33: 4006 | L33: 3820 | M33: 3805 | N33: =VLOOKUP(A33,$A$11:$N$23,14,0) -> Include | O33: Qty
A34: China | B34: No Quantity | C34: 6708 | D34: 6137 | E34: 3624 | F34: 3149 | G34: 3769 | H34: 3458 | I34: 3492 | J34: 3283 | K34: 3938 | L34: 3402 | M34: 3364 | N34: =VLOOKUP(A34,$A$11:$N$23,14,0) -> Exclude | O34: Qty
A35: Korea, Republic of | B35: No Quantity | C35: 1952 | D35: 2095 | E35: 1644 | F35: 1678 | G35: 2033 | H35: 1973 | I35: 2071 | J35: 1727 | K35: 1947 | L35: 1543 | M35: 1342 | N35: Include | O35: Qty
A36: Türkiye | B36: No Quantity | C36: 2111 | D36: 1773 | E36: 1082 | F36: 1108 | G36: 1027 | H36: 1202 | I36: 1020 | J36: 1022 | K36: 984 | L36: 953 | M36: 878 | N36: =VLOOKUP(A36,$A$11:$N$23,14,0) -> Include | O36: Qty
A37: Switzerland | B37: No Quantity | C37: 431 | D37: 343 | E37: 526 | F37: 602 | G37: 209 | H37: 459 | I37: 151 | J37: 165 | K37: 188 | L37: 203 | M37: 427 | N37: Include | O37: Qty
A38: Germany | B38: No Quantity | C38: 2493 | D38: 1950 | E38: 982 | F38: 1026 | G38: 933 | H38: 747 | I38: 607 | J38: 472 | K38: 491 | L38: 454 | M38: 269 | N38: =VLOOKUP(A38,$A$11:$N$23,14,0) -> Include | O38: Qty
A39: Spain | B39: No Quantity | C39: 454 | D39: 482 | E39: 191 | F39: 249 | G39: 304 | H39: 295 | I39: 319 | J39: 232 | K39: 513 | L39: 269 | M39: 153 | N39: Include | O39: Qty
A40: Italy | B40: No Quantity | C40: 1213 | D40: 1278 | E40: 575 | F40: 387 | G40: 452 | H40: 335 | I40: 319 | J40: 225 | K40: 208 | L40: 184 | M40: 133 | N40: =VLOOKUP(A40,$A$11:$N$23,14,0) -> Include | O40: Qty
A41: United States of America | B41: No Quantity | C41: 702 | D41: 1900 | E41: 145 | F41: 91 | G41: 81 | H41: 99 | I41: 90 | J41: 172 | K41: 178 | L41: 185 | M41: 119 | N41: =VLOOKUP(A41,$A$11:$N$23,14,0) -> Include | O41: Qty
A42: Singapore | B42: No Quantity | C42: 258 | D42: 593 | E42: 130 | F42: 97 | G42: 72 | H42: 100 | I42: 125 | J42: 61 | K42: 74 | L42: 76 | M42: 114 | N42: Include | O42: Qty
A43: Israel | B43: No Quantity | C43: 177 | D43: 86 | E43: 7 | F43: 34 | G43: 10 | H43: 112 | I43: 50 | J43: 82 | K43: 22 | L43: 26 | M43: 113 | N43: Include | O43: Qty
A44: Canada | B44: 74 | C44: 130 | D44: 144 | E44: 48 | F44: 105 | G44: 38 | H44: 111 | I44: 120 | J44: 106 | K44: 108 | L44: 170 | M44: 100 | N44: Include | O44: Qty
A45: Thailand | B45: 65 | C45: 82 | D45: 312 | E45: 92 | F45: 79 | G45: 53 | H45: 48 | I45: 40 | J45: 24 | K45: 24 | L45: 21 | M45: 100 | N45: Include | O45: Qty
A46: United Arab Emirates | B46: No Quantity | C46: 678 | D46: 91 | E46: 64 | F46: 63 | G46: 97 | H46: 85 | I46: 117 | J46: 92 | K46: 92 | L46: 133 | M46: 93 | N46: Include | O46: Qty
A47: Belgium | B47: No Quantity | C47: 552 | D47: 323 | E47: 202 | F47: 71 | G47: 93 | H47: 75 | I47: 80 | J47: 82 | K47: 68 | L47: 26 | M47: 85 | N47: Include | O47: Qty
A48: Netherlands | B48: No Quantity | C48: 845 | D48: 1275 | E48: 420 | F48: 419 | G48: 286 | H48: 341 | I48: 330 | J48: 231 | K48: 276 | L48: 132 | M48: 66 | N48: Include | O48: Qty
A49: Indonesia | B49: 61 | C49: 139 | D49: 100 | E49: 226 | F49: 164 | G49: 135 | H49: 137 | I49: 123 | J49: 31 | K49: 116 | L49: 84 | M49: 60 | N49: Include | O49: Qty
A50: Greece | B50: No Quantity | C50: 443 | D50: 512 | E50: 68 | F50: 32 | G50: 82 | H50: 60 | I50: 29 | J50: 24 | K50: 24 | L50: 64 | M50: 56 | N50: Include | O50: Qty
A51: United Kingdom | B51: No Quantity | C51: 207 | D51: 75 | E51: 79 | F51: 133 | G51: 60 | H51: 240 | I51: 95 | J51: 109 | K51: 30 | L51: 51 | M51: 48 | N51: Include | O51: Qty
A52: Hungary | C52: 0 | D52: 1 | E52: 1 | F52: 1 | H52: 2 | I52: 10 | J52: 3 | K52: 8 | L52: 17 | M52: 34 | N52: Include | O52: Qty
A53: France | B53: No Quantity | C53: 92 | D53: 17 | E53: 23 | F53: 43 | G53: 57 | H53: 31 | I53: 38 | J53: 36 | K53: 41 | L53: 21 | M53: 31 | N53: =VLOOKUP(A53,$A$11:$N$23,14,0) -> Include | O53: Qty
A54: Taipei, Chinese | B54: No Quantity | C54: 206 | D54: 134 | E54: 99 | F54: 117 | G54: 59 | H54: 58 | I54: 34 | J54: 20 | K54: 32 | L54: 40 | M54: 31 | N54: =VLOOKUP(A54,$A$11:$N$23,14,0) -> Exclude | O54: Qty
A55: Japan | B55: 132 | C55: 101 | D55: 78 | E55: 165 | F55: 145 | G55: 57 | H55: 21 | I55: 30 | J55: 14 | K55: 7 | L55: 40 | M55: 30 | N55: Include | O55: Qty
A56: Austria | B56: 9 | C56: 1 | D56: 1 | E56: 5 | F56: 5 | G56: 3 | H56: 0 | I56: 0 | J56: 17 | K56: 12 | L56: 32 | M56: 28 | N56: Include | O56: Qty
A57: Norway | B57: 94 | C57: 62 | D57: 180 | E57: 98 | F57: 133 | G57: 155 | H57: 78 | I57: 82 | J57: 39 | K57: 44 | L57: 39 | M57: 25 | N57: Include | O57: Qty
A58: Pakistan | B58: 62 | C58: 847 | F58: 0 | H58: 44 | I58: 3 | L58: 18 | M58: 14 | N58: Include | O58: Qty
A59: Portugal | D59: 5 | E59: 6 | H59: 3 | I59: 83 | J59: 1 | K59: 4 | L59: 9 | M59: 13 | N59: Include | O59: Qty
A60: Saudi Arabia | B60: No Quantity | C60: 246 | D60: 36 | E60: 37 | F60: 22 | G60: 26 | H60: 20 | I60: 20 | J60: 121 | K60: 129 | L60: 163 | M60: 12 | N60: =VLOOKUP(A60,$A$11:$N$23,14,0) -> Include | O60: Qty
A61: Luxembourg | I61: 1 | J61: 1 | K61: 0 | L61: 4 | M61: 5 | N61: Include | O61: Qty
A62: Czech Republic | B62: 8 | C62: 10 | D62: 13 | E62: 14 | F62: 16 | G62: 3 | H62: 5 | I62: 6 | J62: 3 | K62: 4 | L62: 5 | M62: 4 | N62: Include | O62: Qty
A63: Finland | E63: 12 | F63: 30 | G63: 7 | H63: 21 | I63: 18 | J63: 50 | K63: 6 | L63: 32 | M63: 4 | N63: Include | O63: Qty
A64: Brazil | B64: 5 | C64: 8 | D64: 0 | G64: 5 | I64: 1 | M64: 2 | N64: Include | O64: Qty
A65: Mexico | B65: 14 | C65: 90 | D65: 2 | F65: 32 | G65: 15 | H65: 39 | I65: 12 | J65: 6 | K65: 15 | L65: 11 | M65: 2 | N65: Include | O65: Qty
A66: Denmark | B66: No Quantity | C66: 0 | D66: 0 | E66: No Quantity | F66: No Quantity | G66: 11 | H66: No Quantity | I66: 4 | J66: 12 | K66: 25 | L66: No Quantity | M66: 1 | N66: Include | O66: Qty
A67: Hong Kong, China | B67: No Quantity | C67: 14 | D67: 18 | E67: 10 | F67: 94 | G67: 222 | H67: 20 | I67: 2 | J67: 20 | L67: 0 | M67: 1 | N67: Exclude | O67: Qty
A68: Malaysia | D68: 11 | G68: 5 | H68: 2 | I68: 1 | J68: 5 | L68: 5 | M68: 1 | N68: Include | O68: Qty
A69: Russian Federation | M69: 1 | N69: =VLOOKUP(A69,$A$11:$N$23,14,0) -> Exclude | O69: Qty
A70: Viet Nam | B70: No Quantity | E70: No Quantity | F70: No Quantity | G70: No Quantity | H70: 5 | I70: No Quantity | J70: 16 | K70: 6 | L70: No Quantity | M70: 1 | N70: Exclude | O70: Qty

Sheet EX-2.5 Phụ gia RHC
A1: List of supplying markets for a product imported by Egypt | D1: ='EX-1A SV Summary'!D25 -> 3206199
A2: Product: 320619 Pigments and preparations based on titanium dioxide of a kind used for colouring any material ...
A4: Sources: ITC calculations based on UN COMTRADE statistics.
A6: Total quantity imported (ton) | B6: Total quantity imported (Kg) | C6: Total value imported (USD) | D6: Unit price (USD/Kg)
A7: =SUMIFS(M:M,N:N,"Include",O:O,"QTY") -> 1342 | B7: =A7*1000 -> 1342000 | C7: =SUMIFS(M:M,N:N,"Include",O:O,"Val")*1000 -> 6474000 | D7: =C7/B7 -> 4.8241431
A9: Unit : US Dollar thousand
A11: Exporters | B11: Imported value in 2012 | C11: Imported value in 2013 | D11: Imported value in 2014 | E11: Imported value in 2015 | F11: Imported value in 2016 | G11: Imported value in 2017 | H11: Imported value in 2018 | I11: Imported value in 2019 | J11: Imported value in 2020 | K11: Imported value in 2021 | L11: Imported value in 2022 | M11: Imported value in 2023 | N11: Mark | O11: Note
A12: World | B12: 7953 | C12: 5408 | D12: 7334 | E12: 7384 | F12: 10890 | G12: 7149 | H12: 7321 | I12: 7705 | J12: 9027 | K12: 14361 | L12: 9056 | M12: 9214 | N12: Exclude | O12: Val
A13: China | B13: 229 | C13: 52 | D13: 299 | E13: 491 | F13: 2306 | G13: 555 | H13: 770 | I13: 1060 | J13: 2033 | K13: 3104 | L13: 1711 | M13: 2620 | N13: Exclude | O13: Val
A14: United States of America | B14: 476 | C14: 297 | D14: 906 | E14: 1164 | F14: 4453 | G14: 915 | H14: 1405 | I14: 995 | J14: 373 | K14: 1349 | L14: 781 | M14: 1130 | N14: Include | O14: Val
A15: United Kingdom | B15: 230 | C15: 255 | D15: 393 | E15: 189 | F15: 255 | G15: 324 | H15: 387 | I15: 384 | J15: 443 | K15: 550 | L15: 485 | M15: 1052 | N15: Include | O15: Val
A16: Germany | B16: 1159 | C16: 1713 | D16: 1366 | E16: 1888 | F16: 1516 | G16: 1477 | H16: 1591 | I16: 1385 | J16: 985 | K16: 1268 | L16: 804 | M16: 980 | N16: Include | O16: Val
A17: Japan | B17: 200 | C17: 616 | D17: 311 | E17: 585 | F17: 322 | G17: 516 | H17: 606 | I17: 504 | J17: 727 | K17: 806 | L17: 650 | M17: 809 | N17: Include | O17: Val
A18: Belgium | B18: 548 | C18: 319 | D18: 397 | E18: 84 | F18: 336 | G18: 558 | H18: 172 | I18: 587 | J18: 2048 | K18: 969 | L18: 1763 | M18: 430 | N18: Include | O18: Val
A19: Türkiye | B19: 9 | C19: 38 | D19: 4 | E19: 70 | F19: 0 | G19: 198 | H19: 0 | I19: 124 | J19: 363 | K19: 130 | L19: 117 | M19: 365 | N19: Include | O19: Val
A20: India | B20: 401 | C20: 214 | D20: 389 | E20: 386 | F20: 551 | G20: 869 | H20: 599 | I20: 970 | J20: 713 | K20: 489 | L20: 431 | M20: 353 | N20: Include | O20: Val
A21: Thailand | B21: 130 | C21: 1 | D21: 0 | E21: 123 | F21: 9 | G21: 0 | H21: 0 | I21: 7 | J21: 0 | K21: 15 | L21: 37 | M21: 337 | N21: Include | O21: Val
A22: Saudi Arabia | B22: 902 | C22: 67 | D22: 1435 | E22: 124 | F22: 44 | G22: 167 | H22: 46 | I22: 1 | J22: 385 | K22: 4487 | L22: 650 | M22: 197 | N22: Include | O22: Val
A23: Czech Republic | B23: 0 | C23: 6 | D23: 0 | E23: 0 | F23: 0 | G23: 0 | H23: 36 | I23: 171 | J23: 144 | K23: 84 | L23: 64 | M23: 189 | N23: Include | O23: Val
... A28: Hungary | B28: 0 | C28: 0 | D28: 0 | E28: 0 | F28: 0 | G28: 2 | H28: 55 | I28: 0 | J28: 77 | K28: 33 | L28: 57 | M28: 57 | N28: Include | O28: Val
A29: United Arab Emirates | B29: 65 | C29: 7 | D29: 0 | E29: 3 | F29: 2 | G29: 46 | H29: 118 | I29: 71 | J29: 2 | K29: 111 | M29: 33 | N29: Include | O29: Val
A30: Austria | B30: 11 | C30: 0 | D30: 0 | E30: 0 | F30: 0 | G30: 62 | H30: 1 | I30: 105 | J30: 90 | K30: 92 | M30: 32 | N30: Include | O30: Val
A31: Netherlands | B31: 0 | C31: 0 | D31: 123 | E31: 77 | F31: 56 | G31: 122 | H31: 31 | I31: 20 | J31: 0 | K31: 223 | L31: 2 | M31: 25 | N31: Include | O31: Val
A32: Korea, Republic of | B32: 1548 | C32: 54 | D32: 45 | E32: 228 | F32: 0 | G32: 163 | H32: 177 | I32: 81 | J32: 149 | K32: 60 | L32: 196 | M32: 12 | N32: Include | O32: Val
A33: France | B33: 37 | C33: 8 | D33: 11 | E33: 97 | F33: 58 | G33: 11 | H33: 49 | I33: 15 | J33: 9 | K33: 40 | L33: 4 | M33: 9 | N33: Include | O33: Val
A34: Finland | B34: 427 | C34: 198 | D34: 203 | E34: 109 | F34: 0 | G34: 0 | H34: 0 | I34: 0 | J34: 10 | K34: 1 | M34: 5 | N34: Include | O34: Val
A35: Russian Federation | B35: 0 | C35: 0 | D35: 0 | E35: 0 | F35: 0 | G35: 0 | H35: 0 | I35: 0 | J35: 0 | M35: 5 | N35: Exclude | O35: Val
A36: Europe Othr. Nes | B36: 0 | C36: 0 | D36: 0 | E36: 0 | F36: 0 | G36: 0 | H36: 0 | I36: 87 | J36: 36 | K36: 53 | L36: 21 | M36: 3 | N36: Include | O36: Val
A39: List of supplying markets for a product imported by Egypt
A40: Product: 320619 Pigments and preparations based on titanium dioxide of a kind used for colouring any material ...
A41: Sources: ITC calculations based on UN COMTRADE statistics.
A42: The quantities shown in light green are estimated by UNSD. For further information, please refer to the UNSD explanatory note.
A45: Exporters | B45: 2012 | C45: 2013 | D45: 2014 | E45: 2015 | F45: 2016 | G45: 2017 | H45: 2018 | I45: 2019 | J45: 2020 | K45: 2021 | L45: 2022 | M45: 2023
B46: Imported quantity, Tons | C46: Imported quantity, Tons | D46: Imported quantity, Tons | E46: Imported quantity, Tons | F46: Imported quantity, Tons | G46: Imported quantity, Tons | H46: Imported quantity, Tons | I46: Imported quantity, Tons | J46: Imported quantity, Tons | K46: Imported quantity, Tons | L46: Imported quantity, Tons | M46: Imported quantity, Tons | N46: Mark | O46: Note
A47: World | B47: 1968 | C47: 1393 | D47: 2654 | E47: 2288 | F47: 3207 | G47: 2178 | H47: 1978 | I47: 2180 | J47: 2305 | K47: 3577 | L47: 1904 | M47: 1909 | N47: =VLOOKUP(A47,$A$12:$N$36,14,0) -> Exclude | O47: Qty
A48: China | B48: 57 | C48: 262 | D48: 123 | E48: 152 | F48: 679 | G48: 169 | H48: 208 | I48: 300 | J48: 519 | K48: 773 | L48: 360 | M48: 543 | N48: =VLOOKUP(A48,$A$12:$N$36,14,0) -> Exclude | O48: Qty
A49: United States of America | B49: 118 | C49: 45 | D49: 99 | E49: 361 | F49: 1312 | G49: 279 | H49: 380 | I49: 281 | J49: 95 | K49: 336 | L49: 164 | M49: 234 | N49: =VLOOKUP(A49,$A$12:$N$36,14,0) -> Include | O49: Qty
A50: United Kingdom | B50: 57 | C50: 4 | D50: 5 | E50: 59 | F50: 75 | G50: 99 | H50: 105 | I50: 109 | J50: 113 | K50: 137 | L50: 102 | M50: 218 | N50: =VLOOKUP(A50,$A$12:$N$36,14,0) -> Include | O50: Qty
A51: Germany | B51: 287 | C51: 152 | D51: 118 | E51: 585 | F51: 447 | G51: 450 | H51: 430 | I51: 392 | J51: 252 | K51: 316 | L51: 169 | M51: 203 | N51: =VLOOKUP(A51,$A$12:$N$36,14,0) -> Include | O51: Qty
A52: Japan | B52: 50 | C52: 7 | D52: 4 | E52: 181 | F52: 95 | G52: 157 | H52: 164 | I52: 143 | J52: 186 | K52: 201 | L52: 137 | M52: 168 | N52: =VLOOKUP(A52,$A$12:$N$36,14,0) -> Include | O52: Qty
A53: Belgium | B53: 136 | C53: 96 | D53: 113 | E53: 26 | F53: 99 | G53: 170 | H53: 47 | I53: 166 | J53: 523 | K53: 241 | L53: 371 | M53: 89 | N53: =VLOOKUP(A53,$A$12:$N$36,14,0) -> Include | O53: Qty
A54: Türkiye | B54: 2 | C54: 0 | D54: 1 | E54: 22 | G54: 60 | I54: 35 | J54: 93 | K54: 32 | L54: 25 | M54: 76 | N54: =VLOOKUP(A54,$A$12:$N$36,14,0) -> Include | O54: Qty
A55: India | B55: 99 | C55: 49 | D55: 94 | E55: 120 | F55: 162 | G55: 265 | H55: 162 | I55: 275 | J55: 182 | K55: 122 | L55: 91 | M55: 73 | N55: =VLOOKUP(A55,$A$12:$N$36,14,0) -> Include | O55: Qty
A56: Thailand | B56: 32 | C56: 0 | E56: 38 | F56: 3 | I56: 2 | K56: 4 | L56: 8 | M56: 70 | N56: =VLOOKUP(A56,$A$12:$N$36,14,0) -> Include | O56: Qty
A57: Saudi Arabia | B57: 223 | C57: 40 | D57: 1412 | E57: 39 | F57: 13 | G57: 51 | H57: 12 | I57: 0 | J57: 98 | K57: 1118 | L57: 137 | M57: 41 | N57: =VLOOKUP(A57,$A$12:$N$36,14,0) -> Include | O57: Qty
A58: Czech Republic | C58: 2 | H58: 10 | I58: 48 | J58: 37 | K58: 21 | L58: 14 | M58: 39 | N58: =VLOOKUP(A58,$A$12:$N$36,14,0) -> Include | O58: Qty
A59: Luxembourg | E59: 5 | F59: 16 | G59: 23 | H59: 41 | I59: 62 | J59: 51 | K59: 55 | L59: 81 | M59: 35 | N59: =VLOOKUP(A59,$A$12:$N$36,14,0) -> Include | O59: Qty
A60: Italy | B60: 163 | C60: 423 | D60: 370 | E60: 129 | F60: 196 | G60: 147 | H60: 199 | I60: 180 | J60: 30 | K60: 25 | L60: 88 | M60: 34 | N60: =VLOOKUP(A60,$A$12:$N$36,14,0) -> Include | O60: Qty
A61: Spain | B61: 54 | C61: 143 | D61: 24 | E61: 226 | F61: 71 | G61: 139 | H61: 87 | I61: 32 | J61: 13 | K61: 40 | L61: 14 | M61: 25 | N61: =VLOOKUP(A61,$A$12:$N$36,14,0) -> Include | O61: Qty
A62: Viet Nam | B62: 7 | C62: 22 | D62: 71 | H62: 10 | J62: 2 | K62: 0 | L62: 73 | M62: 23 | N62: =VLOOKUP(A62,$A$12:$N$36,14,0) -> Exclude | O62: Qty
A63: Hungary | G63: 0 | H63: 15 | J63: 20 | K63: 8 | L63: 12 | M63: 12 | N63: =VLOOKUP(A63,$A$12:$N$36,14,0) -> Include | O63: Qty
A64: Austria | B64: 3 | G64: 19 | H64: 0 | I64: 30 | J64: 23 | K64: 23 | M64: 7 | N64: =VLOOKUP(A64,$A$12:$N$36,14,0) -> Include | O64: Qty
A65: United Arab Emirates | B65: 16 | C65: 15 | E65: 1 | F65: 1 | G65: 14 | H65: 32 | I65: 20 | J65: 0 | K65: 28 | M65: 7 | N65: =VLOOKUP(A65,$A$12:$N$36,14,0) -> Include | O65: Qty
A66: Netherlands | D66: 28 | E66: 24 | F66: 17 | G66: 37 | H66: 8 | I66: 6 | K66: 56 | L66: 0 | M66: 5 | N66: =VLOOKUP(A66,$A$12:$N$36,14,0) -> Include | O66: Qty
A67: Korea, Republic of | B67: 383 | C67: 7 | D67: 2 | E67: 71 | G67: 50 | H67: 48 | I67: 23 | J67: 38 | K67: 15 | L67: 41 | M67: 2 | N67: =VLOOKUP(A67,$A$12:$N$36,14,0) -> Include | O67: Qty
A68: France | B68: 9 | C68: 0 | D68: 0 | E68: 30 | F68: 17 | G68: 3 | H68: 13 | I68: 4 | J68: 2 | K68: 10 | L68: 1 | M68: 2 | N68: =VLOOKUP(A68,$A$12:$N$36,14,0) -> Include | O68: Qty
A69: Europe Othr. Nes | I69: 25 | J69: 9 | K69: 13 | L69: 4 | M69: 1 | N69: =VLOOKUP(A69,$A$12:$N$36,14,0) -> Include | O69: Qty
A70: Finland | B70: 106 | C70: 48 | D70: 62 | E70: 34 | J70: 3 | K70: 0 | M70: 1 | N70: =VLOOKUP(A70,$A$12:$N$36,14,0) -> Include | O70: Qty
A71: Russian Federation | M71: 1 | N71: =VLOOKUP(A71,$A$12:$N$36,14,0) -> Exclude | O71: Qty

Sheet EX-2.3 Phụ gia 409
B1: List of supplying markets for a product imported by Egypt | E1: ='EX-1A SV Summary'!D21 -> 32061990
B2: Colouring matter; pigments and preparations based on titanium dioxide, containing less than 80% by weight of titanium dioxide calculated on the dry weight
B3: Link: | C3: UN Comtrade
B5: EXCLUDE | C5: World | E5: Total quantity imported (Kg) | F5: Total value imported (USD) | G5: Unit price (USD/Kg)
C6: China | E6: =SUMIFS(O:O,P:P,"Include",Q:Q,"QTY")*1000 -> 2.4325441e+09 | F6: =SUMIFS(O:O,P:P,"Include",Q:Q,"VAL")*1000 -> 11741539097 | G6: =F6/E6 -> 4.8268556
C7: Hong Kong, China | S7: PERIOD OF INVESTIGATION | T7: Y
C8: Taipei, Chinese | S8: flowDesc | T8: Import
C9: Russian Federation | S9: reporterDesc | T9: Egypt
A11: 1/ | B11: Quantity | S11: Sum of qty | T11: refYear | U11: refMonth
B12: Unit : ton | T12: 2023 | Z12: 2024 | AF12: Grand Total
C13: 2023 | I13: 2024 | O13: Grand Total | P13: Mark | Q13: Note | S13: partnerDesc | T13: 7 | U13: 8 | V13: 9 | W13: 10 | X13: 11 | Y13: 12 | Z13: 1 | AA13: 2 | AB13: 3 | AC13: 4 | AD13: 5 | AE13: 6
B14: partnerDesc | C14: 7 | D14: 8 | E14: 9 | F14: 10 | G14: 11 | H14: 12 | I14: 1 | J14: 2 | K14: 3 | L14: 4 | M14: 5 | N14: 6 | S14: World | T14: 148866.28 | U14: 242976.81 | V14: 238958.9 | W14: 276015.95 | X14: 389125.88 | Y14: 176364.65 | Z14: 145004.06 | AA14: 383893.41 | AB14: 339286.27 | AC14: 582857.27 | AD14: 571229.13 | AE14: 235877.33 | AF14: 3730455.9
B15: World | C15: 148866.28 | D15: 242976.81 | E15: 238958.9 | F15: 276015.95 | G15: 389125.88 | H15: 176364.65 | I15: 145004.06 | J15: 383893.41 | K15: 339286.27 | L15: 582857.27 | M15: 571229.13 | N15: 235877.33 | O15: 3730455.9 | P15: Exclude | S15: China | T15: 60470.218 | U15: 125472.41 | V15: 66745.386 | W15: 57675.06 | X15: 176328.81 | Y15: 46240.692 | Z15: 47957.552 | AA15: 47730.748 | AB15: 41008.07 | AC15: 419113.31 | AD15: 157742.39 | AE15: 49390.144 | AF15: 1295874.8
B16: China | C16: 60470.218 | D16: 125472.41 | E16: 66745.386 | F16: 57675.06 | G16: 176328.81 | H16: 46240.692 | I16: 47957.552 | J16: 47730.748 | K16: 41008.07 | L16: 419113.31 | M16: 157742.39 | N16: 49390.144 | O16: 1295874.8 | P16: Exclude | S16: Germany | T16: 13200.08 | U16: 2135.758 | V16: 32506.109 | W16: 3707.208 | X16: 61757.49 | Y16: 27002.7 | Z16: 45862.148 | AA16: 79480.842 | AB16: 29009.604 | AC16: 9550.926 | AD16: 103624.75 | AE16: 28532.074 | AF16: 436369.68
B17: Germany | C17: 13200.08 | D17: 2135.758 | E17: 32506.109 | F17: 3707.208 | G17: 61757.49 | H17: 27002.7 | I17: 45862.148 | J17: 79480.842 | K17: 29009.604 | L17: 9550.926 | M17: 103624.75 | N17: 28532.074 | O17: 436369.68 | P17: Include | Q17: Qty | S17: USA | T17: 42124.325 | U17: 29378.366 | V17: 28004.146 | W17: 53459.684 | Y17: 85960.438 | Z17: 1271.476 | AB17: 5284.27 | AD17: 51956.838 | AE17: 26095.546 | AF17: 323535.09
B18: USA | C18: 42124.325 | D18: 29378.366 | E18: 28004.146 | F18: 53459.684 | H18: 85960.438 | I18: 1271.476 | K18: 5284.27 | M18: 51956.838 | N18: 26095.546 | O18: 323535.09 | P18: Include | Q18: Qty | S18: Japan | V18: 33910.738 | X18: 77811.212 | Y18: 7113.236 | AA18: 87226.286 | AD18: 79534.038 | AF18: 285595.51
B19: Japan | E19: 33910.738 | G19: 77811.212 | H19: 7113.236 | J19: 87226.286 | M19: 79534.038 | O19: 285595.51 | P19: Include | Q19: Qty | S19: Belgium | U19: 1926.285 | V19: 17235.185 | X19: 22384.854 | AB19: 99455.756 | AC19: 114921.42 | AF19: 255923.5
B20: Belgium | D20: 1926.285 | E20: 17235.185 | G20: 22384.854 | K20: 99455.756 | L20: 114921.42 | O20: 255923.5 | P20: Include | Q20: Qty | S20: United Kingdom | T20: 6019.192 | U20: 55105.968 | V20: 1313.642 | W20: 53436.052 | X20: 15195.334 | Y20: 5034.85 | AA20: 486.402 | AB20: 24735.348 | AC20: 5690.784 | AD20: 12520.452 | AE20: 72014.316 | AF20: 251552.34
B21: United Kingdom | C21: 6019.192 | D21: 55105.968 | E21: 1313.642 | F21: 53436.052 | G21: 15195.334 | H21: 5034.85 | J21: 486.402 | K21: 24735.348 | L21: 5690.784 | M21: 12520.452 | N21: 72014.316 | O21: 251552.34 | P21: Include | Q21: Qty | S21: Thailand | W21: 58125.166 | AA21: 66191.186 | AB21: 91376.77 | AD21: 30292.936 | AF21: 245986.06
B22: Thailand | F22: 58125.166 | J22: 66191.186 | K22: 91376.77 | M22: 30292.936 | O22: 245986.06 | P22: Include | Q22: Qty | S22: India | T22: 575.973 | U22: 11221.22 | V22: 1.338 | W22: 13691.918 | X22: 15057.242 | Z22: 3923.958 | AA22: 4338.464 | AB22: 11609.612 | AC22: 4353.38 | AD22: 74568.372 | AE22: 16461.314 | AF22: 155802.79
B23: India | C23: 575.973 | D23: 11221.22 | E23: 1.338 | F23: 13691.918 | G23: 15057.242 | I23: 3923.958 | J23: 4338.464 | K23: 11609.612 | L23: 4353.38 | M23: 74568.372 | N23: 16461.314 | O23: 155802.79 | P23: Include | Q23: Qty | S23: Czechia | V23: 19509.246 | Z23: 34473.782 | AD23: 33064.926 | AF23: 87047.954
B24: Czechia | E24: 19509.246 | I24: 34473.782 | M24: 33064.926 | O24: 87047.954 | P24: Include | Q24: Qty | S24: Türkiye | U24: 216.972 | V24: 2496.073 | X24: 15874.204 | Z24: 9553.028 | AA24: 23407.948 | AB24: 9430.106 | AC24: 269.078 | AD24: 4863.18 | AE24: 12482.926 | AF24: 78593.515
B25: Türkiye | D25: 216.972 | E25: 2496.073 | G25: 15874.204 | I25: 9553.028 | J25: 23407.948 | K25: 9430.106 | L25: 269.078 | M25: 4863.18 | N25: 12482.926 | O25: 78593.515 | P25: Include | Q25: Qty | S25: Luxembourg | V25: 19444.268 | W25: 31494.352 | AD25: 12550.618 | AE25: 14418.536 | AF25: 77907.774
B26: Luxembourg | E26: 19444.268 | F26: 31494.352 | M26: 12550.618 | N26: 14418.536 | O26: 77907.774 | P26: Include | Q26: Qty | S26: Italy | T26: 1581.476 | U26: 1660.659 | V26: 993.905 | W26: 782.87 | X26: 2406.442 | Y26: 5006.036 | Z26: 1962.11 | AA26: 8544.052 | AB26: 13952.204 | AC26: 17175.986 | AD26: 2597.83 | AE26: 16482.474 | AF26: 73146.044
B27: Italy | C27: 1581.476 | D27: 1660.659 | E27: 993.905 | F27: 782.87 | G27: 2406.442 | H27: 5006.036 | I27: 1962.11 | J27: 8544.052 | K27: 13952.204 | L27: 17175.986 | M27: 2597.83 | N27: 16482.474 | O27: 73146.044 | P27: Include | Q27: Qty | S27: Saudi Arabia | U27: 15859.173 | V27: 916.086 | AA27: 36327.14 | AD27: 6859.254 | AF27: 59961.653
B28: Saudi Arabia | D28: 15859.173 | E28: 916.086 | J28: 36327.14 | M28: 6859.254 | O28: 59961.653 | P28: Include | Q28: Qty | S28: United Arab Emirates | V28: 312.191 | AA28: 26503.596 | AF28: 26815.787
B29: United Arab Emirates | E29: 312.191 | J29: 26503.596 | O29: 26815.787 | P29: Include | Q29: Qty | S29: Spain | T29: 23806.866 | AF29: 23806.866
B30: Spain | C30: 23806.866 | O30: 23806.866 | P30: Include | Q30: Qty | S30: Greece | AB30: 9896.568 | AC30: 6548.852 | AF30: 16445.42
B31: Greece | K31: 9896.568 | L31: 6548.852 | O31: 16445.42 | P31: Include | Q31: Qty | S31: Viet Nam | V31: 15570.589 | AF31: 15570.589
B32: Viet Nam | E32: 15570.589 | O32: 15570.589 | P32: Include | Q32: Qty | S32: Austria | W32: 2438.098 | X32: 273.256 | AB32: 3527.962 | AC32: 5233.538 | AF32: 11472.854
B33: Austria | F33: 2438.098 | G33: 273.256 | K33: 3527.962 | L33: 5233.538 | O33: 11472.854 | P33: Include | Q33: Qty | S33: France | AA33: 3640.436 | AF33: 3640.436
B34: France | J34: 3640.436 | O34: 3640.436 | P34: Include | Q34: Qty | S34: Rep. of Korea | T34: 1088.15 | W34: 1205.546 | AF34: 2293.696
B35: Rep. of Korea | C35: 1088.15 | F35: 1205.546 | O35: 2293.696 | P35: Include | Q35: Qty | S35: Russian Federation | X35: 2037.038 | AF35: 2037.038
B36: Russian Federation | G36: 2037.038 | O36: 2037.038 | P36: Exclude | S36: Australia | AD36: 1053.552 | AF36: 1053.552
B37: Australia | M37: 1053.552 | O37: 1053.552 | P37: Include | Q37: Qty | S37: Netherlands | AA37: 16.308 | AF37: 16.308
B38: Netherlands | J38: 16.308 | O38: 16.308 | P38: Include | Q38: Qty | S38: Other Asia, nes | Y38: 6.692 | AF38: 6.692
B39: Other Asia, nes | H39: 6.692 | O39: 6.692 | P39: Include | Q39: Qty | S39: Grand Total | T39: 297732.56 | U39: 485953.62 | V39: 477917.81 | W39: 552031.91 | X39: 778251.77 | Y39: 352729.29 | Z39: 290008.11 | AA39: 767786.82 | AB39: 678572.54 | AC39: 1165714.5 | AD39: 1142458.3 | AE39: 471754.66 | AF39: 7460911.9
B40: Grand Total | C40: 297732.56 | D40: 485953.62 | E40: 477917.81 | F40: 552031.91 | G40: 778251.77 | H40: 352729.29 | I40: 290008.11 | J40: 767786.82 | K40: 678572.54 | L40: 1165714.5 | M40: 1142458.3 | N40: 471754.66 | O40: 7460911.9
S41: PERIOD OF INVESTIGATION | T41: Y
S42: flowDesc | T42: Import
A43: 2/ | B43: Value | S43: reporterDesc | T43: Egypt
B44: Unit : US Dollar thousand
S45: Sum of primaryValue | T45: refYear | U45: refMonth
C46: 2023 | I46: 2024 | O46: Grand Total | P46: Mark | Q46: Note | T46: 2023 | Z46: 2024 | AF46: Grand Total
B47: partnerDesc | C47: 7 | D47: 8 | E47: 9 | F47: 10 | G47: 11 | H47: 12 | I47: 1 | J47: 2 | K47: 3 | L47: 4 | M47: 5 | N47: 6 | S47: partnerDesc | T47: 7 | U47: 8 | V47: 9 | W47: 10 | X47: 11 | Y47: 12 | Z47: 1 | AA47: 2 | AB47: 3 | AC47: 4 | AD47: 5 | AE47: 6
B48: Australia | M48: 5085.348 | O48: 5085.348 | P48: =VLOOKUP(B48,$B$15:$P$40,15,0) -> Include | Q48: Val | S48: Australia | AD48: 5085.348 | AF48: 5085.348
B49: Austria | F49: 11768.344 | G49: 1318.964 | K49: 17028.966 | L49: 25261.536 | O49: 55377.81 | P49: =VLOOKUP(B49,$B$15:$P$40,15,0) -> Include | Q49: Val | S49: Austria | W49: 11768.344 | X49: 1318.964 | AB49: 17028.966 | AC49: 25261.536 | AF49: 55377.81
B50: Belgium | D50: 9297.901 | E50: 83191.75 | G50: 108048.46 | K50: 480058.57 | L50: 554709.09 | O50: 1235305.8 | P50: =VLOOKUP(B50,$B$15:$P$40,15,0) -> Include | Q50: Val | S50: Belgium | U50: 9297.901 | V50: 83191.75 | X50: 108048.46 | AB50: 480058.57 | AC50: 554709.09 | AF50: 1235305.8
B51: China | C51: 291881.01 | D51: 605637.21 | E51: 322170.34 | F51: 278389.19 | G51: 851113.71 | H51: 223197.15 | I51: 231484.18 | J51: 230389.42 | K51: 197940.03 | L51: 2022999.4 | M51: 761399.71 | N51: 238399.09 | O51: 6255000.4 | P51: =VLOOKUP(B51,$B$15:$P$40,15,0) -> Exclude | Q51: Val | S51: China | T51: 291881.01 | U51: 605637.21 | V51: 322170.34 | W51: 278389.19 | X51: 851113.71 | Y51: 223197.15 | Z51: 231484.18 | AA51: 230389.42 | AB51: 197940.03 | AC51: 2022999.4 | AD51: 761399.71 | AE51: 238399.09 | AF51: 6255000.4
B52: Czechia | E52: 94168.313 | I52: 166399.97 | M52: 159599.63 | O52: 420167.91 | P52: =VLOOKUP(B52,$B$15:$P$40,15,0) -> Include | Q52: Val | S52: Czechia | V52: 94168.313 | Z52: 166399.97 | AD52: 159599.63 | AF52: 420167.91
B53: France | J53: 17571.856 | O53: 17571.856 | P53: =VLOOKUP(B53,$B$15:$P$40,15,0) -> Include | Q53: Val | S53: France | AA53: 17571.856 | AF53: 17571.856
B54: Germany | C54: 63714.882 | D54: 10308.993 | E54: 156902.29 | F54: 17894.162 | G54: 298094.48 | H54: 130338.13 | I54: 221369.97 | J54: 383642.54 | K54: 140025.17 | L54: 46100.938 | M54: 500181.68 | N54: 137720.2 | O54: 2106293.4 | P54: =VLOOKUP(B54,$B$15:$P$40,15,0) -> Include | Q54: Val | S54: Germany | T54: 63714.882 | U54: 10308.993 | V54: 156902.29 | W54: 17894.162 | X54: 298094.48 | Y54: 130338.13 | Z54: 221369.97 | AA54: 383642.54 | AB54: 140025.17 | AC54: 46100.938 | AD54: 500181.68 | AE54: 137720.2 | AF54: 2106293.4
B55: Greece | K55: 47769.3 | L55: 31610.36 | O55: 79379.66 | P55: =VLOOKUP(B55,$B$15:$P$40,15,0) -> Include | Q55: Val | S55: Greece | AB55: 47769.3 | AC55: 31610.36 | AF55: 79379.66
B56: India | C56: 2780.137 | D56: 54163.208 | E56: 6.46 | F56: 66088.906 | G56: 72679.132 | I56: 18940.376 | J56: 20941.14 | K56: 56037.922 | L56: 21013.14 | M56: 359930.76 | N56: 79456.382 | O56: 752037.56 | P56: =VLOOKUP(B56,$B$15:$P$40,15,0) -> Include | Q56: Val | S56: India | T56: 2780.137 | U56: 54163.208 | V56: 6.46 | W56: 66088.906 | X56: 72679.132 | Z56: 18940.376 | AA56: 20941.14 | AB56: 56037.922 | AC56: 21013.14 | AD56: 359930.76 | AE56: 79456.382 | AF56: 752037.56
B57: Italy | C57: 7633.557 | D57: 8015.762 | E57: 4797.437 | F57: 3778.796 | G57: 11615.546 | H57: 24163.414 | I57: 9470.818 | J57: 41240.906 | K57: 67345.272 | L57: 82906.004 | M57: 12539.352 | N57: 79558.524 | O57: 353065.39 | P57: =VLOOKUP(B57,$B$15:$P$40,15,0) -> Include | Q57: Val | S57: Italy | T57: 7633.557 | U57: 8015.762 | V57: 4797.437 | W57: 3778.796 | X57: 11615.546 | Y57: 24163.414 | Z57: 9470.818 | AA57: 41240.906 | AB57: 67345.272 | AC57: 82906.004 | AD57: 12539.352 | AE57: 79558.524 | AF57: 353065.39
B58: Japan | E58: 163682.23 | G58: 375583.48 | H58: 34334.562 | J58: 421028.69 | M58: 383899.31 | O58: 1378528.3 | P58: =VLOOKUP(B58,$B$15:$P$40,15,0) -> Include | Q58: Val | S58: Japan | V58: 163682.23 | X58: 375583.48 | Y58: 34334.562 | AA58: 421028.69 | AD58: 383899.31 | AF58: 1378528.3
B59: Luxembourg | E59: 93854.672 | F59: 152018.68 | M59: 60580.02 | N59: 69596.196 | O59: 376049.57 | P59: =VLOOKUP(B59,$B$15:$P$40,15,0) -> Include | Q59: Val | S59: Luxembourg | V59: 93854.672 | W59: 152018.68 | AD59: 60580.02 | AE59: 69596.196 | AF59: 376049.57
B60: Netherlands | J60: 78.718 | O60: 78.718 | P60: =VLOOKUP(B60,$B$15:$P$40,15,0) -> Include | Q60: Val | S60: Netherlands | AA60: 78.718 | AF60: 78.718
B61: Other Asia, nes | H61: 32.302 | O61: 32.302 | P61: =VLOOKUP(B61,$B$15:$P$40,15,0) -> Include | Q61: Val | S61: Other Asia, nes | Y61: 32.302 | AF61: 32.302
B62: Rep. of Korea | C62: 5252.342 | F62: 5818.994 | O62: 11071.336 | P62: =VLOOKUP(B62,$B$15:$P$40,15,0) -> Include | Q62: Val | S62: Rep. of Korea | T62: 5252.342 | W62: 5818.994 | AF62: 11071.336
B63: Russian Federation | G63: 9832.486 | O63: 9832.486 | P63: =VLOOKUP(B63,$B$15:$P$40,15,0) -> Exclude | Q63: Val | S63: Russian Federation | X63: 9832.486 | AF63: 9832.486
B64: Saudi Arabia | D64: 76549.938 | E64: 4421.813 | J64: 175345.86 | M64: 33108.626 | O64: 289426.24 | P64: =VLOOKUP(B64,$B$15:$P$40,15,0) -> Include | Q64: Val | S64: Saudi Arabia | U64: 76549.938 | V64: 4421.813 | AA64: 175345.86 | AD64: 33108.626 | AF64: 289426.24
B65: Spain | C65: 114912.3 | O65: 114912.3 | P65: =VLOOKUP(B65,$B$15:$P$40,15,0) -> Include | Q65: Val | S65: Spain | T65: 114912.3 | AF65: 114912.3
B66: Thailand | F66: 280561.78 | J66: 319495.3 | K66: 441062.47 | M66: 146219.63 | O66: 1187339.2 | P66: =VLOOKUP(B66,$B$15:$P$40,15,0) -> Include | Q66: Val | S66: Thailand | W66: 280561.78 | AA66: 319495.3 | AB66: 441062.47 | AD66: 146219.63 | AF66: 1187339.2
B67: Türkiye | D67: 1047.291 | E67: 12048.184 | G67: 76622.488 | I67: 46111.09 | J67: 112986.78 | K67: 45517.762 | L67: 1298.8 | M67: 23473.866 | N67: 60253.286 | O67: 379359.55 | P67: =VLOOKUP(B67,$B$15:$P$40,15,0) -> Include | Q67: Val | S67: Türkiye | U67: 1047.291 | V67: 12048.184 | X67: 76622.488 | Z67: 46111.09 | AA67: 112986.78 | AB67: 45517.762 | AC67: 1298.8 | AD67: 23473.866 | AE67: 60253.286 | AF67: 379359.55
B68: United Arab Emirates | E68: 1506.899 | J68: 127929.03 | O68: 129435.93 | P68: =VLOOKUP(B68,$B$15:$P$40,15,0) -> Include | Q68: Val | S68: United Arab Emirates | V68: 1506.899 | AA68: 127929.03 | AF68: 129435.93
B69: United Kingdom | C69: 29053.77 | D69: 265988.55 | E69: 6340.761 | F69: 257928.11 | G69: 73345.688 | H69: 24302.492 | J69: 2347.788 | K69: 119393.95 | L69: 27468.592 | M69: 60434.412 | N69: 347602.71 | O69: 1214206.8 | P69: =VLOOKUP(B69,$B$15:$P$40,15,0) -> Include | Q69: Val | S69: United Kingdom | T69: 29053.77 | U69: 265988.55 | V69: 6340.761 | W69: 257928.11 | X69: 73345.688 | Y69: 24302.492 | AA69: 2347.788 | AB69: 119393.95 | AC69: 27468.592 | AD69: 60434.412 | AE69: 347602.71 | AF69: 1214206.8
B70: USA | C70: 203328.03 | D70: 141805.13 | E70: 135171.97 | F70: 258042.17 | H70: 414918.62 | I70: 6137.228 | K70: 25506.412 | M70: 250788.16 | N70: 125959.43 | O70: 1561657.1 | P70: =VLOOKUP(B70,$B$15:$P$40,15,0) -> Include | Q70: Val | S70: USA | T70: 203328.03 | U70: 141805.13 | V70: 135171.97 | W70: 258042.17 | Y70: 414918.62 | Z70: 6137.228 | AB70: 25506.412 | AD70: 250788.16 | AE70: 125959.43 | AF70: 1561657.1
B71: Viet Nam | E71: 75156.984 | O71: 75156.984 | P71: =VLOOKUP(B71,$B$15:$P$40,15,0) -> Include | Q71: Val | S71: Viet Nam | V71: 75156.984 | AF71: 75156.984
B72: World | C72: 718556.03 | D72: 1172814 | E72: 1153420.1 | F72: 1332289.1 | G72: 1878254.4 | H72: 851286.67 | I72: 699913.63 | J72: 1852998 | K72: 1637685.8 | L72: 2813367.9 | M72: 2757240.5 | N72: 1138545.8 | O72: 18006372 | P72: =VLOOKUP(B72,$B$15:$P$40,15,0) -> Exclude | Q72: Val | S72: World | T72: 718556.03 | U72: 1172814 | V72: 1153420.1 | W72: 1332289.1 | X72: 1878254.4 | Y72: 851286.67 | Z72: 699913.63 | AA72: 1852998 | AB72: 1637685.8 | AC72: 2813367.9 | AD72: 2757240.5 | AE72: 1138545.8 | AF72: 18006372
B73: Grand Total | C73: 1437112.1 | D73: 2345628 | E73: 2306840.2 | F73: 2664578.3 | G73: 3756508.9 | H73: 1702573.3 | I73: 1399827.3 | J73: 3705996.1 | K73: 3275371.6 | L73: 5626735.7 | M73: 5514481 | N73: 2277091.6 | O73: 36012744 | S73: Grand Total | T73: 1437112.1 | U73: 2345628 | V73: 2306840.2 | W73: 2664578.3 | X73: 3756508.9 | Y73: 1702573.3 | Z73: 1399827.3 | AA73: 3705996.1 | AB73: 3275371.6 | AC73: 5626735.7 | AD73: 5514481 | AE73: 2277091.6 | AF73: 36012744
B84: MASTER DATA | L84: IMPORT/ EXPORT | O84: COUNTRY | AG84: QUANTITY | AS84: VALUE
A85: PERIOD OF INVESTIGATION | B85: typeCode | C85: freqCode | D85: refPeriodId | E85: refYear | F85: refMonth | G85: period | H85: reporterCode | I85: reporterISO | J85: reporterDesc | K85: flowCode | L85: flowDesc | M85: partnerCode | N85: partnerISO | O85: partnerDesc | P85: partner2Code | Q85: partner2ISO | R85: partner2Desc | S85: classificationCode | T85: classificationSearchCode | U85: isOriginalClassification | V85: cmdCode | W85: cmdDesc | X85: aggrLevel | Y85: isLeaf | Z85: customsCode | AA85: customsDesc | AB85: mosCode | AC85: motCode | AD85: motDesc | AE85: qtyUnitCode | AF85: qtyUnitAbbr | AG85: qty | AH85: isQtyEstimated | AI85: altQtyUnitCode | AJ85: altQtyUnitAbbr | AK85: altQty | AL85: isAltQtyEstimated | AM85: netWgt | AN85: isNetWgtEstimated | AO85: grossWgt | AP85: isGrossWgtEstimated | AQ85: cifvalue | AR85: fobvalue | AS85: primaryValue | AT85: legacyEstimationFlag | AU85: isReported | AV85: isAggregate
B86: C | C86: M | D86: 20230101 | E86: 2023 | F86: 1 | G86: 202301 | H86: 818 | I86: EGY | J86: Egypt | K86: M | L86: Import | M86: 0 | N86: W00 | O86: World | P86: 0 | Q86: W00 | R86: World | S86: H6 | T86: HS | U86: TRUE | V86: 320619 | W86: Colouring matter; pigments and preparations based on titanium dioxide, containing less than 80% by weight of titanium dioxide calculated on the dry weight | X86: 6 | Y86: TRUE | Z86: C00 | AA86: TOTAL CPC | AB86: 0 | AC86: 0 | AD86: TOTAL MOT | AE86: 8 | AF86: kg | AG86: 208649.62 | AH86: TRUE | AI86: -1 | AJ86: N/A | AK86: 0 | AL86: FALSE | AM86: 208649.62 | AN86: TRUE | AO86: 0 | AP86: FALSE | AQ86: 1007121.6 | AS86: 1007121.6 | AT86: 6 | AU86: FALSE | AV86: TRUE
B87: C | C87: M | D87: 20230101 | E87: 2023 | F87: 1 | G87: 202301 | H87: 818 | I87: EGY | J87: Egypt | K87: M | L87: Import | M87: 156 | N87: CHN | O87: China | P87: 0 | Q87: W00 | R87: World | S87: H6 | T87: HS | U87: TRUE | V87: 320619 | W87: Colouring matter; pigments and preparations based on titanium dioxide, containing less than 80% by weight of titanium dioxide calculated on the dry weight | X87: 6 | Y87: TRUE | Z87: C00 | AA87: TOTAL CPC | AB87: 0 | AC87: 0 | AD87: TOTAL MOT | AE87: 8 | AF87: kg | AG87: 37358.426 | AH87: TRUE | AI87: -1 | AJ87: N/A | AK87: 0 | AL87: FALSE | AM87: 37358.426 | AN87: TRUE | AO87: 0 | AP87: FALSE | AQ87: 180323.73 | AS87: 180323.73 | AT87: 6 | AU87: TRUE | AV87: FALSE
B88: C | C88: M | D88: 20230101 | E88: 2023 | F88: 1 | G88: 202301 | H88: 818 | I88: EGY | J88: Egypt | K88: M | L88: Import | M88: 276 | N88: DEU | O88: Germany | P88: 0 | Q88: W00 | R88: World | S88: H6 | T88: HS | U88: TRUE | V88: 320619 | W88: Colouring matter; pigments and preparations based on titanium dioxide, containing less than 80% by weight of titanium dioxide calculated on the dry weight | X88: 6 | Y88: TRUE | Z88: C00 | AA88: TOTAL CPC | AB88: 0 | AC88: 0 | AD88: TOTAL MOT | AE88: 8 | AF88: kg | AG88: 25214.176 | AH88: TRUE | AI88: -1 | AJ88: N/A | AK88: 0 | AL88: FALSE | AM88: 25214.176 | AN88: TRUE | AO88: 0 | AP88: FALSE | AQ88: 121705.19 | AS88: 121705.19 | AT88: 6 | AU88: TRUE | AV88: FALSE
B89: C | C89: M | D89: 20230101 | E89: 2023 | F89: 1 | G89: 202301 | H89: 818 | I89: EGY | J89: Egypt | K89: M | L89: Import | M89: 380 | N89: ITA | O89: Italy | P89: 0 | Q89: W00 | R89: World | S89: H6 | T89: HS | U89: TRUE | V89: 320619 | W89: Colouring matter; pigments and preparations based on titanium dioxide, containing less than 80% by weight of titanium dioxide calculated on the dry weight | X89: 6 | Y89: TRUE | Z89: C00 | AA89: TOTAL CPC | AB89: 0 | AC89: 0 | AD89: TOTAL MOT | AE89: 8 | AF89: kg | AG89: 4805.265 | AH89: TRUE | AI89: -1 | AJ89: N/A | AK89: 0 | AL89: FALSE | AM89: 4805.265 | AN89: TRUE | AO89: 0 | AP89: FALSE | AQ89: 23194.322 | AS89: 23194.322 | AT89: 6 | AU89: TRUE | AV89: FALSE
B90: C | C90: M | D90: 20230101 | E90: 2023 | F90: 1 | G90: 202301 | H90: 818 | I90: EGY | J90: Egypt | K90: M | L90: Import | M90: 392 | N90: JPN | O90: Japan | P90: 0 | Q90: W00 | R90: World | S90: H6 | T90: HS | U90: TRUE | V90: 320619 | W90: Colouring matter; pigments and preparations based on titanium dioxide, containing less than 80% by weight of titanium dioxide calculated on the dry weight | X90: 6 | Y90: TRUE | Z90: C00 | AA90: TOTAL CPC | AB90: 0 | AC90: 0 | AD90: TOTAL MOT | AE90: 8 | AF90: kg | AG90: 31720.222 | AH90: TRUE | AI90: -1 | AJ90: N/A | AK90: 0 | AL90: FALSE | AM90: 31720.222 | AN90: TRUE | AO90: 0 | AP90: FALSE | AQ90: 153108.93 | AS90: 153108.93 | AT90: 6 | AU90: TRUE | AV90: FALSE
B91: C | C91: M | D91: 20230101 | E91: 2023 | F91: 1 | G91: 202301 | H91: 818 | I91: EGY | J91: Egypt | K91: M | L91: Import | M91: 699 | N91: IND | O91: India | P91: 0 | Q91: W00 | R91: World | S91: H6 | T91: HS | U91: TRUE | V91: 320619 | W91: Colouring matter; pigments and preparations based on titanium dioxide, containing less than 80% by weight of titanium dioxide calculated on the dry weight | X91: 6 | Y91: TRUE | Z91: C00 | AA91: TOTAL CPC | AB91: 0 | AC91: 0 | AD91: TOTAL MOT | AE91: 8 | AF91: kg | AG91: 2015.853 | AH91: TRUE | AI91: -1 | AJ91: N/A | AK91: 0 | AL91: FALSE | AM91: 2015.853 | AN91: TRUE | AO91: 0 | AP91: FALSE | AQ91: 9730.23 | AS91: 9730.23 | AT91: 6 | AU91: TRUE | AV91: FALSE
B92: C | C92: M | D92: 20230101 | E92: 2023 | F92: 1 | G92: 202301 | H92: 818 | I92: EGY | J92: Egypt | K92: M | L92: Import | M92: 792 | N92: TUR | O92: Türkiye | P92: 0 | Q92: W00 | R92: World | S92: H6 | T92: HS | U92: TRUE | V92: 320619 | W92: Colouring matter; pigments and preparations based on titanium dioxide, containing less than 80% by weight of titanium dioxide calculated on the dry weight | X92: 6 | Y92: TRUE | Z92: C00 | AA92: TOTAL CPC | AB92: 0 | AC92: 0 | AD92: TOTAL MOT | AE92: 8 | AF92: kg | AG92: 41353.029 | AH92: TRUE | AI92: -1 | AJ92: N/A | AK92: 0 | AL92: FALSE | AM92: 41353.029 | AN92: TRUE | AO92: 0 | AP92: FALSE | AQ92: 199605.1 | AS92: 199605.1 | AT92: 6 | AU92: TRUE | AV92: FALSE
B93: C | C93: M | D93: 20230101 | E93: 2023 | F93: 1 | G93: 202301 | H93: 818 | I93: EGY | J93: Egypt | K93: M | L93: Import | M93: 826 | N93: GBR | O93: United Kingdom | P93: 0 | Q93: W00 | R93: World | S93: H6 | T93: HS | U93: TRUE | V93: 320619 | W93: Colouring matter; pigments and preparations based on titanium dioxide, containing less than 80% by weight of titanium dioxide calculated on the dry weight | X93: 6 | Y93: TRUE | Z93: C00 | AA93: TOTAL CPC | AB93: 0 | AC93: 0 | AD93: TOTAL MOT | AE93: 8 | AF93: kg | AG93: 51725.238 | AH93: TRUE | AI93: -1 | AJ93: N/A | AK93: 0 | AL93: FALSE | AM93: 51725.238 | AN93: TRUE | AO93: 0 | AP93: FALSE | AQ93: 249670.25 | AS93: 249670.25 | AT93: 6 | AU93: TRUE | AV93: FALSE
B94: C | C94: M | D94: 20230101 | E94: 2023 | F94: 1 | G94: 202301 | H94: 818 | I94: EGY | J94: Egypt | K94: M | L94: Import | M94: 842 | N94: USA | O94: USA | P94: 0 | Q94: W00 | R94: World | S94: H6 | T94: HS | U94: TRUE | V94: 320619 | W94: Colouring matter; pigments and preparations based on titanium dioxide, containing less than 80% by weight of titanium dioxide calculated on the dry weight | X94: 6 | Y94: TRUE | Z94: C00 | AA94: TOTAL CPC | AB94: 0 | AC94: 0 | AD94: TOTAL MOT | AE94: 8 | AF94: kg | AG94: 14457.415 | AH94: TRUE | AI94: -1 | AJ94: N/A | AK94: 0 | AL94: FALSE | AM94: 14457.415 | AN94: TRUE | AO94: 0 | AP94: FALSE | AQ94: 69783.856 | AS94: 69783.856 | AT94: 6 | AU94: TRUE | AV94: FALSE
B95: C | C95: M | D95: 20230101 | E95: 2023 | F95: 1 | G95: 202301 | H95: 818 | I95: EGY | J95: Egypt | K95: X | L95: Export | M95: 0 | N95: W00 | O95: World | P95: 0 | Q95: W00 | R95: World | S95: H6 | T95: HS | U95: TRUE | V95: 320619 | W95: Colouring matter; pigments and preparations based on titanium dioxide, containing less than 80% by weight of titanium dioxide calculated on the dry weight | X95: 6 | Y95: TRUE | Z95: C00 | AA95: TOTAL CPC | AB95: 0 | AC95: 0 | AD95: TOTAL MOT | AE95: 8 | AF95: kg | AG95: 26412.538 | AH95: TRUE | AI95: -1 | AJ95: N/A | AK95: 0 | AL95: FALSE | AM95: 26412.538 | AN95: TRUE | AO95: 0 | AP95: FALSE | AR95: 136656 | AS95: 136656 | AT95: 6 | AU95: FALSE | AV95: TRUE
B96: C | C96: M | D96: 20230101 | E96: 2023 | F96: 1 | G96: 202301 | H96: 818 | I96: EGY | J96: Egypt | K96: X | L96: Export | M96: 842 | N96: USA | O96: USA | P96: 0 | Q96: W00 | R96: World | S96: H6 | T96: HS | U96: TRUE | V96: 320619 | W96: Colouring matter; pigments and preparations based on titanium dioxide, containing less than 80% by weight of titanium dioxide calculated on the dry weight | X96: 6 | Y96: TRUE | Z96: C00 | AA96: TOTAL CPC | AB96: 0 | AC96: 0 | AD96: TOTAL MOT | AE96: 8 | AF96: kg | AG96: 26412.538 | AH96: TRUE | AI96: -1 | AJ96: N/A | AK96: 0 | AL96: FALSE | AM96: 26412.538 | AN96: TRUE | AO96: 0 | AP96: FALSE | AR96: 136656 | AS96: 136656 | AT96: 6 | AU96: TRUE | AV96: FALSE
B97: C | C97: M | D97: 20230201 | E97: 2023 | F97: 2 | G97: 202302 | H97: 818 | I97: EGY | J97: Egypt | K97: M | L97: Import | M97: 0 | N97: W00 | O97: World | P97: 0 | Q97: W00 | R97: World | S97: H6 | T97: HS | U97: TRUE | V97: 320619 | W97: Colouring matter; pigments and preparations based on titanium dioxide, containing less than 80% by weight of titanium dioxide calculated on the dry weight | X97: 6 | Y97: TRUE | Z97: C00 | AA97: TOTAL CPC | AB97: 0 | AC97: 0 | AD97: TOTAL MOT | AE97: 8 | AF97: kg | AG97: 110014.12 | AH97: TRUE | AI97: -1 | AJ97: N/A | AK97: 0 | AL97: FALSE | AM97: 110014.12 | AN97: TRUE | AO97: 0 | AP97: FALSE | AQ97: 531022.27 | AS97: 531022.27 | AT97: 6 | AU97: FALSE | AV97: TRUE
B98: C | C98: M | D98: 20230201 | E98: 2023 | F98: 2 | G98: 202302 | H98: 818 | I98: EGY | J98: Egypt | K98: M | L98: Import | M98: 156 | N98: CHN | O98: China | P98: 0 | Q98: W00 | R98: World | S98: H6 | T98: HS | U98: TRUE | V98: 320619 | W98: Colouring matter; pigments and preparations based on titanium dioxide, containing less than 80% by weight of titanium dioxide calculated on the dry weight | X98: 6 | Y98: TRUE | Z98: C00 | AA98: TOTAL CPC | AB98: 0 | AC98: 0 | AD98: TOTAL MOT | AE98: 8 | AF98: kg | AG98: 4022.287 | AH98: TRUE | AI98: -1 | AJ98: N/A | AK98: 0 | AL98: FALSE | AM98: 4022.287 | AN98: TRUE | AO98: 0 | AP98: FALSE | AQ98: 19415 | AS98: 19415 | AT98: 6 | AU98: TRUE | AV98: FALSE
B99: C | C99: M | D99: 20230201 | E99: 2023 | F99: 2 | G99: 202302 | H99: 818 | I99: EGY | J99: Egypt | K99: M | L99: Import | M99: 251 | N99: FRA | O99: France | P99: 0 | Q99: W00 | R99: World | S99: H6 | T99: HS | U99: TRUE | V99: 320619 | W99: Colouring matter; pigments and preparations based on titanium dioxide, containing less than 80% by weight of titanium dioxide calculated on the dry weight | X99: 6 | Y99: TRUE | Z99: C00 | AA99: TOTAL CPC | AB99: 0 | AC99: 0 | AD99: TOTAL MOT | AE99: 8 | AF99: kg | AG99: 1965.999 | AH99: TRUE | AI99: -1 | AJ99: N/A | AK99: 0 | AL99: FALSE | AM99: 1965.999 | AN99: TRUE | AO99: 0 | AP99: FALSE | AQ99: 9489.593 | AS99: 9489.593 | AT99: 6 | AU99: TRUE | AV99: FALSE
B100: C | C100: M | D100: 20230201 | E100: 2023 | F100: 2 | G100: 202302 | H100: 818 | I100: EGY | J100: Egypt | K100: M | L100: Import | M100: 276 | N100: DEU | O100: Germany | P100: 0 | Q100: W00 | R100: World | S100: H6 | T100: HS | U100: TRUE | V100: 320619 | W100: Colouring matter; pigments and preparations based on titanium dioxide, containing less than 80% by weight of titanium dioxide calculated on the dry weight | X100: 6 | Y100: TRUE | Z100: C00 | AA100: TOTAL CPC | AB100: 0 | AC100: 0 | AD100: TOTAL MOT | AE100: 8 | AF100: kg | AG100: 955.802 | AH100: TRUE | AI100: -1 | AJ100: N/A | AK100: 0 | AL100: FALSE | AM100: 955.802 | AN100: TRUE | AO100: 0 | AP100: FALSE | AQ100: 4613.52 | AS100: 4613.52 | AT100: 6 | AU100: TRUE | AV100: FALSE
B101: C | C101: M | D101: 20230201 | E101: 2023 | F101: 2 | G101: 202302 | H101: 818 | I101: EGY | J101: Egypt | K101: M | L101: Import | M101: 392 | N101: JPN | O101: Japan | P101: 0 | Q101: W00 | R101: World | S101: H6 | T101: HS | U101: TRUE | V101: 320619 | W101: Colouring matter; pigments and preparations based on titanium dioxide, containing less than 80% by weight of titanium dioxide calculated on the dry weight | X101: 6 | Y101: TRUE | Z101: C00 | AA101: TOTAL CPC | AB101: 0 | AC101: 0 | AD101: TOTAL MOT | AE101: 8 | AF101: kg | AG101: 25902.633 | AH101: TRUE | AI101: -1 | AJ101: N/A | AK101: 0 | AL101: FALSE | AM101: 25902.633 | AN101: TRUE | AO101: 0 | AP101: FALSE | AQ101: 125028.27 | AS101: 125028.27 | AT101: 6 | AU101: TRUE | AV101: FALSE
B102: C | C102: M | D102: 20230201 | E102: 2023 | F102: 2 | G102: 202302 | H102: 818 | I102: EGY | J102: Egypt | K102: M | L102: Import | M102: 568 | N102: E19 | O102: Other Europe, nes | P102: 0 | Q102: W00 | R102: World | S102: H6 | T102: HS | U102: TRUE | V102: 320619 | W102: Colouring matter; pigments and preparations based on titanium dioxide, containing less than 80% by weight of titanium dioxide calculated on the dry weight | X102: 6 | Y102: TRUE | Z102: C00 | AA102: TOTAL CPC | AB102: 0 | AC102: 0 | AD102: TOTAL MOT | AE102: 8 | AF102: kg | AG102: 687.748 | AH102: TRUE | AI102: -1 | AJ102: N/A | AK102: 0 | AL102: FALSE | AM102: 687.748 | AN102: TRUE | AO102: 0 | AP102: FALSE | AQ102: 3319.662 | AS102: 3319.662 | AT102: 6 | AU102: TRUE | AV102: FALSE
B103: C | C103: M | D103: 20230201 | E103: 2023 | F103: 2 | G103: 202302 | H103: 818 | I103: EGY | J103: Egypt | K103: M | L103: Import | M103: 699 | N103: IND | O103: India | P103: 0 | Q103: W00 | R103: World | S103: H6 | T103: HS | U103: TRUE | V103: 320619 | W103: Colouring matter; pigments and preparations based on titanium dioxide, containing less than 80% by weight of titanium dioxide calculated on the dry weight | X103: 6 | Y103: TRUE | Z103: C00 | AA103: TOTAL CPC | AB103: 0 | AC103: 0 | AD103: TOTAL MOT | AE103: 8 | AF103: kg | AG103: 8958.037 | AH103: TRUE | AI103: -1 | AJ103: N/A | AK103: 0 | AL103: FALSE | AM103: 8958.037 | AN103: TRUE | AO103: 0 | AP103: FALSE | AQ103: 43239.149 | AS103: 43239.149 | AT103: 6 | AU103: TRUE | AV103: FALSE
B104: C | C104: M | D104: 20230201 | E104: 2023 | F104: 2 | G104: 202302 | H104: 818 | I104: EGY | J104: Egypt | K104: M | L104: Import | M104: 764 | N104: THA | O104: Thailand | P104: 0 | Q104: W00 | R104: World | S104: H6 | T104: HS | U104: TRUE | V104: 320619 | W104: Colouring matter; pigments and preparations based on titanium dioxide, containing less than 80% by weight of titanium dioxide calculated on the dry weight | X104: 6 | Y104: TRUE | Z104: C00 | AA104: TOTAL CPC | AB104: 0 | AC104: 0 | AD104: TOTAL MOT | AE104: 8 | AF104: kg | AG104: 17009.454 | AH104: TRUE | AI104: -1 | AJ104: N/A | AK104: 0 | AL104: FALSE | AM104: 17009.454 | AN104: TRUE | AO104: 0 | AP104: FALSE | AQ104: 82102.18 | AS104: 82102.18 | AT104: 6 | AU104: TRUE | AV104: FALSE
B105: C | C105: M | D105: 20230201 | E105: 2023 | F105: 2 | G105: 202302 | H105: 818 | I105: EGY | J105: Egypt | K105: M | L105: Import | M105: 826 | N105: GBR | O105: United Kingdom | P105: 0 | Q105: W00 | R105: World | S105: H6 | T105: HS | U105: TRUE | V105: 320619 | W105: Colouring matter; pigments and preparations based on titanium dioxide, containing less than 80% by weight of titanium dioxide calculated on the dry weight | X105: 6 | Y105: TRUE | Z105: C00 | AA105: TOTAL CPC | AB105: 0 | AC105: 0 | AD105: TOTAL MOT | AE105: 8 | AF105: kg | AG105: 50512.159 | AH105: TRUE | AI105: -1 | AJ105: N/A | AK105: 0 | AL105: FALSE | AM105: 50512.159 | AN105: TRUE | AO105: 0 | AP105: FALSE | AQ105: 243814.9 | AS105: 243814.9 | AT105: 6 | AU105: TRUE | AV105: FALSE
B106: C | C106: M | D106: 20230301 | E106: 2023 | F106: 3 | G106: 202303 | H106: 818 | I106: EGY | J106: Egypt | K106: M | L106: Import | M106: 0 | N106: W00 | O106: World | P106: 0 | Q106: W00 | R106: World | S106: H6 | T106: HS | U106: TRUE | V106: 320619 | W106: Colouring matter; pigments and preparations based on titanium dioxide, containing less than 80% by weight of titanium dioxide calculated on the dry weight | X106: 6 | Y106: TRUE | Z106: C00 | AA106: TOTAL CPC | AB106: 0 | AC106: 0 | AD106: TOTAL MOT | AE106: 8 | AF106: kg | AG106: 91053.752 | AH106: TRUE | AI106: -1 | AJ106: N/A | AK106: 0 | AL106: FALSE | AM106: 91053.752 | AN106: TRUE | AO106: 0 | AP106: FALSE | AQ106: 439503.31 | AS106: 439503.31 | AT106: 6 | AU106: FALSE | AV106: TRUE
B107: C | C107: M | D107: 20230301 | E107: 2023 | F107: 3 | G107: 202303 | H107: 818 | I107: EGY | J107: Egypt | K107: M | L107: Import | M107: 40 | N107: AUT | O107: Austria | P107: 0 | Q107: W00 | R107: World | S107: H6 | T107: HS | U107: TRUE | V107: 320619 | W107: Colouring matter; pigments and preparations based on titanium dioxide, containing less than 80% by weight of titanium dioxide calculated on the dry weight | X107: 6 | Y107: TRUE | Z107: C00 | AA107: TOTAL CPC | AB107: 0 | AC107: 0 | AD107: TOTAL MOT | AE107: 8 | AF107: kg | AG107: 2866.304 | AH107: TRUE | AI107: -1 | AJ107: N/A | AK107: 0 | AL107: FALSE | AM107: 2866.304 | AN107: TRUE | AO107: 0 | AP107: FALSE | AQ107: 13835.236 | AS107: 13835.236 | AT107: 6 | AU107: TRUE | AV107: FALSE
B108: C | C108: M | D108: 20230301 | E108: 2023 | F108: 3 | G108: 202303 | H108: 818 | I108: EGY | J108: Egypt | K108: M | L108: Import | M108: 56 | N108: BEL | O108: Belgium | P108: 0 | Q108: W00 | R108: World | S108: H6 | T108: HS | U108: TRUE | V108: 320619 | W108: Colouring matter; pigments and preparations based on titanium dioxide, containing less than 80% by weight of titanium dioxide calculated on the dry weight | X108: 6 | Y108: TRUE | Z108: C00 | AA108: TOTAL CPC | AB108: 0 | AC108: 0 | AD108: TOTAL MOT | AE108: 8 | AF108: kg | AG108: 20371.371 | AH108: TRUE | AI108: -1 | AJ108: N/A | AK108: 0 | AL108: FALSE | AM108: 20371.371 | AN108: TRUE | AO108: 0 | AP108: FALSE | AQ108: 98329.664 | AS108: 98329.664 | AT108: 6 | AU108: TRUE | AV108: FALSE
... B116: C | C116: M | D116: 20230301 | E116: 2023 | F116: 3 | G116: 202303 | H116: 818 | I116: EGY | J116: Egypt | K116: M | L116: Import | M116: 842 | N116: USA | O116: USA | P116: 0 | Q116: W00 | R116: World | S116: H6 | T116: HS | U116: TRUE | V116: 320619 | W116: Colouring matter; pigments and preparations based on titanium dioxide, containing less than 80% by weight of titanium dioxide calculated on the dry weight | X116: 6 | Y116: TRUE | Z116: C00 | AA116: TOTAL CPC | AB116: 0 | AC116: 0 | AD116: TOTAL MOT | AE116: 8 | AF116: kg | AG116: 1612.682 | AH116: TRUE | AI116: -1 | AJ116: N/A | AK116: 0 | AL116: FALSE | AM116: 1612.682 | AN116: TRUE | AO116: 0 | AP116: FALSE | AQ116: 7784.181 | AS116: 7784.181 | AT116: 6 | AU116: TRUE | AV116: FALSE
B117: C | C117: M | D117: 20230301 | E117: 2023 | F117: 3 | G117: 202303 | H117: 818 | I117: EGY | J117: Egypt | K117: X | L117: Export | M117: 0 | N117: W00 | O117: World | P117: 0 | Q117: W00 | R117: World | S117: H6 | T117: HS | U117: TRUE | V117: 320619 | W117: Colouring matter; pigments and preparations based on titanium dioxide, containing less than 80% by weight of titanium dioxide calculated on the dry weight | X117: 6 | Y117: TRUE | Z117: C00 | AA117: TOTAL CPC | AB117: 0 | AC117: 0 | AD117: TOTAL MOT | AE117: 8 | AF117: kg | AG117: 53114.992 | AH117: TRUE | AI117: -1 | AJ117: N/A | AK117: 0 | AL117: FALSE | AM117: 53114.992 | AN117: TRUE | AO117: 0 | AP117: FALSE | AR117: 274812 | AS117: 274812 | AT117: 6 | AU117: FALSE | AV117: TRUE
B118: C | C118: M | D118: 20230301 | E118: 2023 | F118: 3 | G118: 202303 | H118: 818 | I118: EGY | J118: Egypt | K118: X | L118: Export | M118: 729 | N118: SDN | O118: Sudan | P118: 0 | Q118: W00 | R118: World | S118: H6 | T118: HS | U118: TRUE | V118: 320619 | W118: Colouring matter; pigments and preparations based on titanium dioxide, containing less than 80% by weight of titanium dioxide calculated on the dry weight | X118: 6 | Y118: TRUE | Z118: C00 | AA118: TOTAL CPC | AB118: 0 | AC118: 0 | AD118: TOTAL MOT | AE118: 8 | AF118: kg | AG118: 289.916 | AH118: TRUE | AI118: -1 | AJ118: N/A | AK118: 0 | AL118: FALSE | AM118: 289.916 | AN118: TRUE | AO118: 0 | AP118: FALSE | AR118: 1500 | AS118: 1500 | AT118: 6 | AU118: TRUE | AV118: FALSE
B119: C | C119: M | D119: 20230301 | E119: 2023 | F119: 3 | G119: 202303 | H119: 818 | I119: EGY | J119: Egypt | K119: X | L119: Export | M119: 842 | N119: USA | O119: USA | P119: 0 | Q119: W00 | R119: World | S119: H6 | T119: HS | U119: TRUE | V119: 320619 | W119: Colouring matter; pigments and preparations based on titanium dioxide, containing less than 80% by weight of titanium dioxide calculated on the dry weight | X119: 6 | Y119: TRUE | Z119: C00 | AA119: TOTAL CPC | AB119: 0 | AC119: 0 | AD119: TOTAL MOT | AE119: 8 | AF119: kg | AG119: 52825.076 | AH119: TRUE | AI119: -1 | AJ119: N/A | AK119: 0 | AL119: FALSE | AM119: 52825.076 | AN119: TRUE | AO119: 0 | AP119: FALSE | AR119: 273312 | AS119: 273312 | AT119: 6 | AU119: TRUE | AV119: FALSE
...

Sheet EX-2.6 Phá bọt
A1: List of supplying markets for a product imported by Egypt | D1: ='EX-1A SV Summary'!D31 -> 38249970
A2: Chemical products, mixtures and preparations; n.e.c. heading 3824
A3: Sources: ITC calculations based on UN COMTRADE statistics. | S3: reporterDesc | T3: Egypt
B5: Total quantity imported (Kg) | C5: Total value imported (USD) | D5: Unit price (USD/Kg) | S5: Sum of qty | T5: refYear | U5: refMonth
B6: =SUMIFS(O:O,P:P,"Include",Q:Q,"QTY")*1000 -> 5.8601395e+10 | C6: =SUMIFS(O:O,P:P,"Include",Q:Q,"VAL")*1000 -> 2.7653565e+11 | D6: =C6/B6 -> 4.7189261 | T6: 2023 | Z6: 2024 | AF6: Grand Total
S7: partnerDesc | T7: 7 | U7: 8 | V7: 9 | W7: 10 | X7: 11 | Y7: 12 | Z7: 1 | AA7: 2 | AB7: 3 | AC7: 4 | AD7: 5 | AE7: 6
A8: 1/ | B8: Quantity | S8: Argentina | T8: 7455.004 | AF8: 7455.004
B9: Unit : ton | S9: Australia | T9: 50255.673 | U9: 16828.992 | V9: 1807.724 | W9: 15662.488 | X9: 37274.025 | Z9: 1176.741 | AA9: 1706.948 | AB9: 1259.639 | AD9: 34501.866 | AE9: 6939.868 | AF9: 167413.96
S10: Austria | T10: 14791.938 | U10: 2039.854 | V10: 1168.933 | Y10: 4019.498 | AB10: 2486.313 | AC10: 22757.107 | AE10: 4953.677 | AF10: 52217.32
C11: 2023 | I11: 2024 | O11: Grand Total | P11: Mark | Q11: Note | S11: Belgium | T11: 29973.2 | U11: 72596.92 | V11: 42165.108 | W11: 40955.154 | X11: 199879.83 | Y11: 4467.309 | Z11: 57877.538 | AA11: 76003.049 | AB11: 42985.738 | AC11: 171650.82 | AD11: 101528.02 | AE11: 6555.892 | AF11: 846638.58
B12: partnerDesc | C12: 7 | D12: 8 | E12: 9 | F12: 10 | G12: 11 | H12: 12 | I12: 1 | J12: 2 | K12: 3 | L12: 4 | M12: 5 | N12: 6 | S12: Brazil | T12: 48026.188 | W12: 29461.5 | X12: 27527.319 | Y12: 10460.517 | Z12: 3801.936 | AA12: 26806.948 | AB12: 34779.576 | AC12: 9117.238 | AD12: 15075.089 | AE12: 2190.454 | AF12: 207246.77
B13: Argentina | C13: 7455.004 | O13: 7455.004 | P13: Include | Q13: Qty | S13: Bulgaria | AC13: 2011.593 | AF13: 2011.593
B14: Australia | C14: 50255.673 | D14: 16828.992 | E14: 1807.724 | F14: 15662.488 | G14: 37274.025 | I14: 1176.741 | J14: 1706.948 | K14: 1259.639 | M14: 34501.866 | N14: 6939.868 | O14: 167413.96 | P14: Include | Q14: Qty | S14: Canada | X14: 5070.118 | Y14: 216.688 | Z14: 39724.084 | AA14: 1216.73 | AB14: 275.922 | AC14: 2924.498 | AD14: 664.834 | AE14: 1870.574 | AF14: 51963.448
B15: Austria | C15: 14791.938 | D15: 2039.854 | E15: 1168.933 | H15: 4019.498 | K15: 2486.313 | L15: 22757.107 | N15: 4953.677 | O15: 52217.32 | P15: Include | Q15: Qty | S15: Chile | AC15: 10754.862 | AF15: 10754.862
B16: Belgium | C16: 29973.2 | D16: 72596.92 | E16: 42165.108 | F16: 40955.154 | G16: 199879.83 | H16: 4467.309 | I16: 57877.538 | J16: 76003.049 | K16: 42985.738 | L16: 171650.82 | M16: 101528.02 | N16: 6555.892 | O16: 846638.58 | P16: Include | Q16: Qty | S16: China | T16: 830078.98 | U16: 778578.94 | V16: 425293.28 | W16: 799268.5 | X16: 595904.23 | Y16: 409309.01 | Z16: 724389.84 | AA16: 736605.57 | AB16: 693586.95 | AC16: 492741.04 | AD16: 825500.47 | AE16: 510083.64 | AF16: 7821340.5
B17: Brazil | C17: 48026.188 | F17: 29461.5 | G17: 27527.319 | H17: 10460.517 | I17: 3801.936 | J17: 26806.948 | K17: 34779.576 | L17: 9117.238 | M17: 15075.089 | N17: 2190.454 | O17: 207246.77 | P17: Include | Q17: Qty | S17: China, Hong Kong SAR | T17: 427.986 | X17: 164.281 | AA17: 2257.481 | AD17: 37126.204 | AF17: 39975.952
B18: Bulgaria | L18: 2011.593 | O18: 2011.593 | P18: Include | Q18: Qty | S18: Czechia | AD18: 4788.267 | AF18: 4788.267
B19: Canada | G19: 5070.118 | H19: 216.688 | I19: 39724.084 | J19: 1216.73 | K19: 275.922 | L19: 2924.498 | M19: 664.834 | N19: 1870.574 | O19: 51963.448 | P19: Include | Q19: Qty | S19: Denmark | T19: 29359.304 | U19: 41881.564 | V19: 30199.404 | W19: 34825.184 | X19: 72671.161 | Y19: 2400.364 | Z19: 15727.673 | AA19: 60330.813 | AB19: 78587.716 | AC19: 8072.254 | AD19: 73304.349 | AE19: 12456.296 | AF19: 459816.08
B20: Chile | L20: 10754.862 | O20: 10754.862 | P20: Include | Q20: Qty | S20: Estonia | U20: 2592.85 | AF20: 2592.85
B21: China | C21: 830078.98 | D21: 778578.94 | E21: 425293.28 | F21: 799268.5 | G21: 595904.23 | H21: 409309.01 | I21: 724389.84 | J21: 736605.57 | K21: 693586.95 | L21: 492741.04 | M21: 825500.47 | N21: 510083.64 | O21: 7821340.5 | P21: Exclude | Q21: Qty | S21: Finland | AA21: 266.807 | AB21: 1387.726 | AF21: 1654.533
B22: China, Hong Kong SAR | C22: 427.986 | G22: 164.281 | J22: 2257.481 | M22: 37126.204 | O22: 39975.952 | P22: Exclude | Q22: Qty | S22: France | T22: 395008.91 | U22: 252150.5 | V22: 128007.14 | W22: 103399.61 | X22: 102630.75 | Y22: 83094.263 | Z22: 287877.54 | AA22: 110166.74 | AB22: 111585.21 | AC22: 178257.57 | AD22: 176224.4 | AE22: 73513.37 | AF22: 2001916
B23: Czechia | M23: 4788.267 | O23: 4788.267 | P23: Include | Q23: Qty | S23: Georgia | Y23: 19144.256 | AA23: 4600.649 | AD23: 8739.296 | AF23: 32484.201
B24: Denmark | C24: 29359.304 | D24: 41881.564 | E24: 30199.404 | F24: 34825.184 | G24: 72671.161 | H24: 2400.364 | I24: 15727.673 | J24: 60330.813 | K24: 78587.716 | L24: 8072.254 | M24: 73304.349 | N24: 12456.296 | O24: 459816.08 | P24: Include | Q24: Qty | S24: Germany | T24: 633807.13 | U24: 438130.49 | V24: 421955.49 | W24: 623354.46 | X24: 384202.67 | Y24: 393706.28 | Z24: 445571 | AA24: 556079.31 | AB24: 358295.86 | AC24: 468491.98 | AD24: 549445.76 | AE24: 343255.48 | AF24: 5616295.9
B25: Estonia | D25: 2592.85 | O25: 2592.85 | P25: Include | Q25: Qty | S25: Greece | V25: 14993.894 | Z25: 139.604 | AA25: 8003.504 | AB25: 854.832 | AF25: 23991.834
B26: Finland | J26: 266.807 | K26: 1387.726 | O26: 1654.533 | P26: Include | Q26: Qty | S26: Hungary | AB26: 5846.412 | AF26: 5846.412
B27: France | C27: 395008.91 | D27: 252150.5 | E27: 128007.14 | F27: 103399.61 | G27: 102630.75 | H27: 83094.263 | I27: 287877.54 | J27: 110166.74 | K27: 111585.21 | L27: 178257.57 | M27: 176224.4 | N27: 73513.37 | O27: 2001916 | P27: Include | Q27: Qty | S27: India | T27: 383051.28 | U27: 295591.88 | V27: 289186.54 | W27: 389302.43 | X27: 277728.72 | Y27: 180504.64 | Z27: 136962.85 | AA27: 233371 | AB27: 158973.55 | AC27: 197743.59 | AD27: 364756.43 | AE27: 167340.68 | AF27: 3074513.6
B28: Georgia | H28: 19144.256 | J28: 4600.649 | M28: 8739.296 | O28: 32484.201 | P28: Include | Q28: Qty | S28: Indonesia | W28: 412.722 | Y28: 8860.919 | Z28: 3.423 | AB28: 37167.815 | AD28: 5467.851 | AE28: 21969.621 | AF28: 73882.351
B29: Germany | C29: 633807.13 | D29: 438130.49 | E29: 421955.49 | F29: 623354.46 | G29: 384202.67 | H29: 393706.28 | I29: 445571 | J29: 556079.31 | K29: 358295.86 | L29: 468491.98 | M29: 549445.76 | N29: 343255.48 | O29: 5616295.9 | P29: Include | Q29: Qty | S29: Ireland | V29: 5956.951 | AB29: 8190.29 | AF29: 14147.241
B30: Greece | E30: 14993.894 | I30: 139.604 | J30: 8003.504 | K30: 854.832 | O30: 23991.834 | P30: Include | Q30: Qty | S30: Israel | T30: 8879.376 | W30: 13119.379 | X30: 19559.384 | Y30: 22404.617 | AA30: 2101.151 | AB30: 8180.684 | AC30: 15472.124 | AD30: 6365.822 | AE30: 8877.169 | AF30: 104959.71
B31: Hungary | K31: 5846.412 | O31: 5846.412 | P31: Include | Q31: Qty | S31: Italy | T31: 169219.13 | U31: 323688.86 | V31: 164566.19 | W31: 201481.19 | X31: 134290.71 | Y31: 108070.2 | Z31: 97489.044 | AA31: 90097.702 | AB31: 311125.6 | AC31: 260717.15 | AD31: 141186.3 | AE31: 167778.44 | AF31: 2169710.5
B32: India | C32: 383051.28 | D32: 295591.88 | E32: 289186.54 | F32: 389302.43 | G32: 277728.72 | H32: 180504.64 | I32: 136962.85 | J32: 233371 | K32: 158973.55 | L32: 197743.59 | M32: 364756.43 | N32: 167340.68 | O32: 3074513.6 | P32: Include | Q32: Qty | S32: Japan | U32: 1663.15 | V32: 5231.377 | W32: 5921.626 | X32: 1116.284 | Y32: 339.808 | Z32: 4014.119 | AA32: 28370.049 | AB32: 40.411 | AC32: 4182.356 | AD32: 17123.438 | AE32: 480.32 | AF32: 68482.938
B33: Indonesia | F33: 412.722 | H33: 8860.919 | I33: 3.423 | K33: 37167.815 | M33: 5467.851 | N33: 21969.621 | O33: 73882.351 | P33: Include | Q33: Qty | S33: Jordan | V33: 36650.291 | X33: 13297.099 | Y33: 30277.016 | AC33: 24033.438 | AD33: 1573.456 | AE33: 74464.932 | AF33: 180296.23
B34: Ireland | E34: 5956.951 | K34: 8190.29 | O34: 14147.241 | P34: Include | Q34: Qty | S34: Lithuania | AD34: 1323.775 | AF34: 1323.775
B35: Israel | C35: 8879.376 | F35: 13119.379 | G35: 19559.384 | H35: 22404.617 | J35: 2101.151 | K35: 8180.684 | L35: 15472.124 | M35: 6365.822 | N35: 8877.169 | O35: 104959.71 | P35: Include | Q35: Qty | S35: Luxembourg | U35: 741.249 | AF35: 741.249
B36: Italy | C36: 169219.13 | D36: 323688.86 | E36: 164566.19 | F36: 201481.19 | G36: 134290.71 | H36: 108070.2 | I36: 97489.044 | J36: 90097.702 | K36: 311125.6 | L36: 260717.15 | M36: 141186.3 | N36: 167778.44 | O36: 2169710.5 | P36: Include | Q36: Qty | S36: Malaysia | T36: 24978.074 | U36: 43701.248 | V36: 1188.064 | X36: 8186.311 | Y36: 8941.406 | Z36: 49818.986 | AB36: 10681.567 | AD36: 30749.516 | AE36: 1275.34 | AF36: 179520.51
B37: Japan | D37: 1663.15 | E37: 5231.377 | F37: 5921.626 | G37: 1116.284 | H37: 339.808 | I37: 4014.119 | J37: 28370.049 | K37: 40.411 | L37: 4182.356 | M37: 17123.438 | N37: 480.32 | O37: 68482.938 | P37: Include | Q37: Qty | S37: Mexico | U37: 19915.495 | X37: 1196.069 | AC37: 23855.208 | AD37: 50.357 | AF37: 45017.129
B38: Jordan | E38: 36650.291 | G38: 13297.099 | H38: 30277.016 | L38: 24033.438 | M38: 1573.456 | N38: 74464.932 | O38: 180296.23 | P38: Include | Q38: Qty | S38: Netherlands | U38: 76588.965 | V38: 27204.225 | W38: 74729.677 | X38: 104773.62 | Y38: 193732.52 | Z38: 124657.54 | AA38: 177560.08 | AB38: 105768.52 | AC38: 95742.831 | AD38: 115831.32 | AE38: 109801.38 | AF38: 1206390.7
B39: Lithuania | M39: 1323.775 | O39: 1323.775 | P39: Include | Q39: Qty | S39: New Zealand | Z39: 13335.94 | AF39: 13335.94
B40: Luxembourg | D40: 741.249 | O40: 741.249 | P40: Include | Q40: Qty | S40: Norway | T40: 3490.097 | W40: 11654.235 | X40: 20600.973 | AB40: 1253.849 | AE40: 99.039 | AF40: 37098.193
B41: Malaysia | C41: 24978.074 | D41: 43701.248 | E41: 1188.064 | G41: 8186.311 | H41: 8941.406 | I41: 49818.986 | K41: 10681.567 | M41: 30749.516 | N41: 1275.34 | O41: 179520.51 | P41: Include | Q41: Qty | S41: Other Asia, nes | T41: 21373.203 | X41: 58423.481 | Z41: 34947.002 | AA41: 26895.963 | AC41: 12736.987 | AF41: 154376.64
B42: Mexico | D42: 19915.495 | G42: 1196.069 | L42: 23855.208 | M42: 50.357 | O42: 45017.129 | P42: Include | Q42: Qty | S42: Other Europe, nes | U42: 27506.497 | V42: 74611.518 | W42: 70005.421 | X42: 61429.533 | Y42: 60009.289 | Z42: 15027.906 | AA42: 33772.491 | AB42: 17567.869 | AC42: 3084.333 | AD42: 18686.094 | AE42: 16587.916 | AF42: 398288.87
B43: Netherlands | D43: 76588.965 | E43: 27204.225 | F43: 74729.677 | G43: 104773.62 | H43: 193732.52 | I43: 124657.54 | J43: 177560.08 | K43: 105768.52 | L43: 95742.831 | M43: 115831.32 | N43: 109801.38 | O43: 1206390.7 | P43: Include | Q43: Qty | S43: Philippines | W43: 20361.891 | AF43: 20361.891
B44: New Zealand | I44: 13335.94 | O44: 13335.94 | P44: Include | Q44: Qty | S44: Poland | U44: 1617.929 | V44: 12913.428 | W44: 1281.152 | X44: 37194.682 | Y44: 3027.747 | Z44: 3264.476 | AA44: 12287.046 | AF44: 71586.46
B45: Norway | C45: 3490.097 | F45: 11654.235 | G45: 20600.973 | K45: 1253.849 | N45: 99.039 | O45: 37098.193 | P45: Include | Q45: Qty | S45: Portugal | V45: 191.661 | Z45: 10346.679 | AF45: 10538.34
B46: Other Asia, nes | C46: 21373.203 | G46: 58423.481 | I46: 34947.002 | J46: 26895.963 | L46: 12736.987 | O46: 154376.64 | P46: Include | Q46: Qty | S46: Qatar | T46: 185132.34 | U46: 84865.388 | V46: 102883.85 | W46: 87167.092 | X46: 42898.766 | Y46: 13638.697 | Z46: 212336.76 | AA46: 71921.025 | AB46: 17232.734 | AC46: 118745.88 | AD46: 21125.573 | AE46: 101734.23 | AF46: 1059682.3
B47: Other Europe, nes | D47: 27506.497 | E47: 74611.518 | F47: 70005.421 | G47: 61429.533 | H47: 60009.289 | I47: 15027.906 | J47: 33772.491 | K47: 17567.869 | L47: 3084.333 | M47: 18686.094 | N47: 16587.916 | O47: 398288.87 | P47: Exclude | Q47: Qty | S47: Rep. of Korea | T47: 34488.592 | U47: 61653.217 | V47: 20765.987 | W47: 26310.242 | X47: 39719.955 | Y47: 48498.403 | Z47: 27122.964 | AA47: 64179.808 | AB47: 22126.392 | AC47: 34794.668 | AD47: 64718.114 | AE47: 33870.203 | AF47: 478248.54
B48: Philippines | F48: 20361.891 | O48: 20361.891 | P48: Include | Q48: Qty | S48: Romania | Y48: 4800.745 | AF48: 4800.745
B49: Poland | D49: 1617.929 | E49: 12913.428 | F49: 1281.152 | G49: 37194.682 | H49: 3027.747 | I49: 3264.476 | J49: 12287.046 | O49: 71586.46 | P49: Include | Q49: Qty | S49: Russian Federation | W49: 154.953 | Y49: 12015.446 | AA49: 3996.527 | AE49: 57.69 | AF49: 16224.616
B50: Portugal | E50: 191.661 | I50: 10346.679 | O50: 10538.34 | P50: Include | Q50: Qty | S50: Saudi Arabia | T50: 22.281 | U50: 44190.638 | V50: 63283.618 | W50: 47872.553 | X50: 50476.113 | Y50: 14848.845 | Z50: 7495.836 | AA50: 40381.008 | AB50: 42688.832 | AC50: 38486.513 | AD50: 63322.073 | AE50: 5233.455 | AF50: 418301.77
B51: Qatar | C51: 185132.34 | D51: 84865.388 | E51: 102883.85 | F51: 87167.092 | G51: 42898.766 | H51: 13638.697 | I51: 212336.76 | J51: 71921.025 | K51: 17232.734 | L51: 118745.88 | M51: 21125.573 | N51: 101734.23 | O51: 1059682.3 | P51: Include | Q51: Qty | S51: Serbia | AE51: 8494.867 | AF51: 8494.867
B52: Rep. of Korea | C52: 34488.592 | D52: 61653.217 | E52: 20765.987 | F52: 26310.242 | G52: 39719.955 | H52: 48498.403 | I52: 27122.964 | J52: 64179.808 | K52: 22126.392 | L52: 34794.668 | M52: 64718.114 | N52: 33870.203 | O52: 478248.54 | P52: Include | Q52: Qty | S52: Singapore | T52: 72724.492 | U52: 35585.626 | V52: 14332.992 | W52: 6955.696 | X52: 4109.587 | Y52: 5183.913 | Z52: 5413.52 | AA52: 28826.93 | AC52: 11843.784 | AD52: 53379.069 | AE52: 111.24 | AF52: 238466.85
B53: Romania | H53: 4800.745 | O53: 4800.745 | P53: Include | Q53: Qty | S53: Slovakia | U53: 4292.246 | AF53: 4292.246
B54: Russian Federation | F54: 154.953 | H54: 12015.446 | J54: 3996.527 | N54: 57.69 | O54: 16224.616 | P54: Exclude | Q54: Qty | S54: Slovenia | V54: 1645.816 | W54: 872.629 | X54: 1123.363 | Y54: 1007.81 | AF54: 4649.618
B55: Saudi Arabia | C55: 22.281 | D55: 44190.638 | E55: 63283.618 | F55: 47872.553 | G55: 50476.113 | H55: 14848.845 | I55: 7495.836 | J55: 40381.008 | K55: 42688.832 | L55: 38486.513 | M55: 63322.073 | N55: 5233.455 | O55: 418301.77 | P55: Include | Q55: Qty | S55: South Africa | T55: 17059.087 | U55: 1091.68 | W55: 13730.677 | Z55: 23814.899 | AB55: 8797.674 | AE55: 8873.738 | AF55: 73367.755
B56: Serbia | N56: 8494.867 | O56: 8494.867 | P56: Include | Q56: Qty | S56: Spain | T56: 352220.84 | U56: 178586.74 | V56: 297039.68 | W56: 226368.73 | X56: 321671.58 | Y56: 185778.23 | Z56: 148960.57 | AA56: 362785.46 | AB56: 336436.46 | AC56: 325170.41 | AD56: 563422.48 | AE56: 284974.92 | AF56: 3583416.1
B57: Singapore | C57: 72724.492 | D57: 35585.626 | E57: 14332.992 | F57: 6955.696 | G57: 4109.587 | H57: 5183.913 | I57: 5413.52 | J57: 28826.93 | L57: 11843.784 | M57: 53379.069 | N57: 111.24 | O57: 238466.85 | P57: Include | Q57: Qty | S57: Sweden | U57: 4567.902 | Y57: 1313.482 | Z57: 479.145 | AA57: 12848.127 | AB57: 40315.222 | AC57: 180227.32 | AD57: 6337.607 | AE57: 554.691 | AF57: 246643.49
B58: Slovakia | D58: 4292.246 | O58: 4292.246 | P58: Include | Q58: Qty | S58: Switzerland | T58: 17394.401 | U58: 23045.294 | V58: 13555.125 | W58: 10634.367 | X58: 8942.179 | Z58: 12446.666 | AA58: 9285.037 | AB58: 96939.524 | AC58: 16269.613 | AE58: 6374.521 | AF58: 214886.73
B59: Slovenia | E59: 1645.816 | F59: 872.629 | G59: 1123.363 | H59: 1007.81 | O59: 4649.618 | P59: Include | Q59: Qty | S59: Thailand | T59: 8187.714 | U59: 1050.835 | V59: 7997.004 | W59: 4026.446 | X59: 13944.671 | Y59: 1849.68 | Z59: 4263.885 | AA59: 14662.135 | AB59: 86.299 | AC59: 2704.574 | AD59: 8653.287 | AF59: 67426.53
B60: South Africa | C60: 17059.087 | D60: 1091.68 | F60: 13730.677 | I60: 23814.899 | K60: 8797.674 | N60: 8873.738 | O60: 73367.755 | P60: Include | Q60: Qty | S60: Türkiye | T60: 218983.23 | U60: 74496.922 | V60: 272175.6 | W60: 242787 | X60: 276414.21 | Y60: 177095.59 | Z60: 213448.7 | AA60: 187723.14 | AB60: 109141.19 | AC60: 194049.69 | AD60: 203483.55 | AE60: 149668.2 | AF60: 2319467
B61: Spain | C61: 352220.84 | D61: 178586.74 | E61: 297039.68 | F61: 226368.73 | G61: 321671.58 | H61: 185778.23 | I61: 148960.57 | J61: 362785.46 | K61: 336436.46 | L61: 325170.41 | M61: 563422.48 | N61: 284974.92 | O61: 3583416.1 | P61: Include | Q61: Qty | S61: Ukraine | V61: 40557.811 | Y61: 18317.729 | AB61: 15239.971 | AF61: 74115.511
B62: Sweden | D62: 4567.902 | H62: 1313.482 | I62: 479.145 | J62: 12848.127 | K62: 40315.222 | L62: 180227.32 | M62: 6337.607 | N62: 554.691 | O62: 246643.49 | P62: Include | Q62: Qty | S62: United Arab Emirates | T62: 36453.495 | U62: 138126.63 | V62: 5332.203 | W62: 123294.77 | X62: 99370.646 | Y62: 63631.866 | Z62: 121889.71 | AA62: 78225.38 | AB62: 58137.012 | AC62: 33613.527 | AD62: 28531.043 | AE62: 51737.53 | AF62: 838343.81
B63: Switzerland | C63: 17394.401 | D63: 23045.294 | E63: 13555.125 | F63: 10634.367 | G63: 8942.179 | I63: 12446.666 | J63: 9285.037 | K63: 96939.524 | L63: 16269.613 | N63: 6374.521 | O63: 214886.73 | P63: Include | Q63: Qty | S63: United Kingdom | T63: 31064.658 | U63: 72589.067 | V63: 44914.982 | W63: 49069.666 | X63: 27252.608 | Y63: 29096.24 | Z63: 172897.43 | AA63: 57811.054 | AB63: 11284841 | AC63: 1035847.9 | AD63: 118638.35 | AE63: 84356.789 | AF63: 13008380
B64: Thailand | C64: 8187.714 | D64: 1050.835 | E64: 7997.004 | F64: 4026.446 | G64: 13944.671 | H64: 1849.68 | I64: 4263.885 | J64: 14662.135 | K64: 86.299 | L64: 2704.574 | M64: 8653.287 | O64: 67426.53 | P64: Include | Q64: Qty | S64: USA | T64: 231391.82 | U64: 241030.07 | V64: 282259.85 | W64: 274359.84 | X64: 296512.8 | Y64: 303186.15 | Z64: 455140.92 | AA64: 183146.82 | AB64: 9097106.8 | AC64: 4679636.7 | AD64: 1400781.4 | AE64: 1025812.5 | AF64: 18470366
B65: Türkiye | C65: 218983.23 | D65: 74496.922 | E65: 272175.6 | F65: 242787 | G65: 276414.21 | H65: 177095.59 | I65: 213448.7 | J65: 187723.14 | K65: 109141.19 | L65: 194049.69 | M65: 203483.55 | N65: 149668.2 | O65: 2319467 | P65: Include | Q65: Qty | S65: Viet Nam | W65: 619.6 | X65: 82222.104 | Z65: 81899.181 | AA65: 134319.37 | AB65: 89364.058 | AC65: 178249.88 | AF65: 566674.19
B66: Ukraine | E66: 40557.811 | H66: 18317.729 | K66: 15239.971 | O66: 74115.511 | P66: Include | Q66: Qty | S66: World | T66: 3855298.4 | U66: 3360987.6 | V66: 2850035.7 | W66: 3549420.9 | X66: 3427779.8 | Y66: 2423249.2 | Z66: 3553764.1 | AA66: 3438611.8 | AB66: 23209335 | AC66: 8853987.4 | AD66: 5062405.5 | AE66: 3292348.7 | AF66: 66877225
B67: United Arab Emirates | C67: 36453.495 | D67: 138126.63 | E67: 5332.203 | F67: 123294.77 | G67: 99370.646 | H67: 63631.866 | I67: 121889.71 | J67: 78225.38 | K67: 58137.012 | L67: 33613.527 | M67: 28531.043 | N67: 51737.53 | O67: 838343.81 | P67: Include | Q67: Qty | S67: Grand Total | T67: 7710596.9 | U67: 6721975.3 | V67: 5700071.5 | W67: 7098841.8 | X67: 6855559.7 | Y67: 4846498.3 | Z67: 7107528.2 | AA67: 6877223.7 | AB67: 46418671 | AC67: 17707975 | AD67: 10124811 | AE67: 6584697.4 | AF67: 1.3375445e+08
B68: United Kingdom | C68: 31064.658 | D68: 72589.067 | E68: 44914.982 | F68: 49069.666 | G68: 27252.608 | H68: 29096.24 | I68: 172897.43 | J68: 57811.054 | K68: 11284841 | L68: 1035847.9 | M68: 118638.35 | N68: 84356.789 | O68: 13008380 | P68: Include | Q68: Qty
B69: USA | C69: 231391.82 | D69: 241030.07 | E69: 282259.85 | F69: 274359.84 | G69: 296512.8 | H69: 303186.15 | I69: 455140.92 | J69: 183146.82 | K69: 9097106.8 | L69: 4679636.7 | M69: 1400781.4 | N69: 1025812.5 | O69: 18470366 | P69: Include | Q69: Qty
B70: Viet Nam | F70: 619.6 | G70: 82222.104 | I70: 81899.181 | J70: 134319.37 | K70: 89364.058 | L70: 178249.88 | O70: 566674.19 | P70: Include | Q70: Qty
B71: World | C71: 3855298.4 | D71: 3360987.6 | E71: 2850035.7 | F71: 3549420.9 | G71: 3427779.8 | H71: 2423249.2 | I71: 3553764.1 | J71: 3438611.8 | K71: 23209335 | L71: 8853987.4 | M71: 5062405.5 | N71: 3292348.7 | O71: 66877225 | P71: Exclude | Q71: Qty
B72: Grand Total | C72: 7710596.9 | D72: 6721975.3 | E72: 5700071.5 | F72: 7098841.8 | G72: 6855559.7 | H72: 4846498.3 | I72: 7107528.2 | J72: 6877223.7 | K72: 46418671 | L72: 17707975 | M72: 10124811 | N72: 6584697.4 | O72: 1.3375445e+08 | S72: reporterDesc | T72: Egypt
S74: Sum of primaryValue | T74: refYear | U74: refMonth
A75: 2/ | B75: Value | T75: 2023 | Z75: 2024 | AF75: Grand Total
B76: Unit : US Dollar thousand | S76: partnerDesc | T76: 7 | U76: 8 | V76: 9 | W76: 10 | X76: 11 | Y76: 12 | Z76: 1 | AA76: 2 | AB76: 3 | AC76: 4 | AD76: 5 | AE76: 6
S77: Argentina | T77: 35179.613 | AF77: 35179.613
C78: 2023 | I78: 2024 | O78: Grand Total | P78: Mark | Q78: Note | S78: Australia | T78: 237152.81 | U78: 79414.772 | V78: 8530.517 | W78: 73910.125 | X78: 175893.37 | Z78: 5552.952 | AA78: 8054.962 | AB78: 5944.144 | AD78: 162811.76 | AE78: 32748.724 | AF78: 790014.13
B79: partnerDesc | C79: 7 | D79: 8 | E79: 9 | F79: 10 | G79: 11 | H79: 12 | I79: 1 | J79: 2 | K79: 3 | L79: 4 | M79: 5 | N79: 6 | S79: Austria | T79: 69802.061 | U79: 9625.92 | V79: 5516.109 | Y79: 18967.716 | AB79: 11732.728 | AC79: 107389.1 | AE79: 23376.034 | AF79: 246409.67
B80: Argentina | C80: 35179.613 | O80: 35179.613 | P80: Include | Q80: Val | S80: Belgium | T80: 141441.32 | U80: 342579.5 | V80: 198974.03 | W80: 193264.35 | X80: 943218.13 | Y80: 21080.903 | Z80: 273119.82 | AA80: 358652.77 | AB80: 202846.52 | AC80: 810007.51 | AD80: 479103.24 | AE80: 30936.769 | AF80: 3995224.9
B81: Australia | C81: 237152.81 | D81: 79414.772 | E81: 8530.517 | F81: 73910.125 | G81: 175893.37 | I81: 5552.952 | J81: 8054.962 | K81: 5944.144 | M81: 162811.76 | N81: 32748.724 | O81: 790014.13 | P81: Include | Q81: Val | S81: Brazil | T81: 226632.03 | W81: 139026.64 | X81: 129899.38 | Y81: 49362.406 | Z81: 17941.057 | AA81: 126500.01 | AB81: 164122.25 | AC81: 43023.57 | AD81: 71138.228 | AE81: 10336.59 | AF81: 977982.16
B82: Austria | C82: 69802.061 | D82: 9625.92 | E82: 5516.109 | H82: 18967.716 | K82: 11732.728 | L82: 107389.1 | N82: 23376.034 | O82: 246409.67 | P82: Include | Q82: Val | S82: Bulgaria | AC82: 9492.557 | AF82: 9492.557
B83: Belgium | C83: 141441.32 | D83: 342579.5 | E83: 198974.03 | F83: 193264.35 | G83: 943218.13 | H83: 21080.903 | I83: 273119.82 | J83: 358652.77 | K83: 202846.52 | L83: 810007.51 | M83: 479103.24 | N83: 30936.769 | O83: 3995224.9 | P83: Include | Q83: Val | S83: Canada | X83: 23925.512 | Y83: 1022.534 | Z83: 187455.02 | AA83: 5741.658 | AB83: 1302.053 | AC83: 13800.488 | AD83: 3137.304 | AE83: 8827.103 | AF83: 245211.67
B84: Brazil | C84: 226632.03 | F84: 139026.64 | G84: 129899.38 | H84: 49362.406 | I84: 17941.057 | J84: 126500.01 | K84: 164122.25 | L84: 43023.57 | M84: 71138.228 | N84: 10336.59 | O84: 977982.16 | P84: Include | Q84: Val | S84: Chile | AC84: 50751.398 | AF84: 50751.398
B85: Bulgaria | L85: 9492.557 | O85: 9492.557 | P85: Include | Q85: Val | S85: China | T85: 3917081.3 | U85: 3674056.5 | V85: 2006927.6 | W85: 3771689 | X85: 2812028 | Y85: 1931499 | Z85: 3418342.1 | AA85: 3475987.2 | AB85: 3272985.6 | AC85: 2325208.5 | AD85: 3895475.7 | AE85: 2407047 | AF85: 36908327
B86: Canada | G86: 23925.512 | H86: 1022.534 | I86: 187455.02 | J86: 5741.658 | K86: 1302.053 | L86: 13800.488 | M86: 3137.304 | N86: 8827.103 | O86: 245211.67 | P86: Include | Q86: Val | S86: China, Hong Kong SAR | T86: 2019.633 | X86: 775.229 | AA86: 10652.885 | AD86: 175195.81 | AF86: 188643.56
B87: Chile | L87: 50751.398 | O87: 50751.398 | P87: Include | Q87: Val | S87: Czechia | AD87: 22595.479 | AF87: 22595.479
B88: China | C88: 3917081.3 | D88: 3674056.5 | E88: 2006927.6 | F88: 3771689 | G88: 2812028 | H88: 1931499 | I88: 3418342.1 | J88: 3475987.2 | K88: 3272985.6 | L88: 2325208.5 | M88: 3895475.7 | N88: 2407047 | O88: 36908327 | P88: Exclude | Q88: Val | S88: Denmark | T88: 138544.39 | U88: 197636.01 | V88: 142508.76 | W88: 164337.47 | X88: 342929.84 | Y88: 11327.14 | Z88: 74217.726 | AA88: 284696.65 | AB88: 370849.62 | AC88: 38092.372 | AD88: 345917.8 | AE88: 58780.34 | AF88: 2169838.1
B89: China, Hong Kong SAR | C89: 2019.633 | G89: 775.229 | J89: 10652.885 | M89: 175195.81 | O89: 188643.56 | P89: Exclude | Q89: Val | S89: Estonia | U89: 12235.47 | AF89: 12235.47
B90: Czechia | M90: 22595.479 | O90: 22595.479 | P90: Include | Q90: Val | S90: Finland | AA90: 1259.042 | AB90: 6548.577 | AF90: 7807.619
B91: Denmark | C91: 138544.39 | D91: 197636.01 | E91: 142508.76 | F91: 164337.47 | G91: 342929.84 | H91: 11327.14 | I91: 74217.726 | J91: 284696.65 | K91: 370849.62 | L91: 38092.372 | M91: 345917.8 | N91: 58780.34 | O91: 2169838.1 | P91: Include | Q91: Val | S91: France | T91: 1864017.9 | U91: 1189879.6 | V91: 604056.24 | W91: 487935.12 | X91: 484306.92 | Y91: 392115.68 | Z91: 1358472.8 | AA91: 519868.68 | AB91: 526562.35 | AC91: 841184.31 | AD91: 831589.93 | AE91: 346904.16 | AF91: 9446893.7
B92: Estonia | D92: 12235.47 | O92: 12235.47 | P92: Include | Q92: Val | S92: Georgia | Y92: 90340.328 | AA92: 21710.123 | AD92: 41240.094 | AF92: 153290.54
B93: Finland | J93: 1259.042 | K93: 6548.577 | O93: 7807.619 | P93: Include | Q93: Val | S93: Germany | T93: 2990889 | U93: 2067505.4 | V93: 1991176.8 | W93: 2941563.6 | X93: 1813024 | Y93: 1857870.8 | Z93: 2102616.6 | AA93: 2624097.2 | AB93: 1690771.7 | AC93: 2210779 | AD93: 2592793.9 | AE93: 1619797.3 | AF93: 26502885
B94: France | C94: 1864017.9 | D94: 1189879.6 | E94: 604056.24 | F94: 487935.12 | G94: 484306.92 | H94: 392115.68 | I94: 1358472.8 | J94: 519868.68 | K94: 526562.35 | L94: 841184.31 | M94: 831589.93 | N94: 346904.16 | O94: 9446893.7 | P94: Include | Q94: Val | S94: Greece | V94: 70755.078 | Z94: 658.781 | AA94: 37767.943 | AB94: 4033.888 | AF94: 113215.69
B95: Georgia | H95: 90340.328 | J95: 21710.123 | M95: 41240.094 | O95: 153290.54 | P95: Include | Q95: Val | S95: Hungary | AB95: 27588.785 | AF95: 27588.785
B96: Germany | C96: 2990889 | D96: 2067505.4 | E96: 1991176.8 | F96: 2941563.6 | G96: 1813024 | H96: 1857870.8 | I96: 2102616.6 | J96: 2624097.2 | K96: 1690771.7 | L96: 2210779 | M96: 2592793.9 | N96: 1619797.3 | O96: 26502885 | P96: Include | Q96: Val | S96: India | T96: 1807590.7 | U96: 1394876.2 | V96: 1364649.9 | W96: 1837089.4 | X96: 1310581.3 | Y96: 851788.08 | Z96: 646317.58 | AA96: 1101260.5 | AB96: 750184.41 | AC96: 933137.39 | AD96: 1721258.6 | AE96: 789668.32 | AF96: 14508402
B97: Greece | E97: 70755.078 | I97: 658.781 | J97: 37767.943 | K97: 4033.888 | O97: 113215.69 | P97: Include | Q97: Val | S97: Indonesia | W97: 1947.605 | Y97: 41814.023 | Z97: 16.151 | AB97: 175392.17 | AD97: 25802.385 | AE97: 103673.02 | AF97: 348645.35
B98: Hungary | K98: 27588.785 | O98: 27588.785 | P98: Include | Q98: Val | S98: Ireland | V98: 28110.412 | AB98: 38649.371 | AF98: 66759.783
B99: India | C99: 1807590.7 | D99: 1394876.2 | E99: 1364649.9 | F99: 1837089.4 | G99: 1310581.3 | H99: 851788.08 | I99: 646317.58 | J99: 1101260.5 | K99: 750184.41 | L99: 933137.39 | M99: 1721258.6 | N99: 789668.32 | O99: 14508402 | P99: Include | Q99: Val | S99: Israel | T99: 41901.121 | W99: 61909.381 | X99: 92299.287 | Y99: 105725.73 | AA99: 9915.177 | AB99: 38604.043 | AC99: 73011.809 | AD99: 30039.842 | AE99: 41890.703 | AF99: 495297.09
B100: Indonesia | F100: 1947.605 | H100: 41814.023 | I100: 16.151 | K100: 175392.17 | M100: 25802.385 | N100: 103673.02 | O100: 348645.35 | P100: Include | Q100: Val | S100: Italy | T100: 798532.58 | U100: 1527463.8 | V100: 776575.7 | W100: 950774.85 | X100: 633707.96 | Y100: 509975.27 | Z100: 460043.59 | AA100: 425164.39 | AB100: 1468178.7 | AC100: 1230304.9 | AD100: 666247.69 | AE100: 791734.08 | AF100: 10238704
B101: Ireland | E101: 28110.412 | K101: 38649.371 | O101: 66759.783 | P101: Include | Q101: Val | S101: Japan | U101: 7848.283 | V101: 24686.481 | W101: 27943.717 | X101: 5267.661 | Y101: 1603.526 | Z101: 18942.332 | AA101: 133876.17 | AB101: 190.696 | AC101: 19736.231 | AD101: 80804.236 | AE101: 2266.592 | AF101: 323165.92
B102: Israel | C102: 41901.121 | F102: 61909.381 | G102: 92299.287 | H102: 105725.73 | J102: 9915.177 | K102: 38604.043 | L102: 73011.809 | M102: 30039.842 | N102: 41890.703 | O102: 495297.09 | P102: Include | Q102: Val | S102: Jordan | V102: 172950.02 | X102: 62748.027 | Y102: 142875 | AC102: 113412.02 | AD102: 7425.023 | AE102: 351394.51 | AF102: 850804.59
...

Sheet EX-2.7- Thủy tinh lỏng
A1: List of supplying markets for a product imported by Egypt | D1: ='EX-1A SV Summary'!D32 -> 28391990
A2: Silicates; of sodium (excluding sodium metasilicates)
A3: Sources: ITC calculations based on UN COMTRADE statistics.
B5: Total quantity imported (Kg) | C5: Total value imported (USD) | D5: Unit price (USD/Kg)
B6: =SUMIFS(O:O,P:P,"Include",Q:Q,"QTY")*1000 -> 7.791922e+08 | C6: =SUMIFS(O:O,P:P,"Include",Q:Q,"VAL")*1000 -> 452067064 | D6: =C6/B6 -> 0.58017401
S7: reporterDesc | T7: Egypt
A8: 1/ | B8: Quantity
B9: Unit : ton | S9: Sum of qty | T9: refYear | U9: refMonth
T10: 2023 | Y10: 2024 | AD10: Grand Total
C11: 2023 | I11: 2024 | O11: Grand Total | P11: Mark | Q11: Note | S11: partnerDesc | T11: 7 | U11: 8 | V11: 9 | W11: 10 | X11: 12 | Y11: 1 | Z11: 2 | AA11: 3 | AB11: 4 | AC11: 5
